{
  "url": "https://www.unfpa.org/events/commission-population-and-development-fifty-eighth-session",
  "title": "Commission on Population and Development, fifty-eighth session",
  "text": "© UNFPA Egypt/Roger Anis \n\n\n\n\n\n\n\n\n\nHome\nEvent\nCommission on Population and Development, fifty-eighth session\n\n\n\n\n\nCommission on Population and Development, fifty-eighth session\n\n\n\n07 April - 11 April 2025\n\nUN Web TV\n\n\n\n\n\n\n\n\n\n\n\n\n\n\n\n\n\nThe fifty-eighth session of the Commission on Population and Development will spotlight the critical importance of ensuring healthy lives and well-being for all, at all ages. \nThe session, which begins on World Health Day on 7 April, will feature a number of side events hosted by UNFPA and partners, including the launch of the Global Action Plan for Midwifery – a bold call to action designed to rally the maternal health community and drive political commitment to strengthen midwifery models of care. \nThe Commission on Population and Development is made up of 47 United Nations Member States elected by the Economic and Social Council for a period of four years, based on geographic distribution. It assists the Economic and Social Council in many ways, including advising on population issues, as well as monitoring and assessing the implementation of the Programme of Action of the landmark International Conference on Population and Development.\nThis year’s session will be broadcast on UN Web TV. You can learn more about it here. \n\nSide events hosted by UNFPA and partners\nImproving Health and Well-being for Women and Newborns: Launch of the Midwifery Accelerator\n7 April, 1:15 p.m. – 2:30 p.m. EDT\nUN Headquarters, Conference Room 4\nHosted by UNFPA and partners including the Governments of Denmark, Germany, Luxembourg, Mexico, Sierra Leone, Sweden, and the United Kingdom, as well as the International Confederation of Midwives, UNICEF and the World Health Organization, this event rallies global leaders on the urgent need to expand midwifery services. The release of updated maternal mortality figures will underscore the high stakes, making a robust case for immediate investment in midwifery to drive lasting improvements in maternal, newborn and child health worldwide. Register here or watch here.\n\nIntergenerational Dialogue: Ensuring Healthy Lives – Bridging Generations for Action \n8 April, 1:15 p.m. – 2:30 p.m. EDT\nUN Headquarters, Conference Room 8\nThis event brings together experts, policymakers and advocates to discuss health, demographic shifts and well-being across all ages. It is organized by UNFPA and the Government of Japan, Kingdom of Denmark, Kingdom of the Netherlands, Republic of Benin, Republic of India, Republic of Lebanon, Republic of Moldova, Republic of Uruguay and the UN Youth Office. UNFPA Executive Director Dr. Natalia Kanem will speak at the event. Register here or watch here.\n\nPrioritizing Sexual and Reproductive Health and Sexual and Gender-based Violence in Crisis Response\n8 April 1:15 p.m. – 2:30 p.m. EDT\nUN Headquarters, Conference Room 4\nThis event will address the importance of investing in health systems’ preparedness to respond to the health needs of women and girls affected by humanitarian crises. It will focus on access to life-saving support, including age- and gender-responsive sexual and reproductive health services for survivors of sexual and gender-based violence. It is hosted by UNFPA, together with the Permanent Missions of Colombia, Moldova and Norway, the International Planned Parenthood Federation, Plan International and UNICEF. Register here or watch here.\n\nLaunch of the UNFPA Innovation Strategy 2030: Innovating for Rights and Choices: By, for and with Women and Young People\n8 April, 3:00 p.m. – 4:30 p.m. EDT\nOrange Café, UNFPA Headquarters, 605 Third Avenue, New York\nAs the world accelerates efforts to create universal health coverage and gender equality, innovation plays a critical role in addressing persistent inequalities. This event will introduce the UNFPA Innovation Strategy 2030, a bold framework prioritizing women-led, youth-driven and locally informed solutions. The strategy harnesses emerging technologies and behavioral insights to advance gender-equitable innovation across UNFPA’s mandate. Register here.\n\nDemographic Intelligence for Health Equity: Harnessing Data for Inclusive Policies and Universal Coverage\n10 April, 1:15 p.m. – 2:30 p.m. EDT\nUN Secretariat, Conference Room 12\nOrganized by UNFPA, the Governments of Colombia, Colombia  the Dominican Republic and Ecuador, and together with Harvard Medical School, this event will emphasize the role of demographic insights in advancing health equity, strengthening health systems and ensuring universal access to care. Register here or watch here.\n\nThe Role of the Private Sector, Innovation and Technology in Bridging the Gap in Maternal Health and Ensuring We Leave No One Behind\n10 April, 1:15 p.m. to 2:30 p.m. EDT\nUN Secretariat, Conference Room 12\nAt this event, co-sponsored by the Governments of Finland and Mexico, UNFPA and partners will discuss reproductive health, explore strategic partnerships, highlight best practices and discuss the potential of an integrated approach to support bridging the gap in maternal health outcomes – and to ensure that we leave no one behind. Register here.\n\n\n\n\n\n\n\n\n\n\n\n\nRelated topics\n\n\n\n\nSexual & reproductive health\n\n\n\n\n\n\n\n\n\n\n\n\n\n\n\n\n\n\n\n\n\n\n\n\n\n\n\n\n\n\n\n\n\n\n\n      Back to page\n    \n\n\n\n\nEvents\n\n\n\n\n\n\nShare on Facebook\n\n\n\n\n\nShare on Twitter\n\n\n\n\n\n\n\n\n\n\n\n\n\n\nRelated Content\n\n\n\n\n\n\n\n\n\n\nEvents\n\nIntergenerational Dialogue: Ensuring healthy lives – Bridging generations for…\n\nRead more\n\n\n\n\n\n\n\n\n\n\n\nSpeech\n\nOpening Remarks by UNFPA Executive Director Dr. Natalia Kanem at the Commission…\n\nRead more\n\n\n\n\n\n\n\n\n\n\n\n\n\n\n\nUpdates\n\nMaternal health champions at CPD: It’s time to act for mothers and newborns\n\nRead more\n\n© UNFPA Egypt/Roger Anis \n\n\n\n\n\n\n\n\n\nHome\nEvent\nCommission on Population and Development, fifty-eighth session\n\n\n\n\n\nCommission on Population and Development, fifty-eighth session\n\n\n\n07 April - 11 April 2025\n\nUN Web TV\n\n\n\n\n\n\n\n\n\n\n\n\n\n\n\n\n\nThe fifty-eighth session of the Commission on Population and Development will spotlight the critical importance of ensuring healthy lives and well-being for all, at all ages. \nThe session, which begins on World Health Day on 7 April, will feature a number of side events hosted by UNFPA and partners, including the launch of the Global Action Plan for Midwifery – a bold call to action designed to rally the maternal health community and drive political commitment to strengthen midwifery models of care. \nThe Commission on Population and Development is made up of 47 United Nations Member States elected by the Economic and Social Council for a period of four years, based on geographic distribution. It assists the Economic and Social Council in many ways, including advising on population issues, as well as monitoring and assessing the implementation of the Programme of Action of the landmark International Conference on Population and Development.\nThis year’s session will be broadcast on UN Web TV. You can learn more about it here. \n\nSide events hosted by UNFPA and partners\nImproving Health and Well-being for Women and Newborns: Launch of the Midwifery Accelerator\n7 April, 1:15 p.m. – 2:30 p.m. EDT\nUN Headquarters, Conference Room 4\nHosted by UNFPA and partners including the Governments of Denmark, Germany, Luxembourg, Mexico, Sierra Leone, Sweden, and the United Kingdom, as well as the International Confederation of Midwives, UNICEF and the World Health Organization, this event rallies global leaders on the urgent need to expand midwifery services. The release of updated maternal mortality figures will underscore the high stakes, making a robust case for immediate investment in midwifery to drive lasting improvements in maternal, newborn and child health worldwide. Register here or watch here.\n\nIntergenerational Dialogue: Ensuring Healthy Lives – Bridging Generations for Action \n8 April, 1:15 p.m. – 2:30 p.m. EDT\nUN Headquarters, Conference Room 8\nThis event brings together experts, policymakers and advocates to discuss health, demographic shifts and well-being across all ages. It is organized by UNFPA and the Government of Japan, Kingdom of Denmark, Kingdom of the Netherlands, Republic of Benin, Republic of India, Republic of Lebanon, Republic of Moldova, Republic of Uruguay and the UN Youth Office. UNFPA Executive Director Dr. Natalia Kanem will speak at the event. Register here or watch here.\n\nPrioritizing Sexual and Reproductive Health and Sexual and Gender-based Violence in Crisis Response\n8 April 1:15 p.m. – 2:30 p.m. EDT\nUN Headquarters, Conference Room 4\nThis event will address the importance of investing in health systems’ preparedness to respond to the health needs of women and girls affected by humanitarian crises. It will focus on access to life-saving support, including age- and gender-responsive sexual and reproductive health services for survivors of sexual and gender-based violence. It is hosted by UNFPA, together with the Permanent Missions of Colombia, Moldova and Norway, the International Planned Parenthood Federation, Plan International and UNICEF. Register here or watch here.\n\nLaunch of the UNFPA Innovation Strategy 2030: Innovating for Rights and Choices: By, for and with Women and Young People\n8 April, 3:00 p.m. – 4:30 p.m. EDT\nOrange Café, UNFPA Headquarters, 605 Third Avenue, New York\nAs the world accelerates efforts to create universal health coverage and gender equality, innovation plays a critical role in addressing persistent inequalities. This event will introduce the UNFPA Innovation Strategy 2030, a bold framework prioritizing women-led, youth-driven and locally informed solutions. The strategy harnesses emerging technologies and behavioral insights to advance gender-equitable innovation across UNFPA’s mandate. Register here.\n\nDemographic Intelligence for Health Equity: Harnessing Data for Inclusive Policies and Universal Coverage\n10 April, 1:15 p.m. – 2:30 p.m. EDT\nUN Secretariat, Conference Room 12\nOrganized by UNFPA, the Governments of Colombia, Colombia  the Dominican Republic and Ecuador, and together with Harvard Medical School, this event will emphasize the role of demographic insights in advancing health equity, strengthening health systems and ensuring universal access to care. Register here or watch here.\n\nThe Role of the Private Sector, Innovation and Technology in Bridging the Gap in Maternal Health and Ensuring We Leave No One Behind\n10 April, 1:15 p.m. to 2:30 p.m. EDT\nUN Secretariat, Conference Room 12\nAt this event, co-sponsored by the Governments of Finland and Mexico, UNFPA and partners will discuss reproductive health, explore strategic partnerships, highlight best practices and discuss the potential of an integrated approach to support bridging the gap in maternal health outcomes – and to ensure that we leave no one behind. Register here.\n\n\n\n\n\n\n\n\n\n\n\n\nRelated topics\n\n\n\n\nSexual & reproductive health\n\n\n\n\n\n\n\n\n\n\n\n\n\n\n\n\n\n\n\n\n\n\n\n\n\n\n\n\n\n\n\n\n\n\n\n      Back to page\n    \n\n\n\n\nEvents\n\n\n\n\n\n\nShare on Facebook\n\n\n\n\n\nShare on Twitter\n\n\n\n\n\n\n\n\n\n\n\n\n\n\nRelated Content\n\n\n\n\n\n\n\n\n\n\nEvents\n\nIntergenerational Dialogue: Ensuring healthy lives – Bridging generations for…\n\nRead more\n\n\n\n\n\n\n\n\n\n\n\nSpeech\n\nOpening Remarks by UNFPA Executive Director Dr. Natalia Kanem at the Commission…\n\nRead more\n\n\n\n\n\n\n\n\n\n\n\n\n\n\n\nUpdates\n\nMaternal health champions at CPD: It’s time to act for mothers and newborns\n\nRead more\n\n© UNFPA Egypt/Roger Anis\n\n© UNFPA Egypt/Roger Anis\n\nHome\nEvent\nCommission on Population and Development, fifty-eighth session\n\n\n\n\n\nCommission on Population and Development, fifty-eighth session\n\n\n\n07 April - 11 April 2025\n\nUN Web TV\n\n\n\n\n\n\n\n\n\n\n\n\n\n\n\n\n\nThe fifty-eighth session of the Commission on Population and Development will spotlight the critical importance of ensuring healthy lives and well-being for all, at all ages. \nThe session, which begins on World Health Day on 7 April, will feature a number of side events hosted by UNFPA and partners, including the launch of the Global Action Plan for Midwifery – a bold call to action designed to rally the maternal health community and drive political commitment to strengthen midwifery models of care. \nThe Commission on Population and Development is made up of 47 United Nations Member States elected by the Economic and Social Council for a period of four years, based on geographic distribution. It assists the Economic and Social Council in many ways, including advising on population issues, as well as monitoring and assessing the implementation of the Programme of Action of the landmark International Conference on Population and Development.\nThis year’s session will be broadcast on UN Web TV. You can learn more about it here. \n\nSide events hosted by UNFPA and partners\nImproving Health and Well-being for Women and Newborns: Launch of the Midwifery Accelerator\n7 April, 1:15 p.m. – 2:30 p.m. EDT\nUN Headquarters, Conference Room 4\nHosted by UNFPA and partners including the Governments of Denmark, Germany, Luxembourg, Mexico, Sierra Leone, Sweden, and the United Kingdom, as well as the International Confederation of Midwives, UNICEF and the World Health Organization, this event rallies global leaders on the urgent need to expand midwifery services. The release of updated maternal mortality figures will underscore the high stakes, making a robust case for immediate investment in midwifery to drive lasting improvements in maternal, newborn and child health worldwide. Register here or watch here.\n\nIntergenerational Dialogue: Ensuring Healthy Lives – Bridging Generations for Action \n8 April, 1:15 p.m. – 2:30 p.m. EDT\nUN Headquarters, Conference Room 8\nThis event brings together experts, policymakers and advocates to discuss health, demographic shifts and well-being across all ages. It is organized by UNFPA and the Government of Japan, Kingdom of Denmark, Kingdom of the Netherlands, Republic of Benin, Republic of India, Republic of Lebanon, Republic of Moldova, Republic of Uruguay and the UN Youth Office. UNFPA Executive Director Dr. Natalia Kanem will speak at the event. Register here or watch here.\n\nPrioritizing Sexual and Reproductive Health and Sexual and Gender-based Violence in Crisis Response\n8 April 1:15 p.m. – 2:30 p.m. EDT\nUN Headquarters, Conference Room 4\nThis event will address the importance of investing in health systems’ preparedness to respond to the health needs of women and girls affected by humanitarian crises. It will focus on access to life-saving support, including age- and gender-responsive sexual and reproductive health services for survivors of sexual and gender-based violence. It is hosted by UNFPA, together with the Permanent Missions of Colombia, Moldova and Norway, the International Planned Parenthood Federation, Plan International and UNICEF. Register here or watch here.\n\nLaunch of the UNFPA Innovation Strategy 2030: Innovating for Rights and Choices: By, for and with Women and Young People\n8 April, 3:00 p.m. – 4:30 p.m. EDT\nOrange Café, UNFPA Headquarters, 605 Third Avenue, New York\nAs the world accelerates efforts to create universal health coverage and gender equality, innovation plays a critical role in addressing persistent inequalities. This event will introduce the UNFPA Innovation Strategy 2030, a bold framework prioritizing women-led, youth-driven and locally informed solutions. The strategy harnesses emerging technologies and behavioral insights to advance gender-equitable innovation across UNFPA’s mandate. Register here.\n\nDemographic Intelligence for Health Equity: Harnessing Data for Inclusive Policies and Universal Coverage\n10 April, 1:15 p.m. – 2:30 p.m. EDT\nUN Secretariat, Conference Room 12\nOrganized by UNFPA, the Governments of Colombia, Colombia  the Dominican Republic and Ecuador, and together with Harvard Medical School, this event will emphasize the role of demographic insights in advancing health equity, strengthening health systems and ensuring universal access to care. Register here or watch here.\n\nThe Role of the Private Sector, Innovation and Technology in Bridging the Gap in Maternal Health and Ensuring We Leave No One Behind\n10 April, 1:15 p.m. to 2:30 p.m. EDT\nUN Secretariat, Conference Room 12\nAt this event, co-sponsored by the Governments of Finland and Mexico, UNFPA and partners will discuss reproductive health, explore strategic partnerships, highlight best practices and discuss the potential of an integrated approach to support bridging the gap in maternal health outcomes – and to ensure that we leave no one behind. Register here.\n\n\n\n\n\n\n\n\n\n\n\n\nRelated topics\n\n\n\n\nSexual & reproductive health\n\n\n\n\n\n\n\n\n\n\n\n\n\n\n\n\n\n\n\n\n\n\n\n\n\n\n\n\n\n\n\n\n\n\n\n      Back to page\n    \n\n\n\n\nEvents\n\n\n\n\n\n\nShare on Facebook\n\n\n\n\n\nShare on Twitter\n\n\n\n\n\n\n\n\n\n\n\n\n\n\nRelated Content\n\n\n\n\n\n\n\n\n\n\nEvents\n\nIntergenerational Dialogue: Ensuring healthy lives – Bridging generations for…\n\nRead more\n\n\n\n\n\n\n\n\n\n\n\nSpeech\n\nOpening Remarks by UNFPA Executive Director Dr. Natalia Kanem at the Commission…\n\nRead more\n\n\n\n\n\n\n\n\n\n\n\n\n\n\n\nUpdates\n\nMaternal health champions at CPD: It’s time to act for mothers and newborns\n\nRead more\n\nHome\nEvent\nCommission on Population and Development, fifty-eighth session\n\n\n\n\n\nCommission on Population and Development, fifty-eighth session\n\n\n\n07 April - 11 April 2025\n\nUN Web TV\n\n\n\n\n\n\n\n\n\n\n\n\n\n\n\n\n\nThe fifty-eighth session of the Commission on Population and Development will spotlight the critical importance of ensuring healthy lives and well-being for all, at all ages. \nThe session, which begins on World Health Day on 7 April, will feature a number of side events hosted by UNFPA and partners, including the launch of the Global Action Plan for Midwifery – a bold call to action designed to rally the maternal health community and drive political commitment to strengthen midwifery models of care. \nThe Commission on Population and Development is made up of 47 United Nations Member States elected by the Economic and Social Council for a period of four years, based on geographic distribution. It assists the Economic and Social Council in many ways, including advising on population issues, as well as monitoring and assessing the implementation of the Programme of Action of the landmark International Conference on Population and Development.\nThis year’s session will be broadcast on UN Web TV. You can learn more about it here. \n\nSide events hosted by UNFPA and partners\nImproving Health and Well-being for Women and Newborns: Launch of the Midwifery Accelerator\n7 April, 1:15 p.m. – 2:30 p.m. EDT\nUN Headquarters, Conference Room 4\nHosted by UNFPA and partners including the Governments of Denmark, Germany, Luxembourg, Mexico, Sierra Leone, Sweden, and the United Kingdom, as well as the International Confederation of Midwives, UNICEF and the World Health Organization, this event rallies global leaders on the urgent need to expand midwifery services. The release of updated maternal mortality figures will underscore the high stakes, making a robust case for immediate investment in midwifery to drive lasting improvements in maternal, newborn and child health worldwide. Register here or watch here.\n\nIntergenerational Dialogue: Ensuring Healthy Lives – Bridging Generations for Action \n8 April, 1:15 p.m. – 2:30 p.m. EDT\nUN Headquarters, Conference Room 8\nThis event brings together experts, policymakers and advocates to discuss health, demographic shifts and well-being across all ages. It is organized by UNFPA and the Government of Japan, Kingdom of Denmark, Kingdom of the Netherlands, Republic of Benin, Republic of India, Republic of Lebanon, Republic of Moldova, Republic of Uruguay and the UN Youth Office. UNFPA Executive Director Dr. Natalia Kanem will speak at the event. Register here or watch here.\n\nPrioritizing Sexual and Reproductive Health and Sexual and Gender-based Violence in Crisis Response\n8 April 1:15 p.m. – 2:30 p.m. EDT\nUN Headquarters, Conference Room 4\nThis event will address the importance of investing in health systems’ preparedness to respond to the health needs of women and girls affected by humanitarian crises. It will focus on access to life-saving support, including age- and gender-responsive sexual and reproductive health services for survivors of sexual and gender-based violence. It is hosted by UNFPA, together with the Permanent Missions of Colombia, Moldova and Norway, the International Planned Parenthood Federation, Plan International and UNICEF. Register here or watch here.\n\nLaunch of the UNFPA Innovation Strategy 2030: Innovating for Rights and Choices: By, for and with Women and Young People\n8 April, 3:00 p.m. – 4:30 p.m. EDT\nOrange Café, UNFPA Headquarters, 605 Third Avenue, New York\nAs the world accelerates efforts to create universal health coverage and gender equality, innovation plays a critical role in addressing persistent inequalities. This event will introduce the UNFPA Innovation Strategy 2030, a bold framework prioritizing women-led, youth-driven and locally informed solutions. The strategy harnesses emerging technologies and behavioral insights to advance gender-equitable innovation across UNFPA’s mandate. Register here.\n\nDemographic Intelligence for Health Equity: Harnessing Data for Inclusive Policies and Universal Coverage\n10 April, 1:15 p.m. – 2:30 p.m. EDT\nUN Secretariat, Conference Room 12\nOrganized by UNFPA, the Governments of Colombia, Colombia  the Dominican Republic and Ecuador, and together with Harvard Medical School, this event will emphasize the role of demographic insights in advancing health equity, strengthening health systems and ensuring universal access to care. Register here or watch here.\n\nThe Role of the Private Sector, Innovation and Technology in Bridging the Gap in Maternal Health and Ensuring We Leave No One Behind\n10 April, 1:15 p.m. to 2:30 p.m. EDT\nUN Secretariat, Conference Room 12\nAt this event, co-sponsored by the Governments of Finland and Mexico, UNFPA and partners will discuss reproductive health, explore strategic partnerships, highlight best practices and discuss the potential of an integrated approach to support bridging the gap in maternal health outcomes – and to ensure that we leave no one behind. Register here.\n\n\n\n\n\n\n\n\n\n\n\n\nRelated topics\n\n\n\n\nSexual & reproductive health\n\n\n\n\n\n\n\n\n\n\n\n\n\n\n\n\n\n\n\n\n\n\n\n\n\n\n\n\n\n\n\n\n\n\n\n      Back to page\n    \n\n\n\n\nEvents\n\n\n\n\n\n\nShare on Facebook\n\n\n\n\n\nShare on Twitter\n\n\n\n\n\n\n\n\n\n\n\n\n\n\nRelated Content\n\n\n\n\n\n\n\n\n\n\nEvents\n\nIntergenerational Dialogue: Ensuring healthy lives – Bridging generations for…\n\nRead more\n\n\n\n\n\n\n\n\n\n\n\nSpeech\n\nOpening Remarks by UNFPA Executive Director Dr. Natalia Kanem at the Commission…\n\nRead more\n\n\n\n\n\n\n\n\n\n\n\n\n\n\n\nUpdates\n\nMaternal health champions at CPD: It’s time to act for mothers and newborns\n\nRead more\n\nHome\nEvent\nCommission on Population and Development, fifty-eighth session\n\n\n\n\n\nCommission on Population and Development, fifty-eighth session\n\n\n\n07 April - 11 April 2025\n\nUN Web TV\n\nHome\nEvent\nCommission on Population and Development, fifty-eighth session\n\n\n\n\n\nCommission on Population and Development, fifty-eighth session\n\n\n\n07 April - 11 April 2025\n\nUN Web TV\n\nHome\nEvent\nCommission on Population and Development, fifty-eighth session\n\n\n\n\n\nCommission on Population and Development, fifty-eighth session\n\n\n\n07 April - 11 April 2025\n\nUN Web TV\n\nCommission on Population and Development, fifty-eighth session\n\n\n\n07 April - 11 April 2025\n\nUN Web TV\n\nCommission on Population and Development, fifty-eighth session\n\n\n\n07 April - 11 April 2025\n\nUN Web TV\n\nCommission on Population and Development, fifty-eighth session\n\n\n\n07 April - 11 April 2025\n\nUN Web TV\n\nCommission on Population and Development, fifty-eighth session\n\n\n\n07 April - 11 April 2025\n\nUN Web TV\n\n07 April - 11 April 2025\n\nUN Web TV\n\n07 April - 11 April 2025\n\nUN Web TV\n\n07 April - 11 April 2025\n\nUN Web TV\n\nThe fifty-eighth session of the Commission on Population and Development will spotlight the critical importance of ensuring healthy lives and well-being for all, at all ages. \nThe session, which begins on World Health Day on 7 April, will feature a number of side events hosted by UNFPA and partners, including the launch of the Global Action Plan for Midwifery – a bold call to action designed to rally the maternal health community and drive political commitment to strengthen midwifery models of care. \nThe Commission on Population and Development is made up of 47 United Nations Member States elected by the Economic and Social Council for a period of four years, based on geographic distribution. It assists the Economic and Social Council in many ways, including advising on population issues, as well as monitoring and assessing the implementation of the Programme of Action of the landmark International Conference on Population and Development.\nThis year’s session will be broadcast on UN Web TV. You can learn more about it here. \n\nSide events hosted by UNFPA and partners\nImproving Health and Well-being for Women and Newborns: Launch of the Midwifery Accelerator\n7 April, 1:15 p.m. – 2:30 p.m. EDT\nUN Headquarters, Conference Room 4\nHosted by UNFPA and partners including the Governments of Denmark, Germany, Luxembourg, Mexico, Sierra Leone, Sweden, and the United Kingdom, as well as the International Confederation of Midwives, UNICEF and the World Health Organization, this event rallies global leaders on the urgent need to expand midwifery services. The release of updated maternal mortality figures will underscore the high stakes, making a robust case for immediate investment in midwifery to drive lasting improvements in maternal, newborn and child health worldwide. Register here or watch here.\n\nIntergenerational Dialogue: Ensuring Healthy Lives – Bridging Generations for Action \n8 April, 1:15 p.m. – 2:30 p.m. EDT\nUN Headquarters, Conference Room 8\nThis event brings together experts, policymakers and advocates to discuss health, demographic shifts and well-being across all ages. It is organized by UNFPA and the Government of Japan, Kingdom of Denmark, Kingdom of the Netherlands, Republic of Benin, Republic of India, Republic of Lebanon, Republic of Moldova, Republic of Uruguay and the UN Youth Office. UNFPA Executive Director Dr. Natalia Kanem will speak at the event. Register here or watch here.\n\nPrioritizing Sexual and Reproductive Health and Sexual and Gender-based Violence in Crisis Response\n8 April 1:15 p.m. – 2:30 p.m. EDT\nUN Headquarters, Conference Room 4\nThis event will address the importance of investing in health systems’ preparedness to respond to the health needs of women and girls affected by humanitarian crises. It will focus on access to life-saving support, including age- and gender-responsive sexual and reproductive health services for survivors of sexual and gender-based violence. It is hosted by UNFPA, together with the Permanent Missions of Colombia, Moldova and Norway, the International Planned Parenthood Federation, Plan International and UNICEF. Register here or watch here.\n\nLaunch of the UNFPA Innovation Strategy 2030: Innovating for Rights and Choices: By, for and with Women and Young People\n8 April, 3:00 p.m. – 4:30 p.m. EDT\nOrange Café, UNFPA Headquarters, 605 Third Avenue, New York\nAs the world accelerates efforts to create universal health coverage and gender equality, innovation plays a critical role in addressing persistent inequalities. This event will introduce the UNFPA Innovation Strategy 2030, a bold framework prioritizing women-led, youth-driven and locally informed solutions. The strategy harnesses emerging technologies and behavioral insights to advance gender-equitable innovation across UNFPA’s mandate. Register here.\n\nDemographic Intelligence for Health Equity: Harnessing Data for Inclusive Policies and Universal Coverage\n10 April, 1:15 p.m. – 2:30 p.m. EDT\nUN Secretariat, Conference Room 12\nOrganized by UNFPA, the Governments of Colombia, Colombia  the Dominican Republic and Ecuador, and together with Harvard Medical School, this event will emphasize the role of demographic insights in advancing health equity, strengthening health systems and ensuring universal access to care. Register here or watch here.\n\nThe Role of the Private Sector, Innovation and Technology in Bridging the Gap in Maternal Health and Ensuring We Leave No One Behind\n10 April, 1:15 p.m. to 2:30 p.m. EDT\nUN Secretariat, Conference Room 12\nAt this event, co-sponsored by the Governments of Finland and Mexico, UNFPA and partners will discuss reproductive health, explore strategic partnerships, highlight best practices and discuss the potential of an integrated approach to support bridging the gap in maternal health outcomes – and to ensure that we leave no one behind. Register here.\n\nThe fifty-eighth session of the Commission on Population and Development will spotlight the critical importance of ensuring healthy lives and well-being for all, at all ages. \nThe session, which begins on World Health Day on 7 April, will feature a number of side events hosted by UNFPA and partners, including the launch of the Global Action Plan for Midwifery – a bold call to action designed to rally the maternal health community and drive political commitment to strengthen midwifery models of care. \nThe Commission on Population and Development is made up of 47 United Nations Member States elected by the Economic and Social Council for a period of four years, based on geographic distribution. It assists the Economic and Social Council in many ways, including advising on population issues, as well as monitoring and assessing the implementation of the Programme of Action of the landmark International Conference on Population and Development.\nThis year’s session will be broadcast on UN Web TV. You can learn more about it here. \n\nSide events hosted by UNFPA and partners\nImproving Health and Well-being for Women and Newborns: Launch of the Midwifery Accelerator\n7 April, 1:15 p.m. – 2:30 p.m. EDT\nUN Headquarters, Conference Room 4\nHosted by UNFPA and partners including the Governments of Denmark, Germany, Luxembourg, Mexico, Sierra Leone, Sweden, and the United Kingdom, as well as the International Confederation of Midwives, UNICEF and the World Health Organization, this event rallies global leaders on the urgent need to expand midwifery services. The release of updated maternal mortality figures will underscore the high stakes, making a robust case for immediate investment in midwifery to drive lasting improvements in maternal, newborn and child health worldwide. Register here or watch here.\n\nIntergenerational Dialogue: Ensuring Healthy Lives – Bridging Generations for Action \n8 April, 1:15 p.m. – 2:30 p.m. EDT\nUN Headquarters, Conference Room 8\nThis event brings together experts, policymakers and advocates to discuss health, demographic shifts and well-being across all ages. It is organized by UNFPA and the Government of Japan, Kingdom of Denmark, Kingdom of the Netherlands, Republic of Benin, Republic of India, Republic of Lebanon, Republic of Moldova, Republic of Uruguay and the UN Youth Office. UNFPA Executive Director Dr. Natalia Kanem will speak at the event. Register here or watch here.\n\nPrioritizing Sexual and Reproductive Health and Sexual and Gender-based Violence in Crisis Response\n8 April 1:15 p.m. – 2:30 p.m. EDT\nUN Headquarters, Conference Room 4\nThis event will address the importance of investing in health systems’ preparedness to respond to the health needs of women and girls affected by humanitarian crises. It will focus on access to life-saving support, including age- and gender-responsive sexual and reproductive health services for survivors of sexual and gender-based violence. It is hosted by UNFPA, together with the Permanent Missions of Colombia, Moldova and Norway, the International Planned Parenthood Federation, Plan International and UNICEF. Register here or watch here.\n\nLaunch of the UNFPA Innovation Strategy 2030: Innovating for Rights and Choices: By, for and with Women and Young People\n8 April, 3:00 p.m. – 4:30 p.m. EDT\nOrange Café, UNFPA Headquarters, 605 Third Avenue, New York\nAs the world accelerates efforts to create universal health coverage and gender equality, innovation plays a critical role in addressing persistent inequalities. This event will introduce the UNFPA Innovation Strategy 2030, a bold framework prioritizing women-led, youth-driven and locally informed solutions. The strategy harnesses emerging technologies and behavioral insights to advance gender-equitable innovation across UNFPA’s mandate. Register here.\n\nDemographic Intelligence for Health Equity: Harnessing Data for Inclusive Policies and Universal Coverage\n10 April, 1:15 p.m. – 2:30 p.m. EDT\nUN Secretariat, Conference Room 12\nOrganized by UNFPA, the Governments of Colombia, Colombia  the Dominican Republic and Ecuador, and together with Harvard Medical School, this event will emphasize the role of demographic insights in advancing health equity, strengthening health systems and ensuring universal access to care. Register here or watch here.\n\nThe Role of the Private Sector, Innovation and Technology in Bridging the Gap in Maternal Health and Ensuring We Leave No One Behind\n10 April, 1:15 p.m. to 2:30 p.m. EDT\nUN Secretariat, Conference Room 12\nAt this event, co-sponsored by the Governments of Finland and Mexico, UNFPA and partners will discuss reproductive health, explore strategic partnerships, highlight best practices and discuss the potential of an integrated approach to support bridging the gap in maternal health outcomes – and to ensure that we leave no one behind. Register here.\n\nThe fifty-eighth session of the Commission on Population and Development will spotlight the critical importance of ensuring healthy lives and well-being for all, at all ages. \nThe session, which begins on World Health Day on 7 April, will feature a number of side events hosted by UNFPA and partners, including the launch of the Global Action Plan for Midwifery – a bold call to action designed to rally the maternal health community and drive political commitment to strengthen midwifery models of care. \nThe Commission on Population and Development is made up of 47 United Nations Member States elected by the Economic and Social Council for a period of four years, based on geographic distribution. It assists the Economic and Social Council in many ways, including advising on population issues, as well as monitoring and assessing the implementation of the Programme of Action of the landmark International Conference on Population and Development.\nThis year’s session will be broadcast on UN Web TV. You can learn more about it here. \n\nSide events hosted by UNFPA and partners\nImproving Health and Well-being for Women and Newborns: Launch of the Midwifery Accelerator\n7 April, 1:15 p.m. – 2:30 p.m. EDT\nUN Headquarters, Conference Room 4\nHosted by UNFPA and partners including the Governments of Denmark, Germany, Luxembourg, Mexico, Sierra Leone, Sweden, and the United Kingdom, as well as the International Confederation of Midwives, UNICEF and the World Health Organization, this event rallies global leaders on the urgent need to expand midwifery services. The release of updated maternal mortality figures will underscore the high stakes, making a robust case for immediate investment in midwifery to drive lasting improvements in maternal, newborn and child health worldwide. Register here or watch here.\n\nIntergenerational Dialogue: Ensuring Healthy Lives – Bridging Generations for Action \n8 April, 1:15 p.m. – 2:30 p.m. EDT\nUN Headquarters, Conference Room 8\nThis event brings together experts, policymakers and advocates to discuss health, demographic shifts and well-being across all ages. It is organized by UNFPA and the Government of Japan, Kingdom of Denmark, Kingdom of the Netherlands, Republic of Benin, Republic of India, Republic of Lebanon, Republic of Moldova, Republic of Uruguay and the UN Youth Office. UNFPA Executive Director Dr. Natalia Kanem will speak at the event. Register here or watch here.\n\nPrioritizing Sexual and Reproductive Health and Sexual and Gender-based Violence in Crisis Response\n8 April 1:15 p.m. – 2:30 p.m. EDT\nUN Headquarters, Conference Room 4\nThis event will address the importance of investing in health systems’ preparedness to respond to the health needs of women and girls affected by humanitarian crises. It will focus on access to life-saving support, including age- and gender-responsive sexual and reproductive health services for survivors of sexual and gender-based violence. It is hosted by UNFPA, together with the Permanent Missions of Colombia, Moldova and Norway, the International Planned Parenthood Federation, Plan International and UNICEF. Register here or watch here.\n\nLaunch of the UNFPA Innovation Strategy 2030: Innovating for Rights and Choices: By, for and with Women and Young People\n8 April, 3:00 p.m. – 4:30 p.m. EDT\nOrange Café, UNFPA Headquarters, 605 Third Avenue, New York\nAs the world accelerates efforts to create universal health coverage and gender equality, innovation plays a critical role in addressing persistent inequalities. This event will introduce the UNFPA Innovation Strategy 2030, a bold framework prioritizing women-led, youth-driven and locally informed solutions. The strategy harnesses emerging technologies and behavioral insights to advance gender-equitable innovation across UNFPA’s mandate. Register here.\n\nDemographic Intelligence for Health Equity: Harnessing Data for Inclusive Policies and Universal Coverage\n10 April, 1:15 p.m. – 2:30 p.m. EDT\nUN Secretariat, Conference Room 12\nOrganized by UNFPA, the Governments of Colombia, Colombia  the Dominican Republic and Ecuador, and together with Harvard Medical School, this event will emphasize the role of demographic insights in advancing health equity, strengthening health systems and ensuring universal access to care. Register here or watch here.\n\nThe Role of the Private Sector, Innovation and Technology in Bridging the Gap in Maternal Health and Ensuring We Leave No One Behind\n10 April, 1:15 p.m. to 2:30 p.m. EDT\nUN Secretariat, Conference Room 12\nAt this event, co-sponsored by the Governments of Finland and Mexico, UNFPA and partners will discuss reproductive health, explore strategic partnerships, highlight best practices and discuss the potential of an integrated approach to support bridging the gap in maternal health outcomes – and to ensure that we leave no one behind. Register here.\n\nThe fifty-eighth session of the Commission on Population and Development will spotlight the critical importance of ensuring healthy lives and well-being for all, at all ages. \nThe session, which begins on World Health Day on 7 April, will feature a number of side events hosted by UNFPA and partners, including the launch of the Global Action Plan for Midwifery – a bold call to action designed to rally the maternal health community and drive political commitment to strengthen midwifery models of care. \nThe Commission on Population and Development is made up of 47 United Nations Member States elected by the Economic and Social Council for a period of four years, based on geographic distribution. It assists the Economic and Social Council in many ways, including advising on population issues, as well as monitoring and assessing the implementation of the Programme of Action of the landmark International Conference on Population and Development.\nThis year’s session will be broadcast on UN Web TV. You can learn more about it here. \n\nSide events hosted by UNFPA and partners\nImproving Health and Well-being for Women and Newborns: Launch of the Midwifery Accelerator\n7 April, 1:15 p.m. – 2:30 p.m. EDT\nUN Headquarters, Conference Room 4\nHosted by UNFPA and partners including the Governments of Denmark, Germany, Luxembourg, Mexico, Sierra Leone, Sweden, and the United Kingdom, as well as the International Confederation of Midwives, UNICEF and the World Health Organization, this event rallies global leaders on the urgent need to expand midwifery services. The release of updated maternal mortality figures will underscore the high stakes, making a robust case for immediate investment in midwifery to drive lasting improvements in maternal, newborn and child health worldwide. Register here or watch here.\n\nIntergenerational Dialogue: Ensuring Healthy Lives – Bridging Generations for Action \n8 April, 1:15 p.m. – 2:30 p.m. EDT\nUN Headquarters, Conference Room 8\nThis event brings together experts, policymakers and advocates to discuss health, demographic shifts and well-being across all ages. It is organized by UNFPA and the Government of Japan, Kingdom of Denmark, Kingdom of the Netherlands, Republic of Benin, Republic of India, Republic of Lebanon, Republic of Moldova, Republic of Uruguay and the UN Youth Office. UNFPA Executive Director Dr. Natalia Kanem will speak at the event. Register here or watch here.\n\nPrioritizing Sexual and Reproductive Health and Sexual and Gender-based Violence in Crisis Response\n8 April 1:15 p.m. – 2:30 p.m. EDT\nUN Headquarters, Conference Room 4\nThis event will address the importance of investing in health systems’ preparedness to respond to the health needs of women and girls affected by humanitarian crises. It will focus on access to life-saving support, including age- and gender-responsive sexual and reproductive health services for survivors of sexual and gender-based violence. It is hosted by UNFPA, together with the Permanent Missions of Colombia, Moldova and Norway, the International Planned Parenthood Federation, Plan International and UNICEF. Register here or watch here.\n\nLaunch of the UNFPA Innovation Strategy 2030: Innovating for Rights and Choices: By, for and with Women and Young People\n8 April, 3:00 p.m. – 4:30 p.m. EDT\nOrange Café, UNFPA Headquarters, 605 Third Avenue, New York\nAs the world accelerates efforts to create universal health coverage and gender equality, innovation plays a critical role in addressing persistent inequalities. This event will introduce the UNFPA Innovation Strategy 2030, a bold framework prioritizing women-led, youth-driven and locally informed solutions. The strategy harnesses emerging technologies and behavioral insights to advance gender-equitable innovation across UNFPA’s mandate. Register here.\n\nDemographic Intelligence for Health Equity: Harnessing Data for Inclusive Policies and Universal Coverage\n10 April, 1:15 p.m. – 2:30 p.m. EDT\nUN Secretariat, Conference Room 12\nOrganized by UNFPA, the Governments of Colombia, Colombia  the Dominican Republic and Ecuador, and together with Harvard Medical School, this event will emphasize the role of demographic insights in advancing health equity, strengthening health systems and ensuring universal access to care. Register here or watch here.\n\nThe Role of the Private Sector, Innovation and Technology in Bridging the Gap in Maternal Health and Ensuring We Leave No One Behind\n10 April, 1:15 p.m. to 2:30 p.m. EDT\nUN Secretariat, Conference Room 12\nAt this event, co-sponsored by the Governments of Finland and Mexico, UNFPA and partners will discuss reproductive health, explore strategic partnerships, highlight best practices and discuss the potential of an integrated approach to support bridging the gap in maternal health outcomes – and to ensure that we leave no one behind. Register here.\n\nThe fifty-eighth session of the Commission on Population and Development will spotlight the critical importance of ensuring healthy lives and well-being for all, at all ages. \nThe session, which begins on World Health Day on 7 April, will feature a number of side events hosted by UNFPA and partners, including the launch of the Global Action Plan for Midwifery – a bold call to action designed to rally the maternal health community and drive political commitment to strengthen midwifery models of care. \nThe Commission on Population and Development is made up of 47 United Nations Member States elected by the Economic and Social Council for a period of four years, based on geographic distribution. It assists the Economic and Social Council in many ways, including advising on population issues, as well as monitoring and assessing the implementation of the Programme of Action of the landmark International Conference on Population and Development.\nThis year’s session will be broadcast on UN Web TV. You can learn more about it here. \n\nSide events hosted by UNFPA and partners\nImproving Health and Well-being for Women and Newborns: Launch of the Midwifery Accelerator\n7 April, 1:15 p.m. – 2:30 p.m. EDT\nUN Headquarters, Conference Room 4\nHosted by UNFPA and partners including the Governments of Denmark, Germany, Luxembourg, Mexico, Sierra Leone, Sweden, and the United Kingdom, as well as the International Confederation of Midwives, UNICEF and the World Health Organization, this event rallies global leaders on the urgent need to expand midwifery services. The release of updated maternal mortality figures will underscore the high stakes, making a robust case for immediate investment in midwifery to drive lasting improvements in maternal, newborn and child health worldwide. Register here or watch here.\n\nIntergenerational Dialogue: Ensuring Healthy Lives – Bridging Generations for Action \n8 April, 1:15 p.m. – 2:30 p.m. EDT\nUN Headquarters, Conference Room 8\nThis event brings together experts, policymakers and advocates to discuss health, demographic shifts and well-being across all ages. It is organized by UNFPA and the Government of Japan, Kingdom of Denmark, Kingdom of the Netherlands, Republic of Benin, Republic of India, Republic of Lebanon, Republic of Moldova, Republic of Uruguay and the UN Youth Office. UNFPA Executive Director Dr. Natalia Kanem will speak at the event. Register here or watch here.\n\nPrioritizing Sexual and Reproductive Health and Sexual and Gender-based Violence in Crisis Response\n8 April 1:15 p.m. – 2:30 p.m. EDT\nUN Headquarters, Conference Room 4\nThis event will address the importance of investing in health systems’ preparedness to respond to the health needs of women and girls affected by humanitarian crises. It will focus on access to life-saving support, including age- and gender-responsive sexual and reproductive health services for survivors of sexual and gender-based violence. It is hosted by UNFPA, together with the Permanent Missions of Colombia, Moldova and Norway, the International Planned Parenthood Federation, Plan International and UNICEF. Register here or watch here.\n\nLaunch of the UNFPA Innovation Strategy 2030: Innovating for Rights and Choices: By, for and with Women and Young People\n8 April, 3:00 p.m. – 4:30 p.m. EDT\nOrange Café, UNFPA Headquarters, 605 Third Avenue, New York\nAs the world accelerates efforts to create universal health coverage and gender equality, innovation plays a critical role in addressing persistent inequalities. This event will introduce the UNFPA Innovation Strategy 2030, a bold framework prioritizing women-led, youth-driven and locally informed solutions. The strategy harnesses emerging technologies and behavioral insights to advance gender-equitable innovation across UNFPA’s mandate. Register here.\n\nDemographic Intelligence for Health Equity: Harnessing Data for Inclusive Policies and Universal Coverage\n10 April, 1:15 p.m. – 2:30 p.m. EDT\nUN Secretariat, Conference Room 12\nOrganized by UNFPA, the Governments of Colombia, Colombia  the Dominican Republic and Ecuador, and together with Harvard Medical School, this event will emphasize the role of demographic insights in advancing health equity, strengthening health systems and ensuring universal access to care. Register here or watch here.\n\nThe Role of the Private Sector, Innovation and Technology in Bridging the Gap in Maternal Health and Ensuring We Leave No One Behind\n10 April, 1:15 p.m. to 2:30 p.m. EDT\nUN Secretariat, Conference Room 12\nAt this event, co-sponsored by the Governments of Finland and Mexico, UNFPA and partners will discuss reproductive health, explore strategic partnerships, highlight best practices and discuss the potential of an integrated approach to support bridging the gap in maternal health outcomes – and to ensure that we leave no one behind. Register here.\n\nThe fifty-eighth session of the Commission on Population and Development will spotlight the critical importance of ensuring healthy lives and well-being for all, at all ages. \nThe session, which begins on World Health Day on 7 April, will feature a number of side events hosted by UNFPA and partners, including the launch of the Global Action Plan for Midwifery – a bold call to action designed to rally the maternal health community and drive political commitment to strengthen midwifery models of care. \nThe Commission on Population and Development is made up of 47 United Nations Member States elected by the Economic and Social Council for a period of four years, based on geographic distribution. It assists the Economic and Social Council in many ways, including advising on population issues, as well as monitoring and assessing the implementation of the Programme of Action of the landmark International Conference on Population and Development.\nThis year’s session will be broadcast on UN Web TV. You can learn more about it here. \n\nSide events hosted by UNFPA and partners\nImproving Health and Well-being for Women and Newborns: Launch of the Midwifery Accelerator\n7 April, 1:15 p.m. – 2:30 p.m. EDT\nUN Headquarters, Conference Room 4\nHosted by UNFPA and partners including the Governments of Denmark, Germany, Luxembourg, Mexico, Sierra Leone, Sweden, and the United Kingdom, as well as the International Confederation of Midwives, UNICEF and the World Health Organization, this event rallies global leaders on the urgent need to expand midwifery services. The release of updated maternal mortality figures will underscore the high stakes, making a robust case for immediate investment in midwifery to drive lasting improvements in maternal, newborn and child health worldwide. Register here or watch here.\n\nIntergenerational Dialogue: Ensuring Healthy Lives – Bridging Generations for Action \n8 April, 1:15 p.m. – 2:30 p.m. EDT\nUN Headquarters, Conference Room 8\nThis event brings together experts, policymakers and advocates to discuss health, demographic shifts and well-being across all ages. It is organized by UNFPA and the Government of Japan, Kingdom of Denmark, Kingdom of the Netherlands, Republic of Benin, Republic of India, Republic of Lebanon, Republic of Moldova, Republic of Uruguay and the UN Youth Office. UNFPA Executive Director Dr. Natalia Kanem will speak at the event. Register here or watch here.\n\nPrioritizing Sexual and Reproductive Health and Sexual and Gender-based Violence in Crisis Response\n8 April 1:15 p.m. – 2:30 p.m. EDT\nUN Headquarters, Conference Room 4\nThis event will address the importance of investing in health systems’ preparedness to respond to the health needs of women and girls affected by humanitarian crises. It will focus on access to life-saving support, including age- and gender-responsive sexual and reproductive health services for survivors of sexual and gender-based violence. It is hosted by UNFPA, together with the Permanent Missions of Colombia, Moldova and Norway, the International Planned Parenthood Federation, Plan International and UNICEF. Register here or watch here.\n\nLaunch of the UNFPA Innovation Strategy 2030: Innovating for Rights and Choices: By, for and with Women and Young People\n8 April, 3:00 p.m. – 4:30 p.m. EDT\nOrange Café, UNFPA Headquarters, 605 Third Avenue, New York\nAs the world accelerates efforts to create universal health coverage and gender equality, innovation plays a critical role in addressing persistent inequalities. This event will introduce the UNFPA Innovation Strategy 2030, a bold framework prioritizing women-led, youth-driven and locally informed solutions. The strategy harnesses emerging technologies and behavioral insights to advance gender-equitable innovation across UNFPA’s mandate. Register here.\n\nDemographic Intelligence for Health Equity: Harnessing Data for Inclusive Policies and Universal Coverage\n10 April, 1:15 p.m. – 2:30 p.m. EDT\nUN Secretariat, Conference Room 12\nOrganized by UNFPA, the Governments of Colombia, Colombia  the Dominican Republic and Ecuador, and together with Harvard Medical School, this event will emphasize the role of demographic insights in advancing health equity, strengthening health systems and ensuring universal access to care. Register here or watch here.\n\nThe Role of the Private Sector, Innovation and Technology in Bridging the Gap in Maternal Health and Ensuring We Leave No One Behind\n10 April, 1:15 p.m. to 2:30 p.m. EDT\nUN Secretariat, Conference Room 12\nAt this event, co-sponsored by the Governments of Finland and Mexico, UNFPA and partners will discuss reproductive health, explore strategic partnerships, highlight best practices and discuss the potential of an integrated approach to support bridging the gap in maternal health outcomes – and to ensure that we leave no one behind. Register here.\n\nThe fifty-eighth session of the Commission on Population and Development will spotlight the critical importance of ensuring healthy lives and well-being for all, at all ages.\n\nThe session, which begins on World Health Day on 7 April, will feature a number of side events hosted by UNFPA and partners, including the launch of the Global Action Plan for Midwifery – a bold call to action designed to rally the maternal health community and drive political commitment to strengthen midwifery models of care.\n\nThe Commission on Population and Development is made up of 47 United Nations Member States elected by the Economic and Social Council for a period of four years, based on geographic distribution. It assists the Economic and Social Council in many ways, including advising on population issues, as well as monitoring and assessing the implementation of the Programme of Action of the landmark International Conference on Population and Development.\n\nThis year’s session will be broadcast on UN Web TV. You can learn more about it here.\n\nSide events hosted by UNFPA and partners\n\nImproving Health and Well-being for Women and Newborns: Launch of the Midwifery Accelerator\n\n7 April, 1:15 p.m. – 2:30 p.m. EDT\n\nUN Headquarters, Conference Room 4\n\nHosted by UNFPA and partners including the Governments of Denmark, Germany, Luxembourg, Mexico, Sierra Leone, Sweden, and the United Kingdom, as well as the International Confederation of Midwives, UNICEF and the World Health Organization, this event rallies global leaders on the urgent need to expand midwifery services. The release of updated maternal mortality figures will underscore the high stakes, making a robust case for immediate investment in midwifery to drive lasting improvements in maternal, newborn and child health worldwide. Register here or watch here.\n\nIntergenerational Dialogue: Ensuring Healthy Lives – Bridging Generations for Action\n\n8 April, 1:15 p.m. – 2:30 p.m. EDT\n\nUN Headquarters, Conference Room 8\n\nThis event brings together experts, policymakers and advocates to discuss health, demographic shifts and well-being across all ages. It is organized by UNFPA and the Government of Japan, Kingdom of Denmark, Kingdom of the Netherlands, Republic of Benin, Republic of India, Republic of Lebanon, Republic of Moldova, Republic of Uruguay and the UN Youth Office. UNFPA Executive Director Dr. Natalia Kanem will speak at the event. Register here or watch here.\n\nPrioritizing Sexual and Reproductive Health and Sexual and Gender-based Violence in Crisis Response\n\n8 April 1:15 p.m. – 2:30 p.m. EDT\n\nUN Headquarters, Conference Room 4\n\nThis event will address the importance of investing in health systems’ preparedness to respond to the health needs of women and girls affected by humanitarian crises. It will focus on access to life-saving support, including age- and gender-responsive sexual and reproductive health services for survivors of sexual and gender-based violence. It is hosted by UNFPA, together with the Permanent Missions of Colombia, Moldova and Norway, the International Planned Parenthood Federation, Plan International and UNICEF. Register here or watch here.\n\nLaunch of the UNFPA Innovation Strategy 2030: Innovating for Rights and Choices: By, for and with Women and Young People\n\n8 April, 3:00 p.m. – 4:30 p.m. EDT\n\nOrange Café, UNFPA Headquarters, 605 Third Avenue, New York\n\nAs the world accelerates efforts to create universal health coverage and gender equality, innovation plays a critical role in addressing persistent inequalities. This event will introduce the UNFPA Innovation Strategy 2030, a bold framework prioritizing women-led, youth-driven and locally informed solutions. The strategy harnesses emerging technologies and behavioral insights to advance gender-equitable innovation across UNFPA’s mandate. Register here.\n\nDemographic Intelligence for Health Equity: Harnessing Data for Inclusive Policies and Universal Coverage\n\n10 April, 1:15 p.m. – 2:30 p.m. EDT\n\nUN Secretariat, Conference Room 12\n\nOrganized by UNFPA, the Governments of Colombia, Colombia  the Dominican Republic and Ecuador, and together with Harvard Medical School, this event will emphasize the role of demographic insights in advancing health equity, strengthening health systems and ensuring universal access to care. Register here or watch here.\n\nThe Role of the Private Sector, Innovation and Technology in Bridging the Gap in Maternal Health and Ensuring We Leave No One Behind\n\n10 April, 1:15 p.m. to 2:30 p.m. EDT\n\nUN Secretariat, Conference Room 12\n\nAt this event, co-sponsored by the Governments of Finland and Mexico, UNFPA and partners will discuss reproductive health, explore strategic partnerships, highlight best practices and discuss the potential of an integrated approach to support bridging the gap in maternal health outcomes – and to ensure that we leave no one behind. Register here.\n\nRelated topics\n\n\n\n\nSexual & reproductive health\n\nRelated topics\n\n\n\n\nSexual & reproductive health\n\nRelated topics\n\n\n\n\nSexual & reproductive health\n\nRelated topics\n\n\n\n\nSexual & reproductive health\n\nRelated topics\n\n\n\n\nSexual & reproductive health\n\nSexual & reproductive health\n\nSexual & reproductive health\n\nSexual & reproductive health\n\nBack to page\n    \n\n\n\n\nEvents\n\n\n\n\n\n\nShare on Facebook\n\n\n\n\n\nShare on Twitter\n\nBack to page\n\nBack to page\n\nEvents\n\n\n\n\n\n\nShare on Facebook\n\n\n\n\n\nShare on Twitter\n\nEvents\n\nEvents\n\nShare on Facebook\n\n\n\n\n\nShare on Twitter\n\nShare on Facebook\n\nShare on Twitter\n\nRelated Content\n\n\n\n\n\n\n\n\n\n\nEvents\n\nIntergenerational Dialogue: Ensuring healthy lives – Bridging generations for…\n\nRead more\n\n\n\n\n\n\n\n\n\n\n\nSpeech\n\nOpening Remarks by UNFPA Executive Director Dr. Natalia Kanem at the Commission…\n\nRead more\n\n\n\n\n\n\n\n\n\n\n\n\n\n\n\nUpdates\n\nMaternal health champions at CPD: It’s time to act for mothers and newborns\n\nRead more\n\nRelated Content\n\n\n\n\n\n\n\n\n\n\nEvents\n\nIntergenerational Dialogue: Ensuring healthy lives – Bridging generations for…\n\nRead more\n\n\n\n\n\n\n\n\n\n\n\nSpeech\n\nOpening Remarks by UNFPA Executive Director Dr. Natalia Kanem at the Commission…\n\nRead more\n\n\n\n\n\n\n\n\n\n\n\n\n\n\n\nUpdates\n\nMaternal health champions at CPD: It’s time to act for mothers and newborns\n\nRead more\n\nRelated Content\n\n\n\n\n\n\n\n\n\n\nEvents\n\nIntergenerational Dialogue: Ensuring healthy lives – Bridging generations for…\n\nRead more\n\n\n\n\n\n\n\n\n\n\n\nSpeech\n\nOpening Remarks by UNFPA Executive Director Dr. Natalia Kanem at the Commission…\n\nRead more\n\n\n\n\n\n\n\n\n\n\n\n\n\n\n\nUpdates\n\nMaternal health champions at CPD: It’s time to act for mothers and newborns\n\nRead more\n\nRelated Content\n\n\n\n\n\n\n\n\n\n\nEvents\n\nIntergenerational Dialogue: Ensuring healthy lives – Bridging generations for…\n\nRead more\n\n\n\n\n\n\n\n\n\n\n\nSpeech\n\nOpening Remarks by UNFPA Executive Director Dr. Natalia Kanem at the Commission…\n\nRead more\n\n\n\n\n\n\n\n\n\n\n\n\n\n\n\nUpdates\n\nMaternal health champions at CPD: It’s time to act for mothers and newborns\n\nRead more\n\nRelated Content\n\n\n\n\n\n\n\n\n\n\nEvents\n\nIntergenerational Dialogue: Ensuring healthy lives – Bridging generations for…\n\nRead more\n\n\n\n\n\n\n\n\n\n\n\nSpeech\n\nOpening Remarks by UNFPA Executive Director Dr. Natalia Kanem at the Commission…\n\nRead more\n\n\n\n\n\n\n\n\n\n\n\n\n\n\n\nUpdates\n\nMaternal health champions at CPD: It’s time to act for mothers and newborns\n\nRead more\n\nRelated Content\n\n\n\n\n\n\n\n\n\n\nEvents\n\nIntergenerational Dialogue: Ensuring healthy lives – Bridging generations for…\n\nRead more\n\n\n\n\n\n\n\n\n\n\n\nSpeech\n\nOpening Remarks by UNFPA Executive Director Dr. Natalia Kanem at the Commission…\n\nRead more\n\n\n\n\n\n\n\n\n\n\n\n\n\n\n\nUpdates\n\nMaternal health champions at CPD: It’s time to act for mothers and newborns\n\nRead more\n\nRelated Content\n\n\n\n\n\n\n\n\n\n\nEvents\n\nIntergenerational Dialogue: Ensuring healthy lives – Bridging generations for…\n\nRead more\n\n\n\n\n\n\n\n\n\n\n\nSpeech\n\nOpening Remarks by UNFPA Executive Director Dr. Natalia Kanem at the Commission…\n\nRead more\n\n\n\n\n\n\n\n\n\n\n\n\n\n\n\nUpdates\n\nMaternal health champions at CPD: It’s time to act for mothers and newborns\n\nRead more\n\nRelated Content\n\n\n\n\n\n\n\n\n\n\nEvents\n\nIntergenerational Dialogue: Ensuring healthy lives – Bridging generations for…\n\nRead more\n\n\n\n\n\n\n\n\n\n\n\nSpeech\n\nOpening Remarks by UNFPA Executive Director Dr. Natalia Kanem at the Commission…\n\nRead more\n\n\n\n\n\n\n\n\n\n\n\n\n\n\n\nUpdates\n\nMaternal health champions at CPD: It’s time to act for mothers and newborns\n\nRead more\n\nEvents\n\nIntergenerational Dialogue: Ensuring healthy lives – Bridging generations for…\n\nRead more\n\n\n\n\n\n\n\n\n\n\n\nSpeech\n\nOpening Remarks by UNFPA Executive Director Dr. Natalia Kanem at the Commission…\n\nRead more\n\n\n\n\n\n\n\n\n\n\n\n\n\n\n\nUpdates\n\nMaternal health champions at CPD: It’s time to act for mothers and newborns\n\nRead more\n\nEvents\n\nIntergenerational Dialogue: Ensuring healthy lives – Bridging generations for…\n\nRead more\n\n\n\n\n\n\n\n\n\n\n\nSpeech\n\nOpening Remarks by UNFPA Executive Director Dr. Natalia Kanem at the Commission…\n\nRead more\n\n\n\n\n\n\n\n\n\n\n\n\n\n\n\nUpdates\n\nMaternal health champions at CPD: It’s time to act for mothers and newborns\n\nRead more\n\nEvents\n\nIntergenerational Dialogue: Ensuring healthy lives – Bridging generations for…\n\nRead more\n\nEvents\n\nIntergenerational Dialogue: Ensuring healthy lives – Bridging generations for…\n\nRead more\n\nEvents\n\nIntergenerational Dialogue: Ensuring healthy lives – Bridging generations for…\n\nRead more\n\nEvents\n\nSpeech\n\nOpening Remarks by UNFPA Executive Director Dr. Natalia Kanem at the Commission…\n\nRead more\n\nSpeech\n\nOpening Remarks by UNFPA Executive Director Dr. Natalia Kanem at the Commission…\n\nRead more\n\nSpeech\n\nOpening Remarks by UNFPA Executive Director Dr. Natalia Kanem at the Commission…\n\nRead more\n\nSpeech\n\nUpdates\n\nMaternal health champions at CPD: It’s time to act for mothers and newborns\n\nRead more\n\nUpdates\n\nMaternal health champions at CPD: It’s time to act for mothers and newborns\n\nRead more\n\nUpdates\n\nMaternal health champions at CPD: It’s time to act for mothers and newborns\n\nRead more\n\nUpdates\n\nWe use cookies and other identifiers to help improve your online experience. By using our website you agree to this, see our cookie policy\n\nAccept\n\nX\n\nWe use cookies and other identifiers to help improve your online experience. By using our website you agree to this, see our cookie policy\n\nAccept\n\nX\n\nWe use cookies and other identifiers to help improve your online experience. By using our website you agree to this, see our cookie policy\n\nAccept\n\nX\n\nWe use cookies and other identifiers to help improve your online experience. By using our website you agree to this, see our cookie policy\n\nWe use cookies and other identifiers to help improve your online experience. By using our website you agree to this, see our cookie policy\n\nX",
  "date": "",
  "source_type": "other",
  "extracted_at": "2025-04-07T14:28:33.818928",
  "metadata": {
    "description": "The fifty-eighth session of the",
    "og:type": "article",
    "og:site_name": "United Nations Population Fund"
  },
  "relevance_score": 0.5714285714285714,
  "summary": "© UNFPA Egypt/Roger Anis \n\n\n\n\n\n\n\n\n\nHome\nEvent\nCommission on Population and Development, fifty-eighth session\n\n\n\n\n\nCommission on Population and Development, fifty-eighth session\n\n\n\n07 April - 11 April 2025\n\nUN Web TV\n\n\n\n\n\n\n\n\n\n\n\n\n\n\n\n\n\nThe fifty-eighth session of the Commission on Population and Development will spotlight the critical importance of ensuring healthy lives and well-being for all, at all ages. The session, which begins on World Health Day on 7 April, will feature a number of side events hosted by UNFPA and partners, including the launch of the Global Action Plan for Midwifery – a bold call to action designed to rally the maternal health community and drive political commitment to strengthen midwifery models of care. EDT\nUN Headquarters, Conference Room 4\nHosted by UNFPA and partners including the Governments of Denmark, Germany, Luxembourg, Mexico, Sierra Leone, Sweden, and the United Kingdom, as well as the International Confederation of Midwives, UNICEF and the World Health Organization, this event rallies global leaders on the urgent need to expand midwifery services. EDT\nUN Headquarters, Conference Room 8\nThis event brings together experts, policymakers and advocates to discuss health, demographic shifts and well-being across all ages. EDT\nUN Headquarters, Conference Room 4\nThis event will address the importance of investing in health systems’ preparedness to respond to the health needs of women and girls affected by humanitarian crises. EDT\nOrange Café, UNFPA Headquarters, 605 Third Avenue, New York\nAs the world accelerates efforts to create universal health coverage and gender equality, innovation plays a critical role in addressing persistent inequalities. EDT\nUN Secretariat, Conference Room 12\nOrganized by UNFPA, the Governments of Colombia, Colombia  the Dominican Republic and Ecuador, and together with Harvard Medical School, this event will emphasize the role of demographic insights in advancing health equity, strengthening health systems and ensuring universal access to care. EDT\nUN Secretariat, Conference Room 12\nAt this event, co-sponsored by the Governments of Finland and Mexico, UNFPA and partners will discuss reproductive health, explore strategic partnerships, highlight best practices and discuss the potential of an integrated approach to support bridging the gap in maternal health outcomes – and to ensure that we leave no one behind. Related topics\n\n\n\n\nSexual & reproductive health\n\n\n\n\n\n\n\n\n\n\n\n\n\n\n\n\n\n\n\n\n\n\n\n\n\n\n\n\n\n\n\n\n\n\n\n      Back to page\n    \n\n\n\n\nEvents\n\n\n\n\n\n\nShare on Facebook\n\n\n\n\n\nShare on Twitter\n\n\n\n\n\n\n\n\n\n\n\n\n\n\nRelated Content\n\n\n\n\n\n\n\n\n\n\nEvents\n\nIntergenerational Dialogue: Ensuring healthy lives – Bridging generations for…\n\nRead more\n\n\n\n\n\n\n\n\n\n\n\nSpeech\n\nOpening Remarks by UNFPA Executive Director Dr. Natalia Kanem at the Commission…\n\nRead more\n\n\n\n\n\n\n\n\n\n\n\n\n\n\n\nUpdates\n\nMaternal health champions at CPD: It’s time to act for mothers and newborns\n\nRead more\n\n© UNFPA Egypt/Roger Anis \n\n\n\n\n\n\n\n\n\nHome\nEvent\nCommission on Population and Development, fifty-eighth session\n\n\n\n\n\nCommission on Population and Development, fifty-eighth session\n\n\n\n07 April - 11 April 2025\n\nUN Web TV\n\n\n\n\n\n\n\n\n\n\n\n\n\n\n\n\n\nThe fifty-eighth session of the Commission on Population and Development will spotlight the critical importance of ensuring healthy lives and well-being for all, at all ages. The session, which begins on World Health Day on 7 April, will feature a number of side events hosted by UNFPA and partners, including the launch of the Global Action Plan for Midwifery – a bold call to action designed to rally the maternal health community and drive political commitment to strengthen midwifery models of care. EDT\nUN Headquarters, Conference Room 4\nHosted by UNFPA and partners including the Governments of Denmark, Germany, Luxembourg, Mexico, Sierra Leone, Sweden, and the United Kingdom, as well as the International Confederation of Midwives, UNICEF and the World Health Organization, this event rallies global leaders on the urgent need to expand midwifery services. EDT\nUN Headquarters, Conference Room 8\nThis event brings together experts, policymakers and advocates to discuss health, demographic shifts and well-being across all ages. EDT\nUN Headquarters, Conference Room 4\nThis event will address the importance of investing in health systems’ preparedness to respond to the health needs of women and girls affected by humanitarian crises. EDT\nUN Secretariat, Conference Room 12\nOrganized by UNFPA, the Governments of Colombia, Colombia  the Dominican Republic and Ecuador, and together with Harvard Medical School, this event will emphasize the role of demographic insights in advancing health equity, strengthening health systems and ensuring universal access to care. EDT\nUN Secretariat, Conference Room 12\nAt this event, co-sponsored by the Governments of Finland and Mexico, UNFPA and partners will discuss reproductive health, explore strategic partnerships, highlight best practices and discuss the potential of an integrated approach to support bridging the gap in maternal health outcomes – and to ensure that we leave no one behind. Related topics\n\n\n\n\nSexual & reproductive health\n\n\n\n\n\n\n\n\n\n\n\n\n\n\n\n\n\n\n\n\n\n\n\n\n\n\n\n\n\n\n\n\n\n\n\n      Back to page\n    \n\n\n\n\nEvents\n\n\n\n\n\n\nShare on Facebook\n\n\n\n\n\nShare on Twitter\n\n\n\n\n\n\n\n\n\n\n\n\n\n\nRelated Content\n\n\n\n\n\n\n\n\n\n\nEvents\n\nIntergenerational Dialogue: Ensuring healthy lives – Bridging generations for…\n\nRead more\n\n\n\n\n\n\n\n\n\n\n\nSpeech\n\nOpening Remarks by UNFPA Executive Director Dr. Natalia Kanem at the Commission…\n\nRead more\n\n\n\n\n\n\n\n\n\n\n\n\n\n\n\nUpdates\n\nMaternal health champions at CPD: It’s time to act for mothers and newborns\n\nRead more\n\n© UNFPA Egypt/Roger Anis\n\n© UNFPA Egypt/Roger Anis\n\nHome\nEvent\nCommission on Population and Development, fifty-eighth session\n\n\n\n\n\nCommission on Population and Development, fifty-eighth session\n\n\n\n07 April - 11 April 2025\n\nUN Web TV\n\n\n\n\n\n\n\n\n\n\n\n\n\n\n\n\n\nThe fifty-eighth session of the Commission on Population and Development will spotlight the critical importance of ensuring healthy lives and well-being for all, at all ages. The session, which begins on World Health Day on 7 April, will feature a number of side events hosted by UNFPA and partners, including the launch of the Global Action Plan for Midwifery – a bold call to action designed to rally the maternal health community and drive political commitment to strengthen midwifery models of care. EDT\nUN Headquarters, Conference Room 4\nHosted by UNFPA and partners including the Governments of Denmark, Germany, Luxembourg, Mexico, Sierra Leone, Sweden, and the United Kingdom, as well as the International Confederation of Midwives, UNICEF and the World Health Organization, this event rallies global leaders on the urgent need to expand midwifery services. EDT\nUN Headquarters, Conference Room 8\nThis event brings together experts, policymakers and advocates to discuss health, demographic shifts and well-being across all ages. EDT\nUN Headquarters, Conference Room 4\nThis event will address the importance of investing in health systems’ preparedness to respond to the health needs of women and girls affected by humanitarian crises. EDT\nUN Secretariat, Conference Room 12\nOrganized by UNFPA, the Governments of Colombia, Colombia  the Dominican Republic and Ecuador, and together with Harvard Medical School, this event will emphasize the role of demographic insights in advancing health equity, strengthening health systems and ensuring universal access to care. EDT\nUN Secretariat, Conference Room 12\nAt this event, co-sponsored by the Governments of Finland and Mexico, UNFPA and partners will discuss reproductive health, explore strategic partnerships, highlight best practices and discuss the potential of an integrated approach to support bridging the gap in maternal health outcomes – and to ensure that we leave no one behind. Related topics\n\n\n\n\nSexual & reproductive health\n\n\n\n\n\n\n\n\n\n\n\n\n\n\n\n\n\n\n\n\n\n\n\n\n\n\n\n\n\n\n\n\n\n\n\n      Back to page\n    \n\n\n\n\nEvents\n\n\n\n\n\n\nShare on Facebook\n\n\n\n\n\nShare on Twitter\n\n\n\n\n\n\n\n\n\n\n\n\n\n\nRelated Content\n\n\n\n\n\n\n\n\n\n\nEvents\n\nIntergenerational Dialogue: Ensuring healthy lives – Bridging generations for…\n\nRead more\n\n\n\n\n\n\n\n\n\n\n\nSpeech\n\nOpening Remarks by UNFPA Executive Director Dr. Natalia Kanem at the Commission…\n\nRead more\n\n\n\n\n\n\n\n\n\n\n\n\n\n\n\nUpdates\n\nMaternal health champions at CPD: It’s time to act for mothers and newborns\n\nRead more\n\nHome\nEvent\nCommission on Population and Development, fifty-eighth session\n\n\n\n\n\nCommission on Population and Development, fifty-eighth session\n\n\n\n07 April - 11 April 2025\n\nUN Web TV\n\n\n\n\n\n\n\n\n\n\n\n\n\n\n\n\n\nThe fifty-eighth session of the Commission on Population and Development will spotlight the critical importance of ensuring healthy lives and well-being for all, at all ages. The session, which begins on World Health Day on 7 April, will feature a number of side events hosted by UNFPA and partners, including the launch of the Global Action Plan for Midwifery – a bold call to action designed to rally the maternal health community and drive political commitment to strengthen midwifery models of care. EDT\nUN Headquarters, Conference Room 4\nHosted by UNFPA and partners including the Governments of Denmark, Germany, Luxembourg, Mexico, Sierra Leone, Sweden, and the United Kingdom, as well as the International Confederation of Midwives, UNICEF and the World Health Organization, this event rallies global leaders on the urgent need to expand midwifery services. EDT\nUN Headquarters, Conference Room 8\nThis event brings together experts, policymakers and advocates to discuss health, demographic shifts and well-being across all ages. EDT\nUN Headquarters, Conference Room 4\nThis event will address the importance of investing in health systems’ preparedness to respond to the health needs of women and girls affected by humanitarian crises. EDT\nUN Secretariat, Conference Room 12\nOrganized by UNFPA, the Governments of Colombia, Colombia  the Dominican Republic and Ecuador, and together with Harvard Medical School, this event will emphasize the role of demographic insights in advancing health equity, strengthening health systems and ensuring universal access to care. EDT\nUN Secretariat, Conference Room 12\nAt this event, co-sponsored by the Governments of Finland and Mexico, UNFPA and partners will discuss reproductive health, explore strategic partnerships, highlight best practices and discuss the potential of an integrated approach to support bridging the gap in maternal health outcomes – and to ensure that we leave no one behind. Related topics\n\n\n\n\nSexual & reproductive health\n\n\n\n\n\n\n\n\n\n\n\n\n\n\n\n\n\n\n\n\n\n\n\n\n\n\n\n\n\n\n\n\n\n\n\n      Back to page\n    \n\n\n\n\nEvents\n\n\n\n\n\n\nShare on Facebook\n\n\n\n\n\nShare on Twitter\n\n\n\n\n\n\n\n\n\n\n\n\n\n\nRelated Content\n\n\n\n\n\n\n\n\n\n\nEvents\n\nIntergenerational Dialogue: Ensuring healthy lives – Bridging generations for…\n\nRead more\n\n\n\n\n\n\n\n\n\n\n\nSpeech\n\nOpening Remarks by UNFPA Executive Director Dr. Natalia Kanem at the Commission…\n\nRead more\n\n\n\n\n\n\n\n\n\n\n\n\n\n\n\nUpdates\n\nMaternal health champions at CPD: It’s time to act for mothers and newborns\n\nRead more\n\nHome\nEvent\nCommission on Population and Development, fifty-eighth session\n\n\n\n\n\nCommission on Population and Development, fifty-eighth session\n\n\n\n07 April - 11 April 2025\n\nUN Web TV\n\nHome\nEvent\nCommission on Population and Development, fifty-eighth session\n\n\n\n\n\nCommission on Population and Development, fifty-eighth session\n\n\n\n07 April - 11 April 2025\n\nUN Web TV\n\nHome\nEvent\nCommission on Population and Development, fifty-eighth session\n\n\n\n\n\nCommission on Population and Development, fifty-eighth session\n\n\n\n07 April - 11 April 2025\n\nUN Web TV\n\nCommission on Population and Development, fifty-eighth session\n\n\n\n07 April - 11 April 2025\n\nUN Web TV\n\nCommission on Population and Development, fifty-eighth session\n\n\n\n07 April - 11 April 2025\n\nUN Web TV\n\nCommission on Population and Development, fifty-eighth session\n\n\n\n07 April - 11 April 2025\n\nUN Web TV\n\nCommission on Population and Development, fifty-eighth session\n\n\n\n07 April - 11 April 2025\n\nUN Web TV\n\n07 April - 11 April 2025\n\nUN Web TV\n\n07 April - 11 April 2025\n\nUN Web TV\n\n07 April - 11 April 2025\n\nUN Web TV\n\nThe fifty-eighth session of the Commission on Population and Development will spotlight the critical importance of ensuring healthy lives and well-being for all, at all ages. The session, which begins on World Health Day on 7 April, will feature a number of side events hosted by UNFPA and partners, including the launch of the Global Action Plan for Midwifery – a bold call to action designed to rally the maternal health community and drive political commitment to strengthen midwifery models of care. EDT\nUN Headquarters, Conference Room 4\nHosted by UNFPA and partners including the Governments of Denmark, Germany, Luxembourg, Mexico, Sierra Leone, Sweden, and the United Kingdom, as well as the International Confederation of Midwives, UNICEF and the World Health Organization, this event rallies global leaders on the urgent need to expand midwifery services. EDT\nUN Headquarters, Conference Room 8\nThis event brings together experts, policymakers and advocates to discuss health, demographic shifts and well-being across all ages. EDT\nUN Headquarters, Conference Room 4\nThis event will address the importance of investing in health systems’ preparedness to respond to the health needs of women and girls affected by humanitarian crises. EDT\nUN Secretariat, Conference Room 12\nOrganized by UNFPA, the Governments of Colombia, Colombia  the Dominican Republic and Ecuador, and together with Harvard Medical School, this event will emphasize the role of demographic insights in advancing health equity, strengthening health systems and ensuring universal access to care. EDT\nUN Secretariat, Conference Room 12\nAt this event, co-sponsored by the Governments of Finland and Mexico, UNFPA and partners will discuss reproductive health, explore strategic partnerships, highlight best practices and discuss the potential of an integrated approach to support bridging the gap in maternal health outcomes – and to ensure that we leave no one behind. The session, which begins on World Health Day on 7 April, will feature a number of side events hosted by UNFPA and partners, including the launch of the Global Action Plan for Midwifery – a bold call to action designed to rally the maternal health community and drive political commitment to strengthen midwifery models of care. EDT\nUN Headquarters, Conference Room 4\nHosted by UNFPA and partners including the Governments of Denmark, Germany, Luxembourg, Mexico, Sierra Leone, Sweden, and the United Kingdom, as well as the International Confederation of Midwives, UNICEF and the World Health Organization, this event rallies global leaders on the urgent need to expand midwifery services. EDT\nUN Headquarters, Conference Room 8\nThis event brings together experts, policymakers and advocates to discuss health, demographic shifts and well-being across all ages. EDT\nUN Headquarters, Conference Room 4\nThis event will address the importance of investing in health systems’ preparedness to respond to the health needs of women and girls affected by humanitarian crises. EDT\nUN Secretariat, Conference Room 12\nOrganized by UNFPA, the Governments of Colombia, Colombia  the Dominican Republic and Ecuador, and together with Harvard Medical School, this event will emphasize the role of demographic insights in advancing health equity, strengthening health systems and ensuring universal access to care. EDT\nUN Secretariat, Conference Room 12\nAt this event, co-sponsored by the Governments of Finland and Mexico, UNFPA and partners will discuss reproductive health, explore strategic partnerships, highlight best practices and discuss the potential of an integrated approach to support bridging the gap in maternal health outcomes – and to ensure that we leave no one behind. The session, which begins on World Health Day on 7 April, will feature a number of side events hosted by UNFPA and partners, including the launch of the Global Action Plan for Midwifery – a bold call to action designed to rally the maternal health community and drive political commitment to strengthen midwifery models of care. EDT\nUN Headquarters, Conference Room 4\nHosted by UNFPA and partners including the Governments of Denmark, Germany, Luxembourg, Mexico, Sierra Leone, Sweden, and the United Kingdom, as well as the International Confederation of Midwives, UNICEF and the World Health Organization, this event rallies global leaders on the urgent need to expand midwifery services. EDT\nUN Headquarters, Conference Room 8\nThis event brings together experts, policymakers and advocates to discuss health, demographic shifts and well-being across all ages. EDT\nUN Headquarters, Conference Room 4\nThis event will address the importance of investing in health systems’ preparedness to respond to the health needs of women and girls affected by humanitarian crises. EDT\nUN Secretariat, Conference Room 12\nOrganized by UNFPA, the Governments of Colombia, Colombia  the Dominican Republic and Ecuador, and together with Harvard Medical School, this event will emphasize the role of demographic insights in advancing health equity, strengthening health systems and ensuring universal access to care. EDT\nUN Secretariat, Conference Room 12\nAt this event, co-sponsored by the Governments of Finland and Mexico, UNFPA and partners will discuss reproductive health, explore strategic partnerships, highlight best practices and discuss the potential of an integrated approach to support bridging the gap in maternal health outcomes – and to ensure that we leave no one behind. The session, which begins on World Health Day on 7 April, will feature a number of side events hosted by UNFPA and partners, including the launch of the Global Action Plan for Midwifery – a bold call to action designed to rally the maternal health community and drive political commitment to strengthen midwifery models of care. EDT\nUN Headquarters, Conference Room 4\nHosted by UNFPA and partners including the Governments of Denmark, Germany, Luxembourg, Mexico, Sierra Leone, Sweden, and the United Kingdom, as well as the International Confederation of Midwives, UNICEF and the World Health Organization, this event rallies global leaders on the urgent need to expand midwifery services. EDT\nUN Headquarters, Conference Room 8\nThis event brings together experts, policymakers and advocates to discuss health, demographic shifts and well-being across all ages. EDT\nUN Headquarters, Conference Room 4\nThis event will address the importance of investing in health systems’ preparedness to respond to the health needs of women and girls affected by humanitarian crises. EDT\nUN Secretariat, Conference Room 12\nOrganized by UNFPA, the Governments of Colombia, Colombia  the Dominican Republic and Ecuador, and together with Harvard Medical School, this event will emphasize the role of demographic insights in advancing health equity, strengthening health systems and ensuring universal access to care. EDT\nUN Secretariat, Conference Room 12\nAt this event, co-sponsored by the Governments of Finland and Mexico, UNFPA and partners will discuss reproductive health, explore strategic partnerships, highlight best practices and discuss the potential of an integrated approach to support bridging the gap in maternal health outcomes – and to ensure that we leave no one behind. The session, which begins on World Health Day on 7 April, will feature a number of side events hosted by UNFPA and partners, including the launch of the Global Action Plan for Midwifery – a bold call to action designed to rally the maternal health community and drive political commitment to strengthen midwifery models of care. EDT\nUN Headquarters, Conference Room 4\nHosted by UNFPA and partners including the Governments of Denmark, Germany, Luxembourg, Mexico, Sierra Leone, Sweden, and the United Kingdom, as well as the International Confederation of Midwives, UNICEF and the World Health Organization, this event rallies global leaders on the urgent need to expand midwifery services. EDT\nUN Headquarters, Conference Room 8\nThis event brings together experts, policymakers and advocates to discuss health, demographic shifts and well-being across all ages. EDT\nUN Headquarters, Conference Room 4\nThis event will address the importance of investing in health systems’ preparedness to respond to the health needs of women and girls affected by humanitarian crises. EDT\nUN Secretariat, Conference Room 12\nOrganized by UNFPA, the Governments of Colombia, Colombia  the Dominican Republic and Ecuador, and together with Harvard Medical School, this event will emphasize the role of demographic insights in advancing health equity, strengthening health systems and ensuring universal access to care. EDT\nUN Secretariat, Conference Room 12\nAt this event, co-sponsored by the Governments of Finland and Mexico, UNFPA and partners will discuss reproductive health, explore strategic partnerships, highlight best practices and discuss the potential of an integrated approach to support bridging the gap in maternal health outcomes – and to ensure that we leave no one behind. The session, which begins on World Health Day on 7 April, will feature a number of side events hosted by UNFPA and partners, including the launch of the Global Action Plan for Midwifery – a bold call to action designed to rally the maternal health community and drive political commitment to strengthen midwifery models of care. EDT\nUN Headquarters, Conference Room 4\nHosted by UNFPA and partners including the Governments of Denmark, Germany, Luxembourg, Mexico, Sierra Leone, Sweden, and the United Kingdom, as well as the International Confederation of Midwives, UNICEF and the World Health Organization, this event rallies global leaders on the urgent need to expand midwifery services. EDT\nUN Headquarters, Conference Room 8\nThis event brings together experts, policymakers and advocates to discuss health, demographic shifts and well-being across all ages. EDT\nUN Headquarters, Conference Room 4\nThis event will address the importance of investing in health systems’ preparedness to respond to the health needs of women and girls affected by humanitarian crises. EDT\nUN Secretariat, Conference Room 12\nOrganized by UNFPA, the Governments of Colombia, Colombia  the Dominican Republic and Ecuador, and together with Harvard Medical School, this event will emphasize the role of demographic insights in advancing health equity, strengthening health systems and ensuring universal access to care. EDT\nUN Secretariat, Conference Room 12\nAt this event, co-sponsored by the Governments of Finland and Mexico, UNFPA and partners will discuss reproductive health, explore strategic partnerships, highlight best practices and discuss the potential of an integrated approach to support bridging the gap in maternal health outcomes – and to ensure that we leave no one behind. The session, which begins on World Health Day on 7 April, will feature a number of side events hosted by UNFPA and partners, including the launch of the Global Action Plan for Midwifery – a bold call to action designed to rally the maternal health community and drive political commitment to strengthen midwifery models of care. EDT\n\nUN Headquarters, Conference Room 4\n\nHosted by UNFPA and partners including the Governments of Denmark, Germany, Luxembourg, Mexico, Sierra Leone, Sweden, and the United Kingdom, as well as the International Confederation of Midwives, UNICEF and the World Health Organization, this event rallies global leaders on the urgent need to expand midwifery services. EDT\n\nUN Headquarters, Conference Room 8\n\nThis event brings together experts, policymakers and advocates to discuss health, demographic shifts and well-being across all ages. EDT\n\nUN Headquarters, Conference Room 4\n\nThis event will address the importance of investing in health systems’ preparedness to respond to the health needs of women and girls affected by humanitarian crises. EDT\n\nUN Secretariat, Conference Room 12\n\nOrganized by UNFPA, the Governments of Colombia, Colombia  the Dominican Republic and Ecuador, and together with Harvard Medical School, this event will emphasize the role of demographic insights in advancing health equity, strengthening health systems and ensuring universal access to care. EDT\n\nUN Secretariat, Conference Room 12\n\nAt this event, co-sponsored by the Governments of Finland and Mexico, UNFPA and partners will discuss reproductive health, explore strategic partnerships, highlight best practices and discuss the potential of an integrated approach to support bridging the gap in maternal health outcomes – and to ensure that we leave no one behind. Related topics\n\n\n\n\nSexual & reproductive health\n\nRelated topics\n\n\n\n\nSexual & reproductive health\n\nRelated topics\n\n\n\n\nSexual & reproductive health\n\nRelated topics\n\n\n\n\nSexual & reproductive health\n\nRelated topics\n\n\n\n\nSexual & reproductive health\n\nSexual & reproductive health\n\nSexual & reproductive health\n\nSexual & reproductive health\n\nBack to page\n    \n\n\n\n\nEvents\n\n\n\n\n\n\nShare on Facebook\n\n\n\n\n\nShare on Twitter\n\nBack to page\n\nBack to page\n\nEvents\n\n\n\n\n\n\nShare on Facebook\n\n\n\n\n\nShare on Twitter\n\nEvents\n\nEvents\n\nShare on Facebook\n\n\n\n\n\nShare on Twitter\n\nShare on Facebook\n\nShare on Twitter\n\nRelated Content\n\n\n\n\n\n\n\n\n\n\nEvents\n\nIntergenerational Dialogue: Ensuring healthy lives – Bridging generations for…\n\nRead more\n\n\n\n\n\n\n\n\n\n\n\nSpeech\n\nOpening Remarks by UNFPA Executive Director Dr. Natalia Kanem at the Commission…\n\nRead more\n\n\n\n\n\n\n\n\n\n\n\n\n\n\n\nUpdates\n\nMaternal health champions at CPD: It’s time to act for mothers and newborns\n\nRead more\n\nRelated Content\n\n\n\n\n\n\n\n\n\n\nEvents\n\nIntergenerational Dialogue: Ensuring healthy lives – Bridging generations for…\n\nRead more\n\n\n\n\n\n\n\n\n\n\n\nSpeech\n\nOpening Remarks by UNFPA Executive Director Dr. Natalia Kanem at the Commission…\n\nRead more\n\n\n\n\n\n\n\n\n\n\n\n\n\n\n\nUpdates\n\nMaternal health champions at CPD: It’s time to act for mothers and newborns\n\nRead more\n\nRelated Content\n\n\n\n\n\n\n\n\n\n\nEvents\n\nIntergenerational Dialogue: Ensuring healthy lives – Bridging generations for…\n\nRead more\n\n\n\n\n\n\n\n\n\n\n\nSpeech\n\nOpening Remarks by UNFPA Executive Director Dr. Natalia Kanem at the Commission…\n\nRead more\n\n\n\n\n\n\n\n\n\n\n\n\n\n\n\nUpdates\n\nMaternal health champions at CPD: It’s time to act for mothers and newborns\n\nRead more\n\nRelated Content\n\n\n\n\n\n\n\n\n\n\nEvents\n\nIntergenerational Dialogue: Ensuring healthy lives – Bridging generations for…\n\nRead more\n\n\n\n\n\n\n\n\n\n\n\nSpeech\n\nOpening Remarks by UNFPA Executive Director Dr. Natalia Kanem at the Commission…\n\nRead more\n\n\n\n\n\n\n\n\n\n\n\n\n\n\n\nUpdates\n\nMaternal health champions at CPD: It’s time to act for mothers and newborns\n\nRead more\n\nRelated Content\n\n\n\n\n\n\n\n\n\n\nEvents\n\nIntergenerational Dialogue: Ensuring healthy lives – Bridging generations for…\n\nRead more\n\n\n\n\n\n\n\n\n\n\n\nSpeech\n\nOpening Remarks by UNFPA Executive Director Dr. Natalia Kanem at the Commission…\n\nRead more\n\n\n\n\n\n\n\n\n\n\n\n\n\n\n\nUpdates\n\nMaternal health champions at CPD: It’s time to act for mothers and newborns\n\nRead more\n\nRelated Content\n\n\n\n\n\n\n\n\n\n\nEvents\n\nIntergenerational Dialogue: Ensuring healthy lives – Bridging generations for…\n\nRead more\n\n\n\n\n\n\n\n\n\n\n\nSpeech\n\nOpening Remarks by UNFPA Executive Director Dr. Natalia Kanem at the Commission…\n\nRead more\n\n\n\n\n\n\n\n\n\n\n\n\n\n\n\nUpdates\n\nMaternal health champions at CPD: It’s time to act for mothers and newborns\n\nRead more\n\nRelated Content\n\n\n\n\n\n\n\n\n\n\nEvents\n\nIntergenerational Dialogue: Ensuring healthy lives – Bridging generations for…\n\nRead more\n\n\n\n\n\n\n\n\n\n\n\nSpeech\n\nOpening Remarks by UNFPA Executive Director Dr. Natalia Kanem at the Commission…\n\nRead more\n\n\n\n\n\n\n\n\n\n\n\n\n\n\n\nUpdates\n\nMaternal health champions at CPD: It’s time to act for mothers and newborns\n\nRead more\n\nRelated Content\n\n\n\n\n\n\n\n\n\n\nEvents\n\nIntergenerational Dialogue: Ensuring healthy lives – Bridging generations for…\n\nRead more\n\n\n\n\n\n\n\n\n\n\n\nSpeech\n\nOpening Remarks by UNFPA Executive Director Dr. Natalia Kanem at the Commission…\n\nRead more\n\n\n\n\n\n\n\n\n\n\n\n\n\n\n\nUpdates\n\nMaternal health champions at CPD: It’s time to act for mothers and newborns\n\nRead more\n\nEvents\n\nIntergenerational Dialogue: Ensuring healthy lives – Bridging generations for…\n\nRead more\n\n\n\n\n\n\n\n\n\n\n\nSpeech\n\nOpening Remarks by UNFPA Executive Director Dr. Natalia Kanem at the Commission…\n\nRead more\n\n\n\n\n\n\n\n\n\n\n\n\n\n\n\nUpdates\n\nMaternal health champions at CPD: It’s time to act for mothers and newborns\n\nRead more\n\nEvents\n\nIntergenerational Dialogue: Ensuring healthy lives – Bridging generations for…\n\nRead more\n\n\n\n\n\n\n\n\n\n\n\nSpeech\n\nOpening Remarks by UNFPA Executive Director Dr. Natalia Kanem at the Commission…\n\nRead more\n\n\n\n\n\n\n\n\n\n\n\n\n\n\n\nUpdates\n\nMaternal health champions at CPD: It’s time to act for mothers and newborns\n\nRead more\n\nEvents\n\nIntergenerational Dialogue: Ensuring healthy lives – Bridging generations for…\n\nRead more\n\nEvents\n\nIntergenerational Dialogue: Ensuring healthy lives – Bridging generations for…\n\nRead more\n\nEvents\n\nIntergenerational Dialogue: Ensuring healthy lives – Bridging generations for…\n\nRead more\n\nEvents\n\nSpeech\n\nOpening Remarks by UNFPA Executive Director Dr. Natalia Kanem at the Commission…\n\nRead more\n\nSpeech\n\nUpdates\n\nMaternal health champions at CPD: It’s time to act for mothers and newborns\n\nRead more\n\nUpdates\n\nMaternal health champions at CPD: It’s time to act for mothers and newborns\n\nRead more\n\nUpdates\n\nMaternal health champions at CPD: It’s time to act for mothers and newborns\n\nRead more\n\nUpdates\n\nWe use cookies and other identifiers to help improve your online experience.",
  "entities": {
    "countries": [
      "germany",
      "india",
      "japan",
      "mexico",
      "united kingdom"
    ],
    "organizations": [
      "united nations",
      "un",
      "unicef"
    ],
    "key_issues": [
      "issue",
      "crisis",
      "nation",
      "state",
      "government",
      "solution",
      "approach",
      "strategy",
      "policy",
      "program",
      "action",
      "development",
      "humanitarian",
      "economic",
      "investment",
      "united nations",
      "un",
      "organization"
    ]
  },
  "committee": "Economic and Social Council",
  "topic": "Addressing social inclusion of the elderly"
}