{
  "url": "https://www.helpage.org/global-network/",
  "title": "Global network - HelpAge International",
  "text": "Search\n\nSearch\n\nSearch\n\nGlobal network\n\n\n\n\n\nShare \n\n\n\n (opens in a new window)\n\n\n\n\n\n (opens in a new window)\n\n\n\n\n\n (opens in a new window)\n\n\n\n\n\n (opens in a new window)\n\n\n\n\n\n Copy\n\n\n\n\n\n\n\n\n\n\n\nAGE Myanmar\n\nWebsite\nLinkedIn\n\n\nKing Hussain Foundation / Institute for Family Health (KHF/iFH)\n\nWebsite\n\n\nAgeing with a Smile Initiative\n\nFacebook\n\n\nSIDOM Foundation\n\nWebsite\n\n\nFederal University of Santa Catarina (UFSC)\n\nWebsite\nFacebook\n\n\nSurcos AC\n\nWebsite\nFacebook\n\n\nServicio Social de Iglesias Dominicanas (SSID)\n\nWebsite\nFacebook\n\n\nSociedad Argentina de Gerontología y Geriatría (SAGG)\n\nWebsite\nFacebook\n\n\nSt. Catherine Community Development Agency (SACDA)\n\nWebsite\nFacebook\n\n\nAsociación Red Colombiana de Envejecimiento Activo y Digno (REDCOENVE)\n\nWebsite\nFacebook\n\n\nRAFAM Argentina Foundation\n\nWebsite\nFacebook\n\n\nPro Vida Perú\n\nFacebook\n\n\nONG Sumaj Punchay\n\nFacebook\n\n\nNTD Foundation\n\nWebsite\nFacebook\n\n\nMexican Alzheimer’s Center\n\nWebsite\nFacebook\n\n\nMesa de Trabajo sobre Personas Adultas Mayores\n\nFacebook\n\n\nCentro de Envejexcimiento Activo y Longevidad de la Universidad ISALUD\n\nWebsite\nFacebook\n\n\nFundación Horizontes\n\nFacebook\n\n\nHelpage St. Lucia National Council of and for older persons\n\n\n\nHelpAge Belize\n\nFacebook\n\n\nFundación Yamuni Tabush\n\nWebsite\nFacebook\n\n\nDominica Council on Ageing (DCOA)\n\nWebsite\nFacebook\n\n\nCORDES\n\nWebsite\n\n\nConvite A.C.\n\nWebsite\nFacebook\n\n\nConsejo Distrital de Sabios\n\n\n\nCADENA (Comité de Ayuda a Desastres y Emergencias Nacionales)\n\nWebsite\nFacebook\n\n\nAVU Innovación\n\nWebsite\nFacebook\n\n\nAsociacion Uruguaya de Animadores y Auxiliares Gerontologicos (AUDAAG)\n\nFacebook\n\n\nAsociación Central de Funcionarios Públicos y Docentes Jubilados del Paraguay\n\nFacebook\n\n\nAsociación Mutual de Protección Familiar (AMPF)\n\nWebsite\nFacebook\n\n\nAsociación Mutual Israelita Argentina (AMIA)\n\nWebsite\nFacebook\n\n\nAsociación Alianza de Salvadoreños Retornados (ALSARE)\n\nFacebook\n\n\nAsociación Gerontológica Costarricense (AGECO)\n\nWebsite\nFacebook\n\n\nFundación Acción Familiar Alzheimer Colombia (AFACOL)\n\nWebsite\nFacebook\n\n\nAsociacion Cultural Casa Del Nino (ACCN)\n\nWebsite\nFacebook\n\n\nThe Union for Senior Services – VALLI\n\nWebsite\n\n\nPRO Global / Pensioners without Borders\n\nWebsite\nFacebook\n\n\nKwa Wazee\n\nWebsite\n\n\nHelpAge USA\n\nWebsite\nFacebook\n\n\nHelpAge España\n\nWebsite\nFacebook\n\n\nHelpAge Canada\n\nWebsite\nFacebook\n\n\nGlobale Seniorer\n\nWebsite\nFacebook\n\n\nDorcas Aid International\n\nWebsite\nFacebook\n\n\nCaritas Malta Foundation\n\nWebsite\nFacebook\n\n\nBeauty of Help Foundation\n\nWebsite\nFacebook\n\n\nAge International\n\nWebsite\nFacebook\n\n\nAge Action Ireland\n\nWebsite\nFacebook\n\n\nAARP\n\nWebsite\nFacebook\n\n\nYemen Family Care Association (YFCA)\n\nWebsite\nFacebook\n\n\nEl Wedad Society for Community Rehabilitation (WSCR)\n\nWebsite\nFacebook\n\n\nAUB University for Seniors\n\nWebsite\nFacebook\n\n\nTurbota pro Litnix v Ukraini (TLU)\n\nWebsite\nFacebook\n\n\nCharity Foundation Starenki\n\nWebsite\nFacebook\n\n\nSolidarity Is Global Institute (SIGI)\n\nWebsite\nFacebook\n\n\nSyrian Expatriates Medical Association (SEMA)\n\nWebsite\nFacebook\n\n\nRight to Protection\n\nWebsite\nFacebook\n\n\nRed Cross of Serbia (RCS)\n\nWebsite\nFacebook\n\n\nResource Center for Elderly (RCE)\n\nWebsite\nFacebook\n\n\nPalestinian Center For Communication and Development Strategies (PCCDS)\n\nWebsite\nFacebook\n\n\nMission Armenia\n\nWebsite\nFacebook\n\n\nLife Makers Meeting Place Organisation (LMMPO)\n\nWebsite\nFacebook\n\n\nJuzoor for Health and Social Development\n\nWebsite\nFacebook\n\n\nJiyan Foundation for Human Rights\n\nWebsite\nFacebook\n\n\nHope Revival Organization (HRO)\n\nWebsite\nFacebook\n\n\nBabushka Adoption\n\nWebsite\nFacebook\n\n\nArdager\n\n\n\nAmel Association International (Amel)\n\nWebsite\nFacebook\n\n\nAlzheimer’s Association Lebanon (AAL)\n\nWebsite\nFacebook\n\n\nAlbanian Association of Geriatry and Gerontology (AAGG)\n\nWebsite\n\n\nYoung Power in Social Action (YPSA)\n\nWebsite\nFacebook\n\n\nYayasan Emong Lansia (YEL)\n\n\n\nVietnam Elderly Association\n\nWebsite\n\n\nSenior Citizen Chautari (SCC)\n\nWebsite\nFacebook\n\n\nResource Integration center RIC\n\nWebsite\nFacebook\n\n\nNepal Participatory Action Network (NEPAN)\n\nWebsite\nFacebook\n\n\nNational Senior Citizen Federation (NASCIF)\n\nWebsite\n\n\nNational Council of Senior Citizens Organisations Malaysia (NACSCOM)\n\nWebsite\nFacebook\n\n\nHelpAge Sri Lanka\n\nWebsite\nLinkedIn\n\n\nHelpAge Korea\n\nWebsite\nFacebook\n\n\nHelpAge India\n\nWebsite\nFacebook\n\n\nHelpAge Cambodia\n\nWebsite\nFacebook\n\n\nGramin Vikas Vigyan Samiti (GRAVIS)\n\nWebsite\nFacebook\n\n\nforOldy Project, Help without Frontiers Thailand Foundation (HWFT)\n\nWebsite\nFacebook\n\n\nFoundation for Older Persons’ Development (FOPDEV)\n\nWebsite\nFacebook\n\n\nCoalition of Services of the Elderly (COSE)\n\nWebsite\nFacebook\n\n\nChina National Committee on Ageing (CNCA)\n\nWebsite\n\n\nCentre for Human Rights and Development (CHRD)\n\nWebsite\n\n\nBangladesh Women’s Health Coalition (BWHC)\n\nWebsite\n\n\nAgeing Nepal\n\nWebsite\nX\n\n\nUnivers de solidarité et de développement (UNI.SOL.D.)\n\n\n\nRegional Center for the Welfare of Aging Persons in Cameroon (RECEWAPEC)\n\nWebsite\n\n\nGrandmothers Consortium (GMC)\n\nWebsite\n\n\nVUKOXA – Associacao Humanitaria de Apoio a Velhice\n\n\n\nVoice of the Elderly\n\n\n\nUganda Reach the Aged Association (URAA)\n\nWebsite\n\n\nTesfa Social and Development Association\n\nWebsite\n\n\nTanzania Mission to the Poor and Disabled (PADI)\n\nWebsite\n\n\nSupport To Older People-Zambia (STOP-Zambia)\n\nWebsite\n\n\nSenior Citizens Association of Zambia (SCAZ)\n\nWebsite\n\n\nSaidia Wazee Karagwe (SAWAKA)\n\nWebsite\n\n\nReach One Touch One Ministries (ROTOM)\n\nWebsite\n\n\nRelief to Development Society (REDESO)\n\nWebsite\n\n\nReach A Hand Uganda (RAHU)\n\nWebsite\n\n\nPalliative Care Association of Uganda (PCAU)\n\nWebsite\n\n\nNSINDAGIZA Organization\n\nWebsite\n\n\nMuthande\n\nWebsite\n\n\nMangu Integrated Community Project (MICOP Kenya)\n\nFacebook\n\n\nMauritius Family Planning and Welfare Association (MFPWA)\n\nWebsite\n\n\nMalawi Network of Older Persons’ Organisations (MANEPO)\n\nWebsite\n\n\nKulmiye Pastoral Association (DPA)\n\nWebsite\n\n\nKibera Day Care Centre for the Elderly (KDCCE)\n\nWebsite\n\n\nKenya Society for People with AIDS (KESPA)\n\n\n\nKenyan Aged People Require Information, Knowledge & Advancement (KARIKA)\n\nWebsite\n\n\nHorn International Relief & Development Organization (HIRDO)\n\nWebsite\n\n\nHelpAge Kenya (H.A.K.)\n\nFacebook\n\n\nHealth Nest Uganda (HENU)\n\nFacebook\n\n\nHumanitarian and Development Consortium (HDC)\n\nWebsite\n\n\nFantsuam Foundation\n\nWebsite\n\n\nDroits Humains Ocean Indien (Dis-Moi)\n\nWebsite\n\n\nCoalition of Societies for the Rights of Older Persons in Nigeria (COSROPIN)\n\nWebsite\n\n\nCommunity Based Rehabilitation Alliance (COMBRA)\n\nWebsite\n\n\nCenter for Community Advancement and Family Empowerment (CECAFE)\n\n\n\nAcção para o Desenvolvimento Comunitarios or Association for Community Development Action in Sofala (ASADEC)\n\n\n\nAlmanar Voluntary Organization (AMVO)\n\nWebsite\nFacebook\n\n\nAfrica Development Aid (ADA)\n\nWebsite\n\n\nAgeing Concern Foundation (ACF)\n\nWebsite\n\n\nACAMAGE\n\nFacebook\n\n\n\n\n\n\n\n\n\n\n\n\n\n\n\n\n\n\n\n\n\n\n\n\n\n\n\n\n\n\n\n\n\n\n\n\n\n\n\n\n\n\n\n\n\n\n\n\n\n\n\n\n\n\n\n\n\n\n\n\n\n\n\n\n\n\n\n\n\n\n\n\n\n\n\n\n\n\n\n\n\n\n\n\n\n\n\n\n\n\nJoin the HelpAge global network\n\nBe part of a global movement changing the world for older people\n\nJoin us\n\nGlobal network\n\nGlobal network\n\nShare \n\n\n\n (opens in a new window)\n\n\n\n\n\n (opens in a new window)\n\n\n\n\n\n (opens in a new window)\n\n\n\n\n\n (opens in a new window)\n\n\n\n\n\n Copy\n\nAGE Myanmar\n\nWebsite\nLinkedIn\n\n\nKing Hussain Foundation / Institute for Family Health (KHF/iFH)\n\nWebsite\n\n\nAgeing with a Smile Initiative\n\nFacebook\n\n\nSIDOM Foundation\n\nWebsite\n\n\nFederal University of Santa Catarina (UFSC)\n\nWebsite\nFacebook\n\n\nSurcos AC\n\nWebsite\nFacebook\n\n\nServicio Social de Iglesias Dominicanas (SSID)\n\nWebsite\nFacebook\n\n\nSociedad Argentina de Gerontología y Geriatría (SAGG)\n\nWebsite\nFacebook\n\n\nSt. Catherine Community Development Agency (SACDA)\n\nWebsite\nFacebook\n\n\nAsociación Red Colombiana de Envejecimiento Activo y Digno (REDCOENVE)\n\nWebsite\nFacebook\n\n\nRAFAM Argentina Foundation\n\nWebsite\nFacebook\n\n\nPro Vida Perú\n\nFacebook\n\n\nONG Sumaj Punchay\n\nFacebook\n\n\nNTD Foundation\n\nWebsite\nFacebook\n\n\nMexican Alzheimer’s Center\n\nWebsite\nFacebook\n\n\nMesa de Trabajo sobre Personas Adultas Mayores\n\nFacebook\n\n\nCentro de Envejexcimiento Activo y Longevidad de la Universidad ISALUD\n\nWebsite\nFacebook\n\n\nFundación Horizontes\n\nFacebook\n\n\nHelpage St. Lucia National Council of and for older persons\n\n\n\nHelpAge Belize\n\nFacebook\n\n\nFundación Yamuni Tabush\n\nWebsite\nFacebook\n\n\nDominica Council on Ageing (DCOA)\n\nWebsite\nFacebook\n\n\nCORDES\n\nWebsite\n\n\nConvite A.C.\n\nWebsite\nFacebook\n\n\nConsejo Distrital de Sabios\n\n\n\nCADENA (Comité de Ayuda a Desastres y Emergencias Nacionales)\n\nWebsite\nFacebook\n\n\nAVU Innovación\n\nWebsite\nFacebook\n\n\nAsociacion Uruguaya de Animadores y Auxiliares Gerontologicos (AUDAAG)\n\nFacebook\n\n\nAsociación Central de Funcionarios Públicos y Docentes Jubilados del Paraguay\n\nFacebook\n\n\nAsociación Mutual de Protección Familiar (AMPF)\n\nWebsite\nFacebook\n\n\nAsociación Mutual Israelita Argentina (AMIA)\n\nWebsite\nFacebook\n\n\nAsociación Alianza de Salvadoreños Retornados (ALSARE)\n\nFacebook\n\n\nAsociación Gerontológica Costarricense (AGECO)\n\nWebsite\nFacebook\n\n\nFundación Acción Familiar Alzheimer Colombia (AFACOL)\n\nWebsite\nFacebook\n\n\nAsociacion Cultural Casa Del Nino (ACCN)\n\nWebsite\nFacebook\n\n\nThe Union for Senior Services – VALLI\n\nWebsite\n\n\nPRO Global / Pensioners without Borders\n\nWebsite\nFacebook\n\n\nKwa Wazee\n\nWebsite\n\n\nHelpAge USA\n\nWebsite\nFacebook\n\n\nHelpAge España\n\nWebsite\nFacebook\n\n\nHelpAge Canada\n\nWebsite\nFacebook\n\n\nGlobale Seniorer\n\nWebsite\nFacebook\n\n\nDorcas Aid International\n\nWebsite\nFacebook\n\n\nCaritas Malta Foundation\n\nWebsite\nFacebook\n\n\nBeauty of Help Foundation\n\nWebsite\nFacebook\n\n\nAge International\n\nWebsite\nFacebook\n\n\nAge Action Ireland\n\nWebsite\nFacebook\n\n\nAARP\n\nWebsite\nFacebook\n\n\nYemen Family Care Association (YFCA)\n\nWebsite\nFacebook\n\n\nEl Wedad Society for Community Rehabilitation (WSCR)\n\nWebsite\nFacebook\n\n\nAUB University for Seniors\n\nWebsite\nFacebook\n\n\nTurbota pro Litnix v Ukraini (TLU)\n\nWebsite\nFacebook\n\n\nCharity Foundation Starenki\n\nWebsite\nFacebook\n\n\nSolidarity Is Global Institute (SIGI)\n\nWebsite\nFacebook\n\n\nSyrian Expatriates Medical Association (SEMA)\n\nWebsite\nFacebook\n\n\nRight to Protection\n\nWebsite\nFacebook\n\n\nRed Cross of Serbia (RCS)\n\nWebsite\nFacebook\n\n\nResource Center for Elderly (RCE)\n\nWebsite\nFacebook\n\n\nPalestinian Center For Communication and Development Strategies (PCCDS)\n\nWebsite\nFacebook\n\n\nMission Armenia\n\nWebsite\nFacebook\n\n\nLife Makers Meeting Place Organisation (LMMPO)\n\nWebsite\nFacebook\n\n\nJuzoor for Health and Social Development\n\nWebsite\nFacebook\n\n\nJiyan Foundation for Human Rights\n\nWebsite\nFacebook\n\n\nHope Revival Organization (HRO)\n\nWebsite\nFacebook\n\n\nBabushka Adoption\n\nWebsite\nFacebook\n\n\nArdager\n\n\n\nAmel Association International (Amel)\n\nWebsite\nFacebook\n\n\nAlzheimer’s Association Lebanon (AAL)\n\nWebsite\nFacebook\n\n\nAlbanian Association of Geriatry and Gerontology (AAGG)\n\nWebsite\n\n\nYoung Power in Social Action (YPSA)\n\nWebsite\nFacebook\n\n\nYayasan Emong Lansia (YEL)\n\n\n\nVietnam Elderly Association\n\nWebsite\n\n\nSenior Citizen Chautari (SCC)\n\nWebsite\nFacebook\n\n\nResource Integration center RIC\n\nWebsite\nFacebook\n\n\nNepal Participatory Action Network (NEPAN)\n\nWebsite\nFacebook\n\n\nNational Senior Citizen Federation (NASCIF)\n\nWebsite\n\n\nNational Council of Senior Citizens Organisations Malaysia (NACSCOM)\n\nWebsite\nFacebook\n\n\nHelpAge Sri Lanka\n\nWebsite\nLinkedIn\n\n\nHelpAge Korea\n\nWebsite\nFacebook\n\n\nHelpAge India\n\nWebsite\nFacebook\n\n\nHelpAge Cambodia\n\nWebsite\nFacebook\n\n\nGramin Vikas Vigyan Samiti (GRAVIS)\n\nWebsite\nFacebook\n\n\nforOldy Project, Help without Frontiers Thailand Foundation (HWFT)\n\nWebsite\nFacebook\n\n\nFoundation for Older Persons’ Development (FOPDEV)\n\nWebsite\nFacebook\n\n\nCoalition of Services of the Elderly (COSE)\n\nWebsite\nFacebook\n\n\nChina National Committee on Ageing (CNCA)\n\nWebsite\n\n\nCentre for Human Rights and Development (CHRD)\n\nWebsite\n\n\nBangladesh Women’s Health Coalition (BWHC)\n\nWebsite\n\n\nAgeing Nepal\n\nWebsite\nX\n\n\nUnivers de solidarité et de développement (UNI.SOL.D.)\n\n\n\nRegional Center for the Welfare of Aging Persons in Cameroon (RECEWAPEC)\n\nWebsite\n\n\nGrandmothers Consortium (GMC)\n\nWebsite\n\n\nVUKOXA – Associacao Humanitaria de Apoio a Velhice\n\n\n\nVoice of the Elderly\n\n\n\nUganda Reach the Aged Association (URAA)\n\nWebsite\n\n\nTesfa Social and Development Association\n\nWebsite\n\n\nTanzania Mission to the Poor and Disabled (PADI)\n\nWebsite\n\n\nSupport To Older People-Zambia (STOP-Zambia)\n\nWebsite\n\n\nSenior Citizens Association of Zambia (SCAZ)\n\nWebsite\n\n\nSaidia Wazee Karagwe (SAWAKA)\n\nWebsite\n\n\nReach One Touch One Ministries (ROTOM)\n\nWebsite\n\n\nRelief to Development Society (REDESO)\n\nWebsite\n\n\nReach A Hand Uganda (RAHU)\n\nWebsite\n\n\nPalliative Care Association of Uganda (PCAU)\n\nWebsite\n\n\nNSINDAGIZA Organization\n\nWebsite\n\n\nMuthande\n\nWebsite\n\n\nMangu Integrated Community Project (MICOP Kenya)\n\nFacebook\n\n\nMauritius Family Planning and Welfare Association (MFPWA)\n\nWebsite\n\n\nMalawi Network of Older Persons’ Organisations (MANEPO)\n\nWebsite\n\n\nKulmiye Pastoral Association (DPA)\n\nWebsite\n\n\nKibera Day Care Centre for the Elderly (KDCCE)\n\nWebsite\n\n\nKenya Society for People with AIDS (KESPA)\n\n\n\nKenyan Aged People Require Information, Knowledge & Advancement (KARIKA)\n\nWebsite\n\n\nHorn International Relief & Development Organization (HIRDO)\n\nWebsite\n\n\nHelpAge Kenya (H.A.K.)\n\nFacebook\n\n\nHealth Nest Uganda (HENU)\n\nFacebook\n\n\nHumanitarian and Development Consortium (HDC)\n\nWebsite\n\n\nFantsuam Foundation\n\nWebsite\n\n\nDroits Humains Ocean Indien (Dis-Moi)\n\nWebsite\n\n\nCoalition of Societies for the Rights of Older Persons in Nigeria (COSROPIN)\n\nWebsite\n\n\nCommunity Based Rehabilitation Alliance (COMBRA)\n\nWebsite\n\n\nCenter for Community Advancement and Family Empowerment (CECAFE)\n\n\n\nAcção para o Desenvolvimento Comunitarios or Association for Community Development Action in Sofala (ASADEC)\n\n\n\nAlmanar Voluntary Organization (AMVO)\n\nWebsite\nFacebook\n\n\nAfrica Development Aid (ADA)\n\nWebsite\n\n\nAgeing Concern Foundation (ACF)\n\nWebsite\n\n\nACAMAGE\n\nFacebook\n\nAGE Myanmar\n\nWebsite\nLinkedIn\n\n\nKing Hussain Foundation / Institute for Family Health (KHF/iFH)\n\nWebsite\n\n\nAgeing with a Smile Initiative\n\nFacebook\n\n\nSIDOM Foundation\n\nWebsite\n\n\nFederal University of Santa Catarina (UFSC)\n\nWebsite\nFacebook\n\n\nSurcos AC\n\nWebsite\nFacebook\n\n\nServicio Social de Iglesias Dominicanas (SSID)\n\nWebsite\nFacebook\n\n\nSociedad Argentina de Gerontología y Geriatría (SAGG)\n\nWebsite\nFacebook\n\n\nSt. Catherine Community Development Agency (SACDA)\n\nWebsite\nFacebook\n\n\nAsociación Red Colombiana de Envejecimiento Activo y Digno (REDCOENVE)\n\nWebsite\nFacebook\n\n\nRAFAM Argentina Foundation\n\nWebsite\nFacebook\n\n\nPro Vida Perú\n\nFacebook\n\n\nONG Sumaj Punchay\n\nFacebook\n\n\nNTD Foundation\n\nWebsite\nFacebook\n\n\nMexican Alzheimer’s Center\n\nWebsite\nFacebook\n\n\nMesa de Trabajo sobre Personas Adultas Mayores\n\nFacebook\n\n\nCentro de Envejexcimiento Activo y Longevidad de la Universidad ISALUD\n\nWebsite\nFacebook\n\n\nFundación Horizontes\n\nFacebook\n\n\nHelpage St. Lucia National Council of and for older persons\n\n\n\nHelpAge Belize\n\nFacebook\n\n\nFundación Yamuni Tabush\n\nWebsite\nFacebook\n\n\nDominica Council on Ageing (DCOA)\n\nWebsite\nFacebook\n\n\nCORDES\n\nWebsite\n\n\nConvite A.C.\n\nWebsite\nFacebook\n\n\nConsejo Distrital de Sabios\n\n\n\nCADENA (Comité de Ayuda a Desastres y Emergencias Nacionales)\n\nWebsite\nFacebook\n\n\nAVU Innovación\n\nWebsite\nFacebook\n\n\nAsociacion Uruguaya de Animadores y Auxiliares Gerontologicos (AUDAAG)\n\nFacebook\n\n\nAsociación Central de Funcionarios Públicos y Docentes Jubilados del Paraguay\n\nFacebook\n\n\nAsociación Mutual de Protección Familiar (AMPF)\n\nWebsite\nFacebook\n\n\nAsociación Mutual Israelita Argentina (AMIA)\n\nWebsite\nFacebook\n\n\nAsociación Alianza de Salvadoreños Retornados (ALSARE)\n\nFacebook\n\n\nAsociación Gerontológica Costarricense (AGECO)\n\nWebsite\nFacebook\n\n\nFundación Acción Familiar Alzheimer Colombia (AFACOL)\n\nWebsite\nFacebook\n\n\nAsociacion Cultural Casa Del Nino (ACCN)\n\nWebsite\nFacebook\n\n\nThe Union for Senior Services – VALLI\n\nWebsite\n\n\nPRO Global / Pensioners without Borders\n\nWebsite\nFacebook\n\n\nKwa Wazee\n\nWebsite\n\n\nHelpAge USA\n\nWebsite\nFacebook\n\n\nHelpAge España\n\nWebsite\nFacebook\n\n\nHelpAge Canada\n\nWebsite\nFacebook\n\n\nGlobale Seniorer\n\nWebsite\nFacebook\n\n\nDorcas Aid International\n\nWebsite\nFacebook\n\n\nCaritas Malta Foundation\n\nWebsite\nFacebook\n\n\nBeauty of Help Foundation\n\nWebsite\nFacebook\n\n\nAge International\n\nWebsite\nFacebook\n\n\nAge Action Ireland\n\nWebsite\nFacebook\n\n\nAARP\n\nWebsite\nFacebook\n\n\nYemen Family Care Association (YFCA)\n\nWebsite\nFacebook\n\n\nEl Wedad Society for Community Rehabilitation (WSCR)\n\nWebsite\nFacebook\n\n\nAUB University for Seniors\n\nWebsite\nFacebook\n\n\nTurbota pro Litnix v Ukraini (TLU)\n\nWebsite\nFacebook\n\n\nCharity Foundation Starenki\n\nWebsite\nFacebook\n\n\nSolidarity Is Global Institute (SIGI)\n\nWebsite\nFacebook\n\n\nSyrian Expatriates Medical Association (SEMA)\n\nWebsite\nFacebook\n\n\nRight to Protection\n\nWebsite\nFacebook\n\n\nRed Cross of Serbia (RCS)\n\nWebsite\nFacebook\n\n\nResource Center for Elderly (RCE)\n\nWebsite\nFacebook\n\n\nPalestinian Center For Communication and Development Strategies (PCCDS)\n\nWebsite\nFacebook\n\n\nMission Armenia\n\nWebsite\nFacebook\n\n\nLife Makers Meeting Place Organisation (LMMPO)\n\nWebsite\nFacebook\n\n\nJuzoor for Health and Social Development\n\nWebsite\nFacebook\n\n\nJiyan Foundation for Human Rights\n\nWebsite\nFacebook\n\n\nHope Revival Organization (HRO)\n\nWebsite\nFacebook\n\n\nBabushka Adoption\n\nWebsite\nFacebook\n\n\nArdager\n\n\n\nAmel Association International (Amel)\n\nWebsite\nFacebook\n\n\nAlzheimer’s Association Lebanon (AAL)\n\nWebsite\nFacebook\n\n\nAlbanian Association of Geriatry and Gerontology (AAGG)\n\nWebsite\n\n\nYoung Power in Social Action (YPSA)\n\nWebsite\nFacebook\n\n\nYayasan Emong Lansia (YEL)\n\n\n\nVietnam Elderly Association\n\nWebsite\n\n\nSenior Citizen Chautari (SCC)\n\nWebsite\nFacebook\n\n\nResource Integration center RIC\n\nWebsite\nFacebook\n\n\nNepal Participatory Action Network (NEPAN)\n\nWebsite\nFacebook\n\n\nNational Senior Citizen Federation (NASCIF)\n\nWebsite\n\n\nNational Council of Senior Citizens Organisations Malaysia (NACSCOM)\n\nWebsite\nFacebook\n\n\nHelpAge Sri Lanka\n\nWebsite\nLinkedIn\n\n\nHelpAge Korea\n\nWebsite\nFacebook\n\n\nHelpAge India\n\nWebsite\nFacebook\n\n\nHelpAge Cambodia\n\nWebsite\nFacebook\n\n\nGramin Vikas Vigyan Samiti (GRAVIS)\n\nWebsite\nFacebook\n\n\nforOldy Project, Help without Frontiers Thailand Foundation (HWFT)\n\nWebsite\nFacebook\n\n\nFoundation for Older Persons’ Development (FOPDEV)\n\nWebsite\nFacebook\n\n\nCoalition of Services of the Elderly (COSE)\n\nWebsite\nFacebook\n\n\nChina National Committee on Ageing (CNCA)\n\nWebsite\n\n\nCentre for Human Rights and Development (CHRD)\n\nWebsite\n\n\nBangladesh Women’s Health Coalition (BWHC)\n\nWebsite\n\n\nAgeing Nepal\n\nWebsite\nX\n\n\nUnivers de solidarité et de développement (UNI.SOL.D.)\n\n\n\nRegional Center for the Welfare of Aging Persons in Cameroon (RECEWAPEC)\n\nWebsite\n\n\nGrandmothers Consortium (GMC)\n\nWebsite\n\n\nVUKOXA – Associacao Humanitaria de Apoio a Velhice\n\n\n\nVoice of the Elderly\n\n\n\nUganda Reach the Aged Association (URAA)\n\nWebsite\n\n\nTesfa Social and Development Association\n\nWebsite\n\n\nTanzania Mission to the Poor and Disabled (PADI)\n\nWebsite\n\n\nSupport To Older People-Zambia (STOP-Zambia)\n\nWebsite\n\n\nSenior Citizens Association of Zambia (SCAZ)\n\nWebsite\n\n\nSaidia Wazee Karagwe (SAWAKA)\n\nWebsite\n\n\nReach One Touch One Ministries (ROTOM)\n\nWebsite\n\n\nRelief to Development Society (REDESO)\n\nWebsite\n\n\nReach A Hand Uganda (RAHU)\n\nWebsite\n\n\nPalliative Care Association of Uganda (PCAU)\n\nWebsite\n\n\nNSINDAGIZA Organization\n\nWebsite\n\n\nMuthande\n\nWebsite\n\n\nMangu Integrated Community Project (MICOP Kenya)\n\nFacebook\n\n\nMauritius Family Planning and Welfare Association (MFPWA)\n\nWebsite\n\n\nMalawi Network of Older Persons’ Organisations (MANEPO)\n\nWebsite\n\n\nKulmiye Pastoral Association (DPA)\n\nWebsite\n\n\nKibera Day Care Centre for the Elderly (KDCCE)\n\nWebsite\n\n\nKenya Society for People with AIDS (KESPA)\n\n\n\nKenyan Aged People Require Information, Knowledge & Advancement (KARIKA)\n\nWebsite\n\n\nHorn International Relief & Development Organization (HIRDO)\n\nWebsite\n\n\nHelpAge Kenya (H.A.K.)\n\nFacebook\n\n\nHealth Nest Uganda (HENU)\n\nFacebook\n\n\nHumanitarian and Development Consortium (HDC)\n\nWebsite\n\n\nFantsuam Foundation\n\nWebsite\n\n\nDroits Humains Ocean Indien (Dis-Moi)\n\nWebsite\n\n\nCoalition of Societies for the Rights of Older Persons in Nigeria (COSROPIN)\n\nWebsite\n\n\nCommunity Based Rehabilitation Alliance (COMBRA)\n\nWebsite\n\n\nCenter for Community Advancement and Family Empowerment (CECAFE)\n\n\n\nAcção para o Desenvolvimento Comunitarios or Association for Community Development Action in Sofala (ASADEC)\n\n\n\nAlmanar Voluntary Organization (AMVO)\n\nWebsite\nFacebook\n\n\nAfrica Development Aid (ADA)\n\nWebsite\n\n\nAgeing Concern Foundation (ACF)\n\nWebsite\n\n\nACAMAGE\n\nFacebook\n\nAGE Myanmar\n\nWebsite\nLinkedIn\n\n\nKing Hussain Foundation / Institute for Family Health (KHF/iFH)\n\nWebsite\n\n\nAgeing with a Smile Initiative\n\nFacebook\n\n\nSIDOM Foundation\n\nWebsite\n\n\nFederal University of Santa Catarina (UFSC)\n\nWebsite\nFacebook\n\n\nSurcos AC\n\nWebsite\nFacebook\n\n\nServicio Social de Iglesias Dominicanas (SSID)\n\nWebsite\nFacebook\n\n\nSociedad Argentina de Gerontología y Geriatría (SAGG)\n\nWebsite\nFacebook\n\n\nSt. Catherine Community Development Agency (SACDA)\n\nWebsite\nFacebook\n\n\nAsociación Red Colombiana de Envejecimiento Activo y Digno (REDCOENVE)\n\nWebsite\nFacebook\n\n\nRAFAM Argentina Foundation\n\nWebsite\nFacebook\n\n\nPro Vida Perú\n\nFacebook\n\n\nONG Sumaj Punchay\n\nFacebook\n\n\nNTD Foundation\n\nWebsite\nFacebook\n\n\nMexican Alzheimer’s Center\n\nWebsite\nFacebook\n\n\nMesa de Trabajo sobre Personas Adultas Mayores\n\nFacebook\n\n\nCentro de Envejexcimiento Activo y Longevidad de la Universidad ISALUD\n\nWebsite\nFacebook\n\n\nFundación Horizontes\n\nFacebook\n\n\nHelpage St. Lucia National Council of and for older persons\n\n\n\nHelpAge Belize\n\nFacebook\n\n\nFundación Yamuni Tabush\n\nWebsite\nFacebook\n\n\nDominica Council on Ageing (DCOA)\n\nWebsite\nFacebook\n\n\nCORDES\n\nWebsite\n\n\nConvite A.C.\n\nWebsite\nFacebook\n\n\nConsejo Distrital de Sabios\n\n\n\nCADENA (Comité de Ayuda a Desastres y Emergencias Nacionales)\n\nWebsite\nFacebook\n\n\nAVU Innovación\n\nWebsite\nFacebook\n\n\nAsociacion Uruguaya de Animadores y Auxiliares Gerontologicos (AUDAAG)\n\nFacebook\n\n\nAsociación Central de Funcionarios Públicos y Docentes Jubilados del Paraguay\n\nFacebook\n\n\nAsociación Mutual de Protección Familiar (AMPF)\n\nWebsite\nFacebook\n\n\nAsociación Mutual Israelita Argentina (AMIA)\n\nWebsite\nFacebook\n\n\nAsociación Alianza de Salvadoreños Retornados (ALSARE)\n\nFacebook\n\n\nAsociación Gerontológica Costarricense (AGECO)\n\nWebsite\nFacebook\n\n\nFundación Acción Familiar Alzheimer Colombia (AFACOL)\n\nWebsite\nFacebook\n\n\nAsociacion Cultural Casa Del Nino (ACCN)\n\nWebsite\nFacebook\n\n\nThe Union for Senior Services – VALLI\n\nWebsite\n\n\nPRO Global / Pensioners without Borders\n\nWebsite\nFacebook\n\n\nKwa Wazee\n\nWebsite\n\n\nHelpAge USA\n\nWebsite\nFacebook\n\n\nHelpAge España\n\nWebsite\nFacebook\n\n\nHelpAge Canada\n\nWebsite\nFacebook\n\n\nGlobale Seniorer\n\nWebsite\nFacebook\n\n\nDorcas Aid International\n\nWebsite\nFacebook\n\n\nCaritas Malta Foundation\n\nWebsite\nFacebook\n\n\nBeauty of Help Foundation\n\nWebsite\nFacebook\n\n\nAge International\n\nWebsite\nFacebook\n\n\nAge Action Ireland\n\nWebsite\nFacebook\n\n\nAARP\n\nWebsite\nFacebook\n\n\nYemen Family Care Association (YFCA)\n\nWebsite\nFacebook\n\n\nEl Wedad Society for Community Rehabilitation (WSCR)\n\nWebsite\nFacebook\n\n\nAUB University for Seniors\n\nWebsite\nFacebook\n\n\nTurbota pro Litnix v Ukraini (TLU)\n\nWebsite\nFacebook\n\n\nCharity Foundation Starenki\n\nWebsite\nFacebook\n\n\nSolidarity Is Global Institute (SIGI)\n\nWebsite\nFacebook\n\n\nSyrian Expatriates Medical Association (SEMA)\n\nWebsite\nFacebook\n\n\nRight to Protection\n\nWebsite\nFacebook\n\n\nRed Cross of Serbia (RCS)\n\nWebsite\nFacebook\n\n\nResource Center for Elderly (RCE)\n\nWebsite\nFacebook\n\n\nPalestinian Center For Communication and Development Strategies (PCCDS)\n\nWebsite\nFacebook\n\n\nMission Armenia\n\nWebsite\nFacebook\n\n\nLife Makers Meeting Place Organisation (LMMPO)\n\nWebsite\nFacebook\n\n\nJuzoor for Health and Social Development\n\nWebsite\nFacebook\n\n\nJiyan Foundation for Human Rights\n\nWebsite\nFacebook\n\n\nHope Revival Organization (HRO)\n\nWebsite\nFacebook\n\n\nBabushka Adoption\n\nWebsite\nFacebook\n\n\nArdager\n\n\n\nAmel Association International (Amel)\n\nWebsite\nFacebook\n\n\nAlzheimer’s Association Lebanon (AAL)\n\nWebsite\nFacebook\n\n\nAlbanian Association of Geriatry and Gerontology (AAGG)\n\nWebsite\n\n\nYoung Power in Social Action (YPSA)\n\nWebsite\nFacebook\n\n\nYayasan Emong Lansia (YEL)\n\n\n\nVietnam Elderly Association\n\nWebsite\n\n\nSenior Citizen Chautari (SCC)\n\nWebsite\nFacebook\n\n\nResource Integration center RIC\n\nWebsite\nFacebook\n\n\nNepal Participatory Action Network (NEPAN)\n\nWebsite\nFacebook\n\n\nNational Senior Citizen Federation (NASCIF)\n\nWebsite\n\n\nNational Council of Senior Citizens Organisations Malaysia (NACSCOM)\n\nWebsite\nFacebook\n\n\nHelpAge Sri Lanka\n\nWebsite\nLinkedIn\n\n\nHelpAge Korea\n\nWebsite\nFacebook\n\n\nHelpAge India\n\nWebsite\nFacebook\n\n\nHelpAge Cambodia\n\nWebsite\nFacebook\n\n\nGramin Vikas Vigyan Samiti (GRAVIS)\n\nWebsite\nFacebook\n\n\nforOldy Project, Help without Frontiers Thailand Foundation (HWFT)\n\nWebsite\nFacebook\n\n\nFoundation for Older Persons’ Development (FOPDEV)\n\nWebsite\nFacebook\n\n\nCoalition of Services of the Elderly (COSE)\n\nWebsite\nFacebook\n\n\nChina National Committee on Ageing (CNCA)\n\nWebsite\n\n\nCentre for Human Rights and Development (CHRD)\n\nWebsite\n\n\nBangladesh Women’s Health Coalition (BWHC)\n\nWebsite\n\n\nAgeing Nepal\n\nWebsite\nX\n\n\nUnivers de solidarité et de développement (UNI.SOL.D.)\n\n\n\nRegional Center for the Welfare of Aging Persons in Cameroon (RECEWAPEC)\n\nWebsite\n\n\nGrandmothers Consortium (GMC)\n\nWebsite\n\n\nVUKOXA – Associacao Humanitaria de Apoio a Velhice\n\n\n\nVoice of the Elderly\n\n\n\nUganda Reach the Aged Association (URAA)\n\nWebsite\n\n\nTesfa Social and Development Association\n\nWebsite\n\n\nTanzania Mission to the Poor and Disabled (PADI)\n\nWebsite\n\n\nSupport To Older People-Zambia (STOP-Zambia)\n\nWebsite\n\n\nSenior Citizens Association of Zambia (SCAZ)\n\nWebsite\n\n\nSaidia Wazee Karagwe (SAWAKA)\n\nWebsite\n\n\nReach One Touch One Ministries (ROTOM)\n\nWebsite\n\n\nRelief to Development Society (REDESO)\n\nWebsite\n\n\nReach A Hand Uganda (RAHU)\n\nWebsite\n\n\nPalliative Care Association of Uganda (PCAU)\n\nWebsite\n\n\nNSINDAGIZA Organization\n\nWebsite\n\n\nMuthande\n\nWebsite\n\n\nMangu Integrated Community Project (MICOP Kenya)\n\nFacebook\n\n\nMauritius Family Planning and Welfare Association (MFPWA)\n\nWebsite\n\n\nMalawi Network of Older Persons’ Organisations (MANEPO)\n\nWebsite\n\n\nKulmiye Pastoral Association (DPA)\n\nWebsite\n\n\nKibera Day Care Centre for the Elderly (KDCCE)\n\nWebsite\n\n\nKenya Society for People with AIDS (KESPA)\n\n\n\nKenyan Aged People Require Information, Knowledge & Advancement (KARIKA)\n\nWebsite\n\n\nHorn International Relief & Development Organization (HIRDO)\n\nWebsite\n\n\nHelpAge Kenya (H.A.K.)\n\nFacebook\n\n\nHealth Nest Uganda (HENU)\n\nFacebook\n\n\nHumanitarian and Development Consortium (HDC)\n\nWebsite\n\n\nFantsuam Foundation\n\nWebsite\n\n\nDroits Humains Ocean Indien (Dis-Moi)\n\nWebsite\n\n\nCoalition of Societies for the Rights of Older Persons in Nigeria (COSROPIN)\n\nWebsite\n\n\nCommunity Based Rehabilitation Alliance (COMBRA)\n\nWebsite\n\n\nCenter for Community Advancement and Family Empowerment (CECAFE)\n\n\n\nAcção para o Desenvolvimento Comunitarios or Association for Community Development Action in Sofala (ASADEC)\n\n\n\nAlmanar Voluntary Organization (AMVO)\n\nWebsite\nFacebook\n\n\nAfrica Development Aid (ADA)\n\nWebsite\n\n\nAgeing Concern Foundation (ACF)\n\nWebsite\n\n\nACAMAGE\n\nFacebook\n\nAGE Myanmar\n\nWebsite\nLinkedIn\n\n\nKing Hussain Foundation / Institute for Family Health (KHF/iFH)\n\nWebsite\n\n\nAgeing with a Smile Initiative\n\nFacebook\n\n\nSIDOM Foundation\n\nWebsite\n\n\nFederal University of Santa Catarina (UFSC)\n\nWebsite\nFacebook\n\n\nSurcos AC\n\nWebsite\nFacebook\n\n\nServicio Social de Iglesias Dominicanas (SSID)\n\nWebsite\nFacebook\n\n\nSociedad Argentina de Gerontología y Geriatría (SAGG)\n\nWebsite\nFacebook\n\n\nSt. Catherine Community Development Agency (SACDA)\n\nWebsite\nFacebook\n\n\nAsociación Red Colombiana de Envejecimiento Activo y Digno (REDCOENVE)\n\nWebsite\nFacebook\n\n\nRAFAM Argentina Foundation\n\nWebsite\nFacebook\n\n\nPro Vida Perú\n\nFacebook\n\n\nONG Sumaj Punchay\n\nFacebook\n\n\nNTD Foundation\n\nWebsite\nFacebook\n\n\nMexican Alzheimer’s Center\n\nWebsite\nFacebook\n\n\nMesa de Trabajo sobre Personas Adultas Mayores\n\nFacebook\n\n\nCentro de Envejexcimiento Activo y Longevidad de la Universidad ISALUD\n\nWebsite\nFacebook\n\n\nFundación Horizontes\n\nFacebook\n\n\nHelpage St. Lucia National Council of and for older persons\n\n\n\nHelpAge Belize\n\nFacebook\n\n\nFundación Yamuni Tabush\n\nWebsite\nFacebook\n\n\nDominica Council on Ageing (DCOA)\n\nWebsite\nFacebook\n\n\nCORDES\n\nWebsite\n\n\nConvite A.C.\n\nWebsite\nFacebook\n\n\nConsejo Distrital de Sabios\n\n\n\nCADENA (Comité de Ayuda a Desastres y Emergencias Nacionales)\n\nWebsite\nFacebook\n\n\nAVU Innovación\n\nWebsite\nFacebook\n\n\nAsociacion Uruguaya de Animadores y Auxiliares Gerontologicos (AUDAAG)\n\nFacebook\n\n\nAsociación Central de Funcionarios Públicos y Docentes Jubilados del Paraguay\n\nFacebook\n\n\nAsociación Mutual de Protección Familiar (AMPF)\n\nWebsite\nFacebook\n\n\nAsociación Mutual Israelita Argentina (AMIA)\n\nWebsite\nFacebook\n\n\nAsociación Alianza de Salvadoreños Retornados (ALSARE)\n\nFacebook\n\n\nAsociación Gerontológica Costarricense (AGECO)\n\nWebsite\nFacebook\n\n\nFundación Acción Familiar Alzheimer Colombia (AFACOL)\n\nWebsite\nFacebook\n\n\nAsociacion Cultural Casa Del Nino (ACCN)\n\nWebsite\nFacebook\n\n\nThe Union for Senior Services – VALLI\n\nWebsite\n\n\nPRO Global / Pensioners without Borders\n\nWebsite\nFacebook\n\n\nKwa Wazee\n\nWebsite\n\n\nHelpAge USA\n\nWebsite\nFacebook\n\n\nHelpAge España\n\nWebsite\nFacebook\n\n\nHelpAge Canada\n\nWebsite\nFacebook\n\n\nGlobale Seniorer\n\nWebsite\nFacebook\n\n\nDorcas Aid International\n\nWebsite\nFacebook\n\n\nCaritas Malta Foundation\n\nWebsite\nFacebook\n\n\nBeauty of Help Foundation\n\nWebsite\nFacebook\n\n\nAge International\n\nWebsite\nFacebook\n\n\nAge Action Ireland\n\nWebsite\nFacebook\n\n\nAARP\n\nWebsite\nFacebook\n\n\nYemen Family Care Association (YFCA)\n\nWebsite\nFacebook\n\n\nEl Wedad Society for Community Rehabilitation (WSCR)\n\nWebsite\nFacebook\n\n\nAUB University for Seniors\n\nWebsite\nFacebook\n\n\nTurbota pro Litnix v Ukraini (TLU)\n\nWebsite\nFacebook\n\n\nCharity Foundation Starenki\n\nWebsite\nFacebook\n\n\nSolidarity Is Global Institute (SIGI)\n\nWebsite\nFacebook\n\n\nSyrian Expatriates Medical Association (SEMA)\n\nWebsite\nFacebook\n\n\nRight to Protection\n\nWebsite\nFacebook\n\n\nRed Cross of Serbia (RCS)\n\nWebsite\nFacebook\n\n\nResource Center for Elderly (RCE)\n\nWebsite\nFacebook\n\n\nPalestinian Center For Communication and Development Strategies (PCCDS)\n\nWebsite\nFacebook\n\n\nMission Armenia\n\nWebsite\nFacebook\n\n\nLife Makers Meeting Place Organisation (LMMPO)\n\nWebsite\nFacebook\n\n\nJuzoor for Health and Social Development\n\nWebsite\nFacebook\n\n\nJiyan Foundation for Human Rights\n\nWebsite\nFacebook\n\n\nHope Revival Organization (HRO)\n\nWebsite\nFacebook\n\n\nBabushka Adoption\n\nWebsite\nFacebook\n\n\nArdager\n\n\n\nAmel Association International (Amel)\n\nWebsite\nFacebook\n\n\nAlzheimer’s Association Lebanon (AAL)\n\nWebsite\nFacebook\n\n\nAlbanian Association of Geriatry and Gerontology (AAGG)\n\nWebsite\n\n\nYoung Power in Social Action (YPSA)\n\nWebsite\nFacebook\n\n\nYayasan Emong Lansia (YEL)\n\n\n\nVietnam Elderly Association\n\nWebsite\n\n\nSenior Citizen Chautari (SCC)\n\nWebsite\nFacebook\n\n\nResource Integration center RIC\n\nWebsite\nFacebook\n\n\nNepal Participatory Action Network (NEPAN)\n\nWebsite\nFacebook\n\n\nNational Senior Citizen Federation (NASCIF)\n\nWebsite\n\n\nNational Council of Senior Citizens Organisations Malaysia (NACSCOM)\n\nWebsite\nFacebook\n\n\nHelpAge Sri Lanka\n\nWebsite\nLinkedIn\n\n\nHelpAge Korea\n\nWebsite\nFacebook\n\n\nHelpAge India\n\nWebsite\nFacebook\n\n\nHelpAge Cambodia\n\nWebsite\nFacebook\n\n\nGramin Vikas Vigyan Samiti (GRAVIS)\n\nWebsite\nFacebook\n\n\nforOldy Project, Help without Frontiers Thailand Foundation (HWFT)\n\nWebsite\nFacebook\n\n\nFoundation for Older Persons’ Development (FOPDEV)\n\nWebsite\nFacebook\n\n\nCoalition of Services of the Elderly (COSE)\n\nWebsite\nFacebook\n\n\nChina National Committee on Ageing (CNCA)\n\nWebsite\n\n\nCentre for Human Rights and Development (CHRD)\n\nWebsite\n\n\nBangladesh Women’s Health Coalition (BWHC)\n\nWebsite\n\n\nAgeing Nepal\n\nWebsite\nX\n\n\nUnivers de solidarité et de développement (UNI.SOL.D.)\n\n\n\nRegional Center for the Welfare of Aging Persons in Cameroon (RECEWAPEC)\n\nWebsite\n\n\nGrandmothers Consortium (GMC)\n\nWebsite\n\n\nVUKOXA – Associacao Humanitaria de Apoio a Velhice\n\n\n\nVoice of the Elderly\n\n\n\nUganda Reach the Aged Association (URAA)\n\nWebsite\n\n\nTesfa Social and Development Association\n\nWebsite\n\n\nTanzania Mission to the Poor and Disabled (PADI)\n\nWebsite\n\n\nSupport To Older People-Zambia (STOP-Zambia)\n\nWebsite\n\n\nSenior Citizens Association of Zambia (SCAZ)\n\nWebsite\n\n\nSaidia Wazee Karagwe (SAWAKA)\n\nWebsite\n\n\nReach One Touch One Ministries (ROTOM)\n\nWebsite\n\n\nRelief to Development Society (REDESO)\n\nWebsite\n\n\nReach A Hand Uganda (RAHU)\n\nWebsite\n\n\nPalliative Care Association of Uganda (PCAU)\n\nWebsite\n\n\nNSINDAGIZA Organization\n\nWebsite\n\n\nMuthande\n\nWebsite\n\n\nMangu Integrated Community Project (MICOP Kenya)\n\nFacebook\n\n\nMauritius Family Planning and Welfare Association (MFPWA)\n\nWebsite\n\n\nMalawi Network of Older Persons’ Organisations (MANEPO)\n\nWebsite\n\n\nKulmiye Pastoral Association (DPA)\n\nWebsite\n\n\nKibera Day Care Centre for the Elderly (KDCCE)\n\nWebsite\n\n\nKenya Society for People with AIDS (KESPA)\n\n\n\nKenyan Aged People Require Information, Knowledge & Advancement (KARIKA)\n\nWebsite\n\n\nHorn International Relief & Development Organization (HIRDO)\n\nWebsite\n\n\nHelpAge Kenya (H.A.K.)\n\nFacebook\n\n\nHealth Nest Uganda (HENU)\n\nFacebook\n\n\nHumanitarian and Development Consortium (HDC)\n\nWebsite\n\n\nFantsuam Foundation\n\nWebsite\n\n\nDroits Humains Ocean Indien (Dis-Moi)\n\nWebsite\n\n\nCoalition of Societies for the Rights of Older Persons in Nigeria (COSROPIN)\n\nWebsite\n\n\nCommunity Based Rehabilitation Alliance (COMBRA)\n\nWebsite\n\n\nCenter for Community Advancement and Family Empowerment (CECAFE)\n\n\n\nAcção para o Desenvolvimento Comunitarios or Association for Community Development Action in Sofala (ASADEC)\n\n\n\nAlmanar Voluntary Organization (AMVO)\n\nWebsite\nFacebook\n\n\nAfrica Development Aid (ADA)\n\nWebsite\n\n\nAgeing Concern Foundation (ACF)\n\nWebsite\n\n\nACAMAGE\n\nFacebook\n\nAGE Myanmar\n\nWebsite\nLinkedIn\n\n\nKing Hussain Foundation / Institute for Family Health (KHF/iFH)\n\nWebsite\n\n\nAgeing with a Smile Initiative\n\nFacebook\n\n\nSIDOM Foundation\n\nWebsite\n\n\nFederal University of Santa Catarina (UFSC)\n\nWebsite\nFacebook\n\n\nSurcos AC\n\nWebsite\nFacebook\n\n\nServicio Social de Iglesias Dominicanas (SSID)\n\nWebsite\nFacebook\n\n\nSociedad Argentina de Gerontología y Geriatría (SAGG)\n\nWebsite\nFacebook\n\n\nSt. Catherine Community Development Agency (SACDA)\n\nWebsite\nFacebook\n\n\nAsociación Red Colombiana de Envejecimiento Activo y Digno (REDCOENVE)\n\nWebsite\nFacebook\n\n\nRAFAM Argentina Foundation\n\nWebsite\nFacebook\n\n\nPro Vida Perú\n\nFacebook\n\n\nONG Sumaj Punchay\n\nFacebook\n\n\nNTD Foundation\n\nWebsite\nFacebook\n\n\nMexican Alzheimer’s Center\n\nWebsite\nFacebook\n\n\nMesa de Trabajo sobre Personas Adultas Mayores\n\nFacebook\n\n\nCentro de Envejexcimiento Activo y Longevidad de la Universidad ISALUD\n\nWebsite\nFacebook\n\n\nFundación Horizontes\n\nFacebook\n\n\nHelpage St. Lucia National Council of and for older persons\n\n\n\nHelpAge Belize\n\nFacebook\n\n\nFundación Yamuni Tabush\n\nWebsite\nFacebook\n\n\nDominica Council on Ageing (DCOA)\n\nWebsite\nFacebook\n\n\nCORDES\n\nWebsite\n\n\nConvite A.C.\n\nWebsite\nFacebook\n\n\nConsejo Distrital de Sabios\n\n\n\nCADENA (Comité de Ayuda a Desastres y Emergencias Nacionales)\n\nWebsite\nFacebook\n\n\nAVU Innovación\n\nWebsite\nFacebook\n\n\nAsociacion Uruguaya de Animadores y Auxiliares Gerontologicos (AUDAAG)\n\nFacebook\n\n\nAsociación Central de Funcionarios Públicos y Docentes Jubilados del Paraguay\n\nFacebook\n\n\nAsociación Mutual de Protección Familiar (AMPF)\n\nWebsite\nFacebook\n\n\nAsociación Mutual Israelita Argentina (AMIA)\n\nWebsite\nFacebook\n\n\nAsociación Alianza de Salvadoreños Retornados (ALSARE)\n\nFacebook\n\n\nAsociación Gerontológica Costarricense (AGECO)\n\nWebsite\nFacebook\n\n\nFundación Acción Familiar Alzheimer Colombia (AFACOL)\n\nWebsite\nFacebook\n\n\nAsociacion Cultural Casa Del Nino (ACCN)\n\nWebsite\nFacebook\n\n\nThe Union for Senior Services – VALLI\n\nWebsite\n\n\nPRO Global / Pensioners without Borders\n\nWebsite\nFacebook\n\n\nKwa Wazee\n\nWebsite\n\n\nHelpAge USA\n\nWebsite\nFacebook\n\n\nHelpAge España\n\nWebsite\nFacebook\n\n\nHelpAge Canada\n\nWebsite\nFacebook\n\n\nGlobale Seniorer\n\nWebsite\nFacebook\n\n\nDorcas Aid International\n\nWebsite\nFacebook\n\n\nCaritas Malta Foundation\n\nWebsite\nFacebook\n\n\nBeauty of Help Foundation\n\nWebsite\nFacebook\n\n\nAge International\n\nWebsite\nFacebook\n\n\nAge Action Ireland\n\nWebsite\nFacebook\n\n\nAARP\n\nWebsite\nFacebook\n\n\nYemen Family Care Association (YFCA)\n\nWebsite\nFacebook\n\n\nEl Wedad Society for Community Rehabilitation (WSCR)\n\nWebsite\nFacebook\n\n\nAUB University for Seniors\n\nWebsite\nFacebook\n\n\nTurbota pro Litnix v Ukraini (TLU)\n\nWebsite\nFacebook\n\n\nCharity Foundation Starenki\n\nWebsite\nFacebook\n\n\nSolidarity Is Global Institute (SIGI)\n\nWebsite\nFacebook\n\n\nSyrian Expatriates Medical Association (SEMA)\n\nWebsite\nFacebook\n\n\nRight to Protection\n\nWebsite\nFacebook\n\n\nRed Cross of Serbia (RCS)\n\nWebsite\nFacebook\n\n\nResource Center for Elderly (RCE)\n\nWebsite\nFacebook\n\n\nPalestinian Center For Communication and Development Strategies (PCCDS)\n\nWebsite\nFacebook\n\n\nMission Armenia\n\nWebsite\nFacebook\n\n\nLife Makers Meeting Place Organisation (LMMPO)\n\nWebsite\nFacebook\n\n\nJuzoor for Health and Social Development\n\nWebsite\nFacebook\n\n\nJiyan Foundation for Human Rights\n\nWebsite\nFacebook\n\n\nHope Revival Organization (HRO)\n\nWebsite\nFacebook\n\n\nBabushka Adoption\n\nWebsite\nFacebook\n\n\nArdager\n\n\n\nAmel Association International (Amel)\n\nWebsite\nFacebook\n\n\nAlzheimer’s Association Lebanon (AAL)\n\nWebsite\nFacebook\n\n\nAlbanian Association of Geriatry and Gerontology (AAGG)\n\nWebsite\n\n\nYoung Power in Social Action (YPSA)\n\nWebsite\nFacebook\n\n\nYayasan Emong Lansia (YEL)\n\n\n\nVietnam Elderly Association\n\nWebsite\n\n\nSenior Citizen Chautari (SCC)\n\nWebsite\nFacebook\n\n\nResource Integration center RIC\n\nWebsite\nFacebook\n\n\nNepal Participatory Action Network (NEPAN)\n\nWebsite\nFacebook\n\n\nNational Senior Citizen Federation (NASCIF)\n\nWebsite\n\n\nNational Council of Senior Citizens Organisations Malaysia (NACSCOM)\n\nWebsite\nFacebook\n\n\nHelpAge Sri Lanka\n\nWebsite\nLinkedIn\n\n\nHelpAge Korea\n\nWebsite\nFacebook\n\n\nHelpAge India\n\nWebsite\nFacebook\n\n\nHelpAge Cambodia\n\nWebsite\nFacebook\n\n\nGramin Vikas Vigyan Samiti (GRAVIS)\n\nWebsite\nFacebook\n\n\nforOldy Project, Help without Frontiers Thailand Foundation (HWFT)\n\nWebsite\nFacebook\n\n\nFoundation for Older Persons’ Development (FOPDEV)\n\nWebsite\nFacebook\n\n\nCoalition of Services of the Elderly (COSE)\n\nWebsite\nFacebook\n\n\nChina National Committee on Ageing (CNCA)\n\nWebsite\n\n\nCentre for Human Rights and Development (CHRD)\n\nWebsite\n\n\nBangladesh Women’s Health Coalition (BWHC)\n\nWebsite\n\n\nAgeing Nepal\n\nWebsite\nX\n\n\nUnivers de solidarité et de développement (UNI.SOL.D.)\n\n\n\nRegional Center for the Welfare of Aging Persons in Cameroon (RECEWAPEC)\n\nWebsite\n\n\nGrandmothers Consortium (GMC)\n\nWebsite\n\n\nVUKOXA – Associacao Humanitaria de Apoio a Velhice\n\n\n\nVoice of the Elderly\n\n\n\nUganda Reach the Aged Association (URAA)\n\nWebsite\n\n\nTesfa Social and Development Association\n\nWebsite\n\n\nTanzania Mission to the Poor and Disabled (PADI)\n\nWebsite\n\n\nSupport To Older People-Zambia (STOP-Zambia)\n\nWebsite\n\n\nSenior Citizens Association of Zambia (SCAZ)\n\nWebsite\n\n\nSaidia Wazee Karagwe (SAWAKA)\n\nWebsite\n\n\nReach One Touch One Ministries (ROTOM)\n\nWebsite\n\n\nRelief to Development Society (REDESO)\n\nWebsite\n\n\nReach A Hand Uganda (RAHU)\n\nWebsite\n\n\nPalliative Care Association of Uganda (PCAU)\n\nWebsite\n\n\nNSINDAGIZA Organization\n\nWebsite\n\n\nMuthande\n\nWebsite\n\n\nMangu Integrated Community Project (MICOP Kenya)\n\nFacebook\n\n\nMauritius Family Planning and Welfare Association (MFPWA)\n\nWebsite\n\n\nMalawi Network of Older Persons’ Organisations (MANEPO)\n\nWebsite\n\n\nKulmiye Pastoral Association (DPA)\n\nWebsite\n\n\nKibera Day Care Centre for the Elderly (KDCCE)\n\nWebsite\n\n\nKenya Society for People with AIDS (KESPA)\n\n\n\nKenyan Aged People Require Information, Knowledge & Advancement (KARIKA)\n\nWebsite\n\n\nHorn International Relief & Development Organization (HIRDO)\n\nWebsite\n\n\nHelpAge Kenya (H.A.K.)\n\nFacebook\n\n\nHealth Nest Uganda (HENU)\n\nFacebook\n\n\nHumanitarian and Development Consortium (HDC)\n\nWebsite\n\n\nFantsuam Foundation\n\nWebsite\n\n\nDroits Humains Ocean Indien (Dis-Moi)\n\nWebsite\n\n\nCoalition of Societies for the Rights of Older Persons in Nigeria (COSROPIN)\n\nWebsite\n\n\nCommunity Based Rehabilitation Alliance (COMBRA)\n\nWebsite\n\n\nCenter for Community Advancement and Family Empowerment (CECAFE)\n\n\n\nAcção para o Desenvolvimento Comunitarios or Association for Community Development Action in Sofala (ASADEC)\n\n\n\nAlmanar Voluntary Organization (AMVO)\n\nWebsite\nFacebook\n\n\nAfrica Development Aid (ADA)\n\nWebsite\n\n\nAgeing Concern Foundation (ACF)\n\nWebsite\n\n\nACAMAGE\n\nFacebook\n\nAGE Myanmar\n\nWebsite\nLinkedIn\n\n\nKing Hussain Foundation / Institute for Family Health (KHF/iFH)\n\nWebsite\n\n\nAgeing with a Smile Initiative\n\nFacebook\n\n\nSIDOM Foundation\n\nWebsite\n\n\nFederal University of Santa Catarina (UFSC)\n\nWebsite\nFacebook\n\n\nSurcos AC\n\nWebsite\nFacebook\n\n\nServicio Social de Iglesias Dominicanas (SSID)\n\nWebsite\nFacebook\n\n\nSociedad Argentina de Gerontología y Geriatría (SAGG)\n\nWebsite\nFacebook\n\n\nSt. Catherine Community Development Agency (SACDA)\n\nWebsite\nFacebook\n\n\nAsociación Red Colombiana de Envejecimiento Activo y Digno (REDCOENVE)\n\nWebsite\nFacebook\n\n\nRAFAM Argentina Foundation\n\nWebsite\nFacebook\n\n\nPro Vida Perú\n\nFacebook\n\n\nONG Sumaj Punchay\n\nFacebook\n\n\nNTD Foundation\n\nWebsite\nFacebook\n\n\nMexican Alzheimer’s Center\n\nWebsite\nFacebook\n\n\nMesa de Trabajo sobre Personas Adultas Mayores\n\nFacebook\n\n\nCentro de Envejexcimiento Activo y Longevidad de la Universidad ISALUD\n\nWebsite\nFacebook\n\n\nFundación Horizontes\n\nFacebook\n\n\nHelpage St. Lucia National Council of and for older persons\n\n\n\nHelpAge Belize\n\nFacebook\n\n\nFundación Yamuni Tabush\n\nWebsite\nFacebook\n\n\nDominica Council on Ageing (DCOA)\n\nWebsite\nFacebook\n\n\nCORDES\n\nWebsite\n\n\nConvite A.C.\n\nWebsite\nFacebook\n\n\nConsejo Distrital de Sabios\n\n\n\nCADENA (Comité de Ayuda a Desastres y Emergencias Nacionales)\n\nWebsite\nFacebook\n\n\nAVU Innovación\n\nWebsite\nFacebook\n\n\nAsociacion Uruguaya de Animadores y Auxiliares Gerontologicos (AUDAAG)\n\nFacebook\n\n\nAsociación Central de Funcionarios Públicos y Docentes Jubilados del Paraguay\n\nFacebook\n\n\nAsociación Mutual de Protección Familiar (AMPF)\n\nWebsite\nFacebook\n\n\nAsociación Mutual Israelita Argentina (AMIA)\n\nWebsite\nFacebook\n\n\nAsociación Alianza de Salvadoreños Retornados (ALSARE)\n\nFacebook\n\n\nAsociación Gerontológica Costarricense (AGECO)\n\nWebsite\nFacebook\n\n\nFundación Acción Familiar Alzheimer Colombia (AFACOL)\n\nWebsite\nFacebook\n\n\nAsociacion Cultural Casa Del Nino (ACCN)\n\nWebsite\nFacebook\n\n\nThe Union for Senior Services – VALLI\n\nWebsite\n\n\nPRO Global / Pensioners without Borders\n\nWebsite\nFacebook\n\n\nKwa Wazee\n\nWebsite\n\n\nHelpAge USA\n\nWebsite\nFacebook\n\n\nHelpAge España\n\nWebsite\nFacebook\n\n\nHelpAge Canada\n\nWebsite\nFacebook\n\n\nGlobale Seniorer\n\nWebsite\nFacebook\n\n\nDorcas Aid International\n\nWebsite\nFacebook\n\n\nCaritas Malta Foundation\n\nWebsite\nFacebook\n\n\nBeauty of Help Foundation\n\nWebsite\nFacebook\n\n\nAge International\n\nWebsite\nFacebook\n\n\nAge Action Ireland\n\nWebsite\nFacebook\n\n\nAARP\n\nWebsite\nFacebook\n\n\nYemen Family Care Association (YFCA)\n\nWebsite\nFacebook\n\n\nEl Wedad Society for Community Rehabilitation (WSCR)\n\nWebsite\nFacebook\n\n\nAUB University for Seniors\n\nWebsite\nFacebook\n\n\nTurbota pro Litnix v Ukraini (TLU)\n\nWebsite\nFacebook\n\n\nCharity Foundation Starenki\n\nWebsite\nFacebook\n\n\nSolidarity Is Global Institute (SIGI)\n\nWebsite\nFacebook\n\n\nSyrian Expatriates Medical Association (SEMA)\n\nWebsite\nFacebook\n\n\nRight to Protection\n\nWebsite\nFacebook\n\n\nRed Cross of Serbia (RCS)\n\nWebsite\nFacebook\n\n\nResource Center for Elderly (RCE)\n\nWebsite\nFacebook\n\n\nPalestinian Center For Communication and Development Strategies (PCCDS)\n\nWebsite\nFacebook\n\n\nMission Armenia\n\nWebsite\nFacebook\n\n\nLife Makers Meeting Place Organisation (LMMPO)\n\nWebsite\nFacebook\n\n\nJuzoor for Health and Social Development\n\nWebsite\nFacebook\n\n\nJiyan Foundation for Human Rights\n\nWebsite\nFacebook\n\n\nHope Revival Organization (HRO)\n\nWebsite\nFacebook\n\n\nBabushka Adoption\n\nWebsite\nFacebook\n\n\nArdager\n\n\n\nAmel Association International (Amel)\n\nWebsite\nFacebook\n\n\nAlzheimer’s Association Lebanon (AAL)\n\nWebsite\nFacebook\n\n\nAlbanian Association of Geriatry and Gerontology (AAGG)\n\nWebsite\n\n\nYoung Power in Social Action (YPSA)\n\nWebsite\nFacebook\n\n\nYayasan Emong Lansia (YEL)\n\n\n\nVietnam Elderly Association\n\nWebsite\n\n\nSenior Citizen Chautari (SCC)\n\nWebsite\nFacebook\n\n\nResource Integration center RIC\n\nWebsite\nFacebook\n\n\nNepal Participatory Action Network (NEPAN)\n\nWebsite\nFacebook\n\n\nNational Senior Citizen Federation (NASCIF)\n\nWebsite\n\n\nNational Council of Senior Citizens Organisations Malaysia (NACSCOM)\n\nWebsite\nFacebook\n\n\nHelpAge Sri Lanka\n\nWebsite\nLinkedIn\n\n\nHelpAge Korea\n\nWebsite\nFacebook\n\n\nHelpAge India\n\nWebsite\nFacebook\n\n\nHelpAge Cambodia\n\nWebsite\nFacebook\n\n\nGramin Vikas Vigyan Samiti (GRAVIS)\n\nWebsite\nFacebook\n\n\nforOldy Project, Help without Frontiers Thailand Foundation (HWFT)\n\nWebsite\nFacebook\n\n\nFoundation for Older Persons’ Development (FOPDEV)\n\nWebsite\nFacebook\n\n\nCoalition of Services of the Elderly (COSE)\n\nWebsite\nFacebook\n\n\nChina National Committee on Ageing (CNCA)\n\nWebsite\n\n\nCentre for Human Rights and Development (CHRD)\n\nWebsite\n\n\nBangladesh Women’s Health Coalition (BWHC)\n\nWebsite\n\n\nAgeing Nepal\n\nWebsite\nX\n\n\nUnivers de solidarité et de développement (UNI.SOL.D.)\n\n\n\nRegional Center for the Welfare of Aging Persons in Cameroon (RECEWAPEC)\n\nWebsite\n\n\nGrandmothers Consortium (GMC)\n\nWebsite\n\n\nVUKOXA – Associacao Humanitaria de Apoio a Velhice\n\n\n\nVoice of the Elderly\n\n\n\nUganda Reach the Aged Association (URAA)\n\nWebsite\n\n\nTesfa Social and Development Association\n\nWebsite\n\n\nTanzania Mission to the Poor and Disabled (PADI)\n\nWebsite\n\n\nSupport To Older People-Zambia (STOP-Zambia)\n\nWebsite\n\n\nSenior Citizens Association of Zambia (SCAZ)\n\nWebsite\n\n\nSaidia Wazee Karagwe (SAWAKA)\n\nWebsite\n\n\nReach One Touch One Ministries (ROTOM)\n\nWebsite\n\n\nRelief to Development Society (REDESO)\n\nWebsite\n\n\nReach A Hand Uganda (RAHU)\n\nWebsite\n\n\nPalliative Care Association of Uganda (PCAU)\n\nWebsite\n\n\nNSINDAGIZA Organization\n\nWebsite\n\n\nMuthande\n\nWebsite\n\n\nMangu Integrated Community Project (MICOP Kenya)\n\nFacebook\n\n\nMauritius Family Planning and Welfare Association (MFPWA)\n\nWebsite\n\n\nMalawi Network of Older Persons’ Organisations (MANEPO)\n\nWebsite\n\n\nKulmiye Pastoral Association (DPA)\n\nWebsite\n\n\nKibera Day Care Centre for the Elderly (KDCCE)\n\nWebsite\n\n\nKenya Society for People with AIDS (KESPA)\n\n\n\nKenyan Aged People Require Information, Knowledge & Advancement (KARIKA)\n\nWebsite\n\n\nHorn International Relief & Development Organization (HIRDO)\n\nWebsite\n\n\nHelpAge Kenya (H.A.K.)\n\nFacebook\n\n\nHealth Nest Uganda (HENU)\n\nFacebook\n\n\nHumanitarian and Development Consortium (HDC)\n\nWebsite\n\n\nFantsuam Foundation\n\nWebsite\n\n\nDroits Humains Ocean Indien (Dis-Moi)\n\nWebsite\n\n\nCoalition of Societies for the Rights of Older Persons in Nigeria (COSROPIN)\n\nWebsite\n\n\nCommunity Based Rehabilitation Alliance (COMBRA)\n\nWebsite\n\n\nCenter for Community Advancement and Family Empowerment (CECAFE)\n\n\n\nAcção para o Desenvolvimento Comunitarios or Association for Community Development Action in Sofala (ASADEC)\n\n\n\nAlmanar Voluntary Organization (AMVO)\n\nWebsite\nFacebook\n\n\nAfrica Development Aid (ADA)\n\nWebsite\n\n\nAgeing Concern Foundation (ACF)\n\nWebsite\n\n\nACAMAGE\n\nFacebook\n\nAGE Myanmar\n\nWebsite\nLinkedIn\n\nWebsite\n\nLinkedIn\n\nKing Hussain Foundation / Institute for Family Health (KHF/iFH)\n\nWebsite\n\nWebsite\n\nAgeing with a Smile Initiative\n\nFacebook\n\nFacebook\n\nSIDOM Foundation\n\nWebsite\n\nWebsite\n\nFederal University of Santa Catarina (UFSC)\n\nWebsite\nFacebook\n\nWebsite\n\nFacebook\n\nSurcos AC\n\nWebsite\nFacebook\n\nWebsite\n\nFacebook\n\nServicio Social de Iglesias Dominicanas (SSID)\n\nWebsite\nFacebook\n\nWebsite\n\nFacebook\n\nSociedad Argentina de Gerontología y Geriatría (SAGG)\n\nWebsite\nFacebook\n\nWebsite\n\nFacebook\n\nSt. Catherine Community Development Agency (SACDA)\n\nWebsite\nFacebook\n\nWebsite\n\nFacebook\n\nAsociación Red Colombiana de Envejecimiento Activo y Digno (REDCOENVE)\n\nWebsite\nFacebook\n\nWebsite\n\nFacebook\n\nRAFAM Argentina Foundation\n\nWebsite\nFacebook\n\nWebsite\n\nFacebook\n\nPro Vida Perú\n\nFacebook\n\nFacebook\n\nONG Sumaj Punchay\n\nFacebook\n\nFacebook\n\nNTD Foundation\n\nWebsite\nFacebook\n\nWebsite\n\nFacebook\n\nMexican Alzheimer’s Center\n\nWebsite\nFacebook\n\nWebsite\n\nFacebook\n\nMesa de Trabajo sobre Personas Adultas Mayores\n\nFacebook\n\nFacebook\n\nCentro de Envejexcimiento Activo y Longevidad de la Universidad ISALUD\n\nWebsite\nFacebook\n\nWebsite\n\nFacebook\n\nFundación Horizontes\n\nFacebook\n\nFacebook\n\nHelpage St. Lucia National Council of and for older persons\n\nHelpAge Belize\n\nFacebook\n\nFacebook\n\nFundación Yamuni Tabush\n\nWebsite\nFacebook\n\nWebsite\n\nFacebook\n\nDominica Council on Ageing (DCOA)\n\nWebsite\nFacebook\n\nWebsite\n\nFacebook\n\nCORDES\n\nWebsite\n\nWebsite\n\nConvite A.C.\n\nWebsite\nFacebook\n\nWebsite\n\nFacebook\n\nConsejo Distrital de Sabios\n\nCADENA (Comité de Ayuda a Desastres y Emergencias Nacionales)\n\nWebsite\nFacebook\n\nWebsite\n\nFacebook\n\nAVU Innovación\n\nWebsite\nFacebook\n\nWebsite\n\nFacebook\n\nAsociacion Uruguaya de Animadores y Auxiliares Gerontologicos (AUDAAG)\n\nFacebook\n\nFacebook\n\nAsociación Central de Funcionarios Públicos y Docentes Jubilados del Paraguay\n\nFacebook\n\nFacebook\n\nAsociación Mutual de Protección Familiar (AMPF)\n\nWebsite\nFacebook\n\nWebsite\n\nFacebook\n\nAsociación Mutual Israelita Argentina (AMIA)\n\nWebsite\nFacebook\n\nWebsite\n\nFacebook\n\nAsociación Alianza de Salvadoreños Retornados (ALSARE)\n\nFacebook\n\nFacebook\n\nAsociación Gerontológica Costarricense (AGECO)\n\nWebsite\nFacebook\n\nWebsite\n\nFacebook\n\nFundación Acción Familiar Alzheimer Colombia (AFACOL)\n\nWebsite\nFacebook\n\nWebsite\n\nFacebook\n\nAsociacion Cultural Casa Del Nino (ACCN)\n\nWebsite\nFacebook\n\nWebsite\n\nFacebook\n\nThe Union for Senior Services – VALLI\n\nWebsite\n\nWebsite\n\nPRO Global / Pensioners without Borders\n\nWebsite\nFacebook\n\nWebsite\n\nFacebook\n\nKwa Wazee\n\nWebsite\n\nWebsite\n\nHelpAge USA\n\nWebsite\nFacebook\n\nWebsite\n\nFacebook\n\nHelpAge España\n\nWebsite\nFacebook\n\nWebsite\n\nFacebook\n\nHelpAge Canada\n\nWebsite\nFacebook\n\nWebsite\n\nFacebook\n\nGlobale Seniorer\n\nWebsite\nFacebook\n\nWebsite\n\nFacebook\n\nDorcas Aid International\n\nWebsite\nFacebook\n\nWebsite\n\nFacebook\n\nCaritas Malta Foundation\n\nWebsite\nFacebook\n\nWebsite\n\nFacebook\n\nBeauty of Help Foundation\n\nWebsite\nFacebook\n\nWebsite\n\nFacebook\n\nAge International\n\nWebsite\nFacebook\n\nWebsite\n\nFacebook\n\nAge Action Ireland\n\nWebsite\nFacebook\n\nWebsite\n\nFacebook\n\nAARP\n\nWebsite\nFacebook\n\nWebsite\n\nFacebook\n\nYemen Family Care Association (YFCA)\n\nWebsite\nFacebook\n\nWebsite\n\nFacebook\n\nEl Wedad Society for Community Rehabilitation (WSCR)\n\nWebsite\nFacebook\n\nWebsite\n\nFacebook\n\nAUB University for Seniors\n\nWebsite\nFacebook\n\nWebsite\n\nFacebook\n\nTurbota pro Litnix v Ukraini (TLU)\n\nWebsite\nFacebook\n\nWebsite\n\nFacebook\n\nCharity Foundation Starenki\n\nWebsite\nFacebook\n\nWebsite\n\nFacebook\n\nSolidarity Is Global Institute (SIGI)\n\nWebsite\nFacebook\n\nWebsite\n\nFacebook\n\nSyrian Expatriates Medical Association (SEMA)\n\nWebsite\nFacebook\n\nWebsite\n\nFacebook\n\nRight to Protection\n\nWebsite\nFacebook\n\nWebsite\n\nFacebook\n\nRed Cross of Serbia (RCS)\n\nWebsite\nFacebook\n\nWebsite\n\nFacebook\n\nResource Center for Elderly (RCE)\n\nWebsite\nFacebook\n\nWebsite\n\nFacebook\n\nPalestinian Center For Communication and Development Strategies (PCCDS)\n\nWebsite\nFacebook\n\nWebsite\n\nFacebook\n\nMission Armenia\n\nWebsite\nFacebook\n\nWebsite\n\nFacebook\n\nLife Makers Meeting Place Organisation (LMMPO)\n\nWebsite\nFacebook\n\nWebsite\n\nFacebook\n\nJuzoor for Health and Social Development\n\nWebsite\nFacebook\n\nWebsite\n\nFacebook\n\nJiyan Foundation for Human Rights\n\nWebsite\nFacebook\n\nWebsite\n\nFacebook\n\nHope Revival Organization (HRO)\n\nWebsite\nFacebook\n\nWebsite\n\nFacebook\n\nBabushka Adoption\n\nWebsite\nFacebook\n\nWebsite\n\nFacebook\n\nArdager\n\nAmel Association International (Amel)\n\nWebsite\nFacebook\n\nWebsite\n\nFacebook\n\nAlzheimer’s Association Lebanon (AAL)\n\nWebsite\nFacebook\n\nWebsite\n\nFacebook\n\nAlbanian Association of Geriatry and Gerontology (AAGG)\n\nWebsite\n\nWebsite\n\nYoung Power in Social Action (YPSA)\n\nWebsite\nFacebook\n\nWebsite\n\nFacebook\n\nYayasan Emong Lansia (YEL)\n\nVietnam Elderly Association\n\nWebsite\n\nWebsite\n\nSenior Citizen Chautari (SCC)\n\nWebsite\nFacebook\n\nWebsite\n\nFacebook\n\nResource Integration center RIC\n\nWebsite\nFacebook\n\nWebsite\n\nFacebook\n\nNepal Participatory Action Network (NEPAN)\n\nWebsite\nFacebook\n\nWebsite\n\nFacebook\n\nNational Senior Citizen Federation (NASCIF)\n\nWebsite\n\nWebsite\n\nNational Council of Senior Citizens Organisations Malaysia (NACSCOM)\n\nWebsite\nFacebook\n\nWebsite\n\nFacebook\n\nHelpAge Sri Lanka\n\nWebsite\nLinkedIn\n\nWebsite\n\nLinkedIn\n\nHelpAge Korea\n\nWebsite\nFacebook\n\nWebsite\n\nFacebook\n\nHelpAge India\n\nWebsite\nFacebook\n\nWebsite\n\nFacebook\n\nHelpAge Cambodia\n\nWebsite\nFacebook\n\nWebsite\n\nFacebook\n\nGramin Vikas Vigyan Samiti (GRAVIS)\n\nWebsite\nFacebook\n\nWebsite\n\nFacebook\n\nforOldy Project, Help without Frontiers Thailand Foundation (HWFT)\n\nWebsite\nFacebook\n\nWebsite\n\nFacebook\n\nFoundation for Older Persons’ Development (FOPDEV)\n\nWebsite\nFacebook\n\nWebsite\n\nFacebook\n\nCoalition of Services of the Elderly (COSE)\n\nWebsite\nFacebook\n\nWebsite\n\nFacebook\n\nChina National Committee on Ageing (CNCA)\n\nWebsite\n\nWebsite\n\nCentre for Human Rights and Development (CHRD)\n\nWebsite\n\nWebsite\n\nBangladesh Women’s Health Coalition (BWHC)\n\nWebsite\n\nWebsite\n\nAgeing Nepal\n\nWebsite\nX\n\nWebsite\n\nX\n\nUnivers de solidarité et de développement (UNI.SOL.D.)\n\nRegional Center for the Welfare of Aging Persons in Cameroon (RECEWAPEC)\n\nWebsite\n\nWebsite\n\nGrandmothers Consortium (GMC)\n\nWebsite\n\nWebsite\n\nVUKOXA – Associacao Humanitaria de Apoio a Velhice\n\nVoice of the Elderly\n\nUganda Reach the Aged Association (URAA)\n\nWebsite\n\nWebsite\n\nTesfa Social and Development Association\n\nWebsite\n\nWebsite\n\nTanzania Mission to the Poor and Disabled (PADI)\n\nWebsite\n\nWebsite\n\nSupport To Older People-Zambia (STOP-Zambia)\n\nWebsite\n\nWebsite\n\nSenior Citizens Association of Zambia (SCAZ)\n\nWebsite\n\nWebsite\n\nSaidia Wazee Karagwe (SAWAKA)\n\nWebsite\n\nWebsite\n\nReach One Touch One Ministries (ROTOM)\n\nWebsite\n\nWebsite\n\nRelief to Development Society (REDESO)\n\nWebsite\n\nWebsite\n\nReach A Hand Uganda (RAHU)\n\nWebsite\n\nWebsite\n\nPalliative Care Association of Uganda (PCAU)\n\nWebsite\n\nWebsite\n\nNSINDAGIZA Organization\n\nWebsite\n\nWebsite\n\nMuthande\n\nWebsite\n\nWebsite\n\nMangu Integrated Community Project (MICOP Kenya)\n\nFacebook\n\nFacebook\n\nMauritius Family Planning and Welfare Association (MFPWA)\n\nWebsite\n\nWebsite\n\nMalawi Network of Older Persons’ Organisations (MANEPO)\n\nWebsite\n\nWebsite\n\nKulmiye Pastoral Association (DPA)\n\nWebsite\n\nWebsite\n\nKibera Day Care Centre for the Elderly (KDCCE)\n\nWebsite\n\nWebsite\n\nKenya Society for People with AIDS (KESPA)\n\nKenyan Aged People Require Information, Knowledge & Advancement (KARIKA)\n\nWebsite\n\nWebsite\n\nHorn International Relief & Development Organization (HIRDO)\n\nWebsite\n\nWebsite\n\nHelpAge Kenya (H.A.K.)\n\nFacebook\n\nFacebook\n\nHealth Nest Uganda (HENU)\n\nFacebook\n\nFacebook\n\nHumanitarian and Development Consortium (HDC)\n\nWebsite\n\nWebsite\n\nFantsuam Foundation\n\nWebsite\n\nWebsite\n\nDroits Humains Ocean Indien (Dis-Moi)\n\nWebsite\n\nWebsite\n\nCoalition of Societies for the Rights of Older Persons in Nigeria (COSROPIN)\n\nWebsite\n\nWebsite\n\nCommunity Based Rehabilitation Alliance (COMBRA)\n\nWebsite\n\nWebsite\n\nCenter for Community Advancement and Family Empowerment (CECAFE)\n\nAcção para o Desenvolvimento Comunitarios or Association for Community Development Action in Sofala (ASADEC)\n\nAlmanar Voluntary Organization (AMVO)\n\nWebsite\nFacebook\n\nWebsite\n\nFacebook\n\nAfrica Development Aid (ADA)\n\nWebsite\n\nWebsite\n\nAgeing Concern Foundation (ACF)\n\nWebsite\n\nWebsite\n\nACAMAGE\n\nFacebook\n\nFacebook\n\nJoin the HelpAge global network\n\nBe part of a global movement changing the world for older people\n\nJoin us\n\nJoin the HelpAge global network\n\nBe part of a global movement changing the world for older people\n\nJoin us\n\nJoin the HelpAge global network\n\nBe part of a global movement changing the world for older people\n\nJoin us\n\nBe part of a global movement changing the world for older people\n\nBe part of a global movement changing the world for older people\n\nSubscribe to our newsletter\n\n\n\n\n SIGN UP HERE \n\nX\n\nSubscribe to our newsletter\n\n\n\n\n SIGN UP HERE \n\nX\n\nSubscribe to our newsletter\n\nSubscribe to our newsletter\n\nSIGN UP HERE",
  "date": "",
  "source_type": "other",
  "extracted_at": "2025-04-07T14:30:21.537718",
  "metadata": {
    "description": "Join the HelpAge global network to be part of a worldwide alliance of organisations working together to improve the dignity, wellbeing and voice of older people",
    "og:type": "website",
    "og:site_name": "HelpAge International"
  },
  "relevance_score": 0.5821428571428572,
  "summary": "Website\nFacebook\n\n\nConsejo Distrital de Sabios\n\n\n\nCADENA (Comité de Ayuda a Desastres y Emergencias Nacionales)\n\nWebsite\nFacebook\n\n\nAVU Innovación\n\nWebsite\nFacebook\n\n\nAsociacion Uruguaya de Animadores y Auxiliares Gerontologicos (AUDAAG)\n\nFacebook\n\n\nAsociación Central de Funcionarios Públicos y Docentes Jubilados del Paraguay\n\nFacebook\n\n\nAsociación Mutual de Protección Familiar (AMPF)\n\nWebsite\nFacebook\n\n\nAsociación Mutual Israelita Argentina (AMIA)\n\nWebsite\nFacebook\n\n\nAsociación Alianza de Salvadoreños Retornados (ALSARE)\n\nFacebook\n\n\nAsociación Gerontológica Costarricense (AGECO)\n\nWebsite\nFacebook\n\n\nFundación Acción Familiar Alzheimer Colombia (AFACOL)\n\nWebsite\nFacebook\n\n\nAsociacion Cultural Casa Del Nino (ACCN)\n\nWebsite\nFacebook\n\n\nThe Union for Senior Services – VALLI\n\nWebsite\n\n\nPRO Global / Pensioners without Borders\n\nWebsite\nFacebook\n\n\nKwa Wazee\n\nWebsite\n\n\nHelpAge USA\n\nWebsite\nFacebook\n\n\nHelpAge España\n\nWebsite\nFacebook\n\n\nHelpAge Canada\n\nWebsite\nFacebook\n\n\nGlobale Seniorer\n\nWebsite\nFacebook\n\n\nDorcas Aid International\n\nWebsite\nFacebook\n\n\nCaritas Malta Foundation\n\nWebsite\nFacebook\n\n\nBeauty of Help Foundation\n\nWebsite\nFacebook\n\n\nAge International\n\nWebsite\nFacebook\n\n\nAge Action Ireland\n\nWebsite\nFacebook\n\n\nAARP\n\nWebsite\nFacebook\n\n\nYemen Family Care Association (YFCA)\n\nWebsite\nFacebook\n\n\nEl Wedad Society for Community Rehabilitation (WSCR)\n\nWebsite\nFacebook\n\n\nAUB University for Seniors\n\nWebsite\nFacebook\n\n\nTurbota pro Litnix v Ukraini (TLU)\n\nWebsite\nFacebook\n\n\nCharity Foundation Starenki\n\nWebsite\nFacebook\n\n\nSolidarity Is Global Institute (SIGI)\n\nWebsite\nFacebook\n\n\nSyrian Expatriates Medical Association (SEMA)\n\nWebsite\nFacebook\n\n\nRight to Protection\n\nWebsite\nFacebook\n\n\nRed Cross of Serbia (RCS)\n\nWebsite\nFacebook\n\n\nResource Center for Elderly (RCE)\n\nWebsite\nFacebook\n\n\nPalestinian Center For Communication and Development Strategies (PCCDS)\n\nWebsite\nFacebook\n\n\nMission Armenia\n\nWebsite\nFacebook\n\n\nLife Makers Meeting Place Organisation (LMMPO)\n\nWebsite\nFacebook\n\n\nJuzoor for Health and Social Development\n\nWebsite\nFacebook\n\n\nJiyan Foundation for Human Rights\n\nWebsite\nFacebook\n\n\nHope Revival Organization (HRO)\n\nWebsite\nFacebook\n\n\nBabushka Adoption\n\nWebsite\nFacebook\n\n\nArdager\n\n\n\nAmel Association International (Amel)\n\nWebsite\nFacebook\n\n\nAlzheimer’s Association Lebanon (AAL)\n\nWebsite\nFacebook\n\n\nAlbanian Association of Geriatry and Gerontology (AAGG)\n\nWebsite\n\n\nYoung Power in Social Action (YPSA)\n\nWebsite\nFacebook\n\n\nYayasan Emong Lansia (YEL)\n\n\n\nVietnam Elderly Association\n\nWebsite\n\n\nSenior Citizen Chautari (SCC)\n\nWebsite\nFacebook\n\n\nResource Integration center RIC\n\nWebsite\nFacebook\n\n\nNepal Participatory Action Network (NEPAN)\n\nWebsite\nFacebook\n\n\nNational Senior Citizen Federation (NASCIF)\n\nWebsite\n\n\nNational Council of Senior Citizens Organisations Malaysia (NACSCOM)\n\nWebsite\nFacebook\n\n\nHelpAge Sri Lanka\n\nWebsite\nLinkedIn\n\n\nHelpAge Korea\n\nWebsite\nFacebook\n\n\nHelpAge India\n\nWebsite\nFacebook\n\n\nHelpAge Cambodia\n\nWebsite\nFacebook\n\n\nGramin Vikas Vigyan Samiti (GRAVIS)\n\nWebsite\nFacebook\n\n\nforOldy Project, Help without Frontiers Thailand Foundation (HWFT)\n\nWebsite\nFacebook\n\n\nFoundation for Older Persons’ Development (FOPDEV)\n\nWebsite\nFacebook\n\n\nCoalition of Services of the Elderly (COSE)\n\nWebsite\nFacebook\n\n\nChina National Committee on Ageing (CNCA)\n\nWebsite\n\n\nCentre for Human Rights and Development (CHRD)\n\nWebsite\n\n\nBangladesh Women’s Health Coalition (BWHC)\n\nWebsite\n\n\nAgeing Nepal\n\nWebsite\nX\n\n\nUnivers de solidarité et de développement (UNI.SOL.D.)\n\n\n\nRegional Center for the Welfare of Aging Persons in Cameroon (RECEWAPEC)\n\nWebsite\n\n\nGrandmothers Consortium (GMC)\n\nWebsite\n\n\nVUKOXA – Associacao Humanitaria de Apoio a Velhice\n\n\n\nVoice of the Elderly\n\n\n\nUganda Reach the Aged Association (URAA)\n\nWebsite\n\n\nTesfa Social and Development Association\n\nWebsite\n\n\nTanzania Mission to the Poor and Disabled (PADI)\n\nWebsite\n\n\nSupport To Older People-Zambia (STOP-Zambia)\n\nWebsite\n\n\nSenior Citizens Association of Zambia (SCAZ)\n\nWebsite\n\n\nSaidia Wazee Karagwe (SAWAKA)\n\nWebsite\n\n\nReach One Touch One Ministries (ROTOM)\n\nWebsite\n\n\nRelief to Development Society (REDESO)\n\nWebsite\n\n\nReach A Hand Uganda (RAHU)\n\nWebsite\n\n\nPalliative Care Association of Uganda (PCAU)\n\nWebsite\n\n\nNSINDAGIZA Organization\n\nWebsite\n\n\nMuthande\n\nWebsite\n\n\nMangu Integrated Community Project (MICOP Kenya)\n\nFacebook\n\n\nMauritius Family Planning and Welfare Association (MFPWA)\n\nWebsite\n\n\nMalawi Network of Older Persons’ Organisations (MANEPO)\n\nWebsite\n\n\nKulmiye Pastoral Association (DPA)\n\nWebsite\n\n\nKibera Day Care Centre for the Elderly (KDCCE)\n\nWebsite\n\n\nKenya Society for People with AIDS (KESPA)\n\n\n\nKenyan Aged People Require Information, Knowledge & Advancement (KARIKA)\n\nWebsite\n\n\nHorn International Relief & Development Organization (HIRDO)\n\nWebsite\n\n\nHelpAge Kenya (H.A.K.)\n\nFacebook\n\n\nHealth Nest Uganda (HENU)\n\nFacebook\n\n\nHumanitarian and Development Consortium (HDC)\n\nWebsite\n\n\nFantsuam Foundation\n\nWebsite\n\n\nDroits Humains Ocean Indien (Dis-Moi)\n\nWebsite\n\n\nCoalition of Societies for the Rights of Older Persons in Nigeria (COSROPIN)\n\nWebsite\n\n\nCommunity Based Rehabilitation Alliance (COMBRA)\n\nWebsite\n\n\nCenter for Community Advancement and Family Empowerment (CECAFE)\n\n\n\nAcção para o Desenvolvimento Comunitarios or Association for Community Development Action in Sofala (ASADEC)\n\n\n\nAlmanar Voluntary Organization (AMVO)\n\nWebsite\nFacebook\n\n\nAfrica Development Aid (ADA)\n\nWebsite\n\n\nAgeing Concern Foundation (ACF)\n\nWebsite\n\n\nACAMAGE\n\nFacebook\n\n\n\n\n\n\n\n\n\n\n\n\n\n\n\n\n\n\n\n\n\n\n\n\n\n\n\n\n\n\n\n\n\n\n\n\n\n\n\n\n\n\n\n\n\n\n\n\n\n\n\n\n\n\n\n\n\n\n\n\n\n\n\n\n\n\n\n\n\n\n\n\n\n\n\n\n\n\n\n\n\n\n\n\n\n\n\n\n\n\nJoin the HelpAge global network\n\nBe part of a global movement changing the world for older people\n\nJoin us\n\nGlobal network\n\nGlobal network\n\nShare \n\n\n\n (opens in a new window)\n\n\n\n\n\n (opens in a new window)\n\n\n\n\n\n (opens in a new window)\n\n\n\n\n\n (opens in a new window)\n\n\n\n\n\n Copy\n\nAGE Myanmar\n\nWebsite\nLinkedIn\n\n\nKing Hussain Foundation / Institute for Family Health (KHF/iFH)\n\nWebsite\n\n\nAgeing with a Smile Initiative\n\nFacebook\n\n\nSIDOM Foundation\n\nWebsite\n\n\nFederal University of Santa Catarina (UFSC)\n\nWebsite\nFacebook\n\n\nSurcos AC\n\nWebsite\nFacebook\n\n\nServicio Social de Iglesias Dominicanas (SSID)\n\nWebsite\nFacebook\n\n\nSociedad Argentina de Gerontología y Geriatría (SAGG)\n\nWebsite\nFacebook\n\n\nSt. Website\nFacebook\n\n\nConsejo Distrital de Sabios\n\n\n\nCADENA (Comité de Ayuda a Desastres y Emergencias Nacionales)\n\nWebsite\nFacebook\n\n\nAVU Innovación\n\nWebsite\nFacebook\n\n\nAsociacion Uruguaya de Animadores y Auxiliares Gerontologicos (AUDAAG)\n\nFacebook\n\n\nAsociación Central de Funcionarios Públicos y Docentes Jubilados del Paraguay\n\nFacebook\n\n\nAsociación Mutual de Protección Familiar (AMPF)\n\nWebsite\nFacebook\n\n\nAsociación Mutual Israelita Argentina (AMIA)\n\nWebsite\nFacebook\n\n\nAsociación Alianza de Salvadoreños Retornados (ALSARE)\n\nFacebook\n\n\nAsociación Gerontológica Costarricense (AGECO)\n\nWebsite\nFacebook\n\n\nFundación Acción Familiar Alzheimer Colombia (AFACOL)\n\nWebsite\nFacebook\n\n\nAsociacion Cultural Casa Del Nino (ACCN)\n\nWebsite\nFacebook\n\n\nThe Union for Senior Services – VALLI\n\nWebsite\n\n\nPRO Global / Pensioners without Borders\n\nWebsite\nFacebook\n\n\nKwa Wazee\n\nWebsite\n\n\nHelpAge USA\n\nWebsite\nFacebook\n\n\nHelpAge España\n\nWebsite\nFacebook\n\n\nHelpAge Canada\n\nWebsite\nFacebook\n\n\nGlobale Seniorer\n\nWebsite\nFacebook\n\n\nDorcas Aid International\n\nWebsite\nFacebook\n\n\nCaritas Malta Foundation\n\nWebsite\nFacebook\n\n\nBeauty of Help Foundation\n\nWebsite\nFacebook\n\n\nAge International\n\nWebsite\nFacebook\n\n\nAge Action Ireland\n\nWebsite\nFacebook\n\n\nAARP\n\nWebsite\nFacebook\n\n\nYemen Family Care Association (YFCA)\n\nWebsite\nFacebook\n\n\nEl Wedad Society for Community Rehabilitation (WSCR)\n\nWebsite\nFacebook\n\n\nAUB University for Seniors\n\nWebsite\nFacebook\n\n\nTurbota pro Litnix v Ukraini (TLU)\n\nWebsite\nFacebook\n\n\nCharity Foundation Starenki\n\nWebsite\nFacebook\n\n\nSolidarity Is Global Institute (SIGI)\n\nWebsite\nFacebook\n\n\nSyrian Expatriates Medical Association (SEMA)\n\nWebsite\nFacebook\n\n\nRight to Protection\n\nWebsite\nFacebook\n\n\nRed Cross of Serbia (RCS)\n\nWebsite\nFacebook\n\n\nResource Center for Elderly (RCE)\n\nWebsite\nFacebook\n\n\nPalestinian Center For Communication and Development Strategies (PCCDS)\n\nWebsite\nFacebook\n\n\nMission Armenia\n\nWebsite\nFacebook\n\n\nLife Makers Meeting Place Organisation (LMMPO)\n\nWebsite\nFacebook\n\n\nJuzoor for Health and Social Development\n\nWebsite\nFacebook\n\n\nJiyan Foundation for Human Rights\n\nWebsite\nFacebook\n\n\nHope Revival Organization (HRO)\n\nWebsite\nFacebook\n\n\nBabushka Adoption\n\nWebsite\nFacebook\n\n\nArdager\n\n\n\nAmel Association International (Amel)\n\nWebsite\nFacebook\n\n\nAlzheimer’s Association Lebanon (AAL)\n\nWebsite\nFacebook\n\n\nAlbanian Association of Geriatry and Gerontology (AAGG)\n\nWebsite\n\n\nYoung Power in Social Action (YPSA)\n\nWebsite\nFacebook\n\n\nYayasan Emong Lansia (YEL)\n\n\n\nVietnam Elderly Association\n\nWebsite\n\n\nSenior Citizen Chautari (SCC)\n\nWebsite\nFacebook\n\n\nResource Integration center RIC\n\nWebsite\nFacebook\n\n\nNepal Participatory Action Network (NEPAN)\n\nWebsite\nFacebook\n\n\nNational Senior Citizen Federation (NASCIF)\n\nWebsite\n\n\nNational Council of Senior Citizens Organisations Malaysia (NACSCOM)\n\nWebsite\nFacebook\n\n\nHelpAge Sri Lanka\n\nWebsite\nLinkedIn\n\n\nHelpAge Korea\n\nWebsite\nFacebook\n\n\nHelpAge India\n\nWebsite\nFacebook\n\n\nHelpAge Cambodia\n\nWebsite\nFacebook\n\n\nGramin Vikas Vigyan Samiti (GRAVIS)\n\nWebsite\nFacebook\n\n\nforOldy Project, Help without Frontiers Thailand Foundation (HWFT)\n\nWebsite\nFacebook\n\n\nFoundation for Older Persons’ Development (FOPDEV)\n\nWebsite\nFacebook\n\n\nCoalition of Services of the Elderly (COSE)\n\nWebsite\nFacebook\n\n\nChina National Committee on Ageing (CNCA)\n\nWebsite\n\n\nCentre for Human Rights and Development (CHRD)\n\nWebsite\n\n\nBangladesh Women’s Health Coalition (BWHC)\n\nWebsite\n\n\nAgeing Nepal\n\nWebsite\nX\n\n\nUnivers de solidarité et de développement (UNI.SOL.D.)\n\n\n\nRegional Center for the Welfare of Aging Persons in Cameroon (RECEWAPEC)\n\nWebsite\n\n\nGrandmothers Consortium (GMC)\n\nWebsite\n\n\nVUKOXA – Associacao Humanitaria de Apoio a Velhice\n\n\n\nVoice of the Elderly\n\n\n\nUganda Reach the Aged Association (URAA)\n\nWebsite\n\n\nTesfa Social and Development Association\n\nWebsite\n\n\nTanzania Mission to the Poor and Disabled (PADI)\n\nWebsite\n\n\nSupport To Older People-Zambia (STOP-Zambia)\n\nWebsite\n\n\nSenior Citizens Association of Zambia (SCAZ)\n\nWebsite\n\n\nSaidia Wazee Karagwe (SAWAKA)\n\nWebsite\n\n\nReach One Touch One Ministries (ROTOM)\n\nWebsite\n\n\nRelief to Development Society (REDESO)\n\nWebsite\n\n\nReach A Hand Uganda (RAHU)\n\nWebsite\n\n\nPalliative Care Association of Uganda (PCAU)\n\nWebsite\n\n\nNSINDAGIZA Organization\n\nWebsite\n\n\nMuthande\n\nWebsite\n\n\nMangu Integrated Community Project (MICOP Kenya)\n\nFacebook\n\n\nMauritius Family Planning and Welfare Association (MFPWA)\n\nWebsite\n\n\nMalawi Network of Older Persons’ Organisations (MANEPO)\n\nWebsite\n\n\nKulmiye Pastoral Association (DPA)\n\nWebsite\n\n\nKibera Day Care Centre for the Elderly (KDCCE)\n\nWebsite\n\n\nKenya Society for People with AIDS (KESPA)\n\n\n\nKenyan Aged People Require Information, Knowledge & Advancement (KARIKA)\n\nWebsite\n\n\nHorn International Relief & Development Organization (HIRDO)\n\nWebsite\n\n\nHelpAge Kenya (H.A.K.)\n\nFacebook\n\n\nHealth Nest Uganda (HENU)\n\nFacebook\n\n\nHumanitarian and Development Consortium (HDC)\n\nWebsite\n\n\nFantsuam Foundation\n\nWebsite\n\n\nDroits Humains Ocean Indien (Dis-Moi)\n\nWebsite\n\n\nCoalition of Societies for the Rights of Older Persons in Nigeria (COSROPIN)\n\nWebsite\n\n\nCommunity Based Rehabilitation Alliance (COMBRA)\n\nWebsite\n\n\nCenter for Community Advancement and Family Empowerment (CECAFE)\n\n\n\nAcção para o Desenvolvimento Comunitarios or Association for Community Development Action in Sofala (ASADEC)\n\n\n\nAlmanar Voluntary Organization (AMVO)\n\nWebsite\nFacebook\n\n\nAfrica Development Aid (ADA)\n\nWebsite\n\n\nAgeing Concern Foundation (ACF)\n\nWebsite\n\n\nACAMAGE\n\nFacebook\n\nAGE Myanmar\n\nWebsite\nLinkedIn\n\n\nKing Hussain Foundation / Institute for Family Health (KHF/iFH)\n\nWebsite\n\n\nAgeing with a Smile Initiative\n\nFacebook\n\n\nSIDOM Foundation\n\nWebsite\n\n\nFederal University of Santa Catarina (UFSC)\n\nWebsite\nFacebook\n\n\nSurcos AC\n\nWebsite\nFacebook\n\n\nServicio Social de Iglesias Dominicanas (SSID)\n\nWebsite\nFacebook\n\n\nSociedad Argentina de Gerontología y Geriatría (SAGG)\n\nWebsite\nFacebook\n\n\nSt. Website\nFacebook\n\n\nConsejo Distrital de Sabios\n\n\n\nCADENA (Comité de Ayuda a Desastres y Emergencias Nacionales)\n\nWebsite\nFacebook\n\n\nAVU Innovación\n\nWebsite\nFacebook\n\n\nAsociacion Uruguaya de Animadores y Auxiliares Gerontologicos (AUDAAG)\n\nFacebook\n\n\nAsociación Central de Funcionarios Públicos y Docentes Jubilados del Paraguay\n\nFacebook\n\n\nAsociación Mutual de Protección Familiar (AMPF)\n\nWebsite\nFacebook\n\n\nAsociación Mutual Israelita Argentina (AMIA)\n\nWebsite\nFacebook\n\n\nAsociación Alianza de Salvadoreños Retornados (ALSARE)\n\nFacebook\n\n\nAsociación Gerontológica Costarricense (AGECO)\n\nWebsite\nFacebook\n\n\nFundación Acción Familiar Alzheimer Colombia (AFACOL)\n\nWebsite\nFacebook\n\n\nAsociacion Cultural Casa Del Nino (ACCN)\n\nWebsite\nFacebook\n\n\nThe Union for Senior Services – VALLI\n\nWebsite\n\n\nPRO Global / Pensioners without Borders\n\nWebsite\nFacebook\n\n\nKwa Wazee\n\nWebsite\n\n\nHelpAge USA\n\nWebsite\nFacebook\n\n\nHelpAge España\n\nWebsite\nFacebook\n\n\nHelpAge Canada\n\nWebsite\nFacebook\n\n\nGlobale Seniorer\n\nWebsite\nFacebook\n\n\nDorcas Aid International\n\nWebsite\nFacebook\n\n\nCaritas Malta Foundation\n\nWebsite\nFacebook\n\n\nBeauty of Help Foundation\n\nWebsite\nFacebook\n\n\nAge International\n\nWebsite\nFacebook\n\n\nAge Action Ireland\n\nWebsite\nFacebook\n\n\nAARP\n\nWebsite\nFacebook\n\n\nYemen Family Care Association (YFCA)\n\nWebsite\nFacebook\n\n\nEl Wedad Society for Community Rehabilitation (WSCR)\n\nWebsite\nFacebook\n\n\nAUB University for Seniors\n\nWebsite\nFacebook\n\n\nTurbota pro Litnix v Ukraini (TLU)\n\nWebsite\nFacebook\n\n\nCharity Foundation Starenki\n\nWebsite\nFacebook\n\n\nSolidarity Is Global Institute (SIGI)\n\nWebsite\nFacebook\n\n\nSyrian Expatriates Medical Association (SEMA)\n\nWebsite\nFacebook\n\n\nRight to Protection\n\nWebsite\nFacebook\n\n\nRed Cross of Serbia (RCS)\n\nWebsite\nFacebook\n\n\nResource Center for Elderly (RCE)\n\nWebsite\nFacebook\n\n\nPalestinian Center For Communication and Development Strategies (PCCDS)\n\nWebsite\nFacebook\n\n\nMission Armenia\n\nWebsite\nFacebook\n\n\nLife Makers Meeting Place Organisation (LMMPO)\n\nWebsite\nFacebook\n\n\nJuzoor for Health and Social Development\n\nWebsite\nFacebook\n\n\nJiyan Foundation for Human Rights\n\nWebsite\nFacebook\n\n\nHope Revival Organization (HRO)\n\nWebsite\nFacebook\n\n\nBabushka Adoption\n\nWebsite\nFacebook\n\n\nArdager\n\n\n\nAmel Association International (Amel)\n\nWebsite\nFacebook\n\n\nAlzheimer’s Association Lebanon (AAL)\n\nWebsite\nFacebook\n\n\nAlbanian Association of Geriatry and Gerontology (AAGG)\n\nWebsite\n\n\nYoung Power in Social Action (YPSA)\n\nWebsite\nFacebook\n\n\nYayasan Emong Lansia (YEL)\n\n\n\nVietnam Elderly Association\n\nWebsite\n\n\nSenior Citizen Chautari (SCC)\n\nWebsite\nFacebook\n\n\nResource Integration center RIC\n\nWebsite\nFacebook\n\n\nNepal Participatory Action Network (NEPAN)\n\nWebsite\nFacebook\n\n\nNational Senior Citizen Federation (NASCIF)\n\nWebsite\n\n\nNational Council of Senior Citizens Organisations Malaysia (NACSCOM)\n\nWebsite\nFacebook\n\n\nHelpAge Sri Lanka\n\nWebsite\nLinkedIn\n\n\nHelpAge Korea\n\nWebsite\nFacebook\n\n\nHelpAge India\n\nWebsite\nFacebook\n\n\nHelpAge Cambodia\n\nWebsite\nFacebook\n\n\nGramin Vikas Vigyan Samiti (GRAVIS)\n\nWebsite\nFacebook\n\n\nforOldy Project, Help without Frontiers Thailand Foundation (HWFT)\n\nWebsite\nFacebook\n\n\nFoundation for Older Persons’ Development (FOPDEV)\n\nWebsite\nFacebook\n\n\nCoalition of Services of the Elderly (COSE)\n\nWebsite\nFacebook\n\n\nChina National Committee on Ageing (CNCA)\n\nWebsite\n\n\nCentre for Human Rights and Development (CHRD)\n\nWebsite\n\n\nBangladesh Women’s Health Coalition (BWHC)\n\nWebsite\n\n\nAgeing Nepal\n\nWebsite\nX\n\n\nUnivers de solidarité et de développement (UNI.SOL.D.)\n\n\n\nRegional Center for the Welfare of Aging Persons in Cameroon (RECEWAPEC)\n\nWebsite\n\n\nGrandmothers Consortium (GMC)\n\nWebsite\n\n\nVUKOXA – Associacao Humanitaria de Apoio a Velhice\n\n\n\nVoice of the Elderly\n\n\n\nUganda Reach the Aged Association (URAA)\n\nWebsite\n\n\nTesfa Social and Development Association\n\nWebsite\n\n\nTanzania Mission to the Poor and Disabled (PADI)\n\nWebsite\n\n\nSupport To Older People-Zambia (STOP-Zambia)\n\nWebsite\n\n\nSenior Citizens Association of Zambia (SCAZ)\n\nWebsite\n\n\nSaidia Wazee Karagwe (SAWAKA)\n\nWebsite\n\n\nReach One Touch One Ministries (ROTOM)\n\nWebsite\n\n\nRelief to Development Society (REDESO)\n\nWebsite\n\n\nReach A Hand Uganda (RAHU)\n\nWebsite\n\n\nPalliative Care Association of Uganda (PCAU)\n\nWebsite\n\n\nNSINDAGIZA Organization\n\nWebsite\n\n\nMuthande\n\nWebsite\n\n\nMangu Integrated Community Project (MICOP Kenya)\n\nFacebook\n\n\nMauritius Family Planning and Welfare Association (MFPWA)\n\nWebsite\n\n\nMalawi Network of Older Persons’ Organisations (MANEPO)\n\nWebsite\n\n\nKulmiye Pastoral Association (DPA)\n\nWebsite\n\n\nKibera Day Care Centre for the Elderly (KDCCE)\n\nWebsite\n\n\nKenya Society for People with AIDS (KESPA)\n\n\n\nKenyan Aged People Require Information, Knowledge & Advancement (KARIKA)\n\nWebsite\n\n\nHorn International Relief & Development Organization (HIRDO)\n\nWebsite\n\n\nHelpAge Kenya (H.A.K.)\n\nFacebook\n\n\nHealth Nest Uganda (HENU)\n\nFacebook\n\n\nHumanitarian and Development Consortium (HDC)\n\nWebsite\n\n\nFantsuam Foundation\n\nWebsite\n\n\nDroits Humains Ocean Indien (Dis-Moi)\n\nWebsite\n\n\nCoalition of Societies for the Rights of Older Persons in Nigeria (COSROPIN)\n\nWebsite\n\n\nCommunity Based Rehabilitation Alliance (COMBRA)\n\nWebsite\n\n\nCenter for Community Advancement and Family Empowerment (CECAFE)\n\n\n\nAcção para o Desenvolvimento Comunitarios or Association for Community Development Action in Sofala (ASADEC)\n\n\n\nAlmanar Voluntary Organization (AMVO)\n\nWebsite\nFacebook\n\n\nAfrica Development Aid (ADA)\n\nWebsite\n\n\nAgeing Concern Foundation (ACF)\n\nWebsite\n\n\nACAMAGE\n\nFacebook\n\nAGE Myanmar\n\nWebsite\nLinkedIn\n\n\nKing Hussain Foundation / Institute for Family Health (KHF/iFH)\n\nWebsite\n\n\nAgeing with a Smile Initiative\n\nFacebook\n\n\nSIDOM Foundation\n\nWebsite\n\n\nFederal University of Santa Catarina (UFSC)\n\nWebsite\nFacebook\n\n\nSurcos AC\n\nWebsite\nFacebook\n\n\nServicio Social de Iglesias Dominicanas (SSID)\n\nWebsite\nFacebook\n\n\nSociedad Argentina de Gerontología y Geriatría (SAGG)\n\nWebsite\nFacebook\n\n\nSt. Website\nFacebook\n\n\nConsejo Distrital de Sabios\n\n\n\nCADENA (Comité de Ayuda a Desastres y Emergencias Nacionales)\n\nWebsite\nFacebook\n\n\nAVU Innovación\n\nWebsite\nFacebook\n\n\nAsociacion Uruguaya de Animadores y Auxiliares Gerontologicos (AUDAAG)\n\nFacebook\n\n\nAsociación Central de Funcionarios Públicos y Docentes Jubilados del Paraguay\n\nFacebook\n\n\nAsociación Mutual de Protección Familiar (AMPF)\n\nWebsite\nFacebook\n\n\nAsociación Mutual Israelita Argentina (AMIA)\n\nWebsite\nFacebook\n\n\nAsociación Alianza de Salvadoreños Retornados (ALSARE)\n\nFacebook\n\n\nAsociación Gerontológica Costarricense (AGECO)\n\nWebsite\nFacebook\n\n\nFundación Acción Familiar Alzheimer Colombia (AFACOL)\n\nWebsite\nFacebook\n\n\nAsociacion Cultural Casa Del Nino (ACCN)\n\nWebsite\nFacebook\n\n\nThe Union for Senior Services – VALLI\n\nWebsite\n\n\nPRO Global / Pensioners without Borders\n\nWebsite\nFacebook\n\n\nKwa Wazee\n\nWebsite\n\n\nHelpAge USA\n\nWebsite\nFacebook\n\n\nHelpAge España\n\nWebsite\nFacebook\n\n\nHelpAge Canada\n\nWebsite\nFacebook\n\n\nGlobale Seniorer\n\nWebsite\nFacebook\n\n\nDorcas Aid International\n\nWebsite\nFacebook\n\n\nCaritas Malta Foundation\n\nWebsite\nFacebook\n\n\nBeauty of Help Foundation\n\nWebsite\nFacebook\n\n\nAge International\n\nWebsite\nFacebook\n\n\nAge Action Ireland\n\nWebsite\nFacebook\n\n\nAARP\n\nWebsite\nFacebook\n\n\nYemen Family Care Association (YFCA)\n\nWebsite\nFacebook\n\n\nEl Wedad Society for Community Rehabilitation (WSCR)\n\nWebsite\nFacebook\n\n\nAUB University for Seniors\n\nWebsite\nFacebook\n\n\nTurbota pro Litnix v Ukraini (TLU)\n\nWebsite\nFacebook\n\n\nCharity Foundation Starenki\n\nWebsite\nFacebook\n\n\nSolidarity Is Global Institute (SIGI)\n\nWebsite\nFacebook\n\n\nSyrian Expatriates Medical Association (SEMA)\n\nWebsite\nFacebook\n\n\nRight to Protection\n\nWebsite\nFacebook\n\n\nRed Cross of Serbia (RCS)\n\nWebsite\nFacebook\n\n\nResource Center for Elderly (RCE)\n\nWebsite\nFacebook\n\n\nPalestinian Center For Communication and Development Strategies (PCCDS)\n\nWebsite\nFacebook\n\n\nMission Armenia\n\nWebsite\nFacebook\n\n\nLife Makers Meeting Place Organisation (LMMPO)\n\nWebsite\nFacebook\n\n\nJuzoor for Health and Social Development\n\nWebsite\nFacebook\n\n\nJiyan Foundation for Human Rights\n\nWebsite\nFacebook\n\n\nHope Revival Organization (HRO)\n\nWebsite\nFacebook\n\n\nBabushka Adoption\n\nWebsite\nFacebook\n\n\nArdager\n\n\n\nAmel Association International (Amel)\n\nWebsite\nFacebook\n\n\nAlzheimer’s Association Lebanon (AAL)\n\nWebsite\nFacebook\n\n\nAlbanian Association of Geriatry and Gerontology (AAGG)\n\nWebsite\n\n\nYoung Power in Social Action (YPSA)\n\nWebsite\nFacebook\n\n\nYayasan Emong Lansia (YEL)\n\n\n\nVietnam Elderly Association\n\nWebsite\n\n\nSenior Citizen Chautari (SCC)\n\nWebsite\nFacebook\n\n\nResource Integration center RIC\n\nWebsite\nFacebook\n\n\nNepal Participatory Action Network (NEPAN)\n\nWebsite\nFacebook\n\n\nNational Senior Citizen Federation (NASCIF)\n\nWebsite\n\n\nNational Council of Senior Citizens Organisations Malaysia (NACSCOM)\n\nWebsite\nFacebook\n\n\nHelpAge Sri Lanka\n\nWebsite\nLinkedIn\n\n\nHelpAge Korea\n\nWebsite\nFacebook\n\n\nHelpAge India\n\nWebsite\nFacebook\n\n\nHelpAge Cambodia\n\nWebsite\nFacebook\n\n\nGramin Vikas Vigyan Samiti (GRAVIS)\n\nWebsite\nFacebook\n\n\nforOldy Project, Help without Frontiers Thailand Foundation (HWFT)\n\nWebsite\nFacebook\n\n\nFoundation for Older Persons’ Development (FOPDEV)\n\nWebsite\nFacebook\n\n\nCoalition of Services of the Elderly (COSE)\n\nWebsite\nFacebook\n\n\nChina National Committee on Ageing (CNCA)\n\nWebsite\n\n\nCentre for Human Rights and Development (CHRD)\n\nWebsite\n\n\nBangladesh Women’s Health Coalition (BWHC)\n\nWebsite\n\n\nAgeing Nepal\n\nWebsite\nX\n\n\nUnivers de solidarité et de développement (UNI.SOL.D.)\n\n\n\nRegional Center for the Welfare of Aging Persons in Cameroon (RECEWAPEC)\n\nWebsite\n\n\nGrandmothers Consortium (GMC)\n\nWebsite\n\n\nVUKOXA – Associacao Humanitaria de Apoio a Velhice\n\n\n\nVoice of the Elderly\n\n\n\nUganda Reach the Aged Association (URAA)\n\nWebsite\n\n\nTesfa Social and Development Association\n\nWebsite\n\n\nTanzania Mission to the Poor and Disabled (PADI)\n\nWebsite\n\n\nSupport To Older People-Zambia (STOP-Zambia)\n\nWebsite\n\n\nSenior Citizens Association of Zambia (SCAZ)\n\nWebsite\n\n\nSaidia Wazee Karagwe (SAWAKA)\n\nWebsite\n\n\nReach One Touch One Ministries (ROTOM)\n\nWebsite\n\n\nRelief to Development Society (REDESO)\n\nWebsite\n\n\nReach A Hand Uganda (RAHU)\n\nWebsite\n\n\nPalliative Care Association of Uganda (PCAU)\n\nWebsite\n\n\nNSINDAGIZA Organization\n\nWebsite\n\n\nMuthande\n\nWebsite\n\n\nMangu Integrated Community Project (MICOP Kenya)\n\nFacebook\n\n\nMauritius Family Planning and Welfare Association (MFPWA)\n\nWebsite\n\n\nMalawi Network of Older Persons’ Organisations (MANEPO)\n\nWebsite\n\n\nKulmiye Pastoral Association (DPA)\n\nWebsite\n\n\nKibera Day Care Centre for the Elderly (KDCCE)\n\nWebsite\n\n\nKenya Society for People with AIDS (KESPA)\n\n\n\nKenyan Aged People Require Information, Knowledge & Advancement (KARIKA)\n\nWebsite\n\n\nHorn International Relief & Development Organization (HIRDO)\n\nWebsite\n\n\nHelpAge Kenya (H.A.K.)\n\nFacebook\n\n\nHealth Nest Uganda (HENU)\n\nFacebook\n\n\nHumanitarian and Development Consortium (HDC)\n\nWebsite\n\n\nFantsuam Foundation\n\nWebsite\n\n\nDroits Humains Ocean Indien (Dis-Moi)\n\nWebsite\n\n\nCoalition of Societies for the Rights of Older Persons in Nigeria (COSROPIN)\n\nWebsite\n\n\nCommunity Based Rehabilitation Alliance (COMBRA)\n\nWebsite\n\n\nCenter for Community Advancement and Family Empowerment (CECAFE)\n\n\n\nAcção para o Desenvolvimento Comunitarios or Association for Community Development Action in Sofala (ASADEC)\n\n\n\nAlmanar Voluntary Organization (AMVO)\n\nWebsite\nFacebook\n\n\nAfrica Development Aid (ADA)\n\nWebsite\n\n\nAgeing Concern Foundation (ACF)\n\nWebsite\n\n\nACAMAGE\n\nFacebook\n\nAGE Myanmar\n\nWebsite\nLinkedIn\n\nWebsite\n\nLinkedIn\n\nKing Hussain Foundation / Institute for Family Health (KHF/iFH)\n\nWebsite\n\nWebsite\n\nAgeing with a Smile Initiative\n\nFacebook\n\nFacebook\n\nSIDOM Foundation\n\nWebsite\n\nWebsite\n\nFederal University of Santa Catarina (UFSC)\n\nWebsite\nFacebook\n\nWebsite\n\nFacebook\n\nSurcos AC\n\nWebsite\nFacebook\n\nWebsite\n\nFacebook\n\nServicio Social de Iglesias Dominicanas (SSID)\n\nWebsite\nFacebook\n\nWebsite\n\nFacebook\n\nSociedad Argentina de Gerontología y Geriatría (SAGG)\n\nWebsite\nFacebook\n\nWebsite\n\nFacebook\n\nSt. Website\nFacebook\n\nWebsite\n\nFacebook\n\nConsejo Distrital de Sabios\n\nCADENA (Comité de Ayuda a Desastres y Emergencias Nacionales)\n\nWebsite\nFacebook\n\nWebsite\n\nFacebook\n\nAVU Innovación\n\nWebsite\nFacebook\n\nWebsite\n\nFacebook\n\nAsociacion Uruguaya de Animadores y Auxiliares Gerontologicos (AUDAAG)\n\nFacebook\n\nFacebook\n\nAsociación Central de Funcionarios Públicos y Docentes Jubilados del Paraguay\n\nFacebook\n\nFacebook\n\nAsociación Mutual de Protección Familiar (AMPF)\n\nWebsite\nFacebook\n\nWebsite\n\nFacebook\n\nAsociación Mutual Israelita Argentina (AMIA)\n\nWebsite\nFacebook\n\nWebsite\n\nFacebook\n\nAsociación Alianza de Salvadoreños Retornados (ALSARE)\n\nFacebook\n\nFacebook\n\nAsociación Gerontológica Costarricense (AGECO)\n\nWebsite\nFacebook\n\nWebsite\n\nFacebook\n\nFundación Acción Familiar Alzheimer Colombia (AFACOL)\n\nWebsite\nFacebook\n\nWebsite\n\nFacebook\n\nAsociacion Cultural Casa Del Nino (ACCN)\n\nWebsite\nFacebook\n\nWebsite\n\nFacebook\n\nThe Union for Senior Services – VALLI\n\nWebsite\n\nWebsite\n\nPRO Global / Pensioners without Borders\n\nWebsite\nFacebook\n\nWebsite\n\nFacebook\n\nKwa Wazee\n\nWebsite\n\nWebsite\n\nHelpAge USA\n\nWebsite\nFacebook\n\nWebsite\n\nFacebook\n\nHelpAge España\n\nWebsite\nFacebook\n\nWebsite\n\nFacebook\n\nHelpAge Canada\n\nWebsite\nFacebook\n\nWebsite\n\nFacebook\n\nGlobale Seniorer\n\nWebsite\nFacebook\n\nWebsite\n\nFacebook\n\nDorcas Aid International\n\nWebsite\nFacebook\n\nWebsite\n\nFacebook\n\nCaritas Malta Foundation\n\nWebsite\nFacebook\n\nWebsite\n\nFacebook\n\nBeauty of Help Foundation\n\nWebsite\nFacebook\n\nWebsite\n\nFacebook\n\nAge International\n\nWebsite\nFacebook\n\nWebsite\n\nFacebook\n\nAge Action Ireland\n\nWebsite\nFacebook\n\nWebsite\n\nFacebook\n\nAARP\n\nWebsite\nFacebook\n\nWebsite\n\nFacebook\n\nYemen Family Care Association (YFCA)\n\nWebsite\nFacebook\n\nWebsite\n\nFacebook\n\nEl Wedad Society for Community Rehabilitation (WSCR)\n\nWebsite\nFacebook\n\nWebsite\n\nFacebook\n\nAUB University for Seniors\n\nWebsite\nFacebook\n\nWebsite\n\nFacebook\n\nTurbota pro Litnix v Ukraini (TLU)\n\nWebsite\nFacebook\n\nWebsite\n\nFacebook\n\nCharity Foundation Starenki\n\nWebsite\nFacebook\n\nWebsite\n\nFacebook\n\nSolidarity Is Global Institute (SIGI)\n\nWebsite\nFacebook\n\nWebsite\n\nFacebook\n\nSyrian Expatriates Medical Association (SEMA)\n\nWebsite\nFacebook\n\nWebsite\n\nFacebook\n\nRight to Protection\n\nWebsite\nFacebook\n\nWebsite\n\nFacebook\n\nRed Cross of Serbia (RCS)\n\nWebsite\nFacebook\n\nWebsite\n\nFacebook\n\nResource Center for Elderly (RCE)\n\nWebsite\nFacebook\n\nWebsite\n\nFacebook\n\nPalestinian Center For Communication and Development Strategies (PCCDS)\n\nWebsite\nFacebook\n\nWebsite\n\nFacebook\n\nMission Armenia\n\nWebsite\nFacebook\n\nWebsite\n\nFacebook\n\nLife Makers Meeting Place Organisation (LMMPO)\n\nWebsite\nFacebook\n\nWebsite\n\nFacebook\n\nJuzoor for Health and Social Development\n\nWebsite\nFacebook\n\nWebsite\n\nFacebook\n\nJiyan Foundation for Human Rights\n\nWebsite\nFacebook\n\nWebsite\n\nFacebook\n\nHope Revival Organization (HRO)\n\nWebsite\nFacebook\n\nWebsite\n\nFacebook\n\nBabushka Adoption\n\nWebsite\nFacebook\n\nWebsite\n\nFacebook\n\nArdager\n\nAmel Association International (Amel)\n\nWebsite\nFacebook\n\nWebsite\n\nFacebook\n\nAlzheimer’s Association Lebanon (AAL)\n\nWebsite\nFacebook\n\nWebsite\n\nFacebook\n\nAlbanian Association of Geriatry and Gerontology (AAGG)\n\nWebsite\n\nWebsite\n\nYoung Power in Social Action (YPSA)\n\nWebsite\nFacebook\n\nWebsite\n\nFacebook\n\nYayasan Emong Lansia (YEL)\n\nVietnam Elderly Association\n\nWebsite\n\nWebsite\n\nSenior Citizen Chautari (SCC)\n\nWebsite\nFacebook\n\nWebsite\n\nFacebook\n\nResource Integration center RIC\n\nWebsite\nFacebook\n\nWebsite\n\nFacebook\n\nNepal Participatory Action Network (NEPAN)\n\nWebsite\nFacebook\n\nWebsite\n\nFacebook\n\nNational Senior Citizen Federation (NASCIF)\n\nWebsite\n\nWebsite\n\nNational Council of Senior Citizens Organisations Malaysia (NACSCOM)\n\nWebsite\nFacebook\n\nWebsite\n\nFacebook\n\nHelpAge Sri Lanka\n\nWebsite\nLinkedIn\n\nWebsite\n\nLinkedIn\n\nHelpAge Korea\n\nWebsite\nFacebook\n\nWebsite\n\nFacebook\n\nHelpAge India\n\nWebsite\nFacebook\n\nWebsite\n\nFacebook\n\nHelpAge Cambodia\n\nWebsite\nFacebook\n\nWebsite\n\nFacebook\n\nGramin Vikas Vigyan Samiti (GRAVIS)\n\nWebsite\nFacebook\n\nWebsite\n\nFacebook\n\nforOldy Project, Help without Frontiers Thailand Foundation (HWFT)\n\nWebsite\nFacebook\n\nWebsite\n\nFacebook\n\nFoundation for Older Persons’ Development (FOPDEV)\n\nWebsite\nFacebook\n\nWebsite\n\nFacebook\n\nCoalition of Services of the Elderly (COSE)\n\nWebsite\nFacebook\n\nWebsite\n\nFacebook\n\nChina National Committee on Ageing (CNCA)\n\nWebsite\n\nWebsite\n\nCentre for Human Rights and Development (CHRD)\n\nWebsite\n\nWebsite\n\nBangladesh Women’s Health Coalition (BWHC)\n\nWebsite\n\nWebsite\n\nAgeing Nepal\n\nWebsite\nX\n\nWebsite\n\nX\n\nUnivers de solidarité et de développement (UNI.SOL.D.)\n\nRegional Center for the Welfare of Aging Persons in Cameroon (RECEWAPEC)\n\nWebsite\n\nWebsite\n\nGrandmothers Consortium (GMC)\n\nWebsite\n\nWebsite\n\nVUKOXA – Associacao Humanitaria de Apoio a Velhice\n\nVoice of the Elderly\n\nUganda Reach the Aged Association (URAA)\n\nWebsite\n\nWebsite\n\nTesfa Social and Development Association\n\nWebsite\n\nWebsite\n\nTanzania Mission to the Poor and Disabled (PADI)\n\nWebsite\n\nWebsite\n\nSupport To Older People-Zambia (STOP-Zambia)\n\nWebsite\n\nWebsite\n\nSenior Citizens Association of Zambia (SCAZ)\n\nWebsite\n\nWebsite\n\nSaidia Wazee Karagwe (SAWAKA)\n\nWebsite\n\nWebsite\n\nReach One Touch One Ministries (ROTOM)\n\nWebsite\n\nWebsite\n\nRelief to Development Society (REDESO)\n\nWebsite\n\nWebsite\n\nReach A Hand Uganda (RAHU)\n\nWebsite\n\nWebsite\n\nPalliative Care Association of Uganda (PCAU)\n\nWebsite\n\nWebsite\n\nNSINDAGIZA Organization\n\nWebsite\n\nWebsite\n\nMuthande\n\nWebsite\n\nWebsite\n\nMangu Integrated Community Project (MICOP Kenya)\n\nFacebook\n\nFacebook\n\nMauritius Family Planning and Welfare Association (MFPWA)\n\nWebsite\n\nWebsite\n\nMalawi Network of Older Persons’ Organisations (MANEPO)\n\nWebsite\n\nWebsite\n\nKulmiye Pastoral Association (DPA)\n\nWebsite\n\nWebsite\n\nKibera Day Care Centre for the Elderly (KDCCE)\n\nWebsite\n\nWebsite\n\nKenya Society for People with AIDS (KESPA)\n\nKenyan Aged People Require Information, Knowledge & Advancement (KARIKA)\n\nWebsite\n\nWebsite\n\nHorn International Relief & Development Organization (HIRDO)\n\nWebsite\n\nWebsite\n\nHelpAge Kenya (H.A.K.)\n\nFacebook\n\nFacebook\n\nHealth Nest Uganda (HENU)\n\nFacebook\n\nFacebook\n\nHumanitarian and Development Consortium (HDC)\n\nWebsite\n\nWebsite\n\nFantsuam Foundation\n\nWebsite\n\nWebsite\n\nDroits Humains Ocean Indien (Dis-Moi)\n\nWebsite\n\nWebsite\n\nCoalition of Societies for the Rights of Older Persons in Nigeria (COSROPIN)\n\nWebsite\n\nWebsite\n\nCommunity Based Rehabilitation Alliance (COMBRA)\n\nWebsite\n\nWebsite\n\nCenter for Community Advancement and Family Empowerment (CECAFE)\n\nAcção para o Desenvolvimento Comunitarios or Association for Community Development Action in Sofala (ASADEC)\n\nAlmanar Voluntary Organization (AMVO)\n\nWebsite\nFacebook\n\nWebsite\n\nFacebook\n\nAfrica Development Aid (ADA)\n\nWebsite\n\nWebsite\n\nAgeing Concern Foundation (ACF)\n\nWebsite\n\nWebsite\n\nACAMAGE\n\nFacebook\n\nFacebook\n\nJoin the HelpAge global network\n\nBe part of a global movement changing the world for older people\n\nJoin us\n\nJoin the HelpAge global network\n\nBe part of a global movement changing the world for older people\n\nJoin us\n\nJoin the HelpAge global network\n\nBe part of a global movement changing the world for older people\n\nJoin us\n\nBe part of a global movement changing the world for older people\n\nBe part of a global movement changing the world for older people\n\nSubscribe to our newsletter\n\n\n\n\n SIGN UP HERE \n\nX\n\nSubscribe to our newsletter\n\n\n\n\n SIGN UP HERE \n\nX\n\nSubscribe to our newsletter\n\nSubscribe to our newsletter\n\nSIGN UP HERE",
  "entities": {
    "countries": [
      "canada",
      "china",
      "india",
      "israel",
      "syria",
      "yemen"
    ],
    "organizations": [
      "un",
      "red cross"
    ],
    "key_issues": [
      "concern",
      "nation",
      "region",
      "initiative",
      "action",
      "development",
      "humanitarian",
      "human rights",
      "aid",
      "relief",
      "welfare",
      "un",
      "organization",
      "agency",
      "foundation"
    ]
  },
  "committee": "Economic and Social Council",
  "topic": "Addressing social inclusion of the elderly"
}