{
  "url": "https://www.ifoam.bio/about-us/our-network/regional-bodies/ifoam-asia",
  "title": "IFOAM Asia | IFOAM",
  "text": "IFOAM - Organics International Network\nOur regional bodies, national groups and sector platforms promoting organic throughout the world.\n\n\n\n\nRegional Bodies\n\nIFOAM AgriBioMediterraneo\nIFOAM Asia\nIFOAM Organics Europe\nIFOAM Euro-Asia\nIFOAM Latin America\nIFOAM North America\nIFOAM Southern African Network\n\nNational Groups\n\nIFOAM France\nIFOAM Iran\nIFOAM Japan\n\nSector platforms\n\nAnimal Husbandry Alliance\nIFOAM Apiculture Forum\nIFOAM Aquaculture\nIntercontinental Network of Organic Farmers Organisations - INOFO\nIFOAM Seeds Platform\nTechnology Innovation Platform\n\n\n\n\n\nAbout IFOAM - Organics International       Membership Directory\n \n \n\n\n\n\n\n\n\n\n\n\n\n\n\n\n\n\n\n\n\n\n\n\n\n\n\n\n\n\n\n\n\n\n\n\n\n\n\n \n\n\n\n\n\n\n\n\n\n\n\n\n\n\nIFOAM Asia\n\n\n\n\n\n\n\n\n\n\n\n\n\n\n\n\n\n\n\n\n\n\n\n\n\n\n\n\nEarnest discussions between 18 organic sector leaders from 14 Asian countries led to the establishment of IFOAM Asia in June 2013.\nToday IFOAM Asia nurtures the organic movement across the region in its full diverse cultural, economic, and ecological contexts. Recognizing family farms as the core unit of farming communities and as stewards of nature, the network seeks to improve conditions for laborers, farmers, women, and indigenous or other marginalized groups.\nAt the policy level, IFOAM Asia advocates for organic agriculture by helping governments and their agencies to formulate comprehensive organic policies in their respective countries.\nIFOAM Asia aims to develop and promote regional and domestic organic markets, increase consumer awareness of organic foods and their benefits. IFOAM Asia also recognizes the need for scientific research, education, and development in relation to organic production, processing, and marketing to benefit organic farmers/producers in Asia.\nWebsite and Contact\nhttps://asia.ifoam.bio/\n\n \n\n\n \n\n\n\n\n\n\n\n \n\n\n\n\n\n\n\n\n\n\n\n\n\n\n\n\n\n        About Us\n      \n\nWhat is IFOAM - Organics International?\n\n\n\n  \n  Learn More   \n\n\n\n\n\n\n\n \n\n\n\n\n\n\n \n\nOur Regional Bodies - regional initiatives working across topical areas to unite IFOAM affiliates in around the world.\n\n\n  \n  Read more   \n\n\n\n\n\n\n \n\n\n\n\n\n\n \n\nOur Sector Platforms - enhancing global representation of individual topics relevant to the entire organic movement.\n\n\n  \n  Read more\n\nIFOAM - Organics International Network\nOur regional bodies, national groups and sector platforms promoting organic throughout the world.\n\n\n\n\nRegional Bodies\n\nIFOAM AgriBioMediterraneo\nIFOAM Asia\nIFOAM Organics Europe\nIFOAM Euro-Asia\nIFOAM Latin America\nIFOAM North America\nIFOAM Southern African Network\n\nNational Groups\n\nIFOAM France\nIFOAM Iran\nIFOAM Japan\n\nSector platforms\n\nAnimal Husbandry Alliance\nIFOAM Apiculture Forum\nIFOAM Aquaculture\nIntercontinental Network of Organic Farmers Organisations - INOFO\nIFOAM Seeds Platform\nTechnology Innovation Platform\n\n\n\n\n\nAbout IFOAM - Organics International       Membership Directory\n \n \n\n\n\n\n\n\n\n\n\n\n\n\n\n\n\n\n\n\n\n\n\n\n\n\n\n\n\n\n\n\n\n\n\n\n\n\n\n \n\n\n\n\n\n\n\n\n\n\n\n\n\n\nIFOAM Asia\n\n\n\n\n\n\n\n\n\n\n\n\n\n\n\n\n\n\n\n\n\n\n\n\n\n\n\n\nEarnest discussions between 18 organic sector leaders from 14 Asian countries led to the establishment of IFOAM Asia in June 2013.\nToday IFOAM Asia nurtures the organic movement across the region in its full diverse cultural, economic, and ecological contexts. Recognizing family farms as the core unit of farming communities and as stewards of nature, the network seeks to improve conditions for laborers, farmers, women, and indigenous or other marginalized groups.\nAt the policy level, IFOAM Asia advocates for organic agriculture by helping governments and their agencies to formulate comprehensive organic policies in their respective countries.\nIFOAM Asia aims to develop and promote regional and domestic organic markets, increase consumer awareness of organic foods and their benefits. IFOAM Asia also recognizes the need for scientific research, education, and development in relation to organic production, processing, and marketing to benefit organic farmers/producers in Asia.\nWebsite and Contact\nhttps://asia.ifoam.bio/\n\n \n\n\n \n\n\n\n\n\n\n\n \n\n\n\n\n\n\n\n\n\n\n\n\n\n\n\n\n\n        About Us\n      \n\nWhat is IFOAM - Organics International?\n\n\n\n  \n  Learn More   \n\n\n\n\n\n\n\n \n\n\n\n\n\n\n \n\nOur Regional Bodies - regional initiatives working across topical areas to unite IFOAM affiliates in around the world.\n\n\n  \n  Read more   \n\n\n\n\n\n\n \n\n\n\n\n\n\n \n\nOur Sector Platforms - enhancing global representation of individual topics relevant to the entire organic movement.\n\n\n  \n  Read more\n\nIFOAM - Organics International Network\nOur regional bodies, national groups and sector platforms promoting organic throughout the world.\n\n\n\n\nRegional Bodies\n\nIFOAM AgriBioMediterraneo\nIFOAM Asia\nIFOAM Organics Europe\nIFOAM Euro-Asia\nIFOAM Latin America\nIFOAM North America\nIFOAM Southern African Network\n\nNational Groups\n\nIFOAM France\nIFOAM Iran\nIFOAM Japan\n\nSector platforms\n\nAnimal Husbandry Alliance\nIFOAM Apiculture Forum\nIFOAM Aquaculture\nIntercontinental Network of Organic Farmers Organisations - INOFO\nIFOAM Seeds Platform\nTechnology Innovation Platform\n\n\n\n\n\nAbout IFOAM - Organics International       Membership Directory\n\nIFOAM - Organics International Network\nOur regional bodies, national groups and sector platforms promoting organic throughout the world.\n\n\n\n\nRegional Bodies\n\nIFOAM AgriBioMediterraneo\nIFOAM Asia\nIFOAM Organics Europe\nIFOAM Euro-Asia\nIFOAM Latin America\nIFOAM North America\nIFOAM Southern African Network\n\nNational Groups\n\nIFOAM France\nIFOAM Iran\nIFOAM Japan\n\nSector platforms\n\nAnimal Husbandry Alliance\nIFOAM Apiculture Forum\nIFOAM Aquaculture\nIntercontinental Network of Organic Farmers Organisations - INOFO\nIFOAM Seeds Platform\nTechnology Innovation Platform\n\n\n\n\n\nAbout IFOAM - Organics International       Membership Directory\n\nIFOAM - Organics International Network\nOur regional bodies, national groups and sector platforms promoting organic throughout the world.\n\n\n\n\nRegional Bodies\n\nIFOAM AgriBioMediterraneo\nIFOAM Asia\nIFOAM Organics Europe\nIFOAM Euro-Asia\nIFOAM Latin America\nIFOAM North America\nIFOAM Southern African Network\n\nNational Groups\n\nIFOAM France\nIFOAM Iran\nIFOAM Japan\n\nSector platforms\n\nAnimal Husbandry Alliance\nIFOAM Apiculture Forum\nIFOAM Aquaculture\nIntercontinental Network of Organic Farmers Organisations - INOFO\nIFOAM Seeds Platform\nTechnology Innovation Platform\n\n\n\n\n\nAbout IFOAM - Organics International       Membership Directory\n\nIFOAM - Organics International Network\nOur regional bodies, national groups and sector platforms promoting organic throughout the world.\n\nOur regional bodies, national groups and sector platforms promoting organic throughout the world.\n\nRegional Bodies\n\nIFOAM AgriBioMediterraneo\nIFOAM Asia\nIFOAM Organics Europe\nIFOAM Euro-Asia\nIFOAM Latin America\nIFOAM North America\nIFOAM Southern African Network\n\nNational Groups\n\nIFOAM France\nIFOAM Iran\nIFOAM Japan\n\nSector platforms\n\nAnimal Husbandry Alliance\nIFOAM Apiculture Forum\nIFOAM Aquaculture\nIntercontinental Network of Organic Farmers Organisations - INOFO\nIFOAM Seeds Platform\nTechnology Innovation Platform\n\nRegional Bodies\n\nIFOAM AgriBioMediterraneo\nIFOAM Asia\nIFOAM Organics Europe\nIFOAM Euro-Asia\nIFOAM Latin America\nIFOAM North America\nIFOAM Southern African Network\n\nNational Groups\n\nIFOAM France\nIFOAM Iran\nIFOAM Japan\n\nSector platforms\n\nAnimal Husbandry Alliance\nIFOAM Apiculture Forum\nIFOAM Aquaculture\nIntercontinental Network of Organic Farmers Organisations - INOFO\nIFOAM Seeds Platform\nTechnology Innovation Platform\n\nRegional Bodies\n\nIFOAM AgriBioMediterraneo\nIFOAM Asia\nIFOAM Organics Europe\nIFOAM Euro-Asia\nIFOAM Latin America\nIFOAM North America\nIFOAM Southern African Network\n\nNational Groups\n\nIFOAM France\nIFOAM Iran\nIFOAM Japan\n\nSector platforms\n\nAnimal Husbandry Alliance\nIFOAM Apiculture Forum\nIFOAM Aquaculture\nIntercontinental Network of Organic Farmers Organisations - INOFO\nIFOAM Seeds Platform\nTechnology Innovation Platform\n\nRegional Bodies\n\nIFOAM AgriBioMediterraneo\nIFOAM Asia\nIFOAM Organics Europe\nIFOAM Euro-Asia\nIFOAM Latin America\nIFOAM North America\nIFOAM Southern African Network\n\nRegional Bodies\n\nNational Groups\n\nIFOAM France\nIFOAM Iran\nIFOAM Japan\n\nNational Groups\n\nSector platforms\n\nAnimal Husbandry Alliance\nIFOAM Apiculture Forum\nIFOAM Aquaculture\nIntercontinental Network of Organic Farmers Organisations - INOFO\nIFOAM Seeds Platform\nTechnology Innovation Platform\n\nSector platforms\n\nAbout IFOAM - Organics International       Membership Directory\n\nAbout IFOAM - Organics International       Membership Directory\n\nIFOAM Asia\n\n\n\n\n\n\n\n\n\n\n\n\n\n\n\n\n\n\n\n\n\n\n\n\n\n\n\n\nEarnest discussions between 18 organic sector leaders from 14 Asian countries led to the establishment of IFOAM Asia in June 2013.\nToday IFOAM Asia nurtures the organic movement across the region in its full diverse cultural, economic, and ecological contexts. Recognizing family farms as the core unit of farming communities and as stewards of nature, the network seeks to improve conditions for laborers, farmers, women, and indigenous or other marginalized groups.\nAt the policy level, IFOAM Asia advocates for organic agriculture by helping governments and their agencies to formulate comprehensive organic policies in their respective countries.\nIFOAM Asia aims to develop and promote regional and domestic organic markets, increase consumer awareness of organic foods and their benefits. IFOAM Asia also recognizes the need for scientific research, education, and development in relation to organic production, processing, and marketing to benefit organic farmers/producers in Asia.\nWebsite and Contact\nhttps://asia.ifoam.bio/\n\n \n\n\n \n\n\n\n\n\n\n\n \n\n\n\n\n\n\n\n\n\n\n\n\n\n\n\n\n\n        About Us\n      \n\nWhat is IFOAM - Organics International?\n\n\n\n  \n  Learn More   \n\n\n\n\n\n\n\n \n\n\n\n\n\n\n \n\nOur Regional Bodies - regional initiatives working across topical areas to unite IFOAM affiliates in around the world.\n\n\n  \n  Read more   \n\n\n\n\n\n\n \n\n\n\n\n\n\n \n\nOur Sector Platforms - enhancing global representation of individual topics relevant to the entire organic movement.\n\n\n  \n  Read more\n\nIFOAM Asia\n\n\n\n\n\n\n\n\n\n\n\n\n\n\n\n\n\n\n\n\n\n\n\n\n\n\n\n\nEarnest discussions between 18 organic sector leaders from 14 Asian countries led to the establishment of IFOAM Asia in June 2013.\nToday IFOAM Asia nurtures the organic movement across the region in its full diverse cultural, economic, and ecological contexts. Recognizing family farms as the core unit of farming communities and as stewards of nature, the network seeks to improve conditions for laborers, farmers, women, and indigenous or other marginalized groups.\nAt the policy level, IFOAM Asia advocates for organic agriculture by helping governments and their agencies to formulate comprehensive organic policies in their respective countries.\nIFOAM Asia aims to develop and promote regional and domestic organic markets, increase consumer awareness of organic foods and their benefits. IFOAM Asia also recognizes the need for scientific research, education, and development in relation to organic production, processing, and marketing to benefit organic farmers/producers in Asia.\nWebsite and Contact\nhttps://asia.ifoam.bio/\n\n \n\n\n \n\n\n\n\n\n\n\n \n\n\n\n\n\n\n\n\n\n\n\n\n\n\n\n\n\n        About Us\n      \n\nWhat is IFOAM - Organics International?\n\n\n\n  \n  Learn More   \n\n\n\n\n\n\n\n \n\n\n\n\n\n\n \n\nOur Regional Bodies - regional initiatives working across topical areas to unite IFOAM affiliates in around the world.\n\n\n  \n  Read more   \n\n\n\n\n\n\n \n\n\n\n\n\n\n \n\nOur Sector Platforms - enhancing global representation of individual topics relevant to the entire organic movement.\n\n\n  \n  Read more\n\nIFOAM Asia\n\n\n\n\n\n\n\n\n\n\n\n\n\n\n\n\n\n\n\n\n\n\n\n\n\n\n\n\nEarnest discussions between 18 organic sector leaders from 14 Asian countries led to the establishment of IFOAM Asia in June 2013.\nToday IFOAM Asia nurtures the organic movement across the region in its full diverse cultural, economic, and ecological contexts. Recognizing family farms as the core unit of farming communities and as stewards of nature, the network seeks to improve conditions for laborers, farmers, women, and indigenous or other marginalized groups.\nAt the policy level, IFOAM Asia advocates for organic agriculture by helping governments and their agencies to formulate comprehensive organic policies in their respective countries.\nIFOAM Asia aims to develop and promote regional and domestic organic markets, increase consumer awareness of organic foods and their benefits. IFOAM Asia also recognizes the need for scientific research, education, and development in relation to organic production, processing, and marketing to benefit organic farmers/producers in Asia.\nWebsite and Contact\nhttps://asia.ifoam.bio/\n\n \n\n\n \n\n\n\n\n\n\n\n \n\n\n\n\n\n\n\n\n\n\n\n\n\n\n\n\n\n        About Us\n      \n\nWhat is IFOAM - Organics International?\n\n\n\n  \n  Learn More   \n\n\n\n\n\n\n\n \n\n\n\n\n\n\n \n\nOur Regional Bodies - regional initiatives working across topical areas to unite IFOAM affiliates in around the world.\n\n\n  \n  Read more   \n\n\n\n\n\n\n \n\n\n\n\n\n\n \n\nOur Sector Platforms - enhancing global representation of individual topics relevant to the entire organic movement.\n\n\n  \n  Read more\n\nIFOAM Asia\n\n\n\n\n\n\n\n\n\n\n\n\n\n\n\n\n\n\n\n\n\n\n\n\n\n\n\n\nEarnest discussions between 18 organic sector leaders from 14 Asian countries led to the establishment of IFOAM Asia in June 2013.\nToday IFOAM Asia nurtures the organic movement across the region in its full diverse cultural, economic, and ecological contexts. Recognizing family farms as the core unit of farming communities and as stewards of nature, the network seeks to improve conditions for laborers, farmers, women, and indigenous or other marginalized groups.\nAt the policy level, IFOAM Asia advocates for organic agriculture by helping governments and their agencies to formulate comprehensive organic policies in their respective countries.\nIFOAM Asia aims to develop and promote regional and domestic organic markets, increase consumer awareness of organic foods and their benefits. IFOAM Asia also recognizes the need for scientific research, education, and development in relation to organic production, processing, and marketing to benefit organic farmers/producers in Asia.\nWebsite and Contact\nhttps://asia.ifoam.bio/\n\n \n\n\n \n\n\n\n\n\n\n\n \n\n\n\n\n\n\n\n\n\n\n\n\n\n\n\n\n\n        About Us\n      \n\nWhat is IFOAM - Organics International?\n\n\n\n  \n  Learn More   \n\n\n\n\n\n\n\n \n\n\n\n\n\n\n \n\nOur Regional Bodies - regional initiatives working across topical areas to unite IFOAM affiliates in around the world.\n\n\n  \n  Read more   \n\n\n\n\n\n\n \n\n\n\n\n\n\n \n\nOur Sector Platforms - enhancing global representation of individual topics relevant to the entire organic movement.\n\n\n  \n  Read more\n\nIFOAM Asia\n\n\n\n\n\n\n\n\n\n\n\n\n\n\n\n\n\n\n\n\n\n\n\n\n\n\n\n\nEarnest discussions between 18 organic sector leaders from 14 Asian countries led to the establishment of IFOAM Asia in June 2013.\nToday IFOAM Asia nurtures the organic movement across the region in its full diverse cultural, economic, and ecological contexts. Recognizing family farms as the core unit of farming communities and as stewards of nature, the network seeks to improve conditions for laborers, farmers, women, and indigenous or other marginalized groups.\nAt the policy level, IFOAM Asia advocates for organic agriculture by helping governments and their agencies to formulate comprehensive organic policies in their respective countries.\nIFOAM Asia aims to develop and promote regional and domestic organic markets, increase consumer awareness of organic foods and their benefits. IFOAM Asia also recognizes the need for scientific research, education, and development in relation to organic production, processing, and marketing to benefit organic farmers/producers in Asia.\nWebsite and Contact\nhttps://asia.ifoam.bio/\n\n \n\n\n \n\n\n\n\n\n\n\n \n\n\n\n\n\n\n\n\n\n\n\n\n\n\n\n\n\n        About Us\n      \n\nWhat is IFOAM - Organics International?\n\n\n\n  \n  Learn More   \n\n\n\n\n\n\n\n \n\n\n\n\n\n\n \n\nOur Regional Bodies - regional initiatives working across topical areas to unite IFOAM affiliates in around the world.\n\n\n  \n  Read more   \n\n\n\n\n\n\n \n\n\n\n\n\n\n \n\nOur Sector Platforms - enhancing global representation of individual topics relevant to the entire organic movement.\n\n\n  \n  Read more\n\nIFOAM Asia\n\n\n\n\n\n\n\n\n\n\n\n\n\n\n\n\n\n\n\n\n\n\n\n\n\n\n\n\nEarnest discussions between 18 organic sector leaders from 14 Asian countries led to the establishment of IFOAM Asia in June 2013.\nToday IFOAM Asia nurtures the organic movement across the region in its full diverse cultural, economic, and ecological contexts. Recognizing family farms as the core unit of farming communities and as stewards of nature, the network seeks to improve conditions for laborers, farmers, women, and indigenous or other marginalized groups.\nAt the policy level, IFOAM Asia advocates for organic agriculture by helping governments and their agencies to formulate comprehensive organic policies in their respective countries.\nIFOAM Asia aims to develop and promote regional and domestic organic markets, increase consumer awareness of organic foods and their benefits. IFOAM Asia also recognizes the need for scientific research, education, and development in relation to organic production, processing, and marketing to benefit organic farmers/producers in Asia.\nWebsite and Contact\nhttps://asia.ifoam.bio/\n\n \n\n\n \n\n\n\n\n\n\n\n \n\n\n\n\n\n\n\n\n\n\n\n\n\n\n\n\n\n        About Us\n      \n\nWhat is IFOAM - Organics International?\n\n\n\n  \n  Learn More   \n\n\n\n\n\n\n\n \n\n\n\n\n\n\n \n\nOur Regional Bodies - regional initiatives working across topical areas to unite IFOAM affiliates in around the world.\n\n\n  \n  Read more   \n\n\n\n\n\n\n \n\n\n\n\n\n\n \n\nOur Sector Platforms - enhancing global representation of individual topics relevant to the entire organic movement.\n\n\n  \n  Read more\n\nIFOAM Asia\n\n\n\n\n\n\n\n\n\n\n\n\n\n\n\n\n\n\n\n\n\n\n\n\n\n\n\n\nEarnest discussions between 18 organic sector leaders from 14 Asian countries led to the establishment of IFOAM Asia in June 2013.\nToday IFOAM Asia nurtures the organic movement across the region in its full diverse cultural, economic, and ecological contexts. Recognizing family farms as the core unit of farming communities and as stewards of nature, the network seeks to improve conditions for laborers, farmers, women, and indigenous or other marginalized groups.\nAt the policy level, IFOAM Asia advocates for organic agriculture by helping governments and their agencies to formulate comprehensive organic policies in their respective countries.\nIFOAM Asia aims to develop and promote regional and domestic organic markets, increase consumer awareness of organic foods and their benefits. IFOAM Asia also recognizes the need for scientific research, education, and development in relation to organic production, processing, and marketing to benefit organic farmers/producers in Asia.\nWebsite and Contact\nhttps://asia.ifoam.bio/\n\n \n\n\n \n\n\n\n\n\n\n\n \n\n\n\n\n\n\n\n\n\n\n\n\n\n\n\n\n\n        About Us\n      \n\nWhat is IFOAM - Organics International?\n\n\n\n  \n  Learn More   \n\n\n\n\n\n\n\n \n\n\n\n\n\n\n \n\nOur Regional Bodies - regional initiatives working across topical areas to unite IFOAM affiliates in around the world.\n\n\n  \n  Read more   \n\n\n\n\n\n\n \n\n\n\n\n\n\n \n\nOur Sector Platforms - enhancing global representation of individual topics relevant to the entire organic movement.\n\n\n  \n  Read more\n\nIFOAM Asia\n\nIFOAM Asia\n\nIFOAM Asia\n\nIFOAM Asia\n\nIFOAM Asia\n\nIFOAM Asia\n\nIFOAM Asia\n\nIFOAM Asia\n\nIFOAM Asia\n\nEarnest discussions between 18 organic sector leaders from 14 Asian countries led to the establishment of IFOAM Asia in June 2013.\nToday IFOAM Asia nurtures the organic movement across the region in its full diverse cultural, economic, and ecological contexts. Recognizing family farms as the core unit of farming communities and as stewards of nature, the network seeks to improve conditions for laborers, farmers, women, and indigenous or other marginalized groups.\nAt the policy level, IFOAM Asia advocates for organic agriculture by helping governments and their agencies to formulate comprehensive organic policies in their respective countries.\nIFOAM Asia aims to develop and promote regional and domestic organic markets, increase consumer awareness of organic foods and their benefits. IFOAM Asia also recognizes the need for scientific research, education, and development in relation to organic production, processing, and marketing to benefit organic farmers/producers in Asia.\nWebsite and Contact\nhttps://asia.ifoam.bio/\n\nEarnest discussions between 18 organic sector leaders from 14 Asian countries led to the establishment of IFOAM Asia in June 2013.\nToday IFOAM Asia nurtures the organic movement across the region in its full diverse cultural, economic, and ecological contexts. Recognizing family farms as the core unit of farming communities and as stewards of nature, the network seeks to improve conditions for laborers, farmers, women, and indigenous or other marginalized groups.\nAt the policy level, IFOAM Asia advocates for organic agriculture by helping governments and their agencies to formulate comprehensive organic policies in their respective countries.\nIFOAM Asia aims to develop and promote regional and domestic organic markets, increase consumer awareness of organic foods and their benefits. IFOAM Asia also recognizes the need for scientific research, education, and development in relation to organic production, processing, and marketing to benefit organic farmers/producers in Asia.\nWebsite and Contact\nhttps://asia.ifoam.bio/\n\nEarnest discussions between 18 organic sector leaders from 14 Asian countries led to the establishment of IFOAM Asia in June 2013.\nToday IFOAM Asia nurtures the organic movement across the region in its full diverse cultural, economic, and ecological contexts. Recognizing family farms as the core unit of farming communities and as stewards of nature, the network seeks to improve conditions for laborers, farmers, women, and indigenous or other marginalized groups.\nAt the policy level, IFOAM Asia advocates for organic agriculture by helping governments and their agencies to formulate comprehensive organic policies in their respective countries.\nIFOAM Asia aims to develop and promote regional and domestic organic markets, increase consumer awareness of organic foods and their benefits. IFOAM Asia also recognizes the need for scientific research, education, and development in relation to organic production, processing, and marketing to benefit organic farmers/producers in Asia.\nWebsite and Contact\nhttps://asia.ifoam.bio/\n\nEarnest discussions between 18 organic sector leaders from 14 Asian countries led to the establishment of IFOAM Asia in June 2013.\nToday IFOAM Asia nurtures the organic movement across the region in its full diverse cultural, economic, and ecological contexts. Recognizing family farms as the core unit of farming communities and as stewards of nature, the network seeks to improve conditions for laborers, farmers, women, and indigenous or other marginalized groups.\nAt the policy level, IFOAM Asia advocates for organic agriculture by helping governments and their agencies to formulate comprehensive organic policies in their respective countries.\nIFOAM Asia aims to develop and promote regional and domestic organic markets, increase consumer awareness of organic foods and their benefits. IFOAM Asia also recognizes the need for scientific research, education, and development in relation to organic production, processing, and marketing to benefit organic farmers/producers in Asia.\nWebsite and Contact\nhttps://asia.ifoam.bio/\n\nEarnest discussions between 18 organic sector leaders from 14 Asian countries led to the establishment of IFOAM Asia in June 2013.\nToday IFOAM Asia nurtures the organic movement across the region in its full diverse cultural, economic, and ecological contexts. Recognizing family farms as the core unit of farming communities and as stewards of nature, the network seeks to improve conditions for laborers, farmers, women, and indigenous or other marginalized groups.\nAt the policy level, IFOAM Asia advocates for organic agriculture by helping governments and their agencies to formulate comprehensive organic policies in their respective countries.\nIFOAM Asia aims to develop and promote regional and domestic organic markets, increase consumer awareness of organic foods and their benefits. IFOAM Asia also recognizes the need for scientific research, education, and development in relation to organic production, processing, and marketing to benefit organic farmers/producers in Asia.\nWebsite and Contact\nhttps://asia.ifoam.bio/\n\nEarnest discussions between 18 organic sector leaders from 14 Asian countries led to the establishment of IFOAM Asia in June 2013.\nToday IFOAM Asia nurtures the organic movement across the region in its full diverse cultural, economic, and ecological contexts. Recognizing family farms as the core unit of farming communities and as stewards of nature, the network seeks to improve conditions for laborers, farmers, women, and indigenous or other marginalized groups.\nAt the policy level, IFOAM Asia advocates for organic agriculture by helping governments and their agencies to formulate comprehensive organic policies in their respective countries.\nIFOAM Asia aims to develop and promote regional and domestic organic markets, increase consumer awareness of organic foods and their benefits. IFOAM Asia also recognizes the need for scientific research, education, and development in relation to organic production, processing, and marketing to benefit organic farmers/producers in Asia.\nWebsite and Contact\nhttps://asia.ifoam.bio/\n\nEarnest discussions between 18 organic sector leaders from 14 Asian countries led to the establishment of IFOAM Asia in June 2013.\nToday IFOAM Asia nurtures the organic movement across the region in its full diverse cultural, economic, and ecological contexts. Recognizing family farms as the core unit of farming communities and as stewards of nature, the network seeks to improve conditions for laborers, farmers, women, and indigenous or other marginalized groups.\nAt the policy level, IFOAM Asia advocates for organic agriculture by helping governments and their agencies to formulate comprehensive organic policies in their respective countries.\nIFOAM Asia aims to develop and promote regional and domestic organic markets, increase consumer awareness of organic foods and their benefits. IFOAM Asia also recognizes the need for scientific research, education, and development in relation to organic production, processing, and marketing to benefit organic farmers/producers in Asia.\nWebsite and Contact\nhttps://asia.ifoam.bio/\n\nToday IFOAM Asia nurtures the organic movement across the region in its full diverse cultural, economic, and ecological contexts. Recognizing family farms as the core unit of farming communities and as stewards of nature, the network seeks to improve conditions for laborers, farmers, women, and indigenous or other marginalized groups.\n\nAt the policy level, IFOAM Asia advocates for organic agriculture by helping governments and their agencies to formulate comprehensive organic policies in their respective countries.\n\nIFOAM Asia aims to develop and promote regional and domestic organic markets, increase consumer awareness of organic foods and their benefits. IFOAM Asia also recognizes the need for scientific research, education, and development in relation to organic production, processing, and marketing to benefit organic farmers/producers in Asia.\n\nhttps://asia.ifoam.bio/\n\nAbout Us\n      \n\nWhat is IFOAM - Organics International?\n\n\n\n  \n  Learn More   \n\n\n\n\n\n\n\n \n\n\n\n\n\n\n \n\nOur Regional Bodies - regional initiatives working across topical areas to unite IFOAM affiliates in around the world.\n\n\n  \n  Read more   \n\n\n\n\n\n\n \n\n\n\n\n\n\n \n\nOur Sector Platforms - enhancing global representation of individual topics relevant to the entire organic movement.\n\n\n  \n  Read more\n\nAbout Us\n      \n\nWhat is IFOAM - Organics International?\n\n\n\n  \n  Learn More   \n\n\n\n\n\n\n\n \n\n\n\n\n\n\n \n\nOur Regional Bodies - regional initiatives working across topical areas to unite IFOAM affiliates in around the world.\n\n\n  \n  Read more   \n\n\n\n\n\n\n \n\n\n\n\n\n\n \n\nOur Sector Platforms - enhancing global representation of individual topics relevant to the entire organic movement.\n\n\n  \n  Read more\n\nAbout Us\n      \n\nWhat is IFOAM - Organics International?\n\n\n\n  \n  Learn More   \n\n\n\n\n\n\n\n \n\n\n\n\n\n\n \n\nOur Regional Bodies - regional initiatives working across topical areas to unite IFOAM affiliates in around the world.\n\n\n  \n  Read more   \n\n\n\n\n\n\n \n\n\n\n\n\n\n \n\nOur Sector Platforms - enhancing global representation of individual topics relevant to the entire organic movement.\n\n\n  \n  Read more\n\nAbout Us\n      \n\nWhat is IFOAM - Organics International?\n\n\n\n  \n  Learn More   \n\n\n\n\n\n\n\n \n\n\n\n\n\n\n \n\nOur Regional Bodies - regional initiatives working across topical areas to unite IFOAM affiliates in around the world.\n\n\n  \n  Read more   \n\n\n\n\n\n\n \n\n\n\n\n\n\n \n\nOur Sector Platforms - enhancing global representation of individual topics relevant to the entire organic movement.\n\n\n  \n  Read more\n\nAbout Us\n      \n\nWhat is IFOAM - Organics International?\n\n\n\n  \n  Learn More   \n\n\n\n\n\n\n\n \n\n\n\n\n\n\n \n\nOur Regional Bodies - regional initiatives working across topical areas to unite IFOAM affiliates in around the world.\n\n\n  \n  Read more   \n\n\n\n\n\n\n \n\n\n\n\n\n\n \n\nOur Sector Platforms - enhancing global representation of individual topics relevant to the entire organic movement.\n\n\n  \n  Read more\n\nAbout Us\n      \n\nWhat is IFOAM - Organics International?\n\n\n\n  \n  Learn More   \n\n\n\n\n\n\n\n \n\n\n\n\n\n\n \n\nOur Regional Bodies - regional initiatives working across topical areas to unite IFOAM affiliates in around the world.\n\n\n  \n  Read more   \n\n\n\n\n\n\n \n\n\n\n\n\n\n \n\nOur Sector Platforms - enhancing global representation of individual topics relevant to the entire organic movement.\n\n\n  \n  Read more\n\nAbout Us\n      \n\nWhat is IFOAM - Organics International?\n\n\n\n  \n  Learn More\n\nAbout Us\n      \n\nWhat is IFOAM - Organics International?\n\n\n\n  \n  Learn More\n\nAbout Us\n\nWhat is IFOAM - Organics International?\n\n\n\n  \n  Learn More\n\nLearn More\n\nOur Regional Bodies - regional initiatives working across topical areas to unite IFOAM affiliates in around the world.\n\n\n  \n  Read more\n\nOur Regional Bodies - regional initiatives working across topical areas to unite IFOAM affiliates in around the world.\n\n\n  \n  Read more\n\nOur Regional Bodies - regional initiatives working across topical areas to unite IFOAM affiliates in around the world.\n\n\n  \n  Read more\n\nOur Regional Bodies - regional initiatives working across topical areas to unite IFOAM affiliates in around the world.\n\n\n  \n  Read more\n\nOur Sector Platforms - enhancing global representation of individual topics relevant to the entire organic movement.\n\n\n  \n  Read more\n\nOur Sector Platforms - enhancing global representation of individual topics relevant to the entire organic movement.\n\n\n  \n  Read more\n\nOur Sector Platforms - enhancing global representation of individual topics relevant to the entire organic movement.\n\n\n  \n  Read more\n\nOur Sector Platforms - enhancing global representation of individual topics relevant to the entire organic movement.\n\n\n  \n  Read more",
  "date": "",
  "source_type": "other",
  "extracted_at": "2025-04-07T14:31:30.746484",
  "metadata": {
    "description": "IFOAM Asia nurtures the organic movement across the region in its full diverse cultural, economic, and ecological contexts",
    "og:site_name": "IFOAM"
  },
  "relevance_score": 0.4083333333333333,
  "summary": "Regional Bodies\n\nIFOAM AgriBioMediterraneo\nIFOAM Asia\nIFOAM Organics Europe\nIFOAM Euro-Asia\nIFOAM Latin America\nIFOAM North America\nIFOAM Southern African Network\n\nNational Groups\n\nIFOAM France\nIFOAM Iran\nIFOAM Japan\n\nSector platforms\n\nAnimal Husbandry Alliance\nIFOAM Apiculture Forum\nIFOAM Aquaculture\nIntercontinental Network of Organic Farmers Organisations - INOFO\nIFOAM Seeds Platform\nTechnology Innovation Platform\n\n\n\n\n\nAbout IFOAM - Organics International       Membership Directory\n \n \n\n\n\n\n\n\n\n\n\n\n\n\n\n\n\n\n\n\n\n\n\n\n\n\n\n\n\n\n\n\n\n\n\n\n\n\n\n \n\n\n\n\n\n\n\n\n\n\n\n\n\n\nIFOAM Asia\n\n\n\n\n\n\n\n\n\n\n\n\n\n\n\n\n\n\n\n\n\n\n\n\n\n\n\n\nEarnest discussions between 18 organic sector leaders from 14 Asian countries led to the establishment of IFOAM Asia in June 2013. IFOAM Asia aims to develop and promote regional and domestic organic markets, increase consumer awareness of organic foods and their benefits. IFOAM Asia also recognizes the need for scientific research, education, and development in relation to organic production, processing, and marketing to benefit organic farmers/producers in Asia. Regional Bodies\n\nIFOAM AgriBioMediterraneo\nIFOAM Asia\nIFOAM Organics Europe\nIFOAM Euro-Asia\nIFOAM Latin America\nIFOAM North America\nIFOAM Southern African Network\n\nNational Groups\n\nIFOAM France\nIFOAM Iran\nIFOAM Japan\n\nSector platforms\n\nAnimal Husbandry Alliance\nIFOAM Apiculture Forum\nIFOAM Aquaculture\nIntercontinental Network of Organic Farmers Organisations - INOFO\nIFOAM Seeds Platform\nTechnology Innovation Platform\n\n\n\n\n\nAbout IFOAM - Organics International       Membership Directory\n \n \n\n\n\n\n\n\n\n\n\n\n\n\n\n\n\n\n\n\n\n\n\n\n\n\n\n\n\n\n\n\n\n\n\n\n\n\n\n \n\n\n\n\n\n\n\n\n\n\n\n\n\n\nIFOAM Asia\n\n\n\n\n\n\n\n\n\n\n\n\n\n\n\n\n\n\n\n\n\n\n\n\n\n\n\n\nEarnest discussions between 18 organic sector leaders from 14 Asian countries led to the establishment of IFOAM Asia in June 2013. IFOAM Asia aims to develop and promote regional and domestic organic markets, increase consumer awareness of organic foods and their benefits. IFOAM Asia also recognizes the need for scientific research, education, and development in relation to organic production, processing, and marketing to benefit organic farmers/producers in Asia. Regional Bodies\n\nIFOAM AgriBioMediterraneo\nIFOAM Asia\nIFOAM Organics Europe\nIFOAM Euro-Asia\nIFOAM Latin America\nIFOAM North America\nIFOAM Southern African Network\n\nNational Groups\n\nIFOAM France\nIFOAM Iran\nIFOAM Japan\n\nSector platforms\n\nAnimal Husbandry Alliance\nIFOAM Apiculture Forum\nIFOAM Aquaculture\nIntercontinental Network of Organic Farmers Organisations - INOFO\nIFOAM Seeds Platform\nTechnology Innovation Platform\n\n\n\n\n\nAbout IFOAM - Organics International       Membership Directory\n\nIFOAM - Organics International Network\nOur regional bodies, national groups and sector platforms promoting organic throughout the world. Regional Bodies\n\nIFOAM AgriBioMediterraneo\nIFOAM Asia\nIFOAM Organics Europe\nIFOAM Euro-Asia\nIFOAM Latin America\nIFOAM North America\nIFOAM Southern African Network\n\nNational Groups\n\nIFOAM France\nIFOAM Iran\nIFOAM Japan\n\nSector platforms\n\nAnimal Husbandry Alliance\nIFOAM Apiculture Forum\nIFOAM Aquaculture\nIntercontinental Network of Organic Farmers Organisations - INOFO\nIFOAM Seeds Platform\nTechnology Innovation Platform\n\n\n\n\n\nAbout IFOAM - Organics International       Membership Directory\n\nIFOAM - Organics International Network\nOur regional bodies, national groups and sector platforms promoting organic throughout the world. Regional Bodies\n\nIFOAM AgriBioMediterraneo\nIFOAM Asia\nIFOAM Organics Europe\nIFOAM Euro-Asia\nIFOAM Latin America\nIFOAM North America\nIFOAM Southern African Network\n\nNational Groups\n\nIFOAM France\nIFOAM Iran\nIFOAM Japan\n\nSector platforms\n\nAnimal Husbandry Alliance\nIFOAM Apiculture Forum\nIFOAM Aquaculture\nIntercontinental Network of Organic Farmers Organisations - INOFO\nIFOAM Seeds Platform\nTechnology Innovation Platform\n\n\n\n\n\nAbout IFOAM - Organics International       Membership Directory\n\nIFOAM - Organics International Network\nOur regional bodies, national groups and sector platforms promoting organic throughout the world. Regional Bodies\n\nIFOAM AgriBioMediterraneo\nIFOAM Asia\nIFOAM Organics Europe\nIFOAM Euro-Asia\nIFOAM Latin America\nIFOAM North America\nIFOAM Southern African Network\n\nNational Groups\n\nIFOAM France\nIFOAM Iran\nIFOAM Japan\n\nSector platforms\n\nAnimal Husbandry Alliance\nIFOAM Apiculture Forum\nIFOAM Aquaculture\nIntercontinental Network of Organic Farmers Organisations - INOFO\nIFOAM Seeds Platform\nTechnology Innovation Platform\n\nRegional Bodies\n\nIFOAM AgriBioMediterraneo\nIFOAM Asia\nIFOAM Organics Europe\nIFOAM Euro-Asia\nIFOAM Latin America\nIFOAM North America\nIFOAM Southern African Network\n\nNational Groups\n\nIFOAM France\nIFOAM Iran\nIFOAM Japan\n\nSector platforms\n\nAnimal Husbandry Alliance\nIFOAM Apiculture Forum\nIFOAM Aquaculture\nIntercontinental Network of Organic Farmers Organisations - INOFO\nIFOAM Seeds Platform\nTechnology Innovation Platform\n\nRegional Bodies\n\nIFOAM AgriBioMediterraneo\nIFOAM Asia\nIFOAM Organics Europe\nIFOAM Euro-Asia\nIFOAM Latin America\nIFOAM North America\nIFOAM Southern African Network\n\nNational Groups\n\nIFOAM France\nIFOAM Iran\nIFOAM Japan\n\nSector platforms\n\nAnimal Husbandry Alliance\nIFOAM Apiculture Forum\nIFOAM Aquaculture\nIntercontinental Network of Organic Farmers Organisations - INOFO\nIFOAM Seeds Platform\nTechnology Innovation Platform\n\nRegional Bodies\n\nIFOAM AgriBioMediterraneo\nIFOAM Asia\nIFOAM Organics Europe\nIFOAM Euro-Asia\nIFOAM Latin America\nIFOAM North America\nIFOAM Southern African Network\n\nRegional Bodies\n\nNational Groups\n\nIFOAM France\nIFOAM Iran\nIFOAM Japan\n\nNational Groups\n\nSector platforms\n\nAnimal Husbandry Alliance\nIFOAM Apiculture Forum\nIFOAM Aquaculture\nIntercontinental Network of Organic Farmers Organisations - INOFO\nIFOAM Seeds Platform\nTechnology Innovation Platform\n\nSector platforms\n\nAbout IFOAM - Organics International       Membership Directory\n\nAbout IFOAM - Organics International       Membership Directory\n\nIFOAM Asia\n\n\n\n\n\n\n\n\n\n\n\n\n\n\n\n\n\n\n\n\n\n\n\n\n\n\n\n\nEarnest discussions between 18 organic sector leaders from 14 Asian countries led to the establishment of IFOAM Asia in June 2013. IFOAM Asia aims to develop and promote regional and domestic organic markets, increase consumer awareness of organic foods and their benefits. IFOAM Asia also recognizes the need for scientific research, education, and development in relation to organic production, processing, and marketing to benefit organic farmers/producers in Asia. Read more\n\nIFOAM Asia\n\n\n\n\n\n\n\n\n\n\n\n\n\n\n\n\n\n\n\n\n\n\n\n\n\n\n\n\nEarnest discussions between 18 organic sector leaders from 14 Asian countries led to the establishment of IFOAM Asia in June 2013. IFOAM Asia also recognizes the need for scientific research, education, and development in relation to organic production, processing, and marketing to benefit organic farmers/producers in Asia. Read more\n\nIFOAM Asia\n\n\n\n\n\n\n\n\n\n\n\n\n\n\n\n\n\n\n\n\n\n\n\n\n\n\n\n\nEarnest discussions between 18 organic sector leaders from 14 Asian countries led to the establishment of IFOAM Asia in June 2013. IFOAM Asia also recognizes the need for scientific research, education, and development in relation to organic production, processing, and marketing to benefit organic farmers/producers in Asia. Read more\n\nIFOAM Asia\n\n\n\n\n\n\n\n\n\n\n\n\n\n\n\n\n\n\n\n\n\n\n\n\n\n\n\n\nEarnest discussions between 18 organic sector leaders from 14 Asian countries led to the establishment of IFOAM Asia in June 2013. IFOAM Asia also recognizes the need for scientific research, education, and development in relation to organic production, processing, and marketing to benefit organic farmers/producers in Asia. Read more\n\nIFOAM Asia\n\n\n\n\n\n\n\n\n\n\n\n\n\n\n\n\n\n\n\n\n\n\n\n\n\n\n\n\nEarnest discussions between 18 organic sector leaders from 14 Asian countries led to the establishment of IFOAM Asia in June 2013. IFOAM Asia also recognizes the need for scientific research, education, and development in relation to organic production, processing, and marketing to benefit organic farmers/producers in Asia. Read more\n\nIFOAM Asia\n\n\n\n\n\n\n\n\n\n\n\n\n\n\n\n\n\n\n\n\n\n\n\n\n\n\n\n\nEarnest discussions between 18 organic sector leaders from 14 Asian countries led to the establishment of IFOAM Asia in June 2013. IFOAM Asia also recognizes the need for scientific research, education, and development in relation to organic production, processing, and marketing to benefit organic farmers/producers in Asia. Read more\n\nIFOAM Asia\n\n\n\n\n\n\n\n\n\n\n\n\n\n\n\n\n\n\n\n\n\n\n\n\n\n\n\n\nEarnest discussions between 18 organic sector leaders from 14 Asian countries led to the establishment of IFOAM Asia in June 2013. IFOAM Asia also recognizes the need for scientific research, education, and development in relation to organic production, processing, and marketing to benefit organic farmers/producers in Asia. Read more\n\nIFOAM Asia\n\nIFOAM Asia\n\nIFOAM Asia\n\nIFOAM Asia\n\nIFOAM Asia\n\nIFOAM Asia\n\nIFOAM Asia\n\nIFOAM Asia\n\nIFOAM Asia\n\nEarnest discussions between 18 organic sector leaders from 14 Asian countries led to the establishment of IFOAM Asia in June 2013. IFOAM Asia also recognizes the need for scientific research, education, and development in relation to organic production, processing, and marketing to benefit organic farmers/producers in Asia. IFOAM Asia also recognizes the need for scientific research, education, and development in relation to organic production, processing, and marketing to benefit organic farmers/producers in Asia. IFOAM Asia also recognizes the need for scientific research, education, and development in relation to organic production, processing, and marketing to benefit organic farmers/producers in Asia. IFOAM Asia also recognizes the need for scientific research, education, and development in relation to organic production, processing, and marketing to benefit organic farmers/producers in Asia. IFOAM Asia also recognizes the need for scientific research, education, and development in relation to organic production, processing, and marketing to benefit organic farmers/producers in Asia. IFOAM Asia also recognizes the need for scientific research, education, and development in relation to organic production, processing, and marketing to benefit organic farmers/producers in Asia. IFOAM Asia also recognizes the need for scientific research, education, and development in relation to organic production, processing, and marketing to benefit organic farmers/producers in Asia. IFOAM Asia also recognizes the need for scientific research, education, and development in relation to organic production, processing, and marketing to benefit organic farmers/producers in Asia.",
  "entities": {
    "countries": [
      "france",
      "iran",
      "japan"
    ],
    "organizations": [
      "un"
    ],
    "key_issues": [
      "nation",
      "government",
      "region",
      "policy",
      "initiative",
      "context",
      "development",
      "economic",
      "market",
      "un"
    ]
  },
  "committee": "UN Educational, Scientific and Cultural Organization",
  "topic": "Solidifying sustainable agriculture"
}