{
  "url": "https://www.rescue.org/latest",
  "title": "Latest | International Rescue Committee (IRC)",
  "text": "LatestGet the latest news, photos and videos spotlighting the world's worst humanitarian crises and the International Rescue Committee's work helping people devastated by conflict and disaster.\n\nNews & features        World Health Day\n        Meet Duha: A nurse in the world’s largest Syrian refugee camp\nRead Duha's story        Urgent Appeal\n        Myanmar earthquake: What’s happening and how to help? \nRead the article        Yemen War\n        A decade of war: 10 voices from Yemen\nRead their stories        Ukraine\n        How to help Ukraine\nRead the articleGaza crisisCeasefire reinstatement needed to avert worsening humanitarian disaster in GazaMarch 20, 2025Aid cutsHow U.S. aid cuts impact public healthMarch 19, 2025Economic contributionsHow refugees strengthen the U.S. economyMarch 18, 2025InnovationIRC named one of the most innovative companies of 2025March 17, 2025Origins of the IRC7 facts about Albert Einstein that may surprise youMarch 17, 2025Pathways to safetyWhat is humanitarian parole?March 7, 2025Inside the IRCImpactful giving: How your donation makes a differenceMarch 7, 2025Humanitarian aidU.S. aid cuts put millions in perilFebruary 28, 2025Breaking newsUnited States terminates thousands of aid programsFebruary 27, 2025Our commitmentMeeting the moment: A note from our CEOFebruary 26, 2025Press releasesThe IRC is deeply concerned by new wave of forced displacement amid military escalation in GazaApril 4, 2025Myanmar Earthquake: IRC Teams Report Unprecedented DestructionMarch 31, 2025Major earthquake measuring 7.7 shocks Myanmar, with tremors felt in Thailand and Bangladesh; IRC assessing and preparing to respond to humanitarian needsMarch 28, 2025A decade of conflict in Yemen: Humanitarian lifeline on the brink, warns the IRCMarch 26, 2025Fire devastates displacement camp in northeast Nigeria, leaving over 12,500 people in dire need of urgent humanitarian assistance, IRC warnsMarch 25, 2025World Leaders Must Act Now to Avert Global Nutrition Crisis and Build Resilient Health Systems at Nutrition for Growth Summit, IRC warnsMarch 24, 2025Visit our media center\n\n\n\nCrisis WatchWho We AreWhere We WorkWhat We DoHow To HelpLatestCareersContact UsDonor HelpCode of ConductEthics HotlineOur efficiency87% Program services7% Management and general6% FundraisingDonateJoin our mailing list\n    Get the latest news about the IRC's innovative programs, compelling stories about our clients and how you can make a difference.\n     \n\n  \n  \n          \n        \n                  \n \n    \nSubscribeFollow UsRescue Websites:U.S./GlobalUKGermanySwedenEUKoreaPhone Opt OutRespecting Your PrivacyTerms and ConditionsFraud PreventionInternational Rescue Committee is a 501(c)(3) not-for-profit organization. EIN number 13-5660870.Copyright © International Rescue Committee, 2025.\n\nLatestGet the latest news, photos and videos spotlighting the world's worst humanitarian crises and the International Rescue Committee's work helping people devastated by conflict and disaster.\n\nLatestGet the latest news, photos and videos spotlighting the world's worst humanitarian crises and the International Rescue Committee's work helping people devastated by conflict and disaster.\n\nLatestGet the latest news, photos and videos spotlighting the world's worst humanitarian crises and the International Rescue Committee's work helping people devastated by conflict and disaster.\n\nLatestGet the latest news, photos and videos spotlighting the world's worst humanitarian crises and the International Rescue Committee's work helping people devastated by conflict and disaster.\n\nLatestGet the latest news, photos and videos spotlighting the world's worst humanitarian crises and the International Rescue Committee's work helping people devastated by conflict and disaster.\n\nLatestGet the latest news, photos and videos spotlighting the world's worst humanitarian crises and the International Rescue Committee's work helping people devastated by conflict and disaster.\n\nLatestGet the latest news, photos and videos spotlighting the world's worst humanitarian crises and the International Rescue Committee's work helping people devastated by conflict and disaster.\n\nLatestGet the latest news, photos and videos spotlighting the world's worst humanitarian crises and the International Rescue Committee's work helping people devastated by conflict and disaster.\n\nLatestGet the latest news, photos and videos spotlighting the world's worst humanitarian crises and the International Rescue Committee's work helping people devastated by conflict and disaster.\n\nLatestGet the latest news, photos and videos spotlighting the world's worst humanitarian crises and the International Rescue Committee's work helping people devastated by conflict and disaster.\n\nLatest\n\nGet the latest news, photos and videos spotlighting the world's worst humanitarian crises and the International Rescue Committee's work helping people devastated by conflict and disaster.\n\nGet the latest news, photos and videos spotlighting the world's worst humanitarian crises and the International Rescue Committee's work helping people devastated by conflict and disaster.\n\nGet the latest news, photos and videos spotlighting the world's worst humanitarian crises and the International Rescue Committee's work helping people devastated by conflict and disaster.\n\nNews & features        World Health Day\n        Meet Duha: A nurse in the world’s largest Syrian refugee camp\nRead Duha's story        Urgent Appeal\n        Myanmar earthquake: What’s happening and how to help? \nRead the article        Yemen War\n        A decade of war: 10 voices from Yemen\nRead their stories        Ukraine\n        How to help Ukraine\nRead the articleGaza crisisCeasefire reinstatement needed to avert worsening humanitarian disaster in GazaMarch 20, 2025Aid cutsHow U.S. aid cuts impact public healthMarch 19, 2025Economic contributionsHow refugees strengthen the U.S. economyMarch 18, 2025InnovationIRC named one of the most innovative companies of 2025March 17, 2025Origins of the IRC7 facts about Albert Einstein that may surprise youMarch 17, 2025Pathways to safetyWhat is humanitarian parole?March 7, 2025Inside the IRCImpactful giving: How your donation makes a differenceMarch 7, 2025Humanitarian aidU.S. aid cuts put millions in perilFebruary 28, 2025Breaking newsUnited States terminates thousands of aid programsFebruary 27, 2025Our commitmentMeeting the moment: A note from our CEOFebruary 26, 2025Press releasesThe IRC is deeply concerned by new wave of forced displacement amid military escalation in GazaApril 4, 2025Myanmar Earthquake: IRC Teams Report Unprecedented DestructionMarch 31, 2025Major earthquake measuring 7.7 shocks Myanmar, with tremors felt in Thailand and Bangladesh; IRC assessing and preparing to respond to humanitarian needsMarch 28, 2025A decade of conflict in Yemen: Humanitarian lifeline on the brink, warns the IRCMarch 26, 2025Fire devastates displacement camp in northeast Nigeria, leaving over 12,500 people in dire need of urgent humanitarian assistance, IRC warnsMarch 25, 2025World Leaders Must Act Now to Avert Global Nutrition Crisis and Build Resilient Health Systems at Nutrition for Growth Summit, IRC warnsMarch 24, 2025Visit our media center\n\nNews & features        World Health Day\n        Meet Duha: A nurse in the world’s largest Syrian refugee camp\nRead Duha's story        Urgent Appeal\n        Myanmar earthquake: What’s happening and how to help? \nRead the article        Yemen War\n        A decade of war: 10 voices from Yemen\nRead their stories        Ukraine\n        How to help Ukraine\nRead the articleGaza crisisCeasefire reinstatement needed to avert worsening humanitarian disaster in GazaMarch 20, 2025Aid cutsHow U.S. aid cuts impact public healthMarch 19, 2025Economic contributionsHow refugees strengthen the U.S. economyMarch 18, 2025InnovationIRC named one of the most innovative companies of 2025March 17, 2025Origins of the IRC7 facts about Albert Einstein that may surprise youMarch 17, 2025Pathways to safetyWhat is humanitarian parole?March 7, 2025Inside the IRCImpactful giving: How your donation makes a differenceMarch 7, 2025Humanitarian aidU.S. aid cuts put millions in perilFebruary 28, 2025Breaking newsUnited States terminates thousands of aid programsFebruary 27, 2025Our commitmentMeeting the moment: A note from our CEOFebruary 26, 2025Press releasesThe IRC is deeply concerned by new wave of forced displacement amid military escalation in GazaApril 4, 2025Myanmar Earthquake: IRC Teams Report Unprecedented DestructionMarch 31, 2025Major earthquake measuring 7.7 shocks Myanmar, with tremors felt in Thailand and Bangladesh; IRC assessing and preparing to respond to humanitarian needsMarch 28, 2025A decade of conflict in Yemen: Humanitarian lifeline on the brink, warns the IRCMarch 26, 2025Fire devastates displacement camp in northeast Nigeria, leaving over 12,500 people in dire need of urgent humanitarian assistance, IRC warnsMarch 25, 2025World Leaders Must Act Now to Avert Global Nutrition Crisis and Build Resilient Health Systems at Nutrition for Growth Summit, IRC warnsMarch 24, 2025Visit our media center\n\nNews & features        World Health Day\n        Meet Duha: A nurse in the world’s largest Syrian refugee camp\nRead Duha's story        Urgent Appeal\n        Myanmar earthquake: What’s happening and how to help? \nRead the article        Yemen War\n        A decade of war: 10 voices from Yemen\nRead their stories        Ukraine\n        How to help Ukraine\nRead the articleGaza crisisCeasefire reinstatement needed to avert worsening humanitarian disaster in GazaMarch 20, 2025Aid cutsHow U.S. aid cuts impact public healthMarch 19, 2025Economic contributionsHow refugees strengthen the U.S. economyMarch 18, 2025InnovationIRC named one of the most innovative companies of 2025March 17, 2025Origins of the IRC7 facts about Albert Einstein that may surprise youMarch 17, 2025Pathways to safetyWhat is humanitarian parole?March 7, 2025Inside the IRCImpactful giving: How your donation makes a differenceMarch 7, 2025Humanitarian aidU.S. aid cuts put millions in perilFebruary 28, 2025Breaking newsUnited States terminates thousands of aid programsFebruary 27, 2025Our commitmentMeeting the moment: A note from our CEOFebruary 26, 2025\n\nNews & features        World Health Day\n        Meet Duha: A nurse in the world’s largest Syrian refugee camp\nRead Duha's story        Urgent Appeal\n        Myanmar earthquake: What’s happening and how to help? \nRead the article        Yemen War\n        A decade of war: 10 voices from Yemen\nRead their stories        Ukraine\n        How to help Ukraine\nRead the articleGaza crisisCeasefire reinstatement needed to avert worsening humanitarian disaster in GazaMarch 20, 2025Aid cutsHow U.S. aid cuts impact public healthMarch 19, 2025Economic contributionsHow refugees strengthen the U.S. economyMarch 18, 2025InnovationIRC named one of the most innovative companies of 2025March 17, 2025Origins of the IRC7 facts about Albert Einstein that may surprise youMarch 17, 2025Pathways to safetyWhat is humanitarian parole?March 7, 2025Inside the IRCImpactful giving: How your donation makes a differenceMarch 7, 2025Humanitarian aidU.S. aid cuts put millions in perilFebruary 28, 2025Breaking newsUnited States terminates thousands of aid programsFebruary 27, 2025Our commitmentMeeting the moment: A note from our CEOFebruary 26, 2025\n\nNews & features\n\nNews & features\n\nWorld Health Day\n        Meet Duha: A nurse in the world’s largest Syrian refugee camp\nRead Duha's story        Urgent Appeal\n        Myanmar earthquake: What’s happening and how to help? \nRead the article        Yemen War\n        A decade of war: 10 voices from Yemen\nRead their stories        Ukraine\n        How to help Ukraine\nRead the articleGaza crisisCeasefire reinstatement needed to avert worsening humanitarian disaster in GazaMarch 20, 2025Aid cutsHow U.S. aid cuts impact public healthMarch 19, 2025Economic contributionsHow refugees strengthen the U.S. economyMarch 18, 2025InnovationIRC named one of the most innovative companies of 2025March 17, 2025Origins of the IRC7 facts about Albert Einstein that may surprise youMarch 17, 2025Pathways to safetyWhat is humanitarian parole?March 7, 2025Inside the IRCImpactful giving: How your donation makes a differenceMarch 7, 2025Humanitarian aidU.S. aid cuts put millions in perilFebruary 28, 2025Breaking newsUnited States terminates thousands of aid programsFebruary 27, 2025Our commitmentMeeting the moment: A note from our CEOFebruary 26, 2025\n\nWorld Health Day\n        Meet Duha: A nurse in the world’s largest Syrian refugee camp\nRead Duha's story\n\nWorld Health Day\n        Meet Duha: A nurse in the world’s largest Syrian refugee camp\nRead Duha's story\n\nWorld Health Day\n\nMeet Duha: A nurse in the world’s largest Syrian refugee camp\n\nRead Duha's story\n\nRead Duha's story\n\nUrgent Appeal\n        Myanmar earthquake: What’s happening and how to help? \nRead the article\n\nUrgent Appeal\n        Myanmar earthquake: What’s happening and how to help? \nRead the article\n\nUrgent Appeal\n\nMyanmar earthquake: What’s happening and how to help?\n\nRead the article\n\nRead the article\n\nYemen War\n        A decade of war: 10 voices from Yemen\nRead their stories\n\nYemen War\n        A decade of war: 10 voices from Yemen\nRead their stories\n\nYemen War\n\nA decade of war: 10 voices from Yemen\n\nRead their stories\n\nRead their stories\n\nUkraine\n        How to help Ukraine\nRead the article\n\nUkraine\n        How to help Ukraine\nRead the article\n\nUkraine\n\nHow to help Ukraine\n\nRead the article\n\nRead the article\n\nGaza crisisCeasefire reinstatement needed to avert worsening humanitarian disaster in GazaMarch 20, 2025\n\nGaza crisisCeasefire reinstatement needed to avert worsening humanitarian disaster in GazaMarch 20, 2025\n\nGaza crisis\n\nGaza crisis\n\nCeasefire reinstatement needed to avert worsening humanitarian disaster in Gaza\n\nMarch 20, 2025\n\nMarch 20, 2025\n\nAid cutsHow U.S. aid cuts impact public healthMarch 19, 2025\n\nAid cutsHow U.S. aid cuts impact public healthMarch 19, 2025\n\nAid cuts\n\nAid cuts\n\nHow U.S. aid cuts impact public health\n\nMarch 19, 2025\n\nMarch 19, 2025\n\nEconomic contributionsHow refugees strengthen the U.S. economyMarch 18, 2025\n\nEconomic contributionsHow refugees strengthen the U.S. economyMarch 18, 2025\n\nEconomic contributions\n\nEconomic contributions\n\nHow refugees strengthen the U.S. economy\n\nMarch 18, 2025\n\nMarch 18, 2025\n\nInnovationIRC named one of the most innovative companies of 2025March 17, 2025\n\nInnovationIRC named one of the most innovative companies of 2025March 17, 2025\n\nInnovation\n\nInnovation\n\nIRC named one of the most innovative companies of 2025\n\nMarch 17, 2025\n\nMarch 17, 2025\n\nOrigins of the IRC7 facts about Albert Einstein that may surprise youMarch 17, 2025\n\nOrigins of the IRC7 facts about Albert Einstein that may surprise youMarch 17, 2025\n\nOrigins of the IRC\n\nOrigins of the IRC\n\n7 facts about Albert Einstein that may surprise you\n\nMarch 17, 2025\n\nMarch 17, 2025\n\nPathways to safetyWhat is humanitarian parole?March 7, 2025\n\nPathways to safetyWhat is humanitarian parole?March 7, 2025\n\nPathways to safety\n\nPathways to safety\n\nWhat is humanitarian parole?\n\nMarch 7, 2025\n\nMarch 7, 2025\n\nInside the IRCImpactful giving: How your donation makes a differenceMarch 7, 2025\n\nInside the IRCImpactful giving: How your donation makes a differenceMarch 7, 2025\n\nInside the IRC\n\nInside the IRC\n\nImpactful giving: How your donation makes a difference\n\nMarch 7, 2025\n\nMarch 7, 2025\n\nHumanitarian aidU.S. aid cuts put millions in perilFebruary 28, 2025\n\nHumanitarian aidU.S. aid cuts put millions in perilFebruary 28, 2025\n\nHumanitarian aid\n\nHumanitarian aid\n\nU.S. aid cuts put millions in peril\n\nFebruary 28, 2025\n\nFebruary 28, 2025\n\nBreaking newsUnited States terminates thousands of aid programsFebruary 27, 2025\n\nBreaking newsUnited States terminates thousands of aid programsFebruary 27, 2025\n\nBreaking news\n\nBreaking news\n\nUnited States terminates thousands of aid programs\n\nFebruary 27, 2025\n\nFebruary 27, 2025\n\nOur commitmentMeeting the moment: A note from our CEOFebruary 26, 2025\n\nOur commitmentMeeting the moment: A note from our CEOFebruary 26, 2025\n\nOur commitment\n\nOur commitment\n\nMeeting the moment: A note from our CEO\n\nFebruary 26, 2025\n\nFebruary 26, 2025\n\nPress releasesThe IRC is deeply concerned by new wave of forced displacement amid military escalation in GazaApril 4, 2025Myanmar Earthquake: IRC Teams Report Unprecedented DestructionMarch 31, 2025Major earthquake measuring 7.7 shocks Myanmar, with tremors felt in Thailand and Bangladesh; IRC assessing and preparing to respond to humanitarian needsMarch 28, 2025A decade of conflict in Yemen: Humanitarian lifeline on the brink, warns the IRCMarch 26, 2025Fire devastates displacement camp in northeast Nigeria, leaving over 12,500 people in dire need of urgent humanitarian assistance, IRC warnsMarch 25, 2025World Leaders Must Act Now to Avert Global Nutrition Crisis and Build Resilient Health Systems at Nutrition for Growth Summit, IRC warnsMarch 24, 2025Visit our media center\n\nPress releasesThe IRC is deeply concerned by new wave of forced displacement amid military escalation in GazaApril 4, 2025Myanmar Earthquake: IRC Teams Report Unprecedented DestructionMarch 31, 2025Major earthquake measuring 7.7 shocks Myanmar, with tremors felt in Thailand and Bangladesh; IRC assessing and preparing to respond to humanitarian needsMarch 28, 2025A decade of conflict in Yemen: Humanitarian lifeline on the brink, warns the IRCMarch 26, 2025Fire devastates displacement camp in northeast Nigeria, leaving over 12,500 people in dire need of urgent humanitarian assistance, IRC warnsMarch 25, 2025World Leaders Must Act Now to Avert Global Nutrition Crisis and Build Resilient Health Systems at Nutrition for Growth Summit, IRC warnsMarch 24, 2025Visit our media center\n\nPress releases\n\nPress releases\n\nThe IRC is deeply concerned by new wave of forced displacement amid military escalation in GazaApril 4, 2025Myanmar Earthquake: IRC Teams Report Unprecedented DestructionMarch 31, 2025Major earthquake measuring 7.7 shocks Myanmar, with tremors felt in Thailand and Bangladesh; IRC assessing and preparing to respond to humanitarian needsMarch 28, 2025A decade of conflict in Yemen: Humanitarian lifeline on the brink, warns the IRCMarch 26, 2025Fire devastates displacement camp in northeast Nigeria, leaving over 12,500 people in dire need of urgent humanitarian assistance, IRC warnsMarch 25, 2025World Leaders Must Act Now to Avert Global Nutrition Crisis and Build Resilient Health Systems at Nutrition for Growth Summit, IRC warnsMarch 24, 2025Visit our media center\n\nThe IRC is deeply concerned by new wave of forced displacement amid military escalation in GazaApril 4, 2025Myanmar Earthquake: IRC Teams Report Unprecedented DestructionMarch 31, 2025Major earthquake measuring 7.7 shocks Myanmar, with tremors felt in Thailand and Bangladesh; IRC assessing and preparing to respond to humanitarian needsMarch 28, 2025A decade of conflict in Yemen: Humanitarian lifeline on the brink, warns the IRCMarch 26, 2025Fire devastates displacement camp in northeast Nigeria, leaving over 12,500 people in dire need of urgent humanitarian assistance, IRC warnsMarch 25, 2025World Leaders Must Act Now to Avert Global Nutrition Crisis and Build Resilient Health Systems at Nutrition for Growth Summit, IRC warnsMarch 24, 2025Visit our media center\n\nThe IRC is deeply concerned by new wave of forced displacement amid military escalation in GazaApril 4, 2025Myanmar Earthquake: IRC Teams Report Unprecedented DestructionMarch 31, 2025Major earthquake measuring 7.7 shocks Myanmar, with tremors felt in Thailand and Bangladesh; IRC assessing and preparing to respond to humanitarian needsMarch 28, 2025A decade of conflict in Yemen: Humanitarian lifeline on the brink, warns the IRCMarch 26, 2025Fire devastates displacement camp in northeast Nigeria, leaving over 12,500 people in dire need of urgent humanitarian assistance, IRC warnsMarch 25, 2025World Leaders Must Act Now to Avert Global Nutrition Crisis and Build Resilient Health Systems at Nutrition for Growth Summit, IRC warnsMarch 24, 2025Visit our media center\n\nThe IRC is deeply concerned by new wave of forced displacement amid military escalation in GazaApril 4, 2025Myanmar Earthquake: IRC Teams Report Unprecedented DestructionMarch 31, 2025Major earthquake measuring 7.7 shocks Myanmar, with tremors felt in Thailand and Bangladesh; IRC assessing and preparing to respond to humanitarian needsMarch 28, 2025A decade of conflict in Yemen: Humanitarian lifeline on the brink, warns the IRCMarch 26, 2025Fire devastates displacement camp in northeast Nigeria, leaving over 12,500 people in dire need of urgent humanitarian assistance, IRC warnsMarch 25, 2025World Leaders Must Act Now to Avert Global Nutrition Crisis and Build Resilient Health Systems at Nutrition for Growth Summit, IRC warnsMarch 24, 2025\n\nThe IRC is deeply concerned by new wave of forced displacement amid military escalation in GazaApril 4, 2025\n\nThe IRC is deeply concerned by new wave of forced displacement amid military escalation in Gaza\n\nApril 4, 2025\n\nApril 4, 2025\n\nMyanmar Earthquake: IRC Teams Report Unprecedented DestructionMarch 31, 2025\n\nMyanmar Earthquake: IRC Teams Report Unprecedented Destruction\n\nMarch 31, 2025\n\nMarch 31, 2025\n\nMajor earthquake measuring 7.7 shocks Myanmar, with tremors felt in Thailand and Bangladesh; IRC assessing and preparing to respond to humanitarian needsMarch 28, 2025\n\nMajor earthquake measuring 7.7 shocks Myanmar, with tremors felt in Thailand and Bangladesh; IRC assessing and preparing to respond to humanitarian needs\n\nMarch 28, 2025\n\nMarch 28, 2025\n\nA decade of conflict in Yemen: Humanitarian lifeline on the brink, warns the IRCMarch 26, 2025\n\nA decade of conflict in Yemen: Humanitarian lifeline on the brink, warns the IRC\n\nMarch 26, 2025\n\nMarch 26, 2025\n\nFire devastates displacement camp in northeast Nigeria, leaving over 12,500 people in dire need of urgent humanitarian assistance, IRC warnsMarch 25, 2025\n\nFire devastates displacement camp in northeast Nigeria, leaving over 12,500 people in dire need of urgent humanitarian assistance, IRC warns\n\nMarch 25, 2025\n\nMarch 25, 2025\n\nWorld Leaders Must Act Now to Avert Global Nutrition Crisis and Build Resilient Health Systems at Nutrition for Growth Summit, IRC warnsMarch 24, 2025\n\nWorld Leaders Must Act Now to Avert Global Nutrition Crisis and Build Resilient Health Systems at Nutrition for Growth Summit, IRC warns\n\nMarch 24, 2025\n\nMarch 24, 2025\n\nVisit our media center\n\nVisit our media center\n\nCrisis WatchWho We AreWhere We WorkWhat We DoHow To HelpLatestCareersContact UsDonor HelpCode of ConductEthics HotlineOur efficiency87% Program services7% Management and general6% FundraisingDonateJoin our mailing list\n    Get the latest news about the IRC's innovative programs, compelling stories about our clients and how you can make a difference.\n     \n\n  \n  \n          \n        \n                  \n \n    \nSubscribeFollow UsRescue Websites:U.S./GlobalUKGermanySwedenEUKoreaPhone Opt OutRespecting Your PrivacyTerms and ConditionsFraud PreventionInternational Rescue Committee is a 501(c)(3) not-for-profit organization. EIN number 13-5660870.Copyright © International Rescue Committee, 2025.\n\nCrisis WatchWho We AreWhere We WorkWhat We DoHow To HelpLatestCareersContact UsDonor HelpCode of ConductEthics HotlineOur efficiency87% Program services7% Management and general6% FundraisingDonateJoin our mailing list\n    Get the latest news about the IRC's innovative programs, compelling stories about our clients and how you can make a difference.\n     \n\n  \n  \n          \n        \n                  \n \n    \nSubscribeFollow Us\n\nCrisis WatchWho We AreWhere We WorkWhat We DoHow To HelpLatestCareersContact UsDonor HelpCode of ConductEthics HotlineOur efficiency87% Program services7% Management and general6% FundraisingDonateJoin our mailing list\n    Get the latest news about the IRC's innovative programs, compelling stories about our clients and how you can make a difference.\n     \n\n  \n  \n          \n        \n                  \n \n    \nSubscribeFollow Us\n\nCrisis WatchWho We AreWhere We WorkWhat We DoHow To HelpLatestCareersContact UsDonor HelpCode of ConductEthics Hotline\n\nCrisis Watch\n\nCrisis Watch\n\nWho We AreWhere We WorkWhat We DoHow To HelpLatestCareersContact UsDonor HelpCode of ConductEthics Hotline\n\nOur efficiency87% Program services7% Management and general6% FundraisingDonate\n\nOur efficiency87% Program services7% Management and general6% FundraisingDonate\n\nOur efficiency87% Program services7% Management and general6% FundraisingDonate\n\nOur efficiency\n\n87% Program services7% Management and general6% FundraisingDonate\n\n87% Program services7% Management and general6% FundraisingDonate\n\nDonate\n\nJoin our mailing list\n    Get the latest news about the IRC's innovative programs, compelling stories about our clients and how you can make a difference.\n     \n\n  \n  \n          \n        \n                  \n \n    \nSubscribeFollow Us\n\nJoin our mailing list\n    Get the latest news about the IRC's innovative programs, compelling stories about our clients and how you can make a difference.\n     \n\n  \n  \n          \n        \n                  \n \n    \nSubscribe\n\nJoin our mailing list\n\nGet the latest news about the IRC's innovative programs, compelling stories about our clients and how you can make a difference.\n     \n\n  \n  \n          \n        \n                  \n \n    \nSubscribe\n\nFollow Us\n\nFollow Us\n\nRescue Websites:U.S./GlobalUKGermanySwedenEUKoreaPhone Opt OutRespecting Your PrivacyTerms and ConditionsFraud PreventionInternational Rescue Committee is a 501(c)(3) not-for-profit organization. EIN number 13-5660870.Copyright © International Rescue Committee, 2025.\n\nRescue Websites:U.S./GlobalUKGermanySwedenEUKoreaPhone Opt OutRespecting Your PrivacyTerms and ConditionsFraud PreventionInternational Rescue Committee is a 501(c)(3) not-for-profit organization. EIN number 13-5660870.Copyright © International Rescue Committee, 2025.\n\nRescue Websites:U.S./GlobalUKGermanySwedenEUKorea\n\nRescue Websites:U.S./GlobalUKGermanySwedenEUKorea\n\nRescue Websites:U.S./GlobalUKGermanySwedenEUKorea\n\nPhone Opt OutRespecting Your PrivacyTerms and ConditionsFraud Prevention\n\nPhone Opt OutRespecting Your PrivacyTerms and ConditionsFraud Prevention\n\nPhone Opt OutRespecting Your PrivacyTerms and ConditionsFraud Prevention\n\nInternational Rescue Committee is a 501(c)(3) not-for-profit organization. EIN number 13-5660870.\n\nInternational Rescue Committee is a 501(c)(3) not-for-profit organization. EIN number 13-5660870.\n\nCopyright © International Rescue Committee, 2025.\n\nCopyright © International Rescue Committee, 2025.\n\n×\n\n\n\n\n\n\n\nSearch\n\n×\n\n\n\n\n\n\n\nSearch\n\n×\n\n×\n\nSearch\n\nSearch\n\nSearch\n\nSearch\n\nSearch\n\nSearch",
  "date": "",
  "source_type": "NGO",
  "extracted_at": "2025-04-07T13:52:22.007470",
  "metadata": {
    "description": "Get the latest news, photos and videos spotlighting the world's worst humanitarian crises and the International Rescue Committee's work helping people devastated by conflict and disaster.",
    "og:site_name": "The IRC"
  },
  "relevance_score": 0.30000000000000004,
  "summary": "Read the article        Yemen War\n        A decade of war: 10 voices from Yemen\nRead their stories        Ukraine\n        How to help Ukraine\nRead the articleGaza crisisCeasefire reinstatement needed to avert worsening humanitarian disaster in GazaMarch 20, 2025Aid cutsHow U.S. aid cuts put millions in perilFebruary 28, 2025Breaking newsUnited States terminates thousands of aid programsFebruary 27, 2025Our commitmentMeeting the moment: A note from our CEOFebruary 26, 2025Press releasesThe IRC is deeply concerned by new wave of forced displacement amid military escalation in GazaApril 4, 2025Myanmar Earthquake: IRC Teams Report Unprecedented DestructionMarch 31, 2025Major earthquake measuring 7.7 shocks Myanmar, with tremors felt in Thailand and Bangladesh; IRC assessing and preparing to respond to humanitarian needsMarch 28, 2025A decade of conflict in Yemen: Humanitarian lifeline on the brink, warns the IRCMarch 26, 2025Fire devastates displacement camp in northeast Nigeria, leaving over 12,500 people in dire need of urgent humanitarian assistance, IRC warnsMarch 25, 2025World Leaders Must Act Now to Avert Global Nutrition Crisis and Build Resilient Health Systems at Nutrition for Growth Summit, IRC warnsMarch 24, 2025Visit our media center\n\n\n\nCrisis WatchWho We AreWhere We WorkWhat We DoHow To HelpLatestCareersContact UsDonor HelpCode of ConductEthics HotlineOur efficiency87% Program services7% Management and general6% FundraisingDonateJoin our mailing list\n    Get the latest news about the IRC's innovative programs, compelling stories about our clients and how you can make a difference. Read the article        Yemen War\n        A decade of war: 10 voices from Yemen\nRead their stories        Ukraine\n        How to help Ukraine\nRead the articleGaza crisisCeasefire reinstatement needed to avert worsening humanitarian disaster in GazaMarch 20, 2025Aid cutsHow U.S. aid cuts put millions in perilFebruary 28, 2025Breaking newsUnited States terminates thousands of aid programsFebruary 27, 2025Our commitmentMeeting the moment: A note from our CEOFebruary 26, 2025Press releasesThe IRC is deeply concerned by new wave of forced displacement amid military escalation in GazaApril 4, 2025Myanmar Earthquake: IRC Teams Report Unprecedented DestructionMarch 31, 2025Major earthquake measuring 7.7 shocks Myanmar, with tremors felt in Thailand and Bangladesh; IRC assessing and preparing to respond to humanitarian needsMarch 28, 2025A decade of conflict in Yemen: Humanitarian lifeline on the brink, warns the IRCMarch 26, 2025Fire devastates displacement camp in northeast Nigeria, leaving over 12,500 people in dire need of urgent humanitarian assistance, IRC warnsMarch 25, 2025World Leaders Must Act Now to Avert Global Nutrition Crisis and Build Resilient Health Systems at Nutrition for Growth Summit, IRC warnsMarch 24, 2025Visit our media center\n\nNews & features        World Health Day\n        Meet Duha: A nurse in the world’s largest Syrian refugee camp\nRead Duha's story        Urgent Appeal\n        Myanmar earthquake: What’s happening and how to help? Read the article        Yemen War\n        A decade of war: 10 voices from Yemen\nRead their stories        Ukraine\n        How to help Ukraine\nRead the articleGaza crisisCeasefire reinstatement needed to avert worsening humanitarian disaster in GazaMarch 20, 2025Aid cutsHow U.S. aid cuts put millions in perilFebruary 28, 2025Breaking newsUnited States terminates thousands of aid programsFebruary 27, 2025Our commitmentMeeting the moment: A note from our CEOFebruary 26, 2025Press releasesThe IRC is deeply concerned by new wave of forced displacement amid military escalation in GazaApril 4, 2025Myanmar Earthquake: IRC Teams Report Unprecedented DestructionMarch 31, 2025Major earthquake measuring 7.7 shocks Myanmar, with tremors felt in Thailand and Bangladesh; IRC assessing and preparing to respond to humanitarian needsMarch 28, 2025A decade of conflict in Yemen: Humanitarian lifeline on the brink, warns the IRCMarch 26, 2025Fire devastates displacement camp in northeast Nigeria, leaving over 12,500 people in dire need of urgent humanitarian assistance, IRC warnsMarch 25, 2025World Leaders Must Act Now to Avert Global Nutrition Crisis and Build Resilient Health Systems at Nutrition for Growth Summit, IRC warnsMarch 24, 2025Visit our media center\n\nNews & features        World Health Day\n        Meet Duha: A nurse in the world’s largest Syrian refugee camp\nRead Duha's story        Urgent Appeal\n        Myanmar earthquake: What’s happening and how to help? aid cuts put millions in perilFebruary 28, 2025Breaking newsUnited States terminates thousands of aid programsFebruary 27, 2025Our commitmentMeeting the moment: A note from our CEOFebruary 26, 2025\n\nNews & features        World Health Day\n        Meet Duha: A nurse in the world’s largest Syrian refugee camp\nRead Duha's story        Urgent Appeal\n        Myanmar earthquake: What’s happening and how to help? aid cuts put millions in perilFebruary 28, 2025Breaking newsUnited States terminates thousands of aid programsFebruary 27, 2025Our commitmentMeeting the moment: A note from our CEOFebruary 26, 2025\n\nNews & features\n\nNews & features\n\nWorld Health Day\n        Meet Duha: A nurse in the world’s largest Syrian refugee camp\nRead Duha's story        Urgent Appeal\n        Myanmar earthquake: What’s happening and how to help? aid cuts put millions in perilFebruary 28, 2025Breaking newsUnited States terminates thousands of aid programsFebruary 27, 2025Our commitmentMeeting the moment: A note from our CEOFebruary 26, 2025\n\nWorld Health Day\n        Meet Duha: A nurse in the world’s largest Syrian refugee camp\nRead Duha's story\n\nWorld Health Day\n        Meet Duha: A nurse in the world’s largest Syrian refugee camp\nRead Duha's story\n\nWorld Health Day\n\nMeet Duha: A nurse in the world’s largest Syrian refugee camp\n\nRead Duha's story\n\nRead Duha's story\n\nUrgent Appeal\n        Myanmar earthquake: What’s happening and how to help? Read the article\n\nRead the article\n\nYemen War\n        A decade of war: 10 voices from Yemen\nRead their stories\n\nYemen War\n        A decade of war: 10 voices from Yemen\nRead their stories\n\nYemen War\n\nA decade of war: 10 voices from Yemen\n\nRead their stories\n\nRead their stories\n\nUkraine\n        How to help Ukraine\nRead the article\n\nUkraine\n        How to help Ukraine\nRead the article\n\nUkraine\n\nHow to help Ukraine\n\nRead the article\n\nRead the article\n\nGaza crisisCeasefire reinstatement needed to avert worsening humanitarian disaster in GazaMarch 20, 2025\n\nGaza crisisCeasefire reinstatement needed to avert worsening humanitarian disaster in GazaMarch 20, 2025\n\nGaza crisis\n\nGaza crisis\n\nCeasefire reinstatement needed to avert worsening humanitarian disaster in Gaza\n\nMarch 20, 2025\n\nMarch 20, 2025\n\nAid cutsHow U.S. economy\n\nMarch 18, 2025\n\nMarch 18, 2025\n\nInnovationIRC named one of the most innovative companies of 2025March 17, 2025\n\nInnovationIRC named one of the most innovative companies of 2025March 17, 2025\n\nInnovation\n\nInnovation\n\nIRC named one of the most innovative companies of 2025\n\nMarch 17, 2025\n\nMarch 17, 2025\n\nOrigins of the IRC7 facts about Albert Einstein that may surprise youMarch 17, 2025\n\nOrigins of the IRC7 facts about Albert Einstein that may surprise youMarch 17, 2025\n\nOrigins of the IRC\n\nOrigins of the IRC\n\n7 facts about Albert Einstein that may surprise you\n\nMarch 17, 2025\n\nMarch 17, 2025\n\nPathways to safetyWhat is humanitarian parole?March 7, 2025\n\nPathways to safetyWhat is humanitarian parole?March 7, 2025\n\nPathways to safety\n\nPathways to safety\n\nWhat is humanitarian parole? March 7, 2025\n\nMarch 7, 2025\n\nInside the IRCImpactful giving: How your donation makes a differenceMarch 7, 2025\n\nInside the IRCImpactful giving: How your donation makes a differenceMarch 7, 2025\n\nInside the IRC\n\nInside the IRC\n\nImpactful giving: How your donation makes a difference\n\nMarch 7, 2025\n\nMarch 7, 2025\n\nHumanitarian aidU.S. aid cuts put millions in peril\n\nFebruary 28, 2025\n\nFebruary 28, 2025\n\nBreaking newsUnited States terminates thousands of aid programsFebruary 27, 2025\n\nBreaking newsUnited States terminates thousands of aid programsFebruary 27, 2025\n\nBreaking news\n\nBreaking news\n\nUnited States terminates thousands of aid programs\n\nFebruary 27, 2025\n\nFebruary 27, 2025\n\nOur commitmentMeeting the moment: A note from our CEOFebruary 26, 2025\n\nOur commitmentMeeting the moment: A note from our CEOFebruary 26, 2025\n\nOur commitment\n\nOur commitment\n\nMeeting the moment: A note from our CEO\n\nFebruary 26, 2025\n\nFebruary 26, 2025\n\nPress releasesThe IRC is deeply concerned by new wave of forced displacement amid military escalation in GazaApril 4, 2025Myanmar Earthquake: IRC Teams Report Unprecedented DestructionMarch 31, 2025Major earthquake measuring 7.7 shocks Myanmar, with tremors felt in Thailand and Bangladesh; IRC assessing and preparing to respond to humanitarian needsMarch 28, 2025A decade of conflict in Yemen: Humanitarian lifeline on the brink, warns the IRCMarch 26, 2025Fire devastates displacement camp in northeast Nigeria, leaving over 12,500 people in dire need of urgent humanitarian assistance, IRC warnsMarch 25, 2025World Leaders Must Act Now to Avert Global Nutrition Crisis and Build Resilient Health Systems at Nutrition for Growth Summit, IRC warnsMarch 24, 2025Visit our media center\n\nPress releasesThe IRC is deeply concerned by new wave of forced displacement amid military escalation in GazaApril 4, 2025Myanmar Earthquake: IRC Teams Report Unprecedented DestructionMarch 31, 2025Major earthquake measuring 7.7 shocks Myanmar, with tremors felt in Thailand and Bangladesh; IRC assessing and preparing to respond to humanitarian needsMarch 28, 2025A decade of conflict in Yemen: Humanitarian lifeline on the brink, warns the IRCMarch 26, 2025Fire devastates displacement camp in northeast Nigeria, leaving over 12,500 people in dire need of urgent humanitarian assistance, IRC warnsMarch 25, 2025World Leaders Must Act Now to Avert Global Nutrition Crisis and Build Resilient Health Systems at Nutrition for Growth Summit, IRC warnsMarch 24, 2025Visit our media center\n\nPress releases\n\nPress releases\n\nThe IRC is deeply concerned by new wave of forced displacement amid military escalation in GazaApril 4, 2025Myanmar Earthquake: IRC Teams Report Unprecedented DestructionMarch 31, 2025Major earthquake measuring 7.7 shocks Myanmar, with tremors felt in Thailand and Bangladesh; IRC assessing and preparing to respond to humanitarian needsMarch 28, 2025A decade of conflict in Yemen: Humanitarian lifeline on the brink, warns the IRCMarch 26, 2025Fire devastates displacement camp in northeast Nigeria, leaving over 12,500 people in dire need of urgent humanitarian assistance, IRC warnsMarch 25, 2025World Leaders Must Act Now to Avert Global Nutrition Crisis and Build Resilient Health Systems at Nutrition for Growth Summit, IRC warnsMarch 24, 2025Visit our media center\n\nThe IRC is deeply concerned by new wave of forced displacement amid military escalation in GazaApril 4, 2025Myanmar Earthquake: IRC Teams Report Unprecedented DestructionMarch 31, 2025Major earthquake measuring 7.7 shocks Myanmar, with tremors felt in Thailand and Bangladesh; IRC assessing and preparing to respond to humanitarian needsMarch 28, 2025A decade of conflict in Yemen: Humanitarian lifeline on the brink, warns the IRCMarch 26, 2025Fire devastates displacement camp in northeast Nigeria, leaving over 12,500 people in dire need of urgent humanitarian assistance, IRC warnsMarch 25, 2025World Leaders Must Act Now to Avert Global Nutrition Crisis and Build Resilient Health Systems at Nutrition for Growth Summit, IRC warnsMarch 24, 2025Visit our media center\n\nThe IRC is deeply concerned by new wave of forced displacement amid military escalation in GazaApril 4, 2025Myanmar Earthquake: IRC Teams Report Unprecedented DestructionMarch 31, 2025Major earthquake measuring 7.7 shocks Myanmar, with tremors felt in Thailand and Bangladesh; IRC assessing and preparing to respond to humanitarian needsMarch 28, 2025A decade of conflict in Yemen: Humanitarian lifeline on the brink, warns the IRCMarch 26, 2025Fire devastates displacement camp in northeast Nigeria, leaving over 12,500 people in dire need of urgent humanitarian assistance, IRC warnsMarch 25, 2025World Leaders Must Act Now to Avert Global Nutrition Crisis and Build Resilient Health Systems at Nutrition for Growth Summit, IRC warnsMarch 24, 2025Visit our media center\n\nThe IRC is deeply concerned by new wave of forced displacement amid military escalation in GazaApril 4, 2025Myanmar Earthquake: IRC Teams Report Unprecedented DestructionMarch 31, 2025Major earthquake measuring 7.7 shocks Myanmar, with tremors felt in Thailand and Bangladesh; IRC assessing and preparing to respond to humanitarian needsMarch 28, 2025A decade of conflict in Yemen: Humanitarian lifeline on the brink, warns the IRCMarch 26, 2025Fire devastates displacement camp in northeast Nigeria, leaving over 12,500 people in dire need of urgent humanitarian assistance, IRC warnsMarch 25, 2025World Leaders Must Act Now to Avert Global Nutrition Crisis and Build Resilient Health Systems at Nutrition for Growth Summit, IRC warnsMarch 24, 2025\n\nThe IRC is deeply concerned by new wave of forced displacement amid military escalation in GazaApril 4, 2025\n\nThe IRC is deeply concerned by new wave of forced displacement amid military escalation in Gaza\n\nApril 4, 2025\n\nApril 4, 2025\n\nMyanmar Earthquake: IRC Teams Report Unprecedented DestructionMarch 31, 2025\n\nMyanmar Earthquake: IRC Teams Report Unprecedented Destruction\n\nMarch 31, 2025\n\nMarch 31, 2025\n\nMajor earthquake measuring 7.7 shocks Myanmar, with tremors felt in Thailand and Bangladesh; IRC assessing and preparing to respond to humanitarian needsMarch 28, 2025\n\nMajor earthquake measuring 7.7 shocks Myanmar, with tremors felt in Thailand and Bangladesh; IRC assessing and preparing to respond to humanitarian needs\n\nMarch 28, 2025\n\nMarch 28, 2025\n\nA decade of conflict in Yemen: Humanitarian lifeline on the brink, warns the IRCMarch 26, 2025\n\nA decade of conflict in Yemen: Humanitarian lifeline on the brink, warns the IRC\n\nMarch 26, 2025\n\nMarch 26, 2025\n\nFire devastates displacement camp in northeast Nigeria, leaving over 12,500 people in dire need of urgent humanitarian assistance, IRC warnsMarch 25, 2025\n\nFire devastates displacement camp in northeast Nigeria, leaving over 12,500 people in dire need of urgent humanitarian assistance, IRC warns\n\nMarch 25, 2025\n\nMarch 25, 2025\n\nWorld Leaders Must Act Now to Avert Global Nutrition Crisis and Build Resilient Health Systems at Nutrition for Growth Summit, IRC warnsMarch 24, 2025\n\nWorld Leaders Must Act Now to Avert Global Nutrition Crisis and Build Resilient Health Systems at Nutrition for Growth Summit, IRC warns\n\nMarch 24, 2025\n\nMarch 24, 2025\n\nVisit our media center\n\nVisit our media center\n\nCrisis WatchWho We AreWhere We WorkWhat We DoHow To HelpLatestCareersContact UsDonor HelpCode of ConductEthics HotlineOur efficiency87% Program services7% Management and general6% FundraisingDonateJoin our mailing list\n    Get the latest news about the IRC's innovative programs, compelling stories about our clients and how you can make a difference. SubscribeFollow Us\n\nCrisis WatchWho We AreWhere We WorkWhat We DoHow To HelpLatestCareersContact UsDonor HelpCode of ConductEthics Hotline\n\nCrisis Watch\n\nCrisis Watch\n\nWho We AreWhere We WorkWhat We DoHow To HelpLatestCareersContact UsDonor HelpCode of ConductEthics Hotline\n\nOur efficiency87% Program services7% Management and general6% FundraisingDonate\n\nOur efficiency87% Program services7% Management and general6% FundraisingDonate\n\nOur efficiency87% Program services7% Management and general6% FundraisingDonate\n\nOur efficiency\n\n87% Program services7% Management and general6% FundraisingDonate\n\n87% Program services7% Management and general6% FundraisingDonate\n\nDonate\n\nJoin our mailing list\n    Get the latest news about the IRC's innovative programs, compelling stories about our clients and how you can make a difference.",
  "entities": {
    "countries": [
      "germany",
      "syria",
      "united states",
      "yemen"
    ],
    "organizations": [
      "un",
      "who"
    ],
    "key_issues": [
      "concern",
      "crisis",
      "nation",
      "state",
      "program",
      "origin",
      "humanitarian",
      "aid",
      "assistance",
      "economic",
      "economy",
      "un",
      "organization"
    ]
  },
  "committee": "Third Committee",
  "topic": "Affirming the rights of communities displaced by violence"
}