{
  "url": "https://www.icrc.org/en/article/devastating-earthquake-myanmar-icrc-responds-help-people-ground",
  "title": "Myanmar: Response to devastating earthquake | ICRC",
  "text": "Skip to main content\n\n\n\n\n\n\n\n\n\n\n\n\n\n            Article\n          \n\n01-04-2025\n\n\n\n\n\n5 languages\nEnglish\nFrançais\n中文\nРусский\nDeutsch\n\n\n\n\n\nDevastating earthquake in Myanmar: ICRC responds to help people on the ground\n\n\n        Providing medical supplies, access to clean water, critical supplies, and helping families keep in touch in the wake of disaster\n      \n\n\nMyanmar\n\n\n\n\nSituation on the groundHow our teams are helpingDonate now\n\n\n\n\n\n\n\n\n\n\n\n\nICRC\n\n\n\n\nThousands of people have been confirmed dead, with many more injured, and countless others displaced or missing after a powerful 7.7 magnitude earthquake struck Myanmar on 28 March 2025. Rescue operations are ongoing after the quake left a trail of destruction across several regions, including Mandalay, Sagaing and Shan State – compounding the suffering of people in areas already grappling with armed conflict, violence and instability.\n\n\n\n\n\n\n\n\n\n\n      ဤနောက်ဆုံးအခြေအနေရှင်းလင်းချက်ကို မြန်မာဘာသာဖြင့် ဤနေရာတွင် ဖတ်ရှုနိုင်ပါသည်။\n  \n\n\n\nဝင်ရောက်ဖတ်ရှုရန်\n\n\n\n\n\n\n\n\nEntire neighbourhoods have been reduced to rubble. Homes, hospitals, schools, bridges, and essential infrastructure have been destroyed. Many people have lost access to health care, clean water, and even the ability to contact their loved ones. In some areas, temperatures are soaring above 40°C, intensifying the suffering of those left without shelter.\n\n\n\n\n\n\n\nReaching those in urgent need\nAmid this devastation, the International Committee of the Red Cross (ICRC), together with the Myanmar Red Cross Society and Red Cross and Red Crescent Movement partners, is delivering life-saving support.\nOur priority is to reach those in urgent need across the region, ensuring that families receive essential aid during this difficult time. \nIn Mandalay, where the ICRC has an operational sub-delegation with 45 staff, teams have been on the ground from the outset – working side-by-side with local responders and coordinating with health authorities to reach those in urgent need.\n\n\nEmergency medical aid for the injured\nOn 30 March 2025, just two days after the quake, a joint Red Cross convoy left Yangon carrying vital emergency supplies. This included:\n\nSix emergency health kits, each capable of covering the medical needs of 10,000 people for three months\n600 body bags for the dignified recovery and identification of the deceased\nSupport for Myanmar Red Cross emergency teams conducting search-and-rescue and first aid operations\n\n\n\n\nEssential items for those helping on the front lines\nAfter discussions with front liners and analyzing the situation on the ground, we have provided the following essential items to assist in their work:\n\nHelmets and heavy duty gloves\nRopes, goggles, and items to assist in the search \nStretchers to carry the wounded\n\n\n\n\nSafe water, sanitation and disease prevention\nAccess to clean water is critical in any emergency. To reduce the risk of cholera and diarrhoea outbreaks, the ICRC and Myanmar Red Cross are:\n\nDeploying water treatment units in Mandalay, Sagaing and Nay Pyi Taw to reach 2,500 people\nDistributing chlorine tablets and repairing water systems\nTraining local staff to safely operate water treatment systems\n\n\n\n\nProviding shelter and essential supplies\nICRC emergency stocks pre-positioned near the epicentre are now being mobilized to support communities left with nothing. These include:\n\nFood rations (rice, pulses, and oil)\nTarpaulins and essential household kits\nPlans for distributions are already underway to reach the most vulnerable families\n\n\n\n\nHelping families reconnect\nIn crises like this, families are often torn apart. The ICRC and Red Cross partners are ready to help people reconnect with missing loved ones through the Restoring Family Links programme.\n\n\n\n\n\n\n\n\n\n\n\n\nWe were able to respond within a day through our front liners, which is the most critical timing in emergency situations. I would like to thank all the first responders for their efforts and collaboration in ensuring our assistance reached those in most need, quickly and effectively.\n\n\n      Kyaw Phyo Khaing\n  \n\n      ICRC staff\n  \n\n\n\n\n\n\n\nMy family and I are also survivors of this earthquake. We are currently living in a school compound as my apartment was seriously damaged. So I can imagine how people are dealing with these difficult situations and the challenges they face regarding food and shelter. At the same time, as an ICRC staff, I have adapted to my current situation and used this experience to learn about the most pressing needs and challenges of the communities.\n\n\n      Ko Mohamed Ahyup\n  \n\n      ICRC staff\n  \n\n\n\n\n\n\n\n\n\n\n\n\n\n\n\n\n\n\n\n\n\n\n      Urgent help needed in Myanmar\n  \n\n\n\n      Following the devastating earthquake that has struck Myanmar and bordering regions, the scale of destruction is overwhelming — many are injured, displaced, or missing, with casualty numbers rising by the hour. With your support, we can bring life-saving aid where it’s needed the most.\n\r\nThank you for your generous support.\n  \n\n\nDonate today\n\n\n\n\n\n\n\n\n\n\n\n\n\n\n\n\n\n\n\n\n\n\n\n\n\nICRC\n\n\n\n\n\n\n\n\n\n\nRelated articles\n\n\n\n\n\n\n\n\n\n\n\n\n\n\n\nArticle\n\n04-04-2025\n\n\n\n\nFrequently asked questions about the ICRC's work in Myanmar\n\n\n\n\n\n\n\n\n\n\n\n\n\n\n\n\n\n\nArticle\n\n04-04-2025\n\n\n\n\nIn the minefields of Iraq, Noora works to restore life and hope to her homeland\n\n\n\n\n\n\n\n\n\n\n\n\n\n\n\n\n\n\nArticle\n\n04-04-2025\n\n\n\n\nMyanmar: Landmine awareness saves lives amid conflict and natural disasters\n\n\n\n\n\n\n\n\n\n\n\n\n\n\n\nMore articles\n\nSkip to main content\n\n\n\n\n\n\n\n\n\n\n\n\n\n            Article\n          \n\n01-04-2025\n\n\n\n\n\n5 languages\nEnglish\nFrançais\n中文\nРусский\nDeutsch\n\n\n\n\n\nDevastating earthquake in Myanmar: ICRC responds to help people on the ground\n\n\n        Providing medical supplies, access to clean water, critical supplies, and helping families keep in touch in the wake of disaster\n      \n\n\nMyanmar\n\n\n\n\nSituation on the groundHow our teams are helpingDonate now\n\n\n\n\n\n\n\n\n\n\n\n\nICRC\n\n\n\n\nThousands of people have been confirmed dead, with many more injured, and countless others displaced or missing after a powerful 7.7 magnitude earthquake struck Myanmar on 28 March 2025. Rescue operations are ongoing after the quake left a trail of destruction across several regions, including Mandalay, Sagaing and Shan State – compounding the suffering of people in areas already grappling with armed conflict, violence and instability.\n\n\n\n\n\n\n\n\n\n\n      ဤနောက်ဆုံးအခြေအနေရှင်းလင်းချက်ကို မြန်မာဘာသာဖြင့် ဤနေရာတွင် ဖတ်ရှုနိုင်ပါသည်။\n  \n\n\n\nဝင်ရောက်ဖတ်ရှုရန်\n\n\n\n\n\n\n\n\nEntire neighbourhoods have been reduced to rubble. Homes, hospitals, schools, bridges, and essential infrastructure have been destroyed. Many people have lost access to health care, clean water, and even the ability to contact their loved ones. In some areas, temperatures are soaring above 40°C, intensifying the suffering of those left without shelter.\n\n\n\n\n\n\n\nReaching those in urgent need\nAmid this devastation, the International Committee of the Red Cross (ICRC), together with the Myanmar Red Cross Society and Red Cross and Red Crescent Movement partners, is delivering life-saving support.\nOur priority is to reach those in urgent need across the region, ensuring that families receive essential aid during this difficult time. \nIn Mandalay, where the ICRC has an operational sub-delegation with 45 staff, teams have been on the ground from the outset – working side-by-side with local responders and coordinating with health authorities to reach those in urgent need.\n\n\nEmergency medical aid for the injured\nOn 30 March 2025, just two days after the quake, a joint Red Cross convoy left Yangon carrying vital emergency supplies. This included:\n\nSix emergency health kits, each capable of covering the medical needs of 10,000 people for three months\n600 body bags for the dignified recovery and identification of the deceased\nSupport for Myanmar Red Cross emergency teams conducting search-and-rescue and first aid operations\n\n\n\n\nEssential items for those helping on the front lines\nAfter discussions with front liners and analyzing the situation on the ground, we have provided the following essential items to assist in their work:\n\nHelmets and heavy duty gloves\nRopes, goggles, and items to assist in the search \nStretchers to carry the wounded\n\n\n\n\nSafe water, sanitation and disease prevention\nAccess to clean water is critical in any emergency. To reduce the risk of cholera and diarrhoea outbreaks, the ICRC and Myanmar Red Cross are:\n\nDeploying water treatment units in Mandalay, Sagaing and Nay Pyi Taw to reach 2,500 people\nDistributing chlorine tablets and repairing water systems\nTraining local staff to safely operate water treatment systems\n\n\n\n\nProviding shelter and essential supplies\nICRC emergency stocks pre-positioned near the epicentre are now being mobilized to support communities left with nothing. These include:\n\nFood rations (rice, pulses, and oil)\nTarpaulins and essential household kits\nPlans for distributions are already underway to reach the most vulnerable families\n\n\n\n\nHelping families reconnect\nIn crises like this, families are often torn apart. The ICRC and Red Cross partners are ready to help people reconnect with missing loved ones through the Restoring Family Links programme.\n\n\n\n\n\n\n\n\n\n\n\n\nWe were able to respond within a day through our front liners, which is the most critical timing in emergency situations. I would like to thank all the first responders for their efforts and collaboration in ensuring our assistance reached those in most need, quickly and effectively.\n\n\n      Kyaw Phyo Khaing\n  \n\n      ICRC staff\n  \n\n\n\n\n\n\n\nMy family and I are also survivors of this earthquake. We are currently living in a school compound as my apartment was seriously damaged. So I can imagine how people are dealing with these difficult situations and the challenges they face regarding food and shelter. At the same time, as an ICRC staff, I have adapted to my current situation and used this experience to learn about the most pressing needs and challenges of the communities.\n\n\n      Ko Mohamed Ahyup\n  \n\n      ICRC staff\n  \n\n\n\n\n\n\n\n\n\n\n\n\n\n\n\n\n\n\n\n\n\n\n      Urgent help needed in Myanmar\n  \n\n\n\n      Following the devastating earthquake that has struck Myanmar and bordering regions, the scale of destruction is overwhelming — many are injured, displaced, or missing, with casualty numbers rising by the hour. With your support, we can bring life-saving aid where it’s needed the most.\n\r\nThank you for your generous support.\n  \n\n\nDonate today\n\n\n\n\n\n\n\n\n\n\n\n\n\n\n\n\n\n\n\n\n\n\n\n\n\nICRC\n\n\n\n\n\n\n\n\n\n\nRelated articles\n\n\n\n\n\n\n\n\n\n\n\n\n\n\n\nArticle\n\n04-04-2025\n\n\n\n\nFrequently asked questions about the ICRC's work in Myanmar\n\n\n\n\n\n\n\n\n\n\n\n\n\n\n\n\n\n\nArticle\n\n04-04-2025\n\n\n\n\nIn the minefields of Iraq, Noora works to restore life and hope to her homeland\n\n\n\n\n\n\n\n\n\n\n\n\n\n\n\n\n\n\nArticle\n\n04-04-2025\n\n\n\n\nMyanmar: Landmine awareness saves lives amid conflict and natural disasters\n\n\n\n\n\n\n\n\n\n\n\n\n\n\n\nMore articles\n\nArticle\n          \n\n01-04-2025\n\n\n\n\n\n5 languages\nEnglish\nFrançais\n中文\nРусский\nDeutsch\n\n\n\n\n\nDevastating earthquake in Myanmar: ICRC responds to help people on the ground\n\n\n        Providing medical supplies, access to clean water, critical supplies, and helping families keep in touch in the wake of disaster\n      \n\n\nMyanmar\n\n\n\n\nSituation on the groundHow our teams are helpingDonate now\n\n\n\n\n\n\n\n\n\n\n\n\nICRC\n\n\n\n\nThousands of people have been confirmed dead, with many more injured, and countless others displaced or missing after a powerful 7.7 magnitude earthquake struck Myanmar on 28 March 2025. Rescue operations are ongoing after the quake left a trail of destruction across several regions, including Mandalay, Sagaing and Shan State – compounding the suffering of people in areas already grappling with armed conflict, violence and instability.\n\n\n\n\n\n\n\n\n\n\n      ဤနောက်ဆုံးအခြေအနေရှင်းလင်းချက်ကို မြန်မာဘာသာဖြင့် ဤနေရာတွင် ဖတ်ရှုနိုင်ပါသည်။\n  \n\n\n\nဝင်ရောက်ဖတ်ရှုရန်\n\n\n\n\n\n\n\n\nEntire neighbourhoods have been reduced to rubble. Homes, hospitals, schools, bridges, and essential infrastructure have been destroyed. Many people have lost access to health care, clean water, and even the ability to contact their loved ones. In some areas, temperatures are soaring above 40°C, intensifying the suffering of those left without shelter.\n\n\n\n\n\n\n\nReaching those in urgent need\nAmid this devastation, the International Committee of the Red Cross (ICRC), together with the Myanmar Red Cross Society and Red Cross and Red Crescent Movement partners, is delivering life-saving support.\nOur priority is to reach those in urgent need across the region, ensuring that families receive essential aid during this difficult time. \nIn Mandalay, where the ICRC has an operational sub-delegation with 45 staff, teams have been on the ground from the outset – working side-by-side with local responders and coordinating with health authorities to reach those in urgent need.\n\n\nEmergency medical aid for the injured\nOn 30 March 2025, just two days after the quake, a joint Red Cross convoy left Yangon carrying vital emergency supplies. This included:\n\nSix emergency health kits, each capable of covering the medical needs of 10,000 people for three months\n600 body bags for the dignified recovery and identification of the deceased\nSupport for Myanmar Red Cross emergency teams conducting search-and-rescue and first aid operations\n\n\n\n\nEssential items for those helping on the front lines\nAfter discussions with front liners and analyzing the situation on the ground, we have provided the following essential items to assist in their work:\n\nHelmets and heavy duty gloves\nRopes, goggles, and items to assist in the search \nStretchers to carry the wounded\n\n\n\n\nSafe water, sanitation and disease prevention\nAccess to clean water is critical in any emergency. To reduce the risk of cholera and diarrhoea outbreaks, the ICRC and Myanmar Red Cross are:\n\nDeploying water treatment units in Mandalay, Sagaing and Nay Pyi Taw to reach 2,500 people\nDistributing chlorine tablets and repairing water systems\nTraining local staff to safely operate water treatment systems\n\n\n\n\nProviding shelter and essential supplies\nICRC emergency stocks pre-positioned near the epicentre are now being mobilized to support communities left with nothing. These include:\n\nFood rations (rice, pulses, and oil)\nTarpaulins and essential household kits\nPlans for distributions are already underway to reach the most vulnerable families\n\n\n\n\nHelping families reconnect\nIn crises like this, families are often torn apart. The ICRC and Red Cross partners are ready to help people reconnect with missing loved ones through the Restoring Family Links programme.\n\n\n\n\n\n\n\n\n\n\n\n\nWe were able to respond within a day through our front liners, which is the most critical timing in emergency situations. I would like to thank all the first responders for their efforts and collaboration in ensuring our assistance reached those in most need, quickly and effectively.\n\n\n      Kyaw Phyo Khaing\n  \n\n      ICRC staff\n  \n\n\n\n\n\n\n\nMy family and I are also survivors of this earthquake. We are currently living in a school compound as my apartment was seriously damaged. So I can imagine how people are dealing with these difficult situations and the challenges they face regarding food and shelter. At the same time, as an ICRC staff, I have adapted to my current situation and used this experience to learn about the most pressing needs and challenges of the communities.\n\n\n      Ko Mohamed Ahyup\n  \n\n      ICRC staff\n  \n\n\n\n\n\n\n\n\n\n\n\n\n\n\n\n\n\n\n\n\n\n\n      Urgent help needed in Myanmar\n  \n\n\n\n      Following the devastating earthquake that has struck Myanmar and bordering regions, the scale of destruction is overwhelming — many are injured, displaced, or missing, with casualty numbers rising by the hour. With your support, we can bring life-saving aid where it’s needed the most.\n\r\nThank you for your generous support.\n  \n\n\nDonate today\n\n\n\n\n\n\n\n\n\n\n\n\n\n\n\n\n\n\n\n\n\n\n\n\n\nICRC\n\n\n\n\n\n\n\n\n\n\nRelated articles\n\n\n\n\n\n\n\n\n\n\n\n\n\n\n\nArticle\n\n04-04-2025\n\n\n\n\nFrequently asked questions about the ICRC's work in Myanmar\n\n\n\n\n\n\n\n\n\n\n\n\n\n\n\n\n\n\nArticle\n\n04-04-2025\n\n\n\n\nIn the minefields of Iraq, Noora works to restore life and hope to her homeland\n\n\n\n\n\n\n\n\n\n\n\n\n\n\n\n\n\n\nArticle\n\n04-04-2025\n\n\n\n\nMyanmar: Landmine awareness saves lives amid conflict and natural disasters\n\n\n\n\n\n\n\n\n\n\n\n\n\n\n\nMore articles\n\nArticle\n          \n\n01-04-2025\n\n\n\n\n\n5 languages\nEnglish\nFrançais\n中文\nРусский\nDeutsch\n\n\n\n\n\nDevastating earthquake in Myanmar: ICRC responds to help people on the ground\n\n\n        Providing medical supplies, access to clean water, critical supplies, and helping families keep in touch in the wake of disaster\n      \n\n\nMyanmar\n\n\n\n\nSituation on the groundHow our teams are helpingDonate now\n\n\n\n\n\n\n\n\n\n\n\n\nICRC\n\n\n\n\nThousands of people have been confirmed dead, with many more injured, and countless others displaced or missing after a powerful 7.7 magnitude earthquake struck Myanmar on 28 March 2025. Rescue operations are ongoing after the quake left a trail of destruction across several regions, including Mandalay, Sagaing and Shan State – compounding the suffering of people in areas already grappling with armed conflict, violence and instability.\n\n\n\n\n\n\n\n\n\n\n      ဤနောက်ဆုံးအခြေအနေရှင်းလင်းချက်ကို မြန်မာဘာသာဖြင့် ဤနေရာတွင် ဖတ်ရှုနိုင်ပါသည်။\n  \n\n\n\nဝင်ရောက်ဖတ်ရှုရန်\n\n\n\n\n\n\n\n\nEntire neighbourhoods have been reduced to rubble. Homes, hospitals, schools, bridges, and essential infrastructure have been destroyed. Many people have lost access to health care, clean water, and even the ability to contact their loved ones. In some areas, temperatures are soaring above 40°C, intensifying the suffering of those left without shelter.\n\n\n\n\n\n\n\nReaching those in urgent need\nAmid this devastation, the International Committee of the Red Cross (ICRC), together with the Myanmar Red Cross Society and Red Cross and Red Crescent Movement partners, is delivering life-saving support.\nOur priority is to reach those in urgent need across the region, ensuring that families receive essential aid during this difficult time. \nIn Mandalay, where the ICRC has an operational sub-delegation with 45 staff, teams have been on the ground from the outset – working side-by-side with local responders and coordinating with health authorities to reach those in urgent need.\n\n\nEmergency medical aid for the injured\nOn 30 March 2025, just two days after the quake, a joint Red Cross convoy left Yangon carrying vital emergency supplies. This included:\n\nSix emergency health kits, each capable of covering the medical needs of 10,000 people for three months\n600 body bags for the dignified recovery and identification of the deceased\nSupport for Myanmar Red Cross emergency teams conducting search-and-rescue and first aid operations\n\n\n\n\nEssential items for those helping on the front lines\nAfter discussions with front liners and analyzing the situation on the ground, we have provided the following essential items to assist in their work:\n\nHelmets and heavy duty gloves\nRopes, goggles, and items to assist in the search \nStretchers to carry the wounded\n\n\n\n\nSafe water, sanitation and disease prevention\nAccess to clean water is critical in any emergency. To reduce the risk of cholera and diarrhoea outbreaks, the ICRC and Myanmar Red Cross are:\n\nDeploying water treatment units in Mandalay, Sagaing and Nay Pyi Taw to reach 2,500 people\nDistributing chlorine tablets and repairing water systems\nTraining local staff to safely operate water treatment systems\n\n\n\n\nProviding shelter and essential supplies\nICRC emergency stocks pre-positioned near the epicentre are now being mobilized to support communities left with nothing. These include:\n\nFood rations (rice, pulses, and oil)\nTarpaulins and essential household kits\nPlans for distributions are already underway to reach the most vulnerable families\n\n\n\n\nHelping families reconnect\nIn crises like this, families are often torn apart. The ICRC and Red Cross partners are ready to help people reconnect with missing loved ones through the Restoring Family Links programme.\n\n\n\n\n\n\n\n\n\n\n\n\nWe were able to respond within a day through our front liners, which is the most critical timing in emergency situations. I would like to thank all the first responders for their efforts and collaboration in ensuring our assistance reached those in most need, quickly and effectively.\n\n\n      Kyaw Phyo Khaing\n  \n\n      ICRC staff\n  \n\n\n\n\n\n\n\nMy family and I are also survivors of this earthquake. We are currently living in a school compound as my apartment was seriously damaged. So I can imagine how people are dealing with these difficult situations and the challenges they face regarding food and shelter. At the same time, as an ICRC staff, I have adapted to my current situation and used this experience to learn about the most pressing needs and challenges of the communities.\n\n\n      Ko Mohamed Ahyup\n  \n\n      ICRC staff\n  \n\n\n\n\n\n\n\n\n\n\n\n\n\n\n\n\n\n\n\n\n\n\n      Urgent help needed in Myanmar\n  \n\n\n\n      Following the devastating earthquake that has struck Myanmar and bordering regions, the scale of destruction is overwhelming — many are injured, displaced, or missing, with casualty numbers rising by the hour. With your support, we can bring life-saving aid where it’s needed the most.\n\r\nThank you for your generous support.\n  \n\n\nDonate today\n\n\n\n\n\n\n\n\n\n\n\n\n\n\n\n\n\n\n\n\n\n\n\n\n\nICRC\n\n\n\n\n\n\n\n\n\n\nRelated articles\n\n\n\n\n\n\n\n\n\n\n\n\n\n\n\nArticle\n\n04-04-2025\n\n\n\n\nFrequently asked questions about the ICRC's work in Myanmar\n\n\n\n\n\n\n\n\n\n\n\n\n\n\n\n\n\n\nArticle\n\n04-04-2025\n\n\n\n\nIn the minefields of Iraq, Noora works to restore life and hope to her homeland\n\n\n\n\n\n\n\n\n\n\n\n\n\n\n\n\n\n\nArticle\n\n04-04-2025\n\n\n\n\nMyanmar: Landmine awareness saves lives amid conflict and natural disasters\n\n\n\n\n\n\n\n\n\n\n\n\n\n\n\nMore articles\n\nArticle\n          \n\n01-04-2025\n\n\n\n\n\n5 languages\nEnglish\nFrançais\n中文\nРусский\nDeutsch\n\n\n\n\n\nDevastating earthquake in Myanmar: ICRC responds to help people on the ground\n\n\n        Providing medical supplies, access to clean water, critical supplies, and helping families keep in touch in the wake of disaster\n      \n\n\nMyanmar\n\n\n\n\nSituation on the groundHow our teams are helpingDonate now\n\n\n\n\n\n\n\n\n\n\n\n\nICRC\n\n\n\n\nThousands of people have been confirmed dead, with many more injured, and countless others displaced or missing after a powerful 7.7 magnitude earthquake struck Myanmar on 28 March 2025. Rescue operations are ongoing after the quake left a trail of destruction across several regions, including Mandalay, Sagaing and Shan State – compounding the suffering of people in areas already grappling with armed conflict, violence and instability.\n\n\n\n\n\n\n\n\n\n\n      ဤနောက်ဆုံးအခြေအနေရှင်းလင်းချက်ကို မြန်မာဘာသာဖြင့် ဤနေရာတွင် ဖတ်ရှုနိုင်ပါသည်။\n  \n\n\n\nဝင်ရောက်ဖတ်ရှုရန်\n\n\n\n\n\n\n\n\nEntire neighbourhoods have been reduced to rubble. Homes, hospitals, schools, bridges, and essential infrastructure have been destroyed. Many people have lost access to health care, clean water, and even the ability to contact their loved ones. In some areas, temperatures are soaring above 40°C, intensifying the suffering of those left without shelter.\n\n\n\n\n\n\n\nReaching those in urgent need\nAmid this devastation, the International Committee of the Red Cross (ICRC), together with the Myanmar Red Cross Society and Red Cross and Red Crescent Movement partners, is delivering life-saving support.\nOur priority is to reach those in urgent need across the region, ensuring that families receive essential aid during this difficult time. \nIn Mandalay, where the ICRC has an operational sub-delegation with 45 staff, teams have been on the ground from the outset – working side-by-side with local responders and coordinating with health authorities to reach those in urgent need.\n\n\nEmergency medical aid for the injured\nOn 30 March 2025, just two days after the quake, a joint Red Cross convoy left Yangon carrying vital emergency supplies. This included:\n\nSix emergency health kits, each capable of covering the medical needs of 10,000 people for three months\n600 body bags for the dignified recovery and identification of the deceased\nSupport for Myanmar Red Cross emergency teams conducting search-and-rescue and first aid operations\n\n\n\n\nEssential items for those helping on the front lines\nAfter discussions with front liners and analyzing the situation on the ground, we have provided the following essential items to assist in their work:\n\nHelmets and heavy duty gloves\nRopes, goggles, and items to assist in the search \nStretchers to carry the wounded\n\n\n\n\nSafe water, sanitation and disease prevention\nAccess to clean water is critical in any emergency. To reduce the risk of cholera and diarrhoea outbreaks, the ICRC and Myanmar Red Cross are:\n\nDeploying water treatment units in Mandalay, Sagaing and Nay Pyi Taw to reach 2,500 people\nDistributing chlorine tablets and repairing water systems\nTraining local staff to safely operate water treatment systems\n\n\n\n\nProviding shelter and essential supplies\nICRC emergency stocks pre-positioned near the epicentre are now being mobilized to support communities left with nothing. These include:\n\nFood rations (rice, pulses, and oil)\nTarpaulins and essential household kits\nPlans for distributions are already underway to reach the most vulnerable families\n\n\n\n\nHelping families reconnect\nIn crises like this, families are often torn apart. The ICRC and Red Cross partners are ready to help people reconnect with missing loved ones through the Restoring Family Links programme.\n\n\n\n\n\n\n\n\n\n\n\n\nWe were able to respond within a day through our front liners, which is the most critical timing in emergency situations. I would like to thank all the first responders for their efforts and collaboration in ensuring our assistance reached those in most need, quickly and effectively.\n\n\n      Kyaw Phyo Khaing\n  \n\n      ICRC staff\n  \n\n\n\n\n\n\n\nMy family and I are also survivors of this earthquake. We are currently living in a school compound as my apartment was seriously damaged. So I can imagine how people are dealing with these difficult situations and the challenges they face regarding food and shelter. At the same time, as an ICRC staff, I have adapted to my current situation and used this experience to learn about the most pressing needs and challenges of the communities.\n\n\n      Ko Mohamed Ahyup\n  \n\n      ICRC staff\n  \n\n\n\n\n\n\n\n\n\n\n\n\n\n\n\n\n\n\n\n\n\n\n      Urgent help needed in Myanmar\n  \n\n\n\n      Following the devastating earthquake that has struck Myanmar and bordering regions, the scale of destruction is overwhelming — many are injured, displaced, or missing, with casualty numbers rising by the hour. With your support, we can bring life-saving aid where it’s needed the most.\n\r\nThank you for your generous support.\n  \n\n\nDonate today\n\n\n\n\n\n\n\n\n\n\n\n\n\n\n\n\n\n\n\n\n\n\n\n\n\nICRC\n\n\n\n\n\n\n\n\n\n\nRelated articles\n\n\n\n\n\n\n\n\n\n\n\n\n\n\n\nArticle\n\n04-04-2025\n\n\n\n\nFrequently asked questions about the ICRC's work in Myanmar\n\n\n\n\n\n\n\n\n\n\n\n\n\n\n\n\n\n\nArticle\n\n04-04-2025\n\n\n\n\nIn the minefields of Iraq, Noora works to restore life and hope to her homeland\n\n\n\n\n\n\n\n\n\n\n\n\n\n\n\n\n\n\nArticle\n\n04-04-2025\n\n\n\n\nMyanmar: Landmine awareness saves lives amid conflict and natural disasters\n\n\n\n\n\n\n\n\n\n\n\n\n\n\n\nMore articles\n\nArticle\n          \n\n01-04-2025\n\n\n\n\n\n5 languages\nEnglish\nFrançais\n中文\nРусский\nDeutsch\n\n\n\n\n\nDevastating earthquake in Myanmar: ICRC responds to help people on the ground\n\n\n        Providing medical supplies, access to clean water, critical supplies, and helping families keep in touch in the wake of disaster\n      \n\n\nMyanmar\n\n\n\n\nSituation on the groundHow our teams are helpingDonate now\n\n\n\n\n\n\n\n\n\n\n\n\nICRC\n\n\n\n\nThousands of people have been confirmed dead, with many more injured, and countless others displaced or missing after a powerful 7.7 magnitude earthquake struck Myanmar on 28 March 2025. Rescue operations are ongoing after the quake left a trail of destruction across several regions, including Mandalay, Sagaing and Shan State – compounding the suffering of people in areas already grappling with armed conflict, violence and instability.\n\n\n\n\n\n\n\n\n\n\n      ဤနောက်ဆုံးအခြေအနေရှင်းလင်းချက်ကို မြန်မာဘာသာဖြင့် ဤနေရာတွင် ဖတ်ရှုနိုင်ပါသည်။\n  \n\n\n\nဝင်ရောက်ဖတ်ရှုရန်\n\n\n\n\n\n\n\n\nEntire neighbourhoods have been reduced to rubble. Homes, hospitals, schools, bridges, and essential infrastructure have been destroyed. Many people have lost access to health care, clean water, and even the ability to contact their loved ones. In some areas, temperatures are soaring above 40°C, intensifying the suffering of those left without shelter.\n\n\n\n\n\n\n\nReaching those in urgent need\nAmid this devastation, the International Committee of the Red Cross (ICRC), together with the Myanmar Red Cross Society and Red Cross and Red Crescent Movement partners, is delivering life-saving support.\nOur priority is to reach those in urgent need across the region, ensuring that families receive essential aid during this difficult time. \nIn Mandalay, where the ICRC has an operational sub-delegation with 45 staff, teams have been on the ground from the outset – working side-by-side with local responders and coordinating with health authorities to reach those in urgent need.\n\n\nEmergency medical aid for the injured\nOn 30 March 2025, just two days after the quake, a joint Red Cross convoy left Yangon carrying vital emergency supplies. This included:\n\nSix emergency health kits, each capable of covering the medical needs of 10,000 people for three months\n600 body bags for the dignified recovery and identification of the deceased\nSupport for Myanmar Red Cross emergency teams conducting search-and-rescue and first aid operations\n\n\n\n\nEssential items for those helping on the front lines\nAfter discussions with front liners and analyzing the situation on the ground, we have provided the following essential items to assist in their work:\n\nHelmets and heavy duty gloves\nRopes, goggles, and items to assist in the search \nStretchers to carry the wounded\n\n\n\n\nSafe water, sanitation and disease prevention\nAccess to clean water is critical in any emergency. To reduce the risk of cholera and diarrhoea outbreaks, the ICRC and Myanmar Red Cross are:\n\nDeploying water treatment units in Mandalay, Sagaing and Nay Pyi Taw to reach 2,500 people\nDistributing chlorine tablets and repairing water systems\nTraining local staff to safely operate water treatment systems\n\n\n\n\nProviding shelter and essential supplies\nICRC emergency stocks pre-positioned near the epicentre are now being mobilized to support communities left with nothing. These include:\n\nFood rations (rice, pulses, and oil)\nTarpaulins and essential household kits\nPlans for distributions are already underway to reach the most vulnerable families\n\n\n\n\nHelping families reconnect\nIn crises like this, families are often torn apart. The ICRC and Red Cross partners are ready to help people reconnect with missing loved ones through the Restoring Family Links programme.\n\n\n\n\n\n\n\n\n\n\n\n\nWe were able to respond within a day through our front liners, which is the most critical timing in emergency situations. I would like to thank all the first responders for their efforts and collaboration in ensuring our assistance reached those in most need, quickly and effectively.\n\n\n      Kyaw Phyo Khaing\n  \n\n      ICRC staff\n  \n\n\n\n\n\n\n\nMy family and I are also survivors of this earthquake. We are currently living in a school compound as my apartment was seriously damaged. So I can imagine how people are dealing with these difficult situations and the challenges they face regarding food and shelter. At the same time, as an ICRC staff, I have adapted to my current situation and used this experience to learn about the most pressing needs and challenges of the communities.\n\n\n      Ko Mohamed Ahyup\n  \n\n      ICRC staff\n  \n\n\n\n\n\n\n\n\n\n\n\n\n\n\n\n\n\n\n\n\n\n\n      Urgent help needed in Myanmar\n  \n\n\n\n      Following the devastating earthquake that has struck Myanmar and bordering regions, the scale of destruction is overwhelming — many are injured, displaced, or missing, with casualty numbers rising by the hour. With your support, we can bring life-saving aid where it’s needed the most.\n\r\nThank you for your generous support.\n  \n\n\nDonate today\n\n\n\n\n\n\n\n\n\n\n\n\n\n\n\n\n\n\n\n\n\n\n\n\n\nICRC\n\n\n\n\n\n\n\n\n\n\nRelated articles\n\n\n\n\n\n\n\n\n\n\n\n\n\n\n\nArticle\n\n04-04-2025\n\n\n\n\nFrequently asked questions about the ICRC's work in Myanmar\n\n\n\n\n\n\n\n\n\n\n\n\n\n\n\n\n\n\nArticle\n\n04-04-2025\n\n\n\n\nIn the minefields of Iraq, Noora works to restore life and hope to her homeland\n\n\n\n\n\n\n\n\n\n\n\n\n\n\n\n\n\n\nArticle\n\n04-04-2025\n\n\n\n\nMyanmar: Landmine awareness saves lives amid conflict and natural disasters\n\n\n\n\n\n\n\n\n\n\n\n\n\n\n\nMore articles\n\nArticle\n          \n\n01-04-2025\n\n\n\n\n\n5 languages\nEnglish\nFrançais\n中文\nРусский\nDeutsch\n\n\n\n\n\nDevastating earthquake in Myanmar: ICRC responds to help people on the ground\n\n\n        Providing medical supplies, access to clean water, critical supplies, and helping families keep in touch in the wake of disaster\n      \n\n\nMyanmar\n\n\n\n\nSituation on the groundHow our teams are helpingDonate now\n\n\n\n\n\n\n\n\n\n\n\n\nICRC\n\n\n\n\nThousands of people have been confirmed dead, with many more injured, and countless others displaced or missing after a powerful 7.7 magnitude earthquake struck Myanmar on 28 March 2025. Rescue operations are ongoing after the quake left a trail of destruction across several regions, including Mandalay, Sagaing and Shan State – compounding the suffering of people in areas already grappling with armed conflict, violence and instability.\n\nArticle\n          \n\n01-04-2025\n\n\n\n\n\n5 languages\nEnglish\nFrançais\n中文\nРусский\nDeutsch\n\n\n\n\n\nDevastating earthquake in Myanmar: ICRC responds to help people on the ground\n\n\n        Providing medical supplies, access to clean water, critical supplies, and helping families keep in touch in the wake of disaster\n      \n\n\nMyanmar\n\n\n\n\nSituation on the groundHow our teams are helpingDonate now\n\nArticle\n          \n\n01-04-2025\n\n\n\n\n\n5 languages\nEnglish\nFrançais\n中文\nРусский\nDeutsch\n\nArticle\n          \n\n01-04-2025\n\nArticle\n\n01-04-2025\n\n5 languages\nEnglish\nFrançais\n中文\nРусский\nDeutsch\n\n5 languages\nEnglish\nFrançais\n中文\nРусский\nDeutsch\n\nDevastating earthquake in Myanmar: ICRC responds to help people on the ground\n\nProviding medical supplies, access to clean water, critical supplies, and helping families keep in touch in the wake of disaster\n\nMyanmar\n\nSituation on the groundHow our teams are helpingDonate now\n\nSituation on the groundHow our teams are helpingDonate now\n\nICRC\n\nICRC\n\nICRC\n\nThousands of people have been confirmed dead, with many more injured, and countless others displaced or missing after a powerful 7.7 magnitude earthquake struck Myanmar on 28 March 2025. Rescue operations are ongoing after the quake left a trail of destruction across several regions, including Mandalay, Sagaing and Shan State – compounding the suffering of people in areas already grappling with armed conflict, violence and instability.\n\nThousands of people have been confirmed dead, with many more injured, and countless others displaced or missing after a powerful 7.7 magnitude earthquake struck Myanmar on 28 March 2025. Rescue operations are ongoing after the quake left a trail of destruction across several regions, including Mandalay, Sagaing and Shan State – compounding the suffering of people in areas already grappling with armed conflict, violence and instability.\n\nThousands of people have been confirmed dead, with many more injured, and countless others displaced or missing after a powerful 7.7 magnitude earthquake struck Myanmar on 28 March 2025. Rescue operations are ongoing after the quake left a trail of destruction across several regions, including Mandalay, Sagaing and Shan State – compounding the suffering of people in areas already grappling with armed conflict, violence and instability.\n\nThousands of people have been confirmed dead, with many more injured, and countless others displaced or missing after a powerful 7.7 magnitude earthquake struck Myanmar on 28 March 2025. Rescue operations are ongoing after the quake left a trail of destruction across several regions, including Mandalay, Sagaing and Shan State – compounding the suffering of people in areas already grappling with armed conflict, violence and instability.\n\nဤနောက်ဆုံးအခြေအနေရှင်းလင်းချက်ကို မြန်မာဘာသာဖြင့် ဤနေရာတွင် ဖတ်ရှုနိုင်ပါသည်။\n  \n\n\n\nဝင်ရောက်ဖတ်ရှုရန်\n\nဤနောက်ဆုံးအခြေအနေရှင်းလင်းချက်ကို မြန်မာဘာသာဖြင့် ဤနေရာတွင် ဖတ်ရှုနိုင်ပါသည်။\n  \n\n\n\nဝင်ရောက်ဖတ်ရှုရန်\n\nဤနောက်ဆုံးအခြေအနေရှင်းလင်းချက်ကို မြန်မာဘာသာဖြင့် ဤနေရာတွင် ဖတ်ရှုနိုင်ပါသည်။\n  \n\n\n\nဝင်ရောက်ဖတ်ရှုရန်\n\nဤနောက်ဆုံးအခြေအနေရှင်းလင်းချက်ကို မြန်မာဘာသာဖြင့် ဤနေရာတွင် ဖတ်ရှုနိုင်ပါသည်။\n\nဝင်ရောက်ဖတ်ရှုရန်\n\nဝင်ရောက်ဖတ်ရှုရန်\n\nEntire neighbourhoods have been reduced to rubble. Homes, hospitals, schools, bridges, and essential infrastructure have been destroyed. Many people have lost access to health care, clean water, and even the ability to contact their loved ones. In some areas, temperatures are soaring above 40°C, intensifying the suffering of those left without shelter.\n\nEntire neighbourhoods have been reduced to rubble. Homes, hospitals, schools, bridges, and essential infrastructure have been destroyed. Many people have lost access to health care, clean water, and even the ability to contact their loved ones. In some areas, temperatures are soaring above 40°C, intensifying the suffering of those left without shelter.\n\nEntire neighbourhoods have been reduced to rubble. Homes, hospitals, schools, bridges, and essential infrastructure have been destroyed. Many people have lost access to health care, clean water, and even the ability to contact their loved ones. In some areas, temperatures are soaring above 40°C, intensifying the suffering of those left without shelter.\n\nEntire neighbourhoods have been reduced to rubble. Homes, hospitals, schools, bridges, and essential infrastructure have been destroyed. Many people have lost access to health care, clean water, and even the ability to contact their loved ones. In some areas, temperatures are soaring above 40°C, intensifying the suffering of those left without shelter.\n\nEntire neighbourhoods have been reduced to rubble. Homes, hospitals, schools, bridges, and essential infrastructure have been destroyed. Many people have lost access to health care, clean water, and even the ability to contact their loved ones. In some areas, temperatures are soaring above 40°C, intensifying the suffering of those left without shelter.\n\nReaching those in urgent need\nAmid this devastation, the International Committee of the Red Cross (ICRC), together with the Myanmar Red Cross Society and Red Cross and Red Crescent Movement partners, is delivering life-saving support.\nOur priority is to reach those in urgent need across the region, ensuring that families receive essential aid during this difficult time. \nIn Mandalay, where the ICRC has an operational sub-delegation with 45 staff, teams have been on the ground from the outset – working side-by-side with local responders and coordinating with health authorities to reach those in urgent need.\n\n\nEmergency medical aid for the injured\nOn 30 March 2025, just two days after the quake, a joint Red Cross convoy left Yangon carrying vital emergency supplies. This included:\n\nSix emergency health kits, each capable of covering the medical needs of 10,000 people for three months\n600 body bags for the dignified recovery and identification of the deceased\nSupport for Myanmar Red Cross emergency teams conducting search-and-rescue and first aid operations\n\n\n\n\nEssential items for those helping on the front lines\nAfter discussions with front liners and analyzing the situation on the ground, we have provided the following essential items to assist in their work:\n\nHelmets and heavy duty gloves\nRopes, goggles, and items to assist in the search \nStretchers to carry the wounded\n\n\n\n\nSafe water, sanitation and disease prevention\nAccess to clean water is critical in any emergency. To reduce the risk of cholera and diarrhoea outbreaks, the ICRC and Myanmar Red Cross are:\n\nDeploying water treatment units in Mandalay, Sagaing and Nay Pyi Taw to reach 2,500 people\nDistributing chlorine tablets and repairing water systems\nTraining local staff to safely operate water treatment systems\n\n\n\n\nProviding shelter and essential supplies\nICRC emergency stocks pre-positioned near the epicentre are now being mobilized to support communities left with nothing. These include:\n\nFood rations (rice, pulses, and oil)\nTarpaulins and essential household kits\nPlans for distributions are already underway to reach the most vulnerable families\n\n\n\n\nHelping families reconnect\nIn crises like this, families are often torn apart. The ICRC and Red Cross partners are ready to help people reconnect with missing loved ones through the Restoring Family Links programme.\n\nReaching those in urgent need\nAmid this devastation, the International Committee of the Red Cross (ICRC), together with the Myanmar Red Cross Society and Red Cross and Red Crescent Movement partners, is delivering life-saving support.\nOur priority is to reach those in urgent need across the region, ensuring that families receive essential aid during this difficult time. \nIn Mandalay, where the ICRC has an operational sub-delegation with 45 staff, teams have been on the ground from the outset – working side-by-side with local responders and coordinating with health authorities to reach those in urgent need.\n\n\nEmergency medical aid for the injured\nOn 30 March 2025, just two days after the quake, a joint Red Cross convoy left Yangon carrying vital emergency supplies. This included:\n\nSix emergency health kits, each capable of covering the medical needs of 10,000 people for three months\n600 body bags for the dignified recovery and identification of the deceased\nSupport for Myanmar Red Cross emergency teams conducting search-and-rescue and first aid operations\n\n\n\n\nEssential items for those helping on the front lines\nAfter discussions with front liners and analyzing the situation on the ground, we have provided the following essential items to assist in their work:\n\nHelmets and heavy duty gloves\nRopes, goggles, and items to assist in the search \nStretchers to carry the wounded\n\n\n\n\nSafe water, sanitation and disease prevention\nAccess to clean water is critical in any emergency. To reduce the risk of cholera and diarrhoea outbreaks, the ICRC and Myanmar Red Cross are:\n\nDeploying water treatment units in Mandalay, Sagaing and Nay Pyi Taw to reach 2,500 people\nDistributing chlorine tablets and repairing water systems\nTraining local staff to safely operate water treatment systems\n\n\n\n\nProviding shelter and essential supplies\nICRC emergency stocks pre-positioned near the epicentre are now being mobilized to support communities left with nothing. These include:\n\nFood rations (rice, pulses, and oil)\nTarpaulins and essential household kits\nPlans for distributions are already underway to reach the most vulnerable families\n\n\n\n\nHelping families reconnect\nIn crises like this, families are often torn apart. The ICRC and Red Cross partners are ready to help people reconnect with missing loved ones through the Restoring Family Links programme.\n\nReaching those in urgent need\nAmid this devastation, the International Committee of the Red Cross (ICRC), together with the Myanmar Red Cross Society and Red Cross and Red Crescent Movement partners, is delivering life-saving support.\nOur priority is to reach those in urgent need across the region, ensuring that families receive essential aid during this difficult time. \nIn Mandalay, where the ICRC has an operational sub-delegation with 45 staff, teams have been on the ground from the outset – working side-by-side with local responders and coordinating with health authorities to reach those in urgent need.\n\n\nEmergency medical aid for the injured\nOn 30 March 2025, just two days after the quake, a joint Red Cross convoy left Yangon carrying vital emergency supplies. This included:\n\nSix emergency health kits, each capable of covering the medical needs of 10,000 people for three months\n600 body bags for the dignified recovery and identification of the deceased\nSupport for Myanmar Red Cross emergency teams conducting search-and-rescue and first aid operations\n\n\n\n\nEssential items for those helping on the front lines\nAfter discussions with front liners and analyzing the situation on the ground, we have provided the following essential items to assist in their work:\n\nHelmets and heavy duty gloves\nRopes, goggles, and items to assist in the search \nStretchers to carry the wounded\n\n\n\n\nSafe water, sanitation and disease prevention\nAccess to clean water is critical in any emergency. To reduce the risk of cholera and diarrhoea outbreaks, the ICRC and Myanmar Red Cross are:\n\nDeploying water treatment units in Mandalay, Sagaing and Nay Pyi Taw to reach 2,500 people\nDistributing chlorine tablets and repairing water systems\nTraining local staff to safely operate water treatment systems\n\n\n\n\nProviding shelter and essential supplies\nICRC emergency stocks pre-positioned near the epicentre are now being mobilized to support communities left with nothing. These include:\n\nFood rations (rice, pulses, and oil)\nTarpaulins and essential household kits\nPlans for distributions are already underway to reach the most vulnerable families\n\n\n\n\nHelping families reconnect\nIn crises like this, families are often torn apart. The ICRC and Red Cross partners are ready to help people reconnect with missing loved ones through the Restoring Family Links programme.\n\nAmid this devastation, the International Committee of the Red Cross (ICRC), together with the Myanmar Red Cross Society and Red Cross and Red Crescent Movement partners, is delivering life-saving support.\nOur priority is to reach those in urgent need across the region, ensuring that families receive essential aid during this difficult time. \nIn Mandalay, where the ICRC has an operational sub-delegation with 45 staff, teams have been on the ground from the outset – working side-by-side with local responders and coordinating with health authorities to reach those in urgent need.\n\nAmid this devastation, the International Committee of the Red Cross (ICRC), together with the Myanmar Red Cross Society and Red Cross and Red Crescent Movement partners, is delivering life-saving support.\n\nOur priority is to reach those in urgent need across the region, ensuring that families receive essential aid during this difficult time.\n\nIn Mandalay, where the ICRC has an operational sub-delegation with 45 staff, teams have been on the ground from the outset – working side-by-side with local responders and coordinating with health authorities to reach those in urgent need.\n\nEmergency medical aid for the injured\nOn 30 March 2025, just two days after the quake, a joint Red Cross convoy left Yangon carrying vital emergency supplies. This included:\n\nSix emergency health kits, each capable of covering the medical needs of 10,000 people for three months\n600 body bags for the dignified recovery and identification of the deceased\nSupport for Myanmar Red Cross emergency teams conducting search-and-rescue and first aid operations\n\nOn 30 March 2025, just two days after the quake, a joint Red Cross convoy left Yangon carrying vital emergency supplies. This included:\n\nSix emergency health kits, each capable of covering the medical needs of 10,000 people for three months\n600 body bags for the dignified recovery and identification of the deceased\nSupport for Myanmar Red Cross emergency teams conducting search-and-rescue and first aid operations\n\nOn 30 March 2025, just two days after the quake, a joint Red Cross convoy left Yangon carrying vital emergency supplies. This included:\n\nEssential items for those helping on the front lines\nAfter discussions with front liners and analyzing the situation on the ground, we have provided the following essential items to assist in their work:\n\nHelmets and heavy duty gloves\nRopes, goggles, and items to assist in the search \nStretchers to carry the wounded\n\nAfter discussions with front liners and analyzing the situation on the ground, we have provided the following essential items to assist in their work:\n\nHelmets and heavy duty gloves\nRopes, goggles, and items to assist in the search \nStretchers to carry the wounded\n\nAfter discussions with front liners and analyzing the situation on the ground, we have provided the following essential items to assist in their work:\n\nSafe water, sanitation and disease prevention\nAccess to clean water is critical in any emergency. To reduce the risk of cholera and diarrhoea outbreaks, the ICRC and Myanmar Red Cross are:\n\nDeploying water treatment units in Mandalay, Sagaing and Nay Pyi Taw to reach 2,500 people\nDistributing chlorine tablets and repairing water systems\nTraining local staff to safely operate water treatment systems\n\nAccess to clean water is critical in any emergency. To reduce the risk of cholera and diarrhoea outbreaks, the ICRC and Myanmar Red Cross are:\n\nDeploying water treatment units in Mandalay, Sagaing and Nay Pyi Taw to reach 2,500 people\nDistributing chlorine tablets and repairing water systems\nTraining local staff to safely operate water treatment systems\n\nAccess to clean water is critical in any emergency. To reduce the risk of cholera and diarrhoea outbreaks, the ICRC and Myanmar Red Cross are:\n\nProviding shelter and essential supplies\nICRC emergency stocks pre-positioned near the epicentre are now being mobilized to support communities left with nothing. These include:\n\nFood rations (rice, pulses, and oil)\nTarpaulins and essential household kits\nPlans for distributions are already underway to reach the most vulnerable families\n\nICRC emergency stocks pre-positioned near the epicentre are now being mobilized to support communities left with nothing. These include:\n\nFood rations (rice, pulses, and oil)\nTarpaulins and essential household kits\nPlans for distributions are already underway to reach the most vulnerable families\n\nICRC emergency stocks pre-positioned near the epicentre are now being mobilized to support communities left with nothing. These include:\n\nHelping families reconnect\nIn crises like this, families are often torn apart. The ICRC and Red Cross partners are ready to help people reconnect with missing loved ones through the Restoring Family Links programme.\n\nIn crises like this, families are often torn apart. The ICRC and Red Cross partners are ready to help people reconnect with missing loved ones through the Restoring Family Links programme.\n\nIn crises like this, families are often torn apart. The ICRC and Red Cross partners are ready to help people reconnect with missing loved ones through the Restoring Family Links programme.\n\nWe were able to respond within a day through our front liners, which is the most critical timing in emergency situations. I would like to thank all the first responders for their efforts and collaboration in ensuring our assistance reached those in most need, quickly and effectively.\n\n\n      Kyaw Phyo Khaing\n  \n\n      ICRC staff\n  \n\n\n\n\n\n\n\nMy family and I are also survivors of this earthquake. We are currently living in a school compound as my apartment was seriously damaged. So I can imagine how people are dealing with these difficult situations and the challenges they face regarding food and shelter. At the same time, as an ICRC staff, I have adapted to my current situation and used this experience to learn about the most pressing needs and challenges of the communities.\n\n\n      Ko Mohamed Ahyup\n  \n\n      ICRC staff\n\nWe were able to respond within a day through our front liners, which is the most critical timing in emergency situations. I would like to thank all the first responders for their efforts and collaboration in ensuring our assistance reached those in most need, quickly and effectively.\n\n\n      Kyaw Phyo Khaing\n  \n\n      ICRC staff\n  \n\n\n\n\n\n\n\nMy family and I are also survivors of this earthquake. We are currently living in a school compound as my apartment was seriously damaged. So I can imagine how people are dealing with these difficult situations and the challenges they face regarding food and shelter. At the same time, as an ICRC staff, I have adapted to my current situation and used this experience to learn about the most pressing needs and challenges of the communities.\n\n\n      Ko Mohamed Ahyup\n  \n\n      ICRC staff\n\nWe were able to respond within a day through our front liners, which is the most critical timing in emergency situations. I would like to thank all the first responders for their efforts and collaboration in ensuring our assistance reached those in most need, quickly and effectively.\n\n\n      Kyaw Phyo Khaing\n  \n\n      ICRC staff\n  \n\n\n\n\n\n\n\nMy family and I are also survivors of this earthquake. We are currently living in a school compound as my apartment was seriously damaged. So I can imagine how people are dealing with these difficult situations and the challenges they face regarding food and shelter. At the same time, as an ICRC staff, I have adapted to my current situation and used this experience to learn about the most pressing needs and challenges of the communities.\n\n\n      Ko Mohamed Ahyup\n  \n\n      ICRC staff\n\nWe were able to respond within a day through our front liners, which is the most critical timing in emergency situations. I would like to thank all the first responders for their efforts and collaboration in ensuring our assistance reached those in most need, quickly and effectively.\n\n\n      Kyaw Phyo Khaing\n  \n\n      ICRC staff\n  \n\n\n\n\n\n\n\nMy family and I are also survivors of this earthquake. We are currently living in a school compound as my apartment was seriously damaged. So I can imagine how people are dealing with these difficult situations and the challenges they face regarding food and shelter. At the same time, as an ICRC staff, I have adapted to my current situation and used this experience to learn about the most pressing needs and challenges of the communities.\n\n\n      Ko Mohamed Ahyup\n  \n\n      ICRC staff\n\nWe were able to respond within a day through our front liners, which is the most critical timing in emergency situations. I would like to thank all the first responders for their efforts and collaboration in ensuring our assistance reached those in most need, quickly and effectively.\n\n\n      Kyaw Phyo Khaing\n  \n\n      ICRC staff\n\nWe were able to respond within a day through our front liners, which is the most critical timing in emergency situations. I would like to thank all the first responders for their efforts and collaboration in ensuring our assistance reached those in most need, quickly and effectively.\n\n\n      Kyaw Phyo Khaing\n  \n\n      ICRC staff\n\nWe were able to respond within a day through our front liners, which is the most critical timing in emergency situations. I would like to thank all the first responders for their efforts and collaboration in ensuring our assistance reached those in most need, quickly and effectively.\n\nKyaw Phyo Khaing\n  \n\n      ICRC staff\n\nMy family and I are also survivors of this earthquake. We are currently living in a school compound as my apartment was seriously damaged. So I can imagine how people are dealing with these difficult situations and the challenges they face regarding food and shelter. At the same time, as an ICRC staff, I have adapted to my current situation and used this experience to learn about the most pressing needs and challenges of the communities.\n\n\n      Ko Mohamed Ahyup\n  \n\n      ICRC staff\n\nMy family and I are also survivors of this earthquake. We are currently living in a school compound as my apartment was seriously damaged. So I can imagine how people are dealing with these difficult situations and the challenges they face regarding food and shelter. At the same time, as an ICRC staff, I have adapted to my current situation and used this experience to learn about the most pressing needs and challenges of the communities.\n\n\n      Ko Mohamed Ahyup\n  \n\n      ICRC staff\n\nMy family and I are also survivors of this earthquake. We are currently living in a school compound as my apartment was seriously damaged. So I can imagine how people are dealing with these difficult situations and the challenges they face regarding food and shelter. At the same time, as an ICRC staff, I have adapted to my current situation and used this experience to learn about the most pressing needs and challenges of the communities.\n\nKo Mohamed Ahyup\n  \n\n      ICRC staff\n\nUrgent help needed in Myanmar\n  \n\n\n\n      Following the devastating earthquake that has struck Myanmar and bordering regions, the scale of destruction is overwhelming — many are injured, displaced, or missing, with casualty numbers rising by the hour. With your support, we can bring life-saving aid where it’s needed the most.\n\r\nThank you for your generous support.\n  \n\n\nDonate today\n\nUrgent help needed in Myanmar\n  \n\n\n\n      Following the devastating earthquake that has struck Myanmar and bordering regions, the scale of destruction is overwhelming — many are injured, displaced, or missing, with casualty numbers rising by the hour. With your support, we can bring life-saving aid where it’s needed the most.\n\r\nThank you for your generous support.\n  \n\n\nDonate today\n\nUrgent help needed in Myanmar\n  \n\n\n\n      Following the devastating earthquake that has struck Myanmar and bordering regions, the scale of destruction is overwhelming — many are injured, displaced, or missing, with casualty numbers rising by the hour. With your support, we can bring life-saving aid where it’s needed the most.\n\r\nThank you for your generous support.\n  \n\n\nDonate today\n\nUrgent help needed in Myanmar\n  \n\n\n\n      Following the devastating earthquake that has struck Myanmar and bordering regions, the scale of destruction is overwhelming — many are injured, displaced, or missing, with casualty numbers rising by the hour. With your support, we can bring life-saving aid where it’s needed the most.\n\r\nThank you for your generous support.\n  \n\n\nDonate today\n\nUrgent help needed in Myanmar\n\nFollowing the devastating earthquake that has struck Myanmar and bordering regions, the scale of destruction is overwhelming — many are injured, displaced, or missing, with casualty numbers rising by the hour. With your support, we can bring life-saving aid where it’s needed the most.\n\r\nThank you for your generous support.\n\nFollowing the devastating earthquake that has struck Myanmar and bordering regions, the scale of destruction is overwhelming — many are injured, displaced, or missing, with casualty numbers rising by the hour. With your support, we can bring life-saving aid where it’s needed the most.\n\r\nThank you for your generous support.\n\nDonate today\n\nICRC\n\nICRC\n\nICRC\n\nICRC\n\nICRC\n\nICRC\n\nRelated articles\n\n\n\n\n\n\n\n\n\n\n\n\n\n\n\nArticle\n\n04-04-2025\n\n\n\n\nFrequently asked questions about the ICRC's work in Myanmar\n\n\n\n\n\n\n\n\n\n\n\n\n\n\n\n\n\n\nArticle\n\n04-04-2025\n\n\n\n\nIn the minefields of Iraq, Noora works to restore life and hope to her homeland\n\n\n\n\n\n\n\n\n\n\n\n\n\n\n\n\n\n\nArticle\n\n04-04-2025\n\n\n\n\nMyanmar: Landmine awareness saves lives amid conflict and natural disasters\n\n\n\n\n\n\n\n\n\n\n\n\n\n\n\nMore articles\n\nRelated articles\n\n\n\n\n\n\n\n\n\n\n\n\n\n\n\nArticle\n\n04-04-2025\n\n\n\n\nFrequently asked questions about the ICRC's work in Myanmar\n\n\n\n\n\n\n\n\n\n\n\n\n\n\n\n\n\n\nArticle\n\n04-04-2025\n\n\n\n\nIn the minefields of Iraq, Noora works to restore life and hope to her homeland\n\n\n\n\n\n\n\n\n\n\n\n\n\n\n\n\n\n\nArticle\n\n04-04-2025\n\n\n\n\nMyanmar: Landmine awareness saves lives amid conflict and natural disasters\n\n\n\n\n\n\n\n\n\n\n\n\n\n\n\nMore articles\n\nRelated articles\n\n\n\n\n\n\n\n\n\n\n\n\n\n\n\nArticle\n\n04-04-2025\n\n\n\n\nFrequently asked questions about the ICRC's work in Myanmar\n\n\n\n\n\n\n\n\n\n\n\n\n\n\n\n\n\n\nArticle\n\n04-04-2025\n\n\n\n\nIn the minefields of Iraq, Noora works to restore life and hope to her homeland\n\n\n\n\n\n\n\n\n\n\n\n\n\n\n\n\n\n\nArticle\n\n04-04-2025\n\n\n\n\nMyanmar: Landmine awareness saves lives amid conflict and natural disasters\n\n\n\n\n\n\n\n\n\n\n\n\n\n\n\nMore articles\n\nRelated articles\n\n\n\n\n\n\n\n\n\n\n\n\n\n\n\nArticle\n\n04-04-2025\n\n\n\n\nFrequently asked questions about the ICRC's work in Myanmar\n\n\n\n\n\n\n\n\n\n\n\n\n\n\n\n\n\n\nArticle\n\n04-04-2025\n\n\n\n\nIn the minefields of Iraq, Noora works to restore life and hope to her homeland\n\n\n\n\n\n\n\n\n\n\n\n\n\n\n\n\n\n\nArticle\n\n04-04-2025\n\n\n\n\nMyanmar: Landmine awareness saves lives amid conflict and natural disasters\n\n\n\n\n\n\n\n\n\n\n\n\n\n\n\nMore articles\n\nRelated articles\n\n\n\n\n\n\n\n\n\n\n\n\n\n\n\nArticle\n\n04-04-2025\n\n\n\n\nFrequently asked questions about the ICRC's work in Myanmar\n\n\n\n\n\n\n\n\n\n\n\n\n\n\n\n\n\n\nArticle\n\n04-04-2025\n\n\n\n\nIn the minefields of Iraq, Noora works to restore life and hope to her homeland\n\n\n\n\n\n\n\n\n\n\n\n\n\n\n\n\n\n\nArticle\n\n04-04-2025\n\n\n\n\nMyanmar: Landmine awareness saves lives amid conflict and natural disasters\n\n\n\n\n\n\n\n\n\n\n\n\n\n\n\nMore articles\n\nRelated articles\n\nArticle\n\n04-04-2025\n\n\n\n\nFrequently asked questions about the ICRC's work in Myanmar\n\n\n\n\n\n\n\n\n\n\n\n\n\n\n\n\n\n\nArticle\n\n04-04-2025\n\n\n\n\nIn the minefields of Iraq, Noora works to restore life and hope to her homeland\n\n\n\n\n\n\n\n\n\n\n\n\n\n\n\n\n\n\nArticle\n\n04-04-2025\n\n\n\n\nMyanmar: Landmine awareness saves lives amid conflict and natural disasters\n\n\n\n\n\n\n\n\n\n\n\n\n\n\n\nMore articles\n\nArticle\n\n04-04-2025\n\n\n\n\nFrequently asked questions about the ICRC's work in Myanmar\n\n\n\n\n\n\n\n\n\n\n\n\n\n\n\n\n\n\nArticle\n\n04-04-2025\n\n\n\n\nIn the minefields of Iraq, Noora works to restore life and hope to her homeland\n\n\n\n\n\n\n\n\n\n\n\n\n\n\n\n\n\n\nArticle\n\n04-04-2025\n\n\n\n\nMyanmar: Landmine awareness saves lives amid conflict and natural disasters\n\nArticle\n\n04-04-2025\n\n\n\n\nFrequently asked questions about the ICRC's work in Myanmar\n\nArticle\n\n04-04-2025\n\n\n\n\nFrequently asked questions about the ICRC's work in Myanmar\n\nArticle\n\n04-04-2025\n\n\n\n\nFrequently asked questions about the ICRC's work in Myanmar\n\nArticle\n\n04-04-2025\n\n\n\n\nFrequently asked questions about the ICRC's work in Myanmar\n\nArticle\n\n04-04-2025\n\nArticle\n\n04-04-2025\n\nFrequently asked questions about the ICRC's work in Myanmar\n\nArticle\n\n04-04-2025\n\n\n\n\nIn the minefields of Iraq, Noora works to restore life and hope to her homeland\n\nArticle\n\n04-04-2025\n\n\n\n\nIn the minefields of Iraq, Noora works to restore life and hope to her homeland\n\nArticle\n\n04-04-2025\n\n\n\n\nIn the minefields of Iraq, Noora works to restore life and hope to her homeland\n\nArticle\n\n04-04-2025\n\n\n\n\nIn the minefields of Iraq, Noora works to restore life and hope to her homeland\n\nArticle\n\n04-04-2025\n\nArticle\n\n04-04-2025\n\nIn the minefields of Iraq, Noora works to restore life and hope to her homeland\n\nArticle\n\n04-04-2025\n\n\n\n\nMyanmar: Landmine awareness saves lives amid conflict and natural disasters\n\nArticle\n\n04-04-2025\n\n\n\n\nMyanmar: Landmine awareness saves lives amid conflict and natural disasters\n\nArticle\n\n04-04-2025\n\n\n\n\nMyanmar: Landmine awareness saves lives amid conflict and natural disasters\n\nArticle\n\n04-04-2025\n\n\n\n\nMyanmar: Landmine awareness saves lives amid conflict and natural disasters\n\nArticle\n\n04-04-2025\n\nArticle\n\n04-04-2025\n\nMyanmar: Landmine awareness saves lives amid conflict and natural disasters\n\nMore articles\n\nMore articles",
  "date": "",
  "source_type": "other",
  "extracted_at": "2025-04-07T14:01:01.739137",
  "metadata": {
    "description": "Myanmar earthquake response: ICRC provides life-saving medical aid, clean water, shelter for displaced families, and emergency supplies to those in urgent need.",
    "og:site_name": "International Committee of the Red Cross"
  },
  "relevance_score": 0.5166666666666666,
  "summary": "Skip to main content\n\n\n\n\n\n\n\n\n\n\n\n\n\n            Article\n          \n\n01-04-2025\n\n\n\n\n\n5 languages\nEnglish\nFrançais\n中文\nРусский\nDeutsch\n\n\n\n\n\nDevastating earthquake in Myanmar: ICRC responds to help people on the ground\n\n\n        Providing medical supplies, access to clean water, critical supplies, and helping families keep in touch in the wake of disaster\n      \n\n\nMyanmar\n\n\n\n\nSituation on the groundHow our teams are helpingDonate now\n\n\n\n\n\n\n\n\n\n\n\n\nICRC\n\n\n\n\nThousands of people have been confirmed dead, with many more injured, and countless others displaced or missing after a powerful 7.7 magnitude earthquake struck Myanmar on 28 March 2025. Reaching those in urgent need\nAmid this devastation, the International Committee of the Red Cross (ICRC), together with the Myanmar Red Cross Society and Red Cross and Red Crescent Movement partners, is delivering life-saving support. This included:\n\nSix emergency health kits, each capable of covering the medical needs of 10,000 people for three months\n600 body bags for the dignified recovery and identification of the deceased\nSupport for Myanmar Red Cross emergency teams conducting search-and-rescue and first aid operations\n\n\n\n\nEssential items for those helping on the front lines\nAfter discussions with front liners and analyzing the situation on the ground, we have provided the following essential items to assist in their work:\n\nHelmets and heavy duty gloves\nRopes, goggles, and items to assist in the search \nStretchers to carry the wounded\n\n\n\n\nSafe water, sanitation and disease prevention\nAccess to clean water is critical in any emergency. To reduce the risk of cholera and diarrhoea outbreaks, the ICRC and Myanmar Red Cross are:\n\nDeploying water treatment units in Mandalay, Sagaing and Nay Pyi Taw to reach 2,500 people\nDistributing chlorine tablets and repairing water systems\nTraining local staff to safely operate water treatment systems\n\n\n\n\nProviding shelter and essential supplies\nICRC emergency stocks pre-positioned near the epicentre are now being mobilized to support communities left with nothing. Ko Mohamed Ahyup\n  \n\n      ICRC staff\n  \n\n\n\n\n\n\n\n\n\n\n\n\n\n\n\n\n\n\n\n\n\n\n      Urgent help needed in Myanmar\n  \n\n\n\n      Following the devastating earthquake that has struck Myanmar and bordering regions, the scale of destruction is overwhelming — many are injured, displaced, or missing, with casualty numbers rising by the hour. Donate today\n\n\n\n\n\n\n\n\n\n\n\n\n\n\n\n\n\n\n\n\n\n\n\n\n\nICRC\n\n\n\n\n\n\n\n\n\n\nRelated articles\n\n\n\n\n\n\n\n\n\n\n\n\n\n\n\nArticle\n\n04-04-2025\n\n\n\n\nFrequently asked questions about the ICRC's work in Myanmar\n\n\n\n\n\n\n\n\n\n\n\n\n\n\n\n\n\n\nArticle\n\n04-04-2025\n\n\n\n\nIn the minefields of Iraq, Noora works to restore life and hope to her homeland\n\n\n\n\n\n\n\n\n\n\n\n\n\n\n\n\n\n\nArticle\n\n04-04-2025\n\n\n\n\nMyanmar: Landmine awareness saves lives amid conflict and natural disasters\n\n\n\n\n\n\n\n\n\n\n\n\n\n\n\nMore articles\n\nSkip to main content\n\n\n\n\n\n\n\n\n\n\n\n\n\n            Article\n          \n\n01-04-2025\n\n\n\n\n\n5 languages\nEnglish\nFrançais\n中文\nРусский\nDeutsch\n\n\n\n\n\nDevastating earthquake in Myanmar: ICRC responds to help people on the ground\n\n\n        Providing medical supplies, access to clean water, critical supplies, and helping families keep in touch in the wake of disaster\n      \n\n\nMyanmar\n\n\n\n\nSituation on the groundHow our teams are helpingDonate now\n\n\n\n\n\n\n\n\n\n\n\n\nICRC\n\n\n\n\nThousands of people have been confirmed dead, with many more injured, and countless others displaced or missing after a powerful 7.7 magnitude earthquake struck Myanmar on 28 March 2025. Reaching those in urgent need\nAmid this devastation, the International Committee of the Red Cross (ICRC), together with the Myanmar Red Cross Society and Red Cross and Red Crescent Movement partners, is delivering life-saving support. This included:\n\nSix emergency health kits, each capable of covering the medical needs of 10,000 people for three months\n600 body bags for the dignified recovery and identification of the deceased\nSupport for Myanmar Red Cross emergency teams conducting search-and-rescue and first aid operations\n\n\n\n\nEssential items for those helping on the front lines\nAfter discussions with front liners and analyzing the situation on the ground, we have provided the following essential items to assist in their work:\n\nHelmets and heavy duty gloves\nRopes, goggles, and items to assist in the search \nStretchers to carry the wounded\n\n\n\n\nSafe water, sanitation and disease prevention\nAccess to clean water is critical in any emergency. To reduce the risk of cholera and diarrhoea outbreaks, the ICRC and Myanmar Red Cross are:\n\nDeploying water treatment units in Mandalay, Sagaing and Nay Pyi Taw to reach 2,500 people\nDistributing chlorine tablets and repairing water systems\nTraining local staff to safely operate water treatment systems\n\n\n\n\nProviding shelter and essential supplies\nICRC emergency stocks pre-positioned near the epicentre are now being mobilized to support communities left with nothing. Ko Mohamed Ahyup\n  \n\n      ICRC staff\n  \n\n\n\n\n\n\n\n\n\n\n\n\n\n\n\n\n\n\n\n\n\n\n      Urgent help needed in Myanmar\n  \n\n\n\n      Following the devastating earthquake that has struck Myanmar and bordering regions, the scale of destruction is overwhelming — many are injured, displaced, or missing, with casualty numbers rising by the hour. Donate today\n\n\n\n\n\n\n\n\n\n\n\n\n\n\n\n\n\n\n\n\n\n\n\n\n\nICRC\n\n\n\n\n\n\n\n\n\n\nRelated articles\n\n\n\n\n\n\n\n\n\n\n\n\n\n\n\nArticle\n\n04-04-2025\n\n\n\n\nFrequently asked questions about the ICRC's work in Myanmar\n\n\n\n\n\n\n\n\n\n\n\n\n\n\n\n\n\n\nArticle\n\n04-04-2025\n\n\n\n\nIn the minefields of Iraq, Noora works to restore life and hope to her homeland\n\n\n\n\n\n\n\n\n\n\n\n\n\n\n\n\n\n\nArticle\n\n04-04-2025\n\n\n\n\nMyanmar: Landmine awareness saves lives amid conflict and natural disasters\n\n\n\n\n\n\n\n\n\n\n\n\n\n\n\nMore articles\n\nArticle\n          \n\n01-04-2025\n\n\n\n\n\n5 languages\nEnglish\nFrançais\n中文\nРусский\nDeutsch\n\n\n\n\n\nDevastating earthquake in Myanmar: ICRC responds to help people on the ground\n\n\n        Providing medical supplies, access to clean water, critical supplies, and helping families keep in touch in the wake of disaster\n      \n\n\nMyanmar\n\n\n\n\nSituation on the groundHow our teams are helpingDonate now\n\n\n\n\n\n\n\n\n\n\n\n\nICRC\n\n\n\n\nThousands of people have been confirmed dead, with many more injured, and countless others displaced or missing after a powerful 7.7 magnitude earthquake struck Myanmar on 28 March 2025. Reaching those in urgent need\nAmid this devastation, the International Committee of the Red Cross (ICRC), together with the Myanmar Red Cross Society and Red Cross and Red Crescent Movement partners, is delivering life-saving support. This included:\n\nSix emergency health kits, each capable of covering the medical needs of 10,000 people for three months\n600 body bags for the dignified recovery and identification of the deceased\nSupport for Myanmar Red Cross emergency teams conducting search-and-rescue and first aid operations\n\n\n\n\nEssential items for those helping on the front lines\nAfter discussions with front liners and analyzing the situation on the ground, we have provided the following essential items to assist in their work:\n\nHelmets and heavy duty gloves\nRopes, goggles, and items to assist in the search \nStretchers to carry the wounded\n\n\n\n\nSafe water, sanitation and disease prevention\nAccess to clean water is critical in any emergency. To reduce the risk of cholera and diarrhoea outbreaks, the ICRC and Myanmar Red Cross are:\n\nDeploying water treatment units in Mandalay, Sagaing and Nay Pyi Taw to reach 2,500 people\nDistributing chlorine tablets and repairing water systems\nTraining local staff to safely operate water treatment systems\n\n\n\n\nProviding shelter and essential supplies\nICRC emergency stocks pre-positioned near the epicentre are now being mobilized to support communities left with nothing. Ko Mohamed Ahyup\n  \n\n      ICRC staff\n  \n\n\n\n\n\n\n\n\n\n\n\n\n\n\n\n\n\n\n\n\n\n\n      Urgent help needed in Myanmar\n  \n\n\n\n      Following the devastating earthquake that has struck Myanmar and bordering regions, the scale of destruction is overwhelming — many are injured, displaced, or missing, with casualty numbers rising by the hour. Donate today\n\n\n\n\n\n\n\n\n\n\n\n\n\n\n\n\n\n\n\n\n\n\n\n\n\nICRC\n\n\n\n\n\n\n\n\n\n\nRelated articles\n\n\n\n\n\n\n\n\n\n\n\n\n\n\n\nArticle\n\n04-04-2025\n\n\n\n\nFrequently asked questions about the ICRC's work in Myanmar\n\n\n\n\n\n\n\n\n\n\n\n\n\n\n\n\n\n\nArticle\n\n04-04-2025\n\n\n\n\nIn the minefields of Iraq, Noora works to restore life and hope to her homeland\n\n\n\n\n\n\n\n\n\n\n\n\n\n\n\n\n\n\nArticle\n\n04-04-2025\n\n\n\n\nMyanmar: Landmine awareness saves lives amid conflict and natural disasters\n\n\n\n\n\n\n\n\n\n\n\n\n\n\n\nMore articles\n\nArticle\n          \n\n01-04-2025\n\n\n\n\n\n5 languages\nEnglish\nFrançais\n中文\nРусский\nDeutsch\n\n\n\n\n\nDevastating earthquake in Myanmar: ICRC responds to help people on the ground\n\n\n        Providing medical supplies, access to clean water, critical supplies, and helping families keep in touch in the wake of disaster\n      \n\n\nMyanmar\n\n\n\n\nSituation on the groundHow our teams are helpingDonate now\n\n\n\n\n\n\n\n\n\n\n\n\nICRC\n\n\n\n\nThousands of people have been confirmed dead, with many more injured, and countless others displaced or missing after a powerful 7.7 magnitude earthquake struck Myanmar on 28 March 2025. Reaching those in urgent need\nAmid this devastation, the International Committee of the Red Cross (ICRC), together with the Myanmar Red Cross Society and Red Cross and Red Crescent Movement partners, is delivering life-saving support. This included:\n\nSix emergency health kits, each capable of covering the medical needs of 10,000 people for three months\n600 body bags for the dignified recovery and identification of the deceased\nSupport for Myanmar Red Cross emergency teams conducting search-and-rescue and first aid operations\n\n\n\n\nEssential items for those helping on the front lines\nAfter discussions with front liners and analyzing the situation on the ground, we have provided the following essential items to assist in their work:\n\nHelmets and heavy duty gloves\nRopes, goggles, and items to assist in the search \nStretchers to carry the wounded\n\n\n\n\nSafe water, sanitation and disease prevention\nAccess to clean water is critical in any emergency. To reduce the risk of cholera and diarrhoea outbreaks, the ICRC and Myanmar Red Cross are:\n\nDeploying water treatment units in Mandalay, Sagaing and Nay Pyi Taw to reach 2,500 people\nDistributing chlorine tablets and repairing water systems\nTraining local staff to safely operate water treatment systems\n\n\n\n\nProviding shelter and essential supplies\nICRC emergency stocks pre-positioned near the epicentre are now being mobilized to support communities left with nothing. Ko Mohamed Ahyup\n  \n\n      ICRC staff\n  \n\n\n\n\n\n\n\n\n\n\n\n\n\n\n\n\n\n\n\n\n\n\n      Urgent help needed in Myanmar\n  \n\n\n\n      Following the devastating earthquake that has struck Myanmar and bordering regions, the scale of destruction is overwhelming — many are injured, displaced, or missing, with casualty numbers rising by the hour. Donate today\n\n\n\n\n\n\n\n\n\n\n\n\n\n\n\n\n\n\n\n\n\n\n\n\n\nICRC\n\n\n\n\n\n\n\n\n\n\nRelated articles\n\n\n\n\n\n\n\n\n\n\n\n\n\n\n\nArticle\n\n04-04-2025\n\n\n\n\nFrequently asked questions about the ICRC's work in Myanmar\n\n\n\n\n\n\n\n\n\n\n\n\n\n\n\n\n\n\nArticle\n\n04-04-2025\n\n\n\n\nIn the minefields of Iraq, Noora works to restore life and hope to her homeland\n\n\n\n\n\n\n\n\n\n\n\n\n\n\n\n\n\n\nArticle\n\n04-04-2025\n\n\n\n\nMyanmar: Landmine awareness saves lives amid conflict and natural disasters\n\n\n\n\n\n\n\n\n\n\n\n\n\n\n\nMore articles\n\nArticle\n          \n\n01-04-2025\n\n\n\n\n\n5 languages\nEnglish\nFrançais\n中文\nРусский\nDeutsch\n\n\n\n\n\nDevastating earthquake in Myanmar: ICRC responds to help people on the ground\n\n\n        Providing medical supplies, access to clean water, critical supplies, and helping families keep in touch in the wake of disaster\n      \n\n\nMyanmar\n\n\n\n\nSituation on the groundHow our teams are helpingDonate now\n\n\n\n\n\n\n\n\n\n\n\n\nICRC\n\n\n\n\nThousands of people have been confirmed dead, with many more injured, and countless others displaced or missing after a powerful 7.7 magnitude earthquake struck Myanmar on 28 March 2025. Reaching those in urgent need\nAmid this devastation, the International Committee of the Red Cross (ICRC), together with the Myanmar Red Cross Society and Red Cross and Red Crescent Movement partners, is delivering life-saving support. This included:\n\nSix emergency health kits, each capable of covering the medical needs of 10,000 people for three months\n600 body bags for the dignified recovery and identification of the deceased\nSupport for Myanmar Red Cross emergency teams conducting search-and-rescue and first aid operations\n\n\n\n\nEssential items for those helping on the front lines\nAfter discussions with front liners and analyzing the situation on the ground, we have provided the following essential items to assist in their work:\n\nHelmets and heavy duty gloves\nRopes, goggles, and items to assist in the search \nStretchers to carry the wounded\n\n\n\n\nSafe water, sanitation and disease prevention\nAccess to clean water is critical in any emergency. To reduce the risk of cholera and diarrhoea outbreaks, the ICRC and Myanmar Red Cross are:\n\nDeploying water treatment units in Mandalay, Sagaing and Nay Pyi Taw to reach 2,500 people\nDistributing chlorine tablets and repairing water systems\nTraining local staff to safely operate water treatment systems\n\n\n\n\nProviding shelter and essential supplies\nICRC emergency stocks pre-positioned near the epicentre are now being mobilized to support communities left with nothing. Ko Mohamed Ahyup\n  \n\n      ICRC staff\n  \n\n\n\n\n\n\n\n\n\n\n\n\n\n\n\n\n\n\n\n\n\n\n      Urgent help needed in Myanmar\n  \n\n\n\n      Following the devastating earthquake that has struck Myanmar and bordering regions, the scale of destruction is overwhelming — many are injured, displaced, or missing, with casualty numbers rising by the hour. Donate today\n\n\n\n\n\n\n\n\n\n\n\n\n\n\n\n\n\n\n\n\n\n\n\n\n\nICRC\n\n\n\n\n\n\n\n\n\n\nRelated articles\n\n\n\n\n\n\n\n\n\n\n\n\n\n\n\nArticle\n\n04-04-2025\n\n\n\n\nFrequently asked questions about the ICRC's work in Myanmar\n\n\n\n\n\n\n\n\n\n\n\n\n\n\n\n\n\n\nArticle\n\n04-04-2025\n\n\n\n\nIn the minefields of Iraq, Noora works to restore life and hope to her homeland\n\n\n\n\n\n\n\n\n\n\n\n\n\n\n\n\n\n\nArticle\n\n04-04-2025\n\n\n\n\nMyanmar: Landmine awareness saves lives amid conflict and natural disasters\n\n\n\n\n\n\n\n\n\n\n\n\n\n\n\nMore articles\n\nArticle\n          \n\n01-04-2025\n\n\n\n\n\n5 languages\nEnglish\nFrançais\n中文\nРусский\nDeutsch\n\n\n\n\n\nDevastating earthquake in Myanmar: ICRC responds to help people on the ground\n\n\n        Providing medical supplies, access to clean water, critical supplies, and helping families keep in touch in the wake of disaster\n      \n\n\nMyanmar\n\n\n\n\nSituation on the groundHow our teams are helpingDonate now\n\n\n\n\n\n\n\n\n\n\n\n\nICRC\n\n\n\n\nThousands of people have been confirmed dead, with many more injured, and countless others displaced or missing after a powerful 7.7 magnitude earthquake struck Myanmar on 28 March 2025. Reaching those in urgent need\nAmid this devastation, the International Committee of the Red Cross (ICRC), together with the Myanmar Red Cross Society and Red Cross and Red Crescent Movement partners, is delivering life-saving support. This included:\n\nSix emergency health kits, each capable of covering the medical needs of 10,000 people for three months\n600 body bags for the dignified recovery and identification of the deceased\nSupport for Myanmar Red Cross emergency teams conducting search-and-rescue and first aid operations\n\n\n\n\nEssential items for those helping on the front lines\nAfter discussions with front liners and analyzing the situation on the ground, we have provided the following essential items to assist in their work:\n\nHelmets and heavy duty gloves\nRopes, goggles, and items to assist in the search \nStretchers to carry the wounded\n\n\n\n\nSafe water, sanitation and disease prevention\nAccess to clean water is critical in any emergency. To reduce the risk of cholera and diarrhoea outbreaks, the ICRC and Myanmar Red Cross are:\n\nDeploying water treatment units in Mandalay, Sagaing and Nay Pyi Taw to reach 2,500 people\nDistributing chlorine tablets and repairing water systems\nTraining local staff to safely operate water treatment systems\n\n\n\n\nProviding shelter and essential supplies\nICRC emergency stocks pre-positioned near the epicentre are now being mobilized to support communities left with nothing. Ko Mohamed Ahyup\n  \n\n      ICRC staff\n  \n\n\n\n\n\n\n\n\n\n\n\n\n\n\n\n\n\n\n\n\n\n\n      Urgent help needed in Myanmar\n  \n\n\n\n      Following the devastating earthquake that has struck Myanmar and bordering regions, the scale of destruction is overwhelming — many are injured, displaced, or missing, with casualty numbers rising by the hour. Donate today\n\n\n\n\n\n\n\n\n\n\n\n\n\n\n\n\n\n\n\n\n\n\n\n\n\nICRC\n\n\n\n\n\n\n\n\n\n\nRelated articles\n\n\n\n\n\n\n\n\n\n\n\n\n\n\n\nArticle\n\n04-04-2025\n\n\n\n\nFrequently asked questions about the ICRC's work in Myanmar\n\n\n\n\n\n\n\n\n\n\n\n\n\n\n\n\n\n\nArticle\n\n04-04-2025\n\n\n\n\nIn the minefields of Iraq, Noora works to restore life and hope to her homeland\n\n\n\n\n\n\n\n\n\n\n\n\n\n\n\n\n\n\nArticle\n\n04-04-2025\n\n\n\n\nMyanmar: Landmine awareness saves lives amid conflict and natural disasters\n\n\n\n\n\n\n\n\n\n\n\n\n\n\n\nMore articles\n\nArticle\n          \n\n01-04-2025\n\n\n\n\n\n5 languages\nEnglish\nFrançais\n中文\nРусский\nDeutsch\n\n\n\n\n\nDevastating earthquake in Myanmar: ICRC responds to help people on the ground\n\n\n        Providing medical supplies, access to clean water, critical supplies, and helping families keep in touch in the wake of disaster\n      \n\n\nMyanmar\n\n\n\n\nSituation on the groundHow our teams are helpingDonate now\n\n\n\n\n\n\n\n\n\n\n\n\nICRC\n\n\n\n\nThousands of people have been confirmed dead, with many more injured, and countless others displaced or missing after a powerful 7.7 magnitude earthquake struck Myanmar on 28 March 2025. Article\n          \n\n01-04-2025\n\n\n\n\n\n5 languages\nEnglish\nFrançais\n中文\nРусский\nDeutsch\n\n\n\n\n\nDevastating earthquake in Myanmar: ICRC responds to help people on the ground\n\n\n        Providing medical supplies, access to clean water, critical supplies, and helping families keep in touch in the wake of disaster\n      \n\n\nMyanmar\n\n\n\n\nSituation on the groundHow our teams are helpingDonate now\n\nArticle\n          \n\n01-04-2025\n\n\n\n\n\n5 languages\nEnglish\nFrançais\n中文\nРусский\nDeutsch\n\nArticle\n          \n\n01-04-2025\n\nArticle\n\n01-04-2025\n\n5 languages\nEnglish\nFrançais\n中文\nРусский\nDeutsch\n\n5 languages\nEnglish\nFrançais\n中文\nРусский\nDeutsch\n\nDevastating earthquake in Myanmar: ICRC responds to help people on the ground\n\nProviding medical supplies, access to clean water, critical supplies, and helping families keep in touch in the wake of disaster\n\nMyanmar\n\nSituation on the groundHow our teams are helpingDonate now\n\nSituation on the groundHow our teams are helpingDonate now\n\nICRC\n\nICRC\n\nICRC\n\nThousands of people have been confirmed dead, with many more injured, and countless others displaced or missing after a powerful 7.7 magnitude earthquake struck Myanmar on 28 March 2025. Reaching those in urgent need\nAmid this devastation, the International Committee of the Red Cross (ICRC), together with the Myanmar Red Cross Society and Red Cross and Red Crescent Movement partners, is delivering life-saving support. This included:\n\nSix emergency health kits, each capable of covering the medical needs of 10,000 people for three months\n600 body bags for the dignified recovery and identification of the deceased\nSupport for Myanmar Red Cross emergency teams conducting search-and-rescue and first aid operations\n\n\n\n\nEssential items for those helping on the front lines\nAfter discussions with front liners and analyzing the situation on the ground, we have provided the following essential items to assist in their work:\n\nHelmets and heavy duty gloves\nRopes, goggles, and items to assist in the search \nStretchers to carry the wounded\n\n\n\n\nSafe water, sanitation and disease prevention\nAccess to clean water is critical in any emergency. To reduce the risk of cholera and diarrhoea outbreaks, the ICRC and Myanmar Red Cross are:\n\nDeploying water treatment units in Mandalay, Sagaing and Nay Pyi Taw to reach 2,500 people\nDistributing chlorine tablets and repairing water systems\nTraining local staff to safely operate water treatment systems\n\n\n\n\nProviding shelter and essential supplies\nICRC emergency stocks pre-positioned near the epicentre are now being mobilized to support communities left with nothing. Reaching those in urgent need\nAmid this devastation, the International Committee of the Red Cross (ICRC), together with the Myanmar Red Cross Society and Red Cross and Red Crescent Movement partners, is delivering life-saving support. This included:\n\nSix emergency health kits, each capable of covering the medical needs of 10,000 people for three months\n600 body bags for the dignified recovery and identification of the deceased\nSupport for Myanmar Red Cross emergency teams conducting search-and-rescue and first aid operations\n\n\n\n\nEssential items for those helping on the front lines\nAfter discussions with front liners and analyzing the situation on the ground, we have provided the following essential items to assist in their work:\n\nHelmets and heavy duty gloves\nRopes, goggles, and items to assist in the search \nStretchers to carry the wounded\n\n\n\n\nSafe water, sanitation and disease prevention\nAccess to clean water is critical in any emergency. To reduce the risk of cholera and diarrhoea outbreaks, the ICRC and Myanmar Red Cross are:\n\nDeploying water treatment units in Mandalay, Sagaing and Nay Pyi Taw to reach 2,500 people\nDistributing chlorine tablets and repairing water systems\nTraining local staff to safely operate water treatment systems\n\n\n\n\nProviding shelter and essential supplies\nICRC emergency stocks pre-positioned near the epicentre are now being mobilized to support communities left with nothing. Reaching those in urgent need\nAmid this devastation, the International Committee of the Red Cross (ICRC), together with the Myanmar Red Cross Society and Red Cross and Red Crescent Movement partners, is delivering life-saving support. This included:\n\nSix emergency health kits, each capable of covering the medical needs of 10,000 people for three months\n600 body bags for the dignified recovery and identification of the deceased\nSupport for Myanmar Red Cross emergency teams conducting search-and-rescue and first aid operations\n\n\n\n\nEssential items for those helping on the front lines\nAfter discussions with front liners and analyzing the situation on the ground, we have provided the following essential items to assist in their work:\n\nHelmets and heavy duty gloves\nRopes, goggles, and items to assist in the search \nStretchers to carry the wounded\n\n\n\n\nSafe water, sanitation and disease prevention\nAccess to clean water is critical in any emergency. To reduce the risk of cholera and diarrhoea outbreaks, the ICRC and Myanmar Red Cross are:\n\nDeploying water treatment units in Mandalay, Sagaing and Nay Pyi Taw to reach 2,500 people\nDistributing chlorine tablets and repairing water systems\nTraining local staff to safely operate water treatment systems\n\n\n\n\nProviding shelter and essential supplies\nICRC emergency stocks pre-positioned near the epicentre are now being mobilized to support communities left with nothing. Amid this devastation, the International Committee of the Red Cross (ICRC), together with the Myanmar Red Cross Society and Red Cross and Red Crescent Movement partners, is delivering life-saving support. Amid this devastation, the International Committee of the Red Cross (ICRC), together with the Myanmar Red Cross Society and Red Cross and Red Crescent Movement partners, is delivering life-saving support. This included:\n\nSix emergency health kits, each capable of covering the medical needs of 10,000 people for three months\n600 body bags for the dignified recovery and identification of the deceased\nSupport for Myanmar Red Cross emergency teams conducting search-and-rescue and first aid operations\n\nOn 30 March 2025, just two days after the quake, a joint Red Cross convoy left Yangon carrying vital emergency supplies. This included:\n\nSix emergency health kits, each capable of covering the medical needs of 10,000 people for three months\n600 body bags for the dignified recovery and identification of the deceased\nSupport for Myanmar Red Cross emergency teams conducting search-and-rescue and first aid operations\n\nOn 30 March 2025, just two days after the quake, a joint Red Cross convoy left Yangon carrying vital emergency supplies. This included:\n\nEssential items for those helping on the front lines\nAfter discussions with front liners and analyzing the situation on the ground, we have provided the following essential items to assist in their work:\n\nHelmets and heavy duty gloves\nRopes, goggles, and items to assist in the search \nStretchers to carry the wounded\n\nAfter discussions with front liners and analyzing the situation on the ground, we have provided the following essential items to assist in their work:\n\nHelmets and heavy duty gloves\nRopes, goggles, and items to assist in the search \nStretchers to carry the wounded\n\nAfter discussions with front liners and analyzing the situation on the ground, we have provided the following essential items to assist in their work:\n\nSafe water, sanitation and disease prevention\nAccess to clean water is critical in any emergency. To reduce the risk of cholera and diarrhoea outbreaks, the ICRC and Myanmar Red Cross are:\n\nDeploying water treatment units in Mandalay, Sagaing and Nay Pyi Taw to reach 2,500 people\nDistributing chlorine tablets and repairing water systems\nTraining local staff to safely operate water treatment systems\n\nAccess to clean water is critical in any emergency. To reduce the risk of cholera and diarrhoea outbreaks, the ICRC and Myanmar Red Cross are:\n\nDeploying water treatment units in Mandalay, Sagaing and Nay Pyi Taw to reach 2,500 people\nDistributing chlorine tablets and repairing water systems\nTraining local staff to safely operate water treatment systems\n\nAccess to clean water is critical in any emergency. To reduce the risk of cholera and diarrhoea outbreaks, the ICRC and Myanmar Red Cross are:\n\nProviding shelter and essential supplies\nICRC emergency stocks pre-positioned near the epicentre are now being mobilized to support communities left with nothing. These include:\n\nFood rations (rice, pulses, and oil)\nTarpaulins and essential household kits\nPlans for distributions are already underway to reach the most vulnerable families\n\nICRC emergency stocks pre-positioned near the epicentre are now being mobilized to support communities left with nothing. These include:\n\nFood rations (rice, pulses, and oil)\nTarpaulins and essential household kits\nPlans for distributions are already underway to reach the most vulnerable families\n\nICRC emergency stocks pre-positioned near the epicentre are now being mobilized to support communities left with nothing. Ko Mohamed Ahyup\n  \n\n      ICRC staff\n\nUrgent help needed in Myanmar\n  \n\n\n\n      Following the devastating earthquake that has struck Myanmar and bordering regions, the scale of destruction is overwhelming — many are injured, displaced, or missing, with casualty numbers rising by the hour. Donate today\n\nUrgent help needed in Myanmar\n  \n\n\n\n      Following the devastating earthquake that has struck Myanmar and bordering regions, the scale of destruction is overwhelming — many are injured, displaced, or missing, with casualty numbers rising by the hour. Donate today\n\nICRC\n\nICRC\n\nICRC\n\nICRC\n\nICRC\n\nICRC\n\nRelated articles\n\n\n\n\n\n\n\n\n\n\n\n\n\n\n\nArticle\n\n04-04-2025\n\n\n\n\nFrequently asked questions about the ICRC's work in Myanmar\n\n\n\n\n\n\n\n\n\n\n\n\n\n\n\n\n\n\nArticle\n\n04-04-2025\n\n\n\n\nIn the minefields of Iraq, Noora works to restore life and hope to her homeland\n\n\n\n\n\n\n\n\n\n\n\n\n\n\n\n\n\n\nArticle\n\n04-04-2025\n\n\n\n\nMyanmar: Landmine awareness saves lives amid conflict and natural disasters\n\n\n\n\n\n\n\n\n\n\n\n\n\n\n\nMore articles\n\nRelated articles\n\n\n\n\n\n\n\n\n\n\n\n\n\n\n\nArticle\n\n04-04-2025\n\n\n\n\nFrequently asked questions about the ICRC's work in Myanmar\n\n\n\n\n\n\n\n\n\n\n\n\n\n\n\n\n\n\nArticle\n\n04-04-2025\n\n\n\n\nIn the minefields of Iraq, Noora works to restore life and hope to her homeland\n\n\n\n\n\n\n\n\n\n\n\n\n\n\n\n\n\n\nArticle\n\n04-04-2025\n\n\n\n\nMyanmar: Landmine awareness saves lives amid conflict and natural disasters\n\n\n\n\n\n\n\n\n\n\n\n\n\n\n\nMore articles\n\nRelated articles\n\n\n\n\n\n\n\n\n\n\n\n\n\n\n\nArticle\n\n04-04-2025\n\n\n\n\nFrequently asked questions about the ICRC's work in Myanmar\n\n\n\n\n\n\n\n\n\n\n\n\n\n\n\n\n\n\nArticle\n\n04-04-2025\n\n\n\n\nIn the minefields of Iraq, Noora works to restore life and hope to her homeland\n\n\n\n\n\n\n\n\n\n\n\n\n\n\n\n\n\n\nArticle\n\n04-04-2025\n\n\n\n\nMyanmar: Landmine awareness saves lives amid conflict and natural disasters\n\n\n\n\n\n\n\n\n\n\n\n\n\n\n\nMore articles\n\nRelated articles\n\n\n\n\n\n\n\n\n\n\n\n\n\n\n\nArticle\n\n04-04-2025\n\n\n\n\nFrequently asked questions about the ICRC's work in Myanmar\n\n\n\n\n\n\n\n\n\n\n\n\n\n\n\n\n\n\nArticle\n\n04-04-2025\n\n\n\n\nIn the minefields of Iraq, Noora works to restore life and hope to her homeland\n\n\n\n\n\n\n\n\n\n\n\n\n\n\n\n\n\n\nArticle\n\n04-04-2025\n\n\n\n\nMyanmar: Landmine awareness saves lives amid conflict and natural disasters\n\n\n\n\n\n\n\n\n\n\n\n\n\n\n\nMore articles\n\nRelated articles\n\n\n\n\n\n\n\n\n\n\n\n\n\n\n\nArticle\n\n04-04-2025\n\n\n\n\nFrequently asked questions about the ICRC's work in Myanmar\n\n\n\n\n\n\n\n\n\n\n\n\n\n\n\n\n\n\nArticle\n\n04-04-2025\n\n\n\n\nIn the minefields of Iraq, Noora works to restore life and hope to her homeland\n\n\n\n\n\n\n\n\n\n\n\n\n\n\n\n\n\n\nArticle\n\n04-04-2025\n\n\n\n\nMyanmar: Landmine awareness saves lives amid conflict and natural disasters\n\n\n\n\n\n\n\n\n\n\n\n\n\n\n\nMore articles\n\nRelated articles\n\nArticle\n\n04-04-2025\n\n\n\n\nFrequently asked questions about the ICRC's work in Myanmar\n\n\n\n\n\n\n\n\n\n\n\n\n\n\n\n\n\n\nArticle\n\n04-04-2025\n\n\n\n\nIn the minefields of Iraq, Noora works to restore life and hope to her homeland\n\n\n\n\n\n\n\n\n\n\n\n\n\n\n\n\n\n\nArticle\n\n04-04-2025\n\n\n\n\nMyanmar: Landmine awareness saves lives amid conflict and natural disasters\n\n\n\n\n\n\n\n\n\n\n\n\n\n\n\nMore articles\n\nArticle\n\n04-04-2025\n\n\n\n\nFrequently asked questions about the ICRC's work in Myanmar\n\n\n\n\n\n\n\n\n\n\n\n\n\n\n\n\n\n\nArticle\n\n04-04-2025\n\n\n\n\nIn the minefields of Iraq, Noora works to restore life and hope to her homeland\n\n\n\n\n\n\n\n\n\n\n\n\n\n\n\n\n\n\nArticle\n\n04-04-2025\n\n\n\n\nMyanmar: Landmine awareness saves lives amid conflict and natural disasters\n\nArticle\n\n04-04-2025\n\n\n\n\nFrequently asked questions about the ICRC's work in Myanmar\n\nArticle\n\n04-04-2025\n\n\n\n\nFrequently asked questions about the ICRC's work in Myanmar\n\nArticle\n\n04-04-2025\n\n\n\n\nFrequently asked questions about the ICRC's work in Myanmar\n\nArticle\n\n04-04-2025\n\n\n\n\nFrequently asked questions about the ICRC's work in Myanmar\n\nArticle\n\n04-04-2025\n\nArticle\n\n04-04-2025\n\nFrequently asked questions about the ICRC's work in Myanmar\n\nArticle\n\n04-04-2025\n\n\n\n\nIn the minefields of Iraq, Noora works to restore life and hope to her homeland\n\nArticle\n\n04-04-2025\n\n\n\n\nIn the minefields of Iraq, Noora works to restore life and hope to her homeland\n\nArticle\n\n04-04-2025\n\n\n\n\nIn the minefields of Iraq, Noora works to restore life and hope to her homeland\n\nArticle\n\n04-04-2025\n\n\n\n\nIn the minefields of Iraq, Noora works to restore life and hope to her homeland\n\nArticle\n\n04-04-2025\n\nArticle\n\n04-04-2025\n\nIn the minefields of Iraq, Noora works to restore life and hope to her homeland\n\nArticle\n\n04-04-2025\n\n\n\n\nMyanmar: Landmine awareness saves lives amid conflict and natural disasters\n\nArticle\n\n04-04-2025\n\n\n\n\nMyanmar: Landmine awareness saves lives amid conflict and natural disasters\n\nArticle\n\n04-04-2025\n\n\n\n\nMyanmar: Landmine awareness saves lives amid conflict and natural disasters\n\nArticle\n\n04-04-2025\n\n\n\n\nMyanmar: Landmine awareness saves lives amid conflict and natural disasters\n\nArticle\n\n04-04-2025\n\nArticle\n\n04-04-2025\n\nMyanmar: Landmine awareness saves lives amid conflict and natural disasters\n\nMore articles\n\nMore articles",
  "entities": {
    "countries": [
      "iraq"
    ],
    "organizations": [
      "un",
      "red cross"
    ],
    "key_issues": [
      "challenge",
      "situation",
      "nation",
      "state",
      "region",
      "program",
      "aid",
      "assistance",
      "un",
      "ngo"
    ]
  },
  "committee": "World Health Organization",
  "topic": "Treating disease in areas of prolonged conflict"
}