{
  "url": "https://www.icrc.org/en/article/afghanistan-2024-operational-facts-and-figures",
  "title": "Afghanistan: 2024 Operational facts and figures",
  "text": "Skip to main content\n\n\n\n\n\n\n\n\n\n\n\n\n\n            Article\n          \n\n10-02-2025\n\n\n\n\n\n2 languages\nEnglish\n中文\n\n\n\n\n\nAfghanistan: 2024 Operational facts and figures \n\n\n\nAfghanistan\nPhysical rehabilitation\nHealth\nEconomic Security\nReconnecting families\n\n\n\n\n\n\n\n\n\n\n\n\nAmir Mohammad/ICRC\n\n\n\n\nIn 2024, communities in Afghanistan continued to face significant challenges to access basic necessities such as healthcare, food and clean water. The humanitarian situation in the country remains extremely dire as a result of decades of armed conflict, economic hardship and natural disasters.\nThe International Committee of the Red Cross (ICRC) worked to respond to humanitarian challenges across Afghanistan by supporting healthcare, providing physical rehabilitation services, assisting people in establishing livelihoods and incomes, and improving access to clean water, sanitation and energy. \n\n\n\n\n\n\n\n\nWe also continued to visit places of detention to improve the conditions for detainees and advocate for them to be treated humanely and their rights to be respected. As Afghanistan remained one of the most heavily weapon-contaminated countries in the world, our teams have worked alongside our Afghan Red Crescent Society partners to raise awareness of mine risks within communities and promote the right behaviors to adopt to stay safe. \nA look at the measurable impact of our work in 2024:\n\n\n964,259 patients, (65 per cent women and children), received primary health care at 47 health facilities of the Afghan Red Crescent Society (ARCS) that are supported by the ICRC.\n\n\n312,371 doses of routine vaccinations were administered and 8,788 malnourished children benefited from the ARCS nutrition programme at the 47 clinics.\n\n\n215,274 patients were assisted in 7 ICRC-supported physical rehabilitation centres.\n\n\n34,036 prostheses and orthoses were manufactured, and 325,313 physiotherapy sessions were held.\n\n\n44,992 people received multipurpose cash assistance in Balkh, Badakhshan, Baghlan, Faryab and Nangarhar to meet their basic needs.\n\n\n50,584 farmers received cash grants to buy seeds, fertilizer, and tools to improve agricultural production.\n\n\nAround 460,000 people benefited from improved electricity supply in Zabul, Mazar, Kandahar, Helmand, Khost and Herat provinces.\n\n\nOver 1,120,000 people living in urban areas in Kabul, Herat, Faizabad, Kandahar, Maimana, Khost, Kunduz, and Shindand had improved access to clean drinking water.\n\n\n191 cases of missing people were resolved and their whereabouts ascertained.\n\n\n155 Red Cross messages (containing brief family news) and 6 salamats (oral short messages) were exchanged between detainees and their families.\n\n\nFor more details, access the full document below.\n\n\n\n\n\n\n\n\n\n\n\n\n\n\n\n\n\n      English_ICRC_Afghanistan_Facts_and_Figures_2024.pdf\n  \n\nPDF file\n3.76 MB\n\n\n\n\n\n\n\n\n\n\n\n\n\n\n\n\n\n\n\n\n\n\n      Dari_ICRC_Afghanistan_Facts_and_Figures_2024.pdf\n  \n\nPDF file\n3.92 MB\n\n\n\n\n\n\n\n\n\n\n\n\n\n\n\n\n\n\n\n\n\n\n      Pashto_ICRC_Afghanistan_Facts_and_Figures_2024.pdf\n  \n\nPDF file\n3.96 MB\n\n\n\n\n\n\n\n\n\n\n\n\n\n\n\n\n\n\n\n\nRelated articles\n\n\n\n\n\n\n\n\n\n\n\n\n\n\n\nArticle\n\n04-04-2025\n\n\n\n\nFrequently asked questions about the ICRC's work in Myanmar\n\n\n\n\n\n\n\n\n\n\n\n\n\n\n\n\n\n\nArticle\n\n04-04-2025\n\n\n\n\nIn the minefields of Iraq, Noora works to restore life and hope to her homeland\n\n\n\n\n\n\n\n\n\n\n\n\n\n\n\n\n\n\nArticle\n\n04-04-2025\n\n\n\n\nMyanmar: Landmine awareness saves lives amid conflict and natural disasters\n\n\n\n\n\n\n\n\n\n\n\n\n\n\n\nMore articles\n\nSkip to main content\n\n\n\n\n\n\n\n\n\n\n\n\n\n            Article\n          \n\n10-02-2025\n\n\n\n\n\n2 languages\nEnglish\n中文\n\n\n\n\n\nAfghanistan: 2024 Operational facts and figures \n\n\n\nAfghanistan\nPhysical rehabilitation\nHealth\nEconomic Security\nReconnecting families\n\n\n\n\n\n\n\n\n\n\n\n\nAmir Mohammad/ICRC\n\n\n\n\nIn 2024, communities in Afghanistan continued to face significant challenges to access basic necessities such as healthcare, food and clean water. The humanitarian situation in the country remains extremely dire as a result of decades of armed conflict, economic hardship and natural disasters.\nThe International Committee of the Red Cross (ICRC) worked to respond to humanitarian challenges across Afghanistan by supporting healthcare, providing physical rehabilitation services, assisting people in establishing livelihoods and incomes, and improving access to clean water, sanitation and energy. \n\n\n\n\n\n\n\n\nWe also continued to visit places of detention to improve the conditions for detainees and advocate for them to be treated humanely and their rights to be respected. As Afghanistan remained one of the most heavily weapon-contaminated countries in the world, our teams have worked alongside our Afghan Red Crescent Society partners to raise awareness of mine risks within communities and promote the right behaviors to adopt to stay safe. \nA look at the measurable impact of our work in 2024:\n\n\n964,259 patients, (65 per cent women and children), received primary health care at 47 health facilities of the Afghan Red Crescent Society (ARCS) that are supported by the ICRC.\n\n\n312,371 doses of routine vaccinations were administered and 8,788 malnourished children benefited from the ARCS nutrition programme at the 47 clinics.\n\n\n215,274 patients were assisted in 7 ICRC-supported physical rehabilitation centres.\n\n\n34,036 prostheses and orthoses were manufactured, and 325,313 physiotherapy sessions were held.\n\n\n44,992 people received multipurpose cash assistance in Balkh, Badakhshan, Baghlan, Faryab and Nangarhar to meet their basic needs.\n\n\n50,584 farmers received cash grants to buy seeds, fertilizer, and tools to improve agricultural production.\n\n\nAround 460,000 people benefited from improved electricity supply in Zabul, Mazar, Kandahar, Helmand, Khost and Herat provinces.\n\n\nOver 1,120,000 people living in urban areas in Kabul, Herat, Faizabad, Kandahar, Maimana, Khost, Kunduz, and Shindand had improved access to clean drinking water.\n\n\n191 cases of missing people were resolved and their whereabouts ascertained.\n\n\n155 Red Cross messages (containing brief family news) and 6 salamats (oral short messages) were exchanged between detainees and their families.\n\n\nFor more details, access the full document below.\n\n\n\n\n\n\n\n\n\n\n\n\n\n\n\n\n\n      English_ICRC_Afghanistan_Facts_and_Figures_2024.pdf\n  \n\nPDF file\n3.76 MB\n\n\n\n\n\n\n\n\n\n\n\n\n\n\n\n\n\n\n\n\n\n\n      Dari_ICRC_Afghanistan_Facts_and_Figures_2024.pdf\n  \n\nPDF file\n3.92 MB\n\n\n\n\n\n\n\n\n\n\n\n\n\n\n\n\n\n\n\n\n\n\n      Pashto_ICRC_Afghanistan_Facts_and_Figures_2024.pdf\n  \n\nPDF file\n3.96 MB\n\n\n\n\n\n\n\n\n\n\n\n\n\n\n\n\n\n\n\n\nRelated articles\n\n\n\n\n\n\n\n\n\n\n\n\n\n\n\nArticle\n\n04-04-2025\n\n\n\n\nFrequently asked questions about the ICRC's work in Myanmar\n\n\n\n\n\n\n\n\n\n\n\n\n\n\n\n\n\n\nArticle\n\n04-04-2025\n\n\n\n\nIn the minefields of Iraq, Noora works to restore life and hope to her homeland\n\n\n\n\n\n\n\n\n\n\n\n\n\n\n\n\n\n\nArticle\n\n04-04-2025\n\n\n\n\nMyanmar: Landmine awareness saves lives amid conflict and natural disasters\n\n\n\n\n\n\n\n\n\n\n\n\n\n\n\nMore articles\n\nArticle\n          \n\n10-02-2025\n\n\n\n\n\n2 languages\nEnglish\n中文\n\n\n\n\n\nAfghanistan: 2024 Operational facts and figures \n\n\n\nAfghanistan\nPhysical rehabilitation\nHealth\nEconomic Security\nReconnecting families\n\n\n\n\n\n\n\n\n\n\n\n\nAmir Mohammad/ICRC\n\n\n\n\nIn 2024, communities in Afghanistan continued to face significant challenges to access basic necessities such as healthcare, food and clean water. The humanitarian situation in the country remains extremely dire as a result of decades of armed conflict, economic hardship and natural disasters.\nThe International Committee of the Red Cross (ICRC) worked to respond to humanitarian challenges across Afghanistan by supporting healthcare, providing physical rehabilitation services, assisting people in establishing livelihoods and incomes, and improving access to clean water, sanitation and energy. \n\n\n\n\n\n\n\n\nWe also continued to visit places of detention to improve the conditions for detainees and advocate for them to be treated humanely and their rights to be respected. As Afghanistan remained one of the most heavily weapon-contaminated countries in the world, our teams have worked alongside our Afghan Red Crescent Society partners to raise awareness of mine risks within communities and promote the right behaviors to adopt to stay safe. \nA look at the measurable impact of our work in 2024:\n\n\n964,259 patients, (65 per cent women and children), received primary health care at 47 health facilities of the Afghan Red Crescent Society (ARCS) that are supported by the ICRC.\n\n\n312,371 doses of routine vaccinations were administered and 8,788 malnourished children benefited from the ARCS nutrition programme at the 47 clinics.\n\n\n215,274 patients were assisted in 7 ICRC-supported physical rehabilitation centres.\n\n\n34,036 prostheses and orthoses were manufactured, and 325,313 physiotherapy sessions were held.\n\n\n44,992 people received multipurpose cash assistance in Balkh, Badakhshan, Baghlan, Faryab and Nangarhar to meet their basic needs.\n\n\n50,584 farmers received cash grants to buy seeds, fertilizer, and tools to improve agricultural production.\n\n\nAround 460,000 people benefited from improved electricity supply in Zabul, Mazar, Kandahar, Helmand, Khost and Herat provinces.\n\n\nOver 1,120,000 people living in urban areas in Kabul, Herat, Faizabad, Kandahar, Maimana, Khost, Kunduz, and Shindand had improved access to clean drinking water.\n\n\n191 cases of missing people were resolved and their whereabouts ascertained.\n\n\n155 Red Cross messages (containing brief family news) and 6 salamats (oral short messages) were exchanged between detainees and their families.\n\n\nFor more details, access the full document below.\n\n\n\n\n\n\n\n\n\n\n\n\n\n\n\n\n\n      English_ICRC_Afghanistan_Facts_and_Figures_2024.pdf\n  \n\nPDF file\n3.76 MB\n\n\n\n\n\n\n\n\n\n\n\n\n\n\n\n\n\n\n\n\n\n\n      Dari_ICRC_Afghanistan_Facts_and_Figures_2024.pdf\n  \n\nPDF file\n3.92 MB\n\n\n\n\n\n\n\n\n\n\n\n\n\n\n\n\n\n\n\n\n\n\n      Pashto_ICRC_Afghanistan_Facts_and_Figures_2024.pdf\n  \n\nPDF file\n3.96 MB\n\n\n\n\n\n\n\n\n\n\n\n\n\n\n\n\n\n\n\n\nRelated articles\n\n\n\n\n\n\n\n\n\n\n\n\n\n\n\nArticle\n\n04-04-2025\n\n\n\n\nFrequently asked questions about the ICRC's work in Myanmar\n\n\n\n\n\n\n\n\n\n\n\n\n\n\n\n\n\n\nArticle\n\n04-04-2025\n\n\n\n\nIn the minefields of Iraq, Noora works to restore life and hope to her homeland\n\n\n\n\n\n\n\n\n\n\n\n\n\n\n\n\n\n\nArticle\n\n04-04-2025\n\n\n\n\nMyanmar: Landmine awareness saves lives amid conflict and natural disasters\n\n\n\n\n\n\n\n\n\n\n\n\n\n\n\nMore articles\n\nArticle\n          \n\n10-02-2025\n\n\n\n\n\n2 languages\nEnglish\n中文\n\n\n\n\n\nAfghanistan: 2024 Operational facts and figures \n\n\n\nAfghanistan\nPhysical rehabilitation\nHealth\nEconomic Security\nReconnecting families\n\n\n\n\n\n\n\n\n\n\n\n\nAmir Mohammad/ICRC\n\n\n\n\nIn 2024, communities in Afghanistan continued to face significant challenges to access basic necessities such as healthcare, food and clean water. The humanitarian situation in the country remains extremely dire as a result of decades of armed conflict, economic hardship and natural disasters.\nThe International Committee of the Red Cross (ICRC) worked to respond to humanitarian challenges across Afghanistan by supporting healthcare, providing physical rehabilitation services, assisting people in establishing livelihoods and incomes, and improving access to clean water, sanitation and energy. \n\n\n\n\n\n\n\n\nWe also continued to visit places of detention to improve the conditions for detainees and advocate for them to be treated humanely and their rights to be respected. As Afghanistan remained one of the most heavily weapon-contaminated countries in the world, our teams have worked alongside our Afghan Red Crescent Society partners to raise awareness of mine risks within communities and promote the right behaviors to adopt to stay safe. \nA look at the measurable impact of our work in 2024:\n\n\n964,259 patients, (65 per cent women and children), received primary health care at 47 health facilities of the Afghan Red Crescent Society (ARCS) that are supported by the ICRC.\n\n\n312,371 doses of routine vaccinations were administered and 8,788 malnourished children benefited from the ARCS nutrition programme at the 47 clinics.\n\n\n215,274 patients were assisted in 7 ICRC-supported physical rehabilitation centres.\n\n\n34,036 prostheses and orthoses were manufactured, and 325,313 physiotherapy sessions were held.\n\n\n44,992 people received multipurpose cash assistance in Balkh, Badakhshan, Baghlan, Faryab and Nangarhar to meet their basic needs.\n\n\n50,584 farmers received cash grants to buy seeds, fertilizer, and tools to improve agricultural production.\n\n\nAround 460,000 people benefited from improved electricity supply in Zabul, Mazar, Kandahar, Helmand, Khost and Herat provinces.\n\n\nOver 1,120,000 people living in urban areas in Kabul, Herat, Faizabad, Kandahar, Maimana, Khost, Kunduz, and Shindand had improved access to clean drinking water.\n\n\n191 cases of missing people were resolved and their whereabouts ascertained.\n\n\n155 Red Cross messages (containing brief family news) and 6 salamats (oral short messages) were exchanged between detainees and their families.\n\n\nFor more details, access the full document below.\n\n\n\n\n\n\n\n\n\n\n\n\n\n\n\n\n\n      English_ICRC_Afghanistan_Facts_and_Figures_2024.pdf\n  \n\nPDF file\n3.76 MB\n\n\n\n\n\n\n\n\n\n\n\n\n\n\n\n\n\n\n\n\n\n\n      Dari_ICRC_Afghanistan_Facts_and_Figures_2024.pdf\n  \n\nPDF file\n3.92 MB\n\n\n\n\n\n\n\n\n\n\n\n\n\n\n\n\n\n\n\n\n\n\n      Pashto_ICRC_Afghanistan_Facts_and_Figures_2024.pdf\n  \n\nPDF file\n3.96 MB\n\n\n\n\n\n\n\n\n\n\n\n\n\n\n\n\n\n\n\n\nRelated articles\n\n\n\n\n\n\n\n\n\n\n\n\n\n\n\nArticle\n\n04-04-2025\n\n\n\n\nFrequently asked questions about the ICRC's work in Myanmar\n\n\n\n\n\n\n\n\n\n\n\n\n\n\n\n\n\n\nArticle\n\n04-04-2025\n\n\n\n\nIn the minefields of Iraq, Noora works to restore life and hope to her homeland\n\n\n\n\n\n\n\n\n\n\n\n\n\n\n\n\n\n\nArticle\n\n04-04-2025\n\n\n\n\nMyanmar: Landmine awareness saves lives amid conflict and natural disasters\n\n\n\n\n\n\n\n\n\n\n\n\n\n\n\nMore articles\n\nArticle\n          \n\n10-02-2025\n\n\n\n\n\n2 languages\nEnglish\n中文\n\n\n\n\n\nAfghanistan: 2024 Operational facts and figures \n\n\n\nAfghanistan\nPhysical rehabilitation\nHealth\nEconomic Security\nReconnecting families\n\n\n\n\n\n\n\n\n\n\n\n\nAmir Mohammad/ICRC\n\n\n\n\nIn 2024, communities in Afghanistan continued to face significant challenges to access basic necessities such as healthcare, food and clean water. The humanitarian situation in the country remains extremely dire as a result of decades of armed conflict, economic hardship and natural disasters.\nThe International Committee of the Red Cross (ICRC) worked to respond to humanitarian challenges across Afghanistan by supporting healthcare, providing physical rehabilitation services, assisting people in establishing livelihoods and incomes, and improving access to clean water, sanitation and energy. \n\n\n\n\n\n\n\n\nWe also continued to visit places of detention to improve the conditions for detainees and advocate for them to be treated humanely and their rights to be respected. As Afghanistan remained one of the most heavily weapon-contaminated countries in the world, our teams have worked alongside our Afghan Red Crescent Society partners to raise awareness of mine risks within communities and promote the right behaviors to adopt to stay safe. \nA look at the measurable impact of our work in 2024:\n\n\n964,259 patients, (65 per cent women and children), received primary health care at 47 health facilities of the Afghan Red Crescent Society (ARCS) that are supported by the ICRC.\n\n\n312,371 doses of routine vaccinations were administered and 8,788 malnourished children benefited from the ARCS nutrition programme at the 47 clinics.\n\n\n215,274 patients were assisted in 7 ICRC-supported physical rehabilitation centres.\n\n\n34,036 prostheses and orthoses were manufactured, and 325,313 physiotherapy sessions were held.\n\n\n44,992 people received multipurpose cash assistance in Balkh, Badakhshan, Baghlan, Faryab and Nangarhar to meet their basic needs.\n\n\n50,584 farmers received cash grants to buy seeds, fertilizer, and tools to improve agricultural production.\n\n\nAround 460,000 people benefited from improved electricity supply in Zabul, Mazar, Kandahar, Helmand, Khost and Herat provinces.\n\n\nOver 1,120,000 people living in urban areas in Kabul, Herat, Faizabad, Kandahar, Maimana, Khost, Kunduz, and Shindand had improved access to clean drinking water.\n\n\n191 cases of missing people were resolved and their whereabouts ascertained.\n\n\n155 Red Cross messages (containing brief family news) and 6 salamats (oral short messages) were exchanged between detainees and their families.\n\n\nFor more details, access the full document below.\n\n\n\n\n\n\n\n\n\n\n\n\n\n\n\n\n\n      English_ICRC_Afghanistan_Facts_and_Figures_2024.pdf\n  \n\nPDF file\n3.76 MB\n\n\n\n\n\n\n\n\n\n\n\n\n\n\n\n\n\n\n\n\n\n\n      Dari_ICRC_Afghanistan_Facts_and_Figures_2024.pdf\n  \n\nPDF file\n3.92 MB\n\n\n\n\n\n\n\n\n\n\n\n\n\n\n\n\n\n\n\n\n\n\n      Pashto_ICRC_Afghanistan_Facts_and_Figures_2024.pdf\n  \n\nPDF file\n3.96 MB\n\n\n\n\n\n\n\n\n\n\n\n\n\n\n\n\n\n\n\n\nRelated articles\n\n\n\n\n\n\n\n\n\n\n\n\n\n\n\nArticle\n\n04-04-2025\n\n\n\n\nFrequently asked questions about the ICRC's work in Myanmar\n\n\n\n\n\n\n\n\n\n\n\n\n\n\n\n\n\n\nArticle\n\n04-04-2025\n\n\n\n\nIn the minefields of Iraq, Noora works to restore life and hope to her homeland\n\n\n\n\n\n\n\n\n\n\n\n\n\n\n\n\n\n\nArticle\n\n04-04-2025\n\n\n\n\nMyanmar: Landmine awareness saves lives amid conflict and natural disasters\n\n\n\n\n\n\n\n\n\n\n\n\n\n\n\nMore articles\n\nArticle\n          \n\n10-02-2025\n\n\n\n\n\n2 languages\nEnglish\n中文\n\n\n\n\n\nAfghanistan: 2024 Operational facts and figures \n\n\n\nAfghanistan\nPhysical rehabilitation\nHealth\nEconomic Security\nReconnecting families\n\n\n\n\n\n\n\n\n\n\n\n\nAmir Mohammad/ICRC\n\n\n\n\nIn 2024, communities in Afghanistan continued to face significant challenges to access basic necessities such as healthcare, food and clean water. The humanitarian situation in the country remains extremely dire as a result of decades of armed conflict, economic hardship and natural disasters.\nThe International Committee of the Red Cross (ICRC) worked to respond to humanitarian challenges across Afghanistan by supporting healthcare, providing physical rehabilitation services, assisting people in establishing livelihoods and incomes, and improving access to clean water, sanitation and energy. \n\n\n\n\n\n\n\n\nWe also continued to visit places of detention to improve the conditions for detainees and advocate for them to be treated humanely and their rights to be respected. As Afghanistan remained one of the most heavily weapon-contaminated countries in the world, our teams have worked alongside our Afghan Red Crescent Society partners to raise awareness of mine risks within communities and promote the right behaviors to adopt to stay safe. \nA look at the measurable impact of our work in 2024:\n\n\n964,259 patients, (65 per cent women and children), received primary health care at 47 health facilities of the Afghan Red Crescent Society (ARCS) that are supported by the ICRC.\n\n\n312,371 doses of routine vaccinations were administered and 8,788 malnourished children benefited from the ARCS nutrition programme at the 47 clinics.\n\n\n215,274 patients were assisted in 7 ICRC-supported physical rehabilitation centres.\n\n\n34,036 prostheses and orthoses were manufactured, and 325,313 physiotherapy sessions were held.\n\n\n44,992 people received multipurpose cash assistance in Balkh, Badakhshan, Baghlan, Faryab and Nangarhar to meet their basic needs.\n\n\n50,584 farmers received cash grants to buy seeds, fertilizer, and tools to improve agricultural production.\n\n\nAround 460,000 people benefited from improved electricity supply in Zabul, Mazar, Kandahar, Helmand, Khost and Herat provinces.\n\n\nOver 1,120,000 people living in urban areas in Kabul, Herat, Faizabad, Kandahar, Maimana, Khost, Kunduz, and Shindand had improved access to clean drinking water.\n\n\n191 cases of missing people were resolved and their whereabouts ascertained.\n\n\n155 Red Cross messages (containing brief family news) and 6 salamats (oral short messages) were exchanged between detainees and their families.\n\n\nFor more details, access the full document below.\n\n\n\n\n\n\n\n\n\n\n\n\n\n\n\n\n\n      English_ICRC_Afghanistan_Facts_and_Figures_2024.pdf\n  \n\nPDF file\n3.76 MB\n\n\n\n\n\n\n\n\n\n\n\n\n\n\n\n\n\n\n\n\n\n\n      Dari_ICRC_Afghanistan_Facts_and_Figures_2024.pdf\n  \n\nPDF file\n3.92 MB\n\n\n\n\n\n\n\n\n\n\n\n\n\n\n\n\n\n\n\n\n\n\n      Pashto_ICRC_Afghanistan_Facts_and_Figures_2024.pdf\n  \n\nPDF file\n3.96 MB\n\n\n\n\n\n\n\n\n\n\n\n\n\n\n\n\n\n\n\n\nRelated articles\n\n\n\n\n\n\n\n\n\n\n\n\n\n\n\nArticle\n\n04-04-2025\n\n\n\n\nFrequently asked questions about the ICRC's work in Myanmar\n\n\n\n\n\n\n\n\n\n\n\n\n\n\n\n\n\n\nArticle\n\n04-04-2025\n\n\n\n\nIn the minefields of Iraq, Noora works to restore life and hope to her homeland\n\n\n\n\n\n\n\n\n\n\n\n\n\n\n\n\n\n\nArticle\n\n04-04-2025\n\n\n\n\nMyanmar: Landmine awareness saves lives amid conflict and natural disasters\n\n\n\n\n\n\n\n\n\n\n\n\n\n\n\nMore articles\n\nArticle\n          \n\n10-02-2025\n\n\n\n\n\n2 languages\nEnglish\n中文\n\n\n\n\n\nAfghanistan: 2024 Operational facts and figures \n\n\n\nAfghanistan\nPhysical rehabilitation\nHealth\nEconomic Security\nReconnecting families\n\n\n\n\n\n\n\n\n\n\n\n\nAmir Mohammad/ICRC\n\n\n\n\nIn 2024, communities in Afghanistan continued to face significant challenges to access basic necessities such as healthcare, food and clean water. The humanitarian situation in the country remains extremely dire as a result of decades of armed conflict, economic hardship and natural disasters.\nThe International Committee of the Red Cross (ICRC) worked to respond to humanitarian challenges across Afghanistan by supporting healthcare, providing physical rehabilitation services, assisting people in establishing livelihoods and incomes, and improving access to clean water, sanitation and energy.\n\nArticle\n          \n\n10-02-2025\n\n\n\n\n\n2 languages\nEnglish\n中文\n\n\n\n\n\nAfghanistan: 2024 Operational facts and figures \n\n\n\nAfghanistan\nPhysical rehabilitation\nHealth\nEconomic Security\nReconnecting families\n\nArticle\n          \n\n10-02-2025\n\n\n\n\n\n2 languages\nEnglish\n中文\n\nArticle\n          \n\n10-02-2025\n\nArticle\n\n10-02-2025\n\n2 languages\nEnglish\n中文\n\n2 languages\nEnglish\n中文\n\nAfghanistan: 2024 Operational facts and figures\n\nAfghanistan\nPhysical rehabilitation\nHealth\nEconomic Security\nReconnecting families\n\nAmir Mohammad/ICRC\n\nAmir Mohammad/ICRC\n\nAmir Mohammad/ICRC\n\nIn 2024, communities in Afghanistan continued to face significant challenges to access basic necessities such as healthcare, food and clean water. The humanitarian situation in the country remains extremely dire as a result of decades of armed conflict, economic hardship and natural disasters.\nThe International Committee of the Red Cross (ICRC) worked to respond to humanitarian challenges across Afghanistan by supporting healthcare, providing physical rehabilitation services, assisting people in establishing livelihoods and incomes, and improving access to clean water, sanitation and energy.\n\nIn 2024, communities in Afghanistan continued to face significant challenges to access basic necessities such as healthcare, food and clean water. The humanitarian situation in the country remains extremely dire as a result of decades of armed conflict, economic hardship and natural disasters.\nThe International Committee of the Red Cross (ICRC) worked to respond to humanitarian challenges across Afghanistan by supporting healthcare, providing physical rehabilitation services, assisting people in establishing livelihoods and incomes, and improving access to clean water, sanitation and energy.\n\nIn 2024, communities in Afghanistan continued to face significant challenges to access basic necessities such as healthcare, food and clean water. The humanitarian situation in the country remains extremely dire as a result of decades of armed conflict, economic hardship and natural disasters.\nThe International Committee of the Red Cross (ICRC) worked to respond to humanitarian challenges across Afghanistan by supporting healthcare, providing physical rehabilitation services, assisting people in establishing livelihoods and incomes, and improving access to clean water, sanitation and energy.\n\nIn 2024, communities in Afghanistan continued to face significant challenges to access basic necessities such as healthcare, food and clean water. The humanitarian situation in the country remains extremely dire as a result of decades of armed conflict, economic hardship and natural disasters.\n\nThe International Committee of the Red Cross (ICRC) worked to respond to humanitarian challenges across Afghanistan by supporting healthcare, providing physical rehabilitation services, assisting people in establishing livelihoods and incomes, and improving access to clean water, sanitation and energy.\n\nWe also continued to visit places of detention to improve the conditions for detainees and advocate for them to be treated humanely and their rights to be respected. As Afghanistan remained one of the most heavily weapon-contaminated countries in the world, our teams have worked alongside our Afghan Red Crescent Society partners to raise awareness of mine risks within communities and promote the right behaviors to adopt to stay safe. \nA look at the measurable impact of our work in 2024:\n\n\n964,259 patients, (65 per cent women and children), received primary health care at 47 health facilities of the Afghan Red Crescent Society (ARCS) that are supported by the ICRC.\n\n\n312,371 doses of routine vaccinations were administered and 8,788 malnourished children benefited from the ARCS nutrition programme at the 47 clinics.\n\n\n215,274 patients were assisted in 7 ICRC-supported physical rehabilitation centres.\n\n\n34,036 prostheses and orthoses were manufactured, and 325,313 physiotherapy sessions were held.\n\n\n44,992 people received multipurpose cash assistance in Balkh, Badakhshan, Baghlan, Faryab and Nangarhar to meet their basic needs.\n\n\n50,584 farmers received cash grants to buy seeds, fertilizer, and tools to improve agricultural production.\n\n\nAround 460,000 people benefited from improved electricity supply in Zabul, Mazar, Kandahar, Helmand, Khost and Herat provinces.\n\n\nOver 1,120,000 people living in urban areas in Kabul, Herat, Faizabad, Kandahar, Maimana, Khost, Kunduz, and Shindand had improved access to clean drinking water.\n\n\n191 cases of missing people were resolved and their whereabouts ascertained.\n\n\n155 Red Cross messages (containing brief family news) and 6 salamats (oral short messages) were exchanged between detainees and their families.\n\n\nFor more details, access the full document below.\n\nWe also continued to visit places of detention to improve the conditions for detainees and advocate for them to be treated humanely and their rights to be respected. As Afghanistan remained one of the most heavily weapon-contaminated countries in the world, our teams have worked alongside our Afghan Red Crescent Society partners to raise awareness of mine risks within communities and promote the right behaviors to adopt to stay safe. \nA look at the measurable impact of our work in 2024:\n\n\n964,259 patients, (65 per cent women and children), received primary health care at 47 health facilities of the Afghan Red Crescent Society (ARCS) that are supported by the ICRC.\n\n\n312,371 doses of routine vaccinations were administered and 8,788 malnourished children benefited from the ARCS nutrition programme at the 47 clinics.\n\n\n215,274 patients were assisted in 7 ICRC-supported physical rehabilitation centres.\n\n\n34,036 prostheses and orthoses were manufactured, and 325,313 physiotherapy sessions were held.\n\n\n44,992 people received multipurpose cash assistance in Balkh, Badakhshan, Baghlan, Faryab and Nangarhar to meet their basic needs.\n\n\n50,584 farmers received cash grants to buy seeds, fertilizer, and tools to improve agricultural production.\n\n\nAround 460,000 people benefited from improved electricity supply in Zabul, Mazar, Kandahar, Helmand, Khost and Herat provinces.\n\n\nOver 1,120,000 people living in urban areas in Kabul, Herat, Faizabad, Kandahar, Maimana, Khost, Kunduz, and Shindand had improved access to clean drinking water.\n\n\n191 cases of missing people were resolved and their whereabouts ascertained.\n\n\n155 Red Cross messages (containing brief family news) and 6 salamats (oral short messages) were exchanged between detainees and their families.\n\n\nFor more details, access the full document below.\n\nWe also continued to visit places of detention to improve the conditions for detainees and advocate for them to be treated humanely and their rights to be respected. As Afghanistan remained one of the most heavily weapon-contaminated countries in the world, our teams have worked alongside our Afghan Red Crescent Society partners to raise awareness of mine risks within communities and promote the right behaviors to adopt to stay safe. \nA look at the measurable impact of our work in 2024:\n\n\n964,259 patients, (65 per cent women and children), received primary health care at 47 health facilities of the Afghan Red Crescent Society (ARCS) that are supported by the ICRC.\n\n\n312,371 doses of routine vaccinations were administered and 8,788 malnourished children benefited from the ARCS nutrition programme at the 47 clinics.\n\n\n215,274 patients were assisted in 7 ICRC-supported physical rehabilitation centres.\n\n\n34,036 prostheses and orthoses were manufactured, and 325,313 physiotherapy sessions were held.\n\n\n44,992 people received multipurpose cash assistance in Balkh, Badakhshan, Baghlan, Faryab and Nangarhar to meet their basic needs.\n\n\n50,584 farmers received cash grants to buy seeds, fertilizer, and tools to improve agricultural production.\n\n\nAround 460,000 people benefited from improved electricity supply in Zabul, Mazar, Kandahar, Helmand, Khost and Herat provinces.\n\n\nOver 1,120,000 people living in urban areas in Kabul, Herat, Faizabad, Kandahar, Maimana, Khost, Kunduz, and Shindand had improved access to clean drinking water.\n\n\n191 cases of missing people were resolved and their whereabouts ascertained.\n\n\n155 Red Cross messages (containing brief family news) and 6 salamats (oral short messages) were exchanged between detainees and their families.\n\n\nFor more details, access the full document below.\n\nWe also continued to visit places of detention to improve the conditions for detainees and advocate for them to be treated humanely and their rights to be respected. As Afghanistan remained one of the most heavily weapon-contaminated countries in the world, our teams have worked alongside our Afghan Red Crescent Society partners to raise awareness of mine risks within communities and promote the right behaviors to adopt to stay safe. \nA look at the measurable impact of our work in 2024:\n\n\n964,259 patients, (65 per cent women and children), received primary health care at 47 health facilities of the Afghan Red Crescent Society (ARCS) that are supported by the ICRC.\n\n\n312,371 doses of routine vaccinations were administered and 8,788 malnourished children benefited from the ARCS nutrition programme at the 47 clinics.\n\n\n215,274 patients were assisted in 7 ICRC-supported physical rehabilitation centres.\n\n\n34,036 prostheses and orthoses were manufactured, and 325,313 physiotherapy sessions were held.\n\n\n44,992 people received multipurpose cash assistance in Balkh, Badakhshan, Baghlan, Faryab and Nangarhar to meet their basic needs.\n\n\n50,584 farmers received cash grants to buy seeds, fertilizer, and tools to improve agricultural production.\n\n\nAround 460,000 people benefited from improved electricity supply in Zabul, Mazar, Kandahar, Helmand, Khost and Herat provinces.\n\n\nOver 1,120,000 people living in urban areas in Kabul, Herat, Faizabad, Kandahar, Maimana, Khost, Kunduz, and Shindand had improved access to clean drinking water.\n\n\n191 cases of missing people were resolved and their whereabouts ascertained.\n\n\n155 Red Cross messages (containing brief family news) and 6 salamats (oral short messages) were exchanged between detainees and their families.\n\n\nFor more details, access the full document below.\n\nWe also continued to visit places of detention to improve the conditions for detainees and advocate for them to be treated humanely and their rights to be respected. As Afghanistan remained one of the most heavily weapon-contaminated countries in the world, our teams have worked alongside our Afghan Red Crescent Society partners to raise awareness of mine risks within communities and promote the right behaviors to adopt to stay safe.\n\nA look at the measurable impact of our work in 2024:\n\n964,259 patients, (65 per cent women and children), received primary health care at 47 health facilities of the Afghan Red Crescent Society (ARCS) that are supported by the ICRC.\n\n312,371 doses of routine vaccinations were administered and 8,788 malnourished children benefited from the ARCS nutrition programme at the 47 clinics.\n\n215,274 patients were assisted in 7 ICRC-supported physical rehabilitation centres.\n\n34,036 prostheses and orthoses were manufactured, and 325,313 physiotherapy sessions were held.\n\n44,992 people received multipurpose cash assistance in Balkh, Badakhshan, Baghlan, Faryab and Nangarhar to meet their basic needs.\n\n50,584 farmers received cash grants to buy seeds, fertilizer, and tools to improve agricultural production.\n\nAround 460,000 people benefited from improved electricity supply in Zabul, Mazar, Kandahar, Helmand, Khost and Herat provinces.\n\nOver 1,120,000 people living in urban areas in Kabul, Herat, Faizabad, Kandahar, Maimana, Khost, Kunduz, and Shindand had improved access to clean drinking water.\n\n191 cases of missing people were resolved and their whereabouts ascertained.\n\n155 Red Cross messages (containing brief family news) and 6 salamats (oral short messages) were exchanged between detainees and their families.\n\nFor more details, access the full document below.\n\nEnglish_ICRC_Afghanistan_Facts_and_Figures_2024.pdf\n  \n\nPDF file\n3.76 MB\n\n\n\n\n\n\n\n\n\n\n\n\n\n\n\n\n\n\n\n\n\n\n      Dari_ICRC_Afghanistan_Facts_and_Figures_2024.pdf\n  \n\nPDF file\n3.92 MB\n\n\n\n\n\n\n\n\n\n\n\n\n\n\n\n\n\n\n\n\n\n\n      Pashto_ICRC_Afghanistan_Facts_and_Figures_2024.pdf\n  \n\nPDF file\n3.96 MB\n\nEnglish_ICRC_Afghanistan_Facts_and_Figures_2024.pdf\n  \n\nPDF file\n3.76 MB\n\n\n\n\n\n\n\n\n\n\n\n\n\n\n\n\n\n\n\n\n\n\n      Dari_ICRC_Afghanistan_Facts_and_Figures_2024.pdf\n  \n\nPDF file\n3.92 MB\n\n\n\n\n\n\n\n\n\n\n\n\n\n\n\n\n\n\n\n\n\n\n      Pashto_ICRC_Afghanistan_Facts_and_Figures_2024.pdf\n  \n\nPDF file\n3.96 MB\n\nEnglish_ICRC_Afghanistan_Facts_and_Figures_2024.pdf\n  \n\nPDF file\n3.76 MB\n\n\n\n\n\n\n\n\n\n\n\n\n\n\n\n\n\n\n\n\n\n\n      Dari_ICRC_Afghanistan_Facts_and_Figures_2024.pdf\n  \n\nPDF file\n3.92 MB\n\n\n\n\n\n\n\n\n\n\n\n\n\n\n\n\n\n\n\n\n\n\n      Pashto_ICRC_Afghanistan_Facts_and_Figures_2024.pdf\n  \n\nPDF file\n3.96 MB\n\nEnglish_ICRC_Afghanistan_Facts_and_Figures_2024.pdf\n  \n\nPDF file\n3.76 MB\n\nEnglish_ICRC_Afghanistan_Facts_and_Figures_2024.pdf\n  \n\nPDF file\n3.76 MB\n\nEnglish_ICRC_Afghanistan_Facts_and_Figures_2024.pdf\n\nPDF file\n3.76 MB\n\nPDF file\n\n3.76 MB\n\nDari_ICRC_Afghanistan_Facts_and_Figures_2024.pdf\n  \n\nPDF file\n3.92 MB\n\nDari_ICRC_Afghanistan_Facts_and_Figures_2024.pdf\n  \n\nPDF file\n3.92 MB\n\nDari_ICRC_Afghanistan_Facts_and_Figures_2024.pdf\n\nPDF file\n3.92 MB\n\nPDF file\n\n3.92 MB\n\nPashto_ICRC_Afghanistan_Facts_and_Figures_2024.pdf\n  \n\nPDF file\n3.96 MB\n\nPashto_ICRC_Afghanistan_Facts_and_Figures_2024.pdf\n  \n\nPDF file\n3.96 MB\n\nPashto_ICRC_Afghanistan_Facts_and_Figures_2024.pdf\n\nPDF file\n3.96 MB\n\nPDF file\n\n3.96 MB\n\nRelated articles\n\n\n\n\n\n\n\n\n\n\n\n\n\n\n\nArticle\n\n04-04-2025\n\n\n\n\nFrequently asked questions about the ICRC's work in Myanmar\n\n\n\n\n\n\n\n\n\n\n\n\n\n\n\n\n\n\nArticle\n\n04-04-2025\n\n\n\n\nIn the minefields of Iraq, Noora works to restore life and hope to her homeland\n\n\n\n\n\n\n\n\n\n\n\n\n\n\n\n\n\n\nArticle\n\n04-04-2025\n\n\n\n\nMyanmar: Landmine awareness saves lives amid conflict and natural disasters\n\n\n\n\n\n\n\n\n\n\n\n\n\n\n\nMore articles\n\nRelated articles\n\n\n\n\n\n\n\n\n\n\n\n\n\n\n\nArticle\n\n04-04-2025\n\n\n\n\nFrequently asked questions about the ICRC's work in Myanmar\n\n\n\n\n\n\n\n\n\n\n\n\n\n\n\n\n\n\nArticle\n\n04-04-2025\n\n\n\n\nIn the minefields of Iraq, Noora works to restore life and hope to her homeland\n\n\n\n\n\n\n\n\n\n\n\n\n\n\n\n\n\n\nArticle\n\n04-04-2025\n\n\n\n\nMyanmar: Landmine awareness saves lives amid conflict and natural disasters\n\n\n\n\n\n\n\n\n\n\n\n\n\n\n\nMore articles\n\nRelated articles\n\n\n\n\n\n\n\n\n\n\n\n\n\n\n\nArticle\n\n04-04-2025\n\n\n\n\nFrequently asked questions about the ICRC's work in Myanmar\n\n\n\n\n\n\n\n\n\n\n\n\n\n\n\n\n\n\nArticle\n\n04-04-2025\n\n\n\n\nIn the minefields of Iraq, Noora works to restore life and hope to her homeland\n\n\n\n\n\n\n\n\n\n\n\n\n\n\n\n\n\n\nArticle\n\n04-04-2025\n\n\n\n\nMyanmar: Landmine awareness saves lives amid conflict and natural disasters\n\n\n\n\n\n\n\n\n\n\n\n\n\n\n\nMore articles\n\nRelated articles\n\n\n\n\n\n\n\n\n\n\n\n\n\n\n\nArticle\n\n04-04-2025\n\n\n\n\nFrequently asked questions about the ICRC's work in Myanmar\n\n\n\n\n\n\n\n\n\n\n\n\n\n\n\n\n\n\nArticle\n\n04-04-2025\n\n\n\n\nIn the minefields of Iraq, Noora works to restore life and hope to her homeland\n\n\n\n\n\n\n\n\n\n\n\n\n\n\n\n\n\n\nArticle\n\n04-04-2025\n\n\n\n\nMyanmar: Landmine awareness saves lives amid conflict and natural disasters\n\n\n\n\n\n\n\n\n\n\n\n\n\n\n\nMore articles\n\nRelated articles\n\n\n\n\n\n\n\n\n\n\n\n\n\n\n\nArticle\n\n04-04-2025\n\n\n\n\nFrequently asked questions about the ICRC's work in Myanmar\n\n\n\n\n\n\n\n\n\n\n\n\n\n\n\n\n\n\nArticle\n\n04-04-2025\n\n\n\n\nIn the minefields of Iraq, Noora works to restore life and hope to her homeland\n\n\n\n\n\n\n\n\n\n\n\n\n\n\n\n\n\n\nArticle\n\n04-04-2025\n\n\n\n\nMyanmar: Landmine awareness saves lives amid conflict and natural disasters\n\n\n\n\n\n\n\n\n\n\n\n\n\n\n\nMore articles\n\nRelated articles\n\nArticle\n\n04-04-2025\n\n\n\n\nFrequently asked questions about the ICRC's work in Myanmar\n\n\n\n\n\n\n\n\n\n\n\n\n\n\n\n\n\n\nArticle\n\n04-04-2025\n\n\n\n\nIn the minefields of Iraq, Noora works to restore life and hope to her homeland\n\n\n\n\n\n\n\n\n\n\n\n\n\n\n\n\n\n\nArticle\n\n04-04-2025\n\n\n\n\nMyanmar: Landmine awareness saves lives amid conflict and natural disasters\n\n\n\n\n\n\n\n\n\n\n\n\n\n\n\nMore articles\n\nArticle\n\n04-04-2025\n\n\n\n\nFrequently asked questions about the ICRC's work in Myanmar\n\n\n\n\n\n\n\n\n\n\n\n\n\n\n\n\n\n\nArticle\n\n04-04-2025\n\n\n\n\nIn the minefields of Iraq, Noora works to restore life and hope to her homeland\n\n\n\n\n\n\n\n\n\n\n\n\n\n\n\n\n\n\nArticle\n\n04-04-2025\n\n\n\n\nMyanmar: Landmine awareness saves lives amid conflict and natural disasters\n\nArticle\n\n04-04-2025\n\n\n\n\nFrequently asked questions about the ICRC's work in Myanmar\n\nArticle\n\n04-04-2025\n\n\n\n\nFrequently asked questions about the ICRC's work in Myanmar\n\nArticle\n\n04-04-2025\n\n\n\n\nFrequently asked questions about the ICRC's work in Myanmar\n\nArticle\n\n04-04-2025\n\n\n\n\nFrequently asked questions about the ICRC's work in Myanmar\n\nArticle\n\n04-04-2025\n\nArticle\n\n04-04-2025\n\nFrequently asked questions about the ICRC's work in Myanmar\n\nArticle\n\n04-04-2025\n\n\n\n\nIn the minefields of Iraq, Noora works to restore life and hope to her homeland\n\nArticle\n\n04-04-2025\n\n\n\n\nIn the minefields of Iraq, Noora works to restore life and hope to her homeland\n\nArticle\n\n04-04-2025\n\n\n\n\nIn the minefields of Iraq, Noora works to restore life and hope to her homeland\n\nArticle\n\n04-04-2025\n\n\n\n\nIn the minefields of Iraq, Noora works to restore life and hope to her homeland\n\nArticle\n\n04-04-2025\n\nArticle\n\n04-04-2025\n\nIn the minefields of Iraq, Noora works to restore life and hope to her homeland\n\nArticle\n\n04-04-2025\n\n\n\n\nMyanmar: Landmine awareness saves lives amid conflict and natural disasters\n\nArticle\n\n04-04-2025\n\n\n\n\nMyanmar: Landmine awareness saves lives amid conflict and natural disasters\n\nArticle\n\n04-04-2025\n\n\n\n\nMyanmar: Landmine awareness saves lives amid conflict and natural disasters\n\nArticle\n\n04-04-2025\n\n\n\n\nMyanmar: Landmine awareness saves lives amid conflict and natural disasters\n\nArticle\n\n04-04-2025\n\nArticle\n\n04-04-2025\n\nMyanmar: Landmine awareness saves lives amid conflict and natural disasters\n\nMore articles\n\nMore articles",
  "date": "",
  "source_type": "other",
  "extracted_at": "2025-04-07T14:01:26.106245",
  "metadata": {
    "description": "The humanitarian situation in Afghanistan remains extremely dire as a result of decades of armed conflict, economic hardship and natural disasters.",
    "keywords": "Afghanistan, Economic Security, Physical Rehabilitaiton Centre, Health Care, Healthcare, Detention, Detainees, Restoring Family Links, Civilian",
    "og:site_name": "International Committee of the Red Cross"
  },
  "relevance_score": 0.43333333333333335,
  "summary": "Skip to main content\n\n\n\n\n\n\n\n\n\n\n\n\n\n            Article\n          \n\n10-02-2025\n\n\n\n\n\n2 languages\nEnglish\n中文\n\n\n\n\n\nAfghanistan: 2024 Operational facts and figures \n\n\n\nAfghanistan\nPhysical rehabilitation\nHealth\nEconomic Security\nReconnecting families\n\n\n\n\n\n\n\n\n\n\n\n\nAmir Mohammad/ICRC\n\n\n\n\nIn 2024, communities in Afghanistan continued to face significant challenges to access basic necessities such as healthcare, food and clean water. The International Committee of the Red Cross (ICRC) worked to respond to humanitarian challenges across Afghanistan by supporting healthcare, providing physical rehabilitation services, assisting people in establishing livelihoods and incomes, and improving access to clean water, sanitation and energy. As Afghanistan remained one of the most heavily weapon-contaminated countries in the world, our teams have worked alongside our Afghan Red Crescent Society partners to raise awareness of mine risks within communities and promote the right behaviors to adopt to stay safe. A look at the measurable impact of our work in 2024:\n\n\n964,259 patients, (65 per cent women and children), received primary health care at 47 health facilities of the Afghan Red Crescent Society (ARCS) that are supported by the ICRC. English_ICRC_Afghanistan_Facts_and_Figures_2024.pdf\n  \n\nPDF file\n3.76 MB\n\n\n\n\n\n\n\n\n\n\n\n\n\n\n\n\n\n\n\n\n\n\n      Dari_ICRC_Afghanistan_Facts_and_Figures_2024.pdf\n  \n\nPDF file\n3.92 MB\n\n\n\n\n\n\n\n\n\n\n\n\n\n\n\n\n\n\n\n\n\n\n      Pashto_ICRC_Afghanistan_Facts_and_Figures_2024.pdf\n  \n\nPDF file\n3.96 MB\n\n\n\n\n\n\n\n\n\n\n\n\n\n\n\n\n\n\n\n\nRelated articles\n\n\n\n\n\n\n\n\n\n\n\n\n\n\n\nArticle\n\n04-04-2025\n\n\n\n\nFrequently asked questions about the ICRC's work in Myanmar\n\n\n\n\n\n\n\n\n\n\n\n\n\n\n\n\n\n\nArticle\n\n04-04-2025\n\n\n\n\nIn the minefields of Iraq, Noora works to restore life and hope to her homeland\n\n\n\n\n\n\n\n\n\n\n\n\n\n\n\n\n\n\nArticle\n\n04-04-2025\n\n\n\n\nMyanmar: Landmine awareness saves lives amid conflict and natural disasters\n\n\n\n\n\n\n\n\n\n\n\n\n\n\n\nMore articles\n\nSkip to main content\n\n\n\n\n\n\n\n\n\n\n\n\n\n            Article\n          \n\n10-02-2025\n\n\n\n\n\n2 languages\nEnglish\n中文\n\n\n\n\n\nAfghanistan: 2024 Operational facts and figures \n\n\n\nAfghanistan\nPhysical rehabilitation\nHealth\nEconomic Security\nReconnecting families\n\n\n\n\n\n\n\n\n\n\n\n\nAmir Mohammad/ICRC\n\n\n\n\nIn 2024, communities in Afghanistan continued to face significant challenges to access basic necessities such as healthcare, food and clean water. The International Committee of the Red Cross (ICRC) worked to respond to humanitarian challenges across Afghanistan by supporting healthcare, providing physical rehabilitation services, assisting people in establishing livelihoods and incomes, and improving access to clean water, sanitation and energy. As Afghanistan remained one of the most heavily weapon-contaminated countries in the world, our teams have worked alongside our Afghan Red Crescent Society partners to raise awareness of mine risks within communities and promote the right behaviors to adopt to stay safe. A look at the measurable impact of our work in 2024:\n\n\n964,259 patients, (65 per cent women and children), received primary health care at 47 health facilities of the Afghan Red Crescent Society (ARCS) that are supported by the ICRC. English_ICRC_Afghanistan_Facts_and_Figures_2024.pdf\n  \n\nPDF file\n3.76 MB\n\n\n\n\n\n\n\n\n\n\n\n\n\n\n\n\n\n\n\n\n\n\n      Dari_ICRC_Afghanistan_Facts_and_Figures_2024.pdf\n  \n\nPDF file\n3.92 MB\n\n\n\n\n\n\n\n\n\n\n\n\n\n\n\n\n\n\n\n\n\n\n      Pashto_ICRC_Afghanistan_Facts_and_Figures_2024.pdf\n  \n\nPDF file\n3.96 MB\n\n\n\n\n\n\n\n\n\n\n\n\n\n\n\n\n\n\n\n\nRelated articles\n\n\n\n\n\n\n\n\n\n\n\n\n\n\n\nArticle\n\n04-04-2025\n\n\n\n\nFrequently asked questions about the ICRC's work in Myanmar\n\n\n\n\n\n\n\n\n\n\n\n\n\n\n\n\n\n\nArticle\n\n04-04-2025\n\n\n\n\nIn the minefields of Iraq, Noora works to restore life and hope to her homeland\n\n\n\n\n\n\n\n\n\n\n\n\n\n\n\n\n\n\nArticle\n\n04-04-2025\n\n\n\n\nMyanmar: Landmine awareness saves lives amid conflict and natural disasters\n\n\n\n\n\n\n\n\n\n\n\n\n\n\n\nMore articles\n\nArticle\n          \n\n10-02-2025\n\n\n\n\n\n2 languages\nEnglish\n中文\n\n\n\n\n\nAfghanistan: 2024 Operational facts and figures \n\n\n\nAfghanistan\nPhysical rehabilitation\nHealth\nEconomic Security\nReconnecting families\n\n\n\n\n\n\n\n\n\n\n\n\nAmir Mohammad/ICRC\n\n\n\n\nIn 2024, communities in Afghanistan continued to face significant challenges to access basic necessities such as healthcare, food and clean water. The International Committee of the Red Cross (ICRC) worked to respond to humanitarian challenges across Afghanistan by supporting healthcare, providing physical rehabilitation services, assisting people in establishing livelihoods and incomes, and improving access to clean water, sanitation and energy. As Afghanistan remained one of the most heavily weapon-contaminated countries in the world, our teams have worked alongside our Afghan Red Crescent Society partners to raise awareness of mine risks within communities and promote the right behaviors to adopt to stay safe. A look at the measurable impact of our work in 2024:\n\n\n964,259 patients, (65 per cent women and children), received primary health care at 47 health facilities of the Afghan Red Crescent Society (ARCS) that are supported by the ICRC. English_ICRC_Afghanistan_Facts_and_Figures_2024.pdf\n  \n\nPDF file\n3.76 MB\n\n\n\n\n\n\n\n\n\n\n\n\n\n\n\n\n\n\n\n\n\n\n      Dari_ICRC_Afghanistan_Facts_and_Figures_2024.pdf\n  \n\nPDF file\n3.92 MB\n\n\n\n\n\n\n\n\n\n\n\n\n\n\n\n\n\n\n\n\n\n\n      Pashto_ICRC_Afghanistan_Facts_and_Figures_2024.pdf\n  \n\nPDF file\n3.96 MB\n\n\n\n\n\n\n\n\n\n\n\n\n\n\n\n\n\n\n\n\nRelated articles\n\n\n\n\n\n\n\n\n\n\n\n\n\n\n\nArticle\n\n04-04-2025\n\n\n\n\nFrequently asked questions about the ICRC's work in Myanmar\n\n\n\n\n\n\n\n\n\n\n\n\n\n\n\n\n\n\nArticle\n\n04-04-2025\n\n\n\n\nIn the minefields of Iraq, Noora works to restore life and hope to her homeland\n\n\n\n\n\n\n\n\n\n\n\n\n\n\n\n\n\n\nArticle\n\n04-04-2025\n\n\n\n\nMyanmar: Landmine awareness saves lives amid conflict and natural disasters\n\n\n\n\n\n\n\n\n\n\n\n\n\n\n\nMore articles\n\nArticle\n          \n\n10-02-2025\n\n\n\n\n\n2 languages\nEnglish\n中文\n\n\n\n\n\nAfghanistan: 2024 Operational facts and figures \n\n\n\nAfghanistan\nPhysical rehabilitation\nHealth\nEconomic Security\nReconnecting families\n\n\n\n\n\n\n\n\n\n\n\n\nAmir Mohammad/ICRC\n\n\n\n\nIn 2024, communities in Afghanistan continued to face significant challenges to access basic necessities such as healthcare, food and clean water. The International Committee of the Red Cross (ICRC) worked to respond to humanitarian challenges across Afghanistan by supporting healthcare, providing physical rehabilitation services, assisting people in establishing livelihoods and incomes, and improving access to clean water, sanitation and energy. As Afghanistan remained one of the most heavily weapon-contaminated countries in the world, our teams have worked alongside our Afghan Red Crescent Society partners to raise awareness of mine risks within communities and promote the right behaviors to adopt to stay safe. A look at the measurable impact of our work in 2024:\n\n\n964,259 patients, (65 per cent women and children), received primary health care at 47 health facilities of the Afghan Red Crescent Society (ARCS) that are supported by the ICRC. English_ICRC_Afghanistan_Facts_and_Figures_2024.pdf\n  \n\nPDF file\n3.76 MB\n\n\n\n\n\n\n\n\n\n\n\n\n\n\n\n\n\n\n\n\n\n\n      Dari_ICRC_Afghanistan_Facts_and_Figures_2024.pdf\n  \n\nPDF file\n3.92 MB\n\n\n\n\n\n\n\n\n\n\n\n\n\n\n\n\n\n\n\n\n\n\n      Pashto_ICRC_Afghanistan_Facts_and_Figures_2024.pdf\n  \n\nPDF file\n3.96 MB\n\n\n\n\n\n\n\n\n\n\n\n\n\n\n\n\n\n\n\n\nRelated articles\n\n\n\n\n\n\n\n\n\n\n\n\n\n\n\nArticle\n\n04-04-2025\n\n\n\n\nFrequently asked questions about the ICRC's work in Myanmar\n\n\n\n\n\n\n\n\n\n\n\n\n\n\n\n\n\n\nArticle\n\n04-04-2025\n\n\n\n\nIn the minefields of Iraq, Noora works to restore life and hope to her homeland\n\n\n\n\n\n\n\n\n\n\n\n\n\n\n\n\n\n\nArticle\n\n04-04-2025\n\n\n\n\nMyanmar: Landmine awareness saves lives amid conflict and natural disasters\n\n\n\n\n\n\n\n\n\n\n\n\n\n\n\nMore articles\n\nArticle\n          \n\n10-02-2025\n\n\n\n\n\n2 languages\nEnglish\n中文\n\n\n\n\n\nAfghanistan: 2024 Operational facts and figures \n\n\n\nAfghanistan\nPhysical rehabilitation\nHealth\nEconomic Security\nReconnecting families\n\n\n\n\n\n\n\n\n\n\n\n\nAmir Mohammad/ICRC\n\n\n\n\nIn 2024, communities in Afghanistan continued to face significant challenges to access basic necessities such as healthcare, food and clean water. The International Committee of the Red Cross (ICRC) worked to respond to humanitarian challenges across Afghanistan by supporting healthcare, providing physical rehabilitation services, assisting people in establishing livelihoods and incomes, and improving access to clean water, sanitation and energy. A look at the measurable impact of our work in 2024:\n\n\n964,259 patients, (65 per cent women and children), received primary health care at 47 health facilities of the Afghan Red Crescent Society (ARCS) that are supported by the ICRC. English_ICRC_Afghanistan_Facts_and_Figures_2024.pdf\n  \n\nPDF file\n3.76 MB\n\n\n\n\n\n\n\n\n\n\n\n\n\n\n\n\n\n\n\n\n\n\n      Dari_ICRC_Afghanistan_Facts_and_Figures_2024.pdf\n  \n\nPDF file\n3.92 MB\n\n\n\n\n\n\n\n\n\n\n\n\n\n\n\n\n\n\n\n\n\n\n      Pashto_ICRC_Afghanistan_Facts_and_Figures_2024.pdf\n  \n\nPDF file\n3.96 MB\n\n\n\n\n\n\n\n\n\n\n\n\n\n\n\n\n\n\n\n\nRelated articles\n\n\n\n\n\n\n\n\n\n\n\n\n\n\n\nArticle\n\n04-04-2025\n\n\n\n\nFrequently asked questions about the ICRC's work in Myanmar\n\n\n\n\n\n\n\n\n\n\n\n\n\n\n\n\n\n\nArticle\n\n04-04-2025\n\n\n\n\nIn the minefields of Iraq, Noora works to restore life and hope to her homeland\n\n\n\n\n\n\n\n\n\n\n\n\n\n\n\n\n\n\nArticle\n\n04-04-2025\n\n\n\n\nMyanmar: Landmine awareness saves lives amid conflict and natural disasters\n\n\n\n\n\n\n\n\n\n\n\n\n\n\n\nMore articles\n\nArticle\n          \n\n10-02-2025\n\n\n\n\n\n2 languages\nEnglish\n中文\n\n\n\n\n\nAfghanistan: 2024 Operational facts and figures \n\n\n\nAfghanistan\nPhysical rehabilitation\nHealth\nEconomic Security\nReconnecting families\n\n\n\n\n\n\n\n\n\n\n\n\nAmir Mohammad/ICRC\n\n\n\n\nIn 2024, communities in Afghanistan continued to face significant challenges to access basic necessities such as healthcare, food and clean water. The International Committee of the Red Cross (ICRC) worked to respond to humanitarian challenges across Afghanistan by supporting healthcare, providing physical rehabilitation services, assisting people in establishing livelihoods and incomes, and improving access to clean water, sanitation and energy. A look at the measurable impact of our work in 2024:\n\n\n964,259 patients, (65 per cent women and children), received primary health care at 47 health facilities of the Afghan Red Crescent Society (ARCS) that are supported by the ICRC. English_ICRC_Afghanistan_Facts_and_Figures_2024.pdf\n  \n\nPDF file\n3.76 MB\n\n\n\n\n\n\n\n\n\n\n\n\n\n\n\n\n\n\n\n\n\n\n      Dari_ICRC_Afghanistan_Facts_and_Figures_2024.pdf\n  \n\nPDF file\n3.92 MB\n\n\n\n\n\n\n\n\n\n\n\n\n\n\n\n\n\n\n\n\n\n\n      Pashto_ICRC_Afghanistan_Facts_and_Figures_2024.pdf\n  \n\nPDF file\n3.96 MB\n\n\n\n\n\n\n\n\n\n\n\n\n\n\n\n\n\n\n\n\nRelated articles\n\n\n\n\n\n\n\n\n\n\n\n\n\n\n\nArticle\n\n04-04-2025\n\n\n\n\nFrequently asked questions about the ICRC's work in Myanmar\n\n\n\n\n\n\n\n\n\n\n\n\n\n\n\n\n\n\nArticle\n\n04-04-2025\n\n\n\n\nIn the minefields of Iraq, Noora works to restore life and hope to her homeland\n\n\n\n\n\n\n\n\n\n\n\n\n\n\n\n\n\n\nArticle\n\n04-04-2025\n\n\n\n\nMyanmar: Landmine awareness saves lives amid conflict and natural disasters\n\n\n\n\n\n\n\n\n\n\n\n\n\n\n\nMore articles\n\nArticle\n          \n\n10-02-2025\n\n\n\n\n\n2 languages\nEnglish\n中文\n\n\n\n\n\nAfghanistan: 2024 Operational facts and figures \n\n\n\nAfghanistan\nPhysical rehabilitation\nHealth\nEconomic Security\nReconnecting families\n\n\n\n\n\n\n\n\n\n\n\n\nAmir Mohammad/ICRC\n\n\n\n\nIn 2024, communities in Afghanistan continued to face significant challenges to access basic necessities such as healthcare, food and clean water. The International Committee of the Red Cross (ICRC) worked to respond to humanitarian challenges across Afghanistan by supporting healthcare, providing physical rehabilitation services, assisting people in establishing livelihoods and incomes, and improving access to clean water, sanitation and energy. Article\n          \n\n10-02-2025\n\n\n\n\n\n2 languages\nEnglish\n中文\n\n\n\n\n\nAfghanistan: 2024 Operational facts and figures \n\n\n\nAfghanistan\nPhysical rehabilitation\nHealth\nEconomic Security\nReconnecting families\n\nArticle\n          \n\n10-02-2025\n\n\n\n\n\n2 languages\nEnglish\n中文\n\nArticle\n          \n\n10-02-2025\n\nArticle\n\n10-02-2025\n\n2 languages\nEnglish\n中文\n\n2 languages\nEnglish\n中文\n\nAfghanistan: 2024 Operational facts and figures\n\nAfghanistan\nPhysical rehabilitation\nHealth\nEconomic Security\nReconnecting families\n\nAmir Mohammad/ICRC\n\nAmir Mohammad/ICRC\n\nAmir Mohammad/ICRC\n\nIn 2024, communities in Afghanistan continued to face significant challenges to access basic necessities such as healthcare, food and clean water. The International Committee of the Red Cross (ICRC) worked to respond to humanitarian challenges across Afghanistan by supporting healthcare, providing physical rehabilitation services, assisting people in establishing livelihoods and incomes, and improving access to clean water, sanitation and energy. The International Committee of the Red Cross (ICRC) worked to respond to humanitarian challenges across Afghanistan by supporting healthcare, providing physical rehabilitation services, assisting people in establishing livelihoods and incomes, and improving access to clean water, sanitation and energy. The International Committee of the Red Cross (ICRC) worked to respond to humanitarian challenges across Afghanistan by supporting healthcare, providing physical rehabilitation services, assisting people in establishing livelihoods and incomes, and improving access to clean water, sanitation and energy. The International Committee of the Red Cross (ICRC) worked to respond to humanitarian challenges across Afghanistan by supporting healthcare, providing physical rehabilitation services, assisting people in establishing livelihoods and incomes, and improving access to clean water, sanitation and energy. A look at the measurable impact of our work in 2024:\n\n\n964,259 patients, (65 per cent women and children), received primary health care at 47 health facilities of the Afghan Red Crescent Society (ARCS) that are supported by the ICRC. A look at the measurable impact of our work in 2024:\n\n\n964,259 patients, (65 per cent women and children), received primary health care at 47 health facilities of the Afghan Red Crescent Society (ARCS) that are supported by the ICRC. A look at the measurable impact of our work in 2024:\n\n\n964,259 patients, (65 per cent women and children), received primary health care at 47 health facilities of the Afghan Red Crescent Society (ARCS) that are supported by the ICRC. A look at the measurable impact of our work in 2024:\n\n\n964,259 patients, (65 per cent women and children), received primary health care at 47 health facilities of the Afghan Red Crescent Society (ARCS) that are supported by the ICRC. A look at the measurable impact of our work in 2024:\n\n964,259 patients, (65 per cent women and children), received primary health care at 47 health facilities of the Afghan Red Crescent Society (ARCS) that are supported by the ICRC. English_ICRC_Afghanistan_Facts_and_Figures_2024.pdf\n  \n\nPDF file\n3.76 MB\n\n\n\n\n\n\n\n\n\n\n\n\n\n\n\n\n\n\n\n\n\n\n      Dari_ICRC_Afghanistan_Facts_and_Figures_2024.pdf\n  \n\nPDF file\n3.92 MB\n\n\n\n\n\n\n\n\n\n\n\n\n\n\n\n\n\n\n\n\n\n\n      Pashto_ICRC_Afghanistan_Facts_and_Figures_2024.pdf\n  \n\nPDF file\n3.96 MB\n\nEnglish_ICRC_Afghanistan_Facts_and_Figures_2024.pdf\n  \n\nPDF file\n3.76 MB\n\n\n\n\n\n\n\n\n\n\n\n\n\n\n\n\n\n\n\n\n\n\n      Dari_ICRC_Afghanistan_Facts_and_Figures_2024.pdf\n  \n\nPDF file\n3.92 MB\n\n\n\n\n\n\n\n\n\n\n\n\n\n\n\n\n\n\n\n\n\n\n      Pashto_ICRC_Afghanistan_Facts_and_Figures_2024.pdf\n  \n\nPDF file\n3.96 MB\n\nEnglish_ICRC_Afghanistan_Facts_and_Figures_2024.pdf\n  \n\nPDF file\n3.76 MB\n\n\n\n\n\n\n\n\n\n\n\n\n\n\n\n\n\n\n\n\n\n\n      Dari_ICRC_Afghanistan_Facts_and_Figures_2024.pdf\n  \n\nPDF file\n3.92 MB\n\n\n\n\n\n\n\n\n\n\n\n\n\n\n\n\n\n\n\n\n\n\n      Pashto_ICRC_Afghanistan_Facts_and_Figures_2024.pdf\n  \n\nPDF file\n3.96 MB\n\nEnglish_ICRC_Afghanistan_Facts_and_Figures_2024.pdf\n  \n\nPDF file\n3.76 MB\n\nEnglish_ICRC_Afghanistan_Facts_and_Figures_2024.pdf\n  \n\nPDF file\n3.76 MB\n\nEnglish_ICRC_Afghanistan_Facts_and_Figures_2024.pdf\n\nPDF file\n3.76 MB\n\nPDF file\n\n3.76 MB\n\nDari_ICRC_Afghanistan_Facts_and_Figures_2024.pdf\n  \n\nPDF file\n3.92 MB\n\nDari_ICRC_Afghanistan_Facts_and_Figures_2024.pdf\n  \n\nPDF file\n3.92 MB\n\nDari_ICRC_Afghanistan_Facts_and_Figures_2024.pdf\n\nPDF file\n3.92 MB\n\nPDF file\n\n3.92 MB\n\nPashto_ICRC_Afghanistan_Facts_and_Figures_2024.pdf\n  \n\nPDF file\n3.96 MB\n\nPashto_ICRC_Afghanistan_Facts_and_Figures_2024.pdf\n  \n\nPDF file\n3.96 MB\n\nPashto_ICRC_Afghanistan_Facts_and_Figures_2024.pdf\n\nPDF file\n3.96 MB\n\nPDF file\n\n3.96 MB\n\nRelated articles\n\n\n\n\n\n\n\n\n\n\n\n\n\n\n\nArticle\n\n04-04-2025\n\n\n\n\nFrequently asked questions about the ICRC's work in Myanmar\n\n\n\n\n\n\n\n\n\n\n\n\n\n\n\n\n\n\nArticle\n\n04-04-2025\n\n\n\n\nIn the minefields of Iraq, Noora works to restore life and hope to her homeland\n\n\n\n\n\n\n\n\n\n\n\n\n\n\n\n\n\n\nArticle\n\n04-04-2025\n\n\n\n\nMyanmar: Landmine awareness saves lives amid conflict and natural disasters\n\n\n\n\n\n\n\n\n\n\n\n\n\n\n\nMore articles\n\nRelated articles\n\n\n\n\n\n\n\n\n\n\n\n\n\n\n\nArticle\n\n04-04-2025\n\n\n\n\nFrequently asked questions about the ICRC's work in Myanmar\n\n\n\n\n\n\n\n\n\n\n\n\n\n\n\n\n\n\nArticle\n\n04-04-2025\n\n\n\n\nIn the minefields of Iraq, Noora works to restore life and hope to her homeland\n\n\n\n\n\n\n\n\n\n\n\n\n\n\n\n\n\n\nArticle\n\n04-04-2025\n\n\n\n\nMyanmar: Landmine awareness saves lives amid conflict and natural disasters\n\n\n\n\n\n\n\n\n\n\n\n\n\n\n\nMore articles\n\nRelated articles\n\n\n\n\n\n\n\n\n\n\n\n\n\n\n\nArticle\n\n04-04-2025\n\n\n\n\nFrequently asked questions about the ICRC's work in Myanmar\n\n\n\n\n\n\n\n\n\n\n\n\n\n\n\n\n\n\nArticle\n\n04-04-2025\n\n\n\n\nIn the minefields of Iraq, Noora works to restore life and hope to her homeland\n\n\n\n\n\n\n\n\n\n\n\n\n\n\n\n\n\n\nArticle\n\n04-04-2025\n\n\n\n\nMyanmar: Landmine awareness saves lives amid conflict and natural disasters\n\n\n\n\n\n\n\n\n\n\n\n\n\n\n\nMore articles\n\nRelated articles\n\n\n\n\n\n\n\n\n\n\n\n\n\n\n\nArticle\n\n04-04-2025\n\n\n\n\nFrequently asked questions about the ICRC's work in Myanmar\n\n\n\n\n\n\n\n\n\n\n\n\n\n\n\n\n\n\nArticle\n\n04-04-2025\n\n\n\n\nIn the minefields of Iraq, Noora works to restore life and hope to her homeland\n\n\n\n\n\n\n\n\n\n\n\n\n\n\n\n\n\n\nArticle\n\n04-04-2025\n\n\n\n\nMyanmar: Landmine awareness saves lives amid conflict and natural disasters\n\n\n\n\n\n\n\n\n\n\n\n\n\n\n\nMore articles\n\nRelated articles\n\n\n\n\n\n\n\n\n\n\n\n\n\n\n\nArticle\n\n04-04-2025\n\n\n\n\nFrequently asked questions about the ICRC's work in Myanmar\n\n\n\n\n\n\n\n\n\n\n\n\n\n\n\n\n\n\nArticle\n\n04-04-2025\n\n\n\n\nIn the minefields of Iraq, Noora works to restore life and hope to her homeland\n\n\n\n\n\n\n\n\n\n\n\n\n\n\n\n\n\n\nArticle\n\n04-04-2025\n\n\n\n\nMyanmar: Landmine awareness saves lives amid conflict and natural disasters\n\n\n\n\n\n\n\n\n\n\n\n\n\n\n\nMore articles\n\nRelated articles\n\nArticle\n\n04-04-2025\n\n\n\n\nFrequently asked questions about the ICRC's work in Myanmar\n\n\n\n\n\n\n\n\n\n\n\n\n\n\n\n\n\n\nArticle\n\n04-04-2025\n\n\n\n\nIn the minefields of Iraq, Noora works to restore life and hope to her homeland\n\n\n\n\n\n\n\n\n\n\n\n\n\n\n\n\n\n\nArticle\n\n04-04-2025\n\n\n\n\nMyanmar: Landmine awareness saves lives amid conflict and natural disasters\n\n\n\n\n\n\n\n\n\n\n\n\n\n\n\nMore articles\n\nArticle\n\n04-04-2025\n\n\n\n\nFrequently asked questions about the ICRC's work in Myanmar\n\n\n\n\n\n\n\n\n\n\n\n\n\n\n\n\n\n\nArticle\n\n04-04-2025\n\n\n\n\nIn the minefields of Iraq, Noora works to restore life and hope to her homeland\n\n\n\n\n\n\n\n\n\n\n\n\n\n\n\n\n\n\nArticle\n\n04-04-2025\n\n\n\n\nMyanmar: Landmine awareness saves lives amid conflict and natural disasters\n\nArticle\n\n04-04-2025\n\n\n\n\nFrequently asked questions about the ICRC's work in Myanmar\n\nArticle\n\n04-04-2025\n\n\n\n\nFrequently asked questions about the ICRC's work in Myanmar\n\nArticle\n\n04-04-2025\n\n\n\n\nFrequently asked questions about the ICRC's work in Myanmar\n\nArticle\n\n04-04-2025\n\n\n\n\nFrequently asked questions about the ICRC's work in Myanmar\n\nArticle\n\n04-04-2025\n\nArticle\n\n04-04-2025\n\nFrequently asked questions about the ICRC's work in Myanmar\n\nArticle\n\n04-04-2025\n\n\n\n\nIn the minefields of Iraq, Noora works to restore life and hope to her homeland\n\nArticle\n\n04-04-2025\n\n\n\n\nIn the minefields of Iraq, Noora works to restore life and hope to her homeland\n\nArticle\n\n04-04-2025\n\n\n\n\nIn the minefields of Iraq, Noora works to restore life and hope to her homeland\n\nArticle\n\n04-04-2025\n\n\n\n\nIn the minefields of Iraq, Noora works to restore life and hope to her homeland\n\nArticle\n\n04-04-2025\n\nArticle\n\n04-04-2025\n\nIn the minefields of Iraq, Noora works to restore life and hope to her homeland\n\nArticle\n\n04-04-2025\n\n\n\n\nMyanmar: Landmine awareness saves lives amid conflict and natural disasters\n\nArticle\n\n04-04-2025\n\n\n\n\nMyanmar: Landmine awareness saves lives amid conflict and natural disasters\n\nArticle\n\n04-04-2025\n\n\n\n\nMyanmar: Landmine awareness saves lives amid conflict and natural disasters\n\nArticle\n\n04-04-2025\n\n\n\n\nMyanmar: Landmine awareness saves lives amid conflict and natural disasters\n\nArticle\n\n04-04-2025\n\nArticle\n\n04-04-2025\n\nMyanmar: Landmine awareness saves lives amid conflict and natural disasters\n\nMore articles\n\nMore articles",
  "entities": {
    "countries": [
      "afghanistan",
      "iraq"
    ],
    "organizations": [
      "un",
      "red cross"
    ],
    "key_issues": [
      "challenge",
      "situation",
      "country",
      "nation",
      "program",
      "humanitarian",
      "assistance",
      "economic",
      "un"
    ]
  },
  "committee": "World Health Organization",
  "topic": "Treating disease in areas of prolonged conflict"
}