{
  "url": "https://who.foundation/",
  "title": "WHO Foundation",
  "text": "Donate\n\n\nHello.\n\n\n\nWe bring together funders and high impact health initiatives to further the mission of the World Health Organization (WHO).\n\nAbout us\n\nDonate\n\n\nHello.\n\n\n\nWe bring together funders and high impact health initiatives to further the mission of the World Health Organization (WHO).\n\nAbout us\n\nDonate\n\n\nHello.\n\n\n\nWe bring together funders and high impact health initiatives to further the mission of the World Health Organization (WHO).\n\nAbout us\n\nHello.\n\n\n\nWe bring together funders and high impact health initiatives to further the mission of the World Health Organization (WHO).\n\nAbout us\n\nHello.\n\nWe bring together funders and high impact health initiatives to further the mission of the World Health Organization (WHO).\n\nAbout us\n\nWe bring together funders and high impact health initiatives to further the mission of the World Health Organization (WHO).\n\nAbout us\n\nHow do we achieve this?\n\n\nWe are here to help the World Health Organization and its partners to aid critical health projects across the world – protecting children from disease; helping women to give birth safely in emergencies; and supplying hospitals with essential medicines.\nBut that’s not all we do. We bring together the people trying to solve the world’s most urgent health challenges with those who are able to fund their work. This funding paves the way for innovations in health technology and more sustainable health systems. All with the single goal of saving more lives, in more places.\n\n\n Find out more\n\nHow do we achieve this?\n\n\nWe are here to help the World Health Organization and its partners to aid critical health projects across the world – protecting children from disease; helping women to give birth safely in emergencies; and supplying hospitals with essential medicines.\nBut that’s not all we do. We bring together the people trying to solve the world’s most urgent health challenges with those who are able to fund their work. This funding paves the way for innovations in health technology and more sustainable health systems. All with the single goal of saving more lives, in more places.\n\n\n Find out more\n\nHow do we achieve this?\n\n\nWe are here to help the World Health Organization and its partners to aid critical health projects across the world – protecting children from disease; helping women to give birth safely in emergencies; and supplying hospitals with essential medicines.\nBut that’s not all we do. We bring together the people trying to solve the world’s most urgent health challenges with those who are able to fund their work. This funding paves the way for innovations in health technology and more sustainable health systems. All with the single goal of saving more lives, in more places.\n\n\n Find out more\n\nHow do we achieve this?\n\n\nWe are here to help the World Health Organization and its partners to aid critical health projects across the world – protecting children from disease; helping women to give birth safely in emergencies; and supplying hospitals with essential medicines.\nBut that’s not all we do. We bring together the people trying to solve the world’s most urgent health challenges with those who are able to fund their work. This funding paves the way for innovations in health technology and more sustainable health systems. All with the single goal of saving more lives, in more places.\n\n\n Find out more\n\nHow do we achieve this?\n\nWe are here to help the World Health Organization and its partners to aid critical health projects across the world – protecting children from disease; helping women to give birth safely in emergencies; and supplying hospitals with essential medicines.\nBut that’s not all we do. We bring together the people trying to solve the world’s most urgent health challenges with those who are able to fund their work. This funding paves the way for innovations in health technology and more sustainable health systems. All with the single goal of saving more lives, in more places.\n\n\n Find out more\n\nWe are here to help the World Health Organization and its partners to aid critical health projects across the world – protecting children from disease; helping women to give birth safely in emergencies; and supplying hospitals with essential medicines.\nBut that’s not all we do. We bring together the people trying to solve the world’s most urgent health challenges with those who are able to fund their work. This funding paves the way for innovations in health technology and more sustainable health systems. All with the single goal of saving more lives, in more places.\n\nWe are here to help the World Health Organization and its partners to aid critical health projects across the world – protecting children from disease; helping women to give birth safely in emergencies; and supplying hospitals with essential medicines.\n\nBut that’s not all we do. We bring together the people trying to solve the world’s most urgent health challenges with those who are able to fund their work. This funding paves the way for innovations in health technology and more sustainable health systems. All with the single goal of saving more lives, in more places.\n\nFind out more\n\nWe need you…\n\n\n\n\n\n\nPhilanthropists\nThe WHO Foundation is here to support your vision of a safer, healthier world.\nRead more \n\n\n\n\nCorporate partners\nThe WHO Foundation connects your business to the programs and people solving the world’s health challenges.\nRead more \n\n\n\n\nImpact investors\nThink of us as your ally in creating positive change on a global scale. With your investment, we can create stronger, more sustainable health systems.\nRead more\n\nWe need you…\n\n\n\n\n\n\nPhilanthropists\nThe WHO Foundation is here to support your vision of a safer, healthier world.\nRead more \n\n\n\n\nCorporate partners\nThe WHO Foundation connects your business to the programs and people solving the world’s health challenges.\nRead more \n\n\n\n\nImpact investors\nThink of us as your ally in creating positive change on a global scale. With your investment, we can create stronger, more sustainable health systems.\nRead more\n\nWe need you…\n\nWe need you…\n\nPhilanthropists\nThe WHO Foundation is here to support your vision of a safer, healthier world.\nRead more \n\n\n\n\nCorporate partners\nThe WHO Foundation connects your business to the programs and people solving the world’s health challenges.\nRead more \n\n\n\n\nImpact investors\nThink of us as your ally in creating positive change on a global scale. With your investment, we can create stronger, more sustainable health systems.\nRead more\n\nPhilanthropists\nThe WHO Foundation is here to support your vision of a safer, healthier world.\nRead more\n\nPhilanthropists\nThe WHO Foundation is here to support your vision of a safer, healthier world.\nRead more\n\nThe WHO Foundation is here to support your vision of a safer, healthier world.\n\nRead more\n\nCorporate partners\nThe WHO Foundation connects your business to the programs and people solving the world’s health challenges.\nRead more\n\nCorporate partners\nThe WHO Foundation connects your business to the programs and people solving the world’s health challenges.\nRead more\n\nThe WHO Foundation connects your business to the programs and people solving the world’s health challenges.\n\nRead more\n\nImpact investors\nThink of us as your ally in creating positive change on a global scale. With your investment, we can create stronger, more sustainable health systems.\nRead more\n\nImpact investors\nThink of us as your ally in creating positive change on a global scale. With your investment, we can create stronger, more sustainable health systems.\nRead more\n\nThink of us as your ally in creating positive change on a global scale. With your investment, we can create stronger, more sustainable health systems.\n\nRead more\n\n“We have to create a healthier, more equitable future for everyone. By investing in 8 billion lives and by using a flexible, innovative, partnership-driven approach, our goal is to overcome the health challenges of today and ensure healthy lives tomorrow.”\nProf. Dr. Thomas Zeltner, Founder and Chair of the Board\n\n\n What we do\n\n“We have to create a healthier, more equitable future for everyone. By investing in 8 billion lives and by using a flexible, innovative, partnership-driven approach, our goal is to overcome the health challenges of today and ensure healthy lives tomorrow.”\nProf. Dr. Thomas Zeltner, Founder and Chair of the Board\n\n\n What we do\n\n“We have to create a healthier, more equitable future for everyone. By investing in 8 billion lives and by using a flexible, innovative, partnership-driven approach, our goal is to overcome the health challenges of today and ensure healthy lives tomorrow.”\nProf. Dr. Thomas Zeltner, Founder and Chair of the Board\n\n\n What we do\n\n“We have to create a healthier, more equitable future for everyone. By investing in 8 billion lives and by using a flexible, innovative, partnership-driven approach, our goal is to overcome the health challenges of today and ensure healthy lives tomorrow.”\nProf. Dr. Thomas Zeltner, Founder and Chair of the Board\n\n\n What we do\n\n“We have to create a healthier, more equitable future for everyone. By investing in 8 billion lives and by using a flexible, innovative, partnership-driven approach, our goal is to overcome the health challenges of today and ensure healthy lives tomorrow.”\nProf. Dr. Thomas Zeltner, Founder and Chair of the Board\n\n\n What we do\n\n“We have to create a healthier, more equitable future for everyone. By investing in 8 billion lives and by using a flexible, innovative, partnership-driven approach, our goal is to overcome the health challenges of today and ensure healthy lives tomorrow.”\nProf. Dr. Thomas Zeltner, Founder and Chair of the Board\n\n“We have to create a healthier, more equitable future for everyone. By investing in 8 billion lives and by using a flexible, innovative, partnership-driven approach, our goal is to overcome the health challenges of today and ensure healthy lives tomorrow.”\n\nProf. Dr. Thomas Zeltner, Founder and Chair of the Board\n\nWhat we do\n\nWe value your privacyWe use cookies on our website to give you the most relevant experience by remembering your preferences and repeat visits. By clicking “Accept”, you consent to the use of ALL the cookies. However you may visit Cookie Settings to provide a controlled consent.Cookie PolicyCustomizeReject AllAccept AllConsent Preferences\n\n\n\n\nClose\n\n\n\n\n\n\nPrivacy Overview \nThis website uses cookies to improve your experience while you navigate through the website. Out of these cookies, the cookies that are categorized as necessary are stored on your browser as they are essential for the working of basic functionalities of the website. We also use third-party cookies that help us analyze and understand how you use this website. These cookies will be stored in your browser only with your consent. You also have the option to opt-out of these cookies. But opting out of some of these cookies may have an effect on your browsing experience.\n\n \n\n\n\n\n\n                                Necessary                            \n\n\n Necessary \n\n\n                                    Always Enabled                                \n\n\n\nNecessary cookies are absolutely essential for the website to function properly. These cookies ensure basic functionalities and security features of the website, anonymously.\r\nCookieDurationDescription_wpfuuid1 year 1 month 4 daysThis cookie is used by the WPForms WordPress plugin. The cookie is used to allows the paid version of the plugin to connect entries by the same user and is used for some additional features like the Form Abandonment addon.cookielawinfo-checkbox-advertisement1 yearSet by the GDPR Cookie Consent plugin, this cookie records the user consent for the cookies in the \"Advertisement\" category.cookielawinfo-checkbox-analytics11 monthsThis cookie is set by GDPR Cookie Consent plugin. The cookie is used to store the user consent for the cookies in the category \"Analytics\".cookielawinfo-checkbox-functional11 monthsThe cookie is set by GDPR cookie consent to record the user consent for the cookies in the category \"Functional\".cookielawinfo-checkbox-necessary11 monthsThis cookie is set by GDPR Cookie Consent plugin. The cookies is used to store the user consent for the cookies in the category \"Necessary\".cookielawinfo-checkbox-others11 monthsThis cookie is set by GDPR Cookie Consent plugin. The cookie is used to store the user consent for the cookies in the category \"Other.cookielawinfo-checkbox-performance11 monthsThis cookie is set by GDPR Cookie Consent plugin. The cookie is used to store the user consent for the cookies in the category \"Performance\".CookieLawInfoConsent1 yearCookieYes sets this cookie to record the default button state of the corresponding category and the status of CCPA. It works only in coordination with the primary cookie.fundraiseup_cid1 year 1 month 4 daysThis cookie is set by Fundraise Up, and is used to identify a user’s browser. This cookie is necessary for the platform to function properly and securely, as it helps us detect and prevent fraud.\r\n\r\n fundraiseup_sessionpastThis cookie tracks a user's current session while interacting with the site. It is used for maintaining information about their activities (e.g., donation process) during that session. Once the session ends the cookie is deleted.rc::aneverThis cookie is set by the Google recaptcha service to identify bots to protect the website against malicious spam attacks.rc::csessionThis cookie is set by the Google recaptcha service to identify bots to protect the website against malicious spam attacks.viewed_cookie_policy11 monthsThe cookie is set by the GDPR Cookie Consent plugin and is used to store whether or not user has consented to the use of cookies. It does not store any personal data.wpEmojiSettingsSupportssessionWordPress sets this cookie when a user interacts with emojis on a WordPress site.  It helps determine if the user's browser can display emojis properly.\n\n\n\n\n\n\n\n                                Analytics                            \n\n\nanalytics\n\n\n\n\nAnalytical cookies are used to understand how visitors interact with the website. These cookies help provide information on metrics the number of visitors, bounce rate, traffic source, etc.\r\nCookieDurationDescription_ga2 years\n\n\nThis cookie is a Google Analytics cookie that tracks unique users on a website by storing a random ID. It helps monitor user behavior and sessions for analytics purposes.\n\n\n_ga_GEG38HZZ0G2 years\n\n\n\nGoogle Analytics 4 (GA4) helps WHO Foundation track user interactions on their website, providing insights into audience engagement and demographics for improved user experience and decision-making.\n\n\n\nfundraiseup_statsessionThis cookie is used to determine whether the user has given us permission to track their actions. If permission is granted, we will collect and analyze anonymous statistics about how visitors use the site. This data helps us optimize site functionality and provide a higher quality user experience.\n\n\n\n\n\n\n                                Advertisement                            \n\n\nadvertisement\n\n\n\n\nAdvertisement cookies are used to provide visitors with relevant ads and marketing campaigns. These cookies track visitors across websites and collect information to provide customized ads.\r\nCookieDurationDescriptionVISITOR_INFO1_LIVE6 monthsYouTube sets this cookie to measure bandwidth, determining whether the user gets the new or old player interface.VISITOR_PRIVACY_METADATA6 monthsYouTube sets this cookie to store the user's cookie consent state for the current domain.YSCsessionYoutube sets this cookie to track the views of embedded videos on Youtube pages.yt.innertube::nextIdneverYouTube sets this cookie to register a unique ID to store data on what videos from YouTube the user has seen.yt.innertube::requestsneverYouTube sets this cookie to register a unique ID to store data on what videos from YouTube the user has seen.\n\n\n\n\n\n\n                                Functional                            \n\n\nfunctional\n\n\n\n\nFunctional cookies ensure a website works properly by remembering user preferences and settings. They improve the user experience by storing details like language choices and login info, making the site more personalized and efficient.\r\nCookieDurationDescriptionfundraiseup_funcsession\n\n\n\r\n\r\nThis functional cookie ensures the Fundraise Up service operates properly, enhancing and personalizing the donation experience. It helps optimize site interactions and ensures elements like the Reminder function correctly, ultimately boosting engagement and improving the giving experience for visitors.\r\n\r\n\n\n\nyt-remote-cast-installedsessionThe yt-remote-cast-installed cookie is used to store the user's video player preferences using embedded YouTube video.yt-remote-connected-devicesneverYouTube sets this cookie to store the user's video preferences using embedded YouTube videos.yt-remote-device-idneverYouTube sets this cookie to store the user's video preferences using embedded YouTube videos.yt-remote-fast-check-periodsessionThe yt-remote-fast-check-period cookie is used by YouTube to store the user's video player preferences for embedded YouTube videos.yt-remote-session-appsessionThe yt-remote-session-app cookie is used by YouTube to store user preferences and information about the interface of the embedded YouTube video player.yt-remote-session-namesessionThe yt-remote-session-name cookie is used by YouTube to store the user's video player preferences using embedded YouTube video.ytidb::LAST_RESULT_ENTRY_KEYneverThe cookie ytidb::LAST_RESULT_ENTRY_KEY is used by YouTube to store the last search result entry that was clicked by the user. This information is used to improve the user experience by providing more relevant search results in the future.\n\n\n\n\n\n\n\n\n\n\n\n\n\n\nReject All Save My Preferences Accept All \n\n\n\n                            Powered by GDPR Cookie Compliance\n\nWe value your privacyWe use cookies on our website to give you the most relevant experience by remembering your preferences and repeat visits. By clicking “Accept”, you consent to the use of ALL the cookies. However you may visit Cookie Settings to provide a controlled consent.Cookie PolicyCustomizeReject AllAccept All\n\nWe value your privacyWe use cookies on our website to give you the most relevant experience by remembering your preferences and repeat visits. By clicking “Accept”, you consent to the use of ALL the cookies. However you may visit Cookie Settings to provide a controlled consent.Cookie PolicyCustomizeReject AllAccept All\n\nWe use cookies on our website to give you the most relevant experience by remembering your preferences and repeat visits. By clicking “Accept”, you consent to the use of ALL the cookies. However you may visit Cookie Settings to provide a controlled consent.Cookie PolicyCustomizeReject AllAccept All\n\nWe use cookies on our website to give you the most relevant experience by remembering your preferences and repeat visits. By clicking “Accept”, you consent to the use of ALL the cookies. However you may visit Cookie Settings to provide a controlled consent.\n\nCookie PolicyCustomizeReject AllAccept All\n\nConsent Preferences\n\nClose\n\n\n\n\n\n\nPrivacy Overview \nThis website uses cookies to improve your experience while you navigate through the website. Out of these cookies, the cookies that are categorized as necessary are stored on your browser as they are essential for the working of basic functionalities of the website. We also use third-party cookies that help us analyze and understand how you use this website. These cookies will be stored in your browser only with your consent. You also have the option to opt-out of these cookies. But opting out of some of these cookies may have an effect on your browsing experience.\n\n \n\n\n\n\n\n                                Necessary                            \n\n\n Necessary \n\n\n                                    Always Enabled                                \n\n\n\nNecessary cookies are absolutely essential for the website to function properly. These cookies ensure basic functionalities and security features of the website, anonymously.\r\nCookieDurationDescription_wpfuuid1 year 1 month 4 daysThis cookie is used by the WPForms WordPress plugin. The cookie is used to allows the paid version of the plugin to connect entries by the same user and is used for some additional features like the Form Abandonment addon.cookielawinfo-checkbox-advertisement1 yearSet by the GDPR Cookie Consent plugin, this cookie records the user consent for the cookies in the \"Advertisement\" category.cookielawinfo-checkbox-analytics11 monthsThis cookie is set by GDPR Cookie Consent plugin. The cookie is used to store the user consent for the cookies in the category \"Analytics\".cookielawinfo-checkbox-functional11 monthsThe cookie is set by GDPR cookie consent to record the user consent for the cookies in the category \"Functional\".cookielawinfo-checkbox-necessary11 monthsThis cookie is set by GDPR Cookie Consent plugin. The cookies is used to store the user consent for the cookies in the category \"Necessary\".cookielawinfo-checkbox-others11 monthsThis cookie is set by GDPR Cookie Consent plugin. The cookie is used to store the user consent for the cookies in the category \"Other.cookielawinfo-checkbox-performance11 monthsThis cookie is set by GDPR Cookie Consent plugin. The cookie is used to store the user consent for the cookies in the category \"Performance\".CookieLawInfoConsent1 yearCookieYes sets this cookie to record the default button state of the corresponding category and the status of CCPA. It works only in coordination with the primary cookie.fundraiseup_cid1 year 1 month 4 daysThis cookie is set by Fundraise Up, and is used to identify a user’s browser. This cookie is necessary for the platform to function properly and securely, as it helps us detect and prevent fraud.\r\n\r\n fundraiseup_sessionpastThis cookie tracks a user's current session while interacting with the site. It is used for maintaining information about their activities (e.g., donation process) during that session. Once the session ends the cookie is deleted.rc::aneverThis cookie is set by the Google recaptcha service to identify bots to protect the website against malicious spam attacks.rc::csessionThis cookie is set by the Google recaptcha service to identify bots to protect the website against malicious spam attacks.viewed_cookie_policy11 monthsThe cookie is set by the GDPR Cookie Consent plugin and is used to store whether or not user has consented to the use of cookies. It does not store any personal data.wpEmojiSettingsSupportssessionWordPress sets this cookie when a user interacts with emojis on a WordPress site.  It helps determine if the user's browser can display emojis properly.\n\n\n\n\n\n\n\n                                Analytics                            \n\n\nanalytics\n\n\n\n\nAnalytical cookies are used to understand how visitors interact with the website. These cookies help provide information on metrics the number of visitors, bounce rate, traffic source, etc.\r\nCookieDurationDescription_ga2 years\n\n\nThis cookie is a Google Analytics cookie that tracks unique users on a website by storing a random ID. It helps monitor user behavior and sessions for analytics purposes.\n\n\n_ga_GEG38HZZ0G2 years\n\n\n\nGoogle Analytics 4 (GA4) helps WHO Foundation track user interactions on their website, providing insights into audience engagement and demographics for improved user experience and decision-making.\n\n\n\nfundraiseup_statsessionThis cookie is used to determine whether the user has given us permission to track their actions. If permission is granted, we will collect and analyze anonymous statistics about how visitors use the site. This data helps us optimize site functionality and provide a higher quality user experience.\n\n\n\n\n\n\n                                Advertisement                            \n\n\nadvertisement\n\n\n\n\nAdvertisement cookies are used to provide visitors with relevant ads and marketing campaigns. These cookies track visitors across websites and collect information to provide customized ads.\r\nCookieDurationDescriptionVISITOR_INFO1_LIVE6 monthsYouTube sets this cookie to measure bandwidth, determining whether the user gets the new or old player interface.VISITOR_PRIVACY_METADATA6 monthsYouTube sets this cookie to store the user's cookie consent state for the current domain.YSCsessionYoutube sets this cookie to track the views of embedded videos on Youtube pages.yt.innertube::nextIdneverYouTube sets this cookie to register a unique ID to store data on what videos from YouTube the user has seen.yt.innertube::requestsneverYouTube sets this cookie to register a unique ID to store data on what videos from YouTube the user has seen.\n\n\n\n\n\n\n                                Functional                            \n\n\nfunctional\n\n\n\n\nFunctional cookies ensure a website works properly by remembering user preferences and settings. They improve the user experience by storing details like language choices and login info, making the site more personalized and efficient.\r\nCookieDurationDescriptionfundraiseup_funcsession\n\n\n\r\n\r\nThis functional cookie ensures the Fundraise Up service operates properly, enhancing and personalizing the donation experience. It helps optimize site interactions and ensures elements like the Reminder function correctly, ultimately boosting engagement and improving the giving experience for visitors.\r\n\r\n\n\n\nyt-remote-cast-installedsessionThe yt-remote-cast-installed cookie is used to store the user's video player preferences using embedded YouTube video.yt-remote-connected-devicesneverYouTube sets this cookie to store the user's video preferences using embedded YouTube videos.yt-remote-device-idneverYouTube sets this cookie to store the user's video preferences using embedded YouTube videos.yt-remote-fast-check-periodsessionThe yt-remote-fast-check-period cookie is used by YouTube to store the user's video player preferences for embedded YouTube videos.yt-remote-session-appsessionThe yt-remote-session-app cookie is used by YouTube to store user preferences and information about the interface of the embedded YouTube video player.yt-remote-session-namesessionThe yt-remote-session-name cookie is used by YouTube to store the user's video player preferences using embedded YouTube video.ytidb::LAST_RESULT_ENTRY_KEYneverThe cookie ytidb::LAST_RESULT_ENTRY_KEY is used by YouTube to store the last search result entry that was clicked by the user. This information is used to improve the user experience by providing more relevant search results in the future.\n\n\n\n\n\n\n\n\n\n\n\n\n\n\nReject All Save My Preferences Accept All \n\n\n\n                            Powered by GDPR Cookie Compliance\n\nClose\n\n\n\n\n\n\nPrivacy Overview \nThis website uses cookies to improve your experience while you navigate through the website. Out of these cookies, the cookies that are categorized as necessary are stored on your browser as they are essential for the working of basic functionalities of the website. We also use third-party cookies that help us analyze and understand how you use this website. These cookies will be stored in your browser only with your consent. You also have the option to opt-out of these cookies. But opting out of some of these cookies may have an effect on your browsing experience.\n\n \n\n\n\n\n\n                                Necessary                            \n\n\n Necessary \n\n\n                                    Always Enabled                                \n\n\n\nNecessary cookies are absolutely essential for the website to function properly. These cookies ensure basic functionalities and security features of the website, anonymously.\r\nCookieDurationDescription_wpfuuid1 year 1 month 4 daysThis cookie is used by the WPForms WordPress plugin. The cookie is used to allows the paid version of the plugin to connect entries by the same user and is used for some additional features like the Form Abandonment addon.cookielawinfo-checkbox-advertisement1 yearSet by the GDPR Cookie Consent plugin, this cookie records the user consent for the cookies in the \"Advertisement\" category.cookielawinfo-checkbox-analytics11 monthsThis cookie is set by GDPR Cookie Consent plugin. The cookie is used to store the user consent for the cookies in the category \"Analytics\".cookielawinfo-checkbox-functional11 monthsThe cookie is set by GDPR cookie consent to record the user consent for the cookies in the category \"Functional\".cookielawinfo-checkbox-necessary11 monthsThis cookie is set by GDPR Cookie Consent plugin. The cookies is used to store the user consent for the cookies in the category \"Necessary\".cookielawinfo-checkbox-others11 monthsThis cookie is set by GDPR Cookie Consent plugin. The cookie is used to store the user consent for the cookies in the category \"Other.cookielawinfo-checkbox-performance11 monthsThis cookie is set by GDPR Cookie Consent plugin. The cookie is used to store the user consent for the cookies in the category \"Performance\".CookieLawInfoConsent1 yearCookieYes sets this cookie to record the default button state of the corresponding category and the status of CCPA. It works only in coordination with the primary cookie.fundraiseup_cid1 year 1 month 4 daysThis cookie is set by Fundraise Up, and is used to identify a user’s browser. This cookie is necessary for the platform to function properly and securely, as it helps us detect and prevent fraud.\r\n\r\n fundraiseup_sessionpastThis cookie tracks a user's current session while interacting with the site. It is used for maintaining information about their activities (e.g., donation process) during that session. Once the session ends the cookie is deleted.rc::aneverThis cookie is set by the Google recaptcha service to identify bots to protect the website against malicious spam attacks.rc::csessionThis cookie is set by the Google recaptcha service to identify bots to protect the website against malicious spam attacks.viewed_cookie_policy11 monthsThe cookie is set by the GDPR Cookie Consent plugin and is used to store whether or not user has consented to the use of cookies. It does not store any personal data.wpEmojiSettingsSupportssessionWordPress sets this cookie when a user interacts with emojis on a WordPress site.  It helps determine if the user's browser can display emojis properly.\n\n\n\n\n\n\n\n                                Analytics                            \n\n\nanalytics\n\n\n\n\nAnalytical cookies are used to understand how visitors interact with the website. These cookies help provide information on metrics the number of visitors, bounce rate, traffic source, etc.\r\nCookieDurationDescription_ga2 years\n\n\nThis cookie is a Google Analytics cookie that tracks unique users on a website by storing a random ID. It helps monitor user behavior and sessions for analytics purposes.\n\n\n_ga_GEG38HZZ0G2 years\n\n\n\nGoogle Analytics 4 (GA4) helps WHO Foundation track user interactions on their website, providing insights into audience engagement and demographics for improved user experience and decision-making.\n\n\n\nfundraiseup_statsessionThis cookie is used to determine whether the user has given us permission to track their actions. If permission is granted, we will collect and analyze anonymous statistics about how visitors use the site. This data helps us optimize site functionality and provide a higher quality user experience.\n\n\n\n\n\n\n                                Advertisement                            \n\n\nadvertisement\n\n\n\n\nAdvertisement cookies are used to provide visitors with relevant ads and marketing campaigns. These cookies track visitors across websites and collect information to provide customized ads.\r\nCookieDurationDescriptionVISITOR_INFO1_LIVE6 monthsYouTube sets this cookie to measure bandwidth, determining whether the user gets the new or old player interface.VISITOR_PRIVACY_METADATA6 monthsYouTube sets this cookie to store the user's cookie consent state for the current domain.YSCsessionYoutube sets this cookie to track the views of embedded videos on Youtube pages.yt.innertube::nextIdneverYouTube sets this cookie to register a unique ID to store data on what videos from YouTube the user has seen.yt.innertube::requestsneverYouTube sets this cookie to register a unique ID to store data on what videos from YouTube the user has seen.\n\n\n\n\n\n\n                                Functional                            \n\n\nfunctional\n\n\n\n\nFunctional cookies ensure a website works properly by remembering user preferences and settings. They improve the user experience by storing details like language choices and login info, making the site more personalized and efficient.\r\nCookieDurationDescriptionfundraiseup_funcsession\n\n\n\r\n\r\nThis functional cookie ensures the Fundraise Up service operates properly, enhancing and personalizing the donation experience. It helps optimize site interactions and ensures elements like the Reminder function correctly, ultimately boosting engagement and improving the giving experience for visitors.\r\n\r\n\n\n\nyt-remote-cast-installedsessionThe yt-remote-cast-installed cookie is used to store the user's video player preferences using embedded YouTube video.yt-remote-connected-devicesneverYouTube sets this cookie to store the user's video preferences using embedded YouTube videos.yt-remote-device-idneverYouTube sets this cookie to store the user's video preferences using embedded YouTube videos.yt-remote-fast-check-periodsessionThe yt-remote-fast-check-period cookie is used by YouTube to store the user's video player preferences for embedded YouTube videos.yt-remote-session-appsessionThe yt-remote-session-app cookie is used by YouTube to store user preferences and information about the interface of the embedded YouTube video player.yt-remote-session-namesessionThe yt-remote-session-name cookie is used by YouTube to store the user's video player preferences using embedded YouTube video.ytidb::LAST_RESULT_ENTRY_KEYneverThe cookie ytidb::LAST_RESULT_ENTRY_KEY is used by YouTube to store the last search result entry that was clicked by the user. This information is used to improve the user experience by providing more relevant search results in the future.\n\n\n\n\n\n\n\n\n\n\n\n\n\n\nReject All Save My Preferences Accept All \n\n\n\n                            Powered by GDPR Cookie Compliance\n\nClose\n\n\n\n\n\n\nPrivacy Overview \nThis website uses cookies to improve your experience while you navigate through the website. Out of these cookies, the cookies that are categorized as necessary are stored on your browser as they are essential for the working of basic functionalities of the website. We also use third-party cookies that help us analyze and understand how you use this website. These cookies will be stored in your browser only with your consent. You also have the option to opt-out of these cookies. But opting out of some of these cookies may have an effect on your browsing experience.\n\n \n\n\n\n\n\n                                Necessary                            \n\n\n Necessary \n\n\n                                    Always Enabled                                \n\n\n\nNecessary cookies are absolutely essential for the website to function properly. These cookies ensure basic functionalities and security features of the website, anonymously.\r\nCookieDurationDescription_wpfuuid1 year 1 month 4 daysThis cookie is used by the WPForms WordPress plugin. The cookie is used to allows the paid version of the plugin to connect entries by the same user and is used for some additional features like the Form Abandonment addon.cookielawinfo-checkbox-advertisement1 yearSet by the GDPR Cookie Consent plugin, this cookie records the user consent for the cookies in the \"Advertisement\" category.cookielawinfo-checkbox-analytics11 monthsThis cookie is set by GDPR Cookie Consent plugin. The cookie is used to store the user consent for the cookies in the category \"Analytics\".cookielawinfo-checkbox-functional11 monthsThe cookie is set by GDPR cookie consent to record the user consent for the cookies in the category \"Functional\".cookielawinfo-checkbox-necessary11 monthsThis cookie is set by GDPR Cookie Consent plugin. The cookies is used to store the user consent for the cookies in the category \"Necessary\".cookielawinfo-checkbox-others11 monthsThis cookie is set by GDPR Cookie Consent plugin. The cookie is used to store the user consent for the cookies in the category \"Other.cookielawinfo-checkbox-performance11 monthsThis cookie is set by GDPR Cookie Consent plugin. The cookie is used to store the user consent for the cookies in the category \"Performance\".CookieLawInfoConsent1 yearCookieYes sets this cookie to record the default button state of the corresponding category and the status of CCPA. It works only in coordination with the primary cookie.fundraiseup_cid1 year 1 month 4 daysThis cookie is set by Fundraise Up, and is used to identify a user’s browser. This cookie is necessary for the platform to function properly and securely, as it helps us detect and prevent fraud.\r\n\r\n fundraiseup_sessionpastThis cookie tracks a user's current session while interacting with the site. It is used for maintaining information about their activities (e.g., donation process) during that session. Once the session ends the cookie is deleted.rc::aneverThis cookie is set by the Google recaptcha service to identify bots to protect the website against malicious spam attacks.rc::csessionThis cookie is set by the Google recaptcha service to identify bots to protect the website against malicious spam attacks.viewed_cookie_policy11 monthsThe cookie is set by the GDPR Cookie Consent plugin and is used to store whether or not user has consented to the use of cookies. It does not store any personal data.wpEmojiSettingsSupportssessionWordPress sets this cookie when a user interacts with emojis on a WordPress site.  It helps determine if the user's browser can display emojis properly.\n\n\n\n\n\n\n\n                                Analytics                            \n\n\nanalytics\n\n\n\n\nAnalytical cookies are used to understand how visitors interact with the website. These cookies help provide information on metrics the number of visitors, bounce rate, traffic source, etc.\r\nCookieDurationDescription_ga2 years\n\n\nThis cookie is a Google Analytics cookie that tracks unique users on a website by storing a random ID. It helps monitor user behavior and sessions for analytics purposes.\n\n\n_ga_GEG38HZZ0G2 years\n\n\n\nGoogle Analytics 4 (GA4) helps WHO Foundation track user interactions on their website, providing insights into audience engagement and demographics for improved user experience and decision-making.\n\n\n\nfundraiseup_statsessionThis cookie is used to determine whether the user has given us permission to track their actions. If permission is granted, we will collect and analyze anonymous statistics about how visitors use the site. This data helps us optimize site functionality and provide a higher quality user experience.\n\n\n\n\n\n\n                                Advertisement                            \n\n\nadvertisement\n\n\n\n\nAdvertisement cookies are used to provide visitors with relevant ads and marketing campaigns. These cookies track visitors across websites and collect information to provide customized ads.\r\nCookieDurationDescriptionVISITOR_INFO1_LIVE6 monthsYouTube sets this cookie to measure bandwidth, determining whether the user gets the new or old player interface.VISITOR_PRIVACY_METADATA6 monthsYouTube sets this cookie to store the user's cookie consent state for the current domain.YSCsessionYoutube sets this cookie to track the views of embedded videos on Youtube pages.yt.innertube::nextIdneverYouTube sets this cookie to register a unique ID to store data on what videos from YouTube the user has seen.yt.innertube::requestsneverYouTube sets this cookie to register a unique ID to store data on what videos from YouTube the user has seen.\n\n\n\n\n\n\n                                Functional                            \n\n\nfunctional\n\n\n\n\nFunctional cookies ensure a website works properly by remembering user preferences and settings. They improve the user experience by storing details like language choices and login info, making the site more personalized and efficient.\r\nCookieDurationDescriptionfundraiseup_funcsession\n\n\n\r\n\r\nThis functional cookie ensures the Fundraise Up service operates properly, enhancing and personalizing the donation experience. It helps optimize site interactions and ensures elements like the Reminder function correctly, ultimately boosting engagement and improving the giving experience for visitors.\r\n\r\n\n\n\nyt-remote-cast-installedsessionThe yt-remote-cast-installed cookie is used to store the user's video player preferences using embedded YouTube video.yt-remote-connected-devicesneverYouTube sets this cookie to store the user's video preferences using embedded YouTube videos.yt-remote-device-idneverYouTube sets this cookie to store the user's video preferences using embedded YouTube videos.yt-remote-fast-check-periodsessionThe yt-remote-fast-check-period cookie is used by YouTube to store the user's video player preferences for embedded YouTube videos.yt-remote-session-appsessionThe yt-remote-session-app cookie is used by YouTube to store user preferences and information about the interface of the embedded YouTube video player.yt-remote-session-namesessionThe yt-remote-session-name cookie is used by YouTube to store the user's video player preferences using embedded YouTube video.ytidb::LAST_RESULT_ENTRY_KEYneverThe cookie ytidb::LAST_RESULT_ENTRY_KEY is used by YouTube to store the last search result entry that was clicked by the user. This information is used to improve the user experience by providing more relevant search results in the future.\n\n\n\n\n\n\n\n\n\n\n\n\n\n\nReject All Save My Preferences Accept All \n\n\n\n                            Powered by GDPR Cookie Compliance\n\nPrivacy Overview \nThis website uses cookies to improve your experience while you navigate through the website. Out of these cookies, the cookies that are categorized as necessary are stored on your browser as they are essential for the working of basic functionalities of the website. We also use third-party cookies that help us analyze and understand how you use this website. These cookies will be stored in your browser only with your consent. You also have the option to opt-out of these cookies. But opting out of some of these cookies may have an effect on your browsing experience.\n\n \n\n\n\n\n\n                                Necessary                            \n\n\n Necessary \n\n\n                                    Always Enabled                                \n\n\n\nNecessary cookies are absolutely essential for the website to function properly. These cookies ensure basic functionalities and security features of the website, anonymously.\r\nCookieDurationDescription_wpfuuid1 year 1 month 4 daysThis cookie is used by the WPForms WordPress plugin. The cookie is used to allows the paid version of the plugin to connect entries by the same user and is used for some additional features like the Form Abandonment addon.cookielawinfo-checkbox-advertisement1 yearSet by the GDPR Cookie Consent plugin, this cookie records the user consent for the cookies in the \"Advertisement\" category.cookielawinfo-checkbox-analytics11 monthsThis cookie is set by GDPR Cookie Consent plugin. The cookie is used to store the user consent for the cookies in the category \"Analytics\".cookielawinfo-checkbox-functional11 monthsThe cookie is set by GDPR cookie consent to record the user consent for the cookies in the category \"Functional\".cookielawinfo-checkbox-necessary11 monthsThis cookie is set by GDPR Cookie Consent plugin. The cookies is used to store the user consent for the cookies in the category \"Necessary\".cookielawinfo-checkbox-others11 monthsThis cookie is set by GDPR Cookie Consent plugin. The cookie is used to store the user consent for the cookies in the category \"Other.cookielawinfo-checkbox-performance11 monthsThis cookie is set by GDPR Cookie Consent plugin. The cookie is used to store the user consent for the cookies in the category \"Performance\".CookieLawInfoConsent1 yearCookieYes sets this cookie to record the default button state of the corresponding category and the status of CCPA. It works only in coordination with the primary cookie.fundraiseup_cid1 year 1 month 4 daysThis cookie is set by Fundraise Up, and is used to identify a user’s browser. This cookie is necessary for the platform to function properly and securely, as it helps us detect and prevent fraud.\r\n\r\n fundraiseup_sessionpastThis cookie tracks a user's current session while interacting with the site. It is used for maintaining information about their activities (e.g., donation process) during that session. Once the session ends the cookie is deleted.rc::aneverThis cookie is set by the Google recaptcha service to identify bots to protect the website against malicious spam attacks.rc::csessionThis cookie is set by the Google recaptcha service to identify bots to protect the website against malicious spam attacks.viewed_cookie_policy11 monthsThe cookie is set by the GDPR Cookie Consent plugin and is used to store whether or not user has consented to the use of cookies. It does not store any personal data.wpEmojiSettingsSupportssessionWordPress sets this cookie when a user interacts with emojis on a WordPress site.  It helps determine if the user's browser can display emojis properly.\n\n\n\n\n\n\n\n                                Analytics                            \n\n\nanalytics\n\n\n\n\nAnalytical cookies are used to understand how visitors interact with the website. These cookies help provide information on metrics the number of visitors, bounce rate, traffic source, etc.\r\nCookieDurationDescription_ga2 years\n\n\nThis cookie is a Google Analytics cookie that tracks unique users on a website by storing a random ID. It helps monitor user behavior and sessions for analytics purposes.\n\n\n_ga_GEG38HZZ0G2 years\n\n\n\nGoogle Analytics 4 (GA4) helps WHO Foundation track user interactions on their website, providing insights into audience engagement and demographics for improved user experience and decision-making.\n\n\n\nfundraiseup_statsessionThis cookie is used to determine whether the user has given us permission to track their actions. If permission is granted, we will collect and analyze anonymous statistics about how visitors use the site. This data helps us optimize site functionality and provide a higher quality user experience.\n\n\n\n\n\n\n                                Advertisement                            \n\n\nadvertisement\n\n\n\n\nAdvertisement cookies are used to provide visitors with relevant ads and marketing campaigns. These cookies track visitors across websites and collect information to provide customized ads.\r\nCookieDurationDescriptionVISITOR_INFO1_LIVE6 monthsYouTube sets this cookie to measure bandwidth, determining whether the user gets the new or old player interface.VISITOR_PRIVACY_METADATA6 monthsYouTube sets this cookie to store the user's cookie consent state for the current domain.YSCsessionYoutube sets this cookie to track the views of embedded videos on Youtube pages.yt.innertube::nextIdneverYouTube sets this cookie to register a unique ID to store data on what videos from YouTube the user has seen.yt.innertube::requestsneverYouTube sets this cookie to register a unique ID to store data on what videos from YouTube the user has seen.\n\n\n\n\n\n\n                                Functional                            \n\n\nfunctional\n\n\n\n\nFunctional cookies ensure a website works properly by remembering user preferences and settings. They improve the user experience by storing details like language choices and login info, making the site more personalized and efficient.\r\nCookieDurationDescriptionfundraiseup_funcsession\n\n\n\r\n\r\nThis functional cookie ensures the Fundraise Up service operates properly, enhancing and personalizing the donation experience. It helps optimize site interactions and ensures elements like the Reminder function correctly, ultimately boosting engagement and improving the giving experience for visitors.\r\n\r\n\n\n\nyt-remote-cast-installedsessionThe yt-remote-cast-installed cookie is used to store the user's video player preferences using embedded YouTube video.yt-remote-connected-devicesneverYouTube sets this cookie to store the user's video preferences using embedded YouTube videos.yt-remote-device-idneverYouTube sets this cookie to store the user's video preferences using embedded YouTube videos.yt-remote-fast-check-periodsessionThe yt-remote-fast-check-period cookie is used by YouTube to store the user's video player preferences for embedded YouTube videos.yt-remote-session-appsessionThe yt-remote-session-app cookie is used by YouTube to store user preferences and information about the interface of the embedded YouTube video player.yt-remote-session-namesessionThe yt-remote-session-name cookie is used by YouTube to store the user's video player preferences using embedded YouTube video.ytidb::LAST_RESULT_ENTRY_KEYneverThe cookie ytidb::LAST_RESULT_ENTRY_KEY is used by YouTube to store the last search result entry that was clicked by the user. This information is used to improve the user experience by providing more relevant search results in the future.\n\nPrivacy Overview \nThis website uses cookies to improve your experience while you navigate through the website. Out of these cookies, the cookies that are categorized as necessary are stored on your browser as they are essential for the working of basic functionalities of the website. We also use third-party cookies that help us analyze and understand how you use this website. These cookies will be stored in your browser only with your consent. You also have the option to opt-out of these cookies. But opting out of some of these cookies may have an effect on your browsing experience.\n\n \n\n\n\n\n\n                                Necessary                            \n\n\n Necessary \n\n\n                                    Always Enabled                                \n\n\n\nNecessary cookies are absolutely essential for the website to function properly. These cookies ensure basic functionalities and security features of the website, anonymously.\r\nCookieDurationDescription_wpfuuid1 year 1 month 4 daysThis cookie is used by the WPForms WordPress plugin. The cookie is used to allows the paid version of the plugin to connect entries by the same user and is used for some additional features like the Form Abandonment addon.cookielawinfo-checkbox-advertisement1 yearSet by the GDPR Cookie Consent plugin, this cookie records the user consent for the cookies in the \"Advertisement\" category.cookielawinfo-checkbox-analytics11 monthsThis cookie is set by GDPR Cookie Consent plugin. The cookie is used to store the user consent for the cookies in the category \"Analytics\".cookielawinfo-checkbox-functional11 monthsThe cookie is set by GDPR cookie consent to record the user consent for the cookies in the category \"Functional\".cookielawinfo-checkbox-necessary11 monthsThis cookie is set by GDPR Cookie Consent plugin. The cookies is used to store the user consent for the cookies in the category \"Necessary\".cookielawinfo-checkbox-others11 monthsThis cookie is set by GDPR Cookie Consent plugin. The cookie is used to store the user consent for the cookies in the category \"Other.cookielawinfo-checkbox-performance11 monthsThis cookie is set by GDPR Cookie Consent plugin. The cookie is used to store the user consent for the cookies in the category \"Performance\".CookieLawInfoConsent1 yearCookieYes sets this cookie to record the default button state of the corresponding category and the status of CCPA. It works only in coordination with the primary cookie.fundraiseup_cid1 year 1 month 4 daysThis cookie is set by Fundraise Up, and is used to identify a user’s browser. This cookie is necessary for the platform to function properly and securely, as it helps us detect and prevent fraud.\r\n\r\n fundraiseup_sessionpastThis cookie tracks a user's current session while interacting with the site. It is used for maintaining information about their activities (e.g., donation process) during that session. Once the session ends the cookie is deleted.rc::aneverThis cookie is set by the Google recaptcha service to identify bots to protect the website against malicious spam attacks.rc::csessionThis cookie is set by the Google recaptcha service to identify bots to protect the website against malicious spam attacks.viewed_cookie_policy11 monthsThe cookie is set by the GDPR Cookie Consent plugin and is used to store whether or not user has consented to the use of cookies. It does not store any personal data.wpEmojiSettingsSupportssessionWordPress sets this cookie when a user interacts with emojis on a WordPress site.  It helps determine if the user's browser can display emojis properly.\n\n\n\n\n\n\n\n                                Analytics                            \n\n\nanalytics\n\n\n\n\nAnalytical cookies are used to understand how visitors interact with the website. These cookies help provide information on metrics the number of visitors, bounce rate, traffic source, etc.\r\nCookieDurationDescription_ga2 years\n\n\nThis cookie is a Google Analytics cookie that tracks unique users on a website by storing a random ID. It helps monitor user behavior and sessions for analytics purposes.\n\n\n_ga_GEG38HZZ0G2 years\n\n\n\nGoogle Analytics 4 (GA4) helps WHO Foundation track user interactions on their website, providing insights into audience engagement and demographics for improved user experience and decision-making.\n\n\n\nfundraiseup_statsessionThis cookie is used to determine whether the user has given us permission to track their actions. If permission is granted, we will collect and analyze anonymous statistics about how visitors use the site. This data helps us optimize site functionality and provide a higher quality user experience.\n\n\n\n\n\n\n                                Advertisement                            \n\n\nadvertisement\n\n\n\n\nAdvertisement cookies are used to provide visitors with relevant ads and marketing campaigns. These cookies track visitors across websites and collect information to provide customized ads.\r\nCookieDurationDescriptionVISITOR_INFO1_LIVE6 monthsYouTube sets this cookie to measure bandwidth, determining whether the user gets the new or old player interface.VISITOR_PRIVACY_METADATA6 monthsYouTube sets this cookie to store the user's cookie consent state for the current domain.YSCsessionYoutube sets this cookie to track the views of embedded videos on Youtube pages.yt.innertube::nextIdneverYouTube sets this cookie to register a unique ID to store data on what videos from YouTube the user has seen.yt.innertube::requestsneverYouTube sets this cookie to register a unique ID to store data on what videos from YouTube the user has seen.\n\n\n\n\n\n\n                                Functional                            \n\n\nfunctional\n\n\n\n\nFunctional cookies ensure a website works properly by remembering user preferences and settings. They improve the user experience by storing details like language choices and login info, making the site more personalized and efficient.\r\nCookieDurationDescriptionfundraiseup_funcsession\n\n\n\r\n\r\nThis functional cookie ensures the Fundraise Up service operates properly, enhancing and personalizing the donation experience. It helps optimize site interactions and ensures elements like the Reminder function correctly, ultimately boosting engagement and improving the giving experience for visitors.\r\n\r\n\n\n\nyt-remote-cast-installedsessionThe yt-remote-cast-installed cookie is used to store the user's video player preferences using embedded YouTube video.yt-remote-connected-devicesneverYouTube sets this cookie to store the user's video preferences using embedded YouTube videos.yt-remote-device-idneverYouTube sets this cookie to store the user's video preferences using embedded YouTube videos.yt-remote-fast-check-periodsessionThe yt-remote-fast-check-period cookie is used by YouTube to store the user's video player preferences for embedded YouTube videos.yt-remote-session-appsessionThe yt-remote-session-app cookie is used by YouTube to store user preferences and information about the interface of the embedded YouTube video player.yt-remote-session-namesessionThe yt-remote-session-name cookie is used by YouTube to store the user's video player preferences using embedded YouTube video.ytidb::LAST_RESULT_ENTRY_KEYneverThe cookie ytidb::LAST_RESULT_ENTRY_KEY is used by YouTube to store the last search result entry that was clicked by the user. This information is used to improve the user experience by providing more relevant search results in the future.\n\nPrivacy Overview \nThis website uses cookies to improve your experience while you navigate through the website. Out of these cookies, the cookies that are categorized as necessary are stored on your browser as they are essential for the working of basic functionalities of the website. We also use third-party cookies that help us analyze and understand how you use this website. These cookies will be stored in your browser only with your consent. You also have the option to opt-out of these cookies. But opting out of some of these cookies may have an effect on your browsing experience.\n\n \n\n\n\n\n\n                                Necessary                            \n\n\n Necessary \n\n\n                                    Always Enabled                                \n\n\n\nNecessary cookies are absolutely essential for the website to function properly. These cookies ensure basic functionalities and security features of the website, anonymously.\r\nCookieDurationDescription_wpfuuid1 year 1 month 4 daysThis cookie is used by the WPForms WordPress plugin. The cookie is used to allows the paid version of the plugin to connect entries by the same user and is used for some additional features like the Form Abandonment addon.cookielawinfo-checkbox-advertisement1 yearSet by the GDPR Cookie Consent plugin, this cookie records the user consent for the cookies in the \"Advertisement\" category.cookielawinfo-checkbox-analytics11 monthsThis cookie is set by GDPR Cookie Consent plugin. The cookie is used to store the user consent for the cookies in the category \"Analytics\".cookielawinfo-checkbox-functional11 monthsThe cookie is set by GDPR cookie consent to record the user consent for the cookies in the category \"Functional\".cookielawinfo-checkbox-necessary11 monthsThis cookie is set by GDPR Cookie Consent plugin. The cookies is used to store the user consent for the cookies in the category \"Necessary\".cookielawinfo-checkbox-others11 monthsThis cookie is set by GDPR Cookie Consent plugin. The cookie is used to store the user consent for the cookies in the category \"Other.cookielawinfo-checkbox-performance11 monthsThis cookie is set by GDPR Cookie Consent plugin. The cookie is used to store the user consent for the cookies in the category \"Performance\".CookieLawInfoConsent1 yearCookieYes sets this cookie to record the default button state of the corresponding category and the status of CCPA. It works only in coordination with the primary cookie.fundraiseup_cid1 year 1 month 4 daysThis cookie is set by Fundraise Up, and is used to identify a user’s browser. This cookie is necessary for the platform to function properly and securely, as it helps us detect and prevent fraud.\r\n\r\n fundraiseup_sessionpastThis cookie tracks a user's current session while interacting with the site. It is used for maintaining information about their activities (e.g., donation process) during that session. Once the session ends the cookie is deleted.rc::aneverThis cookie is set by the Google recaptcha service to identify bots to protect the website against malicious spam attacks.rc::csessionThis cookie is set by the Google recaptcha service to identify bots to protect the website against malicious spam attacks.viewed_cookie_policy11 monthsThe cookie is set by the GDPR Cookie Consent plugin and is used to store whether or not user has consented to the use of cookies. It does not store any personal data.wpEmojiSettingsSupportssessionWordPress sets this cookie when a user interacts with emojis on a WordPress site.  It helps determine if the user's browser can display emojis properly.\n\n\n\n\n\n\n\n                                Analytics                            \n\n\nanalytics\n\n\n\n\nAnalytical cookies are used to understand how visitors interact with the website. These cookies help provide information on metrics the number of visitors, bounce rate, traffic source, etc.\r\nCookieDurationDescription_ga2 years\n\n\nThis cookie is a Google Analytics cookie that tracks unique users on a website by storing a random ID. It helps monitor user behavior and sessions for analytics purposes.\n\n\n_ga_GEG38HZZ0G2 years\n\n\n\nGoogle Analytics 4 (GA4) helps WHO Foundation track user interactions on their website, providing insights into audience engagement and demographics for improved user experience and decision-making.\n\n\n\nfundraiseup_statsessionThis cookie is used to determine whether the user has given us permission to track their actions. If permission is granted, we will collect and analyze anonymous statistics about how visitors use the site. This data helps us optimize site functionality and provide a higher quality user experience.\n\n\n\n\n\n\n                                Advertisement                            \n\n\nadvertisement\n\n\n\n\nAdvertisement cookies are used to provide visitors with relevant ads and marketing campaigns. These cookies track visitors across websites and collect information to provide customized ads.\r\nCookieDurationDescriptionVISITOR_INFO1_LIVE6 monthsYouTube sets this cookie to measure bandwidth, determining whether the user gets the new or old player interface.VISITOR_PRIVACY_METADATA6 monthsYouTube sets this cookie to store the user's cookie consent state for the current domain.YSCsessionYoutube sets this cookie to track the views of embedded videos on Youtube pages.yt.innertube::nextIdneverYouTube sets this cookie to register a unique ID to store data on what videos from YouTube the user has seen.yt.innertube::requestsneverYouTube sets this cookie to register a unique ID to store data on what videos from YouTube the user has seen.\n\n\n\n\n\n\n                                Functional                            \n\n\nfunctional\n\n\n\n\nFunctional cookies ensure a website works properly by remembering user preferences and settings. They improve the user experience by storing details like language choices and login info, making the site more personalized and efficient.\r\nCookieDurationDescriptionfundraiseup_funcsession\n\n\n\r\n\r\nThis functional cookie ensures the Fundraise Up service operates properly, enhancing and personalizing the donation experience. It helps optimize site interactions and ensures elements like the Reminder function correctly, ultimately boosting engagement and improving the giving experience for visitors.\r\n\r\n\n\n\nyt-remote-cast-installedsessionThe yt-remote-cast-installed cookie is used to store the user's video player preferences using embedded YouTube video.yt-remote-connected-devicesneverYouTube sets this cookie to store the user's video preferences using embedded YouTube videos.yt-remote-device-idneverYouTube sets this cookie to store the user's video preferences using embedded YouTube videos.yt-remote-fast-check-periodsessionThe yt-remote-fast-check-period cookie is used by YouTube to store the user's video player preferences for embedded YouTube videos.yt-remote-session-appsessionThe yt-remote-session-app cookie is used by YouTube to store user preferences and information about the interface of the embedded YouTube video player.yt-remote-session-namesessionThe yt-remote-session-name cookie is used by YouTube to store the user's video player preferences using embedded YouTube video.ytidb::LAST_RESULT_ENTRY_KEYneverThe cookie ytidb::LAST_RESULT_ENTRY_KEY is used by YouTube to store the last search result entry that was clicked by the user. This information is used to improve the user experience by providing more relevant search results in the future.\n\nPrivacy Overview \nThis website uses cookies to improve your experience while you navigate through the website. Out of these cookies, the cookies that are categorized as necessary are stored on your browser as they are essential for the working of basic functionalities of the website. We also use third-party cookies that help us analyze and understand how you use this website. These cookies will be stored in your browser only with your consent. You also have the option to opt-out of these cookies. But opting out of some of these cookies may have an effect on your browsing experience.\n\nPrivacy Overview \nThis website uses cookies to improve your experience while you navigate through the website. Out of these cookies, the cookies that are categorized as necessary are stored on your browser as they are essential for the working of basic functionalities of the website. We also use third-party cookies that help us analyze and understand how you use this website. These cookies will be stored in your browser only with your consent. You also have the option to opt-out of these cookies. But opting out of some of these cookies may have an effect on your browsing experience.\n\nThis website uses cookies to improve your experience while you navigate through the website. Out of these cookies, the cookies that are categorized as necessary are stored on your browser as they are essential for the working of basic functionalities of the website. We also use third-party cookies that help us analyze and understand how you use this website. These cookies will be stored in your browser only with your consent. You also have the option to opt-out of these cookies. But opting out of some of these cookies may have an effect on your browsing experience.\n\nThis website uses cookies to improve your experience while you navigate through the website. Out of these cookies, the cookies that are categorized as necessary are stored on your browser as they are essential for the working of basic functionalities of the website. We also use third-party cookies that help us analyze and understand how you use this website. These cookies will be stored in your browser only with your consent. You also have the option to opt-out of these cookies. But opting out of some of these cookies may have an effect on your browsing experience.\n\nNecessary                            \n\n\n Necessary \n\n\n                                    Always Enabled                                \n\n\n\nNecessary cookies are absolutely essential for the website to function properly. These cookies ensure basic functionalities and security features of the website, anonymously.\r\nCookieDurationDescription_wpfuuid1 year 1 month 4 daysThis cookie is used by the WPForms WordPress plugin. The cookie is used to allows the paid version of the plugin to connect entries by the same user and is used for some additional features like the Form Abandonment addon.cookielawinfo-checkbox-advertisement1 yearSet by the GDPR Cookie Consent plugin, this cookie records the user consent for the cookies in the \"Advertisement\" category.cookielawinfo-checkbox-analytics11 monthsThis cookie is set by GDPR Cookie Consent plugin. The cookie is used to store the user consent for the cookies in the category \"Analytics\".cookielawinfo-checkbox-functional11 monthsThe cookie is set by GDPR cookie consent to record the user consent for the cookies in the category \"Functional\".cookielawinfo-checkbox-necessary11 monthsThis cookie is set by GDPR Cookie Consent plugin. The cookies is used to store the user consent for the cookies in the category \"Necessary\".cookielawinfo-checkbox-others11 monthsThis cookie is set by GDPR Cookie Consent plugin. The cookie is used to store the user consent for the cookies in the category \"Other.cookielawinfo-checkbox-performance11 monthsThis cookie is set by GDPR Cookie Consent plugin. The cookie is used to store the user consent for the cookies in the category \"Performance\".CookieLawInfoConsent1 yearCookieYes sets this cookie to record the default button state of the corresponding category and the status of CCPA. It works only in coordination with the primary cookie.fundraiseup_cid1 year 1 month 4 daysThis cookie is set by Fundraise Up, and is used to identify a user’s browser. This cookie is necessary for the platform to function properly and securely, as it helps us detect and prevent fraud.\r\n\r\n fundraiseup_sessionpastThis cookie tracks a user's current session while interacting with the site. It is used for maintaining information about their activities (e.g., donation process) during that session. Once the session ends the cookie is deleted.rc::aneverThis cookie is set by the Google recaptcha service to identify bots to protect the website against malicious spam attacks.rc::csessionThis cookie is set by the Google recaptcha service to identify bots to protect the website against malicious spam attacks.viewed_cookie_policy11 monthsThe cookie is set by the GDPR Cookie Consent plugin and is used to store whether or not user has consented to the use of cookies. It does not store any personal data.wpEmojiSettingsSupportssessionWordPress sets this cookie when a user interacts with emojis on a WordPress site.  It helps determine if the user's browser can display emojis properly.\n\n\n\n\n\n\n\n                                Analytics                            \n\n\nanalytics\n\n\n\n\nAnalytical cookies are used to understand how visitors interact with the website. These cookies help provide information on metrics the number of visitors, bounce rate, traffic source, etc.\r\nCookieDurationDescription_ga2 years\n\n\nThis cookie is a Google Analytics cookie that tracks unique users on a website by storing a random ID. It helps monitor user behavior and sessions for analytics purposes.\n\n\n_ga_GEG38HZZ0G2 years\n\n\n\nGoogle Analytics 4 (GA4) helps WHO Foundation track user interactions on their website, providing insights into audience engagement and demographics for improved user experience and decision-making.\n\n\n\nfundraiseup_statsessionThis cookie is used to determine whether the user has given us permission to track their actions. If permission is granted, we will collect and analyze anonymous statistics about how visitors use the site. This data helps us optimize site functionality and provide a higher quality user experience.\n\n\n\n\n\n\n                                Advertisement                            \n\n\nadvertisement\n\n\n\n\nAdvertisement cookies are used to provide visitors with relevant ads and marketing campaigns. These cookies track visitors across websites and collect information to provide customized ads.\r\nCookieDurationDescriptionVISITOR_INFO1_LIVE6 monthsYouTube sets this cookie to measure bandwidth, determining whether the user gets the new or old player interface.VISITOR_PRIVACY_METADATA6 monthsYouTube sets this cookie to store the user's cookie consent state for the current domain.YSCsessionYoutube sets this cookie to track the views of embedded videos on Youtube pages.yt.innertube::nextIdneverYouTube sets this cookie to register a unique ID to store data on what videos from YouTube the user has seen.yt.innertube::requestsneverYouTube sets this cookie to register a unique ID to store data on what videos from YouTube the user has seen.\n\n\n\n\n\n\n                                Functional                            \n\n\nfunctional\n\n\n\n\nFunctional cookies ensure a website works properly by remembering user preferences and settings. They improve the user experience by storing details like language choices and login info, making the site more personalized and efficient.\r\nCookieDurationDescriptionfundraiseup_funcsession\n\n\n\r\n\r\nThis functional cookie ensures the Fundraise Up service operates properly, enhancing and personalizing the donation experience. It helps optimize site interactions and ensures elements like the Reminder function correctly, ultimately boosting engagement and improving the giving experience for visitors.\r\n\r\n\n\n\nyt-remote-cast-installedsessionThe yt-remote-cast-installed cookie is used to store the user's video player preferences using embedded YouTube video.yt-remote-connected-devicesneverYouTube sets this cookie to store the user's video preferences using embedded YouTube videos.yt-remote-device-idneverYouTube sets this cookie to store the user's video preferences using embedded YouTube videos.yt-remote-fast-check-periodsessionThe yt-remote-fast-check-period cookie is used by YouTube to store the user's video player preferences for embedded YouTube videos.yt-remote-session-appsessionThe yt-remote-session-app cookie is used by YouTube to store user preferences and information about the interface of the embedded YouTube video player.yt-remote-session-namesessionThe yt-remote-session-name cookie is used by YouTube to store the user's video player preferences using embedded YouTube video.ytidb::LAST_RESULT_ENTRY_KEYneverThe cookie ytidb::LAST_RESULT_ENTRY_KEY is used by YouTube to store the last search result entry that was clicked by the user. This information is used to improve the user experience by providing more relevant search results in the future.\n\nNecessary                            \n\n\n Necessary \n\n\n                                    Always Enabled                                \n\n\n\nNecessary cookies are absolutely essential for the website to function properly. These cookies ensure basic functionalities and security features of the website, anonymously.\r\nCookieDurationDescription_wpfuuid1 year 1 month 4 daysThis cookie is used by the WPForms WordPress plugin. The cookie is used to allows the paid version of the plugin to connect entries by the same user and is used for some additional features like the Form Abandonment addon.cookielawinfo-checkbox-advertisement1 yearSet by the GDPR Cookie Consent plugin, this cookie records the user consent for the cookies in the \"Advertisement\" category.cookielawinfo-checkbox-analytics11 monthsThis cookie is set by GDPR Cookie Consent plugin. The cookie is used to store the user consent for the cookies in the category \"Analytics\".cookielawinfo-checkbox-functional11 monthsThe cookie is set by GDPR cookie consent to record the user consent for the cookies in the category \"Functional\".cookielawinfo-checkbox-necessary11 monthsThis cookie is set by GDPR Cookie Consent plugin. The cookies is used to store the user consent for the cookies in the category \"Necessary\".cookielawinfo-checkbox-others11 monthsThis cookie is set by GDPR Cookie Consent plugin. The cookie is used to store the user consent for the cookies in the category \"Other.cookielawinfo-checkbox-performance11 monthsThis cookie is set by GDPR Cookie Consent plugin. The cookie is used to store the user consent for the cookies in the category \"Performance\".CookieLawInfoConsent1 yearCookieYes sets this cookie to record the default button state of the corresponding category and the status of CCPA. It works only in coordination with the primary cookie.fundraiseup_cid1 year 1 month 4 daysThis cookie is set by Fundraise Up, and is used to identify a user’s browser. This cookie is necessary for the platform to function properly and securely, as it helps us detect and prevent fraud.\r\n\r\n fundraiseup_sessionpastThis cookie tracks a user's current session while interacting with the site. It is used for maintaining information about their activities (e.g., donation process) during that session. Once the session ends the cookie is deleted.rc::aneverThis cookie is set by the Google recaptcha service to identify bots to protect the website against malicious spam attacks.rc::csessionThis cookie is set by the Google recaptcha service to identify bots to protect the website against malicious spam attacks.viewed_cookie_policy11 monthsThe cookie is set by the GDPR Cookie Consent plugin and is used to store whether or not user has consented to the use of cookies. It does not store any personal data.wpEmojiSettingsSupportssessionWordPress sets this cookie when a user interacts with emojis on a WordPress site.  It helps determine if the user's browser can display emojis properly.\n\nNecessary                            \n\n\n Necessary \n\n\n                                    Always Enabled\n\nNecessary\n\nNecessary cookies are absolutely essential for the website to function properly. These cookies ensure basic functionalities and security features of the website, anonymously.\r\nCookieDurationDescription_wpfuuid1 year 1 month 4 daysThis cookie is used by the WPForms WordPress plugin. The cookie is used to allows the paid version of the plugin to connect entries by the same user and is used for some additional features like the Form Abandonment addon.cookielawinfo-checkbox-advertisement1 yearSet by the GDPR Cookie Consent plugin, this cookie records the user consent for the cookies in the \"Advertisement\" category.cookielawinfo-checkbox-analytics11 monthsThis cookie is set by GDPR Cookie Consent plugin. The cookie is used to store the user consent for the cookies in the category \"Analytics\".cookielawinfo-checkbox-functional11 monthsThe cookie is set by GDPR cookie consent to record the user consent for the cookies in the category \"Functional\".cookielawinfo-checkbox-necessary11 monthsThis cookie is set by GDPR Cookie Consent plugin. The cookies is used to store the user consent for the cookies in the category \"Necessary\".cookielawinfo-checkbox-others11 monthsThis cookie is set by GDPR Cookie Consent plugin. The cookie is used to store the user consent for the cookies in the category \"Other.cookielawinfo-checkbox-performance11 monthsThis cookie is set by GDPR Cookie Consent plugin. The cookie is used to store the user consent for the cookies in the category \"Performance\".CookieLawInfoConsent1 yearCookieYes sets this cookie to record the default button state of the corresponding category and the status of CCPA. It works only in coordination with the primary cookie.fundraiseup_cid1 year 1 month 4 daysThis cookie is set by Fundraise Up, and is used to identify a user’s browser. This cookie is necessary for the platform to function properly and securely, as it helps us detect and prevent fraud.\r\n\r\n fundraiseup_sessionpastThis cookie tracks a user's current session while interacting with the site. It is used for maintaining information about their activities (e.g., donation process) during that session. Once the session ends the cookie is deleted.rc::aneverThis cookie is set by the Google recaptcha service to identify bots to protect the website against malicious spam attacks.rc::csessionThis cookie is set by the Google recaptcha service to identify bots to protect the website against malicious spam attacks.viewed_cookie_policy11 monthsThe cookie is set by the GDPR Cookie Consent plugin and is used to store whether or not user has consented to the use of cookies. It does not store any personal data.wpEmojiSettingsSupportssessionWordPress sets this cookie when a user interacts with emojis on a WordPress site.  It helps determine if the user's browser can display emojis properly.\n\nNecessary cookies are absolutely essential for the website to function properly. These cookies ensure basic functionalities and security features of the website, anonymously.\r\nCookieDurationDescription_wpfuuid1 year 1 month 4 daysThis cookie is used by the WPForms WordPress plugin. The cookie is used to allows the paid version of the plugin to connect entries by the same user and is used for some additional features like the Form Abandonment addon.cookielawinfo-checkbox-advertisement1 yearSet by the GDPR Cookie Consent plugin, this cookie records the user consent for the cookies in the \"Advertisement\" category.cookielawinfo-checkbox-analytics11 monthsThis cookie is set by GDPR Cookie Consent plugin. The cookie is used to store the user consent for the cookies in the category \"Analytics\".cookielawinfo-checkbox-functional11 monthsThe cookie is set by GDPR cookie consent to record the user consent for the cookies in the category \"Functional\".cookielawinfo-checkbox-necessary11 monthsThis cookie is set by GDPR Cookie Consent plugin. The cookies is used to store the user consent for the cookies in the category \"Necessary\".cookielawinfo-checkbox-others11 monthsThis cookie is set by GDPR Cookie Consent plugin. The cookie is used to store the user consent for the cookies in the category \"Other.cookielawinfo-checkbox-performance11 monthsThis cookie is set by GDPR Cookie Consent plugin. The cookie is used to store the user consent for the cookies in the category \"Performance\".CookieLawInfoConsent1 yearCookieYes sets this cookie to record the default button state of the corresponding category and the status of CCPA. It works only in coordination with the primary cookie.fundraiseup_cid1 year 1 month 4 daysThis cookie is set by Fundraise Up, and is used to identify a user’s browser. This cookie is necessary for the platform to function properly and securely, as it helps us detect and prevent fraud.\r\n\r\n fundraiseup_sessionpastThis cookie tracks a user's current session while interacting with the site. It is used for maintaining information about their activities (e.g., donation process) during that session. Once the session ends the cookie is deleted.rc::aneverThis cookie is set by the Google recaptcha service to identify bots to protect the website against malicious spam attacks.rc::csessionThis cookie is set by the Google recaptcha service to identify bots to protect the website against malicious spam attacks.viewed_cookie_policy11 monthsThe cookie is set by the GDPR Cookie Consent plugin and is used to store whether or not user has consented to the use of cookies. It does not store any personal data.wpEmojiSettingsSupportssessionWordPress sets this cookie when a user interacts with emojis on a WordPress site.  It helps determine if the user's browser can display emojis properly.\n\nNecessary cookies are absolutely essential for the website to function properly. These cookies ensure basic functionalities and security features of the website, anonymously.\r\nCookieDurationDescription_wpfuuid1 year 1 month 4 daysThis cookie is used by the WPForms WordPress plugin. The cookie is used to allows the paid version of the plugin to connect entries by the same user and is used for some additional features like the Form Abandonment addon.cookielawinfo-checkbox-advertisement1 yearSet by the GDPR Cookie Consent plugin, this cookie records the user consent for the cookies in the \"Advertisement\" category.cookielawinfo-checkbox-analytics11 monthsThis cookie is set by GDPR Cookie Consent plugin. The cookie is used to store the user consent for the cookies in the category \"Analytics\".cookielawinfo-checkbox-functional11 monthsThe cookie is set by GDPR cookie consent to record the user consent for the cookies in the category \"Functional\".cookielawinfo-checkbox-necessary11 monthsThis cookie is set by GDPR Cookie Consent plugin. The cookies is used to store the user consent for the cookies in the category \"Necessary\".cookielawinfo-checkbox-others11 monthsThis cookie is set by GDPR Cookie Consent plugin. The cookie is used to store the user consent for the cookies in the category \"Other.cookielawinfo-checkbox-performance11 monthsThis cookie is set by GDPR Cookie Consent plugin. The cookie is used to store the user consent for the cookies in the category \"Performance\".CookieLawInfoConsent1 yearCookieYes sets this cookie to record the default button state of the corresponding category and the status of CCPA. It works only in coordination with the primary cookie.fundraiseup_cid1 year 1 month 4 daysThis cookie is set by Fundraise Up, and is used to identify a user’s browser. This cookie is necessary for the platform to function properly and securely, as it helps us detect and prevent fraud.\r\n\r\n fundraiseup_sessionpastThis cookie tracks a user's current session while interacting with the site. It is used for maintaining information about their activities (e.g., donation process) during that session. Once the session ends the cookie is deleted.rc::aneverThis cookie is set by the Google recaptcha service to identify bots to protect the website against malicious spam attacks.rc::csessionThis cookie is set by the Google recaptcha service to identify bots to protect the website against malicious spam attacks.viewed_cookie_policy11 monthsThe cookie is set by the GDPR Cookie Consent plugin and is used to store whether or not user has consented to the use of cookies. It does not store any personal data.wpEmojiSettingsSupportssessionWordPress sets this cookie when a user interacts with emojis on a WordPress site.  It helps determine if the user's browser can display emojis properly.\n\nAnalytics                            \n\n\nanalytics\n\n\n\n\nAnalytical cookies are used to understand how visitors interact with the website. These cookies help provide information on metrics the number of visitors, bounce rate, traffic source, etc.\r\nCookieDurationDescription_ga2 years\n\n\nThis cookie is a Google Analytics cookie that tracks unique users on a website by storing a random ID. It helps monitor user behavior and sessions for analytics purposes.\n\n\n_ga_GEG38HZZ0G2 years\n\n\n\nGoogle Analytics 4 (GA4) helps WHO Foundation track user interactions on their website, providing insights into audience engagement and demographics for improved user experience and decision-making.\n\n\n\nfundraiseup_statsessionThis cookie is used to determine whether the user has given us permission to track their actions. If permission is granted, we will collect and analyze anonymous statistics about how visitors use the site. This data helps us optimize site functionality and provide a higher quality user experience.\n\nAnalytics                            \n\n\nanalytics\n\nanalytics\n\nAnalytical cookies are used to understand how visitors interact with the website. These cookies help provide information on metrics the number of visitors, bounce rate, traffic source, etc.\r\nCookieDurationDescription_ga2 years\n\n\nThis cookie is a Google Analytics cookie that tracks unique users on a website by storing a random ID. It helps monitor user behavior and sessions for analytics purposes.\n\n\n_ga_GEG38HZZ0G2 years\n\n\n\nGoogle Analytics 4 (GA4) helps WHO Foundation track user interactions on their website, providing insights into audience engagement and demographics for improved user experience and decision-making.\n\n\n\nfundraiseup_statsessionThis cookie is used to determine whether the user has given us permission to track their actions. If permission is granted, we will collect and analyze anonymous statistics about how visitors use the site. This data helps us optimize site functionality and provide a higher quality user experience.\n\nAnalytical cookies are used to understand how visitors interact with the website. These cookies help provide information on metrics the number of visitors, bounce rate, traffic source, etc.\r\nCookieDurationDescription_ga2 years\n\n\nThis cookie is a Google Analytics cookie that tracks unique users on a website by storing a random ID. It helps monitor user behavior and sessions for analytics purposes.\n\n\n_ga_GEG38HZZ0G2 years\n\n\n\nGoogle Analytics 4 (GA4) helps WHO Foundation track user interactions on their website, providing insights into audience engagement and demographics for improved user experience and decision-making.\n\n\n\nfundraiseup_statsessionThis cookie is used to determine whether the user has given us permission to track their actions. If permission is granted, we will collect and analyze anonymous statistics about how visitors use the site. This data helps us optimize site functionality and provide a higher quality user experience.\n\nAnalytical cookies are used to understand how visitors interact with the website. These cookies help provide information on metrics the number of visitors, bounce rate, traffic source, etc.\r\nCookieDurationDescription_ga2 years\n\n\nThis cookie is a Google Analytics cookie that tracks unique users on a website by storing a random ID. It helps monitor user behavior and sessions for analytics purposes.\n\n\n_ga_GEG38HZZ0G2 years\n\n\n\nGoogle Analytics 4 (GA4) helps WHO Foundation track user interactions on their website, providing insights into audience engagement and demographics for improved user experience and decision-making.\n\n\n\nfundraiseup_statsessionThis cookie is used to determine whether the user has given us permission to track their actions. If permission is granted, we will collect and analyze anonymous statistics about how visitors use the site. This data helps us optimize site functionality and provide a higher quality user experience.\n\nThis cookie is a Google Analytics cookie that tracks unique users on a website by storing a random ID. It helps monitor user behavior and sessions for analytics purposes.\n\nThis cookie is a Google Analytics cookie that tracks unique users on a website by storing a random ID. It helps monitor user behavior and sessions for analytics purposes.\n\nThis cookie is a Google Analytics cookie that tracks unique users on a website by storing a random ID. It helps monitor user behavior and sessions for analytics purposes.\n\nThis cookie is a Google Analytics cookie that tracks unique users on a website by storing a random ID. It helps monitor user behavior and sessions for analytics purposes.\n\nGoogle Analytics 4 (GA4) helps WHO Foundation track user interactions on their website, providing insights into audience engagement and demographics for improved user experience and decision-making.\n\nGoogle Analytics 4 (GA4) helps WHO Foundation track user interactions on their website, providing insights into audience engagement and demographics for improved user experience and decision-making.\n\nGoogle Analytics 4 (GA4) helps WHO Foundation track user interactions on their website, providing insights into audience engagement and demographics for improved user experience and decision-making.\n\nGoogle Analytics 4 (GA4) helps WHO Foundation track user interactions on their website, providing insights into audience engagement and demographics for improved user experience and decision-making.\n\nGoogle Analytics 4 (GA4) helps WHO Foundation track user interactions on their website, providing insights into audience engagement and demographics for improved user experience and decision-making.\n\nAdvertisement                            \n\n\nadvertisement\n\n\n\n\nAdvertisement cookies are used to provide visitors with relevant ads and marketing campaigns. These cookies track visitors across websites and collect information to provide customized ads.\r\nCookieDurationDescriptionVISITOR_INFO1_LIVE6 monthsYouTube sets this cookie to measure bandwidth, determining whether the user gets the new or old player interface.VISITOR_PRIVACY_METADATA6 monthsYouTube sets this cookie to store the user's cookie consent state for the current domain.YSCsessionYoutube sets this cookie to track the views of embedded videos on Youtube pages.yt.innertube::nextIdneverYouTube sets this cookie to register a unique ID to store data on what videos from YouTube the user has seen.yt.innertube::requestsneverYouTube sets this cookie to register a unique ID to store data on what videos from YouTube the user has seen.\n\nAdvertisement                            \n\n\nadvertisement\n\nadvertisement\n\nAdvertisement cookies are used to provide visitors with relevant ads and marketing campaigns. These cookies track visitors across websites and collect information to provide customized ads.\r\nCookieDurationDescriptionVISITOR_INFO1_LIVE6 monthsYouTube sets this cookie to measure bandwidth, determining whether the user gets the new or old player interface.VISITOR_PRIVACY_METADATA6 monthsYouTube sets this cookie to store the user's cookie consent state for the current domain.YSCsessionYoutube sets this cookie to track the views of embedded videos on Youtube pages.yt.innertube::nextIdneverYouTube sets this cookie to register a unique ID to store data on what videos from YouTube the user has seen.yt.innertube::requestsneverYouTube sets this cookie to register a unique ID to store data on what videos from YouTube the user has seen.\n\nAdvertisement cookies are used to provide visitors with relevant ads and marketing campaigns. These cookies track visitors across websites and collect information to provide customized ads.\r\nCookieDurationDescriptionVISITOR_INFO1_LIVE6 monthsYouTube sets this cookie to measure bandwidth, determining whether the user gets the new or old player interface.VISITOR_PRIVACY_METADATA6 monthsYouTube sets this cookie to store the user's cookie consent state for the current domain.YSCsessionYoutube sets this cookie to track the views of embedded videos on Youtube pages.yt.innertube::nextIdneverYouTube sets this cookie to register a unique ID to store data on what videos from YouTube the user has seen.yt.innertube::requestsneverYouTube sets this cookie to register a unique ID to store data on what videos from YouTube the user has seen.\n\nAdvertisement cookies are used to provide visitors with relevant ads and marketing campaigns. These cookies track visitors across websites and collect information to provide customized ads.\r\nCookieDurationDescriptionVISITOR_INFO1_LIVE6 monthsYouTube sets this cookie to measure bandwidth, determining whether the user gets the new or old player interface.VISITOR_PRIVACY_METADATA6 monthsYouTube sets this cookie to store the user's cookie consent state for the current domain.YSCsessionYoutube sets this cookie to track the views of embedded videos on Youtube pages.yt.innertube::nextIdneverYouTube sets this cookie to register a unique ID to store data on what videos from YouTube the user has seen.yt.innertube::requestsneverYouTube sets this cookie to register a unique ID to store data on what videos from YouTube the user has seen.\n\nFunctional                            \n\n\nfunctional\n\n\n\n\nFunctional cookies ensure a website works properly by remembering user preferences and settings. They improve the user experience by storing details like language choices and login info, making the site more personalized and efficient.\r\nCookieDurationDescriptionfundraiseup_funcsession\n\n\n\r\n\r\nThis functional cookie ensures the Fundraise Up service operates properly, enhancing and personalizing the donation experience. It helps optimize site interactions and ensures elements like the Reminder function correctly, ultimately boosting engagement and improving the giving experience for visitors.\r\n\r\n\n\n\nyt-remote-cast-installedsessionThe yt-remote-cast-installed cookie is used to store the user's video player preferences using embedded YouTube video.yt-remote-connected-devicesneverYouTube sets this cookie to store the user's video preferences using embedded YouTube videos.yt-remote-device-idneverYouTube sets this cookie to store the user's video preferences using embedded YouTube videos.yt-remote-fast-check-periodsessionThe yt-remote-fast-check-period cookie is used by YouTube to store the user's video player preferences for embedded YouTube videos.yt-remote-session-appsessionThe yt-remote-session-app cookie is used by YouTube to store user preferences and information about the interface of the embedded YouTube video player.yt-remote-session-namesessionThe yt-remote-session-name cookie is used by YouTube to store the user's video player preferences using embedded YouTube video.ytidb::LAST_RESULT_ENTRY_KEYneverThe cookie ytidb::LAST_RESULT_ENTRY_KEY is used by YouTube to store the last search result entry that was clicked by the user. This information is used to improve the user experience by providing more relevant search results in the future.\n\nFunctional                            \n\n\nfunctional\n\nfunctional\n\nFunctional cookies ensure a website works properly by remembering user preferences and settings. They improve the user experience by storing details like language choices and login info, making the site more personalized and efficient.\r\nCookieDurationDescriptionfundraiseup_funcsession\n\n\n\r\n\r\nThis functional cookie ensures the Fundraise Up service operates properly, enhancing and personalizing the donation experience. It helps optimize site interactions and ensures elements like the Reminder function correctly, ultimately boosting engagement and improving the giving experience for visitors.\r\n\r\n\n\n\nyt-remote-cast-installedsessionThe yt-remote-cast-installed cookie is used to store the user's video player preferences using embedded YouTube video.yt-remote-connected-devicesneverYouTube sets this cookie to store the user's video preferences using embedded YouTube videos.yt-remote-device-idneverYouTube sets this cookie to store the user's video preferences using embedded YouTube videos.yt-remote-fast-check-periodsessionThe yt-remote-fast-check-period cookie is used by YouTube to store the user's video player preferences for embedded YouTube videos.yt-remote-session-appsessionThe yt-remote-session-app cookie is used by YouTube to store user preferences and information about the interface of the embedded YouTube video player.yt-remote-session-namesessionThe yt-remote-session-name cookie is used by YouTube to store the user's video player preferences using embedded YouTube video.ytidb::LAST_RESULT_ENTRY_KEYneverThe cookie ytidb::LAST_RESULT_ENTRY_KEY is used by YouTube to store the last search result entry that was clicked by the user. This information is used to improve the user experience by providing more relevant search results in the future.\n\nFunctional cookies ensure a website works properly by remembering user preferences and settings. They improve the user experience by storing details like language choices and login info, making the site more personalized and efficient.\r\nCookieDurationDescriptionfundraiseup_funcsession\n\n\n\r\n\r\nThis functional cookie ensures the Fundraise Up service operates properly, enhancing and personalizing the donation experience. It helps optimize site interactions and ensures elements like the Reminder function correctly, ultimately boosting engagement and improving the giving experience for visitors.\r\n\r\n\n\n\nyt-remote-cast-installedsessionThe yt-remote-cast-installed cookie is used to store the user's video player preferences using embedded YouTube video.yt-remote-connected-devicesneverYouTube sets this cookie to store the user's video preferences using embedded YouTube videos.yt-remote-device-idneverYouTube sets this cookie to store the user's video preferences using embedded YouTube videos.yt-remote-fast-check-periodsessionThe yt-remote-fast-check-period cookie is used by YouTube to store the user's video player preferences for embedded YouTube videos.yt-remote-session-appsessionThe yt-remote-session-app cookie is used by YouTube to store user preferences and information about the interface of the embedded YouTube video player.yt-remote-session-namesessionThe yt-remote-session-name cookie is used by YouTube to store the user's video player preferences using embedded YouTube video.ytidb::LAST_RESULT_ENTRY_KEYneverThe cookie ytidb::LAST_RESULT_ENTRY_KEY is used by YouTube to store the last search result entry that was clicked by the user. This information is used to improve the user experience by providing more relevant search results in the future.\n\nFunctional cookies ensure a website works properly by remembering user preferences and settings. They improve the user experience by storing details like language choices and login info, making the site more personalized and efficient.\r\nCookieDurationDescriptionfundraiseup_funcsession\n\n\n\r\n\r\nThis functional cookie ensures the Fundraise Up service operates properly, enhancing and personalizing the donation experience. It helps optimize site interactions and ensures elements like the Reminder function correctly, ultimately boosting engagement and improving the giving experience for visitors.\r\n\r\n\n\n\nyt-remote-cast-installedsessionThe yt-remote-cast-installed cookie is used to store the user's video player preferences using embedded YouTube video.yt-remote-connected-devicesneverYouTube sets this cookie to store the user's video preferences using embedded YouTube videos.yt-remote-device-idneverYouTube sets this cookie to store the user's video preferences using embedded YouTube videos.yt-remote-fast-check-periodsessionThe yt-remote-fast-check-period cookie is used by YouTube to store the user's video player preferences for embedded YouTube videos.yt-remote-session-appsessionThe yt-remote-session-app cookie is used by YouTube to store user preferences and information about the interface of the embedded YouTube video player.yt-remote-session-namesessionThe yt-remote-session-name cookie is used by YouTube to store the user's video player preferences using embedded YouTube video.ytidb::LAST_RESULT_ENTRY_KEYneverThe cookie ytidb::LAST_RESULT_ENTRY_KEY is used by YouTube to store the last search result entry that was clicked by the user. This information is used to improve the user experience by providing more relevant search results in the future.\n\nThis functional cookie ensures the Fundraise Up service operates properly, enhancing and personalizing the donation experience. It helps optimize site interactions and ensures elements like the Reminder function correctly, ultimately boosting engagement and improving the giving experience for visitors.\n\nThis functional cookie ensures the Fundraise Up service operates properly, enhancing and personalizing the donation experience. It helps optimize site interactions and ensures elements like the Reminder function correctly, ultimately boosting engagement and improving the giving experience for visitors.\n\nThis functional cookie ensures the Fundraise Up service operates properly, enhancing and personalizing the donation experience. It helps optimize site interactions and ensures elements like the Reminder function correctly, ultimately boosting engagement and improving the giving experience for visitors.\n\nThis functional cookie ensures the Fundraise Up service operates properly, enhancing and personalizing the donation experience. It helps optimize site interactions and ensures elements like the Reminder function correctly, ultimately boosting engagement and improving the giving experience for visitors.\n\nReject All Save My Preferences Accept All \n\n\n\n                            Powered by GDPR Cookie Compliance\n\nReject All Save My Preferences Accept All \n\n\n\n                            Powered by GDPR Cookie Compliance\n\nReject All Save My Preferences Accept All \n\n\n\n                            Powered by GDPR Cookie Compliance\n\nReject All Save My Preferences Accept All \n\n\n\n                            Powered by GDPR Cookie Compliance\n\nReject All Save My Preferences Accept All\n\nReject All Save My Preferences Accept All\n\nPowered by GDPR Cookie Compliance\n\nPowered by GDPR Cookie Compliance",
  "date": "",
  "source_type": "other",
  "extracted_at": "2025-04-07T13:58:31.606967",
  "metadata": {},
  "relevance_score": 0.44166666666666665,
  "summary": "The cookie is used to allows the paid version of the plugin to connect entries by the same user and is used for some additional features like the Form Abandonment addon.cookielawinfo-checkbox-advertisement1 yearSet by the GDPR Cookie Consent plugin, this cookie records the user consent for the cookies in the \"Advertisement\" category.cookielawinfo-checkbox-analytics11 monthsThis cookie is set by GDPR Cookie Consent plugin. The cookie is used to store the user consent for the cookies in the category \"Analytics\".cookielawinfo-checkbox-functional11 monthsThe cookie is set by GDPR cookie consent to record the user consent for the cookies in the category \"Functional\".cookielawinfo-checkbox-necessary11 monthsThis cookie is set by GDPR Cookie Consent plugin. The cookies is used to store the user consent for the cookies in the category \"Necessary\".cookielawinfo-checkbox-others11 monthsThis cookie is set by GDPR Cookie Consent plugin. The cookie is used to store the user consent for the cookies in the category \"Other.cookielawinfo-checkbox-performance11 monthsThis cookie is set by GDPR Cookie Consent plugin. The cookie is used to store the user consent for the cookies in the category \"Performance\".CookieLawInfoConsent1 yearCookieYes sets this cookie to record the default button state of the corresponding category and the status of CCPA. Once the session ends the cookie is deleted.rc::aneverThis cookie is set by the Google recaptcha service to identify bots to protect the website against malicious spam attacks.rc::csessionThis cookie is set by the Google recaptcha service to identify bots to protect the website against malicious spam attacks.viewed_cookie_policy11 monthsThe cookie is set by the GDPR Cookie Consent plugin and is used to store whether or not user has consented to the use of cookies. CookieDurationDescription_ga2 years\n\n\nThis cookie is a Google Analytics cookie that tracks unique users on a website by storing a random ID. _ga_GEG38HZZ0G2 years\n\n\n\nGoogle Analytics 4 (GA4) helps WHO Foundation track user interactions on their website, providing insights into audience engagement and demographics for improved user experience and decision-making. CookieDurationDescriptionVISITOR_INFO1_LIVE6 monthsYouTube sets this cookie to measure bandwidth, determining whether the user gets the new or old player interface.VISITOR_PRIVACY_METADATA6 monthsYouTube sets this cookie to store the user's cookie consent state for the current domain.YSCsessionYoutube sets this cookie to track the views of embedded videos on Youtube pages.yt.innertube::nextIdneverYouTube sets this cookie to register a unique ID to store data on what videos from YouTube the user has seen.yt.innertube::requestsneverYouTube sets this cookie to register a unique ID to store data on what videos from YouTube the user has seen. yt-remote-cast-installedsessionThe yt-remote-cast-installed cookie is used to store the user's video player preferences using embedded YouTube video.yt-remote-connected-devicesneverYouTube sets this cookie to store the user's video preferences using embedded YouTube videos.yt-remote-device-idneverYouTube sets this cookie to store the user's video preferences using embedded YouTube videos.yt-remote-fast-check-periodsessionThe yt-remote-fast-check-period cookie is used by YouTube to store the user's video player preferences for embedded YouTube videos.yt-remote-session-appsessionThe yt-remote-session-app cookie is used by YouTube to store user preferences and information about the interface of the embedded YouTube video player.yt-remote-session-namesessionThe yt-remote-session-name cookie is used by YouTube to store the user's video player preferences using embedded YouTube video.ytidb::LAST_RESULT_ENTRY_KEYneverThe cookie ytidb::LAST_RESULT_ENTRY_KEY is used by YouTube to store the last search result entry that was clicked by the user. Cookie PolicyCustomizeReject AllAccept All\n\nConsent Preferences\n\nClose\n\n\n\n\n\n\nPrivacy Overview \nThis website uses cookies to improve your experience while you navigate through the website. The cookie is used to allows the paid version of the plugin to connect entries by the same user and is used for some additional features like the Form Abandonment addon.cookielawinfo-checkbox-advertisement1 yearSet by the GDPR Cookie Consent plugin, this cookie records the user consent for the cookies in the \"Advertisement\" category.cookielawinfo-checkbox-analytics11 monthsThis cookie is set by GDPR Cookie Consent plugin. The cookie is used to store the user consent for the cookies in the category \"Analytics\".cookielawinfo-checkbox-functional11 monthsThe cookie is set by GDPR cookie consent to record the user consent for the cookies in the category \"Functional\".cookielawinfo-checkbox-necessary11 monthsThis cookie is set by GDPR Cookie Consent plugin. The cookies is used to store the user consent for the cookies in the category \"Necessary\".cookielawinfo-checkbox-others11 monthsThis cookie is set by GDPR Cookie Consent plugin. The cookie is used to store the user consent for the cookies in the category \"Other.cookielawinfo-checkbox-performance11 monthsThis cookie is set by GDPR Cookie Consent plugin. The cookie is used to store the user consent for the cookies in the category \"Performance\".CookieLawInfoConsent1 yearCookieYes sets this cookie to record the default button state of the corresponding category and the status of CCPA. Once the session ends the cookie is deleted.rc::aneverThis cookie is set by the Google recaptcha service to identify bots to protect the website against malicious spam attacks.rc::csessionThis cookie is set by the Google recaptcha service to identify bots to protect the website against malicious spam attacks.viewed_cookie_policy11 monthsThe cookie is set by the GDPR Cookie Consent plugin and is used to store whether or not user has consented to the use of cookies. CookieDurationDescription_ga2 years\n\n\nThis cookie is a Google Analytics cookie that tracks unique users on a website by storing a random ID. _ga_GEG38HZZ0G2 years\n\n\n\nGoogle Analytics 4 (GA4) helps WHO Foundation track user interactions on their website, providing insights into audience engagement and demographics for improved user experience and decision-making. CookieDurationDescriptionVISITOR_INFO1_LIVE6 monthsYouTube sets this cookie to measure bandwidth, determining whether the user gets the new or old player interface.VISITOR_PRIVACY_METADATA6 monthsYouTube sets this cookie to store the user's cookie consent state for the current domain.YSCsessionYoutube sets this cookie to track the views of embedded videos on Youtube pages.yt.innertube::nextIdneverYouTube sets this cookie to register a unique ID to store data on what videos from YouTube the user has seen.yt.innertube::requestsneverYouTube sets this cookie to register a unique ID to store data on what videos from YouTube the user has seen. yt-remote-cast-installedsessionThe yt-remote-cast-installed cookie is used to store the user's video player preferences using embedded YouTube video.yt-remote-connected-devicesneverYouTube sets this cookie to store the user's video preferences using embedded YouTube videos.yt-remote-device-idneverYouTube sets this cookie to store the user's video preferences using embedded YouTube videos.yt-remote-fast-check-periodsessionThe yt-remote-fast-check-period cookie is used by YouTube to store the user's video player preferences for embedded YouTube videos.yt-remote-session-appsessionThe yt-remote-session-app cookie is used by YouTube to store user preferences and information about the interface of the embedded YouTube video player.yt-remote-session-namesessionThe yt-remote-session-name cookie is used by YouTube to store the user's video player preferences using embedded YouTube video.ytidb::LAST_RESULT_ENTRY_KEYneverThe cookie ytidb::LAST_RESULT_ENTRY_KEY is used by YouTube to store the last search result entry that was clicked by the user. The cookie is used to allows the paid version of the plugin to connect entries by the same user and is used for some additional features like the Form Abandonment addon.cookielawinfo-checkbox-advertisement1 yearSet by the GDPR Cookie Consent plugin, this cookie records the user consent for the cookies in the \"Advertisement\" category.cookielawinfo-checkbox-analytics11 monthsThis cookie is set by GDPR Cookie Consent plugin. The cookie is used to store the user consent for the cookies in the category \"Analytics\".cookielawinfo-checkbox-functional11 monthsThe cookie is set by GDPR cookie consent to record the user consent for the cookies in the category \"Functional\".cookielawinfo-checkbox-necessary11 monthsThis cookie is set by GDPR Cookie Consent plugin. The cookies is used to store the user consent for the cookies in the category \"Necessary\".cookielawinfo-checkbox-others11 monthsThis cookie is set by GDPR Cookie Consent plugin. The cookie is used to store the user consent for the cookies in the category \"Other.cookielawinfo-checkbox-performance11 monthsThis cookie is set by GDPR Cookie Consent plugin. The cookie is used to store the user consent for the cookies in the category \"Performance\".CookieLawInfoConsent1 yearCookieYes sets this cookie to record the default button state of the corresponding category and the status of CCPA. Once the session ends the cookie is deleted.rc::aneverThis cookie is set by the Google recaptcha service to identify bots to protect the website against malicious spam attacks.rc::csessionThis cookie is set by the Google recaptcha service to identify bots to protect the website against malicious spam attacks.viewed_cookie_policy11 monthsThe cookie is set by the GDPR Cookie Consent plugin and is used to store whether or not user has consented to the use of cookies. CookieDurationDescription_ga2 years\n\n\nThis cookie is a Google Analytics cookie that tracks unique users on a website by storing a random ID. _ga_GEG38HZZ0G2 years\n\n\n\nGoogle Analytics 4 (GA4) helps WHO Foundation track user interactions on their website, providing insights into audience engagement and demographics for improved user experience and decision-making. CookieDurationDescriptionVISITOR_INFO1_LIVE6 monthsYouTube sets this cookie to measure bandwidth, determining whether the user gets the new or old player interface.VISITOR_PRIVACY_METADATA6 monthsYouTube sets this cookie to store the user's cookie consent state for the current domain.YSCsessionYoutube sets this cookie to track the views of embedded videos on Youtube pages.yt.innertube::nextIdneverYouTube sets this cookie to register a unique ID to store data on what videos from YouTube the user has seen.yt.innertube::requestsneverYouTube sets this cookie to register a unique ID to store data on what videos from YouTube the user has seen. yt-remote-cast-installedsessionThe yt-remote-cast-installed cookie is used to store the user's video player preferences using embedded YouTube video.yt-remote-connected-devicesneverYouTube sets this cookie to store the user's video preferences using embedded YouTube videos.yt-remote-device-idneverYouTube sets this cookie to store the user's video preferences using embedded YouTube videos.yt-remote-fast-check-periodsessionThe yt-remote-fast-check-period cookie is used by YouTube to store the user's video player preferences for embedded YouTube videos.yt-remote-session-appsessionThe yt-remote-session-app cookie is used by YouTube to store user preferences and information about the interface of the embedded YouTube video player.yt-remote-session-namesessionThe yt-remote-session-name cookie is used by YouTube to store the user's video player preferences using embedded YouTube video.ytidb::LAST_RESULT_ENTRY_KEYneverThe cookie ytidb::LAST_RESULT_ENTRY_KEY is used by YouTube to store the last search result entry that was clicked by the user. The cookie is used to allows the paid version of the plugin to connect entries by the same user and is used for some additional features like the Form Abandonment addon.cookielawinfo-checkbox-advertisement1 yearSet by the GDPR Cookie Consent plugin, this cookie records the user consent for the cookies in the \"Advertisement\" category.cookielawinfo-checkbox-analytics11 monthsThis cookie is set by GDPR Cookie Consent plugin. The cookie is used to store the user consent for the cookies in the category \"Analytics\".cookielawinfo-checkbox-functional11 monthsThe cookie is set by GDPR cookie consent to record the user consent for the cookies in the category \"Functional\".cookielawinfo-checkbox-necessary11 monthsThis cookie is set by GDPR Cookie Consent plugin. The cookies is used to store the user consent for the cookies in the category \"Necessary\".cookielawinfo-checkbox-others11 monthsThis cookie is set by GDPR Cookie Consent plugin. The cookie is used to store the user consent for the cookies in the category \"Other.cookielawinfo-checkbox-performance11 monthsThis cookie is set by GDPR Cookie Consent plugin. The cookie is used to store the user consent for the cookies in the category \"Performance\".CookieLawInfoConsent1 yearCookieYes sets this cookie to record the default button state of the corresponding category and the status of CCPA. Once the session ends the cookie is deleted.rc::aneverThis cookie is set by the Google recaptcha service to identify bots to protect the website against malicious spam attacks.rc::csessionThis cookie is set by the Google recaptcha service to identify bots to protect the website against malicious spam attacks.viewed_cookie_policy11 monthsThe cookie is set by the GDPR Cookie Consent plugin and is used to store whether or not user has consented to the use of cookies. CookieDurationDescription_ga2 years\n\n\nThis cookie is a Google Analytics cookie that tracks unique users on a website by storing a random ID. _ga_GEG38HZZ0G2 years\n\n\n\nGoogle Analytics 4 (GA4) helps WHO Foundation track user interactions on their website, providing insights into audience engagement and demographics for improved user experience and decision-making. CookieDurationDescriptionVISITOR_INFO1_LIVE6 monthsYouTube sets this cookie to measure bandwidth, determining whether the user gets the new or old player interface.VISITOR_PRIVACY_METADATA6 monthsYouTube sets this cookie to store the user's cookie consent state for the current domain.YSCsessionYoutube sets this cookie to track the views of embedded videos on Youtube pages.yt.innertube::nextIdneverYouTube sets this cookie to register a unique ID to store data on what videos from YouTube the user has seen.yt.innertube::requestsneverYouTube sets this cookie to register a unique ID to store data on what videos from YouTube the user has seen. yt-remote-cast-installedsessionThe yt-remote-cast-installed cookie is used to store the user's video player preferences using embedded YouTube video.yt-remote-connected-devicesneverYouTube sets this cookie to store the user's video preferences using embedded YouTube videos.yt-remote-device-idneverYouTube sets this cookie to store the user's video preferences using embedded YouTube videos.yt-remote-fast-check-periodsessionThe yt-remote-fast-check-period cookie is used by YouTube to store the user's video player preferences for embedded YouTube videos.yt-remote-session-appsessionThe yt-remote-session-app cookie is used by YouTube to store user preferences and information about the interface of the embedded YouTube video player.yt-remote-session-namesessionThe yt-remote-session-name cookie is used by YouTube to store the user's video player preferences using embedded YouTube video.ytidb::LAST_RESULT_ENTRY_KEYneverThe cookie ytidb::LAST_RESULT_ENTRY_KEY is used by YouTube to store the last search result entry that was clicked by the user. The cookie is used to allows the paid version of the plugin to connect entries by the same user and is used for some additional features like the Form Abandonment addon.cookielawinfo-checkbox-advertisement1 yearSet by the GDPR Cookie Consent plugin, this cookie records the user consent for the cookies in the \"Advertisement\" category.cookielawinfo-checkbox-analytics11 monthsThis cookie is set by GDPR Cookie Consent plugin. The cookie is used to store the user consent for the cookies in the category \"Analytics\".cookielawinfo-checkbox-functional11 monthsThe cookie is set by GDPR cookie consent to record the user consent for the cookies in the category \"Functional\".cookielawinfo-checkbox-necessary11 monthsThis cookie is set by GDPR Cookie Consent plugin. The cookies is used to store the user consent for the cookies in the category \"Necessary\".cookielawinfo-checkbox-others11 monthsThis cookie is set by GDPR Cookie Consent plugin. The cookie is used to store the user consent for the cookies in the category \"Other.cookielawinfo-checkbox-performance11 monthsThis cookie is set by GDPR Cookie Consent plugin. The cookie is used to store the user consent for the cookies in the category \"Performance\".CookieLawInfoConsent1 yearCookieYes sets this cookie to record the default button state of the corresponding category and the status of CCPA. Once the session ends the cookie is deleted.rc::aneverThis cookie is set by the Google recaptcha service to identify bots to protect the website against malicious spam attacks.rc::csessionThis cookie is set by the Google recaptcha service to identify bots to protect the website against malicious spam attacks.viewed_cookie_policy11 monthsThe cookie is set by the GDPR Cookie Consent plugin and is used to store whether or not user has consented to the use of cookies. CookieDurationDescription_ga2 years\n\n\nThis cookie is a Google Analytics cookie that tracks unique users on a website by storing a random ID. _ga_GEG38HZZ0G2 years\n\n\n\nGoogle Analytics 4 (GA4) helps WHO Foundation track user interactions on their website, providing insights into audience engagement and demographics for improved user experience and decision-making. CookieDurationDescriptionVISITOR_INFO1_LIVE6 monthsYouTube sets this cookie to measure bandwidth, determining whether the user gets the new or old player interface.VISITOR_PRIVACY_METADATA6 monthsYouTube sets this cookie to store the user's cookie consent state for the current domain.YSCsessionYoutube sets this cookie to track the views of embedded videos on Youtube pages.yt.innertube::nextIdneverYouTube sets this cookie to register a unique ID to store data on what videos from YouTube the user has seen.yt.innertube::requestsneverYouTube sets this cookie to register a unique ID to store data on what videos from YouTube the user has seen. yt-remote-cast-installedsessionThe yt-remote-cast-installed cookie is used to store the user's video player preferences using embedded YouTube video.yt-remote-connected-devicesneverYouTube sets this cookie to store the user's video preferences using embedded YouTube videos.yt-remote-device-idneverYouTube sets this cookie to store the user's video preferences using embedded YouTube videos.yt-remote-fast-check-periodsessionThe yt-remote-fast-check-period cookie is used by YouTube to store the user's video player preferences for embedded YouTube videos.yt-remote-session-appsessionThe yt-remote-session-app cookie is used by YouTube to store user preferences and information about the interface of the embedded YouTube video player.yt-remote-session-namesessionThe yt-remote-session-name cookie is used by YouTube to store the user's video player preferences using embedded YouTube video.ytidb::LAST_RESULT_ENTRY_KEYneverThe cookie ytidb::LAST_RESULT_ENTRY_KEY is used by YouTube to store the last search result entry that was clicked by the user. The cookie is used to allows the paid version of the plugin to connect entries by the same user and is used for some additional features like the Form Abandonment addon.cookielawinfo-checkbox-advertisement1 yearSet by the GDPR Cookie Consent plugin, this cookie records the user consent for the cookies in the \"Advertisement\" category.cookielawinfo-checkbox-analytics11 monthsThis cookie is set by GDPR Cookie Consent plugin. The cookie is used to store the user consent for the cookies in the category \"Analytics\".cookielawinfo-checkbox-functional11 monthsThe cookie is set by GDPR cookie consent to record the user consent for the cookies in the category \"Functional\".cookielawinfo-checkbox-necessary11 monthsThis cookie is set by GDPR Cookie Consent plugin. The cookies is used to store the user consent for the cookies in the category \"Necessary\".cookielawinfo-checkbox-others11 monthsThis cookie is set by GDPR Cookie Consent plugin. The cookie is used to store the user consent for the cookies in the category \"Other.cookielawinfo-checkbox-performance11 monthsThis cookie is set by GDPR Cookie Consent plugin. The cookie is used to store the user consent for the cookies in the category \"Performance\".CookieLawInfoConsent1 yearCookieYes sets this cookie to record the default button state of the corresponding category and the status of CCPA. Once the session ends the cookie is deleted.rc::aneverThis cookie is set by the Google recaptcha service to identify bots to protect the website against malicious spam attacks.rc::csessionThis cookie is set by the Google recaptcha service to identify bots to protect the website against malicious spam attacks.viewed_cookie_policy11 monthsThe cookie is set by the GDPR Cookie Consent plugin and is used to store whether or not user has consented to the use of cookies. CookieDurationDescription_ga2 years\n\n\nThis cookie is a Google Analytics cookie that tracks unique users on a website by storing a random ID. CookieDurationDescriptionVISITOR_INFO1_LIVE6 monthsYouTube sets this cookie to measure bandwidth, determining whether the user gets the new or old player interface.VISITOR_PRIVACY_METADATA6 monthsYouTube sets this cookie to store the user's cookie consent state for the current domain.YSCsessionYoutube sets this cookie to track the views of embedded videos on Youtube pages.yt.innertube::nextIdneverYouTube sets this cookie to register a unique ID to store data on what videos from YouTube the user has seen.yt.innertube::requestsneverYouTube sets this cookie to register a unique ID to store data on what videos from YouTube the user has seen. yt-remote-cast-installedsessionThe yt-remote-cast-installed cookie is used to store the user's video player preferences using embedded YouTube video.yt-remote-connected-devicesneverYouTube sets this cookie to store the user's video preferences using embedded YouTube videos.yt-remote-device-idneverYouTube sets this cookie to store the user's video preferences using embedded YouTube videos.yt-remote-fast-check-periodsessionThe yt-remote-fast-check-period cookie is used by YouTube to store the user's video player preferences for embedded YouTube videos.yt-remote-session-appsessionThe yt-remote-session-app cookie is used by YouTube to store user preferences and information about the interface of the embedded YouTube video player.yt-remote-session-namesessionThe yt-remote-session-name cookie is used by YouTube to store the user's video player preferences using embedded YouTube video.ytidb::LAST_RESULT_ENTRY_KEYneverThe cookie ytidb::LAST_RESULT_ENTRY_KEY is used by YouTube to store the last search result entry that was clicked by the user. The cookie is used to allows the paid version of the plugin to connect entries by the same user and is used for some additional features like the Form Abandonment addon.cookielawinfo-checkbox-advertisement1 yearSet by the GDPR Cookie Consent plugin, this cookie records the user consent for the cookies in the \"Advertisement\" category.cookielawinfo-checkbox-analytics11 monthsThis cookie is set by GDPR Cookie Consent plugin. The cookie is used to store the user consent for the cookies in the category \"Analytics\".cookielawinfo-checkbox-functional11 monthsThe cookie is set by GDPR cookie consent to record the user consent for the cookies in the category \"Functional\".cookielawinfo-checkbox-necessary11 monthsThis cookie is set by GDPR Cookie Consent plugin. The cookies is used to store the user consent for the cookies in the category \"Necessary\".cookielawinfo-checkbox-others11 monthsThis cookie is set by GDPR Cookie Consent plugin. The cookie is used to store the user consent for the cookies in the category \"Other.cookielawinfo-checkbox-performance11 monthsThis cookie is set by GDPR Cookie Consent plugin. The cookie is used to store the user consent for the cookies in the category \"Performance\".CookieLawInfoConsent1 yearCookieYes sets this cookie to record the default button state of the corresponding category and the status of CCPA. Once the session ends the cookie is deleted.rc::aneverThis cookie is set by the Google recaptcha service to identify bots to protect the website against malicious spam attacks.rc::csessionThis cookie is set by the Google recaptcha service to identify bots to protect the website against malicious spam attacks.viewed_cookie_policy11 monthsThe cookie is set by the GDPR Cookie Consent plugin and is used to store whether or not user has consented to the use of cookies. CookieDurationDescription_ga2 years\n\n\nThis cookie is a Google Analytics cookie that tracks unique users on a website by storing a random ID. CookieDurationDescriptionVISITOR_INFO1_LIVE6 monthsYouTube sets this cookie to measure bandwidth, determining whether the user gets the new or old player interface.VISITOR_PRIVACY_METADATA6 monthsYouTube sets this cookie to store the user's cookie consent state for the current domain.YSCsessionYoutube sets this cookie to track the views of embedded videos on Youtube pages.yt.innertube::nextIdneverYouTube sets this cookie to register a unique ID to store data on what videos from YouTube the user has seen.yt.innertube::requestsneverYouTube sets this cookie to register a unique ID to store data on what videos from YouTube the user has seen. yt-remote-cast-installedsessionThe yt-remote-cast-installed cookie is used to store the user's video player preferences using embedded YouTube video.yt-remote-connected-devicesneverYouTube sets this cookie to store the user's video preferences using embedded YouTube videos.yt-remote-device-idneverYouTube sets this cookie to store the user's video preferences using embedded YouTube videos.yt-remote-fast-check-periodsessionThe yt-remote-fast-check-period cookie is used by YouTube to store the user's video player preferences for embedded YouTube videos.yt-remote-session-appsessionThe yt-remote-session-app cookie is used by YouTube to store user preferences and information about the interface of the embedded YouTube video player.yt-remote-session-namesessionThe yt-remote-session-name cookie is used by YouTube to store the user's video player preferences using embedded YouTube video.ytidb::LAST_RESULT_ENTRY_KEYneverThe cookie ytidb::LAST_RESULT_ENTRY_KEY is used by YouTube to store the last search result entry that was clicked by the user. The cookie is used to allows the paid version of the plugin to connect entries by the same user and is used for some additional features like the Form Abandonment addon.cookielawinfo-checkbox-advertisement1 yearSet by the GDPR Cookie Consent plugin, this cookie records the user consent for the cookies in the \"Advertisement\" category.cookielawinfo-checkbox-analytics11 monthsThis cookie is set by GDPR Cookie Consent plugin. The cookie is used to store the user consent for the cookies in the category \"Analytics\".cookielawinfo-checkbox-functional11 monthsThe cookie is set by GDPR cookie consent to record the user consent for the cookies in the category \"Functional\".cookielawinfo-checkbox-necessary11 monthsThis cookie is set by GDPR Cookie Consent plugin. The cookies is used to store the user consent for the cookies in the category \"Necessary\".cookielawinfo-checkbox-others11 monthsThis cookie is set by GDPR Cookie Consent plugin. The cookie is used to store the user consent for the cookies in the category \"Other.cookielawinfo-checkbox-performance11 monthsThis cookie is set by GDPR Cookie Consent plugin. The cookie is used to store the user consent for the cookies in the category \"Performance\".CookieLawInfoConsent1 yearCookieYes sets this cookie to record the default button state of the corresponding category and the status of CCPA. Once the session ends the cookie is deleted.rc::aneverThis cookie is set by the Google recaptcha service to identify bots to protect the website against malicious spam attacks.rc::csessionThis cookie is set by the Google recaptcha service to identify bots to protect the website against malicious spam attacks.viewed_cookie_policy11 monthsThe cookie is set by the GDPR Cookie Consent plugin and is used to store whether or not user has consented to the use of cookies. CookieDurationDescription_ga2 years\n\n\nThis cookie is a Google Analytics cookie that tracks unique users on a website by storing a random ID. CookieDurationDescriptionVISITOR_INFO1_LIVE6 monthsYouTube sets this cookie to measure bandwidth, determining whether the user gets the new or old player interface.VISITOR_PRIVACY_METADATA6 monthsYouTube sets this cookie to store the user's cookie consent state for the current domain.YSCsessionYoutube sets this cookie to track the views of embedded videos on Youtube pages.yt.innertube::nextIdneverYouTube sets this cookie to register a unique ID to store data on what videos from YouTube the user has seen.yt.innertube::requestsneverYouTube sets this cookie to register a unique ID to store data on what videos from YouTube the user has seen. yt-remote-cast-installedsessionThe yt-remote-cast-installed cookie is used to store the user's video player preferences using embedded YouTube video.yt-remote-connected-devicesneverYouTube sets this cookie to store the user's video preferences using embedded YouTube videos.yt-remote-device-idneverYouTube sets this cookie to store the user's video preferences using embedded YouTube videos.yt-remote-fast-check-periodsessionThe yt-remote-fast-check-period cookie is used by YouTube to store the user's video player preferences for embedded YouTube videos.yt-remote-session-appsessionThe yt-remote-session-app cookie is used by YouTube to store user preferences and information about the interface of the embedded YouTube video player.yt-remote-session-namesessionThe yt-remote-session-name cookie is used by YouTube to store the user's video player preferences using embedded YouTube video.ytidb::LAST_RESULT_ENTRY_KEYneverThe cookie ytidb::LAST_RESULT_ENTRY_KEY is used by YouTube to store the last search result entry that was clicked by the user. The cookie is used to allows the paid version of the plugin to connect entries by the same user and is used for some additional features like the Form Abandonment addon.cookielawinfo-checkbox-advertisement1 yearSet by the GDPR Cookie Consent plugin, this cookie records the user consent for the cookies in the \"Advertisement\" category.cookielawinfo-checkbox-analytics11 monthsThis cookie is set by GDPR Cookie Consent plugin. The cookie is used to store the user consent for the cookies in the category \"Analytics\".cookielawinfo-checkbox-functional11 monthsThe cookie is set by GDPR cookie consent to record the user consent for the cookies in the category \"Functional\".cookielawinfo-checkbox-necessary11 monthsThis cookie is set by GDPR Cookie Consent plugin. The cookies is used to store the user consent for the cookies in the category \"Necessary\".cookielawinfo-checkbox-others11 monthsThis cookie is set by GDPR Cookie Consent plugin. The cookie is used to store the user consent for the cookies in the category \"Other.cookielawinfo-checkbox-performance11 monthsThis cookie is set by GDPR Cookie Consent plugin. The cookie is used to store the user consent for the cookies in the category \"Performance\".CookieLawInfoConsent1 yearCookieYes sets this cookie to record the default button state of the corresponding category and the status of CCPA. Once the session ends the cookie is deleted.rc::aneverThis cookie is set by the Google recaptcha service to identify bots to protect the website against malicious spam attacks.rc::csessionThis cookie is set by the Google recaptcha service to identify bots to protect the website against malicious spam attacks.viewed_cookie_policy11 monthsThe cookie is set by the GDPR Cookie Consent plugin and is used to store whether or not user has consented to the use of cookies. The cookie is used to allows the paid version of the plugin to connect entries by the same user and is used for some additional features like the Form Abandonment addon.cookielawinfo-checkbox-advertisement1 yearSet by the GDPR Cookie Consent plugin, this cookie records the user consent for the cookies in the \"Advertisement\" category.cookielawinfo-checkbox-analytics11 monthsThis cookie is set by GDPR Cookie Consent plugin. The cookie is used to store the user consent for the cookies in the category \"Analytics\".cookielawinfo-checkbox-functional11 monthsThe cookie is set by GDPR cookie consent to record the user consent for the cookies in the category \"Functional\".cookielawinfo-checkbox-necessary11 monthsThis cookie is set by GDPR Cookie Consent plugin. The cookies is used to store the user consent for the cookies in the category \"Necessary\".cookielawinfo-checkbox-others11 monthsThis cookie is set by GDPR Cookie Consent plugin. The cookie is used to store the user consent for the cookies in the category \"Other.cookielawinfo-checkbox-performance11 monthsThis cookie is set by GDPR Cookie Consent plugin. The cookie is used to store the user consent for the cookies in the category \"Performance\".CookieLawInfoConsent1 yearCookieYes sets this cookie to record the default button state of the corresponding category and the status of CCPA. Once the session ends the cookie is deleted.rc::aneverThis cookie is set by the Google recaptcha service to identify bots to protect the website against malicious spam attacks.rc::csessionThis cookie is set by the Google recaptcha service to identify bots to protect the website against malicious spam attacks.viewed_cookie_policy11 monthsThe cookie is set by the GDPR Cookie Consent plugin and is used to store whether or not user has consented to the use of cookies. The cookie is used to allows the paid version of the plugin to connect entries by the same user and is used for some additional features like the Form Abandonment addon.cookielawinfo-checkbox-advertisement1 yearSet by the GDPR Cookie Consent plugin, this cookie records the user consent for the cookies in the \"Advertisement\" category.cookielawinfo-checkbox-analytics11 monthsThis cookie is set by GDPR Cookie Consent plugin. The cookie is used to store the user consent for the cookies in the category \"Analytics\".cookielawinfo-checkbox-functional11 monthsThe cookie is set by GDPR cookie consent to record the user consent for the cookies in the category \"Functional\".cookielawinfo-checkbox-necessary11 monthsThis cookie is set by GDPR Cookie Consent plugin. The cookies is used to store the user consent for the cookies in the category \"Necessary\".cookielawinfo-checkbox-others11 monthsThis cookie is set by GDPR Cookie Consent plugin. The cookie is used to store the user consent for the cookies in the category \"Other.cookielawinfo-checkbox-performance11 monthsThis cookie is set by GDPR Cookie Consent plugin. The cookie is used to store the user consent for the cookies in the category \"Performance\".CookieLawInfoConsent1 yearCookieYes sets this cookie to record the default button state of the corresponding category and the status of CCPA. Once the session ends the cookie is deleted.rc::aneverThis cookie is set by the Google recaptcha service to identify bots to protect the website against malicious spam attacks.rc::csessionThis cookie is set by the Google recaptcha service to identify bots to protect the website against malicious spam attacks.viewed_cookie_policy11 monthsThe cookie is set by the GDPR Cookie Consent plugin and is used to store whether or not user has consented to the use of cookies. The cookie is used to allows the paid version of the plugin to connect entries by the same user and is used for some additional features like the Form Abandonment addon.cookielawinfo-checkbox-advertisement1 yearSet by the GDPR Cookie Consent plugin, this cookie records the user consent for the cookies in the \"Advertisement\" category.cookielawinfo-checkbox-analytics11 monthsThis cookie is set by GDPR Cookie Consent plugin. The cookie is used to store the user consent for the cookies in the category \"Analytics\".cookielawinfo-checkbox-functional11 monthsThe cookie is set by GDPR cookie consent to record the user consent for the cookies in the category \"Functional\".cookielawinfo-checkbox-necessary11 monthsThis cookie is set by GDPR Cookie Consent plugin. The cookies is used to store the user consent for the cookies in the category \"Necessary\".cookielawinfo-checkbox-others11 monthsThis cookie is set by GDPR Cookie Consent plugin. The cookie is used to store the user consent for the cookies in the category \"Other.cookielawinfo-checkbox-performance11 monthsThis cookie is set by GDPR Cookie Consent plugin. The cookie is used to store the user consent for the cookies in the category \"Performance\".CookieLawInfoConsent1 yearCookieYes sets this cookie to record the default button state of the corresponding category and the status of CCPA. Once the session ends the cookie is deleted.rc::aneverThis cookie is set by the Google recaptcha service to identify bots to protect the website against malicious spam attacks.rc::csessionThis cookie is set by the Google recaptcha service to identify bots to protect the website against malicious spam attacks.viewed_cookie_policy11 monthsThe cookie is set by the GDPR Cookie Consent plugin and is used to store whether or not user has consented to the use of cookies. CookieDurationDescription_ga2 years\n\n\nThis cookie is a Google Analytics cookie that tracks unique users on a website by storing a random ID. CookieDurationDescription_ga2 years\n\n\nThis cookie is a Google Analytics cookie that tracks unique users on a website by storing a random ID. CookieDurationDescription_ga2 years\n\n\nThis cookie is a Google Analytics cookie that tracks unique users on a website by storing a random ID. CookieDurationDescription_ga2 years\n\n\nThis cookie is a Google Analytics cookie that tracks unique users on a website by storing a random ID. CookieDurationDescriptionVISITOR_INFO1_LIVE6 monthsYouTube sets this cookie to measure bandwidth, determining whether the user gets the new or old player interface.VISITOR_PRIVACY_METADATA6 monthsYouTube sets this cookie to store the user's cookie consent state for the current domain.YSCsessionYoutube sets this cookie to track the views of embedded videos on Youtube pages.yt.innertube::nextIdneverYouTube sets this cookie to register a unique ID to store data on what videos from YouTube the user has seen.yt.innertube::requestsneverYouTube sets this cookie to register a unique ID to store data on what videos from YouTube the user has seen. CookieDurationDescriptionVISITOR_INFO1_LIVE6 monthsYouTube sets this cookie to measure bandwidth, determining whether the user gets the new or old player interface.VISITOR_PRIVACY_METADATA6 monthsYouTube sets this cookie to store the user's cookie consent state for the current domain.YSCsessionYoutube sets this cookie to track the views of embedded videos on Youtube pages.yt.innertube::nextIdneverYouTube sets this cookie to register a unique ID to store data on what videos from YouTube the user has seen.yt.innertube::requestsneverYouTube sets this cookie to register a unique ID to store data on what videos from YouTube the user has seen. CookieDurationDescriptionVISITOR_INFO1_LIVE6 monthsYouTube sets this cookie to measure bandwidth, determining whether the user gets the new or old player interface.VISITOR_PRIVACY_METADATA6 monthsYouTube sets this cookie to store the user's cookie consent state for the current domain.YSCsessionYoutube sets this cookie to track the views of embedded videos on Youtube pages.yt.innertube::nextIdneverYouTube sets this cookie to register a unique ID to store data on what videos from YouTube the user has seen.yt.innertube::requestsneverYouTube sets this cookie to register a unique ID to store data on what videos from YouTube the user has seen. CookieDurationDescriptionVISITOR_INFO1_LIVE6 monthsYouTube sets this cookie to measure bandwidth, determining whether the user gets the new or old player interface.VISITOR_PRIVACY_METADATA6 monthsYouTube sets this cookie to store the user's cookie consent state for the current domain.YSCsessionYoutube sets this cookie to track the views of embedded videos on Youtube pages.yt.innertube::nextIdneverYouTube sets this cookie to register a unique ID to store data on what videos from YouTube the user has seen.yt.innertube::requestsneverYouTube sets this cookie to register a unique ID to store data on what videos from YouTube the user has seen. yt-remote-cast-installedsessionThe yt-remote-cast-installed cookie is used to store the user's video player preferences using embedded YouTube video.yt-remote-connected-devicesneverYouTube sets this cookie to store the user's video preferences using embedded YouTube videos.yt-remote-device-idneverYouTube sets this cookie to store the user's video preferences using embedded YouTube videos.yt-remote-fast-check-periodsessionThe yt-remote-fast-check-period cookie is used by YouTube to store the user's video player preferences for embedded YouTube videos.yt-remote-session-appsessionThe yt-remote-session-app cookie is used by YouTube to store user preferences and information about the interface of the embedded YouTube video player.yt-remote-session-namesessionThe yt-remote-session-name cookie is used by YouTube to store the user's video player preferences using embedded YouTube video.ytidb::LAST_RESULT_ENTRY_KEYneverThe cookie ytidb::LAST_RESULT_ENTRY_KEY is used by YouTube to store the last search result entry that was clicked by the user. yt-remote-cast-installedsessionThe yt-remote-cast-installed cookie is used to store the user's video player preferences using embedded YouTube video.yt-remote-connected-devicesneverYouTube sets this cookie to store the user's video preferences using embedded YouTube videos.yt-remote-device-idneverYouTube sets this cookie to store the user's video preferences using embedded YouTube videos.yt-remote-fast-check-periodsessionThe yt-remote-fast-check-period cookie is used by YouTube to store the user's video player preferences for embedded YouTube videos.yt-remote-session-appsessionThe yt-remote-session-app cookie is used by YouTube to store user preferences and information about the interface of the embedded YouTube video player.yt-remote-session-namesessionThe yt-remote-session-name cookie is used by YouTube to store the user's video player preferences using embedded YouTube video.ytidb::LAST_RESULT_ENTRY_KEYneverThe cookie ytidb::LAST_RESULT_ENTRY_KEY is used by YouTube to store the last search result entry that was clicked by the user. yt-remote-cast-installedsessionThe yt-remote-cast-installed cookie is used to store the user's video player preferences using embedded YouTube video.yt-remote-connected-devicesneverYouTube sets this cookie to store the user's video preferences using embedded YouTube videos.yt-remote-device-idneverYouTube sets this cookie to store the user's video preferences using embedded YouTube videos.yt-remote-fast-check-periodsessionThe yt-remote-fast-check-period cookie is used by YouTube to store the user's video player preferences for embedded YouTube videos.yt-remote-session-appsessionThe yt-remote-session-app cookie is used by YouTube to store user preferences and information about the interface of the embedded YouTube video player.yt-remote-session-namesessionThe yt-remote-session-name cookie is used by YouTube to store the user's video player preferences using embedded YouTube video.ytidb::LAST_RESULT_ENTRY_KEYneverThe cookie ytidb::LAST_RESULT_ENTRY_KEY is used by YouTube to store the last search result entry that was clicked by the user. yt-remote-cast-installedsessionThe yt-remote-cast-installed cookie is used to store the user's video player preferences using embedded YouTube video.yt-remote-connected-devicesneverYouTube sets this cookie to store the user's video preferences using embedded YouTube videos.yt-remote-device-idneverYouTube sets this cookie to store the user's video preferences using embedded YouTube videos.yt-remote-fast-check-periodsessionThe yt-remote-fast-check-period cookie is used by YouTube to store the user's video player preferences for embedded YouTube videos.yt-remote-session-appsessionThe yt-remote-session-app cookie is used by YouTube to store user preferences and information about the interface of the embedded YouTube video player.yt-remote-session-namesessionThe yt-remote-session-name cookie is used by YouTube to store the user's video player preferences using embedded YouTube video.ytidb::LAST_RESULT_ENTRY_KEYneverThe cookie ytidb::LAST_RESULT_ENTRY_KEY is used by YouTube to store the last search result entry that was clicked by the user. Reject All Save My Preferences Accept All \n\n\n\n                            Powered by GDPR Cookie Compliance\n\nReject All Save My Preferences Accept All \n\n\n\n                            Powered by GDPR Cookie Compliance\n\nReject All Save My Preferences Accept All \n\n\n\n                            Powered by GDPR Cookie Compliance\n\nReject All Save My Preferences Accept All \n\n\n\n                            Powered by GDPR Cookie Compliance\n\nReject All Save My Preferences Accept All\n\nReject All Save My Preferences Accept All\n\nPowered by GDPR Cookie Compliance\n\nPowered by GDPR Cookie Compliance",
  "entities": {
    "countries": [],
    "organizations": [
      "un",
      "who"
    ],
    "key_issues": [
      "challenge",
      "nation",
      "state",
      "approach",
      "policy",
      "initiative",
      "program",
      "action",
      "aid",
      "market",
      "investment",
      "un",
      "organization",
      "foundation"
    ]
  },
  "committee": "World Health Organization",
  "topic": "Regulation of pandemics and global regulations for lockdowns"
}