{
  "url": "https://www.un.org/en/our-work",
  "title": "Our Work | United Nations",
  "text": "Skip to main content\n\nOur Work\n\n\nThe United Nations coordinates its work with the funds, programmes, specialized agencies and other organizations of the UN System.\n \nThe United Nations itself is one part of the UN System. Cooperation between the UN and the other entities of the UN system is essential in order to achieve the purposes of the Organization laid out in the UN Charter.\nSince its Charter was written, the United Nations has been mandated to do new work which was not envisioned at the time of its creation. The Organization has set goals to build a more sustainable world, and it has agreed to collective action to slow down climate change.\nAs the problems facing humanity have grown, the work of the United Nations has also grown.\nUnited Nations Annual Report\n\n\n\nExplainer: What is the UN?\n\n\n\n\n\nUN's 'work plan'\nAt UN Headquarters in New York, the General Assembly, Security Council, and Economic and Social Council pass resolutions, which set what could informally be called the UN's 'work plan.'\nThe UN Secretariat carries out this work along with UN system entities.\n\n\nUN Secretariat\nThe UN Secretariat, based in New York City, has offices in Geneva, Vienna, and Nairobi.\nAlso part of the UN Secretariat are the Regional Economic Commissions in Addis Ababa, Bangkok, Beirut, Geneva, and Santiago.\n\n\nUN System\nAll of the funds, programmes, specialized agencies, and other entities of the UN system have their own budget, mandate, leadership, and headquarters. They have regional and local offices in all the main geographic areas of the world, as does the UN.\n\n\n\n\nThe United Nations and the UN system work together in five areas that can, and often do overlap.\n\n\n\n\n\n\nWhat We Do\nThe work of the United Nations covers five main areas:\n\n\n\nMaintain International Peace and Security\nProtect Human Rights\nDeliver Humanitarian Aid\nSupport Sustainable Development and Climate Action\nUphold International Law\n\n\n\nLeft to right: ©UN Photo/Marco Dormino, ©UN Photo/Mark Garten, ©OCHA/Iason Athanasiadis, ©UNEP/Patrick Kihara, ©UN Photo/Sylvain Liechti\n\n\n\n\n\n\n\n\n\n\nAs an international organization with 193 Member States, the United Nations is uniquely positioned to address and solve global issues.\n\nMore about Global Issues\n\n\nGlobal Issues\n\n\nWHAT ARE THEY?\n\t\t\t\tThese are the issues that transcend national boundaries and cannot be solved by any one country acting alone.\n\nWHY FOCUS ON THEM?\n\t\t\t\tThe United Nations focuses on these particular issues because if they are not addressed, they could negatively impact the lives of billions, slow progress towards achieving the sustainable development goals, affect the short-term and long-term environmental health of the planet on which we live, and halt human progress in the 21st century.\n\nWHICH ONES ARE RELATIVELY NEW?\n\t\t\t\tIn the more than seven decades since its creation, the United Nations has focused on new challenges, such as youth, gender equality, climate change, big data for the SDGs, and AIDS, in order to find solutions and encourage action.\n\n\n\n\n\n\n\n\n\n\n\nAfrica\n\n\n\n\n\n\n\n\n\nAgeing\n\n\n\n\n\n\n\n\n\nAIDS\n\n\n\n\n\n\n\n\n\nAtomic Energy\n\n\n\n\n\n\n\n\n\nBig Data for the SDGs\n\n\n\n\n\n\n\n\n\nChild and Youth Safety Online\n\n\n\n\n\n\n\n\n\nChildren\n\n\n\n\n\n\n\n\n\nClimate Change\n\n\n\n\n\n\n\n\n\nDecolonization\n\n\n\n\n\n\n\n\n\nDemocracy\n\n\n\n\n\n\n\n\n\nDisarmament\n\n\n\n\n\n\n\n\n\nEnding Poverty\n\n\n\n\n\n\n\n\n\nFood\n\n\n\n\n\n\n\n\n\nGender Equality\n\n\n\n\n\n\n\n\n\nHealth\n\n\n\n\n\n\n\n\n\nHuman Rights\n\n\n\n\n\n\n\n\n\nInternational Law and Justice\n\n\n\n\n\n\n\n\n\nMigration\n\n\n\n\n\n\n\n\n\nOceans and the Law of the Sea\n\n\n\n\n\n\n\n\n\nPeace and Security\n\n\n\n\n\n\n\n\n\nPopulation\n\n\n\n\n\n\n\n\n\nRefugees\n\n\n\n\n\n\n\n\n\nWater\n\n\n\n\n\n\n\n\n\nYouth\n\n\n\n\n\n\n\n\n \n\nDocuments\n\n©UNOG Library Photo\nThe UN has been publishing documents since its founding. UN documents include records of meetings and resolutions that have been passed by a legislative body, such as the General Assembly, Security Council, or the Economic and Social Council, which often contain a work mandate for the United Nations. Reports of the UN Secretary-General assess the state of the Organization and announce new work initiatives.\nExplore UN documents\n \n\n\nOfficial Languages\n\n©UN Photo/Laura Jarriel\nThere are six official languages of the UN: Arabic, Chinese, English, French, Russian, and Spanish. The correct interpretation and translation of the six languages, in both spoken and written form, is very important to the work of the Organization, as this enables clear and concise communication on issues of global importance.\nMore on the 6 official UN languages\n \n\n \n\n\n\n\n\n\nObservances\nThe existence of international days predates the establishment of the United Nations, but the UN has embraced them as a powerful advocacy tool. The UN observes designated days, weeks, years, and decades, each with a theme, or topic.\nWhy do we mark international days?\n\n\n\n\n\n\n \n\n\nInternational Days and Weeks\n\n\n \n\n\n\n\nInternational Years\n\n\n\n\nInternational Decades\n\n\n\n\nUN Anniversaries\n\n\n\n\n\n\n\n\n\n\n\n\n\n\n\n\n\n\n\n\n\n\n\n \n\n\n\n        Main Bodies   General Assembly   Security Council   Economic and Social Council   Trusteeship Council   International Court of Justice   Secretariat       Departments / Offices   New York   Geneva   Nairobi   Vienna   UN System Directory   UN System Chart   Global Leadership   UN Information Centres       Resources / Services   Emergency information   Reporting Wrongdoing   UN Journal   Documents   Guidelines for gender-inclusive language   Databases   Library   UN iLibrary   UN Chronicle   UN Yearbook   Bookshop   Publications for sale   Maps   Media Accreditation   NGO accreditation at ECOSOC   NGO accreditation at DGC   Visitors’ services   Exhibits   Procurement   Employment   Internships   Model UN   Academic Impact   UN Archives   UN Audiovisual Library   How to donate to the UN system   Information on COVID-19 (Coronavirus)   Africa Renewal   Ten ways the UN makes a difference   GA High-level week 2024       Key Documents   UN Charter   Universal Declaration of Human Rights   Convention on the Rights of the Child   Statute of the International Court of Justice   Annual Report of the Secretary-General on the Work of the Organization       News and Media   News   Press Releases   Briefings   Spokesperson   Photos   UNIfeed   UN Web TV   UN Video   Social Media   The Essential UN   Awake at Night podcast       Issues / Campaigns   Global Issues   Observances   Sustainable Development Goals   Our Common Agenda   The Summit of the Future   Climate Action   Peace and Security   Action for Peacekeeping (A4P)   Global Crisis Response Group   Call to Action for Human Rights   Disability Inclusion Strategy   Fight Racism   Hate Speech   LGBTIQ+ People   Safety of Journalists   Rule of Law   Action to Counter Terrorism   Victims of Terrorism   Children and Armed Conflict   Violence Against Children (SRSG)   Sexual Violence in Conflict   Refugees and Migrants   Action Agenda on Internal Displacement   Spotlight Initiative   Preventing Sexual Exploitation and Abuse   Prevention of Genocide and the Responsibility to Protect   The Rwanda Genocide   The Holocaust   The Question of Palestine   The Transatlantic Slave Trade   Decolonization   Messengers of Peace   Roadmap for Digital Cooperation   Digital Financing Task Force   Data Strategy   Information Integrity   Countering Disinformation   UN75: 2020 and Beyond   Women Rise for All   Stop the Red Sea Catastrophe   Black Sea Grain Initiative Joint Coordination Centre\n\nOur Work\n\n\nThe United Nations coordinates its work with the funds, programmes, specialized agencies and other organizations of the UN System.\n \nThe United Nations itself is one part of the UN System. Cooperation between the UN and the other entities of the UN system is essential in order to achieve the purposes of the Organization laid out in the UN Charter.\nSince its Charter was written, the United Nations has been mandated to do new work which was not envisioned at the time of its creation. The Organization has set goals to build a more sustainable world, and it has agreed to collective action to slow down climate change.\nAs the problems facing humanity have grown, the work of the United Nations has also grown.\nUnited Nations Annual Report\n\n\n\nExplainer: What is the UN?\n\n\n\n\n\nUN's 'work plan'\nAt UN Headquarters in New York, the General Assembly, Security Council, and Economic and Social Council pass resolutions, which set what could informally be called the UN's 'work plan.'\nThe UN Secretariat carries out this work along with UN system entities.\n\n\nUN Secretariat\nThe UN Secretariat, based in New York City, has offices in Geneva, Vienna, and Nairobi.\nAlso part of the UN Secretariat are the Regional Economic Commissions in Addis Ababa, Bangkok, Beirut, Geneva, and Santiago.\n\n\nUN System\nAll of the funds, programmes, specialized agencies, and other entities of the UN system have their own budget, mandate, leadership, and headquarters. They have regional and local offices in all the main geographic areas of the world, as does the UN.\n\n\n\n\nThe United Nations and the UN system work together in five areas that can, and often do overlap.\n\n\n\n\n\n\nWhat We Do\nThe work of the United Nations covers five main areas:\n\n\n\nMaintain International Peace and Security\nProtect Human Rights\nDeliver Humanitarian Aid\nSupport Sustainable Development and Climate Action\nUphold International Law\n\n\n\nLeft to right: ©UN Photo/Marco Dormino, ©UN Photo/Mark Garten, ©OCHA/Iason Athanasiadis, ©UNEP/Patrick Kihara, ©UN Photo/Sylvain Liechti\n\n\n\n\n\n\n\n\n\n\nAs an international organization with 193 Member States, the United Nations is uniquely positioned to address and solve global issues.\n\nMore about Global Issues\n\n\nGlobal Issues\n\n\nWHAT ARE THEY?\n\t\t\t\tThese are the issues that transcend national boundaries and cannot be solved by any one country acting alone.\n\nWHY FOCUS ON THEM?\n\t\t\t\tThe United Nations focuses on these particular issues because if they are not addressed, they could negatively impact the lives of billions, slow progress towards achieving the sustainable development goals, affect the short-term and long-term environmental health of the planet on which we live, and halt human progress in the 21st century.\n\nWHICH ONES ARE RELATIVELY NEW?\n\t\t\t\tIn the more than seven decades since its creation, the United Nations has focused on new challenges, such as youth, gender equality, climate change, big data for the SDGs, and AIDS, in order to find solutions and encourage action.\n\n\n\n\n\n\n\n\n\n\n\nAfrica\n\n\n\n\n\n\n\n\n\nAgeing\n\n\n\n\n\n\n\n\n\nAIDS\n\n\n\n\n\n\n\n\n\nAtomic Energy\n\n\n\n\n\n\n\n\n\nBig Data for the SDGs\n\n\n\n\n\n\n\n\n\nChild and Youth Safety Online\n\n\n\n\n\n\n\n\n\nChildren\n\n\n\n\n\n\n\n\n\nClimate Change\n\n\n\n\n\n\n\n\n\nDecolonization\n\n\n\n\n\n\n\n\n\nDemocracy\n\n\n\n\n\n\n\n\n\nDisarmament\n\n\n\n\n\n\n\n\n\nEnding Poverty\n\n\n\n\n\n\n\n\n\nFood\n\n\n\n\n\n\n\n\n\nGender Equality\n\n\n\n\n\n\n\n\n\nHealth\n\n\n\n\n\n\n\n\n\nHuman Rights\n\n\n\n\n\n\n\n\n\nInternational Law and Justice\n\n\n\n\n\n\n\n\n\nMigration\n\n\n\n\n\n\n\n\n\nOceans and the Law of the Sea\n\n\n\n\n\n\n\n\n\nPeace and Security\n\n\n\n\n\n\n\n\n\nPopulation\n\n\n\n\n\n\n\n\n\nRefugees\n\n\n\n\n\n\n\n\n\nWater\n\n\n\n\n\n\n\n\n\nYouth\n\n\n\n\n\n\n\n\n \n\nDocuments\n\n©UNOG Library Photo\nThe UN has been publishing documents since its founding. UN documents include records of meetings and resolutions that have been passed by a legislative body, such as the General Assembly, Security Council, or the Economic and Social Council, which often contain a work mandate for the United Nations. Reports of the UN Secretary-General assess the state of the Organization and announce new work initiatives.\nExplore UN documents\n \n\n\nOfficial Languages\n\n©UN Photo/Laura Jarriel\nThere are six official languages of the UN: Arabic, Chinese, English, French, Russian, and Spanish. The correct interpretation and translation of the six languages, in both spoken and written form, is very important to the work of the Organization, as this enables clear and concise communication on issues of global importance.\nMore on the 6 official UN languages\n \n\n \n\n\n\n\n\n\nObservances\nThe existence of international days predates the establishment of the United Nations, but the UN has embraced them as a powerful advocacy tool. The UN observes designated days, weeks, years, and decades, each with a theme, or topic.\nWhy do we mark international days?\n\n\n\n\n\n\n \n\n\nInternational Days and Weeks\n\n\n \n\n\n\n\nInternational Years\n\n\n\n\nInternational Decades\n\n\n\n\nUN Anniversaries\n\nOur Work\n\n\nThe United Nations coordinates its work with the funds, programmes, specialized agencies and other organizations of the UN System.\n \nThe United Nations itself is one part of the UN System. Cooperation between the UN and the other entities of the UN system is essential in order to achieve the purposes of the Organization laid out in the UN Charter.\nSince its Charter was written, the United Nations has been mandated to do new work which was not envisioned at the time of its creation. The Organization has set goals to build a more sustainable world, and it has agreed to collective action to slow down climate change.\nAs the problems facing humanity have grown, the work of the United Nations has also grown.\nUnited Nations Annual Report\n\n\n\nExplainer: What is the UN?\n\n\n\n\n\nUN's 'work plan'\nAt UN Headquarters in New York, the General Assembly, Security Council, and Economic and Social Council pass resolutions, which set what could informally be called the UN's 'work plan.'\nThe UN Secretariat carries out this work along with UN system entities.\n\n\nUN Secretariat\nThe UN Secretariat, based in New York City, has offices in Geneva, Vienna, and Nairobi.\nAlso part of the UN Secretariat are the Regional Economic Commissions in Addis Ababa, Bangkok, Beirut, Geneva, and Santiago.\n\n\nUN System\nAll of the funds, programmes, specialized agencies, and other entities of the UN system have their own budget, mandate, leadership, and headquarters. They have regional and local offices in all the main geographic areas of the world, as does the UN.\n\n\n\n\nThe United Nations and the UN system work together in five areas that can, and often do overlap.\n\n\n\n\n\n\nWhat We Do\nThe work of the United Nations covers five main areas:\n\n\n\nMaintain International Peace and Security\nProtect Human Rights\nDeliver Humanitarian Aid\nSupport Sustainable Development and Climate Action\nUphold International Law\n\n\n\nLeft to right: ©UN Photo/Marco Dormino, ©UN Photo/Mark Garten, ©OCHA/Iason Athanasiadis, ©UNEP/Patrick Kihara, ©UN Photo/Sylvain Liechti\n\n\n\n\n\n\n\n\n\n\nAs an international organization with 193 Member States, the United Nations is uniquely positioned to address and solve global issues.\n\nMore about Global Issues\n\n\nGlobal Issues\n\n\nWHAT ARE THEY?\n\t\t\t\tThese are the issues that transcend national boundaries and cannot be solved by any one country acting alone.\n\nWHY FOCUS ON THEM?\n\t\t\t\tThe United Nations focuses on these particular issues because if they are not addressed, they could negatively impact the lives of billions, slow progress towards achieving the sustainable development goals, affect the short-term and long-term environmental health of the planet on which we live, and halt human progress in the 21st century.\n\nWHICH ONES ARE RELATIVELY NEW?\n\t\t\t\tIn the more than seven decades since its creation, the United Nations has focused on new challenges, such as youth, gender equality, climate change, big data for the SDGs, and AIDS, in order to find solutions and encourage action.\n\n\n\n\n\n\n\n\n\n\n\nAfrica\n\n\n\n\n\n\n\n\n\nAgeing\n\n\n\n\n\n\n\n\n\nAIDS\n\n\n\n\n\n\n\n\n\nAtomic Energy\n\n\n\n\n\n\n\n\n\nBig Data for the SDGs\n\n\n\n\n\n\n\n\n\nChild and Youth Safety Online\n\n\n\n\n\n\n\n\n\nChildren\n\n\n\n\n\n\n\n\n\nClimate Change\n\n\n\n\n\n\n\n\n\nDecolonization\n\n\n\n\n\n\n\n\n\nDemocracy\n\n\n\n\n\n\n\n\n\nDisarmament\n\n\n\n\n\n\n\n\n\nEnding Poverty\n\n\n\n\n\n\n\n\n\nFood\n\n\n\n\n\n\n\n\n\nGender Equality\n\n\n\n\n\n\n\n\n\nHealth\n\n\n\n\n\n\n\n\n\nHuman Rights\n\n\n\n\n\n\n\n\n\nInternational Law and Justice\n\n\n\n\n\n\n\n\n\nMigration\n\n\n\n\n\n\n\n\n\nOceans and the Law of the Sea\n\n\n\n\n\n\n\n\n\nPeace and Security\n\n\n\n\n\n\n\n\n\nPopulation\n\n\n\n\n\n\n\n\n\nRefugees\n\n\n\n\n\n\n\n\n\nWater\n\n\n\n\n\n\n\n\n\nYouth\n\n\n\n\n\n\n\n\n \n\nDocuments\n\n©UNOG Library Photo\nThe UN has been publishing documents since its founding. UN documents include records of meetings and resolutions that have been passed by a legislative body, such as the General Assembly, Security Council, or the Economic and Social Council, which often contain a work mandate for the United Nations. Reports of the UN Secretary-General assess the state of the Organization and announce new work initiatives.\nExplore UN documents\n \n\n\nOfficial Languages\n\n©UN Photo/Laura Jarriel\nThere are six official languages of the UN: Arabic, Chinese, English, French, Russian, and Spanish. The correct interpretation and translation of the six languages, in both spoken and written form, is very important to the work of the Organization, as this enables clear and concise communication on issues of global importance.\nMore on the 6 official UN languages\n \n\n \n\n\n\n\n\n\nObservances\nThe existence of international days predates the establishment of the United Nations, but the UN has embraced them as a powerful advocacy tool. The UN observes designated days, weeks, years, and decades, each with a theme, or topic.\nWhy do we mark international days?\n\n\n\n\n\n\n \n\n\nInternational Days and Weeks\n\n\n \n\n\n\n\nInternational Years\n\n\n\n\nInternational Decades\n\n\n\n\nUN Anniversaries\n\nOur Work\n\n\nThe United Nations coordinates its work with the funds, programmes, specialized agencies and other organizations of the UN System.\n \nThe United Nations itself is one part of the UN System. Cooperation between the UN and the other entities of the UN system is essential in order to achieve the purposes of the Organization laid out in the UN Charter.\nSince its Charter was written, the United Nations has been mandated to do new work which was not envisioned at the time of its creation. The Organization has set goals to build a more sustainable world, and it has agreed to collective action to slow down climate change.\nAs the problems facing humanity have grown, the work of the United Nations has also grown.\nUnited Nations Annual Report\n\n\n\nExplainer: What is the UN?\n\n\n\n\n\nUN's 'work plan'\nAt UN Headquarters in New York, the General Assembly, Security Council, and Economic and Social Council pass resolutions, which set what could informally be called the UN's 'work plan.'\nThe UN Secretariat carries out this work along with UN system entities.\n\n\nUN Secretariat\nThe UN Secretariat, based in New York City, has offices in Geneva, Vienna, and Nairobi.\nAlso part of the UN Secretariat are the Regional Economic Commissions in Addis Ababa, Bangkok, Beirut, Geneva, and Santiago.\n\n\nUN System\nAll of the funds, programmes, specialized agencies, and other entities of the UN system have their own budget, mandate, leadership, and headquarters. They have regional and local offices in all the main geographic areas of the world, as does the UN.\n\n\n\n\nThe United Nations and the UN system work together in five areas that can, and often do overlap.\n\n\n\n\n\n\nWhat We Do\nThe work of the United Nations covers five main areas:\n\n\n\nMaintain International Peace and Security\nProtect Human Rights\nDeliver Humanitarian Aid\nSupport Sustainable Development and Climate Action\nUphold International Law\n\n\n\nLeft to right: ©UN Photo/Marco Dormino, ©UN Photo/Mark Garten, ©OCHA/Iason Athanasiadis, ©UNEP/Patrick Kihara, ©UN Photo/Sylvain Liechti\n\n\n\n\n\n\n\n\n\n\nAs an international organization with 193 Member States, the United Nations is uniquely positioned to address and solve global issues.\n\nMore about Global Issues\n\n\nGlobal Issues\n\n\nWHAT ARE THEY?\n\t\t\t\tThese are the issues that transcend national boundaries and cannot be solved by any one country acting alone.\n\nWHY FOCUS ON THEM?\n\t\t\t\tThe United Nations focuses on these particular issues because if they are not addressed, they could negatively impact the lives of billions, slow progress towards achieving the sustainable development goals, affect the short-term and long-term environmental health of the planet on which we live, and halt human progress in the 21st century.\n\nWHICH ONES ARE RELATIVELY NEW?\n\t\t\t\tIn the more than seven decades since its creation, the United Nations has focused on new challenges, such as youth, gender equality, climate change, big data for the SDGs, and AIDS, in order to find solutions and encourage action.\n\n\n\n\n\n\n\n\n\n\n\nAfrica\n\n\n\n\n\n\n\n\n\nAgeing\n\n\n\n\n\n\n\n\n\nAIDS\n\n\n\n\n\n\n\n\n\nAtomic Energy\n\n\n\n\n\n\n\n\n\nBig Data for the SDGs\n\n\n\n\n\n\n\n\n\nChild and Youth Safety Online\n\n\n\n\n\n\n\n\n\nChildren\n\n\n\n\n\n\n\n\n\nClimate Change\n\n\n\n\n\n\n\n\n\nDecolonization\n\n\n\n\n\n\n\n\n\nDemocracy\n\n\n\n\n\n\n\n\n\nDisarmament\n\n\n\n\n\n\n\n\n\nEnding Poverty\n\n\n\n\n\n\n\n\n\nFood\n\n\n\n\n\n\n\n\n\nGender Equality\n\n\n\n\n\n\n\n\n\nHealth\n\n\n\n\n\n\n\n\n\nHuman Rights\n\n\n\n\n\n\n\n\n\nInternational Law and Justice\n\n\n\n\n\n\n\n\n\nMigration\n\n\n\n\n\n\n\n\n\nOceans and the Law of the Sea\n\n\n\n\n\n\n\n\n\nPeace and Security\n\n\n\n\n\n\n\n\n\nPopulation\n\n\n\n\n\n\n\n\n\nRefugees\n\n\n\n\n\n\n\n\n\nWater\n\n\n\n\n\n\n\n\n\nYouth\n\n\n\n\n\n\n\n\n \n\nDocuments\n\n©UNOG Library Photo\nThe UN has been publishing documents since its founding. UN documents include records of meetings and resolutions that have been passed by a legislative body, such as the General Assembly, Security Council, or the Economic and Social Council, which often contain a work mandate for the United Nations. Reports of the UN Secretary-General assess the state of the Organization and announce new work initiatives.\nExplore UN documents\n \n\n\nOfficial Languages\n\n©UN Photo/Laura Jarriel\nThere are six official languages of the UN: Arabic, Chinese, English, French, Russian, and Spanish. The correct interpretation and translation of the six languages, in both spoken and written form, is very important to the work of the Organization, as this enables clear and concise communication on issues of global importance.\nMore on the 6 official UN languages\n \n\n \n\n\n\n\n\n\nObservances\nThe existence of international days predates the establishment of the United Nations, but the UN has embraced them as a powerful advocacy tool. The UN observes designated days, weeks, years, and decades, each with a theme, or topic.\nWhy do we mark international days?\n\n\n\n\n\n\n \n\n\nInternational Days and Weeks\n\n\n \n\n\n\n\nInternational Years\n\n\n\n\nInternational Decades\n\n\n\n\nUN Anniversaries\n\nOur Work\n\n\nThe United Nations coordinates its work with the funds, programmes, specialized agencies and other organizations of the UN System.\n \nThe United Nations itself is one part of the UN System. Cooperation between the UN and the other entities of the UN system is essential in order to achieve the purposes of the Organization laid out in the UN Charter.\nSince its Charter was written, the United Nations has been mandated to do new work which was not envisioned at the time of its creation. The Organization has set goals to build a more sustainable world, and it has agreed to collective action to slow down climate change.\nAs the problems facing humanity have grown, the work of the United Nations has also grown.\nUnited Nations Annual Report\n\n\n\nExplainer: What is the UN?\n\n\n\n\n\nUN's 'work plan'\nAt UN Headquarters in New York, the General Assembly, Security Council, and Economic and Social Council pass resolutions, which set what could informally be called the UN's 'work plan.'\nThe UN Secretariat carries out this work along with UN system entities.\n\n\nUN Secretariat\nThe UN Secretariat, based in New York City, has offices in Geneva, Vienna, and Nairobi.\nAlso part of the UN Secretariat are the Regional Economic Commissions in Addis Ababa, Bangkok, Beirut, Geneva, and Santiago.\n\n\nUN System\nAll of the funds, programmes, specialized agencies, and other entities of the UN system have their own budget, mandate, leadership, and headquarters. They have regional and local offices in all the main geographic areas of the world, as does the UN.\n\n\n\n\nThe United Nations and the UN system work together in five areas that can, and often do overlap.\n\n\n\n\n\n\nWhat We Do\nThe work of the United Nations covers five main areas:\n\n\n\nMaintain International Peace and Security\nProtect Human Rights\nDeliver Humanitarian Aid\nSupport Sustainable Development and Climate Action\nUphold International Law\n\n\n\nLeft to right: ©UN Photo/Marco Dormino, ©UN Photo/Mark Garten, ©OCHA/Iason Athanasiadis, ©UNEP/Patrick Kihara, ©UN Photo/Sylvain Liechti\n\n\n\n\n\n\n\n\n\n\nAs an international organization with 193 Member States, the United Nations is uniquely positioned to address and solve global issues.\n\nMore about Global Issues\n\n\nGlobal Issues\n\n\nWHAT ARE THEY?\n\t\t\t\tThese are the issues that transcend national boundaries and cannot be solved by any one country acting alone.\n\nWHY FOCUS ON THEM?\n\t\t\t\tThe United Nations focuses on these particular issues because if they are not addressed, they could negatively impact the lives of billions, slow progress towards achieving the sustainable development goals, affect the short-term and long-term environmental health of the planet on which we live, and halt human progress in the 21st century.\n\nWHICH ONES ARE RELATIVELY NEW?\n\t\t\t\tIn the more than seven decades since its creation, the United Nations has focused on new challenges, such as youth, gender equality, climate change, big data for the SDGs, and AIDS, in order to find solutions and encourage action.\n\n\n\n\n\n\n\n\n\n\n\nAfrica\n\n\n\n\n\n\n\n\n\nAgeing\n\n\n\n\n\n\n\n\n\nAIDS\n\n\n\n\n\n\n\n\n\nAtomic Energy\n\n\n\n\n\n\n\n\n\nBig Data for the SDGs\n\n\n\n\n\n\n\n\n\nChild and Youth Safety Online\n\n\n\n\n\n\n\n\n\nChildren\n\n\n\n\n\n\n\n\n\nClimate Change\n\n\n\n\n\n\n\n\n\nDecolonization\n\n\n\n\n\n\n\n\n\nDemocracy\n\n\n\n\n\n\n\n\n\nDisarmament\n\n\n\n\n\n\n\n\n\nEnding Poverty\n\n\n\n\n\n\n\n\n\nFood\n\n\n\n\n\n\n\n\n\nGender Equality\n\n\n\n\n\n\n\n\n\nHealth\n\n\n\n\n\n\n\n\n\nHuman Rights\n\n\n\n\n\n\n\n\n\nInternational Law and Justice\n\n\n\n\n\n\n\n\n\nMigration\n\n\n\n\n\n\n\n\n\nOceans and the Law of the Sea\n\n\n\n\n\n\n\n\n\nPeace and Security\n\n\n\n\n\n\n\n\n\nPopulation\n\n\n\n\n\n\n\n\n\nRefugees\n\n\n\n\n\n\n\n\n\nWater\n\n\n\n\n\n\n\n\n\nYouth\n\n\n\n\n\n\n\n\n \n\nDocuments\n\n©UNOG Library Photo\nThe UN has been publishing documents since its founding. UN documents include records of meetings and resolutions that have been passed by a legislative body, such as the General Assembly, Security Council, or the Economic and Social Council, which often contain a work mandate for the United Nations. Reports of the UN Secretary-General assess the state of the Organization and announce new work initiatives.\nExplore UN documents\n \n\n\nOfficial Languages\n\n©UN Photo/Laura Jarriel\nThere are six official languages of the UN: Arabic, Chinese, English, French, Russian, and Spanish. The correct interpretation and translation of the six languages, in both spoken and written form, is very important to the work of the Organization, as this enables clear and concise communication on issues of global importance.\nMore on the 6 official UN languages\n \n\n \n\n\n\n\n\n\nObservances\nThe existence of international days predates the establishment of the United Nations, but the UN has embraced them as a powerful advocacy tool. The UN observes designated days, weeks, years, and decades, each with a theme, or topic.\nWhy do we mark international days?\n\n\n\n\n\n\n \n\n\nInternational Days and Weeks\n\n\n \n\n\n\n\nInternational Years\n\n\n\n\nInternational Decades\n\n\n\n\nUN Anniversaries\n\nOur Work\n\n\nThe United Nations coordinates its work with the funds, programmes, specialized agencies and other organizations of the UN System.\n \nThe United Nations itself is one part of the UN System. Cooperation between the UN and the other entities of the UN system is essential in order to achieve the purposes of the Organization laid out in the UN Charter.\nSince its Charter was written, the United Nations has been mandated to do new work which was not envisioned at the time of its creation. The Organization has set goals to build a more sustainable world, and it has agreed to collective action to slow down climate change.\nAs the problems facing humanity have grown, the work of the United Nations has also grown.\nUnited Nations Annual Report\n\n\n\nExplainer: What is the UN?\n\n\n\n\n\nUN's 'work plan'\nAt UN Headquarters in New York, the General Assembly, Security Council, and Economic and Social Council pass resolutions, which set what could informally be called the UN's 'work plan.'\nThe UN Secretariat carries out this work along with UN system entities.\n\n\nUN Secretariat\nThe UN Secretariat, based in New York City, has offices in Geneva, Vienna, and Nairobi.\nAlso part of the UN Secretariat are the Regional Economic Commissions in Addis Ababa, Bangkok, Beirut, Geneva, and Santiago.\n\n\nUN System\nAll of the funds, programmes, specialized agencies, and other entities of the UN system have their own budget, mandate, leadership, and headquarters. They have regional and local offices in all the main geographic areas of the world, as does the UN.\n\n\n\n\nThe United Nations and the UN system work together in five areas that can, and often do overlap.\n\n\n\n\n\n\nWhat We Do\nThe work of the United Nations covers five main areas:\n\n\n\nMaintain International Peace and Security\nProtect Human Rights\nDeliver Humanitarian Aid\nSupport Sustainable Development and Climate Action\nUphold International Law\n\n\n\nLeft to right: ©UN Photo/Marco Dormino, ©UN Photo/Mark Garten, ©OCHA/Iason Athanasiadis, ©UNEP/Patrick Kihara, ©UN Photo/Sylvain Liechti\n\n\n\n\n\n\n\n\n\n\nAs an international organization with 193 Member States, the United Nations is uniquely positioned to address and solve global issues.\n\nMore about Global Issues\n\n\nGlobal Issues\n\n\nWHAT ARE THEY?\n\t\t\t\tThese are the issues that transcend national boundaries and cannot be solved by any one country acting alone.\n\nWHY FOCUS ON THEM?\n\t\t\t\tThe United Nations focuses on these particular issues because if they are not addressed, they could negatively impact the lives of billions, slow progress towards achieving the sustainable development goals, affect the short-term and long-term environmental health of the planet on which we live, and halt human progress in the 21st century.\n\nWHICH ONES ARE RELATIVELY NEW?\n\t\t\t\tIn the more than seven decades since its creation, the United Nations has focused on new challenges, such as youth, gender equality, climate change, big data for the SDGs, and AIDS, in order to find solutions and encourage action.\n\n\n\n\n\n\n\n\n\n\n\nAfrica\n\n\n\n\n\n\n\n\n\nAgeing\n\n\n\n\n\n\n\n\n\nAIDS\n\n\n\n\n\n\n\n\n\nAtomic Energy\n\n\n\n\n\n\n\n\n\nBig Data for the SDGs\n\n\n\n\n\n\n\n\n\nChild and Youth Safety Online\n\n\n\n\n\n\n\n\n\nChildren\n\n\n\n\n\n\n\n\n\nClimate Change\n\n\n\n\n\n\n\n\n\nDecolonization\n\n\n\n\n\n\n\n\n\nDemocracy\n\n\n\n\n\n\n\n\n\nDisarmament\n\n\n\n\n\n\n\n\n\nEnding Poverty\n\n\n\n\n\n\n\n\n\nFood\n\n\n\n\n\n\n\n\n\nGender Equality\n\n\n\n\n\n\n\n\n\nHealth\n\n\n\n\n\n\n\n\n\nHuman Rights\n\n\n\n\n\n\n\n\n\nInternational Law and Justice\n\n\n\n\n\n\n\n\n\nMigration\n\n\n\n\n\n\n\n\n\nOceans and the Law of the Sea\n\n\n\n\n\n\n\n\n\nPeace and Security\n\n\n\n\n\n\n\n\n\nPopulation\n\n\n\n\n\n\n\n\n\nRefugees\n\n\n\n\n\n\n\n\n\nWater\n\n\n\n\n\n\n\n\n\nYouth\n\n\n\n\n\n\n\n\n \n\nDocuments\n\n©UNOG Library Photo\nThe UN has been publishing documents since its founding. UN documents include records of meetings and resolutions that have been passed by a legislative body, such as the General Assembly, Security Council, or the Economic and Social Council, which often contain a work mandate for the United Nations. Reports of the UN Secretary-General assess the state of the Organization and announce new work initiatives.\nExplore UN documents\n \n\n\nOfficial Languages\n\n©UN Photo/Laura Jarriel\nThere are six official languages of the UN: Arabic, Chinese, English, French, Russian, and Spanish. The correct interpretation and translation of the six languages, in both spoken and written form, is very important to the work of the Organization, as this enables clear and concise communication on issues of global importance.\nMore on the 6 official UN languages\n \n\n \n\n\n\n\n\n\nObservances\nThe existence of international days predates the establishment of the United Nations, but the UN has embraced them as a powerful advocacy tool. The UN observes designated days, weeks, years, and decades, each with a theme, or topic.\nWhy do we mark international days?\n\n\n\n\n\n\n \n\n\nInternational Days and Weeks\n\n\n \n\n\n\n\nInternational Years\n\n\n\n\nInternational Decades\n\n\n\n\nUN Anniversaries\n\nOur Work\n\n\nThe United Nations coordinates its work with the funds, programmes, specialized agencies and other organizations of the UN System.\n \nThe United Nations itself is one part of the UN System. Cooperation between the UN and the other entities of the UN system is essential in order to achieve the purposes of the Organization laid out in the UN Charter.\nSince its Charter was written, the United Nations has been mandated to do new work which was not envisioned at the time of its creation. The Organization has set goals to build a more sustainable world, and it has agreed to collective action to slow down climate change.\nAs the problems facing humanity have grown, the work of the United Nations has also grown.\nUnited Nations Annual Report\n\n\n\nExplainer: What is the UN?\n\n\n\n\n\nUN's 'work plan'\nAt UN Headquarters in New York, the General Assembly, Security Council, and Economic and Social Council pass resolutions, which set what could informally be called the UN's 'work plan.'\nThe UN Secretariat carries out this work along with UN system entities.\n\n\nUN Secretariat\nThe UN Secretariat, based in New York City, has offices in Geneva, Vienna, and Nairobi.\nAlso part of the UN Secretariat are the Regional Economic Commissions in Addis Ababa, Bangkok, Beirut, Geneva, and Santiago.\n\n\nUN System\nAll of the funds, programmes, specialized agencies, and other entities of the UN system have their own budget, mandate, leadership, and headquarters. They have regional and local offices in all the main geographic areas of the world, as does the UN.\n\n\n\n\nThe United Nations and the UN system work together in five areas that can, and often do overlap.\n\n\n\n\n\n\nWhat We Do\nThe work of the United Nations covers five main areas:\n\n\n\nMaintain International Peace and Security\nProtect Human Rights\nDeliver Humanitarian Aid\nSupport Sustainable Development and Climate Action\nUphold International Law\n\n\n\nLeft to right: ©UN Photo/Marco Dormino, ©UN Photo/Mark Garten, ©OCHA/Iason Athanasiadis, ©UNEP/Patrick Kihara, ©UN Photo/Sylvain Liechti\n\n\n\n\n\n\n\n\n\n\nAs an international organization with 193 Member States, the United Nations is uniquely positioned to address and solve global issues.\n\nMore about Global Issues\n\n\nGlobal Issues\n\n\nWHAT ARE THEY?\n\t\t\t\tThese are the issues that transcend national boundaries and cannot be solved by any one country acting alone.\n\nWHY FOCUS ON THEM?\n\t\t\t\tThe United Nations focuses on these particular issues because if they are not addressed, they could negatively impact the lives of billions, slow progress towards achieving the sustainable development goals, affect the short-term and long-term environmental health of the planet on which we live, and halt human progress in the 21st century.\n\nWHICH ONES ARE RELATIVELY NEW?\n\t\t\t\tIn the more than seven decades since its creation, the United Nations has focused on new challenges, such as youth, gender equality, climate change, big data for the SDGs, and AIDS, in order to find solutions and encourage action.\n\n\n\n\n\n\n\n\n\n\n\nAfrica\n\n\n\n\n\n\n\n\n\nAgeing\n\n\n\n\n\n\n\n\n\nAIDS\n\n\n\n\n\n\n\n\n\nAtomic Energy\n\n\n\n\n\n\n\n\n\nBig Data for the SDGs\n\n\n\n\n\n\n\n\n\nChild and Youth Safety Online\n\n\n\n\n\n\n\n\n\nChildren\n\n\n\n\n\n\n\n\n\nClimate Change\n\n\n\n\n\n\n\n\n\nDecolonization\n\n\n\n\n\n\n\n\n\nDemocracy\n\n\n\n\n\n\n\n\n\nDisarmament\n\n\n\n\n\n\n\n\n\nEnding Poverty\n\n\n\n\n\n\n\n\n\nFood\n\n\n\n\n\n\n\n\n\nGender Equality\n\n\n\n\n\n\n\n\n\nHealth\n\n\n\n\n\n\n\n\n\nHuman Rights\n\n\n\n\n\n\n\n\n\nInternational Law and Justice\n\n\n\n\n\n\n\n\n\nMigration\n\n\n\n\n\n\n\n\n\nOceans and the Law of the Sea\n\n\n\n\n\n\n\n\n\nPeace and Security\n\n\n\n\n\n\n\n\n\nPopulation\n\n\n\n\n\n\n\n\n\nRefugees\n\n\n\n\n\n\n\n\n\nWater\n\n\n\n\n\n\n\n\n\nYouth\n\n\n\n\n\n\n\n\n \n\nDocuments\n\n©UNOG Library Photo\nThe UN has been publishing documents since its founding. UN documents include records of meetings and resolutions that have been passed by a legislative body, such as the General Assembly, Security Council, or the Economic and Social Council, which often contain a work mandate for the United Nations. Reports of the UN Secretary-General assess the state of the Organization and announce new work initiatives.\nExplore UN documents\n \n\n\nOfficial Languages\n\n©UN Photo/Laura Jarriel\nThere are six official languages of the UN: Arabic, Chinese, English, French, Russian, and Spanish. The correct interpretation and translation of the six languages, in both spoken and written form, is very important to the work of the Organization, as this enables clear and concise communication on issues of global importance.\nMore on the 6 official UN languages\n \n\n \n\n\n\n\n\n\nObservances\nThe existence of international days predates the establishment of the United Nations, but the UN has embraced them as a powerful advocacy tool. The UN observes designated days, weeks, years, and decades, each with a theme, or topic.\nWhy do we mark international days?\n\n\n\n\n\n\n \n\n\nInternational Days and Weeks\n\n\n \n\n\n\n\nInternational Years\n\n\n\n\nInternational Decades\n\n\n\n\nUN Anniversaries\n\nOur Work\n\n\nThe United Nations coordinates its work with the funds, programmes, specialized agencies and other organizations of the UN System.\n \nThe United Nations itself is one part of the UN System. Cooperation between the UN and the other entities of the UN system is essential in order to achieve the purposes of the Organization laid out in the UN Charter.\nSince its Charter was written, the United Nations has been mandated to do new work which was not envisioned at the time of its creation. The Organization has set goals to build a more sustainable world, and it has agreed to collective action to slow down climate change.\nAs the problems facing humanity have grown, the work of the United Nations has also grown.\nUnited Nations Annual Report\n\n\n\nExplainer: What is the UN?\n\n\n\n\n\nUN's 'work plan'\nAt UN Headquarters in New York, the General Assembly, Security Council, and Economic and Social Council pass resolutions, which set what could informally be called the UN's 'work plan.'\nThe UN Secretariat carries out this work along with UN system entities.\n\n\nUN Secretariat\nThe UN Secretariat, based in New York City, has offices in Geneva, Vienna, and Nairobi.\nAlso part of the UN Secretariat are the Regional Economic Commissions in Addis Ababa, Bangkok, Beirut, Geneva, and Santiago.\n\n\nUN System\nAll of the funds, programmes, specialized agencies, and other entities of the UN system have their own budget, mandate, leadership, and headquarters. They have regional and local offices in all the main geographic areas of the world, as does the UN.\n\n\n\n\nThe United Nations and the UN system work together in five areas that can, and often do overlap.\n\n\n\n\n\n\nWhat We Do\nThe work of the United Nations covers five main areas:\n\n\n\nMaintain International Peace and Security\nProtect Human Rights\nDeliver Humanitarian Aid\nSupport Sustainable Development and Climate Action\nUphold International Law\n\n\n\nLeft to right: ©UN Photo/Marco Dormino, ©UN Photo/Mark Garten, ©OCHA/Iason Athanasiadis, ©UNEP/Patrick Kihara, ©UN Photo/Sylvain Liechti\n\n\n\n\n\n\n\n\n\n\nAs an international organization with 193 Member States, the United Nations is uniquely positioned to address and solve global issues.\n\nMore about Global Issues\n\n\nGlobal Issues\n\n\nWHAT ARE THEY?\n\t\t\t\tThese are the issues that transcend national boundaries and cannot be solved by any one country acting alone.\n\nWHY FOCUS ON THEM?\n\t\t\t\tThe United Nations focuses on these particular issues because if they are not addressed, they could negatively impact the lives of billions, slow progress towards achieving the sustainable development goals, affect the short-term and long-term environmental health of the planet on which we live, and halt human progress in the 21st century.\n\nWHICH ONES ARE RELATIVELY NEW?\n\t\t\t\tIn the more than seven decades since its creation, the United Nations has focused on new challenges, such as youth, gender equality, climate change, big data for the SDGs, and AIDS, in order to find solutions and encourage action.\n\n\n\n\n\n\n\n\n\n\n\nAfrica\n\n\n\n\n\n\n\n\n\nAgeing\n\n\n\n\n\n\n\n\n\nAIDS\n\n\n\n\n\n\n\n\n\nAtomic Energy\n\n\n\n\n\n\n\n\n\nBig Data for the SDGs\n\n\n\n\n\n\n\n\n\nChild and Youth Safety Online\n\n\n\n\n\n\n\n\n\nChildren\n\n\n\n\n\n\n\n\n\nClimate Change\n\n\n\n\n\n\n\n\n\nDecolonization\n\n\n\n\n\n\n\n\n\nDemocracy\n\n\n\n\n\n\n\n\n\nDisarmament\n\n\n\n\n\n\n\n\n\nEnding Poverty\n\n\n\n\n\n\n\n\n\nFood\n\n\n\n\n\n\n\n\n\nGender Equality\n\n\n\n\n\n\n\n\n\nHealth\n\n\n\n\n\n\n\n\n\nHuman Rights\n\n\n\n\n\n\n\n\n\nInternational Law and Justice\n\n\n\n\n\n\n\n\n\nMigration\n\n\n\n\n\n\n\n\n\nOceans and the Law of the Sea\n\n\n\n\n\n\n\n\n\nPeace and Security\n\n\n\n\n\n\n\n\n\nPopulation\n\n\n\n\n\n\n\n\n\nRefugees\n\n\n\n\n\n\n\n\n\nWater\n\n\n\n\n\n\n\n\n\nYouth\n\n\n\n\n\n\n\n\n \n\nDocuments\n\n©UNOG Library Photo\nThe UN has been publishing documents since its founding. UN documents include records of meetings and resolutions that have been passed by a legislative body, such as the General Assembly, Security Council, or the Economic and Social Council, which often contain a work mandate for the United Nations. Reports of the UN Secretary-General assess the state of the Organization and announce new work initiatives.\nExplore UN documents\n \n\n\nOfficial Languages\n\n©UN Photo/Laura Jarriel\nThere are six official languages of the UN: Arabic, Chinese, English, French, Russian, and Spanish. The correct interpretation and translation of the six languages, in both spoken and written form, is very important to the work of the Organization, as this enables clear and concise communication on issues of global importance.\nMore on the 6 official UN languages\n \n\n \n\n\n\n\n\n\nObservances\nThe existence of international days predates the establishment of the United Nations, but the UN has embraced them as a powerful advocacy tool. The UN observes designated days, weeks, years, and decades, each with a theme, or topic.\nWhy do we mark international days?\n\n\n\n\n\n\n \n\n\nInternational Days and Weeks\n\n\n \n\n\n\n\nInternational Years\n\n\n\n\nInternational Decades\n\n\n\n\nUN Anniversaries\n\nOur Work\n\n\nThe United Nations coordinates its work with the funds, programmes, specialized agencies and other organizations of the UN System.\n \nThe United Nations itself is one part of the UN System. Cooperation between the UN and the other entities of the UN system is essential in order to achieve the purposes of the Organization laid out in the UN Charter.\nSince its Charter was written, the United Nations has been mandated to do new work which was not envisioned at the time of its creation. The Organization has set goals to build a more sustainable world, and it has agreed to collective action to slow down climate change.\nAs the problems facing humanity have grown, the work of the United Nations has also grown.\nUnited Nations Annual Report\n\n\n\nExplainer: What is the UN?\n\n\n\n\n\nUN's 'work plan'\nAt UN Headquarters in New York, the General Assembly, Security Council, and Economic and Social Council pass resolutions, which set what could informally be called the UN's 'work plan.'\nThe UN Secretariat carries out this work along with UN system entities.\n\n\nUN Secretariat\nThe UN Secretariat, based in New York City, has offices in Geneva, Vienna, and Nairobi.\nAlso part of the UN Secretariat are the Regional Economic Commissions in Addis Ababa, Bangkok, Beirut, Geneva, and Santiago.\n\n\nUN System\nAll of the funds, programmes, specialized agencies, and other entities of the UN system have their own budget, mandate, leadership, and headquarters. They have regional and local offices in all the main geographic areas of the world, as does the UN.\n\n\n\n\nThe United Nations and the UN system work together in five areas that can, and often do overlap.\n\n\n\n\n\n\nWhat We Do\nThe work of the United Nations covers five main areas:\n\n\n\nMaintain International Peace and Security\nProtect Human Rights\nDeliver Humanitarian Aid\nSupport Sustainable Development and Climate Action\nUphold International Law\n\n\n\nLeft to right: ©UN Photo/Marco Dormino, ©UN Photo/Mark Garten, ©OCHA/Iason Athanasiadis, ©UNEP/Patrick Kihara, ©UN Photo/Sylvain Liechti\n\n\n\n\n\n\n\n\n\n\nAs an international organization with 193 Member States, the United Nations is uniquely positioned to address and solve global issues.\n\nMore about Global Issues\n\n\nGlobal Issues\n\n\nWHAT ARE THEY?\n\t\t\t\tThese are the issues that transcend national boundaries and cannot be solved by any one country acting alone.\n\nWHY FOCUS ON THEM?\n\t\t\t\tThe United Nations focuses on these particular issues because if they are not addressed, they could negatively impact the lives of billions, slow progress towards achieving the sustainable development goals, affect the short-term and long-term environmental health of the planet on which we live, and halt human progress in the 21st century.\n\nWHICH ONES ARE RELATIVELY NEW?\n\t\t\t\tIn the more than seven decades since its creation, the United Nations has focused on new challenges, such as youth, gender equality, climate change, big data for the SDGs, and AIDS, in order to find solutions and encourage action.\n\n\n\n\n\n\n\n\n\n\n\nAfrica\n\n\n\n\n\n\n\n\n\nAgeing\n\n\n\n\n\n\n\n\n\nAIDS\n\n\n\n\n\n\n\n\n\nAtomic Energy\n\n\n\n\n\n\n\n\n\nBig Data for the SDGs\n\n\n\n\n\n\n\n\n\nChild and Youth Safety Online\n\n\n\n\n\n\n\n\n\nChildren\n\n\n\n\n\n\n\n\n\nClimate Change\n\n\n\n\n\n\n\n\n\nDecolonization\n\n\n\n\n\n\n\n\n\nDemocracy\n\n\n\n\n\n\n\n\n\nDisarmament\n\n\n\n\n\n\n\n\n\nEnding Poverty\n\n\n\n\n\n\n\n\n\nFood\n\n\n\n\n\n\n\n\n\nGender Equality\n\n\n\n\n\n\n\n\n\nHealth\n\n\n\n\n\n\n\n\n\nHuman Rights\n\n\n\n\n\n\n\n\n\nInternational Law and Justice\n\n\n\n\n\n\n\n\n\nMigration\n\n\n\n\n\n\n\n\n\nOceans and the Law of the Sea\n\n\n\n\n\n\n\n\n\nPeace and Security\n\n\n\n\n\n\n\n\n\nPopulation\n\n\n\n\n\n\n\n\n\nRefugees\n\n\n\n\n\n\n\n\n\nWater\n\n\n\n\n\n\n\n\n\nYouth\n\n\n\n\n\n\n\n\n \n\nDocuments\n\n©UNOG Library Photo\nThe UN has been publishing documents since its founding. UN documents include records of meetings and resolutions that have been passed by a legislative body, such as the General Assembly, Security Council, or the Economic and Social Council, which often contain a work mandate for the United Nations. Reports of the UN Secretary-General assess the state of the Organization and announce new work initiatives.\nExplore UN documents\n \n\n\nOfficial Languages\n\n©UN Photo/Laura Jarriel\nThere are six official languages of the UN: Arabic, Chinese, English, French, Russian, and Spanish. The correct interpretation and translation of the six languages, in both spoken and written form, is very important to the work of the Organization, as this enables clear and concise communication on issues of global importance.\nMore on the 6 official UN languages\n \n\n \n\n\n\n\n\n\nObservances\nThe existence of international days predates the establishment of the United Nations, but the UN has embraced them as a powerful advocacy tool. The UN observes designated days, weeks, years, and decades, each with a theme, or topic.\nWhy do we mark international days?\n\n\n\n\n\n\n \n\n\nInternational Days and Weeks\n\n\n \n\n\n\n\nInternational Years\n\n\n\n\nInternational Decades\n\n\n\n\nUN Anniversaries\n\nOur Work\n\n\nThe United Nations coordinates its work with the funds, programmes, specialized agencies and other organizations of the UN System.\n \nThe United Nations itself is one part of the UN System. Cooperation between the UN and the other entities of the UN system is essential in order to achieve the purposes of the Organization laid out in the UN Charter.\nSince its Charter was written, the United Nations has been mandated to do new work which was not envisioned at the time of its creation. The Organization has set goals to build a more sustainable world, and it has agreed to collective action to slow down climate change.\nAs the problems facing humanity have grown, the work of the United Nations has also grown.\nUnited Nations Annual Report\n\n\n\nExplainer: What is the UN?\n\n\n\n\n\nUN's 'work plan'\nAt UN Headquarters in New York, the General Assembly, Security Council, and Economic and Social Council pass resolutions, which set what could informally be called the UN's 'work plan.'\nThe UN Secretariat carries out this work along with UN system entities.\n\n\nUN Secretariat\nThe UN Secretariat, based in New York City, has offices in Geneva, Vienna, and Nairobi.\nAlso part of the UN Secretariat are the Regional Economic Commissions in Addis Ababa, Bangkok, Beirut, Geneva, and Santiago.\n\n\nUN System\nAll of the funds, programmes, specialized agencies, and other entities of the UN system have their own budget, mandate, leadership, and headquarters. They have regional and local offices in all the main geographic areas of the world, as does the UN.\n\n\n\n\nThe United Nations and the UN system work together in five areas that can, and often do overlap.\n\n\n\n\n\n\nWhat We Do\nThe work of the United Nations covers five main areas:\n\n\n\nMaintain International Peace and Security\nProtect Human Rights\nDeliver Humanitarian Aid\nSupport Sustainable Development and Climate Action\nUphold International Law\n\n\n\nLeft to right: ©UN Photo/Marco Dormino, ©UN Photo/Mark Garten, ©OCHA/Iason Athanasiadis, ©UNEP/Patrick Kihara, ©UN Photo/Sylvain Liechti\n\n\n\n\n\n\n\n\n\n\nAs an international organization with 193 Member States, the United Nations is uniquely positioned to address and solve global issues.\n\nMore about Global Issues\n\n\nGlobal Issues\n\n\nWHAT ARE THEY?\n\t\t\t\tThese are the issues that transcend national boundaries and cannot be solved by any one country acting alone.\n\nWHY FOCUS ON THEM?\n\t\t\t\tThe United Nations focuses on these particular issues because if they are not addressed, they could negatively impact the lives of billions, slow progress towards achieving the sustainable development goals, affect the short-term and long-term environmental health of the planet on which we live, and halt human progress in the 21st century.\n\nWHICH ONES ARE RELATIVELY NEW?\n\t\t\t\tIn the more than seven decades since its creation, the United Nations has focused on new challenges, such as youth, gender equality, climate change, big data for the SDGs, and AIDS, in order to find solutions and encourage action.\n\n\n\n\n\n\n\n\n\n\n\nAfrica\n\n\n\n\n\n\n\n\n\nAgeing\n\n\n\n\n\n\n\n\n\nAIDS\n\n\n\n\n\n\n\n\n\nAtomic Energy\n\n\n\n\n\n\n\n\n\nBig Data for the SDGs\n\n\n\n\n\n\n\n\n\nChild and Youth Safety Online\n\n\n\n\n\n\n\n\n\nChildren\n\n\n\n\n\n\n\n\n\nClimate Change\n\n\n\n\n\n\n\n\n\nDecolonization\n\n\n\n\n\n\n\n\n\nDemocracy\n\n\n\n\n\n\n\n\n\nDisarmament\n\n\n\n\n\n\n\n\n\nEnding Poverty\n\n\n\n\n\n\n\n\n\nFood\n\n\n\n\n\n\n\n\n\nGender Equality\n\n\n\n\n\n\n\n\n\nHealth\n\n\n\n\n\n\n\n\n\nHuman Rights\n\n\n\n\n\n\n\n\n\nInternational Law and Justice\n\n\n\n\n\n\n\n\n\nMigration\n\n\n\n\n\n\n\n\n\nOceans and the Law of the Sea\n\n\n\n\n\n\n\n\n\nPeace and Security\n\n\n\n\n\n\n\n\n\nPopulation\n\n\n\n\n\n\n\n\n\nRefugees\n\n\n\n\n\n\n\n\n\nWater\n\n\n\n\n\n\n\n\n\nYouth\n\n\n\n\n\n\n\n\n \n\nDocuments\n\n©UNOG Library Photo\nThe UN has been publishing documents since its founding. UN documents include records of meetings and resolutions that have been passed by a legislative body, such as the General Assembly, Security Council, or the Economic and Social Council, which often contain a work mandate for the United Nations. Reports of the UN Secretary-General assess the state of the Organization and announce new work initiatives.\nExplore UN documents\n \n\n\nOfficial Languages\n\n©UN Photo/Laura Jarriel\nThere are six official languages of the UN: Arabic, Chinese, English, French, Russian, and Spanish. The correct interpretation and translation of the six languages, in both spoken and written form, is very important to the work of the Organization, as this enables clear and concise communication on issues of global importance.\nMore on the 6 official UN languages\n \n\n \n\n\n\n\n\n\nObservances\nThe existence of international days predates the establishment of the United Nations, but the UN has embraced them as a powerful advocacy tool. The UN observes designated days, weeks, years, and decades, each with a theme, or topic.\nWhy do we mark international days?\n\n\n\n\n\n\n \n\n\nInternational Days and Weeks\n\n\n \n\n\n\n\nInternational Years\n\n\n\n\nInternational Decades\n\n\n\n\nUN Anniversaries\n\nOur Work\n\n\nThe United Nations coordinates its work with the funds, programmes, specialized agencies and other organizations of the UN System.\n \nThe United Nations itself is one part of the UN System. Cooperation between the UN and the other entities of the UN system is essential in order to achieve the purposes of the Organization laid out in the UN Charter.\nSince its Charter was written, the United Nations has been mandated to do new work which was not envisioned at the time of its creation. The Organization has set goals to build a more sustainable world, and it has agreed to collective action to slow down climate change.\nAs the problems facing humanity have grown, the work of the United Nations has also grown.\nUnited Nations Annual Report\n\n\n\nExplainer: What is the UN?\n\n\n\n\n\nUN's 'work plan'\nAt UN Headquarters in New York, the General Assembly, Security Council, and Economic and Social Council pass resolutions, which set what could informally be called the UN's 'work plan.'\nThe UN Secretariat carries out this work along with UN system entities.\n\n\nUN Secretariat\nThe UN Secretariat, based in New York City, has offices in Geneva, Vienna, and Nairobi.\nAlso part of the UN Secretariat are the Regional Economic Commissions in Addis Ababa, Bangkok, Beirut, Geneva, and Santiago.\n\n\nUN System\nAll of the funds, programmes, specialized agencies, and other entities of the UN system have their own budget, mandate, leadership, and headquarters. They have regional and local offices in all the main geographic areas of the world, as does the UN.\n\n\n\n\nThe United Nations and the UN system work together in five areas that can, and often do overlap.\n\n\n\n\n\n\nWhat We Do\nThe work of the United Nations covers five main areas:\n\n\n\nMaintain International Peace and Security\nProtect Human Rights\nDeliver Humanitarian Aid\nSupport Sustainable Development and Climate Action\nUphold International Law\n\n\n\nLeft to right: ©UN Photo/Marco Dormino, ©UN Photo/Mark Garten, ©OCHA/Iason Athanasiadis, ©UNEP/Patrick Kihara, ©UN Photo/Sylvain Liechti\n\n\n\n\n\n\n\n\n\n\nAs an international organization with 193 Member States, the United Nations is uniquely positioned to address and solve global issues.\n\nMore about Global Issues\n\n\nGlobal Issues\n\n\nWHAT ARE THEY?\n\t\t\t\tThese are the issues that transcend national boundaries and cannot be solved by any one country acting alone.\n\nWHY FOCUS ON THEM?\n\t\t\t\tThe United Nations focuses on these particular issues because if they are not addressed, they could negatively impact the lives of billions, slow progress towards achieving the sustainable development goals, affect the short-term and long-term environmental health of the planet on which we live, and halt human progress in the 21st century.\n\nWHICH ONES ARE RELATIVELY NEW?\n\t\t\t\tIn the more than seven decades since its creation, the United Nations has focused on new challenges, such as youth, gender equality, climate change, big data for the SDGs, and AIDS, in order to find solutions and encourage action.\n\n\n\n\n\n\n\n\n\n\n\nAfrica\n\n\n\n\n\n\n\n\n\nAgeing\n\n\n\n\n\n\n\n\n\nAIDS\n\n\n\n\n\n\n\n\n\nAtomic Energy\n\n\n\n\n\n\n\n\n\nBig Data for the SDGs\n\n\n\n\n\n\n\n\n\nChild and Youth Safety Online\n\n\n\n\n\n\n\n\n\nChildren\n\n\n\n\n\n\n\n\n\nClimate Change\n\n\n\n\n\n\n\n\n\nDecolonization\n\n\n\n\n\n\n\n\n\nDemocracy\n\n\n\n\n\n\n\n\n\nDisarmament\n\n\n\n\n\n\n\n\n\nEnding Poverty\n\n\n\n\n\n\n\n\n\nFood\n\n\n\n\n\n\n\n\n\nGender Equality\n\n\n\n\n\n\n\n\n\nHealth\n\n\n\n\n\n\n\n\n\nHuman Rights\n\n\n\n\n\n\n\n\n\nInternational Law and Justice\n\n\n\n\n\n\n\n\n\nMigration\n\n\n\n\n\n\n\n\n\nOceans and the Law of the Sea\n\n\n\n\n\n\n\n\n\nPeace and Security\n\n\n\n\n\n\n\n\n\nPopulation\n\n\n\n\n\n\n\n\n\nRefugees\n\n\n\n\n\n\n\n\n\nWater\n\n\n\n\n\n\n\n\n\nYouth\n\n\n\n\n\n\n\n\n \n\nDocuments\n\n©UNOG Library Photo\nThe UN has been publishing documents since its founding. UN documents include records of meetings and resolutions that have been passed by a legislative body, such as the General Assembly, Security Council, or the Economic and Social Council, which often contain a work mandate for the United Nations. Reports of the UN Secretary-General assess the state of the Organization and announce new work initiatives.\nExplore UN documents\n \n\n\nOfficial Languages\n\n©UN Photo/Laura Jarriel\nThere are six official languages of the UN: Arabic, Chinese, English, French, Russian, and Spanish. The correct interpretation and translation of the six languages, in both spoken and written form, is very important to the work of the Organization, as this enables clear and concise communication on issues of global importance.\nMore on the 6 official UN languages\n \n\n \n\n\n\n\n\n\nObservances\nThe existence of international days predates the establishment of the United Nations, but the UN has embraced them as a powerful advocacy tool. The UN observes designated days, weeks, years, and decades, each with a theme, or topic.\nWhy do we mark international days?\n\n\n\n\n\n\n \n\n\nInternational Days and Weeks\n\n\n \n\n\n\n\nInternational Years\n\n\n\n\nInternational Decades\n\n\n\n\nUN Anniversaries\n\nThe United Nations coordinates its work with the funds, programmes, specialized agencies and other organizations of the UN System.\n \nThe United Nations itself is one part of the UN System. Cooperation between the UN and the other entities of the UN system is essential in order to achieve the purposes of the Organization laid out in the UN Charter.\nSince its Charter was written, the United Nations has been mandated to do new work which was not envisioned at the time of its creation. The Organization has set goals to build a more sustainable world, and it has agreed to collective action to slow down climate change.\nAs the problems facing humanity have grown, the work of the United Nations has also grown.\nUnited Nations Annual Report\n\n\n\nExplainer: What is the UN?\n\nThe United Nations coordinates its work with the funds, programmes, specialized agencies and other organizations of the UN System.\n \nThe United Nations itself is one part of the UN System. Cooperation between the UN and the other entities of the UN system is essential in order to achieve the purposes of the Organization laid out in the UN Charter.\nSince its Charter was written, the United Nations has been mandated to do new work which was not envisioned at the time of its creation. The Organization has set goals to build a more sustainable world, and it has agreed to collective action to slow down climate change.\nAs the problems facing humanity have grown, the work of the United Nations has also grown.\nUnited Nations Annual Report\n\nThe United Nations coordinates its work with the funds, programmes, specialized agencies and other organizations of the UN System.\n\nThe United Nations itself is one part of the UN System. Cooperation between the UN and the other entities of the UN system is essential in order to achieve the purposes of the Organization laid out in the UN Charter.\n\nSince its Charter was written, the United Nations has been mandated to do new work which was not envisioned at the time of its creation. The Organization has set goals to build a more sustainable world, and it has agreed to collective action to slow down climate change.\n\nAs the problems facing humanity have grown, the work of the United Nations has also grown.\n\nUnited Nations Annual Report\n\nExplainer: What is the UN?\n\nExplainer: What is the UN?\n\nUN's 'work plan'\nAt UN Headquarters in New York, the General Assembly, Security Council, and Economic and Social Council pass resolutions, which set what could informally be called the UN's 'work plan.'\nThe UN Secretariat carries out this work along with UN system entities.\n\n\nUN Secretariat\nThe UN Secretariat, based in New York City, has offices in Geneva, Vienna, and Nairobi.\nAlso part of the UN Secretariat are the Regional Economic Commissions in Addis Ababa, Bangkok, Beirut, Geneva, and Santiago.\n\n\nUN System\nAll of the funds, programmes, specialized agencies, and other entities of the UN system have their own budget, mandate, leadership, and headquarters. They have regional and local offices in all the main geographic areas of the world, as does the UN.\n\n\n\n\nThe United Nations and the UN system work together in five areas that can, and often do overlap.\n\nUN's 'work plan'\nAt UN Headquarters in New York, the General Assembly, Security Council, and Economic and Social Council pass resolutions, which set what could informally be called the UN's 'work plan.'\nThe UN Secretariat carries out this work along with UN system entities.\n\n\nUN Secretariat\nThe UN Secretariat, based in New York City, has offices in Geneva, Vienna, and Nairobi.\nAlso part of the UN Secretariat are the Regional Economic Commissions in Addis Ababa, Bangkok, Beirut, Geneva, and Santiago.\n\n\nUN System\nAll of the funds, programmes, specialized agencies, and other entities of the UN system have their own budget, mandate, leadership, and headquarters. They have regional and local offices in all the main geographic areas of the world, as does the UN.\n\nUN's 'work plan'\nAt UN Headquarters in New York, the General Assembly, Security Council, and Economic and Social Council pass resolutions, which set what could informally be called the UN's 'work plan.'\nThe UN Secretariat carries out this work along with UN system entities.\n\nUN's 'work plan'\n\nAt UN Headquarters in New York, the General Assembly, Security Council, and Economic and Social Council pass resolutions, which set what could informally be called the UN's 'work plan.'\n\nThe UN Secretariat carries out this work along with UN system entities.\n\nUN Secretariat\nThe UN Secretariat, based in New York City, has offices in Geneva, Vienna, and Nairobi.\nAlso part of the UN Secretariat are the Regional Economic Commissions in Addis Ababa, Bangkok, Beirut, Geneva, and Santiago.\n\nUN Secretariat\n\nThe UN Secretariat, based in New York City, has offices in Geneva, Vienna, and Nairobi.\n\nAlso part of the UN Secretariat are the Regional Economic Commissions in Addis Ababa, Bangkok, Beirut, Geneva, and Santiago.\n\nUN System\nAll of the funds, programmes, specialized agencies, and other entities of the UN system have their own budget, mandate, leadership, and headquarters. They have regional and local offices in all the main geographic areas of the world, as does the UN.\n\nUN System\n\nAll of the funds, programmes, specialized agencies, and other entities of the UN system have their own budget, mandate, leadership, and headquarters. They have regional and local offices in all the main geographic areas of the world, as does the UN.\n\nThe United Nations and the UN system work together in five areas that can, and often do overlap.\n\nThe United Nations and the UN system work together in five areas that can, and often do overlap.\n\nWhat We Do\nThe work of the United Nations covers five main areas:\n\n\n\nMaintain International Peace and Security\nProtect Human Rights\nDeliver Humanitarian Aid\nSupport Sustainable Development and Climate Action\nUphold International Law\n\n\n\nLeft to right: ©UN Photo/Marco Dormino, ©UN Photo/Mark Garten, ©OCHA/Iason Athanasiadis, ©UNEP/Patrick Kihara, ©UN Photo/Sylvain Liechti\n\nWhat We Do\nThe work of the United Nations covers five main areas:\n\n\n\nMaintain International Peace and Security\nProtect Human Rights\nDeliver Humanitarian Aid\nSupport Sustainable Development and Climate Action\nUphold International Law\n\n\n\nLeft to right: ©UN Photo/Marco Dormino, ©UN Photo/Mark Garten, ©OCHA/Iason Athanasiadis, ©UNEP/Patrick Kihara, ©UN Photo/Sylvain Liechti\n\nWhat We Do\nThe work of the United Nations covers five main areas:\n\n\n\nMaintain International Peace and Security\nProtect Human Rights\nDeliver Humanitarian Aid\nSupport Sustainable Development and Climate Action\nUphold International Law\n\n\n\nLeft to right: ©UN Photo/Marco Dormino, ©UN Photo/Mark Garten, ©OCHA/Iason Athanasiadis, ©UNEP/Patrick Kihara, ©UN Photo/Sylvain Liechti\n\nThe work of the United Nations covers five main areas:\n\nMaintain International Peace and Security\nProtect Human Rights\nDeliver Humanitarian Aid\nSupport Sustainable Development and Climate Action\nUphold International Law\n\n\n\nLeft to right: ©UN Photo/Marco Dormino, ©UN Photo/Mark Garten, ©OCHA/Iason Athanasiadis, ©UNEP/Patrick Kihara, ©UN Photo/Sylvain Liechti\n\nMaintain International Peace and Security\nProtect Human Rights\nDeliver Humanitarian Aid\nSupport Sustainable Development and Climate Action\nUphold International Law\n\nLeft to right: ©UN Photo/Marco Dormino, ©UN Photo/Mark Garten, ©OCHA/Iason Athanasiadis, ©UNEP/Patrick Kihara, ©UN Photo/Sylvain Liechti\n\nLeft to right: ©UN Photo/Marco Dormino, ©UN Photo/Mark Garten, ©OCHA/Iason Athanasiadis, ©UNEP/Patrick Kihara, ©UN Photo/Sylvain Liechti\n\nAs an international organization with 193 Member States, the United Nations is uniquely positioned to address and solve global issues.\n\nMore about Global Issues\n\n\nGlobal Issues\n\n\nWHAT ARE THEY?\n\t\t\t\tThese are the issues that transcend national boundaries and cannot be solved by any one country acting alone.\n\nWHY FOCUS ON THEM?\n\t\t\t\tThe United Nations focuses on these particular issues because if they are not addressed, they could negatively impact the lives of billions, slow progress towards achieving the sustainable development goals, affect the short-term and long-term environmental health of the planet on which we live, and halt human progress in the 21st century.\n\nWHICH ONES ARE RELATIVELY NEW?\n\t\t\t\tIn the more than seven decades since its creation, the United Nations has focused on new challenges, such as youth, gender equality, climate change, big data for the SDGs, and AIDS, in order to find solutions and encourage action.\n\nAs an international organization with 193 Member States, the United Nations is uniquely positioned to address and solve global issues.\n\nMore about Global Issues\n\nAs an international organization with 193 Member States, the United Nations is uniquely positioned to address and solve global issues.\n\nAs an international organization with 193 Member States, the United Nations is uniquely positioned to address and solve global issues.\n\nMore about Global Issues\n\nGlobal Issues\n\n\nWHAT ARE THEY?\n\t\t\t\tThese are the issues that transcend national boundaries and cannot be solved by any one country acting alone.\n\nWHY FOCUS ON THEM?\n\t\t\t\tThe United Nations focuses on these particular issues because if they are not addressed, they could negatively impact the lives of billions, slow progress towards achieving the sustainable development goals, affect the short-term and long-term environmental health of the planet on which we live, and halt human progress in the 21st century.\n\nWHICH ONES ARE RELATIVELY NEW?\n\t\t\t\tIn the more than seven decades since its creation, the United Nations has focused on new challenges, such as youth, gender equality, climate change, big data for the SDGs, and AIDS, in order to find solutions and encourage action.\n\nAfrica\n\n\n\n\n\n\n\n\n\nAgeing\n\n\n\n\n\n\n\n\n\nAIDS\n\n\n\n\n\n\n\n\n\nAtomic Energy\n\n\n\n\n\n\n\n\n\nBig Data for the SDGs\n\n\n\n\n\n\n\n\n\nChild and Youth Safety Online\n\n\n\n\n\n\n\n\n\nChildren\n\n\n\n\n\n\n\n\n\nClimate Change\n\n\n\n\n\n\n\n\n\nDecolonization\n\n\n\n\n\n\n\n\n\nDemocracy\n\n\n\n\n\n\n\n\n\nDisarmament\n\n\n\n\n\n\n\n\n\nEnding Poverty\n\n\n\n\n\n\n\n\n\nFood\n\n\n\n\n\n\n\n\n\nGender Equality\n\n\n\n\n\n\n\n\n\nHealth\n\n\n\n\n\n\n\n\n\nHuman Rights\n\n\n\n\n\n\n\n\n\nInternational Law and Justice\n\n\n\n\n\n\n\n\n\nMigration\n\n\n\n\n\n\n\n\n\nOceans and the Law of the Sea\n\n\n\n\n\n\n\n\n\nPeace and Security\n\n\n\n\n\n\n\n\n\nPopulation\n\n\n\n\n\n\n\n\n\nRefugees\n\n\n\n\n\n\n\n\n\nWater\n\n\n\n\n\n\n\n\n\nYouth\n\nAfrica\n\n\n\n\n\n\n\n\n\nAgeing\n\n\n\n\n\n\n\n\n\nAIDS\n\n\n\n\n\n\n\n\n\nAtomic Energy\n\n\n\n\n\n\n\n\n\nBig Data for the SDGs\n\n\n\n\n\n\n\n\n\nChild and Youth Safety Online\n\n\n\n\n\n\n\n\n\nChildren\n\n\n\n\n\n\n\n\n\nClimate Change\n\n\n\n\n\n\n\n\n\nDecolonization\n\n\n\n\n\n\n\n\n\nDemocracy\n\n\n\n\n\n\n\n\n\nDisarmament\n\n\n\n\n\n\n\n\n\nEnding Poverty\n\n\n\n\n\n\n\n\n\nFood\n\n\n\n\n\n\n\n\n\nGender Equality\n\n\n\n\n\n\n\n\n\nHealth\n\n\n\n\n\n\n\n\n\nHuman Rights\n\n\n\n\n\n\n\n\n\nInternational Law and Justice\n\n\n\n\n\n\n\n\n\nMigration\n\n\n\n\n\n\n\n\n\nOceans and the Law of the Sea\n\n\n\n\n\n\n\n\n\nPeace and Security\n\n\n\n\n\n\n\n\n\nPopulation\n\n\n\n\n\n\n\n\n\nRefugees\n\n\n\n\n\n\n\n\n\nWater\n\n\n\n\n\n\n\n\n\nYouth\n\nAfrica\n\nAfrica\n\nAfrica\n\nAfrica\n\nAfrica\n\nAgeing\n\nAgeing\n\nAgeing\n\nAgeing\n\nAgeing\n\nAIDS\n\nAIDS\n\nAIDS\n\nAIDS\n\nAIDS\n\nAtomic Energy\n\nAtomic Energy\n\nAtomic Energy\n\nAtomic Energy\n\nAtomic Energy\n\nBig Data for the SDGs\n\nBig Data for the SDGs\n\nBig Data for the SDGs\n\nBig Data for the SDGs\n\nBig Data for the SDGs\n\nChild and Youth Safety Online\n\nChild and Youth Safety Online\n\nChild and Youth Safety Online\n\nChild and Youth Safety Online\n\nChild and Youth Safety Online\n\nChildren\n\nChildren\n\nChildren\n\nChildren\n\nChildren\n\nClimate Change\n\nClimate Change\n\nClimate Change\n\nClimate Change\n\nClimate Change\n\nDecolonization\n\nDecolonization\n\nDecolonization\n\nDecolonization\n\nDecolonization\n\nDemocracy\n\nDemocracy\n\nDemocracy\n\nDemocracy\n\nDemocracy\n\nDisarmament\n\nDisarmament\n\nDisarmament\n\nDisarmament\n\nDisarmament\n\nEnding Poverty\n\nEnding Poverty\n\nEnding Poverty\n\nEnding Poverty\n\nEnding Poverty\n\nFood\n\nFood\n\nFood\n\nFood\n\nFood\n\nGender Equality\n\nGender Equality\n\nGender Equality\n\nGender Equality\n\nGender Equality\n\nHealth\n\nHealth\n\nHealth\n\nHealth\n\nHealth\n\nHuman Rights\n\nHuman Rights\n\nHuman Rights\n\nHuman Rights\n\nHuman Rights\n\nInternational Law and Justice\n\nInternational Law and Justice\n\nInternational Law and Justice\n\nInternational Law and Justice\n\nInternational Law and Justice\n\nMigration\n\nMigration\n\nMigration\n\nMigration\n\nMigration\n\nOceans and the Law of the Sea\n\nOceans and the Law of the Sea\n\nOceans and the Law of the Sea\n\nOceans and the Law of the Sea\n\nOceans and the Law of the Sea\n\nPeace and Security\n\nPeace and Security\n\nPeace and Security\n\nPeace and Security\n\nPeace and Security\n\nPopulation\n\nPopulation\n\nPopulation\n\nPopulation\n\nPopulation\n\nRefugees\n\nRefugees\n\nRefugees\n\nRefugees\n\nRefugees\n\nWater\n\nWater\n\nWater\n\nWater\n\nWater\n\nYouth\n\nYouth\n\nYouth\n\nYouth\n\nYouth\n\nDocuments\n\n©UNOG Library Photo\nThe UN has been publishing documents since its founding. UN documents include records of meetings and resolutions that have been passed by a legislative body, such as the General Assembly, Security Council, or the Economic and Social Council, which often contain a work mandate for the United Nations. Reports of the UN Secretary-General assess the state of the Organization and announce new work initiatives.\nExplore UN documents\n \n\n\nOfficial Languages\n\n©UN Photo/Laura Jarriel\nThere are six official languages of the UN: Arabic, Chinese, English, French, Russian, and Spanish. The correct interpretation and translation of the six languages, in both spoken and written form, is very important to the work of the Organization, as this enables clear and concise communication on issues of global importance.\nMore on the 6 official UN languages\n\nDocuments\n\n©UNOG Library Photo\nThe UN has been publishing documents since its founding. UN documents include records of meetings and resolutions that have been passed by a legislative body, such as the General Assembly, Security Council, or the Economic and Social Council, which often contain a work mandate for the United Nations. Reports of the UN Secretary-General assess the state of the Organization and announce new work initiatives.\nExplore UN documents\n\n©UNOG Library Photo\n\nThe UN has been publishing documents since its founding. UN documents include records of meetings and resolutions that have been passed by a legislative body, such as the General Assembly, Security Council, or the Economic and Social Council, which often contain a work mandate for the United Nations. Reports of the UN Secretary-General assess the state of the Organization and announce new work initiatives.\n\nExplore UN documents\n\nOfficial Languages\n\n©UN Photo/Laura Jarriel\nThere are six official languages of the UN: Arabic, Chinese, English, French, Russian, and Spanish. The correct interpretation and translation of the six languages, in both spoken and written form, is very important to the work of the Organization, as this enables clear and concise communication on issues of global importance.\nMore on the 6 official UN languages\n\n©UN Photo/Laura Jarriel\n\nThere are six official languages of the UN: Arabic, Chinese, English, French, Russian, and Spanish. The correct interpretation and translation of the six languages, in both spoken and written form, is very important to the work of the Organization, as this enables clear and concise communication on issues of global importance.\n\nMore on the 6 official UN languages\n\nObservances\nThe existence of international days predates the establishment of the United Nations, but the UN has embraced them as a powerful advocacy tool. The UN observes designated days, weeks, years, and decades, each with a theme, or topic.\nWhy do we mark international days?\n\n\n\n\n\n\n \n\n\nInternational Days and Weeks\n\n\n \n\n\n\n\nInternational Years\n\n\n\n\nInternational Decades\n\n\n\n\nUN Anniversaries\n\nObservances\nThe existence of international days predates the establishment of the United Nations, but the UN has embraced them as a powerful advocacy tool. The UN observes designated days, weeks, years, and decades, each with a theme, or topic.\nWhy do we mark international days?\n\nObservances\nThe existence of international days predates the establishment of the United Nations, but the UN has embraced them as a powerful advocacy tool. The UN observes designated days, weeks, years, and decades, each with a theme, or topic.\nWhy do we mark international days?\n\nObservances\nThe existence of international days predates the establishment of the United Nations, but the UN has embraced them as a powerful advocacy tool. The UN observes designated days, weeks, years, and decades, each with a theme, or topic.\nWhy do we mark international days?\n\nThe existence of international days predates the establishment of the United Nations, but the UN has embraced them as a powerful advocacy tool. The UN observes designated days, weeks, years, and decades, each with a theme, or topic.\n\nWhy do we mark international days?\n\nInternational Days and Weeks\n\n\n \n\n\n\n\nInternational Years\n\n\n\n\nInternational Decades\n\n\n\n\nUN Anniversaries\n\nInternational Days and Weeks\n\n\n \n\n\n\n\nInternational Years\n\n\n\n\nInternational Decades\n\n\n\n\nUN Anniversaries\n\nInternational Days and Weeks\n\nInternational Days and Weeks\n\nInternational Days and Weeks\n\nInternational Years\n\n\n\n\nInternational Decades\n\n\n\n\nUN Anniversaries\n\nInternational Years\n\nInternational Years\n\nInternational Decades\n\nInternational Decades\n\nUN Anniversaries\n\nUN Anniversaries\n\nMain Bodies   General Assembly   Security Council   Economic and Social Council   Trusteeship Council   International Court of Justice   Secretariat       Departments / Offices   New York   Geneva   Nairobi   Vienna   UN System Directory   UN System Chart   Global Leadership   UN Information Centres       Resources / Services   Emergency information   Reporting Wrongdoing   UN Journal   Documents   Guidelines for gender-inclusive language   Databases   Library   UN iLibrary   UN Chronicle   UN Yearbook   Bookshop   Publications for sale   Maps   Media Accreditation   NGO accreditation at ECOSOC   NGO accreditation at DGC   Visitors’ services   Exhibits   Procurement   Employment   Internships   Model UN   Academic Impact   UN Archives   UN Audiovisual Library   How to donate to the UN system   Information on COVID-19 (Coronavirus)   Africa Renewal   Ten ways the UN makes a difference   GA High-level week 2024       Key Documents   UN Charter   Universal Declaration of Human Rights   Convention on the Rights of the Child   Statute of the International Court of Justice   Annual Report of the Secretary-General on the Work of the Organization       News and Media   News   Press Releases   Briefings   Spokesperson   Photos   UNIfeed   UN Web TV   UN Video   Social Media   The Essential UN   Awake at Night podcast       Issues / Campaigns   Global Issues   Observances   Sustainable Development Goals   Our Common Agenda   The Summit of the Future   Climate Action   Peace and Security   Action for Peacekeeping (A4P)   Global Crisis Response Group   Call to Action for Human Rights   Disability Inclusion Strategy   Fight Racism   Hate Speech   LGBTIQ+ People   Safety of Journalists   Rule of Law   Action to Counter Terrorism   Victims of Terrorism   Children and Armed Conflict   Violence Against Children (SRSG)   Sexual Violence in Conflict   Refugees and Migrants   Action Agenda on Internal Displacement   Spotlight Initiative   Preventing Sexual Exploitation and Abuse   Prevention of Genocide and the Responsibility to Protect   The Rwanda Genocide   The Holocaust   The Question of Palestine   The Transatlantic Slave Trade   Decolonization   Messengers of Peace   Roadmap for Digital Cooperation   Digital Financing Task Force   Data Strategy   Information Integrity   Countering Disinformation   UN75: 2020 and Beyond   Women Rise for All   Stop the Red Sea Catastrophe   Black Sea Grain Initiative Joint Coordination Centre\n\nMain Bodies   General Assembly   Security Council   Economic and Social Council   Trusteeship Council   International Court of Justice   Secretariat       Departments / Offices   New York   Geneva   Nairobi   Vienna   UN System Directory   UN System Chart   Global Leadership   UN Information Centres       Resources / Services   Emergency information   Reporting Wrongdoing   UN Journal   Documents   Guidelines for gender-inclusive language   Databases   Library   UN iLibrary   UN Chronicle   UN Yearbook   Bookshop   Publications for sale   Maps   Media Accreditation   NGO accreditation at ECOSOC   NGO accreditation at DGC   Visitors’ services   Exhibits   Procurement   Employment   Internships   Model UN   Academic Impact   UN Archives   UN Audiovisual Library   How to donate to the UN system   Information on COVID-19 (Coronavirus)   Africa Renewal   Ten ways the UN makes a difference   GA High-level week 2024       Key Documents   UN Charter   Universal Declaration of Human Rights   Convention on the Rights of the Child   Statute of the International Court of Justice   Annual Report of the Secretary-General on the Work of the Organization       News and Media   News   Press Releases   Briefings   Spokesperson   Photos   UNIfeed   UN Web TV   UN Video   Social Media   The Essential UN   Awake at Night podcast       Issues / Campaigns   Global Issues   Observances   Sustainable Development Goals   Our Common Agenda   The Summit of the Future   Climate Action   Peace and Security   Action for Peacekeeping (A4P)   Global Crisis Response Group   Call to Action for Human Rights   Disability Inclusion Strategy   Fight Racism   Hate Speech   LGBTIQ+ People   Safety of Journalists   Rule of Law   Action to Counter Terrorism   Victims of Terrorism   Children and Armed Conflict   Violence Against Children (SRSG)   Sexual Violence in Conflict   Refugees and Migrants   Action Agenda on Internal Displacement   Spotlight Initiative   Preventing Sexual Exploitation and Abuse   Prevention of Genocide and the Responsibility to Protect   The Rwanda Genocide   The Holocaust   The Question of Palestine   The Transatlantic Slave Trade   Decolonization   Messengers of Peace   Roadmap for Digital Cooperation   Digital Financing Task Force   Data Strategy   Information Integrity   Countering Disinformation   UN75: 2020 and Beyond   Women Rise for All   Stop the Red Sea Catastrophe   Black Sea Grain Initiative Joint Coordination Centre\n\nMain Bodies   General Assembly   Security Council   Economic and Social Council   Trusteeship Council   International Court of Justice   Secretariat       Departments / Offices   New York   Geneva   Nairobi   Vienna   UN System Directory   UN System Chart   Global Leadership   UN Information Centres       Resources / Services   Emergency information   Reporting Wrongdoing   UN Journal   Documents   Guidelines for gender-inclusive language   Databases   Library   UN iLibrary   UN Chronicle   UN Yearbook   Bookshop   Publications for sale   Maps   Media Accreditation   NGO accreditation at ECOSOC   NGO accreditation at DGC   Visitors’ services   Exhibits   Procurement   Employment   Internships   Model UN   Academic Impact   UN Archives   UN Audiovisual Library   How to donate to the UN system   Information on COVID-19 (Coronavirus)   Africa Renewal   Ten ways the UN makes a difference   GA High-level week 2024       Key Documents   UN Charter   Universal Declaration of Human Rights   Convention on the Rights of the Child   Statute of the International Court of Justice   Annual Report of the Secretary-General on the Work of the Organization       News and Media   News   Press Releases   Briefings   Spokesperson   Photos   UNIfeed   UN Web TV   UN Video   Social Media   The Essential UN   Awake at Night podcast       Issues / Campaigns   Global Issues   Observances   Sustainable Development Goals   Our Common Agenda   The Summit of the Future   Climate Action   Peace and Security   Action for Peacekeeping (A4P)   Global Crisis Response Group   Call to Action for Human Rights   Disability Inclusion Strategy   Fight Racism   Hate Speech   LGBTIQ+ People   Safety of Journalists   Rule of Law   Action to Counter Terrorism   Victims of Terrorism   Children and Armed Conflict   Violence Against Children (SRSG)   Sexual Violence in Conflict   Refugees and Migrants   Action Agenda on Internal Displacement   Spotlight Initiative   Preventing Sexual Exploitation and Abuse   Prevention of Genocide and the Responsibility to Protect   The Rwanda Genocide   The Holocaust   The Question of Palestine   The Transatlantic Slave Trade   Decolonization   Messengers of Peace   Roadmap for Digital Cooperation   Digital Financing Task Force   Data Strategy   Information Integrity   Countering Disinformation   UN75: 2020 and Beyond   Women Rise for All   Stop the Red Sea Catastrophe   Black Sea Grain Initiative Joint Coordination Centre\n\nMain Bodies   General Assembly   Security Council   Economic and Social Council   Trusteeship Council   International Court of Justice   Secretariat       Departments / Offices   New York   Geneva   Nairobi   Vienna   UN System Directory   UN System Chart   Global Leadership   UN Information Centres\n\nMain Bodies   General Assembly   Security Council   Economic and Social Council   Trusteeship Council   International Court of Justice   Secretariat\n\nMain Bodies   General Assembly   Security Council   Economic and Social Council   Trusteeship Council   International Court of Justice   Secretariat\n\nDepartments / Offices   New York   Geneva   Nairobi   Vienna   UN System Directory   UN System Chart   Global Leadership   UN Information Centres\n\nDepartments / Offices   New York   Geneva   Nairobi   Vienna   UN System Directory   UN System Chart   Global Leadership   UN Information Centres\n\nResources / Services   Emergency information   Reporting Wrongdoing   UN Journal   Documents   Guidelines for gender-inclusive language   Databases   Library   UN iLibrary   UN Chronicle   UN Yearbook   Bookshop   Publications for sale   Maps   Media Accreditation   NGO accreditation at ECOSOC   NGO accreditation at DGC   Visitors’ services   Exhibits   Procurement   Employment   Internships   Model UN   Academic Impact   UN Archives   UN Audiovisual Library   How to donate to the UN system   Information on COVID-19 (Coronavirus)   Africa Renewal   Ten ways the UN makes a difference   GA High-level week 2024\n\nResources / Services   Emergency information   Reporting Wrongdoing   UN Journal   Documents   Guidelines for gender-inclusive language   Databases   Library   UN iLibrary   UN Chronicle   UN Yearbook   Bookshop   Publications for sale   Maps   Media Accreditation   NGO accreditation at ECOSOC   NGO accreditation at DGC   Visitors’ services   Exhibits   Procurement   Employment   Internships   Model UN   Academic Impact   UN Archives   UN Audiovisual Library   How to donate to the UN system   Information on COVID-19 (Coronavirus)   Africa Renewal   Ten ways the UN makes a difference   GA High-level week 2024\n\nResources / Services   Emergency information   Reporting Wrongdoing   UN Journal   Documents   Guidelines for gender-inclusive language   Databases   Library   UN iLibrary   UN Chronicle   UN Yearbook   Bookshop   Publications for sale   Maps   Media Accreditation   NGO accreditation at ECOSOC   NGO accreditation at DGC   Visitors’ services   Exhibits   Procurement   Employment   Internships   Model UN   Academic Impact   UN Archives   UN Audiovisual Library   How to donate to the UN system   Information on COVID-19 (Coronavirus)   Africa Renewal   Ten ways the UN makes a difference   GA High-level week 2024\n\nKey Documents   UN Charter   Universal Declaration of Human Rights   Convention on the Rights of the Child   Statute of the International Court of Justice   Annual Report of the Secretary-General on the Work of the Organization       News and Media   News   Press Releases   Briefings   Spokesperson   Photos   UNIfeed   UN Web TV   UN Video   Social Media   The Essential UN   Awake at Night podcast\n\nKey Documents   UN Charter   Universal Declaration of Human Rights   Convention on the Rights of the Child   Statute of the International Court of Justice   Annual Report of the Secretary-General on the Work of the Organization\n\nKey Documents   UN Charter   Universal Declaration of Human Rights   Convention on the Rights of the Child   Statute of the International Court of Justice   Annual Report of the Secretary-General on the Work of the Organization\n\nNews and Media   News   Press Releases   Briefings   Spokesperson   Photos   UNIfeed   UN Web TV   UN Video   Social Media   The Essential UN   Awake at Night podcast\n\nNews and Media   News   Press Releases   Briefings   Spokesperson   Photos   UNIfeed   UN Web TV   UN Video   Social Media   The Essential UN   Awake at Night podcast\n\nIssues / Campaigns   Global Issues   Observances   Sustainable Development Goals   Our Common Agenda   The Summit of the Future   Climate Action   Peace and Security   Action for Peacekeeping (A4P)   Global Crisis Response Group   Call to Action for Human Rights   Disability Inclusion Strategy   Fight Racism   Hate Speech   LGBTIQ+ People   Safety of Journalists   Rule of Law   Action to Counter Terrorism   Victims of Terrorism   Children and Armed Conflict   Violence Against Children (SRSG)   Sexual Violence in Conflict   Refugees and Migrants   Action Agenda on Internal Displacement   Spotlight Initiative   Preventing Sexual Exploitation and Abuse   Prevention of Genocide and the Responsibility to Protect   The Rwanda Genocide   The Holocaust   The Question of Palestine   The Transatlantic Slave Trade   Decolonization   Messengers of Peace   Roadmap for Digital Cooperation   Digital Financing Task Force   Data Strategy   Information Integrity   Countering Disinformation   UN75: 2020 and Beyond   Women Rise for All   Stop the Red Sea Catastrophe   Black Sea Grain Initiative Joint Coordination Centre\n\nIssues / Campaigns   Global Issues   Observances   Sustainable Development Goals   Our Common Agenda   The Summit of the Future   Climate Action   Peace and Security   Action for Peacekeeping (A4P)   Global Crisis Response Group   Call to Action for Human Rights   Disability Inclusion Strategy   Fight Racism   Hate Speech   LGBTIQ+ People   Safety of Journalists   Rule of Law   Action to Counter Terrorism   Victims of Terrorism   Children and Armed Conflict   Violence Against Children (SRSG)   Sexual Violence in Conflict   Refugees and Migrants   Action Agenda on Internal Displacement   Spotlight Initiative   Preventing Sexual Exploitation and Abuse   Prevention of Genocide and the Responsibility to Protect   The Rwanda Genocide   The Holocaust   The Question of Palestine   The Transatlantic Slave Trade   Decolonization   Messengers of Peace   Roadmap for Digital Cooperation   Digital Financing Task Force   Data Strategy   Information Integrity   Countering Disinformation   UN75: 2020 and Beyond   Women Rise for All   Stop the Red Sea Catastrophe   Black Sea Grain Initiative Joint Coordination Centre\n\nIssues / Campaigns   Global Issues   Observances   Sustainable Development Goals   Our Common Agenda   The Summit of the Future   Climate Action   Peace and Security   Action for Peacekeeping (A4P)   Global Crisis Response Group   Call to Action for Human Rights   Disability Inclusion Strategy   Fight Racism   Hate Speech   LGBTIQ+ People   Safety of Journalists   Rule of Law   Action to Counter Terrorism   Victims of Terrorism   Children and Armed Conflict   Violence Against Children (SRSG)   Sexual Violence in Conflict   Refugees and Migrants   Action Agenda on Internal Displacement   Spotlight Initiative   Preventing Sexual Exploitation and Abuse   Prevention of Genocide and the Responsibility to Protect   The Rwanda Genocide   The Holocaust   The Question of Palestine   The Transatlantic Slave Trade   Decolonization   Messengers of Peace   Roadmap for Digital Cooperation   Digital Financing Task Force   Data Strategy   Information Integrity   Countering Disinformation   UN75: 2020 and Beyond   Women Rise for All   Stop the Red Sea Catastrophe   Black Sea Grain Initiative Joint Coordination Centre",
  "date": "",
  "source_type": "UN_organization",
  "extracted_at": "2025-04-07T13:52:42.608654",
  "metadata": {
    "description": "The United Nations is part of the UN system, which is made up of  the UN itself and many funds, programmes, specialized agencies, and other organizations. Together they work towards Maintaining International Peace and Security; \r\nProtecting Human Rights; Delivering Humanitarian Aid; Supporting Sustainable Development and Climate Action and Upholding International Law.",
    "author": "United Nations",
    "og:site_name": "United Nations",
    "og:type": "article"
  },
  "relevance_score": 0.4,
  "summary": "Cooperation between the UN and the other entities of the UN system is essential in order to achieve the purposes of the Organization laid out in the UN Charter. UN's 'work plan'\nAt UN Headquarters in New York, the General Assembly, Security Council, and Economic and Social Council pass resolutions, which set what could informally be called the UN's 'work plan.'\nThe UN Secretariat carries out this work along with UN system entities. What We Do\nThe work of the United Nations covers five main areas:\n\n\n\nMaintain International Peace and Security\nProtect Human Rights\nDeliver Humanitarian Aid\nSupport Sustainable Development and Climate Action\nUphold International Law\n\n\n\nLeft to right: ©UN Photo/Marco Dormino, ©UN Photo/Mark Garten, ©OCHA/Iason Athanasiadis, ©UNEP/Patrick Kihara, ©UN Photo/Sylvain Liechti\n\n\n\n\n\n\n\n\n\n\nAs an international organization with 193 Member States, the United Nations is uniquely positioned to address and solve global issues. Africa\n\n\n\n\n\n\n\n\n\nAgeing\n\n\n\n\n\n\n\n\n\nAIDS\n\n\n\n\n\n\n\n\n\nAtomic Energy\n\n\n\n\n\n\n\n\n\nBig Data for the SDGs\n\n\n\n\n\n\n\n\n\nChild and Youth Safety Online\n\n\n\n\n\n\n\n\n\nChildren\n\n\n\n\n\n\n\n\n\nClimate Change\n\n\n\n\n\n\n\n\n\nDecolonization\n\n\n\n\n\n\n\n\n\nDemocracy\n\n\n\n\n\n\n\n\n\nDisarmament\n\n\n\n\n\n\n\n\n\nEnding Poverty\n\n\n\n\n\n\n\n\n\nFood\n\n\n\n\n\n\n\n\n\nGender Equality\n\n\n\n\n\n\n\n\n\nHealth\n\n\n\n\n\n\n\n\n\nHuman Rights\n\n\n\n\n\n\n\n\n\nInternational Law and Justice\n\n\n\n\n\n\n\n\n\nMigration\n\n\n\n\n\n\n\n\n\nOceans and the Law of the Sea\n\n\n\n\n\n\n\n\n\nPeace and Security\n\n\n\n\n\n\n\n\n\nPopulation\n\n\n\n\n\n\n\n\n\nRefugees\n\n\n\n\n\n\n\n\n\nWater\n\n\n\n\n\n\n\n\n\nYouth\n\n\n\n\n\n\n\n\n \n\nDocuments\n\n©UNOG Library Photo\nThe UN has been publishing documents since its founding. UN documents include records of meetings and resolutions that have been passed by a legislative body, such as the General Assembly, Security Council, or the Economic and Social Council, which often contain a work mandate for the United Nations. More on the 6 official UN languages\n \n\n \n\n\n\n\n\n\nObservances\nThe existence of international days predates the establishment of the United Nations, but the UN has embraced them as a powerful advocacy tool. International Days and Weeks\n\n\n \n\n\n\n\nInternational Years\n\n\n\n\nInternational Decades\n\n\n\n\nUN Anniversaries\n\n\n\n\n\n\n\n\n\n\n\n\n\n\n\n\n\n\n\n\n\n\n\n \n\n\n\n        Main Bodies   General Assembly   Security Council   Economic and Social Council   Trusteeship Council   International Court of Justice   Secretariat       Departments / Offices   New York   Geneva   Nairobi   Vienna   UN System Directory   UN System Chart   Global Leadership   UN Information Centres       Resources / Services   Emergency information   Reporting Wrongdoing   UN Journal   Documents   Guidelines for gender-inclusive language   Databases   Library   UN iLibrary   UN Chronicle   UN Yearbook   Bookshop   Publications for sale   Maps   Media Accreditation   NGO accreditation at ECOSOC   NGO accreditation at DGC   Visitors’ services   Exhibits   Procurement   Employment   Internships   Model UN   Academic Impact   UN Archives   UN Audiovisual Library   How to donate to the UN system   Information on COVID-19 (Coronavirus)   Africa Renewal   Ten ways the UN makes a difference   GA High-level week 2024       Key Documents   UN Charter   Universal Declaration of Human Rights   Convention on the Rights of the Child   Statute of the International Court of Justice   Annual Report of the Secretary-General on the Work of the Organization       News and Media   News   Press Releases   Briefings   Spokesperson   Photos   UNIfeed   UN Web TV   UN Video   Social Media   The Essential UN   Awake at Night podcast       Issues / Campaigns   Global Issues   Observances   Sustainable Development Goals   Our Common Agenda   The Summit of the Future   Climate Action   Peace and Security   Action for Peacekeeping (A4P)   Global Crisis Response Group   Call to Action for Human Rights   Disability Inclusion Strategy   Fight Racism   Hate Speech   LGBTIQ+ People   Safety of Journalists   Rule of Law   Action to Counter Terrorism   Victims of Terrorism   Children and Armed Conflict   Violence Against Children (SRSG)   Sexual Violence in Conflict   Refugees and Migrants   Action Agenda on Internal Displacement   Spotlight Initiative   Preventing Sexual Exploitation and Abuse   Prevention of Genocide and the Responsibility to Protect   The Rwanda Genocide   The Holocaust   The Question of Palestine   The Transatlantic Slave Trade   Decolonization   Messengers of Peace   Roadmap for Digital Cooperation   Digital Financing Task Force   Data Strategy   Information Integrity   Countering Disinformation   UN75: 2020 and Beyond   Women Rise for All   Stop the Red Sea Catastrophe   Black Sea Grain Initiative Joint Coordination Centre\n\nOur Work\n\n\nThe United Nations coordinates its work with the funds, programmes, specialized agencies and other organizations of the UN System. Cooperation between the UN and the other entities of the UN system is essential in order to achieve the purposes of the Organization laid out in the UN Charter. UN's 'work plan'\nAt UN Headquarters in New York, the General Assembly, Security Council, and Economic and Social Council pass resolutions, which set what could informally be called the UN's 'work plan.'\nThe UN Secretariat carries out this work along with UN system entities. What We Do\nThe work of the United Nations covers five main areas:\n\n\n\nMaintain International Peace and Security\nProtect Human Rights\nDeliver Humanitarian Aid\nSupport Sustainable Development and Climate Action\nUphold International Law\n\n\n\nLeft to right: ©UN Photo/Marco Dormino, ©UN Photo/Mark Garten, ©OCHA/Iason Athanasiadis, ©UNEP/Patrick Kihara, ©UN Photo/Sylvain Liechti\n\n\n\n\n\n\n\n\n\n\nAs an international organization with 193 Member States, the United Nations is uniquely positioned to address and solve global issues. Africa\n\n\n\n\n\n\n\n\n\nAgeing\n\n\n\n\n\n\n\n\n\nAIDS\n\n\n\n\n\n\n\n\n\nAtomic Energy\n\n\n\n\n\n\n\n\n\nBig Data for the SDGs\n\n\n\n\n\n\n\n\n\nChild and Youth Safety Online\n\n\n\n\n\n\n\n\n\nChildren\n\n\n\n\n\n\n\n\n\nClimate Change\n\n\n\n\n\n\n\n\n\nDecolonization\n\n\n\n\n\n\n\n\n\nDemocracy\n\n\n\n\n\n\n\n\n\nDisarmament\n\n\n\n\n\n\n\n\n\nEnding Poverty\n\n\n\n\n\n\n\n\n\nFood\n\n\n\n\n\n\n\n\n\nGender Equality\n\n\n\n\n\n\n\n\n\nHealth\n\n\n\n\n\n\n\n\n\nHuman Rights\n\n\n\n\n\n\n\n\n\nInternational Law and Justice\n\n\n\n\n\n\n\n\n\nMigration\n\n\n\n\n\n\n\n\n\nOceans and the Law of the Sea\n\n\n\n\n\n\n\n\n\nPeace and Security\n\n\n\n\n\n\n\n\n\nPopulation\n\n\n\n\n\n\n\n\n\nRefugees\n\n\n\n\n\n\n\n\n\nWater\n\n\n\n\n\n\n\n\n\nYouth\n\n\n\n\n\n\n\n\n \n\nDocuments\n\n©UNOG Library Photo\nThe UN has been publishing documents since its founding. More on the 6 official UN languages\n \n\n \n\n\n\n\n\n\nObservances\nThe existence of international days predates the establishment of the United Nations, but the UN has embraced them as a powerful advocacy tool. International Days and Weeks\n\n\n \n\n\n\n\nInternational Years\n\n\n\n\nInternational Decades\n\n\n\n\nUN Anniversaries\n\nOur Work\n\n\nThe United Nations coordinates its work with the funds, programmes, specialized agencies and other organizations of the UN System. Cooperation between the UN and the other entities of the UN system is essential in order to achieve the purposes of the Organization laid out in the UN Charter. UN's 'work plan'\nAt UN Headquarters in New York, the General Assembly, Security Council, and Economic and Social Council pass resolutions, which set what could informally be called the UN's 'work plan.'\nThe UN Secretariat carries out this work along with UN system entities. What We Do\nThe work of the United Nations covers five main areas:\n\n\n\nMaintain International Peace and Security\nProtect Human Rights\nDeliver Humanitarian Aid\nSupport Sustainable Development and Climate Action\nUphold International Law\n\n\n\nLeft to right: ©UN Photo/Marco Dormino, ©UN Photo/Mark Garten, ©OCHA/Iason Athanasiadis, ©UNEP/Patrick Kihara, ©UN Photo/Sylvain Liechti\n\n\n\n\n\n\n\n\n\n\nAs an international organization with 193 Member States, the United Nations is uniquely positioned to address and solve global issues. Africa\n\n\n\n\n\n\n\n\n\nAgeing\n\n\n\n\n\n\n\n\n\nAIDS\n\n\n\n\n\n\n\n\n\nAtomic Energy\n\n\n\n\n\n\n\n\n\nBig Data for the SDGs\n\n\n\n\n\n\n\n\n\nChild and Youth Safety Online\n\n\n\n\n\n\n\n\n\nChildren\n\n\n\n\n\n\n\n\n\nClimate Change\n\n\n\n\n\n\n\n\n\nDecolonization\n\n\n\n\n\n\n\n\n\nDemocracy\n\n\n\n\n\n\n\n\n\nDisarmament\n\n\n\n\n\n\n\n\n\nEnding Poverty\n\n\n\n\n\n\n\n\n\nFood\n\n\n\n\n\n\n\n\n\nGender Equality\n\n\n\n\n\n\n\n\n\nHealth\n\n\n\n\n\n\n\n\n\nHuman Rights\n\n\n\n\n\n\n\n\n\nInternational Law and Justice\n\n\n\n\n\n\n\n\n\nMigration\n\n\n\n\n\n\n\n\n\nOceans and the Law of the Sea\n\n\n\n\n\n\n\n\n\nPeace and Security\n\n\n\n\n\n\n\n\n\nPopulation\n\n\n\n\n\n\n\n\n\nRefugees\n\n\n\n\n\n\n\n\n\nWater\n\n\n\n\n\n\n\n\n\nYouth\n\n\n\n\n\n\n\n\n \n\nDocuments\n\n©UNOG Library Photo\nThe UN has been publishing documents since its founding. More on the 6 official UN languages\n \n\n \n\n\n\n\n\n\nObservances\nThe existence of international days predates the establishment of the United Nations, but the UN has embraced them as a powerful advocacy tool. International Days and Weeks\n\n\n \n\n\n\n\nInternational Years\n\n\n\n\nInternational Decades\n\n\n\n\nUN Anniversaries\n\nOur Work\n\n\nThe United Nations coordinates its work with the funds, programmes, specialized agencies and other organizations of the UN System. Cooperation between the UN and the other entities of the UN system is essential in order to achieve the purposes of the Organization laid out in the UN Charter. UN's 'work plan'\nAt UN Headquarters in New York, the General Assembly, Security Council, and Economic and Social Council pass resolutions, which set what could informally be called the UN's 'work plan.'\nThe UN Secretariat carries out this work along with UN system entities. What We Do\nThe work of the United Nations covers five main areas:\n\n\n\nMaintain International Peace and Security\nProtect Human Rights\nDeliver Humanitarian Aid\nSupport Sustainable Development and Climate Action\nUphold International Law\n\n\n\nLeft to right: ©UN Photo/Marco Dormino, ©UN Photo/Mark Garten, ©OCHA/Iason Athanasiadis, ©UNEP/Patrick Kihara, ©UN Photo/Sylvain Liechti\n\n\n\n\n\n\n\n\n\n\nAs an international organization with 193 Member States, the United Nations is uniquely positioned to address and solve global issues. Africa\n\n\n\n\n\n\n\n\n\nAgeing\n\n\n\n\n\n\n\n\n\nAIDS\n\n\n\n\n\n\n\n\n\nAtomic Energy\n\n\n\n\n\n\n\n\n\nBig Data for the SDGs\n\n\n\n\n\n\n\n\n\nChild and Youth Safety Online\n\n\n\n\n\n\n\n\n\nChildren\n\n\n\n\n\n\n\n\n\nClimate Change\n\n\n\n\n\n\n\n\n\nDecolonization\n\n\n\n\n\n\n\n\n\nDemocracy\n\n\n\n\n\n\n\n\n\nDisarmament\n\n\n\n\n\n\n\n\n\nEnding Poverty\n\n\n\n\n\n\n\n\n\nFood\n\n\n\n\n\n\n\n\n\nGender Equality\n\n\n\n\n\n\n\n\n\nHealth\n\n\n\n\n\n\n\n\n\nHuman Rights\n\n\n\n\n\n\n\n\n\nInternational Law and Justice\n\n\n\n\n\n\n\n\n\nMigration\n\n\n\n\n\n\n\n\n\nOceans and the Law of the Sea\n\n\n\n\n\n\n\n\n\nPeace and Security\n\n\n\n\n\n\n\n\n\nPopulation\n\n\n\n\n\n\n\n\n\nRefugees\n\n\n\n\n\n\n\n\n\nWater\n\n\n\n\n\n\n\n\n\nYouth\n\n\n\n\n\n\n\n\n \n\nDocuments\n\n©UNOG Library Photo\nThe UN has been publishing documents since its founding. More on the 6 official UN languages\n \n\n \n\n\n\n\n\n\nObservances\nThe existence of international days predates the establishment of the United Nations, but the UN has embraced them as a powerful advocacy tool. International Days and Weeks\n\n\n \n\n\n\n\nInternational Years\n\n\n\n\nInternational Decades\n\n\n\n\nUN Anniversaries\n\nOur Work\n\n\nThe United Nations coordinates its work with the funds, programmes, specialized agencies and other organizations of the UN System. Cooperation between the UN and the other entities of the UN system is essential in order to achieve the purposes of the Organization laid out in the UN Charter. UN's 'work plan'\nAt UN Headquarters in New York, the General Assembly, Security Council, and Economic and Social Council pass resolutions, which set what could informally be called the UN's 'work plan.'\nThe UN Secretariat carries out this work along with UN system entities. What We Do\nThe work of the United Nations covers five main areas:\n\n\n\nMaintain International Peace and Security\nProtect Human Rights\nDeliver Humanitarian Aid\nSupport Sustainable Development and Climate Action\nUphold International Law\n\n\n\nLeft to right: ©UN Photo/Marco Dormino, ©UN Photo/Mark Garten, ©OCHA/Iason Athanasiadis, ©UNEP/Patrick Kihara, ©UN Photo/Sylvain Liechti\n\n\n\n\n\n\n\n\n\n\nAs an international organization with 193 Member States, the United Nations is uniquely positioned to address and solve global issues. Africa\n\n\n\n\n\n\n\n\n\nAgeing\n\n\n\n\n\n\n\n\n\nAIDS\n\n\n\n\n\n\n\n\n\nAtomic Energy\n\n\n\n\n\n\n\n\n\nBig Data for the SDGs\n\n\n\n\n\n\n\n\n\nChild and Youth Safety Online\n\n\n\n\n\n\n\n\n\nChildren\n\n\n\n\n\n\n\n\n\nClimate Change\n\n\n\n\n\n\n\n\n\nDecolonization\n\n\n\n\n\n\n\n\n\nDemocracy\n\n\n\n\n\n\n\n\n\nDisarmament\n\n\n\n\n\n\n\n\n\nEnding Poverty\n\n\n\n\n\n\n\n\n\nFood\n\n\n\n\n\n\n\n\n\nGender Equality\n\n\n\n\n\n\n\n\n\nHealth\n\n\n\n\n\n\n\n\n\nHuman Rights\n\n\n\n\n\n\n\n\n\nInternational Law and Justice\n\n\n\n\n\n\n\n\n\nMigration\n\n\n\n\n\n\n\n\n\nOceans and the Law of the Sea\n\n\n\n\n\n\n\n\n\nPeace and Security\n\n\n\n\n\n\n\n\n\nPopulation\n\n\n\n\n\n\n\n\n\nRefugees\n\n\n\n\n\n\n\n\n\nWater\n\n\n\n\n\n\n\n\n\nYouth\n\n\n\n\n\n\n\n\n \n\nDocuments\n\n©UNOG Library Photo\nThe UN has been publishing documents since its founding. More on the 6 official UN languages\n \n\n \n\n\n\n\n\n\nObservances\nThe existence of international days predates the establishment of the United Nations, but the UN has embraced them as a powerful advocacy tool. International Days and Weeks\n\n\n \n\n\n\n\nInternational Years\n\n\n\n\nInternational Decades\n\n\n\n\nUN Anniversaries\n\nOur Work\n\n\nThe United Nations coordinates its work with the funds, programmes, specialized agencies and other organizations of the UN System. Cooperation between the UN and the other entities of the UN system is essential in order to achieve the purposes of the Organization laid out in the UN Charter. UN's 'work plan'\nAt UN Headquarters in New York, the General Assembly, Security Council, and Economic and Social Council pass resolutions, which set what could informally be called the UN's 'work plan.'\nThe UN Secretariat carries out this work along with UN system entities. What We Do\nThe work of the United Nations covers five main areas:\n\n\n\nMaintain International Peace and Security\nProtect Human Rights\nDeliver Humanitarian Aid\nSupport Sustainable Development and Climate Action\nUphold International Law\n\n\n\nLeft to right: ©UN Photo/Marco Dormino, ©UN Photo/Mark Garten, ©OCHA/Iason Athanasiadis, ©UNEP/Patrick Kihara, ©UN Photo/Sylvain Liechti\n\n\n\n\n\n\n\n\n\n\nAs an international organization with 193 Member States, the United Nations is uniquely positioned to address and solve global issues. Africa\n\n\n\n\n\n\n\n\n\nAgeing\n\n\n\n\n\n\n\n\n\nAIDS\n\n\n\n\n\n\n\n\n\nAtomic Energy\n\n\n\n\n\n\n\n\n\nBig Data for the SDGs\n\n\n\n\n\n\n\n\n\nChild and Youth Safety Online\n\n\n\n\n\n\n\n\n\nChildren\n\n\n\n\n\n\n\n\n\nClimate Change\n\n\n\n\n\n\n\n\n\nDecolonization\n\n\n\n\n\n\n\n\n\nDemocracy\n\n\n\n\n\n\n\n\n\nDisarmament\n\n\n\n\n\n\n\n\n\nEnding Poverty\n\n\n\n\n\n\n\n\n\nFood\n\n\n\n\n\n\n\n\n\nGender Equality\n\n\n\n\n\n\n\n\n\nHealth\n\n\n\n\n\n\n\n\n\nHuman Rights\n\n\n\n\n\n\n\n\n\nInternational Law and Justice\n\n\n\n\n\n\n\n\n\nMigration\n\n\n\n\n\n\n\n\n\nOceans and the Law of the Sea\n\n\n\n\n\n\n\n\n\nPeace and Security\n\n\n\n\n\n\n\n\n\nPopulation\n\n\n\n\n\n\n\n\n\nRefugees\n\n\n\n\n\n\n\n\n\nWater\n\n\n\n\n\n\n\n\n\nYouth\n\n\n\n\n\n\n\n\n \n\nDocuments\n\n©UNOG Library Photo\nThe UN has been publishing documents since its founding. More on the 6 official UN languages\n \n\n \n\n\n\n\n\n\nObservances\nThe existence of international days predates the establishment of the United Nations, but the UN has embraced them as a powerful advocacy tool. International Days and Weeks\n\n\n \n\n\n\n\nInternational Years\n\n\n\n\nInternational Decades\n\n\n\n\nUN Anniversaries\n\nOur Work\n\n\nThe United Nations coordinates its work with the funds, programmes, specialized agencies and other organizations of the UN System. Cooperation between the UN and the other entities of the UN system is essential in order to achieve the purposes of the Organization laid out in the UN Charter. UN's 'work plan'\nAt UN Headquarters in New York, the General Assembly, Security Council, and Economic and Social Council pass resolutions, which set what could informally be called the UN's 'work plan.'\nThe UN Secretariat carries out this work along with UN system entities. What We Do\nThe work of the United Nations covers five main areas:\n\n\n\nMaintain International Peace and Security\nProtect Human Rights\nDeliver Humanitarian Aid\nSupport Sustainable Development and Climate Action\nUphold International Law\n\n\n\nLeft to right: ©UN Photo/Marco Dormino, ©UN Photo/Mark Garten, ©OCHA/Iason Athanasiadis, ©UNEP/Patrick Kihara, ©UN Photo/Sylvain Liechti\n\n\n\n\n\n\n\n\n\n\nAs an international organization with 193 Member States, the United Nations is uniquely positioned to address and solve global issues. Africa\n\n\n\n\n\n\n\n\n\nAgeing\n\n\n\n\n\n\n\n\n\nAIDS\n\n\n\n\n\n\n\n\n\nAtomic Energy\n\n\n\n\n\n\n\n\n\nBig Data for the SDGs\n\n\n\n\n\n\n\n\n\nChild and Youth Safety Online\n\n\n\n\n\n\n\n\n\nChildren\n\n\n\n\n\n\n\n\n\nClimate Change\n\n\n\n\n\n\n\n\n\nDecolonization\n\n\n\n\n\n\n\n\n\nDemocracy\n\n\n\n\n\n\n\n\n\nDisarmament\n\n\n\n\n\n\n\n\n\nEnding Poverty\n\n\n\n\n\n\n\n\n\nFood\n\n\n\n\n\n\n\n\n\nGender Equality\n\n\n\n\n\n\n\n\n\nHealth\n\n\n\n\n\n\n\n\n\nHuman Rights\n\n\n\n\n\n\n\n\n\nInternational Law and Justice\n\n\n\n\n\n\n\n\n\nMigration\n\n\n\n\n\n\n\n\n\nOceans and the Law of the Sea\n\n\n\n\n\n\n\n\n\nPeace and Security\n\n\n\n\n\n\n\n\n\nPopulation\n\n\n\n\n\n\n\n\n\nRefugees\n\n\n\n\n\n\n\n\n\nWater\n\n\n\n\n\n\n\n\n\nYouth\n\n\n\n\n\n\n\n\n \n\nDocuments\n\n©UNOG Library Photo\nThe UN has been publishing documents since its founding. More on the 6 official UN languages\n \n\n \n\n\n\n\n\n\nObservances\nThe existence of international days predates the establishment of the United Nations, but the UN has embraced them as a powerful advocacy tool. International Days and Weeks\n\n\n \n\n\n\n\nInternational Years\n\n\n\n\nInternational Decades\n\n\n\n\nUN Anniversaries\n\nOur Work\n\n\nThe United Nations coordinates its work with the funds, programmes, specialized agencies and other organizations of the UN System. Cooperation between the UN and the other entities of the UN system is essential in order to achieve the purposes of the Organization laid out in the UN Charter. UN's 'work plan'\nAt UN Headquarters in New York, the General Assembly, Security Council, and Economic and Social Council pass resolutions, which set what could informally be called the UN's 'work plan.'\nThe UN Secretariat carries out this work along with UN system entities. What We Do\nThe work of the United Nations covers five main areas:\n\n\n\nMaintain International Peace and Security\nProtect Human Rights\nDeliver Humanitarian Aid\nSupport Sustainable Development and Climate Action\nUphold International Law\n\n\n\nLeft to right: ©UN Photo/Marco Dormino, ©UN Photo/Mark Garten, ©OCHA/Iason Athanasiadis, ©UNEP/Patrick Kihara, ©UN Photo/Sylvain Liechti\n\n\n\n\n\n\n\n\n\n\nAs an international organization with 193 Member States, the United Nations is uniquely positioned to address and solve global issues. Africa\n\n\n\n\n\n\n\n\n\nAgeing\n\n\n\n\n\n\n\n\n\nAIDS\n\n\n\n\n\n\n\n\n\nAtomic Energy\n\n\n\n\n\n\n\n\n\nBig Data for the SDGs\n\n\n\n\n\n\n\n\n\nChild and Youth Safety Online\n\n\n\n\n\n\n\n\n\nChildren\n\n\n\n\n\n\n\n\n\nClimate Change\n\n\n\n\n\n\n\n\n\nDecolonization\n\n\n\n\n\n\n\n\n\nDemocracy\n\n\n\n\n\n\n\n\n\nDisarmament\n\n\n\n\n\n\n\n\n\nEnding Poverty\n\n\n\n\n\n\n\n\n\nFood\n\n\n\n\n\n\n\n\n\nGender Equality\n\n\n\n\n\n\n\n\n\nHealth\n\n\n\n\n\n\n\n\n\nHuman Rights\n\n\n\n\n\n\n\n\n\nInternational Law and Justice\n\n\n\n\n\n\n\n\n\nMigration\n\n\n\n\n\n\n\n\n\nOceans and the Law of the Sea\n\n\n\n\n\n\n\n\n\nPeace and Security\n\n\n\n\n\n\n\n\n\nPopulation\n\n\n\n\n\n\n\n\n\nRefugees\n\n\n\n\n\n\n\n\n\nWater\n\n\n\n\n\n\n\n\n\nYouth\n\n\n\n\n\n\n\n\n \n\nDocuments\n\n©UNOG Library Photo\nThe UN has been publishing documents since its founding. More on the 6 official UN languages\n \n\n \n\n\n\n\n\n\nObservances\nThe existence of international days predates the establishment of the United Nations, but the UN has embraced them as a powerful advocacy tool. International Days and Weeks\n\n\n \n\n\n\n\nInternational Years\n\n\n\n\nInternational Decades\n\n\n\n\nUN Anniversaries\n\nOur Work\n\n\nThe United Nations coordinates its work with the funds, programmes, specialized agencies and other organizations of the UN System. Cooperation between the UN and the other entities of the UN system is essential in order to achieve the purposes of the Organization laid out in the UN Charter. UN's 'work plan'\nAt UN Headquarters in New York, the General Assembly, Security Council, and Economic and Social Council pass resolutions, which set what could informally be called the UN's 'work plan.'\nThe UN Secretariat carries out this work along with UN system entities. What We Do\nThe work of the United Nations covers five main areas:\n\n\n\nMaintain International Peace and Security\nProtect Human Rights\nDeliver Humanitarian Aid\nSupport Sustainable Development and Climate Action\nUphold International Law\n\n\n\nLeft to right: ©UN Photo/Marco Dormino, ©UN Photo/Mark Garten, ©OCHA/Iason Athanasiadis, ©UNEP/Patrick Kihara, ©UN Photo/Sylvain Liechti\n\n\n\n\n\n\n\n\n\n\nAs an international organization with 193 Member States, the United Nations is uniquely positioned to address and solve global issues. Africa\n\n\n\n\n\n\n\n\n\nAgeing\n\n\n\n\n\n\n\n\n\nAIDS\n\n\n\n\n\n\n\n\n\nAtomic Energy\n\n\n\n\n\n\n\n\n\nBig Data for the SDGs\n\n\n\n\n\n\n\n\n\nChild and Youth Safety Online\n\n\n\n\n\n\n\n\n\nChildren\n\n\n\n\n\n\n\n\n\nClimate Change\n\n\n\n\n\n\n\n\n\nDecolonization\n\n\n\n\n\n\n\n\n\nDemocracy\n\n\n\n\n\n\n\n\n\nDisarmament\n\n\n\n\n\n\n\n\n\nEnding Poverty\n\n\n\n\n\n\n\n\n\nFood\n\n\n\n\n\n\n\n\n\nGender Equality\n\n\n\n\n\n\n\n\n\nHealth\n\n\n\n\n\n\n\n\n\nHuman Rights\n\n\n\n\n\n\n\n\n\nInternational Law and Justice\n\n\n\n\n\n\n\n\n\nMigration\n\n\n\n\n\n\n\n\n\nOceans and the Law of the Sea\n\n\n\n\n\n\n\n\n\nPeace and Security\n\n\n\n\n\n\n\n\n\nPopulation\n\n\n\n\n\n\n\n\n\nRefugees\n\n\n\n\n\n\n\n\n\nWater\n\n\n\n\n\n\n\n\n\nYouth\n\n\n\n\n\n\n\n\n \n\nDocuments\n\n©UNOG Library Photo\nThe UN has been publishing documents since its founding. More on the 6 official UN languages\n \n\n \n\n\n\n\n\n\nObservances\nThe existence of international days predates the establishment of the United Nations, but the UN has embraced them as a powerful advocacy tool. International Days and Weeks\n\n\n \n\n\n\n\nInternational Years\n\n\n\n\nInternational Decades\n\n\n\n\nUN Anniversaries\n\nOur Work\n\n\nThe United Nations coordinates its work with the funds, programmes, specialized agencies and other organizations of the UN System. Cooperation between the UN and the other entities of the UN system is essential in order to achieve the purposes of the Organization laid out in the UN Charter. UN's 'work plan'\nAt UN Headquarters in New York, the General Assembly, Security Council, and Economic and Social Council pass resolutions, which set what could informally be called the UN's 'work plan.'\nThe UN Secretariat carries out this work along with UN system entities. What We Do\nThe work of the United Nations covers five main areas:\n\n\n\nMaintain International Peace and Security\nProtect Human Rights\nDeliver Humanitarian Aid\nSupport Sustainable Development and Climate Action\nUphold International Law\n\n\n\nLeft to right: ©UN Photo/Marco Dormino, ©UN Photo/Mark Garten, ©OCHA/Iason Athanasiadis, ©UNEP/Patrick Kihara, ©UN Photo/Sylvain Liechti\n\n\n\n\n\n\n\n\n\n\nAs an international organization with 193 Member States, the United Nations is uniquely positioned to address and solve global issues. Africa\n\n\n\n\n\n\n\n\n\nAgeing\n\n\n\n\n\n\n\n\n\nAIDS\n\n\n\n\n\n\n\n\n\nAtomic Energy\n\n\n\n\n\n\n\n\n\nBig Data for the SDGs\n\n\n\n\n\n\n\n\n\nChild and Youth Safety Online\n\n\n\n\n\n\n\n\n\nChildren\n\n\n\n\n\n\n\n\n\nClimate Change\n\n\n\n\n\n\n\n\n\nDecolonization\n\n\n\n\n\n\n\n\n\nDemocracy\n\n\n\n\n\n\n\n\n\nDisarmament\n\n\n\n\n\n\n\n\n\nEnding Poverty\n\n\n\n\n\n\n\n\n\nFood\n\n\n\n\n\n\n\n\n\nGender Equality\n\n\n\n\n\n\n\n\n\nHealth\n\n\n\n\n\n\n\n\n\nHuman Rights\n\n\n\n\n\n\n\n\n\nInternational Law and Justice\n\n\n\n\n\n\n\n\n\nMigration\n\n\n\n\n\n\n\n\n\nOceans and the Law of the Sea\n\n\n\n\n\n\n\n\n\nPeace and Security\n\n\n\n\n\n\n\n\n\nPopulation\n\n\n\n\n\n\n\n\n\nRefugees\n\n\n\n\n\n\n\n\n\nWater\n\n\n\n\n\n\n\n\n\nYouth\n\n\n\n\n\n\n\n\n \n\nDocuments\n\n©UNOG Library Photo\nThe UN has been publishing documents since its founding. More on the 6 official UN languages\n \n\n \n\n\n\n\n\n\nObservances\nThe existence of international days predates the establishment of the United Nations, but the UN has embraced them as a powerful advocacy tool. International Days and Weeks\n\n\n \n\n\n\n\nInternational Years\n\n\n\n\nInternational Decades\n\n\n\n\nUN Anniversaries\n\nOur Work\n\n\nThe United Nations coordinates its work with the funds, programmes, specialized agencies and other organizations of the UN System. Cooperation between the UN and the other entities of the UN system is essential in order to achieve the purposes of the Organization laid out in the UN Charter. UN's 'work plan'\nAt UN Headquarters in New York, the General Assembly, Security Council, and Economic and Social Council pass resolutions, which set what could informally be called the UN's 'work plan.'\nThe UN Secretariat carries out this work along with UN system entities. What We Do\nThe work of the United Nations covers five main areas:\n\n\n\nMaintain International Peace and Security\nProtect Human Rights\nDeliver Humanitarian Aid\nSupport Sustainable Development and Climate Action\nUphold International Law\n\n\n\nLeft to right: ©UN Photo/Marco Dormino, ©UN Photo/Mark Garten, ©OCHA/Iason Athanasiadis, ©UNEP/Patrick Kihara, ©UN Photo/Sylvain Liechti\n\n\n\n\n\n\n\n\n\n\nAs an international organization with 193 Member States, the United Nations is uniquely positioned to address and solve global issues. Africa\n\n\n\n\n\n\n\n\n\nAgeing\n\n\n\n\n\n\n\n\n\nAIDS\n\n\n\n\n\n\n\n\n\nAtomic Energy\n\n\n\n\n\n\n\n\n\nBig Data for the SDGs\n\n\n\n\n\n\n\n\n\nChild and Youth Safety Online\n\n\n\n\n\n\n\n\n\nChildren\n\n\n\n\n\n\n\n\n\nClimate Change\n\n\n\n\n\n\n\n\n\nDecolonization\n\n\n\n\n\n\n\n\n\nDemocracy\n\n\n\n\n\n\n\n\n\nDisarmament\n\n\n\n\n\n\n\n\n\nEnding Poverty\n\n\n\n\n\n\n\n\n\nFood\n\n\n\n\n\n\n\n\n\nGender Equality\n\n\n\n\n\n\n\n\n\nHealth\n\n\n\n\n\n\n\n\n\nHuman Rights\n\n\n\n\n\n\n\n\n\nInternational Law and Justice\n\n\n\n\n\n\n\n\n\nMigration\n\n\n\n\n\n\n\n\n\nOceans and the Law of the Sea\n\n\n\n\n\n\n\n\n\nPeace and Security\n\n\n\n\n\n\n\n\n\nPopulation\n\n\n\n\n\n\n\n\n\nRefugees\n\n\n\n\n\n\n\n\n\nWater\n\n\n\n\n\n\n\n\n\nYouth\n\n\n\n\n\n\n\n\n \n\nDocuments\n\n©UNOG Library Photo\nThe UN has been publishing documents since its founding. More on the 6 official UN languages\n \n\n \n\n\n\n\n\n\nObservances\nThe existence of international days predates the establishment of the United Nations, but the UN has embraced them as a powerful advocacy tool. International Days and Weeks\n\n\n \n\n\n\n\nInternational Years\n\n\n\n\nInternational Decades\n\n\n\n\nUN Anniversaries\n\nThe United Nations coordinates its work with the funds, programmes, specialized agencies and other organizations of the UN System. Cooperation between the UN and the other entities of the UN system is essential in order to achieve the purposes of the Organization laid out in the UN Charter. Cooperation between the UN and the other entities of the UN system is essential in order to achieve the purposes of the Organization laid out in the UN Charter. Cooperation between the UN and the other entities of the UN system is essential in order to achieve the purposes of the Organization laid out in the UN Charter. UN's 'work plan'\nAt UN Headquarters in New York, the General Assembly, Security Council, and Economic and Social Council pass resolutions, which set what could informally be called the UN's 'work plan.'\nThe UN Secretariat carries out this work along with UN system entities. UN's 'work plan'\nAt UN Headquarters in New York, the General Assembly, Security Council, and Economic and Social Council pass resolutions, which set what could informally be called the UN's 'work plan.'\nThe UN Secretariat carries out this work along with UN system entities. UN's 'work plan'\nAt UN Headquarters in New York, the General Assembly, Security Council, and Economic and Social Council pass resolutions, which set what could informally be called the UN's 'work plan.'\nThe UN Secretariat carries out this work along with UN system entities. UN's 'work plan'\n\nAt UN Headquarters in New York, the General Assembly, Security Council, and Economic and Social Council pass resolutions, which set what could informally be called the UN's 'work plan.'\n\nThe UN Secretariat carries out this work along with UN system entities. What We Do\nThe work of the United Nations covers five main areas:\n\n\n\nMaintain International Peace and Security\nProtect Human Rights\nDeliver Humanitarian Aid\nSupport Sustainable Development and Climate Action\nUphold International Law\n\n\n\nLeft to right: ©UN Photo/Marco Dormino, ©UN Photo/Mark Garten, ©OCHA/Iason Athanasiadis, ©UNEP/Patrick Kihara, ©UN Photo/Sylvain Liechti\n\nWhat We Do\nThe work of the United Nations covers five main areas:\n\n\n\nMaintain International Peace and Security\nProtect Human Rights\nDeliver Humanitarian Aid\nSupport Sustainable Development and Climate Action\nUphold International Law\n\n\n\nLeft to right: ©UN Photo/Marco Dormino, ©UN Photo/Mark Garten, ©OCHA/Iason Athanasiadis, ©UNEP/Patrick Kihara, ©UN Photo/Sylvain Liechti\n\nWhat We Do\nThe work of the United Nations covers five main areas:\n\n\n\nMaintain International Peace and Security\nProtect Human Rights\nDeliver Humanitarian Aid\nSupport Sustainable Development and Climate Action\nUphold International Law\n\n\n\nLeft to right: ©UN Photo/Marco Dormino, ©UN Photo/Mark Garten, ©OCHA/Iason Athanasiadis, ©UNEP/Patrick Kihara, ©UN Photo/Sylvain Liechti\n\nThe work of the United Nations covers five main areas:\n\nMaintain International Peace and Security\nProtect Human Rights\nDeliver Humanitarian Aid\nSupport Sustainable Development and Climate Action\nUphold International Law\n\n\n\nLeft to right: ©UN Photo/Marco Dormino, ©UN Photo/Mark Garten, ©OCHA/Iason Athanasiadis, ©UNEP/Patrick Kihara, ©UN Photo/Sylvain Liechti\n\nMaintain International Peace and Security\nProtect Human Rights\nDeliver Humanitarian Aid\nSupport Sustainable Development and Climate Action\nUphold International Law\n\nLeft to right: ©UN Photo/Marco Dormino, ©UN Photo/Mark Garten, ©OCHA/Iason Athanasiadis, ©UNEP/Patrick Kihara, ©UN Photo/Sylvain Liechti\n\nLeft to right: ©UN Photo/Marco Dormino, ©UN Photo/Mark Garten, ©OCHA/Iason Athanasiadis, ©UNEP/Patrick Kihara, ©UN Photo/Sylvain Liechti\n\nAs an international organization with 193 Member States, the United Nations is uniquely positioned to address and solve global issues. Africa\n\n\n\n\n\n\n\n\n\nAgeing\n\n\n\n\n\n\n\n\n\nAIDS\n\n\n\n\n\n\n\n\n\nAtomic Energy\n\n\n\n\n\n\n\n\n\nBig Data for the SDGs\n\n\n\n\n\n\n\n\n\nChild and Youth Safety Online\n\n\n\n\n\n\n\n\n\nChildren\n\n\n\n\n\n\n\n\n\nClimate Change\n\n\n\n\n\n\n\n\n\nDecolonization\n\n\n\n\n\n\n\n\n\nDemocracy\n\n\n\n\n\n\n\n\n\nDisarmament\n\n\n\n\n\n\n\n\n\nEnding Poverty\n\n\n\n\n\n\n\n\n\nFood\n\n\n\n\n\n\n\n\n\nGender Equality\n\n\n\n\n\n\n\n\n\nHealth\n\n\n\n\n\n\n\n\n\nHuman Rights\n\n\n\n\n\n\n\n\n\nInternational Law and Justice\n\n\n\n\n\n\n\n\n\nMigration\n\n\n\n\n\n\n\n\n\nOceans and the Law of the Sea\n\n\n\n\n\n\n\n\n\nPeace and Security\n\n\n\n\n\n\n\n\n\nPopulation\n\n\n\n\n\n\n\n\n\nRefugees\n\n\n\n\n\n\n\n\n\nWater\n\n\n\n\n\n\n\n\n\nYouth\n\nAfrica\n\n\n\n\n\n\n\n\n\nAgeing\n\n\n\n\n\n\n\n\n\nAIDS\n\n\n\n\n\n\n\n\n\nAtomic Energy\n\n\n\n\n\n\n\n\n\nBig Data for the SDGs\n\n\n\n\n\n\n\n\n\nChild and Youth Safety Online\n\n\n\n\n\n\n\n\n\nChildren\n\n\n\n\n\n\n\n\n\nClimate Change\n\n\n\n\n\n\n\n\n\nDecolonization\n\n\n\n\n\n\n\n\n\nDemocracy\n\n\n\n\n\n\n\n\n\nDisarmament\n\n\n\n\n\n\n\n\n\nEnding Poverty\n\n\n\n\n\n\n\n\n\nFood\n\n\n\n\n\n\n\n\n\nGender Equality\n\n\n\n\n\n\n\n\n\nHealth\n\n\n\n\n\n\n\n\n\nHuman Rights\n\n\n\n\n\n\n\n\n\nInternational Law and Justice\n\n\n\n\n\n\n\n\n\nMigration\n\n\n\n\n\n\n\n\n\nOceans and the Law of the Sea\n\n\n\n\n\n\n\n\n\nPeace and Security\n\n\n\n\n\n\n\n\n\nPopulation\n\n\n\n\n\n\n\n\n\nRefugees\n\n\n\n\n\n\n\n\n\nWater\n\n\n\n\n\n\n\n\n\nYouth\n\nAfrica\n\nAfrica\n\nAfrica\n\nAfrica\n\nAfrica\n\nAgeing\n\nAgeing\n\nAgeing\n\nAgeing\n\nAgeing\n\nAIDS\n\nAIDS\n\nAIDS\n\nAIDS\n\nAIDS\n\nAtomic Energy\n\nAtomic Energy\n\nAtomic Energy\n\nAtomic Energy\n\nAtomic Energy\n\nBig Data for the SDGs\n\nBig Data for the SDGs\n\nBig Data for the SDGs\n\nBig Data for the SDGs\n\nBig Data for the SDGs\n\nChild and Youth Safety Online\n\nChild and Youth Safety Online\n\nChild and Youth Safety Online\n\nChild and Youth Safety Online\n\nChild and Youth Safety Online\n\nChildren\n\nChildren\n\nChildren\n\nChildren\n\nChildren\n\nClimate Change\n\nClimate Change\n\nClimate Change\n\nClimate Change\n\nClimate Change\n\nDecolonization\n\nDecolonization\n\nDecolonization\n\nDecolonization\n\nDecolonization\n\nDemocracy\n\nDemocracy\n\nDemocracy\n\nDemocracy\n\nDemocracy\n\nDisarmament\n\nDisarmament\n\nDisarmament\n\nDisarmament\n\nDisarmament\n\nEnding Poverty\n\nEnding Poverty\n\nEnding Poverty\n\nEnding Poverty\n\nEnding Poverty\n\nFood\n\nFood\n\nFood\n\nFood\n\nFood\n\nGender Equality\n\nGender Equality\n\nGender Equality\n\nGender Equality\n\nGender Equality\n\nHealth\n\nHealth\n\nHealth\n\nHealth\n\nHealth\n\nHuman Rights\n\nHuman Rights\n\nHuman Rights\n\nHuman Rights\n\nHuman Rights\n\nInternational Law and Justice\n\nInternational Law and Justice\n\nInternational Law and Justice\n\nInternational Law and Justice\n\nInternational Law and Justice\n\nMigration\n\nMigration\n\nMigration\n\nMigration\n\nMigration\n\nOceans and the Law of the Sea\n\nOceans and the Law of the Sea\n\nOceans and the Law of the Sea\n\nOceans and the Law of the Sea\n\nOceans and the Law of the Sea\n\nPeace and Security\n\nPeace and Security\n\nPeace and Security\n\nPeace and Security\n\nPeace and Security\n\nPopulation\n\nPopulation\n\nPopulation\n\nPopulation\n\nPopulation\n\nRefugees\n\nRefugees\n\nRefugees\n\nRefugees\n\nRefugees\n\nWater\n\nWater\n\nWater\n\nWater\n\nWater\n\nYouth\n\nYouth\n\nYouth\n\nYouth\n\nYouth\n\nDocuments\n\n©UNOG Library Photo\nThe UN has been publishing documents since its founding. More on the 6 official UN languages\n\nObservances\nThe existence of international days predates the establishment of the United Nations, but the UN has embraced them as a powerful advocacy tool. International Days and Weeks\n\n\n \n\n\n\n\nInternational Years\n\n\n\n\nInternational Decades\n\n\n\n\nUN Anniversaries\n\nObservances\nThe existence of international days predates the establishment of the United Nations, but the UN has embraced them as a powerful advocacy tool. International Days and Weeks\n\n\n \n\n\n\n\nInternational Years\n\n\n\n\nInternational Decades\n\n\n\n\nUN Anniversaries\n\nInternational Days and Weeks\n\n\n \n\n\n\n\nInternational Years\n\n\n\n\nInternational Decades\n\n\n\n\nUN Anniversaries\n\nInternational Days and Weeks\n\nInternational Days and Weeks\n\nInternational Days and Weeks\n\nInternational Years\n\n\n\n\nInternational Decades\n\n\n\n\nUN Anniversaries\n\nInternational Years\n\nInternational Years\n\nInternational Decades\n\nInternational Decades\n\nUN Anniversaries\n\nUN Anniversaries\n\nMain Bodies   General Assembly   Security Council   Economic and Social Council   Trusteeship Council   International Court of Justice   Secretariat       Departments / Offices   New York   Geneva   Nairobi   Vienna   UN System Directory   UN System Chart   Global Leadership   UN Information Centres       Resources / Services   Emergency information   Reporting Wrongdoing   UN Journal   Documents   Guidelines for gender-inclusive language   Databases   Library   UN iLibrary   UN Chronicle   UN Yearbook   Bookshop   Publications for sale   Maps   Media Accreditation   NGO accreditation at ECOSOC   NGO accreditation at DGC   Visitors’ services   Exhibits   Procurement   Employment   Internships   Model UN   Academic Impact   UN Archives   UN Audiovisual Library   How to donate to the UN system   Information on COVID-19 (Coronavirus)   Africa Renewal   Ten ways the UN makes a difference   GA High-level week 2024       Key Documents   UN Charter   Universal Declaration of Human Rights   Convention on the Rights of the Child   Statute of the International Court of Justice   Annual Report of the Secretary-General on the Work of the Organization       News and Media   News   Press Releases   Briefings   Spokesperson   Photos   UNIfeed   UN Web TV   UN Video   Social Media   The Essential UN   Awake at Night podcast       Issues / Campaigns   Global Issues   Observances   Sustainable Development Goals   Our Common Agenda   The Summit of the Future   Climate Action   Peace and Security   Action for Peacekeeping (A4P)   Global Crisis Response Group   Call to Action for Human Rights   Disability Inclusion Strategy   Fight Racism   Hate Speech   LGBTIQ+ People   Safety of Journalists   Rule of Law   Action to Counter Terrorism   Victims of Terrorism   Children and Armed Conflict   Violence Against Children (SRSG)   Sexual Violence in Conflict   Refugees and Migrants   Action Agenda on Internal Displacement   Spotlight Initiative   Preventing Sexual Exploitation and Abuse   Prevention of Genocide and the Responsibility to Protect   The Rwanda Genocide   The Holocaust   The Question of Palestine   The Transatlantic Slave Trade   Decolonization   Messengers of Peace   Roadmap for Digital Cooperation   Digital Financing Task Force   Data Strategy   Information Integrity   Countering Disinformation   UN75: 2020 and Beyond   Women Rise for All   Stop the Red Sea Catastrophe   Black Sea Grain Initiative Joint Coordination Centre\n\nMain Bodies   General Assembly   Security Council   Economic and Social Council   Trusteeship Council   International Court of Justice   Secretariat       Departments / Offices   New York   Geneva   Nairobi   Vienna   UN System Directory   UN System Chart   Global Leadership   UN Information Centres       Resources / Services   Emergency information   Reporting Wrongdoing   UN Journal   Documents   Guidelines for gender-inclusive language   Databases   Library   UN iLibrary   UN Chronicle   UN Yearbook   Bookshop   Publications for sale   Maps   Media Accreditation   NGO accreditation at ECOSOC   NGO accreditation at DGC   Visitors’ services   Exhibits   Procurement   Employment   Internships   Model UN   Academic Impact   UN Archives   UN Audiovisual Library   How to donate to the UN system   Information on COVID-19 (Coronavirus)   Africa Renewal   Ten ways the UN makes a difference   GA High-level week 2024       Key Documents   UN Charter   Universal Declaration of Human Rights   Convention on the Rights of the Child   Statute of the International Court of Justice   Annual Report of the Secretary-General on the Work of the Organization       News and Media   News   Press Releases   Briefings   Spokesperson   Photos   UNIfeed   UN Web TV   UN Video   Social Media   The Essential UN   Awake at Night podcast       Issues / Campaigns   Global Issues   Observances   Sustainable Development Goals   Our Common Agenda   The Summit of the Future   Climate Action   Peace and Security   Action for Peacekeeping (A4P)   Global Crisis Response Group   Call to Action for Human Rights   Disability Inclusion Strategy   Fight Racism   Hate Speech   LGBTIQ+ People   Safety of Journalists   Rule of Law   Action to Counter Terrorism   Victims of Terrorism   Children and Armed Conflict   Violence Against Children (SRSG)   Sexual Violence in Conflict   Refugees and Migrants   Action Agenda on Internal Displacement   Spotlight Initiative   Preventing Sexual Exploitation and Abuse   Prevention of Genocide and the Responsibility to Protect   The Rwanda Genocide   The Holocaust   The Question of Palestine   The Transatlantic Slave Trade   Decolonization   Messengers of Peace   Roadmap for Digital Cooperation   Digital Financing Task Force   Data Strategy   Information Integrity   Countering Disinformation   UN75: 2020 and Beyond   Women Rise for All   Stop the Red Sea Catastrophe   Black Sea Grain Initiative Joint Coordination Centre\n\nMain Bodies   General Assembly   Security Council   Economic and Social Council   Trusteeship Council   International Court of Justice   Secretariat       Departments / Offices   New York   Geneva   Nairobi   Vienna   UN System Directory   UN System Chart   Global Leadership   UN Information Centres       Resources / Services   Emergency information   Reporting Wrongdoing   UN Journal   Documents   Guidelines for gender-inclusive language   Databases   Library   UN iLibrary   UN Chronicle   UN Yearbook   Bookshop   Publications for sale   Maps   Media Accreditation   NGO accreditation at ECOSOC   NGO accreditation at DGC   Visitors’ services   Exhibits   Procurement   Employment   Internships   Model UN   Academic Impact   UN Archives   UN Audiovisual Library   How to donate to the UN system   Information on COVID-19 (Coronavirus)   Africa Renewal   Ten ways the UN makes a difference   GA High-level week 2024       Key Documents   UN Charter   Universal Declaration of Human Rights   Convention on the Rights of the Child   Statute of the International Court of Justice   Annual Report of the Secretary-General on the Work of the Organization       News and Media   News   Press Releases   Briefings   Spokesperson   Photos   UNIfeed   UN Web TV   UN Video   Social Media   The Essential UN   Awake at Night podcast       Issues / Campaigns   Global Issues   Observances   Sustainable Development Goals   Our Common Agenda   The Summit of the Future   Climate Action   Peace and Security   Action for Peacekeeping (A4P)   Global Crisis Response Group   Call to Action for Human Rights   Disability Inclusion Strategy   Fight Racism   Hate Speech   LGBTIQ+ People   Safety of Journalists   Rule of Law   Action to Counter Terrorism   Victims of Terrorism   Children and Armed Conflict   Violence Against Children (SRSG)   Sexual Violence in Conflict   Refugees and Migrants   Action Agenda on Internal Displacement   Spotlight Initiative   Preventing Sexual Exploitation and Abuse   Prevention of Genocide and the Responsibility to Protect   The Rwanda Genocide   The Holocaust   The Question of Palestine   The Transatlantic Slave Trade   Decolonization   Messengers of Peace   Roadmap for Digital Cooperation   Digital Financing Task Force   Data Strategy   Information Integrity   Countering Disinformation   UN75: 2020 and Beyond   Women Rise for All   Stop the Red Sea Catastrophe   Black Sea Grain Initiative Joint Coordination Centre\n\nMain Bodies   General Assembly   Security Council   Economic and Social Council   Trusteeship Council   International Court of Justice   Secretariat       Departments / Offices   New York   Geneva   Nairobi   Vienna   UN System Directory   UN System Chart   Global Leadership   UN Information Centres\n\nMain Bodies   General Assembly   Security Council   Economic and Social Council   Trusteeship Council   International Court of Justice   Secretariat\n\nMain Bodies   General Assembly   Security Council   Economic and Social Council   Trusteeship Council   International Court of Justice   Secretariat\n\nDepartments / Offices   New York   Geneva   Nairobi   Vienna   UN System Directory   UN System Chart   Global Leadership   UN Information Centres\n\nDepartments / Offices   New York   Geneva   Nairobi   Vienna   UN System Directory   UN System Chart   Global Leadership   UN Information Centres\n\nResources / Services   Emergency information   Reporting Wrongdoing   UN Journal   Documents   Guidelines for gender-inclusive language   Databases   Library   UN iLibrary   UN Chronicle   UN Yearbook   Bookshop   Publications for sale   Maps   Media Accreditation   NGO accreditation at ECOSOC   NGO accreditation at DGC   Visitors’ services   Exhibits   Procurement   Employment   Internships   Model UN   Academic Impact   UN Archives   UN Audiovisual Library   How to donate to the UN system   Information on COVID-19 (Coronavirus)   Africa Renewal   Ten ways the UN makes a difference   GA High-level week 2024\n\nResources / Services   Emergency information   Reporting Wrongdoing   UN Journal   Documents   Guidelines for gender-inclusive language   Databases   Library   UN iLibrary   UN Chronicle   UN Yearbook   Bookshop   Publications for sale   Maps   Media Accreditation   NGO accreditation at ECOSOC   NGO accreditation at DGC   Visitors’ services   Exhibits   Procurement   Employment   Internships   Model UN   Academic Impact   UN Archives   UN Audiovisual Library   How to donate to the UN system   Information on COVID-19 (Coronavirus)   Africa Renewal   Ten ways the UN makes a difference   GA High-level week 2024\n\nResources / Services   Emergency information   Reporting Wrongdoing   UN Journal   Documents   Guidelines for gender-inclusive language   Databases   Library   UN iLibrary   UN Chronicle   UN Yearbook   Bookshop   Publications for sale   Maps   Media Accreditation   NGO accreditation at ECOSOC   NGO accreditation at DGC   Visitors’ services   Exhibits   Procurement   Employment   Internships   Model UN   Academic Impact   UN Archives   UN Audiovisual Library   How to donate to the UN system   Information on COVID-19 (Coronavirus)   Africa Renewal   Ten ways the UN makes a difference   GA High-level week 2024\n\nKey Documents   UN Charter   Universal Declaration of Human Rights   Convention on the Rights of the Child   Statute of the International Court of Justice   Annual Report of the Secretary-General on the Work of the Organization       News and Media   News   Press Releases   Briefings   Spokesperson   Photos   UNIfeed   UN Web TV   UN Video   Social Media   The Essential UN   Awake at Night podcast\n\nKey Documents   UN Charter   Universal Declaration of Human Rights   Convention on the Rights of the Child   Statute of the International Court of Justice   Annual Report of the Secretary-General on the Work of the Organization\n\nKey Documents   UN Charter   Universal Declaration of Human Rights   Convention on the Rights of the Child   Statute of the International Court of Justice   Annual Report of the Secretary-General on the Work of the Organization\n\nNews and Media   News   Press Releases   Briefings   Spokesperson   Photos   UNIfeed   UN Web TV   UN Video   Social Media   The Essential UN   Awake at Night podcast\n\nNews and Media   News   Press Releases   Briefings   Spokesperson   Photos   UNIfeed   UN Web TV   UN Video   Social Media   The Essential UN   Awake at Night podcast\n\nIssues / Campaigns   Global Issues   Observances   Sustainable Development Goals   Our Common Agenda   The Summit of the Future   Climate Action   Peace and Security   Action for Peacekeeping (A4P)   Global Crisis Response Group   Call to Action for Human Rights   Disability Inclusion Strategy   Fight Racism   Hate Speech   LGBTIQ+ People   Safety of Journalists   Rule of Law   Action to Counter Terrorism   Victims of Terrorism   Children and Armed Conflict   Violence Against Children (SRSG)   Sexual Violence in Conflict   Refugees and Migrants   Action Agenda on Internal Displacement   Spotlight Initiative   Preventing Sexual Exploitation and Abuse   Prevention of Genocide and the Responsibility to Protect   The Rwanda Genocide   The Holocaust   The Question of Palestine   The Transatlantic Slave Trade   Decolonization   Messengers of Peace   Roadmap for Digital Cooperation   Digital Financing Task Force   Data Strategy   Information Integrity   Countering Disinformation   UN75: 2020 and Beyond   Women Rise for All   Stop the Red Sea Catastrophe   Black Sea Grain Initiative Joint Coordination Centre\n\nIssues / Campaigns   Global Issues   Observances   Sustainable Development Goals   Our Common Agenda   The Summit of the Future   Climate Action   Peace and Security   Action for Peacekeeping (A4P)   Global Crisis Response Group   Call to Action for Human Rights   Disability Inclusion Strategy   Fight Racism   Hate Speech   LGBTIQ+ People   Safety of Journalists   Rule of Law   Action to Counter Terrorism   Victims of Terrorism   Children and Armed Conflict   Violence Against Children (SRSG)   Sexual Violence in Conflict   Refugees and Migrants   Action Agenda on Internal Displacement   Spotlight Initiative   Preventing Sexual Exploitation and Abuse   Prevention of Genocide and the Responsibility to Protect   The Rwanda Genocide   The Holocaust   The Question of Palestine   The Transatlantic Slave Trade   Decolonization   Messengers of Peace   Roadmap for Digital Cooperation   Digital Financing Task Force   Data Strategy   Information Integrity   Countering Disinformation   UN75: 2020 and Beyond   Women Rise for All   Stop the Red Sea Catastrophe   Black Sea Grain Initiative Joint Coordination Centre\n\nIssues / Campaigns   Global Issues   Observances   Sustainable Development Goals   Our Common Agenda   The Summit of the Future   Climate Action   Peace and Security   Action for Peacekeeping (A4P)   Global Crisis Response Group   Call to Action for Human Rights   Disability Inclusion Strategy   Fight Racism   Hate Speech   LGBTIQ+ People   Safety of Journalists   Rule of Law   Action to Counter Terrorism   Victims of Terrorism   Children and Armed Conflict   Violence Against Children (SRSG)   Sexual Violence in Conflict   Refugees and Migrants   Action Agenda on Internal Displacement   Spotlight Initiative   Preventing Sexual Exploitation and Abuse   Prevention of Genocide and the Responsibility to Protect   The Rwanda Genocide   The Holocaust   The Question of Palestine   The Transatlantic Slave Trade   Decolonization   Messengers of Peace   Roadmap for Digital Cooperation   Digital Financing Task Force   Data Strategy   Information Integrity   Countering Disinformation   UN75: 2020 and Beyond   Women Rise for All   Stop the Red Sea Catastrophe   Black Sea Grain Initiative Joint Coordination Centre",
  "entities": {
    "countries": [
      "russia"
    ],
    "organizations": [
      "united nations",
      "un"
    ],
    "key_issues": [
      "issue",
      "problem",
      "challenge",
      "crisis",
      "country",
      "nation",
      "state",
      "region",
      "solution",
      "resolution",
      "strategy",
      "initiative",
      "program",
      "action",
      "development",
      "humanitarian",
      "human rights",
      "aid",
      "economic",
      "trade",
      "united nations",
      "un",
      "security council",
      "general assembly",
      "ngo",
      "organization"
    ]
  },
  "committee": "Fourth Committee",
  "topic": "Ensuring the rights and safety of indigenous populations"
}