{
  "url": "https://www.un.org/en/about-us/growth-in-un-membership",
  "title": "Growth in United Nations membership | United Nations",
  "text": "Skip to main content\n\nGrowth in United Nations membership\n\n\n\n\n\n\n\n\n\n\n\n\n\n\n1945-1950          1950s          1960s          1970s          1980s          1990s          2000-Present\n\n\n \n \n\n\n\nOriginal 51 Members (1945)\n\n\n\nArgentina, Australia, Belgium, Bolivia, Brazil, Byelorussian Soviet Socialist Republic, Canada, Chile, China, Colombia, Costa Rica, Cuba, Czechoslovakia, Denmark, Dominican Republic, Ecuador, Egypt, El Salvador, Ethiopia, France, Greece, Guatemala, Haiti, Honduras, India, Iran, Iraq, Lebanon, Liberia, Luxembourg, Mexico, Netherlands, New Zealand, Nicaragua, Norway, Panama, Paraguay, Peru, Philippine Republic, Poland, Saudi Arabia, Syria, Turkey, Ukrainian Soviet Socialist Republic, Union of South Africa, Union of Soviet Socialist Republics, United Kingdom, United States, Uruguay, Venezuela, Yugoslavia\n\n\n\n\n\n55 Members (1946)\n\n\n\nAdded: Afghanistan, Iceland, Siam, Sweden\n\n\n\n\n\n57 Members (1947)\n\n\n\nAdded: Pakistan, Yemen (the Yemen Arab Republic)\n\n\n\n\n\n58 Members (1948)\n\n\n\nAdded: Burma\n\n\n\n \n\n59 Members (1949)\n\n\n\nAdded: Israel\n\n\n\n\n\n60 Members (1950)\n\n\n\nAdded: Indonesia\n\n\n\n\n\n76 Members (1955)\n\n\n\nAdded: Albania, Austria, Bulgaria, Cambodia, Ceylon, Finland, Hungary, Ireland, Italy, Jordan, Laos, Libya, Nepal, Portugal, Romania, Spain\n\n\n\n\n\n80 Members (1956)\n\n\n\nAdded: Japan, Morocco, Sudan, Tunisia\n\n\n\n\n\n82 Members (1957)\n\n\n\nAdded: Ghana, Federation of Malaya\n\n\n\n \n\n82 Members (1958)*\n\n\n\nAdded: Guinea\n\t\t\t\t\t\t\t\t* On 22 February 1958, Syria merged with Egypt (both original members of the United Nations) to become the United Arab Republic. \n\n\n\n\n\n99 Members (1960)\n\n\n\nAdded: Cameroun, Central African Republic, Chad, Congo (Brazzaville), Congo (Leopoldville), Cyprus, Dahomey, Gabon, Ivory Coast, Malagasy Republic, Mali, Niger, Nigeria, Senegal, Somalia, Togo, Upper Volta\n\n\n\n\n\n104 Members (1961)*\n\n\n\nAdded: Mauritania, Mongolia, Sierra Leone, Tanganyika\n\t\t\t\t\t\t\t\t*On 13 October 1961, Syria, having resumed its status as an independent State from the United Arab Republic, resumed its separate membership in the United Nations.\n\n\n\n\n\n110 Members (1962)\n\n\n\nAdded: Algeria, Burundi, Jamaica, Rwanda, Trinidad and Tobago, Uganda\n\n\n\n\n\n113 Members (1963)\n\n\n\nAdded: Kenya, Kuwait, Zanzibar\n\n\n\n\n\n115 Members (1964)*\n\n\n\nAdded: Malawi, Malta, Zambia\n\t\t\t\t\t\t\t\t*On 26 April 1964, Zanzibar merged with Tanganyika to become the United Republic of Tanzania.\n\n\n\n\n\n117 Members (1965)*\n\n\n\nAdded: The Gambia, Maldive Islands, Singapore\n\t\t\t\t\t\t\t\t*On 20 January 1965, Indonesia temporarily withdrew from the United Nations.\n\n\n\n\n\n122 Members (1966)*\n\n\n\nAdded: Barbados, Botswana, Guyana, Lesotho\n\t\t\t\t\t\t\t\t* On 28 September 1966, Indonesia rejoined the United Nations.\n\n\n\n\n\n123 Members (1967)\n\n\n\nAdded: Yemen (People's Democratic Republic of Yemen)\n\n\n\n \n\n126 Members (1968)\n\n\n\nAdded: Equatorial Guinea, Mauritius, Swaziland\n\n\n\n\n\n127 Members (1970)\n\n\n\nAdded: Fiji\n\n\n\n\n\n132 Members (1971)\n\n\n\nAdded: Bahrain, Bhutan, Oman, Qatar, United Arab Emirates\n\n\n\n\n\n135 Members (1973)\n\n\n\nAdded: Bahamas, Federal Republic of Germany, German Democratic Republic\n\n\n\n\n\n138 Members (1974)\n\n\n\nAdded: Bangladesh, Grenada, Guinea-Bissau\n\n\n\n\n\n144 Members (1975)\n\n\n\nAdded: Cape Verde, Comoros, Mozambique, Papua New Guinea, Sao Tome and Principe, Suriname\n\n\n\n\n\n147 Members (1976)\n\n\n\nAdded: Angola, Samoa, Seychelles\n\n\n\n\n\n149 Members (1977)\n\n\n\nAdded: Djibouti, Viet Nam\n\n\n\n\n\n151 Members (1978)\n\n\n\nAdded: Dominica, Solomon Islands\n\n\n\n \n\n152 Members (1979)\n\n\n\nAdded: Saint Lucia\n\n\n\n\n\n154 Members (1980)\n\n\n\nAdded: Saint Vincent and the Grenadines, Zimbabwe\n\n\n\n\n\n157 Members (1981) \n\n\n\nAdded: Antigua and Barbuda, Belize, Vanuatu\n\n\n\n\n\n158 Members (1983)\n\n\n\nAdded: Saint Christopher and Nevis\n\n\n\n \n\n159 Members (1984)\n\n\n\nAdded: Brunei Darussalam\n\n\n\n\n\n159 Members (1990)*\n\n\n\nAdded: Liechtenstein, Namibia\n\t\t\t\t\t\t\t\t*On 22 May 1990, the People's Democratic Republic of Yemen (member since 1967) was united with the Yemen Arab Republic (member since 1947), forming the Republic of Yemen. \n\t\t\t\t\t\t\t\tOn 3 October 1990, the German Democratic Republic acceded to the Federal Republic of Germany (both members since 1973), resulting in the reunification of Germany.\n\n\n\n\n\n166 Members (1991)\n\n\n\nAdded: Democratic People's Republic of Korea, Estonia, Latvia, Lithuania, Marshall Islands, Federated States of Micronesia, Republic of Korea\n\n\n\n\n\n179 Members (1992)\n\n\n\nAdded: Armenia, Azerbaijan, Bosnia and Herzegovina, Croatia, Georgia, Kazakhstan, Kyrgyzstan, Republic of Moldova, San Marino, Slovenia, Tajikistan, Turkmenistan, Uzbekistan\n\n\n\n\n\n184 Members (1993)*\n\n\n\nAdded: Andorra, Czech Republic, Eritrea, Monaco, Slovakia, The former Yugoslav Republic of Macedonia\n\t\t\t\t\t\t\t\t*Czechoslovakia was an original Member of the United Nations from 24 October 1945. The Czech and Slovak Federal Republic ceased to exist on 31 December 1992. On 19 January 1993, the Czech Republic and the Slovak Republic were both admitted separately to United Nations membership.\n\n\n\n\n\n185 Members (1994)\n\n\n\nAdded: Palau\n\n\n\n \n\n188 Members (1999)\n\n\n\nAdded: Kiribati, Nauru, Tonga\n\n\n\n\n\n189 Members (2000)*\n\n\n\nAdded: Federal Republic of Yugoslavia, Tuvalu\n\t\t\t\t\t\t\t\t*The Federal Republic of Yugoslavia was part of the Socialist Federal Republic of Yugoslavia, which was an original member of the United Nations and was removed from the official roster of UN members in 2000, following its dissolution.\n\n\n\n\n\n191 Members (2002)\n\n\n\nAdded: Switzerland, Timor-Leste\n\n\n\n\n\n192 Members (2006)\n\n\n\nAdded: Montenegro\n\n\n\n\n\n193 Members (2011)\n\n\n\nAdded: South Sudan\n\n\n\n\n\n\n\n\n\n\n\nMEMBER STATES\n\nMembership \n\nAbout UN Membership\nList of UN Member States\nUN Membership research guide\nGrowth in UN Membership\nMembership of Principal UN Organs\nContributions to UN regular budget\nHonour Roll: Contribution Received in Full\nArrears in the Payment of Contribution\n\n\nPermanent Missions\n\nNew York\nGeneva\nVienna\n\n\nPermanent Observers\n\nAbout Permanent Observers\nNon-Member States\nIntergovernmental and Other Organizations\nSpecialized Agencies \n\n\n\n \n\nQuick links for delegates\n\nDelegate (UN Intranet - iSeek for Member States)\nBlue Book\nDelegates' Handbook\nManual of Protocol\n\n\n\n\n\n\n\n\n\n\n\n\n\n\n\n\n\n\n\n\n\n\n\n\n \n\n\n\n        Main Bodies   General Assembly   Security Council   Economic and Social Council   Trusteeship Council   International Court of Justice   Secretariat       Departments / Offices   New York   Geneva   Nairobi   Vienna   UN System Directory   UN System Chart   Global Leadership   UN Information Centres       Resources / Services   Emergency information   Reporting Wrongdoing   UN Journal   Documents   Guidelines for gender-inclusive language   Databases   Library   UN iLibrary   UN Chronicle   UN Yearbook   Bookshop   Publications for sale   Maps   Media Accreditation   NGO accreditation at ECOSOC   NGO accreditation at DGC   Visitors’ services   Exhibits   Procurement   Employment   Internships   Model UN   Academic Impact   UN Archives   UN Audiovisual Library   How to donate to the UN system   Information on COVID-19 (Coronavirus)   Africa Renewal   Ten ways the UN makes a difference   GA High-level week 2024       Key Documents   UN Charter   Universal Declaration of Human Rights   Convention on the Rights of the Child   Statute of the International Court of Justice   Annual Report of the Secretary-General on the Work of the Organization       News and Media   News   Press Releases   Briefings   Spokesperson   Photos   UNIfeed   UN Web TV   UN Video   Social Media   The Essential UN   Awake at Night podcast       Issues / Campaigns   Global Issues   Observances   Sustainable Development Goals   Our Common Agenda   The Summit of the Future   Climate Action   Peace and Security   Action for Peacekeeping (A4P)   Global Crisis Response Group   Call to Action for Human Rights   Disability Inclusion Strategy   Fight Racism   Hate Speech   LGBTIQ+ People   Safety of Journalists   Rule of Law   Action to Counter Terrorism   Victims of Terrorism   Children and Armed Conflict   Violence Against Children (SRSG)   Sexual Violence in Conflict   Refugees and Migrants   Action Agenda on Internal Displacement   Spotlight Initiative   Preventing Sexual Exploitation and Abuse   Prevention of Genocide and the Responsibility to Protect   The Rwanda Genocide   The Holocaust   The Question of Palestine   The Transatlantic Slave Trade   Decolonization   Messengers of Peace   Roadmap for Digital Cooperation   Digital Financing Task Force   Data Strategy   Information Integrity   Countering Disinformation   UN75: 2020 and Beyond   Women Rise for All   Stop the Red Sea Catastrophe   Black Sea Grain Initiative Joint Coordination Centre\n\nGrowth in United Nations membership\n\n\n\n\n\n\n\n\n\n\n\n\n\n\n1945-1950          1950s          1960s          1970s          1980s          1990s          2000-Present\n\n\n \n \n\n\n\nOriginal 51 Members (1945)\n\n\n\nArgentina, Australia, Belgium, Bolivia, Brazil, Byelorussian Soviet Socialist Republic, Canada, Chile, China, Colombia, Costa Rica, Cuba, Czechoslovakia, Denmark, Dominican Republic, Ecuador, Egypt, El Salvador, Ethiopia, France, Greece, Guatemala, Haiti, Honduras, India, Iran, Iraq, Lebanon, Liberia, Luxembourg, Mexico, Netherlands, New Zealand, Nicaragua, Norway, Panama, Paraguay, Peru, Philippine Republic, Poland, Saudi Arabia, Syria, Turkey, Ukrainian Soviet Socialist Republic, Union of South Africa, Union of Soviet Socialist Republics, United Kingdom, United States, Uruguay, Venezuela, Yugoslavia\n\n\n\n\n\n55 Members (1946)\n\n\n\nAdded: Afghanistan, Iceland, Siam, Sweden\n\n\n\n\n\n57 Members (1947)\n\n\n\nAdded: Pakistan, Yemen (the Yemen Arab Republic)\n\n\n\n\n\n58 Members (1948)\n\n\n\nAdded: Burma\n\n\n\n \n\n59 Members (1949)\n\n\n\nAdded: Israel\n\n\n\n\n\n60 Members (1950)\n\n\n\nAdded: Indonesia\n\n\n\n\n\n76 Members (1955)\n\n\n\nAdded: Albania, Austria, Bulgaria, Cambodia, Ceylon, Finland, Hungary, Ireland, Italy, Jordan, Laos, Libya, Nepal, Portugal, Romania, Spain\n\n\n\n\n\n80 Members (1956)\n\n\n\nAdded: Japan, Morocco, Sudan, Tunisia\n\n\n\n\n\n82 Members (1957)\n\n\n\nAdded: Ghana, Federation of Malaya\n\n\n\n \n\n82 Members (1958)*\n\n\n\nAdded: Guinea\n\t\t\t\t\t\t\t\t* On 22 February 1958, Syria merged with Egypt (both original members of the United Nations) to become the United Arab Republic. \n\n\n\n\n\n99 Members (1960)\n\n\n\nAdded: Cameroun, Central African Republic, Chad, Congo (Brazzaville), Congo (Leopoldville), Cyprus, Dahomey, Gabon, Ivory Coast, Malagasy Republic, Mali, Niger, Nigeria, Senegal, Somalia, Togo, Upper Volta\n\n\n\n\n\n104 Members (1961)*\n\n\n\nAdded: Mauritania, Mongolia, Sierra Leone, Tanganyika\n\t\t\t\t\t\t\t\t*On 13 October 1961, Syria, having resumed its status as an independent State from the United Arab Republic, resumed its separate membership in the United Nations.\n\n\n\n\n\n110 Members (1962)\n\n\n\nAdded: Algeria, Burundi, Jamaica, Rwanda, Trinidad and Tobago, Uganda\n\n\n\n\n\n113 Members (1963)\n\n\n\nAdded: Kenya, Kuwait, Zanzibar\n\n\n\n\n\n115 Members (1964)*\n\n\n\nAdded: Malawi, Malta, Zambia\n\t\t\t\t\t\t\t\t*On 26 April 1964, Zanzibar merged with Tanganyika to become the United Republic of Tanzania.\n\n\n\n\n\n117 Members (1965)*\n\n\n\nAdded: The Gambia, Maldive Islands, Singapore\n\t\t\t\t\t\t\t\t*On 20 January 1965, Indonesia temporarily withdrew from the United Nations.\n\n\n\n\n\n122 Members (1966)*\n\n\n\nAdded: Barbados, Botswana, Guyana, Lesotho\n\t\t\t\t\t\t\t\t* On 28 September 1966, Indonesia rejoined the United Nations.\n\n\n\n\n\n123 Members (1967)\n\n\n\nAdded: Yemen (People's Democratic Republic of Yemen)\n\n\n\n \n\n126 Members (1968)\n\n\n\nAdded: Equatorial Guinea, Mauritius, Swaziland\n\n\n\n\n\n127 Members (1970)\n\n\n\nAdded: Fiji\n\n\n\n\n\n132 Members (1971)\n\n\n\nAdded: Bahrain, Bhutan, Oman, Qatar, United Arab Emirates\n\n\n\n\n\n135 Members (1973)\n\n\n\nAdded: Bahamas, Federal Republic of Germany, German Democratic Republic\n\n\n\n\n\n138 Members (1974)\n\n\n\nAdded: Bangladesh, Grenada, Guinea-Bissau\n\n\n\n\n\n144 Members (1975)\n\n\n\nAdded: Cape Verde, Comoros, Mozambique, Papua New Guinea, Sao Tome and Principe, Suriname\n\n\n\n\n\n147 Members (1976)\n\n\n\nAdded: Angola, Samoa, Seychelles\n\n\n\n\n\n149 Members (1977)\n\n\n\nAdded: Djibouti, Viet Nam\n\n\n\n\n\n151 Members (1978)\n\n\n\nAdded: Dominica, Solomon Islands\n\n\n\n \n\n152 Members (1979)\n\n\n\nAdded: Saint Lucia\n\n\n\n\n\n154 Members (1980)\n\n\n\nAdded: Saint Vincent and the Grenadines, Zimbabwe\n\n\n\n\n\n157 Members (1981) \n\n\n\nAdded: Antigua and Barbuda, Belize, Vanuatu\n\n\n\n\n\n158 Members (1983)\n\n\n\nAdded: Saint Christopher and Nevis\n\n\n\n \n\n159 Members (1984)\n\n\n\nAdded: Brunei Darussalam\n\n\n\n\n\n159 Members (1990)*\n\n\n\nAdded: Liechtenstein, Namibia\n\t\t\t\t\t\t\t\t*On 22 May 1990, the People's Democratic Republic of Yemen (member since 1967) was united with the Yemen Arab Republic (member since 1947), forming the Republic of Yemen. \n\t\t\t\t\t\t\t\tOn 3 October 1990, the German Democratic Republic acceded to the Federal Republic of Germany (both members since 1973), resulting in the reunification of Germany.\n\n\n\n\n\n166 Members (1991)\n\n\n\nAdded: Democratic People's Republic of Korea, Estonia, Latvia, Lithuania, Marshall Islands, Federated States of Micronesia, Republic of Korea\n\n\n\n\n\n179 Members (1992)\n\n\n\nAdded: Armenia, Azerbaijan, Bosnia and Herzegovina, Croatia, Georgia, Kazakhstan, Kyrgyzstan, Republic of Moldova, San Marino, Slovenia, Tajikistan, Turkmenistan, Uzbekistan\n\n\n\n\n\n184 Members (1993)*\n\n\n\nAdded: Andorra, Czech Republic, Eritrea, Monaco, Slovakia, The former Yugoslav Republic of Macedonia\n\t\t\t\t\t\t\t\t*Czechoslovakia was an original Member of the United Nations from 24 October 1945. The Czech and Slovak Federal Republic ceased to exist on 31 December 1992. On 19 January 1993, the Czech Republic and the Slovak Republic were both admitted separately to United Nations membership.\n\n\n\n\n\n185 Members (1994)\n\n\n\nAdded: Palau\n\n\n\n \n\n188 Members (1999)\n\n\n\nAdded: Kiribati, Nauru, Tonga\n\n\n\n\n\n189 Members (2000)*\n\n\n\nAdded: Federal Republic of Yugoslavia, Tuvalu\n\t\t\t\t\t\t\t\t*The Federal Republic of Yugoslavia was part of the Socialist Federal Republic of Yugoslavia, which was an original member of the United Nations and was removed from the official roster of UN members in 2000, following its dissolution.\n\n\n\n\n\n191 Members (2002)\n\n\n\nAdded: Switzerland, Timor-Leste\n\n\n\n\n\n192 Members (2006)\n\n\n\nAdded: Montenegro\n\n\n\n\n\n193 Members (2011)\n\n\n\nAdded: South Sudan\n\n\n\n\n\n\n\n\n\n\n\nMEMBER STATES\n\nMembership \n\nAbout UN Membership\nList of UN Member States\nUN Membership research guide\nGrowth in UN Membership\nMembership of Principal UN Organs\nContributions to UN regular budget\nHonour Roll: Contribution Received in Full\nArrears in the Payment of Contribution\n\n\nPermanent Missions\n\nNew York\nGeneva\nVienna\n\n\nPermanent Observers\n\nAbout Permanent Observers\nNon-Member States\nIntergovernmental and Other Organizations\nSpecialized Agencies \n\n\n\n \n\nQuick links for delegates\n\nDelegate (UN Intranet - iSeek for Member States)\nBlue Book\nDelegates' Handbook\nManual of Protocol\n\nGrowth in United Nations membership\n\n\n\n\n\n\n\n\n\n\n\n\n\n\n1945-1950          1950s          1960s          1970s          1980s          1990s          2000-Present\n\n\n \n \n\n\n\nOriginal 51 Members (1945)\n\n\n\nArgentina, Australia, Belgium, Bolivia, Brazil, Byelorussian Soviet Socialist Republic, Canada, Chile, China, Colombia, Costa Rica, Cuba, Czechoslovakia, Denmark, Dominican Republic, Ecuador, Egypt, El Salvador, Ethiopia, France, Greece, Guatemala, Haiti, Honduras, India, Iran, Iraq, Lebanon, Liberia, Luxembourg, Mexico, Netherlands, New Zealand, Nicaragua, Norway, Panama, Paraguay, Peru, Philippine Republic, Poland, Saudi Arabia, Syria, Turkey, Ukrainian Soviet Socialist Republic, Union of South Africa, Union of Soviet Socialist Republics, United Kingdom, United States, Uruguay, Venezuela, Yugoslavia\n\n\n\n\n\n55 Members (1946)\n\n\n\nAdded: Afghanistan, Iceland, Siam, Sweden\n\n\n\n\n\n57 Members (1947)\n\n\n\nAdded: Pakistan, Yemen (the Yemen Arab Republic)\n\n\n\n\n\n58 Members (1948)\n\n\n\nAdded: Burma\n\n\n\n \n\n59 Members (1949)\n\n\n\nAdded: Israel\n\n\n\n\n\n60 Members (1950)\n\n\n\nAdded: Indonesia\n\n\n\n\n\n76 Members (1955)\n\n\n\nAdded: Albania, Austria, Bulgaria, Cambodia, Ceylon, Finland, Hungary, Ireland, Italy, Jordan, Laos, Libya, Nepal, Portugal, Romania, Spain\n\n\n\n\n\n80 Members (1956)\n\n\n\nAdded: Japan, Morocco, Sudan, Tunisia\n\n\n\n\n\n82 Members (1957)\n\n\n\nAdded: Ghana, Federation of Malaya\n\n\n\n \n\n82 Members (1958)*\n\n\n\nAdded: Guinea\n\t\t\t\t\t\t\t\t* On 22 February 1958, Syria merged with Egypt (both original members of the United Nations) to become the United Arab Republic. \n\n\n\n\n\n99 Members (1960)\n\n\n\nAdded: Cameroun, Central African Republic, Chad, Congo (Brazzaville), Congo (Leopoldville), Cyprus, Dahomey, Gabon, Ivory Coast, Malagasy Republic, Mali, Niger, Nigeria, Senegal, Somalia, Togo, Upper Volta\n\n\n\n\n\n104 Members (1961)*\n\n\n\nAdded: Mauritania, Mongolia, Sierra Leone, Tanganyika\n\t\t\t\t\t\t\t\t*On 13 October 1961, Syria, having resumed its status as an independent State from the United Arab Republic, resumed its separate membership in the United Nations.\n\n\n\n\n\n110 Members (1962)\n\n\n\nAdded: Algeria, Burundi, Jamaica, Rwanda, Trinidad and Tobago, Uganda\n\n\n\n\n\n113 Members (1963)\n\n\n\nAdded: Kenya, Kuwait, Zanzibar\n\n\n\n\n\n115 Members (1964)*\n\n\n\nAdded: Malawi, Malta, Zambia\n\t\t\t\t\t\t\t\t*On 26 April 1964, Zanzibar merged with Tanganyika to become the United Republic of Tanzania.\n\n\n\n\n\n117 Members (1965)*\n\n\n\nAdded: The Gambia, Maldive Islands, Singapore\n\t\t\t\t\t\t\t\t*On 20 January 1965, Indonesia temporarily withdrew from the United Nations.\n\n\n\n\n\n122 Members (1966)*\n\n\n\nAdded: Barbados, Botswana, Guyana, Lesotho\n\t\t\t\t\t\t\t\t* On 28 September 1966, Indonesia rejoined the United Nations.\n\n\n\n\n\n123 Members (1967)\n\n\n\nAdded: Yemen (People's Democratic Republic of Yemen)\n\n\n\n \n\n126 Members (1968)\n\n\n\nAdded: Equatorial Guinea, Mauritius, Swaziland\n\n\n\n\n\n127 Members (1970)\n\n\n\nAdded: Fiji\n\n\n\n\n\n132 Members (1971)\n\n\n\nAdded: Bahrain, Bhutan, Oman, Qatar, United Arab Emirates\n\n\n\n\n\n135 Members (1973)\n\n\n\nAdded: Bahamas, Federal Republic of Germany, German Democratic Republic\n\n\n\n\n\n138 Members (1974)\n\n\n\nAdded: Bangladesh, Grenada, Guinea-Bissau\n\n\n\n\n\n144 Members (1975)\n\n\n\nAdded: Cape Verde, Comoros, Mozambique, Papua New Guinea, Sao Tome and Principe, Suriname\n\n\n\n\n\n147 Members (1976)\n\n\n\nAdded: Angola, Samoa, Seychelles\n\n\n\n\n\n149 Members (1977)\n\n\n\nAdded: Djibouti, Viet Nam\n\n\n\n\n\n151 Members (1978)\n\n\n\nAdded: Dominica, Solomon Islands\n\n\n\n \n\n152 Members (1979)\n\n\n\nAdded: Saint Lucia\n\n\n\n\n\n154 Members (1980)\n\n\n\nAdded: Saint Vincent and the Grenadines, Zimbabwe\n\n\n\n\n\n157 Members (1981) \n\n\n\nAdded: Antigua and Barbuda, Belize, Vanuatu\n\n\n\n\n\n158 Members (1983)\n\n\n\nAdded: Saint Christopher and Nevis\n\n\n\n \n\n159 Members (1984)\n\n\n\nAdded: Brunei Darussalam\n\n\n\n\n\n159 Members (1990)*\n\n\n\nAdded: Liechtenstein, Namibia\n\t\t\t\t\t\t\t\t*On 22 May 1990, the People's Democratic Republic of Yemen (member since 1967) was united with the Yemen Arab Republic (member since 1947), forming the Republic of Yemen. \n\t\t\t\t\t\t\t\tOn 3 October 1990, the German Democratic Republic acceded to the Federal Republic of Germany (both members since 1973), resulting in the reunification of Germany.\n\n\n\n\n\n166 Members (1991)\n\n\n\nAdded: Democratic People's Republic of Korea, Estonia, Latvia, Lithuania, Marshall Islands, Federated States of Micronesia, Republic of Korea\n\n\n\n\n\n179 Members (1992)\n\n\n\nAdded: Armenia, Azerbaijan, Bosnia and Herzegovina, Croatia, Georgia, Kazakhstan, Kyrgyzstan, Republic of Moldova, San Marino, Slovenia, Tajikistan, Turkmenistan, Uzbekistan\n\n\n\n\n\n184 Members (1993)*\n\n\n\nAdded: Andorra, Czech Republic, Eritrea, Monaco, Slovakia, The former Yugoslav Republic of Macedonia\n\t\t\t\t\t\t\t\t*Czechoslovakia was an original Member of the United Nations from 24 October 1945. The Czech and Slovak Federal Republic ceased to exist on 31 December 1992. On 19 January 1993, the Czech Republic and the Slovak Republic were both admitted separately to United Nations membership.\n\n\n\n\n\n185 Members (1994)\n\n\n\nAdded: Palau\n\n\n\n \n\n188 Members (1999)\n\n\n\nAdded: Kiribati, Nauru, Tonga\n\n\n\n\n\n189 Members (2000)*\n\n\n\nAdded: Federal Republic of Yugoslavia, Tuvalu\n\t\t\t\t\t\t\t\t*The Federal Republic of Yugoslavia was part of the Socialist Federal Republic of Yugoslavia, which was an original member of the United Nations and was removed from the official roster of UN members in 2000, following its dissolution.\n\n\n\n\n\n191 Members (2002)\n\n\n\nAdded: Switzerland, Timor-Leste\n\n\n\n\n\n192 Members (2006)\n\n\n\nAdded: Montenegro\n\n\n\n\n\n193 Members (2011)\n\n\n\nAdded: South Sudan\n\n\n\n\n\n\n\n\n\n\n\nMEMBER STATES\n\nMembership \n\nAbout UN Membership\nList of UN Member States\nUN Membership research guide\nGrowth in UN Membership\nMembership of Principal UN Organs\nContributions to UN regular budget\nHonour Roll: Contribution Received in Full\nArrears in the Payment of Contribution\n\n\nPermanent Missions\n\nNew York\nGeneva\nVienna\n\n\nPermanent Observers\n\nAbout Permanent Observers\nNon-Member States\nIntergovernmental and Other Organizations\nSpecialized Agencies \n\n\n\n \n\nQuick links for delegates\n\nDelegate (UN Intranet - iSeek for Member States)\nBlue Book\nDelegates' Handbook\nManual of Protocol\n\nGrowth in United Nations membership\n\n\n\n\n\n\n\n\n\n\n\n\n\n\n1945-1950          1950s          1960s          1970s          1980s          1990s          2000-Present\n\n\n \n \n\n\n\nOriginal 51 Members (1945)\n\n\n\nArgentina, Australia, Belgium, Bolivia, Brazil, Byelorussian Soviet Socialist Republic, Canada, Chile, China, Colombia, Costa Rica, Cuba, Czechoslovakia, Denmark, Dominican Republic, Ecuador, Egypt, El Salvador, Ethiopia, France, Greece, Guatemala, Haiti, Honduras, India, Iran, Iraq, Lebanon, Liberia, Luxembourg, Mexico, Netherlands, New Zealand, Nicaragua, Norway, Panama, Paraguay, Peru, Philippine Republic, Poland, Saudi Arabia, Syria, Turkey, Ukrainian Soviet Socialist Republic, Union of South Africa, Union of Soviet Socialist Republics, United Kingdom, United States, Uruguay, Venezuela, Yugoslavia\n\n\n\n\n\n55 Members (1946)\n\n\n\nAdded: Afghanistan, Iceland, Siam, Sweden\n\n\n\n\n\n57 Members (1947)\n\n\n\nAdded: Pakistan, Yemen (the Yemen Arab Republic)\n\n\n\n\n\n58 Members (1948)\n\n\n\nAdded: Burma\n\n\n\n \n\n59 Members (1949)\n\n\n\nAdded: Israel\n\n\n\n\n\n60 Members (1950)\n\n\n\nAdded: Indonesia\n\n\n\n\n\n76 Members (1955)\n\n\n\nAdded: Albania, Austria, Bulgaria, Cambodia, Ceylon, Finland, Hungary, Ireland, Italy, Jordan, Laos, Libya, Nepal, Portugal, Romania, Spain\n\n\n\n\n\n80 Members (1956)\n\n\n\nAdded: Japan, Morocco, Sudan, Tunisia\n\n\n\n\n\n82 Members (1957)\n\n\n\nAdded: Ghana, Federation of Malaya\n\n\n\n \n\n82 Members (1958)*\n\n\n\nAdded: Guinea\n\t\t\t\t\t\t\t\t* On 22 February 1958, Syria merged with Egypt (both original members of the United Nations) to become the United Arab Republic. \n\n\n\n\n\n99 Members (1960)\n\n\n\nAdded: Cameroun, Central African Republic, Chad, Congo (Brazzaville), Congo (Leopoldville), Cyprus, Dahomey, Gabon, Ivory Coast, Malagasy Republic, Mali, Niger, Nigeria, Senegal, Somalia, Togo, Upper Volta\n\n\n\n\n\n104 Members (1961)*\n\n\n\nAdded: Mauritania, Mongolia, Sierra Leone, Tanganyika\n\t\t\t\t\t\t\t\t*On 13 October 1961, Syria, having resumed its status as an independent State from the United Arab Republic, resumed its separate membership in the United Nations.\n\n\n\n\n\n110 Members (1962)\n\n\n\nAdded: Algeria, Burundi, Jamaica, Rwanda, Trinidad and Tobago, Uganda\n\n\n\n\n\n113 Members (1963)\n\n\n\nAdded: Kenya, Kuwait, Zanzibar\n\n\n\n\n\n115 Members (1964)*\n\n\n\nAdded: Malawi, Malta, Zambia\n\t\t\t\t\t\t\t\t*On 26 April 1964, Zanzibar merged with Tanganyika to become the United Republic of Tanzania.\n\n\n\n\n\n117 Members (1965)*\n\n\n\nAdded: The Gambia, Maldive Islands, Singapore\n\t\t\t\t\t\t\t\t*On 20 January 1965, Indonesia temporarily withdrew from the United Nations.\n\n\n\n\n\n122 Members (1966)*\n\n\n\nAdded: Barbados, Botswana, Guyana, Lesotho\n\t\t\t\t\t\t\t\t* On 28 September 1966, Indonesia rejoined the United Nations.\n\n\n\n\n\n123 Members (1967)\n\n\n\nAdded: Yemen (People's Democratic Republic of Yemen)\n\n\n\n \n\n126 Members (1968)\n\n\n\nAdded: Equatorial Guinea, Mauritius, Swaziland\n\n\n\n\n\n127 Members (1970)\n\n\n\nAdded: Fiji\n\n\n\n\n\n132 Members (1971)\n\n\n\nAdded: Bahrain, Bhutan, Oman, Qatar, United Arab Emirates\n\n\n\n\n\n135 Members (1973)\n\n\n\nAdded: Bahamas, Federal Republic of Germany, German Democratic Republic\n\n\n\n\n\n138 Members (1974)\n\n\n\nAdded: Bangladesh, Grenada, Guinea-Bissau\n\n\n\n\n\n144 Members (1975)\n\n\n\nAdded: Cape Verde, Comoros, Mozambique, Papua New Guinea, Sao Tome and Principe, Suriname\n\n\n\n\n\n147 Members (1976)\n\n\n\nAdded: Angola, Samoa, Seychelles\n\n\n\n\n\n149 Members (1977)\n\n\n\nAdded: Djibouti, Viet Nam\n\n\n\n\n\n151 Members (1978)\n\n\n\nAdded: Dominica, Solomon Islands\n\n\n\n \n\n152 Members (1979)\n\n\n\nAdded: Saint Lucia\n\n\n\n\n\n154 Members (1980)\n\n\n\nAdded: Saint Vincent and the Grenadines, Zimbabwe\n\n\n\n\n\n157 Members (1981) \n\n\n\nAdded: Antigua and Barbuda, Belize, Vanuatu\n\n\n\n\n\n158 Members (1983)\n\n\n\nAdded: Saint Christopher and Nevis\n\n\n\n \n\n159 Members (1984)\n\n\n\nAdded: Brunei Darussalam\n\n\n\n\n\n159 Members (1990)*\n\n\n\nAdded: Liechtenstein, Namibia\n\t\t\t\t\t\t\t\t*On 22 May 1990, the People's Democratic Republic of Yemen (member since 1967) was united with the Yemen Arab Republic (member since 1947), forming the Republic of Yemen. \n\t\t\t\t\t\t\t\tOn 3 October 1990, the German Democratic Republic acceded to the Federal Republic of Germany (both members since 1973), resulting in the reunification of Germany.\n\n\n\n\n\n166 Members (1991)\n\n\n\nAdded: Democratic People's Republic of Korea, Estonia, Latvia, Lithuania, Marshall Islands, Federated States of Micronesia, Republic of Korea\n\n\n\n\n\n179 Members (1992)\n\n\n\nAdded: Armenia, Azerbaijan, Bosnia and Herzegovina, Croatia, Georgia, Kazakhstan, Kyrgyzstan, Republic of Moldova, San Marino, Slovenia, Tajikistan, Turkmenistan, Uzbekistan\n\n\n\n\n\n184 Members (1993)*\n\n\n\nAdded: Andorra, Czech Republic, Eritrea, Monaco, Slovakia, The former Yugoslav Republic of Macedonia\n\t\t\t\t\t\t\t\t*Czechoslovakia was an original Member of the United Nations from 24 October 1945. The Czech and Slovak Federal Republic ceased to exist on 31 December 1992. On 19 January 1993, the Czech Republic and the Slovak Republic were both admitted separately to United Nations membership.\n\n\n\n\n\n185 Members (1994)\n\n\n\nAdded: Palau\n\n\n\n \n\n188 Members (1999)\n\n\n\nAdded: Kiribati, Nauru, Tonga\n\n\n\n\n\n189 Members (2000)*\n\n\n\nAdded: Federal Republic of Yugoslavia, Tuvalu\n\t\t\t\t\t\t\t\t*The Federal Republic of Yugoslavia was part of the Socialist Federal Republic of Yugoslavia, which was an original member of the United Nations and was removed from the official roster of UN members in 2000, following its dissolution.\n\n\n\n\n\n191 Members (2002)\n\n\n\nAdded: Switzerland, Timor-Leste\n\n\n\n\n\n192 Members (2006)\n\n\n\nAdded: Montenegro\n\n\n\n\n\n193 Members (2011)\n\n\n\nAdded: South Sudan\n\n\n\n\n\n\n\n\n\n\n\nMEMBER STATES\n\nMembership \n\nAbout UN Membership\nList of UN Member States\nUN Membership research guide\nGrowth in UN Membership\nMembership of Principal UN Organs\nContributions to UN regular budget\nHonour Roll: Contribution Received in Full\nArrears in the Payment of Contribution\n\n\nPermanent Missions\n\nNew York\nGeneva\nVienna\n\n\nPermanent Observers\n\nAbout Permanent Observers\nNon-Member States\nIntergovernmental and Other Organizations\nSpecialized Agencies \n\n\n\n \n\nQuick links for delegates\n\nDelegate (UN Intranet - iSeek for Member States)\nBlue Book\nDelegates' Handbook\nManual of Protocol\n\nGrowth in United Nations membership\n\n\n\n\n\n\n\n\n\n\n\n\n\n\n1945-1950          1950s          1960s          1970s          1980s          1990s          2000-Present\n\n\n \n \n\n\n\nOriginal 51 Members (1945)\n\n\n\nArgentina, Australia, Belgium, Bolivia, Brazil, Byelorussian Soviet Socialist Republic, Canada, Chile, China, Colombia, Costa Rica, Cuba, Czechoslovakia, Denmark, Dominican Republic, Ecuador, Egypt, El Salvador, Ethiopia, France, Greece, Guatemala, Haiti, Honduras, India, Iran, Iraq, Lebanon, Liberia, Luxembourg, Mexico, Netherlands, New Zealand, Nicaragua, Norway, Panama, Paraguay, Peru, Philippine Republic, Poland, Saudi Arabia, Syria, Turkey, Ukrainian Soviet Socialist Republic, Union of South Africa, Union of Soviet Socialist Republics, United Kingdom, United States, Uruguay, Venezuela, Yugoslavia\n\n\n\n\n\n55 Members (1946)\n\n\n\nAdded: Afghanistan, Iceland, Siam, Sweden\n\n\n\n\n\n57 Members (1947)\n\n\n\nAdded: Pakistan, Yemen (the Yemen Arab Republic)\n\n\n\n\n\n58 Members (1948)\n\n\n\nAdded: Burma\n\n\n\n \n\n59 Members (1949)\n\n\n\nAdded: Israel\n\n\n\n\n\n60 Members (1950)\n\n\n\nAdded: Indonesia\n\n\n\n\n\n76 Members (1955)\n\n\n\nAdded: Albania, Austria, Bulgaria, Cambodia, Ceylon, Finland, Hungary, Ireland, Italy, Jordan, Laos, Libya, Nepal, Portugal, Romania, Spain\n\n\n\n\n\n80 Members (1956)\n\n\n\nAdded: Japan, Morocco, Sudan, Tunisia\n\n\n\n\n\n82 Members (1957)\n\n\n\nAdded: Ghana, Federation of Malaya\n\n\n\n \n\n82 Members (1958)*\n\n\n\nAdded: Guinea\n\t\t\t\t\t\t\t\t* On 22 February 1958, Syria merged with Egypt (both original members of the United Nations) to become the United Arab Republic. \n\n\n\n\n\n99 Members (1960)\n\n\n\nAdded: Cameroun, Central African Republic, Chad, Congo (Brazzaville), Congo (Leopoldville), Cyprus, Dahomey, Gabon, Ivory Coast, Malagasy Republic, Mali, Niger, Nigeria, Senegal, Somalia, Togo, Upper Volta\n\n\n\n\n\n104 Members (1961)*\n\n\n\nAdded: Mauritania, Mongolia, Sierra Leone, Tanganyika\n\t\t\t\t\t\t\t\t*On 13 October 1961, Syria, having resumed its status as an independent State from the United Arab Republic, resumed its separate membership in the United Nations.\n\n\n\n\n\n110 Members (1962)\n\n\n\nAdded: Algeria, Burundi, Jamaica, Rwanda, Trinidad and Tobago, Uganda\n\n\n\n\n\n113 Members (1963)\n\n\n\nAdded: Kenya, Kuwait, Zanzibar\n\n\n\n\n\n115 Members (1964)*\n\n\n\nAdded: Malawi, Malta, Zambia\n\t\t\t\t\t\t\t\t*On 26 April 1964, Zanzibar merged with Tanganyika to become the United Republic of Tanzania.\n\n\n\n\n\n117 Members (1965)*\n\n\n\nAdded: The Gambia, Maldive Islands, Singapore\n\t\t\t\t\t\t\t\t*On 20 January 1965, Indonesia temporarily withdrew from the United Nations.\n\n\n\n\n\n122 Members (1966)*\n\n\n\nAdded: Barbados, Botswana, Guyana, Lesotho\n\t\t\t\t\t\t\t\t* On 28 September 1966, Indonesia rejoined the United Nations.\n\n\n\n\n\n123 Members (1967)\n\n\n\nAdded: Yemen (People's Democratic Republic of Yemen)\n\n\n\n \n\n126 Members (1968)\n\n\n\nAdded: Equatorial Guinea, Mauritius, Swaziland\n\n\n\n\n\n127 Members (1970)\n\n\n\nAdded: Fiji\n\n\n\n\n\n132 Members (1971)\n\n\n\nAdded: Bahrain, Bhutan, Oman, Qatar, United Arab Emirates\n\n\n\n\n\n135 Members (1973)\n\n\n\nAdded: Bahamas, Federal Republic of Germany, German Democratic Republic\n\n\n\n\n\n138 Members (1974)\n\n\n\nAdded: Bangladesh, Grenada, Guinea-Bissau\n\n\n\n\n\n144 Members (1975)\n\n\n\nAdded: Cape Verde, Comoros, Mozambique, Papua New Guinea, Sao Tome and Principe, Suriname\n\n\n\n\n\n147 Members (1976)\n\n\n\nAdded: Angola, Samoa, Seychelles\n\n\n\n\n\n149 Members (1977)\n\n\n\nAdded: Djibouti, Viet Nam\n\n\n\n\n\n151 Members (1978)\n\n\n\nAdded: Dominica, Solomon Islands\n\n\n\n \n\n152 Members (1979)\n\n\n\nAdded: Saint Lucia\n\n\n\n\n\n154 Members (1980)\n\n\n\nAdded: Saint Vincent and the Grenadines, Zimbabwe\n\n\n\n\n\n157 Members (1981) \n\n\n\nAdded: Antigua and Barbuda, Belize, Vanuatu\n\n\n\n\n\n158 Members (1983)\n\n\n\nAdded: Saint Christopher and Nevis\n\n\n\n \n\n159 Members (1984)\n\n\n\nAdded: Brunei Darussalam\n\n\n\n\n\n159 Members (1990)*\n\n\n\nAdded: Liechtenstein, Namibia\n\t\t\t\t\t\t\t\t*On 22 May 1990, the People's Democratic Republic of Yemen (member since 1967) was united with the Yemen Arab Republic (member since 1947), forming the Republic of Yemen. \n\t\t\t\t\t\t\t\tOn 3 October 1990, the German Democratic Republic acceded to the Federal Republic of Germany (both members since 1973), resulting in the reunification of Germany.\n\n\n\n\n\n166 Members (1991)\n\n\n\nAdded: Democratic People's Republic of Korea, Estonia, Latvia, Lithuania, Marshall Islands, Federated States of Micronesia, Republic of Korea\n\n\n\n\n\n179 Members (1992)\n\n\n\nAdded: Armenia, Azerbaijan, Bosnia and Herzegovina, Croatia, Georgia, Kazakhstan, Kyrgyzstan, Republic of Moldova, San Marino, Slovenia, Tajikistan, Turkmenistan, Uzbekistan\n\n\n\n\n\n184 Members (1993)*\n\n\n\nAdded: Andorra, Czech Republic, Eritrea, Monaco, Slovakia, The former Yugoslav Republic of Macedonia\n\t\t\t\t\t\t\t\t*Czechoslovakia was an original Member of the United Nations from 24 October 1945. The Czech and Slovak Federal Republic ceased to exist on 31 December 1992. On 19 January 1993, the Czech Republic and the Slovak Republic were both admitted separately to United Nations membership.\n\n\n\n\n\n185 Members (1994)\n\n\n\nAdded: Palau\n\n\n\n \n\n188 Members (1999)\n\n\n\nAdded: Kiribati, Nauru, Tonga\n\n\n\n\n\n189 Members (2000)*\n\n\n\nAdded: Federal Republic of Yugoslavia, Tuvalu\n\t\t\t\t\t\t\t\t*The Federal Republic of Yugoslavia was part of the Socialist Federal Republic of Yugoslavia, which was an original member of the United Nations and was removed from the official roster of UN members in 2000, following its dissolution.\n\n\n\n\n\n191 Members (2002)\n\n\n\nAdded: Switzerland, Timor-Leste\n\n\n\n\n\n192 Members (2006)\n\n\n\nAdded: Montenegro\n\n\n\n\n\n193 Members (2011)\n\n\n\nAdded: South Sudan\n\n\n\n\n\n\n\n\n\n\n\nMEMBER STATES\n\nMembership \n\nAbout UN Membership\nList of UN Member States\nUN Membership research guide\nGrowth in UN Membership\nMembership of Principal UN Organs\nContributions to UN regular budget\nHonour Roll: Contribution Received in Full\nArrears in the Payment of Contribution\n\n\nPermanent Missions\n\nNew York\nGeneva\nVienna\n\n\nPermanent Observers\n\nAbout Permanent Observers\nNon-Member States\nIntergovernmental and Other Organizations\nSpecialized Agencies \n\n\n\n \n\nQuick links for delegates\n\nDelegate (UN Intranet - iSeek for Member States)\nBlue Book\nDelegates' Handbook\nManual of Protocol\n\n1945-1950          1950s          1960s          1970s          1980s          1990s          2000-Present\n\n\n \n \n\n\n\nOriginal 51 Members (1945)\n\n\n\nArgentina, Australia, Belgium, Bolivia, Brazil, Byelorussian Soviet Socialist Republic, Canada, Chile, China, Colombia, Costa Rica, Cuba, Czechoslovakia, Denmark, Dominican Republic, Ecuador, Egypt, El Salvador, Ethiopia, France, Greece, Guatemala, Haiti, Honduras, India, Iran, Iraq, Lebanon, Liberia, Luxembourg, Mexico, Netherlands, New Zealand, Nicaragua, Norway, Panama, Paraguay, Peru, Philippine Republic, Poland, Saudi Arabia, Syria, Turkey, Ukrainian Soviet Socialist Republic, Union of South Africa, Union of Soviet Socialist Republics, United Kingdom, United States, Uruguay, Venezuela, Yugoslavia\n\n\n\n\n\n55 Members (1946)\n\n\n\nAdded: Afghanistan, Iceland, Siam, Sweden\n\n\n\n\n\n57 Members (1947)\n\n\n\nAdded: Pakistan, Yemen (the Yemen Arab Republic)\n\n\n\n\n\n58 Members (1948)\n\n\n\nAdded: Burma\n\n\n\n \n\n59 Members (1949)\n\n\n\nAdded: Israel\n\n\n\n\n\n60 Members (1950)\n\n\n\nAdded: Indonesia\n\n\n\n\n\n76 Members (1955)\n\n\n\nAdded: Albania, Austria, Bulgaria, Cambodia, Ceylon, Finland, Hungary, Ireland, Italy, Jordan, Laos, Libya, Nepal, Portugal, Romania, Spain\n\n\n\n\n\n80 Members (1956)\n\n\n\nAdded: Japan, Morocco, Sudan, Tunisia\n\n\n\n\n\n82 Members (1957)\n\n\n\nAdded: Ghana, Federation of Malaya\n\n\n\n \n\n82 Members (1958)*\n\n\n\nAdded: Guinea\n\t\t\t\t\t\t\t\t* On 22 February 1958, Syria merged with Egypt (both original members of the United Nations) to become the United Arab Republic. \n\n\n\n\n\n99 Members (1960)\n\n\n\nAdded: Cameroun, Central African Republic, Chad, Congo (Brazzaville), Congo (Leopoldville), Cyprus, Dahomey, Gabon, Ivory Coast, Malagasy Republic, Mali, Niger, Nigeria, Senegal, Somalia, Togo, Upper Volta\n\n\n\n\n\n104 Members (1961)*\n\n\n\nAdded: Mauritania, Mongolia, Sierra Leone, Tanganyika\n\t\t\t\t\t\t\t\t*On 13 October 1961, Syria, having resumed its status as an independent State from the United Arab Republic, resumed its separate membership in the United Nations.\n\n\n\n\n\n110 Members (1962)\n\n\n\nAdded: Algeria, Burundi, Jamaica, Rwanda, Trinidad and Tobago, Uganda\n\n\n\n\n\n113 Members (1963)\n\n\n\nAdded: Kenya, Kuwait, Zanzibar\n\n\n\n\n\n115 Members (1964)*\n\n\n\nAdded: Malawi, Malta, Zambia\n\t\t\t\t\t\t\t\t*On 26 April 1964, Zanzibar merged with Tanganyika to become the United Republic of Tanzania.\n\n\n\n\n\n117 Members (1965)*\n\n\n\nAdded: The Gambia, Maldive Islands, Singapore\n\t\t\t\t\t\t\t\t*On 20 January 1965, Indonesia temporarily withdrew from the United Nations.\n\n\n\n\n\n122 Members (1966)*\n\n\n\nAdded: Barbados, Botswana, Guyana, Lesotho\n\t\t\t\t\t\t\t\t* On 28 September 1966, Indonesia rejoined the United Nations.\n\n\n\n\n\n123 Members (1967)\n\n\n\nAdded: Yemen (People's Democratic Republic of Yemen)\n\n\n\n \n\n126 Members (1968)\n\n\n\nAdded: Equatorial Guinea, Mauritius, Swaziland\n\n\n\n\n\n127 Members (1970)\n\n\n\nAdded: Fiji\n\n\n\n\n\n132 Members (1971)\n\n\n\nAdded: Bahrain, Bhutan, Oman, Qatar, United Arab Emirates\n\n\n\n\n\n135 Members (1973)\n\n\n\nAdded: Bahamas, Federal Republic of Germany, German Democratic Republic\n\n\n\n\n\n138 Members (1974)\n\n\n\nAdded: Bangladesh, Grenada, Guinea-Bissau\n\n\n\n\n\n144 Members (1975)\n\n\n\nAdded: Cape Verde, Comoros, Mozambique, Papua New Guinea, Sao Tome and Principe, Suriname\n\n\n\n\n\n147 Members (1976)\n\n\n\nAdded: Angola, Samoa, Seychelles\n\n\n\n\n\n149 Members (1977)\n\n\n\nAdded: Djibouti, Viet Nam\n\n\n\n\n\n151 Members (1978)\n\n\n\nAdded: Dominica, Solomon Islands\n\n\n\n \n\n152 Members (1979)\n\n\n\nAdded: Saint Lucia\n\n\n\n\n\n154 Members (1980)\n\n\n\nAdded: Saint Vincent and the Grenadines, Zimbabwe\n\n\n\n\n\n157 Members (1981) \n\n\n\nAdded: Antigua and Barbuda, Belize, Vanuatu\n\n\n\n\n\n158 Members (1983)\n\n\n\nAdded: Saint Christopher and Nevis\n\n\n\n \n\n159 Members (1984)\n\n\n\nAdded: Brunei Darussalam\n\n\n\n\n\n159 Members (1990)*\n\n\n\nAdded: Liechtenstein, Namibia\n\t\t\t\t\t\t\t\t*On 22 May 1990, the People's Democratic Republic of Yemen (member since 1967) was united with the Yemen Arab Republic (member since 1947), forming the Republic of Yemen. \n\t\t\t\t\t\t\t\tOn 3 October 1990, the German Democratic Republic acceded to the Federal Republic of Germany (both members since 1973), resulting in the reunification of Germany.\n\n\n\n\n\n166 Members (1991)\n\n\n\nAdded: Democratic People's Republic of Korea, Estonia, Latvia, Lithuania, Marshall Islands, Federated States of Micronesia, Republic of Korea\n\n\n\n\n\n179 Members (1992)\n\n\n\nAdded: Armenia, Azerbaijan, Bosnia and Herzegovina, Croatia, Georgia, Kazakhstan, Kyrgyzstan, Republic of Moldova, San Marino, Slovenia, Tajikistan, Turkmenistan, Uzbekistan\n\n\n\n\n\n184 Members (1993)*\n\n\n\nAdded: Andorra, Czech Republic, Eritrea, Monaco, Slovakia, The former Yugoslav Republic of Macedonia\n\t\t\t\t\t\t\t\t*Czechoslovakia was an original Member of the United Nations from 24 October 1945. The Czech and Slovak Federal Republic ceased to exist on 31 December 1992. On 19 January 1993, the Czech Republic and the Slovak Republic were both admitted separately to United Nations membership.\n\n\n\n\n\n185 Members (1994)\n\n\n\nAdded: Palau\n\n\n\n \n\n188 Members (1999)\n\n\n\nAdded: Kiribati, Nauru, Tonga\n\n\n\n\n\n189 Members (2000)*\n\n\n\nAdded: Federal Republic of Yugoslavia, Tuvalu\n\t\t\t\t\t\t\t\t*The Federal Republic of Yugoslavia was part of the Socialist Federal Republic of Yugoslavia, which was an original member of the United Nations and was removed from the official roster of UN members in 2000, following its dissolution.\n\n\n\n\n\n191 Members (2002)\n\n\n\nAdded: Switzerland, Timor-Leste\n\n\n\n\n\n192 Members (2006)\n\n\n\nAdded: Montenegro\n\n\n\n\n\n193 Members (2011)\n\n\n\nAdded: South Sudan\n\n\n\n\n\n\n\n\n\n\n\nMEMBER STATES\n\nMembership \n\nAbout UN Membership\nList of UN Member States\nUN Membership research guide\nGrowth in UN Membership\nMembership of Principal UN Organs\nContributions to UN regular budget\nHonour Roll: Contribution Received in Full\nArrears in the Payment of Contribution\n\n\nPermanent Missions\n\nNew York\nGeneva\nVienna\n\n\nPermanent Observers\n\nAbout Permanent Observers\nNon-Member States\nIntergovernmental and Other Organizations\nSpecialized Agencies \n\n\n\n \n\nQuick links for delegates\n\nDelegate (UN Intranet - iSeek for Member States)\nBlue Book\nDelegates' Handbook\nManual of Protocol\n\n1945-1950          1950s          1960s          1970s          1980s          1990s          2000-Present\n\n\n \n \n\n\n\nOriginal 51 Members (1945)\n\n\n\nArgentina, Australia, Belgium, Bolivia, Brazil, Byelorussian Soviet Socialist Republic, Canada, Chile, China, Colombia, Costa Rica, Cuba, Czechoslovakia, Denmark, Dominican Republic, Ecuador, Egypt, El Salvador, Ethiopia, France, Greece, Guatemala, Haiti, Honduras, India, Iran, Iraq, Lebanon, Liberia, Luxembourg, Mexico, Netherlands, New Zealand, Nicaragua, Norway, Panama, Paraguay, Peru, Philippine Republic, Poland, Saudi Arabia, Syria, Turkey, Ukrainian Soviet Socialist Republic, Union of South Africa, Union of Soviet Socialist Republics, United Kingdom, United States, Uruguay, Venezuela, Yugoslavia\n\n\n\n\n\n55 Members (1946)\n\n\n\nAdded: Afghanistan, Iceland, Siam, Sweden\n\n\n\n\n\n57 Members (1947)\n\n\n\nAdded: Pakistan, Yemen (the Yemen Arab Republic)\n\n\n\n\n\n58 Members (1948)\n\n\n\nAdded: Burma\n\n\n\n \n\n59 Members (1949)\n\n\n\nAdded: Israel\n\n\n\n\n\n60 Members (1950)\n\n\n\nAdded: Indonesia\n\n\n\n\n\n76 Members (1955)\n\n\n\nAdded: Albania, Austria, Bulgaria, Cambodia, Ceylon, Finland, Hungary, Ireland, Italy, Jordan, Laos, Libya, Nepal, Portugal, Romania, Spain\n\n\n\n\n\n80 Members (1956)\n\n\n\nAdded: Japan, Morocco, Sudan, Tunisia\n\n\n\n\n\n82 Members (1957)\n\n\n\nAdded: Ghana, Federation of Malaya\n\n\n\n \n\n82 Members (1958)*\n\n\n\nAdded: Guinea\n\t\t\t\t\t\t\t\t* On 22 February 1958, Syria merged with Egypt (both original members of the United Nations) to become the United Arab Republic. \n\n\n\n\n\n99 Members (1960)\n\n\n\nAdded: Cameroun, Central African Republic, Chad, Congo (Brazzaville), Congo (Leopoldville), Cyprus, Dahomey, Gabon, Ivory Coast, Malagasy Republic, Mali, Niger, Nigeria, Senegal, Somalia, Togo, Upper Volta\n\n\n\n\n\n104 Members (1961)*\n\n\n\nAdded: Mauritania, Mongolia, Sierra Leone, Tanganyika\n\t\t\t\t\t\t\t\t*On 13 October 1961, Syria, having resumed its status as an independent State from the United Arab Republic, resumed its separate membership in the United Nations.\n\n\n\n\n\n110 Members (1962)\n\n\n\nAdded: Algeria, Burundi, Jamaica, Rwanda, Trinidad and Tobago, Uganda\n\n\n\n\n\n113 Members (1963)\n\n\n\nAdded: Kenya, Kuwait, Zanzibar\n\n\n\n\n\n115 Members (1964)*\n\n\n\nAdded: Malawi, Malta, Zambia\n\t\t\t\t\t\t\t\t*On 26 April 1964, Zanzibar merged with Tanganyika to become the United Republic of Tanzania.\n\n\n\n\n\n117 Members (1965)*\n\n\n\nAdded: The Gambia, Maldive Islands, Singapore\n\t\t\t\t\t\t\t\t*On 20 January 1965, Indonesia temporarily withdrew from the United Nations.\n\n\n\n\n\n122 Members (1966)*\n\n\n\nAdded: Barbados, Botswana, Guyana, Lesotho\n\t\t\t\t\t\t\t\t* On 28 September 1966, Indonesia rejoined the United Nations.\n\n\n\n\n\n123 Members (1967)\n\n\n\nAdded: Yemen (People's Democratic Republic of Yemen)\n\n\n\n \n\n126 Members (1968)\n\n\n\nAdded: Equatorial Guinea, Mauritius, Swaziland\n\n\n\n\n\n127 Members (1970)\n\n\n\nAdded: Fiji\n\n\n\n\n\n132 Members (1971)\n\n\n\nAdded: Bahrain, Bhutan, Oman, Qatar, United Arab Emirates\n\n\n\n\n\n135 Members (1973)\n\n\n\nAdded: Bahamas, Federal Republic of Germany, German Democratic Republic\n\n\n\n\n\n138 Members (1974)\n\n\n\nAdded: Bangladesh, Grenada, Guinea-Bissau\n\n\n\n\n\n144 Members (1975)\n\n\n\nAdded: Cape Verde, Comoros, Mozambique, Papua New Guinea, Sao Tome and Principe, Suriname\n\n\n\n\n\n147 Members (1976)\n\n\n\nAdded: Angola, Samoa, Seychelles\n\n\n\n\n\n149 Members (1977)\n\n\n\nAdded: Djibouti, Viet Nam\n\n\n\n\n\n151 Members (1978)\n\n\n\nAdded: Dominica, Solomon Islands\n\n\n\n \n\n152 Members (1979)\n\n\n\nAdded: Saint Lucia\n\n\n\n\n\n154 Members (1980)\n\n\n\nAdded: Saint Vincent and the Grenadines, Zimbabwe\n\n\n\n\n\n157 Members (1981) \n\n\n\nAdded: Antigua and Barbuda, Belize, Vanuatu\n\n\n\n\n\n158 Members (1983)\n\n\n\nAdded: Saint Christopher and Nevis\n\n\n\n \n\n159 Members (1984)\n\n\n\nAdded: Brunei Darussalam\n\n\n\n\n\n159 Members (1990)*\n\n\n\nAdded: Liechtenstein, Namibia\n\t\t\t\t\t\t\t\t*On 22 May 1990, the People's Democratic Republic of Yemen (member since 1967) was united with the Yemen Arab Republic (member since 1947), forming the Republic of Yemen. \n\t\t\t\t\t\t\t\tOn 3 October 1990, the German Democratic Republic acceded to the Federal Republic of Germany (both members since 1973), resulting in the reunification of Germany.\n\n\n\n\n\n166 Members (1991)\n\n\n\nAdded: Democratic People's Republic of Korea, Estonia, Latvia, Lithuania, Marshall Islands, Federated States of Micronesia, Republic of Korea\n\n\n\n\n\n179 Members (1992)\n\n\n\nAdded: Armenia, Azerbaijan, Bosnia and Herzegovina, Croatia, Georgia, Kazakhstan, Kyrgyzstan, Republic of Moldova, San Marino, Slovenia, Tajikistan, Turkmenistan, Uzbekistan\n\n\n\n\n\n184 Members (1993)*\n\n\n\nAdded: Andorra, Czech Republic, Eritrea, Monaco, Slovakia, The former Yugoslav Republic of Macedonia\n\t\t\t\t\t\t\t\t*Czechoslovakia was an original Member of the United Nations from 24 October 1945. The Czech and Slovak Federal Republic ceased to exist on 31 December 1992. On 19 January 1993, the Czech Republic and the Slovak Republic were both admitted separately to United Nations membership.\n\n\n\n\n\n185 Members (1994)\n\n\n\nAdded: Palau\n\n\n\n \n\n188 Members (1999)\n\n\n\nAdded: Kiribati, Nauru, Tonga\n\n\n\n\n\n189 Members (2000)*\n\n\n\nAdded: Federal Republic of Yugoslavia, Tuvalu\n\t\t\t\t\t\t\t\t*The Federal Republic of Yugoslavia was part of the Socialist Federal Republic of Yugoslavia, which was an original member of the United Nations and was removed from the official roster of UN members in 2000, following its dissolution.\n\n\n\n\n\n191 Members (2002)\n\n\n\nAdded: Switzerland, Timor-Leste\n\n\n\n\n\n192 Members (2006)\n\n\n\nAdded: Montenegro\n\n\n\n\n\n193 Members (2011)\n\n\n\nAdded: South Sudan\n\n\n\n\n\n\n\n\n\n\n\nMEMBER STATES\n\nMembership \n\nAbout UN Membership\nList of UN Member States\nUN Membership research guide\nGrowth in UN Membership\nMembership of Principal UN Organs\nContributions to UN regular budget\nHonour Roll: Contribution Received in Full\nArrears in the Payment of Contribution\n\n\nPermanent Missions\n\nNew York\nGeneva\nVienna\n\n\nPermanent Observers\n\nAbout Permanent Observers\nNon-Member States\nIntergovernmental and Other Organizations\nSpecialized Agencies \n\n\n\n \n\nQuick links for delegates\n\nDelegate (UN Intranet - iSeek for Member States)\nBlue Book\nDelegates' Handbook\nManual of Protocol\n\n1945-1950          1950s          1960s          1970s          1980s          1990s          2000-Present\n\n\n \n \n\n\n\nOriginal 51 Members (1945)\n\n\n\nArgentina, Australia, Belgium, Bolivia, Brazil, Byelorussian Soviet Socialist Republic, Canada, Chile, China, Colombia, Costa Rica, Cuba, Czechoslovakia, Denmark, Dominican Republic, Ecuador, Egypt, El Salvador, Ethiopia, France, Greece, Guatemala, Haiti, Honduras, India, Iran, Iraq, Lebanon, Liberia, Luxembourg, Mexico, Netherlands, New Zealand, Nicaragua, Norway, Panama, Paraguay, Peru, Philippine Republic, Poland, Saudi Arabia, Syria, Turkey, Ukrainian Soviet Socialist Republic, Union of South Africa, Union of Soviet Socialist Republics, United Kingdom, United States, Uruguay, Venezuela, Yugoslavia\n\n\n\n\n\n55 Members (1946)\n\n\n\nAdded: Afghanistan, Iceland, Siam, Sweden\n\n\n\n\n\n57 Members (1947)\n\n\n\nAdded: Pakistan, Yemen (the Yemen Arab Republic)\n\n\n\n\n\n58 Members (1948)\n\n\n\nAdded: Burma\n\n\n\n \n\n59 Members (1949)\n\n\n\nAdded: Israel\n\n\n\n\n\n60 Members (1950)\n\n\n\nAdded: Indonesia\n\n\n\n\n\n76 Members (1955)\n\n\n\nAdded: Albania, Austria, Bulgaria, Cambodia, Ceylon, Finland, Hungary, Ireland, Italy, Jordan, Laos, Libya, Nepal, Portugal, Romania, Spain\n\n\n\n\n\n80 Members (1956)\n\n\n\nAdded: Japan, Morocco, Sudan, Tunisia\n\n\n\n\n\n82 Members (1957)\n\n\n\nAdded: Ghana, Federation of Malaya\n\n\n\n \n\n82 Members (1958)*\n\n\n\nAdded: Guinea\n\t\t\t\t\t\t\t\t* On 22 February 1958, Syria merged with Egypt (both original members of the United Nations) to become the United Arab Republic. \n\n\n\n\n\n99 Members (1960)\n\n\n\nAdded: Cameroun, Central African Republic, Chad, Congo (Brazzaville), Congo (Leopoldville), Cyprus, Dahomey, Gabon, Ivory Coast, Malagasy Republic, Mali, Niger, Nigeria, Senegal, Somalia, Togo, Upper Volta\n\n\n\n\n\n104 Members (1961)*\n\n\n\nAdded: Mauritania, Mongolia, Sierra Leone, Tanganyika\n\t\t\t\t\t\t\t\t*On 13 October 1961, Syria, having resumed its status as an independent State from the United Arab Republic, resumed its separate membership in the United Nations.\n\n\n\n\n\n110 Members (1962)\n\n\n\nAdded: Algeria, Burundi, Jamaica, Rwanda, Trinidad and Tobago, Uganda\n\n\n\n\n\n113 Members (1963)\n\n\n\nAdded: Kenya, Kuwait, Zanzibar\n\n\n\n\n\n115 Members (1964)*\n\n\n\nAdded: Malawi, Malta, Zambia\n\t\t\t\t\t\t\t\t*On 26 April 1964, Zanzibar merged with Tanganyika to become the United Republic of Tanzania.\n\n\n\n\n\n117 Members (1965)*\n\n\n\nAdded: The Gambia, Maldive Islands, Singapore\n\t\t\t\t\t\t\t\t*On 20 January 1965, Indonesia temporarily withdrew from the United Nations.\n\n\n\n\n\n122 Members (1966)*\n\n\n\nAdded: Barbados, Botswana, Guyana, Lesotho\n\t\t\t\t\t\t\t\t* On 28 September 1966, Indonesia rejoined the United Nations.\n\n\n\n\n\n123 Members (1967)\n\n\n\nAdded: Yemen (People's Democratic Republic of Yemen)\n\n\n\n \n\n126 Members (1968)\n\n\n\nAdded: Equatorial Guinea, Mauritius, Swaziland\n\n\n\n\n\n127 Members (1970)\n\n\n\nAdded: Fiji\n\n\n\n\n\n132 Members (1971)\n\n\n\nAdded: Bahrain, Bhutan, Oman, Qatar, United Arab Emirates\n\n\n\n\n\n135 Members (1973)\n\n\n\nAdded: Bahamas, Federal Republic of Germany, German Democratic Republic\n\n\n\n\n\n138 Members (1974)\n\n\n\nAdded: Bangladesh, Grenada, Guinea-Bissau\n\n\n\n\n\n144 Members (1975)\n\n\n\nAdded: Cape Verde, Comoros, Mozambique, Papua New Guinea, Sao Tome and Principe, Suriname\n\n\n\n\n\n147 Members (1976)\n\n\n\nAdded: Angola, Samoa, Seychelles\n\n\n\n\n\n149 Members (1977)\n\n\n\nAdded: Djibouti, Viet Nam\n\n\n\n\n\n151 Members (1978)\n\n\n\nAdded: Dominica, Solomon Islands\n\n\n\n \n\n152 Members (1979)\n\n\n\nAdded: Saint Lucia\n\n\n\n\n\n154 Members (1980)\n\n\n\nAdded: Saint Vincent and the Grenadines, Zimbabwe\n\n\n\n\n\n157 Members (1981) \n\n\n\nAdded: Antigua and Barbuda, Belize, Vanuatu\n\n\n\n\n\n158 Members (1983)\n\n\n\nAdded: Saint Christopher and Nevis\n\n\n\n \n\n159 Members (1984)\n\n\n\nAdded: Brunei Darussalam\n\n\n\n\n\n159 Members (1990)*\n\n\n\nAdded: Liechtenstein, Namibia\n\t\t\t\t\t\t\t\t*On 22 May 1990, the People's Democratic Republic of Yemen (member since 1967) was united with the Yemen Arab Republic (member since 1947), forming the Republic of Yemen. \n\t\t\t\t\t\t\t\tOn 3 October 1990, the German Democratic Republic acceded to the Federal Republic of Germany (both members since 1973), resulting in the reunification of Germany.\n\n\n\n\n\n166 Members (1991)\n\n\n\nAdded: Democratic People's Republic of Korea, Estonia, Latvia, Lithuania, Marshall Islands, Federated States of Micronesia, Republic of Korea\n\n\n\n\n\n179 Members (1992)\n\n\n\nAdded: Armenia, Azerbaijan, Bosnia and Herzegovina, Croatia, Georgia, Kazakhstan, Kyrgyzstan, Republic of Moldova, San Marino, Slovenia, Tajikistan, Turkmenistan, Uzbekistan\n\n\n\n\n\n184 Members (1993)*\n\n\n\nAdded: Andorra, Czech Republic, Eritrea, Monaco, Slovakia, The former Yugoslav Republic of Macedonia\n\t\t\t\t\t\t\t\t*Czechoslovakia was an original Member of the United Nations from 24 October 1945. The Czech and Slovak Federal Republic ceased to exist on 31 December 1992. On 19 January 1993, the Czech Republic and the Slovak Republic were both admitted separately to United Nations membership.\n\n\n\n\n\n185 Members (1994)\n\n\n\nAdded: Palau\n\n\n\n \n\n188 Members (1999)\n\n\n\nAdded: Kiribati, Nauru, Tonga\n\n\n\n\n\n189 Members (2000)*\n\n\n\nAdded: Federal Republic of Yugoslavia, Tuvalu\n\t\t\t\t\t\t\t\t*The Federal Republic of Yugoslavia was part of the Socialist Federal Republic of Yugoslavia, which was an original member of the United Nations and was removed from the official roster of UN members in 2000, following its dissolution.\n\n\n\n\n\n191 Members (2002)\n\n\n\nAdded: Switzerland, Timor-Leste\n\n\n\n\n\n192 Members (2006)\n\n\n\nAdded: Montenegro\n\n\n\n\n\n193 Members (2011)\n\n\n\nAdded: South Sudan\n\n\n\n\n\n\n\n\n\n\n\nMEMBER STATES\n\nMembership \n\nAbout UN Membership\nList of UN Member States\nUN Membership research guide\nGrowth in UN Membership\nMembership of Principal UN Organs\nContributions to UN regular budget\nHonour Roll: Contribution Received in Full\nArrears in the Payment of Contribution\n\n\nPermanent Missions\n\nNew York\nGeneva\nVienna\n\n\nPermanent Observers\n\nAbout Permanent Observers\nNon-Member States\nIntergovernmental and Other Organizations\nSpecialized Agencies \n\n\n\n \n\nQuick links for delegates\n\nDelegate (UN Intranet - iSeek for Member States)\nBlue Book\nDelegates' Handbook\nManual of Protocol\n\n1945-1950          1950s          1960s          1970s          1980s          1990s          2000-Present\n\n\n \n \n\n\n\nOriginal 51 Members (1945)\n\n\n\nArgentina, Australia, Belgium, Bolivia, Brazil, Byelorussian Soviet Socialist Republic, Canada, Chile, China, Colombia, Costa Rica, Cuba, Czechoslovakia, Denmark, Dominican Republic, Ecuador, Egypt, El Salvador, Ethiopia, France, Greece, Guatemala, Haiti, Honduras, India, Iran, Iraq, Lebanon, Liberia, Luxembourg, Mexico, Netherlands, New Zealand, Nicaragua, Norway, Panama, Paraguay, Peru, Philippine Republic, Poland, Saudi Arabia, Syria, Turkey, Ukrainian Soviet Socialist Republic, Union of South Africa, Union of Soviet Socialist Republics, United Kingdom, United States, Uruguay, Venezuela, Yugoslavia\n\n\n\n\n\n55 Members (1946)\n\n\n\nAdded: Afghanistan, Iceland, Siam, Sweden\n\n\n\n\n\n57 Members (1947)\n\n\n\nAdded: Pakistan, Yemen (the Yemen Arab Republic)\n\n\n\n\n\n58 Members (1948)\n\n\n\nAdded: Burma\n\n\n\n \n\n59 Members (1949)\n\n\n\nAdded: Israel\n\n\n\n\n\n60 Members (1950)\n\n\n\nAdded: Indonesia\n\n\n\n\n\n76 Members (1955)\n\n\n\nAdded: Albania, Austria, Bulgaria, Cambodia, Ceylon, Finland, Hungary, Ireland, Italy, Jordan, Laos, Libya, Nepal, Portugal, Romania, Spain\n\n\n\n\n\n80 Members (1956)\n\n\n\nAdded: Japan, Morocco, Sudan, Tunisia\n\n\n\n\n\n82 Members (1957)\n\n\n\nAdded: Ghana, Federation of Malaya\n\n\n\n \n\n82 Members (1958)*\n\n\n\nAdded: Guinea\n\t\t\t\t\t\t\t\t* On 22 February 1958, Syria merged with Egypt (both original members of the United Nations) to become the United Arab Republic. \n\n\n\n\n\n99 Members (1960)\n\n\n\nAdded: Cameroun, Central African Republic, Chad, Congo (Brazzaville), Congo (Leopoldville), Cyprus, Dahomey, Gabon, Ivory Coast, Malagasy Republic, Mali, Niger, Nigeria, Senegal, Somalia, Togo, Upper Volta\n\n\n\n\n\n104 Members (1961)*\n\n\n\nAdded: Mauritania, Mongolia, Sierra Leone, Tanganyika\n\t\t\t\t\t\t\t\t*On 13 October 1961, Syria, having resumed its status as an independent State from the United Arab Republic, resumed its separate membership in the United Nations.\n\n\n\n\n\n110 Members (1962)\n\n\n\nAdded: Algeria, Burundi, Jamaica, Rwanda, Trinidad and Tobago, Uganda\n\n\n\n\n\n113 Members (1963)\n\n\n\nAdded: Kenya, Kuwait, Zanzibar\n\n\n\n\n\n115 Members (1964)*\n\n\n\nAdded: Malawi, Malta, Zambia\n\t\t\t\t\t\t\t\t*On 26 April 1964, Zanzibar merged with Tanganyika to become the United Republic of Tanzania.\n\n\n\n\n\n117 Members (1965)*\n\n\n\nAdded: The Gambia, Maldive Islands, Singapore\n\t\t\t\t\t\t\t\t*On 20 January 1965, Indonesia temporarily withdrew from the United Nations.\n\n\n\n\n\n122 Members (1966)*\n\n\n\nAdded: Barbados, Botswana, Guyana, Lesotho\n\t\t\t\t\t\t\t\t* On 28 September 1966, Indonesia rejoined the United Nations.\n\n\n\n\n\n123 Members (1967)\n\n\n\nAdded: Yemen (People's Democratic Republic of Yemen)\n\n\n\n \n\n126 Members (1968)\n\n\n\nAdded: Equatorial Guinea, Mauritius, Swaziland\n\n\n\n\n\n127 Members (1970)\n\n\n\nAdded: Fiji\n\n\n\n\n\n132 Members (1971)\n\n\n\nAdded: Bahrain, Bhutan, Oman, Qatar, United Arab Emirates\n\n\n\n\n\n135 Members (1973)\n\n\n\nAdded: Bahamas, Federal Republic of Germany, German Democratic Republic\n\n\n\n\n\n138 Members (1974)\n\n\n\nAdded: Bangladesh, Grenada, Guinea-Bissau\n\n\n\n\n\n144 Members (1975)\n\n\n\nAdded: Cape Verde, Comoros, Mozambique, Papua New Guinea, Sao Tome and Principe, Suriname\n\n\n\n\n\n147 Members (1976)\n\n\n\nAdded: Angola, Samoa, Seychelles\n\n\n\n\n\n149 Members (1977)\n\n\n\nAdded: Djibouti, Viet Nam\n\n\n\n\n\n151 Members (1978)\n\n\n\nAdded: Dominica, Solomon Islands\n\n\n\n \n\n152 Members (1979)\n\n\n\nAdded: Saint Lucia\n\n\n\n\n\n154 Members (1980)\n\n\n\nAdded: Saint Vincent and the Grenadines, Zimbabwe\n\n\n\n\n\n157 Members (1981) \n\n\n\nAdded: Antigua and Barbuda, Belize, Vanuatu\n\n\n\n\n\n158 Members (1983)\n\n\n\nAdded: Saint Christopher and Nevis\n\n\n\n \n\n159 Members (1984)\n\n\n\nAdded: Brunei Darussalam\n\n\n\n\n\n159 Members (1990)*\n\n\n\nAdded: Liechtenstein, Namibia\n\t\t\t\t\t\t\t\t*On 22 May 1990, the People's Democratic Republic of Yemen (member since 1967) was united with the Yemen Arab Republic (member since 1947), forming the Republic of Yemen. \n\t\t\t\t\t\t\t\tOn 3 October 1990, the German Democratic Republic acceded to the Federal Republic of Germany (both members since 1973), resulting in the reunification of Germany.\n\n\n\n\n\n166 Members (1991)\n\n\n\nAdded: Democratic People's Republic of Korea, Estonia, Latvia, Lithuania, Marshall Islands, Federated States of Micronesia, Republic of Korea\n\n\n\n\n\n179 Members (1992)\n\n\n\nAdded: Armenia, Azerbaijan, Bosnia and Herzegovina, Croatia, Georgia, Kazakhstan, Kyrgyzstan, Republic of Moldova, San Marino, Slovenia, Tajikistan, Turkmenistan, Uzbekistan\n\n\n\n\n\n184 Members (1993)*\n\n\n\nAdded: Andorra, Czech Republic, Eritrea, Monaco, Slovakia, The former Yugoslav Republic of Macedonia\n\t\t\t\t\t\t\t\t*Czechoslovakia was an original Member of the United Nations from 24 October 1945. The Czech and Slovak Federal Republic ceased to exist on 31 December 1992. On 19 January 1993, the Czech Republic and the Slovak Republic were both admitted separately to United Nations membership.\n\n\n\n\n\n185 Members (1994)\n\n\n\nAdded: Palau\n\n\n\n \n\n188 Members (1999)\n\n\n\nAdded: Kiribati, Nauru, Tonga\n\n\n\n\n\n189 Members (2000)*\n\n\n\nAdded: Federal Republic of Yugoslavia, Tuvalu\n\t\t\t\t\t\t\t\t*The Federal Republic of Yugoslavia was part of the Socialist Federal Republic of Yugoslavia, which was an original member of the United Nations and was removed from the official roster of UN members in 2000, following its dissolution.\n\n\n\n\n\n191 Members (2002)\n\n\n\nAdded: Switzerland, Timor-Leste\n\n\n\n\n\n192 Members (2006)\n\n\n\nAdded: Montenegro\n\n\n\n\n\n193 Members (2011)\n\n\n\nAdded: South Sudan\n\n\n\n\n\n\n\n\n\n\n\nMEMBER STATES\n\nMembership \n\nAbout UN Membership\nList of UN Member States\nUN Membership research guide\nGrowth in UN Membership\nMembership of Principal UN Organs\nContributions to UN regular budget\nHonour Roll: Contribution Received in Full\nArrears in the Payment of Contribution\n\n\nPermanent Missions\n\nNew York\nGeneva\nVienna\n\n\nPermanent Observers\n\nAbout Permanent Observers\nNon-Member States\nIntergovernmental and Other Organizations\nSpecialized Agencies \n\n\n\n \n\nQuick links for delegates\n\nDelegate (UN Intranet - iSeek for Member States)\nBlue Book\nDelegates' Handbook\nManual of Protocol\n\n1945-1950          1950s          1960s          1970s          1980s          1990s          2000-Present\n\n\n \n \n\n\n\nOriginal 51 Members (1945)\n\n\n\nArgentina, Australia, Belgium, Bolivia, Brazil, Byelorussian Soviet Socialist Republic, Canada, Chile, China, Colombia, Costa Rica, Cuba, Czechoslovakia, Denmark, Dominican Republic, Ecuador, Egypt, El Salvador, Ethiopia, France, Greece, Guatemala, Haiti, Honduras, India, Iran, Iraq, Lebanon, Liberia, Luxembourg, Mexico, Netherlands, New Zealand, Nicaragua, Norway, Panama, Paraguay, Peru, Philippine Republic, Poland, Saudi Arabia, Syria, Turkey, Ukrainian Soviet Socialist Republic, Union of South Africa, Union of Soviet Socialist Republics, United Kingdom, United States, Uruguay, Venezuela, Yugoslavia\n\n\n\n\n\n55 Members (1946)\n\n\n\nAdded: Afghanistan, Iceland, Siam, Sweden\n\n\n\n\n\n57 Members (1947)\n\n\n\nAdded: Pakistan, Yemen (the Yemen Arab Republic)\n\n\n\n\n\n58 Members (1948)\n\n\n\nAdded: Burma\n\n\n\n \n\n59 Members (1949)\n\n\n\nAdded: Israel\n\n\n\n\n\n60 Members (1950)\n\n\n\nAdded: Indonesia\n\n\n\n\n\n76 Members (1955)\n\n\n\nAdded: Albania, Austria, Bulgaria, Cambodia, Ceylon, Finland, Hungary, Ireland, Italy, Jordan, Laos, Libya, Nepal, Portugal, Romania, Spain\n\n\n\n\n\n80 Members (1956)\n\n\n\nAdded: Japan, Morocco, Sudan, Tunisia\n\n\n\n\n\n82 Members (1957)\n\n\n\nAdded: Ghana, Federation of Malaya\n\n\n\n \n\n82 Members (1958)*\n\n\n\nAdded: Guinea\n\t\t\t\t\t\t\t\t* On 22 February 1958, Syria merged with Egypt (both original members of the United Nations) to become the United Arab Republic. \n\n\n\n\n\n99 Members (1960)\n\n\n\nAdded: Cameroun, Central African Republic, Chad, Congo (Brazzaville), Congo (Leopoldville), Cyprus, Dahomey, Gabon, Ivory Coast, Malagasy Republic, Mali, Niger, Nigeria, Senegal, Somalia, Togo, Upper Volta\n\n\n\n\n\n104 Members (1961)*\n\n\n\nAdded: Mauritania, Mongolia, Sierra Leone, Tanganyika\n\t\t\t\t\t\t\t\t*On 13 October 1961, Syria, having resumed its status as an independent State from the United Arab Republic, resumed its separate membership in the United Nations.\n\n\n\n\n\n110 Members (1962)\n\n\n\nAdded: Algeria, Burundi, Jamaica, Rwanda, Trinidad and Tobago, Uganda\n\n\n\n\n\n113 Members (1963)\n\n\n\nAdded: Kenya, Kuwait, Zanzibar\n\n\n\n\n\n115 Members (1964)*\n\n\n\nAdded: Malawi, Malta, Zambia\n\t\t\t\t\t\t\t\t*On 26 April 1964, Zanzibar merged with Tanganyika to become the United Republic of Tanzania.\n\n\n\n\n\n117 Members (1965)*\n\n\n\nAdded: The Gambia, Maldive Islands, Singapore\n\t\t\t\t\t\t\t\t*On 20 January 1965, Indonesia temporarily withdrew from the United Nations.\n\n\n\n\n\n122 Members (1966)*\n\n\n\nAdded: Barbados, Botswana, Guyana, Lesotho\n\t\t\t\t\t\t\t\t* On 28 September 1966, Indonesia rejoined the United Nations.\n\n\n\n\n\n123 Members (1967)\n\n\n\nAdded: Yemen (People's Democratic Republic of Yemen)\n\n\n\n \n\n126 Members (1968)\n\n\n\nAdded: Equatorial Guinea, Mauritius, Swaziland\n\n\n\n\n\n127 Members (1970)\n\n\n\nAdded: Fiji\n\n\n\n\n\n132 Members (1971)\n\n\n\nAdded: Bahrain, Bhutan, Oman, Qatar, United Arab Emirates\n\n\n\n\n\n135 Members (1973)\n\n\n\nAdded: Bahamas, Federal Republic of Germany, German Democratic Republic\n\n\n\n\n\n138 Members (1974)\n\n\n\nAdded: Bangladesh, Grenada, Guinea-Bissau\n\n\n\n\n\n144 Members (1975)\n\n\n\nAdded: Cape Verde, Comoros, Mozambique, Papua New Guinea, Sao Tome and Principe, Suriname\n\n\n\n\n\n147 Members (1976)\n\n\n\nAdded: Angola, Samoa, Seychelles\n\n\n\n\n\n149 Members (1977)\n\n\n\nAdded: Djibouti, Viet Nam\n\n\n\n\n\n151 Members (1978)\n\n\n\nAdded: Dominica, Solomon Islands\n\n\n\n \n\n152 Members (1979)\n\n\n\nAdded: Saint Lucia\n\n\n\n\n\n154 Members (1980)\n\n\n\nAdded: Saint Vincent and the Grenadines, Zimbabwe\n\n\n\n\n\n157 Members (1981) \n\n\n\nAdded: Antigua and Barbuda, Belize, Vanuatu\n\n\n\n\n\n158 Members (1983)\n\n\n\nAdded: Saint Christopher and Nevis\n\n\n\n \n\n159 Members (1984)\n\n\n\nAdded: Brunei Darussalam\n\n\n\n\n\n159 Members (1990)*\n\n\n\nAdded: Liechtenstein, Namibia\n\t\t\t\t\t\t\t\t*On 22 May 1990, the People's Democratic Republic of Yemen (member since 1967) was united with the Yemen Arab Republic (member since 1947), forming the Republic of Yemen. \n\t\t\t\t\t\t\t\tOn 3 October 1990, the German Democratic Republic acceded to the Federal Republic of Germany (both members since 1973), resulting in the reunification of Germany.\n\n\n\n\n\n166 Members (1991)\n\n\n\nAdded: Democratic People's Republic of Korea, Estonia, Latvia, Lithuania, Marshall Islands, Federated States of Micronesia, Republic of Korea\n\n\n\n\n\n179 Members (1992)\n\n\n\nAdded: Armenia, Azerbaijan, Bosnia and Herzegovina, Croatia, Georgia, Kazakhstan, Kyrgyzstan, Republic of Moldova, San Marino, Slovenia, Tajikistan, Turkmenistan, Uzbekistan\n\n\n\n\n\n184 Members (1993)*\n\n\n\nAdded: Andorra, Czech Republic, Eritrea, Monaco, Slovakia, The former Yugoslav Republic of Macedonia\n\t\t\t\t\t\t\t\t*Czechoslovakia was an original Member of the United Nations from 24 October 1945. The Czech and Slovak Federal Republic ceased to exist on 31 December 1992. On 19 January 1993, the Czech Republic and the Slovak Republic were both admitted separately to United Nations membership.\n\n\n\n\n\n185 Members (1994)\n\n\n\nAdded: Palau\n\n\n\n \n\n188 Members (1999)\n\n\n\nAdded: Kiribati, Nauru, Tonga\n\n\n\n\n\n189 Members (2000)*\n\n\n\nAdded: Federal Republic of Yugoslavia, Tuvalu\n\t\t\t\t\t\t\t\t*The Federal Republic of Yugoslavia was part of the Socialist Federal Republic of Yugoslavia, which was an original member of the United Nations and was removed from the official roster of UN members in 2000, following its dissolution.\n\n\n\n\n\n191 Members (2002)\n\n\n\nAdded: Switzerland, Timor-Leste\n\n\n\n\n\n192 Members (2006)\n\n\n\nAdded: Montenegro\n\n\n\n\n\n193 Members (2011)\n\n\n\nAdded: South Sudan\n\n\n\n\n\n\n\n\n\n\n\nMEMBER STATES\n\nMembership \n\nAbout UN Membership\nList of UN Member States\nUN Membership research guide\nGrowth in UN Membership\nMembership of Principal UN Organs\nContributions to UN regular budget\nHonour Roll: Contribution Received in Full\nArrears in the Payment of Contribution\n\n\nPermanent Missions\n\nNew York\nGeneva\nVienna\n\n\nPermanent Observers\n\nAbout Permanent Observers\nNon-Member States\nIntergovernmental and Other Organizations\nSpecialized Agencies \n\n\n\n \n\nQuick links for delegates\n\nDelegate (UN Intranet - iSeek for Member States)\nBlue Book\nDelegates' Handbook\nManual of Protocol\n\n1945-1950          1950s          1960s          1970s          1980s          1990s          2000-Present\n\n\n \n \n\n\n\nOriginal 51 Members (1945)\n\n\n\nArgentina, Australia, Belgium, Bolivia, Brazil, Byelorussian Soviet Socialist Republic, Canada, Chile, China, Colombia, Costa Rica, Cuba, Czechoslovakia, Denmark, Dominican Republic, Ecuador, Egypt, El Salvador, Ethiopia, France, Greece, Guatemala, Haiti, Honduras, India, Iran, Iraq, Lebanon, Liberia, Luxembourg, Mexico, Netherlands, New Zealand, Nicaragua, Norway, Panama, Paraguay, Peru, Philippine Republic, Poland, Saudi Arabia, Syria, Turkey, Ukrainian Soviet Socialist Republic, Union of South Africa, Union of Soviet Socialist Republics, United Kingdom, United States, Uruguay, Venezuela, Yugoslavia\n\n\n\n\n\n55 Members (1946)\n\n\n\nAdded: Afghanistan, Iceland, Siam, Sweden\n\n\n\n\n\n57 Members (1947)\n\n\n\nAdded: Pakistan, Yemen (the Yemen Arab Republic)\n\n\n\n\n\n58 Members (1948)\n\n\n\nAdded: Burma\n\n\n\n \n\n59 Members (1949)\n\n\n\nAdded: Israel\n\n\n\n\n\n60 Members (1950)\n\n\n\nAdded: Indonesia\n\n\n\n\n\n76 Members (1955)\n\n\n\nAdded: Albania, Austria, Bulgaria, Cambodia, Ceylon, Finland, Hungary, Ireland, Italy, Jordan, Laos, Libya, Nepal, Portugal, Romania, Spain\n\n\n\n\n\n80 Members (1956)\n\n\n\nAdded: Japan, Morocco, Sudan, Tunisia\n\n\n\n\n\n82 Members (1957)\n\n\n\nAdded: Ghana, Federation of Malaya\n\n\n\n \n\n82 Members (1958)*\n\n\n\nAdded: Guinea\n\t\t\t\t\t\t\t\t* On 22 February 1958, Syria merged with Egypt (both original members of the United Nations) to become the United Arab Republic. \n\n\n\n\n\n99 Members (1960)\n\n\n\nAdded: Cameroun, Central African Republic, Chad, Congo (Brazzaville), Congo (Leopoldville), Cyprus, Dahomey, Gabon, Ivory Coast, Malagasy Republic, Mali, Niger, Nigeria, Senegal, Somalia, Togo, Upper Volta\n\n\n\n\n\n104 Members (1961)*\n\n\n\nAdded: Mauritania, Mongolia, Sierra Leone, Tanganyika\n\t\t\t\t\t\t\t\t*On 13 October 1961, Syria, having resumed its status as an independent State from the United Arab Republic, resumed its separate membership in the United Nations.\n\n\n\n\n\n110 Members (1962)\n\n\n\nAdded: Algeria, Burundi, Jamaica, Rwanda, Trinidad and Tobago, Uganda\n\n\n\n\n\n113 Members (1963)\n\n\n\nAdded: Kenya, Kuwait, Zanzibar\n\n\n\n\n\n115 Members (1964)*\n\n\n\nAdded: Malawi, Malta, Zambia\n\t\t\t\t\t\t\t\t*On 26 April 1964, Zanzibar merged with Tanganyika to become the United Republic of Tanzania.\n\n\n\n\n\n117 Members (1965)*\n\n\n\nAdded: The Gambia, Maldive Islands, Singapore\n\t\t\t\t\t\t\t\t*On 20 January 1965, Indonesia temporarily withdrew from the United Nations.\n\n\n\n\n\n122 Members (1966)*\n\n\n\nAdded: Barbados, Botswana, Guyana, Lesotho\n\t\t\t\t\t\t\t\t* On 28 September 1966, Indonesia rejoined the United Nations.\n\n\n\n\n\n123 Members (1967)\n\n\n\nAdded: Yemen (People's Democratic Republic of Yemen)\n\n\n\n \n\n126 Members (1968)\n\n\n\nAdded: Equatorial Guinea, Mauritius, Swaziland\n\n\n\n\n\n127 Members (1970)\n\n\n\nAdded: Fiji\n\n\n\n\n\n132 Members (1971)\n\n\n\nAdded: Bahrain, Bhutan, Oman, Qatar, United Arab Emirates\n\n\n\n\n\n135 Members (1973)\n\n\n\nAdded: Bahamas, Federal Republic of Germany, German Democratic Republic\n\n\n\n\n\n138 Members (1974)\n\n\n\nAdded: Bangladesh, Grenada, Guinea-Bissau\n\n\n\n\n\n144 Members (1975)\n\n\n\nAdded: Cape Verde, Comoros, Mozambique, Papua New Guinea, Sao Tome and Principe, Suriname\n\n\n\n\n\n147 Members (1976)\n\n\n\nAdded: Angola, Samoa, Seychelles\n\n\n\n\n\n149 Members (1977)\n\n\n\nAdded: Djibouti, Viet Nam\n\n\n\n\n\n151 Members (1978)\n\n\n\nAdded: Dominica, Solomon Islands\n\n\n\n \n\n152 Members (1979)\n\n\n\nAdded: Saint Lucia\n\n\n\n\n\n154 Members (1980)\n\n\n\nAdded: Saint Vincent and the Grenadines, Zimbabwe\n\n\n\n\n\n157 Members (1981) \n\n\n\nAdded: Antigua and Barbuda, Belize, Vanuatu\n\n\n\n\n\n158 Members (1983)\n\n\n\nAdded: Saint Christopher and Nevis\n\n\n\n \n\n159 Members (1984)\n\n\n\nAdded: Brunei Darussalam\n\n\n\n\n\n159 Members (1990)*\n\n\n\nAdded: Liechtenstein, Namibia\n\t\t\t\t\t\t\t\t*On 22 May 1990, the People's Democratic Republic of Yemen (member since 1967) was united with the Yemen Arab Republic (member since 1947), forming the Republic of Yemen. \n\t\t\t\t\t\t\t\tOn 3 October 1990, the German Democratic Republic acceded to the Federal Republic of Germany (both members since 1973), resulting in the reunification of Germany.\n\n\n\n\n\n166 Members (1991)\n\n\n\nAdded: Democratic People's Republic of Korea, Estonia, Latvia, Lithuania, Marshall Islands, Federated States of Micronesia, Republic of Korea\n\n\n\n\n\n179 Members (1992)\n\n\n\nAdded: Armenia, Azerbaijan, Bosnia and Herzegovina, Croatia, Georgia, Kazakhstan, Kyrgyzstan, Republic of Moldova, San Marino, Slovenia, Tajikistan, Turkmenistan, Uzbekistan\n\n\n\n\n\n184 Members (1993)*\n\n\n\nAdded: Andorra, Czech Republic, Eritrea, Monaco, Slovakia, The former Yugoslav Republic of Macedonia\n\t\t\t\t\t\t\t\t*Czechoslovakia was an original Member of the United Nations from 24 October 1945. The Czech and Slovak Federal Republic ceased to exist on 31 December 1992. On 19 January 1993, the Czech Republic and the Slovak Republic were both admitted separately to United Nations membership.\n\n\n\n\n\n185 Members (1994)\n\n\n\nAdded: Palau\n\n\n\n \n\n188 Members (1999)\n\n\n\nAdded: Kiribati, Nauru, Tonga\n\n\n\n\n\n189 Members (2000)*\n\n\n\nAdded: Federal Republic of Yugoslavia, Tuvalu\n\t\t\t\t\t\t\t\t*The Federal Republic of Yugoslavia was part of the Socialist Federal Republic of Yugoslavia, which was an original member of the United Nations and was removed from the official roster of UN members in 2000, following its dissolution.\n\n\n\n\n\n191 Members (2002)\n\n\n\nAdded: Switzerland, Timor-Leste\n\n\n\n\n\n192 Members (2006)\n\n\n\nAdded: Montenegro\n\n\n\n\n\n193 Members (2011)\n\n\n\nAdded: South Sudan\n\n1945-1950          1950s          1960s          1970s          1980s          1990s          2000-Present\n\n\n \n \n\n\n\nOriginal 51 Members (1945)\n\n\n\nArgentina, Australia, Belgium, Bolivia, Brazil, Byelorussian Soviet Socialist Republic, Canada, Chile, China, Colombia, Costa Rica, Cuba, Czechoslovakia, Denmark, Dominican Republic, Ecuador, Egypt, El Salvador, Ethiopia, France, Greece, Guatemala, Haiti, Honduras, India, Iran, Iraq, Lebanon, Liberia, Luxembourg, Mexico, Netherlands, New Zealand, Nicaragua, Norway, Panama, Paraguay, Peru, Philippine Republic, Poland, Saudi Arabia, Syria, Turkey, Ukrainian Soviet Socialist Republic, Union of South Africa, Union of Soviet Socialist Republics, United Kingdom, United States, Uruguay, Venezuela, Yugoslavia\n\n\n\n\n\n55 Members (1946)\n\n\n\nAdded: Afghanistan, Iceland, Siam, Sweden\n\n\n\n\n\n57 Members (1947)\n\n\n\nAdded: Pakistan, Yemen (the Yemen Arab Republic)\n\n\n\n\n\n58 Members (1948)\n\n\n\nAdded: Burma\n\n\n\n \n\n59 Members (1949)\n\n\n\nAdded: Israel\n\n\n\n\n\n60 Members (1950)\n\n\n\nAdded: Indonesia\n\n\n\n\n\n76 Members (1955)\n\n\n\nAdded: Albania, Austria, Bulgaria, Cambodia, Ceylon, Finland, Hungary, Ireland, Italy, Jordan, Laos, Libya, Nepal, Portugal, Romania, Spain\n\n\n\n\n\n80 Members (1956)\n\n\n\nAdded: Japan, Morocco, Sudan, Tunisia\n\n\n\n\n\n82 Members (1957)\n\n\n\nAdded: Ghana, Federation of Malaya\n\n\n\n \n\n82 Members (1958)*\n\n\n\nAdded: Guinea\n\t\t\t\t\t\t\t\t* On 22 February 1958, Syria merged with Egypt (both original members of the United Nations) to become the United Arab Republic. \n\n\n\n\n\n99 Members (1960)\n\n\n\nAdded: Cameroun, Central African Republic, Chad, Congo (Brazzaville), Congo (Leopoldville), Cyprus, Dahomey, Gabon, Ivory Coast, Malagasy Republic, Mali, Niger, Nigeria, Senegal, Somalia, Togo, Upper Volta\n\n\n\n\n\n104 Members (1961)*\n\n\n\nAdded: Mauritania, Mongolia, Sierra Leone, Tanganyika\n\t\t\t\t\t\t\t\t*On 13 October 1961, Syria, having resumed its status as an independent State from the United Arab Republic, resumed its separate membership in the United Nations.\n\n\n\n\n\n110 Members (1962)\n\n\n\nAdded: Algeria, Burundi, Jamaica, Rwanda, Trinidad and Tobago, Uganda\n\n\n\n\n\n113 Members (1963)\n\n\n\nAdded: Kenya, Kuwait, Zanzibar\n\n\n\n\n\n115 Members (1964)*\n\n\n\nAdded: Malawi, Malta, Zambia\n\t\t\t\t\t\t\t\t*On 26 April 1964, Zanzibar merged with Tanganyika to become the United Republic of Tanzania.\n\n\n\n\n\n117 Members (1965)*\n\n\n\nAdded: The Gambia, Maldive Islands, Singapore\n\t\t\t\t\t\t\t\t*On 20 January 1965, Indonesia temporarily withdrew from the United Nations.\n\n\n\n\n\n122 Members (1966)*\n\n\n\nAdded: Barbados, Botswana, Guyana, Lesotho\n\t\t\t\t\t\t\t\t* On 28 September 1966, Indonesia rejoined the United Nations.\n\n\n\n\n\n123 Members (1967)\n\n\n\nAdded: Yemen (People's Democratic Republic of Yemen)\n\n\n\n \n\n126 Members (1968)\n\n\n\nAdded: Equatorial Guinea, Mauritius, Swaziland\n\n\n\n\n\n127 Members (1970)\n\n\n\nAdded: Fiji\n\n\n\n\n\n132 Members (1971)\n\n\n\nAdded: Bahrain, Bhutan, Oman, Qatar, United Arab Emirates\n\n\n\n\n\n135 Members (1973)\n\n\n\nAdded: Bahamas, Federal Republic of Germany, German Democratic Republic\n\n\n\n\n\n138 Members (1974)\n\n\n\nAdded: Bangladesh, Grenada, Guinea-Bissau\n\n\n\n\n\n144 Members (1975)\n\n\n\nAdded: Cape Verde, Comoros, Mozambique, Papua New Guinea, Sao Tome and Principe, Suriname\n\n\n\n\n\n147 Members (1976)\n\n\n\nAdded: Angola, Samoa, Seychelles\n\n\n\n\n\n149 Members (1977)\n\n\n\nAdded: Djibouti, Viet Nam\n\n\n\n\n\n151 Members (1978)\n\n\n\nAdded: Dominica, Solomon Islands\n\n\n\n \n\n152 Members (1979)\n\n\n\nAdded: Saint Lucia\n\n\n\n\n\n154 Members (1980)\n\n\n\nAdded: Saint Vincent and the Grenadines, Zimbabwe\n\n\n\n\n\n157 Members (1981) \n\n\n\nAdded: Antigua and Barbuda, Belize, Vanuatu\n\n\n\n\n\n158 Members (1983)\n\n\n\nAdded: Saint Christopher and Nevis\n\n\n\n \n\n159 Members (1984)\n\n\n\nAdded: Brunei Darussalam\n\n\n\n\n\n159 Members (1990)*\n\n\n\nAdded: Liechtenstein, Namibia\n\t\t\t\t\t\t\t\t*On 22 May 1990, the People's Democratic Republic of Yemen (member since 1967) was united with the Yemen Arab Republic (member since 1947), forming the Republic of Yemen. \n\t\t\t\t\t\t\t\tOn 3 October 1990, the German Democratic Republic acceded to the Federal Republic of Germany (both members since 1973), resulting in the reunification of Germany.\n\n\n\n\n\n166 Members (1991)\n\n\n\nAdded: Democratic People's Republic of Korea, Estonia, Latvia, Lithuania, Marshall Islands, Federated States of Micronesia, Republic of Korea\n\n\n\n\n\n179 Members (1992)\n\n\n\nAdded: Armenia, Azerbaijan, Bosnia and Herzegovina, Croatia, Georgia, Kazakhstan, Kyrgyzstan, Republic of Moldova, San Marino, Slovenia, Tajikistan, Turkmenistan, Uzbekistan\n\n\n\n\n\n184 Members (1993)*\n\n\n\nAdded: Andorra, Czech Republic, Eritrea, Monaco, Slovakia, The former Yugoslav Republic of Macedonia\n\t\t\t\t\t\t\t\t*Czechoslovakia was an original Member of the United Nations from 24 October 1945. The Czech and Slovak Federal Republic ceased to exist on 31 December 1992. On 19 January 1993, the Czech Republic and the Slovak Republic were both admitted separately to United Nations membership.\n\n\n\n\n\n185 Members (1994)\n\n\n\nAdded: Palau\n\n\n\n \n\n188 Members (1999)\n\n\n\nAdded: Kiribati, Nauru, Tonga\n\n\n\n\n\n189 Members (2000)*\n\n\n\nAdded: Federal Republic of Yugoslavia, Tuvalu\n\t\t\t\t\t\t\t\t*The Federal Republic of Yugoslavia was part of the Socialist Federal Republic of Yugoslavia, which was an original member of the United Nations and was removed from the official roster of UN members in 2000, following its dissolution.\n\n\n\n\n\n191 Members (2002)\n\n\n\nAdded: Switzerland, Timor-Leste\n\n\n\n\n\n192 Members (2006)\n\n\n\nAdded: Montenegro\n\n\n\n\n\n193 Members (2011)\n\n\n\nAdded: South Sudan\n\n1945-1950          1950s          1960s          1970s          1980s          1990s          2000-Present\n\n\n \n \n\n\n\nOriginal 51 Members (1945)\n\n\n\nArgentina, Australia, Belgium, Bolivia, Brazil, Byelorussian Soviet Socialist Republic, Canada, Chile, China, Colombia, Costa Rica, Cuba, Czechoslovakia, Denmark, Dominican Republic, Ecuador, Egypt, El Salvador, Ethiopia, France, Greece, Guatemala, Haiti, Honduras, India, Iran, Iraq, Lebanon, Liberia, Luxembourg, Mexico, Netherlands, New Zealand, Nicaragua, Norway, Panama, Paraguay, Peru, Philippine Republic, Poland, Saudi Arabia, Syria, Turkey, Ukrainian Soviet Socialist Republic, Union of South Africa, Union of Soviet Socialist Republics, United Kingdom, United States, Uruguay, Venezuela, Yugoslavia\n\n\n\n\n\n55 Members (1946)\n\n\n\nAdded: Afghanistan, Iceland, Siam, Sweden\n\n\n\n\n\n57 Members (1947)\n\n\n\nAdded: Pakistan, Yemen (the Yemen Arab Republic)\n\n\n\n\n\n58 Members (1948)\n\n\n\nAdded: Burma\n\n\n\n \n\n59 Members (1949)\n\n\n\nAdded: Israel\n\n\n\n\n\n60 Members (1950)\n\n\n\nAdded: Indonesia\n\n\n\n\n\n76 Members (1955)\n\n\n\nAdded: Albania, Austria, Bulgaria, Cambodia, Ceylon, Finland, Hungary, Ireland, Italy, Jordan, Laos, Libya, Nepal, Portugal, Romania, Spain\n\n\n\n\n\n80 Members (1956)\n\n\n\nAdded: Japan, Morocco, Sudan, Tunisia\n\n\n\n\n\n82 Members (1957)\n\n\n\nAdded: Ghana, Federation of Malaya\n\n\n\n \n\n82 Members (1958)*\n\n\n\nAdded: Guinea\n\t\t\t\t\t\t\t\t* On 22 February 1958, Syria merged with Egypt (both original members of the United Nations) to become the United Arab Republic. \n\n\n\n\n\n99 Members (1960)\n\n\n\nAdded: Cameroun, Central African Republic, Chad, Congo (Brazzaville), Congo (Leopoldville), Cyprus, Dahomey, Gabon, Ivory Coast, Malagasy Republic, Mali, Niger, Nigeria, Senegal, Somalia, Togo, Upper Volta\n\n\n\n\n\n104 Members (1961)*\n\n\n\nAdded: Mauritania, Mongolia, Sierra Leone, Tanganyika\n\t\t\t\t\t\t\t\t*On 13 October 1961, Syria, having resumed its status as an independent State from the United Arab Republic, resumed its separate membership in the United Nations.\n\n\n\n\n\n110 Members (1962)\n\n\n\nAdded: Algeria, Burundi, Jamaica, Rwanda, Trinidad and Tobago, Uganda\n\n\n\n\n\n113 Members (1963)\n\n\n\nAdded: Kenya, Kuwait, Zanzibar\n\n\n\n\n\n115 Members (1964)*\n\n\n\nAdded: Malawi, Malta, Zambia\n\t\t\t\t\t\t\t\t*On 26 April 1964, Zanzibar merged with Tanganyika to become the United Republic of Tanzania.\n\n\n\n\n\n117 Members (1965)*\n\n\n\nAdded: The Gambia, Maldive Islands, Singapore\n\t\t\t\t\t\t\t\t*On 20 January 1965, Indonesia temporarily withdrew from the United Nations.\n\n\n\n\n\n122 Members (1966)*\n\n\n\nAdded: Barbados, Botswana, Guyana, Lesotho\n\t\t\t\t\t\t\t\t* On 28 September 1966, Indonesia rejoined the United Nations.\n\n\n\n\n\n123 Members (1967)\n\n\n\nAdded: Yemen (People's Democratic Republic of Yemen)\n\n\n\n \n\n126 Members (1968)\n\n\n\nAdded: Equatorial Guinea, Mauritius, Swaziland\n\n\n\n\n\n127 Members (1970)\n\n\n\nAdded: Fiji\n\n\n\n\n\n132 Members (1971)\n\n\n\nAdded: Bahrain, Bhutan, Oman, Qatar, United Arab Emirates\n\n\n\n\n\n135 Members (1973)\n\n\n\nAdded: Bahamas, Federal Republic of Germany, German Democratic Republic\n\n\n\n\n\n138 Members (1974)\n\n\n\nAdded: Bangladesh, Grenada, Guinea-Bissau\n\n\n\n\n\n144 Members (1975)\n\n\n\nAdded: Cape Verde, Comoros, Mozambique, Papua New Guinea, Sao Tome and Principe, Suriname\n\n\n\n\n\n147 Members (1976)\n\n\n\nAdded: Angola, Samoa, Seychelles\n\n\n\n\n\n149 Members (1977)\n\n\n\nAdded: Djibouti, Viet Nam\n\n\n\n\n\n151 Members (1978)\n\n\n\nAdded: Dominica, Solomon Islands\n\n\n\n \n\n152 Members (1979)\n\n\n\nAdded: Saint Lucia\n\n\n\n\n\n154 Members (1980)\n\n\n\nAdded: Saint Vincent and the Grenadines, Zimbabwe\n\n\n\n\n\n157 Members (1981) \n\n\n\nAdded: Antigua and Barbuda, Belize, Vanuatu\n\n\n\n\n\n158 Members (1983)\n\n\n\nAdded: Saint Christopher and Nevis\n\n\n\n \n\n159 Members (1984)\n\n\n\nAdded: Brunei Darussalam\n\n\n\n\n\n159 Members (1990)*\n\n\n\nAdded: Liechtenstein, Namibia\n\t\t\t\t\t\t\t\t*On 22 May 1990, the People's Democratic Republic of Yemen (member since 1967) was united with the Yemen Arab Republic (member since 1947), forming the Republic of Yemen. \n\t\t\t\t\t\t\t\tOn 3 October 1990, the German Democratic Republic acceded to the Federal Republic of Germany (both members since 1973), resulting in the reunification of Germany.\n\n\n\n\n\n166 Members (1991)\n\n\n\nAdded: Democratic People's Republic of Korea, Estonia, Latvia, Lithuania, Marshall Islands, Federated States of Micronesia, Republic of Korea\n\n\n\n\n\n179 Members (1992)\n\n\n\nAdded: Armenia, Azerbaijan, Bosnia and Herzegovina, Croatia, Georgia, Kazakhstan, Kyrgyzstan, Republic of Moldova, San Marino, Slovenia, Tajikistan, Turkmenistan, Uzbekistan\n\n\n\n\n\n184 Members (1993)*\n\n\n\nAdded: Andorra, Czech Republic, Eritrea, Monaco, Slovakia, The former Yugoslav Republic of Macedonia\n\t\t\t\t\t\t\t\t*Czechoslovakia was an original Member of the United Nations from 24 October 1945. The Czech and Slovak Federal Republic ceased to exist on 31 December 1992. On 19 January 1993, the Czech Republic and the Slovak Republic were both admitted separately to United Nations membership.\n\n\n\n\n\n185 Members (1994)\n\n\n\nAdded: Palau\n\n\n\n \n\n188 Members (1999)\n\n\n\nAdded: Kiribati, Nauru, Tonga\n\n\n\n\n\n189 Members (2000)*\n\n\n\nAdded: Federal Republic of Yugoslavia, Tuvalu\n\t\t\t\t\t\t\t\t*The Federal Republic of Yugoslavia was part of the Socialist Federal Republic of Yugoslavia, which was an original member of the United Nations and was removed from the official roster of UN members in 2000, following its dissolution.\n\n\n\n\n\n191 Members (2002)\n\n\n\nAdded: Switzerland, Timor-Leste\n\n\n\n\n\n192 Members (2006)\n\n\n\nAdded: Montenegro\n\n\n\n\n\n193 Members (2011)\n\n\n\nAdded: South Sudan\n\n1945-1950          1950s          1960s          1970s          1980s          1990s          2000-Present\n\n\n \n \n\n\n\nOriginal 51 Members (1945)\n\n\n\nArgentina, Australia, Belgium, Bolivia, Brazil, Byelorussian Soviet Socialist Republic, Canada, Chile, China, Colombia, Costa Rica, Cuba, Czechoslovakia, Denmark, Dominican Republic, Ecuador, Egypt, El Salvador, Ethiopia, France, Greece, Guatemala, Haiti, Honduras, India, Iran, Iraq, Lebanon, Liberia, Luxembourg, Mexico, Netherlands, New Zealand, Nicaragua, Norway, Panama, Paraguay, Peru, Philippine Republic, Poland, Saudi Arabia, Syria, Turkey, Ukrainian Soviet Socialist Republic, Union of South Africa, Union of Soviet Socialist Republics, United Kingdom, United States, Uruguay, Venezuela, Yugoslavia\n\n\n\n\n\n55 Members (1946)\n\n\n\nAdded: Afghanistan, Iceland, Siam, Sweden\n\n\n\n\n\n57 Members (1947)\n\n\n\nAdded: Pakistan, Yemen (the Yemen Arab Republic)\n\n\n\n\n\n58 Members (1948)\n\n\n\nAdded: Burma\n\n\n\n \n\n59 Members (1949)\n\n\n\nAdded: Israel\n\n\n\n\n\n60 Members (1950)\n\n\n\nAdded: Indonesia\n\n\n\n\n\n76 Members (1955)\n\n\n\nAdded: Albania, Austria, Bulgaria, Cambodia, Ceylon, Finland, Hungary, Ireland, Italy, Jordan, Laos, Libya, Nepal, Portugal, Romania, Spain\n\n\n\n\n\n80 Members (1956)\n\n\n\nAdded: Japan, Morocco, Sudan, Tunisia\n\n\n\n\n\n82 Members (1957)\n\n\n\nAdded: Ghana, Federation of Malaya\n\n\n\n \n\n82 Members (1958)*\n\n\n\nAdded: Guinea\n\t\t\t\t\t\t\t\t* On 22 February 1958, Syria merged with Egypt (both original members of the United Nations) to become the United Arab Republic. \n\n\n\n\n\n99 Members (1960)\n\n\n\nAdded: Cameroun, Central African Republic, Chad, Congo (Brazzaville), Congo (Leopoldville), Cyprus, Dahomey, Gabon, Ivory Coast, Malagasy Republic, Mali, Niger, Nigeria, Senegal, Somalia, Togo, Upper Volta\n\n\n\n\n\n104 Members (1961)*\n\n\n\nAdded: Mauritania, Mongolia, Sierra Leone, Tanganyika\n\t\t\t\t\t\t\t\t*On 13 October 1961, Syria, having resumed its status as an independent State from the United Arab Republic, resumed its separate membership in the United Nations.\n\n\n\n\n\n110 Members (1962)\n\n\n\nAdded: Algeria, Burundi, Jamaica, Rwanda, Trinidad and Tobago, Uganda\n\n\n\n\n\n113 Members (1963)\n\n\n\nAdded: Kenya, Kuwait, Zanzibar\n\n\n\n\n\n115 Members (1964)*\n\n\n\nAdded: Malawi, Malta, Zambia\n\t\t\t\t\t\t\t\t*On 26 April 1964, Zanzibar merged with Tanganyika to become the United Republic of Tanzania.\n\n\n\n\n\n117 Members (1965)*\n\n\n\nAdded: The Gambia, Maldive Islands, Singapore\n\t\t\t\t\t\t\t\t*On 20 January 1965, Indonesia temporarily withdrew from the United Nations.\n\n\n\n\n\n122 Members (1966)*\n\n\n\nAdded: Barbados, Botswana, Guyana, Lesotho\n\t\t\t\t\t\t\t\t* On 28 September 1966, Indonesia rejoined the United Nations.\n\n\n\n\n\n123 Members (1967)\n\n\n\nAdded: Yemen (People's Democratic Republic of Yemen)\n\n\n\n \n\n126 Members (1968)\n\n\n\nAdded: Equatorial Guinea, Mauritius, Swaziland\n\n\n\n\n\n127 Members (1970)\n\n\n\nAdded: Fiji\n\n\n\n\n\n132 Members (1971)\n\n\n\nAdded: Bahrain, Bhutan, Oman, Qatar, United Arab Emirates\n\n\n\n\n\n135 Members (1973)\n\n\n\nAdded: Bahamas, Federal Republic of Germany, German Democratic Republic\n\n\n\n\n\n138 Members (1974)\n\n\n\nAdded: Bangladesh, Grenada, Guinea-Bissau\n\n\n\n\n\n144 Members (1975)\n\n\n\nAdded: Cape Verde, Comoros, Mozambique, Papua New Guinea, Sao Tome and Principe, Suriname\n\n\n\n\n\n147 Members (1976)\n\n\n\nAdded: Angola, Samoa, Seychelles\n\n\n\n\n\n149 Members (1977)\n\n\n\nAdded: Djibouti, Viet Nam\n\n\n\n\n\n151 Members (1978)\n\n\n\nAdded: Dominica, Solomon Islands\n\n\n\n \n\n152 Members (1979)\n\n\n\nAdded: Saint Lucia\n\n\n\n\n\n154 Members (1980)\n\n\n\nAdded: Saint Vincent and the Grenadines, Zimbabwe\n\n\n\n\n\n157 Members (1981) \n\n\n\nAdded: Antigua and Barbuda, Belize, Vanuatu\n\n\n\n\n\n158 Members (1983)\n\n\n\nAdded: Saint Christopher and Nevis\n\n\n\n \n\n159 Members (1984)\n\n\n\nAdded: Brunei Darussalam\n\n\n\n\n\n159 Members (1990)*\n\n\n\nAdded: Liechtenstein, Namibia\n\t\t\t\t\t\t\t\t*On 22 May 1990, the People's Democratic Republic of Yemen (member since 1967) was united with the Yemen Arab Republic (member since 1947), forming the Republic of Yemen. \n\t\t\t\t\t\t\t\tOn 3 October 1990, the German Democratic Republic acceded to the Federal Republic of Germany (both members since 1973), resulting in the reunification of Germany.\n\n\n\n\n\n166 Members (1991)\n\n\n\nAdded: Democratic People's Republic of Korea, Estonia, Latvia, Lithuania, Marshall Islands, Federated States of Micronesia, Republic of Korea\n\n\n\n\n\n179 Members (1992)\n\n\n\nAdded: Armenia, Azerbaijan, Bosnia and Herzegovina, Croatia, Georgia, Kazakhstan, Kyrgyzstan, Republic of Moldova, San Marino, Slovenia, Tajikistan, Turkmenistan, Uzbekistan\n\n\n\n\n\n184 Members (1993)*\n\n\n\nAdded: Andorra, Czech Republic, Eritrea, Monaco, Slovakia, The former Yugoslav Republic of Macedonia\n\t\t\t\t\t\t\t\t*Czechoslovakia was an original Member of the United Nations from 24 October 1945. The Czech and Slovak Federal Republic ceased to exist on 31 December 1992. On 19 January 1993, the Czech Republic and the Slovak Republic were both admitted separately to United Nations membership.\n\n\n\n\n\n185 Members (1994)\n\n\n\nAdded: Palau\n\n\n\n \n\n188 Members (1999)\n\n\n\nAdded: Kiribati, Nauru, Tonga\n\n\n\n\n\n189 Members (2000)*\n\n\n\nAdded: Federal Republic of Yugoslavia, Tuvalu\n\t\t\t\t\t\t\t\t*The Federal Republic of Yugoslavia was part of the Socialist Federal Republic of Yugoslavia, which was an original member of the United Nations and was removed from the official roster of UN members in 2000, following its dissolution.\n\n\n\n\n\n191 Members (2002)\n\n\n\nAdded: Switzerland, Timor-Leste\n\n\n\n\n\n192 Members (2006)\n\n\n\nAdded: Montenegro\n\n\n\n\n\n193 Members (2011)\n\n\n\nAdded: South Sudan\n\n1945-1950          1950s          1960s          1970s          1980s          1990s          2000-Present\n\n\n \n \n\n\n\nOriginal 51 Members (1945)\n\n\n\nArgentina, Australia, Belgium, Bolivia, Brazil, Byelorussian Soviet Socialist Republic, Canada, Chile, China, Colombia, Costa Rica, Cuba, Czechoslovakia, Denmark, Dominican Republic, Ecuador, Egypt, El Salvador, Ethiopia, France, Greece, Guatemala, Haiti, Honduras, India, Iran, Iraq, Lebanon, Liberia, Luxembourg, Mexico, Netherlands, New Zealand, Nicaragua, Norway, Panama, Paraguay, Peru, Philippine Republic, Poland, Saudi Arabia, Syria, Turkey, Ukrainian Soviet Socialist Republic, Union of South Africa, Union of Soviet Socialist Republics, United Kingdom, United States, Uruguay, Venezuela, Yugoslavia\n\n\n\n\n\n55 Members (1946)\n\n\n\nAdded: Afghanistan, Iceland, Siam, Sweden\n\n\n\n\n\n57 Members (1947)\n\n\n\nAdded: Pakistan, Yemen (the Yemen Arab Republic)\n\n\n\n\n\n58 Members (1948)\n\n\n\nAdded: Burma\n\n\n\n \n\n59 Members (1949)\n\n\n\nAdded: Israel\n\n\n\n\n\n60 Members (1950)\n\n\n\nAdded: Indonesia\n\n\n\n\n\n76 Members (1955)\n\n\n\nAdded: Albania, Austria, Bulgaria, Cambodia, Ceylon, Finland, Hungary, Ireland, Italy, Jordan, Laos, Libya, Nepal, Portugal, Romania, Spain\n\n\n\n\n\n80 Members (1956)\n\n\n\nAdded: Japan, Morocco, Sudan, Tunisia\n\n\n\n\n\n82 Members (1957)\n\n\n\nAdded: Ghana, Federation of Malaya\n\n\n\n \n\n82 Members (1958)*\n\n\n\nAdded: Guinea\n\t\t\t\t\t\t\t\t* On 22 February 1958, Syria merged with Egypt (both original members of the United Nations) to become the United Arab Republic. \n\n\n\n\n\n99 Members (1960)\n\n\n\nAdded: Cameroun, Central African Republic, Chad, Congo (Brazzaville), Congo (Leopoldville), Cyprus, Dahomey, Gabon, Ivory Coast, Malagasy Republic, Mali, Niger, Nigeria, Senegal, Somalia, Togo, Upper Volta\n\n\n\n\n\n104 Members (1961)*\n\n\n\nAdded: Mauritania, Mongolia, Sierra Leone, Tanganyika\n\t\t\t\t\t\t\t\t*On 13 October 1961, Syria, having resumed its status as an independent State from the United Arab Republic, resumed its separate membership in the United Nations.\n\n\n\n\n\n110 Members (1962)\n\n\n\nAdded: Algeria, Burundi, Jamaica, Rwanda, Trinidad and Tobago, Uganda\n\n\n\n\n\n113 Members (1963)\n\n\n\nAdded: Kenya, Kuwait, Zanzibar\n\n\n\n\n\n115 Members (1964)*\n\n\n\nAdded: Malawi, Malta, Zambia\n\t\t\t\t\t\t\t\t*On 26 April 1964, Zanzibar merged with Tanganyika to become the United Republic of Tanzania.\n\n\n\n\n\n117 Members (1965)*\n\n\n\nAdded: The Gambia, Maldive Islands, Singapore\n\t\t\t\t\t\t\t\t*On 20 January 1965, Indonesia temporarily withdrew from the United Nations.\n\n\n\n\n\n122 Members (1966)*\n\n\n\nAdded: Barbados, Botswana, Guyana, Lesotho\n\t\t\t\t\t\t\t\t* On 28 September 1966, Indonesia rejoined the United Nations.\n\n\n\n\n\n123 Members (1967)\n\n\n\nAdded: Yemen (People's Democratic Republic of Yemen)\n\n\n\n \n\n126 Members (1968)\n\n\n\nAdded: Equatorial Guinea, Mauritius, Swaziland\n\n\n\n\n\n127 Members (1970)\n\n\n\nAdded: Fiji\n\n\n\n\n\n132 Members (1971)\n\n\n\nAdded: Bahrain, Bhutan, Oman, Qatar, United Arab Emirates\n\n\n\n\n\n135 Members (1973)\n\n\n\nAdded: Bahamas, Federal Republic of Germany, German Democratic Republic\n\n\n\n\n\n138 Members (1974)\n\n\n\nAdded: Bangladesh, Grenada, Guinea-Bissau\n\n\n\n\n\n144 Members (1975)\n\n\n\nAdded: Cape Verde, Comoros, Mozambique, Papua New Guinea, Sao Tome and Principe, Suriname\n\n\n\n\n\n147 Members (1976)\n\n\n\nAdded: Angola, Samoa, Seychelles\n\n\n\n\n\n149 Members (1977)\n\n\n\nAdded: Djibouti, Viet Nam\n\n\n\n\n\n151 Members (1978)\n\n\n\nAdded: Dominica, Solomon Islands\n\n\n\n \n\n152 Members (1979)\n\n\n\nAdded: Saint Lucia\n\n\n\n\n\n154 Members (1980)\n\n\n\nAdded: Saint Vincent and the Grenadines, Zimbabwe\n\n\n\n\n\n157 Members (1981) \n\n\n\nAdded: Antigua and Barbuda, Belize, Vanuatu\n\n\n\n\n\n158 Members (1983)\n\n\n\nAdded: Saint Christopher and Nevis\n\n\n\n \n\n159 Members (1984)\n\n\n\nAdded: Brunei Darussalam\n\n\n\n\n\n159 Members (1990)*\n\n\n\nAdded: Liechtenstein, Namibia\n\t\t\t\t\t\t\t\t*On 22 May 1990, the People's Democratic Republic of Yemen (member since 1967) was united with the Yemen Arab Republic (member since 1947), forming the Republic of Yemen. \n\t\t\t\t\t\t\t\tOn 3 October 1990, the German Democratic Republic acceded to the Federal Republic of Germany (both members since 1973), resulting in the reunification of Germany.\n\n\n\n\n\n166 Members (1991)\n\n\n\nAdded: Democratic People's Republic of Korea, Estonia, Latvia, Lithuania, Marshall Islands, Federated States of Micronesia, Republic of Korea\n\n\n\n\n\n179 Members (1992)\n\n\n\nAdded: Armenia, Azerbaijan, Bosnia and Herzegovina, Croatia, Georgia, Kazakhstan, Kyrgyzstan, Republic of Moldova, San Marino, Slovenia, Tajikistan, Turkmenistan, Uzbekistan\n\n\n\n\n\n184 Members (1993)*\n\n\n\nAdded: Andorra, Czech Republic, Eritrea, Monaco, Slovakia, The former Yugoslav Republic of Macedonia\n\t\t\t\t\t\t\t\t*Czechoslovakia was an original Member of the United Nations from 24 October 1945. The Czech and Slovak Federal Republic ceased to exist on 31 December 1992. On 19 January 1993, the Czech Republic and the Slovak Republic were both admitted separately to United Nations membership.\n\n\n\n\n\n185 Members (1994)\n\n\n\nAdded: Palau\n\n\n\n \n\n188 Members (1999)\n\n\n\nAdded: Kiribati, Nauru, Tonga\n\n\n\n\n\n189 Members (2000)*\n\n\n\nAdded: Federal Republic of Yugoslavia, Tuvalu\n\t\t\t\t\t\t\t\t*The Federal Republic of Yugoslavia was part of the Socialist Federal Republic of Yugoslavia, which was an original member of the United Nations and was removed from the official roster of UN members in 2000, following its dissolution.\n\n\n\n\n\n191 Members (2002)\n\n\n\nAdded: Switzerland, Timor-Leste\n\n\n\n\n\n192 Members (2006)\n\n\n\nAdded: Montenegro\n\n\n\n\n\n193 Members (2011)\n\n\n\nAdded: South Sudan\n\n1945-1950          1950s          1960s          1970s          1980s          1990s          2000-Present\n\n\n \n \n\n\n\nOriginal 51 Members (1945)\n\n\n\nArgentina, Australia, Belgium, Bolivia, Brazil, Byelorussian Soviet Socialist Republic, Canada, Chile, China, Colombia, Costa Rica, Cuba, Czechoslovakia, Denmark, Dominican Republic, Ecuador, Egypt, El Salvador, Ethiopia, France, Greece, Guatemala, Haiti, Honduras, India, Iran, Iraq, Lebanon, Liberia, Luxembourg, Mexico, Netherlands, New Zealand, Nicaragua, Norway, Panama, Paraguay, Peru, Philippine Republic, Poland, Saudi Arabia, Syria, Turkey, Ukrainian Soviet Socialist Republic, Union of South Africa, Union of Soviet Socialist Republics, United Kingdom, United States, Uruguay, Venezuela, Yugoslavia\n\n\n\n\n\n55 Members (1946)\n\n\n\nAdded: Afghanistan, Iceland, Siam, Sweden\n\n\n\n\n\n57 Members (1947)\n\n\n\nAdded: Pakistan, Yemen (the Yemen Arab Republic)\n\n\n\n\n\n58 Members (1948)\n\n\n\nAdded: Burma\n\n\n\n \n\n59 Members (1949)\n\n\n\nAdded: Israel\n\n\n\n\n\n60 Members (1950)\n\n\n\nAdded: Indonesia\n\n\n\n\n\n76 Members (1955)\n\n\n\nAdded: Albania, Austria, Bulgaria, Cambodia, Ceylon, Finland, Hungary, Ireland, Italy, Jordan, Laos, Libya, Nepal, Portugal, Romania, Spain\n\n\n\n\n\n80 Members (1956)\n\n\n\nAdded: Japan, Morocco, Sudan, Tunisia\n\n\n\n\n\n82 Members (1957)\n\n\n\nAdded: Ghana, Federation of Malaya\n\n\n\n \n\n82 Members (1958)*\n\n\n\nAdded: Guinea\n\t\t\t\t\t\t\t\t* On 22 February 1958, Syria merged with Egypt (both original members of the United Nations) to become the United Arab Republic. \n\n\n\n\n\n99 Members (1960)\n\n\n\nAdded: Cameroun, Central African Republic, Chad, Congo (Brazzaville), Congo (Leopoldville), Cyprus, Dahomey, Gabon, Ivory Coast, Malagasy Republic, Mali, Niger, Nigeria, Senegal, Somalia, Togo, Upper Volta\n\n\n\n\n\n104 Members (1961)*\n\n\n\nAdded: Mauritania, Mongolia, Sierra Leone, Tanganyika\n\t\t\t\t\t\t\t\t*On 13 October 1961, Syria, having resumed its status as an independent State from the United Arab Republic, resumed its separate membership in the United Nations.\n\n\n\n\n\n110 Members (1962)\n\n\n\nAdded: Algeria, Burundi, Jamaica, Rwanda, Trinidad and Tobago, Uganda\n\n\n\n\n\n113 Members (1963)\n\n\n\nAdded: Kenya, Kuwait, Zanzibar\n\n\n\n\n\n115 Members (1964)*\n\n\n\nAdded: Malawi, Malta, Zambia\n\t\t\t\t\t\t\t\t*On 26 April 1964, Zanzibar merged with Tanganyika to become the United Republic of Tanzania.\n\n\n\n\n\n117 Members (1965)*\n\n\n\nAdded: The Gambia, Maldive Islands, Singapore\n\t\t\t\t\t\t\t\t*On 20 January 1965, Indonesia temporarily withdrew from the United Nations.\n\n\n\n\n\n122 Members (1966)*\n\n\n\nAdded: Barbados, Botswana, Guyana, Lesotho\n\t\t\t\t\t\t\t\t* On 28 September 1966, Indonesia rejoined the United Nations.\n\n\n\n\n\n123 Members (1967)\n\n\n\nAdded: Yemen (People's Democratic Republic of Yemen)\n\n\n\n \n\n126 Members (1968)\n\n\n\nAdded: Equatorial Guinea, Mauritius, Swaziland\n\n\n\n\n\n127 Members (1970)\n\n\n\nAdded: Fiji\n\n\n\n\n\n132 Members (1971)\n\n\n\nAdded: Bahrain, Bhutan, Oman, Qatar, United Arab Emirates\n\n\n\n\n\n135 Members (1973)\n\n\n\nAdded: Bahamas, Federal Republic of Germany, German Democratic Republic\n\n\n\n\n\n138 Members (1974)\n\n\n\nAdded: Bangladesh, Grenada, Guinea-Bissau\n\n\n\n\n\n144 Members (1975)\n\n\n\nAdded: Cape Verde, Comoros, Mozambique, Papua New Guinea, Sao Tome and Principe, Suriname\n\n\n\n\n\n147 Members (1976)\n\n\n\nAdded: Angola, Samoa, Seychelles\n\n\n\n\n\n149 Members (1977)\n\n\n\nAdded: Djibouti, Viet Nam\n\n\n\n\n\n151 Members (1978)\n\n\n\nAdded: Dominica, Solomon Islands\n\n\n\n \n\n152 Members (1979)\n\n\n\nAdded: Saint Lucia\n\n\n\n\n\n154 Members (1980)\n\n\n\nAdded: Saint Vincent and the Grenadines, Zimbabwe\n\n\n\n\n\n157 Members (1981) \n\n\n\nAdded: Antigua and Barbuda, Belize, Vanuatu\n\n\n\n\n\n158 Members (1983)\n\n\n\nAdded: Saint Christopher and Nevis\n\n\n\n \n\n159 Members (1984)\n\n\n\nAdded: Brunei Darussalam\n\n\n\n\n\n159 Members (1990)*\n\n\n\nAdded: Liechtenstein, Namibia\n\t\t\t\t\t\t\t\t*On 22 May 1990, the People's Democratic Republic of Yemen (member since 1967) was united with the Yemen Arab Republic (member since 1947), forming the Republic of Yemen. \n\t\t\t\t\t\t\t\tOn 3 October 1990, the German Democratic Republic acceded to the Federal Republic of Germany (both members since 1973), resulting in the reunification of Germany.\n\n\n\n\n\n166 Members (1991)\n\n\n\nAdded: Democratic People's Republic of Korea, Estonia, Latvia, Lithuania, Marshall Islands, Federated States of Micronesia, Republic of Korea\n\n\n\n\n\n179 Members (1992)\n\n\n\nAdded: Armenia, Azerbaijan, Bosnia and Herzegovina, Croatia, Georgia, Kazakhstan, Kyrgyzstan, Republic of Moldova, San Marino, Slovenia, Tajikistan, Turkmenistan, Uzbekistan\n\n\n\n\n\n184 Members (1993)*\n\n\n\nAdded: Andorra, Czech Republic, Eritrea, Monaco, Slovakia, The former Yugoslav Republic of Macedonia\n\t\t\t\t\t\t\t\t*Czechoslovakia was an original Member of the United Nations from 24 October 1945. The Czech and Slovak Federal Republic ceased to exist on 31 December 1992. On 19 January 1993, the Czech Republic and the Slovak Republic were both admitted separately to United Nations membership.\n\n\n\n\n\n185 Members (1994)\n\n\n\nAdded: Palau\n\n\n\n \n\n188 Members (1999)\n\n\n\nAdded: Kiribati, Nauru, Tonga\n\n\n\n\n\n189 Members (2000)*\n\n\n\nAdded: Federal Republic of Yugoslavia, Tuvalu\n\t\t\t\t\t\t\t\t*The Federal Republic of Yugoslavia was part of the Socialist Federal Republic of Yugoslavia, which was an original member of the United Nations and was removed from the official roster of UN members in 2000, following its dissolution.\n\n\n\n\n\n191 Members (2002)\n\n\n\nAdded: Switzerland, Timor-Leste\n\n\n\n\n\n192 Members (2006)\n\n\n\nAdded: Montenegro\n\n\n\n\n\n193 Members (2011)\n\n\n\nAdded: South Sudan\n\n1945-1950          1950s          1960s          1970s          1980s          1990s          2000-Present\n\n\n \n \n\n\n\nOriginal 51 Members (1945)\n\n\n\nArgentina, Australia, Belgium, Bolivia, Brazil, Byelorussian Soviet Socialist Republic, Canada, Chile, China, Colombia, Costa Rica, Cuba, Czechoslovakia, Denmark, Dominican Republic, Ecuador, Egypt, El Salvador, Ethiopia, France, Greece, Guatemala, Haiti, Honduras, India, Iran, Iraq, Lebanon, Liberia, Luxembourg, Mexico, Netherlands, New Zealand, Nicaragua, Norway, Panama, Paraguay, Peru, Philippine Republic, Poland, Saudi Arabia, Syria, Turkey, Ukrainian Soviet Socialist Republic, Union of South Africa, Union of Soviet Socialist Republics, United Kingdom, United States, Uruguay, Venezuela, Yugoslavia\n\n\n\n\n\n55 Members (1946)\n\n\n\nAdded: Afghanistan, Iceland, Siam, Sweden\n\n\n\n\n\n57 Members (1947)\n\n\n\nAdded: Pakistan, Yemen (the Yemen Arab Republic)\n\n\n\n\n\n58 Members (1948)\n\n\n\nAdded: Burma\n\n\n\n \n\n59 Members (1949)\n\n\n\nAdded: Israel\n\n\n\n\n\n60 Members (1950)\n\n\n\nAdded: Indonesia\n\n\n\n\n\n76 Members (1955)\n\n\n\nAdded: Albania, Austria, Bulgaria, Cambodia, Ceylon, Finland, Hungary, Ireland, Italy, Jordan, Laos, Libya, Nepal, Portugal, Romania, Spain\n\n\n\n\n\n80 Members (1956)\n\n\n\nAdded: Japan, Morocco, Sudan, Tunisia\n\n\n\n\n\n82 Members (1957)\n\n\n\nAdded: Ghana, Federation of Malaya\n\n\n\n \n\n82 Members (1958)*\n\n\n\nAdded: Guinea\n\t\t\t\t\t\t\t\t* On 22 February 1958, Syria merged with Egypt (both original members of the United Nations) to become the United Arab Republic. \n\n\n\n\n\n99 Members (1960)\n\n\n\nAdded: Cameroun, Central African Republic, Chad, Congo (Brazzaville), Congo (Leopoldville), Cyprus, Dahomey, Gabon, Ivory Coast, Malagasy Republic, Mali, Niger, Nigeria, Senegal, Somalia, Togo, Upper Volta\n\n\n\n\n\n104 Members (1961)*\n\n\n\nAdded: Mauritania, Mongolia, Sierra Leone, Tanganyika\n\t\t\t\t\t\t\t\t*On 13 October 1961, Syria, having resumed its status as an independent State from the United Arab Republic, resumed its separate membership in the United Nations.\n\n\n\n\n\n110 Members (1962)\n\n\n\nAdded: Algeria, Burundi, Jamaica, Rwanda, Trinidad and Tobago, Uganda\n\n\n\n\n\n113 Members (1963)\n\n\n\nAdded: Kenya, Kuwait, Zanzibar\n\n\n\n\n\n115 Members (1964)*\n\n\n\nAdded: Malawi, Malta, Zambia\n\t\t\t\t\t\t\t\t*On 26 April 1964, Zanzibar merged with Tanganyika to become the United Republic of Tanzania.\n\n\n\n\n\n117 Members (1965)*\n\n\n\nAdded: The Gambia, Maldive Islands, Singapore\n\t\t\t\t\t\t\t\t*On 20 January 1965, Indonesia temporarily withdrew from the United Nations.\n\n\n\n\n\n122 Members (1966)*\n\n\n\nAdded: Barbados, Botswana, Guyana, Lesotho\n\t\t\t\t\t\t\t\t* On 28 September 1966, Indonesia rejoined the United Nations.\n\n\n\n\n\n123 Members (1967)\n\n\n\nAdded: Yemen (People's Democratic Republic of Yemen)\n\n\n\n \n\n126 Members (1968)\n\n\n\nAdded: Equatorial Guinea, Mauritius, Swaziland\n\n\n\n\n\n127 Members (1970)\n\n\n\nAdded: Fiji\n\n\n\n\n\n132 Members (1971)\n\n\n\nAdded: Bahrain, Bhutan, Oman, Qatar, United Arab Emirates\n\n\n\n\n\n135 Members (1973)\n\n\n\nAdded: Bahamas, Federal Republic of Germany, German Democratic Republic\n\n\n\n\n\n138 Members (1974)\n\n\n\nAdded: Bangladesh, Grenada, Guinea-Bissau\n\n\n\n\n\n144 Members (1975)\n\n\n\nAdded: Cape Verde, Comoros, Mozambique, Papua New Guinea, Sao Tome and Principe, Suriname\n\n\n\n\n\n147 Members (1976)\n\n\n\nAdded: Angola, Samoa, Seychelles\n\n\n\n\n\n149 Members (1977)\n\n\n\nAdded: Djibouti, Viet Nam\n\n\n\n\n\n151 Members (1978)\n\n\n\nAdded: Dominica, Solomon Islands\n\n\n\n \n\n152 Members (1979)\n\n\n\nAdded: Saint Lucia\n\n\n\n\n\n154 Members (1980)\n\n\n\nAdded: Saint Vincent and the Grenadines, Zimbabwe\n\n\n\n\n\n157 Members (1981) \n\n\n\nAdded: Antigua and Barbuda, Belize, Vanuatu\n\n\n\n\n\n158 Members (1983)\n\n\n\nAdded: Saint Christopher and Nevis\n\n\n\n \n\n159 Members (1984)\n\n\n\nAdded: Brunei Darussalam\n\n\n\n\n\n159 Members (1990)*\n\n\n\nAdded: Liechtenstein, Namibia\n\t\t\t\t\t\t\t\t*On 22 May 1990, the People's Democratic Republic of Yemen (member since 1967) was united with the Yemen Arab Republic (member since 1947), forming the Republic of Yemen. \n\t\t\t\t\t\t\t\tOn 3 October 1990, the German Democratic Republic acceded to the Federal Republic of Germany (both members since 1973), resulting in the reunification of Germany.\n\n\n\n\n\n166 Members (1991)\n\n\n\nAdded: Democratic People's Republic of Korea, Estonia, Latvia, Lithuania, Marshall Islands, Federated States of Micronesia, Republic of Korea\n\n\n\n\n\n179 Members (1992)\n\n\n\nAdded: Armenia, Azerbaijan, Bosnia and Herzegovina, Croatia, Georgia, Kazakhstan, Kyrgyzstan, Republic of Moldova, San Marino, Slovenia, Tajikistan, Turkmenistan, Uzbekistan\n\n\n\n\n\n184 Members (1993)*\n\n\n\nAdded: Andorra, Czech Republic, Eritrea, Monaco, Slovakia, The former Yugoslav Republic of Macedonia\n\t\t\t\t\t\t\t\t*Czechoslovakia was an original Member of the United Nations from 24 October 1945. The Czech and Slovak Federal Republic ceased to exist on 31 December 1992. On 19 January 1993, the Czech Republic and the Slovak Republic were both admitted separately to United Nations membership.\n\n\n\n\n\n185 Members (1994)\n\n\n\nAdded: Palau\n\n\n\n \n\n188 Members (1999)\n\n\n\nAdded: Kiribati, Nauru, Tonga\n\n\n\n\n\n189 Members (2000)*\n\n\n\nAdded: Federal Republic of Yugoslavia, Tuvalu\n\t\t\t\t\t\t\t\t*The Federal Republic of Yugoslavia was part of the Socialist Federal Republic of Yugoslavia, which was an original member of the United Nations and was removed from the official roster of UN members in 2000, following its dissolution.\n\n\n\n\n\n191 Members (2002)\n\n\n\nAdded: Switzerland, Timor-Leste\n\n\n\n\n\n192 Members (2006)\n\n\n\nAdded: Montenegro\n\n\n\n\n\n193 Members (2011)\n\n\n\nAdded: South Sudan\n\n1945-1950          1950s          1960s          1970s          1980s          1990s          2000-Present\n\n1945-1950          1950s          1960s          1970s          1980s          1990s          2000-Present\n\n1945-1950          1950s          1960s          1970s          1980s          1990s          2000-Present\n\nOriginal 51 Members (1945)\n\n\n\nArgentina, Australia, Belgium, Bolivia, Brazil, Byelorussian Soviet Socialist Republic, Canada, Chile, China, Colombia, Costa Rica, Cuba, Czechoslovakia, Denmark, Dominican Republic, Ecuador, Egypt, El Salvador, Ethiopia, France, Greece, Guatemala, Haiti, Honduras, India, Iran, Iraq, Lebanon, Liberia, Luxembourg, Mexico, Netherlands, New Zealand, Nicaragua, Norway, Panama, Paraguay, Peru, Philippine Republic, Poland, Saudi Arabia, Syria, Turkey, Ukrainian Soviet Socialist Republic, Union of South Africa, Union of Soviet Socialist Republics, United Kingdom, United States, Uruguay, Venezuela, Yugoslavia\n\n\n\n\n\n55 Members (1946)\n\n\n\nAdded: Afghanistan, Iceland, Siam, Sweden\n\n\n\n\n\n57 Members (1947)\n\n\n\nAdded: Pakistan, Yemen (the Yemen Arab Republic)\n\n\n\n\n\n58 Members (1948)\n\n\n\nAdded: Burma\n\n\n\n \n\n59 Members (1949)\n\n\n\nAdded: Israel\n\n\n\n\n\n60 Members (1950)\n\n\n\nAdded: Indonesia\n\n\n\n\n\n76 Members (1955)\n\n\n\nAdded: Albania, Austria, Bulgaria, Cambodia, Ceylon, Finland, Hungary, Ireland, Italy, Jordan, Laos, Libya, Nepal, Portugal, Romania, Spain\n\n\n\n\n\n80 Members (1956)\n\n\n\nAdded: Japan, Morocco, Sudan, Tunisia\n\n\n\n\n\n82 Members (1957)\n\n\n\nAdded: Ghana, Federation of Malaya\n\n\n\n \n\n82 Members (1958)*\n\n\n\nAdded: Guinea\n\t\t\t\t\t\t\t\t* On 22 February 1958, Syria merged with Egypt (both original members of the United Nations) to become the United Arab Republic. \n\n\n\n\n\n99 Members (1960)\n\n\n\nAdded: Cameroun, Central African Republic, Chad, Congo (Brazzaville), Congo (Leopoldville), Cyprus, Dahomey, Gabon, Ivory Coast, Malagasy Republic, Mali, Niger, Nigeria, Senegal, Somalia, Togo, Upper Volta\n\n\n\n\n\n104 Members (1961)*\n\n\n\nAdded: Mauritania, Mongolia, Sierra Leone, Tanganyika\n\t\t\t\t\t\t\t\t*On 13 October 1961, Syria, having resumed its status as an independent State from the United Arab Republic, resumed its separate membership in the United Nations.\n\n\n\n\n\n110 Members (1962)\n\n\n\nAdded: Algeria, Burundi, Jamaica, Rwanda, Trinidad and Tobago, Uganda\n\n\n\n\n\n113 Members (1963)\n\n\n\nAdded: Kenya, Kuwait, Zanzibar\n\n\n\n\n\n115 Members (1964)*\n\n\n\nAdded: Malawi, Malta, Zambia\n\t\t\t\t\t\t\t\t*On 26 April 1964, Zanzibar merged with Tanganyika to become the United Republic of Tanzania.\n\n\n\n\n\n117 Members (1965)*\n\n\n\nAdded: The Gambia, Maldive Islands, Singapore\n\t\t\t\t\t\t\t\t*On 20 January 1965, Indonesia temporarily withdrew from the United Nations.\n\n\n\n\n\n122 Members (1966)*\n\n\n\nAdded: Barbados, Botswana, Guyana, Lesotho\n\t\t\t\t\t\t\t\t* On 28 September 1966, Indonesia rejoined the United Nations.\n\n\n\n\n\n123 Members (1967)\n\n\n\nAdded: Yemen (People's Democratic Republic of Yemen)\n\n\n\n \n\n126 Members (1968)\n\n\n\nAdded: Equatorial Guinea, Mauritius, Swaziland\n\n\n\n\n\n127 Members (1970)\n\n\n\nAdded: Fiji\n\n\n\n\n\n132 Members (1971)\n\n\n\nAdded: Bahrain, Bhutan, Oman, Qatar, United Arab Emirates\n\n\n\n\n\n135 Members (1973)\n\n\n\nAdded: Bahamas, Federal Republic of Germany, German Democratic Republic\n\n\n\n\n\n138 Members (1974)\n\n\n\nAdded: Bangladesh, Grenada, Guinea-Bissau\n\n\n\n\n\n144 Members (1975)\n\n\n\nAdded: Cape Verde, Comoros, Mozambique, Papua New Guinea, Sao Tome and Principe, Suriname\n\n\n\n\n\n147 Members (1976)\n\n\n\nAdded: Angola, Samoa, Seychelles\n\n\n\n\n\n149 Members (1977)\n\n\n\nAdded: Djibouti, Viet Nam\n\n\n\n\n\n151 Members (1978)\n\n\n\nAdded: Dominica, Solomon Islands\n\n\n\n \n\n152 Members (1979)\n\n\n\nAdded: Saint Lucia\n\n\n\n\n\n154 Members (1980)\n\n\n\nAdded: Saint Vincent and the Grenadines, Zimbabwe\n\n\n\n\n\n157 Members (1981) \n\n\n\nAdded: Antigua and Barbuda, Belize, Vanuatu\n\n\n\n\n\n158 Members (1983)\n\n\n\nAdded: Saint Christopher and Nevis\n\n\n\n \n\n159 Members (1984)\n\n\n\nAdded: Brunei Darussalam\n\n\n\n\n\n159 Members (1990)*\n\n\n\nAdded: Liechtenstein, Namibia\n\t\t\t\t\t\t\t\t*On 22 May 1990, the People's Democratic Republic of Yemen (member since 1967) was united with the Yemen Arab Republic (member since 1947), forming the Republic of Yemen. \n\t\t\t\t\t\t\t\tOn 3 October 1990, the German Democratic Republic acceded to the Federal Republic of Germany (both members since 1973), resulting in the reunification of Germany.\n\n\n\n\n\n166 Members (1991)\n\n\n\nAdded: Democratic People's Republic of Korea, Estonia, Latvia, Lithuania, Marshall Islands, Federated States of Micronesia, Republic of Korea\n\n\n\n\n\n179 Members (1992)\n\n\n\nAdded: Armenia, Azerbaijan, Bosnia and Herzegovina, Croatia, Georgia, Kazakhstan, Kyrgyzstan, Republic of Moldova, San Marino, Slovenia, Tajikistan, Turkmenistan, Uzbekistan\n\n\n\n\n\n184 Members (1993)*\n\n\n\nAdded: Andorra, Czech Republic, Eritrea, Monaco, Slovakia, The former Yugoslav Republic of Macedonia\n\t\t\t\t\t\t\t\t*Czechoslovakia was an original Member of the United Nations from 24 October 1945. The Czech and Slovak Federal Republic ceased to exist on 31 December 1992. On 19 January 1993, the Czech Republic and the Slovak Republic were both admitted separately to United Nations membership.\n\n\n\n\n\n185 Members (1994)\n\n\n\nAdded: Palau\n\n\n\n \n\n188 Members (1999)\n\n\n\nAdded: Kiribati, Nauru, Tonga\n\n\n\n\n\n189 Members (2000)*\n\n\n\nAdded: Federal Republic of Yugoslavia, Tuvalu\n\t\t\t\t\t\t\t\t*The Federal Republic of Yugoslavia was part of the Socialist Federal Republic of Yugoslavia, which was an original member of the United Nations and was removed from the official roster of UN members in 2000, following its dissolution.\n\n\n\n\n\n191 Members (2002)\n\n\n\nAdded: Switzerland, Timor-Leste\n\n\n\n\n\n192 Members (2006)\n\n\n\nAdded: Montenegro\n\n\n\n\n\n193 Members (2011)\n\n\n\nAdded: South Sudan\n\nOriginal 51 Members (1945)\n\n\n\nArgentina, Australia, Belgium, Bolivia, Brazil, Byelorussian Soviet Socialist Republic, Canada, Chile, China, Colombia, Costa Rica, Cuba, Czechoslovakia, Denmark, Dominican Republic, Ecuador, Egypt, El Salvador, Ethiopia, France, Greece, Guatemala, Haiti, Honduras, India, Iran, Iraq, Lebanon, Liberia, Luxembourg, Mexico, Netherlands, New Zealand, Nicaragua, Norway, Panama, Paraguay, Peru, Philippine Republic, Poland, Saudi Arabia, Syria, Turkey, Ukrainian Soviet Socialist Republic, Union of South Africa, Union of Soviet Socialist Republics, United Kingdom, United States, Uruguay, Venezuela, Yugoslavia\n\nOriginal 51 Members (1945)\n\nArgentina, Australia, Belgium, Bolivia, Brazil, Byelorussian Soviet Socialist Republic, Canada, Chile, China, Colombia, Costa Rica, Cuba, Czechoslovakia, Denmark, Dominican Republic, Ecuador, Egypt, El Salvador, Ethiopia, France, Greece, Guatemala, Haiti, Honduras, India, Iran, Iraq, Lebanon, Liberia, Luxembourg, Mexico, Netherlands, New Zealand, Nicaragua, Norway, Panama, Paraguay, Peru, Philippine Republic, Poland, Saudi Arabia, Syria, Turkey, Ukrainian Soviet Socialist Republic, Union of South Africa, Union of Soviet Socialist Republics, United Kingdom, United States, Uruguay, Venezuela, Yugoslavia\n\nArgentina, Australia, Belgium, Bolivia, Brazil, Byelorussian Soviet Socialist Republic, Canada, Chile, China, Colombia, Costa Rica, Cuba, Czechoslovakia, Denmark, Dominican Republic, Ecuador, Egypt, El Salvador, Ethiopia, France, Greece, Guatemala, Haiti, Honduras, India, Iran, Iraq, Lebanon, Liberia, Luxembourg, Mexico, Netherlands, New Zealand, Nicaragua, Norway, Panama, Paraguay, Peru, Philippine Republic, Poland, Saudi Arabia, Syria, Turkey, Ukrainian Soviet Socialist Republic, Union of South Africa, Union of Soviet Socialist Republics, United Kingdom, United States, Uruguay, Venezuela, Yugoslavia\n\nArgentina, Australia, Belgium, Bolivia, Brazil, Byelorussian Soviet Socialist Republic, Canada, Chile, China, Colombia, Costa Rica, Cuba, Czechoslovakia, Denmark, Dominican Republic, Ecuador, Egypt, El Salvador, Ethiopia, France, Greece, Guatemala, Haiti, Honduras, India, Iran, Iraq, Lebanon, Liberia, Luxembourg, Mexico, Netherlands, New Zealand, Nicaragua, Norway, Panama, Paraguay, Peru, Philippine Republic, Poland, Saudi Arabia, Syria, Turkey, Ukrainian Soviet Socialist Republic, Union of South Africa, Union of Soviet Socialist Republics, United Kingdom, United States, Uruguay, Venezuela, Yugoslavia\n\n55 Members (1946)\n\n\n\nAdded: Afghanistan, Iceland, Siam, Sweden\n\n55 Members (1946)\n\nAdded: Afghanistan, Iceland, Siam, Sweden\n\nAdded: Afghanistan, Iceland, Siam, Sweden\n\nAdded: Afghanistan, Iceland, Siam, Sweden\n\n57 Members (1947)\n\n\n\nAdded: Pakistan, Yemen (the Yemen Arab Republic)\n\n57 Members (1947)\n\nAdded: Pakistan, Yemen (the Yemen Arab Republic)\n\nAdded: Pakistan, Yemen (the Yemen Arab Republic)\n\nAdded: Pakistan, Yemen (the Yemen Arab Republic)\n\n58 Members (1948)\n\n\n\nAdded: Burma\n\n58 Members (1948)\n\nAdded: Burma\n\nAdded: Burma\n\nAdded: Burma\n\n59 Members (1949)\n\n\n\nAdded: Israel\n\n59 Members (1949)\n\nAdded: Israel\n\nAdded: Israel\n\nAdded: Israel\n\n60 Members (1950)\n\n\n\nAdded: Indonesia\n\n60 Members (1950)\n\nAdded: Indonesia\n\nAdded: Indonesia\n\nAdded: Indonesia\n\n76 Members (1955)\n\n\n\nAdded: Albania, Austria, Bulgaria, Cambodia, Ceylon, Finland, Hungary, Ireland, Italy, Jordan, Laos, Libya, Nepal, Portugal, Romania, Spain\n\n76 Members (1955)\n\nAdded: Albania, Austria, Bulgaria, Cambodia, Ceylon, Finland, Hungary, Ireland, Italy, Jordan, Laos, Libya, Nepal, Portugal, Romania, Spain\n\nAdded: Albania, Austria, Bulgaria, Cambodia, Ceylon, Finland, Hungary, Ireland, Italy, Jordan, Laos, Libya, Nepal, Portugal, Romania, Spain\n\nAdded: Albania, Austria, Bulgaria, Cambodia, Ceylon, Finland, Hungary, Ireland, Italy, Jordan, Laos, Libya, Nepal, Portugal, Romania, Spain\n\n80 Members (1956)\n\n\n\nAdded: Japan, Morocco, Sudan, Tunisia\n\n80 Members (1956)\n\nAdded: Japan, Morocco, Sudan, Tunisia\n\nAdded: Japan, Morocco, Sudan, Tunisia\n\nAdded: Japan, Morocco, Sudan, Tunisia\n\n82 Members (1957)\n\n\n\nAdded: Ghana, Federation of Malaya\n\n82 Members (1957)\n\nAdded: Ghana, Federation of Malaya\n\nAdded: Ghana, Federation of Malaya\n\nAdded: Ghana, Federation of Malaya\n\n82 Members (1958)*\n\n\n\nAdded: Guinea\n\t\t\t\t\t\t\t\t* On 22 February 1958, Syria merged with Egypt (both original members of the United Nations) to become the United Arab Republic.\n\n82 Members (1958)*\n\nAdded: Guinea\n\t\t\t\t\t\t\t\t* On 22 February 1958, Syria merged with Egypt (both original members of the United Nations) to become the United Arab Republic.\n\nAdded: Guinea\n\t\t\t\t\t\t\t\t* On 22 February 1958, Syria merged with Egypt (both original members of the United Nations) to become the United Arab Republic.\n\nAdded: Guinea\n\t\t\t\t\t\t\t\t* On 22 February 1958, Syria merged with Egypt (both original members of the United Nations) to become the United Arab Republic.\n\n99 Members (1960)\n\n\n\nAdded: Cameroun, Central African Republic, Chad, Congo (Brazzaville), Congo (Leopoldville), Cyprus, Dahomey, Gabon, Ivory Coast, Malagasy Republic, Mali, Niger, Nigeria, Senegal, Somalia, Togo, Upper Volta\n\n99 Members (1960)\n\nAdded: Cameroun, Central African Republic, Chad, Congo (Brazzaville), Congo (Leopoldville), Cyprus, Dahomey, Gabon, Ivory Coast, Malagasy Republic, Mali, Niger, Nigeria, Senegal, Somalia, Togo, Upper Volta\n\nAdded: Cameroun, Central African Republic, Chad, Congo (Brazzaville), Congo (Leopoldville), Cyprus, Dahomey, Gabon, Ivory Coast, Malagasy Republic, Mali, Niger, Nigeria, Senegal, Somalia, Togo, Upper Volta\n\nAdded: Cameroun, Central African Republic, Chad, Congo (Brazzaville), Congo (Leopoldville), Cyprus, Dahomey, Gabon, Ivory Coast, Malagasy Republic, Mali, Niger, Nigeria, Senegal, Somalia, Togo, Upper Volta\n\n104 Members (1961)*\n\n\n\nAdded: Mauritania, Mongolia, Sierra Leone, Tanganyika\n\t\t\t\t\t\t\t\t*On 13 October 1961, Syria, having resumed its status as an independent State from the United Arab Republic, resumed its separate membership in the United Nations.\n\n104 Members (1961)*\n\nAdded: Mauritania, Mongolia, Sierra Leone, Tanganyika\n\t\t\t\t\t\t\t\t*On 13 October 1961, Syria, having resumed its status as an independent State from the United Arab Republic, resumed its separate membership in the United Nations.\n\nAdded: Mauritania, Mongolia, Sierra Leone, Tanganyika\n\t\t\t\t\t\t\t\t*On 13 October 1961, Syria, having resumed its status as an independent State from the United Arab Republic, resumed its separate membership in the United Nations.\n\nAdded: Mauritania, Mongolia, Sierra Leone, Tanganyika\n\t\t\t\t\t\t\t\t*On 13 October 1961, Syria, having resumed its status as an independent State from the United Arab Republic, resumed its separate membership in the United Nations.\n\n110 Members (1962)\n\n\n\nAdded: Algeria, Burundi, Jamaica, Rwanda, Trinidad and Tobago, Uganda\n\n110 Members (1962)\n\nAdded: Algeria, Burundi, Jamaica, Rwanda, Trinidad and Tobago, Uganda\n\nAdded: Algeria, Burundi, Jamaica, Rwanda, Trinidad and Tobago, Uganda\n\nAdded: Algeria, Burundi, Jamaica, Rwanda, Trinidad and Tobago, Uganda\n\n113 Members (1963)\n\n\n\nAdded: Kenya, Kuwait, Zanzibar\n\n113 Members (1963)\n\nAdded: Kenya, Kuwait, Zanzibar\n\nAdded: Kenya, Kuwait, Zanzibar\n\nAdded: Kenya, Kuwait, Zanzibar\n\n115 Members (1964)*\n\n\n\nAdded: Malawi, Malta, Zambia\n\t\t\t\t\t\t\t\t*On 26 April 1964, Zanzibar merged with Tanganyika to become the United Republic of Tanzania.\n\n115 Members (1964)*\n\nAdded: Malawi, Malta, Zambia\n\t\t\t\t\t\t\t\t*On 26 April 1964, Zanzibar merged with Tanganyika to become the United Republic of Tanzania.\n\nAdded: Malawi, Malta, Zambia\n\t\t\t\t\t\t\t\t*On 26 April 1964, Zanzibar merged with Tanganyika to become the United Republic of Tanzania.\n\nAdded: Malawi, Malta, Zambia\n\t\t\t\t\t\t\t\t*On 26 April 1964, Zanzibar merged with Tanganyika to become the United Republic of Tanzania.\n\n117 Members (1965)*\n\n\n\nAdded: The Gambia, Maldive Islands, Singapore\n\t\t\t\t\t\t\t\t*On 20 January 1965, Indonesia temporarily withdrew from the United Nations.\n\n117 Members (1965)*\n\nAdded: The Gambia, Maldive Islands, Singapore\n\t\t\t\t\t\t\t\t*On 20 January 1965, Indonesia temporarily withdrew from the United Nations.\n\nAdded: The Gambia, Maldive Islands, Singapore\n\t\t\t\t\t\t\t\t*On 20 January 1965, Indonesia temporarily withdrew from the United Nations.\n\nAdded: The Gambia, Maldive Islands, Singapore\n\t\t\t\t\t\t\t\t*On 20 January 1965, Indonesia temporarily withdrew from the United Nations.\n\n122 Members (1966)*\n\n\n\nAdded: Barbados, Botswana, Guyana, Lesotho\n\t\t\t\t\t\t\t\t* On 28 September 1966, Indonesia rejoined the United Nations.\n\n122 Members (1966)*\n\nAdded: Barbados, Botswana, Guyana, Lesotho\n\t\t\t\t\t\t\t\t* On 28 September 1966, Indonesia rejoined the United Nations.\n\nAdded: Barbados, Botswana, Guyana, Lesotho\n\t\t\t\t\t\t\t\t* On 28 September 1966, Indonesia rejoined the United Nations.\n\nAdded: Barbados, Botswana, Guyana, Lesotho\n\t\t\t\t\t\t\t\t* On 28 September 1966, Indonesia rejoined the United Nations.\n\n123 Members (1967)\n\n\n\nAdded: Yemen (People's Democratic Republic of Yemen)\n\n123 Members (1967)\n\nAdded: Yemen (People's Democratic Republic of Yemen)\n\nAdded: Yemen (People's Democratic Republic of Yemen)\n\nAdded: Yemen (People's Democratic Republic of Yemen)\n\n126 Members (1968)\n\n\n\nAdded: Equatorial Guinea, Mauritius, Swaziland\n\n126 Members (1968)\n\nAdded: Equatorial Guinea, Mauritius, Swaziland\n\nAdded: Equatorial Guinea, Mauritius, Swaziland\n\nAdded: Equatorial Guinea, Mauritius, Swaziland\n\n127 Members (1970)\n\n\n\nAdded: Fiji\n\n127 Members (1970)\n\nAdded: Fiji\n\nAdded: Fiji\n\nAdded: Fiji\n\n132 Members (1971)\n\n\n\nAdded: Bahrain, Bhutan, Oman, Qatar, United Arab Emirates\n\n132 Members (1971)\n\nAdded: Bahrain, Bhutan, Oman, Qatar, United Arab Emirates\n\nAdded: Bahrain, Bhutan, Oman, Qatar, United Arab Emirates\n\nAdded: Bahrain, Bhutan, Oman, Qatar, United Arab Emirates\n\n135 Members (1973)\n\n\n\nAdded: Bahamas, Federal Republic of Germany, German Democratic Republic\n\n135 Members (1973)\n\nAdded: Bahamas, Federal Republic of Germany, German Democratic Republic\n\nAdded: Bahamas, Federal Republic of Germany, German Democratic Republic\n\nAdded: Bahamas, Federal Republic of Germany, German Democratic Republic\n\n138 Members (1974)\n\n\n\nAdded: Bangladesh, Grenada, Guinea-Bissau\n\n138 Members (1974)\n\nAdded: Bangladesh, Grenada, Guinea-Bissau\n\nAdded: Bangladesh, Grenada, Guinea-Bissau\n\nAdded: Bangladesh, Grenada, Guinea-Bissau\n\n144 Members (1975)\n\n\n\nAdded: Cape Verde, Comoros, Mozambique, Papua New Guinea, Sao Tome and Principe, Suriname\n\n144 Members (1975)\n\nAdded: Cape Verde, Comoros, Mozambique, Papua New Guinea, Sao Tome and Principe, Suriname\n\nAdded: Cape Verde, Comoros, Mozambique, Papua New Guinea, Sao Tome and Principe, Suriname\n\nAdded: Cape Verde, Comoros, Mozambique, Papua New Guinea, Sao Tome and Principe, Suriname\n\n147 Members (1976)\n\n\n\nAdded: Angola, Samoa, Seychelles\n\n147 Members (1976)\n\nAdded: Angola, Samoa, Seychelles\n\nAdded: Angola, Samoa, Seychelles\n\nAdded: Angola, Samoa, Seychelles\n\n149 Members (1977)\n\n\n\nAdded: Djibouti, Viet Nam\n\n149 Members (1977)\n\nAdded: Djibouti, Viet Nam\n\nAdded: Djibouti, Viet Nam\n\nAdded: Djibouti, Viet Nam\n\n151 Members (1978)\n\n\n\nAdded: Dominica, Solomon Islands\n\n151 Members (1978)\n\nAdded: Dominica, Solomon Islands\n\nAdded: Dominica, Solomon Islands\n\nAdded: Dominica, Solomon Islands\n\n152 Members (1979)\n\n\n\nAdded: Saint Lucia\n\n152 Members (1979)\n\nAdded: Saint Lucia\n\nAdded: Saint Lucia\n\nAdded: Saint Lucia\n\n154 Members (1980)\n\n\n\nAdded: Saint Vincent and the Grenadines, Zimbabwe\n\n154 Members (1980)\n\nAdded: Saint Vincent and the Grenadines, Zimbabwe\n\nAdded: Saint Vincent and the Grenadines, Zimbabwe\n\nAdded: Saint Vincent and the Grenadines, Zimbabwe\n\n157 Members (1981) \n\n\n\nAdded: Antigua and Barbuda, Belize, Vanuatu\n\n157 Members (1981)\n\nAdded: Antigua and Barbuda, Belize, Vanuatu\n\nAdded: Antigua and Barbuda, Belize, Vanuatu\n\nAdded: Antigua and Barbuda, Belize, Vanuatu\n\n158 Members (1983)\n\n\n\nAdded: Saint Christopher and Nevis\n\n158 Members (1983)\n\nAdded: Saint Christopher and Nevis\n\nAdded: Saint Christopher and Nevis\n\nAdded: Saint Christopher and Nevis\n\n159 Members (1984)\n\n\n\nAdded: Brunei Darussalam\n\n159 Members (1984)\n\nAdded: Brunei Darussalam\n\nAdded: Brunei Darussalam\n\nAdded: Brunei Darussalam\n\n159 Members (1990)*\n\n\n\nAdded: Liechtenstein, Namibia\n\t\t\t\t\t\t\t\t*On 22 May 1990, the People's Democratic Republic of Yemen (member since 1967) was united with the Yemen Arab Republic (member since 1947), forming the Republic of Yemen. \n\t\t\t\t\t\t\t\tOn 3 October 1990, the German Democratic Republic acceded to the Federal Republic of Germany (both members since 1973), resulting in the reunification of Germany.\n\n159 Members (1990)*\n\nAdded: Liechtenstein, Namibia\n\t\t\t\t\t\t\t\t*On 22 May 1990, the People's Democratic Republic of Yemen (member since 1967) was united with the Yemen Arab Republic (member since 1947), forming the Republic of Yemen. \n\t\t\t\t\t\t\t\tOn 3 October 1990, the German Democratic Republic acceded to the Federal Republic of Germany (both members since 1973), resulting in the reunification of Germany.\n\nAdded: Liechtenstein, Namibia\n\t\t\t\t\t\t\t\t*On 22 May 1990, the People's Democratic Republic of Yemen (member since 1967) was united with the Yemen Arab Republic (member since 1947), forming the Republic of Yemen. \n\t\t\t\t\t\t\t\tOn 3 October 1990, the German Democratic Republic acceded to the Federal Republic of Germany (both members since 1973), resulting in the reunification of Germany.\n\nAdded: Liechtenstein, Namibia\n\t\t\t\t\t\t\t\t*On 22 May 1990, the People's Democratic Republic of Yemen (member since 1967) was united with the Yemen Arab Republic (member since 1947), forming the Republic of Yemen. \n\t\t\t\t\t\t\t\tOn 3 October 1990, the German Democratic Republic acceded to the Federal Republic of Germany (both members since 1973), resulting in the reunification of Germany.\n\n166 Members (1991)\n\n\n\nAdded: Democratic People's Republic of Korea, Estonia, Latvia, Lithuania, Marshall Islands, Federated States of Micronesia, Republic of Korea\n\n166 Members (1991)\n\nAdded: Democratic People's Republic of Korea, Estonia, Latvia, Lithuania, Marshall Islands, Federated States of Micronesia, Republic of Korea\n\nAdded: Democratic People's Republic of Korea, Estonia, Latvia, Lithuania, Marshall Islands, Federated States of Micronesia, Republic of Korea\n\nAdded: Democratic People's Republic of Korea, Estonia, Latvia, Lithuania, Marshall Islands, Federated States of Micronesia, Republic of Korea\n\n179 Members (1992)\n\n\n\nAdded: Armenia, Azerbaijan, Bosnia and Herzegovina, Croatia, Georgia, Kazakhstan, Kyrgyzstan, Republic of Moldova, San Marino, Slovenia, Tajikistan, Turkmenistan, Uzbekistan\n\n179 Members (1992)\n\nAdded: Armenia, Azerbaijan, Bosnia and Herzegovina, Croatia, Georgia, Kazakhstan, Kyrgyzstan, Republic of Moldova, San Marino, Slovenia, Tajikistan, Turkmenistan, Uzbekistan\n\nAdded: Armenia, Azerbaijan, Bosnia and Herzegovina, Croatia, Georgia, Kazakhstan, Kyrgyzstan, Republic of Moldova, San Marino, Slovenia, Tajikistan, Turkmenistan, Uzbekistan\n\nAdded: Armenia, Azerbaijan, Bosnia and Herzegovina, Croatia, Georgia, Kazakhstan, Kyrgyzstan, Republic of Moldova, San Marino, Slovenia, Tajikistan, Turkmenistan, Uzbekistan\n\n184 Members (1993)*\n\n\n\nAdded: Andorra, Czech Republic, Eritrea, Monaco, Slovakia, The former Yugoslav Republic of Macedonia\n\t\t\t\t\t\t\t\t*Czechoslovakia was an original Member of the United Nations from 24 October 1945. The Czech and Slovak Federal Republic ceased to exist on 31 December 1992. On 19 January 1993, the Czech Republic and the Slovak Republic were both admitted separately to United Nations membership.\n\n184 Members (1993)*\n\nAdded: Andorra, Czech Republic, Eritrea, Monaco, Slovakia, The former Yugoslav Republic of Macedonia\n\t\t\t\t\t\t\t\t*Czechoslovakia was an original Member of the United Nations from 24 October 1945. The Czech and Slovak Federal Republic ceased to exist on 31 December 1992. On 19 January 1993, the Czech Republic and the Slovak Republic were both admitted separately to United Nations membership.\n\nAdded: Andorra, Czech Republic, Eritrea, Monaco, Slovakia, The former Yugoslav Republic of Macedonia\n\t\t\t\t\t\t\t\t*Czechoslovakia was an original Member of the United Nations from 24 October 1945. The Czech and Slovak Federal Republic ceased to exist on 31 December 1992. On 19 January 1993, the Czech Republic and the Slovak Republic were both admitted separately to United Nations membership.\n\nAdded: Andorra, Czech Republic, Eritrea, Monaco, Slovakia, The former Yugoslav Republic of Macedonia\n\t\t\t\t\t\t\t\t*Czechoslovakia was an original Member of the United Nations from 24 October 1945. The Czech and Slovak Federal Republic ceased to exist on 31 December 1992. On 19 January 1993, the Czech Republic and the Slovak Republic were both admitted separately to United Nations membership.\n\n185 Members (1994)\n\n\n\nAdded: Palau\n\n185 Members (1994)\n\nAdded: Palau\n\nAdded: Palau\n\nAdded: Palau\n\n188 Members (1999)\n\n\n\nAdded: Kiribati, Nauru, Tonga\n\n188 Members (1999)\n\nAdded: Kiribati, Nauru, Tonga\n\nAdded: Kiribati, Nauru, Tonga\n\nAdded: Kiribati, Nauru, Tonga\n\n189 Members (2000)*\n\n\n\nAdded: Federal Republic of Yugoslavia, Tuvalu\n\t\t\t\t\t\t\t\t*The Federal Republic of Yugoslavia was part of the Socialist Federal Republic of Yugoslavia, which was an original member of the United Nations and was removed from the official roster of UN members in 2000, following its dissolution.\n\n189 Members (2000)*\n\nAdded: Federal Republic of Yugoslavia, Tuvalu\n\t\t\t\t\t\t\t\t*The Federal Republic of Yugoslavia was part of the Socialist Federal Republic of Yugoslavia, which was an original member of the United Nations and was removed from the official roster of UN members in 2000, following its dissolution.\n\nAdded: Federal Republic of Yugoslavia, Tuvalu\n\t\t\t\t\t\t\t\t*The Federal Republic of Yugoslavia was part of the Socialist Federal Republic of Yugoslavia, which was an original member of the United Nations and was removed from the official roster of UN members in 2000, following its dissolution.\n\nAdded: Federal Republic of Yugoslavia, Tuvalu\n\t\t\t\t\t\t\t\t*The Federal Republic of Yugoslavia was part of the Socialist Federal Republic of Yugoslavia, which was an original member of the United Nations and was removed from the official roster of UN members in 2000, following its dissolution.\n\n191 Members (2002)\n\n\n\nAdded: Switzerland, Timor-Leste\n\n191 Members (2002)\n\nAdded: Switzerland, Timor-Leste\n\nAdded: Switzerland, Timor-Leste\n\nAdded: Switzerland, Timor-Leste\n\n192 Members (2006)\n\n\n\nAdded: Montenegro\n\n192 Members (2006)\n\nAdded: Montenegro\n\nAdded: Montenegro\n\nAdded: Montenegro\n\n193 Members (2011)\n\n\n\nAdded: South Sudan\n\n193 Members (2011)\n\nAdded: South Sudan\n\nAdded: South Sudan\n\nAdded: South Sudan\n\nMEMBER STATES\n\nMembership \n\nAbout UN Membership\nList of UN Member States\nUN Membership research guide\nGrowth in UN Membership\nMembership of Principal UN Organs\nContributions to UN regular budget\nHonour Roll: Contribution Received in Full\nArrears in the Payment of Contribution\n\n\nPermanent Missions\n\nNew York\nGeneva\nVienna\n\n\nPermanent Observers\n\nAbout Permanent Observers\nNon-Member States\nIntergovernmental and Other Organizations\nSpecialized Agencies \n\n\n\n \n\nQuick links for delegates\n\nDelegate (UN Intranet - iSeek for Member States)\nBlue Book\nDelegates' Handbook\nManual of Protocol\n\nMEMBER STATES\n\nMembership \n\nAbout UN Membership\nList of UN Member States\nUN Membership research guide\nGrowth in UN Membership\nMembership of Principal UN Organs\nContributions to UN regular budget\nHonour Roll: Contribution Received in Full\nArrears in the Payment of Contribution\n\n\nPermanent Missions\n\nNew York\nGeneva\nVienna\n\n\nPermanent Observers\n\nAbout Permanent Observers\nNon-Member States\nIntergovernmental and Other Organizations\nSpecialized Agencies \n\n\n\n \n\nQuick links for delegates\n\nDelegate (UN Intranet - iSeek for Member States)\nBlue Book\nDelegates' Handbook\nManual of Protocol\n\nMEMBER STATES\n\nMembership \n\nAbout UN Membership\nList of UN Member States\nUN Membership research guide\nGrowth in UN Membership\nMembership of Principal UN Organs\nContributions to UN regular budget\nHonour Roll: Contribution Received in Full\nArrears in the Payment of Contribution\n\n\nPermanent Missions\n\nNew York\nGeneva\nVienna\n\n\nPermanent Observers\n\nAbout Permanent Observers\nNon-Member States\nIntergovernmental and Other Organizations\nSpecialized Agencies \n\n\n\n \n\nQuick links for delegates\n\nDelegate (UN Intranet - iSeek for Member States)\nBlue Book\nDelegates' Handbook\nManual of Protocol\n\nMembership \n\nAbout UN Membership\nList of UN Member States\nUN Membership research guide\nGrowth in UN Membership\nMembership of Principal UN Organs\nContributions to UN regular budget\nHonour Roll: Contribution Received in Full\nArrears in the Payment of Contribution\n\n\nPermanent Missions\n\nNew York\nGeneva\nVienna\n\n\nPermanent Observers\n\nAbout Permanent Observers\nNon-Member States\nIntergovernmental and Other Organizations\nSpecialized Agencies \n\n\n\n \n\nQuick links for delegates\n\nDelegate (UN Intranet - iSeek for Member States)\nBlue Book\nDelegates' Handbook\nManual of Protocol\n\nQuick links for delegates\n\nDelegate (UN Intranet - iSeek for Member States)\nBlue Book\nDelegates' Handbook\nManual of Protocol\n\nMain Bodies   General Assembly   Security Council   Economic and Social Council   Trusteeship Council   International Court of Justice   Secretariat       Departments / Offices   New York   Geneva   Nairobi   Vienna   UN System Directory   UN System Chart   Global Leadership   UN Information Centres       Resources / Services   Emergency information   Reporting Wrongdoing   UN Journal   Documents   Guidelines for gender-inclusive language   Databases   Library   UN iLibrary   UN Chronicle   UN Yearbook   Bookshop   Publications for sale   Maps   Media Accreditation   NGO accreditation at ECOSOC   NGO accreditation at DGC   Visitors’ services   Exhibits   Procurement   Employment   Internships   Model UN   Academic Impact   UN Archives   UN Audiovisual Library   How to donate to the UN system   Information on COVID-19 (Coronavirus)   Africa Renewal   Ten ways the UN makes a difference   GA High-level week 2024       Key Documents   UN Charter   Universal Declaration of Human Rights   Convention on the Rights of the Child   Statute of the International Court of Justice   Annual Report of the Secretary-General on the Work of the Organization       News and Media   News   Press Releases   Briefings   Spokesperson   Photos   UNIfeed   UN Web TV   UN Video   Social Media   The Essential UN   Awake at Night podcast       Issues / Campaigns   Global Issues   Observances   Sustainable Development Goals   Our Common Agenda   The Summit of the Future   Climate Action   Peace and Security   Action for Peacekeeping (A4P)   Global Crisis Response Group   Call to Action for Human Rights   Disability Inclusion Strategy   Fight Racism   Hate Speech   LGBTIQ+ People   Safety of Journalists   Rule of Law   Action to Counter Terrorism   Victims of Terrorism   Children and Armed Conflict   Violence Against Children (SRSG)   Sexual Violence in Conflict   Refugees and Migrants   Action Agenda on Internal Displacement   Spotlight Initiative   Preventing Sexual Exploitation and Abuse   Prevention of Genocide and the Responsibility to Protect   The Rwanda Genocide   The Holocaust   The Question of Palestine   The Transatlantic Slave Trade   Decolonization   Messengers of Peace   Roadmap for Digital Cooperation   Digital Financing Task Force   Data Strategy   Information Integrity   Countering Disinformation   UN75: 2020 and Beyond   Women Rise for All   Stop the Red Sea Catastrophe   Black Sea Grain Initiative Joint Coordination Centre\n\nMain Bodies   General Assembly   Security Council   Economic and Social Council   Trusteeship Council   International Court of Justice   Secretariat       Departments / Offices   New York   Geneva   Nairobi   Vienna   UN System Directory   UN System Chart   Global Leadership   UN Information Centres       Resources / Services   Emergency information   Reporting Wrongdoing   UN Journal   Documents   Guidelines for gender-inclusive language   Databases   Library   UN iLibrary   UN Chronicle   UN Yearbook   Bookshop   Publications for sale   Maps   Media Accreditation   NGO accreditation at ECOSOC   NGO accreditation at DGC   Visitors’ services   Exhibits   Procurement   Employment   Internships   Model UN   Academic Impact   UN Archives   UN Audiovisual Library   How to donate to the UN system   Information on COVID-19 (Coronavirus)   Africa Renewal   Ten ways the UN makes a difference   GA High-level week 2024       Key Documents   UN Charter   Universal Declaration of Human Rights   Convention on the Rights of the Child   Statute of the International Court of Justice   Annual Report of the Secretary-General on the Work of the Organization       News and Media   News   Press Releases   Briefings   Spokesperson   Photos   UNIfeed   UN Web TV   UN Video   Social Media   The Essential UN   Awake at Night podcast       Issues / Campaigns   Global Issues   Observances   Sustainable Development Goals   Our Common Agenda   The Summit of the Future   Climate Action   Peace and Security   Action for Peacekeeping (A4P)   Global Crisis Response Group   Call to Action for Human Rights   Disability Inclusion Strategy   Fight Racism   Hate Speech   LGBTIQ+ People   Safety of Journalists   Rule of Law   Action to Counter Terrorism   Victims of Terrorism   Children and Armed Conflict   Violence Against Children (SRSG)   Sexual Violence in Conflict   Refugees and Migrants   Action Agenda on Internal Displacement   Spotlight Initiative   Preventing Sexual Exploitation and Abuse   Prevention of Genocide and the Responsibility to Protect   The Rwanda Genocide   The Holocaust   The Question of Palestine   The Transatlantic Slave Trade   Decolonization   Messengers of Peace   Roadmap for Digital Cooperation   Digital Financing Task Force   Data Strategy   Information Integrity   Countering Disinformation   UN75: 2020 and Beyond   Women Rise for All   Stop the Red Sea Catastrophe   Black Sea Grain Initiative Joint Coordination Centre\n\nMain Bodies   General Assembly   Security Council   Economic and Social Council   Trusteeship Council   International Court of Justice   Secretariat       Departments / Offices   New York   Geneva   Nairobi   Vienna   UN System Directory   UN System Chart   Global Leadership   UN Information Centres       Resources / Services   Emergency information   Reporting Wrongdoing   UN Journal   Documents   Guidelines for gender-inclusive language   Databases   Library   UN iLibrary   UN Chronicle   UN Yearbook   Bookshop   Publications for sale   Maps   Media Accreditation   NGO accreditation at ECOSOC   NGO accreditation at DGC   Visitors’ services   Exhibits   Procurement   Employment   Internships   Model UN   Academic Impact   UN Archives   UN Audiovisual Library   How to donate to the UN system   Information on COVID-19 (Coronavirus)   Africa Renewal   Ten ways the UN makes a difference   GA High-level week 2024       Key Documents   UN Charter   Universal Declaration of Human Rights   Convention on the Rights of the Child   Statute of the International Court of Justice   Annual Report of the Secretary-General on the Work of the Organization       News and Media   News   Press Releases   Briefings   Spokesperson   Photos   UNIfeed   UN Web TV   UN Video   Social Media   The Essential UN   Awake at Night podcast       Issues / Campaigns   Global Issues   Observances   Sustainable Development Goals   Our Common Agenda   The Summit of the Future   Climate Action   Peace and Security   Action for Peacekeeping (A4P)   Global Crisis Response Group   Call to Action for Human Rights   Disability Inclusion Strategy   Fight Racism   Hate Speech   LGBTIQ+ People   Safety of Journalists   Rule of Law   Action to Counter Terrorism   Victims of Terrorism   Children and Armed Conflict   Violence Against Children (SRSG)   Sexual Violence in Conflict   Refugees and Migrants   Action Agenda on Internal Displacement   Spotlight Initiative   Preventing Sexual Exploitation and Abuse   Prevention of Genocide and the Responsibility to Protect   The Rwanda Genocide   The Holocaust   The Question of Palestine   The Transatlantic Slave Trade   Decolonization   Messengers of Peace   Roadmap for Digital Cooperation   Digital Financing Task Force   Data Strategy   Information Integrity   Countering Disinformation   UN75: 2020 and Beyond   Women Rise for All   Stop the Red Sea Catastrophe   Black Sea Grain Initiative Joint Coordination Centre\n\nMain Bodies   General Assembly   Security Council   Economic and Social Council   Trusteeship Council   International Court of Justice   Secretariat       Departments / Offices   New York   Geneva   Nairobi   Vienna   UN System Directory   UN System Chart   Global Leadership   UN Information Centres\n\nMain Bodies   General Assembly   Security Council   Economic and Social Council   Trusteeship Council   International Court of Justice   Secretariat\n\nMain Bodies   General Assembly   Security Council   Economic and Social Council   Trusteeship Council   International Court of Justice   Secretariat\n\nDepartments / Offices   New York   Geneva   Nairobi   Vienna   UN System Directory   UN System Chart   Global Leadership   UN Information Centres\n\nDepartments / Offices   New York   Geneva   Nairobi   Vienna   UN System Directory   UN System Chart   Global Leadership   UN Information Centres\n\nResources / Services   Emergency information   Reporting Wrongdoing   UN Journal   Documents   Guidelines for gender-inclusive language   Databases   Library   UN iLibrary   UN Chronicle   UN Yearbook   Bookshop   Publications for sale   Maps   Media Accreditation   NGO accreditation at ECOSOC   NGO accreditation at DGC   Visitors’ services   Exhibits   Procurement   Employment   Internships   Model UN   Academic Impact   UN Archives   UN Audiovisual Library   How to donate to the UN system   Information on COVID-19 (Coronavirus)   Africa Renewal   Ten ways the UN makes a difference   GA High-level week 2024\n\nResources / Services   Emergency information   Reporting Wrongdoing   UN Journal   Documents   Guidelines for gender-inclusive language   Databases   Library   UN iLibrary   UN Chronicle   UN Yearbook   Bookshop   Publications for sale   Maps   Media Accreditation   NGO accreditation at ECOSOC   NGO accreditation at DGC   Visitors’ services   Exhibits   Procurement   Employment   Internships   Model UN   Academic Impact   UN Archives   UN Audiovisual Library   How to donate to the UN system   Information on COVID-19 (Coronavirus)   Africa Renewal   Ten ways the UN makes a difference   GA High-level week 2024\n\nResources / Services   Emergency information   Reporting Wrongdoing   UN Journal   Documents   Guidelines for gender-inclusive language   Databases   Library   UN iLibrary   UN Chronicle   UN Yearbook   Bookshop   Publications for sale   Maps   Media Accreditation   NGO accreditation at ECOSOC   NGO accreditation at DGC   Visitors’ services   Exhibits   Procurement   Employment   Internships   Model UN   Academic Impact   UN Archives   UN Audiovisual Library   How to donate to the UN system   Information on COVID-19 (Coronavirus)   Africa Renewal   Ten ways the UN makes a difference   GA High-level week 2024\n\nKey Documents   UN Charter   Universal Declaration of Human Rights   Convention on the Rights of the Child   Statute of the International Court of Justice   Annual Report of the Secretary-General on the Work of the Organization       News and Media   News   Press Releases   Briefings   Spokesperson   Photos   UNIfeed   UN Web TV   UN Video   Social Media   The Essential UN   Awake at Night podcast\n\nKey Documents   UN Charter   Universal Declaration of Human Rights   Convention on the Rights of the Child   Statute of the International Court of Justice   Annual Report of the Secretary-General on the Work of the Organization\n\nKey Documents   UN Charter   Universal Declaration of Human Rights   Convention on the Rights of the Child   Statute of the International Court of Justice   Annual Report of the Secretary-General on the Work of the Organization\n\nNews and Media   News   Press Releases   Briefings   Spokesperson   Photos   UNIfeed   UN Web TV   UN Video   Social Media   The Essential UN   Awake at Night podcast\n\nNews and Media   News   Press Releases   Briefings   Spokesperson   Photos   UNIfeed   UN Web TV   UN Video   Social Media   The Essential UN   Awake at Night podcast\n\nIssues / Campaigns   Global Issues   Observances   Sustainable Development Goals   Our Common Agenda   The Summit of the Future   Climate Action   Peace and Security   Action for Peacekeeping (A4P)   Global Crisis Response Group   Call to Action for Human Rights   Disability Inclusion Strategy   Fight Racism   Hate Speech   LGBTIQ+ People   Safety of Journalists   Rule of Law   Action to Counter Terrorism   Victims of Terrorism   Children and Armed Conflict   Violence Against Children (SRSG)   Sexual Violence in Conflict   Refugees and Migrants   Action Agenda on Internal Displacement   Spotlight Initiative   Preventing Sexual Exploitation and Abuse   Prevention of Genocide and the Responsibility to Protect   The Rwanda Genocide   The Holocaust   The Question of Palestine   The Transatlantic Slave Trade   Decolonization   Messengers of Peace   Roadmap for Digital Cooperation   Digital Financing Task Force   Data Strategy   Information Integrity   Countering Disinformation   UN75: 2020 and Beyond   Women Rise for All   Stop the Red Sea Catastrophe   Black Sea Grain Initiative Joint Coordination Centre\n\nIssues / Campaigns   Global Issues   Observances   Sustainable Development Goals   Our Common Agenda   The Summit of the Future   Climate Action   Peace and Security   Action for Peacekeeping (A4P)   Global Crisis Response Group   Call to Action for Human Rights   Disability Inclusion Strategy   Fight Racism   Hate Speech   LGBTIQ+ People   Safety of Journalists   Rule of Law   Action to Counter Terrorism   Victims of Terrorism   Children and Armed Conflict   Violence Against Children (SRSG)   Sexual Violence in Conflict   Refugees and Migrants   Action Agenda on Internal Displacement   Spotlight Initiative   Preventing Sexual Exploitation and Abuse   Prevention of Genocide and the Responsibility to Protect   The Rwanda Genocide   The Holocaust   The Question of Palestine   The Transatlantic Slave Trade   Decolonization   Messengers of Peace   Roadmap for Digital Cooperation   Digital Financing Task Force   Data Strategy   Information Integrity   Countering Disinformation   UN75: 2020 and Beyond   Women Rise for All   Stop the Red Sea Catastrophe   Black Sea Grain Initiative Joint Coordination Centre\n\nIssues / Campaigns   Global Issues   Observances   Sustainable Development Goals   Our Common Agenda   The Summit of the Future   Climate Action   Peace and Security   Action for Peacekeeping (A4P)   Global Crisis Response Group   Call to Action for Human Rights   Disability Inclusion Strategy   Fight Racism   Hate Speech   LGBTIQ+ People   Safety of Journalists   Rule of Law   Action to Counter Terrorism   Victims of Terrorism   Children and Armed Conflict   Violence Against Children (SRSG)   Sexual Violence in Conflict   Refugees and Migrants   Action Agenda on Internal Displacement   Spotlight Initiative   Preventing Sexual Exploitation and Abuse   Prevention of Genocide and the Responsibility to Protect   The Rwanda Genocide   The Holocaust   The Question of Palestine   The Transatlantic Slave Trade   Decolonization   Messengers of Peace   Roadmap for Digital Cooperation   Digital Financing Task Force   Data Strategy   Information Integrity   Countering Disinformation   UN75: 2020 and Beyond   Women Rise for All   Stop the Red Sea Catastrophe   Black Sea Grain Initiative Joint Coordination Centre",
  "date": "",
  "source_type": "UN_organization",
  "extracted_at": "2025-04-07T13:52:50.072511",
  "metadata": {
    "description": "",
    "author": "United Nations",
    "og:site_name": "United Nations",
    "og:type": "article"
  },
  "relevance_score": 0.4,
  "summary": "Skip to main content\n\nGrowth in United Nations membership\n\n\n\n\n\n\n\n\n\n\n\n\n\n\n1945-1950          1950s          1960s          1970s          1980s          1990s          2000-Present\n\n\n \n \n\n\n\nOriginal 51 Members (1945)\n\n\n\nArgentina, Australia, Belgium, Bolivia, Brazil, Byelorussian Soviet Socialist Republic, Canada, Chile, China, Colombia, Costa Rica, Cuba, Czechoslovakia, Denmark, Dominican Republic, Ecuador, Egypt, El Salvador, Ethiopia, France, Greece, Guatemala, Haiti, Honduras, India, Iran, Iraq, Lebanon, Liberia, Luxembourg, Mexico, Netherlands, New Zealand, Nicaragua, Norway, Panama, Paraguay, Peru, Philippine Republic, Poland, Saudi Arabia, Syria, Turkey, Ukrainian Soviet Socialist Republic, Union of South Africa, Union of Soviet Socialist Republics, United Kingdom, United States, Uruguay, Venezuela, Yugoslavia\n\n\n\n\n\n55 Members (1946)\n\n\n\nAdded: Afghanistan, Iceland, Siam, Sweden\n\n\n\n\n\n57 Members (1947)\n\n\n\nAdded: Pakistan, Yemen (the Yemen Arab Republic)\n\n\n\n\n\n58 Members (1948)\n\n\n\nAdded: Burma\n\n\n\n \n\n59 Members (1949)\n\n\n\nAdded: Israel\n\n\n\n\n\n60 Members (1950)\n\n\n\nAdded: Indonesia\n\n\n\n\n\n76 Members (1955)\n\n\n\nAdded: Albania, Austria, Bulgaria, Cambodia, Ceylon, Finland, Hungary, Ireland, Italy, Jordan, Laos, Libya, Nepal, Portugal, Romania, Spain\n\n\n\n\n\n80 Members (1956)\n\n\n\nAdded: Japan, Morocco, Sudan, Tunisia\n\n\n\n\n\n82 Members (1957)\n\n\n\nAdded: Ghana, Federation of Malaya\n\n\n\n \n\n82 Members (1958)*\n\n\n\nAdded: Guinea\n\t\t\t\t\t\t\t\t* On 22 February 1958, Syria merged with Egypt (both original members of the United Nations) to become the United Arab Republic. 123 Members (1967)\n\n\n\nAdded: Yemen (People's Democratic Republic of Yemen)\n\n\n\n \n\n126 Members (1968)\n\n\n\nAdded: Equatorial Guinea, Mauritius, Swaziland\n\n\n\n\n\n127 Members (1970)\n\n\n\nAdded: Fiji\n\n\n\n\n\n132 Members (1971)\n\n\n\nAdded: Bahrain, Bhutan, Oman, Qatar, United Arab Emirates\n\n\n\n\n\n135 Members (1973)\n\n\n\nAdded: Bahamas, Federal Republic of Germany, German Democratic Republic\n\n\n\n\n\n138 Members (1974)\n\n\n\nAdded: Bangladesh, Grenada, Guinea-Bissau\n\n\n\n\n\n144 Members (1975)\n\n\n\nAdded: Cape Verde, Comoros, Mozambique, Papua New Guinea, Sao Tome and Principe, Suriname\n\n\n\n\n\n147 Members (1976)\n\n\n\nAdded: Angola, Samoa, Seychelles\n\n\n\n\n\n149 Members (1977)\n\n\n\nAdded: Djibouti, Viet Nam\n\n\n\n\n\n151 Members (1978)\n\n\n\nAdded: Dominica, Solomon Islands\n\n\n\n \n\n152 Members (1979)\n\n\n\nAdded: Saint Lucia\n\n\n\n\n\n154 Members (1980)\n\n\n\nAdded: Saint Vincent and the Grenadines, Zimbabwe\n\n\n\n\n\n157 Members (1981) \n\n\n\nAdded: Antigua and Barbuda, Belize, Vanuatu\n\n\n\n\n\n158 Members (1983)\n\n\n\nAdded: Saint Christopher and Nevis\n\n\n\n \n\n159 Members (1984)\n\n\n\nAdded: Brunei Darussalam\n\n\n\n\n\n159 Members (1990)*\n\n\n\nAdded: Liechtenstein, Namibia\n\t\t\t\t\t\t\t\t*On 22 May 1990, the People's Democratic Republic of Yemen (member since 1967) was united with the Yemen Arab Republic (member since 1947), forming the Republic of Yemen. 166 Members (1991)\n\n\n\nAdded: Democratic People's Republic of Korea, Estonia, Latvia, Lithuania, Marshall Islands, Federated States of Micronesia, Republic of Korea\n\n\n\n\n\n179 Members (1992)\n\n\n\nAdded: Armenia, Azerbaijan, Bosnia and Herzegovina, Croatia, Georgia, Kazakhstan, Kyrgyzstan, Republic of Moldova, San Marino, Slovenia, Tajikistan, Turkmenistan, Uzbekistan\n\n\n\n\n\n184 Members (1993)*\n\n\n\nAdded: Andorra, Czech Republic, Eritrea, Monaco, Slovakia, The former Yugoslav Republic of Macedonia\n\t\t\t\t\t\t\t\t*Czechoslovakia was an original Member of the United Nations from 24 October 1945. 191 Members (2002)\n\n\n\nAdded: Switzerland, Timor-Leste\n\n\n\n\n\n192 Members (2006)\n\n\n\nAdded: Montenegro\n\n\n\n\n\n193 Members (2011)\n\n\n\nAdded: South Sudan\n\n\n\n\n\n\n\n\n\n\n\nMEMBER STATES\n\nMembership \n\nAbout UN Membership\nList of UN Member States\nUN Membership research guide\nGrowth in UN Membership\nMembership of Principal UN Organs\nContributions to UN regular budget\nHonour Roll: Contribution Received in Full\nArrears in the Payment of Contribution\n\n\nPermanent Missions\n\nNew York\nGeneva\nVienna\n\n\nPermanent Observers\n\nAbout Permanent Observers\nNon-Member States\nIntergovernmental and Other Organizations\nSpecialized Agencies \n\n\n\n \n\nQuick links for delegates\n\nDelegate (UN Intranet - iSeek for Member States)\nBlue Book\nDelegates' Handbook\nManual of Protocol\n\n\n\n\n\n\n\n\n\n\n\n\n\n\n\n\n\n\n\n\n\n\n\n\n \n\n\n\n        Main Bodies   General Assembly   Security Council   Economic and Social Council   Trusteeship Council   International Court of Justice   Secretariat       Departments / Offices   New York   Geneva   Nairobi   Vienna   UN System Directory   UN System Chart   Global Leadership   UN Information Centres       Resources / Services   Emergency information   Reporting Wrongdoing   UN Journal   Documents   Guidelines for gender-inclusive language   Databases   Library   UN iLibrary   UN Chronicle   UN Yearbook   Bookshop   Publications for sale   Maps   Media Accreditation   NGO accreditation at ECOSOC   NGO accreditation at DGC   Visitors’ services   Exhibits   Procurement   Employment   Internships   Model UN   Academic Impact   UN Archives   UN Audiovisual Library   How to donate to the UN system   Information on COVID-19 (Coronavirus)   Africa Renewal   Ten ways the UN makes a difference   GA High-level week 2024       Key Documents   UN Charter   Universal Declaration of Human Rights   Convention on the Rights of the Child   Statute of the International Court of Justice   Annual Report of the Secretary-General on the Work of the Organization       News and Media   News   Press Releases   Briefings   Spokesperson   Photos   UNIfeed   UN Web TV   UN Video   Social Media   The Essential UN   Awake at Night podcast       Issues / Campaigns   Global Issues   Observances   Sustainable Development Goals   Our Common Agenda   The Summit of the Future   Climate Action   Peace and Security   Action for Peacekeeping (A4P)   Global Crisis Response Group   Call to Action for Human Rights   Disability Inclusion Strategy   Fight Racism   Hate Speech   LGBTIQ+ People   Safety of Journalists   Rule of Law   Action to Counter Terrorism   Victims of Terrorism   Children and Armed Conflict   Violence Against Children (SRSG)   Sexual Violence in Conflict   Refugees and Migrants   Action Agenda on Internal Displacement   Spotlight Initiative   Preventing Sexual Exploitation and Abuse   Prevention of Genocide and the Responsibility to Protect   The Rwanda Genocide   The Holocaust   The Question of Palestine   The Transatlantic Slave Trade   Decolonization   Messengers of Peace   Roadmap for Digital Cooperation   Digital Financing Task Force   Data Strategy   Information Integrity   Countering Disinformation   UN75: 2020 and Beyond   Women Rise for All   Stop the Red Sea Catastrophe   Black Sea Grain Initiative Joint Coordination Centre\n\nGrowth in United Nations membership\n\n\n\n\n\n\n\n\n\n\n\n\n\n\n1945-1950          1950s          1960s          1970s          1980s          1990s          2000-Present\n\n\n \n \n\n\n\nOriginal 51 Members (1945)\n\n\n\nArgentina, Australia, Belgium, Bolivia, Brazil, Byelorussian Soviet Socialist Republic, Canada, Chile, China, Colombia, Costa Rica, Cuba, Czechoslovakia, Denmark, Dominican Republic, Ecuador, Egypt, El Salvador, Ethiopia, France, Greece, Guatemala, Haiti, Honduras, India, Iran, Iraq, Lebanon, Liberia, Luxembourg, Mexico, Netherlands, New Zealand, Nicaragua, Norway, Panama, Paraguay, Peru, Philippine Republic, Poland, Saudi Arabia, Syria, Turkey, Ukrainian Soviet Socialist Republic, Union of South Africa, Union of Soviet Socialist Republics, United Kingdom, United States, Uruguay, Venezuela, Yugoslavia\n\n\n\n\n\n55 Members (1946)\n\n\n\nAdded: Afghanistan, Iceland, Siam, Sweden\n\n\n\n\n\n57 Members (1947)\n\n\n\nAdded: Pakistan, Yemen (the Yemen Arab Republic)\n\n\n\n\n\n58 Members (1948)\n\n\n\nAdded: Burma\n\n\n\n \n\n59 Members (1949)\n\n\n\nAdded: Israel\n\n\n\n\n\n60 Members (1950)\n\n\n\nAdded: Indonesia\n\n\n\n\n\n76 Members (1955)\n\n\n\nAdded: Albania, Austria, Bulgaria, Cambodia, Ceylon, Finland, Hungary, Ireland, Italy, Jordan, Laos, Libya, Nepal, Portugal, Romania, Spain\n\n\n\n\n\n80 Members (1956)\n\n\n\nAdded: Japan, Morocco, Sudan, Tunisia\n\n\n\n\n\n82 Members (1957)\n\n\n\nAdded: Ghana, Federation of Malaya\n\n\n\n \n\n82 Members (1958)*\n\n\n\nAdded: Guinea\n\t\t\t\t\t\t\t\t* On 22 February 1958, Syria merged with Egypt (both original members of the United Nations) to become the United Arab Republic. 123 Members (1967)\n\n\n\nAdded: Yemen (People's Democratic Republic of Yemen)\n\n\n\n \n\n126 Members (1968)\n\n\n\nAdded: Equatorial Guinea, Mauritius, Swaziland\n\n\n\n\n\n127 Members (1970)\n\n\n\nAdded: Fiji\n\n\n\n\n\n132 Members (1971)\n\n\n\nAdded: Bahrain, Bhutan, Oman, Qatar, United Arab Emirates\n\n\n\n\n\n135 Members (1973)\n\n\n\nAdded: Bahamas, Federal Republic of Germany, German Democratic Republic\n\n\n\n\n\n138 Members (1974)\n\n\n\nAdded: Bangladesh, Grenada, Guinea-Bissau\n\n\n\n\n\n144 Members (1975)\n\n\n\nAdded: Cape Verde, Comoros, Mozambique, Papua New Guinea, Sao Tome and Principe, Suriname\n\n\n\n\n\n147 Members (1976)\n\n\n\nAdded: Angola, Samoa, Seychelles\n\n\n\n\n\n149 Members (1977)\n\n\n\nAdded: Djibouti, Viet Nam\n\n\n\n\n\n151 Members (1978)\n\n\n\nAdded: Dominica, Solomon Islands\n\n\n\n \n\n152 Members (1979)\n\n\n\nAdded: Saint Lucia\n\n\n\n\n\n154 Members (1980)\n\n\n\nAdded: Saint Vincent and the Grenadines, Zimbabwe\n\n\n\n\n\n157 Members (1981) \n\n\n\nAdded: Antigua and Barbuda, Belize, Vanuatu\n\n\n\n\n\n158 Members (1983)\n\n\n\nAdded: Saint Christopher and Nevis\n\n\n\n \n\n159 Members (1984)\n\n\n\nAdded: Brunei Darussalam\n\n\n\n\n\n159 Members (1990)*\n\n\n\nAdded: Liechtenstein, Namibia\n\t\t\t\t\t\t\t\t*On 22 May 1990, the People's Democratic Republic of Yemen (member since 1967) was united with the Yemen Arab Republic (member since 1947), forming the Republic of Yemen. 166 Members (1991)\n\n\n\nAdded: Democratic People's Republic of Korea, Estonia, Latvia, Lithuania, Marshall Islands, Federated States of Micronesia, Republic of Korea\n\n\n\n\n\n179 Members (1992)\n\n\n\nAdded: Armenia, Azerbaijan, Bosnia and Herzegovina, Croatia, Georgia, Kazakhstan, Kyrgyzstan, Republic of Moldova, San Marino, Slovenia, Tajikistan, Turkmenistan, Uzbekistan\n\n\n\n\n\n184 Members (1993)*\n\n\n\nAdded: Andorra, Czech Republic, Eritrea, Monaco, Slovakia, The former Yugoslav Republic of Macedonia\n\t\t\t\t\t\t\t\t*Czechoslovakia was an original Member of the United Nations from 24 October 1945. 191 Members (2002)\n\n\n\nAdded: Switzerland, Timor-Leste\n\n\n\n\n\n192 Members (2006)\n\n\n\nAdded: Montenegro\n\n\n\n\n\n193 Members (2011)\n\n\n\nAdded: South Sudan\n\n\n\n\n\n\n\n\n\n\n\nMEMBER STATES\n\nMembership \n\nAbout UN Membership\nList of UN Member States\nUN Membership research guide\nGrowth in UN Membership\nMembership of Principal UN Organs\nContributions to UN regular budget\nHonour Roll: Contribution Received in Full\nArrears in the Payment of Contribution\n\n\nPermanent Missions\n\nNew York\nGeneva\nVienna\n\n\nPermanent Observers\n\nAbout Permanent Observers\nNon-Member States\nIntergovernmental and Other Organizations\nSpecialized Agencies \n\n\n\n \n\nQuick links for delegates\n\nDelegate (UN Intranet - iSeek for Member States)\nBlue Book\nDelegates' Handbook\nManual of Protocol\n\nGrowth in United Nations membership\n\n\n\n\n\n\n\n\n\n\n\n\n\n\n1945-1950          1950s          1960s          1970s          1980s          1990s          2000-Present\n\n\n \n \n\n\n\nOriginal 51 Members (1945)\n\n\n\nArgentina, Australia, Belgium, Bolivia, Brazil, Byelorussian Soviet Socialist Republic, Canada, Chile, China, Colombia, Costa Rica, Cuba, Czechoslovakia, Denmark, Dominican Republic, Ecuador, Egypt, El Salvador, Ethiopia, France, Greece, Guatemala, Haiti, Honduras, India, Iran, Iraq, Lebanon, Liberia, Luxembourg, Mexico, Netherlands, New Zealand, Nicaragua, Norway, Panama, Paraguay, Peru, Philippine Republic, Poland, Saudi Arabia, Syria, Turkey, Ukrainian Soviet Socialist Republic, Union of South Africa, Union of Soviet Socialist Republics, United Kingdom, United States, Uruguay, Venezuela, Yugoslavia\n\n\n\n\n\n55 Members (1946)\n\n\n\nAdded: Afghanistan, Iceland, Siam, Sweden\n\n\n\n\n\n57 Members (1947)\n\n\n\nAdded: Pakistan, Yemen (the Yemen Arab Republic)\n\n\n\n\n\n58 Members (1948)\n\n\n\nAdded: Burma\n\n\n\n \n\n59 Members (1949)\n\n\n\nAdded: Israel\n\n\n\n\n\n60 Members (1950)\n\n\n\nAdded: Indonesia\n\n\n\n\n\n76 Members (1955)\n\n\n\nAdded: Albania, Austria, Bulgaria, Cambodia, Ceylon, Finland, Hungary, Ireland, Italy, Jordan, Laos, Libya, Nepal, Portugal, Romania, Spain\n\n\n\n\n\n80 Members (1956)\n\n\n\nAdded: Japan, Morocco, Sudan, Tunisia\n\n\n\n\n\n82 Members (1957)\n\n\n\nAdded: Ghana, Federation of Malaya\n\n\n\n \n\n82 Members (1958)*\n\n\n\nAdded: Guinea\n\t\t\t\t\t\t\t\t* On 22 February 1958, Syria merged with Egypt (both original members of the United Nations) to become the United Arab Republic. 123 Members (1967)\n\n\n\nAdded: Yemen (People's Democratic Republic of Yemen)\n\n\n\n \n\n126 Members (1968)\n\n\n\nAdded: Equatorial Guinea, Mauritius, Swaziland\n\n\n\n\n\n127 Members (1970)\n\n\n\nAdded: Fiji\n\n\n\n\n\n132 Members (1971)\n\n\n\nAdded: Bahrain, Bhutan, Oman, Qatar, United Arab Emirates\n\n\n\n\n\n135 Members (1973)\n\n\n\nAdded: Bahamas, Federal Republic of Germany, German Democratic Republic\n\n\n\n\n\n138 Members (1974)\n\n\n\nAdded: Bangladesh, Grenada, Guinea-Bissau\n\n\n\n\n\n144 Members (1975)\n\n\n\nAdded: Cape Verde, Comoros, Mozambique, Papua New Guinea, Sao Tome and Principe, Suriname\n\n\n\n\n\n147 Members (1976)\n\n\n\nAdded: Angola, Samoa, Seychelles\n\n\n\n\n\n149 Members (1977)\n\n\n\nAdded: Djibouti, Viet Nam\n\n\n\n\n\n151 Members (1978)\n\n\n\nAdded: Dominica, Solomon Islands\n\n\n\n \n\n152 Members (1979)\n\n\n\nAdded: Saint Lucia\n\n\n\n\n\n154 Members (1980)\n\n\n\nAdded: Saint Vincent and the Grenadines, Zimbabwe\n\n\n\n\n\n157 Members (1981) \n\n\n\nAdded: Antigua and Barbuda, Belize, Vanuatu\n\n\n\n\n\n158 Members (1983)\n\n\n\nAdded: Saint Christopher and Nevis\n\n\n\n \n\n159 Members (1984)\n\n\n\nAdded: Brunei Darussalam\n\n\n\n\n\n159 Members (1990)*\n\n\n\nAdded: Liechtenstein, Namibia\n\t\t\t\t\t\t\t\t*On 22 May 1990, the People's Democratic Republic of Yemen (member since 1967) was united with the Yemen Arab Republic (member since 1947), forming the Republic of Yemen. 166 Members (1991)\n\n\n\nAdded: Democratic People's Republic of Korea, Estonia, Latvia, Lithuania, Marshall Islands, Federated States of Micronesia, Republic of Korea\n\n\n\n\n\n179 Members (1992)\n\n\n\nAdded: Armenia, Azerbaijan, Bosnia and Herzegovina, Croatia, Georgia, Kazakhstan, Kyrgyzstan, Republic of Moldova, San Marino, Slovenia, Tajikistan, Turkmenistan, Uzbekistan\n\n\n\n\n\n184 Members (1993)*\n\n\n\nAdded: Andorra, Czech Republic, Eritrea, Monaco, Slovakia, The former Yugoslav Republic of Macedonia\n\t\t\t\t\t\t\t\t*Czechoslovakia was an original Member of the United Nations from 24 October 1945. 191 Members (2002)\n\n\n\nAdded: Switzerland, Timor-Leste\n\n\n\n\n\n192 Members (2006)\n\n\n\nAdded: Montenegro\n\n\n\n\n\n193 Members (2011)\n\n\n\nAdded: South Sudan\n\n\n\n\n\n\n\n\n\n\n\nMEMBER STATES\n\nMembership \n\nAbout UN Membership\nList of UN Member States\nUN Membership research guide\nGrowth in UN Membership\nMembership of Principal UN Organs\nContributions to UN regular budget\nHonour Roll: Contribution Received in Full\nArrears in the Payment of Contribution\n\n\nPermanent Missions\n\nNew York\nGeneva\nVienna\n\n\nPermanent Observers\n\nAbout Permanent Observers\nNon-Member States\nIntergovernmental and Other Organizations\nSpecialized Agencies \n\n\n\n \n\nQuick links for delegates\n\nDelegate (UN Intranet - iSeek for Member States)\nBlue Book\nDelegates' Handbook\nManual of Protocol\n\nGrowth in United Nations membership\n\n\n\n\n\n\n\n\n\n\n\n\n\n\n1945-1950          1950s          1960s          1970s          1980s          1990s          2000-Present\n\n\n \n \n\n\n\nOriginal 51 Members (1945)\n\n\n\nArgentina, Australia, Belgium, Bolivia, Brazil, Byelorussian Soviet Socialist Republic, Canada, Chile, China, Colombia, Costa Rica, Cuba, Czechoslovakia, Denmark, Dominican Republic, Ecuador, Egypt, El Salvador, Ethiopia, France, Greece, Guatemala, Haiti, Honduras, India, Iran, Iraq, Lebanon, Liberia, Luxembourg, Mexico, Netherlands, New Zealand, Nicaragua, Norway, Panama, Paraguay, Peru, Philippine Republic, Poland, Saudi Arabia, Syria, Turkey, Ukrainian Soviet Socialist Republic, Union of South Africa, Union of Soviet Socialist Republics, United Kingdom, United States, Uruguay, Venezuela, Yugoslavia\n\n\n\n\n\n55 Members (1946)\n\n\n\nAdded: Afghanistan, Iceland, Siam, Sweden\n\n\n\n\n\n57 Members (1947)\n\n\n\nAdded: Pakistan, Yemen (the Yemen Arab Republic)\n\n\n\n\n\n58 Members (1948)\n\n\n\nAdded: Burma\n\n\n\n \n\n59 Members (1949)\n\n\n\nAdded: Israel\n\n\n\n\n\n60 Members (1950)\n\n\n\nAdded: Indonesia\n\n\n\n\n\n76 Members (1955)\n\n\n\nAdded: Albania, Austria, Bulgaria, Cambodia, Ceylon, Finland, Hungary, Ireland, Italy, Jordan, Laos, Libya, Nepal, Portugal, Romania, Spain\n\n\n\n\n\n80 Members (1956)\n\n\n\nAdded: Japan, Morocco, Sudan, Tunisia\n\n\n\n\n\n82 Members (1957)\n\n\n\nAdded: Ghana, Federation of Malaya\n\n\n\n \n\n82 Members (1958)*\n\n\n\nAdded: Guinea\n\t\t\t\t\t\t\t\t* On 22 February 1958, Syria merged with Egypt (both original members of the United Nations) to become the United Arab Republic. 123 Members (1967)\n\n\n\nAdded: Yemen (People's Democratic Republic of Yemen)\n\n\n\n \n\n126 Members (1968)\n\n\n\nAdded: Equatorial Guinea, Mauritius, Swaziland\n\n\n\n\n\n127 Members (1970)\n\n\n\nAdded: Fiji\n\n\n\n\n\n132 Members (1971)\n\n\n\nAdded: Bahrain, Bhutan, Oman, Qatar, United Arab Emirates\n\n\n\n\n\n135 Members (1973)\n\n\n\nAdded: Bahamas, Federal Republic of Germany, German Democratic Republic\n\n\n\n\n\n138 Members (1974)\n\n\n\nAdded: Bangladesh, Grenada, Guinea-Bissau\n\n\n\n\n\n144 Members (1975)\n\n\n\nAdded: Cape Verde, Comoros, Mozambique, Papua New Guinea, Sao Tome and Principe, Suriname\n\n\n\n\n\n147 Members (1976)\n\n\n\nAdded: Angola, Samoa, Seychelles\n\n\n\n\n\n149 Members (1977)\n\n\n\nAdded: Djibouti, Viet Nam\n\n\n\n\n\n151 Members (1978)\n\n\n\nAdded: Dominica, Solomon Islands\n\n\n\n \n\n152 Members (1979)\n\n\n\nAdded: Saint Lucia\n\n\n\n\n\n154 Members (1980)\n\n\n\nAdded: Saint Vincent and the Grenadines, Zimbabwe\n\n\n\n\n\n157 Members (1981) \n\n\n\nAdded: Antigua and Barbuda, Belize, Vanuatu\n\n\n\n\n\n158 Members (1983)\n\n\n\nAdded: Saint Christopher and Nevis\n\n\n\n \n\n159 Members (1984)\n\n\n\nAdded: Brunei Darussalam\n\n\n\n\n\n159 Members (1990)*\n\n\n\nAdded: Liechtenstein, Namibia\n\t\t\t\t\t\t\t\t*On 22 May 1990, the People's Democratic Republic of Yemen (member since 1967) was united with the Yemen Arab Republic (member since 1947), forming the Republic of Yemen. 166 Members (1991)\n\n\n\nAdded: Democratic People's Republic of Korea, Estonia, Latvia, Lithuania, Marshall Islands, Federated States of Micronesia, Republic of Korea\n\n\n\n\n\n179 Members (1992)\n\n\n\nAdded: Armenia, Azerbaijan, Bosnia and Herzegovina, Croatia, Georgia, Kazakhstan, Kyrgyzstan, Republic of Moldova, San Marino, Slovenia, Tajikistan, Turkmenistan, Uzbekistan\n\n\n\n\n\n184 Members (1993)*\n\n\n\nAdded: Andorra, Czech Republic, Eritrea, Monaco, Slovakia, The former Yugoslav Republic of Macedonia\n\t\t\t\t\t\t\t\t*Czechoslovakia was an original Member of the United Nations from 24 October 1945. 191 Members (2002)\n\n\n\nAdded: Switzerland, Timor-Leste\n\n\n\n\n\n192 Members (2006)\n\n\n\nAdded: Montenegro\n\n\n\n\n\n193 Members (2011)\n\n\n\nAdded: South Sudan\n\n\n\n\n\n\n\n\n\n\n\nMEMBER STATES\n\nMembership \n\nAbout UN Membership\nList of UN Member States\nUN Membership research guide\nGrowth in UN Membership\nMembership of Principal UN Organs\nContributions to UN regular budget\nHonour Roll: Contribution Received in Full\nArrears in the Payment of Contribution\n\n\nPermanent Missions\n\nNew York\nGeneva\nVienna\n\n\nPermanent Observers\n\nAbout Permanent Observers\nNon-Member States\nIntergovernmental and Other Organizations\nSpecialized Agencies \n\n\n\n \n\nQuick links for delegates\n\nDelegate (UN Intranet - iSeek for Member States)\nBlue Book\nDelegates' Handbook\nManual of Protocol\n\nGrowth in United Nations membership\n\n\n\n\n\n\n\n\n\n\n\n\n\n\n1945-1950          1950s          1960s          1970s          1980s          1990s          2000-Present\n\n\n \n \n\n\n\nOriginal 51 Members (1945)\n\n\n\nArgentina, Australia, Belgium, Bolivia, Brazil, Byelorussian Soviet Socialist Republic, Canada, Chile, China, Colombia, Costa Rica, Cuba, Czechoslovakia, Denmark, Dominican Republic, Ecuador, Egypt, El Salvador, Ethiopia, France, Greece, Guatemala, Haiti, Honduras, India, Iran, Iraq, Lebanon, Liberia, Luxembourg, Mexico, Netherlands, New Zealand, Nicaragua, Norway, Panama, Paraguay, Peru, Philippine Republic, Poland, Saudi Arabia, Syria, Turkey, Ukrainian Soviet Socialist Republic, Union of South Africa, Union of Soviet Socialist Republics, United Kingdom, United States, Uruguay, Venezuela, Yugoslavia\n\n\n\n\n\n55 Members (1946)\n\n\n\nAdded: Afghanistan, Iceland, Siam, Sweden\n\n\n\n\n\n57 Members (1947)\n\n\n\nAdded: Pakistan, Yemen (the Yemen Arab Republic)\n\n\n\n\n\n58 Members (1948)\n\n\n\nAdded: Burma\n\n\n\n \n\n59 Members (1949)\n\n\n\nAdded: Israel\n\n\n\n\n\n60 Members (1950)\n\n\n\nAdded: Indonesia\n\n\n\n\n\n76 Members (1955)\n\n\n\nAdded: Albania, Austria, Bulgaria, Cambodia, Ceylon, Finland, Hungary, Ireland, Italy, Jordan, Laos, Libya, Nepal, Portugal, Romania, Spain\n\n\n\n\n\n80 Members (1956)\n\n\n\nAdded: Japan, Morocco, Sudan, Tunisia\n\n\n\n\n\n82 Members (1957)\n\n\n\nAdded: Ghana, Federation of Malaya\n\n\n\n \n\n82 Members (1958)*\n\n\n\nAdded: Guinea\n\t\t\t\t\t\t\t\t* On 22 February 1958, Syria merged with Egypt (both original members of the United Nations) to become the United Arab Republic. 123 Members (1967)\n\n\n\nAdded: Yemen (People's Democratic Republic of Yemen)\n\n\n\n \n\n126 Members (1968)\n\n\n\nAdded: Equatorial Guinea, Mauritius, Swaziland\n\n\n\n\n\n127 Members (1970)\n\n\n\nAdded: Fiji\n\n\n\n\n\n132 Members (1971)\n\n\n\nAdded: Bahrain, Bhutan, Oman, Qatar, United Arab Emirates\n\n\n\n\n\n135 Members (1973)\n\n\n\nAdded: Bahamas, Federal Republic of Germany, German Democratic Republic\n\n\n\n\n\n138 Members (1974)\n\n\n\nAdded: Bangladesh, Grenada, Guinea-Bissau\n\n\n\n\n\n144 Members (1975)\n\n\n\nAdded: Cape Verde, Comoros, Mozambique, Papua New Guinea, Sao Tome and Principe, Suriname\n\n\n\n\n\n147 Members (1976)\n\n\n\nAdded: Angola, Samoa, Seychelles\n\n\n\n\n\n149 Members (1977)\n\n\n\nAdded: Djibouti, Viet Nam\n\n\n\n\n\n151 Members (1978)\n\n\n\nAdded: Dominica, Solomon Islands\n\n\n\n \n\n152 Members (1979)\n\n\n\nAdded: Saint Lucia\n\n\n\n\n\n154 Members (1980)\n\n\n\nAdded: Saint Vincent and the Grenadines, Zimbabwe\n\n\n\n\n\n157 Members (1981) \n\n\n\nAdded: Antigua and Barbuda, Belize, Vanuatu\n\n\n\n\n\n158 Members (1983)\n\n\n\nAdded: Saint Christopher and Nevis\n\n\n\n \n\n159 Members (1984)\n\n\n\nAdded: Brunei Darussalam\n\n\n\n\n\n159 Members (1990)*\n\n\n\nAdded: Liechtenstein, Namibia\n\t\t\t\t\t\t\t\t*On 22 May 1990, the People's Democratic Republic of Yemen (member since 1967) was united with the Yemen Arab Republic (member since 1947), forming the Republic of Yemen. 166 Members (1991)\n\n\n\nAdded: Democratic People's Republic of Korea, Estonia, Latvia, Lithuania, Marshall Islands, Federated States of Micronesia, Republic of Korea\n\n\n\n\n\n179 Members (1992)\n\n\n\nAdded: Armenia, Azerbaijan, Bosnia and Herzegovina, Croatia, Georgia, Kazakhstan, Kyrgyzstan, Republic of Moldova, San Marino, Slovenia, Tajikistan, Turkmenistan, Uzbekistan\n\n\n\n\n\n184 Members (1993)*\n\n\n\nAdded: Andorra, Czech Republic, Eritrea, Monaco, Slovakia, The former Yugoslav Republic of Macedonia\n\t\t\t\t\t\t\t\t*Czechoslovakia was an original Member of the United Nations from 24 October 1945. 191 Members (2002)\n\n\n\nAdded: Switzerland, Timor-Leste\n\n\n\n\n\n192 Members (2006)\n\n\n\nAdded: Montenegro\n\n\n\n\n\n193 Members (2011)\n\n\n\nAdded: South Sudan\n\n\n\n\n\n\n\n\n\n\n\nMEMBER STATES\n\nMembership \n\nAbout UN Membership\nList of UN Member States\nUN Membership research guide\nGrowth in UN Membership\nMembership of Principal UN Organs\nContributions to UN regular budget\nHonour Roll: Contribution Received in Full\nArrears in the Payment of Contribution\n\n\nPermanent Missions\n\nNew York\nGeneva\nVienna\n\n\nPermanent Observers\n\nAbout Permanent Observers\nNon-Member States\nIntergovernmental and Other Organizations\nSpecialized Agencies \n\n\n\n \n\nQuick links for delegates\n\nDelegate (UN Intranet - iSeek for Member States)\nBlue Book\nDelegates' Handbook\nManual of Protocol\n\n1945-1950          1950s          1960s          1970s          1980s          1990s          2000-Present\n\n\n \n \n\n\n\nOriginal 51 Members (1945)\n\n\n\nArgentina, Australia, Belgium, Bolivia, Brazil, Byelorussian Soviet Socialist Republic, Canada, Chile, China, Colombia, Costa Rica, Cuba, Czechoslovakia, Denmark, Dominican Republic, Ecuador, Egypt, El Salvador, Ethiopia, France, Greece, Guatemala, Haiti, Honduras, India, Iran, Iraq, Lebanon, Liberia, Luxembourg, Mexico, Netherlands, New Zealand, Nicaragua, Norway, Panama, Paraguay, Peru, Philippine Republic, Poland, Saudi Arabia, Syria, Turkey, Ukrainian Soviet Socialist Republic, Union of South Africa, Union of Soviet Socialist Republics, United Kingdom, United States, Uruguay, Venezuela, Yugoslavia\n\n\n\n\n\n55 Members (1946)\n\n\n\nAdded: Afghanistan, Iceland, Siam, Sweden\n\n\n\n\n\n57 Members (1947)\n\n\n\nAdded: Pakistan, Yemen (the Yemen Arab Republic)\n\n\n\n\n\n58 Members (1948)\n\n\n\nAdded: Burma\n\n\n\n \n\n59 Members (1949)\n\n\n\nAdded: Israel\n\n\n\n\n\n60 Members (1950)\n\n\n\nAdded: Indonesia\n\n\n\n\n\n76 Members (1955)\n\n\n\nAdded: Albania, Austria, Bulgaria, Cambodia, Ceylon, Finland, Hungary, Ireland, Italy, Jordan, Laos, Libya, Nepal, Portugal, Romania, Spain\n\n\n\n\n\n80 Members (1956)\n\n\n\nAdded: Japan, Morocco, Sudan, Tunisia\n\n\n\n\n\n82 Members (1957)\n\n\n\nAdded: Ghana, Federation of Malaya\n\n\n\n \n\n82 Members (1958)*\n\n\n\nAdded: Guinea\n\t\t\t\t\t\t\t\t* On 22 February 1958, Syria merged with Egypt (both original members of the United Nations) to become the United Arab Republic. 123 Members (1967)\n\n\n\nAdded: Yemen (People's Democratic Republic of Yemen)\n\n\n\n \n\n126 Members (1968)\n\n\n\nAdded: Equatorial Guinea, Mauritius, Swaziland\n\n\n\n\n\n127 Members (1970)\n\n\n\nAdded: Fiji\n\n\n\n\n\n132 Members (1971)\n\n\n\nAdded: Bahrain, Bhutan, Oman, Qatar, United Arab Emirates\n\n\n\n\n\n135 Members (1973)\n\n\n\nAdded: Bahamas, Federal Republic of Germany, German Democratic Republic\n\n\n\n\n\n138 Members (1974)\n\n\n\nAdded: Bangladesh, Grenada, Guinea-Bissau\n\n\n\n\n\n144 Members (1975)\n\n\n\nAdded: Cape Verde, Comoros, Mozambique, Papua New Guinea, Sao Tome and Principe, Suriname\n\n\n\n\n\n147 Members (1976)\n\n\n\nAdded: Angola, Samoa, Seychelles\n\n\n\n\n\n149 Members (1977)\n\n\n\nAdded: Djibouti, Viet Nam\n\n\n\n\n\n151 Members (1978)\n\n\n\nAdded: Dominica, Solomon Islands\n\n\n\n \n\n152 Members (1979)\n\n\n\nAdded: Saint Lucia\n\n\n\n\n\n154 Members (1980)\n\n\n\nAdded: Saint Vincent and the Grenadines, Zimbabwe\n\n\n\n\n\n157 Members (1981) \n\n\n\nAdded: Antigua and Barbuda, Belize, Vanuatu\n\n\n\n\n\n158 Members (1983)\n\n\n\nAdded: Saint Christopher and Nevis\n\n\n\n \n\n159 Members (1984)\n\n\n\nAdded: Brunei Darussalam\n\n\n\n\n\n159 Members (1990)*\n\n\n\nAdded: Liechtenstein, Namibia\n\t\t\t\t\t\t\t\t*On 22 May 1990, the People's Democratic Republic of Yemen (member since 1967) was united with the Yemen Arab Republic (member since 1947), forming the Republic of Yemen. 191 Members (2002)\n\n\n\nAdded: Switzerland, Timor-Leste\n\n\n\n\n\n192 Members (2006)\n\n\n\nAdded: Montenegro\n\n\n\n\n\n193 Members (2011)\n\n\n\nAdded: South Sudan\n\n\n\n\n\n\n\n\n\n\n\nMEMBER STATES\n\nMembership \n\nAbout UN Membership\nList of UN Member States\nUN Membership research guide\nGrowth in UN Membership\nMembership of Principal UN Organs\nContributions to UN regular budget\nHonour Roll: Contribution Received in Full\nArrears in the Payment of Contribution\n\n\nPermanent Missions\n\nNew York\nGeneva\nVienna\n\n\nPermanent Observers\n\nAbout Permanent Observers\nNon-Member States\nIntergovernmental and Other Organizations\nSpecialized Agencies \n\n\n\n \n\nQuick links for delegates\n\nDelegate (UN Intranet - iSeek for Member States)\nBlue Book\nDelegates' Handbook\nManual of Protocol\n\n1945-1950          1950s          1960s          1970s          1980s          1990s          2000-Present\n\n\n \n \n\n\n\nOriginal 51 Members (1945)\n\n\n\nArgentina, Australia, Belgium, Bolivia, Brazil, Byelorussian Soviet Socialist Republic, Canada, Chile, China, Colombia, Costa Rica, Cuba, Czechoslovakia, Denmark, Dominican Republic, Ecuador, Egypt, El Salvador, Ethiopia, France, Greece, Guatemala, Haiti, Honduras, India, Iran, Iraq, Lebanon, Liberia, Luxembourg, Mexico, Netherlands, New Zealand, Nicaragua, Norway, Panama, Paraguay, Peru, Philippine Republic, Poland, Saudi Arabia, Syria, Turkey, Ukrainian Soviet Socialist Republic, Union of South Africa, Union of Soviet Socialist Republics, United Kingdom, United States, Uruguay, Venezuela, Yugoslavia\n\n\n\n\n\n55 Members (1946)\n\n\n\nAdded: Afghanistan, Iceland, Siam, Sweden\n\n\n\n\n\n57 Members (1947)\n\n\n\nAdded: Pakistan, Yemen (the Yemen Arab Republic)\n\n\n\n\n\n58 Members (1948)\n\n\n\nAdded: Burma\n\n\n\n \n\n59 Members (1949)\n\n\n\nAdded: Israel\n\n\n\n\n\n60 Members (1950)\n\n\n\nAdded: Indonesia\n\n\n\n\n\n76 Members (1955)\n\n\n\nAdded: Albania, Austria, Bulgaria, Cambodia, Ceylon, Finland, Hungary, Ireland, Italy, Jordan, Laos, Libya, Nepal, Portugal, Romania, Spain\n\n\n\n\n\n80 Members (1956)\n\n\n\nAdded: Japan, Morocco, Sudan, Tunisia\n\n\n\n\n\n82 Members (1957)\n\n\n\nAdded: Ghana, Federation of Malaya\n\n\n\n \n\n82 Members (1958)*\n\n\n\nAdded: Guinea\n\t\t\t\t\t\t\t\t* On 22 February 1958, Syria merged with Egypt (both original members of the United Nations) to become the United Arab Republic. 123 Members (1967)\n\n\n\nAdded: Yemen (People's Democratic Republic of Yemen)\n\n\n\n \n\n126 Members (1968)\n\n\n\nAdded: Equatorial Guinea, Mauritius, Swaziland\n\n\n\n\n\n127 Members (1970)\n\n\n\nAdded: Fiji\n\n\n\n\n\n132 Members (1971)\n\n\n\nAdded: Bahrain, Bhutan, Oman, Qatar, United Arab Emirates\n\n\n\n\n\n135 Members (1973)\n\n\n\nAdded: Bahamas, Federal Republic of Germany, German Democratic Republic\n\n\n\n\n\n138 Members (1974)\n\n\n\nAdded: Bangladesh, Grenada, Guinea-Bissau\n\n\n\n\n\n144 Members (1975)\n\n\n\nAdded: Cape Verde, Comoros, Mozambique, Papua New Guinea, Sao Tome and Principe, Suriname\n\n\n\n\n\n147 Members (1976)\n\n\n\nAdded: Angola, Samoa, Seychelles\n\n\n\n\n\n149 Members (1977)\n\n\n\nAdded: Djibouti, Viet Nam\n\n\n\n\n\n151 Members (1978)\n\n\n\nAdded: Dominica, Solomon Islands\n\n\n\n \n\n152 Members (1979)\n\n\n\nAdded: Saint Lucia\n\n\n\n\n\n154 Members (1980)\n\n\n\nAdded: Saint Vincent and the Grenadines, Zimbabwe\n\n\n\n\n\n157 Members (1981) \n\n\n\nAdded: Antigua and Barbuda, Belize, Vanuatu\n\n\n\n\n\n158 Members (1983)\n\n\n\nAdded: Saint Christopher and Nevis\n\n\n\n \n\n159 Members (1984)\n\n\n\nAdded: Brunei Darussalam\n\n\n\n\n\n159 Members (1990)*\n\n\n\nAdded: Liechtenstein, Namibia\n\t\t\t\t\t\t\t\t*On 22 May 1990, the People's Democratic Republic of Yemen (member since 1967) was united with the Yemen Arab Republic (member since 1947), forming the Republic of Yemen. 191 Members (2002)\n\n\n\nAdded: Switzerland, Timor-Leste\n\n\n\n\n\n192 Members (2006)\n\n\n\nAdded: Montenegro\n\n\n\n\n\n193 Members (2011)\n\n\n\nAdded: South Sudan\n\n\n\n\n\n\n\n\n\n\n\nMEMBER STATES\n\nMembership \n\nAbout UN Membership\nList of UN Member States\nUN Membership research guide\nGrowth in UN Membership\nMembership of Principal UN Organs\nContributions to UN regular budget\nHonour Roll: Contribution Received in Full\nArrears in the Payment of Contribution\n\n\nPermanent Missions\n\nNew York\nGeneva\nVienna\n\n\nPermanent Observers\n\nAbout Permanent Observers\nNon-Member States\nIntergovernmental and Other Organizations\nSpecialized Agencies \n\n\n\n \n\nQuick links for delegates\n\nDelegate (UN Intranet - iSeek for Member States)\nBlue Book\nDelegates' Handbook\nManual of Protocol\n\n1945-1950          1950s          1960s          1970s          1980s          1990s          2000-Present\n\n\n \n \n\n\n\nOriginal 51 Members (1945)\n\n\n\nArgentina, Australia, Belgium, Bolivia, Brazil, Byelorussian Soviet Socialist Republic, Canada, Chile, China, Colombia, Costa Rica, Cuba, Czechoslovakia, Denmark, Dominican Republic, Ecuador, Egypt, El Salvador, Ethiopia, France, Greece, Guatemala, Haiti, Honduras, India, Iran, Iraq, Lebanon, Liberia, Luxembourg, Mexico, Netherlands, New Zealand, Nicaragua, Norway, Panama, Paraguay, Peru, Philippine Republic, Poland, Saudi Arabia, Syria, Turkey, Ukrainian Soviet Socialist Republic, Union of South Africa, Union of Soviet Socialist Republics, United Kingdom, United States, Uruguay, Venezuela, Yugoslavia\n\n\n\n\n\n55 Members (1946)\n\n\n\nAdded: Afghanistan, Iceland, Siam, Sweden\n\n\n\n\n\n57 Members (1947)\n\n\n\nAdded: Pakistan, Yemen (the Yemen Arab Republic)\n\n\n\n\n\n58 Members (1948)\n\n\n\nAdded: Burma\n\n\n\n \n\n59 Members (1949)\n\n\n\nAdded: Israel\n\n\n\n\n\n60 Members (1950)\n\n\n\nAdded: Indonesia\n\n\n\n\n\n76 Members (1955)\n\n\n\nAdded: Albania, Austria, Bulgaria, Cambodia, Ceylon, Finland, Hungary, Ireland, Italy, Jordan, Laos, Libya, Nepal, Portugal, Romania, Spain\n\n\n\n\n\n80 Members (1956)\n\n\n\nAdded: Japan, Morocco, Sudan, Tunisia\n\n\n\n\n\n82 Members (1957)\n\n\n\nAdded: Ghana, Federation of Malaya\n\n\n\n \n\n82 Members (1958)*\n\n\n\nAdded: Guinea\n\t\t\t\t\t\t\t\t* On 22 February 1958, Syria merged with Egypt (both original members of the United Nations) to become the United Arab Republic. 123 Members (1967)\n\n\n\nAdded: Yemen (People's Democratic Republic of Yemen)\n\n\n\n \n\n126 Members (1968)\n\n\n\nAdded: Equatorial Guinea, Mauritius, Swaziland\n\n\n\n\n\n127 Members (1970)\n\n\n\nAdded: Fiji\n\n\n\n\n\n132 Members (1971)\n\n\n\nAdded: Bahrain, Bhutan, Oman, Qatar, United Arab Emirates\n\n\n\n\n\n135 Members (1973)\n\n\n\nAdded: Bahamas, Federal Republic of Germany, German Democratic Republic\n\n\n\n\n\n138 Members (1974)\n\n\n\nAdded: Bangladesh, Grenada, Guinea-Bissau\n\n\n\n\n\n144 Members (1975)\n\n\n\nAdded: Cape Verde, Comoros, Mozambique, Papua New Guinea, Sao Tome and Principe, Suriname\n\n\n\n\n\n147 Members (1976)\n\n\n\nAdded: Angola, Samoa, Seychelles\n\n\n\n\n\n149 Members (1977)\n\n\n\nAdded: Djibouti, Viet Nam\n\n\n\n\n\n151 Members (1978)\n\n\n\nAdded: Dominica, Solomon Islands\n\n\n\n \n\n152 Members (1979)\n\n\n\nAdded: Saint Lucia\n\n\n\n\n\n154 Members (1980)\n\n\n\nAdded: Saint Vincent and the Grenadines, Zimbabwe\n\n\n\n\n\n157 Members (1981) \n\n\n\nAdded: Antigua and Barbuda, Belize, Vanuatu\n\n\n\n\n\n158 Members (1983)\n\n\n\nAdded: Saint Christopher and Nevis\n\n\n\n \n\n159 Members (1984)\n\n\n\nAdded: Brunei Darussalam\n\n\n\n\n\n159 Members (1990)*\n\n\n\nAdded: Liechtenstein, Namibia\n\t\t\t\t\t\t\t\t*On 22 May 1990, the People's Democratic Republic of Yemen (member since 1967) was united with the Yemen Arab Republic (member since 1947), forming the Republic of Yemen. 191 Members (2002)\n\n\n\nAdded: Switzerland, Timor-Leste\n\n\n\n\n\n192 Members (2006)\n\n\n\nAdded: Montenegro\n\n\n\n\n\n193 Members (2011)\n\n\n\nAdded: South Sudan\n\n\n\n\n\n\n\n\n\n\n\nMEMBER STATES\n\nMembership \n\nAbout UN Membership\nList of UN Member States\nUN Membership research guide\nGrowth in UN Membership\nMembership of Principal UN Organs\nContributions to UN regular budget\nHonour Roll: Contribution Received in Full\nArrears in the Payment of Contribution\n\n\nPermanent Missions\n\nNew York\nGeneva\nVienna\n\n\nPermanent Observers\n\nAbout Permanent Observers\nNon-Member States\nIntergovernmental and Other Organizations\nSpecialized Agencies \n\n\n\n \n\nQuick links for delegates\n\nDelegate (UN Intranet - iSeek for Member States)\nBlue Book\nDelegates' Handbook\nManual of Protocol\n\n1945-1950          1950s          1960s          1970s          1980s          1990s          2000-Present\n\n\n \n \n\n\n\nOriginal 51 Members (1945)\n\n\n\nArgentina, Australia, Belgium, Bolivia, Brazil, Byelorussian Soviet Socialist Republic, Canada, Chile, China, Colombia, Costa Rica, Cuba, Czechoslovakia, Denmark, Dominican Republic, Ecuador, Egypt, El Salvador, Ethiopia, France, Greece, Guatemala, Haiti, Honduras, India, Iran, Iraq, Lebanon, Liberia, Luxembourg, Mexico, Netherlands, New Zealand, Nicaragua, Norway, Panama, Paraguay, Peru, Philippine Republic, Poland, Saudi Arabia, Syria, Turkey, Ukrainian Soviet Socialist Republic, Union of South Africa, Union of Soviet Socialist Republics, United Kingdom, United States, Uruguay, Venezuela, Yugoslavia\n\n\n\n\n\n55 Members (1946)\n\n\n\nAdded: Afghanistan, Iceland, Siam, Sweden\n\n\n\n\n\n57 Members (1947)\n\n\n\nAdded: Pakistan, Yemen (the Yemen Arab Republic)\n\n\n\n\n\n58 Members (1948)\n\n\n\nAdded: Burma\n\n\n\n \n\n59 Members (1949)\n\n\n\nAdded: Israel\n\n\n\n\n\n60 Members (1950)\n\n\n\nAdded: Indonesia\n\n\n\n\n\n76 Members (1955)\n\n\n\nAdded: Albania, Austria, Bulgaria, Cambodia, Ceylon, Finland, Hungary, Ireland, Italy, Jordan, Laos, Libya, Nepal, Portugal, Romania, Spain\n\n\n\n\n\n80 Members (1956)\n\n\n\nAdded: Japan, Morocco, Sudan, Tunisia\n\n\n\n\n\n82 Members (1957)\n\n\n\nAdded: Ghana, Federation of Malaya\n\n\n\n \n\n82 Members (1958)*\n\n\n\nAdded: Guinea\n\t\t\t\t\t\t\t\t* On 22 February 1958, Syria merged with Egypt (both original members of the United Nations) to become the United Arab Republic. 123 Members (1967)\n\n\n\nAdded: Yemen (People's Democratic Republic of Yemen)\n\n\n\n \n\n126 Members (1968)\n\n\n\nAdded: Equatorial Guinea, Mauritius, Swaziland\n\n\n\n\n\n127 Members (1970)\n\n\n\nAdded: Fiji\n\n\n\n\n\n132 Members (1971)\n\n\n\nAdded: Bahrain, Bhutan, Oman, Qatar, United Arab Emirates\n\n\n\n\n\n135 Members (1973)\n\n\n\nAdded: Bahamas, Federal Republic of Germany, German Democratic Republic\n\n\n\n\n\n138 Members (1974)\n\n\n\nAdded: Bangladesh, Grenada, Guinea-Bissau\n\n\n\n\n\n144 Members (1975)\n\n\n\nAdded: Cape Verde, Comoros, Mozambique, Papua New Guinea, Sao Tome and Principe, Suriname\n\n\n\n\n\n147 Members (1976)\n\n\n\nAdded: Angola, Samoa, Seychelles\n\n\n\n\n\n149 Members (1977)\n\n\n\nAdded: Djibouti, Viet Nam\n\n\n\n\n\n151 Members (1978)\n\n\n\nAdded: Dominica, Solomon Islands\n\n\n\n \n\n152 Members (1979)\n\n\n\nAdded: Saint Lucia\n\n\n\n\n\n154 Members (1980)\n\n\n\nAdded: Saint Vincent and the Grenadines, Zimbabwe\n\n\n\n\n\n157 Members (1981) \n\n\n\nAdded: Antigua and Barbuda, Belize, Vanuatu\n\n\n\n\n\n158 Members (1983)\n\n\n\nAdded: Saint Christopher and Nevis\n\n\n\n \n\n159 Members (1984)\n\n\n\nAdded: Brunei Darussalam\n\n\n\n\n\n159 Members (1990)*\n\n\n\nAdded: Liechtenstein, Namibia\n\t\t\t\t\t\t\t\t*On 22 May 1990, the People's Democratic Republic of Yemen (member since 1967) was united with the Yemen Arab Republic (member since 1947), forming the Republic of Yemen. 191 Members (2002)\n\n\n\nAdded: Switzerland, Timor-Leste\n\n\n\n\n\n192 Members (2006)\n\n\n\nAdded: Montenegro\n\n\n\n\n\n193 Members (2011)\n\n\n\nAdded: South Sudan\n\n\n\n\n\n\n\n\n\n\n\nMEMBER STATES\n\nMembership \n\nAbout UN Membership\nList of UN Member States\nUN Membership research guide\nGrowth in UN Membership\nMembership of Principal UN Organs\nContributions to UN regular budget\nHonour Roll: Contribution Received in Full\nArrears in the Payment of Contribution\n\n\nPermanent Missions\n\nNew York\nGeneva\nVienna\n\n\nPermanent Observers\n\nAbout Permanent Observers\nNon-Member States\nIntergovernmental and Other Organizations\nSpecialized Agencies \n\n\n\n \n\nQuick links for delegates\n\nDelegate (UN Intranet - iSeek for Member States)\nBlue Book\nDelegates' Handbook\nManual of Protocol\n\n1945-1950          1950s          1960s          1970s          1980s          1990s          2000-Present\n\n\n \n \n\n\n\nOriginal 51 Members (1945)\n\n\n\nArgentina, Australia, Belgium, Bolivia, Brazil, Byelorussian Soviet Socialist Republic, Canada, Chile, China, Colombia, Costa Rica, Cuba, Czechoslovakia, Denmark, Dominican Republic, Ecuador, Egypt, El Salvador, Ethiopia, France, Greece, Guatemala, Haiti, Honduras, India, Iran, Iraq, Lebanon, Liberia, Luxembourg, Mexico, Netherlands, New Zealand, Nicaragua, Norway, Panama, Paraguay, Peru, Philippine Republic, Poland, Saudi Arabia, Syria, Turkey, Ukrainian Soviet Socialist Republic, Union of South Africa, Union of Soviet Socialist Republics, United Kingdom, United States, Uruguay, Venezuela, Yugoslavia\n\n\n\n\n\n55 Members (1946)\n\n\n\nAdded: Afghanistan, Iceland, Siam, Sweden\n\n\n\n\n\n57 Members (1947)\n\n\n\nAdded: Pakistan, Yemen (the Yemen Arab Republic)\n\n\n\n\n\n58 Members (1948)\n\n\n\nAdded: Burma\n\n\n\n \n\n59 Members (1949)\n\n\n\nAdded: Israel\n\n\n\n\n\n60 Members (1950)\n\n\n\nAdded: Indonesia\n\n\n\n\n\n76 Members (1955)\n\n\n\nAdded: Albania, Austria, Bulgaria, Cambodia, Ceylon, Finland, Hungary, Ireland, Italy, Jordan, Laos, Libya, Nepal, Portugal, Romania, Spain\n\n\n\n\n\n80 Members (1956)\n\n\n\nAdded: Japan, Morocco, Sudan, Tunisia\n\n\n\n\n\n82 Members (1957)\n\n\n\nAdded: Ghana, Federation of Malaya\n\n\n\n \n\n82 Members (1958)*\n\n\n\nAdded: Guinea\n\t\t\t\t\t\t\t\t* On 22 February 1958, Syria merged with Egypt (both original members of the United Nations) to become the United Arab Republic. 123 Members (1967)\n\n\n\nAdded: Yemen (People's Democratic Republic of Yemen)\n\n\n\n \n\n126 Members (1968)\n\n\n\nAdded: Equatorial Guinea, Mauritius, Swaziland\n\n\n\n\n\n127 Members (1970)\n\n\n\nAdded: Fiji\n\n\n\n\n\n132 Members (1971)\n\n\n\nAdded: Bahrain, Bhutan, Oman, Qatar, United Arab Emirates\n\n\n\n\n\n135 Members (1973)\n\n\n\nAdded: Bahamas, Federal Republic of Germany, German Democratic Republic\n\n\n\n\n\n138 Members (1974)\n\n\n\nAdded: Bangladesh, Grenada, Guinea-Bissau\n\n\n\n\n\n144 Members (1975)\n\n\n\nAdded: Cape Verde, Comoros, Mozambique, Papua New Guinea, Sao Tome and Principe, Suriname\n\n\n\n\n\n147 Members (1976)\n\n\n\nAdded: Angola, Samoa, Seychelles\n\n\n\n\n\n149 Members (1977)\n\n\n\nAdded: Djibouti, Viet Nam\n\n\n\n\n\n151 Members (1978)\n\n\n\nAdded: Dominica, Solomon Islands\n\n\n\n \n\n152 Members (1979)\n\n\n\nAdded: Saint Lucia\n\n\n\n\n\n154 Members (1980)\n\n\n\nAdded: Saint Vincent and the Grenadines, Zimbabwe\n\n\n\n\n\n157 Members (1981) \n\n\n\nAdded: Antigua and Barbuda, Belize, Vanuatu\n\n\n\n\n\n158 Members (1983)\n\n\n\nAdded: Saint Christopher and Nevis\n\n\n\n \n\n159 Members (1984)\n\n\n\nAdded: Brunei Darussalam\n\n\n\n\n\n159 Members (1990)*\n\n\n\nAdded: Liechtenstein, Namibia\n\t\t\t\t\t\t\t\t*On 22 May 1990, the People's Democratic Republic of Yemen (member since 1967) was united with the Yemen Arab Republic (member since 1947), forming the Republic of Yemen. 191 Members (2002)\n\n\n\nAdded: Switzerland, Timor-Leste\n\n\n\n\n\n192 Members (2006)\n\n\n\nAdded: Montenegro\n\n\n\n\n\n193 Members (2011)\n\n\n\nAdded: South Sudan\n\n\n\n\n\n\n\n\n\n\n\nMEMBER STATES\n\nMembership \n\nAbout UN Membership\nList of UN Member States\nUN Membership research guide\nGrowth in UN Membership\nMembership of Principal UN Organs\nContributions to UN regular budget\nHonour Roll: Contribution Received in Full\nArrears in the Payment of Contribution\n\n\nPermanent Missions\n\nNew York\nGeneva\nVienna\n\n\nPermanent Observers\n\nAbout Permanent Observers\nNon-Member States\nIntergovernmental and Other Organizations\nSpecialized Agencies \n\n\n\n \n\nQuick links for delegates\n\nDelegate (UN Intranet - iSeek for Member States)\nBlue Book\nDelegates' Handbook\nManual of Protocol\n\n1945-1950          1950s          1960s          1970s          1980s          1990s          2000-Present\n\n\n \n \n\n\n\nOriginal 51 Members (1945)\n\n\n\nArgentina, Australia, Belgium, Bolivia, Brazil, Byelorussian Soviet Socialist Republic, Canada, Chile, China, Colombia, Costa Rica, Cuba, Czechoslovakia, Denmark, Dominican Republic, Ecuador, Egypt, El Salvador, Ethiopia, France, Greece, Guatemala, Haiti, Honduras, India, Iran, Iraq, Lebanon, Liberia, Luxembourg, Mexico, Netherlands, New Zealand, Nicaragua, Norway, Panama, Paraguay, Peru, Philippine Republic, Poland, Saudi Arabia, Syria, Turkey, Ukrainian Soviet Socialist Republic, Union of South Africa, Union of Soviet Socialist Republics, United Kingdom, United States, Uruguay, Venezuela, Yugoslavia\n\n\n\n\n\n55 Members (1946)\n\n\n\nAdded: Afghanistan, Iceland, Siam, Sweden\n\n\n\n\n\n57 Members (1947)\n\n\n\nAdded: Pakistan, Yemen (the Yemen Arab Republic)\n\n\n\n\n\n58 Members (1948)\n\n\n\nAdded: Burma\n\n\n\n \n\n59 Members (1949)\n\n\n\nAdded: Israel\n\n\n\n\n\n60 Members (1950)\n\n\n\nAdded: Indonesia\n\n\n\n\n\n76 Members (1955)\n\n\n\nAdded: Albania, Austria, Bulgaria, Cambodia, Ceylon, Finland, Hungary, Ireland, Italy, Jordan, Laos, Libya, Nepal, Portugal, Romania, Spain\n\n\n\n\n\n80 Members (1956)\n\n\n\nAdded: Japan, Morocco, Sudan, Tunisia\n\n\n\n\n\n82 Members (1957)\n\n\n\nAdded: Ghana, Federation of Malaya\n\n\n\n \n\n82 Members (1958)*\n\n\n\nAdded: Guinea\n\t\t\t\t\t\t\t\t* On 22 February 1958, Syria merged with Egypt (both original members of the United Nations) to become the United Arab Republic. 123 Members (1967)\n\n\n\nAdded: Yemen (People's Democratic Republic of Yemen)\n\n\n\n \n\n126 Members (1968)\n\n\n\nAdded: Equatorial Guinea, Mauritius, Swaziland\n\n\n\n\n\n127 Members (1970)\n\n\n\nAdded: Fiji\n\n\n\n\n\n132 Members (1971)\n\n\n\nAdded: Bahrain, Bhutan, Oman, Qatar, United Arab Emirates\n\n\n\n\n\n135 Members (1973)\n\n\n\nAdded: Bahamas, Federal Republic of Germany, German Democratic Republic\n\n\n\n\n\n138 Members (1974)\n\n\n\nAdded: Bangladesh, Grenada, Guinea-Bissau\n\n\n\n\n\n144 Members (1975)\n\n\n\nAdded: Cape Verde, Comoros, Mozambique, Papua New Guinea, Sao Tome and Principe, Suriname\n\n\n\n\n\n147 Members (1976)\n\n\n\nAdded: Angola, Samoa, Seychelles\n\n\n\n\n\n149 Members (1977)\n\n\n\nAdded: Djibouti, Viet Nam\n\n\n\n\n\n151 Members (1978)\n\n\n\nAdded: Dominica, Solomon Islands\n\n\n\n \n\n152 Members (1979)\n\n\n\nAdded: Saint Lucia\n\n\n\n\n\n154 Members (1980)\n\n\n\nAdded: Saint Vincent and the Grenadines, Zimbabwe\n\n\n\n\n\n157 Members (1981) \n\n\n\nAdded: Antigua and Barbuda, Belize, Vanuatu\n\n\n\n\n\n158 Members (1983)\n\n\n\nAdded: Saint Christopher and Nevis\n\n\n\n \n\n159 Members (1984)\n\n\n\nAdded: Brunei Darussalam\n\n\n\n\n\n159 Members (1990)*\n\n\n\nAdded: Liechtenstein, Namibia\n\t\t\t\t\t\t\t\t*On 22 May 1990, the People's Democratic Republic of Yemen (member since 1967) was united with the Yemen Arab Republic (member since 1947), forming the Republic of Yemen. 191 Members (2002)\n\n\n\nAdded: Switzerland, Timor-Leste\n\n\n\n\n\n192 Members (2006)\n\n\n\nAdded: Montenegro\n\n\n\n\n\n193 Members (2011)\n\n\n\nAdded: South Sudan\n\n1945-1950          1950s          1960s          1970s          1980s          1990s          2000-Present\n\n\n \n \n\n\n\nOriginal 51 Members (1945)\n\n\n\nArgentina, Australia, Belgium, Bolivia, Brazil, Byelorussian Soviet Socialist Republic, Canada, Chile, China, Colombia, Costa Rica, Cuba, Czechoslovakia, Denmark, Dominican Republic, Ecuador, Egypt, El Salvador, Ethiopia, France, Greece, Guatemala, Haiti, Honduras, India, Iran, Iraq, Lebanon, Liberia, Luxembourg, Mexico, Netherlands, New Zealand, Nicaragua, Norway, Panama, Paraguay, Peru, Philippine Republic, Poland, Saudi Arabia, Syria, Turkey, Ukrainian Soviet Socialist Republic, Union of South Africa, Union of Soviet Socialist Republics, United Kingdom, United States, Uruguay, Venezuela, Yugoslavia\n\n\n\n\n\n55 Members (1946)\n\n\n\nAdded: Afghanistan, Iceland, Siam, Sweden\n\n\n\n\n\n57 Members (1947)\n\n\n\nAdded: Pakistan, Yemen (the Yemen Arab Republic)\n\n\n\n\n\n58 Members (1948)\n\n\n\nAdded: Burma\n\n\n\n \n\n59 Members (1949)\n\n\n\nAdded: Israel\n\n\n\n\n\n60 Members (1950)\n\n\n\nAdded: Indonesia\n\n\n\n\n\n76 Members (1955)\n\n\n\nAdded: Albania, Austria, Bulgaria, Cambodia, Ceylon, Finland, Hungary, Ireland, Italy, Jordan, Laos, Libya, Nepal, Portugal, Romania, Spain\n\n\n\n\n\n80 Members (1956)\n\n\n\nAdded: Japan, Morocco, Sudan, Tunisia\n\n\n\n\n\n82 Members (1957)\n\n\n\nAdded: Ghana, Federation of Malaya\n\n\n\n \n\n82 Members (1958)*\n\n\n\nAdded: Guinea\n\t\t\t\t\t\t\t\t* On 22 February 1958, Syria merged with Egypt (both original members of the United Nations) to become the United Arab Republic. 123 Members (1967)\n\n\n\nAdded: Yemen (People's Democratic Republic of Yemen)\n\n\n\n \n\n126 Members (1968)\n\n\n\nAdded: Equatorial Guinea, Mauritius, Swaziland\n\n\n\n\n\n127 Members (1970)\n\n\n\nAdded: Fiji\n\n\n\n\n\n132 Members (1971)\n\n\n\nAdded: Bahrain, Bhutan, Oman, Qatar, United Arab Emirates\n\n\n\n\n\n135 Members (1973)\n\n\n\nAdded: Bahamas, Federal Republic of Germany, German Democratic Republic\n\n\n\n\n\n138 Members (1974)\n\n\n\nAdded: Bangladesh, Grenada, Guinea-Bissau\n\n\n\n\n\n144 Members (1975)\n\n\n\nAdded: Cape Verde, Comoros, Mozambique, Papua New Guinea, Sao Tome and Principe, Suriname\n\n\n\n\n\n147 Members (1976)\n\n\n\nAdded: Angola, Samoa, Seychelles\n\n\n\n\n\n149 Members (1977)\n\n\n\nAdded: Djibouti, Viet Nam\n\n\n\n\n\n151 Members (1978)\n\n\n\nAdded: Dominica, Solomon Islands\n\n\n\n \n\n152 Members (1979)\n\n\n\nAdded: Saint Lucia\n\n\n\n\n\n154 Members (1980)\n\n\n\nAdded: Saint Vincent and the Grenadines, Zimbabwe\n\n\n\n\n\n157 Members (1981) \n\n\n\nAdded: Antigua and Barbuda, Belize, Vanuatu\n\n\n\n\n\n158 Members (1983)\n\n\n\nAdded: Saint Christopher and Nevis\n\n\n\n \n\n159 Members (1984)\n\n\n\nAdded: Brunei Darussalam\n\n\n\n\n\n159 Members (1990)*\n\n\n\nAdded: Liechtenstein, Namibia\n\t\t\t\t\t\t\t\t*On 22 May 1990, the People's Democratic Republic of Yemen (member since 1967) was united with the Yemen Arab Republic (member since 1947), forming the Republic of Yemen. 191 Members (2002)\n\n\n\nAdded: Switzerland, Timor-Leste\n\n\n\n\n\n192 Members (2006)\n\n\n\nAdded: Montenegro\n\n\n\n\n\n193 Members (2011)\n\n\n\nAdded: South Sudan\n\n1945-1950          1950s          1960s          1970s          1980s          1990s          2000-Present\n\n\n \n \n\n\n\nOriginal 51 Members (1945)\n\n\n\nArgentina, Australia, Belgium, Bolivia, Brazil, Byelorussian Soviet Socialist Republic, Canada, Chile, China, Colombia, Costa Rica, Cuba, Czechoslovakia, Denmark, Dominican Republic, Ecuador, Egypt, El Salvador, Ethiopia, France, Greece, Guatemala, Haiti, Honduras, India, Iran, Iraq, Lebanon, Liberia, Luxembourg, Mexico, Netherlands, New Zealand, Nicaragua, Norway, Panama, Paraguay, Peru, Philippine Republic, Poland, Saudi Arabia, Syria, Turkey, Ukrainian Soviet Socialist Republic, Union of South Africa, Union of Soviet Socialist Republics, United Kingdom, United States, Uruguay, Venezuela, Yugoslavia\n\n\n\n\n\n55 Members (1946)\n\n\n\nAdded: Afghanistan, Iceland, Siam, Sweden\n\n\n\n\n\n57 Members (1947)\n\n\n\nAdded: Pakistan, Yemen (the Yemen Arab Republic)\n\n\n\n\n\n58 Members (1948)\n\n\n\nAdded: Burma\n\n\n\n \n\n59 Members (1949)\n\n\n\nAdded: Israel\n\n\n\n\n\n60 Members (1950)\n\n\n\nAdded: Indonesia\n\n\n\n\n\n76 Members (1955)\n\n\n\nAdded: Albania, Austria, Bulgaria, Cambodia, Ceylon, Finland, Hungary, Ireland, Italy, Jordan, Laos, Libya, Nepal, Portugal, Romania, Spain\n\n\n\n\n\n80 Members (1956)\n\n\n\nAdded: Japan, Morocco, Sudan, Tunisia\n\n\n\n\n\n82 Members (1957)\n\n\n\nAdded: Ghana, Federation of Malaya\n\n\n\n \n\n82 Members (1958)*\n\n\n\nAdded: Guinea\n\t\t\t\t\t\t\t\t* On 22 February 1958, Syria merged with Egypt (both original members of the United Nations) to become the United Arab Republic. 123 Members (1967)\n\n\n\nAdded: Yemen (People's Democratic Republic of Yemen)\n\n\n\n \n\n126 Members (1968)\n\n\n\nAdded: Equatorial Guinea, Mauritius, Swaziland\n\n\n\n\n\n127 Members (1970)\n\n\n\nAdded: Fiji\n\n\n\n\n\n132 Members (1971)\n\n\n\nAdded: Bahrain, Bhutan, Oman, Qatar, United Arab Emirates\n\n\n\n\n\n135 Members (1973)\n\n\n\nAdded: Bahamas, Federal Republic of Germany, German Democratic Republic\n\n\n\n\n\n138 Members (1974)\n\n\n\nAdded: Bangladesh, Grenada, Guinea-Bissau\n\n\n\n\n\n144 Members (1975)\n\n\n\nAdded: Cape Verde, Comoros, Mozambique, Papua New Guinea, Sao Tome and Principe, Suriname\n\n\n\n\n\n147 Members (1976)\n\n\n\nAdded: Angola, Samoa, Seychelles\n\n\n\n\n\n149 Members (1977)\n\n\n\nAdded: Djibouti, Viet Nam\n\n\n\n\n\n151 Members (1978)\n\n\n\nAdded: Dominica, Solomon Islands\n\n\n\n \n\n152 Members (1979)\n\n\n\nAdded: Saint Lucia\n\n\n\n\n\n154 Members (1980)\n\n\n\nAdded: Saint Vincent and the Grenadines, Zimbabwe\n\n\n\n\n\n157 Members (1981) \n\n\n\nAdded: Antigua and Barbuda, Belize, Vanuatu\n\n\n\n\n\n158 Members (1983)\n\n\n\nAdded: Saint Christopher and Nevis\n\n\n\n \n\n159 Members (1984)\n\n\n\nAdded: Brunei Darussalam\n\n\n\n\n\n159 Members (1990)*\n\n\n\nAdded: Liechtenstein, Namibia\n\t\t\t\t\t\t\t\t*On 22 May 1990, the People's Democratic Republic of Yemen (member since 1967) was united with the Yemen Arab Republic (member since 1947), forming the Republic of Yemen. 191 Members (2002)\n\n\n\nAdded: Switzerland, Timor-Leste\n\n\n\n\n\n192 Members (2006)\n\n\n\nAdded: Montenegro\n\n\n\n\n\n193 Members (2011)\n\n\n\nAdded: South Sudan\n\n1945-1950          1950s          1960s          1970s          1980s          1990s          2000-Present\n\n\n \n \n\n\n\nOriginal 51 Members (1945)\n\n\n\nArgentina, Australia, Belgium, Bolivia, Brazil, Byelorussian Soviet Socialist Republic, Canada, Chile, China, Colombia, Costa Rica, Cuba, Czechoslovakia, Denmark, Dominican Republic, Ecuador, Egypt, El Salvador, Ethiopia, France, Greece, Guatemala, Haiti, Honduras, India, Iran, Iraq, Lebanon, Liberia, Luxembourg, Mexico, Netherlands, New Zealand, Nicaragua, Norway, Panama, Paraguay, Peru, Philippine Republic, Poland, Saudi Arabia, Syria, Turkey, Ukrainian Soviet Socialist Republic, Union of South Africa, Union of Soviet Socialist Republics, United Kingdom, United States, Uruguay, Venezuela, Yugoslavia\n\n\n\n\n\n55 Members (1946)\n\n\n\nAdded: Afghanistan, Iceland, Siam, Sweden\n\n\n\n\n\n57 Members (1947)\n\n\n\nAdded: Pakistan, Yemen (the Yemen Arab Republic)\n\n\n\n\n\n58 Members (1948)\n\n\n\nAdded: Burma\n\n\n\n \n\n59 Members (1949)\n\n\n\nAdded: Israel\n\n\n\n\n\n60 Members (1950)\n\n\n\nAdded: Indonesia\n\n\n\n\n\n76 Members (1955)\n\n\n\nAdded: Albania, Austria, Bulgaria, Cambodia, Ceylon, Finland, Hungary, Ireland, Italy, Jordan, Laos, Libya, Nepal, Portugal, Romania, Spain\n\n\n\n\n\n80 Members (1956)\n\n\n\nAdded: Japan, Morocco, Sudan, Tunisia\n\n\n\n\n\n82 Members (1957)\n\n\n\nAdded: Ghana, Federation of Malaya\n\n\n\n \n\n82 Members (1958)*\n\n\n\nAdded: Guinea\n\t\t\t\t\t\t\t\t* On 22 February 1958, Syria merged with Egypt (both original members of the United Nations) to become the United Arab Republic. 123 Members (1967)\n\n\n\nAdded: Yemen (People's Democratic Republic of Yemen)\n\n\n\n \n\n126 Members (1968)\n\n\n\nAdded: Equatorial Guinea, Mauritius, Swaziland\n\n\n\n\n\n127 Members (1970)\n\n\n\nAdded: Fiji\n\n\n\n\n\n132 Members (1971)\n\n\n\nAdded: Bahrain, Bhutan, Oman, Qatar, United Arab Emirates\n\n\n\n\n\n135 Members (1973)\n\n\n\nAdded: Bahamas, Federal Republic of Germany, German Democratic Republic\n\n\n\n\n\n138 Members (1974)\n\n\n\nAdded: Bangladesh, Grenada, Guinea-Bissau\n\n\n\n\n\n144 Members (1975)\n\n\n\nAdded: Cape Verde, Comoros, Mozambique, Papua New Guinea, Sao Tome and Principe, Suriname\n\n\n\n\n\n147 Members (1976)\n\n\n\nAdded: Angola, Samoa, Seychelles\n\n\n\n\n\n149 Members (1977)\n\n\n\nAdded: Djibouti, Viet Nam\n\n\n\n\n\n151 Members (1978)\n\n\n\nAdded: Dominica, Solomon Islands\n\n\n\n \n\n152 Members (1979)\n\n\n\nAdded: Saint Lucia\n\n\n\n\n\n154 Members (1980)\n\n\n\nAdded: Saint Vincent and the Grenadines, Zimbabwe\n\n\n\n\n\n157 Members (1981) \n\n\n\nAdded: Antigua and Barbuda, Belize, Vanuatu\n\n\n\n\n\n158 Members (1983)\n\n\n\nAdded: Saint Christopher and Nevis\n\n\n\n \n\n159 Members (1984)\n\n\n\nAdded: Brunei Darussalam\n\n\n\n\n\n159 Members (1990)*\n\n\n\nAdded: Liechtenstein, Namibia\n\t\t\t\t\t\t\t\t*On 22 May 1990, the People's Democratic Republic of Yemen (member since 1967) was united with the Yemen Arab Republic (member since 1947), forming the Republic of Yemen. 191 Members (2002)\n\n\n\nAdded: Switzerland, Timor-Leste\n\n\n\n\n\n192 Members (2006)\n\n\n\nAdded: Montenegro\n\n\n\n\n\n193 Members (2011)\n\n\n\nAdded: South Sudan\n\n1945-1950          1950s          1960s          1970s          1980s          1990s          2000-Present\n\n\n \n \n\n\n\nOriginal 51 Members (1945)\n\n\n\nArgentina, Australia, Belgium, Bolivia, Brazil, Byelorussian Soviet Socialist Republic, Canada, Chile, China, Colombia, Costa Rica, Cuba, Czechoslovakia, Denmark, Dominican Republic, Ecuador, Egypt, El Salvador, Ethiopia, France, Greece, Guatemala, Haiti, Honduras, India, Iran, Iraq, Lebanon, Liberia, Luxembourg, Mexico, Netherlands, New Zealand, Nicaragua, Norway, Panama, Paraguay, Peru, Philippine Republic, Poland, Saudi Arabia, Syria, Turkey, Ukrainian Soviet Socialist Republic, Union of South Africa, Union of Soviet Socialist Republics, United Kingdom, United States, Uruguay, Venezuela, Yugoslavia\n\n\n\n\n\n55 Members (1946)\n\n\n\nAdded: Afghanistan, Iceland, Siam, Sweden\n\n\n\n\n\n57 Members (1947)\n\n\n\nAdded: Pakistan, Yemen (the Yemen Arab Republic)\n\n\n\n\n\n58 Members (1948)\n\n\n\nAdded: Burma\n\n\n\n \n\n59 Members (1949)\n\n\n\nAdded: Israel\n\n\n\n\n\n60 Members (1950)\n\n\n\nAdded: Indonesia\n\n\n\n\n\n76 Members (1955)\n\n\n\nAdded: Albania, Austria, Bulgaria, Cambodia, Ceylon, Finland, Hungary, Ireland, Italy, Jordan, Laos, Libya, Nepal, Portugal, Romania, Spain\n\n\n\n\n\n80 Members (1956)\n\n\n\nAdded: Japan, Morocco, Sudan, Tunisia\n\n\n\n\n\n82 Members (1957)\n\n\n\nAdded: Ghana, Federation of Malaya\n\n\n\n \n\n82 Members (1958)*\n\n\n\nAdded: Guinea\n\t\t\t\t\t\t\t\t* On 22 February 1958, Syria merged with Egypt (both original members of the United Nations) to become the United Arab Republic. 123 Members (1967)\n\n\n\nAdded: Yemen (People's Democratic Republic of Yemen)\n\n\n\n \n\n126 Members (1968)\n\n\n\nAdded: Equatorial Guinea, Mauritius, Swaziland\n\n\n\n\n\n127 Members (1970)\n\n\n\nAdded: Fiji\n\n\n\n\n\n132 Members (1971)\n\n\n\nAdded: Bahrain, Bhutan, Oman, Qatar, United Arab Emirates\n\n\n\n\n\n135 Members (1973)\n\n\n\nAdded: Bahamas, Federal Republic of Germany, German Democratic Republic\n\n\n\n\n\n138 Members (1974)\n\n\n\nAdded: Bangladesh, Grenada, Guinea-Bissau\n\n\n\n\n\n144 Members (1975)\n\n\n\nAdded: Cape Verde, Comoros, Mozambique, Papua New Guinea, Sao Tome and Principe, Suriname\n\n\n\n\n\n147 Members (1976)\n\n\n\nAdded: Angola, Samoa, Seychelles\n\n\n\n\n\n149 Members (1977)\n\n\n\nAdded: Djibouti, Viet Nam\n\n\n\n\n\n151 Members (1978)\n\n\n\nAdded: Dominica, Solomon Islands\n\n\n\n \n\n152 Members (1979)\n\n\n\nAdded: Saint Lucia\n\n\n\n\n\n154 Members (1980)\n\n\n\nAdded: Saint Vincent and the Grenadines, Zimbabwe\n\n\n\n\n\n157 Members (1981) \n\n\n\nAdded: Antigua and Barbuda, Belize, Vanuatu\n\n\n\n\n\n158 Members (1983)\n\n\n\nAdded: Saint Christopher and Nevis\n\n\n\n \n\n159 Members (1984)\n\n\n\nAdded: Brunei Darussalam\n\n\n\n\n\n159 Members (1990)*\n\n\n\nAdded: Liechtenstein, Namibia\n\t\t\t\t\t\t\t\t*On 22 May 1990, the People's Democratic Republic of Yemen (member since 1967) was united with the Yemen Arab Republic (member since 1947), forming the Republic of Yemen. 191 Members (2002)\n\n\n\nAdded: Switzerland, Timor-Leste\n\n\n\n\n\n192 Members (2006)\n\n\n\nAdded: Montenegro\n\n\n\n\n\n193 Members (2011)\n\n\n\nAdded: South Sudan\n\n1945-1950          1950s          1960s          1970s          1980s          1990s          2000-Present\n\n\n \n \n\n\n\nOriginal 51 Members (1945)\n\n\n\nArgentina, Australia, Belgium, Bolivia, Brazil, Byelorussian Soviet Socialist Republic, Canada, Chile, China, Colombia, Costa Rica, Cuba, Czechoslovakia, Denmark, Dominican Republic, Ecuador, Egypt, El Salvador, Ethiopia, France, Greece, Guatemala, Haiti, Honduras, India, Iran, Iraq, Lebanon, Liberia, Luxembourg, Mexico, Netherlands, New Zealand, Nicaragua, Norway, Panama, Paraguay, Peru, Philippine Republic, Poland, Saudi Arabia, Syria, Turkey, Ukrainian Soviet Socialist Republic, Union of South Africa, Union of Soviet Socialist Republics, United Kingdom, United States, Uruguay, Venezuela, Yugoslavia\n\n\n\n\n\n55 Members (1946)\n\n\n\nAdded: Afghanistan, Iceland, Siam, Sweden\n\n\n\n\n\n57 Members (1947)\n\n\n\nAdded: Pakistan, Yemen (the Yemen Arab Republic)\n\n\n\n\n\n58 Members (1948)\n\n\n\nAdded: Burma\n\n\n\n \n\n59 Members (1949)\n\n\n\nAdded: Israel\n\n\n\n\n\n60 Members (1950)\n\n\n\nAdded: Indonesia\n\n\n\n\n\n76 Members (1955)\n\n\n\nAdded: Albania, Austria, Bulgaria, Cambodia, Ceylon, Finland, Hungary, Ireland, Italy, Jordan, Laos, Libya, Nepal, Portugal, Romania, Spain\n\n\n\n\n\n80 Members (1956)\n\n\n\nAdded: Japan, Morocco, Sudan, Tunisia\n\n\n\n\n\n82 Members (1957)\n\n\n\nAdded: Ghana, Federation of Malaya\n\n\n\n \n\n82 Members (1958)*\n\n\n\nAdded: Guinea\n\t\t\t\t\t\t\t\t* On 22 February 1958, Syria merged with Egypt (both original members of the United Nations) to become the United Arab Republic. 123 Members (1967)\n\n\n\nAdded: Yemen (People's Democratic Republic of Yemen)\n\n\n\n \n\n126 Members (1968)\n\n\n\nAdded: Equatorial Guinea, Mauritius, Swaziland\n\n\n\n\n\n127 Members (1970)\n\n\n\nAdded: Fiji\n\n\n\n\n\n132 Members (1971)\n\n\n\nAdded: Bahrain, Bhutan, Oman, Qatar, United Arab Emirates\n\n\n\n\n\n135 Members (1973)\n\n\n\nAdded: Bahamas, Federal Republic of Germany, German Democratic Republic\n\n\n\n\n\n138 Members (1974)\n\n\n\nAdded: Bangladesh, Grenada, Guinea-Bissau\n\n\n\n\n\n144 Members (1975)\n\n\n\nAdded: Cape Verde, Comoros, Mozambique, Papua New Guinea, Sao Tome and Principe, Suriname\n\n\n\n\n\n147 Members (1976)\n\n\n\nAdded: Angola, Samoa, Seychelles\n\n\n\n\n\n149 Members (1977)\n\n\n\nAdded: Djibouti, Viet Nam\n\n\n\n\n\n151 Members (1978)\n\n\n\nAdded: Dominica, Solomon Islands\n\n\n\n \n\n152 Members (1979)\n\n\n\nAdded: Saint Lucia\n\n\n\n\n\n154 Members (1980)\n\n\n\nAdded: Saint Vincent and the Grenadines, Zimbabwe\n\n\n\n\n\n157 Members (1981) \n\n\n\nAdded: Antigua and Barbuda, Belize, Vanuatu\n\n\n\n\n\n158 Members (1983)\n\n\n\nAdded: Saint Christopher and Nevis\n\n\n\n \n\n159 Members (1984)\n\n\n\nAdded: Brunei Darussalam\n\n\n\n\n\n159 Members (1990)*\n\n\n\nAdded: Liechtenstein, Namibia\n\t\t\t\t\t\t\t\t*On 22 May 1990, the People's Democratic Republic of Yemen (member since 1967) was united with the Yemen Arab Republic (member since 1947), forming the Republic of Yemen. 191 Members (2002)\n\n\n\nAdded: Switzerland, Timor-Leste\n\n\n\n\n\n192 Members (2006)\n\n\n\nAdded: Montenegro\n\n\n\n\n\n193 Members (2011)\n\n\n\nAdded: South Sudan\n\n1945-1950          1950s          1960s          1970s          1980s          1990s          2000-Present\n\n\n \n \n\n\n\nOriginal 51 Members (1945)\n\n\n\nArgentina, Australia, Belgium, Bolivia, Brazil, Byelorussian Soviet Socialist Republic, Canada, Chile, China, Colombia, Costa Rica, Cuba, Czechoslovakia, Denmark, Dominican Republic, Ecuador, Egypt, El Salvador, Ethiopia, France, Greece, Guatemala, Haiti, Honduras, India, Iran, Iraq, Lebanon, Liberia, Luxembourg, Mexico, Netherlands, New Zealand, Nicaragua, Norway, Panama, Paraguay, Peru, Philippine Republic, Poland, Saudi Arabia, Syria, Turkey, Ukrainian Soviet Socialist Republic, Union of South Africa, Union of Soviet Socialist Republics, United Kingdom, United States, Uruguay, Venezuela, Yugoslavia\n\n\n\n\n\n55 Members (1946)\n\n\n\nAdded: Afghanistan, Iceland, Siam, Sweden\n\n\n\n\n\n57 Members (1947)\n\n\n\nAdded: Pakistan, Yemen (the Yemen Arab Republic)\n\n\n\n\n\n58 Members (1948)\n\n\n\nAdded: Burma\n\n\n\n \n\n59 Members (1949)\n\n\n\nAdded: Israel\n\n\n\n\n\n60 Members (1950)\n\n\n\nAdded: Indonesia\n\n\n\n\n\n76 Members (1955)\n\n\n\nAdded: Albania, Austria, Bulgaria, Cambodia, Ceylon, Finland, Hungary, Ireland, Italy, Jordan, Laos, Libya, Nepal, Portugal, Romania, Spain\n\n\n\n\n\n80 Members (1956)\n\n\n\nAdded: Japan, Morocco, Sudan, Tunisia\n\n\n\n\n\n82 Members (1957)\n\n\n\nAdded: Ghana, Federation of Malaya\n\n\n\n \n\n82 Members (1958)*\n\n\n\nAdded: Guinea\n\t\t\t\t\t\t\t\t* On 22 February 1958, Syria merged with Egypt (both original members of the United Nations) to become the United Arab Republic. 123 Members (1967)\n\n\n\nAdded: Yemen (People's Democratic Republic of Yemen)\n\n\n\n \n\n126 Members (1968)\n\n\n\nAdded: Equatorial Guinea, Mauritius, Swaziland\n\n\n\n\n\n127 Members (1970)\n\n\n\nAdded: Fiji\n\n\n\n\n\n132 Members (1971)\n\n\n\nAdded: Bahrain, Bhutan, Oman, Qatar, United Arab Emirates\n\n\n\n\n\n135 Members (1973)\n\n\n\nAdded: Bahamas, Federal Republic of Germany, German Democratic Republic\n\n\n\n\n\n138 Members (1974)\n\n\n\nAdded: Bangladesh, Grenada, Guinea-Bissau\n\n\n\n\n\n144 Members (1975)\n\n\n\nAdded: Cape Verde, Comoros, Mozambique, Papua New Guinea, Sao Tome and Principe, Suriname\n\n\n\n\n\n147 Members (1976)\n\n\n\nAdded: Angola, Samoa, Seychelles\n\n\n\n\n\n149 Members (1977)\n\n\n\nAdded: Djibouti, Viet Nam\n\n\n\n\n\n151 Members (1978)\n\n\n\nAdded: Dominica, Solomon Islands\n\n\n\n \n\n152 Members (1979)\n\n\n\nAdded: Saint Lucia\n\n\n\n\n\n154 Members (1980)\n\n\n\nAdded: Saint Vincent and the Grenadines, Zimbabwe\n\n\n\n\n\n157 Members (1981) \n\n\n\nAdded: Antigua and Barbuda, Belize, Vanuatu\n\n\n\n\n\n158 Members (1983)\n\n\n\nAdded: Saint Christopher and Nevis\n\n\n\n \n\n159 Members (1984)\n\n\n\nAdded: Brunei Darussalam\n\n\n\n\n\n159 Members (1990)*\n\n\n\nAdded: Liechtenstein, Namibia\n\t\t\t\t\t\t\t\t*On 22 May 1990, the People's Democratic Republic of Yemen (member since 1967) was united with the Yemen Arab Republic (member since 1947), forming the Republic of Yemen. 191 Members (2002)\n\n\n\nAdded: Switzerland, Timor-Leste\n\n\n\n\n\n192 Members (2006)\n\n\n\nAdded: Montenegro\n\n\n\n\n\n193 Members (2011)\n\n\n\nAdded: South Sudan\n\n1945-1950          1950s          1960s          1970s          1980s          1990s          2000-Present\n\n1945-1950          1950s          1960s          1970s          1980s          1990s          2000-Present\n\n1945-1950          1950s          1960s          1970s          1980s          1990s          2000-Present\n\nOriginal 51 Members (1945)\n\n\n\nArgentina, Australia, Belgium, Bolivia, Brazil, Byelorussian Soviet Socialist Republic, Canada, Chile, China, Colombia, Costa Rica, Cuba, Czechoslovakia, Denmark, Dominican Republic, Ecuador, Egypt, El Salvador, Ethiopia, France, Greece, Guatemala, Haiti, Honduras, India, Iran, Iraq, Lebanon, Liberia, Luxembourg, Mexico, Netherlands, New Zealand, Nicaragua, Norway, Panama, Paraguay, Peru, Philippine Republic, Poland, Saudi Arabia, Syria, Turkey, Ukrainian Soviet Socialist Republic, Union of South Africa, Union of Soviet Socialist Republics, United Kingdom, United States, Uruguay, Venezuela, Yugoslavia\n\n\n\n\n\n55 Members (1946)\n\n\n\nAdded: Afghanistan, Iceland, Siam, Sweden\n\n\n\n\n\n57 Members (1947)\n\n\n\nAdded: Pakistan, Yemen (the Yemen Arab Republic)\n\n\n\n\n\n58 Members (1948)\n\n\n\nAdded: Burma\n\n\n\n \n\n59 Members (1949)\n\n\n\nAdded: Israel\n\n\n\n\n\n60 Members (1950)\n\n\n\nAdded: Indonesia\n\n\n\n\n\n76 Members (1955)\n\n\n\nAdded: Albania, Austria, Bulgaria, Cambodia, Ceylon, Finland, Hungary, Ireland, Italy, Jordan, Laos, Libya, Nepal, Portugal, Romania, Spain\n\n\n\n\n\n80 Members (1956)\n\n\n\nAdded: Japan, Morocco, Sudan, Tunisia\n\n\n\n\n\n82 Members (1957)\n\n\n\nAdded: Ghana, Federation of Malaya\n\n\n\n \n\n82 Members (1958)*\n\n\n\nAdded: Guinea\n\t\t\t\t\t\t\t\t* On 22 February 1958, Syria merged with Egypt (both original members of the United Nations) to become the United Arab Republic. 123 Members (1967)\n\n\n\nAdded: Yemen (People's Democratic Republic of Yemen)\n\n\n\n \n\n126 Members (1968)\n\n\n\nAdded: Equatorial Guinea, Mauritius, Swaziland\n\n\n\n\n\n127 Members (1970)\n\n\n\nAdded: Fiji\n\n\n\n\n\n132 Members (1971)\n\n\n\nAdded: Bahrain, Bhutan, Oman, Qatar, United Arab Emirates\n\n\n\n\n\n135 Members (1973)\n\n\n\nAdded: Bahamas, Federal Republic of Germany, German Democratic Republic\n\n\n\n\n\n138 Members (1974)\n\n\n\nAdded: Bangladesh, Grenada, Guinea-Bissau\n\n\n\n\n\n144 Members (1975)\n\n\n\nAdded: Cape Verde, Comoros, Mozambique, Papua New Guinea, Sao Tome and Principe, Suriname\n\n\n\n\n\n147 Members (1976)\n\n\n\nAdded: Angola, Samoa, Seychelles\n\n\n\n\n\n149 Members (1977)\n\n\n\nAdded: Djibouti, Viet Nam\n\n\n\n\n\n151 Members (1978)\n\n\n\nAdded: Dominica, Solomon Islands\n\n\n\n \n\n152 Members (1979)\n\n\n\nAdded: Saint Lucia\n\n\n\n\n\n154 Members (1980)\n\n\n\nAdded: Saint Vincent and the Grenadines, Zimbabwe\n\n\n\n\n\n157 Members (1981) \n\n\n\nAdded: Antigua and Barbuda, Belize, Vanuatu\n\n\n\n\n\n158 Members (1983)\n\n\n\nAdded: Saint Christopher and Nevis\n\n\n\n \n\n159 Members (1984)\n\n\n\nAdded: Brunei Darussalam\n\n\n\n\n\n159 Members (1990)*\n\n\n\nAdded: Liechtenstein, Namibia\n\t\t\t\t\t\t\t\t*On 22 May 1990, the People's Democratic Republic of Yemen (member since 1967) was united with the Yemen Arab Republic (member since 1947), forming the Republic of Yemen. 191 Members (2002)\n\n\n\nAdded: Switzerland, Timor-Leste\n\n\n\n\n\n192 Members (2006)\n\n\n\nAdded: Montenegro\n\n\n\n\n\n193 Members (2011)\n\n\n\nAdded: South Sudan\n\nOriginal 51 Members (1945)\n\n\n\nArgentina, Australia, Belgium, Bolivia, Brazil, Byelorussian Soviet Socialist Republic, Canada, Chile, China, Colombia, Costa Rica, Cuba, Czechoslovakia, Denmark, Dominican Republic, Ecuador, Egypt, El Salvador, Ethiopia, France, Greece, Guatemala, Haiti, Honduras, India, Iran, Iraq, Lebanon, Liberia, Luxembourg, Mexico, Netherlands, New Zealand, Nicaragua, Norway, Panama, Paraguay, Peru, Philippine Republic, Poland, Saudi Arabia, Syria, Turkey, Ukrainian Soviet Socialist Republic, Union of South Africa, Union of Soviet Socialist Republics, United Kingdom, United States, Uruguay, Venezuela, Yugoslavia\n\nOriginal 51 Members (1945)\n\nArgentina, Australia, Belgium, Bolivia, Brazil, Byelorussian Soviet Socialist Republic, Canada, Chile, China, Colombia, Costa Rica, Cuba, Czechoslovakia, Denmark, Dominican Republic, Ecuador, Egypt, El Salvador, Ethiopia, France, Greece, Guatemala, Haiti, Honduras, India, Iran, Iraq, Lebanon, Liberia, Luxembourg, Mexico, Netherlands, New Zealand, Nicaragua, Norway, Panama, Paraguay, Peru, Philippine Republic, Poland, Saudi Arabia, Syria, Turkey, Ukrainian Soviet Socialist Republic, Union of South Africa, Union of Soviet Socialist Republics, United Kingdom, United States, Uruguay, Venezuela, Yugoslavia\n\nArgentina, Australia, Belgium, Bolivia, Brazil, Byelorussian Soviet Socialist Republic, Canada, Chile, China, Colombia, Costa Rica, Cuba, Czechoslovakia, Denmark, Dominican Republic, Ecuador, Egypt, El Salvador, Ethiopia, France, Greece, Guatemala, Haiti, Honduras, India, Iran, Iraq, Lebanon, Liberia, Luxembourg, Mexico, Netherlands, New Zealand, Nicaragua, Norway, Panama, Paraguay, Peru, Philippine Republic, Poland, Saudi Arabia, Syria, Turkey, Ukrainian Soviet Socialist Republic, Union of South Africa, Union of Soviet Socialist Republics, United Kingdom, United States, Uruguay, Venezuela, Yugoslavia\n\nArgentina, Australia, Belgium, Bolivia, Brazil, Byelorussian Soviet Socialist Republic, Canada, Chile, China, Colombia, Costa Rica, Cuba, Czechoslovakia, Denmark, Dominican Republic, Ecuador, Egypt, El Salvador, Ethiopia, France, Greece, Guatemala, Haiti, Honduras, India, Iran, Iraq, Lebanon, Liberia, Luxembourg, Mexico, Netherlands, New Zealand, Nicaragua, Norway, Panama, Paraguay, Peru, Philippine Republic, Poland, Saudi Arabia, Syria, Turkey, Ukrainian Soviet Socialist Republic, Union of South Africa, Union of Soviet Socialist Republics, United Kingdom, United States, Uruguay, Venezuela, Yugoslavia\n\n55 Members (1946)\n\n\n\nAdded: Afghanistan, Iceland, Siam, Sweden\n\n55 Members (1946)\n\nAdded: Afghanistan, Iceland, Siam, Sweden\n\nAdded: Afghanistan, Iceland, Siam, Sweden\n\nAdded: Afghanistan, Iceland, Siam, Sweden\n\n57 Members (1947)\n\n\n\nAdded: Pakistan, Yemen (the Yemen Arab Republic)\n\n57 Members (1947)\n\nAdded: Pakistan, Yemen (the Yemen Arab Republic)\n\nAdded: Pakistan, Yemen (the Yemen Arab Republic)\n\nAdded: Pakistan, Yemen (the Yemen Arab Republic)\n\n58 Members (1948)\n\n\n\nAdded: Burma\n\n58 Members (1948)\n\nAdded: Burma\n\nAdded: Burma\n\nAdded: Burma\n\n59 Members (1949)\n\n\n\nAdded: Israel\n\n59 Members (1949)\n\nAdded: Israel\n\nAdded: Israel\n\nAdded: Israel\n\n60 Members (1950)\n\n\n\nAdded: Indonesia\n\n60 Members (1950)\n\nAdded: Indonesia\n\nAdded: Indonesia\n\nAdded: Indonesia\n\n76 Members (1955)\n\n\n\nAdded: Albania, Austria, Bulgaria, Cambodia, Ceylon, Finland, Hungary, Ireland, Italy, Jordan, Laos, Libya, Nepal, Portugal, Romania, Spain\n\n76 Members (1955)\n\nAdded: Albania, Austria, Bulgaria, Cambodia, Ceylon, Finland, Hungary, Ireland, Italy, Jordan, Laos, Libya, Nepal, Portugal, Romania, Spain\n\nAdded: Albania, Austria, Bulgaria, Cambodia, Ceylon, Finland, Hungary, Ireland, Italy, Jordan, Laos, Libya, Nepal, Portugal, Romania, Spain\n\nAdded: Albania, Austria, Bulgaria, Cambodia, Ceylon, Finland, Hungary, Ireland, Italy, Jordan, Laos, Libya, Nepal, Portugal, Romania, Spain\n\n80 Members (1956)\n\n\n\nAdded: Japan, Morocco, Sudan, Tunisia\n\n80 Members (1956)\n\nAdded: Japan, Morocco, Sudan, Tunisia\n\nAdded: Japan, Morocco, Sudan, Tunisia\n\nAdded: Japan, Morocco, Sudan, Tunisia\n\n82 Members (1957)\n\n\n\nAdded: Ghana, Federation of Malaya\n\n82 Members (1957)\n\nAdded: Ghana, Federation of Malaya\n\nAdded: Ghana, Federation of Malaya\n\nAdded: Ghana, Federation of Malaya\n\n82 Members (1958)*\n\n\n\nAdded: Guinea\n\t\t\t\t\t\t\t\t* On 22 February 1958, Syria merged with Egypt (both original members of the United Nations) to become the United Arab Republic. 99 Members (1960)\n\n\n\nAdded: Cameroun, Central African Republic, Chad, Congo (Brazzaville), Congo (Leopoldville), Cyprus, Dahomey, Gabon, Ivory Coast, Malagasy Republic, Mali, Niger, Nigeria, Senegal, Somalia, Togo, Upper Volta\n\n99 Members (1960)\n\nAdded: Cameroun, Central African Republic, Chad, Congo (Brazzaville), Congo (Leopoldville), Cyprus, Dahomey, Gabon, Ivory Coast, Malagasy Republic, Mali, Niger, Nigeria, Senegal, Somalia, Togo, Upper Volta\n\nAdded: Cameroun, Central African Republic, Chad, Congo (Brazzaville), Congo (Leopoldville), Cyprus, Dahomey, Gabon, Ivory Coast, Malagasy Republic, Mali, Niger, Nigeria, Senegal, Somalia, Togo, Upper Volta\n\nAdded: Cameroun, Central African Republic, Chad, Congo (Brazzaville), Congo (Leopoldville), Cyprus, Dahomey, Gabon, Ivory Coast, Malagasy Republic, Mali, Niger, Nigeria, Senegal, Somalia, Togo, Upper Volta\n\n104 Members (1961)*\n\n\n\nAdded: Mauritania, Mongolia, Sierra Leone, Tanganyika\n\t\t\t\t\t\t\t\t*On 13 October 1961, Syria, having resumed its status as an independent State from the United Arab Republic, resumed its separate membership in the United Nations. 110 Members (1962)\n\n\n\nAdded: Algeria, Burundi, Jamaica, Rwanda, Trinidad and Tobago, Uganda\n\n110 Members (1962)\n\nAdded: Algeria, Burundi, Jamaica, Rwanda, Trinidad and Tobago, Uganda\n\nAdded: Algeria, Burundi, Jamaica, Rwanda, Trinidad and Tobago, Uganda\n\nAdded: Algeria, Burundi, Jamaica, Rwanda, Trinidad and Tobago, Uganda\n\n113 Members (1963)\n\n\n\nAdded: Kenya, Kuwait, Zanzibar\n\n113 Members (1963)\n\nAdded: Kenya, Kuwait, Zanzibar\n\nAdded: Kenya, Kuwait, Zanzibar\n\nAdded: Kenya, Kuwait, Zanzibar\n\n115 Members (1964)*\n\n\n\nAdded: Malawi, Malta, Zambia\n\t\t\t\t\t\t\t\t*On 26 April 1964, Zanzibar merged with Tanganyika to become the United Republic of Tanzania. 123 Members (1967)\n\n\n\nAdded: Yemen (People's Democratic Republic of Yemen)\n\n123 Members (1967)\n\nAdded: Yemen (People's Democratic Republic of Yemen)\n\nAdded: Yemen (People's Democratic Republic of Yemen)\n\nAdded: Yemen (People's Democratic Republic of Yemen)\n\n126 Members (1968)\n\n\n\nAdded: Equatorial Guinea, Mauritius, Swaziland\n\n126 Members (1968)\n\nAdded: Equatorial Guinea, Mauritius, Swaziland\n\nAdded: Equatorial Guinea, Mauritius, Swaziland\n\nAdded: Equatorial Guinea, Mauritius, Swaziland\n\n127 Members (1970)\n\n\n\nAdded: Fiji\n\n127 Members (1970)\n\nAdded: Fiji\n\nAdded: Fiji\n\nAdded: Fiji\n\n132 Members (1971)\n\n\n\nAdded: Bahrain, Bhutan, Oman, Qatar, United Arab Emirates\n\n132 Members (1971)\n\nAdded: Bahrain, Bhutan, Oman, Qatar, United Arab Emirates\n\nAdded: Bahrain, Bhutan, Oman, Qatar, United Arab Emirates\n\nAdded: Bahrain, Bhutan, Oman, Qatar, United Arab Emirates\n\n135 Members (1973)\n\n\n\nAdded: Bahamas, Federal Republic of Germany, German Democratic Republic\n\n135 Members (1973)\n\nAdded: Bahamas, Federal Republic of Germany, German Democratic Republic\n\nAdded: Bahamas, Federal Republic of Germany, German Democratic Republic\n\nAdded: Bahamas, Federal Republic of Germany, German Democratic Republic\n\n138 Members (1974)\n\n\n\nAdded: Bangladesh, Grenada, Guinea-Bissau\n\n138 Members (1974)\n\nAdded: Bangladesh, Grenada, Guinea-Bissau\n\nAdded: Bangladesh, Grenada, Guinea-Bissau\n\nAdded: Bangladesh, Grenada, Guinea-Bissau\n\n144 Members (1975)\n\n\n\nAdded: Cape Verde, Comoros, Mozambique, Papua New Guinea, Sao Tome and Principe, Suriname\n\n144 Members (1975)\n\nAdded: Cape Verde, Comoros, Mozambique, Papua New Guinea, Sao Tome and Principe, Suriname\n\nAdded: Cape Verde, Comoros, Mozambique, Papua New Guinea, Sao Tome and Principe, Suriname\n\nAdded: Cape Verde, Comoros, Mozambique, Papua New Guinea, Sao Tome and Principe, Suriname\n\n147 Members (1976)\n\n\n\nAdded: Angola, Samoa, Seychelles\n\n147 Members (1976)\n\nAdded: Angola, Samoa, Seychelles\n\nAdded: Angola, Samoa, Seychelles\n\nAdded: Angola, Samoa, Seychelles\n\n149 Members (1977)\n\n\n\nAdded: Djibouti, Viet Nam\n\n149 Members (1977)\n\nAdded: Djibouti, Viet Nam\n\nAdded: Djibouti, Viet Nam\n\nAdded: Djibouti, Viet Nam\n\n151 Members (1978)\n\n\n\nAdded: Dominica, Solomon Islands\n\n151 Members (1978)\n\nAdded: Dominica, Solomon Islands\n\nAdded: Dominica, Solomon Islands\n\nAdded: Dominica, Solomon Islands\n\n152 Members (1979)\n\n\n\nAdded: Saint Lucia\n\n152 Members (1979)\n\nAdded: Saint Lucia\n\nAdded: Saint Lucia\n\nAdded: Saint Lucia\n\n154 Members (1980)\n\n\n\nAdded: Saint Vincent and the Grenadines, Zimbabwe\n\n154 Members (1980)\n\nAdded: Saint Vincent and the Grenadines, Zimbabwe\n\nAdded: Saint Vincent and the Grenadines, Zimbabwe\n\nAdded: Saint Vincent and the Grenadines, Zimbabwe\n\n157 Members (1981) \n\n\n\nAdded: Antigua and Barbuda, Belize, Vanuatu\n\n157 Members (1981)\n\nAdded: Antigua and Barbuda, Belize, Vanuatu\n\nAdded: Antigua and Barbuda, Belize, Vanuatu\n\nAdded: Antigua and Barbuda, Belize, Vanuatu\n\n158 Members (1983)\n\n\n\nAdded: Saint Christopher and Nevis\n\n158 Members (1983)\n\nAdded: Saint Christopher and Nevis\n\nAdded: Saint Christopher and Nevis\n\nAdded: Saint Christopher and Nevis\n\n159 Members (1984)\n\n\n\nAdded: Brunei Darussalam\n\n159 Members (1984)\n\nAdded: Brunei Darussalam\n\nAdded: Brunei Darussalam\n\nAdded: Brunei Darussalam\n\n159 Members (1990)*\n\n\n\nAdded: Liechtenstein, Namibia\n\t\t\t\t\t\t\t\t*On 22 May 1990, the People's Democratic Republic of Yemen (member since 1967) was united with the Yemen Arab Republic (member since 1947), forming the Republic of Yemen. 166 Members (1991)\n\n\n\nAdded: Democratic People's Republic of Korea, Estonia, Latvia, Lithuania, Marshall Islands, Federated States of Micronesia, Republic of Korea\n\n166 Members (1991)\n\nAdded: Democratic People's Republic of Korea, Estonia, Latvia, Lithuania, Marshall Islands, Federated States of Micronesia, Republic of Korea\n\nAdded: Democratic People's Republic of Korea, Estonia, Latvia, Lithuania, Marshall Islands, Federated States of Micronesia, Republic of Korea\n\nAdded: Democratic People's Republic of Korea, Estonia, Latvia, Lithuania, Marshall Islands, Federated States of Micronesia, Republic of Korea\n\n179 Members (1992)\n\n\n\nAdded: Armenia, Azerbaijan, Bosnia and Herzegovina, Croatia, Georgia, Kazakhstan, Kyrgyzstan, Republic of Moldova, San Marino, Slovenia, Tajikistan, Turkmenistan, Uzbekistan\n\n179 Members (1992)\n\nAdded: Armenia, Azerbaijan, Bosnia and Herzegovina, Croatia, Georgia, Kazakhstan, Kyrgyzstan, Republic of Moldova, San Marino, Slovenia, Tajikistan, Turkmenistan, Uzbekistan\n\nAdded: Armenia, Azerbaijan, Bosnia and Herzegovina, Croatia, Georgia, Kazakhstan, Kyrgyzstan, Republic of Moldova, San Marino, Slovenia, Tajikistan, Turkmenistan, Uzbekistan\n\nAdded: Armenia, Azerbaijan, Bosnia and Herzegovina, Croatia, Georgia, Kazakhstan, Kyrgyzstan, Republic of Moldova, San Marino, Slovenia, Tajikistan, Turkmenistan, Uzbekistan\n\n184 Members (1993)*\n\n\n\nAdded: Andorra, Czech Republic, Eritrea, Monaco, Slovakia, The former Yugoslav Republic of Macedonia\n\t\t\t\t\t\t\t\t*Czechoslovakia was an original Member of the United Nations from 24 October 1945. 185 Members (1994)\n\n\n\nAdded: Palau\n\n185 Members (1994)\n\nAdded: Palau\n\nAdded: Palau\n\nAdded: Palau\n\n188 Members (1999)\n\n\n\nAdded: Kiribati, Nauru, Tonga\n\n188 Members (1999)\n\nAdded: Kiribati, Nauru, Tonga\n\nAdded: Kiribati, Nauru, Tonga\n\nAdded: Kiribati, Nauru, Tonga\n\n189 Members (2000)*\n\n\n\nAdded: Federal Republic of Yugoslavia, Tuvalu\n\t\t\t\t\t\t\t\t*The Federal Republic of Yugoslavia was part of the Socialist Federal Republic of Yugoslavia, which was an original member of the United Nations and was removed from the official roster of UN members in 2000, following its dissolution. 191 Members (2002)\n\n\n\nAdded: Switzerland, Timor-Leste\n\n191 Members (2002)\n\nAdded: Switzerland, Timor-Leste\n\nAdded: Switzerland, Timor-Leste\n\nAdded: Switzerland, Timor-Leste\n\n192 Members (2006)\n\n\n\nAdded: Montenegro\n\n192 Members (2006)\n\nAdded: Montenegro\n\nAdded: Montenegro\n\nAdded: Montenegro\n\n193 Members (2011)\n\n\n\nAdded: South Sudan\n\n193 Members (2011)\n\nAdded: South Sudan\n\nAdded: South Sudan\n\nAdded: South Sudan\n\nMEMBER STATES\n\nMembership \n\nAbout UN Membership\nList of UN Member States\nUN Membership research guide\nGrowth in UN Membership\nMembership of Principal UN Organs\nContributions to UN regular budget\nHonour Roll: Contribution Received in Full\nArrears in the Payment of Contribution\n\n\nPermanent Missions\n\nNew York\nGeneva\nVienna\n\n\nPermanent Observers\n\nAbout Permanent Observers\nNon-Member States\nIntergovernmental and Other Organizations\nSpecialized Agencies \n\n\n\n \n\nQuick links for delegates\n\nDelegate (UN Intranet - iSeek for Member States)\nBlue Book\nDelegates' Handbook\nManual of Protocol\n\nMEMBER STATES\n\nMembership \n\nAbout UN Membership\nList of UN Member States\nUN Membership research guide\nGrowth in UN Membership\nMembership of Principal UN Organs\nContributions to UN regular budget\nHonour Roll: Contribution Received in Full\nArrears in the Payment of Contribution\n\n\nPermanent Missions\n\nNew York\nGeneva\nVienna\n\n\nPermanent Observers\n\nAbout Permanent Observers\nNon-Member States\nIntergovernmental and Other Organizations\nSpecialized Agencies \n\n\n\n \n\nQuick links for delegates\n\nDelegate (UN Intranet - iSeek for Member States)\nBlue Book\nDelegates' Handbook\nManual of Protocol\n\nMEMBER STATES\n\nMembership \n\nAbout UN Membership\nList of UN Member States\nUN Membership research guide\nGrowth in UN Membership\nMembership of Principal UN Organs\nContributions to UN regular budget\nHonour Roll: Contribution Received in Full\nArrears in the Payment of Contribution\n\n\nPermanent Missions\n\nNew York\nGeneva\nVienna\n\n\nPermanent Observers\n\nAbout Permanent Observers\nNon-Member States\nIntergovernmental and Other Organizations\nSpecialized Agencies \n\n\n\n \n\nQuick links for delegates\n\nDelegate (UN Intranet - iSeek for Member States)\nBlue Book\nDelegates' Handbook\nManual of Protocol\n\nMembership \n\nAbout UN Membership\nList of UN Member States\nUN Membership research guide\nGrowth in UN Membership\nMembership of Principal UN Organs\nContributions to UN regular budget\nHonour Roll: Contribution Received in Full\nArrears in the Payment of Contribution\n\n\nPermanent Missions\n\nNew York\nGeneva\nVienna\n\n\nPermanent Observers\n\nAbout Permanent Observers\nNon-Member States\nIntergovernmental and Other Organizations\nSpecialized Agencies \n\n\n\n \n\nQuick links for delegates\n\nDelegate (UN Intranet - iSeek for Member States)\nBlue Book\nDelegates' Handbook\nManual of Protocol\n\nQuick links for delegates\n\nDelegate (UN Intranet - iSeek for Member States)\nBlue Book\nDelegates' Handbook\nManual of Protocol\n\nMain Bodies   General Assembly   Security Council   Economic and Social Council   Trusteeship Council   International Court of Justice   Secretariat       Departments / Offices   New York   Geneva   Nairobi   Vienna   UN System Directory   UN System Chart   Global Leadership   UN Information Centres       Resources / Services   Emergency information   Reporting Wrongdoing   UN Journal   Documents   Guidelines for gender-inclusive language   Databases   Library   UN iLibrary   UN Chronicle   UN Yearbook   Bookshop   Publications for sale   Maps   Media Accreditation   NGO accreditation at ECOSOC   NGO accreditation at DGC   Visitors’ services   Exhibits   Procurement   Employment   Internships   Model UN   Academic Impact   UN Archives   UN Audiovisual Library   How to donate to the UN system   Information on COVID-19 (Coronavirus)   Africa Renewal   Ten ways the UN makes a difference   GA High-level week 2024       Key Documents   UN Charter   Universal Declaration of Human Rights   Convention on the Rights of the Child   Statute of the International Court of Justice   Annual Report of the Secretary-General on the Work of the Organization       News and Media   News   Press Releases   Briefings   Spokesperson   Photos   UNIfeed   UN Web TV   UN Video   Social Media   The Essential UN   Awake at Night podcast       Issues / Campaigns   Global Issues   Observances   Sustainable Development Goals   Our Common Agenda   The Summit of the Future   Climate Action   Peace and Security   Action for Peacekeeping (A4P)   Global Crisis Response Group   Call to Action for Human Rights   Disability Inclusion Strategy   Fight Racism   Hate Speech   LGBTIQ+ People   Safety of Journalists   Rule of Law   Action to Counter Terrorism   Victims of Terrorism   Children and Armed Conflict   Violence Against Children (SRSG)   Sexual Violence in Conflict   Refugees and Migrants   Action Agenda on Internal Displacement   Spotlight Initiative   Preventing Sexual Exploitation and Abuse   Prevention of Genocide and the Responsibility to Protect   The Rwanda Genocide   The Holocaust   The Question of Palestine   The Transatlantic Slave Trade   Decolonization   Messengers of Peace   Roadmap for Digital Cooperation   Digital Financing Task Force   Data Strategy   Information Integrity   Countering Disinformation   UN75: 2020 and Beyond   Women Rise for All   Stop the Red Sea Catastrophe   Black Sea Grain Initiative Joint Coordination Centre\n\nMain Bodies   General Assembly   Security Council   Economic and Social Council   Trusteeship Council   International Court of Justice   Secretariat       Departments / Offices   New York   Geneva   Nairobi   Vienna   UN System Directory   UN System Chart   Global Leadership   UN Information Centres       Resources / Services   Emergency information   Reporting Wrongdoing   UN Journal   Documents   Guidelines for gender-inclusive language   Databases   Library   UN iLibrary   UN Chronicle   UN Yearbook   Bookshop   Publications for sale   Maps   Media Accreditation   NGO accreditation at ECOSOC   NGO accreditation at DGC   Visitors’ services   Exhibits   Procurement   Employment   Internships   Model UN   Academic Impact   UN Archives   UN Audiovisual Library   How to donate to the UN system   Information on COVID-19 (Coronavirus)   Africa Renewal   Ten ways the UN makes a difference   GA High-level week 2024       Key Documents   UN Charter   Universal Declaration of Human Rights   Convention on the Rights of the Child   Statute of the International Court of Justice   Annual Report of the Secretary-General on the Work of the Organization       News and Media   News   Press Releases   Briefings   Spokesperson   Photos   UNIfeed   UN Web TV   UN Video   Social Media   The Essential UN   Awake at Night podcast       Issues / Campaigns   Global Issues   Observances   Sustainable Development Goals   Our Common Agenda   The Summit of the Future   Climate Action   Peace and Security   Action for Peacekeeping (A4P)   Global Crisis Response Group   Call to Action for Human Rights   Disability Inclusion Strategy   Fight Racism   Hate Speech   LGBTIQ+ People   Safety of Journalists   Rule of Law   Action to Counter Terrorism   Victims of Terrorism   Children and Armed Conflict   Violence Against Children (SRSG)   Sexual Violence in Conflict   Refugees and Migrants   Action Agenda on Internal Displacement   Spotlight Initiative   Preventing Sexual Exploitation and Abuse   Prevention of Genocide and the Responsibility to Protect   The Rwanda Genocide   The Holocaust   The Question of Palestine   The Transatlantic Slave Trade   Decolonization   Messengers of Peace   Roadmap for Digital Cooperation   Digital Financing Task Force   Data Strategy   Information Integrity   Countering Disinformation   UN75: 2020 and Beyond   Women Rise for All   Stop the Red Sea Catastrophe   Black Sea Grain Initiative Joint Coordination Centre\n\nMain Bodies   General Assembly   Security Council   Economic and Social Council   Trusteeship Council   International Court of Justice   Secretariat       Departments / Offices   New York   Geneva   Nairobi   Vienna   UN System Directory   UN System Chart   Global Leadership   UN Information Centres       Resources / Services   Emergency information   Reporting Wrongdoing   UN Journal   Documents   Guidelines for gender-inclusive language   Databases   Library   UN iLibrary   UN Chronicle   UN Yearbook   Bookshop   Publications for sale   Maps   Media Accreditation   NGO accreditation at ECOSOC   NGO accreditation at DGC   Visitors’ services   Exhibits   Procurement   Employment   Internships   Model UN   Academic Impact   UN Archives   UN Audiovisual Library   How to donate to the UN system   Information on COVID-19 (Coronavirus)   Africa Renewal   Ten ways the UN makes a difference   GA High-level week 2024       Key Documents   UN Charter   Universal Declaration of Human Rights   Convention on the Rights of the Child   Statute of the International Court of Justice   Annual Report of the Secretary-General on the Work of the Organization       News and Media   News   Press Releases   Briefings   Spokesperson   Photos   UNIfeed   UN Web TV   UN Video   Social Media   The Essential UN   Awake at Night podcast       Issues / Campaigns   Global Issues   Observances   Sustainable Development Goals   Our Common Agenda   The Summit of the Future   Climate Action   Peace and Security   Action for Peacekeeping (A4P)   Global Crisis Response Group   Call to Action for Human Rights   Disability Inclusion Strategy   Fight Racism   Hate Speech   LGBTIQ+ People   Safety of Journalists   Rule of Law   Action to Counter Terrorism   Victims of Terrorism   Children and Armed Conflict   Violence Against Children (SRSG)   Sexual Violence in Conflict   Refugees and Migrants   Action Agenda on Internal Displacement   Spotlight Initiative   Preventing Sexual Exploitation and Abuse   Prevention of Genocide and the Responsibility to Protect   The Rwanda Genocide   The Holocaust   The Question of Palestine   The Transatlantic Slave Trade   Decolonization   Messengers of Peace   Roadmap for Digital Cooperation   Digital Financing Task Force   Data Strategy   Information Integrity   Countering Disinformation   UN75: 2020 and Beyond   Women Rise for All   Stop the Red Sea Catastrophe   Black Sea Grain Initiative Joint Coordination Centre\n\nMain Bodies   General Assembly   Security Council   Economic and Social Council   Trusteeship Council   International Court of Justice   Secretariat       Departments / Offices   New York   Geneva   Nairobi   Vienna   UN System Directory   UN System Chart   Global Leadership   UN Information Centres\n\nMain Bodies   General Assembly   Security Council   Economic and Social Council   Trusteeship Council   International Court of Justice   Secretariat\n\nMain Bodies   General Assembly   Security Council   Economic and Social Council   Trusteeship Council   International Court of Justice   Secretariat\n\nDepartments / Offices   New York   Geneva   Nairobi   Vienna   UN System Directory   UN System Chart   Global Leadership   UN Information Centres\n\nDepartments / Offices   New York   Geneva   Nairobi   Vienna   UN System Directory   UN System Chart   Global Leadership   UN Information Centres\n\nResources / Services   Emergency information   Reporting Wrongdoing   UN Journal   Documents   Guidelines for gender-inclusive language   Databases   Library   UN iLibrary   UN Chronicle   UN Yearbook   Bookshop   Publications for sale   Maps   Media Accreditation   NGO accreditation at ECOSOC   NGO accreditation at DGC   Visitors’ services   Exhibits   Procurement   Employment   Internships   Model UN   Academic Impact   UN Archives   UN Audiovisual Library   How to donate to the UN system   Information on COVID-19 (Coronavirus)   Africa Renewal   Ten ways the UN makes a difference   GA High-level week 2024\n\nResources / Services   Emergency information   Reporting Wrongdoing   UN Journal   Documents   Guidelines for gender-inclusive language   Databases   Library   UN iLibrary   UN Chronicle   UN Yearbook   Bookshop   Publications for sale   Maps   Media Accreditation   NGO accreditation at ECOSOC   NGO accreditation at DGC   Visitors’ services   Exhibits   Procurement   Employment   Internships   Model UN   Academic Impact   UN Archives   UN Audiovisual Library   How to donate to the UN system   Information on COVID-19 (Coronavirus)   Africa Renewal   Ten ways the UN makes a difference   GA High-level week 2024\n\nResources / Services   Emergency information   Reporting Wrongdoing   UN Journal   Documents   Guidelines for gender-inclusive language   Databases   Library   UN iLibrary   UN Chronicle   UN Yearbook   Bookshop   Publications for sale   Maps   Media Accreditation   NGO accreditation at ECOSOC   NGO accreditation at DGC   Visitors’ services   Exhibits   Procurement   Employment   Internships   Model UN   Academic Impact   UN Archives   UN Audiovisual Library   How to donate to the UN system   Information on COVID-19 (Coronavirus)   Africa Renewal   Ten ways the UN makes a difference   GA High-level week 2024\n\nKey Documents   UN Charter   Universal Declaration of Human Rights   Convention on the Rights of the Child   Statute of the International Court of Justice   Annual Report of the Secretary-General on the Work of the Organization       News and Media   News   Press Releases   Briefings   Spokesperson   Photos   UNIfeed   UN Web TV   UN Video   Social Media   The Essential UN   Awake at Night podcast\n\nKey Documents   UN Charter   Universal Declaration of Human Rights   Convention on the Rights of the Child   Statute of the International Court of Justice   Annual Report of the Secretary-General on the Work of the Organization\n\nKey Documents   UN Charter   Universal Declaration of Human Rights   Convention on the Rights of the Child   Statute of the International Court of Justice   Annual Report of the Secretary-General on the Work of the Organization\n\nNews and Media   News   Press Releases   Briefings   Spokesperson   Photos   UNIfeed   UN Web TV   UN Video   Social Media   The Essential UN   Awake at Night podcast\n\nNews and Media   News   Press Releases   Briefings   Spokesperson   Photos   UNIfeed   UN Web TV   UN Video   Social Media   The Essential UN   Awake at Night podcast\n\nIssues / Campaigns   Global Issues   Observances   Sustainable Development Goals   Our Common Agenda   The Summit of the Future   Climate Action   Peace and Security   Action for Peacekeeping (A4P)   Global Crisis Response Group   Call to Action for Human Rights   Disability Inclusion Strategy   Fight Racism   Hate Speech   LGBTIQ+ People   Safety of Journalists   Rule of Law   Action to Counter Terrorism   Victims of Terrorism   Children and Armed Conflict   Violence Against Children (SRSG)   Sexual Violence in Conflict   Refugees and Migrants   Action Agenda on Internal Displacement   Spotlight Initiative   Preventing Sexual Exploitation and Abuse   Prevention of Genocide and the Responsibility to Protect   The Rwanda Genocide   The Holocaust   The Question of Palestine   The Transatlantic Slave Trade   Decolonization   Messengers of Peace   Roadmap for Digital Cooperation   Digital Financing Task Force   Data Strategy   Information Integrity   Countering Disinformation   UN75: 2020 and Beyond   Women Rise for All   Stop the Red Sea Catastrophe   Black Sea Grain Initiative Joint Coordination Centre\n\nIssues / Campaigns   Global Issues   Observances   Sustainable Development Goals   Our Common Agenda   The Summit of the Future   Climate Action   Peace and Security   Action for Peacekeeping (A4P)   Global Crisis Response Group   Call to Action for Human Rights   Disability Inclusion Strategy   Fight Racism   Hate Speech   LGBTIQ+ People   Safety of Journalists   Rule of Law   Action to Counter Terrorism   Victims of Terrorism   Children and Armed Conflict   Violence Against Children (SRSG)   Sexual Violence in Conflict   Refugees and Migrants   Action Agenda on Internal Displacement   Spotlight Initiative   Preventing Sexual Exploitation and Abuse   Prevention of Genocide and the Responsibility to Protect   The Rwanda Genocide   The Holocaust   The Question of Palestine   The Transatlantic Slave Trade   Decolonization   Messengers of Peace   Roadmap for Digital Cooperation   Digital Financing Task Force   Data Strategy   Information Integrity   Countering Disinformation   UN75: 2020 and Beyond   Women Rise for All   Stop the Red Sea Catastrophe   Black Sea Grain Initiative Joint Coordination Centre\n\nIssues / Campaigns   Global Issues   Observances   Sustainable Development Goals   Our Common Agenda   The Summit of the Future   Climate Action   Peace and Security   Action for Peacekeeping (A4P)   Global Crisis Response Group   Call to Action for Human Rights   Disability Inclusion Strategy   Fight Racism   Hate Speech   LGBTIQ+ People   Safety of Journalists   Rule of Law   Action to Counter Terrorism   Victims of Terrorism   Children and Armed Conflict   Violence Against Children (SRSG)   Sexual Violence in Conflict   Refugees and Migrants   Action Agenda on Internal Displacement   Spotlight Initiative   Preventing Sexual Exploitation and Abuse   Prevention of Genocide and the Responsibility to Protect   The Rwanda Genocide   The Holocaust   The Question of Palestine   The Transatlantic Slave Trade   Decolonization   Messengers of Peace   Roadmap for Digital Cooperation   Digital Financing Task Force   Data Strategy   Information Integrity   Countering Disinformation   UN75: 2020 and Beyond   Women Rise for All   Stop the Red Sea Catastrophe   Black Sea Grain Initiative Joint Coordination Centre",
  "entities": {
    "countries": [
      "afghanistan",
      "australia",
      "brazil",
      "canada",
      "china",
      "france",
      "germany",
      "india",
      "iran",
      "iraq",
      "israel",
      "japan",
      "mexico",
      "pakistan",
      "russia",
      "syria",
      "united kingdom",
      "united states",
      "yemen"
    ],
    "organizations": [
      "united nations",
      "un"
    ],
    "key_issues": [
      "issue",
      "crisis",
      "nation",
      "state",
      "government",
      "solution",
      "strategy",
      "initiative",
      "action",
      "origin",
      "development",
      "human rights",
      "economic",
      "trade",
      "united nations",
      "un",
      "security council",
      "general assembly",
      "ngo",
      "organization"
    ]
  },
  "committee": "Fourth Committee",
  "topic": "Ensuring the rights and safety of indigenous populations"
}