{
  "url": "https://www.un.org/en/about-us/un-charter",
  "title": "UN Charter | United Nations",
  "text": "Skip to main content\n\nUN Charter\n\n\n\n\n\n\nUN CharterPreambleChapter I: Purposes and Principles (Articles 1-2)Chapter II: Membership (Articles 3-6)Chapter III: Organs (Articles 7-8)Chapter IV: The General Assembly (Articles 9-22) Chapter V: The Security Council (Articles 23-32)Chapter VI: Pacific Settlement of Disputes (Articles 33-38)Chapter VII: Action with Respect to Threats to the Peace, Breaches of the Peace, and  Acts of Aggression (Articles 39-51)Chapter VIII: Regional Arrangements (Articles 52-54)Chapter IX: International Economic and Social Cooperation (Articles 55-60)Chapter X: The Economic and Social Council (Articles 61-72)Chapter XI: Declaration Regarding Non-Self-Governing Territories (Articles 73-74)Chapter XII: International Trusteeship System (Articles 75-85)Chapter XIII: The Trusteeship Council (Articles 86-91)Chapter XIV: The International Court of Justice (Articles 92-96)Chapter XV: The Secretariat (Articles 97-101)Chapter XVI: Miscellaneous Provisions (Articles 102-105)Chapter XVII: Transitional Security Arrangements (Articles 106-107)Chapter XVIII: Amendments (Articles 108-109) Chapter XIX: Ratification and Signature (Articles 110-111)Amendments to Articles 23, 27, 61, 109 \n\n\n\n \n\nUnited Nations Charter\nThe Charter of the United Nations is the founding document of the United Nations. It was signed on 26 June 1945, in San Francisco, at the conclusion of the United Nations Conference on International Organization, and came into force on 24 October 1945.\nThe United Nations can take action on a wide variety of issues due to its unique international character and the powers vested in its Charter, which is considered an international treaty. As such, the UN Charter is an instrument of international law, and UN Member States are bound by it. The UN Charter codifies the major principles of international relations, from sovereign equality of States to the prohibition of the use of force in international relations.\nSince the UN's founding in 1945, the mission and work of the Organization have been guided by the purposes and principles contained in its founding Charter, which has been amended three times in 1963, 1965, and 1973.\nThe International Court of Justice, the principal judicial organ of the United Nations, functions in accordance with the Statute of the International Court of Justice, which is annexed to the UN Charter, and forms an integral part of it. (See Chapter XIV, Article 92) \n\nFind the full text of the UN Charter, or read about the history of its making. Listen to a reading of the Preamble.\n\n\nBuy the UN Charter\nA booklet is available for purchase. This redesigned edition for the UN’s 70th anniversary features a new introduction titled “From War to Peace,” exclusive archival photos and the Statute of the International Court of Justice.\n\n\nUN Audiovisual Library\nWatch historical footage of the signing of the UN Charter Documentary about the founding of the United Nations Organization and the San Francisco Conference in 1945\n\n\nFanfare for All Peoples\nThis film, set against the stirring words of the Preamble of the United Nations Charter, premiered to an audience of Heads of States from around the world. Fanfare incorporates six languages and incorporates cutting-edge drone footage and breathtaking aerial photography with an inspiring original symphonic score.\n\n\n \n\n\n \n  Outline UN CharterPreamble\nChapter I: Purposes and Principles (Articles 1-2)\nChapter II: Membership (Articles 3-6)\nChapter III: Organs (Articles 7-8)\nChapter IV: The General Assembly (Articles 9-22) \nChapter V: The Security Council (Articles 23-32)\nChapter VI: Pacific Settlement of Disputes (Articles 33-38)\nChapter VII: Action with Respect to Threats to the Peace, Breaches of the Peace, and  Acts of Aggression (Articles 39-51)\nChapter VIII: Regional Arrangements (Articles 52-54)\nChapter IX: International Economic and Social Cooperation (Articles 55-60)\nChapter X: The Economic and Social Council (Articles 61-72)\nChapter XI: Declaration Regarding Non-Self-Governing Territories (Articles 73-74)\nChapter XII: International Trusteeship System (Articles 75-85)\nChapter XIII: The Trusteeship Council (Articles 86-91)\nChapter XIV: The International Court of Justice (Articles 92-96)\nChapter XV: The Secretariat (Articles 97-101)\nChapter XVI: Miscellaneous Provisions (Articles 102-105)\nChapter XVII: Transitional Security Arrangements (Articles 106-107)\nChapter XVIII: Amendments (Articles 108-109)\n Chapter XIX: Ratification and Signature (Articles 110-111)\nAmendments to Articles 23, 27, 61, 109\n\n\n\nPreamble ›\n\n\n\n\n\n\n\n\n\n\n\n\n\n\n\n\n\n\n\n\n \n\n\n\n        Main Bodies   General Assembly   Security Council   Economic and Social Council   Trusteeship Council   International Court of Justice   Secretariat       Departments / Offices   New York   Geneva   Nairobi   Vienna   UN System Directory   UN System Chart   Global Leadership   UN Information Centres       Resources / Services   Emergency information   Reporting Wrongdoing   UN Journal   Documents   Guidelines for gender-inclusive language   Databases   Library   UN iLibrary   UN Chronicle   UN Yearbook   Bookshop   Publications for sale   Maps   Media Accreditation   NGO accreditation at ECOSOC   NGO accreditation at DGC   Visitors’ services   Exhibits   Procurement   Employment   Internships   Model UN   Academic Impact   UN Archives   UN Audiovisual Library   How to donate to the UN system   Information on COVID-19 (Coronavirus)   Africa Renewal   Ten ways the UN makes a difference   GA High-level week 2024       Key Documents   UN Charter   Universal Declaration of Human Rights   Convention on the Rights of the Child   Statute of the International Court of Justice   Annual Report of the Secretary-General on the Work of the Organization       News and Media   News   Press Releases   Briefings   Spokesperson   Photos   UNIfeed   UN Web TV   UN Video   Social Media   The Essential UN   Awake at Night podcast       Issues / Campaigns   Global Issues   Observances   Sustainable Development Goals   Our Common Agenda   The Summit of the Future   Climate Action   Peace and Security   Action for Peacekeeping (A4P)   Global Crisis Response Group   Call to Action for Human Rights   Disability Inclusion Strategy   Fight Racism   Hate Speech   LGBTIQ+ People   Safety of Journalists   Rule of Law   Action to Counter Terrorism   Victims of Terrorism   Children and Armed Conflict   Violence Against Children (SRSG)   Sexual Violence in Conflict   Refugees and Migrants   Action Agenda on Internal Displacement   Spotlight Initiative   Preventing Sexual Exploitation and Abuse   Prevention of Genocide and the Responsibility to Protect   The Rwanda Genocide   The Holocaust   The Question of Palestine   The Transatlantic Slave Trade   Decolonization   Messengers of Peace   Roadmap for Digital Cooperation   Digital Financing Task Force   Data Strategy   Information Integrity   Countering Disinformation   UN75: 2020 and Beyond   Women Rise for All   Stop the Red Sea Catastrophe   Black Sea Grain Initiative Joint Coordination Centre\n\nUN Charter\n\n\n\n\n\n\nUN CharterPreambleChapter I: Purposes and Principles (Articles 1-2)Chapter II: Membership (Articles 3-6)Chapter III: Organs (Articles 7-8)Chapter IV: The General Assembly (Articles 9-22) Chapter V: The Security Council (Articles 23-32)Chapter VI: Pacific Settlement of Disputes (Articles 33-38)Chapter VII: Action with Respect to Threats to the Peace, Breaches of the Peace, and  Acts of Aggression (Articles 39-51)Chapter VIII: Regional Arrangements (Articles 52-54)Chapter IX: International Economic and Social Cooperation (Articles 55-60)Chapter X: The Economic and Social Council (Articles 61-72)Chapter XI: Declaration Regarding Non-Self-Governing Territories (Articles 73-74)Chapter XII: International Trusteeship System (Articles 75-85)Chapter XIII: The Trusteeship Council (Articles 86-91)Chapter XIV: The International Court of Justice (Articles 92-96)Chapter XV: The Secretariat (Articles 97-101)Chapter XVI: Miscellaneous Provisions (Articles 102-105)Chapter XVII: Transitional Security Arrangements (Articles 106-107)Chapter XVIII: Amendments (Articles 108-109) Chapter XIX: Ratification and Signature (Articles 110-111)Amendments to Articles 23, 27, 61, 109 \n\n\n\n \n\nUnited Nations Charter\nThe Charter of the United Nations is the founding document of the United Nations. It was signed on 26 June 1945, in San Francisco, at the conclusion of the United Nations Conference on International Organization, and came into force on 24 October 1945.\nThe United Nations can take action on a wide variety of issues due to its unique international character and the powers vested in its Charter, which is considered an international treaty. As such, the UN Charter is an instrument of international law, and UN Member States are bound by it. The UN Charter codifies the major principles of international relations, from sovereign equality of States to the prohibition of the use of force in international relations.\nSince the UN's founding in 1945, the mission and work of the Organization have been guided by the purposes and principles contained in its founding Charter, which has been amended three times in 1963, 1965, and 1973.\nThe International Court of Justice, the principal judicial organ of the United Nations, functions in accordance with the Statute of the International Court of Justice, which is annexed to the UN Charter, and forms an integral part of it. (See Chapter XIV, Article 92) \n\nFind the full text of the UN Charter, or read about the history of its making. Listen to a reading of the Preamble.\n\n\nBuy the UN Charter\nA booklet is available for purchase. This redesigned edition for the UN’s 70th anniversary features a new introduction titled “From War to Peace,” exclusive archival photos and the Statute of the International Court of Justice.\n\n\nUN Audiovisual Library\nWatch historical footage of the signing of the UN Charter Documentary about the founding of the United Nations Organization and the San Francisco Conference in 1945\n\n\nFanfare for All Peoples\nThis film, set against the stirring words of the Preamble of the United Nations Charter, premiered to an audience of Heads of States from around the world. Fanfare incorporates six languages and incorporates cutting-edge drone footage and breathtaking aerial photography with an inspiring original symphonic score.\n\n\n \n\n\n \n  Outline UN CharterPreamble\nChapter I: Purposes and Principles (Articles 1-2)\nChapter II: Membership (Articles 3-6)\nChapter III: Organs (Articles 7-8)\nChapter IV: The General Assembly (Articles 9-22) \nChapter V: The Security Council (Articles 23-32)\nChapter VI: Pacific Settlement of Disputes (Articles 33-38)\nChapter VII: Action with Respect to Threats to the Peace, Breaches of the Peace, and  Acts of Aggression (Articles 39-51)\nChapter VIII: Regional Arrangements (Articles 52-54)\nChapter IX: International Economic and Social Cooperation (Articles 55-60)\nChapter X: The Economic and Social Council (Articles 61-72)\nChapter XI: Declaration Regarding Non-Self-Governing Territories (Articles 73-74)\nChapter XII: International Trusteeship System (Articles 75-85)\nChapter XIII: The Trusteeship Council (Articles 86-91)\nChapter XIV: The International Court of Justice (Articles 92-96)\nChapter XV: The Secretariat (Articles 97-101)\nChapter XVI: Miscellaneous Provisions (Articles 102-105)\nChapter XVII: Transitional Security Arrangements (Articles 106-107)\nChapter XVIII: Amendments (Articles 108-109)\n Chapter XIX: Ratification and Signature (Articles 110-111)\nAmendments to Articles 23, 27, 61, 109\n\n\n\nPreamble ›\n\nUN Charter\n\n\n\n\n\n\nUN CharterPreambleChapter I: Purposes and Principles (Articles 1-2)Chapter II: Membership (Articles 3-6)Chapter III: Organs (Articles 7-8)Chapter IV: The General Assembly (Articles 9-22) Chapter V: The Security Council (Articles 23-32)Chapter VI: Pacific Settlement of Disputes (Articles 33-38)Chapter VII: Action with Respect to Threats to the Peace, Breaches of the Peace, and  Acts of Aggression (Articles 39-51)Chapter VIII: Regional Arrangements (Articles 52-54)Chapter IX: International Economic and Social Cooperation (Articles 55-60)Chapter X: The Economic and Social Council (Articles 61-72)Chapter XI: Declaration Regarding Non-Self-Governing Territories (Articles 73-74)Chapter XII: International Trusteeship System (Articles 75-85)Chapter XIII: The Trusteeship Council (Articles 86-91)Chapter XIV: The International Court of Justice (Articles 92-96)Chapter XV: The Secretariat (Articles 97-101)Chapter XVI: Miscellaneous Provisions (Articles 102-105)Chapter XVII: Transitional Security Arrangements (Articles 106-107)Chapter XVIII: Amendments (Articles 108-109) Chapter XIX: Ratification and Signature (Articles 110-111)Amendments to Articles 23, 27, 61, 109 \n\n\n\n \n\nUnited Nations Charter\nThe Charter of the United Nations is the founding document of the United Nations. It was signed on 26 June 1945, in San Francisco, at the conclusion of the United Nations Conference on International Organization, and came into force on 24 October 1945.\nThe United Nations can take action on a wide variety of issues due to its unique international character and the powers vested in its Charter, which is considered an international treaty. As such, the UN Charter is an instrument of international law, and UN Member States are bound by it. The UN Charter codifies the major principles of international relations, from sovereign equality of States to the prohibition of the use of force in international relations.\nSince the UN's founding in 1945, the mission and work of the Organization have been guided by the purposes and principles contained in its founding Charter, which has been amended three times in 1963, 1965, and 1973.\nThe International Court of Justice, the principal judicial organ of the United Nations, functions in accordance with the Statute of the International Court of Justice, which is annexed to the UN Charter, and forms an integral part of it. (See Chapter XIV, Article 92) \n\nFind the full text of the UN Charter, or read about the history of its making. Listen to a reading of the Preamble.\n\n\nBuy the UN Charter\nA booklet is available for purchase. This redesigned edition for the UN’s 70th anniversary features a new introduction titled “From War to Peace,” exclusive archival photos and the Statute of the International Court of Justice.\n\n\nUN Audiovisual Library\nWatch historical footage of the signing of the UN Charter Documentary about the founding of the United Nations Organization and the San Francisco Conference in 1945\n\n\nFanfare for All Peoples\nThis film, set against the stirring words of the Preamble of the United Nations Charter, premiered to an audience of Heads of States from around the world. Fanfare incorporates six languages and incorporates cutting-edge drone footage and breathtaking aerial photography with an inspiring original symphonic score.\n\n\n \n\n\n \n  Outline UN CharterPreamble\nChapter I: Purposes and Principles (Articles 1-2)\nChapter II: Membership (Articles 3-6)\nChapter III: Organs (Articles 7-8)\nChapter IV: The General Assembly (Articles 9-22) \nChapter V: The Security Council (Articles 23-32)\nChapter VI: Pacific Settlement of Disputes (Articles 33-38)\nChapter VII: Action with Respect to Threats to the Peace, Breaches of the Peace, and  Acts of Aggression (Articles 39-51)\nChapter VIII: Regional Arrangements (Articles 52-54)\nChapter IX: International Economic and Social Cooperation (Articles 55-60)\nChapter X: The Economic and Social Council (Articles 61-72)\nChapter XI: Declaration Regarding Non-Self-Governing Territories (Articles 73-74)\nChapter XII: International Trusteeship System (Articles 75-85)\nChapter XIII: The Trusteeship Council (Articles 86-91)\nChapter XIV: The International Court of Justice (Articles 92-96)\nChapter XV: The Secretariat (Articles 97-101)\nChapter XVI: Miscellaneous Provisions (Articles 102-105)\nChapter XVII: Transitional Security Arrangements (Articles 106-107)\nChapter XVIII: Amendments (Articles 108-109)\n Chapter XIX: Ratification and Signature (Articles 110-111)\nAmendments to Articles 23, 27, 61, 109\n\n\n\nPreamble ›\n\nUN Charter\n\n\n\n\n\n\nUN CharterPreambleChapter I: Purposes and Principles (Articles 1-2)Chapter II: Membership (Articles 3-6)Chapter III: Organs (Articles 7-8)Chapter IV: The General Assembly (Articles 9-22) Chapter V: The Security Council (Articles 23-32)Chapter VI: Pacific Settlement of Disputes (Articles 33-38)Chapter VII: Action with Respect to Threats to the Peace, Breaches of the Peace, and  Acts of Aggression (Articles 39-51)Chapter VIII: Regional Arrangements (Articles 52-54)Chapter IX: International Economic and Social Cooperation (Articles 55-60)Chapter X: The Economic and Social Council (Articles 61-72)Chapter XI: Declaration Regarding Non-Self-Governing Territories (Articles 73-74)Chapter XII: International Trusteeship System (Articles 75-85)Chapter XIII: The Trusteeship Council (Articles 86-91)Chapter XIV: The International Court of Justice (Articles 92-96)Chapter XV: The Secretariat (Articles 97-101)Chapter XVI: Miscellaneous Provisions (Articles 102-105)Chapter XVII: Transitional Security Arrangements (Articles 106-107)Chapter XVIII: Amendments (Articles 108-109) Chapter XIX: Ratification and Signature (Articles 110-111)Amendments to Articles 23, 27, 61, 109 \n\n\n\n \n\nUnited Nations Charter\nThe Charter of the United Nations is the founding document of the United Nations. It was signed on 26 June 1945, in San Francisco, at the conclusion of the United Nations Conference on International Organization, and came into force on 24 October 1945.\nThe United Nations can take action on a wide variety of issues due to its unique international character and the powers vested in its Charter, which is considered an international treaty. As such, the UN Charter is an instrument of international law, and UN Member States are bound by it. The UN Charter codifies the major principles of international relations, from sovereign equality of States to the prohibition of the use of force in international relations.\nSince the UN's founding in 1945, the mission and work of the Organization have been guided by the purposes and principles contained in its founding Charter, which has been amended three times in 1963, 1965, and 1973.\nThe International Court of Justice, the principal judicial organ of the United Nations, functions in accordance with the Statute of the International Court of Justice, which is annexed to the UN Charter, and forms an integral part of it. (See Chapter XIV, Article 92) \n\nFind the full text of the UN Charter, or read about the history of its making. Listen to a reading of the Preamble.\n\n\nBuy the UN Charter\nA booklet is available for purchase. This redesigned edition for the UN’s 70th anniversary features a new introduction titled “From War to Peace,” exclusive archival photos and the Statute of the International Court of Justice.\n\n\nUN Audiovisual Library\nWatch historical footage of the signing of the UN Charter Documentary about the founding of the United Nations Organization and the San Francisco Conference in 1945\n\n\nFanfare for All Peoples\nThis film, set against the stirring words of the Preamble of the United Nations Charter, premiered to an audience of Heads of States from around the world. Fanfare incorporates six languages and incorporates cutting-edge drone footage and breathtaking aerial photography with an inspiring original symphonic score.\n\n\n \n\n\n \n  Outline UN CharterPreamble\nChapter I: Purposes and Principles (Articles 1-2)\nChapter II: Membership (Articles 3-6)\nChapter III: Organs (Articles 7-8)\nChapter IV: The General Assembly (Articles 9-22) \nChapter V: The Security Council (Articles 23-32)\nChapter VI: Pacific Settlement of Disputes (Articles 33-38)\nChapter VII: Action with Respect to Threats to the Peace, Breaches of the Peace, and  Acts of Aggression (Articles 39-51)\nChapter VIII: Regional Arrangements (Articles 52-54)\nChapter IX: International Economic and Social Cooperation (Articles 55-60)\nChapter X: The Economic and Social Council (Articles 61-72)\nChapter XI: Declaration Regarding Non-Self-Governing Territories (Articles 73-74)\nChapter XII: International Trusteeship System (Articles 75-85)\nChapter XIII: The Trusteeship Council (Articles 86-91)\nChapter XIV: The International Court of Justice (Articles 92-96)\nChapter XV: The Secretariat (Articles 97-101)\nChapter XVI: Miscellaneous Provisions (Articles 102-105)\nChapter XVII: Transitional Security Arrangements (Articles 106-107)\nChapter XVIII: Amendments (Articles 108-109)\n Chapter XIX: Ratification and Signature (Articles 110-111)\nAmendments to Articles 23, 27, 61, 109\n\n\n\nPreamble ›\n\nUN Charter\n\n\n\n\n\n\nUN CharterPreambleChapter I: Purposes and Principles (Articles 1-2)Chapter II: Membership (Articles 3-6)Chapter III: Organs (Articles 7-8)Chapter IV: The General Assembly (Articles 9-22) Chapter V: The Security Council (Articles 23-32)Chapter VI: Pacific Settlement of Disputes (Articles 33-38)Chapter VII: Action with Respect to Threats to the Peace, Breaches of the Peace, and  Acts of Aggression (Articles 39-51)Chapter VIII: Regional Arrangements (Articles 52-54)Chapter IX: International Economic and Social Cooperation (Articles 55-60)Chapter X: The Economic and Social Council (Articles 61-72)Chapter XI: Declaration Regarding Non-Self-Governing Territories (Articles 73-74)Chapter XII: International Trusteeship System (Articles 75-85)Chapter XIII: The Trusteeship Council (Articles 86-91)Chapter XIV: The International Court of Justice (Articles 92-96)Chapter XV: The Secretariat (Articles 97-101)Chapter XVI: Miscellaneous Provisions (Articles 102-105)Chapter XVII: Transitional Security Arrangements (Articles 106-107)Chapter XVIII: Amendments (Articles 108-109) Chapter XIX: Ratification and Signature (Articles 110-111)Amendments to Articles 23, 27, 61, 109 \n\n\n\n \n\nUnited Nations Charter\nThe Charter of the United Nations is the founding document of the United Nations. It was signed on 26 June 1945, in San Francisco, at the conclusion of the United Nations Conference on International Organization, and came into force on 24 October 1945.\nThe United Nations can take action on a wide variety of issues due to its unique international character and the powers vested in its Charter, which is considered an international treaty. As such, the UN Charter is an instrument of international law, and UN Member States are bound by it. The UN Charter codifies the major principles of international relations, from sovereign equality of States to the prohibition of the use of force in international relations.\nSince the UN's founding in 1945, the mission and work of the Organization have been guided by the purposes and principles contained in its founding Charter, which has been amended three times in 1963, 1965, and 1973.\nThe International Court of Justice, the principal judicial organ of the United Nations, functions in accordance with the Statute of the International Court of Justice, which is annexed to the UN Charter, and forms an integral part of it. (See Chapter XIV, Article 92) \n\nFind the full text of the UN Charter, or read about the history of its making. Listen to a reading of the Preamble.\n\n\nBuy the UN Charter\nA booklet is available for purchase. This redesigned edition for the UN’s 70th anniversary features a new introduction titled “From War to Peace,” exclusive archival photos and the Statute of the International Court of Justice.\n\n\nUN Audiovisual Library\nWatch historical footage of the signing of the UN Charter Documentary about the founding of the United Nations Organization and the San Francisco Conference in 1945\n\n\nFanfare for All Peoples\nThis film, set against the stirring words of the Preamble of the United Nations Charter, premiered to an audience of Heads of States from around the world. Fanfare incorporates six languages and incorporates cutting-edge drone footage and breathtaking aerial photography with an inspiring original symphonic score.\n\n\n \n\n\n \n  Outline UN CharterPreamble\nChapter I: Purposes and Principles (Articles 1-2)\nChapter II: Membership (Articles 3-6)\nChapter III: Organs (Articles 7-8)\nChapter IV: The General Assembly (Articles 9-22) \nChapter V: The Security Council (Articles 23-32)\nChapter VI: Pacific Settlement of Disputes (Articles 33-38)\nChapter VII: Action with Respect to Threats to the Peace, Breaches of the Peace, and  Acts of Aggression (Articles 39-51)\nChapter VIII: Regional Arrangements (Articles 52-54)\nChapter IX: International Economic and Social Cooperation (Articles 55-60)\nChapter X: The Economic and Social Council (Articles 61-72)\nChapter XI: Declaration Regarding Non-Self-Governing Territories (Articles 73-74)\nChapter XII: International Trusteeship System (Articles 75-85)\nChapter XIII: The Trusteeship Council (Articles 86-91)\nChapter XIV: The International Court of Justice (Articles 92-96)\nChapter XV: The Secretariat (Articles 97-101)\nChapter XVI: Miscellaneous Provisions (Articles 102-105)\nChapter XVII: Transitional Security Arrangements (Articles 106-107)\nChapter XVIII: Amendments (Articles 108-109)\n Chapter XIX: Ratification and Signature (Articles 110-111)\nAmendments to Articles 23, 27, 61, 109\n\n\n\nPreamble ›\n\nUN CharterPreambleChapter I: Purposes and Principles (Articles 1-2)Chapter II: Membership (Articles 3-6)Chapter III: Organs (Articles 7-8)Chapter IV: The General Assembly (Articles 9-22) Chapter V: The Security Council (Articles 23-32)Chapter VI: Pacific Settlement of Disputes (Articles 33-38)Chapter VII: Action with Respect to Threats to the Peace, Breaches of the Peace, and  Acts of Aggression (Articles 39-51)Chapter VIII: Regional Arrangements (Articles 52-54)Chapter IX: International Economic and Social Cooperation (Articles 55-60)Chapter X: The Economic and Social Council (Articles 61-72)Chapter XI: Declaration Regarding Non-Self-Governing Territories (Articles 73-74)Chapter XII: International Trusteeship System (Articles 75-85)Chapter XIII: The Trusteeship Council (Articles 86-91)Chapter XIV: The International Court of Justice (Articles 92-96)Chapter XV: The Secretariat (Articles 97-101)Chapter XVI: Miscellaneous Provisions (Articles 102-105)Chapter XVII: Transitional Security Arrangements (Articles 106-107)Chapter XVIII: Amendments (Articles 108-109) Chapter XIX: Ratification and Signature (Articles 110-111)Amendments to Articles 23, 27, 61, 109 \n\n\n\n \n\nUnited Nations Charter\nThe Charter of the United Nations is the founding document of the United Nations. It was signed on 26 June 1945, in San Francisco, at the conclusion of the United Nations Conference on International Organization, and came into force on 24 October 1945.\nThe United Nations can take action on a wide variety of issues due to its unique international character and the powers vested in its Charter, which is considered an international treaty. As such, the UN Charter is an instrument of international law, and UN Member States are bound by it. The UN Charter codifies the major principles of international relations, from sovereign equality of States to the prohibition of the use of force in international relations.\nSince the UN's founding in 1945, the mission and work of the Organization have been guided by the purposes and principles contained in its founding Charter, which has been amended three times in 1963, 1965, and 1973.\nThe International Court of Justice, the principal judicial organ of the United Nations, functions in accordance with the Statute of the International Court of Justice, which is annexed to the UN Charter, and forms an integral part of it. (See Chapter XIV, Article 92) \n\nFind the full text of the UN Charter, or read about the history of its making. Listen to a reading of the Preamble.\n\n\nBuy the UN Charter\nA booklet is available for purchase. This redesigned edition for the UN’s 70th anniversary features a new introduction titled “From War to Peace,” exclusive archival photos and the Statute of the International Court of Justice.\n\n\nUN Audiovisual Library\nWatch historical footage of the signing of the UN Charter Documentary about the founding of the United Nations Organization and the San Francisco Conference in 1945\n\n\nFanfare for All Peoples\nThis film, set against the stirring words of the Preamble of the United Nations Charter, premiered to an audience of Heads of States from around the world. Fanfare incorporates six languages and incorporates cutting-edge drone footage and breathtaking aerial photography with an inspiring original symphonic score.\n\n\n \n\n\n \n  Outline UN CharterPreamble\nChapter I: Purposes and Principles (Articles 1-2)\nChapter II: Membership (Articles 3-6)\nChapter III: Organs (Articles 7-8)\nChapter IV: The General Assembly (Articles 9-22) \nChapter V: The Security Council (Articles 23-32)\nChapter VI: Pacific Settlement of Disputes (Articles 33-38)\nChapter VII: Action with Respect to Threats to the Peace, Breaches of the Peace, and  Acts of Aggression (Articles 39-51)\nChapter VIII: Regional Arrangements (Articles 52-54)\nChapter IX: International Economic and Social Cooperation (Articles 55-60)\nChapter X: The Economic and Social Council (Articles 61-72)\nChapter XI: Declaration Regarding Non-Self-Governing Territories (Articles 73-74)\nChapter XII: International Trusteeship System (Articles 75-85)\nChapter XIII: The Trusteeship Council (Articles 86-91)\nChapter XIV: The International Court of Justice (Articles 92-96)\nChapter XV: The Secretariat (Articles 97-101)\nChapter XVI: Miscellaneous Provisions (Articles 102-105)\nChapter XVII: Transitional Security Arrangements (Articles 106-107)\nChapter XVIII: Amendments (Articles 108-109)\n Chapter XIX: Ratification and Signature (Articles 110-111)\nAmendments to Articles 23, 27, 61, 109\n\n\n\nPreamble ›\n\nUN CharterPreambleChapter I: Purposes and Principles (Articles 1-2)Chapter II: Membership (Articles 3-6)Chapter III: Organs (Articles 7-8)Chapter IV: The General Assembly (Articles 9-22) Chapter V: The Security Council (Articles 23-32)Chapter VI: Pacific Settlement of Disputes (Articles 33-38)Chapter VII: Action with Respect to Threats to the Peace, Breaches of the Peace, and  Acts of Aggression (Articles 39-51)Chapter VIII: Regional Arrangements (Articles 52-54)Chapter IX: International Economic and Social Cooperation (Articles 55-60)Chapter X: The Economic and Social Council (Articles 61-72)Chapter XI: Declaration Regarding Non-Self-Governing Territories (Articles 73-74)Chapter XII: International Trusteeship System (Articles 75-85)Chapter XIII: The Trusteeship Council (Articles 86-91)Chapter XIV: The International Court of Justice (Articles 92-96)Chapter XV: The Secretariat (Articles 97-101)Chapter XVI: Miscellaneous Provisions (Articles 102-105)Chapter XVII: Transitional Security Arrangements (Articles 106-107)Chapter XVIII: Amendments (Articles 108-109) Chapter XIX: Ratification and Signature (Articles 110-111)Amendments to Articles 23, 27, 61, 109 \n\n\n\n \n\nUnited Nations Charter\nThe Charter of the United Nations is the founding document of the United Nations. It was signed on 26 June 1945, in San Francisco, at the conclusion of the United Nations Conference on International Organization, and came into force on 24 October 1945.\nThe United Nations can take action on a wide variety of issues due to its unique international character and the powers vested in its Charter, which is considered an international treaty. As such, the UN Charter is an instrument of international law, and UN Member States are bound by it. The UN Charter codifies the major principles of international relations, from sovereign equality of States to the prohibition of the use of force in international relations.\nSince the UN's founding in 1945, the mission and work of the Organization have been guided by the purposes and principles contained in its founding Charter, which has been amended three times in 1963, 1965, and 1973.\nThe International Court of Justice, the principal judicial organ of the United Nations, functions in accordance with the Statute of the International Court of Justice, which is annexed to the UN Charter, and forms an integral part of it. (See Chapter XIV, Article 92) \n\nFind the full text of the UN Charter, or read about the history of its making. Listen to a reading of the Preamble.\n\n\nBuy the UN Charter\nA booklet is available for purchase. This redesigned edition for the UN’s 70th anniversary features a new introduction titled “From War to Peace,” exclusive archival photos and the Statute of the International Court of Justice.\n\n\nUN Audiovisual Library\nWatch historical footage of the signing of the UN Charter Documentary about the founding of the United Nations Organization and the San Francisco Conference in 1945\n\n\nFanfare for All Peoples\nThis film, set against the stirring words of the Preamble of the United Nations Charter, premiered to an audience of Heads of States from around the world. Fanfare incorporates six languages and incorporates cutting-edge drone footage and breathtaking aerial photography with an inspiring original symphonic score.\n\n\n \n\n\n \n  Outline UN CharterPreamble\nChapter I: Purposes and Principles (Articles 1-2)\nChapter II: Membership (Articles 3-6)\nChapter III: Organs (Articles 7-8)\nChapter IV: The General Assembly (Articles 9-22) \nChapter V: The Security Council (Articles 23-32)\nChapter VI: Pacific Settlement of Disputes (Articles 33-38)\nChapter VII: Action with Respect to Threats to the Peace, Breaches of the Peace, and  Acts of Aggression (Articles 39-51)\nChapter VIII: Regional Arrangements (Articles 52-54)\nChapter IX: International Economic and Social Cooperation (Articles 55-60)\nChapter X: The Economic and Social Council (Articles 61-72)\nChapter XI: Declaration Regarding Non-Self-Governing Territories (Articles 73-74)\nChapter XII: International Trusteeship System (Articles 75-85)\nChapter XIII: The Trusteeship Council (Articles 86-91)\nChapter XIV: The International Court of Justice (Articles 92-96)\nChapter XV: The Secretariat (Articles 97-101)\nChapter XVI: Miscellaneous Provisions (Articles 102-105)\nChapter XVII: Transitional Security Arrangements (Articles 106-107)\nChapter XVIII: Amendments (Articles 108-109)\n Chapter XIX: Ratification and Signature (Articles 110-111)\nAmendments to Articles 23, 27, 61, 109\n\n\n\nPreamble ›\n\nUN CharterPreambleChapter I: Purposes and Principles (Articles 1-2)Chapter II: Membership (Articles 3-6)Chapter III: Organs (Articles 7-8)Chapter IV: The General Assembly (Articles 9-22) Chapter V: The Security Council (Articles 23-32)Chapter VI: Pacific Settlement of Disputes (Articles 33-38)Chapter VII: Action with Respect to Threats to the Peace, Breaches of the Peace, and  Acts of Aggression (Articles 39-51)Chapter VIII: Regional Arrangements (Articles 52-54)Chapter IX: International Economic and Social Cooperation (Articles 55-60)Chapter X: The Economic and Social Council (Articles 61-72)Chapter XI: Declaration Regarding Non-Self-Governing Territories (Articles 73-74)Chapter XII: International Trusteeship System (Articles 75-85)Chapter XIII: The Trusteeship Council (Articles 86-91)Chapter XIV: The International Court of Justice (Articles 92-96)Chapter XV: The Secretariat (Articles 97-101)Chapter XVI: Miscellaneous Provisions (Articles 102-105)Chapter XVII: Transitional Security Arrangements (Articles 106-107)Chapter XVIII: Amendments (Articles 108-109) Chapter XIX: Ratification and Signature (Articles 110-111)Amendments to Articles 23, 27, 61, 109 \n\n\n\n \n\nUnited Nations Charter\nThe Charter of the United Nations is the founding document of the United Nations. It was signed on 26 June 1945, in San Francisco, at the conclusion of the United Nations Conference on International Organization, and came into force on 24 October 1945.\nThe United Nations can take action on a wide variety of issues due to its unique international character and the powers vested in its Charter, which is considered an international treaty. As such, the UN Charter is an instrument of international law, and UN Member States are bound by it. The UN Charter codifies the major principles of international relations, from sovereign equality of States to the prohibition of the use of force in international relations.\nSince the UN's founding in 1945, the mission and work of the Organization have been guided by the purposes and principles contained in its founding Charter, which has been amended three times in 1963, 1965, and 1973.\nThe International Court of Justice, the principal judicial organ of the United Nations, functions in accordance with the Statute of the International Court of Justice, which is annexed to the UN Charter, and forms an integral part of it. (See Chapter XIV, Article 92) \n\nFind the full text of the UN Charter, or read about the history of its making. Listen to a reading of the Preamble.\n\n\nBuy the UN Charter\nA booklet is available for purchase. This redesigned edition for the UN’s 70th anniversary features a new introduction titled “From War to Peace,” exclusive archival photos and the Statute of the International Court of Justice.\n\n\nUN Audiovisual Library\nWatch historical footage of the signing of the UN Charter Documentary about the founding of the United Nations Organization and the San Francisco Conference in 1945\n\n\nFanfare for All Peoples\nThis film, set against the stirring words of the Preamble of the United Nations Charter, premiered to an audience of Heads of States from around the world. Fanfare incorporates six languages and incorporates cutting-edge drone footage and breathtaking aerial photography with an inspiring original symphonic score.\n\n\n \n\n\n \n  Outline UN CharterPreamble\nChapter I: Purposes and Principles (Articles 1-2)\nChapter II: Membership (Articles 3-6)\nChapter III: Organs (Articles 7-8)\nChapter IV: The General Assembly (Articles 9-22) \nChapter V: The Security Council (Articles 23-32)\nChapter VI: Pacific Settlement of Disputes (Articles 33-38)\nChapter VII: Action with Respect to Threats to the Peace, Breaches of the Peace, and  Acts of Aggression (Articles 39-51)\nChapter VIII: Regional Arrangements (Articles 52-54)\nChapter IX: International Economic and Social Cooperation (Articles 55-60)\nChapter X: The Economic and Social Council (Articles 61-72)\nChapter XI: Declaration Regarding Non-Self-Governing Territories (Articles 73-74)\nChapter XII: International Trusteeship System (Articles 75-85)\nChapter XIII: The Trusteeship Council (Articles 86-91)\nChapter XIV: The International Court of Justice (Articles 92-96)\nChapter XV: The Secretariat (Articles 97-101)\nChapter XVI: Miscellaneous Provisions (Articles 102-105)\nChapter XVII: Transitional Security Arrangements (Articles 106-107)\nChapter XVIII: Amendments (Articles 108-109)\n Chapter XIX: Ratification and Signature (Articles 110-111)\nAmendments to Articles 23, 27, 61, 109\n\n\n\nPreamble ›\n\nUN CharterPreambleChapter I: Purposes and Principles (Articles 1-2)Chapter II: Membership (Articles 3-6)Chapter III: Organs (Articles 7-8)Chapter IV: The General Assembly (Articles 9-22) Chapter V: The Security Council (Articles 23-32)Chapter VI: Pacific Settlement of Disputes (Articles 33-38)Chapter VII: Action with Respect to Threats to the Peace, Breaches of the Peace, and  Acts of Aggression (Articles 39-51)Chapter VIII: Regional Arrangements (Articles 52-54)Chapter IX: International Economic and Social Cooperation (Articles 55-60)Chapter X: The Economic and Social Council (Articles 61-72)Chapter XI: Declaration Regarding Non-Self-Governing Territories (Articles 73-74)Chapter XII: International Trusteeship System (Articles 75-85)Chapter XIII: The Trusteeship Council (Articles 86-91)Chapter XIV: The International Court of Justice (Articles 92-96)Chapter XV: The Secretariat (Articles 97-101)Chapter XVI: Miscellaneous Provisions (Articles 102-105)Chapter XVII: Transitional Security Arrangements (Articles 106-107)Chapter XVIII: Amendments (Articles 108-109) Chapter XIX: Ratification and Signature (Articles 110-111)Amendments to Articles 23, 27, 61, 109\n\nUN CharterPreambleChapter I: Purposes and Principles (Articles 1-2)Chapter II: Membership (Articles 3-6)Chapter III: Organs (Articles 7-8)Chapter IV: The General Assembly (Articles 9-22) Chapter V: The Security Council (Articles 23-32)Chapter VI: Pacific Settlement of Disputes (Articles 33-38)Chapter VII: Action with Respect to Threats to the Peace, Breaches of the Peace, and  Acts of Aggression (Articles 39-51)Chapter VIII: Regional Arrangements (Articles 52-54)Chapter IX: International Economic and Social Cooperation (Articles 55-60)Chapter X: The Economic and Social Council (Articles 61-72)Chapter XI: Declaration Regarding Non-Self-Governing Territories (Articles 73-74)Chapter XII: International Trusteeship System (Articles 75-85)Chapter XIII: The Trusteeship Council (Articles 86-91)Chapter XIV: The International Court of Justice (Articles 92-96)Chapter XV: The Secretariat (Articles 97-101)Chapter XVI: Miscellaneous Provisions (Articles 102-105)Chapter XVII: Transitional Security Arrangements (Articles 106-107)Chapter XVIII: Amendments (Articles 108-109) Chapter XIX: Ratification and Signature (Articles 110-111)Amendments to Articles 23, 27, 61, 109\n\nUnited Nations Charter\nThe Charter of the United Nations is the founding document of the United Nations. It was signed on 26 June 1945, in San Francisco, at the conclusion of the United Nations Conference on International Organization, and came into force on 24 October 1945.\nThe United Nations can take action on a wide variety of issues due to its unique international character and the powers vested in its Charter, which is considered an international treaty. As such, the UN Charter is an instrument of international law, and UN Member States are bound by it. The UN Charter codifies the major principles of international relations, from sovereign equality of States to the prohibition of the use of force in international relations.\nSince the UN's founding in 1945, the mission and work of the Organization have been guided by the purposes and principles contained in its founding Charter, which has been amended three times in 1963, 1965, and 1973.\nThe International Court of Justice, the principal judicial organ of the United Nations, functions in accordance with the Statute of the International Court of Justice, which is annexed to the UN Charter, and forms an integral part of it. (See Chapter XIV, Article 92) \n\nFind the full text of the UN Charter, or read about the history of its making. Listen to a reading of the Preamble.\n\n\nBuy the UN Charter\nA booklet is available for purchase. This redesigned edition for the UN’s 70th anniversary features a new introduction titled “From War to Peace,” exclusive archival photos and the Statute of the International Court of Justice.\n\n\nUN Audiovisual Library\nWatch historical footage of the signing of the UN Charter Documentary about the founding of the United Nations Organization and the San Francisco Conference in 1945\n\n\nFanfare for All Peoples\nThis film, set against the stirring words of the Preamble of the United Nations Charter, premiered to an audience of Heads of States from around the world. Fanfare incorporates six languages and incorporates cutting-edge drone footage and breathtaking aerial photography with an inspiring original symphonic score.\n\n\n \n\n\n \n  Outline UN CharterPreamble\nChapter I: Purposes and Principles (Articles 1-2)\nChapter II: Membership (Articles 3-6)\nChapter III: Organs (Articles 7-8)\nChapter IV: The General Assembly (Articles 9-22) \nChapter V: The Security Council (Articles 23-32)\nChapter VI: Pacific Settlement of Disputes (Articles 33-38)\nChapter VII: Action with Respect to Threats to the Peace, Breaches of the Peace, and  Acts of Aggression (Articles 39-51)\nChapter VIII: Regional Arrangements (Articles 52-54)\nChapter IX: International Economic and Social Cooperation (Articles 55-60)\nChapter X: The Economic and Social Council (Articles 61-72)\nChapter XI: Declaration Regarding Non-Self-Governing Territories (Articles 73-74)\nChapter XII: International Trusteeship System (Articles 75-85)\nChapter XIII: The Trusteeship Council (Articles 86-91)\nChapter XIV: The International Court of Justice (Articles 92-96)\nChapter XV: The Secretariat (Articles 97-101)\nChapter XVI: Miscellaneous Provisions (Articles 102-105)\nChapter XVII: Transitional Security Arrangements (Articles 106-107)\nChapter XVIII: Amendments (Articles 108-109)\n Chapter XIX: Ratification and Signature (Articles 110-111)\nAmendments to Articles 23, 27, 61, 109\n\n\n\nPreamble ›\n\nUnited Nations Charter\nThe Charter of the United Nations is the founding document of the United Nations. It was signed on 26 June 1945, in San Francisco, at the conclusion of the United Nations Conference on International Organization, and came into force on 24 October 1945.\nThe United Nations can take action on a wide variety of issues due to its unique international character and the powers vested in its Charter, which is considered an international treaty. As such, the UN Charter is an instrument of international law, and UN Member States are bound by it. The UN Charter codifies the major principles of international relations, from sovereign equality of States to the prohibition of the use of force in international relations.\nSince the UN's founding in 1945, the mission and work of the Organization have been guided by the purposes and principles contained in its founding Charter, which has been amended three times in 1963, 1965, and 1973.\nThe International Court of Justice, the principal judicial organ of the United Nations, functions in accordance with the Statute of the International Court of Justice, which is annexed to the UN Charter, and forms an integral part of it. (See Chapter XIV, Article 92) \n\nFind the full text of the UN Charter, or read about the history of its making. Listen to a reading of the Preamble.\n\n\nBuy the UN Charter\nA booklet is available for purchase. This redesigned edition for the UN’s 70th anniversary features a new introduction titled “From War to Peace,” exclusive archival photos and the Statute of the International Court of Justice.\n\n\nUN Audiovisual Library\nWatch historical footage of the signing of the UN Charter Documentary about the founding of the United Nations Organization and the San Francisco Conference in 1945\n\n\nFanfare for All Peoples\nThis film, set against the stirring words of the Preamble of the United Nations Charter, premiered to an audience of Heads of States from around the world. Fanfare incorporates six languages and incorporates cutting-edge drone footage and breathtaking aerial photography with an inspiring original symphonic score.\n\nUnited Nations Charter\nThe Charter of the United Nations is the founding document of the United Nations. It was signed on 26 June 1945, in San Francisco, at the conclusion of the United Nations Conference on International Organization, and came into force on 24 October 1945.\nThe United Nations can take action on a wide variety of issues due to its unique international character and the powers vested in its Charter, which is considered an international treaty. As such, the UN Charter is an instrument of international law, and UN Member States are bound by it. The UN Charter codifies the major principles of international relations, from sovereign equality of States to the prohibition of the use of force in international relations.\nSince the UN's founding in 1945, the mission and work of the Organization have been guided by the purposes and principles contained in its founding Charter, which has been amended three times in 1963, 1965, and 1973.\nThe International Court of Justice, the principal judicial organ of the United Nations, functions in accordance with the Statute of the International Court of Justice, which is annexed to the UN Charter, and forms an integral part of it. (See Chapter XIV, Article 92) \n\nFind the full text of the UN Charter, or read about the history of its making. Listen to a reading of the Preamble.\n\n\nBuy the UN Charter\nA booklet is available for purchase. This redesigned edition for the UN’s 70th anniversary features a new introduction titled “From War to Peace,” exclusive archival photos and the Statute of the International Court of Justice.\n\n\nUN Audiovisual Library\nWatch historical footage of the signing of the UN Charter Documentary about the founding of the United Nations Organization and the San Francisco Conference in 1945\n\n\nFanfare for All Peoples\nThis film, set against the stirring words of the Preamble of the United Nations Charter, premiered to an audience of Heads of States from around the world. Fanfare incorporates six languages and incorporates cutting-edge drone footage and breathtaking aerial photography with an inspiring original symphonic score.\n\nUnited Nations Charter\nThe Charter of the United Nations is the founding document of the United Nations. It was signed on 26 June 1945, in San Francisco, at the conclusion of the United Nations Conference on International Organization, and came into force on 24 October 1945.\nThe United Nations can take action on a wide variety of issues due to its unique international character and the powers vested in its Charter, which is considered an international treaty. As such, the UN Charter is an instrument of international law, and UN Member States are bound by it. The UN Charter codifies the major principles of international relations, from sovereign equality of States to the prohibition of the use of force in international relations.\nSince the UN's founding in 1945, the mission and work of the Organization have been guided by the purposes and principles contained in its founding Charter, which has been amended three times in 1963, 1965, and 1973.\nThe International Court of Justice, the principal judicial organ of the United Nations, functions in accordance with the Statute of the International Court of Justice, which is annexed to the UN Charter, and forms an integral part of it. (See Chapter XIV, Article 92) \n\nFind the full text of the UN Charter, or read about the history of its making. Listen to a reading of the Preamble.\n\n\nBuy the UN Charter\nA booklet is available for purchase. This redesigned edition for the UN’s 70th anniversary features a new introduction titled “From War to Peace,” exclusive archival photos and the Statute of the International Court of Justice.\n\n\nUN Audiovisual Library\nWatch historical footage of the signing of the UN Charter Documentary about the founding of the United Nations Organization and the San Francisco Conference in 1945\n\n\nFanfare for All Peoples\nThis film, set against the stirring words of the Preamble of the United Nations Charter, premiered to an audience of Heads of States from around the world. Fanfare incorporates six languages and incorporates cutting-edge drone footage and breathtaking aerial photography with an inspiring original symphonic score.\n\nUnited Nations Charter\nThe Charter of the United Nations is the founding document of the United Nations. It was signed on 26 June 1945, in San Francisco, at the conclusion of the United Nations Conference on International Organization, and came into force on 24 October 1945.\nThe United Nations can take action on a wide variety of issues due to its unique international character and the powers vested in its Charter, which is considered an international treaty. As such, the UN Charter is an instrument of international law, and UN Member States are bound by it. The UN Charter codifies the major principles of international relations, from sovereign equality of States to the prohibition of the use of force in international relations.\nSince the UN's founding in 1945, the mission and work of the Organization have been guided by the purposes and principles contained in its founding Charter, which has been amended three times in 1963, 1965, and 1973.\nThe International Court of Justice, the principal judicial organ of the United Nations, functions in accordance with the Statute of the International Court of Justice, which is annexed to the UN Charter, and forms an integral part of it. (See Chapter XIV, Article 92) \n\nFind the full text of the UN Charter, or read about the history of its making. Listen to a reading of the Preamble.\n\n\nBuy the UN Charter\nA booklet is available for purchase. This redesigned edition for the UN’s 70th anniversary features a new introduction titled “From War to Peace,” exclusive archival photos and the Statute of the International Court of Justice.\n\n\nUN Audiovisual Library\nWatch historical footage of the signing of the UN Charter Documentary about the founding of the United Nations Organization and the San Francisco Conference in 1945\n\n\nFanfare for All Peoples\nThis film, set against the stirring words of the Preamble of the United Nations Charter, premiered to an audience of Heads of States from around the world. Fanfare incorporates six languages and incorporates cutting-edge drone footage and breathtaking aerial photography with an inspiring original symphonic score.\n\nUnited Nations Charter\nThe Charter of the United Nations is the founding document of the United Nations. It was signed on 26 June 1945, in San Francisco, at the conclusion of the United Nations Conference on International Organization, and came into force on 24 October 1945.\nThe United Nations can take action on a wide variety of issues due to its unique international character and the powers vested in its Charter, which is considered an international treaty. As such, the UN Charter is an instrument of international law, and UN Member States are bound by it. The UN Charter codifies the major principles of international relations, from sovereign equality of States to the prohibition of the use of force in international relations.\nSince the UN's founding in 1945, the mission and work of the Organization have been guided by the purposes and principles contained in its founding Charter, which has been amended three times in 1963, 1965, and 1973.\nThe International Court of Justice, the principal judicial organ of the United Nations, functions in accordance with the Statute of the International Court of Justice, which is annexed to the UN Charter, and forms an integral part of it. (See Chapter XIV, Article 92) \n\nFind the full text of the UN Charter, or read about the history of its making. Listen to a reading of the Preamble.\n\n\nBuy the UN Charter\nA booklet is available for purchase. This redesigned edition for the UN’s 70th anniversary features a new introduction titled “From War to Peace,” exclusive archival photos and the Statute of the International Court of Justice.\n\n\nUN Audiovisual Library\nWatch historical footage of the signing of the UN Charter Documentary about the founding of the United Nations Organization and the San Francisco Conference in 1945\n\n\nFanfare for All Peoples\nThis film, set against the stirring words of the Preamble of the United Nations Charter, premiered to an audience of Heads of States from around the world. Fanfare incorporates six languages and incorporates cutting-edge drone footage and breathtaking aerial photography with an inspiring original symphonic score.\n\nThe Charter of the United Nations is the founding document of the United Nations. It was signed on 26 June 1945, in San Francisco, at the conclusion of the United Nations Conference on International Organization, and came into force on 24 October 1945.\n\nThe United Nations can take action on a wide variety of issues due to its unique international character and the powers vested in its Charter, which is considered an international treaty. As such, the UN Charter is an instrument of international law, and UN Member States are bound by it. The UN Charter codifies the major principles of international relations, from sovereign equality of States to the prohibition of the use of force in international relations.\n\nSince the UN's founding in 1945, the mission and work of the Organization have been guided by the purposes and principles contained in its founding Charter, which has been amended three times in 1963, 1965, and 1973.\n\nThe International Court of Justice, the principal judicial organ of the United Nations, functions in accordance with the Statute of the International Court of Justice, which is annexed to the UN Charter, and forms an integral part of it. (See Chapter XIV, Article 92)\n\nFind the full text of the UN Charter, or read about the history of its making. Listen to a reading of the Preamble.\n\nBuy the UN Charter\nA booklet is available for purchase. This redesigned edition for the UN’s 70th anniversary features a new introduction titled “From War to Peace,” exclusive archival photos and the Statute of the International Court of Justice.\n\n\nUN Audiovisual Library\nWatch historical footage of the signing of the UN Charter Documentary about the founding of the United Nations Organization and the San Francisco Conference in 1945\n\n\nFanfare for All Peoples\nThis film, set against the stirring words of the Preamble of the United Nations Charter, premiered to an audience of Heads of States from around the world. Fanfare incorporates six languages and incorporates cutting-edge drone footage and breathtaking aerial photography with an inspiring original symphonic score.\n\nBuy the UN Charter\nA booklet is available for purchase. This redesigned edition for the UN’s 70th anniversary features a new introduction titled “From War to Peace,” exclusive archival photos and the Statute of the International Court of Justice.\n\nA booklet is available for purchase. This redesigned edition for the UN’s 70th anniversary features a new introduction titled “From War to Peace,” exclusive archival photos and the Statute of the International Court of Justice.\n\nUN Audiovisual Library\nWatch historical footage of the signing of the UN Charter Documentary about the founding of the United Nations Organization and the San Francisco Conference in 1945\n\nWatch historical footage of the signing of the UN Charter Documentary about the founding of the United Nations Organization and the San Francisco Conference in 1945\n\nFanfare for All Peoples\nThis film, set against the stirring words of the Preamble of the United Nations Charter, premiered to an audience of Heads of States from around the world. Fanfare incorporates six languages and incorporates cutting-edge drone footage and breathtaking aerial photography with an inspiring original symphonic score.\n\nThis film, set against the stirring words of the Preamble of the United Nations Charter, premiered to an audience of Heads of States from around the world. Fanfare incorporates six languages and incorporates cutting-edge drone footage and breathtaking aerial photography with an inspiring original symphonic score.\n\nOutline UN CharterPreamble\nChapter I: Purposes and Principles (Articles 1-2)\nChapter II: Membership (Articles 3-6)\nChapter III: Organs (Articles 7-8)\nChapter IV: The General Assembly (Articles 9-22) \nChapter V: The Security Council (Articles 23-32)\nChapter VI: Pacific Settlement of Disputes (Articles 33-38)\nChapter VII: Action with Respect to Threats to the Peace, Breaches of the Peace, and  Acts of Aggression (Articles 39-51)\nChapter VIII: Regional Arrangements (Articles 52-54)\nChapter IX: International Economic and Social Cooperation (Articles 55-60)\nChapter X: The Economic and Social Council (Articles 61-72)\nChapter XI: Declaration Regarding Non-Self-Governing Territories (Articles 73-74)\nChapter XII: International Trusteeship System (Articles 75-85)\nChapter XIII: The Trusteeship Council (Articles 86-91)\nChapter XIV: The International Court of Justice (Articles 92-96)\nChapter XV: The Secretariat (Articles 97-101)\nChapter XVI: Miscellaneous Provisions (Articles 102-105)\nChapter XVII: Transitional Security Arrangements (Articles 106-107)\nChapter XVIII: Amendments (Articles 108-109)\n Chapter XIX: Ratification and Signature (Articles 110-111)\nAmendments to Articles 23, 27, 61, 109\n\n\n\nPreamble ›\n\nOutline UN CharterPreamble\nChapter I: Purposes and Principles (Articles 1-2)\nChapter II: Membership (Articles 3-6)\nChapter III: Organs (Articles 7-8)\nChapter IV: The General Assembly (Articles 9-22) \nChapter V: The Security Council (Articles 23-32)\nChapter VI: Pacific Settlement of Disputes (Articles 33-38)\nChapter VII: Action with Respect to Threats to the Peace, Breaches of the Peace, and  Acts of Aggression (Articles 39-51)\nChapter VIII: Regional Arrangements (Articles 52-54)\nChapter IX: International Economic and Social Cooperation (Articles 55-60)\nChapter X: The Economic and Social Council (Articles 61-72)\nChapter XI: Declaration Regarding Non-Self-Governing Territories (Articles 73-74)\nChapter XII: International Trusteeship System (Articles 75-85)\nChapter XIII: The Trusteeship Council (Articles 86-91)\nChapter XIV: The International Court of Justice (Articles 92-96)\nChapter XV: The Secretariat (Articles 97-101)\nChapter XVI: Miscellaneous Provisions (Articles 102-105)\nChapter XVII: Transitional Security Arrangements (Articles 106-107)\nChapter XVIII: Amendments (Articles 108-109)\n Chapter XIX: Ratification and Signature (Articles 110-111)\nAmendments to Articles 23, 27, 61, 109\n\nMain Bodies   General Assembly   Security Council   Economic and Social Council   Trusteeship Council   International Court of Justice   Secretariat       Departments / Offices   New York   Geneva   Nairobi   Vienna   UN System Directory   UN System Chart   Global Leadership   UN Information Centres       Resources / Services   Emergency information   Reporting Wrongdoing   UN Journal   Documents   Guidelines for gender-inclusive language   Databases   Library   UN iLibrary   UN Chronicle   UN Yearbook   Bookshop   Publications for sale   Maps   Media Accreditation   NGO accreditation at ECOSOC   NGO accreditation at DGC   Visitors’ services   Exhibits   Procurement   Employment   Internships   Model UN   Academic Impact   UN Archives   UN Audiovisual Library   How to donate to the UN system   Information on COVID-19 (Coronavirus)   Africa Renewal   Ten ways the UN makes a difference   GA High-level week 2024       Key Documents   UN Charter   Universal Declaration of Human Rights   Convention on the Rights of the Child   Statute of the International Court of Justice   Annual Report of the Secretary-General on the Work of the Organization       News and Media   News   Press Releases   Briefings   Spokesperson   Photos   UNIfeed   UN Web TV   UN Video   Social Media   The Essential UN   Awake at Night podcast       Issues / Campaigns   Global Issues   Observances   Sustainable Development Goals   Our Common Agenda   The Summit of the Future   Climate Action   Peace and Security   Action for Peacekeeping (A4P)   Global Crisis Response Group   Call to Action for Human Rights   Disability Inclusion Strategy   Fight Racism   Hate Speech   LGBTIQ+ People   Safety of Journalists   Rule of Law   Action to Counter Terrorism   Victims of Terrorism   Children and Armed Conflict   Violence Against Children (SRSG)   Sexual Violence in Conflict   Refugees and Migrants   Action Agenda on Internal Displacement   Spotlight Initiative   Preventing Sexual Exploitation and Abuse   Prevention of Genocide and the Responsibility to Protect   The Rwanda Genocide   The Holocaust   The Question of Palestine   The Transatlantic Slave Trade   Decolonization   Messengers of Peace   Roadmap for Digital Cooperation   Digital Financing Task Force   Data Strategy   Information Integrity   Countering Disinformation   UN75: 2020 and Beyond   Women Rise for All   Stop the Red Sea Catastrophe   Black Sea Grain Initiative Joint Coordination Centre\n\nMain Bodies   General Assembly   Security Council   Economic and Social Council   Trusteeship Council   International Court of Justice   Secretariat       Departments / Offices   New York   Geneva   Nairobi   Vienna   UN System Directory   UN System Chart   Global Leadership   UN Information Centres       Resources / Services   Emergency information   Reporting Wrongdoing   UN Journal   Documents   Guidelines for gender-inclusive language   Databases   Library   UN iLibrary   UN Chronicle   UN Yearbook   Bookshop   Publications for sale   Maps   Media Accreditation   NGO accreditation at ECOSOC   NGO accreditation at DGC   Visitors’ services   Exhibits   Procurement   Employment   Internships   Model UN   Academic Impact   UN Archives   UN Audiovisual Library   How to donate to the UN system   Information on COVID-19 (Coronavirus)   Africa Renewal   Ten ways the UN makes a difference   GA High-level week 2024       Key Documents   UN Charter   Universal Declaration of Human Rights   Convention on the Rights of the Child   Statute of the International Court of Justice   Annual Report of the Secretary-General on the Work of the Organization       News and Media   News   Press Releases   Briefings   Spokesperson   Photos   UNIfeed   UN Web TV   UN Video   Social Media   The Essential UN   Awake at Night podcast       Issues / Campaigns   Global Issues   Observances   Sustainable Development Goals   Our Common Agenda   The Summit of the Future   Climate Action   Peace and Security   Action for Peacekeeping (A4P)   Global Crisis Response Group   Call to Action for Human Rights   Disability Inclusion Strategy   Fight Racism   Hate Speech   LGBTIQ+ People   Safety of Journalists   Rule of Law   Action to Counter Terrorism   Victims of Terrorism   Children and Armed Conflict   Violence Against Children (SRSG)   Sexual Violence in Conflict   Refugees and Migrants   Action Agenda on Internal Displacement   Spotlight Initiative   Preventing Sexual Exploitation and Abuse   Prevention of Genocide and the Responsibility to Protect   The Rwanda Genocide   The Holocaust   The Question of Palestine   The Transatlantic Slave Trade   Decolonization   Messengers of Peace   Roadmap for Digital Cooperation   Digital Financing Task Force   Data Strategy   Information Integrity   Countering Disinformation   UN75: 2020 and Beyond   Women Rise for All   Stop the Red Sea Catastrophe   Black Sea Grain Initiative Joint Coordination Centre\n\nMain Bodies   General Assembly   Security Council   Economic and Social Council   Trusteeship Council   International Court of Justice   Secretariat       Departments / Offices   New York   Geneva   Nairobi   Vienna   UN System Directory   UN System Chart   Global Leadership   UN Information Centres       Resources / Services   Emergency information   Reporting Wrongdoing   UN Journal   Documents   Guidelines for gender-inclusive language   Databases   Library   UN iLibrary   UN Chronicle   UN Yearbook   Bookshop   Publications for sale   Maps   Media Accreditation   NGO accreditation at ECOSOC   NGO accreditation at DGC   Visitors’ services   Exhibits   Procurement   Employment   Internships   Model UN   Academic Impact   UN Archives   UN Audiovisual Library   How to donate to the UN system   Information on COVID-19 (Coronavirus)   Africa Renewal   Ten ways the UN makes a difference   GA High-level week 2024       Key Documents   UN Charter   Universal Declaration of Human Rights   Convention on the Rights of the Child   Statute of the International Court of Justice   Annual Report of the Secretary-General on the Work of the Organization       News and Media   News   Press Releases   Briefings   Spokesperson   Photos   UNIfeed   UN Web TV   UN Video   Social Media   The Essential UN   Awake at Night podcast       Issues / Campaigns   Global Issues   Observances   Sustainable Development Goals   Our Common Agenda   The Summit of the Future   Climate Action   Peace and Security   Action for Peacekeeping (A4P)   Global Crisis Response Group   Call to Action for Human Rights   Disability Inclusion Strategy   Fight Racism   Hate Speech   LGBTIQ+ People   Safety of Journalists   Rule of Law   Action to Counter Terrorism   Victims of Terrorism   Children and Armed Conflict   Violence Against Children (SRSG)   Sexual Violence in Conflict   Refugees and Migrants   Action Agenda on Internal Displacement   Spotlight Initiative   Preventing Sexual Exploitation and Abuse   Prevention of Genocide and the Responsibility to Protect   The Rwanda Genocide   The Holocaust   The Question of Palestine   The Transatlantic Slave Trade   Decolonization   Messengers of Peace   Roadmap for Digital Cooperation   Digital Financing Task Force   Data Strategy   Information Integrity   Countering Disinformation   UN75: 2020 and Beyond   Women Rise for All   Stop the Red Sea Catastrophe   Black Sea Grain Initiative Joint Coordination Centre\n\nMain Bodies   General Assembly   Security Council   Economic and Social Council   Trusteeship Council   International Court of Justice   Secretariat       Departments / Offices   New York   Geneva   Nairobi   Vienna   UN System Directory   UN System Chart   Global Leadership   UN Information Centres\n\nMain Bodies   General Assembly   Security Council   Economic and Social Council   Trusteeship Council   International Court of Justice   Secretariat\n\nMain Bodies   General Assembly   Security Council   Economic and Social Council   Trusteeship Council   International Court of Justice   Secretariat\n\nDepartments / Offices   New York   Geneva   Nairobi   Vienna   UN System Directory   UN System Chart   Global Leadership   UN Information Centres\n\nDepartments / Offices   New York   Geneva   Nairobi   Vienna   UN System Directory   UN System Chart   Global Leadership   UN Information Centres\n\nResources / Services   Emergency information   Reporting Wrongdoing   UN Journal   Documents   Guidelines for gender-inclusive language   Databases   Library   UN iLibrary   UN Chronicle   UN Yearbook   Bookshop   Publications for sale   Maps   Media Accreditation   NGO accreditation at ECOSOC   NGO accreditation at DGC   Visitors’ services   Exhibits   Procurement   Employment   Internships   Model UN   Academic Impact   UN Archives   UN Audiovisual Library   How to donate to the UN system   Information on COVID-19 (Coronavirus)   Africa Renewal   Ten ways the UN makes a difference   GA High-level week 2024\n\nResources / Services   Emergency information   Reporting Wrongdoing   UN Journal   Documents   Guidelines for gender-inclusive language   Databases   Library   UN iLibrary   UN Chronicle   UN Yearbook   Bookshop   Publications for sale   Maps   Media Accreditation   NGO accreditation at ECOSOC   NGO accreditation at DGC   Visitors’ services   Exhibits   Procurement   Employment   Internships   Model UN   Academic Impact   UN Archives   UN Audiovisual Library   How to donate to the UN system   Information on COVID-19 (Coronavirus)   Africa Renewal   Ten ways the UN makes a difference   GA High-level week 2024\n\nResources / Services   Emergency information   Reporting Wrongdoing   UN Journal   Documents   Guidelines for gender-inclusive language   Databases   Library   UN iLibrary   UN Chronicle   UN Yearbook   Bookshop   Publications for sale   Maps   Media Accreditation   NGO accreditation at ECOSOC   NGO accreditation at DGC   Visitors’ services   Exhibits   Procurement   Employment   Internships   Model UN   Academic Impact   UN Archives   UN Audiovisual Library   How to donate to the UN system   Information on COVID-19 (Coronavirus)   Africa Renewal   Ten ways the UN makes a difference   GA High-level week 2024\n\nKey Documents   UN Charter   Universal Declaration of Human Rights   Convention on the Rights of the Child   Statute of the International Court of Justice   Annual Report of the Secretary-General on the Work of the Organization       News and Media   News   Press Releases   Briefings   Spokesperson   Photos   UNIfeed   UN Web TV   UN Video   Social Media   The Essential UN   Awake at Night podcast\n\nKey Documents   UN Charter   Universal Declaration of Human Rights   Convention on the Rights of the Child   Statute of the International Court of Justice   Annual Report of the Secretary-General on the Work of the Organization\n\nKey Documents   UN Charter   Universal Declaration of Human Rights   Convention on the Rights of the Child   Statute of the International Court of Justice   Annual Report of the Secretary-General on the Work of the Organization\n\nNews and Media   News   Press Releases   Briefings   Spokesperson   Photos   UNIfeed   UN Web TV   UN Video   Social Media   The Essential UN   Awake at Night podcast\n\nNews and Media   News   Press Releases   Briefings   Spokesperson   Photos   UNIfeed   UN Web TV   UN Video   Social Media   The Essential UN   Awake at Night podcast\n\nIssues / Campaigns   Global Issues   Observances   Sustainable Development Goals   Our Common Agenda   The Summit of the Future   Climate Action   Peace and Security   Action for Peacekeeping (A4P)   Global Crisis Response Group   Call to Action for Human Rights   Disability Inclusion Strategy   Fight Racism   Hate Speech   LGBTIQ+ People   Safety of Journalists   Rule of Law   Action to Counter Terrorism   Victims of Terrorism   Children and Armed Conflict   Violence Against Children (SRSG)   Sexual Violence in Conflict   Refugees and Migrants   Action Agenda on Internal Displacement   Spotlight Initiative   Preventing Sexual Exploitation and Abuse   Prevention of Genocide and the Responsibility to Protect   The Rwanda Genocide   The Holocaust   The Question of Palestine   The Transatlantic Slave Trade   Decolonization   Messengers of Peace   Roadmap for Digital Cooperation   Digital Financing Task Force   Data Strategy   Information Integrity   Countering Disinformation   UN75: 2020 and Beyond   Women Rise for All   Stop the Red Sea Catastrophe   Black Sea Grain Initiative Joint Coordination Centre\n\nIssues / Campaigns   Global Issues   Observances   Sustainable Development Goals   Our Common Agenda   The Summit of the Future   Climate Action   Peace and Security   Action for Peacekeeping (A4P)   Global Crisis Response Group   Call to Action for Human Rights   Disability Inclusion Strategy   Fight Racism   Hate Speech   LGBTIQ+ People   Safety of Journalists   Rule of Law   Action to Counter Terrorism   Victims of Terrorism   Children and Armed Conflict   Violence Against Children (SRSG)   Sexual Violence in Conflict   Refugees and Migrants   Action Agenda on Internal Displacement   Spotlight Initiative   Preventing Sexual Exploitation and Abuse   Prevention of Genocide and the Responsibility to Protect   The Rwanda Genocide   The Holocaust   The Question of Palestine   The Transatlantic Slave Trade   Decolonization   Messengers of Peace   Roadmap for Digital Cooperation   Digital Financing Task Force   Data Strategy   Information Integrity   Countering Disinformation   UN75: 2020 and Beyond   Women Rise for All   Stop the Red Sea Catastrophe   Black Sea Grain Initiative Joint Coordination Centre\n\nIssues / Campaigns   Global Issues   Observances   Sustainable Development Goals   Our Common Agenda   The Summit of the Future   Climate Action   Peace and Security   Action for Peacekeeping (A4P)   Global Crisis Response Group   Call to Action for Human Rights   Disability Inclusion Strategy   Fight Racism   Hate Speech   LGBTIQ+ People   Safety of Journalists   Rule of Law   Action to Counter Terrorism   Victims of Terrorism   Children and Armed Conflict   Violence Against Children (SRSG)   Sexual Violence in Conflict   Refugees and Migrants   Action Agenda on Internal Displacement   Spotlight Initiative   Preventing Sexual Exploitation and Abuse   Prevention of Genocide and the Responsibility to Protect   The Rwanda Genocide   The Holocaust   The Question of Palestine   The Transatlantic Slave Trade   Decolonization   Messengers of Peace   Roadmap for Digital Cooperation   Digital Financing Task Force   Data Strategy   Information Integrity   Countering Disinformation   UN75: 2020 and Beyond   Women Rise for All   Stop the Red Sea Catastrophe   Black Sea Grain Initiative Joint Coordination Centre",
  "date": "",
  "source_type": "UN_organization",
  "extracted_at": "2025-04-07T13:52:45.367816",
  "metadata": {
    "description": "The Charter of the United Nations was signed on 26 June 1945, in San Francisco, at the conclusion of the United Nations Conference on International Organization, and came into force on 24 October 1945. The Statute of the International Court of Justice is an integral part of the Charter. Visit the UN Dag Hammarskjöld Library's&nbsp;collection of translations of the UN Charter.\n\n&nbsp;",
    "author": "United Nations",
    "og:site_name": "United Nations",
    "og:type": "article"
  },
  "relevance_score": 0.4,
  "summary": "Skip to main content\n\nUN Charter\n\n\n\n\n\n\nUN CharterPreambleChapter I: Purposes and Principles (Articles 1-2)Chapter II: Membership (Articles 3-6)Chapter III: Organs (Articles 7-8)Chapter IV: The General Assembly (Articles 9-22) Chapter V: The Security Council (Articles 23-32)Chapter VI: Pacific Settlement of Disputes (Articles 33-38)Chapter VII: Action with Respect to Threats to the Peace, Breaches of the Peace, and  Acts of Aggression (Articles 39-51)Chapter VIII: Regional Arrangements (Articles 52-54)Chapter IX: International Economic and Social Cooperation (Articles 55-60)Chapter X: The Economic and Social Council (Articles 61-72)Chapter XI: Declaration Regarding Non-Self-Governing Territories (Articles 73-74)Chapter XII: International Trusteeship System (Articles 75-85)Chapter XIII: The Trusteeship Council (Articles 86-91)Chapter XIV: The International Court of Justice (Articles 92-96)Chapter XV: The Secretariat (Articles 97-101)Chapter XVI: Miscellaneous Provisions (Articles 102-105)Chapter XVII: Transitional Security Arrangements (Articles 106-107)Chapter XVIII: Amendments (Articles 108-109) Chapter XIX: Ratification and Signature (Articles 110-111)Amendments to Articles 23, 27, 61, 109 \n\n\n\n \n\nUnited Nations Charter\nThe Charter of the United Nations is the founding document of the United Nations. The International Court of Justice, the principal judicial organ of the United Nations, functions in accordance with the Statute of the International Court of Justice, which is annexed to the UN Charter, and forms an integral part of it. UN Audiovisual Library\nWatch historical footage of the signing of the UN Charter Documentary about the founding of the United Nations Organization and the San Francisco Conference in 1945\n\n\nFanfare for All Peoples\nThis film, set against the stirring words of the Preamble of the United Nations Charter, premiered to an audience of Heads of States from around the world. Outline UN CharterPreamble\nChapter I: Purposes and Principles (Articles 1-2)\nChapter II: Membership (Articles 3-6)\nChapter III: Organs (Articles 7-8)\nChapter IV: The General Assembly (Articles 9-22) \nChapter V: The Security Council (Articles 23-32)\nChapter VI: Pacific Settlement of Disputes (Articles 33-38)\nChapter VII: Action with Respect to Threats to the Peace, Breaches of the Peace, and  Acts of Aggression (Articles 39-51)\nChapter VIII: Regional Arrangements (Articles 52-54)\nChapter IX: International Economic and Social Cooperation (Articles 55-60)\nChapter X: The Economic and Social Council (Articles 61-72)\nChapter XI: Declaration Regarding Non-Self-Governing Territories (Articles 73-74)\nChapter XII: International Trusteeship System (Articles 75-85)\nChapter XIII: The Trusteeship Council (Articles 86-91)\nChapter XIV: The International Court of Justice (Articles 92-96)\nChapter XV: The Secretariat (Articles 97-101)\nChapter XVI: Miscellaneous Provisions (Articles 102-105)\nChapter XVII: Transitional Security Arrangements (Articles 106-107)\nChapter XVIII: Amendments (Articles 108-109)\n Chapter XIX: Ratification and Signature (Articles 110-111)\nAmendments to Articles 23, 27, 61, 109\n\n\n\nPreamble ›\n\n\n\n\n\n\n\n\n\n\n\n\n\n\n\n\n\n\n\n\n \n\n\n\n        Main Bodies   General Assembly   Security Council   Economic and Social Council   Trusteeship Council   International Court of Justice   Secretariat       Departments / Offices   New York   Geneva   Nairobi   Vienna   UN System Directory   UN System Chart   Global Leadership   UN Information Centres       Resources / Services   Emergency information   Reporting Wrongdoing   UN Journal   Documents   Guidelines for gender-inclusive language   Databases   Library   UN iLibrary   UN Chronicle   UN Yearbook   Bookshop   Publications for sale   Maps   Media Accreditation   NGO accreditation at ECOSOC   NGO accreditation at DGC   Visitors’ services   Exhibits   Procurement   Employment   Internships   Model UN   Academic Impact   UN Archives   UN Audiovisual Library   How to donate to the UN system   Information on COVID-19 (Coronavirus)   Africa Renewal   Ten ways the UN makes a difference   GA High-level week 2024       Key Documents   UN Charter   Universal Declaration of Human Rights   Convention on the Rights of the Child   Statute of the International Court of Justice   Annual Report of the Secretary-General on the Work of the Organization       News and Media   News   Press Releases   Briefings   Spokesperson   Photos   UNIfeed   UN Web TV   UN Video   Social Media   The Essential UN   Awake at Night podcast       Issues / Campaigns   Global Issues   Observances   Sustainable Development Goals   Our Common Agenda   The Summit of the Future   Climate Action   Peace and Security   Action for Peacekeeping (A4P)   Global Crisis Response Group   Call to Action for Human Rights   Disability Inclusion Strategy   Fight Racism   Hate Speech   LGBTIQ+ People   Safety of Journalists   Rule of Law   Action to Counter Terrorism   Victims of Terrorism   Children and Armed Conflict   Violence Against Children (SRSG)   Sexual Violence in Conflict   Refugees and Migrants   Action Agenda on Internal Displacement   Spotlight Initiative   Preventing Sexual Exploitation and Abuse   Prevention of Genocide and the Responsibility to Protect   The Rwanda Genocide   The Holocaust   The Question of Palestine   The Transatlantic Slave Trade   Decolonization   Messengers of Peace   Roadmap for Digital Cooperation   Digital Financing Task Force   Data Strategy   Information Integrity   Countering Disinformation   UN75: 2020 and Beyond   Women Rise for All   Stop the Red Sea Catastrophe   Black Sea Grain Initiative Joint Coordination Centre\n\nUN Charter\n\n\n\n\n\n\nUN CharterPreambleChapter I: Purposes and Principles (Articles 1-2)Chapter II: Membership (Articles 3-6)Chapter III: Organs (Articles 7-8)Chapter IV: The General Assembly (Articles 9-22) Chapter V: The Security Council (Articles 23-32)Chapter VI: Pacific Settlement of Disputes (Articles 33-38)Chapter VII: Action with Respect to Threats to the Peace, Breaches of the Peace, and  Acts of Aggression (Articles 39-51)Chapter VIII: Regional Arrangements (Articles 52-54)Chapter IX: International Economic and Social Cooperation (Articles 55-60)Chapter X: The Economic and Social Council (Articles 61-72)Chapter XI: Declaration Regarding Non-Self-Governing Territories (Articles 73-74)Chapter XII: International Trusteeship System (Articles 75-85)Chapter XIII: The Trusteeship Council (Articles 86-91)Chapter XIV: The International Court of Justice (Articles 92-96)Chapter XV: The Secretariat (Articles 97-101)Chapter XVI: Miscellaneous Provisions (Articles 102-105)Chapter XVII: Transitional Security Arrangements (Articles 106-107)Chapter XVIII: Amendments (Articles 108-109) Chapter XIX: Ratification and Signature (Articles 110-111)Amendments to Articles 23, 27, 61, 109 \n\n\n\n \n\nUnited Nations Charter\nThe Charter of the United Nations is the founding document of the United Nations. The International Court of Justice, the principal judicial organ of the United Nations, functions in accordance with the Statute of the International Court of Justice, which is annexed to the UN Charter, and forms an integral part of it. UN Audiovisual Library\nWatch historical footage of the signing of the UN Charter Documentary about the founding of the United Nations Organization and the San Francisco Conference in 1945\n\n\nFanfare for All Peoples\nThis film, set against the stirring words of the Preamble of the United Nations Charter, premiered to an audience of Heads of States from around the world. Outline UN CharterPreamble\nChapter I: Purposes and Principles (Articles 1-2)\nChapter II: Membership (Articles 3-6)\nChapter III: Organs (Articles 7-8)\nChapter IV: The General Assembly (Articles 9-22) \nChapter V: The Security Council (Articles 23-32)\nChapter VI: Pacific Settlement of Disputes (Articles 33-38)\nChapter VII: Action with Respect to Threats to the Peace, Breaches of the Peace, and  Acts of Aggression (Articles 39-51)\nChapter VIII: Regional Arrangements (Articles 52-54)\nChapter IX: International Economic and Social Cooperation (Articles 55-60)\nChapter X: The Economic and Social Council (Articles 61-72)\nChapter XI: Declaration Regarding Non-Self-Governing Territories (Articles 73-74)\nChapter XII: International Trusteeship System (Articles 75-85)\nChapter XIII: The Trusteeship Council (Articles 86-91)\nChapter XIV: The International Court of Justice (Articles 92-96)\nChapter XV: The Secretariat (Articles 97-101)\nChapter XVI: Miscellaneous Provisions (Articles 102-105)\nChapter XVII: Transitional Security Arrangements (Articles 106-107)\nChapter XVIII: Amendments (Articles 108-109)\n Chapter XIX: Ratification and Signature (Articles 110-111)\nAmendments to Articles 23, 27, 61, 109\n\n\n\nPreamble ›\n\nUN Charter\n\n\n\n\n\n\nUN CharterPreambleChapter I: Purposes and Principles (Articles 1-2)Chapter II: Membership (Articles 3-6)Chapter III: Organs (Articles 7-8)Chapter IV: The General Assembly (Articles 9-22) Chapter V: The Security Council (Articles 23-32)Chapter VI: Pacific Settlement of Disputes (Articles 33-38)Chapter VII: Action with Respect to Threats to the Peace, Breaches of the Peace, and  Acts of Aggression (Articles 39-51)Chapter VIII: Regional Arrangements (Articles 52-54)Chapter IX: International Economic and Social Cooperation (Articles 55-60)Chapter X: The Economic and Social Council (Articles 61-72)Chapter XI: Declaration Regarding Non-Self-Governing Territories (Articles 73-74)Chapter XII: International Trusteeship System (Articles 75-85)Chapter XIII: The Trusteeship Council (Articles 86-91)Chapter XIV: The International Court of Justice (Articles 92-96)Chapter XV: The Secretariat (Articles 97-101)Chapter XVI: Miscellaneous Provisions (Articles 102-105)Chapter XVII: Transitional Security Arrangements (Articles 106-107)Chapter XVIII: Amendments (Articles 108-109) Chapter XIX: Ratification and Signature (Articles 110-111)Amendments to Articles 23, 27, 61, 109 \n\n\n\n \n\nUnited Nations Charter\nThe Charter of the United Nations is the founding document of the United Nations. The International Court of Justice, the principal judicial organ of the United Nations, functions in accordance with the Statute of the International Court of Justice, which is annexed to the UN Charter, and forms an integral part of it. UN Audiovisual Library\nWatch historical footage of the signing of the UN Charter Documentary about the founding of the United Nations Organization and the San Francisco Conference in 1945\n\n\nFanfare for All Peoples\nThis film, set against the stirring words of the Preamble of the United Nations Charter, premiered to an audience of Heads of States from around the world. Outline UN CharterPreamble\nChapter I: Purposes and Principles (Articles 1-2)\nChapter II: Membership (Articles 3-6)\nChapter III: Organs (Articles 7-8)\nChapter IV: The General Assembly (Articles 9-22) \nChapter V: The Security Council (Articles 23-32)\nChapter VI: Pacific Settlement of Disputes (Articles 33-38)\nChapter VII: Action with Respect to Threats to the Peace, Breaches of the Peace, and  Acts of Aggression (Articles 39-51)\nChapter VIII: Regional Arrangements (Articles 52-54)\nChapter IX: International Economic and Social Cooperation (Articles 55-60)\nChapter X: The Economic and Social Council (Articles 61-72)\nChapter XI: Declaration Regarding Non-Self-Governing Territories (Articles 73-74)\nChapter XII: International Trusteeship System (Articles 75-85)\nChapter XIII: The Trusteeship Council (Articles 86-91)\nChapter XIV: The International Court of Justice (Articles 92-96)\nChapter XV: The Secretariat (Articles 97-101)\nChapter XVI: Miscellaneous Provisions (Articles 102-105)\nChapter XVII: Transitional Security Arrangements (Articles 106-107)\nChapter XVIII: Amendments (Articles 108-109)\n Chapter XIX: Ratification and Signature (Articles 110-111)\nAmendments to Articles 23, 27, 61, 109\n\n\n\nPreamble ›\n\nUN Charter\n\n\n\n\n\n\nUN CharterPreambleChapter I: Purposes and Principles (Articles 1-2)Chapter II: Membership (Articles 3-6)Chapter III: Organs (Articles 7-8)Chapter IV: The General Assembly (Articles 9-22) Chapter V: The Security Council (Articles 23-32)Chapter VI: Pacific Settlement of Disputes (Articles 33-38)Chapter VII: Action with Respect to Threats to the Peace, Breaches of the Peace, and  Acts of Aggression (Articles 39-51)Chapter VIII: Regional Arrangements (Articles 52-54)Chapter IX: International Economic and Social Cooperation (Articles 55-60)Chapter X: The Economic and Social Council (Articles 61-72)Chapter XI: Declaration Regarding Non-Self-Governing Territories (Articles 73-74)Chapter XII: International Trusteeship System (Articles 75-85)Chapter XIII: The Trusteeship Council (Articles 86-91)Chapter XIV: The International Court of Justice (Articles 92-96)Chapter XV: The Secretariat (Articles 97-101)Chapter XVI: Miscellaneous Provisions (Articles 102-105)Chapter XVII: Transitional Security Arrangements (Articles 106-107)Chapter XVIII: Amendments (Articles 108-109) Chapter XIX: Ratification and Signature (Articles 110-111)Amendments to Articles 23, 27, 61, 109 \n\n\n\n \n\nUnited Nations Charter\nThe Charter of the United Nations is the founding document of the United Nations. The International Court of Justice, the principal judicial organ of the United Nations, functions in accordance with the Statute of the International Court of Justice, which is annexed to the UN Charter, and forms an integral part of it. UN Audiovisual Library\nWatch historical footage of the signing of the UN Charter Documentary about the founding of the United Nations Organization and the San Francisco Conference in 1945\n\n\nFanfare for All Peoples\nThis film, set against the stirring words of the Preamble of the United Nations Charter, premiered to an audience of Heads of States from around the world. Outline UN CharterPreamble\nChapter I: Purposes and Principles (Articles 1-2)\nChapter II: Membership (Articles 3-6)\nChapter III: Organs (Articles 7-8)\nChapter IV: The General Assembly (Articles 9-22) \nChapter V: The Security Council (Articles 23-32)\nChapter VI: Pacific Settlement of Disputes (Articles 33-38)\nChapter VII: Action with Respect to Threats to the Peace, Breaches of the Peace, and  Acts of Aggression (Articles 39-51)\nChapter VIII: Regional Arrangements (Articles 52-54)\nChapter IX: International Economic and Social Cooperation (Articles 55-60)\nChapter X: The Economic and Social Council (Articles 61-72)\nChapter XI: Declaration Regarding Non-Self-Governing Territories (Articles 73-74)\nChapter XII: International Trusteeship System (Articles 75-85)\nChapter XIII: The Trusteeship Council (Articles 86-91)\nChapter XIV: The International Court of Justice (Articles 92-96)\nChapter XV: The Secretariat (Articles 97-101)\nChapter XVI: Miscellaneous Provisions (Articles 102-105)\nChapter XVII: Transitional Security Arrangements (Articles 106-107)\nChapter XVIII: Amendments (Articles 108-109)\n Chapter XIX: Ratification and Signature (Articles 110-111)\nAmendments to Articles 23, 27, 61, 109\n\n\n\nPreamble ›\n\nUN Charter\n\n\n\n\n\n\nUN CharterPreambleChapter I: Purposes and Principles (Articles 1-2)Chapter II: Membership (Articles 3-6)Chapter III: Organs (Articles 7-8)Chapter IV: The General Assembly (Articles 9-22) Chapter V: The Security Council (Articles 23-32)Chapter VI: Pacific Settlement of Disputes (Articles 33-38)Chapter VII: Action with Respect to Threats to the Peace, Breaches of the Peace, and  Acts of Aggression (Articles 39-51)Chapter VIII: Regional Arrangements (Articles 52-54)Chapter IX: International Economic and Social Cooperation (Articles 55-60)Chapter X: The Economic and Social Council (Articles 61-72)Chapter XI: Declaration Regarding Non-Self-Governing Territories (Articles 73-74)Chapter XII: International Trusteeship System (Articles 75-85)Chapter XIII: The Trusteeship Council (Articles 86-91)Chapter XIV: The International Court of Justice (Articles 92-96)Chapter XV: The Secretariat (Articles 97-101)Chapter XVI: Miscellaneous Provisions (Articles 102-105)Chapter XVII: Transitional Security Arrangements (Articles 106-107)Chapter XVIII: Amendments (Articles 108-109) Chapter XIX: Ratification and Signature (Articles 110-111)Amendments to Articles 23, 27, 61, 109 \n\n\n\n \n\nUnited Nations Charter\nThe Charter of the United Nations is the founding document of the United Nations. The International Court of Justice, the principal judicial organ of the United Nations, functions in accordance with the Statute of the International Court of Justice, which is annexed to the UN Charter, and forms an integral part of it. UN Audiovisual Library\nWatch historical footage of the signing of the UN Charter Documentary about the founding of the United Nations Organization and the San Francisco Conference in 1945\n\n\nFanfare for All Peoples\nThis film, set against the stirring words of the Preamble of the United Nations Charter, premiered to an audience of Heads of States from around the world. Outline UN CharterPreamble\nChapter I: Purposes and Principles (Articles 1-2)\nChapter II: Membership (Articles 3-6)\nChapter III: Organs (Articles 7-8)\nChapter IV: The General Assembly (Articles 9-22) \nChapter V: The Security Council (Articles 23-32)\nChapter VI: Pacific Settlement of Disputes (Articles 33-38)\nChapter VII: Action with Respect to Threats to the Peace, Breaches of the Peace, and  Acts of Aggression (Articles 39-51)\nChapter VIII: Regional Arrangements (Articles 52-54)\nChapter IX: International Economic and Social Cooperation (Articles 55-60)\nChapter X: The Economic and Social Council (Articles 61-72)\nChapter XI: Declaration Regarding Non-Self-Governing Territories (Articles 73-74)\nChapter XII: International Trusteeship System (Articles 75-85)\nChapter XIII: The Trusteeship Council (Articles 86-91)\nChapter XIV: The International Court of Justice (Articles 92-96)\nChapter XV: The Secretariat (Articles 97-101)\nChapter XVI: Miscellaneous Provisions (Articles 102-105)\nChapter XVII: Transitional Security Arrangements (Articles 106-107)\nChapter XVIII: Amendments (Articles 108-109)\n Chapter XIX: Ratification and Signature (Articles 110-111)\nAmendments to Articles 23, 27, 61, 109\n\n\n\nPreamble ›\n\nUN CharterPreambleChapter I: Purposes and Principles (Articles 1-2)Chapter II: Membership (Articles 3-6)Chapter III: Organs (Articles 7-8)Chapter IV: The General Assembly (Articles 9-22) Chapter V: The Security Council (Articles 23-32)Chapter VI: Pacific Settlement of Disputes (Articles 33-38)Chapter VII: Action with Respect to Threats to the Peace, Breaches of the Peace, and  Acts of Aggression (Articles 39-51)Chapter VIII: Regional Arrangements (Articles 52-54)Chapter IX: International Economic and Social Cooperation (Articles 55-60)Chapter X: The Economic and Social Council (Articles 61-72)Chapter XI: Declaration Regarding Non-Self-Governing Territories (Articles 73-74)Chapter XII: International Trusteeship System (Articles 75-85)Chapter XIII: The Trusteeship Council (Articles 86-91)Chapter XIV: The International Court of Justice (Articles 92-96)Chapter XV: The Secretariat (Articles 97-101)Chapter XVI: Miscellaneous Provisions (Articles 102-105)Chapter XVII: Transitional Security Arrangements (Articles 106-107)Chapter XVIII: Amendments (Articles 108-109) Chapter XIX: Ratification and Signature (Articles 110-111)Amendments to Articles 23, 27, 61, 109 \n\n\n\n \n\nUnited Nations Charter\nThe Charter of the United Nations is the founding document of the United Nations. The International Court of Justice, the principal judicial organ of the United Nations, functions in accordance with the Statute of the International Court of Justice, which is annexed to the UN Charter, and forms an integral part of it. UN Audiovisual Library\nWatch historical footage of the signing of the UN Charter Documentary about the founding of the United Nations Organization and the San Francisco Conference in 1945\n\n\nFanfare for All Peoples\nThis film, set against the stirring words of the Preamble of the United Nations Charter, premiered to an audience of Heads of States from around the world. Outline UN CharterPreamble\nChapter I: Purposes and Principles (Articles 1-2)\nChapter II: Membership (Articles 3-6)\nChapter III: Organs (Articles 7-8)\nChapter IV: The General Assembly (Articles 9-22) \nChapter V: The Security Council (Articles 23-32)\nChapter VI: Pacific Settlement of Disputes (Articles 33-38)\nChapter VII: Action with Respect to Threats to the Peace, Breaches of the Peace, and  Acts of Aggression (Articles 39-51)\nChapter VIII: Regional Arrangements (Articles 52-54)\nChapter IX: International Economic and Social Cooperation (Articles 55-60)\nChapter X: The Economic and Social Council (Articles 61-72)\nChapter XI: Declaration Regarding Non-Self-Governing Territories (Articles 73-74)\nChapter XII: International Trusteeship System (Articles 75-85)\nChapter XIII: The Trusteeship Council (Articles 86-91)\nChapter XIV: The International Court of Justice (Articles 92-96)\nChapter XV: The Secretariat (Articles 97-101)\nChapter XVI: Miscellaneous Provisions (Articles 102-105)\nChapter XVII: Transitional Security Arrangements (Articles 106-107)\nChapter XVIII: Amendments (Articles 108-109)\n Chapter XIX: Ratification and Signature (Articles 110-111)\nAmendments to Articles 23, 27, 61, 109\n\n\n\nPreamble ›\n\nUN CharterPreambleChapter I: Purposes and Principles (Articles 1-2)Chapter II: Membership (Articles 3-6)Chapter III: Organs (Articles 7-8)Chapter IV: The General Assembly (Articles 9-22) Chapter V: The Security Council (Articles 23-32)Chapter VI: Pacific Settlement of Disputes (Articles 33-38)Chapter VII: Action with Respect to Threats to the Peace, Breaches of the Peace, and  Acts of Aggression (Articles 39-51)Chapter VIII: Regional Arrangements (Articles 52-54)Chapter IX: International Economic and Social Cooperation (Articles 55-60)Chapter X: The Economic and Social Council (Articles 61-72)Chapter XI: Declaration Regarding Non-Self-Governing Territories (Articles 73-74)Chapter XII: International Trusteeship System (Articles 75-85)Chapter XIII: The Trusteeship Council (Articles 86-91)Chapter XIV: The International Court of Justice (Articles 92-96)Chapter XV: The Secretariat (Articles 97-101)Chapter XVI: Miscellaneous Provisions (Articles 102-105)Chapter XVII: Transitional Security Arrangements (Articles 106-107)Chapter XVIII: Amendments (Articles 108-109) Chapter XIX: Ratification and Signature (Articles 110-111)Amendments to Articles 23, 27, 61, 109 \n\n\n\n \n\nUnited Nations Charter\nThe Charter of the United Nations is the founding document of the United Nations. The International Court of Justice, the principal judicial organ of the United Nations, functions in accordance with the Statute of the International Court of Justice, which is annexed to the UN Charter, and forms an integral part of it. UN Audiovisual Library\nWatch historical footage of the signing of the UN Charter Documentary about the founding of the United Nations Organization and the San Francisco Conference in 1945\n\n\nFanfare for All Peoples\nThis film, set against the stirring words of the Preamble of the United Nations Charter, premiered to an audience of Heads of States from around the world. Outline UN CharterPreamble\nChapter I: Purposes and Principles (Articles 1-2)\nChapter II: Membership (Articles 3-6)\nChapter III: Organs (Articles 7-8)\nChapter IV: The General Assembly (Articles 9-22) \nChapter V: The Security Council (Articles 23-32)\nChapter VI: Pacific Settlement of Disputes (Articles 33-38)\nChapter VII: Action with Respect to Threats to the Peace, Breaches of the Peace, and  Acts of Aggression (Articles 39-51)\nChapter VIII: Regional Arrangements (Articles 52-54)\nChapter IX: International Economic and Social Cooperation (Articles 55-60)\nChapter X: The Economic and Social Council (Articles 61-72)\nChapter XI: Declaration Regarding Non-Self-Governing Territories (Articles 73-74)\nChapter XII: International Trusteeship System (Articles 75-85)\nChapter XIII: The Trusteeship Council (Articles 86-91)\nChapter XIV: The International Court of Justice (Articles 92-96)\nChapter XV: The Secretariat (Articles 97-101)\nChapter XVI: Miscellaneous Provisions (Articles 102-105)\nChapter XVII: Transitional Security Arrangements (Articles 106-107)\nChapter XVIII: Amendments (Articles 108-109)\n Chapter XIX: Ratification and Signature (Articles 110-111)\nAmendments to Articles 23, 27, 61, 109\n\n\n\nPreamble ›\n\nUN CharterPreambleChapter I: Purposes and Principles (Articles 1-2)Chapter II: Membership (Articles 3-6)Chapter III: Organs (Articles 7-8)Chapter IV: The General Assembly (Articles 9-22) Chapter V: The Security Council (Articles 23-32)Chapter VI: Pacific Settlement of Disputes (Articles 33-38)Chapter VII: Action with Respect to Threats to the Peace, Breaches of the Peace, and  Acts of Aggression (Articles 39-51)Chapter VIII: Regional Arrangements (Articles 52-54)Chapter IX: International Economic and Social Cooperation (Articles 55-60)Chapter X: The Economic and Social Council (Articles 61-72)Chapter XI: Declaration Regarding Non-Self-Governing Territories (Articles 73-74)Chapter XII: International Trusteeship System (Articles 75-85)Chapter XIII: The Trusteeship Council (Articles 86-91)Chapter XIV: The International Court of Justice (Articles 92-96)Chapter XV: The Secretariat (Articles 97-101)Chapter XVI: Miscellaneous Provisions (Articles 102-105)Chapter XVII: Transitional Security Arrangements (Articles 106-107)Chapter XVIII: Amendments (Articles 108-109) Chapter XIX: Ratification and Signature (Articles 110-111)Amendments to Articles 23, 27, 61, 109 \n\n\n\n \n\nUnited Nations Charter\nThe Charter of the United Nations is the founding document of the United Nations. The International Court of Justice, the principal judicial organ of the United Nations, functions in accordance with the Statute of the International Court of Justice, which is annexed to the UN Charter, and forms an integral part of it. UN Audiovisual Library\nWatch historical footage of the signing of the UN Charter Documentary about the founding of the United Nations Organization and the San Francisco Conference in 1945\n\n\nFanfare for All Peoples\nThis film, set against the stirring words of the Preamble of the United Nations Charter, premiered to an audience of Heads of States from around the world. Outline UN CharterPreamble\nChapter I: Purposes and Principles (Articles 1-2)\nChapter II: Membership (Articles 3-6)\nChapter III: Organs (Articles 7-8)\nChapter IV: The General Assembly (Articles 9-22) \nChapter V: The Security Council (Articles 23-32)\nChapter VI: Pacific Settlement of Disputes (Articles 33-38)\nChapter VII: Action with Respect to Threats to the Peace, Breaches of the Peace, and  Acts of Aggression (Articles 39-51)\nChapter VIII: Regional Arrangements (Articles 52-54)\nChapter IX: International Economic and Social Cooperation (Articles 55-60)\nChapter X: The Economic and Social Council (Articles 61-72)\nChapter XI: Declaration Regarding Non-Self-Governing Territories (Articles 73-74)\nChapter XII: International Trusteeship System (Articles 75-85)\nChapter XIII: The Trusteeship Council (Articles 86-91)\nChapter XIV: The International Court of Justice (Articles 92-96)\nChapter XV: The Secretariat (Articles 97-101)\nChapter XVI: Miscellaneous Provisions (Articles 102-105)\nChapter XVII: Transitional Security Arrangements (Articles 106-107)\nChapter XVIII: Amendments (Articles 108-109)\n Chapter XIX: Ratification and Signature (Articles 110-111)\nAmendments to Articles 23, 27, 61, 109\n\n\n\nPreamble ›\n\nUN CharterPreambleChapter I: Purposes and Principles (Articles 1-2)Chapter II: Membership (Articles 3-6)Chapter III: Organs (Articles 7-8)Chapter IV: The General Assembly (Articles 9-22) Chapter V: The Security Council (Articles 23-32)Chapter VI: Pacific Settlement of Disputes (Articles 33-38)Chapter VII: Action with Respect to Threats to the Peace, Breaches of the Peace, and  Acts of Aggression (Articles 39-51)Chapter VIII: Regional Arrangements (Articles 52-54)Chapter IX: International Economic and Social Cooperation (Articles 55-60)Chapter X: The Economic and Social Council (Articles 61-72)Chapter XI: Declaration Regarding Non-Self-Governing Territories (Articles 73-74)Chapter XII: International Trusteeship System (Articles 75-85)Chapter XIII: The Trusteeship Council (Articles 86-91)Chapter XIV: The International Court of Justice (Articles 92-96)Chapter XV: The Secretariat (Articles 97-101)Chapter XVI: Miscellaneous Provisions (Articles 102-105)Chapter XVII: Transitional Security Arrangements (Articles 106-107)Chapter XVIII: Amendments (Articles 108-109) Chapter XIX: Ratification and Signature (Articles 110-111)Amendments to Articles 23, 27, 61, 109\n\nUN CharterPreambleChapter I: Purposes and Principles (Articles 1-2)Chapter II: Membership (Articles 3-6)Chapter III: Organs (Articles 7-8)Chapter IV: The General Assembly (Articles 9-22) Chapter V: The Security Council (Articles 23-32)Chapter VI: Pacific Settlement of Disputes (Articles 33-38)Chapter VII: Action with Respect to Threats to the Peace, Breaches of the Peace, and  Acts of Aggression (Articles 39-51)Chapter VIII: Regional Arrangements (Articles 52-54)Chapter IX: International Economic and Social Cooperation (Articles 55-60)Chapter X: The Economic and Social Council (Articles 61-72)Chapter XI: Declaration Regarding Non-Self-Governing Territories (Articles 73-74)Chapter XII: International Trusteeship System (Articles 75-85)Chapter XIII: The Trusteeship Council (Articles 86-91)Chapter XIV: The International Court of Justice (Articles 92-96)Chapter XV: The Secretariat (Articles 97-101)Chapter XVI: Miscellaneous Provisions (Articles 102-105)Chapter XVII: Transitional Security Arrangements (Articles 106-107)Chapter XVIII: Amendments (Articles 108-109) Chapter XIX: Ratification and Signature (Articles 110-111)Amendments to Articles 23, 27, 61, 109\n\nUnited Nations Charter\nThe Charter of the United Nations is the founding document of the United Nations. The International Court of Justice, the principal judicial organ of the United Nations, functions in accordance with the Statute of the International Court of Justice, which is annexed to the UN Charter, and forms an integral part of it. UN Audiovisual Library\nWatch historical footage of the signing of the UN Charter Documentary about the founding of the United Nations Organization and the San Francisco Conference in 1945\n\n\nFanfare for All Peoples\nThis film, set against the stirring words of the Preamble of the United Nations Charter, premiered to an audience of Heads of States from around the world. Outline UN CharterPreamble\nChapter I: Purposes and Principles (Articles 1-2)\nChapter II: Membership (Articles 3-6)\nChapter III: Organs (Articles 7-8)\nChapter IV: The General Assembly (Articles 9-22) \nChapter V: The Security Council (Articles 23-32)\nChapter VI: Pacific Settlement of Disputes (Articles 33-38)\nChapter VII: Action with Respect to Threats to the Peace, Breaches of the Peace, and  Acts of Aggression (Articles 39-51)\nChapter VIII: Regional Arrangements (Articles 52-54)\nChapter IX: International Economic and Social Cooperation (Articles 55-60)\nChapter X: The Economic and Social Council (Articles 61-72)\nChapter XI: Declaration Regarding Non-Self-Governing Territories (Articles 73-74)\nChapter XII: International Trusteeship System (Articles 75-85)\nChapter XIII: The Trusteeship Council (Articles 86-91)\nChapter XIV: The International Court of Justice (Articles 92-96)\nChapter XV: The Secretariat (Articles 97-101)\nChapter XVI: Miscellaneous Provisions (Articles 102-105)\nChapter XVII: Transitional Security Arrangements (Articles 106-107)\nChapter XVIII: Amendments (Articles 108-109)\n Chapter XIX: Ratification and Signature (Articles 110-111)\nAmendments to Articles 23, 27, 61, 109\n\n\n\nPreamble ›\n\nUnited Nations Charter\nThe Charter of the United Nations is the founding document of the United Nations. The International Court of Justice, the principal judicial organ of the United Nations, functions in accordance with the Statute of the International Court of Justice, which is annexed to the UN Charter, and forms an integral part of it. UN Audiovisual Library\nWatch historical footage of the signing of the UN Charter Documentary about the founding of the United Nations Organization and the San Francisco Conference in 1945\n\n\nFanfare for All Peoples\nThis film, set against the stirring words of the Preamble of the United Nations Charter, premiered to an audience of Heads of States from around the world. The International Court of Justice, the principal judicial organ of the United Nations, functions in accordance with the Statute of the International Court of Justice, which is annexed to the UN Charter, and forms an integral part of it. UN Audiovisual Library\nWatch historical footage of the signing of the UN Charter Documentary about the founding of the United Nations Organization and the San Francisco Conference in 1945\n\n\nFanfare for All Peoples\nThis film, set against the stirring words of the Preamble of the United Nations Charter, premiered to an audience of Heads of States from around the world. The International Court of Justice, the principal judicial organ of the United Nations, functions in accordance with the Statute of the International Court of Justice, which is annexed to the UN Charter, and forms an integral part of it. UN Audiovisual Library\nWatch historical footage of the signing of the UN Charter Documentary about the founding of the United Nations Organization and the San Francisco Conference in 1945\n\n\nFanfare for All Peoples\nThis film, set against the stirring words of the Preamble of the United Nations Charter, premiered to an audience of Heads of States from around the world. The International Court of Justice, the principal judicial organ of the United Nations, functions in accordance with the Statute of the International Court of Justice, which is annexed to the UN Charter, and forms an integral part of it. UN Audiovisual Library\nWatch historical footage of the signing of the UN Charter Documentary about the founding of the United Nations Organization and the San Francisco Conference in 1945\n\n\nFanfare for All Peoples\nThis film, set against the stirring words of the Preamble of the United Nations Charter, premiered to an audience of Heads of States from around the world. UN Audiovisual Library\nWatch historical footage of the signing of the UN Charter Documentary about the founding of the United Nations Organization and the San Francisco Conference in 1945\n\n\nFanfare for All Peoples\nThis film, set against the stirring words of the Preamble of the United Nations Charter, premiered to an audience of Heads of States from around the world. UN Audiovisual Library\nWatch historical footage of the signing of the UN Charter Documentary about the founding of the United Nations Organization and the San Francisco Conference in 1945\n\n\nFanfare for All Peoples\nThis film, set against the stirring words of the Preamble of the United Nations Charter, premiered to an audience of Heads of States from around the world. UN Audiovisual Library\nWatch historical footage of the signing of the UN Charter Documentary about the founding of the United Nations Organization and the San Francisco Conference in 1945\n\nWatch historical footage of the signing of the UN Charter Documentary about the founding of the United Nations Organization and the San Francisco Conference in 1945\n\nFanfare for All Peoples\nThis film, set against the stirring words of the Preamble of the United Nations Charter, premiered to an audience of Heads of States from around the world. Outline UN CharterPreamble\nChapter I: Purposes and Principles (Articles 1-2)\nChapter II: Membership (Articles 3-6)\nChapter III: Organs (Articles 7-8)\nChapter IV: The General Assembly (Articles 9-22) \nChapter V: The Security Council (Articles 23-32)\nChapter VI: Pacific Settlement of Disputes (Articles 33-38)\nChapter VII: Action with Respect to Threats to the Peace, Breaches of the Peace, and  Acts of Aggression (Articles 39-51)\nChapter VIII: Regional Arrangements (Articles 52-54)\nChapter IX: International Economic and Social Cooperation (Articles 55-60)\nChapter X: The Economic and Social Council (Articles 61-72)\nChapter XI: Declaration Regarding Non-Self-Governing Territories (Articles 73-74)\nChapter XII: International Trusteeship System (Articles 75-85)\nChapter XIII: The Trusteeship Council (Articles 86-91)\nChapter XIV: The International Court of Justice (Articles 92-96)\nChapter XV: The Secretariat (Articles 97-101)\nChapter XVI: Miscellaneous Provisions (Articles 102-105)\nChapter XVII: Transitional Security Arrangements (Articles 106-107)\nChapter XVIII: Amendments (Articles 108-109)\n Chapter XIX: Ratification and Signature (Articles 110-111)\nAmendments to Articles 23, 27, 61, 109\n\n\n\nPreamble ›\n\nOutline UN CharterPreamble\nChapter I: Purposes and Principles (Articles 1-2)\nChapter II: Membership (Articles 3-6)\nChapter III: Organs (Articles 7-8)\nChapter IV: The General Assembly (Articles 9-22) \nChapter V: The Security Council (Articles 23-32)\nChapter VI: Pacific Settlement of Disputes (Articles 33-38)\nChapter VII: Action with Respect to Threats to the Peace, Breaches of the Peace, and  Acts of Aggression (Articles 39-51)\nChapter VIII: Regional Arrangements (Articles 52-54)\nChapter IX: International Economic and Social Cooperation (Articles 55-60)\nChapter X: The Economic and Social Council (Articles 61-72)\nChapter XI: Declaration Regarding Non-Self-Governing Territories (Articles 73-74)\nChapter XII: International Trusteeship System (Articles 75-85)\nChapter XIII: The Trusteeship Council (Articles 86-91)\nChapter XIV: The International Court of Justice (Articles 92-96)\nChapter XV: The Secretariat (Articles 97-101)\nChapter XVI: Miscellaneous Provisions (Articles 102-105)\nChapter XVII: Transitional Security Arrangements (Articles 106-107)\nChapter XVIII: Amendments (Articles 108-109)\n Chapter XIX: Ratification and Signature (Articles 110-111)\nAmendments to Articles 23, 27, 61, 109\n\nMain Bodies   General Assembly   Security Council   Economic and Social Council   Trusteeship Council   International Court of Justice   Secretariat       Departments / Offices   New York   Geneva   Nairobi   Vienna   UN System Directory   UN System Chart   Global Leadership   UN Information Centres       Resources / Services   Emergency information   Reporting Wrongdoing   UN Journal   Documents   Guidelines for gender-inclusive language   Databases   Library   UN iLibrary   UN Chronicle   UN Yearbook   Bookshop   Publications for sale   Maps   Media Accreditation   NGO accreditation at ECOSOC   NGO accreditation at DGC   Visitors’ services   Exhibits   Procurement   Employment   Internships   Model UN   Academic Impact   UN Archives   UN Audiovisual Library   How to donate to the UN system   Information on COVID-19 (Coronavirus)   Africa Renewal   Ten ways the UN makes a difference   GA High-level week 2024       Key Documents   UN Charter   Universal Declaration of Human Rights   Convention on the Rights of the Child   Statute of the International Court of Justice   Annual Report of the Secretary-General on the Work of the Organization       News and Media   News   Press Releases   Briefings   Spokesperson   Photos   UNIfeed   UN Web TV   UN Video   Social Media   The Essential UN   Awake at Night podcast       Issues / Campaigns   Global Issues   Observances   Sustainable Development Goals   Our Common Agenda   The Summit of the Future   Climate Action   Peace and Security   Action for Peacekeeping (A4P)   Global Crisis Response Group   Call to Action for Human Rights   Disability Inclusion Strategy   Fight Racism   Hate Speech   LGBTIQ+ People   Safety of Journalists   Rule of Law   Action to Counter Terrorism   Victims of Terrorism   Children and Armed Conflict   Violence Against Children (SRSG)   Sexual Violence in Conflict   Refugees and Migrants   Action Agenda on Internal Displacement   Spotlight Initiative   Preventing Sexual Exploitation and Abuse   Prevention of Genocide and the Responsibility to Protect   The Rwanda Genocide   The Holocaust   The Question of Palestine   The Transatlantic Slave Trade   Decolonization   Messengers of Peace   Roadmap for Digital Cooperation   Digital Financing Task Force   Data Strategy   Information Integrity   Countering Disinformation   UN75: 2020 and Beyond   Women Rise for All   Stop the Red Sea Catastrophe   Black Sea Grain Initiative Joint Coordination Centre\n\nMain Bodies   General Assembly   Security Council   Economic and Social Council   Trusteeship Council   International Court of Justice   Secretariat       Departments / Offices   New York   Geneva   Nairobi   Vienna   UN System Directory   UN System Chart   Global Leadership   UN Information Centres       Resources / Services   Emergency information   Reporting Wrongdoing   UN Journal   Documents   Guidelines for gender-inclusive language   Databases   Library   UN iLibrary   UN Chronicle   UN Yearbook   Bookshop   Publications for sale   Maps   Media Accreditation   NGO accreditation at ECOSOC   NGO accreditation at DGC   Visitors’ services   Exhibits   Procurement   Employment   Internships   Model UN   Academic Impact   UN Archives   UN Audiovisual Library   How to donate to the UN system   Information on COVID-19 (Coronavirus)   Africa Renewal   Ten ways the UN makes a difference   GA High-level week 2024       Key Documents   UN Charter   Universal Declaration of Human Rights   Convention on the Rights of the Child   Statute of the International Court of Justice   Annual Report of the Secretary-General on the Work of the Organization       News and Media   News   Press Releases   Briefings   Spokesperson   Photos   UNIfeed   UN Web TV   UN Video   Social Media   The Essential UN   Awake at Night podcast       Issues / Campaigns   Global Issues   Observances   Sustainable Development Goals   Our Common Agenda   The Summit of the Future   Climate Action   Peace and Security   Action for Peacekeeping (A4P)   Global Crisis Response Group   Call to Action for Human Rights   Disability Inclusion Strategy   Fight Racism   Hate Speech   LGBTIQ+ People   Safety of Journalists   Rule of Law   Action to Counter Terrorism   Victims of Terrorism   Children and Armed Conflict   Violence Against Children (SRSG)   Sexual Violence in Conflict   Refugees and Migrants   Action Agenda on Internal Displacement   Spotlight Initiative   Preventing Sexual Exploitation and Abuse   Prevention of Genocide and the Responsibility to Protect   The Rwanda Genocide   The Holocaust   The Question of Palestine   The Transatlantic Slave Trade   Decolonization   Messengers of Peace   Roadmap for Digital Cooperation   Digital Financing Task Force   Data Strategy   Information Integrity   Countering Disinformation   UN75: 2020 and Beyond   Women Rise for All   Stop the Red Sea Catastrophe   Black Sea Grain Initiative Joint Coordination Centre\n\nMain Bodies   General Assembly   Security Council   Economic and Social Council   Trusteeship Council   International Court of Justice   Secretariat       Departments / Offices   New York   Geneva   Nairobi   Vienna   UN System Directory   UN System Chart   Global Leadership   UN Information Centres       Resources / Services   Emergency information   Reporting Wrongdoing   UN Journal   Documents   Guidelines for gender-inclusive language   Databases   Library   UN iLibrary   UN Chronicle   UN Yearbook   Bookshop   Publications for sale   Maps   Media Accreditation   NGO accreditation at ECOSOC   NGO accreditation at DGC   Visitors’ services   Exhibits   Procurement   Employment   Internships   Model UN   Academic Impact   UN Archives   UN Audiovisual Library   How to donate to the UN system   Information on COVID-19 (Coronavirus)   Africa Renewal   Ten ways the UN makes a difference   GA High-level week 2024       Key Documents   UN Charter   Universal Declaration of Human Rights   Convention on the Rights of the Child   Statute of the International Court of Justice   Annual Report of the Secretary-General on the Work of the Organization       News and Media   News   Press Releases   Briefings   Spokesperson   Photos   UNIfeed   UN Web TV   UN Video   Social Media   The Essential UN   Awake at Night podcast       Issues / Campaigns   Global Issues   Observances   Sustainable Development Goals   Our Common Agenda   The Summit of the Future   Climate Action   Peace and Security   Action for Peacekeeping (A4P)   Global Crisis Response Group   Call to Action for Human Rights   Disability Inclusion Strategy   Fight Racism   Hate Speech   LGBTIQ+ People   Safety of Journalists   Rule of Law   Action to Counter Terrorism   Victims of Terrorism   Children and Armed Conflict   Violence Against Children (SRSG)   Sexual Violence in Conflict   Refugees and Migrants   Action Agenda on Internal Displacement   Spotlight Initiative   Preventing Sexual Exploitation and Abuse   Prevention of Genocide and the Responsibility to Protect   The Rwanda Genocide   The Holocaust   The Question of Palestine   The Transatlantic Slave Trade   Decolonization   Messengers of Peace   Roadmap for Digital Cooperation   Digital Financing Task Force   Data Strategy   Information Integrity   Countering Disinformation   UN75: 2020 and Beyond   Women Rise for All   Stop the Red Sea Catastrophe   Black Sea Grain Initiative Joint Coordination Centre\n\nMain Bodies   General Assembly   Security Council   Economic and Social Council   Trusteeship Council   International Court of Justice   Secretariat       Departments / Offices   New York   Geneva   Nairobi   Vienna   UN System Directory   UN System Chart   Global Leadership   UN Information Centres\n\nMain Bodies   General Assembly   Security Council   Economic and Social Council   Trusteeship Council   International Court of Justice   Secretariat\n\nMain Bodies   General Assembly   Security Council   Economic and Social Council   Trusteeship Council   International Court of Justice   Secretariat\n\nDepartments / Offices   New York   Geneva   Nairobi   Vienna   UN System Directory   UN System Chart   Global Leadership   UN Information Centres\n\nDepartments / Offices   New York   Geneva   Nairobi   Vienna   UN System Directory   UN System Chart   Global Leadership   UN Information Centres\n\nResources / Services   Emergency information   Reporting Wrongdoing   UN Journal   Documents   Guidelines for gender-inclusive language   Databases   Library   UN iLibrary   UN Chronicle   UN Yearbook   Bookshop   Publications for sale   Maps   Media Accreditation   NGO accreditation at ECOSOC   NGO accreditation at DGC   Visitors’ services   Exhibits   Procurement   Employment   Internships   Model UN   Academic Impact   UN Archives   UN Audiovisual Library   How to donate to the UN system   Information on COVID-19 (Coronavirus)   Africa Renewal   Ten ways the UN makes a difference   GA High-level week 2024\n\nResources / Services   Emergency information   Reporting Wrongdoing   UN Journal   Documents   Guidelines for gender-inclusive language   Databases   Library   UN iLibrary   UN Chronicle   UN Yearbook   Bookshop   Publications for sale   Maps   Media Accreditation   NGO accreditation at ECOSOC   NGO accreditation at DGC   Visitors’ services   Exhibits   Procurement   Employment   Internships   Model UN   Academic Impact   UN Archives   UN Audiovisual Library   How to donate to the UN system   Information on COVID-19 (Coronavirus)   Africa Renewal   Ten ways the UN makes a difference   GA High-level week 2024\n\nResources / Services   Emergency information   Reporting Wrongdoing   UN Journal   Documents   Guidelines for gender-inclusive language   Databases   Library   UN iLibrary   UN Chronicle   UN Yearbook   Bookshop   Publications for sale   Maps   Media Accreditation   NGO accreditation at ECOSOC   NGO accreditation at DGC   Visitors’ services   Exhibits   Procurement   Employment   Internships   Model UN   Academic Impact   UN Archives   UN Audiovisual Library   How to donate to the UN system   Information on COVID-19 (Coronavirus)   Africa Renewal   Ten ways the UN makes a difference   GA High-level week 2024\n\nKey Documents   UN Charter   Universal Declaration of Human Rights   Convention on the Rights of the Child   Statute of the International Court of Justice   Annual Report of the Secretary-General on the Work of the Organization       News and Media   News   Press Releases   Briefings   Spokesperson   Photos   UNIfeed   UN Web TV   UN Video   Social Media   The Essential UN   Awake at Night podcast\n\nKey Documents   UN Charter   Universal Declaration of Human Rights   Convention on the Rights of the Child   Statute of the International Court of Justice   Annual Report of the Secretary-General on the Work of the Organization\n\nKey Documents   UN Charter   Universal Declaration of Human Rights   Convention on the Rights of the Child   Statute of the International Court of Justice   Annual Report of the Secretary-General on the Work of the Organization\n\nNews and Media   News   Press Releases   Briefings   Spokesperson   Photos   UNIfeed   UN Web TV   UN Video   Social Media   The Essential UN   Awake at Night podcast\n\nNews and Media   News   Press Releases   Briefings   Spokesperson   Photos   UNIfeed   UN Web TV   UN Video   Social Media   The Essential UN   Awake at Night podcast\n\nIssues / Campaigns   Global Issues   Observances   Sustainable Development Goals   Our Common Agenda   The Summit of the Future   Climate Action   Peace and Security   Action for Peacekeeping (A4P)   Global Crisis Response Group   Call to Action for Human Rights   Disability Inclusion Strategy   Fight Racism   Hate Speech   LGBTIQ+ People   Safety of Journalists   Rule of Law   Action to Counter Terrorism   Victims of Terrorism   Children and Armed Conflict   Violence Against Children (SRSG)   Sexual Violence in Conflict   Refugees and Migrants   Action Agenda on Internal Displacement   Spotlight Initiative   Preventing Sexual Exploitation and Abuse   Prevention of Genocide and the Responsibility to Protect   The Rwanda Genocide   The Holocaust   The Question of Palestine   The Transatlantic Slave Trade   Decolonization   Messengers of Peace   Roadmap for Digital Cooperation   Digital Financing Task Force   Data Strategy   Information Integrity   Countering Disinformation   UN75: 2020 and Beyond   Women Rise for All   Stop the Red Sea Catastrophe   Black Sea Grain Initiative Joint Coordination Centre\n\nIssues / Campaigns   Global Issues   Observances   Sustainable Development Goals   Our Common Agenda   The Summit of the Future   Climate Action   Peace and Security   Action for Peacekeeping (A4P)   Global Crisis Response Group   Call to Action for Human Rights   Disability Inclusion Strategy   Fight Racism   Hate Speech   LGBTIQ+ People   Safety of Journalists   Rule of Law   Action to Counter Terrorism   Victims of Terrorism   Children and Armed Conflict   Violence Against Children (SRSG)   Sexual Violence in Conflict   Refugees and Migrants   Action Agenda on Internal Displacement   Spotlight Initiative   Preventing Sexual Exploitation and Abuse   Prevention of Genocide and the Responsibility to Protect   The Rwanda Genocide   The Holocaust   The Question of Palestine   The Transatlantic Slave Trade   Decolonization   Messengers of Peace   Roadmap for Digital Cooperation   Digital Financing Task Force   Data Strategy   Information Integrity   Countering Disinformation   UN75: 2020 and Beyond   Women Rise for All   Stop the Red Sea Catastrophe   Black Sea Grain Initiative Joint Coordination Centre\n\nIssues / Campaigns   Global Issues   Observances   Sustainable Development Goals   Our Common Agenda   The Summit of the Future   Climate Action   Peace and Security   Action for Peacekeeping (A4P)   Global Crisis Response Group   Call to Action for Human Rights   Disability Inclusion Strategy   Fight Racism   Hate Speech   LGBTIQ+ People   Safety of Journalists   Rule of Law   Action to Counter Terrorism   Victims of Terrorism   Children and Armed Conflict   Violence Against Children (SRSG)   Sexual Violence in Conflict   Refugees and Migrants   Action Agenda on Internal Displacement   Spotlight Initiative   Preventing Sexual Exploitation and Abuse   Prevention of Genocide and the Responsibility to Protect   The Rwanda Genocide   The Holocaust   The Question of Palestine   The Transatlantic Slave Trade   Decolonization   Messengers of Peace   Roadmap for Digital Cooperation   Digital Financing Task Force   Data Strategy   Information Integrity   Countering Disinformation   UN75: 2020 and Beyond   Women Rise for All   Stop the Red Sea Catastrophe   Black Sea Grain Initiative Joint Coordination Centre",
  "entities": {
    "countries": [],
    "organizations": [
      "united nations",
      "un"
    ],
    "key_issues": [
      "issue",
      "crisis",
      "nation",
      "state",
      "region",
      "strategy",
      "initiative",
      "action",
      "history",
      "origin",
      "development",
      "human rights",
      "economic",
      "trade",
      "united nations",
      "un",
      "security council",
      "general assembly",
      "ngo",
      "organization"
    ]
  },
  "committee": "Fourth Committee",
  "topic": "Ensuring the rights and safety of indigenous populations"
}