{
  "url": "https://www.unodc.org/unodc/index.html",
  "title": "United Nations Office on Drugs and Crime",
  "text": "United NationsOffice on Drugs and CrimeSite Search\n\nUnited NationsOffice on Drugs and CrimeSite Search\n\nUnited NationsOffice on Drugs and Crime\n\nUnited Nations\n\nOffice on Drugs and Crime\n\nSite Search\n\nSite Search\n\nGet back up and try again: the power of sports in violence and crime prevention\n\n04/04/2025\n\n\n\n\n\nUsing open-source intelligence to investigate human trafficking and migrant smuggling\n\n27/03/2025\n\n\n\n\n\nNo more shortcuts: addressing corruption in India\n\n26/03/2025\n\n\n\n\n\nFarmers cultivate an opium-free future for Laos\n\n24/03/2025\n\n\n\nPreviousNext\n\n\n\nAll StoriesSubscribe\n\n\n\n\n\n\n\nHighlights\nCommission on Narcotic Drugs (CND) - 68th session\nVienna, Austria 10-14 March 2025\nProgramme and Webcast | Media accreditationReal-time photos\n\nNews\nExplainer: What is the Commission on Narcotic Drugs?More News\n\nPress Releases\n\n\n07/04/2025 — UNODC: new study shows forest crime converging with other types of organized crime,\n                     fueling harms to the environment, communities, and economy\n\n\n12/03/2025 — UNODC: Opium prices in Afghanistan near historic peaks, mostly benefiting large-scale\n                     traffickers\n\n\n05/03/2025 — UN Office on Drugs and Crime and Zero Project/ Essl Foundation announce new partnership\n                     for people with disabilities\n\n\n\n\nAll Press Releases\n\n\n\n\nSubscribe\n\n\n\n\n\n\n\nIn Focus\n\n\nFLAGSHIP REPORTS\n\n\n\n\n\nFemicides in 2023\n\nSubmit to the ‘My Voice matters in the Fight against Organized Crime’ Zine\n\nUNODC World Drug Report 2024\n\n\n\n\npublications\n\n\nMultimedia\n\n\n\n\n\n\n\n\n07/04/2025 — Global Analysis on Crimes against the Environment - Forest Crime\n\nAll Publications\n\n5 facts about the Cybercrime Convention\n\nScam Artist or Human Trafficking Victim? - Inside a Scam Farm\n\n\n\n\n\n\n\n\n\n\n\nAbout UNODC\n\nAnnual Appeal\nAnnual Report\nCareers\nEvaluation\nFunding and partnerships\nGoodwill Ambassadors\nInternational days and campaigns\nLeadership\nLibrary\nProcurement\nPublications\nSustainable Development Goals\nContact UNODC\n\n\n\nQuick Links\n\nAd hoc committee to elaborate an international convention on countering the use of ICTs for criminal purposes\nCivil Society Engagement\nCommission on Crime Prevention and Criminal Justice (CCPCJ)\nCommission on Narcotic Drugs (CND)\nConference of the Parties to the United Nations Convention against Transnational Organized Crime and its Protocols (CTOP/COP)\nConference of the States Parties to the United Nations Convention against Corruption (COSP)\nIMOLIN - the international money laundering information network\nInternational Anti-Corruption Day (9 December)\nInternational Day against Drug Abuse and Illicit Trafficking (26 June)\nInternational Narcotics Control Board (INCB)\nTreatnet\nUnited Nations drug, crime and terrorism treaties\nUnited Nations system website locator\nUnited Nations Trust Fund for Victims of Human Trafficking\nUNODC Youth Initiative\nWorld Drug Report\n\n\n\nField Offices\n\nEurope and West/Central Asia\n\nAfghanistan\nCentral Asia\nIran, Islamic Republic of\nPakistan\nSouth Eastern Europe\nUkraine\nRegional Programme for Afghanistan and Neighbouring Countries\n\n\nAfrica and Middle East \n\nEastern Africa\nMiddle East and North Africa\nNigeria\nSouthern Africa\nWest and Central Africa\n\n\nLatin America and the Caribbean\n\nAndean Region and Southern Cone \n\n         Argentina         Bolivia            Chile            Colombia            Ecuador            Peru            Uruguay\n\nBrazil\nCentral America and the Caribbean\nMexico\n\n\nSoutheast Asia and the PacificCambodiaIndonesiaLao PDRMalaysiaMyanmarPacific IslandsPapua New GuineaPhlippinesThailandViet Nam\nSouth Asia\nLiaison Office - Brussels\nLiaison Office - New York\n\nGet back up and try again: the power of sports in violence and crime prevention\n\n04/04/2025\n\n\n\n\n\nUsing open-source intelligence to investigate human trafficking and migrant smuggling\n\n27/03/2025\n\n\n\n\n\nNo more shortcuts: addressing corruption in India\n\n26/03/2025\n\n\n\n\n\nFarmers cultivate an opium-free future for Laos\n\n24/03/2025\n\n\n\nPreviousNext\n\n\n\nAll StoriesSubscribe\n\nGet back up and try again: the power of sports in violence and crime prevention\n\n04/04/2025\n\n\n\n\n\nUsing open-source intelligence to investigate human trafficking and migrant smuggling\n\n27/03/2025\n\n\n\n\n\nNo more shortcuts: addressing corruption in India\n\n26/03/2025\n\n\n\n\n\nFarmers cultivate an opium-free future for Laos\n\n24/03/2025\n\n\n\nPreviousNext\n\n\n\nAll StoriesSubscribe\n\nGet back up and try again: the power of sports in violence and crime prevention\n\n04/04/2025\n\n\n\n\n\nUsing open-source intelligence to investigate human trafficking and migrant smuggling\n\n27/03/2025\n\n\n\n\n\nNo more shortcuts: addressing corruption in India\n\n26/03/2025\n\n\n\n\n\nFarmers cultivate an opium-free future for Laos\n\n24/03/2025\n\n\n\nPreviousNext\n\n\n\nAll StoriesSubscribe\n\nGet back up and try again: the power of sports in violence and crime prevention\n\n04/04/2025\n\n\n\n\n\nUsing open-source intelligence to investigate human trafficking and migrant smuggling\n\n27/03/2025\n\n\n\n\n\nNo more shortcuts: addressing corruption in India\n\n26/03/2025\n\n\n\n\n\nFarmers cultivate an opium-free future for Laos\n\n24/03/2025\n\n\n\nPreviousNext\n\nGet back up and try again: the power of sports in violence and crime prevention\n\n04/04/2025\n\n\n\n\n\nUsing open-source intelligence to investigate human trafficking and migrant smuggling\n\n27/03/2025\n\n\n\n\n\nNo more shortcuts: addressing corruption in India\n\n26/03/2025\n\n\n\n\n\nFarmers cultivate an opium-free future for Laos\n\n24/03/2025\n\n\n\nPreviousNext\n\nGet back up and try again: the power of sports in violence and crime prevention\n\n04/04/2025\n\n\n\n\n\nUsing open-source intelligence to investigate human trafficking and migrant smuggling\n\n27/03/2025\n\n\n\n\n\nNo more shortcuts: addressing corruption in India\n\n26/03/2025\n\n\n\n\n\nFarmers cultivate an opium-free future for Laos\n\n24/03/2025\n\nGet back up and try again: the power of sports in violence and crime prevention\n\n04/04/2025\n\nGet back up and try again: the power of sports in violence and crime prevention\n\n04/04/2025\n\nGet back up and try again: the power of sports in violence and crime prevention\n\n04/04/2025\n\n04/04/2025\n\nUsing open-source intelligence to investigate human trafficking and migrant smuggling\n\n27/03/2025\n\nUsing open-source intelligence to investigate human trafficking and migrant smuggling\n\n27/03/2025\n\nUsing open-source intelligence to investigate human trafficking and migrant smuggling\n\n27/03/2025\n\n27/03/2025\n\nNo more shortcuts: addressing corruption in India\n\n26/03/2025\n\nNo more shortcuts: addressing corruption in India\n\n26/03/2025\n\nNo more shortcuts: addressing corruption in India\n\n26/03/2025\n\n26/03/2025\n\nFarmers cultivate an opium-free future for Laos\n\n24/03/2025\n\nFarmers cultivate an opium-free future for Laos\n\n24/03/2025\n\nFarmers cultivate an opium-free future for Laos\n\n24/03/2025\n\n24/03/2025\n\nAll StoriesSubscribe\n\nAll StoriesSubscribe\n\nAll StoriesSubscribe\n\nHighlights\nCommission on Narcotic Drugs (CND) - 68th session\nVienna, Austria 10-14 March 2025\nProgramme and Webcast | Media accreditationReal-time photos\n\nNews\nExplainer: What is the Commission on Narcotic Drugs?More News\n\nPress Releases\n\n\n07/04/2025 — UNODC: new study shows forest crime converging with other types of organized crime,\n                     fueling harms to the environment, communities, and economy\n\n\n12/03/2025 — UNODC: Opium prices in Afghanistan near historic peaks, mostly benefiting large-scale\n                     traffickers\n\n\n05/03/2025 — UN Office on Drugs and Crime and Zero Project/ Essl Foundation announce new partnership\n                     for people with disabilities\n\n\n\n\nAll Press Releases\n\n\n\n\nSubscribe\n\nHighlights\nCommission on Narcotic Drugs (CND) - 68th session\nVienna, Austria 10-14 March 2025\nProgramme and Webcast | Media accreditationReal-time photos\n\nNews\nExplainer: What is the Commission on Narcotic Drugs?More News\n\nPress Releases\n\n\n07/04/2025 — UNODC: new study shows forest crime converging with other types of organized crime,\n                     fueling harms to the environment, communities, and economy\n\n\n12/03/2025 — UNODC: Opium prices in Afghanistan near historic peaks, mostly benefiting large-scale\n                     traffickers\n\n\n05/03/2025 — UN Office on Drugs and Crime and Zero Project/ Essl Foundation announce new partnership\n                     for people with disabilities\n\n\n\n\nAll Press Releases\n\n\n\n\nSubscribe\n\nHighlights\nCommission on Narcotic Drugs (CND) - 68th session\nVienna, Austria 10-14 March 2025\nProgramme and Webcast | Media accreditationReal-time photos\n\nNews\nExplainer: What is the Commission on Narcotic Drugs?More News\n\nPress Releases\n\n\n07/04/2025 — UNODC: new study shows forest crime converging with other types of organized crime,\n                     fueling harms to the environment, communities, and economy\n\n\n12/03/2025 — UNODC: Opium prices in Afghanistan near historic peaks, mostly benefiting large-scale\n                     traffickers\n\n\n05/03/2025 — UN Office on Drugs and Crime and Zero Project/ Essl Foundation announce new partnership\n                     for people with disabilities\n\n\n\n\nAll Press Releases\n\n\n\n\nSubscribe\n\n07/04/2025 — UNODC: new study shows forest crime converging with other types of organized crime,\n                     fueling harms to the environment, communities, and economy\n\n12/03/2025 — UNODC: Opium prices in Afghanistan near historic peaks, mostly benefiting large-scale\n                     traffickers\n\n05/03/2025 — UN Office on Drugs and Crime and Zero Project/ Essl Foundation announce new partnership\n                     for people with disabilities\n\nAll Press Releases\n\nAll Press Releases\n\nAll Press Releases\n\nSubscribe\n\nSubscribe\n\nSubscribe\n\nIn Focus\n\n\nFLAGSHIP REPORTS\n\nIn Focus\n\n\nFLAGSHIP REPORTS\n\nIn Focus\n\nFLAGSHIP REPORTS\n\nFemicides in 2023\n\nSubmit to the ‘My Voice matters in the Fight against Organized Crime’ Zine\n\nUNODC World Drug Report 2024\n\nFemicides in 2023\n\nSubmit to the ‘My Voice matters in the Fight against Organized Crime’ Zine\n\nUNODC World Drug Report 2024\n\nFemicides in 2023\n\nSubmit to the ‘My Voice matters in the Fight against Organized Crime’ Zine\n\nUNODC World Drug Report 2024\n\npublications\n\n\nMultimedia\n\npublications\n\n\nMultimedia\n\npublications\n\nMultimedia\n\n07/04/2025 — Global Analysis on Crimes against the Environment - Forest Crime\n\nAll Publications\n\n5 facts about the Cybercrime Convention\n\nScam Artist or Human Trafficking Victim? - Inside a Scam Farm\n\n07/04/2025 — Global Analysis on Crimes against the Environment - Forest Crime\n\nAll Publications\n\n5 facts about the Cybercrime Convention\n\nScam Artist or Human Trafficking Victim? - Inside a Scam Farm\n\n07/04/2025 — Global Analysis on Crimes against the Environment - Forest Crime\n\nAll Publications\n\n07/04/2025 — Global Analysis on Crimes against the Environment - Forest Crime\n\n5 facts about the Cybercrime Convention\n\nScam Artist or Human Trafficking Victim? - Inside a Scam Farm\n\nAbout UNODC\n\nAnnual Appeal\nAnnual Report\nCareers\nEvaluation\nFunding and partnerships\nGoodwill Ambassadors\nInternational days and campaigns\nLeadership\nLibrary\nProcurement\nPublications\nSustainable Development Goals\nContact UNODC\n\n\n\nQuick Links\n\nAd hoc committee to elaborate an international convention on countering the use of ICTs for criminal purposes\nCivil Society Engagement\nCommission on Crime Prevention and Criminal Justice (CCPCJ)\nCommission on Narcotic Drugs (CND)\nConference of the Parties to the United Nations Convention against Transnational Organized Crime and its Protocols (CTOP/COP)\nConference of the States Parties to the United Nations Convention against Corruption (COSP)\nIMOLIN - the international money laundering information network\nInternational Anti-Corruption Day (9 December)\nInternational Day against Drug Abuse and Illicit Trafficking (26 June)\nInternational Narcotics Control Board (INCB)\nTreatnet\nUnited Nations drug, crime and terrorism treaties\nUnited Nations system website locator\nUnited Nations Trust Fund for Victims of Human Trafficking\nUNODC Youth Initiative\nWorld Drug Report\n\n\n\nField Offices\n\nEurope and West/Central Asia\n\nAfghanistan\nCentral Asia\nIran, Islamic Republic of\nPakistan\nSouth Eastern Europe\nUkraine\nRegional Programme for Afghanistan and Neighbouring Countries\n\n\nAfrica and Middle East \n\nEastern Africa\nMiddle East and North Africa\nNigeria\nSouthern Africa\nWest and Central Africa\n\n\nLatin America and the Caribbean\n\nAndean Region and Southern Cone \n\n         Argentina         Bolivia            Chile            Colombia            Ecuador            Peru            Uruguay\n\nBrazil\nCentral America and the Caribbean\nMexico\n\n\nSoutheast Asia and the PacificCambodiaIndonesiaLao PDRMalaysiaMyanmarPacific IslandsPapua New GuineaPhlippinesThailandViet Nam\nSouth Asia\nLiaison Office - Brussels\nLiaison Office - New York\n\nAbout UNODC\n\nAnnual Appeal\nAnnual Report\nCareers\nEvaluation\nFunding and partnerships\nGoodwill Ambassadors\nInternational days and campaigns\nLeadership\nLibrary\nProcurement\nPublications\nSustainable Development Goals\nContact UNODC\n\n\n\nQuick Links\n\nAd hoc committee to elaborate an international convention on countering the use of ICTs for criminal purposes\nCivil Society Engagement\nCommission on Crime Prevention and Criminal Justice (CCPCJ)\nCommission on Narcotic Drugs (CND)\nConference of the Parties to the United Nations Convention against Transnational Organized Crime and its Protocols (CTOP/COP)\nConference of the States Parties to the United Nations Convention against Corruption (COSP)\nIMOLIN - the international money laundering information network\nInternational Anti-Corruption Day (9 December)\nInternational Day against Drug Abuse and Illicit Trafficking (26 June)\nInternational Narcotics Control Board (INCB)\nTreatnet\nUnited Nations drug, crime and terrorism treaties\nUnited Nations system website locator\nUnited Nations Trust Fund for Victims of Human Trafficking\nUNODC Youth Initiative\nWorld Drug Report\n\n\n\nField Offices\n\nEurope and West/Central Asia\n\nAfghanistan\nCentral Asia\nIran, Islamic Republic of\nPakistan\nSouth Eastern Europe\nUkraine\nRegional Programme for Afghanistan and Neighbouring Countries\n\n\nAfrica and Middle East \n\nEastern Africa\nMiddle East and North Africa\nNigeria\nSouthern Africa\nWest and Central Africa\n\n\nLatin America and the Caribbean\n\nAndean Region and Southern Cone \n\n         Argentina         Bolivia            Chile            Colombia            Ecuador            Peru            Uruguay\n\nBrazil\nCentral America and the Caribbean\nMexico\n\n\nSoutheast Asia and the PacificCambodiaIndonesiaLao PDRMalaysiaMyanmarPacific IslandsPapua New GuineaPhlippinesThailandViet Nam\nSouth Asia\nLiaison Office - Brussels\nLiaison Office - New York\n\nAbout UNODC\n\nAnnual Appeal\nAnnual Report\nCareers\nEvaluation\nFunding and partnerships\nGoodwill Ambassadors\nInternational days and campaigns\nLeadership\nLibrary\nProcurement\nPublications\nSustainable Development Goals\nContact UNODC\n\n\n\nQuick Links\n\nAd hoc committee to elaborate an international convention on countering the use of ICTs for criminal purposes\nCivil Society Engagement\nCommission on Crime Prevention and Criminal Justice (CCPCJ)\nCommission on Narcotic Drugs (CND)\nConference of the Parties to the United Nations Convention against Transnational Organized Crime and its Protocols (CTOP/COP)\nConference of the States Parties to the United Nations Convention against Corruption (COSP)\nIMOLIN - the international money laundering information network\nInternational Anti-Corruption Day (9 December)\nInternational Day against Drug Abuse and Illicit Trafficking (26 June)\nInternational Narcotics Control Board (INCB)\nTreatnet\nUnited Nations drug, crime and terrorism treaties\nUnited Nations system website locator\nUnited Nations Trust Fund for Victims of Human Trafficking\nUNODC Youth Initiative\nWorld Drug Report\n\n\n\nField Offices\n\nEurope and West/Central Asia\n\nAfghanistan\nCentral Asia\nIran, Islamic Republic of\nPakistan\nSouth Eastern Europe\nUkraine\nRegional Programme for Afghanistan and Neighbouring Countries\n\n\nAfrica and Middle East \n\nEastern Africa\nMiddle East and North Africa\nNigeria\nSouthern Africa\nWest and Central Africa\n\n\nLatin America and the Caribbean\n\nAndean Region and Southern Cone \n\n         Argentina         Bolivia            Chile            Colombia            Ecuador            Peru            Uruguay\n\nBrazil\nCentral America and the Caribbean\nMexico\n\n\nSoutheast Asia and the PacificCambodiaIndonesiaLao PDRMalaysiaMyanmarPacific IslandsPapua New GuineaPhlippinesThailandViet Nam\nSouth Asia\nLiaison Office - Brussels\nLiaison Office - New York\n\nUnited Nations Office on Drugs and CrimeHomeContactsFraud AlertLegal Notice\n\nUnited Nations Office on Drugs and CrimeHomeContactsFraud AlertLegal Notice\n\nUnited Nations Office on Drugs and Crime\n\nUnited Nations Office on Drugs and Crime\n\nUnited Nations Office on Drugs and Crime\n\nUnited Nations Office on Drugs and Crime\n\nHomeContactsFraud AlertLegal Notice\n\nHomeContactsFraud AlertLegal Notice\n\nHomeContactsFraud AlertLegal Notice",
  "date": "",
  "source_type": "other",
  "extracted_at": "2025-04-07T14:32:55.868653",
  "metadata": {
    "og:site_name": "United Nations : Office on Drugs and Crime",
    "keywords": "United Nations Office on Drugs and Crime"
  },
  "relevance_score": 0.5416666666666666,
  "summary": "United NationsOffice on Drugs and CrimeSite Search\n\nUnited NationsOffice on Drugs and CrimeSite Search\n\nUnited NationsOffice on Drugs and Crime\n\nUnited Nations\n\nOffice on Drugs and Crime\n\nSite Search\n\nSite Search\n\nGet back up and try again: the power of sports in violence and crime prevention\n\n04/04/2025\n\n\n\n\n\nUsing open-source intelligence to investigate human trafficking and migrant smuggling\n\n27/03/2025\n\n\n\n\n\nNo more shortcuts: addressing corruption in India\n\n26/03/2025\n\n\n\n\n\nFarmers cultivate an opium-free future for Laos\n\n24/03/2025\n\n\n\nPreviousNext\n\n\n\nAll StoriesSubscribe\n\n\n\n\n\n\n\nHighlights\nCommission on Narcotic Drugs (CND) - 68th session\nVienna, Austria 10-14 March 2025\nProgramme and Webcast | Media accreditationReal-time photos\n\nNews\nExplainer: What is the Commission on Narcotic Drugs?More News\n\nPress Releases\n\n\n07/04/2025 — UNODC: new study shows forest crime converging with other types of organized crime,\n                     fueling harms to the environment, communities, and economy\n\n\n12/03/2025 — UNODC: Opium prices in Afghanistan near historic peaks, mostly benefiting large-scale\n                     traffickers\n\n\n05/03/2025 — UN Office on Drugs and Crime and Zero Project/ Essl Foundation announce new partnership\n                     for people with disabilities\n\n\n\n\nAll Press Releases\n\n\n\n\nSubscribe\n\n\n\n\n\n\n\nIn Focus\n\n\nFLAGSHIP REPORTS\n\n\n\n\n\nFemicides in 2023\n\nSubmit to the ‘My Voice matters in the Fight against Organized Crime’ Zine\n\nUNODC World Drug Report 2024\n\n\n\n\npublications\n\n\nMultimedia\n\n\n\n\n\n\n\n\n07/04/2025 — Global Analysis on Crimes against the Environment - Forest Crime\n\nAll Publications\n\n5 facts about the Cybercrime Convention\n\nScam Artist or Human Trafficking Victim? - Inside a Scam Farm\n\n\n\n\n\n\n\n\n\n\n\nAbout UNODC\n\nAnnual Appeal\nAnnual Report\nCareers\nEvaluation\nFunding and partnerships\nGoodwill Ambassadors\nInternational days and campaigns\nLeadership\nLibrary\nProcurement\nPublications\nSustainable Development Goals\nContact UNODC\n\n\n\nQuick Links\n\nAd hoc committee to elaborate an international convention on countering the use of ICTs for criminal purposes\nCivil Society Engagement\nCommission on Crime Prevention and Criminal Justice (CCPCJ)\nCommission on Narcotic Drugs (CND)\nConference of the Parties to the United Nations Convention against Transnational Organized Crime and its Protocols (CTOP/COP)\nConference of the States Parties to the United Nations Convention against Corruption (COSP)\nIMOLIN - the international money laundering information network\nInternational Anti-Corruption Day (9 December)\nInternational Day against Drug Abuse and Illicit Trafficking (26 June)\nInternational Narcotics Control Board (INCB)\nTreatnet\nUnited Nations drug, crime and terrorism treaties\nUnited Nations system website locator\nUnited Nations Trust Fund for Victims of Human Trafficking\nUNODC Youth Initiative\nWorld Drug Report\n\n\n\nField Offices\n\nEurope and West/Central Asia\n\nAfghanistan\nCentral Asia\nIran, Islamic Republic of\nPakistan\nSouth Eastern Europe\nUkraine\nRegional Programme for Afghanistan and Neighbouring Countries\n\n\nAfrica and Middle East \n\nEastern Africa\nMiddle East and North Africa\nNigeria\nSouthern Africa\nWest and Central Africa\n\n\nLatin America and the Caribbean\n\nAndean Region and Southern Cone \n\n         Argentina         Bolivia            Chile            Colombia            Ecuador            Peru            Uruguay\n\nBrazil\nCentral America and the Caribbean\nMexico\n\n\nSoutheast Asia and the PacificCambodiaIndonesiaLao PDRMalaysiaMyanmarPacific IslandsPapua New GuineaPhlippinesThailandViet Nam\nSouth Asia\nLiaison Office - Brussels\nLiaison Office - New York\n\nGet back up and try again: the power of sports in violence and crime prevention\n\n04/04/2025\n\n\n\n\n\nUsing open-source intelligence to investigate human trafficking and migrant smuggling\n\n27/03/2025\n\n\n\n\n\nNo more shortcuts: addressing corruption in India\n\n26/03/2025\n\n\n\n\n\nFarmers cultivate an opium-free future for Laos\n\n24/03/2025\n\n\n\nPreviousNext\n\n\n\nAll StoriesSubscribe\n\nGet back up and try again: the power of sports in violence and crime prevention\n\n04/04/2025\n\n\n\n\n\nUsing open-source intelligence to investigate human trafficking and migrant smuggling\n\n27/03/2025\n\n\n\n\n\nNo more shortcuts: addressing corruption in India\n\n26/03/2025\n\n\n\n\n\nFarmers cultivate an opium-free future for Laos\n\n24/03/2025\n\n\n\nPreviousNext\n\n\n\nAll StoriesSubscribe\n\nGet back up and try again: the power of sports in violence and crime prevention\n\n04/04/2025\n\n\n\n\n\nUsing open-source intelligence to investigate human trafficking and migrant smuggling\n\n27/03/2025\n\n\n\n\n\nNo more shortcuts: addressing corruption in India\n\n26/03/2025\n\n\n\n\n\nFarmers cultivate an opium-free future for Laos\n\n24/03/2025\n\n\n\nPreviousNext\n\n\n\nAll StoriesSubscribe\n\nGet back up and try again: the power of sports in violence and crime prevention\n\n04/04/2025\n\n\n\n\n\nUsing open-source intelligence to investigate human trafficking and migrant smuggling\n\n27/03/2025\n\n\n\n\n\nNo more shortcuts: addressing corruption in India\n\n26/03/2025\n\n\n\n\n\nFarmers cultivate an opium-free future for Laos\n\n24/03/2025\n\n\n\nPreviousNext\n\nGet back up and try again: the power of sports in violence and crime prevention\n\n04/04/2025\n\n\n\n\n\nUsing open-source intelligence to investigate human trafficking and migrant smuggling\n\n27/03/2025\n\n\n\n\n\nNo more shortcuts: addressing corruption in India\n\n26/03/2025\n\n\n\n\n\nFarmers cultivate an opium-free future for Laos\n\n24/03/2025\n\n\n\nPreviousNext\n\nGet back up and try again: the power of sports in violence and crime prevention\n\n04/04/2025\n\n\n\n\n\nUsing open-source intelligence to investigate human trafficking and migrant smuggling\n\n27/03/2025\n\n\n\n\n\nNo more shortcuts: addressing corruption in India\n\n26/03/2025\n\n\n\n\n\nFarmers cultivate an opium-free future for Laos\n\n24/03/2025\n\nGet back up and try again: the power of sports in violence and crime prevention\n\n04/04/2025\n\nGet back up and try again: the power of sports in violence and crime prevention\n\n04/04/2025\n\nGet back up and try again: the power of sports in violence and crime prevention\n\n04/04/2025\n\n04/04/2025\n\nUsing open-source intelligence to investigate human trafficking and migrant smuggling\n\n27/03/2025\n\nUsing open-source intelligence to investigate human trafficking and migrant smuggling\n\n27/03/2025\n\nUsing open-source intelligence to investigate human trafficking and migrant smuggling\n\n27/03/2025\n\n27/03/2025\n\nNo more shortcuts: addressing corruption in India\n\n26/03/2025\n\nNo more shortcuts: addressing corruption in India\n\n26/03/2025\n\nNo more shortcuts: addressing corruption in India\n\n26/03/2025\n\n26/03/2025\n\nFarmers cultivate an opium-free future for Laos\n\n24/03/2025\n\nFarmers cultivate an opium-free future for Laos\n\n24/03/2025\n\nFarmers cultivate an opium-free future for Laos\n\n24/03/2025\n\n24/03/2025\n\nAll StoriesSubscribe\n\nAll StoriesSubscribe\n\nAll StoriesSubscribe\n\nHighlights\nCommission on Narcotic Drugs (CND) - 68th session\nVienna, Austria 10-14 March 2025\nProgramme and Webcast | Media accreditationReal-time photos\n\nNews\nExplainer: What is the Commission on Narcotic Drugs?More News\n\nPress Releases\n\n\n07/04/2025 — UNODC: new study shows forest crime converging with other types of organized crime,\n                     fueling harms to the environment, communities, and economy\n\n\n12/03/2025 — UNODC: Opium prices in Afghanistan near historic peaks, mostly benefiting large-scale\n                     traffickers\n\n\n05/03/2025 — UN Office on Drugs and Crime and Zero Project/ Essl Foundation announce new partnership\n                     for people with disabilities\n\n\n\n\nAll Press Releases\n\n\n\n\nSubscribe\n\nHighlights\nCommission on Narcotic Drugs (CND) - 68th session\nVienna, Austria 10-14 March 2025\nProgramme and Webcast | Media accreditationReal-time photos\n\nNews\nExplainer: What is the Commission on Narcotic Drugs?More News\n\nPress Releases\n\n\n07/04/2025 — UNODC: new study shows forest crime converging with other types of organized crime,\n                     fueling harms to the environment, communities, and economy\n\n\n12/03/2025 — UNODC: Opium prices in Afghanistan near historic peaks, mostly benefiting large-scale\n                     traffickers\n\n\n05/03/2025 — UN Office on Drugs and Crime and Zero Project/ Essl Foundation announce new partnership\n                     for people with disabilities\n\n\n\n\nAll Press Releases\n\n\n\n\nSubscribe\n\nHighlights\nCommission on Narcotic Drugs (CND) - 68th session\nVienna, Austria 10-14 March 2025\nProgramme and Webcast | Media accreditationReal-time photos\n\nNews\nExplainer: What is the Commission on Narcotic Drugs?More News\n\nPress Releases\n\n\n07/04/2025 — UNODC: new study shows forest crime converging with other types of organized crime,\n                     fueling harms to the environment, communities, and economy\n\n\n12/03/2025 — UNODC: Opium prices in Afghanistan near historic peaks, mostly benefiting large-scale\n                     traffickers\n\n\n05/03/2025 — UN Office on Drugs and Crime and Zero Project/ Essl Foundation announce new partnership\n                     for people with disabilities\n\n\n\n\nAll Press Releases\n\n\n\n\nSubscribe\n\n07/04/2025 — UNODC: new study shows forest crime converging with other types of organized crime,\n                     fueling harms to the environment, communities, and economy\n\n12/03/2025 — UNODC: Opium prices in Afghanistan near historic peaks, mostly benefiting large-scale\n                     traffickers\n\n05/03/2025 — UN Office on Drugs and Crime and Zero Project/ Essl Foundation announce new partnership\n                     for people with disabilities\n\nAll Press Releases\n\nAll Press Releases\n\nAll Press Releases\n\nSubscribe\n\nSubscribe\n\nSubscribe\n\nIn Focus\n\n\nFLAGSHIP REPORTS\n\nIn Focus\n\n\nFLAGSHIP REPORTS\n\nIn Focus\n\nFLAGSHIP REPORTS\n\nFemicides in 2023\n\nSubmit to the ‘My Voice matters in the Fight against Organized Crime’ Zine\n\nUNODC World Drug Report 2024\n\nFemicides in 2023\n\nSubmit to the ‘My Voice matters in the Fight against Organized Crime’ Zine\n\nUNODC World Drug Report 2024\n\nFemicides in 2023\n\nSubmit to the ‘My Voice matters in the Fight against Organized Crime’ Zine\n\nUNODC World Drug Report 2024\n\npublications\n\n\nMultimedia\n\npublications\n\n\nMultimedia\n\npublications\n\nMultimedia\n\n07/04/2025 — Global Analysis on Crimes against the Environment - Forest Crime\n\nAll Publications\n\n5 facts about the Cybercrime Convention\n\nScam Artist or Human Trafficking Victim? - Inside a Scam Farm\n\n07/04/2025 — Global Analysis on Crimes against the Environment - Forest Crime\n\nAll Publications\n\n5 facts about the Cybercrime Convention\n\nScam Artist or Human Trafficking Victim? - Inside a Scam Farm\n\n07/04/2025 — Global Analysis on Crimes against the Environment - Forest Crime\n\nAll Publications\n\n07/04/2025 — Global Analysis on Crimes against the Environment - Forest Crime\n\n5 facts about the Cybercrime Convention\n\nScam Artist or Human Trafficking Victim? - Inside a Scam Farm\n\nAbout UNODC\n\nAnnual Appeal\nAnnual Report\nCareers\nEvaluation\nFunding and partnerships\nGoodwill Ambassadors\nInternational days and campaigns\nLeadership\nLibrary\nProcurement\nPublications\nSustainable Development Goals\nContact UNODC\n\n\n\nQuick Links\n\nAd hoc committee to elaborate an international convention on countering the use of ICTs for criminal purposes\nCivil Society Engagement\nCommission on Crime Prevention and Criminal Justice (CCPCJ)\nCommission on Narcotic Drugs (CND)\nConference of the Parties to the United Nations Convention against Transnational Organized Crime and its Protocols (CTOP/COP)\nConference of the States Parties to the United Nations Convention against Corruption (COSP)\nIMOLIN - the international money laundering information network\nInternational Anti-Corruption Day (9 December)\nInternational Day against Drug Abuse and Illicit Trafficking (26 June)\nInternational Narcotics Control Board (INCB)\nTreatnet\nUnited Nations drug, crime and terrorism treaties\nUnited Nations system website locator\nUnited Nations Trust Fund for Victims of Human Trafficking\nUNODC Youth Initiative\nWorld Drug Report\n\n\n\nField Offices\n\nEurope and West/Central Asia\n\nAfghanistan\nCentral Asia\nIran, Islamic Republic of\nPakistan\nSouth Eastern Europe\nUkraine\nRegional Programme for Afghanistan and Neighbouring Countries\n\n\nAfrica and Middle East \n\nEastern Africa\nMiddle East and North Africa\nNigeria\nSouthern Africa\nWest and Central Africa\n\n\nLatin America and the Caribbean\n\nAndean Region and Southern Cone \n\n         Argentina         Bolivia            Chile            Colombia            Ecuador            Peru            Uruguay\n\nBrazil\nCentral America and the Caribbean\nMexico\n\n\nSoutheast Asia and the PacificCambodiaIndonesiaLao PDRMalaysiaMyanmarPacific IslandsPapua New GuineaPhlippinesThailandViet Nam\nSouth Asia\nLiaison Office - Brussels\nLiaison Office - New York\n\nAbout UNODC\n\nAnnual Appeal\nAnnual Report\nCareers\nEvaluation\nFunding and partnerships\nGoodwill Ambassadors\nInternational days and campaigns\nLeadership\nLibrary\nProcurement\nPublications\nSustainable Development Goals\nContact UNODC\n\n\n\nQuick Links\n\nAd hoc committee to elaborate an international convention on countering the use of ICTs for criminal purposes\nCivil Society Engagement\nCommission on Crime Prevention and Criminal Justice (CCPCJ)\nCommission on Narcotic Drugs (CND)\nConference of the Parties to the United Nations Convention against Transnational Organized Crime and its Protocols (CTOP/COP)\nConference of the States Parties to the United Nations Convention against Corruption (COSP)\nIMOLIN - the international money laundering information network\nInternational Anti-Corruption Day (9 December)\nInternational Day against Drug Abuse and Illicit Trafficking (26 June)\nInternational Narcotics Control Board (INCB)\nTreatnet\nUnited Nations drug, crime and terrorism treaties\nUnited Nations system website locator\nUnited Nations Trust Fund for Victims of Human Trafficking\nUNODC Youth Initiative\nWorld Drug Report\n\n\n\nField Offices\n\nEurope and West/Central Asia\n\nAfghanistan\nCentral Asia\nIran, Islamic Republic of\nPakistan\nSouth Eastern Europe\nUkraine\nRegional Programme for Afghanistan and Neighbouring Countries\n\n\nAfrica and Middle East \n\nEastern Africa\nMiddle East and North Africa\nNigeria\nSouthern Africa\nWest and Central Africa\n\n\nLatin America and the Caribbean\n\nAndean Region and Southern Cone \n\n         Argentina         Bolivia            Chile            Colombia            Ecuador            Peru            Uruguay\n\nBrazil\nCentral America and the Caribbean\nMexico\n\n\nSoutheast Asia and the PacificCambodiaIndonesiaLao PDRMalaysiaMyanmarPacific IslandsPapua New GuineaPhlippinesThailandViet Nam\nSouth Asia\nLiaison Office - Brussels\nLiaison Office - New York\n\nAbout UNODC\n\nAnnual Appeal\nAnnual Report\nCareers\nEvaluation\nFunding and partnerships\nGoodwill Ambassadors\nInternational days and campaigns\nLeadership\nLibrary\nProcurement\nPublications\nSustainable Development Goals\nContact UNODC\n\n\n\nQuick Links\n\nAd hoc committee to elaborate an international convention on countering the use of ICTs for criminal purposes\nCivil Society Engagement\nCommission on Crime Prevention and Criminal Justice (CCPCJ)\nCommission on Narcotic Drugs (CND)\nConference of the Parties to the United Nations Convention against Transnational Organized Crime and its Protocols (CTOP/COP)\nConference of the States Parties to the United Nations Convention against Corruption (COSP)\nIMOLIN - the international money laundering information network\nInternational Anti-Corruption Day (9 December)\nInternational Day against Drug Abuse and Illicit Trafficking (26 June)\nInternational Narcotics Control Board (INCB)\nTreatnet\nUnited Nations drug, crime and terrorism treaties\nUnited Nations system website locator\nUnited Nations Trust Fund for Victims of Human Trafficking\nUNODC Youth Initiative\nWorld Drug Report\n\n\n\nField Offices\n\nEurope and West/Central Asia\n\nAfghanistan\nCentral Asia\nIran, Islamic Republic of\nPakistan\nSouth Eastern Europe\nUkraine\nRegional Programme for Afghanistan and Neighbouring Countries\n\n\nAfrica and Middle East \n\nEastern Africa\nMiddle East and North Africa\nNigeria\nSouthern Africa\nWest and Central Africa\n\n\nLatin America and the Caribbean\n\nAndean Region and Southern Cone \n\n         Argentina         Bolivia            Chile            Colombia            Ecuador            Peru            Uruguay\n\nBrazil\nCentral America and the Caribbean\nMexico\n\n\nSoutheast Asia and the PacificCambodiaIndonesiaLao PDRMalaysiaMyanmarPacific IslandsPapua New GuineaPhlippinesThailandViet Nam\nSouth Asia\nLiaison Office - Brussels\nLiaison Office - New York\n\nUnited Nations Office on Drugs and CrimeHomeContactsFraud AlertLegal Notice\n\nUnited Nations Office on Drugs and CrimeHomeContactsFraud AlertLegal Notice\n\nUnited Nations Office on Drugs and Crime\n\nUnited Nations Office on Drugs and Crime\n\nUnited Nations Office on Drugs and Crime\n\nUnited Nations Office on Drugs and Crime\n\nHomeContactsFraud AlertLegal Notice\n\nHomeContactsFraud AlertLegal Notice\n\nHomeContactsFraud AlertLegal Notice",
  "entities": {
    "countries": [
      "afghanistan",
      "brazil",
      "india",
      "iran",
      "mexico",
      "pakistan"
    ],
    "organizations": [
      "united nations",
      "un"
    ],
    "key_issues": [
      "matter",
      "nation",
      "state",
      "region",
      "initiative",
      "program",
      "development",
      "economy",
      "united nations",
      "un",
      "foundation"
    ]
  },
  "committee": "Regional Security Council",
  "topic": "Combating illegal drug trafficking in the Caribbean"
}