{
  "url": "https://www.ifad.org/web/new-ifad.org/rural-voices",
  "title": "Rural Voices",
  "text": "Rural Voices - IFAD\n\n\n\n\n\n\n\n\n\n\n\n\n\n\n\n\n\n\n\n\n\n\n\n\n\n\n\n\n\n      Rural voices\n     \n\n\n\n\n\n\n\n\n\n\n\n \n\n\n\n\n\n\n\n\n\n\n\n\n\n\n\n Theme \nSelect\n\n\n\n\n\n\n\n Year \nSelect\n\n\n\n\n\n\n\n Country \nSelect\n\n\n\n\n\n\n\n\n \n\n\n\n\n\n\n\n\n\n\n\n\n\n\n\n  Show more  \n\n\n\n\n\n  \n\n\n\n\n\n\n\n\n\n\n\n\n\n\n\n\n\n\nRural Voices\n\n Soil is getting saltier – but African farmers are standing strong Farmers in western and southern Africa are building resilience to salinity through innovative approaches in their fields. \n\n  Read now \n              \n \n\n\n\n\n\n\n\n\n\n\n\n\n\n\n\n\n\n\nRural Voices\n\n Forest bounty feeds the world Meet some of the rural people that IFAD works with to celebrate and nurture the bounty of our forests. \n\n  Read now \n              \n \n\n\n\n\n\n\n\n\n\n\n\n\n\n\n\n\n\nRural Voices\n\n Investment from Malians abroad supports farmers back home Overseas Malians are exploring ways to invest in businesses that yield both societal impact and financial returns – and agriculture is high on the priority list. \n\n  Read now \n              \n \n\n\n\n\n\n\n\n\n\n\n\n\n\n\n\n\n\n\n\nRural Voices\n\n Rural women ring in change in West Africa Meet three women who are leading their communities towards a more prosperous and equal future. \n\n  Read now \n              \n \n\n\n\n\n\n\n\n\n\n\n\n\n\n\n\n\n\nRural Voices\n\n With digital tools, farmers can lead the way to a sustainable future When designed with the needs and contexts of rural people in mind, digital tools can be a gamechanger for small-scale farmers and sustainable food systems. \n\n  Read now \n              \n \n\n\n\n\n\n\n\n\n\n\n\n\n\n\n\n\n\nRural Voices\n\n For Mexico’s Indigenous Peoples, self-driven development protects people and planet In the Michoacán region, an IFAD-supported Indigenous community is restoring their homeland and strengthening their community. \n\n  Read now \n              \n \n\n\n\n\n\n\n\n\n\n\n\n\n\n\n\n\n\n\n\nRural Voices\n\n Clean energy powers rural resilience in Cuba Rural Cuba has been impacted by recurring blackouts. But along its eastern coastline, an energy transition is brewing. \n\n  Read now \n              \n \n\n\n\n\n\n\n\n\n\n\n\n\n\n\n\n\n\nRural Voices\n\n Building resilient food systems in small island developing states Small island developing states (SIDS) share a range of challenges. Here’s how small-scale farmers are making their agrifood systems more resilient. \n\n  Read now \n              \n \n\n\n\n\n\n\n\n\n\n\n\n\n\n\n\n\n\nRural Voices\n\n Climate-smart irrigation reaps rewards for rural women From Laos to Moldova, meet three women who are using climate-smart irrigation to adapt to their new normal. \n\n  Read now \n              \n \n\n\n\n\n\n\n\n\n\n\n\n\n\n\n\n\n\n\n\nRural Voices\n\n How a Senegal fishing family found safe harbour at home Ousmane and Adama dared to dream of a better future abroad – and, with IFAD’s support, ended up finding it at home. \n\n  Read now \n              \n \n\n\n\n\n\n\n\n\n\n\n\n\n\n\n\n\n\nRural Voices\n\n Monorails connect mountains to markets in China Getting fruit from mountain to market is not a straightforward matter. But in one community, a new monorail is bridging the gap. \n\n  Read now \n              \n \n\n\n\n\n\n\n\n\n\n\n\n\n\n\n\n\n\nRural Voices\n\n Marketing works magic for rural entrepreneurs With IFAD's support, farmers across North Africa and the Middle East are marketing effectively – and getting the recognition they deserve. \n\n  Read now \n              \n \n\n\n\n\n\n\n\n\n\n\n\n        Showing 1 to 12 of 353\n       \n\n\n\n\n\n\n\n1\n2\n3\n...\n30\n\n\n\n\n\n\n\n\n\n\n\n\n\n\n\n\n\n\n       Please configure the desktop menu widget below\n      \n\n\n\n\n\n\n\n\n About IFAD \n Who we are   Where we work   What we do   Action Areas   Knowledge & Data \n\n\n For Member States \n Member States interactive platform \n\n\n For Investors \n Investors   Finance \n\n\n For Job seekers \n Work with us   Frequently Asked Questions \n\n\n For Media \n News   Media Contacts   Image Bank \n\n\n Get Involved \n Join an event   Rural Voices   Opinions & Insights \n\n\n\n\n\n\n\n\n\n\n\n\n\n       Please configure the mobile menu widget below\n      \n\n\n\n\n\n\n\n\n Who we are \n\n\n\n What we do \n\n\n\n Where we work \n\n\n\n Action Areas \n\n\n\n Knowledge & Data \n\n\n\n Get Involved \n\n\n\n News and Stories \n\n\n\n\n\n\n\n\n\n\n\n\n\n  \n Legal  Privacy notice  Fraudulent job offers  Contact us Stay connected\n\n\n\n  \n\n  \n\n  \n\n  \n\n  \n\n \n\n\n\n\n\n\n\n\nHidden\n\nRural Voices - IFAD\n\n\n\n\n\n\n\n\n\n\n\n\n\n\n\n\n\n\n\n\n\n\n\n\n\n\n\n\n\n      Rural voices\n     \n\n\n\n\n\n\n\n\n\n\n\n \n\n\n\n\n\n\n\n\n\n\n\n\n\n\n\n Theme \nSelect\n\n\n\n\n\n\n\n Year \nSelect\n\n\n\n\n\n\n\n Country \nSelect\n\n\n\n\n\n\n\n\n \n\n\n\n\n\n\n\n\n\n\n\n\n\n\n\n  Show more  \n\n\n\n\n\n  \n\n\n\n\n\n\n\n\n\n\n\n\n\n\n\n\n\n\nRural Voices\n\n Soil is getting saltier – but African farmers are standing strong Farmers in western and southern Africa are building resilience to salinity through innovative approaches in their fields. \n\n  Read now \n              \n \n\n\n\n\n\n\n\n\n\n\n\n\n\n\n\n\n\n\nRural Voices\n\n Forest bounty feeds the world Meet some of the rural people that IFAD works with to celebrate and nurture the bounty of our forests. \n\n  Read now \n              \n \n\n\n\n\n\n\n\n\n\n\n\n\n\n\n\n\n\nRural Voices\n\n Investment from Malians abroad supports farmers back home Overseas Malians are exploring ways to invest in businesses that yield both societal impact and financial returns – and agriculture is high on the priority list. \n\n  Read now \n              \n \n\n\n\n\n\n\n\n\n\n\n\n\n\n\n\n\n\n\n\nRural Voices\n\n Rural women ring in change in West Africa Meet three women who are leading their communities towards a more prosperous and equal future. \n\n  Read now \n              \n \n\n\n\n\n\n\n\n\n\n\n\n\n\n\n\n\n\nRural Voices\n\n With digital tools, farmers can lead the way to a sustainable future When designed with the needs and contexts of rural people in mind, digital tools can be a gamechanger for small-scale farmers and sustainable food systems. \n\n  Read now \n              \n \n\n\n\n\n\n\n\n\n\n\n\n\n\n\n\n\n\nRural Voices\n\n For Mexico’s Indigenous Peoples, self-driven development protects people and planet In the Michoacán region, an IFAD-supported Indigenous community is restoring their homeland and strengthening their community. \n\n  Read now \n              \n \n\n\n\n\n\n\n\n\n\n\n\n\n\n\n\n\n\n\n\nRural Voices\n\n Clean energy powers rural resilience in Cuba Rural Cuba has been impacted by recurring blackouts. But along its eastern coastline, an energy transition is brewing. \n\n  Read now \n              \n \n\n\n\n\n\n\n\n\n\n\n\n\n\n\n\n\n\nRural Voices\n\n Building resilient food systems in small island developing states Small island developing states (SIDS) share a range of challenges. Here’s how small-scale farmers are making their agrifood systems more resilient. \n\n  Read now \n              \n \n\n\n\n\n\n\n\n\n\n\n\n\n\n\n\n\n\nRural Voices\n\n Climate-smart irrigation reaps rewards for rural women From Laos to Moldova, meet three women who are using climate-smart irrigation to adapt to their new normal. \n\n  Read now \n              \n \n\n\n\n\n\n\n\n\n\n\n\n\n\n\n\n\n\n\n\nRural Voices\n\n How a Senegal fishing family found safe harbour at home Ousmane and Adama dared to dream of a better future abroad – and, with IFAD’s support, ended up finding it at home. \n\n  Read now \n              \n \n\n\n\n\n\n\n\n\n\n\n\n\n\n\n\n\n\nRural Voices\n\n Monorails connect mountains to markets in China Getting fruit from mountain to market is not a straightforward matter. But in one community, a new monorail is bridging the gap. \n\n  Read now \n              \n \n\n\n\n\n\n\n\n\n\n\n\n\n\n\n\n\n\nRural Voices\n\n Marketing works magic for rural entrepreneurs With IFAD's support, farmers across North Africa and the Middle East are marketing effectively – and getting the recognition they deserve. \n\n  Read now \n              \n \n\n\n\n\n\n\n\n\n\n\n\n        Showing 1 to 12 of 353\n       \n\n\n\n\n\n\n\n1\n2\n3\n...\n30\n\n\n\n\n\n\n\n\n\n\n\n\n\n\n\n\n\n\n       Please configure the desktop menu widget below\n      \n\n\n\n\n\n\n\n\n About IFAD \n Who we are   Where we work   What we do   Action Areas   Knowledge & Data \n\n\n For Member States \n Member States interactive platform \n\n\n For Investors \n Investors   Finance \n\n\n For Job seekers \n Work with us   Frequently Asked Questions \n\n\n For Media \n News   Media Contacts   Image Bank \n\n\n Get Involved \n Join an event   Rural Voices   Opinions & Insights \n\n\n\n\n\n\n\n\n\n\n\n\n\n       Please configure the mobile menu widget below\n      \n\n\n\n\n\n\n\n\n Who we are \n\n\n\n What we do \n\n\n\n Where we work \n\n\n\n Action Areas \n\n\n\n Knowledge & Data \n\n\n\n Get Involved \n\n\n\n News and Stories \n\n\n\n\n\n\n\n\n\n\n\n\n\n  \n Legal  Privacy notice  Fraudulent job offers  Contact us Stay connected\n\n\n\n  \n\n  \n\n  \n\n  \n\n  \n\n \n\n\n\n\n\n\n\n\nHidden\n\nRural Voices - IFAD\n\n\n\n\n\n\n\n\n\n\n\n\n\n\n\n\n\n\n\n\n\n\n\n\n\n\n\n\n\n      Rural voices\n     \n\n\n\n\n\n\n\n\n\n\n\n \n\n\n\n\n\n\n\n\n\n\n\n\n\n\n\n Theme \nSelect\n\n\n\n\n\n\n\n Year \nSelect\n\n\n\n\n\n\n\n Country \nSelect\n\n\n\n\n\n\n\n\n \n\n\n\n\n\n\n\n\n\n\n\n\n\n\n\n  Show more  \n\n\n\n\n\n  \n\n\n\n\n\n\n\n\n\n\n\n\n\n\n\n\n\n\nRural Voices\n\n Soil is getting saltier – but African farmers are standing strong Farmers in western and southern Africa are building resilience to salinity through innovative approaches in their fields. \n\n  Read now \n              \n \n\n\n\n\n\n\n\n\n\n\n\n\n\n\n\n\n\n\nRural Voices\n\n Forest bounty feeds the world Meet some of the rural people that IFAD works with to celebrate and nurture the bounty of our forests. \n\n  Read now \n              \n \n\n\n\n\n\n\n\n\n\n\n\n\n\n\n\n\n\nRural Voices\n\n Investment from Malians abroad supports farmers back home Overseas Malians are exploring ways to invest in businesses that yield both societal impact and financial returns – and agriculture is high on the priority list. \n\n  Read now \n              \n \n\n\n\n\n\n\n\n\n\n\n\n\n\n\n\n\n\n\n\nRural Voices\n\n Rural women ring in change in West Africa Meet three women who are leading their communities towards a more prosperous and equal future. \n\n  Read now \n              \n \n\n\n\n\n\n\n\n\n\n\n\n\n\n\n\n\n\nRural Voices\n\n With digital tools, farmers can lead the way to a sustainable future When designed with the needs and contexts of rural people in mind, digital tools can be a gamechanger for small-scale farmers and sustainable food systems. \n\n  Read now \n              \n \n\n\n\n\n\n\n\n\n\n\n\n\n\n\n\n\n\nRural Voices\n\n For Mexico’s Indigenous Peoples, self-driven development protects people and planet In the Michoacán region, an IFAD-supported Indigenous community is restoring their homeland and strengthening their community. \n\n  Read now \n              \n \n\n\n\n\n\n\n\n\n\n\n\n\n\n\n\n\n\n\n\nRural Voices\n\n Clean energy powers rural resilience in Cuba Rural Cuba has been impacted by recurring blackouts. But along its eastern coastline, an energy transition is brewing. \n\n  Read now \n              \n \n\n\n\n\n\n\n\n\n\n\n\n\n\n\n\n\n\nRural Voices\n\n Building resilient food systems in small island developing states Small island developing states (SIDS) share a range of challenges. Here’s how small-scale farmers are making their agrifood systems more resilient. \n\n  Read now \n              \n \n\n\n\n\n\n\n\n\n\n\n\n\n\n\n\n\n\nRural Voices\n\n Climate-smart irrigation reaps rewards for rural women From Laos to Moldova, meet three women who are using climate-smart irrigation to adapt to their new normal. \n\n  Read now \n              \n \n\n\n\n\n\n\n\n\n\n\n\n\n\n\n\n\n\n\n\nRural Voices\n\n How a Senegal fishing family found safe harbour at home Ousmane and Adama dared to dream of a better future abroad – and, with IFAD’s support, ended up finding it at home. \n\n  Read now \n              \n \n\n\n\n\n\n\n\n\n\n\n\n\n\n\n\n\n\nRural Voices\n\n Monorails connect mountains to markets in China Getting fruit from mountain to market is not a straightforward matter. But in one community, a new monorail is bridging the gap. \n\n  Read now \n              \n \n\n\n\n\n\n\n\n\n\n\n\n\n\n\n\n\n\nRural Voices\n\n Marketing works magic for rural entrepreneurs With IFAD's support, farmers across North Africa and the Middle East are marketing effectively – and getting the recognition they deserve. \n\n  Read now \n              \n \n\n\n\n\n\n\n\n\n\n\n\n        Showing 1 to 12 of 353\n       \n\n\n\n\n\n\n\n1\n2\n3\n...\n30\n\n\n\n\n\n\n\n\n\n\n\n\n\n\n\n\n\n\n       Please configure the desktop menu widget below\n      \n\n\n\n\n\n\n\n\n About IFAD \n Who we are   Where we work   What we do   Action Areas   Knowledge & Data \n\n\n For Member States \n Member States interactive platform \n\n\n For Investors \n Investors   Finance \n\n\n For Job seekers \n Work with us   Frequently Asked Questions \n\n\n For Media \n News   Media Contacts   Image Bank \n\n\n Get Involved \n Join an event   Rural Voices   Opinions & Insights \n\n\n\n\n\n\n\n\n\n\n\n\n\n       Please configure the mobile menu widget below\n      \n\n\n\n\n\n\n\n\n Who we are \n\n\n\n What we do \n\n\n\n Where we work \n\n\n\n Action Areas \n\n\n\n Knowledge & Data \n\n\n\n Get Involved \n\n\n\n News and Stories \n\n\n\n\n\n\n\n\n\n\n\n\n\n  \n Legal  Privacy notice  Fraudulent job offers  Contact us Stay connected\n\n\n\n  \n\n  \n\n  \n\n  \n\n  \n\n \n\n\n\n\n\n\n\n\nHidden\n\nRural voices\n     \n\n\n\n\n\n\n\n\n\n\n\n \n\n\n\n\n\n\n\n\n\n\n\n\n\n\n\n Theme \nSelect\n\n\n\n\n\n\n\n Year \nSelect\n\n\n\n\n\n\n\n Country \nSelect\n\n\n\n\n\n\n\n\n \n\n\n\n\n\n\n\n\n\n\n\n\n\n\n\n  Show more  \n\n\n\n\n\n  \n\n\n\n\n\n\n\n\n\n\n\n\n\n\n\n\n\n\nRural Voices\n\n Soil is getting saltier – but African farmers are standing strong Farmers in western and southern Africa are building resilience to salinity through innovative approaches in their fields. \n\n  Read now \n              \n \n\n\n\n\n\n\n\n\n\n\n\n\n\n\n\n\n\n\nRural Voices\n\n Forest bounty feeds the world Meet some of the rural people that IFAD works with to celebrate and nurture the bounty of our forests. \n\n  Read now \n              \n \n\n\n\n\n\n\n\n\n\n\n\n\n\n\n\n\n\nRural Voices\n\n Investment from Malians abroad supports farmers back home Overseas Malians are exploring ways to invest in businesses that yield both societal impact and financial returns – and agriculture is high on the priority list. \n\n  Read now \n              \n \n\n\n\n\n\n\n\n\n\n\n\n\n\n\n\n\n\n\n\nRural Voices\n\n Rural women ring in change in West Africa Meet three women who are leading their communities towards a more prosperous and equal future. \n\n  Read now \n              \n \n\n\n\n\n\n\n\n\n\n\n\n\n\n\n\n\n\nRural Voices\n\n With digital tools, farmers can lead the way to a sustainable future When designed with the needs and contexts of rural people in mind, digital tools can be a gamechanger for small-scale farmers and sustainable food systems. \n\n  Read now \n              \n \n\n\n\n\n\n\n\n\n\n\n\n\n\n\n\n\n\nRural Voices\n\n For Mexico’s Indigenous Peoples, self-driven development protects people and planet In the Michoacán region, an IFAD-supported Indigenous community is restoring their homeland and strengthening their community. \n\n  Read now \n              \n \n\n\n\n\n\n\n\n\n\n\n\n\n\n\n\n\n\n\n\nRural Voices\n\n Clean energy powers rural resilience in Cuba Rural Cuba has been impacted by recurring blackouts. But along its eastern coastline, an energy transition is brewing. \n\n  Read now \n              \n \n\n\n\n\n\n\n\n\n\n\n\n\n\n\n\n\n\nRural Voices\n\n Building resilient food systems in small island developing states Small island developing states (SIDS) share a range of challenges. Here’s how small-scale farmers are making their agrifood systems more resilient. \n\n  Read now \n              \n \n\n\n\n\n\n\n\n\n\n\n\n\n\n\n\n\n\nRural Voices\n\n Climate-smart irrigation reaps rewards for rural women From Laos to Moldova, meet three women who are using climate-smart irrigation to adapt to their new normal. \n\n  Read now \n              \n \n\n\n\n\n\n\n\n\n\n\n\n\n\n\n\n\n\n\n\nRural Voices\n\n How a Senegal fishing family found safe harbour at home Ousmane and Adama dared to dream of a better future abroad – and, with IFAD’s support, ended up finding it at home. \n\n  Read now \n              \n \n\n\n\n\n\n\n\n\n\n\n\n\n\n\n\n\n\nRural Voices\n\n Monorails connect mountains to markets in China Getting fruit from mountain to market is not a straightforward matter. But in one community, a new monorail is bridging the gap. \n\n  Read now \n              \n \n\n\n\n\n\n\n\n\n\n\n\n\n\n\n\n\n\nRural Voices\n\n Marketing works magic for rural entrepreneurs With IFAD's support, farmers across North Africa and the Middle East are marketing effectively – and getting the recognition they deserve. \n\n  Read now \n              \n \n\n\n\n\n\n\n\n\n\n\n\n        Showing 1 to 12 of 353\n       \n\n\n\n\n\n\n\n1\n2\n3\n...\n30\n\n\n\n\n\n\n\n\n\n\n\n\n\n\n\n\n\n\n       Please configure the desktop menu widget below\n      \n\n\n\n\n\n\n\n\n About IFAD \n Who we are   Where we work   What we do   Action Areas   Knowledge & Data \n\n\n For Member States \n Member States interactive platform \n\n\n For Investors \n Investors   Finance \n\n\n For Job seekers \n Work with us   Frequently Asked Questions \n\n\n For Media \n News   Media Contacts   Image Bank \n\n\n Get Involved \n Join an event   Rural Voices   Opinions & Insights \n\n\n\n\n\n\n\n\n\n\n\n\n\n       Please configure the mobile menu widget below\n      \n\n\n\n\n\n\n\n\n Who we are \n\n\n\n What we do \n\n\n\n Where we work \n\n\n\n Action Areas \n\n\n\n Knowledge & Data \n\n\n\n Get Involved \n\n\n\n News and Stories \n\n\n\n\n\n\n\n\n\n\n\n\n\n  \n Legal  Privacy notice  Fraudulent job offers  Contact us Stay connected\n\nRural voices\n     \n\n\n\n\n\n\n\n\n\n\n\n \n\n\n\n\n\n\n\n\n\n\n\n\n\n\n\n Theme \nSelect\n\n\n\n\n\n\n\n Year \nSelect\n\n\n\n\n\n\n\n Country \nSelect\n\n\n\n\n\n\n\n\n \n\n\n\n\n\n\n\n\n\n\n\n\n\n\n\n  Show more  \n\n\n\n\n\n  \n\n\n\n\n\n\n\n\n\n\n\n\n\n\n\n\n\n\nRural Voices\n\n Soil is getting saltier – but African farmers are standing strong Farmers in western and southern Africa are building resilience to salinity through innovative approaches in their fields. \n\n  Read now \n              \n \n\n\n\n\n\n\n\n\n\n\n\n\n\n\n\n\n\n\nRural Voices\n\n Forest bounty feeds the world Meet some of the rural people that IFAD works with to celebrate and nurture the bounty of our forests. \n\n  Read now \n              \n \n\n\n\n\n\n\n\n\n\n\n\n\n\n\n\n\n\nRural Voices\n\n Investment from Malians abroad supports farmers back home Overseas Malians are exploring ways to invest in businesses that yield both societal impact and financial returns – and agriculture is high on the priority list. \n\n  Read now \n              \n \n\n\n\n\n\n\n\n\n\n\n\n\n\n\n\n\n\n\n\nRural Voices\n\n Rural women ring in change in West Africa Meet three women who are leading their communities towards a more prosperous and equal future. \n\n  Read now \n              \n \n\n\n\n\n\n\n\n\n\n\n\n\n\n\n\n\n\nRural Voices\n\n With digital tools, farmers can lead the way to a sustainable future When designed with the needs and contexts of rural people in mind, digital tools can be a gamechanger for small-scale farmers and sustainable food systems. \n\n  Read now \n              \n \n\n\n\n\n\n\n\n\n\n\n\n\n\n\n\n\n\nRural Voices\n\n For Mexico’s Indigenous Peoples, self-driven development protects people and planet In the Michoacán region, an IFAD-supported Indigenous community is restoring their homeland and strengthening their community. \n\n  Read now \n              \n \n\n\n\n\n\n\n\n\n\n\n\n\n\n\n\n\n\n\n\nRural Voices\n\n Clean energy powers rural resilience in Cuba Rural Cuba has been impacted by recurring blackouts. But along its eastern coastline, an energy transition is brewing. \n\n  Read now \n              \n \n\n\n\n\n\n\n\n\n\n\n\n\n\n\n\n\n\nRural Voices\n\n Building resilient food systems in small island developing states Small island developing states (SIDS) share a range of challenges. Here’s how small-scale farmers are making their agrifood systems more resilient. \n\n  Read now \n              \n \n\n\n\n\n\n\n\n\n\n\n\n\n\n\n\n\n\nRural Voices\n\n Climate-smart irrigation reaps rewards for rural women From Laos to Moldova, meet three women who are using climate-smart irrigation to adapt to their new normal. \n\n  Read now \n              \n \n\n\n\n\n\n\n\n\n\n\n\n\n\n\n\n\n\n\n\nRural Voices\n\n How a Senegal fishing family found safe harbour at home Ousmane and Adama dared to dream of a better future abroad – and, with IFAD’s support, ended up finding it at home. \n\n  Read now \n              \n \n\n\n\n\n\n\n\n\n\n\n\n\n\n\n\n\n\nRural Voices\n\n Monorails connect mountains to markets in China Getting fruit from mountain to market is not a straightforward matter. But in one community, a new monorail is bridging the gap. \n\n  Read now \n              \n \n\n\n\n\n\n\n\n\n\n\n\n\n\n\n\n\n\nRural Voices\n\n Marketing works magic for rural entrepreneurs With IFAD's support, farmers across North Africa and the Middle East are marketing effectively – and getting the recognition they deserve. \n\n  Read now \n              \n \n\n\n\n\n\n\n\n\n\n\n\n        Showing 1 to 12 of 353\n       \n\n\n\n\n\n\n\n1\n2\n3\n...\n30\n\n\n\n\n\n\n\n\n\n\n\n\n\n\n\n\n\n\n       Please configure the desktop menu widget below\n      \n\n\n\n\n\n\n\n\n About IFAD \n Who we are   Where we work   What we do   Action Areas   Knowledge & Data \n\n\n For Member States \n Member States interactive platform \n\n\n For Investors \n Investors   Finance \n\n\n For Job seekers \n Work with us   Frequently Asked Questions \n\n\n For Media \n News   Media Contacts   Image Bank \n\n\n Get Involved \n Join an event   Rural Voices   Opinions & Insights \n\n\n\n\n\n\n\n\n\n\n\n\n\n       Please configure the mobile menu widget below\n      \n\n\n\n\n\n\n\n\n Who we are \n\n\n\n What we do \n\n\n\n Where we work \n\n\n\n Action Areas \n\n\n\n Knowledge & Data \n\n\n\n Get Involved \n\n\n\n News and Stories \n\n\n\n\n\n\n\n\n\n\n\n\n\n  \n Legal  Privacy notice  Fraudulent job offers  Contact us Stay connected\n\nRural voices\n     \n\n\n\n\n\n\n\n\n\n\n\n \n\n\n\n\n\n\n\n\n\n\n\n\n\n\n\n Theme \nSelect\n\n\n\n\n\n\n\n Year \nSelect\n\n\n\n\n\n\n\n Country \nSelect\n\n\n\n\n\n\n\n\n \n\n\n\n\n\n\n\n\n\n\n\n\n\n\n\n  Show more  \n\n\n\n\n\n  \n\n\n\n\n\n\n\n\n\n\n\n\n\n\n\n\n\n\nRural Voices\n\n Soil is getting saltier – but African farmers are standing strong Farmers in western and southern Africa are building resilience to salinity through innovative approaches in their fields. \n\n  Read now \n              \n \n\n\n\n\n\n\n\n\n\n\n\n\n\n\n\n\n\n\nRural Voices\n\n Forest bounty feeds the world Meet some of the rural people that IFAD works with to celebrate and nurture the bounty of our forests. \n\n  Read now \n              \n \n\n\n\n\n\n\n\n\n\n\n\n\n\n\n\n\n\nRural Voices\n\n Investment from Malians abroad supports farmers back home Overseas Malians are exploring ways to invest in businesses that yield both societal impact and financial returns – and agriculture is high on the priority list. \n\n  Read now \n              \n \n\n\n\n\n\n\n\n\n\n\n\n\n\n\n\n\n\n\n\nRural Voices\n\n Rural women ring in change in West Africa Meet three women who are leading their communities towards a more prosperous and equal future. \n\n  Read now \n              \n \n\n\n\n\n\n\n\n\n\n\n\n\n\n\n\n\n\nRural Voices\n\n With digital tools, farmers can lead the way to a sustainable future When designed with the needs and contexts of rural people in mind, digital tools can be a gamechanger for small-scale farmers and sustainable food systems. \n\n  Read now \n              \n \n\n\n\n\n\n\n\n\n\n\n\n\n\n\n\n\n\nRural Voices\n\n For Mexico’s Indigenous Peoples, self-driven development protects people and planet In the Michoacán region, an IFAD-supported Indigenous community is restoring their homeland and strengthening their community. \n\n  Read now \n              \n \n\n\n\n\n\n\n\n\n\n\n\n\n\n\n\n\n\n\n\nRural Voices\n\n Clean energy powers rural resilience in Cuba Rural Cuba has been impacted by recurring blackouts. But along its eastern coastline, an energy transition is brewing. \n\n  Read now \n              \n \n\n\n\n\n\n\n\n\n\n\n\n\n\n\n\n\n\nRural Voices\n\n Building resilient food systems in small island developing states Small island developing states (SIDS) share a range of challenges. Here’s how small-scale farmers are making their agrifood systems more resilient. \n\n  Read now \n              \n \n\n\n\n\n\n\n\n\n\n\n\n\n\n\n\n\n\nRural Voices\n\n Climate-smart irrigation reaps rewards for rural women From Laos to Moldova, meet three women who are using climate-smart irrigation to adapt to their new normal. \n\n  Read now \n              \n \n\n\n\n\n\n\n\n\n\n\n\n\n\n\n\n\n\n\n\nRural Voices\n\n How a Senegal fishing family found safe harbour at home Ousmane and Adama dared to dream of a better future abroad – and, with IFAD’s support, ended up finding it at home. \n\n  Read now \n              \n \n\n\n\n\n\n\n\n\n\n\n\n\n\n\n\n\n\nRural Voices\n\n Monorails connect mountains to markets in China Getting fruit from mountain to market is not a straightforward matter. But in one community, a new monorail is bridging the gap. \n\n  Read now \n              \n \n\n\n\n\n\n\n\n\n\n\n\n\n\n\n\n\n\nRural Voices\n\n Marketing works magic for rural entrepreneurs With IFAD's support, farmers across North Africa and the Middle East are marketing effectively – and getting the recognition they deserve. \n\n  Read now \n              \n \n\n\n\n\n\n\n\n\n\n\n\n        Showing 1 to 12 of 353\n       \n\n\n\n\n\n\n\n1\n2\n3\n...\n30\n\nRural voices\n\nRural voices\n\nRural voices\n\nTheme \nSelect\n\n\n\n\n\n\n\n Year \nSelect\n\n\n\n\n\n\n\n Country \nSelect\n\n\n\n\n\n\n\n\n \n\n\n\n\n\n\n\n\n\n\n\n\n\n\n\n  Show more  \n\n\n\n\n\n  \n\n\n\n\n\n\n\n\n\n\n\n\n\n\n\n\n\n\nRural Voices\n\n Soil is getting saltier – but African farmers are standing strong Farmers in western and southern Africa are building resilience to salinity through innovative approaches in their fields. \n\n  Read now \n              \n \n\n\n\n\n\n\n\n\n\n\n\n\n\n\n\n\n\n\nRural Voices\n\n Forest bounty feeds the world Meet some of the rural people that IFAD works with to celebrate and nurture the bounty of our forests. \n\n  Read now \n              \n \n\n\n\n\n\n\n\n\n\n\n\n\n\n\n\n\n\nRural Voices\n\n Investment from Malians abroad supports farmers back home Overseas Malians are exploring ways to invest in businesses that yield both societal impact and financial returns – and agriculture is high on the priority list. \n\n  Read now \n              \n \n\n\n\n\n\n\n\n\n\n\n\n\n\n\n\n\n\n\n\nRural Voices\n\n Rural women ring in change in West Africa Meet three women who are leading their communities towards a more prosperous and equal future. \n\n  Read now \n              \n \n\n\n\n\n\n\n\n\n\n\n\n\n\n\n\n\n\nRural Voices\n\n With digital tools, farmers can lead the way to a sustainable future When designed with the needs and contexts of rural people in mind, digital tools can be a gamechanger for small-scale farmers and sustainable food systems. \n\n  Read now \n              \n \n\n\n\n\n\n\n\n\n\n\n\n\n\n\n\n\n\nRural Voices\n\n For Mexico’s Indigenous Peoples, self-driven development protects people and planet In the Michoacán region, an IFAD-supported Indigenous community is restoring their homeland and strengthening their community. \n\n  Read now \n              \n \n\n\n\n\n\n\n\n\n\n\n\n\n\n\n\n\n\n\n\nRural Voices\n\n Clean energy powers rural resilience in Cuba Rural Cuba has been impacted by recurring blackouts. But along its eastern coastline, an energy transition is brewing. \n\n  Read now \n              \n \n\n\n\n\n\n\n\n\n\n\n\n\n\n\n\n\n\nRural Voices\n\n Building resilient food systems in small island developing states Small island developing states (SIDS) share a range of challenges. Here’s how small-scale farmers are making their agrifood systems more resilient. \n\n  Read now \n              \n \n\n\n\n\n\n\n\n\n\n\n\n\n\n\n\n\n\nRural Voices\n\n Climate-smart irrigation reaps rewards for rural women From Laos to Moldova, meet three women who are using climate-smart irrigation to adapt to their new normal. \n\n  Read now \n              \n \n\n\n\n\n\n\n\n\n\n\n\n\n\n\n\n\n\n\n\nRural Voices\n\n How a Senegal fishing family found safe harbour at home Ousmane and Adama dared to dream of a better future abroad – and, with IFAD’s support, ended up finding it at home. \n\n  Read now \n              \n \n\n\n\n\n\n\n\n\n\n\n\n\n\n\n\n\n\nRural Voices\n\n Monorails connect mountains to markets in China Getting fruit from mountain to market is not a straightforward matter. But in one community, a new monorail is bridging the gap. \n\n  Read now \n              \n \n\n\n\n\n\n\n\n\n\n\n\n\n\n\n\n\n\nRural Voices\n\n Marketing works magic for rural entrepreneurs With IFAD's support, farmers across North Africa and the Middle East are marketing effectively – and getting the recognition they deserve. \n\n  Read now \n              \n \n\n\n\n\n\n\n\n\n\n\n\n        Showing 1 to 12 of 353\n       \n\n\n\n\n\n\n\n1\n2\n3\n...\n30\n\nTheme \nSelect\n\n\n\n\n\n\n\n Year \nSelect\n\n\n\n\n\n\n\n Country \nSelect\n\n\n\n\n\n\n\n\n \n\n\n\n\n\n\n\n\n\n\n\n\n\n\n\n  Show more  \n\n\n\n\n\n  \n\n\n\n\n\n\n\n\n\n\n\n\n\n\n\n\n\n\nRural Voices\n\n Soil is getting saltier – but African farmers are standing strong Farmers in western and southern Africa are building resilience to salinity through innovative approaches in their fields. \n\n  Read now \n              \n \n\n\n\n\n\n\n\n\n\n\n\n\n\n\n\n\n\n\nRural Voices\n\n Forest bounty feeds the world Meet some of the rural people that IFAD works with to celebrate and nurture the bounty of our forests. \n\n  Read now \n              \n \n\n\n\n\n\n\n\n\n\n\n\n\n\n\n\n\n\nRural Voices\n\n Investment from Malians abroad supports farmers back home Overseas Malians are exploring ways to invest in businesses that yield both societal impact and financial returns – and agriculture is high on the priority list. \n\n  Read now \n              \n \n\n\n\n\n\n\n\n\n\n\n\n\n\n\n\n\n\n\n\nRural Voices\n\n Rural women ring in change in West Africa Meet three women who are leading their communities towards a more prosperous and equal future. \n\n  Read now \n              \n \n\n\n\n\n\n\n\n\n\n\n\n\n\n\n\n\n\nRural Voices\n\n With digital tools, farmers can lead the way to a sustainable future When designed with the needs and contexts of rural people in mind, digital tools can be a gamechanger for small-scale farmers and sustainable food systems. \n\n  Read now \n              \n \n\n\n\n\n\n\n\n\n\n\n\n\n\n\n\n\n\nRural Voices\n\n For Mexico’s Indigenous Peoples, self-driven development protects people and planet In the Michoacán region, an IFAD-supported Indigenous community is restoring their homeland and strengthening their community. \n\n  Read now \n              \n \n\n\n\n\n\n\n\n\n\n\n\n\n\n\n\n\n\n\n\nRural Voices\n\n Clean energy powers rural resilience in Cuba Rural Cuba has been impacted by recurring blackouts. But along its eastern coastline, an energy transition is brewing. \n\n  Read now \n              \n \n\n\n\n\n\n\n\n\n\n\n\n\n\n\n\n\n\nRural Voices\n\n Building resilient food systems in small island developing states Small island developing states (SIDS) share a range of challenges. Here’s how small-scale farmers are making their agrifood systems more resilient. \n\n  Read now \n              \n \n\n\n\n\n\n\n\n\n\n\n\n\n\n\n\n\n\nRural Voices\n\n Climate-smart irrigation reaps rewards for rural women From Laos to Moldova, meet three women who are using climate-smart irrigation to adapt to their new normal. \n\n  Read now \n              \n \n\n\n\n\n\n\n\n\n\n\n\n\n\n\n\n\n\n\n\nRural Voices\n\n How a Senegal fishing family found safe harbour at home Ousmane and Adama dared to dream of a better future abroad – and, with IFAD’s support, ended up finding it at home. \n\n  Read now \n              \n \n\n\n\n\n\n\n\n\n\n\n\n\n\n\n\n\n\nRural Voices\n\n Monorails connect mountains to markets in China Getting fruit from mountain to market is not a straightforward matter. But in one community, a new monorail is bridging the gap. \n\n  Read now \n              \n \n\n\n\n\n\n\n\n\n\n\n\n\n\n\n\n\n\nRural Voices\n\n Marketing works magic for rural entrepreneurs With IFAD's support, farmers across North Africa and the Middle East are marketing effectively – and getting the recognition they deserve. \n\n  Read now \n              \n \n\n\n\n\n\n\n\n\n\n\n\n        Showing 1 to 12 of 353\n       \n\n\n\n\n\n\n\n1\n2\n3\n...\n30\n\nTheme \nSelect\n\n\n\n\n\n\n\n Year \nSelect\n\n\n\n\n\n\n\n Country \nSelect\n\n\n\n\n\n\n\n\n \n\n\n\n\n\n\n\n\n\n\n\n\n\n\n\n  Show more\n\nTheme \nSelect\n\n\n\n\n\n\n\n Year \nSelect\n\n\n\n\n\n\n\n Country \nSelect\n\nTheme \nSelect\n\n\n\n\n\n\n\n Year \nSelect\n\n\n\n\n\n\n\n Country \nSelect\n\nTheme \nSelect\n\nTheme \nSelect\n\nTheme \nSelect\n\nSelect\n\nYear \nSelect\n\nYear \nSelect\n\nYear \nSelect\n\nSelect\n\nCountry \nSelect\n\nCountry \nSelect\n\nCountry \nSelect\n\nSelect\n\nShow more\n\nShow more\n\nShow more\n\nRural Voices\n\n Soil is getting saltier – but African farmers are standing strong Farmers in western and southern Africa are building resilience to salinity through innovative approaches in their fields. \n\n  Read now \n              \n \n\n\n\n\n\n\n\n\n\n\n\n\n\n\n\n\n\n\nRural Voices\n\n Forest bounty feeds the world Meet some of the rural people that IFAD works with to celebrate and nurture the bounty of our forests. \n\n  Read now \n              \n \n\n\n\n\n\n\n\n\n\n\n\n\n\n\n\n\n\nRural Voices\n\n Investment from Malians abroad supports farmers back home Overseas Malians are exploring ways to invest in businesses that yield both societal impact and financial returns – and agriculture is high on the priority list. \n\n  Read now \n              \n \n\n\n\n\n\n\n\n\n\n\n\n\n\n\n\n\n\n\n\nRural Voices\n\n Rural women ring in change in West Africa Meet three women who are leading their communities towards a more prosperous and equal future. \n\n  Read now \n              \n \n\n\n\n\n\n\n\n\n\n\n\n\n\n\n\n\n\nRural Voices\n\n With digital tools, farmers can lead the way to a sustainable future When designed with the needs and contexts of rural people in mind, digital tools can be a gamechanger for small-scale farmers and sustainable food systems. \n\n  Read now \n              \n \n\n\n\n\n\n\n\n\n\n\n\n\n\n\n\n\n\nRural Voices\n\n For Mexico’s Indigenous Peoples, self-driven development protects people and planet In the Michoacán region, an IFAD-supported Indigenous community is restoring their homeland and strengthening their community. \n\n  Read now \n              \n \n\n\n\n\n\n\n\n\n\n\n\n\n\n\n\n\n\n\n\nRural Voices\n\n Clean energy powers rural resilience in Cuba Rural Cuba has been impacted by recurring blackouts. But along its eastern coastline, an energy transition is brewing. \n\n  Read now \n              \n \n\n\n\n\n\n\n\n\n\n\n\n\n\n\n\n\n\nRural Voices\n\n Building resilient food systems in small island developing states Small island developing states (SIDS) share a range of challenges. Here’s how small-scale farmers are making their agrifood systems more resilient. \n\n  Read now \n              \n \n\n\n\n\n\n\n\n\n\n\n\n\n\n\n\n\n\nRural Voices\n\n Climate-smart irrigation reaps rewards for rural women From Laos to Moldova, meet three women who are using climate-smart irrigation to adapt to their new normal. \n\n  Read now \n              \n \n\n\n\n\n\n\n\n\n\n\n\n\n\n\n\n\n\n\n\nRural Voices\n\n How a Senegal fishing family found safe harbour at home Ousmane and Adama dared to dream of a better future abroad – and, with IFAD’s support, ended up finding it at home. \n\n  Read now \n              \n \n\n\n\n\n\n\n\n\n\n\n\n\n\n\n\n\n\nRural Voices\n\n Monorails connect mountains to markets in China Getting fruit from mountain to market is not a straightforward matter. But in one community, a new monorail is bridging the gap. \n\n  Read now \n              \n \n\n\n\n\n\n\n\n\n\n\n\n\n\n\n\n\n\nRural Voices\n\n Marketing works magic for rural entrepreneurs With IFAD's support, farmers across North Africa and the Middle East are marketing effectively – and getting the recognition they deserve. \n\n  Read now \n              \n \n\n\n\n\n\n\n\n\n\n\n\n        Showing 1 to 12 of 353\n       \n\n\n\n\n\n\n\n1\n2\n3\n...\n30\n\nRural Voices\n\n Soil is getting saltier – but African farmers are standing strong Farmers in western and southern Africa are building resilience to salinity through innovative approaches in their fields. \n\n  Read now \n              \n \n\n\n\n\n\n\n\n\n\n\n\n\n\n\n\n\n\n\nRural Voices\n\n Forest bounty feeds the world Meet some of the rural people that IFAD works with to celebrate and nurture the bounty of our forests. \n\n  Read now \n              \n \n\n\n\n\n\n\n\n\n\n\n\n\n\n\n\n\n\nRural Voices\n\n Investment from Malians abroad supports farmers back home Overseas Malians are exploring ways to invest in businesses that yield both societal impact and financial returns – and agriculture is high on the priority list. \n\n  Read now \n              \n \n\n\n\n\n\n\n\n\n\n\n\n\n\n\n\n\n\n\n\nRural Voices\n\n Rural women ring in change in West Africa Meet three women who are leading their communities towards a more prosperous and equal future. \n\n  Read now \n              \n \n\n\n\n\n\n\n\n\n\n\n\n\n\n\n\n\n\nRural Voices\n\n With digital tools, farmers can lead the way to a sustainable future When designed with the needs and contexts of rural people in mind, digital tools can be a gamechanger for small-scale farmers and sustainable food systems. \n\n  Read now \n              \n \n\n\n\n\n\n\n\n\n\n\n\n\n\n\n\n\n\nRural Voices\n\n For Mexico’s Indigenous Peoples, self-driven development protects people and planet In the Michoacán region, an IFAD-supported Indigenous community is restoring their homeland and strengthening their community. \n\n  Read now \n              \n \n\n\n\n\n\n\n\n\n\n\n\n\n\n\n\n\n\n\n\nRural Voices\n\n Clean energy powers rural resilience in Cuba Rural Cuba has been impacted by recurring blackouts. But along its eastern coastline, an energy transition is brewing. \n\n  Read now \n              \n \n\n\n\n\n\n\n\n\n\n\n\n\n\n\n\n\n\nRural Voices\n\n Building resilient food systems in small island developing states Small island developing states (SIDS) share a range of challenges. Here’s how small-scale farmers are making their agrifood systems more resilient. \n\n  Read now \n              \n \n\n\n\n\n\n\n\n\n\n\n\n\n\n\n\n\n\nRural Voices\n\n Climate-smart irrigation reaps rewards for rural women From Laos to Moldova, meet three women who are using climate-smart irrigation to adapt to their new normal. \n\n  Read now \n              \n \n\n\n\n\n\n\n\n\n\n\n\n\n\n\n\n\n\n\n\nRural Voices\n\n How a Senegal fishing family found safe harbour at home Ousmane and Adama dared to dream of a better future abroad – and, with IFAD’s support, ended up finding it at home. \n\n  Read now \n              \n \n\n\n\n\n\n\n\n\n\n\n\n\n\n\n\n\n\nRural Voices\n\n Monorails connect mountains to markets in China Getting fruit from mountain to market is not a straightforward matter. But in one community, a new monorail is bridging the gap. \n\n  Read now \n              \n \n\n\n\n\n\n\n\n\n\n\n\n\n\n\n\n\n\nRural Voices\n\n Marketing works magic for rural entrepreneurs With IFAD's support, farmers across North Africa and the Middle East are marketing effectively – and getting the recognition they deserve. \n\n  Read now\n\nRural Voices\n\n Soil is getting saltier – but African farmers are standing strong Farmers in western and southern Africa are building resilience to salinity through innovative approaches in their fields. \n\n  Read now \n              \n \n\n\n\n\n\n\n\n\n\n\n\n\n\n\n\n\n\n\nRural Voices\n\n Forest bounty feeds the world Meet some of the rural people that IFAD works with to celebrate and nurture the bounty of our forests. \n\n  Read now \n              \n \n\n\n\n\n\n\n\n\n\n\n\n\n\n\n\n\n\nRural Voices\n\n Investment from Malians abroad supports farmers back home Overseas Malians are exploring ways to invest in businesses that yield both societal impact and financial returns – and agriculture is high on the priority list. \n\n  Read now\n\nRural Voices\n\n Soil is getting saltier – but African farmers are standing strong Farmers in western and southern Africa are building resilience to salinity through innovative approaches in their fields. \n\n  Read now\n\nRural Voices\n\n Soil is getting saltier – but African farmers are standing strong Farmers in western and southern Africa are building resilience to salinity through innovative approaches in their fields. \n\n  Read now\n\nRural Voices\n\n Soil is getting saltier – but African farmers are standing strong Farmers in western and southern Africa are building resilience to salinity through innovative approaches in their fields. \n\n  Read now\n\nRural Voices\n\n Soil is getting saltier – but African farmers are standing strong Farmers in western and southern Africa are building resilience to salinity through innovative approaches in their fields. \n\n  Read now\n\nRural Voices\n\n Soil is getting saltier – but African farmers are standing strong Farmers in western and southern Africa are building resilience to salinity through innovative approaches in their fields. \n\n  Read now\n\nRural Voices\n\n Soil is getting saltier – but African farmers are standing strong Farmers in western and southern Africa are building resilience to salinity through innovative approaches in their fields. \n\n  Read now\n\nRural Voices\n\n Soil is getting saltier – but African farmers are standing strong Farmers in western and southern Africa are building resilience to salinity through innovative approaches in their fields.\n\nRural Voices\n\nRural Voices\n\nSoil is getting saltier – but African farmers are standing strong Farmers in western and southern Africa are building resilience to salinity through innovative approaches in their fields.\n\nSoil is getting saltier – but African farmers are standing strong\n\nFarmers in western and southern Africa are building resilience to salinity through innovative approaches in their fields.\n\nRural Voices\n\n Forest bounty feeds the world Meet some of the rural people that IFAD works with to celebrate and nurture the bounty of our forests. \n\n  Read now\n\nRural Voices\n\n Forest bounty feeds the world Meet some of the rural people that IFAD works with to celebrate and nurture the bounty of our forests. \n\n  Read now\n\nRural Voices\n\n Forest bounty feeds the world Meet some of the rural people that IFAD works with to celebrate and nurture the bounty of our forests. \n\n  Read now\n\nRural Voices\n\n Forest bounty feeds the world Meet some of the rural people that IFAD works with to celebrate and nurture the bounty of our forests. \n\n  Read now\n\nRural Voices\n\n Forest bounty feeds the world Meet some of the rural people that IFAD works with to celebrate and nurture the bounty of our forests. \n\n  Read now\n\nRural Voices\n\n Forest bounty feeds the world Meet some of the rural people that IFAD works with to celebrate and nurture the bounty of our forests. \n\n  Read now\n\nRural Voices\n\n Forest bounty feeds the world Meet some of the rural people that IFAD works with to celebrate and nurture the bounty of our forests.\n\nRural Voices\n\nRural Voices\n\nForest bounty feeds the world Meet some of the rural people that IFAD works with to celebrate and nurture the bounty of our forests.\n\nForest bounty feeds the world\n\nMeet some of the rural people that IFAD works with to celebrate and nurture the bounty of our forests.\n\nRural Voices\n\n Investment from Malians abroad supports farmers back home Overseas Malians are exploring ways to invest in businesses that yield both societal impact and financial returns – and agriculture is high on the priority list. \n\n  Read now\n\nRural Voices\n\n Investment from Malians abroad supports farmers back home Overseas Malians are exploring ways to invest in businesses that yield both societal impact and financial returns – and agriculture is high on the priority list. \n\n  Read now\n\nRural Voices\n\n Investment from Malians abroad supports farmers back home Overseas Malians are exploring ways to invest in businesses that yield both societal impact and financial returns – and agriculture is high on the priority list. \n\n  Read now\n\nRural Voices\n\n Investment from Malians abroad supports farmers back home Overseas Malians are exploring ways to invest in businesses that yield both societal impact and financial returns – and agriculture is high on the priority list. \n\n  Read now\n\nRural Voices\n\n Investment from Malians abroad supports farmers back home Overseas Malians are exploring ways to invest in businesses that yield both societal impact and financial returns – and agriculture is high on the priority list. \n\n  Read now\n\nRural Voices\n\n Investment from Malians abroad supports farmers back home Overseas Malians are exploring ways to invest in businesses that yield both societal impact and financial returns – and agriculture is high on the priority list. \n\n  Read now\n\nRural Voices\n\n Investment from Malians abroad supports farmers back home Overseas Malians are exploring ways to invest in businesses that yield both societal impact and financial returns – and agriculture is high on the priority list.\n\nRural Voices\n\nRural Voices\n\nInvestment from Malians abroad supports farmers back home Overseas Malians are exploring ways to invest in businesses that yield both societal impact and financial returns – and agriculture is high on the priority list.\n\nInvestment from Malians abroad supports farmers back home\n\nOverseas Malians are exploring ways to invest in businesses that yield both societal impact and financial returns – and agriculture is high on the priority list.\n\nRural Voices\n\n Rural women ring in change in West Africa Meet three women who are leading their communities towards a more prosperous and equal future. \n\n  Read now \n              \n \n\n\n\n\n\n\n\n\n\n\n\n\n\n\n\n\n\nRural Voices\n\n With digital tools, farmers can lead the way to a sustainable future When designed with the needs and contexts of rural people in mind, digital tools can be a gamechanger for small-scale farmers and sustainable food systems. \n\n  Read now \n              \n \n\n\n\n\n\n\n\n\n\n\n\n\n\n\n\n\n\nRural Voices\n\n For Mexico’s Indigenous Peoples, self-driven development protects people and planet In the Michoacán region, an IFAD-supported Indigenous community is restoring their homeland and strengthening their community. \n\n  Read now\n\nRural Voices\n\n Rural women ring in change in West Africa Meet three women who are leading their communities towards a more prosperous and equal future. \n\n  Read now\n\nRural Voices\n\n Rural women ring in change in West Africa Meet three women who are leading their communities towards a more prosperous and equal future. \n\n  Read now\n\nRural Voices\n\n Rural women ring in change in West Africa Meet three women who are leading their communities towards a more prosperous and equal future. \n\n  Read now\n\nRural Voices\n\n Rural women ring in change in West Africa Meet three women who are leading their communities towards a more prosperous and equal future. \n\n  Read now\n\nRural Voices\n\n Rural women ring in change in West Africa Meet three women who are leading their communities towards a more prosperous and equal future. \n\n  Read now\n\nRural Voices\n\n Rural women ring in change in West Africa Meet three women who are leading their communities towards a more prosperous and equal future. \n\n  Read now\n\nRural Voices\n\n Rural women ring in change in West Africa Meet three women who are leading their communities towards a more prosperous and equal future.\n\nRural Voices\n\nRural Voices\n\nRural women ring in change in West Africa Meet three women who are leading their communities towards a more prosperous and equal future.\n\nRural women ring in change in West Africa\n\nMeet three women who are leading their communities towards a more prosperous and equal future.\n\nRural Voices\n\n With digital tools, farmers can lead the way to a sustainable future When designed with the needs and contexts of rural people in mind, digital tools can be a gamechanger for small-scale farmers and sustainable food systems. \n\n  Read now\n\nRural Voices\n\n With digital tools, farmers can lead the way to a sustainable future When designed with the needs and contexts of rural people in mind, digital tools can be a gamechanger for small-scale farmers and sustainable food systems. \n\n  Read now\n\nRural Voices\n\n With digital tools, farmers can lead the way to a sustainable future When designed with the needs and contexts of rural people in mind, digital tools can be a gamechanger for small-scale farmers and sustainable food systems. \n\n  Read now\n\nRural Voices\n\n With digital tools, farmers can lead the way to a sustainable future When designed with the needs and contexts of rural people in mind, digital tools can be a gamechanger for small-scale farmers and sustainable food systems. \n\n  Read now\n\nRural Voices\n\n With digital tools, farmers can lead the way to a sustainable future When designed with the needs and contexts of rural people in mind, digital tools can be a gamechanger for small-scale farmers and sustainable food systems. \n\n  Read now\n\nRural Voices\n\n With digital tools, farmers can lead the way to a sustainable future When designed with the needs and contexts of rural people in mind, digital tools can be a gamechanger for small-scale farmers and sustainable food systems. \n\n  Read now\n\nRural Voices\n\n With digital tools, farmers can lead the way to a sustainable future When designed with the needs and contexts of rural people in mind, digital tools can be a gamechanger for small-scale farmers and sustainable food systems.\n\nRural Voices\n\nRural Voices\n\nWith digital tools, farmers can lead the way to a sustainable future When designed with the needs and contexts of rural people in mind, digital tools can be a gamechanger for small-scale farmers and sustainable food systems.\n\nWith digital tools, farmers can lead the way to a sustainable future\n\nWhen designed with the needs and contexts of rural people in mind, digital tools can be a gamechanger for small-scale farmers and sustainable food systems.\n\nRural Voices\n\n For Mexico’s Indigenous Peoples, self-driven development protects people and planet In the Michoacán region, an IFAD-supported Indigenous community is restoring their homeland and strengthening their community. \n\n  Read now\n\nRural Voices\n\n For Mexico’s Indigenous Peoples, self-driven development protects people and planet In the Michoacán region, an IFAD-supported Indigenous community is restoring their homeland and strengthening their community. \n\n  Read now\n\nRural Voices\n\n For Mexico’s Indigenous Peoples, self-driven development protects people and planet In the Michoacán region, an IFAD-supported Indigenous community is restoring their homeland and strengthening their community. \n\n  Read now\n\nRural Voices\n\n For Mexico’s Indigenous Peoples, self-driven development protects people and planet In the Michoacán region, an IFAD-supported Indigenous community is restoring their homeland and strengthening their community. \n\n  Read now\n\nRural Voices\n\n For Mexico’s Indigenous Peoples, self-driven development protects people and planet In the Michoacán region, an IFAD-supported Indigenous community is restoring their homeland and strengthening their community. \n\n  Read now\n\nRural Voices\n\n For Mexico’s Indigenous Peoples, self-driven development protects people and planet In the Michoacán region, an IFAD-supported Indigenous community is restoring their homeland and strengthening their community. \n\n  Read now\n\nRural Voices\n\n For Mexico’s Indigenous Peoples, self-driven development protects people and planet In the Michoacán region, an IFAD-supported Indigenous community is restoring their homeland and strengthening their community.\n\nRural Voices\n\nRural Voices\n\nFor Mexico’s Indigenous Peoples, self-driven development protects people and planet In the Michoacán region, an IFAD-supported Indigenous community is restoring their homeland and strengthening their community.\n\nFor Mexico’s Indigenous Peoples, self-driven development protects people and planet\n\nIn the Michoacán region, an IFAD-supported Indigenous community is restoring their homeland and strengthening their community.\n\nRural Voices\n\n Clean energy powers rural resilience in Cuba Rural Cuba has been impacted by recurring blackouts. But along its eastern coastline, an energy transition is brewing. \n\n  Read now \n              \n \n\n\n\n\n\n\n\n\n\n\n\n\n\n\n\n\n\nRural Voices\n\n Building resilient food systems in small island developing states Small island developing states (SIDS) share a range of challenges. Here’s how small-scale farmers are making their agrifood systems more resilient. \n\n  Read now \n              \n \n\n\n\n\n\n\n\n\n\n\n\n\n\n\n\n\n\nRural Voices\n\n Climate-smart irrigation reaps rewards for rural women From Laos to Moldova, meet three women who are using climate-smart irrigation to adapt to their new normal. \n\n  Read now\n\nRural Voices\n\n Clean energy powers rural resilience in Cuba Rural Cuba has been impacted by recurring blackouts. But along its eastern coastline, an energy transition is brewing. \n\n  Read now\n\nRural Voices\n\n Clean energy powers rural resilience in Cuba Rural Cuba has been impacted by recurring blackouts. But along its eastern coastline, an energy transition is brewing. \n\n  Read now\n\nRural Voices\n\n Clean energy powers rural resilience in Cuba Rural Cuba has been impacted by recurring blackouts. But along its eastern coastline, an energy transition is brewing. \n\n  Read now\n\nRural Voices\n\n Clean energy powers rural resilience in Cuba Rural Cuba has been impacted by recurring blackouts. But along its eastern coastline, an energy transition is brewing. \n\n  Read now\n\nRural Voices\n\n Clean energy powers rural resilience in Cuba Rural Cuba has been impacted by recurring blackouts. But along its eastern coastline, an energy transition is brewing. \n\n  Read now\n\nRural Voices\n\n Clean energy powers rural resilience in Cuba Rural Cuba has been impacted by recurring blackouts. But along its eastern coastline, an energy transition is brewing. \n\n  Read now\n\nRural Voices\n\n Clean energy powers rural resilience in Cuba Rural Cuba has been impacted by recurring blackouts. But along its eastern coastline, an energy transition is brewing.\n\nRural Voices\n\nRural Voices\n\nClean energy powers rural resilience in Cuba Rural Cuba has been impacted by recurring blackouts. But along its eastern coastline, an energy transition is brewing.\n\nClean energy powers rural resilience in Cuba\n\nRural Cuba has been impacted by recurring blackouts. But along its eastern coastline, an energy transition is brewing.\n\nRural Voices\n\n Building resilient food systems in small island developing states Small island developing states (SIDS) share a range of challenges. Here’s how small-scale farmers are making their agrifood systems more resilient. \n\n  Read now\n\nRural Voices\n\n Building resilient food systems in small island developing states Small island developing states (SIDS) share a range of challenges. Here’s how small-scale farmers are making their agrifood systems more resilient. \n\n  Read now\n\nRural Voices\n\n Building resilient food systems in small island developing states Small island developing states (SIDS) share a range of challenges. Here’s how small-scale farmers are making their agrifood systems more resilient. \n\n  Read now\n\nRural Voices\n\n Building resilient food systems in small island developing states Small island developing states (SIDS) share a range of challenges. Here’s how small-scale farmers are making their agrifood systems more resilient. \n\n  Read now\n\nRural Voices\n\n Building resilient food systems in small island developing states Small island developing states (SIDS) share a range of challenges. Here’s how small-scale farmers are making their agrifood systems more resilient. \n\n  Read now\n\nRural Voices\n\n Building resilient food systems in small island developing states Small island developing states (SIDS) share a range of challenges. Here’s how small-scale farmers are making their agrifood systems more resilient. \n\n  Read now\n\nRural Voices\n\n Building resilient food systems in small island developing states Small island developing states (SIDS) share a range of challenges. Here’s how small-scale farmers are making their agrifood systems more resilient.\n\nRural Voices\n\nRural Voices\n\nBuilding resilient food systems in small island developing states Small island developing states (SIDS) share a range of challenges. Here’s how small-scale farmers are making their agrifood systems more resilient.\n\nBuilding resilient food systems in small island developing states\n\nSmall island developing states (SIDS) share a range of challenges. Here’s how small-scale farmers are making their agrifood systems more resilient.\n\nRural Voices\n\n Climate-smart irrigation reaps rewards for rural women From Laos to Moldova, meet three women who are using climate-smart irrigation to adapt to their new normal. \n\n  Read now\n\nRural Voices\n\n Climate-smart irrigation reaps rewards for rural women From Laos to Moldova, meet three women who are using climate-smart irrigation to adapt to their new normal. \n\n  Read now\n\nRural Voices\n\n Climate-smart irrigation reaps rewards for rural women From Laos to Moldova, meet three women who are using climate-smart irrigation to adapt to their new normal. \n\n  Read now\n\nRural Voices\n\n Climate-smart irrigation reaps rewards for rural women From Laos to Moldova, meet three women who are using climate-smart irrigation to adapt to their new normal. \n\n  Read now\n\nRural Voices\n\n Climate-smart irrigation reaps rewards for rural women From Laos to Moldova, meet three women who are using climate-smart irrigation to adapt to their new normal. \n\n  Read now\n\nRural Voices\n\n Climate-smart irrigation reaps rewards for rural women From Laos to Moldova, meet three women who are using climate-smart irrigation to adapt to their new normal. \n\n  Read now\n\nRural Voices\n\n Climate-smart irrigation reaps rewards for rural women From Laos to Moldova, meet three women who are using climate-smart irrigation to adapt to their new normal.\n\nRural Voices\n\nRural Voices\n\nClimate-smart irrigation reaps rewards for rural women From Laos to Moldova, meet three women who are using climate-smart irrigation to adapt to their new normal.\n\nClimate-smart irrigation reaps rewards for rural women\n\nFrom Laos to Moldova, meet three women who are using climate-smart irrigation to adapt to their new normal.\n\nRural Voices\n\n How a Senegal fishing family found safe harbour at home Ousmane and Adama dared to dream of a better future abroad – and, with IFAD’s support, ended up finding it at home. \n\n  Read now \n              \n \n\n\n\n\n\n\n\n\n\n\n\n\n\n\n\n\n\nRural Voices\n\n Monorails connect mountains to markets in China Getting fruit from mountain to market is not a straightforward matter. But in one community, a new monorail is bridging the gap. \n\n  Read now \n              \n \n\n\n\n\n\n\n\n\n\n\n\n\n\n\n\n\n\nRural Voices\n\n Marketing works magic for rural entrepreneurs With IFAD's support, farmers across North Africa and the Middle East are marketing effectively – and getting the recognition they deserve. \n\n  Read now\n\nRural Voices\n\n How a Senegal fishing family found safe harbour at home Ousmane and Adama dared to dream of a better future abroad – and, with IFAD’s support, ended up finding it at home. \n\n  Read now\n\nRural Voices\n\n How a Senegal fishing family found safe harbour at home Ousmane and Adama dared to dream of a better future abroad – and, with IFAD’s support, ended up finding it at home. \n\n  Read now\n\nRural Voices\n\n How a Senegal fishing family found safe harbour at home Ousmane and Adama dared to dream of a better future abroad – and, with IFAD’s support, ended up finding it at home. \n\n  Read now\n\nRural Voices\n\n How a Senegal fishing family found safe harbour at home Ousmane and Adama dared to dream of a better future abroad – and, with IFAD’s support, ended up finding it at home. \n\n  Read now\n\nRural Voices\n\n How a Senegal fishing family found safe harbour at home Ousmane and Adama dared to dream of a better future abroad – and, with IFAD’s support, ended up finding it at home. \n\n  Read now\n\nRural Voices\n\n How a Senegal fishing family found safe harbour at home Ousmane and Adama dared to dream of a better future abroad – and, with IFAD’s support, ended up finding it at home. \n\n  Read now\n\nRural Voices\n\n How a Senegal fishing family found safe harbour at home Ousmane and Adama dared to dream of a better future abroad – and, with IFAD’s support, ended up finding it at home.\n\nRural Voices\n\nRural Voices\n\nHow a Senegal fishing family found safe harbour at home Ousmane and Adama dared to dream of a better future abroad – and, with IFAD’s support, ended up finding it at home.\n\nHow a Senegal fishing family found safe harbour at home\n\nOusmane and Adama dared to dream of a better future abroad – and, with IFAD’s support, ended up finding it at home.\n\nRural Voices\n\n Monorails connect mountains to markets in China Getting fruit from mountain to market is not a straightforward matter. But in one community, a new monorail is bridging the gap. \n\n  Read now\n\nRural Voices\n\n Monorails connect mountains to markets in China Getting fruit from mountain to market is not a straightforward matter. But in one community, a new monorail is bridging the gap. \n\n  Read now\n\nRural Voices\n\n Monorails connect mountains to markets in China Getting fruit from mountain to market is not a straightforward matter. But in one community, a new monorail is bridging the gap. \n\n  Read now\n\nRural Voices\n\n Monorails connect mountains to markets in China Getting fruit from mountain to market is not a straightforward matter. But in one community, a new monorail is bridging the gap. \n\n  Read now\n\nRural Voices\n\n Monorails connect mountains to markets in China Getting fruit from mountain to market is not a straightforward matter. But in one community, a new monorail is bridging the gap. \n\n  Read now\n\nRural Voices\n\n Monorails connect mountains to markets in China Getting fruit from mountain to market is not a straightforward matter. But in one community, a new monorail is bridging the gap. \n\n  Read now\n\nRural Voices\n\n Monorails connect mountains to markets in China Getting fruit from mountain to market is not a straightforward matter. But in one community, a new monorail is bridging the gap.\n\nRural Voices\n\nRural Voices\n\nMonorails connect mountains to markets in China Getting fruit from mountain to market is not a straightforward matter. But in one community, a new monorail is bridging the gap.\n\nMonorails connect mountains to markets in China\n\nGetting fruit from mountain to market is not a straightforward matter. But in one community, a new monorail is bridging the gap.\n\nRural Voices\n\n Marketing works magic for rural entrepreneurs With IFAD's support, farmers across North Africa and the Middle East are marketing effectively – and getting the recognition they deserve. \n\n  Read now\n\nRural Voices\n\n Marketing works magic for rural entrepreneurs With IFAD's support, farmers across North Africa and the Middle East are marketing effectively – and getting the recognition they deserve. \n\n  Read now\n\nRural Voices\n\n Marketing works magic for rural entrepreneurs With IFAD's support, farmers across North Africa and the Middle East are marketing effectively – and getting the recognition they deserve. \n\n  Read now\n\nRural Voices\n\n Marketing works magic for rural entrepreneurs With IFAD's support, farmers across North Africa and the Middle East are marketing effectively – and getting the recognition they deserve. \n\n  Read now\n\nRural Voices\n\n Marketing works magic for rural entrepreneurs With IFAD's support, farmers across North Africa and the Middle East are marketing effectively – and getting the recognition they deserve. \n\n  Read now\n\nRural Voices\n\n Marketing works magic for rural entrepreneurs With IFAD's support, farmers across North Africa and the Middle East are marketing effectively – and getting the recognition they deserve. \n\n  Read now\n\nRural Voices\n\n Marketing works magic for rural entrepreneurs With IFAD's support, farmers across North Africa and the Middle East are marketing effectively – and getting the recognition they deserve.\n\nRural Voices\n\nRural Voices\n\nMarketing works magic for rural entrepreneurs With IFAD's support, farmers across North Africa and the Middle East are marketing effectively – and getting the recognition they deserve.\n\nMarketing works magic for rural entrepreneurs\n\nWith IFAD's support, farmers across North Africa and the Middle East are marketing effectively – and getting the recognition they deserve.\n\nShowing 1 to 12 of 353\n       \n\n\n\n\n\n\n\n1\n2\n3\n...\n30\n\nShowing 1 to 12 of 353\n       \n\n\n\n\n\n\n\n1\n2\n3\n...\n30\n\nShowing 1 to 12 of 353\n\nPlease configure the desktop menu widget below\n      \n\n\n\n\n\n\n\n\n About IFAD \n Who we are   Where we work   What we do   Action Areas   Knowledge & Data \n\n\n For Member States \n Member States interactive platform \n\n\n For Investors \n Investors   Finance \n\n\n For Job seekers \n Work with us   Frequently Asked Questions \n\n\n For Media \n News   Media Contacts   Image Bank \n\n\n Get Involved \n Join an event   Rural Voices   Opinions & Insights \n\n\n\n\n\n\n\n\n\n\n\n\n\n       Please configure the mobile menu widget below\n      \n\n\n\n\n\n\n\n\n Who we are \n\n\n\n What we do \n\n\n\n Where we work \n\n\n\n Action Areas \n\n\n\n Knowledge & Data \n\n\n\n Get Involved \n\n\n\n News and Stories \n\n\n\n\n\n\n\n\n\n\n\n\n\n  \n Legal  Privacy notice  Fraudulent job offers  Contact us Stay connected\n\nPlease configure the desktop menu widget below\n      \n\n\n\n\n\n\n\n\n About IFAD \n Who we are   Where we work   What we do   Action Areas   Knowledge & Data \n\n\n For Member States \n Member States interactive platform \n\n\n For Investors \n Investors   Finance \n\n\n For Job seekers \n Work with us   Frequently Asked Questions \n\n\n For Media \n News   Media Contacts   Image Bank \n\n\n Get Involved \n Join an event   Rural Voices   Opinions & Insights \n\n\n\n\n\n\n\n\n\n\n\n\n\n       Please configure the mobile menu widget below\n      \n\n\n\n\n\n\n\n\n Who we are \n\n\n\n What we do \n\n\n\n Where we work \n\n\n\n Action Areas \n\n\n\n Knowledge & Data \n\n\n\n Get Involved \n\n\n\n News and Stories \n\n\n\n\n\n\n\n\n\n\n\n\n\n  \n Legal  Privacy notice  Fraudulent job offers  Contact us Stay connected\n\nPlease configure the desktop menu widget below\n      \n\n\n\n\n\n\n\n\n About IFAD \n Who we are   Where we work   What we do   Action Areas   Knowledge & Data \n\n\n For Member States \n Member States interactive platform \n\n\n For Investors \n Investors   Finance \n\n\n For Job seekers \n Work with us   Frequently Asked Questions \n\n\n For Media \n News   Media Contacts   Image Bank \n\n\n Get Involved \n Join an event   Rural Voices   Opinions & Insights \n\n\n\n\n\n\n\n\n\n\n\n\n\n       Please configure the mobile menu widget below\n      \n\n\n\n\n\n\n\n\n Who we are \n\n\n\n What we do \n\n\n\n Where we work \n\n\n\n Action Areas \n\n\n\n Knowledge & Data \n\n\n\n Get Involved \n\n\n\n News and Stories \n\n\n\n\n\n\n\n\n\n\n\n\n\n  \n Legal  Privacy notice  Fraudulent job offers  Contact us Stay connected\n\nPlease configure the desktop menu widget below\n      \n\n\n\n\n\n\n\n\n About IFAD \n Who we are   Where we work   What we do   Action Areas   Knowledge & Data \n\n\n For Member States \n Member States interactive platform \n\n\n For Investors \n Investors   Finance \n\n\n For Job seekers \n Work with us   Frequently Asked Questions \n\n\n For Media \n News   Media Contacts   Image Bank \n\n\n Get Involved \n Join an event   Rural Voices   Opinions & Insights \n\n\n\n\n\n\n\n\n\n\n\n\n\n       Please configure the mobile menu widget below\n      \n\n\n\n\n\n\n\n\n Who we are \n\n\n\n What we do \n\n\n\n Where we work \n\n\n\n Action Areas \n\n\n\n Knowledge & Data \n\n\n\n Get Involved \n\n\n\n News and Stories\n\nPlease configure the desktop menu widget below\n      \n\n\n\n\n\n\n\n\n About IFAD \n Who we are   Where we work   What we do   Action Areas   Knowledge & Data \n\n\n For Member States \n Member States interactive platform \n\n\n For Investors \n Investors   Finance \n\n\n For Job seekers \n Work with us   Frequently Asked Questions \n\n\n For Media \n News   Media Contacts   Image Bank \n\n\n Get Involved \n Join an event   Rural Voices   Opinions & Insights\n\nPlease configure the desktop menu widget below\n\nAbout IFAD \n Who we are   Where we work   What we do   Action Areas   Knowledge & Data \n\n\n For Member States \n Member States interactive platform \n\n\n For Investors \n Investors   Finance \n\n\n For Job seekers \n Work with us   Frequently Asked Questions \n\n\n For Media \n News   Media Contacts   Image Bank \n\n\n Get Involved \n Join an event   Rural Voices   Opinions & Insights\n\nAbout IFAD \n Who we are   Where we work   What we do   Action Areas   Knowledge & Data \n\n\n For Member States \n Member States interactive platform \n\n\n For Investors \n Investors   Finance \n\n\n For Job seekers \n Work with us   Frequently Asked Questions \n\n\n For Media \n News   Media Contacts   Image Bank \n\n\n Get Involved \n Join an event   Rural Voices   Opinions & Insights\n\nAbout IFAD \n Who we are   Where we work   What we do   Action Areas   Knowledge & Data \n\n\n For Member States \n Member States interactive platform \n\n\n For Investors \n Investors   Finance \n\n\n For Job seekers \n Work with us   Frequently Asked Questions \n\n\n For Media \n News   Media Contacts   Image Bank \n\n\n Get Involved \n Join an event   Rural Voices   Opinions & Insights\n\nAbout IFAD \n Who we are   Where we work   What we do   Action Areas   Knowledge & Data \n\n\n For Member States \n Member States interactive platform \n\n\n For Investors \n Investors   Finance \n\n\n For Job seekers \n Work with us   Frequently Asked Questions \n\n\n For Media \n News   Media Contacts   Image Bank \n\n\n Get Involved \n Join an event   Rural Voices   Opinions & Insights\n\nAbout IFAD \n Who we are   Where we work   What we do   Action Areas   Knowledge & Data \n\n\n For Member States \n Member States interactive platform \n\n\n For Investors \n Investors   Finance \n\n\n For Job seekers \n Work with us   Frequently Asked Questions \n\n\n For Media \n News   Media Contacts   Image Bank \n\n\n Get Involved \n Join an event   Rural Voices   Opinions & Insights\n\nAbout IFAD \n Who we are   Where we work   What we do   Action Areas   Knowledge & Data \n\n\n For Member States \n Member States interactive platform \n\n\n For Investors \n Investors   Finance \n\n\n For Job seekers \n Work with us   Frequently Asked Questions \n\n\n For Media \n News   Media Contacts   Image Bank \n\n\n Get Involved \n Join an event   Rural Voices   Opinions & Insights\n\nAbout IFAD \n Who we are   Where we work   What we do   Action Areas   Knowledge & Data \n\n\n For Member States \n Member States interactive platform \n\n\n For Investors \n Investors   Finance \n\n\n For Job seekers \n Work with us   Frequently Asked Questions \n\n\n For Media \n News   Media Contacts   Image Bank \n\n\n Get Involved \n Join an event   Rural Voices   Opinions & Insights\n\nAbout IFAD \n Who we are   Where we work   What we do   Action Areas   Knowledge & Data \n\n\n For Member States \n Member States interactive platform \n\n\n For Investors \n Investors   Finance \n\n\n For Job seekers \n Work with us   Frequently Asked Questions \n\n\n For Media \n News   Media Contacts   Image Bank \n\n\n Get Involved \n Join an event   Rural Voices   Opinions & Insights\n\nAbout IFAD \n Who we are   Where we work   What we do   Action Areas   Knowledge & Data\n\nWho we are   Where we work   What we do   Action Areas   Knowledge & Data\n\nFor Member States \n Member States interactive platform\n\nMember States interactive platform\n\nFor Investors \n Investors   Finance\n\nInvestors   Finance\n\nFor Job seekers \n Work with us   Frequently Asked Questions\n\nWork with us   Frequently Asked Questions\n\nFor Media \n News   Media Contacts   Image Bank\n\nNews   Media Contacts   Image Bank\n\nGet Involved \n Join an event   Rural Voices   Opinions & Insights\n\nJoin an event   Rural Voices   Opinions & Insights\n\nPlease configure the mobile menu widget below\n      \n\n\n\n\n\n\n\n\n Who we are \n\n\n\n What we do \n\n\n\n Where we work \n\n\n\n Action Areas \n\n\n\n Knowledge & Data \n\n\n\n Get Involved \n\n\n\n News and Stories\n\nPlease configure the mobile menu widget below\n\nWho we are \n\n\n\n What we do \n\n\n\n Where we work \n\n\n\n Action Areas \n\n\n\n Knowledge & Data \n\n\n\n Get Involved \n\n\n\n News and Stories\n\nWho we are \n\n\n\n What we do \n\n\n\n Where we work \n\n\n\n Action Areas \n\n\n\n Knowledge & Data \n\n\n\n Get Involved \n\n\n\n News and Stories\n\nWho we are \n\n\n\n What we do \n\n\n\n Where we work \n\n\n\n Action Areas \n\n\n\n Knowledge & Data \n\n\n\n Get Involved \n\n\n\n News and Stories\n\nWho we are \n\n\n\n What we do \n\n\n\n Where we work \n\n\n\n Action Areas \n\n\n\n Knowledge & Data \n\n\n\n Get Involved \n\n\n\n News and Stories\n\nWho we are \n\n\n\n What we do \n\n\n\n Where we work \n\n\n\n Action Areas \n\n\n\n Knowledge & Data \n\n\n\n Get Involved \n\n\n\n News and Stories\n\nWho we are \n\n\n\n What we do \n\n\n\n Where we work \n\n\n\n Action Areas \n\n\n\n Knowledge & Data \n\n\n\n Get Involved \n\n\n\n News and Stories\n\nWho we are \n\n\n\n What we do \n\n\n\n Where we work \n\n\n\n Action Areas \n\n\n\n Knowledge & Data \n\n\n\n Get Involved \n\n\n\n News and Stories\n\nWho we are \n\n\n\n What we do \n\n\n\n Where we work \n\n\n\n Action Areas \n\n\n\n Knowledge & Data \n\n\n\n Get Involved \n\n\n\n News and Stories\n\nWho we are\n\nWhat we do\n\nWhere we work\n\nAction Areas\n\nKnowledge & Data\n\nGet Involved\n\nNews and Stories\n\nLegal  Privacy notice  Fraudulent job offers  Contact us Stay connected\n\nLegal  Privacy notice  Fraudulent job offers  Contact us Stay connected",
  "date": "",
  "source_type": "other",
  "extracted_at": "2025-04-07T14:28:21.317724",
  "metadata": {
    "og:site_name": "IFAD",
    "og:type": "website"
  },
  "relevance_score": 0.5,
  "summary": "Rural Voices - IFAD\n\n\n\n\n\n\n\n\n\n\n\n\n\n\n\n\n\n\n\n\n\n\n\n\n\n\n\n\n\n      Rural voices\n     \n\n\n\n\n\n\n\n\n\n\n\n \n\n\n\n\n\n\n\n\n\n\n\n\n\n\n\n Theme \nSelect\n\n\n\n\n\n\n\n Year \nSelect\n\n\n\n\n\n\n\n Country \nSelect\n\n\n\n\n\n\n\n\n \n\n\n\n\n\n\n\n\n\n\n\n\n\n\n\n  Show more  \n\n\n\n\n\n  \n\n\n\n\n\n\n\n\n\n\n\n\n\n\n\n\n\n\nRural Voices\n\n Soil is getting saltier – but African farmers are standing strong Farmers in western and southern Africa are building resilience to salinity through innovative approaches in their fields. Read now \n              \n \n\n\n\n\n\n\n\n\n\n\n\n\n\n\n\n\n\nRural Voices\n\n With digital tools, farmers can lead the way to a sustainable future When designed with the needs and contexts of rural people in mind, digital tools can be a gamechanger for small-scale farmers and sustainable food systems. Read now \n              \n \n\n\n\n\n\n\n\n\n\n\n\n\n\n\n\n\n\n\n\nRural Voices\n\n Clean energy powers rural resilience in Cuba Rural Cuba has been impacted by recurring blackouts. Read now \n              \n \n\n\n\n\n\n\n\n\n\n\n\n\n\n\n\n\n\nRural Voices\n\n Marketing works magic for rural entrepreneurs With IFAD's support, farmers across North Africa and the Middle East are marketing effectively – and getting the recognition they deserve. 30\n\n\n\n\n\n\n\n\n\n\n\n\n\n\n\n\n\n\n       Please configure the desktop menu widget below\n      \n\n\n\n\n\n\n\n\n About IFAD \n Who we are   Where we work   What we do   Action Areas   Knowledge & Data \n\n\n For Member States \n Member States interactive platform \n\n\n For Investors \n Investors   Finance \n\n\n For Job seekers \n Work with us   Frequently Asked Questions \n\n\n For Media \n News   Media Contacts   Image Bank \n\n\n Get Involved \n Join an event   Rural Voices   Opinions & Insights \n\n\n\n\n\n\n\n\n\n\n\n\n\n       Please configure the mobile menu widget below\n      \n\n\n\n\n\n\n\n\n Who we are \n\n\n\n What we do \n\n\n\n Where we work \n\n\n\n Action Areas \n\n\n\n Knowledge & Data \n\n\n\n Get Involved \n\n\n\n News and Stories \n\n\n\n\n\n\n\n\n\n\n\n\n\n  \n Legal  Privacy notice  Fraudulent job offers  Contact us Stay connected\n\n\n\n  \n\n  \n\n  \n\n  \n\n  \n\n \n\n\n\n\n\n\n\n\nHidden\n\nRural Voices - IFAD\n\n\n\n\n\n\n\n\n\n\n\n\n\n\n\n\n\n\n\n\n\n\n\n\n\n\n\n\n\n      Rural voices\n     \n\n\n\n\n\n\n\n\n\n\n\n \n\n\n\n\n\n\n\n\n\n\n\n\n\n\n\n Theme \nSelect\n\n\n\n\n\n\n\n Year \nSelect\n\n\n\n\n\n\n\n Country \nSelect\n\n\n\n\n\n\n\n\n \n\n\n\n\n\n\n\n\n\n\n\n\n\n\n\n  Show more  \n\n\n\n\n\n  \n\n\n\n\n\n\n\n\n\n\n\n\n\n\n\n\n\n\nRural Voices\n\n Soil is getting saltier – but African farmers are standing strong Farmers in western and southern Africa are building resilience to salinity through innovative approaches in their fields. Read now \n              \n \n\n\n\n\n\n\n\n\n\n\n\n\n\n\n\n\n\nRural Voices\n\n With digital tools, farmers can lead the way to a sustainable future When designed with the needs and contexts of rural people in mind, digital tools can be a gamechanger for small-scale farmers and sustainable food systems. Read now \n              \n \n\n\n\n\n\n\n\n\n\n\n\n\n\n\n\n\n\n\n\nRural Voices\n\n Clean energy powers rural resilience in Cuba Rural Cuba has been impacted by recurring blackouts. Read now \n              \n \n\n\n\n\n\n\n\n\n\n\n\n\n\n\n\n\n\nRural Voices\n\n Marketing works magic for rural entrepreneurs With IFAD's support, farmers across North Africa and the Middle East are marketing effectively – and getting the recognition they deserve. 30\n\n\n\n\n\n\n\n\n\n\n\n\n\n\n\n\n\n\n       Please configure the desktop menu widget below\n      \n\n\n\n\n\n\n\n\n About IFAD \n Who we are   Where we work   What we do   Action Areas   Knowledge & Data \n\n\n For Member States \n Member States interactive platform \n\n\n For Investors \n Investors   Finance \n\n\n For Job seekers \n Work with us   Frequently Asked Questions \n\n\n For Media \n News   Media Contacts   Image Bank \n\n\n Get Involved \n Join an event   Rural Voices   Opinions & Insights \n\n\n\n\n\n\n\n\n\n\n\n\n\n       Please configure the mobile menu widget below\n      \n\n\n\n\n\n\n\n\n Who we are \n\n\n\n What we do \n\n\n\n Where we work \n\n\n\n Action Areas \n\n\n\n Knowledge & Data \n\n\n\n Get Involved \n\n\n\n News and Stories \n\n\n\n\n\n\n\n\n\n\n\n\n\n  \n Legal  Privacy notice  Fraudulent job offers  Contact us Stay connected\n\n\n\n  \n\n  \n\n  \n\n  \n\n  \n\n \n\n\n\n\n\n\n\n\nHidden\n\nRural Voices - IFAD\n\n\n\n\n\n\n\n\n\n\n\n\n\n\n\n\n\n\n\n\n\n\n\n\n\n\n\n\n\n      Rural voices\n     \n\n\n\n\n\n\n\n\n\n\n\n \n\n\n\n\n\n\n\n\n\n\n\n\n\n\n\n Theme \nSelect\n\n\n\n\n\n\n\n Year \nSelect\n\n\n\n\n\n\n\n Country \nSelect\n\n\n\n\n\n\n\n\n \n\n\n\n\n\n\n\n\n\n\n\n\n\n\n\n  Show more  \n\n\n\n\n\n  \n\n\n\n\n\n\n\n\n\n\n\n\n\n\n\n\n\n\nRural Voices\n\n Soil is getting saltier – but African farmers are standing strong Farmers in western and southern Africa are building resilience to salinity through innovative approaches in their fields. Read now \n              \n \n\n\n\n\n\n\n\n\n\n\n\n\n\n\n\n\n\nRural Voices\n\n With digital tools, farmers can lead the way to a sustainable future When designed with the needs and contexts of rural people in mind, digital tools can be a gamechanger for small-scale farmers and sustainable food systems. Read now \n              \n \n\n\n\n\n\n\n\n\n\n\n\n\n\n\n\n\n\n\n\nRural Voices\n\n Clean energy powers rural resilience in Cuba Rural Cuba has been impacted by recurring blackouts. Read now \n              \n \n\n\n\n\n\n\n\n\n\n\n\n\n\n\n\n\n\nRural Voices\n\n Marketing works magic for rural entrepreneurs With IFAD's support, farmers across North Africa and the Middle East are marketing effectively – and getting the recognition they deserve. 30\n\n\n\n\n\n\n\n\n\n\n\n\n\n\n\n\n\n\n       Please configure the desktop menu widget below\n      \n\n\n\n\n\n\n\n\n About IFAD \n Who we are   Where we work   What we do   Action Areas   Knowledge & Data \n\n\n For Member States \n Member States interactive platform \n\n\n For Investors \n Investors   Finance \n\n\n For Job seekers \n Work with us   Frequently Asked Questions \n\n\n For Media \n News   Media Contacts   Image Bank \n\n\n Get Involved \n Join an event   Rural Voices   Opinions & Insights \n\n\n\n\n\n\n\n\n\n\n\n\n\n       Please configure the mobile menu widget below\n      \n\n\n\n\n\n\n\n\n Who we are \n\n\n\n What we do \n\n\n\n Where we work \n\n\n\n Action Areas \n\n\n\n Knowledge & Data \n\n\n\n Get Involved \n\n\n\n News and Stories \n\n\n\n\n\n\n\n\n\n\n\n\n\n  \n Legal  Privacy notice  Fraudulent job offers  Contact us Stay connected\n\n\n\n  \n\n  \n\n  \n\n  \n\n  \n\n \n\n\n\n\n\n\n\n\nHidden\n\nRural voices\n     \n\n\n\n\n\n\n\n\n\n\n\n \n\n\n\n\n\n\n\n\n\n\n\n\n\n\n\n Theme \nSelect\n\n\n\n\n\n\n\n Year \nSelect\n\n\n\n\n\n\n\n Country \nSelect\n\n\n\n\n\n\n\n\n \n\n\n\n\n\n\n\n\n\n\n\n\n\n\n\n  Show more  \n\n\n\n\n\n  \n\n\n\n\n\n\n\n\n\n\n\n\n\n\n\n\n\n\nRural Voices\n\n Soil is getting saltier – but African farmers are standing strong Farmers in western and southern Africa are building resilience to salinity through innovative approaches in their fields. Read now \n              \n \n\n\n\n\n\n\n\n\n\n\n\n\n\n\n\n\n\nRural Voices\n\n With digital tools, farmers can lead the way to a sustainable future When designed with the needs and contexts of rural people in mind, digital tools can be a gamechanger for small-scale farmers and sustainable food systems. Read now \n              \n \n\n\n\n\n\n\n\n\n\n\n\n\n\n\n\n\n\n\n\nRural Voices\n\n Clean energy powers rural resilience in Cuba Rural Cuba has been impacted by recurring blackouts. Read now \n              \n \n\n\n\n\n\n\n\n\n\n\n\n\n\n\n\n\n\nRural Voices\n\n Marketing works magic for rural entrepreneurs With IFAD's support, farmers across North Africa and the Middle East are marketing effectively – and getting the recognition they deserve. 30\n\n\n\n\n\n\n\n\n\n\n\n\n\n\n\n\n\n\n       Please configure the desktop menu widget below\n      \n\n\n\n\n\n\n\n\n About IFAD \n Who we are   Where we work   What we do   Action Areas   Knowledge & Data \n\n\n For Member States \n Member States interactive platform \n\n\n For Investors \n Investors   Finance \n\n\n For Job seekers \n Work with us   Frequently Asked Questions \n\n\n For Media \n News   Media Contacts   Image Bank \n\n\n Get Involved \n Join an event   Rural Voices   Opinions & Insights \n\n\n\n\n\n\n\n\n\n\n\n\n\n       Please configure the mobile menu widget below\n      \n\n\n\n\n\n\n\n\n Who we are \n\n\n\n What we do \n\n\n\n Where we work \n\n\n\n Action Areas \n\n\n\n Knowledge & Data \n\n\n\n Get Involved \n\n\n\n News and Stories \n\n\n\n\n\n\n\n\n\n\n\n\n\n  \n Legal  Privacy notice  Fraudulent job offers  Contact us Stay connected\n\nRural voices\n     \n\n\n\n\n\n\n\n\n\n\n\n \n\n\n\n\n\n\n\n\n\n\n\n\n\n\n\n Theme \nSelect\n\n\n\n\n\n\n\n Year \nSelect\n\n\n\n\n\n\n\n Country \nSelect\n\n\n\n\n\n\n\n\n \n\n\n\n\n\n\n\n\n\n\n\n\n\n\n\n  Show more  \n\n\n\n\n\n  \n\n\n\n\n\n\n\n\n\n\n\n\n\n\n\n\n\n\nRural Voices\n\n Soil is getting saltier – but African farmers are standing strong Farmers in western and southern Africa are building resilience to salinity through innovative approaches in their fields. Read now \n              \n \n\n\n\n\n\n\n\n\n\n\n\n\n\n\n\n\n\nRural Voices\n\n With digital tools, farmers can lead the way to a sustainable future When designed with the needs and contexts of rural people in mind, digital tools can be a gamechanger for small-scale farmers and sustainable food systems. Read now \n              \n \n\n\n\n\n\n\n\n\n\n\n\n\n\n\n\n\n\n\n\nRural Voices\n\n Clean energy powers rural resilience in Cuba Rural Cuba has been impacted by recurring blackouts. Read now \n              \n \n\n\n\n\n\n\n\n\n\n\n\n\n\n\n\n\n\nRural Voices\n\n Marketing works magic for rural entrepreneurs With IFAD's support, farmers across North Africa and the Middle East are marketing effectively – and getting the recognition they deserve. 30\n\n\n\n\n\n\n\n\n\n\n\n\n\n\n\n\n\n\n       Please configure the desktop menu widget below\n      \n\n\n\n\n\n\n\n\n About IFAD \n Who we are   Where we work   What we do   Action Areas   Knowledge & Data \n\n\n For Member States \n Member States interactive platform \n\n\n For Investors \n Investors   Finance \n\n\n For Job seekers \n Work with us   Frequently Asked Questions \n\n\n For Media \n News   Media Contacts   Image Bank \n\n\n Get Involved \n Join an event   Rural Voices   Opinions & Insights \n\n\n\n\n\n\n\n\n\n\n\n\n\n       Please configure the mobile menu widget below\n      \n\n\n\n\n\n\n\n\n Who we are \n\n\n\n What we do \n\n\n\n Where we work \n\n\n\n Action Areas \n\n\n\n Knowledge & Data \n\n\n\n Get Involved \n\n\n\n News and Stories \n\n\n\n\n\n\n\n\n\n\n\n\n\n  \n Legal  Privacy notice  Fraudulent job offers  Contact us Stay connected\n\nRural voices\n     \n\n\n\n\n\n\n\n\n\n\n\n \n\n\n\n\n\n\n\n\n\n\n\n\n\n\n\n Theme \nSelect\n\n\n\n\n\n\n\n Year \nSelect\n\n\n\n\n\n\n\n Country \nSelect\n\n\n\n\n\n\n\n\n \n\n\n\n\n\n\n\n\n\n\n\n\n\n\n\n  Show more  \n\n\n\n\n\n  \n\n\n\n\n\n\n\n\n\n\n\n\n\n\n\n\n\n\nRural Voices\n\n Soil is getting saltier – but African farmers are standing strong Farmers in western and southern Africa are building resilience to salinity through innovative approaches in their fields. Read now \n              \n \n\n\n\n\n\n\n\n\n\n\n\n\n\n\n\n\n\nRural Voices\n\n With digital tools, farmers can lead the way to a sustainable future When designed with the needs and contexts of rural people in mind, digital tools can be a gamechanger for small-scale farmers and sustainable food systems. Read now \n              \n \n\n\n\n\n\n\n\n\n\n\n\n\n\n\n\n\n\n\n\nRural Voices\n\n Clean energy powers rural resilience in Cuba Rural Cuba has been impacted by recurring blackouts. Read now \n              \n \n\n\n\n\n\n\n\n\n\n\n\n\n\n\n\n\n\nRural Voices\n\n Marketing works magic for rural entrepreneurs With IFAD's support, farmers across North Africa and the Middle East are marketing effectively – and getting the recognition they deserve. 30\n\nRural voices\n\nRural voices\n\nRural voices\n\nTheme \nSelect\n\n\n\n\n\n\n\n Year \nSelect\n\n\n\n\n\n\n\n Country \nSelect\n\n\n\n\n\n\n\n\n \n\n\n\n\n\n\n\n\n\n\n\n\n\n\n\n  Show more  \n\n\n\n\n\n  \n\n\n\n\n\n\n\n\n\n\n\n\n\n\n\n\n\n\nRural Voices\n\n Soil is getting saltier – but African farmers are standing strong Farmers in western and southern Africa are building resilience to salinity through innovative approaches in their fields. Read now \n              \n \n\n\n\n\n\n\n\n\n\n\n\n\n\n\n\n\n\nRural Voices\n\n With digital tools, farmers can lead the way to a sustainable future When designed with the needs and contexts of rural people in mind, digital tools can be a gamechanger for small-scale farmers and sustainable food systems. Read now \n              \n \n\n\n\n\n\n\n\n\n\n\n\n\n\n\n\n\n\n\n\nRural Voices\n\n Clean energy powers rural resilience in Cuba Rural Cuba has been impacted by recurring blackouts. Read now \n              \n \n\n\n\n\n\n\n\n\n\n\n\n\n\n\n\n\n\nRural Voices\n\n Marketing works magic for rural entrepreneurs With IFAD's support, farmers across North Africa and the Middle East are marketing effectively – and getting the recognition they deserve. Read now \n              \n \n\n\n\n\n\n\n\n\n\n\n\n\n\n\n\n\n\nRural Voices\n\n With digital tools, farmers can lead the way to a sustainable future When designed with the needs and contexts of rural people in mind, digital tools can be a gamechanger for small-scale farmers and sustainable food systems. Read now \n              \n \n\n\n\n\n\n\n\n\n\n\n\n\n\n\n\n\n\n\n\nRural Voices\n\n Clean energy powers rural resilience in Cuba Rural Cuba has been impacted by recurring blackouts. Read now \n              \n \n\n\n\n\n\n\n\n\n\n\n\n\n\n\n\n\n\nRural Voices\n\n Marketing works magic for rural entrepreneurs With IFAD's support, farmers across North Africa and the Middle East are marketing effectively – and getting the recognition they deserve. 30\n\nTheme \nSelect\n\n\n\n\n\n\n\n Year \nSelect\n\n\n\n\n\n\n\n Country \nSelect\n\n\n\n\n\n\n\n\n \n\n\n\n\n\n\n\n\n\n\n\n\n\n\n\n  Show more\n\nTheme \nSelect\n\n\n\n\n\n\n\n Year \nSelect\n\n\n\n\n\n\n\n Country \nSelect\n\nTheme \nSelect\n\n\n\n\n\n\n\n Year \nSelect\n\n\n\n\n\n\n\n Country \nSelect\n\nTheme \nSelect\n\nTheme \nSelect\n\nTheme \nSelect\n\nSelect\n\nYear \nSelect\n\nYear \nSelect\n\nYear \nSelect\n\nSelect\n\nCountry \nSelect\n\nCountry \nSelect\n\nCountry \nSelect\n\nSelect\n\nShow more\n\nShow more\n\nShow more\n\nRural Voices\n\n Soil is getting saltier – but African farmers are standing strong Farmers in western and southern Africa are building resilience to salinity through innovative approaches in their fields. Read now \n              \n \n\n\n\n\n\n\n\n\n\n\n\n\n\n\n\n\n\nRural Voices\n\n With digital tools, farmers can lead the way to a sustainable future When designed with the needs and contexts of rural people in mind, digital tools can be a gamechanger for small-scale farmers and sustainable food systems. Read now \n              \n \n\n\n\n\n\n\n\n\n\n\n\n\n\n\n\n\n\n\n\nRural Voices\n\n Clean energy powers rural resilience in Cuba Rural Cuba has been impacted by recurring blackouts. Read now \n              \n \n\n\n\n\n\n\n\n\n\n\n\n\n\n\n\n\n\nRural Voices\n\n Marketing works magic for rural entrepreneurs With IFAD's support, farmers across North Africa and the Middle East are marketing effectively – and getting the recognition they deserve. Read now \n              \n \n\n\n\n\n\n\n\n\n\n\n\n\n\n\n\n\n\nRural Voices\n\n With digital tools, farmers can lead the way to a sustainable future When designed with the needs and contexts of rural people in mind, digital tools can be a gamechanger for small-scale farmers and sustainable food systems. Read now \n              \n \n\n\n\n\n\n\n\n\n\n\n\n\n\n\n\n\n\nRural Voices\n\n Marketing works magic for rural entrepreneurs With IFAD's support, farmers across North Africa and the Middle East are marketing effectively – and getting the recognition they deserve. Rural Voices\n\nRural Voices\n\nSoil is getting saltier – but African farmers are standing strong Farmers in western and southern Africa are building resilience to salinity through innovative approaches in their fields. Rural Voices\n\nRural Voices\n\nForest bounty feeds the world Meet some of the rural people that IFAD works with to celebrate and nurture the bounty of our forests. Rural Voices\n\nRural Voices\n\nInvestment from Malians abroad supports farmers back home Overseas Malians are exploring ways to invest in businesses that yield both societal impact and financial returns – and agriculture is high on the priority list. Read now \n              \n \n\n\n\n\n\n\n\n\n\n\n\n\n\n\n\n\n\nRural Voices\n\n With digital tools, farmers can lead the way to a sustainable future When designed with the needs and contexts of rural people in mind, digital tools can be a gamechanger for small-scale farmers and sustainable food systems. Rural Voices\n\nRural Voices\n\nRural women ring in change in West Africa Meet three women who are leading their communities towards a more prosperous and equal future. Rural Voices\n\n With digital tools, farmers can lead the way to a sustainable future When designed with the needs and contexts of rural people in mind, digital tools can be a gamechanger for small-scale farmers and sustainable food systems. Read now\n\nRural Voices\n\n With digital tools, farmers can lead the way to a sustainable future When designed with the needs and contexts of rural people in mind, digital tools can be a gamechanger for small-scale farmers and sustainable food systems. Read now\n\nRural Voices\n\n With digital tools, farmers can lead the way to a sustainable future When designed with the needs and contexts of rural people in mind, digital tools can be a gamechanger for small-scale farmers and sustainable food systems. Read now\n\nRural Voices\n\n With digital tools, farmers can lead the way to a sustainable future When designed with the needs and contexts of rural people in mind, digital tools can be a gamechanger for small-scale farmers and sustainable food systems. Read now\n\nRural Voices\n\n With digital tools, farmers can lead the way to a sustainable future When designed with the needs and contexts of rural people in mind, digital tools can be a gamechanger for small-scale farmers and sustainable food systems. Read now\n\nRural Voices\n\n With digital tools, farmers can lead the way to a sustainable future When designed with the needs and contexts of rural people in mind, digital tools can be a gamechanger for small-scale farmers and sustainable food systems. Read now\n\nRural Voices\n\n With digital tools, farmers can lead the way to a sustainable future When designed with the needs and contexts of rural people in mind, digital tools can be a gamechanger for small-scale farmers and sustainable food systems. Rural Voices\n\nRural Voices\n\nWith digital tools, farmers can lead the way to a sustainable future When designed with the needs and contexts of rural people in mind, digital tools can be a gamechanger for small-scale farmers and sustainable food systems. Rural Voices\n\nRural Voices\n\nClean energy powers rural resilience in Cuba Rural Cuba has been impacted by recurring blackouts. Rural Voices\n\nRural Voices\n\nBuilding resilient food systems in small island developing states Small island developing states (SIDS) share a range of challenges. Rural Voices\n\nRural Voices\n\nClimate-smart irrigation reaps rewards for rural women From Laos to Moldova, meet three women who are using climate-smart irrigation to adapt to their new normal. Read now \n              \n \n\n\n\n\n\n\n\n\n\n\n\n\n\n\n\n\n\nRural Voices\n\n Marketing works magic for rural entrepreneurs With IFAD's support, farmers across North Africa and the Middle East are marketing effectively – and getting the recognition they deserve. Read now\n\nRural Voices\n\n Marketing works magic for rural entrepreneurs With IFAD's support, farmers across North Africa and the Middle East are marketing effectively – and getting the recognition they deserve. Read now\n\nRural Voices\n\n Marketing works magic for rural entrepreneurs With IFAD's support, farmers across North Africa and the Middle East are marketing effectively – and getting the recognition they deserve. Read now\n\nRural Voices\n\n Marketing works magic for rural entrepreneurs With IFAD's support, farmers across North Africa and the Middle East are marketing effectively – and getting the recognition they deserve. Read now\n\nRural Voices\n\n Marketing works magic for rural entrepreneurs With IFAD's support, farmers across North Africa and the Middle East are marketing effectively – and getting the recognition they deserve. Read now\n\nRural Voices\n\n Marketing works magic for rural entrepreneurs With IFAD's support, farmers across North Africa and the Middle East are marketing effectively – and getting the recognition they deserve. Read now\n\nRural Voices\n\n Marketing works magic for rural entrepreneurs With IFAD's support, farmers across North Africa and the Middle East are marketing effectively – and getting the recognition they deserve. Rural Voices\n\nRural Voices\n\nMarketing works magic for rural entrepreneurs With IFAD's support, farmers across North Africa and the Middle East are marketing effectively – and getting the recognition they deserve. 30\n\nShowing 1 to 12 of 353\n\nPlease configure the desktop menu widget below\n      \n\n\n\n\n\n\n\n\n About IFAD \n Who we are   Where we work   What we do   Action Areas   Knowledge & Data \n\n\n For Member States \n Member States interactive platform \n\n\n For Investors \n Investors   Finance \n\n\n For Job seekers \n Work with us   Frequently Asked Questions \n\n\n For Media \n News   Media Contacts   Image Bank \n\n\n Get Involved \n Join an event   Rural Voices   Opinions & Insights \n\n\n\n\n\n\n\n\n\n\n\n\n\n       Please configure the mobile menu widget below\n      \n\n\n\n\n\n\n\n\n Who we are \n\n\n\n What we do \n\n\n\n Where we work \n\n\n\n Action Areas \n\n\n\n Knowledge & Data \n\n\n\n Get Involved \n\n\n\n News and Stories \n\n\n\n\n\n\n\n\n\n\n\n\n\n  \n Legal  Privacy notice  Fraudulent job offers  Contact us Stay connected\n\nPlease configure the desktop menu widget below\n      \n\n\n\n\n\n\n\n\n About IFAD \n Who we are   Where we work   What we do   Action Areas   Knowledge & Data \n\n\n For Member States \n Member States interactive platform \n\n\n For Investors \n Investors   Finance \n\n\n For Job seekers \n Work with us   Frequently Asked Questions \n\n\n For Media \n News   Media Contacts   Image Bank \n\n\n Get Involved \n Join an event   Rural Voices   Opinions & Insights \n\n\n\n\n\n\n\n\n\n\n\n\n\n       Please configure the mobile menu widget below\n      \n\n\n\n\n\n\n\n\n Who we are \n\n\n\n What we do \n\n\n\n Where we work \n\n\n\n Action Areas \n\n\n\n Knowledge & Data \n\n\n\n Get Involved \n\n\n\n News and Stories \n\n\n\n\n\n\n\n\n\n\n\n\n\n  \n Legal  Privacy notice  Fraudulent job offers  Contact us Stay connected\n\nPlease configure the desktop menu widget below\n      \n\n\n\n\n\n\n\n\n About IFAD \n Who we are   Where we work   What we do   Action Areas   Knowledge & Data \n\n\n For Member States \n Member States interactive platform \n\n\n For Investors \n Investors   Finance \n\n\n For Job seekers \n Work with us   Frequently Asked Questions \n\n\n For Media \n News   Media Contacts   Image Bank \n\n\n Get Involved \n Join an event   Rural Voices   Opinions & Insights \n\n\n\n\n\n\n\n\n\n\n\n\n\n       Please configure the mobile menu widget below\n      \n\n\n\n\n\n\n\n\n Who we are \n\n\n\n What we do \n\n\n\n Where we work \n\n\n\n Action Areas \n\n\n\n Knowledge & Data \n\n\n\n Get Involved \n\n\n\n News and Stories \n\n\n\n\n\n\n\n\n\n\n\n\n\n  \n Legal  Privacy notice  Fraudulent job offers  Contact us Stay connected\n\nPlease configure the desktop menu widget below\n      \n\n\n\n\n\n\n\n\n About IFAD \n Who we are   Where we work   What we do   Action Areas   Knowledge & Data \n\n\n For Member States \n Member States interactive platform \n\n\n For Investors \n Investors   Finance \n\n\n For Job seekers \n Work with us   Frequently Asked Questions \n\n\n For Media \n News   Media Contacts   Image Bank \n\n\n Get Involved \n Join an event   Rural Voices   Opinions & Insights \n\n\n\n\n\n\n\n\n\n\n\n\n\n       Please configure the mobile menu widget below\n      \n\n\n\n\n\n\n\n\n Who we are \n\n\n\n What we do \n\n\n\n Where we work \n\n\n\n Action Areas \n\n\n\n Knowledge & Data \n\n\n\n Get Involved \n\n\n\n News and Stories\n\nPlease configure the desktop menu widget below\n      \n\n\n\n\n\n\n\n\n About IFAD \n Who we are   Where we work   What we do   Action Areas   Knowledge & Data \n\n\n For Member States \n Member States interactive platform \n\n\n For Investors \n Investors   Finance \n\n\n For Job seekers \n Work with us   Frequently Asked Questions \n\n\n For Media \n News   Media Contacts   Image Bank \n\n\n Get Involved \n Join an event   Rural Voices   Opinions & Insights\n\nPlease configure the desktop menu widget below\n\nAbout IFAD \n Who we are   Where we work   What we do   Action Areas   Knowledge & Data \n\n\n For Member States \n Member States interactive platform \n\n\n For Investors \n Investors   Finance \n\n\n For Job seekers \n Work with us   Frequently Asked Questions \n\n\n For Media \n News   Media Contacts   Image Bank \n\n\n Get Involved \n Join an event   Rural Voices   Opinions & Insights\n\nAbout IFAD \n Who we are   Where we work   What we do   Action Areas   Knowledge & Data \n\n\n For Member States \n Member States interactive platform \n\n\n For Investors \n Investors   Finance \n\n\n For Job seekers \n Work with us   Frequently Asked Questions \n\n\n For Media \n News   Media Contacts   Image Bank \n\n\n Get Involved \n Join an event   Rural Voices   Opinions & Insights\n\nAbout IFAD \n Who we are   Where we work   What we do   Action Areas   Knowledge & Data \n\n\n For Member States \n Member States interactive platform \n\n\n For Investors \n Investors   Finance \n\n\n For Job seekers \n Work with us   Frequently Asked Questions \n\n\n For Media \n News   Media Contacts   Image Bank \n\n\n Get Involved \n Join an event   Rural Voices   Opinions & Insights\n\nAbout IFAD \n Who we are   Where we work   What we do   Action Areas   Knowledge & Data \n\n\n For Member States \n Member States interactive platform \n\n\n For Investors \n Investors   Finance \n\n\n For Job seekers \n Work with us   Frequently Asked Questions \n\n\n For Media \n News   Media Contacts   Image Bank \n\n\n Get Involved \n Join an event   Rural Voices   Opinions & Insights\n\nAbout IFAD \n Who we are   Where we work   What we do   Action Areas   Knowledge & Data \n\n\n For Member States \n Member States interactive platform \n\n\n For Investors \n Investors   Finance \n\n\n For Job seekers \n Work with us   Frequently Asked Questions \n\n\n For Media \n News   Media Contacts   Image Bank \n\n\n Get Involved \n Join an event   Rural Voices   Opinions & Insights\n\nAbout IFAD \n Who we are   Where we work   What we do   Action Areas   Knowledge & Data \n\n\n For Member States \n Member States interactive platform \n\n\n For Investors \n Investors   Finance \n\n\n For Job seekers \n Work with us   Frequently Asked Questions \n\n\n For Media \n News   Media Contacts   Image Bank \n\n\n Get Involved \n Join an event   Rural Voices   Opinions & Insights\n\nAbout IFAD \n Who we are   Where we work   What we do   Action Areas   Knowledge & Data \n\n\n For Member States \n Member States interactive platform \n\n\n For Investors \n Investors   Finance \n\n\n For Job seekers \n Work with us   Frequently Asked Questions \n\n\n For Media \n News   Media Contacts   Image Bank \n\n\n Get Involved \n Join an event   Rural Voices   Opinions & Insights\n\nAbout IFAD \n Who we are   Where we work   What we do   Action Areas   Knowledge & Data \n\n\n For Member States \n Member States interactive platform \n\n\n For Investors \n Investors   Finance \n\n\n For Job seekers \n Work with us   Frequently Asked Questions \n\n\n For Media \n News   Media Contacts   Image Bank \n\n\n Get Involved \n Join an event   Rural Voices   Opinions & Insights\n\nAbout IFAD \n Who we are   Where we work   What we do   Action Areas   Knowledge & Data\n\nWho we are   Where we work   What we do   Action Areas   Knowledge & Data\n\nFor Member States \n Member States interactive platform\n\nMember States interactive platform\n\nFor Investors \n Investors   Finance\n\nInvestors   Finance\n\nFor Job seekers \n Work with us   Frequently Asked Questions\n\nWork with us   Frequently Asked Questions\n\nFor Media \n News   Media Contacts   Image Bank\n\nNews   Media Contacts   Image Bank\n\nGet Involved \n Join an event   Rural Voices   Opinions & Insights\n\nJoin an event   Rural Voices   Opinions & Insights\n\nPlease configure the mobile menu widget below\n      \n\n\n\n\n\n\n\n\n Who we are \n\n\n\n What we do \n\n\n\n Where we work \n\n\n\n Action Areas \n\n\n\n Knowledge & Data \n\n\n\n Get Involved \n\n\n\n News and Stories\n\nPlease configure the mobile menu widget below\n\nWho we are \n\n\n\n What we do \n\n\n\n Where we work \n\n\n\n Action Areas \n\n\n\n Knowledge & Data \n\n\n\n Get Involved \n\n\n\n News and Stories\n\nWho we are \n\n\n\n What we do \n\n\n\n Where we work \n\n\n\n Action Areas \n\n\n\n Knowledge & Data \n\n\n\n Get Involved \n\n\n\n News and Stories\n\nWho we are \n\n\n\n What we do \n\n\n\n Where we work \n\n\n\n Action Areas \n\n\n\n Knowledge & Data \n\n\n\n Get Involved \n\n\n\n News and Stories\n\nWho we are \n\n\n\n What we do \n\n\n\n Where we work \n\n\n\n Action Areas \n\n\n\n Knowledge & Data \n\n\n\n Get Involved \n\n\n\n News and Stories\n\nWho we are \n\n\n\n What we do \n\n\n\n Where we work \n\n\n\n Action Areas \n\n\n\n Knowledge & Data \n\n\n\n Get Involved \n\n\n\n News and Stories\n\nWho we are \n\n\n\n What we do \n\n\n\n Where we work \n\n\n\n Action Areas \n\n\n\n Knowledge & Data \n\n\n\n Get Involved \n\n\n\n News and Stories\n\nWho we are \n\n\n\n What we do \n\n\n\n Where we work \n\n\n\n Action Areas \n\n\n\n Knowledge & Data \n\n\n\n Get Involved \n\n\n\n News and Stories\n\nWho we are \n\n\n\n What we do \n\n\n\n Where we work \n\n\n\n Action Areas \n\n\n\n Knowledge & Data \n\n\n\n Get Involved \n\n\n\n News and Stories\n\nWho we are\n\nWhat we do\n\nWhere we work\n\nAction Areas\n\nKnowledge & Data\n\nGet Involved\n\nNews and Stories\n\nLegal  Privacy notice  Fraudulent job offers  Contact us Stay connected\n\nLegal  Privacy notice  Fraudulent job offers  Contact us Stay connected",
  "entities": {
    "countries": [
      "china",
      "mexico"
    ],
    "organizations": [
      "un",
      "who"
    ],
    "key_issues": [
      "challenge",
      "matter",
      "country",
      "state",
      "region",
      "approach",
      "action",
      "context",
      "development",
      "financial",
      "market",
      "investment",
      "un"
    ]
  },
  "committee": "Economic and Social Council",
  "topic": "Promoting rural development in Africa"
}