{
  "url": "https://repository.uneca.org/discover",
  "title": "Search",
  "text": "46165 publications\n\n\n\n\n\n\n\n\n\n\n\nAdvanced Search\n\n46165 publications\n\n\n\n\n\n\n\n\n\n\n\nAdvanced Search\n\n46165 publications\n\nAdvanced Search\n\nSearch \n\n\n \n                        ECA IR Home\n\n\nSearch\n\n\n\n\n\n \n            ECA IR Home\n\nSearch\n\nSearch \n\n\n \n                        ECA IR Home\n\n\nSearch\n\n\n\n\n\n \n            ECA IR Home\n\nSearch\n\nSearch \n\n\n \n                        ECA IR Home\n\n\nSearch\n\n\n\n\n\n \n            ECA IR Home\n\nSearch\n\nSearch \n\n\n \n                        ECA IR Home\n\n\nSearch\n\n\n\n\n\n \n            ECA IR Home\n\nSearch\n\nSearch \n\n\n \n                        ECA IR Home\n\n\nSearch\n\nJavaScript is disabled for your browser. Some features of this site may not work without it.\n\nJavaScript is disabled for your browser. Some features of this site may not work without it.\n\nJavaScript is disabled for your browser. Some features of this site may not work without it.\n\nSearch\n\n\n\n\n\n\n\n\n\n\n\n\n\nAll of ECA IRAfrican Policy CentersCommunities and Collections developed on the BrowseOther Communities and Collections not in the Main Areas of WorkRegional Coordination Mechanism (RCM)TaxonomyWork programmes\n\n\n\n\nGo\n\n\n\n\n\n\n\n\n\n\n\n\n\n\nShow Advanced FiltersHide Advanced Filters\n\n\nFilters\n\nUse filters to refine the search results.\n\n\nLimit your search to items with or without files\nall itemsitems with filesitems without files\n\n\n\n\n\n\nResetAdd New FilterApply\n\n\n\n\n\n\n\n\n\n\n\n\n\n\n\n\n\n\n\n\n\n\n\n\n\n\n\n\n\n\n\n\n\nNow showing items 1-10 of 42199\n\n\n\n\n\nSort Options:\n\nRelevance\n\n\nTitle Asc\n\n\nTitle Desc\n\n\nIssue Date Asc\n\n\nIssue Date Desc\n\n\nResults Per Page:\n\n5\n\n\n10\n\n\n20\n\n\n40\n\n\n60\n\n\n80\n\n\n100\n\n\n\n\n\n\n\n\n\n\n\n\n\n\n\n\nThe evaluation report on multimodal transport sub-sector: the third and final evaluation report on the second United Nations Transport and Communication Decade in Africa (UNTACDA II) 1991-2000 \n\n\n\nUnited Nations. Economic Commission for Africa (2001-09)\nThe UNTACDA II sub-sectoral evaluation report in the field of Multimodal Transport (MT) has been prepared according to the revised terms of reference for preparation of modal reports. The content of various chapters are ...\n\n\n\n\n\n\n\n\n\n\n\nScaling-up the response to HIV/AIDS: building on lessons learnt from intensified responses to HIV/AIDS \n\n\n\nUnited Nations. Economic Commission for Africa (2000-12)\nThere is an urgent need to build on the lessons learned about HIV/AIDS prevention and care over the past two decades. The major challenge is how to develop successfully within the resource constraints facing African ...\n\n\n\n\n\n\n\n\n\n\n\nRapport de la réunion ad-hoc du groupe spécial d'experts pour l'examen des stratégies et politiques requises pour améliorer le processus de mise en œuvre de la privatisation en Afrique: \n\n\n\nNations Unies. Commission économique pour l'Afrique; Nations Unies. Conseil Economique et Social (1999-11)\nLa réunion du Groupe spécial d’experts organisé par la Commission économique pour l’Afrique sur l’examen des stratégies et politiques requises pour améliorer le processus de mise en œuvre de la privatisation en Afrique se ...\n\n\n\n\n\n\n\n\n\n\n\nRestructuring and privatization of public enterprises \n\n\n\nUnited Nations. Economic Commission for Africa. (1993-03)\nThere is agreement among policy-makers, experts, and practitioners that the public enterprise sector has in general not performed according to the expectations which were vested into it. The low efficiency of the public ...\n\n\n\n\n\n\n\n\n\n\n\nReport to the twelfth meeting of the Conference of African Ministres of Industry \n\n\n\nUnited National Industrial Development Organization; United Nations. Economic Commission for Africa (1995-06)\nThe twelfth meeting of the Conference of African Ministers of Industry, jointly organized by the United Nations Economic Commission for Africa (EGA) and the United Nations Industrial Development Organization (UNIDO), in ...\n\n\n\n\n\n\n\n\n\n\n\nInternational legal instruments relevant to women \n\n\n\nUnited Nations. Economic Commission for Africa. African Centre for Women (1995-06)\nThe principal purpose for publishing this document is to enhance the awareness and enlightenment of women and policy makers with regard to the basic legal rights of women and the existing international legal instruments ...\n\n\n\n\n\n\n\n\n\n\n\nSouthern Africa Sub-regional Development Center : Lusaka, Zambia \n\n\n\nUnited Nations. Economic Commission for Africa (1997-07)\nThis is the second issue of the Southern Africa Development Bulletin published by the Sub-Regional Development Center of the United Nations Economic Commission for Africa for Southern Africa. The first issue was published ...\n\n\n\n\n\n\n\n\n\n\n\nGender mainstreaming at ECA : review of the past present and future \n\n\n\nUnited Nations. Economic Commission for Africa. African Centre for Women (1996-05)\nThe Vision statement provides the framework for the development of the 1998 - 2001 Medium-term Plan, designed to increase the impact of the organization's work priorities by sharpening the focus of its programs. In this ...\n\n\n\n\n\n\n\n\n\n\n\nSome aspects of family planning programmes and fertility in selected ECA member states \n\n\n\nUnited Nations. Economic Commission for Africa. Population Division. Planning and Policies Section. (1985-03)\nRapid population growth has become an increasingly important concern to governments in the ECA member States. The estimated regional population growth rate was 3.1 per cent per annum for the 1980-85 quinquennium.Among the ...\n\n\n\n\n\n\n\n\n\n\n\nApplication of science and technology in Agro-industry \n\n\n\nUnited Nations. Economic Commission for Africa; Food Security and Sustainable Develoment Division (FSSDD) (1999-12)\nAgro-industries are usually the first to be established in modern manufacturing sector of a developing economy where agriculture has been the mainstay of the economy. Moreover, food processing has a stimulating effect on ...\n\n\n\n\n\n\n\n\n\n\n\n1\n\n\n2\n\n\n3\n\n\n4\n\n\n. . .\n\n\n4220\n\n\n\n\n\n\n\n\n\n\n\n\n\n\n\n\n\nBrowse\n\nAll of ECA IRCommunities & CollectionsTitleAuthorSubjectBy Issue DateECA Conference ProceedingsFlagship PublicationHas File(s)SpeechesPress ReleasesResolutionsBest Practices\n\nMy Account\n\nMy AccountRegister\n\n\n\nDiscover\n\nAuthorLopes, Carlos (267)Amoako, K.Y. (243)Janneh, Abdoulie (182)Adedeji, Adebayo (110)K.Y., Amoako (103)... View MoreSubjectAFRICA (8418)AFRIQUE (8300)ECONOMIC DEVELOPMENT (3210)DEVELOPPEMENT ECONOMIQUE (3196)WORK PROGRAMME (3188)... View MoreDate2020 - 2025 (4226)2010 - 2019 (8389)2000 - 2009 (4756)1990 - 1999 (6763)1980 - 1989 (6868)1970 - 1979 (5157)1960 - 1969 (5588)1958 - 1959 (110)ECA Conference ProceedingsSessions of the Commission (4479)Conferences of African Ministers (1920)Conferences on Statistical Development (1521)Conferences on Trade, Regional Cooperation and Integration (693)Preparatory Committees (668)... View MoreFlagship PublicationCountry profiles (134)Economic Report on Africa (72)ECA Journals (22)Assessing Regional Integration in Africa (20)Africa’s quarterly economic performance and outlook (19)... View MoreECA Media Format9 p. : ill, (1)TypeConference document (14249)Reports (10399)Press release (7206)Working paper (2862)Speech (1751)Technical paper (927)Briefing paper (580)Book (549)Policy paper (429)Resolutions and decisions (376)... View MoreSeriesPress Release (611)Communiqué de presse. (383)Speech (336)COVID-19 Situation Report: (305)COVID-19 Situation Report : (208)ATPC work in progress; (63)ECA Policy Brief (46)Official records. Supplement / Economic and Social Council (46)Note d’orientation de la CEA (35)Document Officiel  Supplément / Conseil Economique et Social (34)... View MoreHas File(s)Yes (40419)No (1780)\n\nReporting Suite\n\nMost Popular ItemsStatistics by CountryMost Popular Authors\n\nSearch\n\n\n\n\n\n\n\n\n\n\n\n\n\nAll of ECA IRAfrican Policy CentersCommunities and Collections developed on the BrowseOther Communities and Collections not in the Main Areas of WorkRegional Coordination Mechanism (RCM)TaxonomyWork programmes\n\n\n\n\nGo\n\n\n\n\n\n\n\n\n\n\n\n\n\n\nShow Advanced FiltersHide Advanced Filters\n\n\nFilters\n\nUse filters to refine the search results.\n\n\nLimit your search to items with or without files\nall itemsitems with filesitems without files\n\n\n\n\n\n\nResetAdd New FilterApply\n\n\n\n\n\n\n\n\n\n\n\n\n\n\n\n\n\n\n\n\n\n\n\n\n\n\n\n\n\n\n\n\n\nNow showing items 1-10 of 42199\n\n\n\n\n\nSort Options:\n\nRelevance\n\n\nTitle Asc\n\n\nTitle Desc\n\n\nIssue Date Asc\n\n\nIssue Date Desc\n\n\nResults Per Page:\n\n5\n\n\n10\n\n\n20\n\n\n40\n\n\n60\n\n\n80\n\n\n100\n\n\n\n\n\n\n\n\n\n\n\n\n\n\n\n\nThe evaluation report on multimodal transport sub-sector: the third and final evaluation report on the second United Nations Transport and Communication Decade in Africa (UNTACDA II) 1991-2000 \n\n\n\nUnited Nations. Economic Commission for Africa (2001-09)\nThe UNTACDA II sub-sectoral evaluation report in the field of Multimodal Transport (MT) has been prepared according to the revised terms of reference for preparation of modal reports. The content of various chapters are ...\n\n\n\n\n\n\n\n\n\n\n\nScaling-up the response to HIV/AIDS: building on lessons learnt from intensified responses to HIV/AIDS \n\n\n\nUnited Nations. Economic Commission for Africa (2000-12)\nThere is an urgent need to build on the lessons learned about HIV/AIDS prevention and care over the past two decades. The major challenge is how to develop successfully within the resource constraints facing African ...\n\n\n\n\n\n\n\n\n\n\n\nRapport de la réunion ad-hoc du groupe spécial d'experts pour l'examen des stratégies et politiques requises pour améliorer le processus de mise en œuvre de la privatisation en Afrique: \n\n\n\nNations Unies. Commission économique pour l'Afrique; Nations Unies. Conseil Economique et Social (1999-11)\nLa réunion du Groupe spécial d’experts organisé par la Commission économique pour l’Afrique sur l’examen des stratégies et politiques requises pour améliorer le processus de mise en œuvre de la privatisation en Afrique se ...\n\n\n\n\n\n\n\n\n\n\n\nRestructuring and privatization of public enterprises \n\n\n\nUnited Nations. Economic Commission for Africa. (1993-03)\nThere is agreement among policy-makers, experts, and practitioners that the public enterprise sector has in general not performed according to the expectations which were vested into it. The low efficiency of the public ...\n\n\n\n\n\n\n\n\n\n\n\nReport to the twelfth meeting of the Conference of African Ministres of Industry \n\n\n\nUnited National Industrial Development Organization; United Nations. Economic Commission for Africa (1995-06)\nThe twelfth meeting of the Conference of African Ministers of Industry, jointly organized by the United Nations Economic Commission for Africa (EGA) and the United Nations Industrial Development Organization (UNIDO), in ...\n\n\n\n\n\n\n\n\n\n\n\nInternational legal instruments relevant to women \n\n\n\nUnited Nations. Economic Commission for Africa. African Centre for Women (1995-06)\nThe principal purpose for publishing this document is to enhance the awareness and enlightenment of women and policy makers with regard to the basic legal rights of women and the existing international legal instruments ...\n\n\n\n\n\n\n\n\n\n\n\nSouthern Africa Sub-regional Development Center : Lusaka, Zambia \n\n\n\nUnited Nations. Economic Commission for Africa (1997-07)\nThis is the second issue of the Southern Africa Development Bulletin published by the Sub-Regional Development Center of the United Nations Economic Commission for Africa for Southern Africa. The first issue was published ...\n\n\n\n\n\n\n\n\n\n\n\nGender mainstreaming at ECA : review of the past present and future \n\n\n\nUnited Nations. Economic Commission for Africa. African Centre for Women (1996-05)\nThe Vision statement provides the framework for the development of the 1998 - 2001 Medium-term Plan, designed to increase the impact of the organization's work priorities by sharpening the focus of its programs. In this ...\n\n\n\n\n\n\n\n\n\n\n\nSome aspects of family planning programmes and fertility in selected ECA member states \n\n\n\nUnited Nations. Economic Commission for Africa. Population Division. Planning and Policies Section. (1985-03)\nRapid population growth has become an increasingly important concern to governments in the ECA member States. The estimated regional population growth rate was 3.1 per cent per annum for the 1980-85 quinquennium.Among the ...\n\n\n\n\n\n\n\n\n\n\n\nApplication of science and technology in Agro-industry \n\n\n\nUnited Nations. Economic Commission for Africa; Food Security and Sustainable Develoment Division (FSSDD) (1999-12)\nAgro-industries are usually the first to be established in modern manufacturing sector of a developing economy where agriculture has been the mainstay of the economy. Moreover, food processing has a stimulating effect on ...\n\n\n\n\n\n\n\n\n\n\n\n1\n\n\n2\n\n\n3\n\n\n4\n\n\n. . .\n\n\n4220\n\n\n\n\n\n\n\n\n\n\n\n\n\n\n\n\n\nBrowse\n\nAll of ECA IRCommunities & CollectionsTitleAuthorSubjectBy Issue DateECA Conference ProceedingsFlagship PublicationHas File(s)SpeechesPress ReleasesResolutionsBest Practices\n\nMy Account\n\nMy AccountRegister\n\n\n\nDiscover\n\nAuthorLopes, Carlos (267)Amoako, K.Y. (243)Janneh, Abdoulie (182)Adedeji, Adebayo (110)K.Y., Amoako (103)... View MoreSubjectAFRICA (8418)AFRIQUE (8300)ECONOMIC DEVELOPMENT (3210)DEVELOPPEMENT ECONOMIQUE (3196)WORK PROGRAMME (3188)... View MoreDate2020 - 2025 (4226)2010 - 2019 (8389)2000 - 2009 (4756)1990 - 1999 (6763)1980 - 1989 (6868)1970 - 1979 (5157)1960 - 1969 (5588)1958 - 1959 (110)ECA Conference ProceedingsSessions of the Commission (4479)Conferences of African Ministers (1920)Conferences on Statistical Development (1521)Conferences on Trade, Regional Cooperation and Integration (693)Preparatory Committees (668)... View MoreFlagship PublicationCountry profiles (134)Economic Report on Africa (72)ECA Journals (22)Assessing Regional Integration in Africa (20)Africa’s quarterly economic performance and outlook (19)... View MoreECA Media Format9 p. : ill, (1)TypeConference document (14249)Reports (10399)Press release (7206)Working paper (2862)Speech (1751)Technical paper (927)Briefing paper (580)Book (549)Policy paper (429)Resolutions and decisions (376)... View MoreSeriesPress Release (611)Communiqué de presse. (383)Speech (336)COVID-19 Situation Report: (305)COVID-19 Situation Report : (208)ATPC work in progress; (63)ECA Policy Brief (46)Official records. Supplement / Economic and Social Council (46)Note d’orientation de la CEA (35)Document Officiel  Supplément / Conseil Economique et Social (34)... View MoreHas File(s)Yes (40419)No (1780)\n\nReporting Suite\n\nMost Popular ItemsStatistics by CountryMost Popular Authors\n\nSearch\n\n\n\n\n\n\n\n\n\n\n\n\n\nAll of ECA IRAfrican Policy CentersCommunities and Collections developed on the BrowseOther Communities and Collections not in the Main Areas of WorkRegional Coordination Mechanism (RCM)TaxonomyWork programmes\n\n\n\n\nGo\n\n\n\n\n\n\n\n\n\n\n\n\n\n\nShow Advanced FiltersHide Advanced Filters\n\n\nFilters\n\nUse filters to refine the search results.\n\n\nLimit your search to items with or without files\nall itemsitems with filesitems without files\n\n\n\n\n\n\nResetAdd New FilterApply\n\n\n\n\n\n\n\n\n\n\n\n\n\n\n\n\n\n\n\n\n\n\n\n\n\n\n\n\n\n\n\n\n\nNow showing items 1-10 of 42199\n\n\n\n\n\nSort Options:\n\nRelevance\n\n\nTitle Asc\n\n\nTitle Desc\n\n\nIssue Date Asc\n\n\nIssue Date Desc\n\n\nResults Per Page:\n\n5\n\n\n10\n\n\n20\n\n\n40\n\n\n60\n\n\n80\n\n\n100\n\n\n\n\n\n\n\n\n\n\n\n\n\n\n\n\nThe evaluation report on multimodal transport sub-sector: the third and final evaluation report on the second United Nations Transport and Communication Decade in Africa (UNTACDA II) 1991-2000 \n\n\n\nUnited Nations. Economic Commission for Africa (2001-09)\nThe UNTACDA II sub-sectoral evaluation report in the field of Multimodal Transport (MT) has been prepared according to the revised terms of reference for preparation of modal reports. The content of various chapters are ...\n\n\n\n\n\n\n\n\n\n\n\nScaling-up the response to HIV/AIDS: building on lessons learnt from intensified responses to HIV/AIDS \n\n\n\nUnited Nations. Economic Commission for Africa (2000-12)\nThere is an urgent need to build on the lessons learned about HIV/AIDS prevention and care over the past two decades. The major challenge is how to develop successfully within the resource constraints facing African ...\n\n\n\n\n\n\n\n\n\n\n\nRapport de la réunion ad-hoc du groupe spécial d'experts pour l'examen des stratégies et politiques requises pour améliorer le processus de mise en œuvre de la privatisation en Afrique: \n\n\n\nNations Unies. Commission économique pour l'Afrique; Nations Unies. Conseil Economique et Social (1999-11)\nLa réunion du Groupe spécial d’experts organisé par la Commission économique pour l’Afrique sur l’examen des stratégies et politiques requises pour améliorer le processus de mise en œuvre de la privatisation en Afrique se ...\n\n\n\n\n\n\n\n\n\n\n\nRestructuring and privatization of public enterprises \n\n\n\nUnited Nations. Economic Commission for Africa. (1993-03)\nThere is agreement among policy-makers, experts, and practitioners that the public enterprise sector has in general not performed according to the expectations which were vested into it. The low efficiency of the public ...\n\n\n\n\n\n\n\n\n\n\n\nReport to the twelfth meeting of the Conference of African Ministres of Industry \n\n\n\nUnited National Industrial Development Organization; United Nations. Economic Commission for Africa (1995-06)\nThe twelfth meeting of the Conference of African Ministers of Industry, jointly organized by the United Nations Economic Commission for Africa (EGA) and the United Nations Industrial Development Organization (UNIDO), in ...\n\n\n\n\n\n\n\n\n\n\n\nInternational legal instruments relevant to women \n\n\n\nUnited Nations. Economic Commission for Africa. African Centre for Women (1995-06)\nThe principal purpose for publishing this document is to enhance the awareness and enlightenment of women and policy makers with regard to the basic legal rights of women and the existing international legal instruments ...\n\n\n\n\n\n\n\n\n\n\n\nSouthern Africa Sub-regional Development Center : Lusaka, Zambia \n\n\n\nUnited Nations. Economic Commission for Africa (1997-07)\nThis is the second issue of the Southern Africa Development Bulletin published by the Sub-Regional Development Center of the United Nations Economic Commission for Africa for Southern Africa. The first issue was published ...\n\n\n\n\n\n\n\n\n\n\n\nGender mainstreaming at ECA : review of the past present and future \n\n\n\nUnited Nations. Economic Commission for Africa. African Centre for Women (1996-05)\nThe Vision statement provides the framework for the development of the 1998 - 2001 Medium-term Plan, designed to increase the impact of the organization's work priorities by sharpening the focus of its programs. In this ...\n\n\n\n\n\n\n\n\n\n\n\nSome aspects of family planning programmes and fertility in selected ECA member states \n\n\n\nUnited Nations. Economic Commission for Africa. Population Division. Planning and Policies Section. (1985-03)\nRapid population growth has become an increasingly important concern to governments in the ECA member States. The estimated regional population growth rate was 3.1 per cent per annum for the 1980-85 quinquennium.Among the ...\n\n\n\n\n\n\n\n\n\n\n\nApplication of science and technology in Agro-industry \n\n\n\nUnited Nations. Economic Commission for Africa; Food Security and Sustainable Develoment Division (FSSDD) (1999-12)\nAgro-industries are usually the first to be established in modern manufacturing sector of a developing economy where agriculture has been the mainstay of the economy. Moreover, food processing has a stimulating effect on ...\n\n\n\n\n\n\n\n\n\n\n\n1\n\n\n2\n\n\n3\n\n\n4\n\n\n. . .\n\n\n4220\n\n\n\n\n\n\n\n\n\n\n\n\n\n\n\n\n\nBrowse\n\nAll of ECA IRCommunities & CollectionsTitleAuthorSubjectBy Issue DateECA Conference ProceedingsFlagship PublicationHas File(s)SpeechesPress ReleasesResolutionsBest Practices\n\nMy Account\n\nMy AccountRegister\n\n\n\nDiscover\n\nAuthorLopes, Carlos (267)Amoako, K.Y. (243)Janneh, Abdoulie (182)Adedeji, Adebayo (110)K.Y., Amoako (103)... View MoreSubjectAFRICA (8418)AFRIQUE (8300)ECONOMIC DEVELOPMENT (3210)DEVELOPPEMENT ECONOMIQUE (3196)WORK PROGRAMME (3188)... View MoreDate2020 - 2025 (4226)2010 - 2019 (8389)2000 - 2009 (4756)1990 - 1999 (6763)1980 - 1989 (6868)1970 - 1979 (5157)1960 - 1969 (5588)1958 - 1959 (110)ECA Conference ProceedingsSessions of the Commission (4479)Conferences of African Ministers (1920)Conferences on Statistical Development (1521)Conferences on Trade, Regional Cooperation and Integration (693)Preparatory Committees (668)... View MoreFlagship PublicationCountry profiles (134)Economic Report on Africa (72)ECA Journals (22)Assessing Regional Integration in Africa (20)Africa’s quarterly economic performance and outlook (19)... View MoreECA Media Format9 p. : ill, (1)TypeConference document (14249)Reports (10399)Press release (7206)Working paper (2862)Speech (1751)Technical paper (927)Briefing paper (580)Book (549)Policy paper (429)Resolutions and decisions (376)... View MoreSeriesPress Release (611)Communiqué de presse. (383)Speech (336)COVID-19 Situation Report: (305)COVID-19 Situation Report : (208)ATPC work in progress; (63)ECA Policy Brief (46)Official records. Supplement / Economic and Social Council (46)Note d’orientation de la CEA (35)Document Officiel  Supplément / Conseil Economique et Social (34)... View MoreHas File(s)Yes (40419)No (1780)\n\nReporting Suite\n\nMost Popular ItemsStatistics by CountryMost Popular Authors\n\nSearch\n\n\n\n\n\n\n\n\n\n\n\n\n\nAll of ECA IRAfrican Policy CentersCommunities and Collections developed on the BrowseOther Communities and Collections not in the Main Areas of WorkRegional Coordination Mechanism (RCM)TaxonomyWork programmes\n\n\n\n\nGo\n\n\n\n\n\n\n\n\n\n\n\n\n\n\nShow Advanced FiltersHide Advanced Filters\n\n\nFilters\n\nUse filters to refine the search results.\n\n\nLimit your search to items with or without files\nall itemsitems with filesitems without files\n\n\n\n\n\n\nResetAdd New FilterApply\n\n\n\n\n\n\n\n\n\n\n\n\n\n\n\n\n\n\n\n\n\n\n\n\n\n\n\n\n\n\n\n\n\nNow showing items 1-10 of 42199\n\n\n\n\n\nSort Options:\n\nRelevance\n\n\nTitle Asc\n\n\nTitle Desc\n\n\nIssue Date Asc\n\n\nIssue Date Desc\n\n\nResults Per Page:\n\n5\n\n\n10\n\n\n20\n\n\n40\n\n\n60\n\n\n80\n\n\n100\n\n\n\n\n\n\n\n\n\n\n\n\n\n\n\n\nThe evaluation report on multimodal transport sub-sector: the third and final evaluation report on the second United Nations Transport and Communication Decade in Africa (UNTACDA II) 1991-2000 \n\n\n\nUnited Nations. Economic Commission for Africa (2001-09)\nThe UNTACDA II sub-sectoral evaluation report in the field of Multimodal Transport (MT) has been prepared according to the revised terms of reference for preparation of modal reports. The content of various chapters are ...\n\n\n\n\n\n\n\n\n\n\n\nScaling-up the response to HIV/AIDS: building on lessons learnt from intensified responses to HIV/AIDS \n\n\n\nUnited Nations. Economic Commission for Africa (2000-12)\nThere is an urgent need to build on the lessons learned about HIV/AIDS prevention and care over the past two decades. The major challenge is how to develop successfully within the resource constraints facing African ...\n\n\n\n\n\n\n\n\n\n\n\nRapport de la réunion ad-hoc du groupe spécial d'experts pour l'examen des stratégies et politiques requises pour améliorer le processus de mise en œuvre de la privatisation en Afrique: \n\n\n\nNations Unies. Commission économique pour l'Afrique; Nations Unies. Conseil Economique et Social (1999-11)\nLa réunion du Groupe spécial d’experts organisé par la Commission économique pour l’Afrique sur l’examen des stratégies et politiques requises pour améliorer le processus de mise en œuvre de la privatisation en Afrique se ...\n\n\n\n\n\n\n\n\n\n\n\nRestructuring and privatization of public enterprises \n\n\n\nUnited Nations. Economic Commission for Africa. (1993-03)\nThere is agreement among policy-makers, experts, and practitioners that the public enterprise sector has in general not performed according to the expectations which were vested into it. The low efficiency of the public ...\n\n\n\n\n\n\n\n\n\n\n\nReport to the twelfth meeting of the Conference of African Ministres of Industry \n\n\n\nUnited National Industrial Development Organization; United Nations. Economic Commission for Africa (1995-06)\nThe twelfth meeting of the Conference of African Ministers of Industry, jointly organized by the United Nations Economic Commission for Africa (EGA) and the United Nations Industrial Development Organization (UNIDO), in ...\n\n\n\n\n\n\n\n\n\n\n\nInternational legal instruments relevant to women \n\n\n\nUnited Nations. Economic Commission for Africa. African Centre for Women (1995-06)\nThe principal purpose for publishing this document is to enhance the awareness and enlightenment of women and policy makers with regard to the basic legal rights of women and the existing international legal instruments ...\n\n\n\n\n\n\n\n\n\n\n\nSouthern Africa Sub-regional Development Center : Lusaka, Zambia \n\n\n\nUnited Nations. Economic Commission for Africa (1997-07)\nThis is the second issue of the Southern Africa Development Bulletin published by the Sub-Regional Development Center of the United Nations Economic Commission for Africa for Southern Africa. The first issue was published ...\n\n\n\n\n\n\n\n\n\n\n\nGender mainstreaming at ECA : review of the past present and future \n\n\n\nUnited Nations. Economic Commission for Africa. African Centre for Women (1996-05)\nThe Vision statement provides the framework for the development of the 1998 - 2001 Medium-term Plan, designed to increase the impact of the organization's work priorities by sharpening the focus of its programs. In this ...\n\n\n\n\n\n\n\n\n\n\n\nSome aspects of family planning programmes and fertility in selected ECA member states \n\n\n\nUnited Nations. Economic Commission for Africa. Population Division. Planning and Policies Section. (1985-03)\nRapid population growth has become an increasingly important concern to governments in the ECA member States. The estimated regional population growth rate was 3.1 per cent per annum for the 1980-85 quinquennium.Among the ...\n\n\n\n\n\n\n\n\n\n\n\nApplication of science and technology in Agro-industry \n\n\n\nUnited Nations. Economic Commission for Africa; Food Security and Sustainable Develoment Division (FSSDD) (1999-12)\nAgro-industries are usually the first to be established in modern manufacturing sector of a developing economy where agriculture has been the mainstay of the economy. Moreover, food processing has a stimulating effect on ...\n\n\n\n\n\n\n\n\n\n\n\n1\n\n\n2\n\n\n3\n\n\n4\n\n\n. . .\n\n\n4220\n\nSearch\n\n\n\n\n\n\n\n\n\n\n\n\n\nAll of ECA IRAfrican Policy CentersCommunities and Collections developed on the BrowseOther Communities and Collections not in the Main Areas of WorkRegional Coordination Mechanism (RCM)TaxonomyWork programmes\n\n\n\n\nGo\n\n\n\n\n\n\n\n\n\n\n\n\n\n\nShow Advanced FiltersHide Advanced Filters\n\n\nFilters\n\nUse filters to refine the search results.\n\n\nLimit your search to items with or without files\nall itemsitems with filesitems without files\n\n\n\n\n\n\nResetAdd New FilterApply\n\n\n\n\n\n\n\n\n\n\n\n\n\n\n\n\n\n\n\n\n\n\n\n\n\n\n\n\n\n\n\n\n\nNow showing items 1-10 of 42199\n\n\n\n\n\nSort Options:\n\nRelevance\n\n\nTitle Asc\n\n\nTitle Desc\n\n\nIssue Date Asc\n\n\nIssue Date Desc\n\n\nResults Per Page:\n\n5\n\n\n10\n\n\n20\n\n\n40\n\n\n60\n\n\n80\n\n\n100\n\n\n\n\n\n\n\n\n\n\n\n\n\n\n\n\nThe evaluation report on multimodal transport sub-sector: the third and final evaluation report on the second United Nations Transport and Communication Decade in Africa (UNTACDA II) 1991-2000 \n\n\n\nUnited Nations. Economic Commission for Africa (2001-09)\nThe UNTACDA II sub-sectoral evaluation report in the field of Multimodal Transport (MT) has been prepared according to the revised terms of reference for preparation of modal reports. The content of various chapters are ...\n\n\n\n\n\n\n\n\n\n\n\nScaling-up the response to HIV/AIDS: building on lessons learnt from intensified responses to HIV/AIDS \n\n\n\nUnited Nations. Economic Commission for Africa (2000-12)\nThere is an urgent need to build on the lessons learned about HIV/AIDS prevention and care over the past two decades. The major challenge is how to develop successfully within the resource constraints facing African ...\n\n\n\n\n\n\n\n\n\n\n\nRapport de la réunion ad-hoc du groupe spécial d'experts pour l'examen des stratégies et politiques requises pour améliorer le processus de mise en œuvre de la privatisation en Afrique: \n\n\n\nNations Unies. Commission économique pour l'Afrique; Nations Unies. Conseil Economique et Social (1999-11)\nLa réunion du Groupe spécial d’experts organisé par la Commission économique pour l’Afrique sur l’examen des stratégies et politiques requises pour améliorer le processus de mise en œuvre de la privatisation en Afrique se ...\n\n\n\n\n\n\n\n\n\n\n\nRestructuring and privatization of public enterprises \n\n\n\nUnited Nations. Economic Commission for Africa. (1993-03)\nThere is agreement among policy-makers, experts, and practitioners that the public enterprise sector has in general not performed according to the expectations which were vested into it. The low efficiency of the public ...\n\n\n\n\n\n\n\n\n\n\n\nReport to the twelfth meeting of the Conference of African Ministres of Industry \n\n\n\nUnited National Industrial Development Organization; United Nations. Economic Commission for Africa (1995-06)\nThe twelfth meeting of the Conference of African Ministers of Industry, jointly organized by the United Nations Economic Commission for Africa (EGA) and the United Nations Industrial Development Organization (UNIDO), in ...\n\n\n\n\n\n\n\n\n\n\n\nInternational legal instruments relevant to women \n\n\n\nUnited Nations. Economic Commission for Africa. African Centre for Women (1995-06)\nThe principal purpose for publishing this document is to enhance the awareness and enlightenment of women and policy makers with regard to the basic legal rights of women and the existing international legal instruments ...\n\n\n\n\n\n\n\n\n\n\n\nSouthern Africa Sub-regional Development Center : Lusaka, Zambia \n\n\n\nUnited Nations. Economic Commission for Africa (1997-07)\nThis is the second issue of the Southern Africa Development Bulletin published by the Sub-Regional Development Center of the United Nations Economic Commission for Africa for Southern Africa. The first issue was published ...\n\n\n\n\n\n\n\n\n\n\n\nGender mainstreaming at ECA : review of the past present and future \n\n\n\nUnited Nations. Economic Commission for Africa. African Centre for Women (1996-05)\nThe Vision statement provides the framework for the development of the 1998 - 2001 Medium-term Plan, designed to increase the impact of the organization's work priorities by sharpening the focus of its programs. In this ...\n\n\n\n\n\n\n\n\n\n\n\nSome aspects of family planning programmes and fertility in selected ECA member states \n\n\n\nUnited Nations. Economic Commission for Africa. Population Division. Planning and Policies Section. (1985-03)\nRapid population growth has become an increasingly important concern to governments in the ECA member States. The estimated regional population growth rate was 3.1 per cent per annum for the 1980-85 quinquennium.Among the ...\n\n\n\n\n\n\n\n\n\n\n\nApplication of science and technology in Agro-industry \n\n\n\nUnited Nations. Economic Commission for Africa; Food Security and Sustainable Develoment Division (FSSDD) (1999-12)\nAgro-industries are usually the first to be established in modern manufacturing sector of a developing economy where agriculture has been the mainstay of the economy. Moreover, food processing has a stimulating effect on ...\n\n\n\n\n\n\n\n\n\n\n\n1\n\n\n2\n\n\n3\n\n\n4\n\n\n. . .\n\n\n4220\n\nAll of ECA IRAfrican Policy CentersCommunities and Collections developed on the BrowseOther Communities and Collections not in the Main Areas of WorkRegional Coordination Mechanism (RCM)TaxonomyWork programmes\n\n\n\n\nGo\n\n\n\n\n\n\n\n\n\n\n\n\n\n\nShow Advanced FiltersHide Advanced Filters\n\n\nFilters\n\nUse filters to refine the search results.\n\n\nLimit your search to items with or without files\nall itemsitems with filesitems without files\n\n\n\n\n\n\nResetAdd New FilterApply\n\n\n\n\n\n\n\n\n\n\n\n\n\n\n\n\n\n\n\n\n\n\n\n\n\n\n\n\n\n\n\n\n\nNow showing items 1-10 of 42199\n\n\n\n\n\nSort Options:\n\nRelevance\n\n\nTitle Asc\n\n\nTitle Desc\n\n\nIssue Date Asc\n\n\nIssue Date Desc\n\n\nResults Per Page:\n\n5\n\n\n10\n\n\n20\n\n\n40\n\n\n60\n\n\n80\n\n\n100\n\n\n\n\n\n\n\n\n\n\n\n\n\n\n\n\nThe evaluation report on multimodal transport sub-sector: the third and final evaluation report on the second United Nations Transport and Communication Decade in Africa (UNTACDA II) 1991-2000 \n\n\n\nUnited Nations. Economic Commission for Africa (2001-09)\nThe UNTACDA II sub-sectoral evaluation report in the field of Multimodal Transport (MT) has been prepared according to the revised terms of reference for preparation of modal reports. The content of various chapters are ...\n\n\n\n\n\n\n\n\n\n\n\nScaling-up the response to HIV/AIDS: building on lessons learnt from intensified responses to HIV/AIDS \n\n\n\nUnited Nations. Economic Commission for Africa (2000-12)\nThere is an urgent need to build on the lessons learned about HIV/AIDS prevention and care over the past two decades. The major challenge is how to develop successfully within the resource constraints facing African ...\n\n\n\n\n\n\n\n\n\n\n\nRapport de la réunion ad-hoc du groupe spécial d'experts pour l'examen des stratégies et politiques requises pour améliorer le processus de mise en œuvre de la privatisation en Afrique: \n\n\n\nNations Unies. Commission économique pour l'Afrique; Nations Unies. Conseil Economique et Social (1999-11)\nLa réunion du Groupe spécial d’experts organisé par la Commission économique pour l’Afrique sur l’examen des stratégies et politiques requises pour améliorer le processus de mise en œuvre de la privatisation en Afrique se ...\n\n\n\n\n\n\n\n\n\n\n\nRestructuring and privatization of public enterprises \n\n\n\nUnited Nations. Economic Commission for Africa. (1993-03)\nThere is agreement among policy-makers, experts, and practitioners that the public enterprise sector has in general not performed according to the expectations which were vested into it. The low efficiency of the public ...\n\n\n\n\n\n\n\n\n\n\n\nReport to the twelfth meeting of the Conference of African Ministres of Industry \n\n\n\nUnited National Industrial Development Organization; United Nations. Economic Commission for Africa (1995-06)\nThe twelfth meeting of the Conference of African Ministers of Industry, jointly organized by the United Nations Economic Commission for Africa (EGA) and the United Nations Industrial Development Organization (UNIDO), in ...\n\n\n\n\n\n\n\n\n\n\n\nInternational legal instruments relevant to women \n\n\n\nUnited Nations. Economic Commission for Africa. African Centre for Women (1995-06)\nThe principal purpose for publishing this document is to enhance the awareness and enlightenment of women and policy makers with regard to the basic legal rights of women and the existing international legal instruments ...\n\n\n\n\n\n\n\n\n\n\n\nSouthern Africa Sub-regional Development Center : Lusaka, Zambia \n\n\n\nUnited Nations. Economic Commission for Africa (1997-07)\nThis is the second issue of the Southern Africa Development Bulletin published by the Sub-Regional Development Center of the United Nations Economic Commission for Africa for Southern Africa. The first issue was published ...\n\n\n\n\n\n\n\n\n\n\n\nGender mainstreaming at ECA : review of the past present and future \n\n\n\nUnited Nations. Economic Commission for Africa. African Centre for Women (1996-05)\nThe Vision statement provides the framework for the development of the 1998 - 2001 Medium-term Plan, designed to increase the impact of the organization's work priorities by sharpening the focus of its programs. In this ...\n\n\n\n\n\n\n\n\n\n\n\nSome aspects of family planning programmes and fertility in selected ECA member states \n\n\n\nUnited Nations. Economic Commission for Africa. Population Division. Planning and Policies Section. (1985-03)\nRapid population growth has become an increasingly important concern to governments in the ECA member States. The estimated regional population growth rate was 3.1 per cent per annum for the 1980-85 quinquennium.Among the ...\n\n\n\n\n\n\n\n\n\n\n\nApplication of science and technology in Agro-industry \n\n\n\nUnited Nations. Economic Commission for Africa; Food Security and Sustainable Develoment Division (FSSDD) (1999-12)\nAgro-industries are usually the first to be established in modern manufacturing sector of a developing economy where agriculture has been the mainstay of the economy. Moreover, food processing has a stimulating effect on ...\n\n\n\n\n\n\n\n\n\n\n\n1\n\n\n2\n\n\n3\n\n\n4\n\n\n. . .\n\n\n4220\n\nAll of ECA IRAfrican Policy CentersCommunities and Collections developed on the BrowseOther Communities and Collections not in the Main Areas of WorkRegional Coordination Mechanism (RCM)TaxonomyWork programmes\n\n\n\n\nGo\n\n\n\n\n\n\n\n\n\n\n\n\n\n\nShow Advanced FiltersHide Advanced Filters\n\n\nFilters\n\nUse filters to refine the search results.\n\n\nLimit your search to items with or without files\nall itemsitems with filesitems without files\n\n\n\n\n\n\nResetAdd New FilterApply\n\nAll of ECA IRAfrican Policy CentersCommunities and Collections developed on the BrowseOther Communities and Collections not in the Main Areas of WorkRegional Coordination Mechanism (RCM)TaxonomyWork programmes\n\n\n\n\nGo\n\nAll of ECA IRAfrican Policy CentersCommunities and Collections developed on the BrowseOther Communities and Collections not in the Main Areas of WorkRegional Coordination Mechanism (RCM)TaxonomyWork programmes\n\nAll of ECA IRAfrican Policy CentersCommunities and Collections developed on the BrowseOther Communities and Collections not in the Main Areas of WorkRegional Coordination Mechanism (RCM)TaxonomyWork programmes\n\nGo\n\nGo\n\nShow Advanced FiltersHide Advanced Filters\n\nShow Advanced FiltersHide Advanced Filters\n\nUse filters to refine the search results.\n\n\nLimit your search to items with or without files\nall itemsitems with filesitems without files\n\n\n\n\n\n\nResetAdd New FilterApply\n\nUse filters to refine the search results.\n\nLimit your search to items with or without files\nall itemsitems with filesitems without files\n\n\n\n\n\n\nResetAdd New FilterApply\n\nLimit your search to items with or without files\nall itemsitems with filesitems without files\n\nResetAdd New FilterApply\n\nResetAdd New FilterApply\n\nResetAdd New FilterApply\n\nNow showing items 1-10 of 42199\n\n\n\n\n\nSort Options:\n\nRelevance\n\n\nTitle Asc\n\n\nTitle Desc\n\n\nIssue Date Asc\n\n\nIssue Date Desc\n\n\nResults Per Page:\n\n5\n\n\n10\n\n\n20\n\n\n40\n\n\n60\n\n\n80\n\n\n100\n\nNow showing items 1-10 of 42199\n\n\n\n\n\nSort Options:\n\nRelevance\n\n\nTitle Asc\n\n\nTitle Desc\n\n\nIssue Date Asc\n\n\nIssue Date Desc\n\n\nResults Per Page:\n\n5\n\n\n10\n\n\n20\n\n\n40\n\n\n60\n\n\n80\n\n\n100\n\nNow showing items 1-10 of 42199\n\nNow showing items 1-10 of 42199\n\nSort Options:\n\nRelevance\n\n\nTitle Asc\n\n\nTitle Desc\n\n\nIssue Date Asc\n\n\nIssue Date Desc\n\n\nResults Per Page:\n\n5\n\n\n10\n\n\n20\n\n\n40\n\n\n60\n\n\n80\n\n\n100\n\nSort Options:\n\nRelevance\n\n\nTitle Asc\n\n\nTitle Desc\n\n\nIssue Date Asc\n\n\nIssue Date Desc\n\n\nResults Per Page:\n\n5\n\n\n10\n\n\n20\n\n\n40\n\n\n60\n\n\n80\n\n\n100\n\nThe evaluation report on multimodal transport sub-sector: the third and final evaluation report on the second United Nations Transport and Communication Decade in Africa (UNTACDA II) 1991-2000 \n\n\n\nUnited Nations. Economic Commission for Africa (2001-09)\nThe UNTACDA II sub-sectoral evaluation report in the field of Multimodal Transport (MT) has been prepared according to the revised terms of reference for preparation of modal reports. The content of various chapters are ...\n\n\n\n\n\n\n\n\n\n\n\nScaling-up the response to HIV/AIDS: building on lessons learnt from intensified responses to HIV/AIDS \n\n\n\nUnited Nations. Economic Commission for Africa (2000-12)\nThere is an urgent need to build on the lessons learned about HIV/AIDS prevention and care over the past two decades. The major challenge is how to develop successfully within the resource constraints facing African ...\n\n\n\n\n\n\n\n\n\n\n\nRapport de la réunion ad-hoc du groupe spécial d'experts pour l'examen des stratégies et politiques requises pour améliorer le processus de mise en œuvre de la privatisation en Afrique: \n\n\n\nNations Unies. Commission économique pour l'Afrique; Nations Unies. Conseil Economique et Social (1999-11)\nLa réunion du Groupe spécial d’experts organisé par la Commission économique pour l’Afrique sur l’examen des stratégies et politiques requises pour améliorer le processus de mise en œuvre de la privatisation en Afrique se ...\n\n\n\n\n\n\n\n\n\n\n\nRestructuring and privatization of public enterprises \n\n\n\nUnited Nations. Economic Commission for Africa. (1993-03)\nThere is agreement among policy-makers, experts, and practitioners that the public enterprise sector has in general not performed according to the expectations which were vested into it. The low efficiency of the public ...\n\n\n\n\n\n\n\n\n\n\n\nReport to the twelfth meeting of the Conference of African Ministres of Industry \n\n\n\nUnited National Industrial Development Organization; United Nations. Economic Commission for Africa (1995-06)\nThe twelfth meeting of the Conference of African Ministers of Industry, jointly organized by the United Nations Economic Commission for Africa (EGA) and the United Nations Industrial Development Organization (UNIDO), in ...\n\n\n\n\n\n\n\n\n\n\n\nInternational legal instruments relevant to women \n\n\n\nUnited Nations. Economic Commission for Africa. African Centre for Women (1995-06)\nThe principal purpose for publishing this document is to enhance the awareness and enlightenment of women and policy makers with regard to the basic legal rights of women and the existing international legal instruments ...\n\n\n\n\n\n\n\n\n\n\n\nSouthern Africa Sub-regional Development Center : Lusaka, Zambia \n\n\n\nUnited Nations. Economic Commission for Africa (1997-07)\nThis is the second issue of the Southern Africa Development Bulletin published by the Sub-Regional Development Center of the United Nations Economic Commission for Africa for Southern Africa. The first issue was published ...\n\n\n\n\n\n\n\n\n\n\n\nGender mainstreaming at ECA : review of the past present and future \n\n\n\nUnited Nations. Economic Commission for Africa. African Centre for Women (1996-05)\nThe Vision statement provides the framework for the development of the 1998 - 2001 Medium-term Plan, designed to increase the impact of the organization's work priorities by sharpening the focus of its programs. In this ...\n\n\n\n\n\n\n\n\n\n\n\nSome aspects of family planning programmes and fertility in selected ECA member states \n\n\n\nUnited Nations. Economic Commission for Africa. Population Division. Planning and Policies Section. (1985-03)\nRapid population growth has become an increasingly important concern to governments in the ECA member States. The estimated regional population growth rate was 3.1 per cent per annum for the 1980-85 quinquennium.Among the ...\n\n\n\n\n\n\n\n\n\n\n\nApplication of science and technology in Agro-industry \n\n\n\nUnited Nations. Economic Commission for Africa; Food Security and Sustainable Develoment Division (FSSDD) (1999-12)\nAgro-industries are usually the first to be established in modern manufacturing sector of a developing economy where agriculture has been the mainstay of the economy. Moreover, food processing has a stimulating effect on ...\n\nThe evaluation report on multimodal transport sub-sector: the third and final evaluation report on the second United Nations Transport and Communication Decade in Africa (UNTACDA II) 1991-2000 \n\n\n\nUnited Nations. Economic Commission for Africa (2001-09)\nThe UNTACDA II sub-sectoral evaluation report in the field of Multimodal Transport (MT) has been prepared according to the revised terms of reference for preparation of modal reports. The content of various chapters are ...\n\nThe evaluation report on multimodal transport sub-sector: the third and final evaluation report on the second United Nations Transport and Communication Decade in Africa (UNTACDA II) 1991-2000 \n\n\n\nUnited Nations. Economic Commission for Africa (2001-09)\nThe UNTACDA II sub-sectoral evaluation report in the field of Multimodal Transport (MT) has been prepared according to the revised terms of reference for preparation of modal reports. The content of various chapters are ...\n\nUnited Nations. Economic Commission for Africa (2001-09)\nThe UNTACDA II sub-sectoral evaluation report in the field of Multimodal Transport (MT) has been prepared according to the revised terms of reference for preparation of modal reports. The content of various chapters are ...\n\nThe UNTACDA II sub-sectoral evaluation report in the field of Multimodal Transport (MT) has been prepared according to the revised terms of reference for preparation of modal reports. The content of various chapters are ...\n\nScaling-up the response to HIV/AIDS: building on lessons learnt from intensified responses to HIV/AIDS \n\n\n\nUnited Nations. Economic Commission for Africa (2000-12)\nThere is an urgent need to build on the lessons learned about HIV/AIDS prevention and care over the past two decades. The major challenge is how to develop successfully within the resource constraints facing African ...\n\nScaling-up the response to HIV/AIDS: building on lessons learnt from intensified responses to HIV/AIDS \n\n\n\nUnited Nations. Economic Commission for Africa (2000-12)\nThere is an urgent need to build on the lessons learned about HIV/AIDS prevention and care over the past two decades. The major challenge is how to develop successfully within the resource constraints facing African ...\n\nUnited Nations. Economic Commission for Africa (2000-12)\nThere is an urgent need to build on the lessons learned about HIV/AIDS prevention and care over the past two decades. The major challenge is how to develop successfully within the resource constraints facing African ...\n\nThere is an urgent need to build on the lessons learned about HIV/AIDS prevention and care over the past two decades. The major challenge is how to develop successfully within the resource constraints facing African ...\n\nRapport de la réunion ad-hoc du groupe spécial d'experts pour l'examen des stratégies et politiques requises pour améliorer le processus de mise en œuvre de la privatisation en Afrique: \n\n\n\nNations Unies. Commission économique pour l'Afrique; Nations Unies. Conseil Economique et Social (1999-11)\nLa réunion du Groupe spécial d’experts organisé par la Commission économique pour l’Afrique sur l’examen des stratégies et politiques requises pour améliorer le processus de mise en œuvre de la privatisation en Afrique se ...\n\nRapport de la réunion ad-hoc du groupe spécial d'experts pour l'examen des stratégies et politiques requises pour améliorer le processus de mise en œuvre de la privatisation en Afrique: \n\n\n\nNations Unies. Commission économique pour l'Afrique; Nations Unies. Conseil Economique et Social (1999-11)\nLa réunion du Groupe spécial d’experts organisé par la Commission économique pour l’Afrique sur l’examen des stratégies et politiques requises pour améliorer le processus de mise en œuvre de la privatisation en Afrique se ...\n\nNations Unies. Commission économique pour l'Afrique; Nations Unies. Conseil Economique et Social (1999-11)\nLa réunion du Groupe spécial d’experts organisé par la Commission économique pour l’Afrique sur l’examen des stratégies et politiques requises pour améliorer le processus de mise en œuvre de la privatisation en Afrique se ...\n\nLa réunion du Groupe spécial d’experts organisé par la Commission économique pour l’Afrique sur l’examen des stratégies et politiques requises pour améliorer le processus de mise en œuvre de la privatisation en Afrique se ...\n\nRestructuring and privatization of public enterprises \n\n\n\nUnited Nations. Economic Commission for Africa. (1993-03)\nThere is agreement among policy-makers, experts, and practitioners that the public enterprise sector has in general not performed according to the expectations which were vested into it. The low efficiency of the public ...\n\nRestructuring and privatization of public enterprises \n\n\n\nUnited Nations. Economic Commission for Africa. (1993-03)\nThere is agreement among policy-makers, experts, and practitioners that the public enterprise sector has in general not performed according to the expectations which were vested into it. The low efficiency of the public ...\n\nUnited Nations. Economic Commission for Africa. (1993-03)\nThere is agreement among policy-makers, experts, and practitioners that the public enterprise sector has in general not performed according to the expectations which were vested into it. The low efficiency of the public ...\n\nThere is agreement among policy-makers, experts, and practitioners that the public enterprise sector has in general not performed according to the expectations which were vested into it. The low efficiency of the public ...\n\nReport to the twelfth meeting of the Conference of African Ministres of Industry \n\n\n\nUnited National Industrial Development Organization; United Nations. Economic Commission for Africa (1995-06)\nThe twelfth meeting of the Conference of African Ministers of Industry, jointly organized by the United Nations Economic Commission for Africa (EGA) and the United Nations Industrial Development Organization (UNIDO), in ...\n\nReport to the twelfth meeting of the Conference of African Ministres of Industry \n\n\n\nUnited National Industrial Development Organization; United Nations. Economic Commission for Africa (1995-06)\nThe twelfth meeting of the Conference of African Ministers of Industry, jointly organized by the United Nations Economic Commission for Africa (EGA) and the United Nations Industrial Development Organization (UNIDO), in ...\n\nUnited National Industrial Development Organization; United Nations. Economic Commission for Africa (1995-06)\nThe twelfth meeting of the Conference of African Ministers of Industry, jointly organized by the United Nations Economic Commission for Africa (EGA) and the United Nations Industrial Development Organization (UNIDO), in ...\n\nThe twelfth meeting of the Conference of African Ministers of Industry, jointly organized by the United Nations Economic Commission for Africa (EGA) and the United Nations Industrial Development Organization (UNIDO), in ...\n\nInternational legal instruments relevant to women \n\n\n\nUnited Nations. Economic Commission for Africa. African Centre for Women (1995-06)\nThe principal purpose for publishing this document is to enhance the awareness and enlightenment of women and policy makers with regard to the basic legal rights of women and the existing international legal instruments ...\n\nInternational legal instruments relevant to women \n\n\n\nUnited Nations. Economic Commission for Africa. African Centre for Women (1995-06)\nThe principal purpose for publishing this document is to enhance the awareness and enlightenment of women and policy makers with regard to the basic legal rights of women and the existing international legal instruments ...\n\nUnited Nations. Economic Commission for Africa. African Centre for Women (1995-06)\nThe principal purpose for publishing this document is to enhance the awareness and enlightenment of women and policy makers with regard to the basic legal rights of women and the existing international legal instruments ...\n\nThe principal purpose for publishing this document is to enhance the awareness and enlightenment of women and policy makers with regard to the basic legal rights of women and the existing international legal instruments ...\n\nSouthern Africa Sub-regional Development Center : Lusaka, Zambia \n\n\n\nUnited Nations. Economic Commission for Africa (1997-07)\nThis is the second issue of the Southern Africa Development Bulletin published by the Sub-Regional Development Center of the United Nations Economic Commission for Africa for Southern Africa. The first issue was published ...\n\nSouthern Africa Sub-regional Development Center : Lusaka, Zambia \n\n\n\nUnited Nations. Economic Commission for Africa (1997-07)\nThis is the second issue of the Southern Africa Development Bulletin published by the Sub-Regional Development Center of the United Nations Economic Commission for Africa for Southern Africa. The first issue was published ...\n\nUnited Nations. Economic Commission for Africa (1997-07)\nThis is the second issue of the Southern Africa Development Bulletin published by the Sub-Regional Development Center of the United Nations Economic Commission for Africa for Southern Africa. The first issue was published ...\n\nThis is the second issue of the Southern Africa Development Bulletin published by the Sub-Regional Development Center of the United Nations Economic Commission for Africa for Southern Africa. The first issue was published ...\n\nGender mainstreaming at ECA : review of the past present and future \n\n\n\nUnited Nations. Economic Commission for Africa. African Centre for Women (1996-05)\nThe Vision statement provides the framework for the development of the 1998 - 2001 Medium-term Plan, designed to increase the impact of the organization's work priorities by sharpening the focus of its programs. In this ...\n\nGender mainstreaming at ECA : review of the past present and future \n\n\n\nUnited Nations. Economic Commission for Africa. African Centre for Women (1996-05)\nThe Vision statement provides the framework for the development of the 1998 - 2001 Medium-term Plan, designed to increase the impact of the organization's work priorities by sharpening the focus of its programs. In this ...\n\nUnited Nations. Economic Commission for Africa. African Centre for Women (1996-05)\nThe Vision statement provides the framework for the development of the 1998 - 2001 Medium-term Plan, designed to increase the impact of the organization's work priorities by sharpening the focus of its programs. In this ...\n\nThe Vision statement provides the framework for the development of the 1998 - 2001 Medium-term Plan, designed to increase the impact of the organization's work priorities by sharpening the focus of its programs. In this ...\n\nSome aspects of family planning programmes and fertility in selected ECA member states \n\n\n\nUnited Nations. Economic Commission for Africa. Population Division. Planning and Policies Section. (1985-03)\nRapid population growth has become an increasingly important concern to governments in the ECA member States. The estimated regional population growth rate was 3.1 per cent per annum for the 1980-85 quinquennium.Among the ...\n\nSome aspects of family planning programmes and fertility in selected ECA member states \n\n\n\nUnited Nations. Economic Commission for Africa. Population Division. Planning and Policies Section. (1985-03)\nRapid population growth has become an increasingly important concern to governments in the ECA member States. The estimated regional population growth rate was 3.1 per cent per annum for the 1980-85 quinquennium.Among the ...\n\nUnited Nations. Economic Commission for Africa. Population Division. Planning and Policies Section. (1985-03)\nRapid population growth has become an increasingly important concern to governments in the ECA member States. The estimated regional population growth rate was 3.1 per cent per annum for the 1980-85 quinquennium.Among the ...\n\nRapid population growth has become an increasingly important concern to governments in the ECA member States. The estimated regional population growth rate was 3.1 per cent per annum for the 1980-85 quinquennium.Among the ...\n\nApplication of science and technology in Agro-industry \n\n\n\nUnited Nations. Economic Commission for Africa; Food Security and Sustainable Develoment Division (FSSDD) (1999-12)\nAgro-industries are usually the first to be established in modern manufacturing sector of a developing economy where agriculture has been the mainstay of the economy. Moreover, food processing has a stimulating effect on ...\n\nApplication of science and technology in Agro-industry \n\n\n\nUnited Nations. Economic Commission for Africa; Food Security and Sustainable Develoment Division (FSSDD) (1999-12)\nAgro-industries are usually the first to be established in modern manufacturing sector of a developing economy where agriculture has been the mainstay of the economy. Moreover, food processing has a stimulating effect on ...\n\nUnited Nations. Economic Commission for Africa; Food Security and Sustainable Develoment Division (FSSDD) (1999-12)\nAgro-industries are usually the first to be established in modern manufacturing sector of a developing economy where agriculture has been the mainstay of the economy. Moreover, food processing has a stimulating effect on ...\n\nAgro-industries are usually the first to be established in modern manufacturing sector of a developing economy where agriculture has been the mainstay of the economy. Moreover, food processing has a stimulating effect on ...\n\n1\n\n\n2\n\n\n3\n\n\n4\n\n\n. . .\n\n\n4220\n\n1\n\n\n2\n\n\n3\n\n\n4\n\n\n. . .\n\n\n4220\n\nBrowse\n\nAll of ECA IRCommunities & CollectionsTitleAuthorSubjectBy Issue DateECA Conference ProceedingsFlagship PublicationHas File(s)SpeechesPress ReleasesResolutionsBest Practices\n\nMy Account\n\nMy AccountRegister\n\n\n\nDiscover\n\nAuthorLopes, Carlos (267)Amoako, K.Y. (243)Janneh, Abdoulie (182)Adedeji, Adebayo (110)K.Y., Amoako (103)... View MoreSubjectAFRICA (8418)AFRIQUE (8300)ECONOMIC DEVELOPMENT (3210)DEVELOPPEMENT ECONOMIQUE (3196)WORK PROGRAMME (3188)... View MoreDate2020 - 2025 (4226)2010 - 2019 (8389)2000 - 2009 (4756)1990 - 1999 (6763)1980 - 1989 (6868)1970 - 1979 (5157)1960 - 1969 (5588)1958 - 1959 (110)ECA Conference ProceedingsSessions of the Commission (4479)Conferences of African Ministers (1920)Conferences on Statistical Development (1521)Conferences on Trade, Regional Cooperation and Integration (693)Preparatory Committees (668)... View MoreFlagship PublicationCountry profiles (134)Economic Report on Africa (72)ECA Journals (22)Assessing Regional Integration in Africa (20)Africa’s quarterly economic performance and outlook (19)... View MoreECA Media Format9 p. : ill, (1)TypeConference document (14249)Reports (10399)Press release (7206)Working paper (2862)Speech (1751)Technical paper (927)Briefing paper (580)Book (549)Policy paper (429)Resolutions and decisions (376)... View MoreSeriesPress Release (611)Communiqué de presse. (383)Speech (336)COVID-19 Situation Report: (305)COVID-19 Situation Report : (208)ATPC work in progress; (63)ECA Policy Brief (46)Official records. Supplement / Economic and Social Council (46)Note d’orientation de la CEA (35)Document Officiel  Supplément / Conseil Economique et Social (34)... View MoreHas File(s)Yes (40419)No (1780)\n\nReporting Suite\n\nMost Popular ItemsStatistics by CountryMost Popular Authors\n\nBrowse\n\nAll of ECA IRCommunities & CollectionsTitleAuthorSubjectBy Issue DateECA Conference ProceedingsFlagship PublicationHas File(s)SpeechesPress ReleasesResolutionsBest Practices\n\nMy Account\n\nMy AccountRegister\n\n\n\nDiscover\n\nAuthorLopes, Carlos (267)Amoako, K.Y. (243)Janneh, Abdoulie (182)Adedeji, Adebayo (110)K.Y., Amoako (103)... View MoreSubjectAFRICA (8418)AFRIQUE (8300)ECONOMIC DEVELOPMENT (3210)DEVELOPPEMENT ECONOMIQUE (3196)WORK PROGRAMME (3188)... View MoreDate2020 - 2025 (4226)2010 - 2019 (8389)2000 - 2009 (4756)1990 - 1999 (6763)1980 - 1989 (6868)1970 - 1979 (5157)1960 - 1969 (5588)1958 - 1959 (110)ECA Conference ProceedingsSessions of the Commission (4479)Conferences of African Ministers (1920)Conferences on Statistical Development (1521)Conferences on Trade, Regional Cooperation and Integration (693)Preparatory Committees (668)... View MoreFlagship PublicationCountry profiles (134)Economic Report on Africa (72)ECA Journals (22)Assessing Regional Integration in Africa (20)Africa’s quarterly economic performance and outlook (19)... View MoreECA Media Format9 p. : ill, (1)TypeConference document (14249)Reports (10399)Press release (7206)Working paper (2862)Speech (1751)Technical paper (927)Briefing paper (580)Book (549)Policy paper (429)Resolutions and decisions (376)... View MoreSeriesPress Release (611)Communiqué de presse. (383)Speech (336)COVID-19 Situation Report: (305)COVID-19 Situation Report : (208)ATPC work in progress; (63)ECA Policy Brief (46)Official records. Supplement / Economic and Social Council (46)Note d’orientation de la CEA (35)Document Officiel  Supplément / Conseil Economique et Social (34)... View MoreHas File(s)Yes (40419)No (1780)\n\nReporting Suite\n\nMost Popular ItemsStatistics by CountryMost Popular Authors\n\nBrowse\n\nAll of ECA IRCommunities & CollectionsTitleAuthorSubjectBy Issue DateECA Conference ProceedingsFlagship PublicationHas File(s)SpeechesPress ReleasesResolutionsBest Practices\n\nMy Account\n\nMy AccountRegister\n\nDiscover\n\nAuthorLopes, Carlos (267)Amoako, K.Y. (243)Janneh, Abdoulie (182)Adedeji, Adebayo (110)K.Y., Amoako (103)... View MoreSubjectAFRICA (8418)AFRIQUE (8300)ECONOMIC DEVELOPMENT (3210)DEVELOPPEMENT ECONOMIQUE (3196)WORK PROGRAMME (3188)... View MoreDate2020 - 2025 (4226)2010 - 2019 (8389)2000 - 2009 (4756)1990 - 1999 (6763)1980 - 1989 (6868)1970 - 1979 (5157)1960 - 1969 (5588)1958 - 1959 (110)ECA Conference ProceedingsSessions of the Commission (4479)Conferences of African Ministers (1920)Conferences on Statistical Development (1521)Conferences on Trade, Regional Cooperation and Integration (693)Preparatory Committees (668)... View MoreFlagship PublicationCountry profiles (134)Economic Report on Africa (72)ECA Journals (22)Assessing Regional Integration in Africa (20)Africa’s quarterly economic performance and outlook (19)... View MoreECA Media Format9 p. : ill, (1)TypeConference document (14249)Reports (10399)Press release (7206)Working paper (2862)Speech (1751)Technical paper (927)Briefing paper (580)Book (549)Policy paper (429)Resolutions and decisions (376)... View MoreSeriesPress Release (611)Communiqué de presse. (383)Speech (336)COVID-19 Situation Report: (305)COVID-19 Situation Report : (208)ATPC work in progress; (63)ECA Policy Brief (46)Official records. Supplement / Economic and Social Council (46)Note d’orientation de la CEA (35)Document Officiel  Supplément / Conseil Economique et Social (34)... View MoreHas File(s)Yes (40419)No (1780)\n\nReporting Suite\n\nMost Popular ItemsStatistics by CountryMost Popular Authors",
  "date": "",
  "source_type": "other",
  "extracted_at": "2025-04-07T14:26:51.653443",
  "metadata": {},
  "relevance_score": 0.6000000000000001,
  "summary": "46165 publications\n\n\n\n\n\n\n\n\n\n\n\nAdvanced Search\n\n46165 publications\n\n\n\n\n\n\n\n\n\n\n\nAdvanced Search\n\n46165 publications\n\nAdvanced Search\n\nSearch \n\n\n \n                        ECA IR Home\n\n\nSearch\n\n\n\n\n\n \n            ECA IR Home\n\nSearch\n\nSearch \n\n\n \n                        ECA IR Home\n\n\nSearch\n\n\n\n\n\n \n            ECA IR Home\n\nSearch\n\nSearch \n\n\n \n                        ECA IR Home\n\n\nSearch\n\n\n\n\n\n \n            ECA IR Home\n\nSearch\n\nSearch \n\n\n \n                        ECA IR Home\n\n\nSearch\n\n\n\n\n\n \n            ECA IR Home\n\nSearch\n\nSearch \n\n\n \n                        ECA IR Home\n\n\nSearch\n\nJavaScript is disabled for your browser. Limit your search to items with or without files\nall itemsitems with filesitems without files\n\n\n\n\n\n\nResetAdd New FilterApply\n\n\n\n\n\n\n\n\n\n\n\n\n\n\n\n\n\n\n\n\n\n\n\n\n\n\n\n\n\n\n\n\n\nNow showing items 1-10 of 42199\n\n\n\n\n\nSort Options:\n\nRelevance\n\n\nTitle Asc\n\n\nTitle Desc\n\n\nIssue Date Asc\n\n\nIssue Date Desc\n\n\nResults Per Page:\n\n5\n\n\n10\n\n\n20\n\n\n40\n\n\n60\n\n\n80\n\n\n100\n\n\n\n\n\n\n\n\n\n\n\n\n\n\n\n\nThe evaluation report on multimodal transport sub-sector: the third and final evaluation report on the second United Nations Transport and Communication Decade in Africa (UNTACDA II) 1991-2000 \n\n\n\nUnited Nations. Economic Commission for Africa (2001-09)\nThe UNTACDA II sub-sectoral evaluation report in the field of Multimodal Transport (MT) has been prepared according to the revised terms of reference for preparation of modal reports. Rapport de la réunion ad-hoc du groupe spécial d'experts pour l'examen des stratégies et politiques requises pour améliorer le processus de mise en œuvre de la privatisation en Afrique: \n\n\n\nNations Unies. Conseil Economique et Social (1999-11)\nLa réunion du Groupe spécial d’experts organisé par la Commission économique pour l’Afrique sur l’examen des stratégies et politiques requises pour améliorer le processus de mise en œuvre de la privatisation en Afrique se ... Report to the twelfth meeting of the Conference of African Ministres of Industry \n\n\n\nUnited National Industrial Development Organization; United Nations. Economic Commission for Africa (1995-06)\nThe twelfth meeting of the Conference of African Ministers of Industry, jointly organized by the United Nations Economic Commission for Africa (EGA) and the United Nations Industrial Development Organization (UNIDO), in ... Economic Commission for Africa (1997-07)\nThis is the second issue of the Southern Africa Development Bulletin published by the Sub-Regional Development Center of the United Nations Economic Commission for Africa for Southern Africa. Economic Commission for Africa; Food Security and Sustainable Develoment Division (FSSDD) (1999-12)\nAgro-industries are usually the first to be established in modern manufacturing sector of a developing economy where agriculture has been the mainstay of the economy. View MoreDate2020 - 2025 (4226)2010 - 2019 (8389)2000 - 2009 (4756)1990 - 1999 (6763)1980 - 1989 (6868)1970 - 1979 (5157)1960 - 1969 (5588)1958 - 1959 (110)ECA Conference ProceedingsSessions of the Commission (4479)Conferences of African Ministers (1920)Conferences on Statistical Development (1521)Conferences on Trade, Regional Cooperation and Integration (693)Preparatory Committees (668)... View MoreFlagship PublicationCountry profiles (134)Economic Report on Africa (72)ECA Journals (22)Assessing Regional Integration in Africa (20)Africa’s quarterly economic performance and outlook (19)... Limit your search to items with or without files\nall itemsitems with filesitems without files\n\n\n\n\n\n\nResetAdd New FilterApply\n\n\n\n\n\n\n\n\n\n\n\n\n\n\n\n\n\n\n\n\n\n\n\n\n\n\n\n\n\n\n\n\n\nNow showing items 1-10 of 42199\n\n\n\n\n\nSort Options:\n\nRelevance\n\n\nTitle Asc\n\n\nTitle Desc\n\n\nIssue Date Asc\n\n\nIssue Date Desc\n\n\nResults Per Page:\n\n5\n\n\n10\n\n\n20\n\n\n40\n\n\n60\n\n\n80\n\n\n100\n\n\n\n\n\n\n\n\n\n\n\n\n\n\n\n\nThe evaluation report on multimodal transport sub-sector: the third and final evaluation report on the second United Nations Transport and Communication Decade in Africa (UNTACDA II) 1991-2000 \n\n\n\nUnited Nations. Economic Commission for Africa (2001-09)\nThe UNTACDA II sub-sectoral evaluation report in the field of Multimodal Transport (MT) has been prepared according to the revised terms of reference for preparation of modal reports. Rapport de la réunion ad-hoc du groupe spécial d'experts pour l'examen des stratégies et politiques requises pour améliorer le processus de mise en œuvre de la privatisation en Afrique: \n\n\n\nNations Unies. Conseil Economique et Social (1999-11)\nLa réunion du Groupe spécial d’experts organisé par la Commission économique pour l’Afrique sur l’examen des stratégies et politiques requises pour améliorer le processus de mise en œuvre de la privatisation en Afrique se ... Report to the twelfth meeting of the Conference of African Ministres of Industry \n\n\n\nUnited National Industrial Development Organization; United Nations. Economic Commission for Africa (1995-06)\nThe twelfth meeting of the Conference of African Ministers of Industry, jointly organized by the United Nations Economic Commission for Africa (EGA) and the United Nations Industrial Development Organization (UNIDO), in ... Economic Commission for Africa (1997-07)\nThis is the second issue of the Southern Africa Development Bulletin published by the Sub-Regional Development Center of the United Nations Economic Commission for Africa for Southern Africa. Economic Commission for Africa; Food Security and Sustainable Develoment Division (FSSDD) (1999-12)\nAgro-industries are usually the first to be established in modern manufacturing sector of a developing economy where agriculture has been the mainstay of the economy. View MoreDate2020 - 2025 (4226)2010 - 2019 (8389)2000 - 2009 (4756)1990 - 1999 (6763)1980 - 1989 (6868)1970 - 1979 (5157)1960 - 1969 (5588)1958 - 1959 (110)ECA Conference ProceedingsSessions of the Commission (4479)Conferences of African Ministers (1920)Conferences on Statistical Development (1521)Conferences on Trade, Regional Cooperation and Integration (693)Preparatory Committees (668)... View MoreFlagship PublicationCountry profiles (134)Economic Report on Africa (72)ECA Journals (22)Assessing Regional Integration in Africa (20)Africa’s quarterly economic performance and outlook (19)... Limit your search to items with or without files\nall itemsitems with filesitems without files\n\n\n\n\n\n\nResetAdd New FilterApply\n\n\n\n\n\n\n\n\n\n\n\n\n\n\n\n\n\n\n\n\n\n\n\n\n\n\n\n\n\n\n\n\n\nNow showing items 1-10 of 42199\n\n\n\n\n\nSort Options:\n\nRelevance\n\n\nTitle Asc\n\n\nTitle Desc\n\n\nIssue Date Asc\n\n\nIssue Date Desc\n\n\nResults Per Page:\n\n5\n\n\n10\n\n\n20\n\n\n40\n\n\n60\n\n\n80\n\n\n100\n\n\n\n\n\n\n\n\n\n\n\n\n\n\n\n\nThe evaluation report on multimodal transport sub-sector: the third and final evaluation report on the second United Nations Transport and Communication Decade in Africa (UNTACDA II) 1991-2000 \n\n\n\nUnited Nations. Economic Commission for Africa (2001-09)\nThe UNTACDA II sub-sectoral evaluation report in the field of Multimodal Transport (MT) has been prepared according to the revised terms of reference for preparation of modal reports. Rapport de la réunion ad-hoc du groupe spécial d'experts pour l'examen des stratégies et politiques requises pour améliorer le processus de mise en œuvre de la privatisation en Afrique: \n\n\n\nNations Unies. Conseil Economique et Social (1999-11)\nLa réunion du Groupe spécial d’experts organisé par la Commission économique pour l’Afrique sur l’examen des stratégies et politiques requises pour améliorer le processus de mise en œuvre de la privatisation en Afrique se ... Report to the twelfth meeting of the Conference of African Ministres of Industry \n\n\n\nUnited National Industrial Development Organization; United Nations. Economic Commission for Africa (1995-06)\nThe twelfth meeting of the Conference of African Ministers of Industry, jointly organized by the United Nations Economic Commission for Africa (EGA) and the United Nations Industrial Development Organization (UNIDO), in ... Economic Commission for Africa (1997-07)\nThis is the second issue of the Southern Africa Development Bulletin published by the Sub-Regional Development Center of the United Nations Economic Commission for Africa for Southern Africa. Economic Commission for Africa; Food Security and Sustainable Develoment Division (FSSDD) (1999-12)\nAgro-industries are usually the first to be established in modern manufacturing sector of a developing economy where agriculture has been the mainstay of the economy. View MoreDate2020 - 2025 (4226)2010 - 2019 (8389)2000 - 2009 (4756)1990 - 1999 (6763)1980 - 1989 (6868)1970 - 1979 (5157)1960 - 1969 (5588)1958 - 1959 (110)ECA Conference ProceedingsSessions of the Commission (4479)Conferences of African Ministers (1920)Conferences on Statistical Development (1521)Conferences on Trade, Regional Cooperation and Integration (693)Preparatory Committees (668)... View MoreFlagship PublicationCountry profiles (134)Economic Report on Africa (72)ECA Journals (22)Assessing Regional Integration in Africa (20)Africa’s quarterly economic performance and outlook (19)... Limit your search to items with or without files\nall itemsitems with filesitems without files\n\n\n\n\n\n\nResetAdd New FilterApply\n\n\n\n\n\n\n\n\n\n\n\n\n\n\n\n\n\n\n\n\n\n\n\n\n\n\n\n\n\n\n\n\n\nNow showing items 1-10 of 42199\n\n\n\n\n\nSort Options:\n\nRelevance\n\n\nTitle Asc\n\n\nTitle Desc\n\n\nIssue Date Asc\n\n\nIssue Date Desc\n\n\nResults Per Page:\n\n5\n\n\n10\n\n\n20\n\n\n40\n\n\n60\n\n\n80\n\n\n100\n\n\n\n\n\n\n\n\n\n\n\n\n\n\n\n\nThe evaluation report on multimodal transport sub-sector: the third and final evaluation report on the second United Nations Transport and Communication Decade in Africa (UNTACDA II) 1991-2000 \n\n\n\nUnited Nations. Economic Commission for Africa (2001-09)\nThe UNTACDA II sub-sectoral evaluation report in the field of Multimodal Transport (MT) has been prepared according to the revised terms of reference for preparation of modal reports. Rapport de la réunion ad-hoc du groupe spécial d'experts pour l'examen des stratégies et politiques requises pour améliorer le processus de mise en œuvre de la privatisation en Afrique: \n\n\n\nNations Unies. Conseil Economique et Social (1999-11)\nLa réunion du Groupe spécial d’experts organisé par la Commission économique pour l’Afrique sur l’examen des stratégies et politiques requises pour améliorer le processus de mise en œuvre de la privatisation en Afrique se ... Report to the twelfth meeting of the Conference of African Ministres of Industry \n\n\n\nUnited National Industrial Development Organization; United Nations. Economic Commission for Africa (1995-06)\nThe twelfth meeting of the Conference of African Ministers of Industry, jointly organized by the United Nations Economic Commission for Africa (EGA) and the United Nations Industrial Development Organization (UNIDO), in ... Economic Commission for Africa (1997-07)\nThis is the second issue of the Southern Africa Development Bulletin published by the Sub-Regional Development Center of the United Nations Economic Commission for Africa for Southern Africa. Economic Commission for Africa; Food Security and Sustainable Develoment Division (FSSDD) (1999-12)\nAgro-industries are usually the first to be established in modern manufacturing sector of a developing economy where agriculture has been the mainstay of the economy. Limit your search to items with or without files\nall itemsitems with filesitems without files\n\n\n\n\n\n\nResetAdd New FilterApply\n\n\n\n\n\n\n\n\n\n\n\n\n\n\n\n\n\n\n\n\n\n\n\n\n\n\n\n\n\n\n\n\n\nNow showing items 1-10 of 42199\n\n\n\n\n\nSort Options:\n\nRelevance\n\n\nTitle Asc\n\n\nTitle Desc\n\n\nIssue Date Asc\n\n\nIssue Date Desc\n\n\nResults Per Page:\n\n5\n\n\n10\n\n\n20\n\n\n40\n\n\n60\n\n\n80\n\n\n100\n\n\n\n\n\n\n\n\n\n\n\n\n\n\n\n\nThe evaluation report on multimodal transport sub-sector: the third and final evaluation report on the second United Nations Transport and Communication Decade in Africa (UNTACDA II) 1991-2000 \n\n\n\nUnited Nations. Economic Commission for Africa (2001-09)\nThe UNTACDA II sub-sectoral evaluation report in the field of Multimodal Transport (MT) has been prepared according to the revised terms of reference for preparation of modal reports. Rapport de la réunion ad-hoc du groupe spécial d'experts pour l'examen des stratégies et politiques requises pour améliorer le processus de mise en œuvre de la privatisation en Afrique: \n\n\n\nNations Unies. Conseil Economique et Social (1999-11)\nLa réunion du Groupe spécial d’experts organisé par la Commission économique pour l’Afrique sur l’examen des stratégies et politiques requises pour améliorer le processus de mise en œuvre de la privatisation en Afrique se ... Report to the twelfth meeting of the Conference of African Ministres of Industry \n\n\n\nUnited National Industrial Development Organization; United Nations. Economic Commission for Africa (1995-06)\nThe twelfth meeting of the Conference of African Ministers of Industry, jointly organized by the United Nations Economic Commission for Africa (EGA) and the United Nations Industrial Development Organization (UNIDO), in ... Economic Commission for Africa (1997-07)\nThis is the second issue of the Southern Africa Development Bulletin published by the Sub-Regional Development Center of the United Nations Economic Commission for Africa for Southern Africa. Economic Commission for Africa; Food Security and Sustainable Develoment Division (FSSDD) (1999-12)\nAgro-industries are usually the first to be established in modern manufacturing sector of a developing economy where agriculture has been the mainstay of the economy. Limit your search to items with or without files\nall itemsitems with filesitems without files\n\n\n\n\n\n\nResetAdd New FilterApply\n\n\n\n\n\n\n\n\n\n\n\n\n\n\n\n\n\n\n\n\n\n\n\n\n\n\n\n\n\n\n\n\n\nNow showing items 1-10 of 42199\n\n\n\n\n\nSort Options:\n\nRelevance\n\n\nTitle Asc\n\n\nTitle Desc\n\n\nIssue Date Asc\n\n\nIssue Date Desc\n\n\nResults Per Page:\n\n5\n\n\n10\n\n\n20\n\n\n40\n\n\n60\n\n\n80\n\n\n100\n\n\n\n\n\n\n\n\n\n\n\n\n\n\n\n\nThe evaluation report on multimodal transport sub-sector: the third and final evaluation report on the second United Nations Transport and Communication Decade in Africa (UNTACDA II) 1991-2000 \n\n\n\nUnited Nations. Economic Commission for Africa (2001-09)\nThe UNTACDA II sub-sectoral evaluation report in the field of Multimodal Transport (MT) has been prepared according to the revised terms of reference for preparation of modal reports. Rapport de la réunion ad-hoc du groupe spécial d'experts pour l'examen des stratégies et politiques requises pour améliorer le processus de mise en œuvre de la privatisation en Afrique: \n\n\n\nNations Unies. Conseil Economique et Social (1999-11)\nLa réunion du Groupe spécial d’experts organisé par la Commission économique pour l’Afrique sur l’examen des stratégies et politiques requises pour améliorer le processus de mise en œuvre de la privatisation en Afrique se ... Report to the twelfth meeting of the Conference of African Ministres of Industry \n\n\n\nUnited National Industrial Development Organization; United Nations. Economic Commission for Africa (1995-06)\nThe twelfth meeting of the Conference of African Ministers of Industry, jointly organized by the United Nations Economic Commission for Africa (EGA) and the United Nations Industrial Development Organization (UNIDO), in ... Economic Commission for Africa (1997-07)\nThis is the second issue of the Southern Africa Development Bulletin published by the Sub-Regional Development Center of the United Nations Economic Commission for Africa for Southern Africa. Economic Commission for Africa; Food Security and Sustainable Develoment Division (FSSDD) (1999-12)\nAgro-industries are usually the first to be established in modern manufacturing sector of a developing economy where agriculture has been the mainstay of the economy. Limit your search to items with or without files\nall itemsitems with filesitems without files\n\n\n\n\n\n\nResetAdd New FilterApply\n\nAll of ECA IRAfrican Policy CentersCommunities and Collections developed on the BrowseOther Communities and Collections not in the Main Areas of WorkRegional Coordination Mechanism (RCM)TaxonomyWork programmes\n\n\n\n\nGo\n\nAll of ECA IRAfrican Policy CentersCommunities and Collections developed on the BrowseOther Communities and Collections not in the Main Areas of WorkRegional Coordination Mechanism (RCM)TaxonomyWork programmes\n\nAll of ECA IRAfrican Policy CentersCommunities and Collections developed on the BrowseOther Communities and Collections not in the Main Areas of WorkRegional Coordination Mechanism (RCM)TaxonomyWork programmes\n\nGo\n\nGo\n\nShow Advanced FiltersHide Advanced Filters\n\nShow Advanced FiltersHide Advanced Filters\n\nUse filters to refine the search results. Limit your search to items with or without files\nall itemsitems with filesitems without files\n\n\n\n\n\n\nResetAdd New FilterApply\n\nLimit your search to items with or without files\nall itemsitems with filesitems without files\n\nResetAdd New FilterApply\n\nResetAdd New FilterApply\n\nResetAdd New FilterApply\n\nNow showing items 1-10 of 42199\n\n\n\n\n\nSort Options:\n\nRelevance\n\n\nTitle Asc\n\n\nTitle Desc\n\n\nIssue Date Asc\n\n\nIssue Date Desc\n\n\nResults Per Page:\n\n5\n\n\n10\n\n\n20\n\n\n40\n\n\n60\n\n\n80\n\n\n100\n\nNow showing items 1-10 of 42199\n\n\n\n\n\nSort Options:\n\nRelevance\n\n\nTitle Asc\n\n\nTitle Desc\n\n\nIssue Date Asc\n\n\nIssue Date Desc\n\n\nResults Per Page:\n\n5\n\n\n10\n\n\n20\n\n\n40\n\n\n60\n\n\n80\n\n\n100\n\nNow showing items 1-10 of 42199\n\nNow showing items 1-10 of 42199\n\nSort Options:\n\nRelevance\n\n\nTitle Asc\n\n\nTitle Desc\n\n\nIssue Date Asc\n\n\nIssue Date Desc\n\n\nResults Per Page:\n\n5\n\n\n10\n\n\n20\n\n\n40\n\n\n60\n\n\n80\n\n\n100\n\nSort Options:\n\nRelevance\n\n\nTitle Asc\n\n\nTitle Desc\n\n\nIssue Date Asc\n\n\nIssue Date Desc\n\n\nResults Per Page:\n\n5\n\n\n10\n\n\n20\n\n\n40\n\n\n60\n\n\n80\n\n\n100\n\nThe evaluation report on multimodal transport sub-sector: the third and final evaluation report on the second United Nations Transport and Communication Decade in Africa (UNTACDA II) 1991-2000 \n\n\n\nUnited Nations. Economic Commission for Africa (2001-09)\nThe UNTACDA II sub-sectoral evaluation report in the field of Multimodal Transport (MT) has been prepared according to the revised terms of reference for preparation of modal reports. Rapport de la réunion ad-hoc du groupe spécial d'experts pour l'examen des stratégies et politiques requises pour améliorer le processus de mise en œuvre de la privatisation en Afrique: \n\n\n\nNations Unies. Conseil Economique et Social (1999-11)\nLa réunion du Groupe spécial d’experts organisé par la Commission économique pour l’Afrique sur l’examen des stratégies et politiques requises pour améliorer le processus de mise en œuvre de la privatisation en Afrique se ... Report to the twelfth meeting of the Conference of African Ministres of Industry \n\n\n\nUnited National Industrial Development Organization; United Nations. Economic Commission for Africa (1995-06)\nThe twelfth meeting of the Conference of African Ministers of Industry, jointly organized by the United Nations Economic Commission for Africa (EGA) and the United Nations Industrial Development Organization (UNIDO), in ... Economic Commission for Africa (1997-07)\nThis is the second issue of the Southern Africa Development Bulletin published by the Sub-Regional Development Center of the United Nations Economic Commission for Africa for Southern Africa. Economic Commission for Africa; Food Security and Sustainable Develoment Division (FSSDD) (1999-12)\nAgro-industries are usually the first to be established in modern manufacturing sector of a developing economy where agriculture has been the mainstay of the economy. The evaluation report on multimodal transport sub-sector: the third and final evaluation report on the second United Nations Transport and Communication Decade in Africa (UNTACDA II) 1991-2000 \n\n\n\nUnited Nations. Economic Commission for Africa (2001-09)\nThe UNTACDA II sub-sectoral evaluation report in the field of Multimodal Transport (MT) has been prepared according to the revised terms of reference for preparation of modal reports. The evaluation report on multimodal transport sub-sector: the third and final evaluation report on the second United Nations Transport and Communication Decade in Africa (UNTACDA II) 1991-2000 \n\n\n\nUnited Nations. Economic Commission for Africa (2001-09)\nThe UNTACDA II sub-sectoral evaluation report in the field of Multimodal Transport (MT) has been prepared according to the revised terms of reference for preparation of modal reports. Economic Commission for Africa (2001-09)\nThe UNTACDA II sub-sectoral evaluation report in the field of Multimodal Transport (MT) has been prepared according to the revised terms of reference for preparation of modal reports. Rapport de la réunion ad-hoc du groupe spécial d'experts pour l'examen des stratégies et politiques requises pour améliorer le processus de mise en œuvre de la privatisation en Afrique: \n\n\n\nNations Unies. Conseil Economique et Social (1999-11)\nLa réunion du Groupe spécial d’experts organisé par la Commission économique pour l’Afrique sur l’examen des stratégies et politiques requises pour améliorer le processus de mise en œuvre de la privatisation en Afrique se ... Rapport de la réunion ad-hoc du groupe spécial d'experts pour l'examen des stratégies et politiques requises pour améliorer le processus de mise en œuvre de la privatisation en Afrique: \n\n\n\nNations Unies. Conseil Economique et Social (1999-11)\nLa réunion du Groupe spécial d’experts organisé par la Commission économique pour l’Afrique sur l’examen des stratégies et politiques requises pour améliorer le processus de mise en œuvre de la privatisation en Afrique se ... Conseil Economique et Social (1999-11)\nLa réunion du Groupe spécial d’experts organisé par la Commission économique pour l’Afrique sur l’examen des stratégies et politiques requises pour améliorer le processus de mise en œuvre de la privatisation en Afrique se ... La réunion du Groupe spécial d’experts organisé par la Commission économique pour l’Afrique sur l’examen des stratégies et politiques requises pour améliorer le processus de mise en œuvre de la privatisation en Afrique se ... Report to the twelfth meeting of the Conference of African Ministres of Industry \n\n\n\nUnited National Industrial Development Organization; United Nations. Economic Commission for Africa (1995-06)\nThe twelfth meeting of the Conference of African Ministers of Industry, jointly organized by the United Nations Economic Commission for Africa (EGA) and the United Nations Industrial Development Organization (UNIDO), in ... Report to the twelfth meeting of the Conference of African Ministres of Industry \n\n\n\nUnited National Industrial Development Organization; United Nations. Economic Commission for Africa (1995-06)\nThe twelfth meeting of the Conference of African Ministers of Industry, jointly organized by the United Nations Economic Commission for Africa (EGA) and the United Nations Industrial Development Organization (UNIDO), in ... Economic Commission for Africa (1995-06)\nThe twelfth meeting of the Conference of African Ministers of Industry, jointly organized by the United Nations Economic Commission for Africa (EGA) and the United Nations Industrial Development Organization (UNIDO), in ... The twelfth meeting of the Conference of African Ministers of Industry, jointly organized by the United Nations Economic Commission for Africa (EGA) and the United Nations Industrial Development Organization (UNIDO), in ... Economic Commission for Africa (1997-07)\nThis is the second issue of the Southern Africa Development Bulletin published by the Sub-Regional Development Center of the United Nations Economic Commission for Africa for Southern Africa. Economic Commission for Africa (1997-07)\nThis is the second issue of the Southern Africa Development Bulletin published by the Sub-Regional Development Center of the United Nations Economic Commission for Africa for Southern Africa. Economic Commission for Africa (1997-07)\nThis is the second issue of the Southern Africa Development Bulletin published by the Sub-Regional Development Center of the United Nations Economic Commission for Africa for Southern Africa. This is the second issue of the Southern Africa Development Bulletin published by the Sub-Regional Development Center of the United Nations Economic Commission for Africa for Southern Africa. View MoreDate2020 - 2025 (4226)2010 - 2019 (8389)2000 - 2009 (4756)1990 - 1999 (6763)1980 - 1989 (6868)1970 - 1979 (5157)1960 - 1969 (5588)1958 - 1959 (110)ECA Conference ProceedingsSessions of the Commission (4479)Conferences of African Ministers (1920)Conferences on Statistical Development (1521)Conferences on Trade, Regional Cooperation and Integration (693)Preparatory Committees (668)... View MoreFlagship PublicationCountry profiles (134)Economic Report on Africa (72)ECA Journals (22)Assessing Regional Integration in Africa (20)Africa’s quarterly economic performance and outlook (19)... View MoreDate2020 - 2025 (4226)2010 - 2019 (8389)2000 - 2009 (4756)1990 - 1999 (6763)1980 - 1989 (6868)1970 - 1979 (5157)1960 - 1969 (5588)1958 - 1959 (110)ECA Conference ProceedingsSessions of the Commission (4479)Conferences of African Ministers (1920)Conferences on Statistical Development (1521)Conferences on Trade, Regional Cooperation and Integration (693)Preparatory Committees (668)... View MoreFlagship PublicationCountry profiles (134)Economic Report on Africa (72)ECA Journals (22)Assessing Regional Integration in Africa (20)Africa’s quarterly economic performance and outlook (19)... View MoreDate2020 - 2025 (4226)2010 - 2019 (8389)2000 - 2009 (4756)1990 - 1999 (6763)1980 - 1989 (6868)1970 - 1979 (5157)1960 - 1969 (5588)1958 - 1959 (110)ECA Conference ProceedingsSessions of the Commission (4479)Conferences of African Ministers (1920)Conferences on Statistical Development (1521)Conferences on Trade, Regional Cooperation and Integration (693)Preparatory Committees (668)... View MoreFlagship PublicationCountry profiles (134)Economic Report on Africa (72)ECA Journals (22)Assessing Regional Integration in Africa (20)Africa’s quarterly economic performance and outlook (19)...",
  "entities": {
    "countries": [],
    "organizations": [
      "united nations",
      "un"
    ],
    "key_issues": [
      "issue",
      "challenge",
      "concern",
      "situation",
      "country",
      "nation",
      "state",
      "government",
      "region",
      "solution",
      "resolution",
      "policy",
      "program",
      "development",
      "aid",
      "economic",
      "economy",
      "trade",
      "industry",
      "united nations",
      "un",
      "organization"
    ]
  },
  "committee": "Economic and Social Council",
  "topic": "Promoting rural development in Africa"
}