{
  "url": "https://www.ifad.org/en/what-we-do",
  "title": "What we do",
  "text": "What we do - IFAD\n\n\n\n\n\n\n\n\n\n\n\n\n\n\n\n\n\n\n\n\n\n\n\n\n\n\n\n\n\n\n\n\n\n\n\nWhat we do\n\n\n\n\n\n\n\n\n\n©IFAD/David Rose \n\n\n\n\n\n\n\nSimply put, IFAD invests in rural people.\n\n\n\n\n\n\n\n\n\n\n\n\n\n\n\n\n\n\n\nProgrammes for progress\n\n\n\n\n\nWe reduce poverty, improve nutrition and increase food production by providing loans and grants that transform rural communities.\nWe develop solutions with governments and rural people themselves so that our investments solve the issues at hand while laying the foundations for thriving rural economies in the long-term.\n\n\n\n \n\n\n\n\n\n\n\n\n\n\n\n\n\n\n\n\n\n\n\n\n\nFor rural people, by rural people\n\n\n\n\n\n\nThe more engaged rural people are as decision-makers, the greater our impact. That's why we take a people-centred approach to transforming rural livelihoods. \nOur investments support those most vulnerable, including women, youth, Indigenous Peoples and persons with disabilities. In this way, our work not only helps rural people grow and earn more, but it also promotes gender equality and inclusiveness.\n\n\n\n \n\n\n\n\n\n\n\n\n\n\n\n\n\n\n\n\n\n\n\n\n\n\n\n\n\n\n\n\n\n\n\n\nMaking finance work for those who need it most\n\n\n\n\n\n\nThe global financial system often excludes those who could benefit most from it. That’s why IFAD provides financing to governments at favourable terms so they can transform their economies.\nOur investments empower rural communities to flourish.We are constantly exploring new financing mechanisms so we can have an even greater impact.\n \n\n\n\n\n\n\n\n\n\n\n\n\n\n\n\n\n\n\nMeasuring what matters\n\n\n\n\n\n\nTo understand whether IFAD is making a difference, we systematically measure results, including through impact assessments.\nEach of our projects includes a monitoring and evaluation system for collecting data so we can identify what works. Our Independent Office of Evaluation conducts independent project evaluations which offer additional insights.\n\n\n\n\n\n\n\n\n\n\n\n\n\n\n\n\n\n\nEmbracing innovation\n\n\n\n\n\n\nIn an increasingly complex world, we cannot rely on conventional approaches to respond to today’s challenges.\nWe need innovation to make rural development sustainable, resilient and equitable. IFAD tests and learns to deliver better results. We co-finance proven innovations that can be scaled up.\n\n\n\n\n\n\n\n\n\n\nKeep exploring\n\n\n\n\n\n\n\n\n\n\n\n\n\n\n\n\n Rural finance With access to finance, rural people can produce more, grow their enterprises, earn more and get through hard times. \n\n  Explore more \n           \n \n\n\n\n\n\n\n\n\n\n\n\n\n\n\n\n\n\n Assessing our impact IFAD's impact assessments accurately measure and report on the impact of our work \n\n  Explore more \n           \n \n\n\n\n\n\n\n\n\n\n\n\n\n\n\n\n\n Who we are IFAD is the world’s fund for transforming agriculture, rural economies and food systems. \n\n  Explore more \n           \n \n\n\n\n\n\n\n\n\n\n\n\n\n\n\n\n       Please configure the desktop menu widget below\n      \n\n\n\n\n\n\n\n\n About IFAD \n Who we are   Where we work   What we do   Action Areas   Knowledge & Data \n\n\n For Member States \n Member States interactive platform \n\n\n For Investors \n Investors   Finance \n\n\n For Job seekers \n Work with us   Frequently Asked Questions \n\n\n For Media \n News   Media Contacts   Image Bank \n\n\n Get Involved \n Join an event   Rural Voices   Opinions & Insights \n\n\n\n\n\n\n\n\n\n\n\n\n\n       Please configure the mobile menu widget below\n      \n\n\n\n\n\n\n\n\n Who we are \n\n\n\n What we do \n\n\n\n Where we work \n\n\n\n Action Areas \n\n\n\n Knowledge & Data \n\n\n\n Get Involved \n\n\n\n News and Stories \n\n\n\n\n\n\n\n\n\n\n\n\n\n  \n Legal  Privacy notice  Fraudulent job offers  Contact us Stay connected\n\n\n\n  \n\n  \n\n  \n\n  \n\n  \n\n \n\n\n\n\n\n\n\n\nHidden\n\nWhat we do - IFAD\n\n\n\n\n\n\n\n\n\n\n\n\n\n\n\n\n\n\n\n\n\n\n\n\n\n\n\n\n\n\n\n\n\n\n\nWhat we do\n\n\n\n\n\n\n\n\n\n©IFAD/David Rose \n\n\n\n\n\n\n\nSimply put, IFAD invests in rural people.\n\n\n\n\n\n\n\n\n\n\n\n\n\n\n\n\n\n\n\nProgrammes for progress\n\n\n\n\n\nWe reduce poverty, improve nutrition and increase food production by providing loans and grants that transform rural communities.\nWe develop solutions with governments and rural people themselves so that our investments solve the issues at hand while laying the foundations for thriving rural economies in the long-term.\n\n\n\n \n\n\n\n\n\n\n\n\n\n\n\n\n\n\n\n\n\n\n\n\n\nFor rural people, by rural people\n\n\n\n\n\n\nThe more engaged rural people are as decision-makers, the greater our impact. That's why we take a people-centred approach to transforming rural livelihoods. \nOur investments support those most vulnerable, including women, youth, Indigenous Peoples and persons with disabilities. In this way, our work not only helps rural people grow and earn more, but it also promotes gender equality and inclusiveness.\n\n\n\n \n\n\n\n\n\n\n\n\n\n\n\n\n\n\n\n\n\n\n\n\n\n\n\n\n\n\n\n\n\n\n\n\nMaking finance work for those who need it most\n\n\n\n\n\n\nThe global financial system often excludes those who could benefit most from it. That’s why IFAD provides financing to governments at favourable terms so they can transform their economies.\nOur investments empower rural communities to flourish.We are constantly exploring new financing mechanisms so we can have an even greater impact.\n \n\n\n\n\n\n\n\n\n\n\n\n\n\n\n\n\n\n\nMeasuring what matters\n\n\n\n\n\n\nTo understand whether IFAD is making a difference, we systematically measure results, including through impact assessments.\nEach of our projects includes a monitoring and evaluation system for collecting data so we can identify what works. Our Independent Office of Evaluation conducts independent project evaluations which offer additional insights.\n\n\n\n\n\n\n\n\n\n\n\n\n\n\n\n\n\n\nEmbracing innovation\n\n\n\n\n\n\nIn an increasingly complex world, we cannot rely on conventional approaches to respond to today’s challenges.\nWe need innovation to make rural development sustainable, resilient and equitable. IFAD tests and learns to deliver better results. We co-finance proven innovations that can be scaled up.\n\n\n\n\n\n\n\n\n\n\nKeep exploring\n\n\n\n\n\n\n\n\n\n\n\n\n\n\n\n\n Rural finance With access to finance, rural people can produce more, grow their enterprises, earn more and get through hard times. \n\n  Explore more \n           \n \n\n\n\n\n\n\n\n\n\n\n\n\n\n\n\n\n\n Assessing our impact IFAD's impact assessments accurately measure and report on the impact of our work \n\n  Explore more \n           \n \n\n\n\n\n\n\n\n\n\n\n\n\n\n\n\n\n Who we are IFAD is the world’s fund for transforming agriculture, rural economies and food systems. \n\n  Explore more \n           \n \n\n\n\n\n\n\n\n\n\n\n\n\n\n\n\n       Please configure the desktop menu widget below\n      \n\n\n\n\n\n\n\n\n About IFAD \n Who we are   Where we work   What we do   Action Areas   Knowledge & Data \n\n\n For Member States \n Member States interactive platform \n\n\n For Investors \n Investors   Finance \n\n\n For Job seekers \n Work with us   Frequently Asked Questions \n\n\n For Media \n News   Media Contacts   Image Bank \n\n\n Get Involved \n Join an event   Rural Voices   Opinions & Insights \n\n\n\n\n\n\n\n\n\n\n\n\n\n       Please configure the mobile menu widget below\n      \n\n\n\n\n\n\n\n\n Who we are \n\n\n\n What we do \n\n\n\n Where we work \n\n\n\n Action Areas \n\n\n\n Knowledge & Data \n\n\n\n Get Involved \n\n\n\n News and Stories \n\n\n\n\n\n\n\n\n\n\n\n\n\n  \n Legal  Privacy notice  Fraudulent job offers  Contact us Stay connected\n\n\n\n  \n\n  \n\n  \n\n  \n\n  \n\n \n\n\n\n\n\n\n\n\nHidden\n\nWhat we do - IFAD\n\n\n\n\n\n\n\n\n\n\n\n\n\n\n\n\n\n\n\n\n\n\n\n\n\n\n\n\n\n\n\n\n\n\n\nWhat we do\n\n\n\n\n\n\n\n\n\n©IFAD/David Rose \n\n\n\n\n\n\n\nSimply put, IFAD invests in rural people.\n\n\n\n\n\n\n\n\n\n\n\n\n\n\n\n\n\n\n\nProgrammes for progress\n\n\n\n\n\nWe reduce poverty, improve nutrition and increase food production by providing loans and grants that transform rural communities.\nWe develop solutions with governments and rural people themselves so that our investments solve the issues at hand while laying the foundations for thriving rural economies in the long-term.\n\n\n\n \n\n\n\n\n\n\n\n\n\n\n\n\n\n\n\n\n\n\n\n\n\nFor rural people, by rural people\n\n\n\n\n\n\nThe more engaged rural people are as decision-makers, the greater our impact. That's why we take a people-centred approach to transforming rural livelihoods. \nOur investments support those most vulnerable, including women, youth, Indigenous Peoples and persons with disabilities. In this way, our work not only helps rural people grow and earn more, but it also promotes gender equality and inclusiveness.\n\n\n\n \n\n\n\n\n\n\n\n\n\n\n\n\n\n\n\n\n\n\n\n\n\n\n\n\n\n\n\n\n\n\n\n\nMaking finance work for those who need it most\n\n\n\n\n\n\nThe global financial system often excludes those who could benefit most from it. That’s why IFAD provides financing to governments at favourable terms so they can transform their economies.\nOur investments empower rural communities to flourish.We are constantly exploring new financing mechanisms so we can have an even greater impact.\n \n\n\n\n\n\n\n\n\n\n\n\n\n\n\n\n\n\n\nMeasuring what matters\n\n\n\n\n\n\nTo understand whether IFAD is making a difference, we systematically measure results, including through impact assessments.\nEach of our projects includes a monitoring and evaluation system for collecting data so we can identify what works. Our Independent Office of Evaluation conducts independent project evaluations which offer additional insights.\n\n\n\n\n\n\n\n\n\n\n\n\n\n\n\n\n\n\nEmbracing innovation\n\n\n\n\n\n\nIn an increasingly complex world, we cannot rely on conventional approaches to respond to today’s challenges.\nWe need innovation to make rural development sustainable, resilient and equitable. IFAD tests and learns to deliver better results. We co-finance proven innovations that can be scaled up.\n\n\n\n\n\n\n\n\n\n\nKeep exploring\n\n\n\n\n\n\n\n\n\n\n\n\n\n\n\n\n Rural finance With access to finance, rural people can produce more, grow their enterprises, earn more and get through hard times. \n\n  Explore more \n           \n \n\n\n\n\n\n\n\n\n\n\n\n\n\n\n\n\n\n Assessing our impact IFAD's impact assessments accurately measure and report on the impact of our work \n\n  Explore more \n           \n \n\n\n\n\n\n\n\n\n\n\n\n\n\n\n\n\n Who we are IFAD is the world’s fund for transforming agriculture, rural economies and food systems. \n\n  Explore more \n           \n \n\n\n\n\n\n\n\n\n\n\n\n\n\n\n\n       Please configure the desktop menu widget below\n      \n\n\n\n\n\n\n\n\n About IFAD \n Who we are   Where we work   What we do   Action Areas   Knowledge & Data \n\n\n For Member States \n Member States interactive platform \n\n\n For Investors \n Investors   Finance \n\n\n For Job seekers \n Work with us   Frequently Asked Questions \n\n\n For Media \n News   Media Contacts   Image Bank \n\n\n Get Involved \n Join an event   Rural Voices   Opinions & Insights \n\n\n\n\n\n\n\n\n\n\n\n\n\n       Please configure the mobile menu widget below\n      \n\n\n\n\n\n\n\n\n Who we are \n\n\n\n What we do \n\n\n\n Where we work \n\n\n\n Action Areas \n\n\n\n Knowledge & Data \n\n\n\n Get Involved \n\n\n\n News and Stories \n\n\n\n\n\n\n\n\n\n\n\n\n\n  \n Legal  Privacy notice  Fraudulent job offers  Contact us Stay connected\n\n\n\n  \n\n  \n\n  \n\n  \n\n  \n\n \n\n\n\n\n\n\n\n\nHidden\n\nWhat we do\n\n\n\n\n\n\n\n\n\n©IFAD/David Rose \n\n\n\n\n\n\n\nSimply put, IFAD invests in rural people.\n\n\n\n\n\n\n\n\n\n\n\n\n\n\n\n\n\n\n\nProgrammes for progress\n\n\n\n\n\nWe reduce poverty, improve nutrition and increase food production by providing loans and grants that transform rural communities.\nWe develop solutions with governments and rural people themselves so that our investments solve the issues at hand while laying the foundations for thriving rural economies in the long-term.\n\n\n\n \n\n\n\n\n\n\n\n\n\n\n\n\n\n\n\n\n\n\n\n\n\nFor rural people, by rural people\n\n\n\n\n\n\nThe more engaged rural people are as decision-makers, the greater our impact. That's why we take a people-centred approach to transforming rural livelihoods. \nOur investments support those most vulnerable, including women, youth, Indigenous Peoples and persons with disabilities. In this way, our work not only helps rural people grow and earn more, but it also promotes gender equality and inclusiveness.\n\n\n\n \n\n\n\n\n\n\n\n\n\n\n\n\n\n\n\n\n\n\n\n\n\n\n\n\n\n\n\n\n\n\n\n\nMaking finance work for those who need it most\n\n\n\n\n\n\nThe global financial system often excludes those who could benefit most from it. That’s why IFAD provides financing to governments at favourable terms so they can transform their economies.\nOur investments empower rural communities to flourish.We are constantly exploring new financing mechanisms so we can have an even greater impact.\n \n\n\n\n\n\n\n\n\n\n\n\n\n\n\n\n\n\n\nMeasuring what matters\n\n\n\n\n\n\nTo understand whether IFAD is making a difference, we systematically measure results, including through impact assessments.\nEach of our projects includes a monitoring and evaluation system for collecting data so we can identify what works. Our Independent Office of Evaluation conducts independent project evaluations which offer additional insights.\n\n\n\n\n\n\n\n\n\n\n\n\n\n\n\n\n\n\nEmbracing innovation\n\n\n\n\n\n\nIn an increasingly complex world, we cannot rely on conventional approaches to respond to today’s challenges.\nWe need innovation to make rural development sustainable, resilient and equitable. IFAD tests and learns to deliver better results. We co-finance proven innovations that can be scaled up.\n\n\n\n\n\n\n\n\n\n\nKeep exploring\n\n\n\n\n\n\n\n\n\n\n\n\n\n\n\n\n Rural finance With access to finance, rural people can produce more, grow their enterprises, earn more and get through hard times. \n\n  Explore more \n           \n \n\n\n\n\n\n\n\n\n\n\n\n\n\n\n\n\n\n Assessing our impact IFAD's impact assessments accurately measure and report on the impact of our work \n\n  Explore more \n           \n \n\n\n\n\n\n\n\n\n\n\n\n\n\n\n\n\n Who we are IFAD is the world’s fund for transforming agriculture, rural economies and food systems. \n\n  Explore more \n           \n \n\n\n\n\n\n\n\n\n\n\n\n\n\n\n\n       Please configure the desktop menu widget below\n      \n\n\n\n\n\n\n\n\n About IFAD \n Who we are   Where we work   What we do   Action Areas   Knowledge & Data \n\n\n For Member States \n Member States interactive platform \n\n\n For Investors \n Investors   Finance \n\n\n For Job seekers \n Work with us   Frequently Asked Questions \n\n\n For Media \n News   Media Contacts   Image Bank \n\n\n Get Involved \n Join an event   Rural Voices   Opinions & Insights \n\n\n\n\n\n\n\n\n\n\n\n\n\n       Please configure the mobile menu widget below\n      \n\n\n\n\n\n\n\n\n Who we are \n\n\n\n What we do \n\n\n\n Where we work \n\n\n\n Action Areas \n\n\n\n Knowledge & Data \n\n\n\n Get Involved \n\n\n\n News and Stories \n\n\n\n\n\n\n\n\n\n\n\n\n\n  \n Legal  Privacy notice  Fraudulent job offers  Contact us Stay connected\n\nWhat we do\n\n\n\n\n\n\n\n\n\n©IFAD/David Rose \n\n\n\n\n\n\n\nSimply put, IFAD invests in rural people.\n\n\n\n\n\n\n\n\n\n\n\n\n\n\n\n\n\n\n\nProgrammes for progress\n\n\n\n\n\nWe reduce poverty, improve nutrition and increase food production by providing loans and grants that transform rural communities.\nWe develop solutions with governments and rural people themselves so that our investments solve the issues at hand while laying the foundations for thriving rural economies in the long-term.\n\n\n\n \n\n\n\n\n\n\n\n\n\n\n\n\n\n\n\n\n\n\n\n\n\nFor rural people, by rural people\n\n\n\n\n\n\nThe more engaged rural people are as decision-makers, the greater our impact. That's why we take a people-centred approach to transforming rural livelihoods. \nOur investments support those most vulnerable, including women, youth, Indigenous Peoples and persons with disabilities. In this way, our work not only helps rural people grow and earn more, but it also promotes gender equality and inclusiveness.\n\n\n\n \n\n\n\n\n\n\n\n\n\n\n\n\n\n\n\n\n\n\n\n\n\n\n\n\n\n\n\n\n\n\n\n\nMaking finance work for those who need it most\n\n\n\n\n\n\nThe global financial system often excludes those who could benefit most from it. That’s why IFAD provides financing to governments at favourable terms so they can transform their economies.\nOur investments empower rural communities to flourish.We are constantly exploring new financing mechanisms so we can have an even greater impact.\n \n\n\n\n\n\n\n\n\n\n\n\n\n\n\n\n\n\n\nMeasuring what matters\n\n\n\n\n\n\nTo understand whether IFAD is making a difference, we systematically measure results, including through impact assessments.\nEach of our projects includes a monitoring and evaluation system for collecting data so we can identify what works. Our Independent Office of Evaluation conducts independent project evaluations which offer additional insights.\n\n\n\n\n\n\n\n\n\n\n\n\n\n\n\n\n\n\nEmbracing innovation\n\n\n\n\n\n\nIn an increasingly complex world, we cannot rely on conventional approaches to respond to today’s challenges.\nWe need innovation to make rural development sustainable, resilient and equitable. IFAD tests and learns to deliver better results. We co-finance proven innovations that can be scaled up.\n\n\n\n\n\n\n\n\n\n\nKeep exploring\n\n\n\n\n\n\n\n\n\n\n\n\n\n\n\n\n Rural finance With access to finance, rural people can produce more, grow their enterprises, earn more and get through hard times. \n\n  Explore more \n           \n \n\n\n\n\n\n\n\n\n\n\n\n\n\n\n\n\n\n Assessing our impact IFAD's impact assessments accurately measure and report on the impact of our work \n\n  Explore more \n           \n \n\n\n\n\n\n\n\n\n\n\n\n\n\n\n\n\n Who we are IFAD is the world’s fund for transforming agriculture, rural economies and food systems. \n\n  Explore more \n           \n \n\n\n\n\n\n\n\n\n\n\n\n\n\n\n\n       Please configure the desktop menu widget below\n      \n\n\n\n\n\n\n\n\n About IFAD \n Who we are   Where we work   What we do   Action Areas   Knowledge & Data \n\n\n For Member States \n Member States interactive platform \n\n\n For Investors \n Investors   Finance \n\n\n For Job seekers \n Work with us   Frequently Asked Questions \n\n\n For Media \n News   Media Contacts   Image Bank \n\n\n Get Involved \n Join an event   Rural Voices   Opinions & Insights \n\n\n\n\n\n\n\n\n\n\n\n\n\n       Please configure the mobile menu widget below\n      \n\n\n\n\n\n\n\n\n Who we are \n\n\n\n What we do \n\n\n\n Where we work \n\n\n\n Action Areas \n\n\n\n Knowledge & Data \n\n\n\n Get Involved \n\n\n\n News and Stories \n\n\n\n\n\n\n\n\n\n\n\n\n\n  \n Legal  Privacy notice  Fraudulent job offers  Contact us Stay connected\n\nWhat we do\n\n\n\n\n\n\n\n\n\n©IFAD/David Rose \n\n\n\n\n\n\n\nSimply put, IFAD invests in rural people.\n\n\n\n\n\n\n\n\n\n\n\n\n\n\n\n\n\n\n\nProgrammes for progress\n\n\n\n\n\nWe reduce poverty, improve nutrition and increase food production by providing loans and grants that transform rural communities.\nWe develop solutions with governments and rural people themselves so that our investments solve the issues at hand while laying the foundations for thriving rural economies in the long-term.\n\n\n\n \n\n\n\n\n\n\n\n\n\n\n\n\n\n\n\n\n\n\n\n\n\nFor rural people, by rural people\n\n\n\n\n\n\nThe more engaged rural people are as decision-makers, the greater our impact. That's why we take a people-centred approach to transforming rural livelihoods. \nOur investments support those most vulnerable, including women, youth, Indigenous Peoples and persons with disabilities. In this way, our work not only helps rural people grow and earn more, but it also promotes gender equality and inclusiveness.\n\n\n\n \n\n\n\n\n\n\n\n\n\n\n\n\n\n\n\n\n\n\n\n\n\n\n\n\n\n\n\n\n\n\n\n\nMaking finance work for those who need it most\n\n\n\n\n\n\nThe global financial system often excludes those who could benefit most from it. That’s why IFAD provides financing to governments at favourable terms so they can transform their economies.\nOur investments empower rural communities to flourish.We are constantly exploring new financing mechanisms so we can have an even greater impact.\n \n\n\n\n\n\n\n\n\n\n\n\n\n\n\n\n\n\n\nMeasuring what matters\n\n\n\n\n\n\nTo understand whether IFAD is making a difference, we systematically measure results, including through impact assessments.\nEach of our projects includes a monitoring and evaluation system for collecting data so we can identify what works. Our Independent Office of Evaluation conducts independent project evaluations which offer additional insights.\n\n\n\n\n\n\n\n\n\n\n\n\n\n\n\n\n\n\nEmbracing innovation\n\n\n\n\n\n\nIn an increasingly complex world, we cannot rely on conventional approaches to respond to today’s challenges.\nWe need innovation to make rural development sustainable, resilient and equitable. IFAD tests and learns to deliver better results. We co-finance proven innovations that can be scaled up.\n\n\n\n\n\n\n\n\n\n\nKeep exploring\n\n\n\n\n\n\n\n\n\n\n\n\n\n\n\n\n Rural finance With access to finance, rural people can produce more, grow their enterprises, earn more and get through hard times. \n\n  Explore more \n           \n \n\n\n\n\n\n\n\n\n\n\n\n\n\n\n\n\n\n Assessing our impact IFAD's impact assessments accurately measure and report on the impact of our work \n\n  Explore more \n           \n \n\n\n\n\n\n\n\n\n\n\n\n\n\n\n\n\n Who we are IFAD is the world’s fund for transforming agriculture, rural economies and food systems. \n\n  Explore more\n\nWhat we do\n\nWhat we do\n\nWhat we do\n\nWhat we do\n\n©IFAD/David Rose\n\n©IFAD/David Rose\n\n©IFAD/David Rose\n\nSimply put, IFAD invests in rural people.\n\nSimply put, IFAD invests in rural people.\n\nSimply put, IFAD invests in rural people.\n\nProgrammes for progress\n\n\n\n\n\nWe reduce poverty, improve nutrition and increase food production by providing loans and grants that transform rural communities.\nWe develop solutions with governments and rural people themselves so that our investments solve the issues at hand while laying the foundations for thriving rural economies in the long-term.\n\n\n\n \n\n\n\n\n\n\n\n\n\n\n\n\n\n\n\n\n\n\n\n\n\nFor rural people, by rural people\n\n\n\n\n\n\nThe more engaged rural people are as decision-makers, the greater our impact. That's why we take a people-centred approach to transforming rural livelihoods. \nOur investments support those most vulnerable, including women, youth, Indigenous Peoples and persons with disabilities. In this way, our work not only helps rural people grow and earn more, but it also promotes gender equality and inclusiveness.\n\nProgrammes for progress\n\n\n\n\n\nWe reduce poverty, improve nutrition and increase food production by providing loans and grants that transform rural communities.\nWe develop solutions with governments and rural people themselves so that our investments solve the issues at hand while laying the foundations for thriving rural economies in the long-term.\n\n\n\n \n\n\n\n\n\n\n\n\n\n\n\n\n\n\n\n\n\n\n\n\n\nFor rural people, by rural people\n\n\n\n\n\n\nThe more engaged rural people are as decision-makers, the greater our impact. That's why we take a people-centred approach to transforming rural livelihoods. \nOur investments support those most vulnerable, including women, youth, Indigenous Peoples and persons with disabilities. In this way, our work not only helps rural people grow and earn more, but it also promotes gender equality and inclusiveness.\n\nProgrammes for progress\n\n\n\n\n\nWe reduce poverty, improve nutrition and increase food production by providing loans and grants that transform rural communities.\nWe develop solutions with governments and rural people themselves so that our investments solve the issues at hand while laying the foundations for thriving rural economies in the long-term.\n\nProgrammes for progress\n\nProgrammes for progress\n\nWe reduce poverty, improve nutrition and increase food production by providing loans and grants that transform rural communities.\nWe develop solutions with governments and rural people themselves so that our investments solve the issues at hand while laying the foundations for thriving rural economies in the long-term.\n\nWe reduce poverty, improve nutrition and increase food production by providing loans and grants that transform rural communities.\nWe develop solutions with governments and rural people themselves so that our investments solve the issues at hand while laying the foundations for thriving rural economies in the long-term.\n\nWe reduce poverty, improve nutrition and increase food production by providing loans and grants that transform rural communities.\nWe develop solutions with governments and rural people themselves so that our investments solve the issues at hand while laying the foundations for thriving rural economies in the long-term.\n\nWe reduce poverty, improve nutrition and increase food production by providing loans and grants that transform rural communities.\n\nWe develop solutions with governments and rural people themselves so that our investments solve the issues at hand while laying the foundations for thriving rural economies in the long-term.\n\nFor rural people, by rural people\n\n\n\n\n\n\nThe more engaged rural people are as decision-makers, the greater our impact. That's why we take a people-centred approach to transforming rural livelihoods. \nOur investments support those most vulnerable, including women, youth, Indigenous Peoples and persons with disabilities. In this way, our work not only helps rural people grow and earn more, but it also promotes gender equality and inclusiveness.\n\nFor rural people, by rural people\n\nFor rural people, by rural people\n\nThe more engaged rural people are as decision-makers, the greater our impact. That's why we take a people-centred approach to transforming rural livelihoods. \nOur investments support those most vulnerable, including women, youth, Indigenous Peoples and persons with disabilities. In this way, our work not only helps rural people grow and earn more, but it also promotes gender equality and inclusiveness.\n\nThe more engaged rural people are as decision-makers, the greater our impact. That's why we take a people-centred approach to transforming rural livelihoods. \nOur investments support those most vulnerable, including women, youth, Indigenous Peoples and persons with disabilities. In this way, our work not only helps rural people grow and earn more, but it also promotes gender equality and inclusiveness.\n\nThe more engaged rural people are as decision-makers, the greater our impact. That's why we take a people-centred approach to transforming rural livelihoods. \nOur investments support those most vulnerable, including women, youth, Indigenous Peoples and persons with disabilities. In this way, our work not only helps rural people grow and earn more, but it also promotes gender equality and inclusiveness.\n\nThe more engaged rural people are as decision-makers, the greater our impact. That's why we take a people-centred approach to transforming rural livelihoods.\n\nOur investments support those most vulnerable, including women, youth, Indigenous Peoples and persons with disabilities. In this way, our work not only helps rural people grow and earn more, but it also promotes gender equality and inclusiveness.\n\nMaking finance work for those who need it most\n\n\n\n\n\n\nThe global financial system often excludes those who could benefit most from it. That’s why IFAD provides financing to governments at favourable terms so they can transform their economies.\nOur investments empower rural communities to flourish.We are constantly exploring new financing mechanisms so we can have an even greater impact.\n \n\n\n\n\n\n\n\n\n\n\n\n\n\n\n\n\n\n\nMeasuring what matters\n\n\n\n\n\n\nTo understand whether IFAD is making a difference, we systematically measure results, including through impact assessments.\nEach of our projects includes a monitoring and evaluation system for collecting data so we can identify what works. Our Independent Office of Evaluation conducts independent project evaluations which offer additional insights.\n\n\n\n\n\n\n\n\n\n\n\n\n\n\n\n\n\n\nEmbracing innovation\n\n\n\n\n\n\nIn an increasingly complex world, we cannot rely on conventional approaches to respond to today’s challenges.\nWe need innovation to make rural development sustainable, resilient and equitable. IFAD tests and learns to deliver better results. We co-finance proven innovations that can be scaled up.\n\nMaking finance work for those who need it most\n\n\n\n\n\n\nThe global financial system often excludes those who could benefit most from it. That’s why IFAD provides financing to governments at favourable terms so they can transform their economies.\nOur investments empower rural communities to flourish.We are constantly exploring new financing mechanisms so we can have an even greater impact.\n \n\n\n\n\n\n\n\n\n\n\n\n\n\n\n\n\n\n\nMeasuring what matters\n\n\n\n\n\n\nTo understand whether IFAD is making a difference, we systematically measure results, including through impact assessments.\nEach of our projects includes a monitoring and evaluation system for collecting data so we can identify what works. Our Independent Office of Evaluation conducts independent project evaluations which offer additional insights.\n\n\n\n\n\n\n\n\n\n\n\n\n\n\n\n\n\n\nEmbracing innovation\n\n\n\n\n\n\nIn an increasingly complex world, we cannot rely on conventional approaches to respond to today’s challenges.\nWe need innovation to make rural development sustainable, resilient and equitable. IFAD tests and learns to deliver better results. We co-finance proven innovations that can be scaled up.\n\nMaking finance work for those who need it most\n\n\n\n\n\n\nThe global financial system often excludes those who could benefit most from it. That’s why IFAD provides financing to governments at favourable terms so they can transform their economies.\nOur investments empower rural communities to flourish.We are constantly exploring new financing mechanisms so we can have an even greater impact.\n\nMaking finance work for those who need it most\n\nMaking finance work for those who need it most\n\nThe global financial system often excludes those who could benefit most from it. That’s why IFAD provides financing to governments at favourable terms so they can transform their economies.\nOur investments empower rural communities to flourish.We are constantly exploring new financing mechanisms so we can have an even greater impact.\n\nThe global financial system often excludes those who could benefit most from it. That’s why IFAD provides financing to governments at favourable terms so they can transform their economies.\nOur investments empower rural communities to flourish.We are constantly exploring new financing mechanisms so we can have an even greater impact.\n\nThe global financial system often excludes those who could benefit most from it. That’s why IFAD provides financing to governments at favourable terms so they can transform their economies.\nOur investments empower rural communities to flourish.We are constantly exploring new financing mechanisms so we can have an even greater impact.\n\nThe global financial system often excludes those who could benefit most from it. That’s why IFAD provides financing to governments at favourable terms so they can transform their economies.\n\nOur investments empower rural communities to flourish.We are constantly exploring new financing mechanisms so we can have an even greater impact.\n\nMeasuring what matters\n\n\n\n\n\n\nTo understand whether IFAD is making a difference, we systematically measure results, including through impact assessments.\nEach of our projects includes a monitoring and evaluation system for collecting data so we can identify what works. Our Independent Office of Evaluation conducts independent project evaluations which offer additional insights.\n\nMeasuring what matters\n\nMeasuring what matters\n\nTo understand whether IFAD is making a difference, we systematically measure results, including through impact assessments.\nEach of our projects includes a monitoring and evaluation system for collecting data so we can identify what works. Our Independent Office of Evaluation conducts independent project evaluations which offer additional insights.\n\nTo understand whether IFAD is making a difference, we systematically measure results, including through impact assessments.\nEach of our projects includes a monitoring and evaluation system for collecting data so we can identify what works. Our Independent Office of Evaluation conducts independent project evaluations which offer additional insights.\n\nTo understand whether IFAD is making a difference, we systematically measure results, including through impact assessments.\nEach of our projects includes a monitoring and evaluation system for collecting data so we can identify what works. Our Independent Office of Evaluation conducts independent project evaluations which offer additional insights.\n\nTo understand whether IFAD is making a difference, we systematically measure results, including through impact assessments.\n\nEach of our projects includes a monitoring and evaluation system for collecting data so we can identify what works. Our Independent Office of Evaluation conducts independent project evaluations which offer additional insights.\n\nEmbracing innovation\n\n\n\n\n\n\nIn an increasingly complex world, we cannot rely on conventional approaches to respond to today’s challenges.\nWe need innovation to make rural development sustainable, resilient and equitable. IFAD tests and learns to deliver better results. We co-finance proven innovations that can be scaled up.\n\nEmbracing innovation\n\nEmbracing innovation\n\nIn an increasingly complex world, we cannot rely on conventional approaches to respond to today’s challenges.\nWe need innovation to make rural development sustainable, resilient and equitable. IFAD tests and learns to deliver better results. We co-finance proven innovations that can be scaled up.\n\nIn an increasingly complex world, we cannot rely on conventional approaches to respond to today’s challenges.\nWe need innovation to make rural development sustainable, resilient and equitable. IFAD tests and learns to deliver better results. We co-finance proven innovations that can be scaled up.\n\nIn an increasingly complex world, we cannot rely on conventional approaches to respond to today’s challenges.\nWe need innovation to make rural development sustainable, resilient and equitable. IFAD tests and learns to deliver better results. We co-finance proven innovations that can be scaled up.\n\nIn an increasingly complex world, we cannot rely on conventional approaches to respond to today’s challenges.\n\nWe need innovation to make rural development sustainable, resilient and equitable. IFAD tests and learns to deliver better results. We co-finance proven innovations that can be scaled up.\n\nKeep exploring\n\n\n\n\n\n\n\n\n\n\n\n\n\n\n\n\n Rural finance With access to finance, rural people can produce more, grow their enterprises, earn more and get through hard times. \n\n  Explore more \n           \n \n\n\n\n\n\n\n\n\n\n\n\n\n\n\n\n\n\n Assessing our impact IFAD's impact assessments accurately measure and report on the impact of our work \n\n  Explore more \n           \n \n\n\n\n\n\n\n\n\n\n\n\n\n\n\n\n\n Who we are IFAD is the world’s fund for transforming agriculture, rural economies and food systems. \n\n  Explore more\n\nKeep exploring\n\nKeep exploring\n\nRural finance With access to finance, rural people can produce more, grow their enterprises, earn more and get through hard times. \n\n  Explore more \n           \n \n\n\n\n\n\n\n\n\n\n\n\n\n\n\n\n\n\n Assessing our impact IFAD's impact assessments accurately measure and report on the impact of our work \n\n  Explore more \n           \n \n\n\n\n\n\n\n\n\n\n\n\n\n\n\n\n\n Who we are IFAD is the world’s fund for transforming agriculture, rural economies and food systems. \n\n  Explore more\n\nRural finance With access to finance, rural people can produce more, grow their enterprises, earn more and get through hard times. \n\n  Explore more \n           \n \n\n\n\n\n\n\n\n\n\n\n\n\n\n\n\n\n\n Assessing our impact IFAD's impact assessments accurately measure and report on the impact of our work \n\n  Explore more \n           \n \n\n\n\n\n\n\n\n\n\n\n\n\n\n\n\n\n Who we are IFAD is the world’s fund for transforming agriculture, rural economies and food systems. \n\n  Explore more\n\nRural finance With access to finance, rural people can produce more, grow their enterprises, earn more and get through hard times. \n\n  Explore more\n\nRural finance With access to finance, rural people can produce more, grow their enterprises, earn more and get through hard times. \n\n  Explore more\n\nRural finance With access to finance, rural people can produce more, grow their enterprises, earn more and get through hard times. \n\n  Explore more\n\nRural finance With access to finance, rural people can produce more, grow their enterprises, earn more and get through hard times. \n\n  Explore more\n\nRural finance With access to finance, rural people can produce more, grow their enterprises, earn more and get through hard times. \n\n  Explore more\n\nRural finance With access to finance, rural people can produce more, grow their enterprises, earn more and get through hard times.\n\nRural finance With access to finance, rural people can produce more, grow their enterprises, earn more and get through hard times.\n\nRural finance\n\nWith access to finance, rural people can produce more, grow their enterprises, earn more and get through hard times.\n\nAssessing our impact IFAD's impact assessments accurately measure and report on the impact of our work \n\n  Explore more\n\nAssessing our impact IFAD's impact assessments accurately measure and report on the impact of our work \n\n  Explore more\n\nAssessing our impact IFAD's impact assessments accurately measure and report on the impact of our work \n\n  Explore more\n\nAssessing our impact IFAD's impact assessments accurately measure and report on the impact of our work \n\n  Explore more\n\nAssessing our impact IFAD's impact assessments accurately measure and report on the impact of our work \n\n  Explore more\n\nAssessing our impact IFAD's impact assessments accurately measure and report on the impact of our work\n\nAssessing our impact IFAD's impact assessments accurately measure and report on the impact of our work\n\nAssessing our impact\n\nIFAD's impact assessments accurately measure and report on the impact of our work\n\nWho we are IFAD is the world’s fund for transforming agriculture, rural economies and food systems. \n\n  Explore more\n\nWho we are IFAD is the world’s fund for transforming agriculture, rural economies and food systems. \n\n  Explore more\n\nWho we are IFAD is the world’s fund for transforming agriculture, rural economies and food systems. \n\n  Explore more\n\nWho we are IFAD is the world’s fund for transforming agriculture, rural economies and food systems. \n\n  Explore more\n\nWho we are IFAD is the world’s fund for transforming agriculture, rural economies and food systems. \n\n  Explore more\n\nWho we are IFAD is the world’s fund for transforming agriculture, rural economies and food systems.\n\nWho we are IFAD is the world’s fund for transforming agriculture, rural economies and food systems.\n\nWho we are\n\nIFAD is the world’s fund for transforming agriculture, rural economies and food systems.\n\nPlease configure the desktop menu widget below\n      \n\n\n\n\n\n\n\n\n About IFAD \n Who we are   Where we work   What we do   Action Areas   Knowledge & Data \n\n\n For Member States \n Member States interactive platform \n\n\n For Investors \n Investors   Finance \n\n\n For Job seekers \n Work with us   Frequently Asked Questions \n\n\n For Media \n News   Media Contacts   Image Bank \n\n\n Get Involved \n Join an event   Rural Voices   Opinions & Insights \n\n\n\n\n\n\n\n\n\n\n\n\n\n       Please configure the mobile menu widget below\n      \n\n\n\n\n\n\n\n\n Who we are \n\n\n\n What we do \n\n\n\n Where we work \n\n\n\n Action Areas \n\n\n\n Knowledge & Data \n\n\n\n Get Involved \n\n\n\n News and Stories \n\n\n\n\n\n\n\n\n\n\n\n\n\n  \n Legal  Privacy notice  Fraudulent job offers  Contact us Stay connected\n\nPlease configure the desktop menu widget below\n      \n\n\n\n\n\n\n\n\n About IFAD \n Who we are   Where we work   What we do   Action Areas   Knowledge & Data \n\n\n For Member States \n Member States interactive platform \n\n\n For Investors \n Investors   Finance \n\n\n For Job seekers \n Work with us   Frequently Asked Questions \n\n\n For Media \n News   Media Contacts   Image Bank \n\n\n Get Involved \n Join an event   Rural Voices   Opinions & Insights \n\n\n\n\n\n\n\n\n\n\n\n\n\n       Please configure the mobile menu widget below\n      \n\n\n\n\n\n\n\n\n Who we are \n\n\n\n What we do \n\n\n\n Where we work \n\n\n\n Action Areas \n\n\n\n Knowledge & Data \n\n\n\n Get Involved \n\n\n\n News and Stories \n\n\n\n\n\n\n\n\n\n\n\n\n\n  \n Legal  Privacy notice  Fraudulent job offers  Contact us Stay connected\n\nPlease configure the desktop menu widget below\n      \n\n\n\n\n\n\n\n\n About IFAD \n Who we are   Where we work   What we do   Action Areas   Knowledge & Data \n\n\n For Member States \n Member States interactive platform \n\n\n For Investors \n Investors   Finance \n\n\n For Job seekers \n Work with us   Frequently Asked Questions \n\n\n For Media \n News   Media Contacts   Image Bank \n\n\n Get Involved \n Join an event   Rural Voices   Opinions & Insights \n\n\n\n\n\n\n\n\n\n\n\n\n\n       Please configure the mobile menu widget below\n      \n\n\n\n\n\n\n\n\n Who we are \n\n\n\n What we do \n\n\n\n Where we work \n\n\n\n Action Areas \n\n\n\n Knowledge & Data \n\n\n\n Get Involved \n\n\n\n News and Stories \n\n\n\n\n\n\n\n\n\n\n\n\n\n  \n Legal  Privacy notice  Fraudulent job offers  Contact us Stay connected\n\nPlease configure the desktop menu widget below\n      \n\n\n\n\n\n\n\n\n About IFAD \n Who we are   Where we work   What we do   Action Areas   Knowledge & Data \n\n\n For Member States \n Member States interactive platform \n\n\n For Investors \n Investors   Finance \n\n\n For Job seekers \n Work with us   Frequently Asked Questions \n\n\n For Media \n News   Media Contacts   Image Bank \n\n\n Get Involved \n Join an event   Rural Voices   Opinions & Insights \n\n\n\n\n\n\n\n\n\n\n\n\n\n       Please configure the mobile menu widget below\n      \n\n\n\n\n\n\n\n\n Who we are \n\n\n\n What we do \n\n\n\n Where we work \n\n\n\n Action Areas \n\n\n\n Knowledge & Data \n\n\n\n Get Involved \n\n\n\n News and Stories\n\nPlease configure the desktop menu widget below\n      \n\n\n\n\n\n\n\n\n About IFAD \n Who we are   Where we work   What we do   Action Areas   Knowledge & Data \n\n\n For Member States \n Member States interactive platform \n\n\n For Investors \n Investors   Finance \n\n\n For Job seekers \n Work with us   Frequently Asked Questions \n\n\n For Media \n News   Media Contacts   Image Bank \n\n\n Get Involved \n Join an event   Rural Voices   Opinions & Insights\n\nPlease configure the desktop menu widget below\n\nAbout IFAD \n Who we are   Where we work   What we do   Action Areas   Knowledge & Data \n\n\n For Member States \n Member States interactive platform \n\n\n For Investors \n Investors   Finance \n\n\n For Job seekers \n Work with us   Frequently Asked Questions \n\n\n For Media \n News   Media Contacts   Image Bank \n\n\n Get Involved \n Join an event   Rural Voices   Opinions & Insights\n\nAbout IFAD \n Who we are   Where we work   What we do   Action Areas   Knowledge & Data \n\n\n For Member States \n Member States interactive platform \n\n\n For Investors \n Investors   Finance \n\n\n For Job seekers \n Work with us   Frequently Asked Questions \n\n\n For Media \n News   Media Contacts   Image Bank \n\n\n Get Involved \n Join an event   Rural Voices   Opinions & Insights\n\nAbout IFAD \n Who we are   Where we work   What we do   Action Areas   Knowledge & Data \n\n\n For Member States \n Member States interactive platform \n\n\n For Investors \n Investors   Finance \n\n\n For Job seekers \n Work with us   Frequently Asked Questions \n\n\n For Media \n News   Media Contacts   Image Bank \n\n\n Get Involved \n Join an event   Rural Voices   Opinions & Insights\n\nAbout IFAD \n Who we are   Where we work   What we do   Action Areas   Knowledge & Data \n\n\n For Member States \n Member States interactive platform \n\n\n For Investors \n Investors   Finance \n\n\n For Job seekers \n Work with us   Frequently Asked Questions \n\n\n For Media \n News   Media Contacts   Image Bank \n\n\n Get Involved \n Join an event   Rural Voices   Opinions & Insights\n\nAbout IFAD \n Who we are   Where we work   What we do   Action Areas   Knowledge & Data \n\n\n For Member States \n Member States interactive platform \n\n\n For Investors \n Investors   Finance \n\n\n For Job seekers \n Work with us   Frequently Asked Questions \n\n\n For Media \n News   Media Contacts   Image Bank \n\n\n Get Involved \n Join an event   Rural Voices   Opinions & Insights\n\nAbout IFAD \n Who we are   Where we work   What we do   Action Areas   Knowledge & Data \n\n\n For Member States \n Member States interactive platform \n\n\n For Investors \n Investors   Finance \n\n\n For Job seekers \n Work with us   Frequently Asked Questions \n\n\n For Media \n News   Media Contacts   Image Bank \n\n\n Get Involved \n Join an event   Rural Voices   Opinions & Insights\n\nAbout IFAD \n Who we are   Where we work   What we do   Action Areas   Knowledge & Data \n\n\n For Member States \n Member States interactive platform \n\n\n For Investors \n Investors   Finance \n\n\n For Job seekers \n Work with us   Frequently Asked Questions \n\n\n For Media \n News   Media Contacts   Image Bank \n\n\n Get Involved \n Join an event   Rural Voices   Opinions & Insights\n\nAbout IFAD \n Who we are   Where we work   What we do   Action Areas   Knowledge & Data \n\n\n For Member States \n Member States interactive platform \n\n\n For Investors \n Investors   Finance \n\n\n For Job seekers \n Work with us   Frequently Asked Questions \n\n\n For Media \n News   Media Contacts   Image Bank \n\n\n Get Involved \n Join an event   Rural Voices   Opinions & Insights\n\nAbout IFAD \n Who we are   Where we work   What we do   Action Areas   Knowledge & Data\n\nWho we are   Where we work   What we do   Action Areas   Knowledge & Data\n\nFor Member States \n Member States interactive platform\n\nMember States interactive platform\n\nFor Investors \n Investors   Finance\n\nInvestors   Finance\n\nFor Job seekers \n Work with us   Frequently Asked Questions\n\nWork with us   Frequently Asked Questions\n\nFor Media \n News   Media Contacts   Image Bank\n\nNews   Media Contacts   Image Bank\n\nGet Involved \n Join an event   Rural Voices   Opinions & Insights\n\nJoin an event   Rural Voices   Opinions & Insights\n\nPlease configure the mobile menu widget below\n      \n\n\n\n\n\n\n\n\n Who we are \n\n\n\n What we do \n\n\n\n Where we work \n\n\n\n Action Areas \n\n\n\n Knowledge & Data \n\n\n\n Get Involved \n\n\n\n News and Stories\n\nPlease configure the mobile menu widget below\n\nWho we are \n\n\n\n What we do \n\n\n\n Where we work \n\n\n\n Action Areas \n\n\n\n Knowledge & Data \n\n\n\n Get Involved \n\n\n\n News and Stories\n\nWho we are \n\n\n\n What we do \n\n\n\n Where we work \n\n\n\n Action Areas \n\n\n\n Knowledge & Data \n\n\n\n Get Involved \n\n\n\n News and Stories\n\nWho we are \n\n\n\n What we do \n\n\n\n Where we work \n\n\n\n Action Areas \n\n\n\n Knowledge & Data \n\n\n\n Get Involved \n\n\n\n News and Stories\n\nWho we are \n\n\n\n What we do \n\n\n\n Where we work \n\n\n\n Action Areas \n\n\n\n Knowledge & Data \n\n\n\n Get Involved \n\n\n\n News and Stories\n\nWho we are \n\n\n\n What we do \n\n\n\n Where we work \n\n\n\n Action Areas \n\n\n\n Knowledge & Data \n\n\n\n Get Involved \n\n\n\n News and Stories\n\nWho we are \n\n\n\n What we do \n\n\n\n Where we work \n\n\n\n Action Areas \n\n\n\n Knowledge & Data \n\n\n\n Get Involved \n\n\n\n News and Stories\n\nWho we are \n\n\n\n What we do \n\n\n\n Where we work \n\n\n\n Action Areas \n\n\n\n Knowledge & Data \n\n\n\n Get Involved \n\n\n\n News and Stories\n\nWho we are \n\n\n\n What we do \n\n\n\n Where we work \n\n\n\n Action Areas \n\n\n\n Knowledge & Data \n\n\n\n Get Involved \n\n\n\n News and Stories\n\nWho we are\n\nWhat we do\n\nWhere we work\n\nAction Areas\n\nKnowledge & Data\n\nGet Involved\n\nNews and Stories\n\nLegal  Privacy notice  Fraudulent job offers  Contact us Stay connected\n\nLegal  Privacy notice  Fraudulent job offers  Contact us Stay connected",
  "date": "",
  "source_type": "other",
  "extracted_at": "2025-04-07T14:27:58.468105",
  "metadata": {
    "description": "Simply put, IFAD invests in rural people. We do this by financing programmes, measuring results, innovating and working with rural people themselves.",
    "keywords": "What we do",
    "og:site_name": "IFAD",
    "og:type": "website"
  },
  "relevance_score": 0.42500000000000004,
  "summary": "We develop solutions with governments and rural people themselves so that our investments solve the issues at hand while laying the foundations for thriving rural economies in the long-term. For rural people, by rural people\n\n\n\n\n\n\nThe more engaged rural people are as decision-makers, the greater our impact. Keep exploring\n\n\n\n\n\n\n\n\n\n\n\n\n\n\n\n\n Rural finance With access to finance, rural people can produce more, grow their enterprises, earn more and get through hard times. Explore more \n           \n \n\n\n\n\n\n\n\n\n\n\n\n\n\n\n\n\n\n Assessing our impact IFAD's impact assessments accurately measure and report on the impact of our work \n\n  Explore more \n           \n \n\n\n\n\n\n\n\n\n\n\n\n\n\n\n\n\n Who we are IFAD is the world’s fund for transforming agriculture, rural economies and food systems. Explore more \n           \n \n\n\n\n\n\n\n\n\n\n\n\n\n\n\n\n       Please configure the desktop menu widget below\n      \n\n\n\n\n\n\n\n\n About IFAD \n Who we are   Where we work   What we do   Action Areas   Knowledge & Data \n\n\n For Member States \n Member States interactive platform \n\n\n For Investors \n Investors   Finance \n\n\n For Job seekers \n Work with us   Frequently Asked Questions \n\n\n For Media \n News   Media Contacts   Image Bank \n\n\n Get Involved \n Join an event   Rural Voices   Opinions & Insights \n\n\n\n\n\n\n\n\n\n\n\n\n\n       Please configure the mobile menu widget below\n      \n\n\n\n\n\n\n\n\n Who we are \n\n\n\n What we do \n\n\n\n Where we work \n\n\n\n Action Areas \n\n\n\n Knowledge & Data \n\n\n\n Get Involved \n\n\n\n News and Stories \n\n\n\n\n\n\n\n\n\n\n\n\n\n  \n Legal  Privacy notice  Fraudulent job offers  Contact us Stay connected\n\n\n\n  \n\n  \n\n  \n\n  \n\n  \n\n \n\n\n\n\n\n\n\n\nHidden\n\nWhat we do - IFAD\n\n\n\n\n\n\n\n\n\n\n\n\n\n\n\n\n\n\n\n\n\n\n\n\n\n\n\n\n\n\n\n\n\n\n\nWhat we do\n\n\n\n\n\n\n\n\n\n©IFAD/David Rose \n\n\n\n\n\n\n\nSimply put, IFAD invests in rural people. We develop solutions with governments and rural people themselves so that our investments solve the issues at hand while laying the foundations for thriving rural economies in the long-term. For rural people, by rural people\n\n\n\n\n\n\nThe more engaged rural people are as decision-makers, the greater our impact. Keep exploring\n\n\n\n\n\n\n\n\n\n\n\n\n\n\n\n\n Rural finance With access to finance, rural people can produce more, grow their enterprises, earn more and get through hard times. Explore more \n           \n \n\n\n\n\n\n\n\n\n\n\n\n\n\n\n\n\n\n Assessing our impact IFAD's impact assessments accurately measure and report on the impact of our work \n\n  Explore more \n           \n \n\n\n\n\n\n\n\n\n\n\n\n\n\n\n\n\n Who we are IFAD is the world’s fund for transforming agriculture, rural economies and food systems. Explore more \n           \n \n\n\n\n\n\n\n\n\n\n\n\n\n\n\n\n       Please configure the desktop menu widget below\n      \n\n\n\n\n\n\n\n\n About IFAD \n Who we are   Where we work   What we do   Action Areas   Knowledge & Data \n\n\n For Member States \n Member States interactive platform \n\n\n For Investors \n Investors   Finance \n\n\n For Job seekers \n Work with us   Frequently Asked Questions \n\n\n For Media \n News   Media Contacts   Image Bank \n\n\n Get Involved \n Join an event   Rural Voices   Opinions & Insights \n\n\n\n\n\n\n\n\n\n\n\n\n\n       Please configure the mobile menu widget below\n      \n\n\n\n\n\n\n\n\n Who we are \n\n\n\n What we do \n\n\n\n Where we work \n\n\n\n Action Areas \n\n\n\n Knowledge & Data \n\n\n\n Get Involved \n\n\n\n News and Stories \n\n\n\n\n\n\n\n\n\n\n\n\n\n  \n Legal  Privacy notice  Fraudulent job offers  Contact us Stay connected\n\n\n\n  \n\n  \n\n  \n\n  \n\n  \n\n \n\n\n\n\n\n\n\n\nHidden\n\nWhat we do - IFAD\n\n\n\n\n\n\n\n\n\n\n\n\n\n\n\n\n\n\n\n\n\n\n\n\n\n\n\n\n\n\n\n\n\n\n\nWhat we do\n\n\n\n\n\n\n\n\n\n©IFAD/David Rose \n\n\n\n\n\n\n\nSimply put, IFAD invests in rural people. We develop solutions with governments and rural people themselves so that our investments solve the issues at hand while laying the foundations for thriving rural economies in the long-term. For rural people, by rural people\n\n\n\n\n\n\nThe more engaged rural people are as decision-makers, the greater our impact. Keep exploring\n\n\n\n\n\n\n\n\n\n\n\n\n\n\n\n\n Rural finance With access to finance, rural people can produce more, grow their enterprises, earn more and get through hard times. Explore more \n           \n \n\n\n\n\n\n\n\n\n\n\n\n\n\n\n\n\n\n Assessing our impact IFAD's impact assessments accurately measure and report on the impact of our work \n\n  Explore more \n           \n \n\n\n\n\n\n\n\n\n\n\n\n\n\n\n\n\n Who we are IFAD is the world’s fund for transforming agriculture, rural economies and food systems. Explore more \n           \n \n\n\n\n\n\n\n\n\n\n\n\n\n\n\n\n       Please configure the desktop menu widget below\n      \n\n\n\n\n\n\n\n\n About IFAD \n Who we are   Where we work   What we do   Action Areas   Knowledge & Data \n\n\n For Member States \n Member States interactive platform \n\n\n For Investors \n Investors   Finance \n\n\n For Job seekers \n Work with us   Frequently Asked Questions \n\n\n For Media \n News   Media Contacts   Image Bank \n\n\n Get Involved \n Join an event   Rural Voices   Opinions & Insights \n\n\n\n\n\n\n\n\n\n\n\n\n\n       Please configure the mobile menu widget below\n      \n\n\n\n\n\n\n\n\n Who we are \n\n\n\n What we do \n\n\n\n Where we work \n\n\n\n Action Areas \n\n\n\n Knowledge & Data \n\n\n\n Get Involved \n\n\n\n News and Stories \n\n\n\n\n\n\n\n\n\n\n\n\n\n  \n Legal  Privacy notice  Fraudulent job offers  Contact us Stay connected\n\n\n\n  \n\n  \n\n  \n\n  \n\n  \n\n \n\n\n\n\n\n\n\n\nHidden\n\nWhat we do\n\n\n\n\n\n\n\n\n\n©IFAD/David Rose \n\n\n\n\n\n\n\nSimply put, IFAD invests in rural people. We develop solutions with governments and rural people themselves so that our investments solve the issues at hand while laying the foundations for thriving rural economies in the long-term. For rural people, by rural people\n\n\n\n\n\n\nThe more engaged rural people are as decision-makers, the greater our impact. Keep exploring\n\n\n\n\n\n\n\n\n\n\n\n\n\n\n\n\n Rural finance With access to finance, rural people can produce more, grow their enterprises, earn more and get through hard times. Explore more \n           \n \n\n\n\n\n\n\n\n\n\n\n\n\n\n\n\n\n\n Assessing our impact IFAD's impact assessments accurately measure and report on the impact of our work \n\n  Explore more \n           \n \n\n\n\n\n\n\n\n\n\n\n\n\n\n\n\n\n Who we are IFAD is the world’s fund for transforming agriculture, rural economies and food systems. Explore more \n           \n \n\n\n\n\n\n\n\n\n\n\n\n\n\n\n\n       Please configure the desktop menu widget below\n      \n\n\n\n\n\n\n\n\n About IFAD \n Who we are   Where we work   What we do   Action Areas   Knowledge & Data \n\n\n For Member States \n Member States interactive platform \n\n\n For Investors \n Investors   Finance \n\n\n For Job seekers \n Work with us   Frequently Asked Questions \n\n\n For Media \n News   Media Contacts   Image Bank \n\n\n Get Involved \n Join an event   Rural Voices   Opinions & Insights \n\n\n\n\n\n\n\n\n\n\n\n\n\n       Please configure the mobile menu widget below\n      \n\n\n\n\n\n\n\n\n Who we are \n\n\n\n What we do \n\n\n\n Where we work \n\n\n\n Action Areas \n\n\n\n Knowledge & Data \n\n\n\n Get Involved \n\n\n\n News and Stories \n\n\n\n\n\n\n\n\n\n\n\n\n\n  \n Legal  Privacy notice  Fraudulent job offers  Contact us Stay connected\n\nWhat we do\n\n\n\n\n\n\n\n\n\n©IFAD/David Rose \n\n\n\n\n\n\n\nSimply put, IFAD invests in rural people. We develop solutions with governments and rural people themselves so that our investments solve the issues at hand while laying the foundations for thriving rural economies in the long-term. For rural people, by rural people\n\n\n\n\n\n\nThe more engaged rural people are as decision-makers, the greater our impact. Keep exploring\n\n\n\n\n\n\n\n\n\n\n\n\n\n\n\n\n Rural finance With access to finance, rural people can produce more, grow their enterprises, earn more and get through hard times. Explore more \n           \n \n\n\n\n\n\n\n\n\n\n\n\n\n\n\n\n\n\n Assessing our impact IFAD's impact assessments accurately measure and report on the impact of our work \n\n  Explore more \n           \n \n\n\n\n\n\n\n\n\n\n\n\n\n\n\n\n\n Who we are IFAD is the world’s fund for transforming agriculture, rural economies and food systems. Explore more \n           \n \n\n\n\n\n\n\n\n\n\n\n\n\n\n\n\n       Please configure the desktop menu widget below\n      \n\n\n\n\n\n\n\n\n About IFAD \n Who we are   Where we work   What we do   Action Areas   Knowledge & Data \n\n\n For Member States \n Member States interactive platform \n\n\n For Investors \n Investors   Finance \n\n\n For Job seekers \n Work with us   Frequently Asked Questions \n\n\n For Media \n News   Media Contacts   Image Bank \n\n\n Get Involved \n Join an event   Rural Voices   Opinions & Insights \n\n\n\n\n\n\n\n\n\n\n\n\n\n       Please configure the mobile menu widget below\n      \n\n\n\n\n\n\n\n\n Who we are \n\n\n\n What we do \n\n\n\n Where we work \n\n\n\n Action Areas \n\n\n\n Knowledge & Data \n\n\n\n Get Involved \n\n\n\n News and Stories \n\n\n\n\n\n\n\n\n\n\n\n\n\n  \n Legal  Privacy notice  Fraudulent job offers  Contact us Stay connected\n\nWhat we do\n\n\n\n\n\n\n\n\n\n©IFAD/David Rose \n\n\n\n\n\n\n\nSimply put, IFAD invests in rural people. We develop solutions with governments and rural people themselves so that our investments solve the issues at hand while laying the foundations for thriving rural economies in the long-term. For rural people, by rural people\n\n\n\n\n\n\nThe more engaged rural people are as decision-makers, the greater our impact. Keep exploring\n\n\n\n\n\n\n\n\n\n\n\n\n\n\n\n\n Rural finance With access to finance, rural people can produce more, grow their enterprises, earn more and get through hard times. Explore more \n           \n \n\n\n\n\n\n\n\n\n\n\n\n\n\n\n\n\n\n Assessing our impact IFAD's impact assessments accurately measure and report on the impact of our work \n\n  Explore more \n           \n \n\n\n\n\n\n\n\n\n\n\n\n\n\n\n\n\n Who we are IFAD is the world’s fund for transforming agriculture, rural economies and food systems. We develop solutions with governments and rural people themselves so that our investments solve the issues at hand while laying the foundations for thriving rural economies in the long-term. For rural people, by rural people\n\n\n\n\n\n\nThe more engaged rural people are as decision-makers, the greater our impact. For rural people, by rural people\n\n\n\n\n\n\nThe more engaged rural people are as decision-makers, the greater our impact. For rural people, by rural people\n\n\n\n\n\n\nThe more engaged rural people are as decision-makers, the greater our impact. For rural people, by rural people\n\nFor rural people, by rural people\n\nThe more engaged rural people are as decision-makers, the greater our impact. Keep exploring\n\n\n\n\n\n\n\n\n\n\n\n\n\n\n\n\n Rural finance With access to finance, rural people can produce more, grow their enterprises, earn more and get through hard times. Explore more \n           \n \n\n\n\n\n\n\n\n\n\n\n\n\n\n\n\n\n\n Assessing our impact IFAD's impact assessments accurately measure and report on the impact of our work \n\n  Explore more \n           \n \n\n\n\n\n\n\n\n\n\n\n\n\n\n\n\n\n Who we are IFAD is the world’s fund for transforming agriculture, rural economies and food systems. Explore more\n\nKeep exploring\n\nKeep exploring\n\nRural finance With access to finance, rural people can produce more, grow their enterprises, earn more and get through hard times. Explore more \n           \n \n\n\n\n\n\n\n\n\n\n\n\n\n\n\n\n\n\n Assessing our impact IFAD's impact assessments accurately measure and report on the impact of our work \n\n  Explore more \n           \n \n\n\n\n\n\n\n\n\n\n\n\n\n\n\n\n\n Who we are IFAD is the world’s fund for transforming agriculture, rural economies and food systems. Explore more\n\nRural finance With access to finance, rural people can produce more, grow their enterprises, earn more and get through hard times. Explore more \n           \n \n\n\n\n\n\n\n\n\n\n\n\n\n\n\n\n\n\n Assessing our impact IFAD's impact assessments accurately measure and report on the impact of our work \n\n  Explore more \n           \n \n\n\n\n\n\n\n\n\n\n\n\n\n\n\n\n\n Who we are IFAD is the world’s fund for transforming agriculture, rural economies and food systems. Explore more\n\nRural finance With access to finance, rural people can produce more, grow their enterprises, earn more and get through hard times. Explore more\n\nRural finance With access to finance, rural people can produce more, grow their enterprises, earn more and get through hard times. Explore more\n\nRural finance With access to finance, rural people can produce more, grow their enterprises, earn more and get through hard times. Explore more\n\nRural finance With access to finance, rural people can produce more, grow their enterprises, earn more and get through hard times. Explore more\n\nRural finance With access to finance, rural people can produce more, grow their enterprises, earn more and get through hard times. Explore more\n\nRural finance With access to finance, rural people can produce more, grow their enterprises, earn more and get through hard times. Rural finance With access to finance, rural people can produce more, grow their enterprises, earn more and get through hard times. Rural finance\n\nWith access to finance, rural people can produce more, grow their enterprises, earn more and get through hard times. Assessing our impact IFAD's impact assessments accurately measure and report on the impact of our work \n\n  Explore more\n\nAssessing our impact IFAD's impact assessments accurately measure and report on the impact of our work \n\n  Explore more\n\nAssessing our impact IFAD's impact assessments accurately measure and report on the impact of our work \n\n  Explore more\n\nAssessing our impact IFAD's impact assessments accurately measure and report on the impact of our work \n\n  Explore more\n\nAssessing our impact IFAD's impact assessments accurately measure and report on the impact of our work \n\n  Explore more\n\nAssessing our impact IFAD's impact assessments accurately measure and report on the impact of our work\n\nAssessing our impact IFAD's impact assessments accurately measure and report on the impact of our work\n\nAssessing our impact\n\nIFAD's impact assessments accurately measure and report on the impact of our work\n\nWho we are IFAD is the world’s fund for transforming agriculture, rural economies and food systems. Please configure the desktop menu widget below\n      \n\n\n\n\n\n\n\n\n About IFAD \n Who we are   Where we work   What we do   Action Areas   Knowledge & Data \n\n\n For Member States \n Member States interactive platform \n\n\n For Investors \n Investors   Finance \n\n\n For Job seekers \n Work with us   Frequently Asked Questions \n\n\n For Media \n News   Media Contacts   Image Bank \n\n\n Get Involved \n Join an event   Rural Voices   Opinions & Insights \n\n\n\n\n\n\n\n\n\n\n\n\n\n       Please configure the mobile menu widget below\n      \n\n\n\n\n\n\n\n\n Who we are \n\n\n\n What we do \n\n\n\n Where we work \n\n\n\n Action Areas \n\n\n\n Knowledge & Data \n\n\n\n Get Involved \n\n\n\n News and Stories \n\n\n\n\n\n\n\n\n\n\n\n\n\n  \n Legal  Privacy notice  Fraudulent job offers  Contact us Stay connected\n\nPlease configure the desktop menu widget below\n      \n\n\n\n\n\n\n\n\n About IFAD \n Who we are   Where we work   What we do   Action Areas   Knowledge & Data \n\n\n For Member States \n Member States interactive platform \n\n\n For Investors \n Investors   Finance \n\n\n For Job seekers \n Work with us   Frequently Asked Questions \n\n\n For Media \n News   Media Contacts   Image Bank \n\n\n Get Involved \n Join an event   Rural Voices   Opinions & Insights \n\n\n\n\n\n\n\n\n\n\n\n\n\n       Please configure the mobile menu widget below\n      \n\n\n\n\n\n\n\n\n Who we are \n\n\n\n What we do \n\n\n\n Where we work \n\n\n\n Action Areas \n\n\n\n Knowledge & Data \n\n\n\n Get Involved \n\n\n\n News and Stories \n\n\n\n\n\n\n\n\n\n\n\n\n\n  \n Legal  Privacy notice  Fraudulent job offers  Contact us Stay connected\n\nPlease configure the desktop menu widget below\n      \n\n\n\n\n\n\n\n\n About IFAD \n Who we are   Where we work   What we do   Action Areas   Knowledge & Data \n\n\n For Member States \n Member States interactive platform \n\n\n For Investors \n Investors   Finance \n\n\n For Job seekers \n Work with us   Frequently Asked Questions \n\n\n For Media \n News   Media Contacts   Image Bank \n\n\n Get Involved \n Join an event   Rural Voices   Opinions & Insights \n\n\n\n\n\n\n\n\n\n\n\n\n\n       Please configure the mobile menu widget below\n      \n\n\n\n\n\n\n\n\n Who we are \n\n\n\n What we do \n\n\n\n Where we work \n\n\n\n Action Areas \n\n\n\n Knowledge & Data \n\n\n\n Get Involved \n\n\n\n News and Stories \n\n\n\n\n\n\n\n\n\n\n\n\n\n  \n Legal  Privacy notice  Fraudulent job offers  Contact us Stay connected\n\nPlease configure the desktop menu widget below\n      \n\n\n\n\n\n\n\n\n About IFAD \n Who we are   Where we work   What we do   Action Areas   Knowledge & Data \n\n\n For Member States \n Member States interactive platform \n\n\n For Investors \n Investors   Finance \n\n\n For Job seekers \n Work with us   Frequently Asked Questions \n\n\n For Media \n News   Media Contacts   Image Bank \n\n\n Get Involved \n Join an event   Rural Voices   Opinions & Insights \n\n\n\n\n\n\n\n\n\n\n\n\n\n       Please configure the mobile menu widget below\n      \n\n\n\n\n\n\n\n\n Who we are \n\n\n\n What we do \n\n\n\n Where we work \n\n\n\n Action Areas \n\n\n\n Knowledge & Data \n\n\n\n Get Involved \n\n\n\n News and Stories\n\nPlease configure the desktop menu widget below\n      \n\n\n\n\n\n\n\n\n About IFAD \n Who we are   Where we work   What we do   Action Areas   Knowledge & Data \n\n\n For Member States \n Member States interactive platform \n\n\n For Investors \n Investors   Finance \n\n\n For Job seekers \n Work with us   Frequently Asked Questions \n\n\n For Media \n News   Media Contacts   Image Bank \n\n\n Get Involved \n Join an event   Rural Voices   Opinions & Insights\n\nPlease configure the desktop menu widget below\n\nAbout IFAD \n Who we are   Where we work   What we do   Action Areas   Knowledge & Data \n\n\n For Member States \n Member States interactive platform \n\n\n For Investors \n Investors   Finance \n\n\n For Job seekers \n Work with us   Frequently Asked Questions \n\n\n For Media \n News   Media Contacts   Image Bank \n\n\n Get Involved \n Join an event   Rural Voices   Opinions & Insights\n\nAbout IFAD \n Who we are   Where we work   What we do   Action Areas   Knowledge & Data \n\n\n For Member States \n Member States interactive platform \n\n\n For Investors \n Investors   Finance \n\n\n For Job seekers \n Work with us   Frequently Asked Questions \n\n\n For Media \n News   Media Contacts   Image Bank \n\n\n Get Involved \n Join an event   Rural Voices   Opinions & Insights\n\nAbout IFAD \n Who we are   Where we work   What we do   Action Areas   Knowledge & Data \n\n\n For Member States \n Member States interactive platform \n\n\n For Investors \n Investors   Finance \n\n\n For Job seekers \n Work with us   Frequently Asked Questions \n\n\n For Media \n News   Media Contacts   Image Bank \n\n\n Get Involved \n Join an event   Rural Voices   Opinions & Insights\n\nAbout IFAD \n Who we are   Where we work   What we do   Action Areas   Knowledge & Data \n\n\n For Member States \n Member States interactive platform \n\n\n For Investors \n Investors   Finance \n\n\n For Job seekers \n Work with us   Frequently Asked Questions \n\n\n For Media \n News   Media Contacts   Image Bank \n\n\n Get Involved \n Join an event   Rural Voices   Opinions & Insights\n\nAbout IFAD \n Who we are   Where we work   What we do   Action Areas   Knowledge & Data \n\n\n For Member States \n Member States interactive platform \n\n\n For Investors \n Investors   Finance \n\n\n For Job seekers \n Work with us   Frequently Asked Questions \n\n\n For Media \n News   Media Contacts   Image Bank \n\n\n Get Involved \n Join an event   Rural Voices   Opinions & Insights\n\nAbout IFAD \n Who we are   Where we work   What we do   Action Areas   Knowledge & Data \n\n\n For Member States \n Member States interactive platform \n\n\n For Investors \n Investors   Finance \n\n\n For Job seekers \n Work with us   Frequently Asked Questions \n\n\n For Media \n News   Media Contacts   Image Bank \n\n\n Get Involved \n Join an event   Rural Voices   Opinions & Insights\n\nAbout IFAD \n Who we are   Where we work   What we do   Action Areas   Knowledge & Data \n\n\n For Member States \n Member States interactive platform \n\n\n For Investors \n Investors   Finance \n\n\n For Job seekers \n Work with us   Frequently Asked Questions \n\n\n For Media \n News   Media Contacts   Image Bank \n\n\n Get Involved \n Join an event   Rural Voices   Opinions & Insights\n\nAbout IFAD \n Who we are   Where we work   What we do   Action Areas   Knowledge & Data \n\n\n For Member States \n Member States interactive platform \n\n\n For Investors \n Investors   Finance \n\n\n For Job seekers \n Work with us   Frequently Asked Questions \n\n\n For Media \n News   Media Contacts   Image Bank \n\n\n Get Involved \n Join an event   Rural Voices   Opinions & Insights\n\nAbout IFAD \n Who we are   Where we work   What we do   Action Areas   Knowledge & Data\n\nWho we are   Where we work   What we do   Action Areas   Knowledge & Data\n\nFor Member States \n Member States interactive platform\n\nMember States interactive platform\n\nFor Investors \n Investors   Finance\n\nInvestors   Finance\n\nFor Job seekers \n Work with us   Frequently Asked Questions\n\nWork with us   Frequently Asked Questions\n\nFor Media \n News   Media Contacts   Image Bank\n\nNews   Media Contacts   Image Bank\n\nGet Involved \n Join an event   Rural Voices   Opinions & Insights\n\nJoin an event   Rural Voices   Opinions & Insights\n\nPlease configure the mobile menu widget below\n      \n\n\n\n\n\n\n\n\n Who we are \n\n\n\n What we do \n\n\n\n Where we work \n\n\n\n Action Areas \n\n\n\n Knowledge & Data \n\n\n\n Get Involved \n\n\n\n News and Stories\n\nPlease configure the mobile menu widget below\n\nWho we are \n\n\n\n What we do \n\n\n\n Where we work \n\n\n\n Action Areas \n\n\n\n Knowledge & Data \n\n\n\n Get Involved \n\n\n\n News and Stories\n\nWho we are \n\n\n\n What we do \n\n\n\n Where we work \n\n\n\n Action Areas \n\n\n\n Knowledge & Data \n\n\n\n Get Involved \n\n\n\n News and Stories\n\nWho we are \n\n\n\n What we do \n\n\n\n Where we work \n\n\n\n Action Areas \n\n\n\n Knowledge & Data \n\n\n\n Get Involved \n\n\n\n News and Stories\n\nWho we are \n\n\n\n What we do \n\n\n\n Where we work \n\n\n\n Action Areas \n\n\n\n Knowledge & Data \n\n\n\n Get Involved \n\n\n\n News and Stories\n\nWho we are \n\n\n\n What we do \n\n\n\n Where we work \n\n\n\n Action Areas \n\n\n\n Knowledge & Data \n\n\n\n Get Involved \n\n\n\n News and Stories\n\nWho we are \n\n\n\n What we do \n\n\n\n Where we work \n\n\n\n Action Areas \n\n\n\n Knowledge & Data \n\n\n\n Get Involved \n\n\n\n News and Stories\n\nWho we are \n\n\n\n What we do \n\n\n\n Where we work \n\n\n\n Action Areas \n\n\n\n Knowledge & Data \n\n\n\n Get Involved \n\n\n\n News and Stories\n\nWho we are \n\n\n\n What we do \n\n\n\n Where we work \n\n\n\n Action Areas \n\n\n\n Knowledge & Data \n\n\n\n Get Involved \n\n\n\n News and Stories\n\nWho we are\n\nWhat we do\n\nWhere we work\n\nAction Areas\n\nKnowledge & Data\n\nGet Involved\n\nNews and Stories\n\nLegal  Privacy notice  Fraudulent job offers  Contact us Stay connected\n\nLegal  Privacy notice  Fraudulent job offers  Contact us Stay connected",
  "entities": {
    "countries": [],
    "organizations": [
      "un",
      "who"
    ],
    "key_issues": [
      "issue",
      "challenge",
      "matter",
      "state",
      "government",
      "solution",
      "approach",
      "program",
      "action",
      "development",
      "financial",
      "investment",
      "un",
      "foundation"
    ]
  },
  "committee": "Economic and Social Council",
  "topic": "Promoting rural development in Africa"
}