{
  "url": "https://www.ifad.org/en/our-vision",
  "title": "Our Vision",
  "text": "Our Vision - IFAD\n\n\n\n\n\n\n\n\n\n\n\n\n\n\n\n\n\n\n\n\n\n\n\n\n\n\n\n\n\n\n\n\n\n\n\nOur vision\n\n\n\n\n\n\n\n\n ©IFAD/GMB Akash\n\n\n\n\n\n\n\n\n\n\n\n\n\n\nAt the International Fund for Agricultural Development, we envisage vibrant, inclusive and sustainable rural communities where people live free from poverty and hunger.  \n\n\n\n\n\n\n\n\n\n\n\n\n\nThree in four of the world's poorest people live in the rural areas of developing countries. Most of them depend on agriculture for their livelihoods – and in turn, produce much of the food we eat. It’s not an easy job.  \nMany rural people living in poverty face massive economic, social and environmental challenges – from climate change and food insecurity, to inequality, conflict and lack of access to resources.  \nThese overlapping problems cannot be solved working alone. As an assembler of development finance, we partner with governments, the private sector, civil society and others to provide grants and concessional and low-interest loans to developing countries. This helps to address critical needs and support rural people as they lead their own development.  \nIFAD-supported projects promote prosperity, food security and resilience by connecting rural poor people to the finance, markets, technology and knowledge they need to address their biggest challenges. \nWe catalyse public and private investments, advocate for policies that empower rural people and their institutions, and promote innovation in order to achieve lasting, systemic change for rural communities in every region of the world.  \nThroughout our work, we emphasize the importance of inclusion and equity, focusing special attention on gender and groups that are often overlooked, like youth, Indigenous Peoples and persons with disabilities. We strive to foster an organizational culture built around these values.   \nFurthermore, as a results-driven organization, we conduct rigorous monitoring and evaluation to assess our impact and scale up what we know works. That’s one of the reasons we are a top-rated development organization. \n\n\n\n\n\n\n\n\n\n\n\n\n\n\n\n\n\n\nOur objectives \n\n\n\n\n\n\nIFAD is the only UN agency exclusively dedicated to transforming agriculture, rural economies and food systems. We invest in the millions of people who are most at risk of being left behind: poor, small-scale food producers living in rural areas.\nWe support rural people in some of the most remote and fragile contexts so that they can: \n\nProduce and sell more \nEat more nutritious foods  \nManage natural resources well  \nEarn more money \nAccess new technologies  \nAdapt to climate change \nBuild resilience to economic shocks, conflict and other crises \n\nThrough our investments, we help ensure that rural people lead their own change. \n\n\n\n\n\n\n\n\nBigger, better, smarter \n\n\n\n\n\n\nWe periodically update our strategic framework to align our objectives with the evolving global context.\nAdopted in 2016, IFAD’s Strategic Framework guides how we will progress toward our vision through 2025. It articulates our contribution to the 2030 Agenda for Sustainable Development and outlines how we will work in ways that are bigger, better and smarter.\nBigger, by mobilizing and leveraging greater investment in rural areas.\nBetter, by strengthening the quality of rural development programmes.\nSmarter, by sharpening our efficiency and delivering results in a more cost-effective way. \n\n\n\n\n\n\n\n\n\n\n\nKeep exploring\n\n\n\n\n\n\n\n\n\n\n\n\n\n\n\n\n IFAD's History IFAD has been investing in rural people and empowering them to improve their food security and nutrition since 1977. \n\n  Explore more \n           \n \n\n\n\n\n\n\n\n\n\n\n\n\n\n\n\n\n\n Leadership IFAD’s leadership manages resources and focuses on our mission. \n\n  Explore more \n           \n \n\n\n\n\n\n\n\n\n\n\n\n\n\n\n\nCorporate Document\n\n IFAD Strategic Framework 2016-2025 IFAD’s fifth Strategic Framework presents the overarching goal, principles of engagement, strategic objectives, outcomes and pillars of results delivery that will guide IFAD’s operations over the 2016-2025 period. It situates IFAD in the evolving global context and articulates its contribution to the 2030 Agenda for Sustainable Development (Agenda 2030). Agenda 2030 offers clear evidence that IFAD’s mandate of investing in rural people and enabling inclusive and sustainable transformation of rural areas, notably through smallholder agriculture-led growth, is of absolute global relevance today and over the coming decade. After several years of growth and reform, IFAD is now recognized for its experience, knowledge and performance in this domain; it stands ready to achieve greater impact and it is well positioned to play a larger role in helping countries fulfil their priorities relative to Agenda 2030. \n\n  Read now \n           \n \n\n\n\n\n\n\n\n\n\n\n\n\n\n\n\n       Please configure the desktop menu widget below\n      \n\n\n\n\n\n\n\n\n About IFAD \n Who we are   Where we work   What we do   Action Areas   Knowledge & Data \n\n\n For Member States \n Member States interactive platform \n\n\n For Investors \n Investors   Finance \n\n\n For Job seekers \n Work with us   Frequently Asked Questions \n\n\n For Media \n News   Media Contacts   Image Bank \n\n\n Get Involved \n Join an event   Rural Voices   Opinions & Insights \n\n\n\n\n\n\n\n\n\n\n\n\n\n       Please configure the mobile menu widget below\n      \n\n\n\n\n\n\n\n\n Who we are \n\n\n\n What we do \n\n\n\n Where we work \n\n\n\n Action Areas \n\n\n\n Knowledge & Data \n\n\n\n Get Involved \n\n\n\n News and Stories \n\n\n\n\n\n\n\n\n\n\n\n\n\n  \n Legal  Privacy notice  Fraudulent job offers  Contact us Stay connected\n\n\n\n  \n\n  \n\n  \n\n  \n\n  \n\n \n\n\n\n\n\n\n\n\nHidden\n\nOur Vision - IFAD\n\n\n\n\n\n\n\n\n\n\n\n\n\n\n\n\n\n\n\n\n\n\n\n\n\n\n\n\n\n\n\n\n\n\n\nOur vision\n\n\n\n\n\n\n\n\n ©IFAD/GMB Akash\n\n\n\n\n\n\n\n\n\n\n\n\n\n\nAt the International Fund for Agricultural Development, we envisage vibrant, inclusive and sustainable rural communities where people live free from poverty and hunger.  \n\n\n\n\n\n\n\n\n\n\n\n\n\nThree in four of the world's poorest people live in the rural areas of developing countries. Most of them depend on agriculture for their livelihoods – and in turn, produce much of the food we eat. It’s not an easy job.  \nMany rural people living in poverty face massive economic, social and environmental challenges – from climate change and food insecurity, to inequality, conflict and lack of access to resources.  \nThese overlapping problems cannot be solved working alone. As an assembler of development finance, we partner with governments, the private sector, civil society and others to provide grants and concessional and low-interest loans to developing countries. This helps to address critical needs and support rural people as they lead their own development.  \nIFAD-supported projects promote prosperity, food security and resilience by connecting rural poor people to the finance, markets, technology and knowledge they need to address their biggest challenges. \nWe catalyse public and private investments, advocate for policies that empower rural people and their institutions, and promote innovation in order to achieve lasting, systemic change for rural communities in every region of the world.  \nThroughout our work, we emphasize the importance of inclusion and equity, focusing special attention on gender and groups that are often overlooked, like youth, Indigenous Peoples and persons with disabilities. We strive to foster an organizational culture built around these values.   \nFurthermore, as a results-driven organization, we conduct rigorous monitoring and evaluation to assess our impact and scale up what we know works. That’s one of the reasons we are a top-rated development organization. \n\n\n\n\n\n\n\n\n\n\n\n\n\n\n\n\n\n\nOur objectives \n\n\n\n\n\n\nIFAD is the only UN agency exclusively dedicated to transforming agriculture, rural economies and food systems. We invest in the millions of people who are most at risk of being left behind: poor, small-scale food producers living in rural areas.\nWe support rural people in some of the most remote and fragile contexts so that they can: \n\nProduce and sell more \nEat more nutritious foods  \nManage natural resources well  \nEarn more money \nAccess new technologies  \nAdapt to climate change \nBuild resilience to economic shocks, conflict and other crises \n\nThrough our investments, we help ensure that rural people lead their own change. \n\n\n\n\n\n\n\n\nBigger, better, smarter \n\n\n\n\n\n\nWe periodically update our strategic framework to align our objectives with the evolving global context.\nAdopted in 2016, IFAD’s Strategic Framework guides how we will progress toward our vision through 2025. It articulates our contribution to the 2030 Agenda for Sustainable Development and outlines how we will work in ways that are bigger, better and smarter.\nBigger, by mobilizing and leveraging greater investment in rural areas.\nBetter, by strengthening the quality of rural development programmes.\nSmarter, by sharpening our efficiency and delivering results in a more cost-effective way. \n\n\n\n\n\n\n\n\n\n\n\nKeep exploring\n\n\n\n\n\n\n\n\n\n\n\n\n\n\n\n\n IFAD's History IFAD has been investing in rural people and empowering them to improve their food security and nutrition since 1977. \n\n  Explore more \n           \n \n\n\n\n\n\n\n\n\n\n\n\n\n\n\n\n\n\n Leadership IFAD’s leadership manages resources and focuses on our mission. \n\n  Explore more \n           \n \n\n\n\n\n\n\n\n\n\n\n\n\n\n\n\nCorporate Document\n\n IFAD Strategic Framework 2016-2025 IFAD’s fifth Strategic Framework presents the overarching goal, principles of engagement, strategic objectives, outcomes and pillars of results delivery that will guide IFAD’s operations over the 2016-2025 period. It situates IFAD in the evolving global context and articulates its contribution to the 2030 Agenda for Sustainable Development (Agenda 2030). Agenda 2030 offers clear evidence that IFAD’s mandate of investing in rural people and enabling inclusive and sustainable transformation of rural areas, notably through smallholder agriculture-led growth, is of absolute global relevance today and over the coming decade. After several years of growth and reform, IFAD is now recognized for its experience, knowledge and performance in this domain; it stands ready to achieve greater impact and it is well positioned to play a larger role in helping countries fulfil their priorities relative to Agenda 2030. \n\n  Read now \n           \n \n\n\n\n\n\n\n\n\n\n\n\n\n\n\n\n       Please configure the desktop menu widget below\n      \n\n\n\n\n\n\n\n\n About IFAD \n Who we are   Where we work   What we do   Action Areas   Knowledge & Data \n\n\n For Member States \n Member States interactive platform \n\n\n For Investors \n Investors   Finance \n\n\n For Job seekers \n Work with us   Frequently Asked Questions \n\n\n For Media \n News   Media Contacts   Image Bank \n\n\n Get Involved \n Join an event   Rural Voices   Opinions & Insights \n\n\n\n\n\n\n\n\n\n\n\n\n\n       Please configure the mobile menu widget below\n      \n\n\n\n\n\n\n\n\n Who we are \n\n\n\n What we do \n\n\n\n Where we work \n\n\n\n Action Areas \n\n\n\n Knowledge & Data \n\n\n\n Get Involved \n\n\n\n News and Stories \n\n\n\n\n\n\n\n\n\n\n\n\n\n  \n Legal  Privacy notice  Fraudulent job offers  Contact us Stay connected\n\n\n\n  \n\n  \n\n  \n\n  \n\n  \n\n \n\n\n\n\n\n\n\n\nHidden\n\nOur Vision - IFAD\n\n\n\n\n\n\n\n\n\n\n\n\n\n\n\n\n\n\n\n\n\n\n\n\n\n\n\n\n\n\n\n\n\n\n\nOur vision\n\n\n\n\n\n\n\n\n ©IFAD/GMB Akash\n\n\n\n\n\n\n\n\n\n\n\n\n\n\nAt the International Fund for Agricultural Development, we envisage vibrant, inclusive and sustainable rural communities where people live free from poverty and hunger.  \n\n\n\n\n\n\n\n\n\n\n\n\n\nThree in four of the world's poorest people live in the rural areas of developing countries. Most of them depend on agriculture for their livelihoods – and in turn, produce much of the food we eat. It’s not an easy job.  \nMany rural people living in poverty face massive economic, social and environmental challenges – from climate change and food insecurity, to inequality, conflict and lack of access to resources.  \nThese overlapping problems cannot be solved working alone. As an assembler of development finance, we partner with governments, the private sector, civil society and others to provide grants and concessional and low-interest loans to developing countries. This helps to address critical needs and support rural people as they lead their own development.  \nIFAD-supported projects promote prosperity, food security and resilience by connecting rural poor people to the finance, markets, technology and knowledge they need to address their biggest challenges. \nWe catalyse public and private investments, advocate for policies that empower rural people and their institutions, and promote innovation in order to achieve lasting, systemic change for rural communities in every region of the world.  \nThroughout our work, we emphasize the importance of inclusion and equity, focusing special attention on gender and groups that are often overlooked, like youth, Indigenous Peoples and persons with disabilities. We strive to foster an organizational culture built around these values.   \nFurthermore, as a results-driven organization, we conduct rigorous monitoring and evaluation to assess our impact and scale up what we know works. That’s one of the reasons we are a top-rated development organization. \n\n\n\n\n\n\n\n\n\n\n\n\n\n\n\n\n\n\nOur objectives \n\n\n\n\n\n\nIFAD is the only UN agency exclusively dedicated to transforming agriculture, rural economies and food systems. We invest in the millions of people who are most at risk of being left behind: poor, small-scale food producers living in rural areas.\nWe support rural people in some of the most remote and fragile contexts so that they can: \n\nProduce and sell more \nEat more nutritious foods  \nManage natural resources well  \nEarn more money \nAccess new technologies  \nAdapt to climate change \nBuild resilience to economic shocks, conflict and other crises \n\nThrough our investments, we help ensure that rural people lead their own change. \n\n\n\n\n\n\n\n\nBigger, better, smarter \n\n\n\n\n\n\nWe periodically update our strategic framework to align our objectives with the evolving global context.\nAdopted in 2016, IFAD’s Strategic Framework guides how we will progress toward our vision through 2025. It articulates our contribution to the 2030 Agenda for Sustainable Development and outlines how we will work in ways that are bigger, better and smarter.\nBigger, by mobilizing and leveraging greater investment in rural areas.\nBetter, by strengthening the quality of rural development programmes.\nSmarter, by sharpening our efficiency and delivering results in a more cost-effective way. \n\n\n\n\n\n\n\n\n\n\n\nKeep exploring\n\n\n\n\n\n\n\n\n\n\n\n\n\n\n\n\n IFAD's History IFAD has been investing in rural people and empowering them to improve their food security and nutrition since 1977. \n\n  Explore more \n           \n \n\n\n\n\n\n\n\n\n\n\n\n\n\n\n\n\n\n Leadership IFAD’s leadership manages resources and focuses on our mission. \n\n  Explore more \n           \n \n\n\n\n\n\n\n\n\n\n\n\n\n\n\n\nCorporate Document\n\n IFAD Strategic Framework 2016-2025 IFAD’s fifth Strategic Framework presents the overarching goal, principles of engagement, strategic objectives, outcomes and pillars of results delivery that will guide IFAD’s operations over the 2016-2025 period. It situates IFAD in the evolving global context and articulates its contribution to the 2030 Agenda for Sustainable Development (Agenda 2030). Agenda 2030 offers clear evidence that IFAD’s mandate of investing in rural people and enabling inclusive and sustainable transformation of rural areas, notably through smallholder agriculture-led growth, is of absolute global relevance today and over the coming decade. After several years of growth and reform, IFAD is now recognized for its experience, knowledge and performance in this domain; it stands ready to achieve greater impact and it is well positioned to play a larger role in helping countries fulfil their priorities relative to Agenda 2030. \n\n  Read now \n           \n \n\n\n\n\n\n\n\n\n\n\n\n\n\n\n\n       Please configure the desktop menu widget below\n      \n\n\n\n\n\n\n\n\n About IFAD \n Who we are   Where we work   What we do   Action Areas   Knowledge & Data \n\n\n For Member States \n Member States interactive platform \n\n\n For Investors \n Investors   Finance \n\n\n For Job seekers \n Work with us   Frequently Asked Questions \n\n\n For Media \n News   Media Contacts   Image Bank \n\n\n Get Involved \n Join an event   Rural Voices   Opinions & Insights \n\n\n\n\n\n\n\n\n\n\n\n\n\n       Please configure the mobile menu widget below\n      \n\n\n\n\n\n\n\n\n Who we are \n\n\n\n What we do \n\n\n\n Where we work \n\n\n\n Action Areas \n\n\n\n Knowledge & Data \n\n\n\n Get Involved \n\n\n\n News and Stories \n\n\n\n\n\n\n\n\n\n\n\n\n\n  \n Legal  Privacy notice  Fraudulent job offers  Contact us Stay connected\n\n\n\n  \n\n  \n\n  \n\n  \n\n  \n\n \n\n\n\n\n\n\n\n\nHidden\n\nOur vision\n\n\n\n\n\n\n\n\n ©IFAD/GMB Akash\n\n\n\n\n\n\n\n\n\n\n\n\n\n\nAt the International Fund for Agricultural Development, we envisage vibrant, inclusive and sustainable rural communities where people live free from poverty and hunger.  \n\n\n\n\n\n\n\n\n\n\n\n\n\nThree in four of the world's poorest people live in the rural areas of developing countries. Most of them depend on agriculture for their livelihoods – and in turn, produce much of the food we eat. It’s not an easy job.  \nMany rural people living in poverty face massive economic, social and environmental challenges – from climate change and food insecurity, to inequality, conflict and lack of access to resources.  \nThese overlapping problems cannot be solved working alone. As an assembler of development finance, we partner with governments, the private sector, civil society and others to provide grants and concessional and low-interest loans to developing countries. This helps to address critical needs and support rural people as they lead their own development.  \nIFAD-supported projects promote prosperity, food security and resilience by connecting rural poor people to the finance, markets, technology and knowledge they need to address their biggest challenges. \nWe catalyse public and private investments, advocate for policies that empower rural people and their institutions, and promote innovation in order to achieve lasting, systemic change for rural communities in every region of the world.  \nThroughout our work, we emphasize the importance of inclusion and equity, focusing special attention on gender and groups that are often overlooked, like youth, Indigenous Peoples and persons with disabilities. We strive to foster an organizational culture built around these values.   \nFurthermore, as a results-driven organization, we conduct rigorous monitoring and evaluation to assess our impact and scale up what we know works. That’s one of the reasons we are a top-rated development organization. \n\n\n\n\n\n\n\n\n\n\n\n\n\n\n\n\n\n\nOur objectives \n\n\n\n\n\n\nIFAD is the only UN agency exclusively dedicated to transforming agriculture, rural economies and food systems. We invest in the millions of people who are most at risk of being left behind: poor, small-scale food producers living in rural areas.\nWe support rural people in some of the most remote and fragile contexts so that they can: \n\nProduce and sell more \nEat more nutritious foods  \nManage natural resources well  \nEarn more money \nAccess new technologies  \nAdapt to climate change \nBuild resilience to economic shocks, conflict and other crises \n\nThrough our investments, we help ensure that rural people lead their own change. \n\n\n\n\n\n\n\n\nBigger, better, smarter \n\n\n\n\n\n\nWe periodically update our strategic framework to align our objectives with the evolving global context.\nAdopted in 2016, IFAD’s Strategic Framework guides how we will progress toward our vision through 2025. It articulates our contribution to the 2030 Agenda for Sustainable Development and outlines how we will work in ways that are bigger, better and smarter.\nBigger, by mobilizing and leveraging greater investment in rural areas.\nBetter, by strengthening the quality of rural development programmes.\nSmarter, by sharpening our efficiency and delivering results in a more cost-effective way. \n\n\n\n\n\n\n\n\n\n\n\nKeep exploring\n\n\n\n\n\n\n\n\n\n\n\n\n\n\n\n\n IFAD's History IFAD has been investing in rural people and empowering them to improve their food security and nutrition since 1977. \n\n  Explore more \n           \n \n\n\n\n\n\n\n\n\n\n\n\n\n\n\n\n\n\n Leadership IFAD’s leadership manages resources and focuses on our mission. \n\n  Explore more \n           \n \n\n\n\n\n\n\n\n\n\n\n\n\n\n\n\nCorporate Document\n\n IFAD Strategic Framework 2016-2025 IFAD’s fifth Strategic Framework presents the overarching goal, principles of engagement, strategic objectives, outcomes and pillars of results delivery that will guide IFAD’s operations over the 2016-2025 period. It situates IFAD in the evolving global context and articulates its contribution to the 2030 Agenda for Sustainable Development (Agenda 2030). Agenda 2030 offers clear evidence that IFAD’s mandate of investing in rural people and enabling inclusive and sustainable transformation of rural areas, notably through smallholder agriculture-led growth, is of absolute global relevance today and over the coming decade. After several years of growth and reform, IFAD is now recognized for its experience, knowledge and performance in this domain; it stands ready to achieve greater impact and it is well positioned to play a larger role in helping countries fulfil their priorities relative to Agenda 2030. \n\n  Read now \n           \n \n\n\n\n\n\n\n\n\n\n\n\n\n\n\n\n       Please configure the desktop menu widget below\n      \n\n\n\n\n\n\n\n\n About IFAD \n Who we are   Where we work   What we do   Action Areas   Knowledge & Data \n\n\n For Member States \n Member States interactive platform \n\n\n For Investors \n Investors   Finance \n\n\n For Job seekers \n Work with us   Frequently Asked Questions \n\n\n For Media \n News   Media Contacts   Image Bank \n\n\n Get Involved \n Join an event   Rural Voices   Opinions & Insights \n\n\n\n\n\n\n\n\n\n\n\n\n\n       Please configure the mobile menu widget below\n      \n\n\n\n\n\n\n\n\n Who we are \n\n\n\n What we do \n\n\n\n Where we work \n\n\n\n Action Areas \n\n\n\n Knowledge & Data \n\n\n\n Get Involved \n\n\n\n News and Stories \n\n\n\n\n\n\n\n\n\n\n\n\n\n  \n Legal  Privacy notice  Fraudulent job offers  Contact us Stay connected\n\nOur vision\n\n\n\n\n\n\n\n\n ©IFAD/GMB Akash\n\n\n\n\n\n\n\n\n\n\n\n\n\n\nAt the International Fund for Agricultural Development, we envisage vibrant, inclusive and sustainable rural communities where people live free from poverty and hunger.  \n\n\n\n\n\n\n\n\n\n\n\n\n\nThree in four of the world's poorest people live in the rural areas of developing countries. Most of them depend on agriculture for their livelihoods – and in turn, produce much of the food we eat. It’s not an easy job.  \nMany rural people living in poverty face massive economic, social and environmental challenges – from climate change and food insecurity, to inequality, conflict and lack of access to resources.  \nThese overlapping problems cannot be solved working alone. As an assembler of development finance, we partner with governments, the private sector, civil society and others to provide grants and concessional and low-interest loans to developing countries. This helps to address critical needs and support rural people as they lead their own development.  \nIFAD-supported projects promote prosperity, food security and resilience by connecting rural poor people to the finance, markets, technology and knowledge they need to address their biggest challenges. \nWe catalyse public and private investments, advocate for policies that empower rural people and their institutions, and promote innovation in order to achieve lasting, systemic change for rural communities in every region of the world.  \nThroughout our work, we emphasize the importance of inclusion and equity, focusing special attention on gender and groups that are often overlooked, like youth, Indigenous Peoples and persons with disabilities. We strive to foster an organizational culture built around these values.   \nFurthermore, as a results-driven organization, we conduct rigorous monitoring and evaluation to assess our impact and scale up what we know works. That’s one of the reasons we are a top-rated development organization. \n\n\n\n\n\n\n\n\n\n\n\n\n\n\n\n\n\n\nOur objectives \n\n\n\n\n\n\nIFAD is the only UN agency exclusively dedicated to transforming agriculture, rural economies and food systems. We invest in the millions of people who are most at risk of being left behind: poor, small-scale food producers living in rural areas.\nWe support rural people in some of the most remote and fragile contexts so that they can: \n\nProduce and sell more \nEat more nutritious foods  \nManage natural resources well  \nEarn more money \nAccess new technologies  \nAdapt to climate change \nBuild resilience to economic shocks, conflict and other crises \n\nThrough our investments, we help ensure that rural people lead their own change. \n\n\n\n\n\n\n\n\nBigger, better, smarter \n\n\n\n\n\n\nWe periodically update our strategic framework to align our objectives with the evolving global context.\nAdopted in 2016, IFAD’s Strategic Framework guides how we will progress toward our vision through 2025. It articulates our contribution to the 2030 Agenda for Sustainable Development and outlines how we will work in ways that are bigger, better and smarter.\nBigger, by mobilizing and leveraging greater investment in rural areas.\nBetter, by strengthening the quality of rural development programmes.\nSmarter, by sharpening our efficiency and delivering results in a more cost-effective way. \n\n\n\n\n\n\n\n\n\n\n\nKeep exploring\n\n\n\n\n\n\n\n\n\n\n\n\n\n\n\n\n IFAD's History IFAD has been investing in rural people and empowering them to improve their food security and nutrition since 1977. \n\n  Explore more \n           \n \n\n\n\n\n\n\n\n\n\n\n\n\n\n\n\n\n\n Leadership IFAD’s leadership manages resources and focuses on our mission. \n\n  Explore more \n           \n \n\n\n\n\n\n\n\n\n\n\n\n\n\n\n\nCorporate Document\n\n IFAD Strategic Framework 2016-2025 IFAD’s fifth Strategic Framework presents the overarching goal, principles of engagement, strategic objectives, outcomes and pillars of results delivery that will guide IFAD’s operations over the 2016-2025 period. It situates IFAD in the evolving global context and articulates its contribution to the 2030 Agenda for Sustainable Development (Agenda 2030). Agenda 2030 offers clear evidence that IFAD’s mandate of investing in rural people and enabling inclusive and sustainable transformation of rural areas, notably through smallholder agriculture-led growth, is of absolute global relevance today and over the coming decade. After several years of growth and reform, IFAD is now recognized for its experience, knowledge and performance in this domain; it stands ready to achieve greater impact and it is well positioned to play a larger role in helping countries fulfil their priorities relative to Agenda 2030. \n\n  Read now \n           \n \n\n\n\n\n\n\n\n\n\n\n\n\n\n\n\n       Please configure the desktop menu widget below\n      \n\n\n\n\n\n\n\n\n About IFAD \n Who we are   Where we work   What we do   Action Areas   Knowledge & Data \n\n\n For Member States \n Member States interactive platform \n\n\n For Investors \n Investors   Finance \n\n\n For Job seekers \n Work with us   Frequently Asked Questions \n\n\n For Media \n News   Media Contacts   Image Bank \n\n\n Get Involved \n Join an event   Rural Voices   Opinions & Insights \n\n\n\n\n\n\n\n\n\n\n\n\n\n       Please configure the mobile menu widget below\n      \n\n\n\n\n\n\n\n\n Who we are \n\n\n\n What we do \n\n\n\n Where we work \n\n\n\n Action Areas \n\n\n\n Knowledge & Data \n\n\n\n Get Involved \n\n\n\n News and Stories \n\n\n\n\n\n\n\n\n\n\n\n\n\n  \n Legal  Privacy notice  Fraudulent job offers  Contact us Stay connected\n\nOur vision\n\n\n\n\n\n\n\n\n ©IFAD/GMB Akash\n\n\n\n\n\n\n\n\n\n\n\n\n\n\nAt the International Fund for Agricultural Development, we envisage vibrant, inclusive and sustainable rural communities where people live free from poverty and hunger.  \n\n\n\n\n\n\n\n\n\n\n\n\n\nThree in four of the world's poorest people live in the rural areas of developing countries. Most of them depend on agriculture for their livelihoods – and in turn, produce much of the food we eat. It’s not an easy job.  \nMany rural people living in poverty face massive economic, social and environmental challenges – from climate change and food insecurity, to inequality, conflict and lack of access to resources.  \nThese overlapping problems cannot be solved working alone. As an assembler of development finance, we partner with governments, the private sector, civil society and others to provide grants and concessional and low-interest loans to developing countries. This helps to address critical needs and support rural people as they lead their own development.  \nIFAD-supported projects promote prosperity, food security and resilience by connecting rural poor people to the finance, markets, technology and knowledge they need to address their biggest challenges. \nWe catalyse public and private investments, advocate for policies that empower rural people and their institutions, and promote innovation in order to achieve lasting, systemic change for rural communities in every region of the world.  \nThroughout our work, we emphasize the importance of inclusion and equity, focusing special attention on gender and groups that are often overlooked, like youth, Indigenous Peoples and persons with disabilities. We strive to foster an organizational culture built around these values.   \nFurthermore, as a results-driven organization, we conduct rigorous monitoring and evaluation to assess our impact and scale up what we know works. That’s one of the reasons we are a top-rated development organization. \n\n\n\n\n\n\n\n\n\n\n\n\n\n\n\n\n\n\nOur objectives \n\n\n\n\n\n\nIFAD is the only UN agency exclusively dedicated to transforming agriculture, rural economies and food systems. We invest in the millions of people who are most at risk of being left behind: poor, small-scale food producers living in rural areas.\nWe support rural people in some of the most remote and fragile contexts so that they can: \n\nProduce and sell more \nEat more nutritious foods  \nManage natural resources well  \nEarn more money \nAccess new technologies  \nAdapt to climate change \nBuild resilience to economic shocks, conflict and other crises \n\nThrough our investments, we help ensure that rural people lead their own change. \n\n\n\n\n\n\n\n\nBigger, better, smarter \n\n\n\n\n\n\nWe periodically update our strategic framework to align our objectives with the evolving global context.\nAdopted in 2016, IFAD’s Strategic Framework guides how we will progress toward our vision through 2025. It articulates our contribution to the 2030 Agenda for Sustainable Development and outlines how we will work in ways that are bigger, better and smarter.\nBigger, by mobilizing and leveraging greater investment in rural areas.\nBetter, by strengthening the quality of rural development programmes.\nSmarter, by sharpening our efficiency and delivering results in a more cost-effective way. \n\n\n\n\n\n\n\n\n\n\n\nKeep exploring\n\n\n\n\n\n\n\n\n\n\n\n\n\n\n\n\n IFAD's History IFAD has been investing in rural people and empowering them to improve their food security and nutrition since 1977. \n\n  Explore more \n           \n \n\n\n\n\n\n\n\n\n\n\n\n\n\n\n\n\n\n Leadership IFAD’s leadership manages resources and focuses on our mission. \n\n  Explore more \n           \n \n\n\n\n\n\n\n\n\n\n\n\n\n\n\n\nCorporate Document\n\n IFAD Strategic Framework 2016-2025 IFAD’s fifth Strategic Framework presents the overarching goal, principles of engagement, strategic objectives, outcomes and pillars of results delivery that will guide IFAD’s operations over the 2016-2025 period. It situates IFAD in the evolving global context and articulates its contribution to the 2030 Agenda for Sustainable Development (Agenda 2030). Agenda 2030 offers clear evidence that IFAD’s mandate of investing in rural people and enabling inclusive and sustainable transformation of rural areas, notably through smallholder agriculture-led growth, is of absolute global relevance today and over the coming decade. After several years of growth and reform, IFAD is now recognized for its experience, knowledge and performance in this domain; it stands ready to achieve greater impact and it is well positioned to play a larger role in helping countries fulfil their priorities relative to Agenda 2030. \n\n  Read now\n\nOur vision\n\nOur vision\n\nOur vision\n\nOur vision\n\n©IFAD/GMB Akash\n\n©IFAD/GMB Akash\n\n©IFAD/GMB Akash\n\nAt the International Fund for Agricultural Development, we envisage vibrant, inclusive and sustainable rural communities where people live free from poverty and hunger.  \n\n\n\n\n\n\n\n\n\n\n\n\n\nThree in four of the world's poorest people live in the rural areas of developing countries. Most of them depend on agriculture for their livelihoods – and in turn, produce much of the food we eat. It’s not an easy job.  \nMany rural people living in poverty face massive economic, social and environmental challenges – from climate change and food insecurity, to inequality, conflict and lack of access to resources.  \nThese overlapping problems cannot be solved working alone. As an assembler of development finance, we partner with governments, the private sector, civil society and others to provide grants and concessional and low-interest loans to developing countries. This helps to address critical needs and support rural people as they lead their own development.  \nIFAD-supported projects promote prosperity, food security and resilience by connecting rural poor people to the finance, markets, technology and knowledge they need to address their biggest challenges. \nWe catalyse public and private investments, advocate for policies that empower rural people and their institutions, and promote innovation in order to achieve lasting, systemic change for rural communities in every region of the world.  \nThroughout our work, we emphasize the importance of inclusion and equity, focusing special attention on gender and groups that are often overlooked, like youth, Indigenous Peoples and persons with disabilities. We strive to foster an organizational culture built around these values.   \nFurthermore, as a results-driven organization, we conduct rigorous monitoring and evaluation to assess our impact and scale up what we know works. That’s one of the reasons we are a top-rated development organization.\n\nAt the International Fund for Agricultural Development, we envisage vibrant, inclusive and sustainable rural communities where people live free from poverty and hunger.\n\nAt the International Fund for Agricultural Development, we envisage vibrant, inclusive and sustainable rural communities where people live free from poverty and hunger.\n\nThree in four of the world's poorest people live in the rural areas of developing countries. Most of them depend on agriculture for their livelihoods – and in turn, produce much of the food we eat. It’s not an easy job.  \nMany rural people living in poverty face massive economic, social and environmental challenges – from climate change and food insecurity, to inequality, conflict and lack of access to resources.  \nThese overlapping problems cannot be solved working alone. As an assembler of development finance, we partner with governments, the private sector, civil society and others to provide grants and concessional and low-interest loans to developing countries. This helps to address critical needs and support rural people as they lead their own development.  \nIFAD-supported projects promote prosperity, food security and resilience by connecting rural poor people to the finance, markets, technology and knowledge they need to address their biggest challenges. \nWe catalyse public and private investments, advocate for policies that empower rural people and their institutions, and promote innovation in order to achieve lasting, systemic change for rural communities in every region of the world.  \nThroughout our work, we emphasize the importance of inclusion and equity, focusing special attention on gender and groups that are often overlooked, like youth, Indigenous Peoples and persons with disabilities. We strive to foster an organizational culture built around these values.   \nFurthermore, as a results-driven organization, we conduct rigorous monitoring and evaluation to assess our impact and scale up what we know works. That’s one of the reasons we are a top-rated development organization.\n\nThree in four of the world's poorest people live in the rural areas of developing countries. Most of them depend on agriculture for their livelihoods – and in turn, produce much of the food we eat. It’s not an easy job.  \nMany rural people living in poverty face massive economic, social and environmental challenges – from climate change and food insecurity, to inequality, conflict and lack of access to resources.  \nThese overlapping problems cannot be solved working alone. As an assembler of development finance, we partner with governments, the private sector, civil society and others to provide grants and concessional and low-interest loans to developing countries. This helps to address critical needs and support rural people as they lead their own development.  \nIFAD-supported projects promote prosperity, food security and resilience by connecting rural poor people to the finance, markets, technology and knowledge they need to address their biggest challenges. \nWe catalyse public and private investments, advocate for policies that empower rural people and their institutions, and promote innovation in order to achieve lasting, systemic change for rural communities in every region of the world.  \nThroughout our work, we emphasize the importance of inclusion and equity, focusing special attention on gender and groups that are often overlooked, like youth, Indigenous Peoples and persons with disabilities. We strive to foster an organizational culture built around these values.   \nFurthermore, as a results-driven organization, we conduct rigorous monitoring and evaluation to assess our impact and scale up what we know works. That’s one of the reasons we are a top-rated development organization.\n\nThree in four of the world's poorest people live in the rural areas of developing countries. Most of them depend on agriculture for their livelihoods – and in turn, produce much of the food we eat. It’s not an easy job.  \nMany rural people living in poverty face massive economic, social and environmental challenges – from climate change and food insecurity, to inequality, conflict and lack of access to resources.  \nThese overlapping problems cannot be solved working alone. As an assembler of development finance, we partner with governments, the private sector, civil society and others to provide grants and concessional and low-interest loans to developing countries. This helps to address critical needs and support rural people as they lead their own development.  \nIFAD-supported projects promote prosperity, food security and resilience by connecting rural poor people to the finance, markets, technology and knowledge they need to address their biggest challenges. \nWe catalyse public and private investments, advocate for policies that empower rural people and their institutions, and promote innovation in order to achieve lasting, systemic change for rural communities in every region of the world.  \nThroughout our work, we emphasize the importance of inclusion and equity, focusing special attention on gender and groups that are often overlooked, like youth, Indigenous Peoples and persons with disabilities. We strive to foster an organizational culture built around these values.   \nFurthermore, as a results-driven organization, we conduct rigorous monitoring and evaluation to assess our impact and scale up what we know works. That’s one of the reasons we are a top-rated development organization.\n\nThree in four of the world's poorest people live in the rural areas of developing countries. Most of them depend on agriculture for their livelihoods – and in turn, produce much of the food we eat. It’s not an easy job.\n\nMany rural people living in poverty face massive economic, social and environmental challenges – from climate change and food insecurity, to inequality, conflict and lack of access to resources.\n\nThese overlapping problems cannot be solved working alone. As an assembler of development finance, we partner with governments, the private sector, civil society and others to provide grants and concessional and low-interest loans to developing countries. This helps to address critical needs and support rural people as they lead their own development.\n\nIFAD-supported projects promote prosperity, food security and resilience by connecting rural poor people to the finance, markets, technology and knowledge they need to address their biggest challenges.\n\nWe catalyse public and private investments, advocate for policies that empower rural people and their institutions, and promote innovation in order to achieve lasting, systemic change for rural communities in every region of the world.\n\nThroughout our work, we emphasize the importance of inclusion and equity, focusing special attention on gender and groups that are often overlooked, like youth, Indigenous Peoples and persons with disabilities. We strive to foster an organizational culture built around these values.\n\nFurthermore, as a results-driven organization, we conduct rigorous monitoring and evaluation to assess our impact and scale up what we know works. That’s one of the reasons we are a top-rated development organization.\n\nOur objectives \n\n\n\n\n\n\nIFAD is the only UN agency exclusively dedicated to transforming agriculture, rural economies and food systems. We invest in the millions of people who are most at risk of being left behind: poor, small-scale food producers living in rural areas.\nWe support rural people in some of the most remote and fragile contexts so that they can: \n\nProduce and sell more \nEat more nutritious foods  \nManage natural resources well  \nEarn more money \nAccess new technologies  \nAdapt to climate change \nBuild resilience to economic shocks, conflict and other crises \n\nThrough our investments, we help ensure that rural people lead their own change. \n\n\n\n\n\n\n\n\nBigger, better, smarter \n\n\n\n\n\n\nWe periodically update our strategic framework to align our objectives with the evolving global context.\nAdopted in 2016, IFAD’s Strategic Framework guides how we will progress toward our vision through 2025. It articulates our contribution to the 2030 Agenda for Sustainable Development and outlines how we will work in ways that are bigger, better and smarter.\nBigger, by mobilizing and leveraging greater investment in rural areas.\nBetter, by strengthening the quality of rural development programmes.\nSmarter, by sharpening our efficiency and delivering results in a more cost-effective way.\n\nOur objectives \n\n\n\n\n\n\nIFAD is the only UN agency exclusively dedicated to transforming agriculture, rural economies and food systems. We invest in the millions of people who are most at risk of being left behind: poor, small-scale food producers living in rural areas.\nWe support rural people in some of the most remote and fragile contexts so that they can: \n\nProduce and sell more \nEat more nutritious foods  \nManage natural resources well  \nEarn more money \nAccess new technologies  \nAdapt to climate change \nBuild resilience to economic shocks, conflict and other crises \n\nThrough our investments, we help ensure that rural people lead their own change. \n\n\n\n\n\n\n\n\nBigger, better, smarter \n\n\n\n\n\n\nWe periodically update our strategic framework to align our objectives with the evolving global context.\nAdopted in 2016, IFAD’s Strategic Framework guides how we will progress toward our vision through 2025. It articulates our contribution to the 2030 Agenda for Sustainable Development and outlines how we will work in ways that are bigger, better and smarter.\nBigger, by mobilizing and leveraging greater investment in rural areas.\nBetter, by strengthening the quality of rural development programmes.\nSmarter, by sharpening our efficiency and delivering results in a more cost-effective way.\n\nOur objectives \n\n\n\n\n\n\nIFAD is the only UN agency exclusively dedicated to transforming agriculture, rural economies and food systems. We invest in the millions of people who are most at risk of being left behind: poor, small-scale food producers living in rural areas.\nWe support rural people in some of the most remote and fragile contexts so that they can: \n\nProduce and sell more \nEat more nutritious foods  \nManage natural resources well  \nEarn more money \nAccess new technologies  \nAdapt to climate change \nBuild resilience to economic shocks, conflict and other crises \n\nThrough our investments, we help ensure that rural people lead their own change. \n\n\n\n\n\n\n\n\nBigger, better, smarter \n\n\n\n\n\n\nWe periodically update our strategic framework to align our objectives with the evolving global context.\nAdopted in 2016, IFAD’s Strategic Framework guides how we will progress toward our vision through 2025. It articulates our contribution to the 2030 Agenda for Sustainable Development and outlines how we will work in ways that are bigger, better and smarter.\nBigger, by mobilizing and leveraging greater investment in rural areas.\nBetter, by strengthening the quality of rural development programmes.\nSmarter, by sharpening our efficiency and delivering results in a more cost-effective way.\n\nOur objectives \n\n\n\n\n\n\nIFAD is the only UN agency exclusively dedicated to transforming agriculture, rural economies and food systems. We invest in the millions of people who are most at risk of being left behind: poor, small-scale food producers living in rural areas.\nWe support rural people in some of the most remote and fragile contexts so that they can: \n\nProduce and sell more \nEat more nutritious foods  \nManage natural resources well  \nEarn more money \nAccess new technologies  \nAdapt to climate change \nBuild resilience to economic shocks, conflict and other crises \n\nThrough our investments, we help ensure that rural people lead their own change.\n\nOur objectives\n\nOur objectives\n\nIFAD is the only UN agency exclusively dedicated to transforming agriculture, rural economies and food systems. We invest in the millions of people who are most at risk of being left behind: poor, small-scale food producers living in rural areas.\nWe support rural people in some of the most remote and fragile contexts so that they can: \n\nProduce and sell more \nEat more nutritious foods  \nManage natural resources well  \nEarn more money \nAccess new technologies  \nAdapt to climate change \nBuild resilience to economic shocks, conflict and other crises \n\nThrough our investments, we help ensure that rural people lead their own change.\n\nIFAD is the only UN agency exclusively dedicated to transforming agriculture, rural economies and food systems. We invest in the millions of people who are most at risk of being left behind: poor, small-scale food producers living in rural areas.\nWe support rural people in some of the most remote and fragile contexts so that they can: \n\nProduce and sell more \nEat more nutritious foods  \nManage natural resources well  \nEarn more money \nAccess new technologies  \nAdapt to climate change \nBuild resilience to economic shocks, conflict and other crises \n\nThrough our investments, we help ensure that rural people lead their own change.\n\nIFAD is the only UN agency exclusively dedicated to transforming agriculture, rural economies and food systems. We invest in the millions of people who are most at risk of being left behind: poor, small-scale food producers living in rural areas.\nWe support rural people in some of the most remote and fragile contexts so that they can: \n\nProduce and sell more \nEat more nutritious foods  \nManage natural resources well  \nEarn more money \nAccess new technologies  \nAdapt to climate change \nBuild resilience to economic shocks, conflict and other crises \n\nThrough our investments, we help ensure that rural people lead their own change.\n\nIFAD is the only UN agency exclusively dedicated to transforming agriculture, rural economies and food systems. We invest in the millions of people who are most at risk of being left behind: poor, small-scale food producers living in rural areas.\n\nWe support rural people in some of the most remote and fragile contexts so that they can:\n\nProduce and sell more\n\nEat more nutritious foods\n\nManage natural resources well\n\nEarn more money\n\nAccess new technologies\n\nAdapt to climate change\n\nBuild resilience to economic shocks, conflict and other crises\n\nThrough our investments, we help ensure that rural people lead their own change.\n\nBigger, better, smarter \n\n\n\n\n\n\nWe periodically update our strategic framework to align our objectives with the evolving global context.\nAdopted in 2016, IFAD’s Strategic Framework guides how we will progress toward our vision through 2025. It articulates our contribution to the 2030 Agenda for Sustainable Development and outlines how we will work in ways that are bigger, better and smarter.\nBigger, by mobilizing and leveraging greater investment in rural areas.\nBetter, by strengthening the quality of rural development programmes.\nSmarter, by sharpening our efficiency and delivering results in a more cost-effective way.\n\nBigger, better, smarter\n\nBigger, better, smarter\n\nWe periodically update our strategic framework to align our objectives with the evolving global context.\nAdopted in 2016, IFAD’s Strategic Framework guides how we will progress toward our vision through 2025. It articulates our contribution to the 2030 Agenda for Sustainable Development and outlines how we will work in ways that are bigger, better and smarter.\nBigger, by mobilizing and leveraging greater investment in rural areas.\nBetter, by strengthening the quality of rural development programmes.\nSmarter, by sharpening our efficiency and delivering results in a more cost-effective way.\n\nWe periodically update our strategic framework to align our objectives with the evolving global context.\nAdopted in 2016, IFAD’s Strategic Framework guides how we will progress toward our vision through 2025. It articulates our contribution to the 2030 Agenda for Sustainable Development and outlines how we will work in ways that are bigger, better and smarter.\nBigger, by mobilizing and leveraging greater investment in rural areas.\nBetter, by strengthening the quality of rural development programmes.\nSmarter, by sharpening our efficiency and delivering results in a more cost-effective way.\n\nWe periodically update our strategic framework to align our objectives with the evolving global context.\nAdopted in 2016, IFAD’s Strategic Framework guides how we will progress toward our vision through 2025. It articulates our contribution to the 2030 Agenda for Sustainable Development and outlines how we will work in ways that are bigger, better and smarter.\nBigger, by mobilizing and leveraging greater investment in rural areas.\nBetter, by strengthening the quality of rural development programmes.\nSmarter, by sharpening our efficiency and delivering results in a more cost-effective way.\n\nWe periodically update our strategic framework to align our objectives with the evolving global context.\n\nAdopted in 2016, IFAD’s Strategic Framework guides how we will progress toward our vision through 2025. It articulates our contribution to the 2030 Agenda for Sustainable Development and outlines how we will work in ways that are bigger, better and smarter.\n\nBigger, by mobilizing and leveraging greater investment in rural areas.\n\nBetter, by strengthening the quality of rural development programmes.\n\nSmarter, by sharpening our efficiency and delivering results in a more cost-effective way.\n\nKeep exploring\n\n\n\n\n\n\n\n\n\n\n\n\n\n\n\n\n IFAD's History IFAD has been investing in rural people and empowering them to improve their food security and nutrition since 1977. \n\n  Explore more \n           \n \n\n\n\n\n\n\n\n\n\n\n\n\n\n\n\n\n\n Leadership IFAD’s leadership manages resources and focuses on our mission. \n\n  Explore more \n           \n \n\n\n\n\n\n\n\n\n\n\n\n\n\n\n\nCorporate Document\n\n IFAD Strategic Framework 2016-2025 IFAD’s fifth Strategic Framework presents the overarching goal, principles of engagement, strategic objectives, outcomes and pillars of results delivery that will guide IFAD’s operations over the 2016-2025 period. It situates IFAD in the evolving global context and articulates its contribution to the 2030 Agenda for Sustainable Development (Agenda 2030). Agenda 2030 offers clear evidence that IFAD’s mandate of investing in rural people and enabling inclusive and sustainable transformation of rural areas, notably through smallholder agriculture-led growth, is of absolute global relevance today and over the coming decade. After several years of growth and reform, IFAD is now recognized for its experience, knowledge and performance in this domain; it stands ready to achieve greater impact and it is well positioned to play a larger role in helping countries fulfil their priorities relative to Agenda 2030. \n\n  Read now\n\nKeep exploring\n\nKeep exploring\n\nIFAD's History IFAD has been investing in rural people and empowering them to improve their food security and nutrition since 1977. \n\n  Explore more \n           \n \n\n\n\n\n\n\n\n\n\n\n\n\n\n\n\n\n\n Leadership IFAD’s leadership manages resources and focuses on our mission. \n\n  Explore more \n           \n \n\n\n\n\n\n\n\n\n\n\n\n\n\n\n\nCorporate Document\n\n IFAD Strategic Framework 2016-2025 IFAD’s fifth Strategic Framework presents the overarching goal, principles of engagement, strategic objectives, outcomes and pillars of results delivery that will guide IFAD’s operations over the 2016-2025 period. It situates IFAD in the evolving global context and articulates its contribution to the 2030 Agenda for Sustainable Development (Agenda 2030). Agenda 2030 offers clear evidence that IFAD’s mandate of investing in rural people and enabling inclusive and sustainable transformation of rural areas, notably through smallholder agriculture-led growth, is of absolute global relevance today and over the coming decade. After several years of growth and reform, IFAD is now recognized for its experience, knowledge and performance in this domain; it stands ready to achieve greater impact and it is well positioned to play a larger role in helping countries fulfil their priorities relative to Agenda 2030. \n\n  Read now\n\nIFAD's History IFAD has been investing in rural people and empowering them to improve their food security and nutrition since 1977. \n\n  Explore more \n           \n \n\n\n\n\n\n\n\n\n\n\n\n\n\n\n\n\n\n Leadership IFAD’s leadership manages resources and focuses on our mission. \n\n  Explore more \n           \n \n\n\n\n\n\n\n\n\n\n\n\n\n\n\n\nCorporate Document\n\n IFAD Strategic Framework 2016-2025 IFAD’s fifth Strategic Framework presents the overarching goal, principles of engagement, strategic objectives, outcomes and pillars of results delivery that will guide IFAD’s operations over the 2016-2025 period. It situates IFAD in the evolving global context and articulates its contribution to the 2030 Agenda for Sustainable Development (Agenda 2030). Agenda 2030 offers clear evidence that IFAD’s mandate of investing in rural people and enabling inclusive and sustainable transformation of rural areas, notably through smallholder agriculture-led growth, is of absolute global relevance today and over the coming decade. After several years of growth and reform, IFAD is now recognized for its experience, knowledge and performance in this domain; it stands ready to achieve greater impact and it is well positioned to play a larger role in helping countries fulfil their priorities relative to Agenda 2030. \n\n  Read now\n\nIFAD's History IFAD has been investing in rural people and empowering them to improve their food security and nutrition since 1977. \n\n  Explore more\n\nIFAD's History IFAD has been investing in rural people and empowering them to improve their food security and nutrition since 1977. \n\n  Explore more\n\nIFAD's History IFAD has been investing in rural people and empowering them to improve their food security and nutrition since 1977. \n\n  Explore more\n\nIFAD's History IFAD has been investing in rural people and empowering them to improve their food security and nutrition since 1977. \n\n  Explore more\n\nIFAD's History IFAD has been investing in rural people and empowering them to improve their food security and nutrition since 1977. \n\n  Explore more\n\nIFAD's History IFAD has been investing in rural people and empowering them to improve their food security and nutrition since 1977.\n\nIFAD's History IFAD has been investing in rural people and empowering them to improve their food security and nutrition since 1977.\n\nIFAD's History\n\nIFAD has been investing in rural people and empowering them to improve their food security and nutrition since 1977.\n\nLeadership IFAD’s leadership manages resources and focuses on our mission. \n\n  Explore more\n\nLeadership IFAD’s leadership manages resources and focuses on our mission. \n\n  Explore more\n\nLeadership IFAD’s leadership manages resources and focuses on our mission. \n\n  Explore more\n\nLeadership IFAD’s leadership manages resources and focuses on our mission. \n\n  Explore more\n\nLeadership IFAD’s leadership manages resources and focuses on our mission. \n\n  Explore more\n\nLeadership IFAD’s leadership manages resources and focuses on our mission.\n\nLeadership IFAD’s leadership manages resources and focuses on our mission.\n\nLeadership\n\nIFAD’s leadership manages resources and focuses on our mission.\n\nCorporate Document\n\n IFAD Strategic Framework 2016-2025 IFAD’s fifth Strategic Framework presents the overarching goal, principles of engagement, strategic objectives, outcomes and pillars of results delivery that will guide IFAD’s operations over the 2016-2025 period. It situates IFAD in the evolving global context and articulates its contribution to the 2030 Agenda for Sustainable Development (Agenda 2030). Agenda 2030 offers clear evidence that IFAD’s mandate of investing in rural people and enabling inclusive and sustainable transformation of rural areas, notably through smallholder agriculture-led growth, is of absolute global relevance today and over the coming decade. After several years of growth and reform, IFAD is now recognized for its experience, knowledge and performance in this domain; it stands ready to achieve greater impact and it is well positioned to play a larger role in helping countries fulfil their priorities relative to Agenda 2030. \n\n  Read now\n\nCorporate Document\n\n IFAD Strategic Framework 2016-2025 IFAD’s fifth Strategic Framework presents the overarching goal, principles of engagement, strategic objectives, outcomes and pillars of results delivery that will guide IFAD’s operations over the 2016-2025 period. It situates IFAD in the evolving global context and articulates its contribution to the 2030 Agenda for Sustainable Development (Agenda 2030). Agenda 2030 offers clear evidence that IFAD’s mandate of investing in rural people and enabling inclusive and sustainable transformation of rural areas, notably through smallholder agriculture-led growth, is of absolute global relevance today and over the coming decade. After several years of growth and reform, IFAD is now recognized for its experience, knowledge and performance in this domain; it stands ready to achieve greater impact and it is well positioned to play a larger role in helping countries fulfil their priorities relative to Agenda 2030. \n\n  Read now\n\nCorporate Document\n\n IFAD Strategic Framework 2016-2025 IFAD’s fifth Strategic Framework presents the overarching goal, principles of engagement, strategic objectives, outcomes and pillars of results delivery that will guide IFAD’s operations over the 2016-2025 period. It situates IFAD in the evolving global context and articulates its contribution to the 2030 Agenda for Sustainable Development (Agenda 2030). Agenda 2030 offers clear evidence that IFAD’s mandate of investing in rural people and enabling inclusive and sustainable transformation of rural areas, notably through smallholder agriculture-led growth, is of absolute global relevance today and over the coming decade. After several years of growth and reform, IFAD is now recognized for its experience, knowledge and performance in this domain; it stands ready to achieve greater impact and it is well positioned to play a larger role in helping countries fulfil their priorities relative to Agenda 2030. \n\n  Read now\n\nCorporate Document\n\n IFAD Strategic Framework 2016-2025 IFAD’s fifth Strategic Framework presents the overarching goal, principles of engagement, strategic objectives, outcomes and pillars of results delivery that will guide IFAD’s operations over the 2016-2025 period. It situates IFAD in the evolving global context and articulates its contribution to the 2030 Agenda for Sustainable Development (Agenda 2030). Agenda 2030 offers clear evidence that IFAD’s mandate of investing in rural people and enabling inclusive and sustainable transformation of rural areas, notably through smallholder agriculture-led growth, is of absolute global relevance today and over the coming decade. After several years of growth and reform, IFAD is now recognized for its experience, knowledge and performance in this domain; it stands ready to achieve greater impact and it is well positioned to play a larger role in helping countries fulfil their priorities relative to Agenda 2030. \n\n  Read now\n\nCorporate Document\n\n IFAD Strategic Framework 2016-2025 IFAD’s fifth Strategic Framework presents the overarching goal, principles of engagement, strategic objectives, outcomes and pillars of results delivery that will guide IFAD’s operations over the 2016-2025 period. It situates IFAD in the evolving global context and articulates its contribution to the 2030 Agenda for Sustainable Development (Agenda 2030). Agenda 2030 offers clear evidence that IFAD’s mandate of investing in rural people and enabling inclusive and sustainable transformation of rural areas, notably through smallholder agriculture-led growth, is of absolute global relevance today and over the coming decade. After several years of growth and reform, IFAD is now recognized for its experience, knowledge and performance in this domain; it stands ready to achieve greater impact and it is well positioned to play a larger role in helping countries fulfil their priorities relative to Agenda 2030. \n\n  Read now\n\nCorporate Document\n\n IFAD Strategic Framework 2016-2025 IFAD’s fifth Strategic Framework presents the overarching goal, principles of engagement, strategic objectives, outcomes and pillars of results delivery that will guide IFAD’s operations over the 2016-2025 period. It situates IFAD in the evolving global context and articulates its contribution to the 2030 Agenda for Sustainable Development (Agenda 2030). Agenda 2030 offers clear evidence that IFAD’s mandate of investing in rural people and enabling inclusive and sustainable transformation of rural areas, notably through smallholder agriculture-led growth, is of absolute global relevance today and over the coming decade. After several years of growth and reform, IFAD is now recognized for its experience, knowledge and performance in this domain; it stands ready to achieve greater impact and it is well positioned to play a larger role in helping countries fulfil their priorities relative to Agenda 2030.\n\nCorporate Document\n\nCorporate Document\n\nIFAD Strategic Framework 2016-2025 IFAD’s fifth Strategic Framework presents the overarching goal, principles of engagement, strategic objectives, outcomes and pillars of results delivery that will guide IFAD’s operations over the 2016-2025 period. It situates IFAD in the evolving global context and articulates its contribution to the 2030 Agenda for Sustainable Development (Agenda 2030). Agenda 2030 offers clear evidence that IFAD’s mandate of investing in rural people and enabling inclusive and sustainable transformation of rural areas, notably through smallholder agriculture-led growth, is of absolute global relevance today and over the coming decade. After several years of growth and reform, IFAD is now recognized for its experience, knowledge and performance in this domain; it stands ready to achieve greater impact and it is well positioned to play a larger role in helping countries fulfil their priorities relative to Agenda 2030.\n\nIFAD Strategic Framework 2016-2025\n\nIFAD’s fifth Strategic Framework presents the overarching goal, principles of engagement, strategic objectives, outcomes and pillars of results delivery that will guide IFAD’s operations over the 2016-2025 period. It situates IFAD in the evolving global context and articulates its contribution to the 2030 Agenda for Sustainable Development (Agenda 2030). Agenda 2030 offers clear evidence that IFAD’s mandate of investing in rural people and enabling inclusive and sustainable transformation of rural areas, notably through smallholder agriculture-led growth, is of absolute global relevance today and over the coming decade. After several years of growth and reform, IFAD is now recognized for its experience, knowledge and performance in this domain; it stands ready to achieve greater impact and it is well positioned to play a larger role in helping countries fulfil their priorities relative to Agenda 2030.\n\nPlease configure the desktop menu widget below\n      \n\n\n\n\n\n\n\n\n About IFAD \n Who we are   Where we work   What we do   Action Areas   Knowledge & Data \n\n\n For Member States \n Member States interactive platform \n\n\n For Investors \n Investors   Finance \n\n\n For Job seekers \n Work with us   Frequently Asked Questions \n\n\n For Media \n News   Media Contacts   Image Bank \n\n\n Get Involved \n Join an event   Rural Voices   Opinions & Insights \n\n\n\n\n\n\n\n\n\n\n\n\n\n       Please configure the mobile menu widget below\n      \n\n\n\n\n\n\n\n\n Who we are \n\n\n\n What we do \n\n\n\n Where we work \n\n\n\n Action Areas \n\n\n\n Knowledge & Data \n\n\n\n Get Involved \n\n\n\n News and Stories \n\n\n\n\n\n\n\n\n\n\n\n\n\n  \n Legal  Privacy notice  Fraudulent job offers  Contact us Stay connected\n\nPlease configure the desktop menu widget below\n      \n\n\n\n\n\n\n\n\n About IFAD \n Who we are   Where we work   What we do   Action Areas   Knowledge & Data \n\n\n For Member States \n Member States interactive platform \n\n\n For Investors \n Investors   Finance \n\n\n For Job seekers \n Work with us   Frequently Asked Questions \n\n\n For Media \n News   Media Contacts   Image Bank \n\n\n Get Involved \n Join an event   Rural Voices   Opinions & Insights \n\n\n\n\n\n\n\n\n\n\n\n\n\n       Please configure the mobile menu widget below\n      \n\n\n\n\n\n\n\n\n Who we are \n\n\n\n What we do \n\n\n\n Where we work \n\n\n\n Action Areas \n\n\n\n Knowledge & Data \n\n\n\n Get Involved \n\n\n\n News and Stories \n\n\n\n\n\n\n\n\n\n\n\n\n\n  \n Legal  Privacy notice  Fraudulent job offers  Contact us Stay connected\n\nPlease configure the desktop menu widget below\n      \n\n\n\n\n\n\n\n\n About IFAD \n Who we are   Where we work   What we do   Action Areas   Knowledge & Data \n\n\n For Member States \n Member States interactive platform \n\n\n For Investors \n Investors   Finance \n\n\n For Job seekers \n Work with us   Frequently Asked Questions \n\n\n For Media \n News   Media Contacts   Image Bank \n\n\n Get Involved \n Join an event   Rural Voices   Opinions & Insights \n\n\n\n\n\n\n\n\n\n\n\n\n\n       Please configure the mobile menu widget below\n      \n\n\n\n\n\n\n\n\n Who we are \n\n\n\n What we do \n\n\n\n Where we work \n\n\n\n Action Areas \n\n\n\n Knowledge & Data \n\n\n\n Get Involved \n\n\n\n News and Stories \n\n\n\n\n\n\n\n\n\n\n\n\n\n  \n Legal  Privacy notice  Fraudulent job offers  Contact us Stay connected\n\nPlease configure the desktop menu widget below\n      \n\n\n\n\n\n\n\n\n About IFAD \n Who we are   Where we work   What we do   Action Areas   Knowledge & Data \n\n\n For Member States \n Member States interactive platform \n\n\n For Investors \n Investors   Finance \n\n\n For Job seekers \n Work with us   Frequently Asked Questions \n\n\n For Media \n News   Media Contacts   Image Bank \n\n\n Get Involved \n Join an event   Rural Voices   Opinions & Insights \n\n\n\n\n\n\n\n\n\n\n\n\n\n       Please configure the mobile menu widget below\n      \n\n\n\n\n\n\n\n\n Who we are \n\n\n\n What we do \n\n\n\n Where we work \n\n\n\n Action Areas \n\n\n\n Knowledge & Data \n\n\n\n Get Involved \n\n\n\n News and Stories\n\nPlease configure the desktop menu widget below\n      \n\n\n\n\n\n\n\n\n About IFAD \n Who we are   Where we work   What we do   Action Areas   Knowledge & Data \n\n\n For Member States \n Member States interactive platform \n\n\n For Investors \n Investors   Finance \n\n\n For Job seekers \n Work with us   Frequently Asked Questions \n\n\n For Media \n News   Media Contacts   Image Bank \n\n\n Get Involved \n Join an event   Rural Voices   Opinions & Insights\n\nPlease configure the desktop menu widget below\n\nAbout IFAD \n Who we are   Where we work   What we do   Action Areas   Knowledge & Data \n\n\n For Member States \n Member States interactive platform \n\n\n For Investors \n Investors   Finance \n\n\n For Job seekers \n Work with us   Frequently Asked Questions \n\n\n For Media \n News   Media Contacts   Image Bank \n\n\n Get Involved \n Join an event   Rural Voices   Opinions & Insights\n\nAbout IFAD \n Who we are   Where we work   What we do   Action Areas   Knowledge & Data \n\n\n For Member States \n Member States interactive platform \n\n\n For Investors \n Investors   Finance \n\n\n For Job seekers \n Work with us   Frequently Asked Questions \n\n\n For Media \n News   Media Contacts   Image Bank \n\n\n Get Involved \n Join an event   Rural Voices   Opinions & Insights\n\nAbout IFAD \n Who we are   Where we work   What we do   Action Areas   Knowledge & Data \n\n\n For Member States \n Member States interactive platform \n\n\n For Investors \n Investors   Finance \n\n\n For Job seekers \n Work with us   Frequently Asked Questions \n\n\n For Media \n News   Media Contacts   Image Bank \n\n\n Get Involved \n Join an event   Rural Voices   Opinions & Insights\n\nAbout IFAD \n Who we are   Where we work   What we do   Action Areas   Knowledge & Data \n\n\n For Member States \n Member States interactive platform \n\n\n For Investors \n Investors   Finance \n\n\n For Job seekers \n Work with us   Frequently Asked Questions \n\n\n For Media \n News   Media Contacts   Image Bank \n\n\n Get Involved \n Join an event   Rural Voices   Opinions & Insights\n\nAbout IFAD \n Who we are   Where we work   What we do   Action Areas   Knowledge & Data \n\n\n For Member States \n Member States interactive platform \n\n\n For Investors \n Investors   Finance \n\n\n For Job seekers \n Work with us   Frequently Asked Questions \n\n\n For Media \n News   Media Contacts   Image Bank \n\n\n Get Involved \n Join an event   Rural Voices   Opinions & Insights\n\nAbout IFAD \n Who we are   Where we work   What we do   Action Areas   Knowledge & Data \n\n\n For Member States \n Member States interactive platform \n\n\n For Investors \n Investors   Finance \n\n\n For Job seekers \n Work with us   Frequently Asked Questions \n\n\n For Media \n News   Media Contacts   Image Bank \n\n\n Get Involved \n Join an event   Rural Voices   Opinions & Insights\n\nAbout IFAD \n Who we are   Where we work   What we do   Action Areas   Knowledge & Data \n\n\n For Member States \n Member States interactive platform \n\n\n For Investors \n Investors   Finance \n\n\n For Job seekers \n Work with us   Frequently Asked Questions \n\n\n For Media \n News   Media Contacts   Image Bank \n\n\n Get Involved \n Join an event   Rural Voices   Opinions & Insights\n\nAbout IFAD \n Who we are   Where we work   What we do   Action Areas   Knowledge & Data \n\n\n For Member States \n Member States interactive platform \n\n\n For Investors \n Investors   Finance \n\n\n For Job seekers \n Work with us   Frequently Asked Questions \n\n\n For Media \n News   Media Contacts   Image Bank \n\n\n Get Involved \n Join an event   Rural Voices   Opinions & Insights\n\nAbout IFAD \n Who we are   Where we work   What we do   Action Areas   Knowledge & Data\n\nWho we are   Where we work   What we do   Action Areas   Knowledge & Data\n\nFor Member States \n Member States interactive platform\n\nMember States interactive platform\n\nFor Investors \n Investors   Finance\n\nInvestors   Finance\n\nFor Job seekers \n Work with us   Frequently Asked Questions\n\nWork with us   Frequently Asked Questions\n\nFor Media \n News   Media Contacts   Image Bank\n\nNews   Media Contacts   Image Bank\n\nGet Involved \n Join an event   Rural Voices   Opinions & Insights\n\nJoin an event   Rural Voices   Opinions & Insights\n\nPlease configure the mobile menu widget below\n      \n\n\n\n\n\n\n\n\n Who we are \n\n\n\n What we do \n\n\n\n Where we work \n\n\n\n Action Areas \n\n\n\n Knowledge & Data \n\n\n\n Get Involved \n\n\n\n News and Stories\n\nPlease configure the mobile menu widget below\n\nWho we are \n\n\n\n What we do \n\n\n\n Where we work \n\n\n\n Action Areas \n\n\n\n Knowledge & Data \n\n\n\n Get Involved \n\n\n\n News and Stories\n\nWho we are \n\n\n\n What we do \n\n\n\n Where we work \n\n\n\n Action Areas \n\n\n\n Knowledge & Data \n\n\n\n Get Involved \n\n\n\n News and Stories\n\nWho we are \n\n\n\n What we do \n\n\n\n Where we work \n\n\n\n Action Areas \n\n\n\n Knowledge & Data \n\n\n\n Get Involved \n\n\n\n News and Stories\n\nWho we are \n\n\n\n What we do \n\n\n\n Where we work \n\n\n\n Action Areas \n\n\n\n Knowledge & Data \n\n\n\n Get Involved \n\n\n\n News and Stories\n\nWho we are \n\n\n\n What we do \n\n\n\n Where we work \n\n\n\n Action Areas \n\n\n\n Knowledge & Data \n\n\n\n Get Involved \n\n\n\n News and Stories\n\nWho we are \n\n\n\n What we do \n\n\n\n Where we work \n\n\n\n Action Areas \n\n\n\n Knowledge & Data \n\n\n\n Get Involved \n\n\n\n News and Stories\n\nWho we are \n\n\n\n What we do \n\n\n\n Where we work \n\n\n\n Action Areas \n\n\n\n Knowledge & Data \n\n\n\n Get Involved \n\n\n\n News and Stories\n\nWho we are \n\n\n\n What we do \n\n\n\n Where we work \n\n\n\n Action Areas \n\n\n\n Knowledge & Data \n\n\n\n Get Involved \n\n\n\n News and Stories\n\nWho we are\n\nWhat we do\n\nWhere we work\n\nAction Areas\n\nKnowledge & Data\n\nGet Involved\n\nNews and Stories\n\nLegal  Privacy notice  Fraudulent job offers  Contact us Stay connected\n\nLegal  Privacy notice  Fraudulent job offers  Contact us Stay connected",
  "date": "",
  "source_type": "other",
  "extracted_at": "2025-04-07T14:27:22.853587",
  "metadata": {
    "description": "At IFAD, we envisage vibrant, inclusive and sustainable rural communities where people live free from poverty and hunger.",
    "og:site_name": "IFAD",
    "og:type": "website"
  },
  "relevance_score": 0.525,
  "summary": "Our Vision - IFAD\n\n\n\n\n\n\n\n\n\n\n\n\n\n\n\n\n\n\n\n\n\n\n\n\n\n\n\n\n\n\n\n\n\n\n\nOur vision\n\n\n\n\n\n\n\n\n ©IFAD/GMB Akash\n\n\n\n\n\n\n\n\n\n\n\n\n\n\nAt the International Fund for Agricultural Development, we envisage vibrant, inclusive and sustainable rural communities where people live free from poverty and hunger. We catalyse public and private investments, advocate for policies that empower rural people and their institutions, and promote innovation in order to achieve lasting, systemic change for rural communities in every region of the world. We support rural people in some of the most remote and fragile contexts so that they can: \n\nProduce and sell more \nEat more nutritious foods  \nManage natural resources well  \nEarn more money \nAccess new technologies  \nAdapt to climate change \nBuild resilience to economic shocks, conflict and other crises \n\nThrough our investments, we help ensure that rural people lead their own change. Keep exploring\n\n\n\n\n\n\n\n\n\n\n\n\n\n\n\n\n IFAD's History IFAD has been investing in rural people and empowering them to improve their food security and nutrition since 1977. Explore more \n           \n \n\n\n\n\n\n\n\n\n\n\n\n\n\n\n\nCorporate Document\n\n IFAD Strategic Framework 2016-2025 IFAD’s fifth Strategic Framework presents the overarching goal, principles of engagement, strategic objectives, outcomes and pillars of results delivery that will guide IFAD’s operations over the 2016-2025 period. Agenda 2030 offers clear evidence that IFAD’s mandate of investing in rural people and enabling inclusive and sustainable transformation of rural areas, notably through smallholder agriculture-led growth, is of absolute global relevance today and over the coming decade. Read now \n           \n \n\n\n\n\n\n\n\n\n\n\n\n\n\n\n\n       Please configure the desktop menu widget below\n      \n\n\n\n\n\n\n\n\n About IFAD \n Who we are   Where we work   What we do   Action Areas   Knowledge & Data \n\n\n For Member States \n Member States interactive platform \n\n\n For Investors \n Investors   Finance \n\n\n For Job seekers \n Work with us   Frequently Asked Questions \n\n\n For Media \n News   Media Contacts   Image Bank \n\n\n Get Involved \n Join an event   Rural Voices   Opinions & Insights \n\n\n\n\n\n\n\n\n\n\n\n\n\n       Please configure the mobile menu widget below\n      \n\n\n\n\n\n\n\n\n Who we are \n\n\n\n What we do \n\n\n\n Where we work \n\n\n\n Action Areas \n\n\n\n Knowledge & Data \n\n\n\n Get Involved \n\n\n\n News and Stories \n\n\n\n\n\n\n\n\n\n\n\n\n\n  \n Legal  Privacy notice  Fraudulent job offers  Contact us Stay connected\n\n\n\n  \n\n  \n\n  \n\n  \n\n  \n\n \n\n\n\n\n\n\n\n\nHidden\n\nOur Vision - IFAD\n\n\n\n\n\n\n\n\n\n\n\n\n\n\n\n\n\n\n\n\n\n\n\n\n\n\n\n\n\n\n\n\n\n\n\nOur vision\n\n\n\n\n\n\n\n\n ©IFAD/GMB Akash\n\n\n\n\n\n\n\n\n\n\n\n\n\n\nAt the International Fund for Agricultural Development, we envisage vibrant, inclusive and sustainable rural communities where people live free from poverty and hunger. We catalyse public and private investments, advocate for policies that empower rural people and their institutions, and promote innovation in order to achieve lasting, systemic change for rural communities in every region of the world. We support rural people in some of the most remote and fragile contexts so that they can: \n\nProduce and sell more \nEat more nutritious foods  \nManage natural resources well  \nEarn more money \nAccess new technologies  \nAdapt to climate change \nBuild resilience to economic shocks, conflict and other crises \n\nThrough our investments, we help ensure that rural people lead their own change. Keep exploring\n\n\n\n\n\n\n\n\n\n\n\n\n\n\n\n\n IFAD's History IFAD has been investing in rural people and empowering them to improve their food security and nutrition since 1977. Explore more \n           \n \n\n\n\n\n\n\n\n\n\n\n\n\n\n\n\nCorporate Document\n\n IFAD Strategic Framework 2016-2025 IFAD’s fifth Strategic Framework presents the overarching goal, principles of engagement, strategic objectives, outcomes and pillars of results delivery that will guide IFAD’s operations over the 2016-2025 period. Agenda 2030 offers clear evidence that IFAD’s mandate of investing in rural people and enabling inclusive and sustainable transformation of rural areas, notably through smallholder agriculture-led growth, is of absolute global relevance today and over the coming decade. Read now \n           \n \n\n\n\n\n\n\n\n\n\n\n\n\n\n\n\n       Please configure the desktop menu widget below\n      \n\n\n\n\n\n\n\n\n About IFAD \n Who we are   Where we work   What we do   Action Areas   Knowledge & Data \n\n\n For Member States \n Member States interactive platform \n\n\n For Investors \n Investors   Finance \n\n\n For Job seekers \n Work with us   Frequently Asked Questions \n\n\n For Media \n News   Media Contacts   Image Bank \n\n\n Get Involved \n Join an event   Rural Voices   Opinions & Insights \n\n\n\n\n\n\n\n\n\n\n\n\n\n       Please configure the mobile menu widget below\n      \n\n\n\n\n\n\n\n\n Who we are \n\n\n\n What we do \n\n\n\n Where we work \n\n\n\n Action Areas \n\n\n\n Knowledge & Data \n\n\n\n Get Involved \n\n\n\n News and Stories \n\n\n\n\n\n\n\n\n\n\n\n\n\n  \n Legal  Privacy notice  Fraudulent job offers  Contact us Stay connected\n\n\n\n  \n\n  \n\n  \n\n  \n\n  \n\n \n\n\n\n\n\n\n\n\nHidden\n\nOur Vision - IFAD\n\n\n\n\n\n\n\n\n\n\n\n\n\n\n\n\n\n\n\n\n\n\n\n\n\n\n\n\n\n\n\n\n\n\n\nOur vision\n\n\n\n\n\n\n\n\n ©IFAD/GMB Akash\n\n\n\n\n\n\n\n\n\n\n\n\n\n\nAt the International Fund for Agricultural Development, we envisage vibrant, inclusive and sustainable rural communities where people live free from poverty and hunger. We catalyse public and private investments, advocate for policies that empower rural people and their institutions, and promote innovation in order to achieve lasting, systemic change for rural communities in every region of the world. We support rural people in some of the most remote and fragile contexts so that they can: \n\nProduce and sell more \nEat more nutritious foods  \nManage natural resources well  \nEarn more money \nAccess new technologies  \nAdapt to climate change \nBuild resilience to economic shocks, conflict and other crises \n\nThrough our investments, we help ensure that rural people lead their own change. Keep exploring\n\n\n\n\n\n\n\n\n\n\n\n\n\n\n\n\n IFAD's History IFAD has been investing in rural people and empowering them to improve their food security and nutrition since 1977. Explore more \n           \n \n\n\n\n\n\n\n\n\n\n\n\n\n\n\n\nCorporate Document\n\n IFAD Strategic Framework 2016-2025 IFAD’s fifth Strategic Framework presents the overarching goal, principles of engagement, strategic objectives, outcomes and pillars of results delivery that will guide IFAD’s operations over the 2016-2025 period. Agenda 2030 offers clear evidence that IFAD’s mandate of investing in rural people and enabling inclusive and sustainable transformation of rural areas, notably through smallholder agriculture-led growth, is of absolute global relevance today and over the coming decade. Read now \n           \n \n\n\n\n\n\n\n\n\n\n\n\n\n\n\n\n       Please configure the desktop menu widget below\n      \n\n\n\n\n\n\n\n\n About IFAD \n Who we are   Where we work   What we do   Action Areas   Knowledge & Data \n\n\n For Member States \n Member States interactive platform \n\n\n For Investors \n Investors   Finance \n\n\n For Job seekers \n Work with us   Frequently Asked Questions \n\n\n For Media \n News   Media Contacts   Image Bank \n\n\n Get Involved \n Join an event   Rural Voices   Opinions & Insights \n\n\n\n\n\n\n\n\n\n\n\n\n\n       Please configure the mobile menu widget below\n      \n\n\n\n\n\n\n\n\n Who we are \n\n\n\n What we do \n\n\n\n Where we work \n\n\n\n Action Areas \n\n\n\n Knowledge & Data \n\n\n\n Get Involved \n\n\n\n News and Stories \n\n\n\n\n\n\n\n\n\n\n\n\n\n  \n Legal  Privacy notice  Fraudulent job offers  Contact us Stay connected\n\n\n\n  \n\n  \n\n  \n\n  \n\n  \n\n \n\n\n\n\n\n\n\n\nHidden\n\nOur vision\n\n\n\n\n\n\n\n\n ©IFAD/GMB Akash\n\n\n\n\n\n\n\n\n\n\n\n\n\n\nAt the International Fund for Agricultural Development, we envisage vibrant, inclusive and sustainable rural communities where people live free from poverty and hunger. We support rural people in some of the most remote and fragile contexts so that they can: \n\nProduce and sell more \nEat more nutritious foods  \nManage natural resources well  \nEarn more money \nAccess new technologies  \nAdapt to climate change \nBuild resilience to economic shocks, conflict and other crises \n\nThrough our investments, we help ensure that rural people lead their own change. Keep exploring\n\n\n\n\n\n\n\n\n\n\n\n\n\n\n\n\n IFAD's History IFAD has been investing in rural people and empowering them to improve their food security and nutrition since 1977. Explore more \n           \n \n\n\n\n\n\n\n\n\n\n\n\n\n\n\n\nCorporate Document\n\n IFAD Strategic Framework 2016-2025 IFAD’s fifth Strategic Framework presents the overarching goal, principles of engagement, strategic objectives, outcomes and pillars of results delivery that will guide IFAD’s operations over the 2016-2025 period. Agenda 2030 offers clear evidence that IFAD’s mandate of investing in rural people and enabling inclusive and sustainable transformation of rural areas, notably through smallholder agriculture-led growth, is of absolute global relevance today and over the coming decade. Read now \n           \n \n\n\n\n\n\n\n\n\n\n\n\n\n\n\n\n       Please configure the desktop menu widget below\n      \n\n\n\n\n\n\n\n\n About IFAD \n Who we are   Where we work   What we do   Action Areas   Knowledge & Data \n\n\n For Member States \n Member States interactive platform \n\n\n For Investors \n Investors   Finance \n\n\n For Job seekers \n Work with us   Frequently Asked Questions \n\n\n For Media \n News   Media Contacts   Image Bank \n\n\n Get Involved \n Join an event   Rural Voices   Opinions & Insights \n\n\n\n\n\n\n\n\n\n\n\n\n\n       Please configure the mobile menu widget below\n      \n\n\n\n\n\n\n\n\n Who we are \n\n\n\n What we do \n\n\n\n Where we work \n\n\n\n Action Areas \n\n\n\n Knowledge & Data \n\n\n\n Get Involved \n\n\n\n News and Stories \n\n\n\n\n\n\n\n\n\n\n\n\n\n  \n Legal  Privacy notice  Fraudulent job offers  Contact us Stay connected\n\nOur vision\n\n\n\n\n\n\n\n\n ©IFAD/GMB Akash\n\n\n\n\n\n\n\n\n\n\n\n\n\n\nAt the International Fund for Agricultural Development, we envisage vibrant, inclusive and sustainable rural communities where people live free from poverty and hunger. We support rural people in some of the most remote and fragile contexts so that they can: \n\nProduce and sell more \nEat more nutritious foods  \nManage natural resources well  \nEarn more money \nAccess new technologies  \nAdapt to climate change \nBuild resilience to economic shocks, conflict and other crises \n\nThrough our investments, we help ensure that rural people lead their own change. Keep exploring\n\n\n\n\n\n\n\n\n\n\n\n\n\n\n\n\n IFAD's History IFAD has been investing in rural people and empowering them to improve their food security and nutrition since 1977. Explore more \n           \n \n\n\n\n\n\n\n\n\n\n\n\n\n\n\n\nCorporate Document\n\n IFAD Strategic Framework 2016-2025 IFAD’s fifth Strategic Framework presents the overarching goal, principles of engagement, strategic objectives, outcomes and pillars of results delivery that will guide IFAD’s operations over the 2016-2025 period. Agenda 2030 offers clear evidence that IFAD’s mandate of investing in rural people and enabling inclusive and sustainable transformation of rural areas, notably through smallholder agriculture-led growth, is of absolute global relevance today and over the coming decade. Read now \n           \n \n\n\n\n\n\n\n\n\n\n\n\n\n\n\n\n       Please configure the desktop menu widget below\n      \n\n\n\n\n\n\n\n\n About IFAD \n Who we are   Where we work   What we do   Action Areas   Knowledge & Data \n\n\n For Member States \n Member States interactive platform \n\n\n For Investors \n Investors   Finance \n\n\n For Job seekers \n Work with us   Frequently Asked Questions \n\n\n For Media \n News   Media Contacts   Image Bank \n\n\n Get Involved \n Join an event   Rural Voices   Opinions & Insights \n\n\n\n\n\n\n\n\n\n\n\n\n\n       Please configure the mobile menu widget below\n      \n\n\n\n\n\n\n\n\n Who we are \n\n\n\n What we do \n\n\n\n Where we work \n\n\n\n Action Areas \n\n\n\n Knowledge & Data \n\n\n\n Get Involved \n\n\n\n News and Stories \n\n\n\n\n\n\n\n\n\n\n\n\n\n  \n Legal  Privacy notice  Fraudulent job offers  Contact us Stay connected\n\nOur vision\n\n\n\n\n\n\n\n\n ©IFAD/GMB Akash\n\n\n\n\n\n\n\n\n\n\n\n\n\n\nAt the International Fund for Agricultural Development, we envisage vibrant, inclusive and sustainable rural communities where people live free from poverty and hunger. We support rural people in some of the most remote and fragile contexts so that they can: \n\nProduce and sell more \nEat more nutritious foods  \nManage natural resources well  \nEarn more money \nAccess new technologies  \nAdapt to climate change \nBuild resilience to economic shocks, conflict and other crises \n\nThrough our investments, we help ensure that rural people lead their own change. Keep exploring\n\n\n\n\n\n\n\n\n\n\n\n\n\n\n\n\n IFAD's History IFAD has been investing in rural people and empowering them to improve their food security and nutrition since 1977. Explore more \n           \n \n\n\n\n\n\n\n\n\n\n\n\n\n\n\n\nCorporate Document\n\n IFAD Strategic Framework 2016-2025 IFAD’s fifth Strategic Framework presents the overarching goal, principles of engagement, strategic objectives, outcomes and pillars of results delivery that will guide IFAD’s operations over the 2016-2025 period. Agenda 2030 offers clear evidence that IFAD’s mandate of investing in rural people and enabling inclusive and sustainable transformation of rural areas, notably through smallholder agriculture-led growth, is of absolute global relevance today and over the coming decade. We support rural people in some of the most remote and fragile contexts so that they can: \n\nProduce and sell more \nEat more nutritious foods  \nManage natural resources well  \nEarn more money \nAccess new technologies  \nAdapt to climate change \nBuild resilience to economic shocks, conflict and other crises \n\nThrough our investments, we help ensure that rural people lead their own change. We support rural people in some of the most remote and fragile contexts so that they can: \n\nProduce and sell more \nEat more nutritious foods  \nManage natural resources well  \nEarn more money \nAccess new technologies  \nAdapt to climate change \nBuild resilience to economic shocks, conflict and other crises \n\nThrough our investments, we help ensure that rural people lead their own change. We support rural people in some of the most remote and fragile contexts so that they can: \n\nProduce and sell more \nEat more nutritious foods  \nManage natural resources well  \nEarn more money \nAccess new technologies  \nAdapt to climate change \nBuild resilience to economic shocks, conflict and other crises \n\nThrough our investments, we help ensure that rural people lead their own change. We support rural people in some of the most remote and fragile contexts so that they can: \n\nProduce and sell more \nEat more nutritious foods  \nManage natural resources well  \nEarn more money \nAccess new technologies  \nAdapt to climate change \nBuild resilience to economic shocks, conflict and other crises \n\nThrough our investments, we help ensure that rural people lead their own change. We support rural people in some of the most remote and fragile contexts so that they can: \n\nProduce and sell more \nEat more nutritious foods  \nManage natural resources well  \nEarn more money \nAccess new technologies  \nAdapt to climate change \nBuild resilience to economic shocks, conflict and other crises \n\nThrough our investments, we help ensure that rural people lead their own change. We support rural people in some of the most remote and fragile contexts so that they can: \n\nProduce and sell more \nEat more nutritious foods  \nManage natural resources well  \nEarn more money \nAccess new technologies  \nAdapt to climate change \nBuild resilience to economic shocks, conflict and other crises \n\nThrough our investments, we help ensure that rural people lead their own change. We support rural people in some of the most remote and fragile contexts so that they can: \n\nProduce and sell more \nEat more nutritious foods  \nManage natural resources well  \nEarn more money \nAccess new technologies  \nAdapt to climate change \nBuild resilience to economic shocks, conflict and other crises \n\nThrough our investments, we help ensure that rural people lead their own change. We support rural people in some of the most remote and fragile contexts so that they can:\n\nProduce and sell more\n\nEat more nutritious foods\n\nManage natural resources well\n\nEarn more money\n\nAccess new technologies\n\nAdapt to climate change\n\nBuild resilience to economic shocks, conflict and other crises\n\nThrough our investments, we help ensure that rural people lead their own change. Keep exploring\n\n\n\n\n\n\n\n\n\n\n\n\n\n\n\n\n IFAD's History IFAD has been investing in rural people and empowering them to improve their food security and nutrition since 1977. Explore more \n           \n \n\n\n\n\n\n\n\n\n\n\n\n\n\n\n\nCorporate Document\n\n IFAD Strategic Framework 2016-2025 IFAD’s fifth Strategic Framework presents the overarching goal, principles of engagement, strategic objectives, outcomes and pillars of results delivery that will guide IFAD’s operations over the 2016-2025 period. Agenda 2030 offers clear evidence that IFAD’s mandate of investing in rural people and enabling inclusive and sustainable transformation of rural areas, notably through smallholder agriculture-led growth, is of absolute global relevance today and over the coming decade. Read now\n\nKeep exploring\n\nKeep exploring\n\nIFAD's History IFAD has been investing in rural people and empowering them to improve their food security and nutrition since 1977. Explore more \n           \n \n\n\n\n\n\n\n\n\n\n\n\n\n\n\n\nCorporate Document\n\n IFAD Strategic Framework 2016-2025 IFAD’s fifth Strategic Framework presents the overarching goal, principles of engagement, strategic objectives, outcomes and pillars of results delivery that will guide IFAD’s operations over the 2016-2025 period. Agenda 2030 offers clear evidence that IFAD’s mandate of investing in rural people and enabling inclusive and sustainable transformation of rural areas, notably through smallholder agriculture-led growth, is of absolute global relevance today and over the coming decade. Read now\n\nIFAD's History IFAD has been investing in rural people and empowering them to improve their food security and nutrition since 1977. Explore more \n           \n \n\n\n\n\n\n\n\n\n\n\n\n\n\n\n\nCorporate Document\n\n IFAD Strategic Framework 2016-2025 IFAD’s fifth Strategic Framework presents the overarching goal, principles of engagement, strategic objectives, outcomes and pillars of results delivery that will guide IFAD’s operations over the 2016-2025 period. Agenda 2030 offers clear evidence that IFAD’s mandate of investing in rural people and enabling inclusive and sustainable transformation of rural areas, notably through smallholder agriculture-led growth, is of absolute global relevance today and over the coming decade. Read now\n\nIFAD's History IFAD has been investing in rural people and empowering them to improve their food security and nutrition since 1977. Explore more\n\nIFAD's History IFAD has been investing in rural people and empowering them to improve their food security and nutrition since 1977. Explore more\n\nIFAD's History IFAD has been investing in rural people and empowering them to improve their food security and nutrition since 1977. Explore more\n\nIFAD's History IFAD has been investing in rural people and empowering them to improve their food security and nutrition since 1977. Explore more\n\nIFAD's History IFAD has been investing in rural people and empowering them to improve their food security and nutrition since 1977. Explore more\n\nIFAD's History IFAD has been investing in rural people and empowering them to improve their food security and nutrition since 1977. IFAD's History IFAD has been investing in rural people and empowering them to improve their food security and nutrition since 1977. IFAD's History\n\nIFAD has been investing in rural people and empowering them to improve their food security and nutrition since 1977. Corporate Document\n\n IFAD Strategic Framework 2016-2025 IFAD’s fifth Strategic Framework presents the overarching goal, principles of engagement, strategic objectives, outcomes and pillars of results delivery that will guide IFAD’s operations over the 2016-2025 period. Agenda 2030 offers clear evidence that IFAD’s mandate of investing in rural people and enabling inclusive and sustainable transformation of rural areas, notably through smallholder agriculture-led growth, is of absolute global relevance today and over the coming decade. Read now\n\nCorporate Document\n\n IFAD Strategic Framework 2016-2025 IFAD’s fifth Strategic Framework presents the overarching goal, principles of engagement, strategic objectives, outcomes and pillars of results delivery that will guide IFAD’s operations over the 2016-2025 period. Agenda 2030 offers clear evidence that IFAD’s mandate of investing in rural people and enabling inclusive and sustainable transformation of rural areas, notably through smallholder agriculture-led growth, is of absolute global relevance today and over the coming decade. Read now\n\nCorporate Document\n\n IFAD Strategic Framework 2016-2025 IFAD’s fifth Strategic Framework presents the overarching goal, principles of engagement, strategic objectives, outcomes and pillars of results delivery that will guide IFAD’s operations over the 2016-2025 period. Agenda 2030 offers clear evidence that IFAD’s mandate of investing in rural people and enabling inclusive and sustainable transformation of rural areas, notably through smallholder agriculture-led growth, is of absolute global relevance today and over the coming decade. Read now\n\nCorporate Document\n\n IFAD Strategic Framework 2016-2025 IFAD’s fifth Strategic Framework presents the overarching goal, principles of engagement, strategic objectives, outcomes and pillars of results delivery that will guide IFAD’s operations over the 2016-2025 period. Agenda 2030 offers clear evidence that IFAD’s mandate of investing in rural people and enabling inclusive and sustainable transformation of rural areas, notably through smallholder agriculture-led growth, is of absolute global relevance today and over the coming decade. Read now\n\nCorporate Document\n\n IFAD Strategic Framework 2016-2025 IFAD’s fifth Strategic Framework presents the overarching goal, principles of engagement, strategic objectives, outcomes and pillars of results delivery that will guide IFAD’s operations over the 2016-2025 period. Agenda 2030 offers clear evidence that IFAD’s mandate of investing in rural people and enabling inclusive and sustainable transformation of rural areas, notably through smallholder agriculture-led growth, is of absolute global relevance today and over the coming decade. Read now\n\nCorporate Document\n\n IFAD Strategic Framework 2016-2025 IFAD’s fifth Strategic Framework presents the overarching goal, principles of engagement, strategic objectives, outcomes and pillars of results delivery that will guide IFAD’s operations over the 2016-2025 period. Agenda 2030 offers clear evidence that IFAD’s mandate of investing in rural people and enabling inclusive and sustainable transformation of rural areas, notably through smallholder agriculture-led growth, is of absolute global relevance today and over the coming decade. Corporate Document\n\nCorporate Document\n\nIFAD Strategic Framework 2016-2025 IFAD’s fifth Strategic Framework presents the overarching goal, principles of engagement, strategic objectives, outcomes and pillars of results delivery that will guide IFAD’s operations over the 2016-2025 period. Agenda 2030 offers clear evidence that IFAD’s mandate of investing in rural people and enabling inclusive and sustainable transformation of rural areas, notably through smallholder agriculture-led growth, is of absolute global relevance today and over the coming decade. IFAD Strategic Framework 2016-2025\n\nIFAD’s fifth Strategic Framework presents the overarching goal, principles of engagement, strategic objectives, outcomes and pillars of results delivery that will guide IFAD’s operations over the 2016-2025 period. Agenda 2030 offers clear evidence that IFAD’s mandate of investing in rural people and enabling inclusive and sustainable transformation of rural areas, notably through smallholder agriculture-led growth, is of absolute global relevance today and over the coming decade. After several years of growth and reform, IFAD is now recognized for its experience, knowledge and performance in this domain; it stands ready to achieve greater impact and it is well positioned to play a larger role in helping countries fulfil their priorities relative to Agenda 2030. Please configure the desktop menu widget below\n      \n\n\n\n\n\n\n\n\n About IFAD \n Who we are   Where we work   What we do   Action Areas   Knowledge & Data \n\n\n For Member States \n Member States interactive platform \n\n\n For Investors \n Investors   Finance \n\n\n For Job seekers \n Work with us   Frequently Asked Questions \n\n\n For Media \n News   Media Contacts   Image Bank \n\n\n Get Involved \n Join an event   Rural Voices   Opinions & Insights \n\n\n\n\n\n\n\n\n\n\n\n\n\n       Please configure the mobile menu widget below\n      \n\n\n\n\n\n\n\n\n Who we are \n\n\n\n What we do \n\n\n\n Where we work \n\n\n\n Action Areas \n\n\n\n Knowledge & Data \n\n\n\n Get Involved \n\n\n\n News and Stories \n\n\n\n\n\n\n\n\n\n\n\n\n\n  \n Legal  Privacy notice  Fraudulent job offers  Contact us Stay connected\n\nPlease configure the desktop menu widget below\n      \n\n\n\n\n\n\n\n\n About IFAD \n Who we are   Where we work   What we do   Action Areas   Knowledge & Data \n\n\n For Member States \n Member States interactive platform \n\n\n For Investors \n Investors   Finance \n\n\n For Job seekers \n Work with us   Frequently Asked Questions \n\n\n For Media \n News   Media Contacts   Image Bank \n\n\n Get Involved \n Join an event   Rural Voices   Opinions & Insights \n\n\n\n\n\n\n\n\n\n\n\n\n\n       Please configure the mobile menu widget below\n      \n\n\n\n\n\n\n\n\n Who we are \n\n\n\n What we do \n\n\n\n Where we work \n\n\n\n Action Areas \n\n\n\n Knowledge & Data \n\n\n\n Get Involved \n\n\n\n News and Stories \n\n\n\n\n\n\n\n\n\n\n\n\n\n  \n Legal  Privacy notice  Fraudulent job offers  Contact us Stay connected\n\nPlease configure the desktop menu widget below\n      \n\n\n\n\n\n\n\n\n About IFAD \n Who we are   Where we work   What we do   Action Areas   Knowledge & Data \n\n\n For Member States \n Member States interactive platform \n\n\n For Investors \n Investors   Finance \n\n\n For Job seekers \n Work with us   Frequently Asked Questions \n\n\n For Media \n News   Media Contacts   Image Bank \n\n\n Get Involved \n Join an event   Rural Voices   Opinions & Insights \n\n\n\n\n\n\n\n\n\n\n\n\n\n       Please configure the mobile menu widget below\n      \n\n\n\n\n\n\n\n\n Who we are \n\n\n\n What we do \n\n\n\n Where we work \n\n\n\n Action Areas \n\n\n\n Knowledge & Data \n\n\n\n Get Involved \n\n\n\n News and Stories \n\n\n\n\n\n\n\n\n\n\n\n\n\n  \n Legal  Privacy notice  Fraudulent job offers  Contact us Stay connected\n\nPlease configure the desktop menu widget below\n      \n\n\n\n\n\n\n\n\n About IFAD \n Who we are   Where we work   What we do   Action Areas   Knowledge & Data \n\n\n For Member States \n Member States interactive platform \n\n\n For Investors \n Investors   Finance \n\n\n For Job seekers \n Work with us   Frequently Asked Questions \n\n\n For Media \n News   Media Contacts   Image Bank \n\n\n Get Involved \n Join an event   Rural Voices   Opinions & Insights \n\n\n\n\n\n\n\n\n\n\n\n\n\n       Please configure the mobile menu widget below\n      \n\n\n\n\n\n\n\n\n Who we are \n\n\n\n What we do \n\n\n\n Where we work \n\n\n\n Action Areas \n\n\n\n Knowledge & Data \n\n\n\n Get Involved \n\n\n\n News and Stories\n\nPlease configure the desktop menu widget below\n      \n\n\n\n\n\n\n\n\n About IFAD \n Who we are   Where we work   What we do   Action Areas   Knowledge & Data \n\n\n For Member States \n Member States interactive platform \n\n\n For Investors \n Investors   Finance \n\n\n For Job seekers \n Work with us   Frequently Asked Questions \n\n\n For Media \n News   Media Contacts   Image Bank \n\n\n Get Involved \n Join an event   Rural Voices   Opinions & Insights\n\nPlease configure the desktop menu widget below\n\nAbout IFAD \n Who we are   Where we work   What we do   Action Areas   Knowledge & Data \n\n\n For Member States \n Member States interactive platform \n\n\n For Investors \n Investors   Finance \n\n\n For Job seekers \n Work with us   Frequently Asked Questions \n\n\n For Media \n News   Media Contacts   Image Bank \n\n\n Get Involved \n Join an event   Rural Voices   Opinions & Insights\n\nAbout IFAD \n Who we are   Where we work   What we do   Action Areas   Knowledge & Data \n\n\n For Member States \n Member States interactive platform \n\n\n For Investors \n Investors   Finance \n\n\n For Job seekers \n Work with us   Frequently Asked Questions \n\n\n For Media \n News   Media Contacts   Image Bank \n\n\n Get Involved \n Join an event   Rural Voices   Opinions & Insights\n\nAbout IFAD \n Who we are   Where we work   What we do   Action Areas   Knowledge & Data \n\n\n For Member States \n Member States interactive platform \n\n\n For Investors \n Investors   Finance \n\n\n For Job seekers \n Work with us   Frequently Asked Questions \n\n\n For Media \n News   Media Contacts   Image Bank \n\n\n Get Involved \n Join an event   Rural Voices   Opinions & Insights\n\nAbout IFAD \n Who we are   Where we work   What we do   Action Areas   Knowledge & Data \n\n\n For Member States \n Member States interactive platform \n\n\n For Investors \n Investors   Finance \n\n\n For Job seekers \n Work with us   Frequently Asked Questions \n\n\n For Media \n News   Media Contacts   Image Bank \n\n\n Get Involved \n Join an event   Rural Voices   Opinions & Insights\n\nAbout IFAD \n Who we are   Where we work   What we do   Action Areas   Knowledge & Data \n\n\n For Member States \n Member States interactive platform \n\n\n For Investors \n Investors   Finance \n\n\n For Job seekers \n Work with us   Frequently Asked Questions \n\n\n For Media \n News   Media Contacts   Image Bank \n\n\n Get Involved \n Join an event   Rural Voices   Opinions & Insights\n\nAbout IFAD \n Who we are   Where we work   What we do   Action Areas   Knowledge & Data \n\n\n For Member States \n Member States interactive platform \n\n\n For Investors \n Investors   Finance \n\n\n For Job seekers \n Work with us   Frequently Asked Questions \n\n\n For Media \n News   Media Contacts   Image Bank \n\n\n Get Involved \n Join an event   Rural Voices   Opinions & Insights\n\nAbout IFAD \n Who we are   Where we work   What we do   Action Areas   Knowledge & Data \n\n\n For Member States \n Member States interactive platform \n\n\n For Investors \n Investors   Finance \n\n\n For Job seekers \n Work with us   Frequently Asked Questions \n\n\n For Media \n News   Media Contacts   Image Bank \n\n\n Get Involved \n Join an event   Rural Voices   Opinions & Insights\n\nAbout IFAD \n Who we are   Where we work   What we do   Action Areas   Knowledge & Data \n\n\n For Member States \n Member States interactive platform \n\n\n For Investors \n Investors   Finance \n\n\n For Job seekers \n Work with us   Frequently Asked Questions \n\n\n For Media \n News   Media Contacts   Image Bank \n\n\n Get Involved \n Join an event   Rural Voices   Opinions & Insights\n\nAbout IFAD \n Who we are   Where we work   What we do   Action Areas   Knowledge & Data\n\nWho we are   Where we work   What we do   Action Areas   Knowledge & Data\n\nFor Member States \n Member States interactive platform\n\nMember States interactive platform\n\nFor Investors \n Investors   Finance\n\nInvestors   Finance\n\nFor Job seekers \n Work with us   Frequently Asked Questions\n\nWork with us   Frequently Asked Questions\n\nFor Media \n News   Media Contacts   Image Bank\n\nNews   Media Contacts   Image Bank\n\nGet Involved \n Join an event   Rural Voices   Opinions & Insights\n\nJoin an event   Rural Voices   Opinions & Insights\n\nPlease configure the mobile menu widget below\n      \n\n\n\n\n\n\n\n\n Who we are \n\n\n\n What we do \n\n\n\n Where we work \n\n\n\n Action Areas \n\n\n\n Knowledge & Data \n\n\n\n Get Involved \n\n\n\n News and Stories\n\nPlease configure the mobile menu widget below\n\nWho we are \n\n\n\n What we do \n\n\n\n Where we work \n\n\n\n Action Areas \n\n\n\n Knowledge & Data \n\n\n\n Get Involved \n\n\n\n News and Stories\n\nWho we are \n\n\n\n What we do \n\n\n\n Where we work \n\n\n\n Action Areas \n\n\n\n Knowledge & Data \n\n\n\n Get Involved \n\n\n\n News and Stories\n\nWho we are \n\n\n\n What we do \n\n\n\n Where we work \n\n\n\n Action Areas \n\n\n\n Knowledge & Data \n\n\n\n Get Involved \n\n\n\n News and Stories\n\nWho we are \n\n\n\n What we do \n\n\n\n Where we work \n\n\n\n Action Areas \n\n\n\n Knowledge & Data \n\n\n\n Get Involved \n\n\n\n News and Stories\n\nWho we are \n\n\n\n What we do \n\n\n\n Where we work \n\n\n\n Action Areas \n\n\n\n Knowledge & Data \n\n\n\n Get Involved \n\n\n\n News and Stories\n\nWho we are \n\n\n\n What we do \n\n\n\n Where we work \n\n\n\n Action Areas \n\n\n\n Knowledge & Data \n\n\n\n Get Involved \n\n\n\n News and Stories\n\nWho we are \n\n\n\n What we do \n\n\n\n Where we work \n\n\n\n Action Areas \n\n\n\n Knowledge & Data \n\n\n\n Get Involved \n\n\n\n News and Stories\n\nWho we are \n\n\n\n What we do \n\n\n\n Where we work \n\n\n\n Action Areas \n\n\n\n Knowledge & Data \n\n\n\n Get Involved \n\n\n\n News and Stories\n\nWho we are\n\nWhat we do\n\nWhere we work\n\nAction Areas\n\nKnowledge & Data\n\nGet Involved\n\nNews and Stories\n\nLegal  Privacy notice  Fraudulent job offers  Contact us Stay connected\n\nLegal  Privacy notice  Fraudulent job offers  Contact us Stay connected",
  "entities": {
    "countries": [],
    "organizations": [
      "un",
      "who"
    ],
    "key_issues": [
      "problem",
      "challenge",
      "nation",
      "state",
      "government",
      "region",
      "program",
      "action",
      "history",
      "context",
      "development",
      "economic",
      "market",
      "investment",
      "un",
      "organization",
      "agency"
    ]
  },
  "committee": "Economic and Social Council",
  "topic": "Promoting rural development in Africa"
}