{
  "url": "https://www.ifad.org/en/action-areas",
  "title": "Action areas",
  "text": "Action areas - IFAD\n\n\n\n\n\n\n\n\n\n\n\n\n\n\n\n\n\n\n\n\n\n\n\n\n\n\n\n\n\n\n\n\n\n\n\nAction areas\n\n\n\n\n\n\n\n\n\n©IFAD/GMB Akash \n\n\n\n\n\n\n\n\n\n\nIFAD’s investments support rural people so they can pull themselves out of poverty and build better lives.\n\n\n\n\n\n\n\n\nWe build resilience so rural communities have options and can weather crises skilfully.\nWe empower vulnerable groups to ensure that no one is left behind.\nWe enhance livelihoods and connect people to markets so that rural producers can prosper from their hard work.\nWe protect the environment and promote sustainable farming practices so that generations to come can thrive on a healthy planet.\nOur aim? Rural areas are transformed into prosperous and profitable places to live.\n\n\n\n\n\n\n\n\n\n\n\nEmpowering rural people\n\n\n\n\n\n\n\n\n\n\n\n\n\n\n\n\n Rural women Gender inequality is one of the biggest impediments to sustainable development. Without tackling its root causes, we cannot end global hunger and poverty \n\n  Explore more \n           \n \n\n\n\n\n\n\n\n\n\n\n\n\n\n\n\n\n\n Rural Youth As the farmers and producers of tomorrow, rural young people have the potential to feed the world's growing population. \n\n  Explore more \n           \n \n\n\n\n\n\n\n\n\n\n\n\n\n\n\n\n\n Indigenous Peoples With their traditional knowledge and deep connection to their environments, we work with Indigenous Peoples to build a more inclusive, sustainable future. \n\n  Explore more \n           \n \n\n\n\n\n\n\n\n\n\n\n\n\n\n\n\n\n Persons with disabilities Equal opportunities enable persons with disabilities to thrive while transforming rural communities \n\n  Explore more \n           \n \n\n\n\n\n\n\n\n\n\n\n\nProtecting the environment\n\n\n\n\n\n\n\n\n\n\n\n\n\n\n\n Climate and environment The lives of small-scale farmers are being upended by climate change. They need support to adapt to climate change and to protect the planet’s precious resources \n\n  Explore more \n           \n \n\n\n\n\n\n\n\n\n\n\n\n\n\n\n\n\n Biodiversity Rich and diverse ecosystems are essential to produce our food and protect us from climate change impacts \n\n  Explore more \n           \n \n\n\n\n\n\n\n\n\n\n\n\n\n\nEnhancing livelihoods and markets\n\n\n\n\n\n\n\n\n\n\n\n\n\n\n\n Private sector The private sector drives entrepreneurship, employment and growth in rural economies, and is essential to eradicating poverty and hunger. \n\n  Explore more \n           \n \n\n\n\n\n\n\n\n\n\n\n\n\n\n\n\n\n Rural finance With access to finance, rural people can produce more, grow their enterprises, earn more and get through hard times. \n\n  Explore more \n           \n \n\n\n\n\n\n\n\n\n\n\n\n\n\n\n\n\n Markets and value chains Reliable market access and strong value chains boost productivity, increase incomes and strengthen food security \n\n  Explore more \n           \n \n\n\n\n\n\n\n\n\n\n\n\n\n\n\n\n\n Land and resources Ensuring rural people have access land and natural resources for food, shelter, income and resilience \n\n  Explore more \n           \n \n\n\n\n\n\n\n\n\n\n\nPromoting sustainable farming\n\n\n\n\n\n\n\n\n\n\n\n\n\n\n\n\n Water Water is essential for food systems, yet this precious resource is under threat. For rural communities to flourish, they must sustainably access and manage water \n\n  Explore more \n           \n \n\n\n\n\n\n\n\n\n\n\n\n\n\n\n\n\n Crops Small-scale farmers grow a third of the world’s food. In a rapidly changing world, they need support to do so sustainably. \n\n  Explore more \n           \n \n\n\n\n\n\n\n\n\n\n\n\n\n\n\n\n\n Livestock Supporting sustainable livestock production and value chains is key to eradicating poverty and hunger while addressing climate challenges. \n\n  Explore more \n           \n \n\n\n\n\n\n\n\n\n\n\n\n\n\n\n\n\n Fisheries and aquaculture Responsible stewardship of the world’s fisheries ensures better livelihoods and a healthier planet. \n\n  Explore more \n           \n \n\n\n\n\n\n\n\n\n\n\n\nBuilding resilience\n\n\n\n\n\n\n\n\n\n\n\n\n\n\n\n Rural institutions and organizations Farmers’ organizations help rural people increase their incomes and output, share knowledge, access resources and influence policy dialogue. \n\n  Explore more \n           \n \n\n\n\n\n\n\n\n\n\n\n\n\n\n\n\n\n Remittances The funds sent home by migrant workers are a lifeline for rural families, helping to build resilience and support sustainable development \n\n  Explore more \n           \n \n\n\n\n\n\n\n\n\n\n\n\n\n\n\n\n\n Nutrition An investment in agriculture is an investment in nutrition. Farming shapes sustainable food systems that nourish rural people and break cycles of poverty. \n\n  Explore more \n           \n \n\n\n\n\n\n\n\n\n\n\n\n\n\n\n\n\n Fragile contexts and crises By building resilience, rural people can better endure crises. \n\n  Explore more \n           \n \n\n\n\n\n\n\n\n\n\n\n\n\n\n\n\n       Please configure the desktop menu widget below\n      \n\n\n\n\n\n\n\n\n About IFAD \n Who we are   Where we work   What we do   Action Areas   Knowledge & Data \n\n\n For Member States \n Member States interactive platform \n\n\n For Investors \n Investors   Finance \n\n\n For Job seekers \n Work with us   Frequently Asked Questions \n\n\n For Media \n News   Media Contacts   Image Bank \n\n\n Get Involved \n Join an event   Rural Voices   Opinions & Insights \n\n\n\n\n\n\n\n\n\n\n\n\n\n       Please configure the mobile menu widget below\n      \n\n\n\n\n\n\n\n\n Who we are \n\n\n\n What we do \n\n\n\n Where we work \n\n\n\n Action Areas \n\n\n\n Knowledge & Data \n\n\n\n Get Involved \n\n\n\n News and Stories \n\n\n\n\n\n\n\n\n\n\n\n\n\n  \n Legal  Privacy notice  Fraudulent job offers  Contact us Stay connected\n\n\n\n  \n\n  \n\n  \n\n  \n\n  \n\n \n\n\n\n\n\n\n\n\nHidden\n\nAction areas - IFAD\n\n\n\n\n\n\n\n\n\n\n\n\n\n\n\n\n\n\n\n\n\n\n\n\n\n\n\n\n\n\n\n\n\n\n\nAction areas\n\n\n\n\n\n\n\n\n\n©IFAD/GMB Akash \n\n\n\n\n\n\n\n\n\n\nIFAD’s investments support rural people so they can pull themselves out of poverty and build better lives.\n\n\n\n\n\n\n\n\nWe build resilience so rural communities have options and can weather crises skilfully.\nWe empower vulnerable groups to ensure that no one is left behind.\nWe enhance livelihoods and connect people to markets so that rural producers can prosper from their hard work.\nWe protect the environment and promote sustainable farming practices so that generations to come can thrive on a healthy planet.\nOur aim? Rural areas are transformed into prosperous and profitable places to live.\n\n\n\n\n\n\n\n\n\n\n\nEmpowering rural people\n\n\n\n\n\n\n\n\n\n\n\n\n\n\n\n\n Rural women Gender inequality is one of the biggest impediments to sustainable development. Without tackling its root causes, we cannot end global hunger and poverty \n\n  Explore more \n           \n \n\n\n\n\n\n\n\n\n\n\n\n\n\n\n\n\n\n Rural Youth As the farmers and producers of tomorrow, rural young people have the potential to feed the world's growing population. \n\n  Explore more \n           \n \n\n\n\n\n\n\n\n\n\n\n\n\n\n\n\n\n Indigenous Peoples With their traditional knowledge and deep connection to their environments, we work with Indigenous Peoples to build a more inclusive, sustainable future. \n\n  Explore more \n           \n \n\n\n\n\n\n\n\n\n\n\n\n\n\n\n\n\n Persons with disabilities Equal opportunities enable persons with disabilities to thrive while transforming rural communities \n\n  Explore more \n           \n \n\n\n\n\n\n\n\n\n\n\n\nProtecting the environment\n\n\n\n\n\n\n\n\n\n\n\n\n\n\n\n Climate and environment The lives of small-scale farmers are being upended by climate change. They need support to adapt to climate change and to protect the planet’s precious resources \n\n  Explore more \n           \n \n\n\n\n\n\n\n\n\n\n\n\n\n\n\n\n\n Biodiversity Rich and diverse ecosystems are essential to produce our food and protect us from climate change impacts \n\n  Explore more \n           \n \n\n\n\n\n\n\n\n\n\n\n\n\n\nEnhancing livelihoods and markets\n\n\n\n\n\n\n\n\n\n\n\n\n\n\n\n Private sector The private sector drives entrepreneurship, employment and growth in rural economies, and is essential to eradicating poverty and hunger. \n\n  Explore more \n           \n \n\n\n\n\n\n\n\n\n\n\n\n\n\n\n\n\n Rural finance With access to finance, rural people can produce more, grow their enterprises, earn more and get through hard times. \n\n  Explore more \n           \n \n\n\n\n\n\n\n\n\n\n\n\n\n\n\n\n\n Markets and value chains Reliable market access and strong value chains boost productivity, increase incomes and strengthen food security \n\n  Explore more \n           \n \n\n\n\n\n\n\n\n\n\n\n\n\n\n\n\n\n Land and resources Ensuring rural people have access land and natural resources for food, shelter, income and resilience \n\n  Explore more \n           \n \n\n\n\n\n\n\n\n\n\n\nPromoting sustainable farming\n\n\n\n\n\n\n\n\n\n\n\n\n\n\n\n\n Water Water is essential for food systems, yet this precious resource is under threat. For rural communities to flourish, they must sustainably access and manage water \n\n  Explore more \n           \n \n\n\n\n\n\n\n\n\n\n\n\n\n\n\n\n\n Crops Small-scale farmers grow a third of the world’s food. In a rapidly changing world, they need support to do so sustainably. \n\n  Explore more \n           \n \n\n\n\n\n\n\n\n\n\n\n\n\n\n\n\n\n Livestock Supporting sustainable livestock production and value chains is key to eradicating poverty and hunger while addressing climate challenges. \n\n  Explore more \n           \n \n\n\n\n\n\n\n\n\n\n\n\n\n\n\n\n\n Fisheries and aquaculture Responsible stewardship of the world’s fisheries ensures better livelihoods and a healthier planet. \n\n  Explore more \n           \n \n\n\n\n\n\n\n\n\n\n\n\nBuilding resilience\n\n\n\n\n\n\n\n\n\n\n\n\n\n\n\n Rural institutions and organizations Farmers’ organizations help rural people increase their incomes and output, share knowledge, access resources and influence policy dialogue. \n\n  Explore more \n           \n \n\n\n\n\n\n\n\n\n\n\n\n\n\n\n\n\n Remittances The funds sent home by migrant workers are a lifeline for rural families, helping to build resilience and support sustainable development \n\n  Explore more \n           \n \n\n\n\n\n\n\n\n\n\n\n\n\n\n\n\n\n Nutrition An investment in agriculture is an investment in nutrition. Farming shapes sustainable food systems that nourish rural people and break cycles of poverty. \n\n  Explore more \n           \n \n\n\n\n\n\n\n\n\n\n\n\n\n\n\n\n\n Fragile contexts and crises By building resilience, rural people can better endure crises. \n\n  Explore more \n           \n \n\n\n\n\n\n\n\n\n\n\n\n\n\n\n\n       Please configure the desktop menu widget below\n      \n\n\n\n\n\n\n\n\n About IFAD \n Who we are   Where we work   What we do   Action Areas   Knowledge & Data \n\n\n For Member States \n Member States interactive platform \n\n\n For Investors \n Investors   Finance \n\n\n For Job seekers \n Work with us   Frequently Asked Questions \n\n\n For Media \n News   Media Contacts   Image Bank \n\n\n Get Involved \n Join an event   Rural Voices   Opinions & Insights \n\n\n\n\n\n\n\n\n\n\n\n\n\n       Please configure the mobile menu widget below\n      \n\n\n\n\n\n\n\n\n Who we are \n\n\n\n What we do \n\n\n\n Where we work \n\n\n\n Action Areas \n\n\n\n Knowledge & Data \n\n\n\n Get Involved \n\n\n\n News and Stories \n\n\n\n\n\n\n\n\n\n\n\n\n\n  \n Legal  Privacy notice  Fraudulent job offers  Contact us Stay connected\n\n\n\n  \n\n  \n\n  \n\n  \n\n  \n\n \n\n\n\n\n\n\n\n\nHidden\n\nAction areas - IFAD\n\n\n\n\n\n\n\n\n\n\n\n\n\n\n\n\n\n\n\n\n\n\n\n\n\n\n\n\n\n\n\n\n\n\n\nAction areas\n\n\n\n\n\n\n\n\n\n©IFAD/GMB Akash \n\n\n\n\n\n\n\n\n\n\nIFAD’s investments support rural people so they can pull themselves out of poverty and build better lives.\n\n\n\n\n\n\n\n\nWe build resilience so rural communities have options and can weather crises skilfully.\nWe empower vulnerable groups to ensure that no one is left behind.\nWe enhance livelihoods and connect people to markets so that rural producers can prosper from their hard work.\nWe protect the environment and promote sustainable farming practices so that generations to come can thrive on a healthy planet.\nOur aim? Rural areas are transformed into prosperous and profitable places to live.\n\n\n\n\n\n\n\n\n\n\n\nEmpowering rural people\n\n\n\n\n\n\n\n\n\n\n\n\n\n\n\n\n Rural women Gender inequality is one of the biggest impediments to sustainable development. Without tackling its root causes, we cannot end global hunger and poverty \n\n  Explore more \n           \n \n\n\n\n\n\n\n\n\n\n\n\n\n\n\n\n\n\n Rural Youth As the farmers and producers of tomorrow, rural young people have the potential to feed the world's growing population. \n\n  Explore more \n           \n \n\n\n\n\n\n\n\n\n\n\n\n\n\n\n\n\n Indigenous Peoples With their traditional knowledge and deep connection to their environments, we work with Indigenous Peoples to build a more inclusive, sustainable future. \n\n  Explore more \n           \n \n\n\n\n\n\n\n\n\n\n\n\n\n\n\n\n\n Persons with disabilities Equal opportunities enable persons with disabilities to thrive while transforming rural communities \n\n  Explore more \n           \n \n\n\n\n\n\n\n\n\n\n\n\nProtecting the environment\n\n\n\n\n\n\n\n\n\n\n\n\n\n\n\n Climate and environment The lives of small-scale farmers are being upended by climate change. They need support to adapt to climate change and to protect the planet’s precious resources \n\n  Explore more \n           \n \n\n\n\n\n\n\n\n\n\n\n\n\n\n\n\n\n Biodiversity Rich and diverse ecosystems are essential to produce our food and protect us from climate change impacts \n\n  Explore more \n           \n \n\n\n\n\n\n\n\n\n\n\n\n\n\nEnhancing livelihoods and markets\n\n\n\n\n\n\n\n\n\n\n\n\n\n\n\n Private sector The private sector drives entrepreneurship, employment and growth in rural economies, and is essential to eradicating poverty and hunger. \n\n  Explore more \n           \n \n\n\n\n\n\n\n\n\n\n\n\n\n\n\n\n\n Rural finance With access to finance, rural people can produce more, grow their enterprises, earn more and get through hard times. \n\n  Explore more \n           \n \n\n\n\n\n\n\n\n\n\n\n\n\n\n\n\n\n Markets and value chains Reliable market access and strong value chains boost productivity, increase incomes and strengthen food security \n\n  Explore more \n           \n \n\n\n\n\n\n\n\n\n\n\n\n\n\n\n\n\n Land and resources Ensuring rural people have access land and natural resources for food, shelter, income and resilience \n\n  Explore more \n           \n \n\n\n\n\n\n\n\n\n\n\nPromoting sustainable farming\n\n\n\n\n\n\n\n\n\n\n\n\n\n\n\n\n Water Water is essential for food systems, yet this precious resource is under threat. For rural communities to flourish, they must sustainably access and manage water \n\n  Explore more \n           \n \n\n\n\n\n\n\n\n\n\n\n\n\n\n\n\n\n Crops Small-scale farmers grow a third of the world’s food. In a rapidly changing world, they need support to do so sustainably. \n\n  Explore more \n           \n \n\n\n\n\n\n\n\n\n\n\n\n\n\n\n\n\n Livestock Supporting sustainable livestock production and value chains is key to eradicating poverty and hunger while addressing climate challenges. \n\n  Explore more \n           \n \n\n\n\n\n\n\n\n\n\n\n\n\n\n\n\n\n Fisheries and aquaculture Responsible stewardship of the world’s fisheries ensures better livelihoods and a healthier planet. \n\n  Explore more \n           \n \n\n\n\n\n\n\n\n\n\n\n\nBuilding resilience\n\n\n\n\n\n\n\n\n\n\n\n\n\n\n\n Rural institutions and organizations Farmers’ organizations help rural people increase their incomes and output, share knowledge, access resources and influence policy dialogue. \n\n  Explore more \n           \n \n\n\n\n\n\n\n\n\n\n\n\n\n\n\n\n\n Remittances The funds sent home by migrant workers are a lifeline for rural families, helping to build resilience and support sustainable development \n\n  Explore more \n           \n \n\n\n\n\n\n\n\n\n\n\n\n\n\n\n\n\n Nutrition An investment in agriculture is an investment in nutrition. Farming shapes sustainable food systems that nourish rural people and break cycles of poverty. \n\n  Explore more \n           \n \n\n\n\n\n\n\n\n\n\n\n\n\n\n\n\n\n Fragile contexts and crises By building resilience, rural people can better endure crises. \n\n  Explore more \n           \n \n\n\n\n\n\n\n\n\n\n\n\n\n\n\n\n       Please configure the desktop menu widget below\n      \n\n\n\n\n\n\n\n\n About IFAD \n Who we are   Where we work   What we do   Action Areas   Knowledge & Data \n\n\n For Member States \n Member States interactive platform \n\n\n For Investors \n Investors   Finance \n\n\n For Job seekers \n Work with us   Frequently Asked Questions \n\n\n For Media \n News   Media Contacts   Image Bank \n\n\n Get Involved \n Join an event   Rural Voices   Opinions & Insights \n\n\n\n\n\n\n\n\n\n\n\n\n\n       Please configure the mobile menu widget below\n      \n\n\n\n\n\n\n\n\n Who we are \n\n\n\n What we do \n\n\n\n Where we work \n\n\n\n Action Areas \n\n\n\n Knowledge & Data \n\n\n\n Get Involved \n\n\n\n News and Stories \n\n\n\n\n\n\n\n\n\n\n\n\n\n  \n Legal  Privacy notice  Fraudulent job offers  Contact us Stay connected\n\n\n\n  \n\n  \n\n  \n\n  \n\n  \n\n \n\n\n\n\n\n\n\n\nHidden\n\nAction areas\n\n\n\n\n\n\n\n\n\n©IFAD/GMB Akash \n\n\n\n\n\n\n\n\n\n\nIFAD’s investments support rural people so they can pull themselves out of poverty and build better lives.\n\n\n\n\n\n\n\n\nWe build resilience so rural communities have options and can weather crises skilfully.\nWe empower vulnerable groups to ensure that no one is left behind.\nWe enhance livelihoods and connect people to markets so that rural producers can prosper from their hard work.\nWe protect the environment and promote sustainable farming practices so that generations to come can thrive on a healthy planet.\nOur aim? Rural areas are transformed into prosperous and profitable places to live.\n\n\n\n\n\n\n\n\n\n\n\nEmpowering rural people\n\n\n\n\n\n\n\n\n\n\n\n\n\n\n\n\n Rural women Gender inequality is one of the biggest impediments to sustainable development. Without tackling its root causes, we cannot end global hunger and poverty \n\n  Explore more \n           \n \n\n\n\n\n\n\n\n\n\n\n\n\n\n\n\n\n\n Rural Youth As the farmers and producers of tomorrow, rural young people have the potential to feed the world's growing population. \n\n  Explore more \n           \n \n\n\n\n\n\n\n\n\n\n\n\n\n\n\n\n\n Indigenous Peoples With their traditional knowledge and deep connection to their environments, we work with Indigenous Peoples to build a more inclusive, sustainable future. \n\n  Explore more \n           \n \n\n\n\n\n\n\n\n\n\n\n\n\n\n\n\n\n Persons with disabilities Equal opportunities enable persons with disabilities to thrive while transforming rural communities \n\n  Explore more \n           \n \n\n\n\n\n\n\n\n\n\n\n\nProtecting the environment\n\n\n\n\n\n\n\n\n\n\n\n\n\n\n\n Climate and environment The lives of small-scale farmers are being upended by climate change. They need support to adapt to climate change and to protect the planet’s precious resources \n\n  Explore more \n           \n \n\n\n\n\n\n\n\n\n\n\n\n\n\n\n\n\n Biodiversity Rich and diverse ecosystems are essential to produce our food and protect us from climate change impacts \n\n  Explore more \n           \n \n\n\n\n\n\n\n\n\n\n\n\n\n\nEnhancing livelihoods and markets\n\n\n\n\n\n\n\n\n\n\n\n\n\n\n\n Private sector The private sector drives entrepreneurship, employment and growth in rural economies, and is essential to eradicating poverty and hunger. \n\n  Explore more \n           \n \n\n\n\n\n\n\n\n\n\n\n\n\n\n\n\n\n Rural finance With access to finance, rural people can produce more, grow their enterprises, earn more and get through hard times. \n\n  Explore more \n           \n \n\n\n\n\n\n\n\n\n\n\n\n\n\n\n\n\n Markets and value chains Reliable market access and strong value chains boost productivity, increase incomes and strengthen food security \n\n  Explore more \n           \n \n\n\n\n\n\n\n\n\n\n\n\n\n\n\n\n\n Land and resources Ensuring rural people have access land and natural resources for food, shelter, income and resilience \n\n  Explore more \n           \n \n\n\n\n\n\n\n\n\n\n\nPromoting sustainable farming\n\n\n\n\n\n\n\n\n\n\n\n\n\n\n\n\n Water Water is essential for food systems, yet this precious resource is under threat. For rural communities to flourish, they must sustainably access and manage water \n\n  Explore more \n           \n \n\n\n\n\n\n\n\n\n\n\n\n\n\n\n\n\n Crops Small-scale farmers grow a third of the world’s food. In a rapidly changing world, they need support to do so sustainably. \n\n  Explore more \n           \n \n\n\n\n\n\n\n\n\n\n\n\n\n\n\n\n\n Livestock Supporting sustainable livestock production and value chains is key to eradicating poverty and hunger while addressing climate challenges. \n\n  Explore more \n           \n \n\n\n\n\n\n\n\n\n\n\n\n\n\n\n\n\n Fisheries and aquaculture Responsible stewardship of the world’s fisheries ensures better livelihoods and a healthier planet. \n\n  Explore more \n           \n \n\n\n\n\n\n\n\n\n\n\n\nBuilding resilience\n\n\n\n\n\n\n\n\n\n\n\n\n\n\n\n Rural institutions and organizations Farmers’ organizations help rural people increase their incomes and output, share knowledge, access resources and influence policy dialogue. \n\n  Explore more \n           \n \n\n\n\n\n\n\n\n\n\n\n\n\n\n\n\n\n Remittances The funds sent home by migrant workers are a lifeline for rural families, helping to build resilience and support sustainable development \n\n  Explore more \n           \n \n\n\n\n\n\n\n\n\n\n\n\n\n\n\n\n\n Nutrition An investment in agriculture is an investment in nutrition. Farming shapes sustainable food systems that nourish rural people and break cycles of poverty. \n\n  Explore more \n           \n \n\n\n\n\n\n\n\n\n\n\n\n\n\n\n\n\n Fragile contexts and crises By building resilience, rural people can better endure crises. \n\n  Explore more \n           \n \n\n\n\n\n\n\n\n\n\n\n\n\n\n\n\n       Please configure the desktop menu widget below\n      \n\n\n\n\n\n\n\n\n About IFAD \n Who we are   Where we work   What we do   Action Areas   Knowledge & Data \n\n\n For Member States \n Member States interactive platform \n\n\n For Investors \n Investors   Finance \n\n\n For Job seekers \n Work with us   Frequently Asked Questions \n\n\n For Media \n News   Media Contacts   Image Bank \n\n\n Get Involved \n Join an event   Rural Voices   Opinions & Insights \n\n\n\n\n\n\n\n\n\n\n\n\n\n       Please configure the mobile menu widget below\n      \n\n\n\n\n\n\n\n\n Who we are \n\n\n\n What we do \n\n\n\n Where we work \n\n\n\n Action Areas \n\n\n\n Knowledge & Data \n\n\n\n Get Involved \n\n\n\n News and Stories \n\n\n\n\n\n\n\n\n\n\n\n\n\n  \n Legal  Privacy notice  Fraudulent job offers  Contact us Stay connected\n\nAction areas\n\n\n\n\n\n\n\n\n\n©IFAD/GMB Akash \n\n\n\n\n\n\n\n\n\n\nIFAD’s investments support rural people so they can pull themselves out of poverty and build better lives.\n\n\n\n\n\n\n\n\nWe build resilience so rural communities have options and can weather crises skilfully.\nWe empower vulnerable groups to ensure that no one is left behind.\nWe enhance livelihoods and connect people to markets so that rural producers can prosper from their hard work.\nWe protect the environment and promote sustainable farming practices so that generations to come can thrive on a healthy planet.\nOur aim? Rural areas are transformed into prosperous and profitable places to live.\n\n\n\n\n\n\n\n\n\n\n\nEmpowering rural people\n\n\n\n\n\n\n\n\n\n\n\n\n\n\n\n\n Rural women Gender inequality is one of the biggest impediments to sustainable development. Without tackling its root causes, we cannot end global hunger and poverty \n\n  Explore more \n           \n \n\n\n\n\n\n\n\n\n\n\n\n\n\n\n\n\n\n Rural Youth As the farmers and producers of tomorrow, rural young people have the potential to feed the world's growing population. \n\n  Explore more \n           \n \n\n\n\n\n\n\n\n\n\n\n\n\n\n\n\n\n Indigenous Peoples With their traditional knowledge and deep connection to their environments, we work with Indigenous Peoples to build a more inclusive, sustainable future. \n\n  Explore more \n           \n \n\n\n\n\n\n\n\n\n\n\n\n\n\n\n\n\n Persons with disabilities Equal opportunities enable persons with disabilities to thrive while transforming rural communities \n\n  Explore more \n           \n \n\n\n\n\n\n\n\n\n\n\n\nProtecting the environment\n\n\n\n\n\n\n\n\n\n\n\n\n\n\n\n Climate and environment The lives of small-scale farmers are being upended by climate change. They need support to adapt to climate change and to protect the planet’s precious resources \n\n  Explore more \n           \n \n\n\n\n\n\n\n\n\n\n\n\n\n\n\n\n\n Biodiversity Rich and diverse ecosystems are essential to produce our food and protect us from climate change impacts \n\n  Explore more \n           \n \n\n\n\n\n\n\n\n\n\n\n\n\n\nEnhancing livelihoods and markets\n\n\n\n\n\n\n\n\n\n\n\n\n\n\n\n Private sector The private sector drives entrepreneurship, employment and growth in rural economies, and is essential to eradicating poverty and hunger. \n\n  Explore more \n           \n \n\n\n\n\n\n\n\n\n\n\n\n\n\n\n\n\n Rural finance With access to finance, rural people can produce more, grow their enterprises, earn more and get through hard times. \n\n  Explore more \n           \n \n\n\n\n\n\n\n\n\n\n\n\n\n\n\n\n\n Markets and value chains Reliable market access and strong value chains boost productivity, increase incomes and strengthen food security \n\n  Explore more \n           \n \n\n\n\n\n\n\n\n\n\n\n\n\n\n\n\n\n Land and resources Ensuring rural people have access land and natural resources for food, shelter, income and resilience \n\n  Explore more \n           \n \n\n\n\n\n\n\n\n\n\n\nPromoting sustainable farming\n\n\n\n\n\n\n\n\n\n\n\n\n\n\n\n\n Water Water is essential for food systems, yet this precious resource is under threat. For rural communities to flourish, they must sustainably access and manage water \n\n  Explore more \n           \n \n\n\n\n\n\n\n\n\n\n\n\n\n\n\n\n\n Crops Small-scale farmers grow a third of the world’s food. In a rapidly changing world, they need support to do so sustainably. \n\n  Explore more \n           \n \n\n\n\n\n\n\n\n\n\n\n\n\n\n\n\n\n Livestock Supporting sustainable livestock production and value chains is key to eradicating poverty and hunger while addressing climate challenges. \n\n  Explore more \n           \n \n\n\n\n\n\n\n\n\n\n\n\n\n\n\n\n\n Fisheries and aquaculture Responsible stewardship of the world’s fisheries ensures better livelihoods and a healthier planet. \n\n  Explore more \n           \n \n\n\n\n\n\n\n\n\n\n\n\nBuilding resilience\n\n\n\n\n\n\n\n\n\n\n\n\n\n\n\n Rural institutions and organizations Farmers’ organizations help rural people increase their incomes and output, share knowledge, access resources and influence policy dialogue. \n\n  Explore more \n           \n \n\n\n\n\n\n\n\n\n\n\n\n\n\n\n\n\n Remittances The funds sent home by migrant workers are a lifeline for rural families, helping to build resilience and support sustainable development \n\n  Explore more \n           \n \n\n\n\n\n\n\n\n\n\n\n\n\n\n\n\n\n Nutrition An investment in agriculture is an investment in nutrition. Farming shapes sustainable food systems that nourish rural people and break cycles of poverty. \n\n  Explore more \n           \n \n\n\n\n\n\n\n\n\n\n\n\n\n\n\n\n\n Fragile contexts and crises By building resilience, rural people can better endure crises. \n\n  Explore more \n           \n \n\n\n\n\n\n\n\n\n\n\n\n\n\n\n\n       Please configure the desktop menu widget below\n      \n\n\n\n\n\n\n\n\n About IFAD \n Who we are   Where we work   What we do   Action Areas   Knowledge & Data \n\n\n For Member States \n Member States interactive platform \n\n\n For Investors \n Investors   Finance \n\n\n For Job seekers \n Work with us   Frequently Asked Questions \n\n\n For Media \n News   Media Contacts   Image Bank \n\n\n Get Involved \n Join an event   Rural Voices   Opinions & Insights \n\n\n\n\n\n\n\n\n\n\n\n\n\n       Please configure the mobile menu widget below\n      \n\n\n\n\n\n\n\n\n Who we are \n\n\n\n What we do \n\n\n\n Where we work \n\n\n\n Action Areas \n\n\n\n Knowledge & Data \n\n\n\n Get Involved \n\n\n\n News and Stories \n\n\n\n\n\n\n\n\n\n\n\n\n\n  \n Legal  Privacy notice  Fraudulent job offers  Contact us Stay connected\n\nAction areas\n\n\n\n\n\n\n\n\n\n©IFAD/GMB Akash \n\n\n\n\n\n\n\n\n\n\nIFAD’s investments support rural people so they can pull themselves out of poverty and build better lives.\n\n\n\n\n\n\n\n\nWe build resilience so rural communities have options and can weather crises skilfully.\nWe empower vulnerable groups to ensure that no one is left behind.\nWe enhance livelihoods and connect people to markets so that rural producers can prosper from their hard work.\nWe protect the environment and promote sustainable farming practices so that generations to come can thrive on a healthy planet.\nOur aim? Rural areas are transformed into prosperous and profitable places to live.\n\n\n\n\n\n\n\n\n\n\n\nEmpowering rural people\n\n\n\n\n\n\n\n\n\n\n\n\n\n\n\n\n Rural women Gender inequality is one of the biggest impediments to sustainable development. Without tackling its root causes, we cannot end global hunger and poverty \n\n  Explore more \n           \n \n\n\n\n\n\n\n\n\n\n\n\n\n\n\n\n\n\n Rural Youth As the farmers and producers of tomorrow, rural young people have the potential to feed the world's growing population. \n\n  Explore more \n           \n \n\n\n\n\n\n\n\n\n\n\n\n\n\n\n\n\n Indigenous Peoples With their traditional knowledge and deep connection to their environments, we work with Indigenous Peoples to build a more inclusive, sustainable future. \n\n  Explore more \n           \n \n\n\n\n\n\n\n\n\n\n\n\n\n\n\n\n\n Persons with disabilities Equal opportunities enable persons with disabilities to thrive while transforming rural communities \n\n  Explore more \n           \n \n\n\n\n\n\n\n\n\n\n\n\nProtecting the environment\n\n\n\n\n\n\n\n\n\n\n\n\n\n\n\n Climate and environment The lives of small-scale farmers are being upended by climate change. They need support to adapt to climate change and to protect the planet’s precious resources \n\n  Explore more \n           \n \n\n\n\n\n\n\n\n\n\n\n\n\n\n\n\n\n Biodiversity Rich and diverse ecosystems are essential to produce our food and protect us from climate change impacts \n\n  Explore more \n           \n \n\n\n\n\n\n\n\n\n\n\n\n\n\nEnhancing livelihoods and markets\n\n\n\n\n\n\n\n\n\n\n\n\n\n\n\n Private sector The private sector drives entrepreneurship, employment and growth in rural economies, and is essential to eradicating poverty and hunger. \n\n  Explore more \n           \n \n\n\n\n\n\n\n\n\n\n\n\n\n\n\n\n\n Rural finance With access to finance, rural people can produce more, grow their enterprises, earn more and get through hard times. \n\n  Explore more \n           \n \n\n\n\n\n\n\n\n\n\n\n\n\n\n\n\n\n Markets and value chains Reliable market access and strong value chains boost productivity, increase incomes and strengthen food security \n\n  Explore more \n           \n \n\n\n\n\n\n\n\n\n\n\n\n\n\n\n\n\n Land and resources Ensuring rural people have access land and natural resources for food, shelter, income and resilience \n\n  Explore more \n           \n \n\n\n\n\n\n\n\n\n\n\nPromoting sustainable farming\n\n\n\n\n\n\n\n\n\n\n\n\n\n\n\n\n Water Water is essential for food systems, yet this precious resource is under threat. For rural communities to flourish, they must sustainably access and manage water \n\n  Explore more \n           \n \n\n\n\n\n\n\n\n\n\n\n\n\n\n\n\n\n Crops Small-scale farmers grow a third of the world’s food. In a rapidly changing world, they need support to do so sustainably. \n\n  Explore more \n           \n \n\n\n\n\n\n\n\n\n\n\n\n\n\n\n\n\n Livestock Supporting sustainable livestock production and value chains is key to eradicating poverty and hunger while addressing climate challenges. \n\n  Explore more \n           \n \n\n\n\n\n\n\n\n\n\n\n\n\n\n\n\n\n Fisheries and aquaculture Responsible stewardship of the world’s fisheries ensures better livelihoods and a healthier planet. \n\n  Explore more \n           \n \n\n\n\n\n\n\n\n\n\n\n\nBuilding resilience\n\n\n\n\n\n\n\n\n\n\n\n\n\n\n\n Rural institutions and organizations Farmers’ organizations help rural people increase their incomes and output, share knowledge, access resources and influence policy dialogue. \n\n  Explore more \n           \n \n\n\n\n\n\n\n\n\n\n\n\n\n\n\n\n\n Remittances The funds sent home by migrant workers are a lifeline for rural families, helping to build resilience and support sustainable development \n\n  Explore more \n           \n \n\n\n\n\n\n\n\n\n\n\n\n\n\n\n\n\n Nutrition An investment in agriculture is an investment in nutrition. Farming shapes sustainable food systems that nourish rural people and break cycles of poverty. \n\n  Explore more \n           \n \n\n\n\n\n\n\n\n\n\n\n\n\n\n\n\n\n Fragile contexts and crises By building resilience, rural people can better endure crises. \n\n  Explore more\n\nAction areas\n\nAction areas\n\nAction areas\n\nAction areas\n\n©IFAD/GMB Akash\n\n©IFAD/GMB Akash\n\n©IFAD/GMB Akash\n\nIFAD’s investments support rural people so they can pull themselves out of poverty and build better lives.\n\n\n\n\n\n\n\n\nWe build resilience so rural communities have options and can weather crises skilfully.\nWe empower vulnerable groups to ensure that no one is left behind.\nWe enhance livelihoods and connect people to markets so that rural producers can prosper from their hard work.\nWe protect the environment and promote sustainable farming practices so that generations to come can thrive on a healthy planet.\nOur aim? Rural areas are transformed into prosperous and profitable places to live.\n\nIFAD’s investments support rural people so they can pull themselves out of poverty and build better lives.\n\n\n\n\n\n\n\n\nWe build resilience so rural communities have options and can weather crises skilfully.\nWe empower vulnerable groups to ensure that no one is left behind.\nWe enhance livelihoods and connect people to markets so that rural producers can prosper from their hard work.\nWe protect the environment and promote sustainable farming practices so that generations to come can thrive on a healthy planet.\nOur aim? Rural areas are transformed into prosperous and profitable places to live.\n\nIFAD’s investments support rural people so they can pull themselves out of poverty and build better lives.\n\n\n\n\n\n\n\n\nWe build resilience so rural communities have options and can weather crises skilfully.\nWe empower vulnerable groups to ensure that no one is left behind.\nWe enhance livelihoods and connect people to markets so that rural producers can prosper from their hard work.\nWe protect the environment and promote sustainable farming practices so that generations to come can thrive on a healthy planet.\nOur aim? Rural areas are transformed into prosperous and profitable places to live.\n\nIFAD’s investments support rural people so they can pull themselves out of poverty and build better lives.\n\nIFAD’s investments support rural people so they can pull themselves out of poverty and build better lives.\n\nIFAD’s investments support rural people so they can pull themselves out of poverty and build better lives.\n\nWe build resilience so rural communities have options and can weather crises skilfully.\nWe empower vulnerable groups to ensure that no one is left behind.\nWe enhance livelihoods and connect people to markets so that rural producers can prosper from their hard work.\nWe protect the environment and promote sustainable farming practices so that generations to come can thrive on a healthy planet.\nOur aim? Rural areas are transformed into prosperous and profitable places to live.\n\nWe build resilience so rural communities have options and can weather crises skilfully.\nWe empower vulnerable groups to ensure that no one is left behind.\nWe enhance livelihoods and connect people to markets so that rural producers can prosper from their hard work.\nWe protect the environment and promote sustainable farming practices so that generations to come can thrive on a healthy planet.\nOur aim? Rural areas are transformed into prosperous and profitable places to live.\n\nWe build resilience so rural communities have options and can weather crises skilfully.\nWe empower vulnerable groups to ensure that no one is left behind.\nWe enhance livelihoods and connect people to markets so that rural producers can prosper from their hard work.\nWe protect the environment and promote sustainable farming practices so that generations to come can thrive on a healthy planet.\nOur aim? Rural areas are transformed into prosperous and profitable places to live.\n\nWe build resilience so rural communities have options and can weather crises skilfully.\nWe empower vulnerable groups to ensure that no one is left behind.\nWe enhance livelihoods and connect people to markets so that rural producers can prosper from their hard work.\nWe protect the environment and promote sustainable farming practices so that generations to come can thrive on a healthy planet.\nOur aim? Rural areas are transformed into prosperous and profitable places to live.\n\nWe build resilience so rural communities have options and can weather crises skilfully.\n\nWe empower vulnerable groups to ensure that no one is left behind.\n\nWe enhance livelihoods and connect people to markets so that rural producers can prosper from their hard work.\n\nWe protect the environment and promote sustainable farming practices so that generations to come can thrive on a healthy planet.\n\nOur aim? Rural areas are transformed into prosperous and profitable places to live.\n\nEmpowering rural people\n\n\n\n\n\n\n\n\n\n\n\n\n\n\n\n\n Rural women Gender inequality is one of the biggest impediments to sustainable development. Without tackling its root causes, we cannot end global hunger and poverty \n\n  Explore more \n           \n \n\n\n\n\n\n\n\n\n\n\n\n\n\n\n\n\n\n Rural Youth As the farmers and producers of tomorrow, rural young people have the potential to feed the world's growing population. \n\n  Explore more \n           \n \n\n\n\n\n\n\n\n\n\n\n\n\n\n\n\n\n Indigenous Peoples With their traditional knowledge and deep connection to their environments, we work with Indigenous Peoples to build a more inclusive, sustainable future. \n\n  Explore more \n           \n \n\n\n\n\n\n\n\n\n\n\n\n\n\n\n\n\n Persons with disabilities Equal opportunities enable persons with disabilities to thrive while transforming rural communities \n\n  Explore more\n\nEmpowering rural people\n\nEmpowering rural people\n\nRural women Gender inequality is one of the biggest impediments to sustainable development. Without tackling its root causes, we cannot end global hunger and poverty \n\n  Explore more \n           \n \n\n\n\n\n\n\n\n\n\n\n\n\n\n\n\n\n\n Rural Youth As the farmers and producers of tomorrow, rural young people have the potential to feed the world's growing population. \n\n  Explore more \n           \n \n\n\n\n\n\n\n\n\n\n\n\n\n\n\n\n\n Indigenous Peoples With their traditional knowledge and deep connection to their environments, we work with Indigenous Peoples to build a more inclusive, sustainable future. \n\n  Explore more \n           \n \n\n\n\n\n\n\n\n\n\n\n\n\n\n\n\n\n Persons with disabilities Equal opportunities enable persons with disabilities to thrive while transforming rural communities \n\n  Explore more\n\nRural women Gender inequality is one of the biggest impediments to sustainable development. Without tackling its root causes, we cannot end global hunger and poverty \n\n  Explore more \n           \n \n\n\n\n\n\n\n\n\n\n\n\n\n\n\n\n\n\n Rural Youth As the farmers and producers of tomorrow, rural young people have the potential to feed the world's growing population. \n\n  Explore more \n           \n \n\n\n\n\n\n\n\n\n\n\n\n\n\n\n\n\n Indigenous Peoples With their traditional knowledge and deep connection to their environments, we work with Indigenous Peoples to build a more inclusive, sustainable future. \n\n  Explore more \n           \n \n\n\n\n\n\n\n\n\n\n\n\n\n\n\n\n\n Persons with disabilities Equal opportunities enable persons with disabilities to thrive while transforming rural communities \n\n  Explore more\n\nRural women Gender inequality is one of the biggest impediments to sustainable development. Without tackling its root causes, we cannot end global hunger and poverty \n\n  Explore more\n\nRural women Gender inequality is one of the biggest impediments to sustainable development. Without tackling its root causes, we cannot end global hunger and poverty \n\n  Explore more\n\nRural women Gender inequality is one of the biggest impediments to sustainable development. Without tackling its root causes, we cannot end global hunger and poverty \n\n  Explore more\n\nRural women Gender inequality is one of the biggest impediments to sustainable development. Without tackling its root causes, we cannot end global hunger and poverty \n\n  Explore more\n\nRural women Gender inequality is one of the biggest impediments to sustainable development. Without tackling its root causes, we cannot end global hunger and poverty \n\n  Explore more\n\nRural women Gender inequality is one of the biggest impediments to sustainable development. Without tackling its root causes, we cannot end global hunger and poverty\n\nRural women Gender inequality is one of the biggest impediments to sustainable development. Without tackling its root causes, we cannot end global hunger and poverty\n\nRural women\n\nGender inequality is one of the biggest impediments to sustainable development. Without tackling its root causes, we cannot end global hunger and poverty\n\nRural Youth As the farmers and producers of tomorrow, rural young people have the potential to feed the world's growing population. \n\n  Explore more\n\nRural Youth As the farmers and producers of tomorrow, rural young people have the potential to feed the world's growing population. \n\n  Explore more\n\nRural Youth As the farmers and producers of tomorrow, rural young people have the potential to feed the world's growing population. \n\n  Explore more\n\nRural Youth As the farmers and producers of tomorrow, rural young people have the potential to feed the world's growing population. \n\n  Explore more\n\nRural Youth As the farmers and producers of tomorrow, rural young people have the potential to feed the world's growing population. \n\n  Explore more\n\nRural Youth As the farmers and producers of tomorrow, rural young people have the potential to feed the world's growing population.\n\nRural Youth As the farmers and producers of tomorrow, rural young people have the potential to feed the world's growing population.\n\nRural Youth\n\nAs the farmers and producers of tomorrow, rural young people have the potential to feed the world's growing population.\n\nIndigenous Peoples With their traditional knowledge and deep connection to their environments, we work with Indigenous Peoples to build a more inclusive, sustainable future. \n\n  Explore more\n\nIndigenous Peoples With their traditional knowledge and deep connection to their environments, we work with Indigenous Peoples to build a more inclusive, sustainable future. \n\n  Explore more\n\nIndigenous Peoples With their traditional knowledge and deep connection to their environments, we work with Indigenous Peoples to build a more inclusive, sustainable future. \n\n  Explore more\n\nIndigenous Peoples With their traditional knowledge and deep connection to their environments, we work with Indigenous Peoples to build a more inclusive, sustainable future. \n\n  Explore more\n\nIndigenous Peoples With their traditional knowledge and deep connection to their environments, we work with Indigenous Peoples to build a more inclusive, sustainable future. \n\n  Explore more\n\nIndigenous Peoples With their traditional knowledge and deep connection to their environments, we work with Indigenous Peoples to build a more inclusive, sustainable future.\n\nIndigenous Peoples With their traditional knowledge and deep connection to their environments, we work with Indigenous Peoples to build a more inclusive, sustainable future.\n\nIndigenous Peoples\n\nWith their traditional knowledge and deep connection to their environments, we work with Indigenous Peoples to build a more inclusive, sustainable future.\n\nPersons with disabilities Equal opportunities enable persons with disabilities to thrive while transforming rural communities \n\n  Explore more\n\nPersons with disabilities Equal opportunities enable persons with disabilities to thrive while transforming rural communities \n\n  Explore more\n\nPersons with disabilities Equal opportunities enable persons with disabilities to thrive while transforming rural communities \n\n  Explore more\n\nPersons with disabilities Equal opportunities enable persons with disabilities to thrive while transforming rural communities \n\n  Explore more\n\nPersons with disabilities Equal opportunities enable persons with disabilities to thrive while transforming rural communities \n\n  Explore more\n\nPersons with disabilities Equal opportunities enable persons with disabilities to thrive while transforming rural communities\n\nPersons with disabilities Equal opportunities enable persons with disabilities to thrive while transforming rural communities\n\nPersons with disabilities\n\nEqual opportunities enable persons with disabilities to thrive while transforming rural communities\n\nProtecting the environment\n\n\n\n\n\n\n\n\n\n\n\n\n\n\n\n Climate and environment The lives of small-scale farmers are being upended by climate change. They need support to adapt to climate change and to protect the planet’s precious resources \n\n  Explore more \n           \n \n\n\n\n\n\n\n\n\n\n\n\n\n\n\n\n\n Biodiversity Rich and diverse ecosystems are essential to produce our food and protect us from climate change impacts \n\n  Explore more\n\nProtecting the environment\n\nProtecting the environment\n\nClimate and environment The lives of small-scale farmers are being upended by climate change. They need support to adapt to climate change and to protect the planet’s precious resources \n\n  Explore more \n           \n \n\n\n\n\n\n\n\n\n\n\n\n\n\n\n\n\n Biodiversity Rich and diverse ecosystems are essential to produce our food and protect us from climate change impacts \n\n  Explore more\n\nClimate and environment The lives of small-scale farmers are being upended by climate change. They need support to adapt to climate change and to protect the planet’s precious resources \n\n  Explore more \n           \n \n\n\n\n\n\n\n\n\n\n\n\n\n\n\n\n\n Biodiversity Rich and diverse ecosystems are essential to produce our food and protect us from climate change impacts \n\n  Explore more\n\nClimate and environment The lives of small-scale farmers are being upended by climate change. They need support to adapt to climate change and to protect the planet’s precious resources \n\n  Explore more\n\nClimate and environment The lives of small-scale farmers are being upended by climate change. They need support to adapt to climate change and to protect the planet’s precious resources \n\n  Explore more\n\nClimate and environment The lives of small-scale farmers are being upended by climate change. They need support to adapt to climate change and to protect the planet’s precious resources \n\n  Explore more\n\nClimate and environment The lives of small-scale farmers are being upended by climate change. They need support to adapt to climate change and to protect the planet’s precious resources \n\n  Explore more\n\nClimate and environment The lives of small-scale farmers are being upended by climate change. They need support to adapt to climate change and to protect the planet’s precious resources \n\n  Explore more\n\nClimate and environment The lives of small-scale farmers are being upended by climate change. They need support to adapt to climate change and to protect the planet’s precious resources\n\nClimate and environment The lives of small-scale farmers are being upended by climate change. They need support to adapt to climate change and to protect the planet’s precious resources\n\nClimate and environment\n\nThe lives of small-scale farmers are being upended by climate change. They need support to adapt to climate change and to protect the planet’s precious resources\n\nBiodiversity Rich and diverse ecosystems are essential to produce our food and protect us from climate change impacts \n\n  Explore more\n\nBiodiversity Rich and diverse ecosystems are essential to produce our food and protect us from climate change impacts \n\n  Explore more\n\nBiodiversity Rich and diverse ecosystems are essential to produce our food and protect us from climate change impacts \n\n  Explore more\n\nBiodiversity Rich and diverse ecosystems are essential to produce our food and protect us from climate change impacts \n\n  Explore more\n\nBiodiversity Rich and diverse ecosystems are essential to produce our food and protect us from climate change impacts \n\n  Explore more\n\nBiodiversity Rich and diverse ecosystems are essential to produce our food and protect us from climate change impacts\n\nBiodiversity Rich and diverse ecosystems are essential to produce our food and protect us from climate change impacts\n\nBiodiversity\n\nRich and diverse ecosystems are essential to produce our food and protect us from climate change impacts\n\nEnhancing livelihoods and markets\n\n\n\n\n\n\n\n\n\n\n\n\n\n\n\n Private sector The private sector drives entrepreneurship, employment and growth in rural economies, and is essential to eradicating poverty and hunger. \n\n  Explore more \n           \n \n\n\n\n\n\n\n\n\n\n\n\n\n\n\n\n\n Rural finance With access to finance, rural people can produce more, grow their enterprises, earn more and get through hard times. \n\n  Explore more \n           \n \n\n\n\n\n\n\n\n\n\n\n\n\n\n\n\n\n Markets and value chains Reliable market access and strong value chains boost productivity, increase incomes and strengthen food security \n\n  Explore more \n           \n \n\n\n\n\n\n\n\n\n\n\n\n\n\n\n\n\n Land and resources Ensuring rural people have access land and natural resources for food, shelter, income and resilience \n\n  Explore more\n\nEnhancing livelihoods and markets\n\nEnhancing livelihoods and markets\n\nPrivate sector The private sector drives entrepreneurship, employment and growth in rural economies, and is essential to eradicating poverty and hunger. \n\n  Explore more \n           \n \n\n\n\n\n\n\n\n\n\n\n\n\n\n\n\n\n Rural finance With access to finance, rural people can produce more, grow their enterprises, earn more and get through hard times. \n\n  Explore more \n           \n \n\n\n\n\n\n\n\n\n\n\n\n\n\n\n\n\n Markets and value chains Reliable market access and strong value chains boost productivity, increase incomes and strengthen food security \n\n  Explore more \n           \n \n\n\n\n\n\n\n\n\n\n\n\n\n\n\n\n\n Land and resources Ensuring rural people have access land and natural resources for food, shelter, income and resilience \n\n  Explore more\n\nPrivate sector The private sector drives entrepreneurship, employment and growth in rural economies, and is essential to eradicating poverty and hunger. \n\n  Explore more \n           \n \n\n\n\n\n\n\n\n\n\n\n\n\n\n\n\n\n Rural finance With access to finance, rural people can produce more, grow their enterprises, earn more and get through hard times. \n\n  Explore more \n           \n \n\n\n\n\n\n\n\n\n\n\n\n\n\n\n\n\n Markets and value chains Reliable market access and strong value chains boost productivity, increase incomes and strengthen food security \n\n  Explore more \n           \n \n\n\n\n\n\n\n\n\n\n\n\n\n\n\n\n\n Land and resources Ensuring rural people have access land and natural resources for food, shelter, income and resilience \n\n  Explore more\n\nPrivate sector The private sector drives entrepreneurship, employment and growth in rural economies, and is essential to eradicating poverty and hunger. \n\n  Explore more\n\nPrivate sector The private sector drives entrepreneurship, employment and growth in rural economies, and is essential to eradicating poverty and hunger. \n\n  Explore more\n\nPrivate sector The private sector drives entrepreneurship, employment and growth in rural economies, and is essential to eradicating poverty and hunger. \n\n  Explore more\n\nPrivate sector The private sector drives entrepreneurship, employment and growth in rural economies, and is essential to eradicating poverty and hunger. \n\n  Explore more\n\nPrivate sector The private sector drives entrepreneurship, employment and growth in rural economies, and is essential to eradicating poverty and hunger. \n\n  Explore more\n\nPrivate sector The private sector drives entrepreneurship, employment and growth in rural economies, and is essential to eradicating poverty and hunger.\n\nPrivate sector The private sector drives entrepreneurship, employment and growth in rural economies, and is essential to eradicating poverty and hunger.\n\nPrivate sector\n\nThe private sector drives entrepreneurship, employment and growth in rural economies, and is essential to eradicating poverty and hunger.\n\nRural finance With access to finance, rural people can produce more, grow their enterprises, earn more and get through hard times. \n\n  Explore more\n\nRural finance With access to finance, rural people can produce more, grow their enterprises, earn more and get through hard times. \n\n  Explore more\n\nRural finance With access to finance, rural people can produce more, grow their enterprises, earn more and get through hard times. \n\n  Explore more\n\nRural finance With access to finance, rural people can produce more, grow their enterprises, earn more and get through hard times. \n\n  Explore more\n\nRural finance With access to finance, rural people can produce more, grow their enterprises, earn more and get through hard times. \n\n  Explore more\n\nRural finance With access to finance, rural people can produce more, grow their enterprises, earn more and get through hard times.\n\nRural finance With access to finance, rural people can produce more, grow their enterprises, earn more and get through hard times.\n\nRural finance\n\nWith access to finance, rural people can produce more, grow their enterprises, earn more and get through hard times.\n\nMarkets and value chains Reliable market access and strong value chains boost productivity, increase incomes and strengthen food security \n\n  Explore more\n\nMarkets and value chains Reliable market access and strong value chains boost productivity, increase incomes and strengthen food security \n\n  Explore more\n\nMarkets and value chains Reliable market access and strong value chains boost productivity, increase incomes and strengthen food security \n\n  Explore more\n\nMarkets and value chains Reliable market access and strong value chains boost productivity, increase incomes and strengthen food security \n\n  Explore more\n\nMarkets and value chains Reliable market access and strong value chains boost productivity, increase incomes and strengthen food security \n\n  Explore more\n\nMarkets and value chains Reliable market access and strong value chains boost productivity, increase incomes and strengthen food security\n\nMarkets and value chains Reliable market access and strong value chains boost productivity, increase incomes and strengthen food security\n\nMarkets and value chains\n\nReliable market access and strong value chains boost productivity, increase incomes and strengthen food security\n\nLand and resources Ensuring rural people have access land and natural resources for food, shelter, income and resilience \n\n  Explore more\n\nLand and resources Ensuring rural people have access land and natural resources for food, shelter, income and resilience \n\n  Explore more\n\nLand and resources Ensuring rural people have access land and natural resources for food, shelter, income and resilience \n\n  Explore more\n\nLand and resources Ensuring rural people have access land and natural resources for food, shelter, income and resilience \n\n  Explore more\n\nLand and resources Ensuring rural people have access land and natural resources for food, shelter, income and resilience \n\n  Explore more\n\nLand and resources Ensuring rural people have access land and natural resources for food, shelter, income and resilience\n\nLand and resources Ensuring rural people have access land and natural resources for food, shelter, income and resilience\n\nLand and resources\n\nEnsuring rural people have access land and natural resources for food, shelter, income and resilience\n\nPromoting sustainable farming\n\nPromoting sustainable farming\n\nWater Water is essential for food systems, yet this precious resource is under threat. For rural communities to flourish, they must sustainably access and manage water \n\n  Explore more \n           \n \n\n\n\n\n\n\n\n\n\n\n\n\n\n\n\n\n Crops Small-scale farmers grow a third of the world’s food. In a rapidly changing world, they need support to do so sustainably. \n\n  Explore more \n           \n \n\n\n\n\n\n\n\n\n\n\n\n\n\n\n\n\n Livestock Supporting sustainable livestock production and value chains is key to eradicating poverty and hunger while addressing climate challenges. \n\n  Explore more \n           \n \n\n\n\n\n\n\n\n\n\n\n\n\n\n\n\n\n Fisheries and aquaculture Responsible stewardship of the world’s fisheries ensures better livelihoods and a healthier planet. \n\n  Explore more\n\nWater Water is essential for food systems, yet this precious resource is under threat. For rural communities to flourish, they must sustainably access and manage water \n\n  Explore more \n           \n \n\n\n\n\n\n\n\n\n\n\n\n\n\n\n\n\n Crops Small-scale farmers grow a third of the world’s food. In a rapidly changing world, they need support to do so sustainably. \n\n  Explore more \n           \n \n\n\n\n\n\n\n\n\n\n\n\n\n\n\n\n\n Livestock Supporting sustainable livestock production and value chains is key to eradicating poverty and hunger while addressing climate challenges. \n\n  Explore more \n           \n \n\n\n\n\n\n\n\n\n\n\n\n\n\n\n\n\n Fisheries and aquaculture Responsible stewardship of the world’s fisheries ensures better livelihoods and a healthier planet. \n\n  Explore more\n\nWater Water is essential for food systems, yet this precious resource is under threat. For rural communities to flourish, they must sustainably access and manage water \n\n  Explore more \n           \n \n\n\n\n\n\n\n\n\n\n\n\n\n\n\n\n\n Crops Small-scale farmers grow a third of the world’s food. In a rapidly changing world, they need support to do so sustainably. \n\n  Explore more \n           \n \n\n\n\n\n\n\n\n\n\n\n\n\n\n\n\n\n Livestock Supporting sustainable livestock production and value chains is key to eradicating poverty and hunger while addressing climate challenges. \n\n  Explore more \n           \n \n\n\n\n\n\n\n\n\n\n\n\n\n\n\n\n\n Fisheries and aquaculture Responsible stewardship of the world’s fisheries ensures better livelihoods and a healthier planet. \n\n  Explore more\n\nWater Water is essential for food systems, yet this precious resource is under threat. For rural communities to flourish, they must sustainably access and manage water \n\n  Explore more\n\nWater Water is essential for food systems, yet this precious resource is under threat. For rural communities to flourish, they must sustainably access and manage water \n\n  Explore more\n\nWater Water is essential for food systems, yet this precious resource is under threat. For rural communities to flourish, they must sustainably access and manage water \n\n  Explore more\n\nWater Water is essential for food systems, yet this precious resource is under threat. For rural communities to flourish, they must sustainably access and manage water \n\n  Explore more\n\nWater Water is essential for food systems, yet this precious resource is under threat. For rural communities to flourish, they must sustainably access and manage water \n\n  Explore more\n\nWater Water is essential for food systems, yet this precious resource is under threat. For rural communities to flourish, they must sustainably access and manage water\n\nWater Water is essential for food systems, yet this precious resource is under threat. For rural communities to flourish, they must sustainably access and manage water\n\nWater\n\nWater is essential for food systems, yet this precious resource is under threat. For rural communities to flourish, they must sustainably access and manage water\n\nCrops Small-scale farmers grow a third of the world’s food. In a rapidly changing world, they need support to do so sustainably. \n\n  Explore more\n\nCrops Small-scale farmers grow a third of the world’s food. In a rapidly changing world, they need support to do so sustainably. \n\n  Explore more\n\nCrops Small-scale farmers grow a third of the world’s food. In a rapidly changing world, they need support to do so sustainably. \n\n  Explore more\n\nCrops Small-scale farmers grow a third of the world’s food. In a rapidly changing world, they need support to do so sustainably. \n\n  Explore more\n\nCrops Small-scale farmers grow a third of the world’s food. In a rapidly changing world, they need support to do so sustainably. \n\n  Explore more\n\nCrops Small-scale farmers grow a third of the world’s food. In a rapidly changing world, they need support to do so sustainably.\n\nCrops Small-scale farmers grow a third of the world’s food. In a rapidly changing world, they need support to do so sustainably.\n\nCrops\n\nSmall-scale farmers grow a third of the world’s food. In a rapidly changing world, they need support to do so sustainably.\n\nLivestock Supporting sustainable livestock production and value chains is key to eradicating poverty and hunger while addressing climate challenges. \n\n  Explore more\n\nLivestock Supporting sustainable livestock production and value chains is key to eradicating poverty and hunger while addressing climate challenges. \n\n  Explore more\n\nLivestock Supporting sustainable livestock production and value chains is key to eradicating poverty and hunger while addressing climate challenges. \n\n  Explore more\n\nLivestock Supporting sustainable livestock production and value chains is key to eradicating poverty and hunger while addressing climate challenges. \n\n  Explore more\n\nLivestock Supporting sustainable livestock production and value chains is key to eradicating poverty and hunger while addressing climate challenges. \n\n  Explore more\n\nLivestock Supporting sustainable livestock production and value chains is key to eradicating poverty and hunger while addressing climate challenges.\n\nLivestock Supporting sustainable livestock production and value chains is key to eradicating poverty and hunger while addressing climate challenges.\n\nLivestock\n\nSupporting sustainable livestock production and value chains is key to eradicating poverty and hunger while addressing climate challenges.\n\nFisheries and aquaculture Responsible stewardship of the world’s fisheries ensures better livelihoods and a healthier planet. \n\n  Explore more\n\nFisheries and aquaculture Responsible stewardship of the world’s fisheries ensures better livelihoods and a healthier planet. \n\n  Explore more\n\nFisheries and aquaculture Responsible stewardship of the world’s fisheries ensures better livelihoods and a healthier planet. \n\n  Explore more\n\nFisheries and aquaculture Responsible stewardship of the world’s fisheries ensures better livelihoods and a healthier planet. \n\n  Explore more\n\nFisheries and aquaculture Responsible stewardship of the world’s fisheries ensures better livelihoods and a healthier planet. \n\n  Explore more\n\nFisheries and aquaculture Responsible stewardship of the world’s fisheries ensures better livelihoods and a healthier planet.\n\nFisheries and aquaculture Responsible stewardship of the world’s fisheries ensures better livelihoods and a healthier planet.\n\nFisheries and aquaculture\n\nResponsible stewardship of the world’s fisheries ensures better livelihoods and a healthier planet.\n\nBuilding resilience\n\n\n\n\n\n\n\n\n\n\n\n\n\n\n\n Rural institutions and organizations Farmers’ organizations help rural people increase their incomes and output, share knowledge, access resources and influence policy dialogue. \n\n  Explore more \n           \n \n\n\n\n\n\n\n\n\n\n\n\n\n\n\n\n\n Remittances The funds sent home by migrant workers are a lifeline for rural families, helping to build resilience and support sustainable development \n\n  Explore more \n           \n \n\n\n\n\n\n\n\n\n\n\n\n\n\n\n\n\n Nutrition An investment in agriculture is an investment in nutrition. Farming shapes sustainable food systems that nourish rural people and break cycles of poverty. \n\n  Explore more \n           \n \n\n\n\n\n\n\n\n\n\n\n\n\n\n\n\n\n Fragile contexts and crises By building resilience, rural people can better endure crises. \n\n  Explore more\n\nBuilding resilience\n\nBuilding resilience\n\nRural institutions and organizations Farmers’ organizations help rural people increase their incomes and output, share knowledge, access resources and influence policy dialogue. \n\n  Explore more \n           \n \n\n\n\n\n\n\n\n\n\n\n\n\n\n\n\n\n Remittances The funds sent home by migrant workers are a lifeline for rural families, helping to build resilience and support sustainable development \n\n  Explore more \n           \n \n\n\n\n\n\n\n\n\n\n\n\n\n\n\n\n\n Nutrition An investment in agriculture is an investment in nutrition. Farming shapes sustainable food systems that nourish rural people and break cycles of poverty. \n\n  Explore more \n           \n \n\n\n\n\n\n\n\n\n\n\n\n\n\n\n\n\n Fragile contexts and crises By building resilience, rural people can better endure crises. \n\n  Explore more\n\nRural institutions and organizations Farmers’ organizations help rural people increase their incomes and output, share knowledge, access resources and influence policy dialogue. \n\n  Explore more \n           \n \n\n\n\n\n\n\n\n\n\n\n\n\n\n\n\n\n Remittances The funds sent home by migrant workers are a lifeline for rural families, helping to build resilience and support sustainable development \n\n  Explore more \n           \n \n\n\n\n\n\n\n\n\n\n\n\n\n\n\n\n\n Nutrition An investment in agriculture is an investment in nutrition. Farming shapes sustainable food systems that nourish rural people and break cycles of poverty. \n\n  Explore more \n           \n \n\n\n\n\n\n\n\n\n\n\n\n\n\n\n\n\n Fragile contexts and crises By building resilience, rural people can better endure crises. \n\n  Explore more\n\nRural institutions and organizations Farmers’ organizations help rural people increase their incomes and output, share knowledge, access resources and influence policy dialogue. \n\n  Explore more\n\nRural institutions and organizations Farmers’ organizations help rural people increase their incomes and output, share knowledge, access resources and influence policy dialogue. \n\n  Explore more\n\nRural institutions and organizations Farmers’ organizations help rural people increase their incomes and output, share knowledge, access resources and influence policy dialogue. \n\n  Explore more\n\nRural institutions and organizations Farmers’ organizations help rural people increase their incomes and output, share knowledge, access resources and influence policy dialogue. \n\n  Explore more\n\nRural institutions and organizations Farmers’ organizations help rural people increase their incomes and output, share knowledge, access resources and influence policy dialogue. \n\n  Explore more\n\nRural institutions and organizations Farmers’ organizations help rural people increase their incomes and output, share knowledge, access resources and influence policy dialogue.\n\nRural institutions and organizations Farmers’ organizations help rural people increase their incomes and output, share knowledge, access resources and influence policy dialogue.\n\nRural institutions and organizations\n\nFarmers’ organizations help rural people increase their incomes and output, share knowledge, access resources and influence policy dialogue.\n\nRemittances The funds sent home by migrant workers are a lifeline for rural families, helping to build resilience and support sustainable development \n\n  Explore more\n\nRemittances The funds sent home by migrant workers are a lifeline for rural families, helping to build resilience and support sustainable development \n\n  Explore more\n\nRemittances The funds sent home by migrant workers are a lifeline for rural families, helping to build resilience and support sustainable development \n\n  Explore more\n\nRemittances The funds sent home by migrant workers are a lifeline for rural families, helping to build resilience and support sustainable development \n\n  Explore more\n\nRemittances The funds sent home by migrant workers are a lifeline for rural families, helping to build resilience and support sustainable development \n\n  Explore more\n\nRemittances The funds sent home by migrant workers are a lifeline for rural families, helping to build resilience and support sustainable development\n\nRemittances The funds sent home by migrant workers are a lifeline for rural families, helping to build resilience and support sustainable development\n\nRemittances\n\nThe funds sent home by migrant workers are a lifeline for rural families, helping to build resilience and support sustainable development\n\nNutrition An investment in agriculture is an investment in nutrition. Farming shapes sustainable food systems that nourish rural people and break cycles of poverty. \n\n  Explore more\n\nNutrition An investment in agriculture is an investment in nutrition. Farming shapes sustainable food systems that nourish rural people and break cycles of poverty. \n\n  Explore more\n\nNutrition An investment in agriculture is an investment in nutrition. Farming shapes sustainable food systems that nourish rural people and break cycles of poverty. \n\n  Explore more\n\nNutrition An investment in agriculture is an investment in nutrition. Farming shapes sustainable food systems that nourish rural people and break cycles of poverty. \n\n  Explore more\n\nNutrition An investment in agriculture is an investment in nutrition. Farming shapes sustainable food systems that nourish rural people and break cycles of poverty. \n\n  Explore more\n\nNutrition An investment in agriculture is an investment in nutrition. Farming shapes sustainable food systems that nourish rural people and break cycles of poverty.\n\nNutrition An investment in agriculture is an investment in nutrition. Farming shapes sustainable food systems that nourish rural people and break cycles of poverty.\n\nNutrition\n\nAn investment in agriculture is an investment in nutrition. Farming shapes sustainable food systems that nourish rural people and break cycles of poverty.\n\nFragile contexts and crises By building resilience, rural people can better endure crises. \n\n  Explore more\n\nFragile contexts and crises By building resilience, rural people can better endure crises. \n\n  Explore more\n\nFragile contexts and crises By building resilience, rural people can better endure crises. \n\n  Explore more\n\nFragile contexts and crises By building resilience, rural people can better endure crises. \n\n  Explore more\n\nFragile contexts and crises By building resilience, rural people can better endure crises. \n\n  Explore more\n\nFragile contexts and crises By building resilience, rural people can better endure crises.\n\nFragile contexts and crises By building resilience, rural people can better endure crises.\n\nFragile contexts and crises\n\nBy building resilience, rural people can better endure crises.\n\nPlease configure the desktop menu widget below\n      \n\n\n\n\n\n\n\n\n About IFAD \n Who we are   Where we work   What we do   Action Areas   Knowledge & Data \n\n\n For Member States \n Member States interactive platform \n\n\n For Investors \n Investors   Finance \n\n\n For Job seekers \n Work with us   Frequently Asked Questions \n\n\n For Media \n News   Media Contacts   Image Bank \n\n\n Get Involved \n Join an event   Rural Voices   Opinions & Insights \n\n\n\n\n\n\n\n\n\n\n\n\n\n       Please configure the mobile menu widget below\n      \n\n\n\n\n\n\n\n\n Who we are \n\n\n\n What we do \n\n\n\n Where we work \n\n\n\n Action Areas \n\n\n\n Knowledge & Data \n\n\n\n Get Involved \n\n\n\n News and Stories \n\n\n\n\n\n\n\n\n\n\n\n\n\n  \n Legal  Privacy notice  Fraudulent job offers  Contact us Stay connected\n\nPlease configure the desktop menu widget below\n      \n\n\n\n\n\n\n\n\n About IFAD \n Who we are   Where we work   What we do   Action Areas   Knowledge & Data \n\n\n For Member States \n Member States interactive platform \n\n\n For Investors \n Investors   Finance \n\n\n For Job seekers \n Work with us   Frequently Asked Questions \n\n\n For Media \n News   Media Contacts   Image Bank \n\n\n Get Involved \n Join an event   Rural Voices   Opinions & Insights \n\n\n\n\n\n\n\n\n\n\n\n\n\n       Please configure the mobile menu widget below\n      \n\n\n\n\n\n\n\n\n Who we are \n\n\n\n What we do \n\n\n\n Where we work \n\n\n\n Action Areas \n\n\n\n Knowledge & Data \n\n\n\n Get Involved \n\n\n\n News and Stories \n\n\n\n\n\n\n\n\n\n\n\n\n\n  \n Legal  Privacy notice  Fraudulent job offers  Contact us Stay connected\n\nPlease configure the desktop menu widget below\n      \n\n\n\n\n\n\n\n\n About IFAD \n Who we are   Where we work   What we do   Action Areas   Knowledge & Data \n\n\n For Member States \n Member States interactive platform \n\n\n For Investors \n Investors   Finance \n\n\n For Job seekers \n Work with us   Frequently Asked Questions \n\n\n For Media \n News   Media Contacts   Image Bank \n\n\n Get Involved \n Join an event   Rural Voices   Opinions & Insights \n\n\n\n\n\n\n\n\n\n\n\n\n\n       Please configure the mobile menu widget below\n      \n\n\n\n\n\n\n\n\n Who we are \n\n\n\n What we do \n\n\n\n Where we work \n\n\n\n Action Areas \n\n\n\n Knowledge & Data \n\n\n\n Get Involved \n\n\n\n News and Stories \n\n\n\n\n\n\n\n\n\n\n\n\n\n  \n Legal  Privacy notice  Fraudulent job offers  Contact us Stay connected\n\nPlease configure the desktop menu widget below\n      \n\n\n\n\n\n\n\n\n About IFAD \n Who we are   Where we work   What we do   Action Areas   Knowledge & Data \n\n\n For Member States \n Member States interactive platform \n\n\n For Investors \n Investors   Finance \n\n\n For Job seekers \n Work with us   Frequently Asked Questions \n\n\n For Media \n News   Media Contacts   Image Bank \n\n\n Get Involved \n Join an event   Rural Voices   Opinions & Insights \n\n\n\n\n\n\n\n\n\n\n\n\n\n       Please configure the mobile menu widget below\n      \n\n\n\n\n\n\n\n\n Who we are \n\n\n\n What we do \n\n\n\n Where we work \n\n\n\n Action Areas \n\n\n\n Knowledge & Data \n\n\n\n Get Involved \n\n\n\n News and Stories\n\nPlease configure the desktop menu widget below\n      \n\n\n\n\n\n\n\n\n About IFAD \n Who we are   Where we work   What we do   Action Areas   Knowledge & Data \n\n\n For Member States \n Member States interactive platform \n\n\n For Investors \n Investors   Finance \n\n\n For Job seekers \n Work with us   Frequently Asked Questions \n\n\n For Media \n News   Media Contacts   Image Bank \n\n\n Get Involved \n Join an event   Rural Voices   Opinions & Insights\n\nPlease configure the desktop menu widget below\n\nAbout IFAD \n Who we are   Where we work   What we do   Action Areas   Knowledge & Data \n\n\n For Member States \n Member States interactive platform \n\n\n For Investors \n Investors   Finance \n\n\n For Job seekers \n Work with us   Frequently Asked Questions \n\n\n For Media \n News   Media Contacts   Image Bank \n\n\n Get Involved \n Join an event   Rural Voices   Opinions & Insights\n\nAbout IFAD \n Who we are   Where we work   What we do   Action Areas   Knowledge & Data \n\n\n For Member States \n Member States interactive platform \n\n\n For Investors \n Investors   Finance \n\n\n For Job seekers \n Work with us   Frequently Asked Questions \n\n\n For Media \n News   Media Contacts   Image Bank \n\n\n Get Involved \n Join an event   Rural Voices   Opinions & Insights\n\nAbout IFAD \n Who we are   Where we work   What we do   Action Areas   Knowledge & Data \n\n\n For Member States \n Member States interactive platform \n\n\n For Investors \n Investors   Finance \n\n\n For Job seekers \n Work with us   Frequently Asked Questions \n\n\n For Media \n News   Media Contacts   Image Bank \n\n\n Get Involved \n Join an event   Rural Voices   Opinions & Insights\n\nAbout IFAD \n Who we are   Where we work   What we do   Action Areas   Knowledge & Data \n\n\n For Member States \n Member States interactive platform \n\n\n For Investors \n Investors   Finance \n\n\n For Job seekers \n Work with us   Frequently Asked Questions \n\n\n For Media \n News   Media Contacts   Image Bank \n\n\n Get Involved \n Join an event   Rural Voices   Opinions & Insights\n\nAbout IFAD \n Who we are   Where we work   What we do   Action Areas   Knowledge & Data \n\n\n For Member States \n Member States interactive platform \n\n\n For Investors \n Investors   Finance \n\n\n For Job seekers \n Work with us   Frequently Asked Questions \n\n\n For Media \n News   Media Contacts   Image Bank \n\n\n Get Involved \n Join an event   Rural Voices   Opinions & Insights\n\nAbout IFAD \n Who we are   Where we work   What we do   Action Areas   Knowledge & Data \n\n\n For Member States \n Member States interactive platform \n\n\n For Investors \n Investors   Finance \n\n\n For Job seekers \n Work with us   Frequently Asked Questions \n\n\n For Media \n News   Media Contacts   Image Bank \n\n\n Get Involved \n Join an event   Rural Voices   Opinions & Insights\n\nAbout IFAD \n Who we are   Where we work   What we do   Action Areas   Knowledge & Data \n\n\n For Member States \n Member States interactive platform \n\n\n For Investors \n Investors   Finance \n\n\n For Job seekers \n Work with us   Frequently Asked Questions \n\n\n For Media \n News   Media Contacts   Image Bank \n\n\n Get Involved \n Join an event   Rural Voices   Opinions & Insights\n\nAbout IFAD \n Who we are   Where we work   What we do   Action Areas   Knowledge & Data \n\n\n For Member States \n Member States interactive platform \n\n\n For Investors \n Investors   Finance \n\n\n For Job seekers \n Work with us   Frequently Asked Questions \n\n\n For Media \n News   Media Contacts   Image Bank \n\n\n Get Involved \n Join an event   Rural Voices   Opinions & Insights\n\nAbout IFAD \n Who we are   Where we work   What we do   Action Areas   Knowledge & Data\n\nWho we are   Where we work   What we do   Action Areas   Knowledge & Data\n\nFor Member States \n Member States interactive platform\n\nMember States interactive platform\n\nFor Investors \n Investors   Finance\n\nInvestors   Finance\n\nFor Job seekers \n Work with us   Frequently Asked Questions\n\nWork with us   Frequently Asked Questions\n\nFor Media \n News   Media Contacts   Image Bank\n\nNews   Media Contacts   Image Bank\n\nGet Involved \n Join an event   Rural Voices   Opinions & Insights\n\nJoin an event   Rural Voices   Opinions & Insights\n\nPlease configure the mobile menu widget below\n      \n\n\n\n\n\n\n\n\n Who we are \n\n\n\n What we do \n\n\n\n Where we work \n\n\n\n Action Areas \n\n\n\n Knowledge & Data \n\n\n\n Get Involved \n\n\n\n News and Stories\n\nPlease configure the mobile menu widget below\n\nWho we are \n\n\n\n What we do \n\n\n\n Where we work \n\n\n\n Action Areas \n\n\n\n Knowledge & Data \n\n\n\n Get Involved \n\n\n\n News and Stories\n\nWho we are \n\n\n\n What we do \n\n\n\n Where we work \n\n\n\n Action Areas \n\n\n\n Knowledge & Data \n\n\n\n Get Involved \n\n\n\n News and Stories\n\nWho we are \n\n\n\n What we do \n\n\n\n Where we work \n\n\n\n Action Areas \n\n\n\n Knowledge & Data \n\n\n\n Get Involved \n\n\n\n News and Stories\n\nWho we are \n\n\n\n What we do \n\n\n\n Where we work \n\n\n\n Action Areas \n\n\n\n Knowledge & Data \n\n\n\n Get Involved \n\n\n\n News and Stories\n\nWho we are \n\n\n\n What we do \n\n\n\n Where we work \n\n\n\n Action Areas \n\n\n\n Knowledge & Data \n\n\n\n Get Involved \n\n\n\n News and Stories\n\nWho we are \n\n\n\n What we do \n\n\n\n Where we work \n\n\n\n Action Areas \n\n\n\n Knowledge & Data \n\n\n\n Get Involved \n\n\n\n News and Stories\n\nWho we are \n\n\n\n What we do \n\n\n\n Where we work \n\n\n\n Action Areas \n\n\n\n Knowledge & Data \n\n\n\n Get Involved \n\n\n\n News and Stories\n\nWho we are \n\n\n\n What we do \n\n\n\n Where we work \n\n\n\n Action Areas \n\n\n\n Knowledge & Data \n\n\n\n Get Involved \n\n\n\n News and Stories\n\nWho we are\n\nWhat we do\n\nWhere we work\n\nAction Areas\n\nKnowledge & Data\n\nGet Involved\n\nNews and Stories\n\nLegal  Privacy notice  Fraudulent job offers  Contact us Stay connected\n\nLegal  Privacy notice  Fraudulent job offers  Contact us Stay connected",
  "date": "",
  "source_type": "other",
  "extracted_at": "2025-04-07T14:28:01.822456",
  "metadata": {
    "description": "From building resilience to empowering rural people and protecting the environment, explore our main areas of work.",
    "keywords": "Action areas",
    "og:site_name": "IFAD",
    "og:type": "website"
  },
  "relevance_score": 0.525,
  "summary": "Without tackling its root causes, we cannot end global hunger and poverty \n\n  Explore more \n           \n \n\n\n\n\n\n\n\n\n\n\n\n\n\n\n\n\n\n Rural Youth As the farmers and producers of tomorrow, rural young people have the potential to feed the world's growing population. Explore more \n           \n \n\n\n\n\n\n\n\n\n\n\n\n\n\n\n\n\n Persons with disabilities Equal opportunities enable persons with disabilities to thrive while transforming rural communities \n\n  Explore more \n           \n \n\n\n\n\n\n\n\n\n\n\n\nProtecting the environment\n\n\n\n\n\n\n\n\n\n\n\n\n\n\n\n Climate and environment The lives of small-scale farmers are being upended by climate change. They need support to adapt to climate change and to protect the planet’s precious resources \n\n  Explore more \n           \n \n\n\n\n\n\n\n\n\n\n\n\n\n\n\n\n\n Biodiversity Rich and diverse ecosystems are essential to produce our food and protect us from climate change impacts \n\n  Explore more \n           \n \n\n\n\n\n\n\n\n\n\n\n\n\n\nEnhancing livelihoods and markets\n\n\n\n\n\n\n\n\n\n\n\n\n\n\n\n Private sector The private sector drives entrepreneurship, employment and growth in rural economies, and is essential to eradicating poverty and hunger. Explore more \n           \n \n\n\n\n\n\n\n\n\n\n\n\n\n\n\n\n\n Markets and value chains Reliable market access and strong value chains boost productivity, increase incomes and strengthen food security \n\n  Explore more \n           \n \n\n\n\n\n\n\n\n\n\n\n\n\n\n\n\n\n Land and resources Ensuring rural people have access land and natural resources for food, shelter, income and resilience \n\n  Explore more \n           \n \n\n\n\n\n\n\n\n\n\n\nPromoting sustainable farming\n\n\n\n\n\n\n\n\n\n\n\n\n\n\n\n\n Water Water is essential for food systems, yet this precious resource is under threat. Explore more \n           \n \n\n\n\n\n\n\n\n\n\n\n\nBuilding resilience\n\n\n\n\n\n\n\n\n\n\n\n\n\n\n\n Rural institutions and organizations Farmers’ organizations help rural people increase their incomes and output, share knowledge, access resources and influence policy dialogue. Explore more \n           \n \n\n\n\n\n\n\n\n\n\n\n\n\n\n\n\n\n Remittances The funds sent home by migrant workers are a lifeline for rural families, helping to build resilience and support sustainable development \n\n  Explore more \n           \n \n\n\n\n\n\n\n\n\n\n\n\n\n\n\n\n\n Nutrition An investment in agriculture is an investment in nutrition. Explore more \n           \n \n\n\n\n\n\n\n\n\n\n\n\n\n\n\n\n       Please configure the desktop menu widget below\n      \n\n\n\n\n\n\n\n\n About IFAD \n Who we are   Where we work   What we do   Action Areas   Knowledge & Data \n\n\n For Member States \n Member States interactive platform \n\n\n For Investors \n Investors   Finance \n\n\n For Job seekers \n Work with us   Frequently Asked Questions \n\n\n For Media \n News   Media Contacts   Image Bank \n\n\n Get Involved \n Join an event   Rural Voices   Opinions & Insights \n\n\n\n\n\n\n\n\n\n\n\n\n\n       Please configure the mobile menu widget below\n      \n\n\n\n\n\n\n\n\n Who we are \n\n\n\n What we do \n\n\n\n Where we work \n\n\n\n Action Areas \n\n\n\n Knowledge & Data \n\n\n\n Get Involved \n\n\n\n News and Stories \n\n\n\n\n\n\n\n\n\n\n\n\n\n  \n Legal  Privacy notice  Fraudulent job offers  Contact us Stay connected\n\n\n\n  \n\n  \n\n  \n\n  \n\n  \n\n \n\n\n\n\n\n\n\n\nHidden\n\nAction areas - IFAD\n\n\n\n\n\n\n\n\n\n\n\n\n\n\n\n\n\n\n\n\n\n\n\n\n\n\n\n\n\n\n\n\n\n\n\nAction areas\n\n\n\n\n\n\n\n\n\n©IFAD/GMB Akash \n\n\n\n\n\n\n\n\n\n\nIFAD’s investments support rural people so they can pull themselves out of poverty and build better lives. Without tackling its root causes, we cannot end global hunger and poverty \n\n  Explore more \n           \n \n\n\n\n\n\n\n\n\n\n\n\n\n\n\n\n\n\n Rural Youth As the farmers and producers of tomorrow, rural young people have the potential to feed the world's growing population. Explore more \n           \n \n\n\n\n\n\n\n\n\n\n\n\n\n\n\n\n\n Persons with disabilities Equal opportunities enable persons with disabilities to thrive while transforming rural communities \n\n  Explore more \n           \n \n\n\n\n\n\n\n\n\n\n\n\nProtecting the environment\n\n\n\n\n\n\n\n\n\n\n\n\n\n\n\n Climate and environment The lives of small-scale farmers are being upended by climate change. They need support to adapt to climate change and to protect the planet’s precious resources \n\n  Explore more \n           \n \n\n\n\n\n\n\n\n\n\n\n\n\n\n\n\n\n Biodiversity Rich and diverse ecosystems are essential to produce our food and protect us from climate change impacts \n\n  Explore more \n           \n \n\n\n\n\n\n\n\n\n\n\n\n\n\nEnhancing livelihoods and markets\n\n\n\n\n\n\n\n\n\n\n\n\n\n\n\n Private sector The private sector drives entrepreneurship, employment and growth in rural economies, and is essential to eradicating poverty and hunger. Explore more \n           \n \n\n\n\n\n\n\n\n\n\n\n\n\n\n\n\n\n Markets and value chains Reliable market access and strong value chains boost productivity, increase incomes and strengthen food security \n\n  Explore more \n           \n \n\n\n\n\n\n\n\n\n\n\n\n\n\n\n\n\n Land and resources Ensuring rural people have access land and natural resources for food, shelter, income and resilience \n\n  Explore more \n           \n \n\n\n\n\n\n\n\n\n\n\nPromoting sustainable farming\n\n\n\n\n\n\n\n\n\n\n\n\n\n\n\n\n Water Water is essential for food systems, yet this precious resource is under threat. Explore more \n           \n \n\n\n\n\n\n\n\n\n\n\n\nBuilding resilience\n\n\n\n\n\n\n\n\n\n\n\n\n\n\n\n Rural institutions and organizations Farmers’ organizations help rural people increase their incomes and output, share knowledge, access resources and influence policy dialogue. Explore more \n           \n \n\n\n\n\n\n\n\n\n\n\n\n\n\n\n\n\n Remittances The funds sent home by migrant workers are a lifeline for rural families, helping to build resilience and support sustainable development \n\n  Explore more \n           \n \n\n\n\n\n\n\n\n\n\n\n\n\n\n\n\n\n Nutrition An investment in agriculture is an investment in nutrition. Explore more \n           \n \n\n\n\n\n\n\n\n\n\n\n\n\n\n\n\n       Please configure the desktop menu widget below\n      \n\n\n\n\n\n\n\n\n About IFAD \n Who we are   Where we work   What we do   Action Areas   Knowledge & Data \n\n\n For Member States \n Member States interactive platform \n\n\n For Investors \n Investors   Finance \n\n\n For Job seekers \n Work with us   Frequently Asked Questions \n\n\n For Media \n News   Media Contacts   Image Bank \n\n\n Get Involved \n Join an event   Rural Voices   Opinions & Insights \n\n\n\n\n\n\n\n\n\n\n\n\n\n       Please configure the mobile menu widget below\n      \n\n\n\n\n\n\n\n\n Who we are \n\n\n\n What we do \n\n\n\n Where we work \n\n\n\n Action Areas \n\n\n\n Knowledge & Data \n\n\n\n Get Involved \n\n\n\n News and Stories \n\n\n\n\n\n\n\n\n\n\n\n\n\n  \n Legal  Privacy notice  Fraudulent job offers  Contact us Stay connected\n\n\n\n  \n\n  \n\n  \n\n  \n\n  \n\n \n\n\n\n\n\n\n\n\nHidden\n\nAction areas - IFAD\n\n\n\n\n\n\n\n\n\n\n\n\n\n\n\n\n\n\n\n\n\n\n\n\n\n\n\n\n\n\n\n\n\n\n\nAction areas\n\n\n\n\n\n\n\n\n\n©IFAD/GMB Akash \n\n\n\n\n\n\n\n\n\n\nIFAD’s investments support rural people so they can pull themselves out of poverty and build better lives. Without tackling its root causes, we cannot end global hunger and poverty \n\n  Explore more \n           \n \n\n\n\n\n\n\n\n\n\n\n\n\n\n\n\n\n\n Rural Youth As the farmers and producers of tomorrow, rural young people have the potential to feed the world's growing population. Explore more \n           \n \n\n\n\n\n\n\n\n\n\n\n\n\n\n\n\n\n Persons with disabilities Equal opportunities enable persons with disabilities to thrive while transforming rural communities \n\n  Explore more \n           \n \n\n\n\n\n\n\n\n\n\n\n\nProtecting the environment\n\n\n\n\n\n\n\n\n\n\n\n\n\n\n\n Climate and environment The lives of small-scale farmers are being upended by climate change. They need support to adapt to climate change and to protect the planet’s precious resources \n\n  Explore more \n           \n \n\n\n\n\n\n\n\n\n\n\n\n\n\n\n\n\n Biodiversity Rich and diverse ecosystems are essential to produce our food and protect us from climate change impacts \n\n  Explore more \n           \n \n\n\n\n\n\n\n\n\n\n\n\n\n\nEnhancing livelihoods and markets\n\n\n\n\n\n\n\n\n\n\n\n\n\n\n\n Private sector The private sector drives entrepreneurship, employment and growth in rural economies, and is essential to eradicating poverty and hunger. Explore more \n           \n \n\n\n\n\n\n\n\n\n\n\n\n\n\n\n\n\n Markets and value chains Reliable market access and strong value chains boost productivity, increase incomes and strengthen food security \n\n  Explore more \n           \n \n\n\n\n\n\n\n\n\n\n\n\n\n\n\n\n\n Land and resources Ensuring rural people have access land and natural resources for food, shelter, income and resilience \n\n  Explore more \n           \n \n\n\n\n\n\n\n\n\n\n\nPromoting sustainable farming\n\n\n\n\n\n\n\n\n\n\n\n\n\n\n\n\n Water Water is essential for food systems, yet this precious resource is under threat. Explore more \n           \n \n\n\n\n\n\n\n\n\n\n\n\nBuilding resilience\n\n\n\n\n\n\n\n\n\n\n\n\n\n\n\n Rural institutions and organizations Farmers’ organizations help rural people increase their incomes and output, share knowledge, access resources and influence policy dialogue. Explore more \n           \n \n\n\n\n\n\n\n\n\n\n\n\n\n\n\n\n\n Remittances The funds sent home by migrant workers are a lifeline for rural families, helping to build resilience and support sustainable development \n\n  Explore more \n           \n \n\n\n\n\n\n\n\n\n\n\n\n\n\n\n\n\n Nutrition An investment in agriculture is an investment in nutrition. Explore more \n           \n \n\n\n\n\n\n\n\n\n\n\n\n\n\n\n\n       Please configure the desktop menu widget below\n      \n\n\n\n\n\n\n\n\n About IFAD \n Who we are   Where we work   What we do   Action Areas   Knowledge & Data \n\n\n For Member States \n Member States interactive platform \n\n\n For Investors \n Investors   Finance \n\n\n For Job seekers \n Work with us   Frequently Asked Questions \n\n\n For Media \n News   Media Contacts   Image Bank \n\n\n Get Involved \n Join an event   Rural Voices   Opinions & Insights \n\n\n\n\n\n\n\n\n\n\n\n\n\n       Please configure the mobile menu widget below\n      \n\n\n\n\n\n\n\n\n Who we are \n\n\n\n What we do \n\n\n\n Where we work \n\n\n\n Action Areas \n\n\n\n Knowledge & Data \n\n\n\n Get Involved \n\n\n\n News and Stories \n\n\n\n\n\n\n\n\n\n\n\n\n\n  \n Legal  Privacy notice  Fraudulent job offers  Contact us Stay connected\n\n\n\n  \n\n  \n\n  \n\n  \n\n  \n\n \n\n\n\n\n\n\n\n\nHidden\n\nAction areas\n\n\n\n\n\n\n\n\n\n©IFAD/GMB Akash \n\n\n\n\n\n\n\n\n\n\nIFAD’s investments support rural people so they can pull themselves out of poverty and build better lives. Without tackling its root causes, we cannot end global hunger and poverty \n\n  Explore more \n           \n \n\n\n\n\n\n\n\n\n\n\n\n\n\n\n\n\n\n Rural Youth As the farmers and producers of tomorrow, rural young people have the potential to feed the world's growing population. Explore more \n           \n \n\n\n\n\n\n\n\n\n\n\n\n\n\n\n\n\n Persons with disabilities Equal opportunities enable persons with disabilities to thrive while transforming rural communities \n\n  Explore more \n           \n \n\n\n\n\n\n\n\n\n\n\n\nProtecting the environment\n\n\n\n\n\n\n\n\n\n\n\n\n\n\n\n Climate and environment The lives of small-scale farmers are being upended by climate change. They need support to adapt to climate change and to protect the planet’s precious resources \n\n  Explore more \n           \n \n\n\n\n\n\n\n\n\n\n\n\n\n\n\n\n\n Biodiversity Rich and diverse ecosystems are essential to produce our food and protect us from climate change impacts \n\n  Explore more \n           \n \n\n\n\n\n\n\n\n\n\n\n\n\n\nEnhancing livelihoods and markets\n\n\n\n\n\n\n\n\n\n\n\n\n\n\n\n Private sector The private sector drives entrepreneurship, employment and growth in rural economies, and is essential to eradicating poverty and hunger. Explore more \n           \n \n\n\n\n\n\n\n\n\n\n\n\n\n\n\n\n\n Markets and value chains Reliable market access and strong value chains boost productivity, increase incomes and strengthen food security \n\n  Explore more \n           \n \n\n\n\n\n\n\n\n\n\n\n\n\n\n\n\n\n Land and resources Ensuring rural people have access land and natural resources for food, shelter, income and resilience \n\n  Explore more \n           \n \n\n\n\n\n\n\n\n\n\n\nPromoting sustainable farming\n\n\n\n\n\n\n\n\n\n\n\n\n\n\n\n\n Water Water is essential for food systems, yet this precious resource is under threat. Explore more \n           \n \n\n\n\n\n\n\n\n\n\n\n\nBuilding resilience\n\n\n\n\n\n\n\n\n\n\n\n\n\n\n\n Rural institutions and organizations Farmers’ organizations help rural people increase their incomes and output, share knowledge, access resources and influence policy dialogue. Explore more \n           \n \n\n\n\n\n\n\n\n\n\n\n\n\n\n\n\n\n Remittances The funds sent home by migrant workers are a lifeline for rural families, helping to build resilience and support sustainable development \n\n  Explore more \n           \n \n\n\n\n\n\n\n\n\n\n\n\n\n\n\n\n\n Nutrition An investment in agriculture is an investment in nutrition. Explore more \n           \n \n\n\n\n\n\n\n\n\n\n\n\n\n\n\n\n       Please configure the desktop menu widget below\n      \n\n\n\n\n\n\n\n\n About IFAD \n Who we are   Where we work   What we do   Action Areas   Knowledge & Data \n\n\n For Member States \n Member States interactive platform \n\n\n For Investors \n Investors   Finance \n\n\n For Job seekers \n Work with us   Frequently Asked Questions \n\n\n For Media \n News   Media Contacts   Image Bank \n\n\n Get Involved \n Join an event   Rural Voices   Opinions & Insights \n\n\n\n\n\n\n\n\n\n\n\n\n\n       Please configure the mobile menu widget below\n      \n\n\n\n\n\n\n\n\n Who we are \n\n\n\n What we do \n\n\n\n Where we work \n\n\n\n Action Areas \n\n\n\n Knowledge & Data \n\n\n\n Get Involved \n\n\n\n News and Stories \n\n\n\n\n\n\n\n\n\n\n\n\n\n  \n Legal  Privacy notice  Fraudulent job offers  Contact us Stay connected\n\nAction areas\n\n\n\n\n\n\n\n\n\n©IFAD/GMB Akash \n\n\n\n\n\n\n\n\n\n\nIFAD’s investments support rural people so they can pull themselves out of poverty and build better lives. Without tackling its root causes, we cannot end global hunger and poverty \n\n  Explore more \n           \n \n\n\n\n\n\n\n\n\n\n\n\n\n\n\n\n\n\n Rural Youth As the farmers and producers of tomorrow, rural young people have the potential to feed the world's growing population. Explore more \n           \n \n\n\n\n\n\n\n\n\n\n\n\n\n\n\n\n\n Persons with disabilities Equal opportunities enable persons with disabilities to thrive while transforming rural communities \n\n  Explore more \n           \n \n\n\n\n\n\n\n\n\n\n\n\nProtecting the environment\n\n\n\n\n\n\n\n\n\n\n\n\n\n\n\n Climate and environment The lives of small-scale farmers are being upended by climate change. They need support to adapt to climate change and to protect the planet’s precious resources \n\n  Explore more \n           \n \n\n\n\n\n\n\n\n\n\n\n\n\n\n\n\n\n Biodiversity Rich and diverse ecosystems are essential to produce our food and protect us from climate change impacts \n\n  Explore more \n           \n \n\n\n\n\n\n\n\n\n\n\n\n\n\nEnhancing livelihoods and markets\n\n\n\n\n\n\n\n\n\n\n\n\n\n\n\n Private sector The private sector drives entrepreneurship, employment and growth in rural economies, and is essential to eradicating poverty and hunger. Explore more \n           \n \n\n\n\n\n\n\n\n\n\n\n\n\n\n\n\n\n Markets and value chains Reliable market access and strong value chains boost productivity, increase incomes and strengthen food security \n\n  Explore more \n           \n \n\n\n\n\n\n\n\n\n\n\n\n\n\n\n\n\n Land and resources Ensuring rural people have access land and natural resources for food, shelter, income and resilience \n\n  Explore more \n           \n \n\n\n\n\n\n\n\n\n\n\nPromoting sustainable farming\n\n\n\n\n\n\n\n\n\n\n\n\n\n\n\n\n Water Water is essential for food systems, yet this precious resource is under threat. Explore more \n           \n \n\n\n\n\n\n\n\n\n\n\n\nBuilding resilience\n\n\n\n\n\n\n\n\n\n\n\n\n\n\n\n Rural institutions and organizations Farmers’ organizations help rural people increase their incomes and output, share knowledge, access resources and influence policy dialogue. Explore more \n           \n \n\n\n\n\n\n\n\n\n\n\n\n\n\n\n\n\n Remittances The funds sent home by migrant workers are a lifeline for rural families, helping to build resilience and support sustainable development \n\n  Explore more \n           \n \n\n\n\n\n\n\n\n\n\n\n\n\n\n\n\n\n Nutrition An investment in agriculture is an investment in nutrition. Explore more \n           \n \n\n\n\n\n\n\n\n\n\n\n\n\n\n\n\n       Please configure the desktop menu widget below\n      \n\n\n\n\n\n\n\n\n About IFAD \n Who we are   Where we work   What we do   Action Areas   Knowledge & Data \n\n\n For Member States \n Member States interactive platform \n\n\n For Investors \n Investors   Finance \n\n\n For Job seekers \n Work with us   Frequently Asked Questions \n\n\n For Media \n News   Media Contacts   Image Bank \n\n\n Get Involved \n Join an event   Rural Voices   Opinions & Insights \n\n\n\n\n\n\n\n\n\n\n\n\n\n       Please configure the mobile menu widget below\n      \n\n\n\n\n\n\n\n\n Who we are \n\n\n\n What we do \n\n\n\n Where we work \n\n\n\n Action Areas \n\n\n\n Knowledge & Data \n\n\n\n Get Involved \n\n\n\n News and Stories \n\n\n\n\n\n\n\n\n\n\n\n\n\n  \n Legal  Privacy notice  Fraudulent job offers  Contact us Stay connected\n\nAction areas\n\n\n\n\n\n\n\n\n\n©IFAD/GMB Akash \n\n\n\n\n\n\n\n\n\n\nIFAD’s investments support rural people so they can pull themselves out of poverty and build better lives. Without tackling its root causes, we cannot end global hunger and poverty \n\n  Explore more \n           \n \n\n\n\n\n\n\n\n\n\n\n\n\n\n\n\n\n\n Rural Youth As the farmers and producers of tomorrow, rural young people have the potential to feed the world's growing population. Explore more \n           \n \n\n\n\n\n\n\n\n\n\n\n\n\n\n\n\n\n Persons with disabilities Equal opportunities enable persons with disabilities to thrive while transforming rural communities \n\n  Explore more \n           \n \n\n\n\n\n\n\n\n\n\n\n\nProtecting the environment\n\n\n\n\n\n\n\n\n\n\n\n\n\n\n\n Climate and environment The lives of small-scale farmers are being upended by climate change. They need support to adapt to climate change and to protect the planet’s precious resources \n\n  Explore more \n           \n \n\n\n\n\n\n\n\n\n\n\n\n\n\n\n\n\n Biodiversity Rich and diverse ecosystems are essential to produce our food and protect us from climate change impacts \n\n  Explore more \n           \n \n\n\n\n\n\n\n\n\n\n\n\n\n\nEnhancing livelihoods and markets\n\n\n\n\n\n\n\n\n\n\n\n\n\n\n\n Private sector The private sector drives entrepreneurship, employment and growth in rural economies, and is essential to eradicating poverty and hunger. Explore more \n           \n \n\n\n\n\n\n\n\n\n\n\n\n\n\n\n\n\n Markets and value chains Reliable market access and strong value chains boost productivity, increase incomes and strengthen food security \n\n  Explore more \n           \n \n\n\n\n\n\n\n\n\n\n\n\n\n\n\n\n\n Land and resources Ensuring rural people have access land and natural resources for food, shelter, income and resilience \n\n  Explore more \n           \n \n\n\n\n\n\n\n\n\n\n\nPromoting sustainable farming\n\n\n\n\n\n\n\n\n\n\n\n\n\n\n\n\n Water Water is essential for food systems, yet this precious resource is under threat. Explore more \n           \n \n\n\n\n\n\n\n\n\n\n\n\nBuilding resilience\n\n\n\n\n\n\n\n\n\n\n\n\n\n\n\n Rural institutions and organizations Farmers’ organizations help rural people increase their incomes and output, share knowledge, access resources and influence policy dialogue. Explore more \n           \n \n\n\n\n\n\n\n\n\n\n\n\n\n\n\n\n\n Remittances The funds sent home by migrant workers are a lifeline for rural families, helping to build resilience and support sustainable development \n\n  Explore more \n           \n \n\n\n\n\n\n\n\n\n\n\n\n\n\n\n\n\n Nutrition An investment in agriculture is an investment in nutrition. Explore more\n\nAction areas\n\nAction areas\n\nAction areas\n\nAction areas\n\n©IFAD/GMB Akash\n\n©IFAD/GMB Akash\n\n©IFAD/GMB Akash\n\nIFAD’s investments support rural people so they can pull themselves out of poverty and build better lives. Without tackling its root causes, we cannot end global hunger and poverty \n\n  Explore more \n           \n \n\n\n\n\n\n\n\n\n\n\n\n\n\n\n\n\n\n Rural Youth As the farmers and producers of tomorrow, rural young people have the potential to feed the world's growing population. Explore more \n           \n \n\n\n\n\n\n\n\n\n\n\n\n\n\n\n\n\n Persons with disabilities Equal opportunities enable persons with disabilities to thrive while transforming rural communities \n\n  Explore more\n\nEmpowering rural people\n\nEmpowering rural people\n\nRural women Gender inequality is one of the biggest impediments to sustainable development. Without tackling its root causes, we cannot end global hunger and poverty \n\n  Explore more \n           \n \n\n\n\n\n\n\n\n\n\n\n\n\n\n\n\n\n\n Rural Youth As the farmers and producers of tomorrow, rural young people have the potential to feed the world's growing population. Explore more \n           \n \n\n\n\n\n\n\n\n\n\n\n\n\n\n\n\n\n Persons with disabilities Equal opportunities enable persons with disabilities to thrive while transforming rural communities \n\n  Explore more\n\nRural women Gender inequality is one of the biggest impediments to sustainable development. Without tackling its root causes, we cannot end global hunger and poverty \n\n  Explore more \n           \n \n\n\n\n\n\n\n\n\n\n\n\n\n\n\n\n\n\n Rural Youth As the farmers and producers of tomorrow, rural young people have the potential to feed the world's growing population. Explore more \n           \n \n\n\n\n\n\n\n\n\n\n\n\n\n\n\n\n\n Persons with disabilities Equal opportunities enable persons with disabilities to thrive while transforming rural communities \n\n  Explore more\n\nRural women Gender inequality is one of the biggest impediments to sustainable development. Persons with disabilities Equal opportunities enable persons with disabilities to thrive while transforming rural communities \n\n  Explore more\n\nPersons with disabilities Equal opportunities enable persons with disabilities to thrive while transforming rural communities \n\n  Explore more\n\nPersons with disabilities Equal opportunities enable persons with disabilities to thrive while transforming rural communities \n\n  Explore more\n\nPersons with disabilities Equal opportunities enable persons with disabilities to thrive while transforming rural communities \n\n  Explore more\n\nPersons with disabilities Equal opportunities enable persons with disabilities to thrive while transforming rural communities \n\n  Explore more\n\nPersons with disabilities Equal opportunities enable persons with disabilities to thrive while transforming rural communities\n\nPersons with disabilities Equal opportunities enable persons with disabilities to thrive while transforming rural communities\n\nPersons with disabilities\n\nEqual opportunities enable persons with disabilities to thrive while transforming rural communities\n\nProtecting the environment\n\n\n\n\n\n\n\n\n\n\n\n\n\n\n\n Climate and environment The lives of small-scale farmers are being upended by climate change. They need support to adapt to climate change and to protect the planet’s precious resources \n\n  Explore more \n           \n \n\n\n\n\n\n\n\n\n\n\n\n\n\n\n\n\n Biodiversity Rich and diverse ecosystems are essential to produce our food and protect us from climate change impacts \n\n  Explore more\n\nProtecting the environment\n\nProtecting the environment\n\nClimate and environment The lives of small-scale farmers are being upended by climate change. They need support to adapt to climate change and to protect the planet’s precious resources \n\n  Explore more \n           \n \n\n\n\n\n\n\n\n\n\n\n\n\n\n\n\n\n Biodiversity Rich and diverse ecosystems are essential to produce our food and protect us from climate change impacts \n\n  Explore more\n\nClimate and environment The lives of small-scale farmers are being upended by climate change. They need support to adapt to climate change and to protect the planet’s precious resources \n\n  Explore more \n           \n \n\n\n\n\n\n\n\n\n\n\n\n\n\n\n\n\n Biodiversity Rich and diverse ecosystems are essential to produce our food and protect us from climate change impacts \n\n  Explore more\n\nClimate and environment The lives of small-scale farmers are being upended by climate change. They need support to adapt to climate change and to protect the planet’s precious resources\n\nBiodiversity Rich and diverse ecosystems are essential to produce our food and protect us from climate change impacts \n\n  Explore more\n\nBiodiversity Rich and diverse ecosystems are essential to produce our food and protect us from climate change impacts \n\n  Explore more\n\nBiodiversity Rich and diverse ecosystems are essential to produce our food and protect us from climate change impacts \n\n  Explore more\n\nBiodiversity Rich and diverse ecosystems are essential to produce our food and protect us from climate change impacts \n\n  Explore more\n\nBiodiversity Rich and diverse ecosystems are essential to produce our food and protect us from climate change impacts \n\n  Explore more\n\nBiodiversity Rich and diverse ecosystems are essential to produce our food and protect us from climate change impacts\n\nBiodiversity Rich and diverse ecosystems are essential to produce our food and protect us from climate change impacts\n\nBiodiversity\n\nRich and diverse ecosystems are essential to produce our food and protect us from climate change impacts\n\nEnhancing livelihoods and markets\n\n\n\n\n\n\n\n\n\n\n\n\n\n\n\n Private sector The private sector drives entrepreneurship, employment and growth in rural economies, and is essential to eradicating poverty and hunger. Explore more \n           \n \n\n\n\n\n\n\n\n\n\n\n\n\n\n\n\n\n Markets and value chains Reliable market access and strong value chains boost productivity, increase incomes and strengthen food security \n\n  Explore more \n           \n \n\n\n\n\n\n\n\n\n\n\n\n\n\n\n\n\n Land and resources Ensuring rural people have access land and natural resources for food, shelter, income and resilience \n\n  Explore more\n\nEnhancing livelihoods and markets\n\nEnhancing livelihoods and markets\n\nPrivate sector The private sector drives entrepreneurship, employment and growth in rural economies, and is essential to eradicating poverty and hunger. Explore more \n           \n \n\n\n\n\n\n\n\n\n\n\n\n\n\n\n\n\n Markets and value chains Reliable market access and strong value chains boost productivity, increase incomes and strengthen food security \n\n  Explore more \n           \n \n\n\n\n\n\n\n\n\n\n\n\n\n\n\n\n\n Land and resources Ensuring rural people have access land and natural resources for food, shelter, income and resilience \n\n  Explore more\n\nPrivate sector The private sector drives entrepreneurship, employment and growth in rural economies, and is essential to eradicating poverty and hunger. Explore more \n           \n \n\n\n\n\n\n\n\n\n\n\n\n\n\n\n\n\n Markets and value chains Reliable market access and strong value chains boost productivity, increase incomes and strengthen food security \n\n  Explore more \n           \n \n\n\n\n\n\n\n\n\n\n\n\n\n\n\n\n\n Land and resources Ensuring rural people have access land and natural resources for food, shelter, income and resilience \n\n  Explore more\n\nPrivate sector The private sector drives entrepreneurship, employment and growth in rural economies, and is essential to eradicating poverty and hunger. Markets and value chains Reliable market access and strong value chains boost productivity, increase incomes and strengthen food security \n\n  Explore more\n\nMarkets and value chains Reliable market access and strong value chains boost productivity, increase incomes and strengthen food security \n\n  Explore more\n\nMarkets and value chains Reliable market access and strong value chains boost productivity, increase incomes and strengthen food security \n\n  Explore more\n\nMarkets and value chains Reliable market access and strong value chains boost productivity, increase incomes and strengthen food security \n\n  Explore more\n\nMarkets and value chains Reliable market access and strong value chains boost productivity, increase incomes and strengthen food security \n\n  Explore more\n\nMarkets and value chains Reliable market access and strong value chains boost productivity, increase incomes and strengthen food security\n\nMarkets and value chains Reliable market access and strong value chains boost productivity, increase incomes and strengthen food security\n\nMarkets and value chains\n\nReliable market access and strong value chains boost productivity, increase incomes and strengthen food security\n\nLand and resources Ensuring rural people have access land and natural resources for food, shelter, income and resilience \n\n  Explore more\n\nLand and resources Ensuring rural people have access land and natural resources for food, shelter, income and resilience \n\n  Explore more\n\nLand and resources Ensuring rural people have access land and natural resources for food, shelter, income and resilience \n\n  Explore more\n\nLand and resources Ensuring rural people have access land and natural resources for food, shelter, income and resilience \n\n  Explore more\n\nLand and resources Ensuring rural people have access land and natural resources for food, shelter, income and resilience \n\n  Explore more\n\nLand and resources Ensuring rural people have access land and natural resources for food, shelter, income and resilience\n\nLand and resources Ensuring rural people have access land and natural resources for food, shelter, income and resilience\n\nLand and resources\n\nEnsuring rural people have access land and natural resources for food, shelter, income and resilience\n\nPromoting sustainable farming\n\nPromoting sustainable farming\n\nWater Water is essential for food systems, yet this precious resource is under threat. Explore more \n           \n \n\n\n\n\n\n\n\n\n\n\n\n\n\n\n\n\n Remittances The funds sent home by migrant workers are a lifeline for rural families, helping to build resilience and support sustainable development \n\n  Explore more \n           \n \n\n\n\n\n\n\n\n\n\n\n\n\n\n\n\n\n Nutrition An investment in agriculture is an investment in nutrition. Explore more\n\nBuilding resilience\n\nBuilding resilience\n\nRural institutions and organizations Farmers’ organizations help rural people increase their incomes and output, share knowledge, access resources and influence policy dialogue. Explore more \n           \n \n\n\n\n\n\n\n\n\n\n\n\n\n\n\n\n\n Remittances The funds sent home by migrant workers are a lifeline for rural families, helping to build resilience and support sustainable development \n\n  Explore more \n           \n \n\n\n\n\n\n\n\n\n\n\n\n\n\n\n\n\n Nutrition An investment in agriculture is an investment in nutrition. Explore more\n\nRural institutions and organizations Farmers’ organizations help rural people increase their incomes and output, share knowledge, access resources and influence policy dialogue. Explore more \n           \n \n\n\n\n\n\n\n\n\n\n\n\n\n\n\n\n\n Remittances The funds sent home by migrant workers are a lifeline for rural families, helping to build resilience and support sustainable development \n\n  Explore more \n           \n \n\n\n\n\n\n\n\n\n\n\n\n\n\n\n\n\n Nutrition An investment in agriculture is an investment in nutrition. Explore more\n\nRural institutions and organizations Farmers’ organizations help rural people increase their incomes and output, share knowledge, access resources and influence policy dialogue. Explore more\n\nRural institutions and organizations Farmers’ organizations help rural people increase their incomes and output, share knowledge, access resources and influence policy dialogue. Explore more\n\nRural institutions and organizations Farmers’ organizations help rural people increase their incomes and output, share knowledge, access resources and influence policy dialogue. Explore more\n\nRural institutions and organizations Farmers’ organizations help rural people increase their incomes and output, share knowledge, access resources and influence policy dialogue. Explore more\n\nRural institutions and organizations Farmers’ organizations help rural people increase their incomes and output, share knowledge, access resources and influence policy dialogue. Explore more\n\nRural institutions and organizations Farmers’ organizations help rural people increase their incomes and output, share knowledge, access resources and influence policy dialogue. Remittances The funds sent home by migrant workers are a lifeline for rural families, helping to build resilience and support sustainable development \n\n  Explore more\n\nRemittances The funds sent home by migrant workers are a lifeline for rural families, helping to build resilience and support sustainable development \n\n  Explore more\n\nRemittances The funds sent home by migrant workers are a lifeline for rural families, helping to build resilience and support sustainable development \n\n  Explore more\n\nRemittances The funds sent home by migrant workers are a lifeline for rural families, helping to build resilience and support sustainable development \n\n  Explore more\n\nRemittances The funds sent home by migrant workers are a lifeline for rural families, helping to build resilience and support sustainable development \n\n  Explore more\n\nRemittances The funds sent home by migrant workers are a lifeline for rural families, helping to build resilience and support sustainable development\n\nRemittances The funds sent home by migrant workers are a lifeline for rural families, helping to build resilience and support sustainable development\n\nRemittances\n\nThe funds sent home by migrant workers are a lifeline for rural families, helping to build resilience and support sustainable development\n\nNutrition An investment in agriculture is an investment in nutrition. Please configure the desktop menu widget below\n      \n\n\n\n\n\n\n\n\n About IFAD \n Who we are   Where we work   What we do   Action Areas   Knowledge & Data \n\n\n For Member States \n Member States interactive platform \n\n\n For Investors \n Investors   Finance \n\n\n For Job seekers \n Work with us   Frequently Asked Questions \n\n\n For Media \n News   Media Contacts   Image Bank \n\n\n Get Involved \n Join an event   Rural Voices   Opinions & Insights \n\n\n\n\n\n\n\n\n\n\n\n\n\n       Please configure the mobile menu widget below\n      \n\n\n\n\n\n\n\n\n Who we are \n\n\n\n What we do \n\n\n\n Where we work \n\n\n\n Action Areas \n\n\n\n Knowledge & Data \n\n\n\n Get Involved \n\n\n\n News and Stories \n\n\n\n\n\n\n\n\n\n\n\n\n\n  \n Legal  Privacy notice  Fraudulent job offers  Contact us Stay connected\n\nPlease configure the desktop menu widget below\n      \n\n\n\n\n\n\n\n\n About IFAD \n Who we are   Where we work   What we do   Action Areas   Knowledge & Data \n\n\n For Member States \n Member States interactive platform \n\n\n For Investors \n Investors   Finance \n\n\n For Job seekers \n Work with us   Frequently Asked Questions \n\n\n For Media \n News   Media Contacts   Image Bank \n\n\n Get Involved \n Join an event   Rural Voices   Opinions & Insights \n\n\n\n\n\n\n\n\n\n\n\n\n\n       Please configure the mobile menu widget below\n      \n\n\n\n\n\n\n\n\n Who we are \n\n\n\n What we do \n\n\n\n Where we work \n\n\n\n Action Areas \n\n\n\n Knowledge & Data \n\n\n\n Get Involved \n\n\n\n News and Stories \n\n\n\n\n\n\n\n\n\n\n\n\n\n  \n Legal  Privacy notice  Fraudulent job offers  Contact us Stay connected\n\nPlease configure the desktop menu widget below\n      \n\n\n\n\n\n\n\n\n About IFAD \n Who we are   Where we work   What we do   Action Areas   Knowledge & Data \n\n\n For Member States \n Member States interactive platform \n\n\n For Investors \n Investors   Finance \n\n\n For Job seekers \n Work with us   Frequently Asked Questions \n\n\n For Media \n News   Media Contacts   Image Bank \n\n\n Get Involved \n Join an event   Rural Voices   Opinions & Insights \n\n\n\n\n\n\n\n\n\n\n\n\n\n       Please configure the mobile menu widget below\n      \n\n\n\n\n\n\n\n\n Who we are \n\n\n\n What we do \n\n\n\n Where we work \n\n\n\n Action Areas \n\n\n\n Knowledge & Data \n\n\n\n Get Involved \n\n\n\n News and Stories \n\n\n\n\n\n\n\n\n\n\n\n\n\n  \n Legal  Privacy notice  Fraudulent job offers  Contact us Stay connected\n\nPlease configure the desktop menu widget below\n      \n\n\n\n\n\n\n\n\n About IFAD \n Who we are   Where we work   What we do   Action Areas   Knowledge & Data \n\n\n For Member States \n Member States interactive platform \n\n\n For Investors \n Investors   Finance \n\n\n For Job seekers \n Work with us   Frequently Asked Questions \n\n\n For Media \n News   Media Contacts   Image Bank \n\n\n Get Involved \n Join an event   Rural Voices   Opinions & Insights \n\n\n\n\n\n\n\n\n\n\n\n\n\n       Please configure the mobile menu widget below\n      \n\n\n\n\n\n\n\n\n Who we are \n\n\n\n What we do \n\n\n\n Where we work \n\n\n\n Action Areas \n\n\n\n Knowledge & Data \n\n\n\n Get Involved \n\n\n\n News and Stories\n\nPlease configure the desktop menu widget below\n      \n\n\n\n\n\n\n\n\n About IFAD \n Who we are   Where we work   What we do   Action Areas   Knowledge & Data \n\n\n For Member States \n Member States interactive platform \n\n\n For Investors \n Investors   Finance \n\n\n For Job seekers \n Work with us   Frequently Asked Questions \n\n\n For Media \n News   Media Contacts   Image Bank \n\n\n Get Involved \n Join an event   Rural Voices   Opinions & Insights\n\nPlease configure the desktop menu widget below\n\nAbout IFAD \n Who we are   Where we work   What we do   Action Areas   Knowledge & Data \n\n\n For Member States \n Member States interactive platform \n\n\n For Investors \n Investors   Finance \n\n\n For Job seekers \n Work with us   Frequently Asked Questions \n\n\n For Media \n News   Media Contacts   Image Bank \n\n\n Get Involved \n Join an event   Rural Voices   Opinions & Insights\n\nAbout IFAD \n Who we are   Where we work   What we do   Action Areas   Knowledge & Data \n\n\n For Member States \n Member States interactive platform \n\n\n For Investors \n Investors   Finance \n\n\n For Job seekers \n Work with us   Frequently Asked Questions \n\n\n For Media \n News   Media Contacts   Image Bank \n\n\n Get Involved \n Join an event   Rural Voices   Opinions & Insights\n\nAbout IFAD \n Who we are   Where we work   What we do   Action Areas   Knowledge & Data \n\n\n For Member States \n Member States interactive platform \n\n\n For Investors \n Investors   Finance \n\n\n For Job seekers \n Work with us   Frequently Asked Questions \n\n\n For Media \n News   Media Contacts   Image Bank \n\n\n Get Involved \n Join an event   Rural Voices   Opinions & Insights\n\nAbout IFAD \n Who we are   Where we work   What we do   Action Areas   Knowledge & Data \n\n\n For Member States \n Member States interactive platform \n\n\n For Investors \n Investors   Finance \n\n\n For Job seekers \n Work with us   Frequently Asked Questions \n\n\n For Media \n News   Media Contacts   Image Bank \n\n\n Get Involved \n Join an event   Rural Voices   Opinions & Insights\n\nAbout IFAD \n Who we are   Where we work   What we do   Action Areas   Knowledge & Data \n\n\n For Member States \n Member States interactive platform \n\n\n For Investors \n Investors   Finance \n\n\n For Job seekers \n Work with us   Frequently Asked Questions \n\n\n For Media \n News   Media Contacts   Image Bank \n\n\n Get Involved \n Join an event   Rural Voices   Opinions & Insights\n\nAbout IFAD \n Who we are   Where we work   What we do   Action Areas   Knowledge & Data \n\n\n For Member States \n Member States interactive platform \n\n\n For Investors \n Investors   Finance \n\n\n For Job seekers \n Work with us   Frequently Asked Questions \n\n\n For Media \n News   Media Contacts   Image Bank \n\n\n Get Involved \n Join an event   Rural Voices   Opinions & Insights\n\nAbout IFAD \n Who we are   Where we work   What we do   Action Areas   Knowledge & Data \n\n\n For Member States \n Member States interactive platform \n\n\n For Investors \n Investors   Finance \n\n\n For Job seekers \n Work with us   Frequently Asked Questions \n\n\n For Media \n News   Media Contacts   Image Bank \n\n\n Get Involved \n Join an event   Rural Voices   Opinions & Insights\n\nAbout IFAD \n Who we are   Where we work   What we do   Action Areas   Knowledge & Data \n\n\n For Member States \n Member States interactive platform \n\n\n For Investors \n Investors   Finance \n\n\n For Job seekers \n Work with us   Frequently Asked Questions \n\n\n For Media \n News   Media Contacts   Image Bank \n\n\n Get Involved \n Join an event   Rural Voices   Opinions & Insights\n\nAbout IFAD \n Who we are   Where we work   What we do   Action Areas   Knowledge & Data\n\nWho we are   Where we work   What we do   Action Areas   Knowledge & Data\n\nFor Member States \n Member States interactive platform\n\nMember States interactive platform\n\nFor Investors \n Investors   Finance\n\nInvestors   Finance\n\nFor Job seekers \n Work with us   Frequently Asked Questions\n\nWork with us   Frequently Asked Questions\n\nFor Media \n News   Media Contacts   Image Bank\n\nNews   Media Contacts   Image Bank\n\nGet Involved \n Join an event   Rural Voices   Opinions & Insights\n\nJoin an event   Rural Voices   Opinions & Insights\n\nPlease configure the mobile menu widget below\n      \n\n\n\n\n\n\n\n\n Who we are \n\n\n\n What we do \n\n\n\n Where we work \n\n\n\n Action Areas \n\n\n\n Knowledge & Data \n\n\n\n Get Involved \n\n\n\n News and Stories\n\nPlease configure the mobile menu widget below\n\nWho we are \n\n\n\n What we do \n\n\n\n Where we work \n\n\n\n Action Areas \n\n\n\n Knowledge & Data \n\n\n\n Get Involved \n\n\n\n News and Stories\n\nWho we are \n\n\n\n What we do \n\n\n\n Where we work \n\n\n\n Action Areas \n\n\n\n Knowledge & Data \n\n\n\n Get Involved \n\n\n\n News and Stories\n\nWho we are \n\n\n\n What we do \n\n\n\n Where we work \n\n\n\n Action Areas \n\n\n\n Knowledge & Data \n\n\n\n Get Involved \n\n\n\n News and Stories\n\nWho we are \n\n\n\n What we do \n\n\n\n Where we work \n\n\n\n Action Areas \n\n\n\n Knowledge & Data \n\n\n\n Get Involved \n\n\n\n News and Stories\n\nWho we are \n\n\n\n What we do \n\n\n\n Where we work \n\n\n\n Action Areas \n\n\n\n Knowledge & Data \n\n\n\n Get Involved \n\n\n\n News and Stories\n\nWho we are \n\n\n\n What we do \n\n\n\n Where we work \n\n\n\n Action Areas \n\n\n\n Knowledge & Data \n\n\n\n Get Involved \n\n\n\n News and Stories\n\nWho we are \n\n\n\n What we do \n\n\n\n Where we work \n\n\n\n Action Areas \n\n\n\n Knowledge & Data \n\n\n\n Get Involved \n\n\n\n News and Stories\n\nWho we are \n\n\n\n What we do \n\n\n\n Where we work \n\n\n\n Action Areas \n\n\n\n Knowledge & Data \n\n\n\n Get Involved \n\n\n\n News and Stories\n\nWho we are\n\nWhat we do\n\nWhere we work\n\nAction Areas\n\nKnowledge & Data\n\nGet Involved\n\nNews and Stories\n\nLegal  Privacy notice  Fraudulent job offers  Contact us Stay connected\n\nLegal  Privacy notice  Fraudulent job offers  Contact us Stay connected",
  "entities": {
    "countries": [],
    "organizations": [
      "un",
      "who"
    ],
    "key_issues": [
      "challenge",
      "state",
      "policy",
      "action",
      "context",
      "development",
      "market",
      "investment",
      "un",
      "organization"
    ]
  },
  "committee": "Economic and Social Council",
  "topic": "Promoting rural development in Africa"
}