{
  "url": "https://www.ifad.org/en/knowledge-and-data",
  "title": "Knowledge & Data",
  "text": "Knowledge &amp; Data - IFAD\n\n\n\n\n\n\n\n\n\n\n\n\n\n\n\n\n\n\n\n\n\n\n\n\n\n\n\n\nAll Publications\n\n\n\n\n\n\n\n\n Theme \nSelect\n\n\n\n\n\n\n\n Year \nSelect\n\n\n\n\n\n\n\n Country \nSelect\n\n\n\n\n\n\n\n\n\n\n\n  Show more  \n\n\n\n\n\n  \n\n\n\n\n\n\n\n\n\n\n\n\n\n\n\n\n\nPublication\n\n How to do note: The ecosystem approach to decent rural youth employment and entrepreneurship This practical guide provides actionable strategies to strengthen agribusiness ecosystems that support rural youth employment and entrepreneurship, enhance collaboration among governments, private sector actors and youth organizations, and scale innovative approaches that create decent wages and self-employment opportunities for rural youth. \n\n  Read now \n            \n \n\n\n\n\n\n\n\n\n\n\n\n\n\n\n\n\nPublication\n\n IFAD at a glance IFAD is the only multilateral development institution that focuses exclusively on investing in rural communities. \n\n  Read now \n            \n \n\n\n\n\n\n\n\n\n\n\n\n\n\n\n\nPublication\n\n Photobook: Fostering change in people’s lives in Liberia This photobook showcases the positive impact of IFAD-supported projects on Liberia’s rural communities, including the Tree Crops Extension Projects (TCEP-I and II) and the Smallholder Agriculture Transformation and Agribusiness Revitalization Project (STAR-P). \n\n  Read now \n            \n \n\n\n\n\n\n\n\n\n\n\n\n\n\n\n\n\n\nPublication\n\n Photobook: Growing stronger rural futures in Türkiye This photobook showcases the impact of two projects in Türkiye that were financed by IFAD alongside the Government of Türkiye: the Uplands Rural Development Programme (URDP) and the Göksu Taşeli Watershed Development Project (GTWDP). \n\n  Read now \n            \n \n\n\n\n\n\n\n\n\n\n\n\n\n\n\n\nPublication\n\n Sustainable and Resilient Agriculture in Malawi This brief provides an overview of the Investing in Livelihood Resilience and Soil Health in ACP Countries (ILSA) programme in Malawi, funded by the European Union and implemented by IFAD. \n\n  Read now \n            \n \n\n\n\n\n\n\n\n\n\n\n\n\n\n\n\nPublication\n\n IFAD Project Procurement Annual Report 2024 The 2024 Project Procurement Annual Report provides a comprehensive overview of IFAD's project procurement activities throughout the year. \n\n  Read now \n            \n \n\n\n\n\n\n\n\n\n\n\n\n\n\n\n\n\n\nPublication\n\n Highlights from the Crisis Response Initiative in Eritrea This document highlights the main results of activities funded by IFAD’s Crisis Response Initiative (CRI) in Eritrea. \n\n  Read now \n            \n \n\n\n\n\n\n\n\n\n\n\n\n\n\n\n\nPublication\n\n Investing in rural people in Guinea-Bissau This factsheet outlines IFAD’s work in Guinea-Bissau, including context, strategy and ongoing operations. \n\n  Read now \n            \n \n\n\n\n\n\n\n\n\n\n\n\n\n\n\n\nPublication\n\n Investing in rural people in Yemen This factsheet outlines IFAD’s work in Yemen, including context, strategy and ongoing operations. \n\n  Read now \n            \n \n\n\n\n\n\n\n\n\n\n\n       Showing 1 to 9 of 1380\n      \n\n\n\n\n\n\n\n1\n2\n3\n...\n154\n\n\n\n\n\n\n\n\n\n\n\n\n\n\n\n\n\n       Please configure the desktop menu widget below\n      \n\n\n\n\n\n\n\n\n About IFAD \n Who we are   Where we work   What we do   Action Areas   Knowledge & Data \n\n\n For Member States \n Member States interactive platform \n\n\n For Investors \n Investors   Finance \n\n\n For Job seekers \n Work with us   Frequently Asked Questions \n\n\n For Media \n News   Media Contacts   Image Bank \n\n\n Get Involved \n Join an event   Rural Voices   Opinions & Insights \n\n\n\n\n\n\n\n\n\n\n\n\n\n       Please configure the mobile menu widget below\n      \n\n\n\n\n\n\n\n\n Who we are \n\n\n\n What we do \n\n\n\n Where we work \n\n\n\n Action Areas \n\n\n\n Knowledge & Data \n\n\n\n Get Involved \n\n\n\n News and Stories \n\n\n\n\n\n\n\n\n\n\n\n\n\n  \n Legal  Privacy notice  Fraudulent job offers  Contact us Stay connected\n\n\n\n  \n\n  \n\n  \n\n  \n\n  \n\n \n\n\n\n\n\n\n\n\nHidden\n\nKnowledge &amp; Data - IFAD\n\n\n\n\n\n\n\n\n\n\n\n\n\n\n\n\n\n\n\n\n\n\n\n\n\n\n\n\nAll Publications\n\n\n\n\n\n\n\n\n Theme \nSelect\n\n\n\n\n\n\n\n Year \nSelect\n\n\n\n\n\n\n\n Country \nSelect\n\n\n\n\n\n\n\n\n\n\n\n  Show more  \n\n\n\n\n\n  \n\n\n\n\n\n\n\n\n\n\n\n\n\n\n\n\n\nPublication\n\n How to do note: The ecosystem approach to decent rural youth employment and entrepreneurship This practical guide provides actionable strategies to strengthen agribusiness ecosystems that support rural youth employment and entrepreneurship, enhance collaboration among governments, private sector actors and youth organizations, and scale innovative approaches that create decent wages and self-employment opportunities for rural youth. \n\n  Read now \n            \n \n\n\n\n\n\n\n\n\n\n\n\n\n\n\n\n\nPublication\n\n IFAD at a glance IFAD is the only multilateral development institution that focuses exclusively on investing in rural communities. \n\n  Read now \n            \n \n\n\n\n\n\n\n\n\n\n\n\n\n\n\n\nPublication\n\n Photobook: Fostering change in people’s lives in Liberia This photobook showcases the positive impact of IFAD-supported projects on Liberia’s rural communities, including the Tree Crops Extension Projects (TCEP-I and II) and the Smallholder Agriculture Transformation and Agribusiness Revitalization Project (STAR-P). \n\n  Read now \n            \n \n\n\n\n\n\n\n\n\n\n\n\n\n\n\n\n\n\nPublication\n\n Photobook: Growing stronger rural futures in Türkiye This photobook showcases the impact of two projects in Türkiye that were financed by IFAD alongside the Government of Türkiye: the Uplands Rural Development Programme (URDP) and the Göksu Taşeli Watershed Development Project (GTWDP). \n\n  Read now \n            \n \n\n\n\n\n\n\n\n\n\n\n\n\n\n\n\nPublication\n\n Sustainable and Resilient Agriculture in Malawi This brief provides an overview of the Investing in Livelihood Resilience and Soil Health in ACP Countries (ILSA) programme in Malawi, funded by the European Union and implemented by IFAD. \n\n  Read now \n            \n \n\n\n\n\n\n\n\n\n\n\n\n\n\n\n\nPublication\n\n IFAD Project Procurement Annual Report 2024 The 2024 Project Procurement Annual Report provides a comprehensive overview of IFAD's project procurement activities throughout the year. \n\n  Read now \n            \n \n\n\n\n\n\n\n\n\n\n\n\n\n\n\n\n\n\nPublication\n\n Highlights from the Crisis Response Initiative in Eritrea This document highlights the main results of activities funded by IFAD’s Crisis Response Initiative (CRI) in Eritrea. \n\n  Read now \n            \n \n\n\n\n\n\n\n\n\n\n\n\n\n\n\n\nPublication\n\n Investing in rural people in Guinea-Bissau This factsheet outlines IFAD’s work in Guinea-Bissau, including context, strategy and ongoing operations. \n\n  Read now \n            \n \n\n\n\n\n\n\n\n\n\n\n\n\n\n\n\nPublication\n\n Investing in rural people in Yemen This factsheet outlines IFAD’s work in Yemen, including context, strategy and ongoing operations. \n\n  Read now \n            \n \n\n\n\n\n\n\n\n\n\n\n       Showing 1 to 9 of 1380\n      \n\n\n\n\n\n\n\n1\n2\n3\n...\n154\n\n\n\n\n\n\n\n\n\n\n\n\n\n\n\n\n\n       Please configure the desktop menu widget below\n      \n\n\n\n\n\n\n\n\n About IFAD \n Who we are   Where we work   What we do   Action Areas   Knowledge & Data \n\n\n For Member States \n Member States interactive platform \n\n\n For Investors \n Investors   Finance \n\n\n For Job seekers \n Work with us   Frequently Asked Questions \n\n\n For Media \n News   Media Contacts   Image Bank \n\n\n Get Involved \n Join an event   Rural Voices   Opinions & Insights \n\n\n\n\n\n\n\n\n\n\n\n\n\n       Please configure the mobile menu widget below\n      \n\n\n\n\n\n\n\n\n Who we are \n\n\n\n What we do \n\n\n\n Where we work \n\n\n\n Action Areas \n\n\n\n Knowledge & Data \n\n\n\n Get Involved \n\n\n\n News and Stories \n\n\n\n\n\n\n\n\n\n\n\n\n\n  \n Legal  Privacy notice  Fraudulent job offers  Contact us Stay connected\n\n\n\n  \n\n  \n\n  \n\n  \n\n  \n\n \n\n\n\n\n\n\n\n\nHidden\n\nKnowledge &amp; Data - IFAD\n\n\n\n\n\n\n\n\n\n\n\n\n\n\n\n\n\n\n\n\n\n\n\n\n\n\n\n\nAll Publications\n\n\n\n\n\n\n\n\n Theme \nSelect\n\n\n\n\n\n\n\n Year \nSelect\n\n\n\n\n\n\n\n Country \nSelect\n\n\n\n\n\n\n\n\n\n\n\n  Show more  \n\n\n\n\n\n  \n\n\n\n\n\n\n\n\n\n\n\n\n\n\n\n\n\nPublication\n\n How to do note: The ecosystem approach to decent rural youth employment and entrepreneurship This practical guide provides actionable strategies to strengthen agribusiness ecosystems that support rural youth employment and entrepreneurship, enhance collaboration among governments, private sector actors and youth organizations, and scale innovative approaches that create decent wages and self-employment opportunities for rural youth. \n\n  Read now \n            \n \n\n\n\n\n\n\n\n\n\n\n\n\n\n\n\n\nPublication\n\n IFAD at a glance IFAD is the only multilateral development institution that focuses exclusively on investing in rural communities. \n\n  Read now \n            \n \n\n\n\n\n\n\n\n\n\n\n\n\n\n\n\nPublication\n\n Photobook: Fostering change in people’s lives in Liberia This photobook showcases the positive impact of IFAD-supported projects on Liberia’s rural communities, including the Tree Crops Extension Projects (TCEP-I and II) and the Smallholder Agriculture Transformation and Agribusiness Revitalization Project (STAR-P). \n\n  Read now \n            \n \n\n\n\n\n\n\n\n\n\n\n\n\n\n\n\n\n\nPublication\n\n Photobook: Growing stronger rural futures in Türkiye This photobook showcases the impact of two projects in Türkiye that were financed by IFAD alongside the Government of Türkiye: the Uplands Rural Development Programme (URDP) and the Göksu Taşeli Watershed Development Project (GTWDP). \n\n  Read now \n            \n \n\n\n\n\n\n\n\n\n\n\n\n\n\n\n\nPublication\n\n Sustainable and Resilient Agriculture in Malawi This brief provides an overview of the Investing in Livelihood Resilience and Soil Health in ACP Countries (ILSA) programme in Malawi, funded by the European Union and implemented by IFAD. \n\n  Read now \n            \n \n\n\n\n\n\n\n\n\n\n\n\n\n\n\n\nPublication\n\n IFAD Project Procurement Annual Report 2024 The 2024 Project Procurement Annual Report provides a comprehensive overview of IFAD's project procurement activities throughout the year. \n\n  Read now \n            \n \n\n\n\n\n\n\n\n\n\n\n\n\n\n\n\n\n\nPublication\n\n Highlights from the Crisis Response Initiative in Eritrea This document highlights the main results of activities funded by IFAD’s Crisis Response Initiative (CRI) in Eritrea. \n\n  Read now \n            \n \n\n\n\n\n\n\n\n\n\n\n\n\n\n\n\nPublication\n\n Investing in rural people in Guinea-Bissau This factsheet outlines IFAD’s work in Guinea-Bissau, including context, strategy and ongoing operations. \n\n  Read now \n            \n \n\n\n\n\n\n\n\n\n\n\n\n\n\n\n\nPublication\n\n Investing in rural people in Yemen This factsheet outlines IFAD’s work in Yemen, including context, strategy and ongoing operations. \n\n  Read now \n            \n \n\n\n\n\n\n\n\n\n\n\n       Showing 1 to 9 of 1380\n      \n\n\n\n\n\n\n\n1\n2\n3\n...\n154\n\n\n\n\n\n\n\n\n\n\n\n\n\n\n\n\n\n       Please configure the desktop menu widget below\n      \n\n\n\n\n\n\n\n\n About IFAD \n Who we are   Where we work   What we do   Action Areas   Knowledge & Data \n\n\n For Member States \n Member States interactive platform \n\n\n For Investors \n Investors   Finance \n\n\n For Job seekers \n Work with us   Frequently Asked Questions \n\n\n For Media \n News   Media Contacts   Image Bank \n\n\n Get Involved \n Join an event   Rural Voices   Opinions & Insights \n\n\n\n\n\n\n\n\n\n\n\n\n\n       Please configure the mobile menu widget below\n      \n\n\n\n\n\n\n\n\n Who we are \n\n\n\n What we do \n\n\n\n Where we work \n\n\n\n Action Areas \n\n\n\n Knowledge & Data \n\n\n\n Get Involved \n\n\n\n News and Stories \n\n\n\n\n\n\n\n\n\n\n\n\n\n  \n Legal  Privacy notice  Fraudulent job offers  Contact us Stay connected\n\n\n\n  \n\n  \n\n  \n\n  \n\n  \n\n \n\n\n\n\n\n\n\n\nHidden\n\nAll Publications\n\n\n\n\n\n\n\n\n Theme \nSelect\n\n\n\n\n\n\n\n Year \nSelect\n\n\n\n\n\n\n\n Country \nSelect\n\n\n\n\n\n\n\n\n\n\n\n  Show more  \n\n\n\n\n\n  \n\n\n\n\n\n\n\n\n\n\n\n\n\n\n\n\n\nPublication\n\n How to do note: The ecosystem approach to decent rural youth employment and entrepreneurship This practical guide provides actionable strategies to strengthen agribusiness ecosystems that support rural youth employment and entrepreneurship, enhance collaboration among governments, private sector actors and youth organizations, and scale innovative approaches that create decent wages and self-employment opportunities for rural youth. \n\n  Read now \n            \n \n\n\n\n\n\n\n\n\n\n\n\n\n\n\n\n\nPublication\n\n IFAD at a glance IFAD is the only multilateral development institution that focuses exclusively on investing in rural communities. \n\n  Read now \n            \n \n\n\n\n\n\n\n\n\n\n\n\n\n\n\n\nPublication\n\n Photobook: Fostering change in people’s lives in Liberia This photobook showcases the positive impact of IFAD-supported projects on Liberia’s rural communities, including the Tree Crops Extension Projects (TCEP-I and II) and the Smallholder Agriculture Transformation and Agribusiness Revitalization Project (STAR-P). \n\n  Read now \n            \n \n\n\n\n\n\n\n\n\n\n\n\n\n\n\n\n\n\nPublication\n\n Photobook: Growing stronger rural futures in Türkiye This photobook showcases the impact of two projects in Türkiye that were financed by IFAD alongside the Government of Türkiye: the Uplands Rural Development Programme (URDP) and the Göksu Taşeli Watershed Development Project (GTWDP). \n\n  Read now \n            \n \n\n\n\n\n\n\n\n\n\n\n\n\n\n\n\nPublication\n\n Sustainable and Resilient Agriculture in Malawi This brief provides an overview of the Investing in Livelihood Resilience and Soil Health in ACP Countries (ILSA) programme in Malawi, funded by the European Union and implemented by IFAD. \n\n  Read now \n            \n \n\n\n\n\n\n\n\n\n\n\n\n\n\n\n\nPublication\n\n IFAD Project Procurement Annual Report 2024 The 2024 Project Procurement Annual Report provides a comprehensive overview of IFAD's project procurement activities throughout the year. \n\n  Read now \n            \n \n\n\n\n\n\n\n\n\n\n\n\n\n\n\n\n\n\nPublication\n\n Highlights from the Crisis Response Initiative in Eritrea This document highlights the main results of activities funded by IFAD’s Crisis Response Initiative (CRI) in Eritrea. \n\n  Read now \n            \n \n\n\n\n\n\n\n\n\n\n\n\n\n\n\n\nPublication\n\n Investing in rural people in Guinea-Bissau This factsheet outlines IFAD’s work in Guinea-Bissau, including context, strategy and ongoing operations. \n\n  Read now \n            \n \n\n\n\n\n\n\n\n\n\n\n\n\n\n\n\nPublication\n\n Investing in rural people in Yemen This factsheet outlines IFAD’s work in Yemen, including context, strategy and ongoing operations. \n\n  Read now \n            \n \n\n\n\n\n\n\n\n\n\n\n       Showing 1 to 9 of 1380\n      \n\n\n\n\n\n\n\n1\n2\n3\n...\n154\n\n\n\n\n\n\n\n\n\n\n\n\n\n\n\n\n\n       Please configure the desktop menu widget below\n      \n\n\n\n\n\n\n\n\n About IFAD \n Who we are   Where we work   What we do   Action Areas   Knowledge & Data \n\n\n For Member States \n Member States interactive platform \n\n\n For Investors \n Investors   Finance \n\n\n For Job seekers \n Work with us   Frequently Asked Questions \n\n\n For Media \n News   Media Contacts   Image Bank \n\n\n Get Involved \n Join an event   Rural Voices   Opinions & Insights \n\n\n\n\n\n\n\n\n\n\n\n\n\n       Please configure the mobile menu widget below\n      \n\n\n\n\n\n\n\n\n Who we are \n\n\n\n What we do \n\n\n\n Where we work \n\n\n\n Action Areas \n\n\n\n Knowledge & Data \n\n\n\n Get Involved \n\n\n\n News and Stories \n\n\n\n\n\n\n\n\n\n\n\n\n\n  \n Legal  Privacy notice  Fraudulent job offers  Contact us Stay connected\n\nAll Publications\n\n\n\n\n\n\n\n\n Theme \nSelect\n\n\n\n\n\n\n\n Year \nSelect\n\n\n\n\n\n\n\n Country \nSelect\n\n\n\n\n\n\n\n\n\n\n\n  Show more  \n\n\n\n\n\n  \n\n\n\n\n\n\n\n\n\n\n\n\n\n\n\n\n\nPublication\n\n How to do note: The ecosystem approach to decent rural youth employment and entrepreneurship This practical guide provides actionable strategies to strengthen agribusiness ecosystems that support rural youth employment and entrepreneurship, enhance collaboration among governments, private sector actors and youth organizations, and scale innovative approaches that create decent wages and self-employment opportunities for rural youth. \n\n  Read now \n            \n \n\n\n\n\n\n\n\n\n\n\n\n\n\n\n\n\nPublication\n\n IFAD at a glance IFAD is the only multilateral development institution that focuses exclusively on investing in rural communities. \n\n  Read now \n            \n \n\n\n\n\n\n\n\n\n\n\n\n\n\n\n\nPublication\n\n Photobook: Fostering change in people’s lives in Liberia This photobook showcases the positive impact of IFAD-supported projects on Liberia’s rural communities, including the Tree Crops Extension Projects (TCEP-I and II) and the Smallholder Agriculture Transformation and Agribusiness Revitalization Project (STAR-P). \n\n  Read now \n            \n \n\n\n\n\n\n\n\n\n\n\n\n\n\n\n\n\n\nPublication\n\n Photobook: Growing stronger rural futures in Türkiye This photobook showcases the impact of two projects in Türkiye that were financed by IFAD alongside the Government of Türkiye: the Uplands Rural Development Programme (URDP) and the Göksu Taşeli Watershed Development Project (GTWDP). \n\n  Read now \n            \n \n\n\n\n\n\n\n\n\n\n\n\n\n\n\n\nPublication\n\n Sustainable and Resilient Agriculture in Malawi This brief provides an overview of the Investing in Livelihood Resilience and Soil Health in ACP Countries (ILSA) programme in Malawi, funded by the European Union and implemented by IFAD. \n\n  Read now \n            \n \n\n\n\n\n\n\n\n\n\n\n\n\n\n\n\nPublication\n\n IFAD Project Procurement Annual Report 2024 The 2024 Project Procurement Annual Report provides a comprehensive overview of IFAD's project procurement activities throughout the year. \n\n  Read now \n            \n \n\n\n\n\n\n\n\n\n\n\n\n\n\n\n\n\n\nPublication\n\n Highlights from the Crisis Response Initiative in Eritrea This document highlights the main results of activities funded by IFAD’s Crisis Response Initiative (CRI) in Eritrea. \n\n  Read now \n            \n \n\n\n\n\n\n\n\n\n\n\n\n\n\n\n\nPublication\n\n Investing in rural people in Guinea-Bissau This factsheet outlines IFAD’s work in Guinea-Bissau, including context, strategy and ongoing operations. \n\n  Read now \n            \n \n\n\n\n\n\n\n\n\n\n\n\n\n\n\n\nPublication\n\n Investing in rural people in Yemen This factsheet outlines IFAD’s work in Yemen, including context, strategy and ongoing operations. \n\n  Read now \n            \n \n\n\n\n\n\n\n\n\n\n\n       Showing 1 to 9 of 1380\n      \n\n\n\n\n\n\n\n1\n2\n3\n...\n154\n\n\n\n\n\n\n\n\n\n\n\n\n\n\n\n\n\n       Please configure the desktop menu widget below\n      \n\n\n\n\n\n\n\n\n About IFAD \n Who we are   Where we work   What we do   Action Areas   Knowledge & Data \n\n\n For Member States \n Member States interactive platform \n\n\n For Investors \n Investors   Finance \n\n\n For Job seekers \n Work with us   Frequently Asked Questions \n\n\n For Media \n News   Media Contacts   Image Bank \n\n\n Get Involved \n Join an event   Rural Voices   Opinions & Insights \n\n\n\n\n\n\n\n\n\n\n\n\n\n       Please configure the mobile menu widget below\n      \n\n\n\n\n\n\n\n\n Who we are \n\n\n\n What we do \n\n\n\n Where we work \n\n\n\n Action Areas \n\n\n\n Knowledge & Data \n\n\n\n Get Involved \n\n\n\n News and Stories \n\n\n\n\n\n\n\n\n\n\n\n\n\n  \n Legal  Privacy notice  Fraudulent job offers  Contact us Stay connected\n\nAll Publications\n\n\n\n\n\n\n\n\n Theme \nSelect\n\n\n\n\n\n\n\n Year \nSelect\n\n\n\n\n\n\n\n Country \nSelect\n\n\n\n\n\n\n\n\n\n\n\n  Show more  \n\n\n\n\n\n  \n\n\n\n\n\n\n\n\n\n\n\n\n\n\n\n\n\nPublication\n\n How to do note: The ecosystem approach to decent rural youth employment and entrepreneurship This practical guide provides actionable strategies to strengthen agribusiness ecosystems that support rural youth employment and entrepreneurship, enhance collaboration among governments, private sector actors and youth organizations, and scale innovative approaches that create decent wages and self-employment opportunities for rural youth. \n\n  Read now \n            \n \n\n\n\n\n\n\n\n\n\n\n\n\n\n\n\n\nPublication\n\n IFAD at a glance IFAD is the only multilateral development institution that focuses exclusively on investing in rural communities. \n\n  Read now \n            \n \n\n\n\n\n\n\n\n\n\n\n\n\n\n\n\nPublication\n\n Photobook: Fostering change in people’s lives in Liberia This photobook showcases the positive impact of IFAD-supported projects on Liberia’s rural communities, including the Tree Crops Extension Projects (TCEP-I and II) and the Smallholder Agriculture Transformation and Agribusiness Revitalization Project (STAR-P). \n\n  Read now \n            \n \n\n\n\n\n\n\n\n\n\n\n\n\n\n\n\n\n\nPublication\n\n Photobook: Growing stronger rural futures in Türkiye This photobook showcases the impact of two projects in Türkiye that were financed by IFAD alongside the Government of Türkiye: the Uplands Rural Development Programme (URDP) and the Göksu Taşeli Watershed Development Project (GTWDP). \n\n  Read now \n            \n \n\n\n\n\n\n\n\n\n\n\n\n\n\n\n\nPublication\n\n Sustainable and Resilient Agriculture in Malawi This brief provides an overview of the Investing in Livelihood Resilience and Soil Health in ACP Countries (ILSA) programme in Malawi, funded by the European Union and implemented by IFAD. \n\n  Read now \n            \n \n\n\n\n\n\n\n\n\n\n\n\n\n\n\n\nPublication\n\n IFAD Project Procurement Annual Report 2024 The 2024 Project Procurement Annual Report provides a comprehensive overview of IFAD's project procurement activities throughout the year. \n\n  Read now \n            \n \n\n\n\n\n\n\n\n\n\n\n\n\n\n\n\n\n\nPublication\n\n Highlights from the Crisis Response Initiative in Eritrea This document highlights the main results of activities funded by IFAD’s Crisis Response Initiative (CRI) in Eritrea. \n\n  Read now \n            \n \n\n\n\n\n\n\n\n\n\n\n\n\n\n\n\nPublication\n\n Investing in rural people in Guinea-Bissau This factsheet outlines IFAD’s work in Guinea-Bissau, including context, strategy and ongoing operations. \n\n  Read now \n            \n \n\n\n\n\n\n\n\n\n\n\n\n\n\n\n\nPublication\n\n Investing in rural people in Yemen This factsheet outlines IFAD’s work in Yemen, including context, strategy and ongoing operations. \n\n  Read now \n            \n \n\n\n\n\n\n\n\n\n\n\n       Showing 1 to 9 of 1380\n      \n\n\n\n\n\n\n\n1\n2\n3\n...\n154\n\nAll Publications\n\n\n\n\n\n\n\n\n Theme \nSelect\n\n\n\n\n\n\n\n Year \nSelect\n\n\n\n\n\n\n\n Country \nSelect\n\n\n\n\n\n\n\n\n\n\n\n  Show more  \n\n\n\n\n\n  \n\n\n\n\n\n\n\n\n\n\n\n\n\n\n\n\n\nPublication\n\n How to do note: The ecosystem approach to decent rural youth employment and entrepreneurship This practical guide provides actionable strategies to strengthen agribusiness ecosystems that support rural youth employment and entrepreneurship, enhance collaboration among governments, private sector actors and youth organizations, and scale innovative approaches that create decent wages and self-employment opportunities for rural youth. \n\n  Read now \n            \n \n\n\n\n\n\n\n\n\n\n\n\n\n\n\n\n\nPublication\n\n IFAD at a glance IFAD is the only multilateral development institution that focuses exclusively on investing in rural communities. \n\n  Read now \n            \n \n\n\n\n\n\n\n\n\n\n\n\n\n\n\n\nPublication\n\n Photobook: Fostering change in people’s lives in Liberia This photobook showcases the positive impact of IFAD-supported projects on Liberia’s rural communities, including the Tree Crops Extension Projects (TCEP-I and II) and the Smallholder Agriculture Transformation and Agribusiness Revitalization Project (STAR-P). \n\n  Read now \n            \n \n\n\n\n\n\n\n\n\n\n\n\n\n\n\n\n\n\nPublication\n\n Photobook: Growing stronger rural futures in Türkiye This photobook showcases the impact of two projects in Türkiye that were financed by IFAD alongside the Government of Türkiye: the Uplands Rural Development Programme (URDP) and the Göksu Taşeli Watershed Development Project (GTWDP). \n\n  Read now \n            \n \n\n\n\n\n\n\n\n\n\n\n\n\n\n\n\nPublication\n\n Sustainable and Resilient Agriculture in Malawi This brief provides an overview of the Investing in Livelihood Resilience and Soil Health in ACP Countries (ILSA) programme in Malawi, funded by the European Union and implemented by IFAD. \n\n  Read now \n            \n \n\n\n\n\n\n\n\n\n\n\n\n\n\n\n\nPublication\n\n IFAD Project Procurement Annual Report 2024 The 2024 Project Procurement Annual Report provides a comprehensive overview of IFAD's project procurement activities throughout the year. \n\n  Read now \n            \n \n\n\n\n\n\n\n\n\n\n\n\n\n\n\n\n\n\nPublication\n\n Highlights from the Crisis Response Initiative in Eritrea This document highlights the main results of activities funded by IFAD’s Crisis Response Initiative (CRI) in Eritrea. \n\n  Read now \n            \n \n\n\n\n\n\n\n\n\n\n\n\n\n\n\n\nPublication\n\n Investing in rural people in Guinea-Bissau This factsheet outlines IFAD’s work in Guinea-Bissau, including context, strategy and ongoing operations. \n\n  Read now \n            \n \n\n\n\n\n\n\n\n\n\n\n\n\n\n\n\nPublication\n\n Investing in rural people in Yemen This factsheet outlines IFAD’s work in Yemen, including context, strategy and ongoing operations. \n\n  Read now \n            \n \n\n\n\n\n\n\n\n\n\n\n       Showing 1 to 9 of 1380\n      \n\n\n\n\n\n\n\n1\n2\n3\n...\n154\n\nAll Publications\n\nAll Publications\n\nTheme \nSelect\n\n\n\n\n\n\n\n Year \nSelect\n\n\n\n\n\n\n\n Country \nSelect\n\n\n\n\n\n\n\n\n\n\n\n  Show more\n\nTheme \nSelect\n\n\n\n\n\n\n\n Year \nSelect\n\n\n\n\n\n\n\n Country \nSelect\n\nTheme \nSelect\n\n\n\n\n\n\n\n Year \nSelect\n\n\n\n\n\n\n\n Country \nSelect\n\nTheme \nSelect\n\nTheme \nSelect\n\nTheme \nSelect\n\nSelect\n\nYear \nSelect\n\nYear \nSelect\n\nYear \nSelect\n\nSelect\n\nCountry \nSelect\n\nCountry \nSelect\n\nCountry \nSelect\n\nSelect\n\nShow more\n\nShow more\n\nShow more\n\nPublication\n\n How to do note: The ecosystem approach to decent rural youth employment and entrepreneurship This practical guide provides actionable strategies to strengthen agribusiness ecosystems that support rural youth employment and entrepreneurship, enhance collaboration among governments, private sector actors and youth organizations, and scale innovative approaches that create decent wages and self-employment opportunities for rural youth. \n\n  Read now \n            \n \n\n\n\n\n\n\n\n\n\n\n\n\n\n\n\n\nPublication\n\n IFAD at a glance IFAD is the only multilateral development institution that focuses exclusively on investing in rural communities. \n\n  Read now \n            \n \n\n\n\n\n\n\n\n\n\n\n\n\n\n\n\nPublication\n\n Photobook: Fostering change in people’s lives in Liberia This photobook showcases the positive impact of IFAD-supported projects on Liberia’s rural communities, including the Tree Crops Extension Projects (TCEP-I and II) and the Smallholder Agriculture Transformation and Agribusiness Revitalization Project (STAR-P). \n\n  Read now \n            \n \n\n\n\n\n\n\n\n\n\n\n\n\n\n\n\n\n\nPublication\n\n Photobook: Growing stronger rural futures in Türkiye This photobook showcases the impact of two projects in Türkiye that were financed by IFAD alongside the Government of Türkiye: the Uplands Rural Development Programme (URDP) and the Göksu Taşeli Watershed Development Project (GTWDP). \n\n  Read now \n            \n \n\n\n\n\n\n\n\n\n\n\n\n\n\n\n\nPublication\n\n Sustainable and Resilient Agriculture in Malawi This brief provides an overview of the Investing in Livelihood Resilience and Soil Health in ACP Countries (ILSA) programme in Malawi, funded by the European Union and implemented by IFAD. \n\n  Read now \n            \n \n\n\n\n\n\n\n\n\n\n\n\n\n\n\n\nPublication\n\n IFAD Project Procurement Annual Report 2024 The 2024 Project Procurement Annual Report provides a comprehensive overview of IFAD's project procurement activities throughout the year. \n\n  Read now \n            \n \n\n\n\n\n\n\n\n\n\n\n\n\n\n\n\n\n\nPublication\n\n Highlights from the Crisis Response Initiative in Eritrea This document highlights the main results of activities funded by IFAD’s Crisis Response Initiative (CRI) in Eritrea. \n\n  Read now \n            \n \n\n\n\n\n\n\n\n\n\n\n\n\n\n\n\nPublication\n\n Investing in rural people in Guinea-Bissau This factsheet outlines IFAD’s work in Guinea-Bissau, including context, strategy and ongoing operations. \n\n  Read now \n            \n \n\n\n\n\n\n\n\n\n\n\n\n\n\n\n\nPublication\n\n Investing in rural people in Yemen This factsheet outlines IFAD’s work in Yemen, including context, strategy and ongoing operations. \n\n  Read now \n            \n \n\n\n\n\n\n\n\n\n\n\n       Showing 1 to 9 of 1380\n      \n\n\n\n\n\n\n\n1\n2\n3\n...\n154\n\nPublication\n\n How to do note: The ecosystem approach to decent rural youth employment and entrepreneurship This practical guide provides actionable strategies to strengthen agribusiness ecosystems that support rural youth employment and entrepreneurship, enhance collaboration among governments, private sector actors and youth organizations, and scale innovative approaches that create decent wages and self-employment opportunities for rural youth. \n\n  Read now \n            \n \n\n\n\n\n\n\n\n\n\n\n\n\n\n\n\n\nPublication\n\n IFAD at a glance IFAD is the only multilateral development institution that focuses exclusively on investing in rural communities. \n\n  Read now \n            \n \n\n\n\n\n\n\n\n\n\n\n\n\n\n\n\nPublication\n\n Photobook: Fostering change in people’s lives in Liberia This photobook showcases the positive impact of IFAD-supported projects on Liberia’s rural communities, including the Tree Crops Extension Projects (TCEP-I and II) and the Smallholder Agriculture Transformation and Agribusiness Revitalization Project (STAR-P). \n\n  Read now \n            \n \n\n\n\n\n\n\n\n\n\n\n\n\n\n\n\n\n\nPublication\n\n Photobook: Growing stronger rural futures in Türkiye This photobook showcases the impact of two projects in Türkiye that were financed by IFAD alongside the Government of Türkiye: the Uplands Rural Development Programme (URDP) and the Göksu Taşeli Watershed Development Project (GTWDP). \n\n  Read now \n            \n \n\n\n\n\n\n\n\n\n\n\n\n\n\n\n\nPublication\n\n Sustainable and Resilient Agriculture in Malawi This brief provides an overview of the Investing in Livelihood Resilience and Soil Health in ACP Countries (ILSA) programme in Malawi, funded by the European Union and implemented by IFAD. \n\n  Read now \n            \n \n\n\n\n\n\n\n\n\n\n\n\n\n\n\n\nPublication\n\n IFAD Project Procurement Annual Report 2024 The 2024 Project Procurement Annual Report provides a comprehensive overview of IFAD's project procurement activities throughout the year. \n\n  Read now \n            \n \n\n\n\n\n\n\n\n\n\n\n\n\n\n\n\n\n\nPublication\n\n Highlights from the Crisis Response Initiative in Eritrea This document highlights the main results of activities funded by IFAD’s Crisis Response Initiative (CRI) in Eritrea. \n\n  Read now \n            \n \n\n\n\n\n\n\n\n\n\n\n\n\n\n\n\nPublication\n\n Investing in rural people in Guinea-Bissau This factsheet outlines IFAD’s work in Guinea-Bissau, including context, strategy and ongoing operations. \n\n  Read now \n            \n \n\n\n\n\n\n\n\n\n\n\n\n\n\n\n\nPublication\n\n Investing in rural people in Yemen This factsheet outlines IFAD’s work in Yemen, including context, strategy and ongoing operations. \n\n  Read now\n\nPublication\n\n How to do note: The ecosystem approach to decent rural youth employment and entrepreneurship This practical guide provides actionable strategies to strengthen agribusiness ecosystems that support rural youth employment and entrepreneurship, enhance collaboration among governments, private sector actors and youth organizations, and scale innovative approaches that create decent wages and self-employment opportunities for rural youth. \n\n  Read now \n            \n \n\n\n\n\n\n\n\n\n\n\n\n\n\n\n\n\nPublication\n\n IFAD at a glance IFAD is the only multilateral development institution that focuses exclusively on investing in rural communities. \n\n  Read now \n            \n \n\n\n\n\n\n\n\n\n\n\n\n\n\n\n\nPublication\n\n Photobook: Fostering change in people’s lives in Liberia This photobook showcases the positive impact of IFAD-supported projects on Liberia’s rural communities, including the Tree Crops Extension Projects (TCEP-I and II) and the Smallholder Agriculture Transformation and Agribusiness Revitalization Project (STAR-P). \n\n  Read now\n\nPublication\n\n How to do note: The ecosystem approach to decent rural youth employment and entrepreneurship This practical guide provides actionable strategies to strengthen agribusiness ecosystems that support rural youth employment and entrepreneurship, enhance collaboration among governments, private sector actors and youth organizations, and scale innovative approaches that create decent wages and self-employment opportunities for rural youth. \n\n  Read now\n\nPublication\n\n How to do note: The ecosystem approach to decent rural youth employment and entrepreneurship This practical guide provides actionable strategies to strengthen agribusiness ecosystems that support rural youth employment and entrepreneurship, enhance collaboration among governments, private sector actors and youth organizations, and scale innovative approaches that create decent wages and self-employment opportunities for rural youth. \n\n  Read now\n\nPublication\n\n How to do note: The ecosystem approach to decent rural youth employment and entrepreneurship This practical guide provides actionable strategies to strengthen agribusiness ecosystems that support rural youth employment and entrepreneurship, enhance collaboration among governments, private sector actors and youth organizations, and scale innovative approaches that create decent wages and self-employment opportunities for rural youth. \n\n  Read now\n\nPublication\n\n How to do note: The ecosystem approach to decent rural youth employment and entrepreneurship This practical guide provides actionable strategies to strengthen agribusiness ecosystems that support rural youth employment and entrepreneurship, enhance collaboration among governments, private sector actors and youth organizations, and scale innovative approaches that create decent wages and self-employment opportunities for rural youth. \n\n  Read now\n\nPublication\n\n How to do note: The ecosystem approach to decent rural youth employment and entrepreneurship This practical guide provides actionable strategies to strengthen agribusiness ecosystems that support rural youth employment and entrepreneurship, enhance collaboration among governments, private sector actors and youth organizations, and scale innovative approaches that create decent wages and self-employment opportunities for rural youth. \n\n  Read now\n\nPublication\n\n How to do note: The ecosystem approach to decent rural youth employment and entrepreneurship This practical guide provides actionable strategies to strengthen agribusiness ecosystems that support rural youth employment and entrepreneurship, enhance collaboration among governments, private sector actors and youth organizations, and scale innovative approaches that create decent wages and self-employment opportunities for rural youth.\n\nPublication\n\nPublication\n\nHow to do note: The ecosystem approach to decent rural youth employment and entrepreneurship This practical guide provides actionable strategies to strengthen agribusiness ecosystems that support rural youth employment and entrepreneurship, enhance collaboration among governments, private sector actors and youth organizations, and scale innovative approaches that create decent wages and self-employment opportunities for rural youth.\n\nHow to do note: The ecosystem approach to decent rural youth employment and entrepreneurship\n\nThis practical guide provides actionable strategies to strengthen agribusiness ecosystems that support rural youth employment and entrepreneurship, enhance collaboration among governments, private sector actors and youth organizations, and scale innovative approaches that create decent wages and self-employment opportunities for rural youth.\n\nPublication\n\n IFAD at a glance IFAD is the only multilateral development institution that focuses exclusively on investing in rural communities. \n\n  Read now\n\nPublication\n\n IFAD at a glance IFAD is the only multilateral development institution that focuses exclusively on investing in rural communities. \n\n  Read now\n\nPublication\n\n IFAD at a glance IFAD is the only multilateral development institution that focuses exclusively on investing in rural communities. \n\n  Read now\n\nPublication\n\n IFAD at a glance IFAD is the only multilateral development institution that focuses exclusively on investing in rural communities. \n\n  Read now\n\nPublication\n\n IFAD at a glance IFAD is the only multilateral development institution that focuses exclusively on investing in rural communities. \n\n  Read now\n\nPublication\n\n IFAD at a glance IFAD is the only multilateral development institution that focuses exclusively on investing in rural communities.\n\nPublication\n\nPublication\n\nIFAD at a glance IFAD is the only multilateral development institution that focuses exclusively on investing in rural communities.\n\nIFAD at a glance\n\nIFAD is the only multilateral development institution that focuses exclusively on investing in rural communities.\n\nPublication\n\n Photobook: Fostering change in people’s lives in Liberia This photobook showcases the positive impact of IFAD-supported projects on Liberia’s rural communities, including the Tree Crops Extension Projects (TCEP-I and II) and the Smallholder Agriculture Transformation and Agribusiness Revitalization Project (STAR-P). \n\n  Read now\n\nPublication\n\n Photobook: Fostering change in people’s lives in Liberia This photobook showcases the positive impact of IFAD-supported projects on Liberia’s rural communities, including the Tree Crops Extension Projects (TCEP-I and II) and the Smallholder Agriculture Transformation and Agribusiness Revitalization Project (STAR-P). \n\n  Read now\n\nPublication\n\n Photobook: Fostering change in people’s lives in Liberia This photobook showcases the positive impact of IFAD-supported projects on Liberia’s rural communities, including the Tree Crops Extension Projects (TCEP-I and II) and the Smallholder Agriculture Transformation and Agribusiness Revitalization Project (STAR-P). \n\n  Read now\n\nPublication\n\n Photobook: Fostering change in people’s lives in Liberia This photobook showcases the positive impact of IFAD-supported projects on Liberia’s rural communities, including the Tree Crops Extension Projects (TCEP-I and II) and the Smallholder Agriculture Transformation and Agribusiness Revitalization Project (STAR-P). \n\n  Read now\n\nPublication\n\n Photobook: Fostering change in people’s lives in Liberia This photobook showcases the positive impact of IFAD-supported projects on Liberia’s rural communities, including the Tree Crops Extension Projects (TCEP-I and II) and the Smallholder Agriculture Transformation and Agribusiness Revitalization Project (STAR-P). \n\n  Read now\n\nPublication\n\n Photobook: Fostering change in people’s lives in Liberia This photobook showcases the positive impact of IFAD-supported projects on Liberia’s rural communities, including the Tree Crops Extension Projects (TCEP-I and II) and the Smallholder Agriculture Transformation and Agribusiness Revitalization Project (STAR-P).\n\nPublication\n\nPublication\n\nPhotobook: Fostering change in people’s lives in Liberia This photobook showcases the positive impact of IFAD-supported projects on Liberia’s rural communities, including the Tree Crops Extension Projects (TCEP-I and II) and the Smallholder Agriculture Transformation and Agribusiness Revitalization Project (STAR-P).\n\nPhotobook: Fostering change in people’s lives in Liberia\n\nThis photobook showcases the positive impact of IFAD-supported projects on Liberia’s rural communities, including the Tree Crops Extension Projects (TCEP-I and II) and the Smallholder Agriculture Transformation and Agribusiness Revitalization Project (STAR-P).\n\nPublication\n\n Photobook: Growing stronger rural futures in Türkiye This photobook showcases the impact of two projects in Türkiye that were financed by IFAD alongside the Government of Türkiye: the Uplands Rural Development Programme (URDP) and the Göksu Taşeli Watershed Development Project (GTWDP). \n\n  Read now \n            \n \n\n\n\n\n\n\n\n\n\n\n\n\n\n\n\nPublication\n\n Sustainable and Resilient Agriculture in Malawi This brief provides an overview of the Investing in Livelihood Resilience and Soil Health in ACP Countries (ILSA) programme in Malawi, funded by the European Union and implemented by IFAD. \n\n  Read now \n            \n \n\n\n\n\n\n\n\n\n\n\n\n\n\n\n\nPublication\n\n IFAD Project Procurement Annual Report 2024 The 2024 Project Procurement Annual Report provides a comprehensive overview of IFAD's project procurement activities throughout the year. \n\n  Read now\n\nPublication\n\n Photobook: Growing stronger rural futures in Türkiye This photobook showcases the impact of two projects in Türkiye that were financed by IFAD alongside the Government of Türkiye: the Uplands Rural Development Programme (URDP) and the Göksu Taşeli Watershed Development Project (GTWDP). \n\n  Read now\n\nPublication\n\n Photobook: Growing stronger rural futures in Türkiye This photobook showcases the impact of two projects in Türkiye that were financed by IFAD alongside the Government of Türkiye: the Uplands Rural Development Programme (URDP) and the Göksu Taşeli Watershed Development Project (GTWDP). \n\n  Read now\n\nPublication\n\n Photobook: Growing stronger rural futures in Türkiye This photobook showcases the impact of two projects in Türkiye that were financed by IFAD alongside the Government of Türkiye: the Uplands Rural Development Programme (URDP) and the Göksu Taşeli Watershed Development Project (GTWDP). \n\n  Read now\n\nPublication\n\n Photobook: Growing stronger rural futures in Türkiye This photobook showcases the impact of two projects in Türkiye that were financed by IFAD alongside the Government of Türkiye: the Uplands Rural Development Programme (URDP) and the Göksu Taşeli Watershed Development Project (GTWDP). \n\n  Read now\n\nPublication\n\n Photobook: Growing stronger rural futures in Türkiye This photobook showcases the impact of two projects in Türkiye that were financed by IFAD alongside the Government of Türkiye: the Uplands Rural Development Programme (URDP) and the Göksu Taşeli Watershed Development Project (GTWDP). \n\n  Read now\n\nPublication\n\n Photobook: Growing stronger rural futures in Türkiye This photobook showcases the impact of two projects in Türkiye that were financed by IFAD alongside the Government of Türkiye: the Uplands Rural Development Programme (URDP) and the Göksu Taşeli Watershed Development Project (GTWDP).\n\nPublication\n\nPublication\n\nPhotobook: Growing stronger rural futures in Türkiye This photobook showcases the impact of two projects in Türkiye that were financed by IFAD alongside the Government of Türkiye: the Uplands Rural Development Programme (URDP) and the Göksu Taşeli Watershed Development Project (GTWDP).\n\nPhotobook: Growing stronger rural futures in Türkiye\n\nThis photobook showcases the impact of two projects in Türkiye that were financed by IFAD alongside the Government of Türkiye: the Uplands Rural Development Programme (URDP) and the Göksu Taşeli Watershed Development Project (GTWDP).\n\nPublication\n\n Sustainable and Resilient Agriculture in Malawi This brief provides an overview of the Investing in Livelihood Resilience and Soil Health in ACP Countries (ILSA) programme in Malawi, funded by the European Union and implemented by IFAD. \n\n  Read now\n\nPublication\n\n Sustainable and Resilient Agriculture in Malawi This brief provides an overview of the Investing in Livelihood Resilience and Soil Health in ACP Countries (ILSA) programme in Malawi, funded by the European Union and implemented by IFAD. \n\n  Read now\n\nPublication\n\n Sustainable and Resilient Agriculture in Malawi This brief provides an overview of the Investing in Livelihood Resilience and Soil Health in ACP Countries (ILSA) programme in Malawi, funded by the European Union and implemented by IFAD. \n\n  Read now\n\nPublication\n\n Sustainable and Resilient Agriculture in Malawi This brief provides an overview of the Investing in Livelihood Resilience and Soil Health in ACP Countries (ILSA) programme in Malawi, funded by the European Union and implemented by IFAD. \n\n  Read now\n\nPublication\n\n Sustainable and Resilient Agriculture in Malawi This brief provides an overview of the Investing in Livelihood Resilience and Soil Health in ACP Countries (ILSA) programme in Malawi, funded by the European Union and implemented by IFAD. \n\n  Read now\n\nPublication\n\n Sustainable and Resilient Agriculture in Malawi This brief provides an overview of the Investing in Livelihood Resilience and Soil Health in ACP Countries (ILSA) programme in Malawi, funded by the European Union and implemented by IFAD.\n\nPublication\n\nPublication\n\nSustainable and Resilient Agriculture in Malawi This brief provides an overview of the Investing in Livelihood Resilience and Soil Health in ACP Countries (ILSA) programme in Malawi, funded by the European Union and implemented by IFAD.\n\nSustainable and Resilient Agriculture in Malawi\n\nThis brief provides an overview of the Investing in Livelihood Resilience and Soil Health in ACP Countries (ILSA) programme in Malawi, funded by the European Union and implemented by IFAD.\n\nPublication\n\n IFAD Project Procurement Annual Report 2024 The 2024 Project Procurement Annual Report provides a comprehensive overview of IFAD's project procurement activities throughout the year. \n\n  Read now\n\nPublication\n\n IFAD Project Procurement Annual Report 2024 The 2024 Project Procurement Annual Report provides a comprehensive overview of IFAD's project procurement activities throughout the year. \n\n  Read now\n\nPublication\n\n IFAD Project Procurement Annual Report 2024 The 2024 Project Procurement Annual Report provides a comprehensive overview of IFAD's project procurement activities throughout the year. \n\n  Read now\n\nPublication\n\n IFAD Project Procurement Annual Report 2024 The 2024 Project Procurement Annual Report provides a comprehensive overview of IFAD's project procurement activities throughout the year. \n\n  Read now\n\nPublication\n\n IFAD Project Procurement Annual Report 2024 The 2024 Project Procurement Annual Report provides a comprehensive overview of IFAD's project procurement activities throughout the year. \n\n  Read now\n\nPublication\n\n IFAD Project Procurement Annual Report 2024 The 2024 Project Procurement Annual Report provides a comprehensive overview of IFAD's project procurement activities throughout the year.\n\nPublication\n\nPublication\n\nIFAD Project Procurement Annual Report 2024 The 2024 Project Procurement Annual Report provides a comprehensive overview of IFAD's project procurement activities throughout the year.\n\nIFAD Project Procurement Annual Report 2024\n\nThe 2024 Project Procurement Annual Report provides a comprehensive overview of IFAD's project procurement activities throughout the year.\n\nPublication\n\n Highlights from the Crisis Response Initiative in Eritrea This document highlights the main results of activities funded by IFAD’s Crisis Response Initiative (CRI) in Eritrea. \n\n  Read now \n            \n \n\n\n\n\n\n\n\n\n\n\n\n\n\n\n\nPublication\n\n Investing in rural people in Guinea-Bissau This factsheet outlines IFAD’s work in Guinea-Bissau, including context, strategy and ongoing operations. \n\n  Read now \n            \n \n\n\n\n\n\n\n\n\n\n\n\n\n\n\n\nPublication\n\n Investing in rural people in Yemen This factsheet outlines IFAD’s work in Yemen, including context, strategy and ongoing operations. \n\n  Read now\n\nPublication\n\n Highlights from the Crisis Response Initiative in Eritrea This document highlights the main results of activities funded by IFAD’s Crisis Response Initiative (CRI) in Eritrea. \n\n  Read now\n\nPublication\n\n Highlights from the Crisis Response Initiative in Eritrea This document highlights the main results of activities funded by IFAD’s Crisis Response Initiative (CRI) in Eritrea. \n\n  Read now\n\nPublication\n\n Highlights from the Crisis Response Initiative in Eritrea This document highlights the main results of activities funded by IFAD’s Crisis Response Initiative (CRI) in Eritrea. \n\n  Read now\n\nPublication\n\n Highlights from the Crisis Response Initiative in Eritrea This document highlights the main results of activities funded by IFAD’s Crisis Response Initiative (CRI) in Eritrea. \n\n  Read now\n\nPublication\n\n Highlights from the Crisis Response Initiative in Eritrea This document highlights the main results of activities funded by IFAD’s Crisis Response Initiative (CRI) in Eritrea. \n\n  Read now\n\nPublication\n\n Highlights from the Crisis Response Initiative in Eritrea This document highlights the main results of activities funded by IFAD’s Crisis Response Initiative (CRI) in Eritrea.\n\nPublication\n\nPublication\n\nHighlights from the Crisis Response Initiative in Eritrea This document highlights the main results of activities funded by IFAD’s Crisis Response Initiative (CRI) in Eritrea.\n\nHighlights from the Crisis Response Initiative in Eritrea\n\nThis document highlights the main results of activities funded by IFAD’s Crisis Response Initiative (CRI) in Eritrea.\n\nPublication\n\n Investing in rural people in Guinea-Bissau This factsheet outlines IFAD’s work in Guinea-Bissau, including context, strategy and ongoing operations. \n\n  Read now\n\nPublication\n\n Investing in rural people in Guinea-Bissau This factsheet outlines IFAD’s work in Guinea-Bissau, including context, strategy and ongoing operations. \n\n  Read now\n\nPublication\n\n Investing in rural people in Guinea-Bissau This factsheet outlines IFAD’s work in Guinea-Bissau, including context, strategy and ongoing operations. \n\n  Read now\n\nPublication\n\n Investing in rural people in Guinea-Bissau This factsheet outlines IFAD’s work in Guinea-Bissau, including context, strategy and ongoing operations. \n\n  Read now\n\nPublication\n\n Investing in rural people in Guinea-Bissau This factsheet outlines IFAD’s work in Guinea-Bissau, including context, strategy and ongoing operations. \n\n  Read now\n\nPublication\n\n Investing in rural people in Guinea-Bissau This factsheet outlines IFAD’s work in Guinea-Bissau, including context, strategy and ongoing operations.\n\nPublication\n\nPublication\n\nInvesting in rural people in Guinea-Bissau This factsheet outlines IFAD’s work in Guinea-Bissau, including context, strategy and ongoing operations.\n\nInvesting in rural people in Guinea-Bissau\n\nThis factsheet outlines IFAD’s work in Guinea-Bissau, including context, strategy and ongoing operations.\n\nPublication\n\n Investing in rural people in Yemen This factsheet outlines IFAD’s work in Yemen, including context, strategy and ongoing operations. \n\n  Read now\n\nPublication\n\n Investing in rural people in Yemen This factsheet outlines IFAD’s work in Yemen, including context, strategy and ongoing operations. \n\n  Read now\n\nPublication\n\n Investing in rural people in Yemen This factsheet outlines IFAD’s work in Yemen, including context, strategy and ongoing operations. \n\n  Read now\n\nPublication\n\n Investing in rural people in Yemen This factsheet outlines IFAD’s work in Yemen, including context, strategy and ongoing operations. \n\n  Read now\n\nPublication\n\n Investing in rural people in Yemen This factsheet outlines IFAD’s work in Yemen, including context, strategy and ongoing operations. \n\n  Read now\n\nPublication\n\n Investing in rural people in Yemen This factsheet outlines IFAD’s work in Yemen, including context, strategy and ongoing operations.\n\nPublication\n\nPublication\n\nInvesting in rural people in Yemen This factsheet outlines IFAD’s work in Yemen, including context, strategy and ongoing operations.\n\nInvesting in rural people in Yemen\n\nThis factsheet outlines IFAD’s work in Yemen, including context, strategy and ongoing operations.\n\nShowing 1 to 9 of 1380\n      \n\n\n\n\n\n\n\n1\n2\n3\n...\n154\n\nShowing 1 to 9 of 1380\n      \n\n\n\n\n\n\n\n1\n2\n3\n...\n154\n\nShowing 1 to 9 of 1380\n\nPlease configure the desktop menu widget below\n      \n\n\n\n\n\n\n\n\n About IFAD \n Who we are   Where we work   What we do   Action Areas   Knowledge & Data \n\n\n For Member States \n Member States interactive platform \n\n\n For Investors \n Investors   Finance \n\n\n For Job seekers \n Work with us   Frequently Asked Questions \n\n\n For Media \n News   Media Contacts   Image Bank \n\n\n Get Involved \n Join an event   Rural Voices   Opinions & Insights \n\n\n\n\n\n\n\n\n\n\n\n\n\n       Please configure the mobile menu widget below\n      \n\n\n\n\n\n\n\n\n Who we are \n\n\n\n What we do \n\n\n\n Where we work \n\n\n\n Action Areas \n\n\n\n Knowledge & Data \n\n\n\n Get Involved \n\n\n\n News and Stories \n\n\n\n\n\n\n\n\n\n\n\n\n\n  \n Legal  Privacy notice  Fraudulent job offers  Contact us Stay connected\n\nPlease configure the desktop menu widget below\n      \n\n\n\n\n\n\n\n\n About IFAD \n Who we are   Where we work   What we do   Action Areas   Knowledge & Data \n\n\n For Member States \n Member States interactive platform \n\n\n For Investors \n Investors   Finance \n\n\n For Job seekers \n Work with us   Frequently Asked Questions \n\n\n For Media \n News   Media Contacts   Image Bank \n\n\n Get Involved \n Join an event   Rural Voices   Opinions & Insights \n\n\n\n\n\n\n\n\n\n\n\n\n\n       Please configure the mobile menu widget below\n      \n\n\n\n\n\n\n\n\n Who we are \n\n\n\n What we do \n\n\n\n Where we work \n\n\n\n Action Areas \n\n\n\n Knowledge & Data \n\n\n\n Get Involved \n\n\n\n News and Stories \n\n\n\n\n\n\n\n\n\n\n\n\n\n  \n Legal  Privacy notice  Fraudulent job offers  Contact us Stay connected\n\nPlease configure the desktop menu widget below\n      \n\n\n\n\n\n\n\n\n About IFAD \n Who we are   Where we work   What we do   Action Areas   Knowledge & Data \n\n\n For Member States \n Member States interactive platform \n\n\n For Investors \n Investors   Finance \n\n\n For Job seekers \n Work with us   Frequently Asked Questions \n\n\n For Media \n News   Media Contacts   Image Bank \n\n\n Get Involved \n Join an event   Rural Voices   Opinions & Insights \n\n\n\n\n\n\n\n\n\n\n\n\n\n       Please configure the mobile menu widget below\n      \n\n\n\n\n\n\n\n\n Who we are \n\n\n\n What we do \n\n\n\n Where we work \n\n\n\n Action Areas \n\n\n\n Knowledge & Data \n\n\n\n Get Involved \n\n\n\n News and Stories \n\n\n\n\n\n\n\n\n\n\n\n\n\n  \n Legal  Privacy notice  Fraudulent job offers  Contact us Stay connected\n\nPlease configure the desktop menu widget below\n      \n\n\n\n\n\n\n\n\n About IFAD \n Who we are   Where we work   What we do   Action Areas   Knowledge & Data \n\n\n For Member States \n Member States interactive platform \n\n\n For Investors \n Investors   Finance \n\n\n For Job seekers \n Work with us   Frequently Asked Questions \n\n\n For Media \n News   Media Contacts   Image Bank \n\n\n Get Involved \n Join an event   Rural Voices   Opinions & Insights \n\n\n\n\n\n\n\n\n\n\n\n\n\n       Please configure the mobile menu widget below\n      \n\n\n\n\n\n\n\n\n Who we are \n\n\n\n What we do \n\n\n\n Where we work \n\n\n\n Action Areas \n\n\n\n Knowledge & Data \n\n\n\n Get Involved \n\n\n\n News and Stories\n\nPlease configure the desktop menu widget below\n      \n\n\n\n\n\n\n\n\n About IFAD \n Who we are   Where we work   What we do   Action Areas   Knowledge & Data \n\n\n For Member States \n Member States interactive platform \n\n\n For Investors \n Investors   Finance \n\n\n For Job seekers \n Work with us   Frequently Asked Questions \n\n\n For Media \n News   Media Contacts   Image Bank \n\n\n Get Involved \n Join an event   Rural Voices   Opinions & Insights\n\nPlease configure the desktop menu widget below\n\nAbout IFAD \n Who we are   Where we work   What we do   Action Areas   Knowledge & Data \n\n\n For Member States \n Member States interactive platform \n\n\n For Investors \n Investors   Finance \n\n\n For Job seekers \n Work with us   Frequently Asked Questions \n\n\n For Media \n News   Media Contacts   Image Bank \n\n\n Get Involved \n Join an event   Rural Voices   Opinions & Insights\n\nAbout IFAD \n Who we are   Where we work   What we do   Action Areas   Knowledge & Data \n\n\n For Member States \n Member States interactive platform \n\n\n For Investors \n Investors   Finance \n\n\n For Job seekers \n Work with us   Frequently Asked Questions \n\n\n For Media \n News   Media Contacts   Image Bank \n\n\n Get Involved \n Join an event   Rural Voices   Opinions & Insights\n\nAbout IFAD \n Who we are   Where we work   What we do   Action Areas   Knowledge & Data \n\n\n For Member States \n Member States interactive platform \n\n\n For Investors \n Investors   Finance \n\n\n For Job seekers \n Work with us   Frequently Asked Questions \n\n\n For Media \n News   Media Contacts   Image Bank \n\n\n Get Involved \n Join an event   Rural Voices   Opinions & Insights\n\nAbout IFAD \n Who we are   Where we work   What we do   Action Areas   Knowledge & Data \n\n\n For Member States \n Member States interactive platform \n\n\n For Investors \n Investors   Finance \n\n\n For Job seekers \n Work with us   Frequently Asked Questions \n\n\n For Media \n News   Media Contacts   Image Bank \n\n\n Get Involved \n Join an event   Rural Voices   Opinions & Insights\n\nAbout IFAD \n Who we are   Where we work   What we do   Action Areas   Knowledge & Data \n\n\n For Member States \n Member States interactive platform \n\n\n For Investors \n Investors   Finance \n\n\n For Job seekers \n Work with us   Frequently Asked Questions \n\n\n For Media \n News   Media Contacts   Image Bank \n\n\n Get Involved \n Join an event   Rural Voices   Opinions & Insights\n\nAbout IFAD \n Who we are   Where we work   What we do   Action Areas   Knowledge & Data \n\n\n For Member States \n Member States interactive platform \n\n\n For Investors \n Investors   Finance \n\n\n For Job seekers \n Work with us   Frequently Asked Questions \n\n\n For Media \n News   Media Contacts   Image Bank \n\n\n Get Involved \n Join an event   Rural Voices   Opinions & Insights\n\nAbout IFAD \n Who we are   Where we work   What we do   Action Areas   Knowledge & Data \n\n\n For Member States \n Member States interactive platform \n\n\n For Investors \n Investors   Finance \n\n\n For Job seekers \n Work with us   Frequently Asked Questions \n\n\n For Media \n News   Media Contacts   Image Bank \n\n\n Get Involved \n Join an event   Rural Voices   Opinions & Insights\n\nAbout IFAD \n Who we are   Where we work   What we do   Action Areas   Knowledge & Data \n\n\n For Member States \n Member States interactive platform \n\n\n For Investors \n Investors   Finance \n\n\n For Job seekers \n Work with us   Frequently Asked Questions \n\n\n For Media \n News   Media Contacts   Image Bank \n\n\n Get Involved \n Join an event   Rural Voices   Opinions & Insights\n\nAbout IFAD \n Who we are   Where we work   What we do   Action Areas   Knowledge & Data\n\nWho we are   Where we work   What we do   Action Areas   Knowledge & Data\n\nFor Member States \n Member States interactive platform\n\nMember States interactive platform\n\nFor Investors \n Investors   Finance\n\nInvestors   Finance\n\nFor Job seekers \n Work with us   Frequently Asked Questions\n\nWork with us   Frequently Asked Questions\n\nFor Media \n News   Media Contacts   Image Bank\n\nNews   Media Contacts   Image Bank\n\nGet Involved \n Join an event   Rural Voices   Opinions & Insights\n\nJoin an event   Rural Voices   Opinions & Insights\n\nPlease configure the mobile menu widget below\n      \n\n\n\n\n\n\n\n\n Who we are \n\n\n\n What we do \n\n\n\n Where we work \n\n\n\n Action Areas \n\n\n\n Knowledge & Data \n\n\n\n Get Involved \n\n\n\n News and Stories\n\nPlease configure the mobile menu widget below\n\nWho we are \n\n\n\n What we do \n\n\n\n Where we work \n\n\n\n Action Areas \n\n\n\n Knowledge & Data \n\n\n\n Get Involved \n\n\n\n News and Stories\n\nWho we are \n\n\n\n What we do \n\n\n\n Where we work \n\n\n\n Action Areas \n\n\n\n Knowledge & Data \n\n\n\n Get Involved \n\n\n\n News and Stories\n\nWho we are \n\n\n\n What we do \n\n\n\n Where we work \n\n\n\n Action Areas \n\n\n\n Knowledge & Data \n\n\n\n Get Involved \n\n\n\n News and Stories\n\nWho we are \n\n\n\n What we do \n\n\n\n Where we work \n\n\n\n Action Areas \n\n\n\n Knowledge & Data \n\n\n\n Get Involved \n\n\n\n News and Stories\n\nWho we are \n\n\n\n What we do \n\n\n\n Where we work \n\n\n\n Action Areas \n\n\n\n Knowledge & Data \n\n\n\n Get Involved \n\n\n\n News and Stories\n\nWho we are \n\n\n\n What we do \n\n\n\n Where we work \n\n\n\n Action Areas \n\n\n\n Knowledge & Data \n\n\n\n Get Involved \n\n\n\n News and Stories\n\nWho we are \n\n\n\n What we do \n\n\n\n Where we work \n\n\n\n Action Areas \n\n\n\n Knowledge & Data \n\n\n\n Get Involved \n\n\n\n News and Stories\n\nWho we are \n\n\n\n What we do \n\n\n\n Where we work \n\n\n\n Action Areas \n\n\n\n Knowledge & Data \n\n\n\n Get Involved \n\n\n\n News and Stories\n\nWho we are\n\nWhat we do\n\nWhere we work\n\nAction Areas\n\nKnowledge & Data\n\nGet Involved\n\nNews and Stories\n\nLegal  Privacy notice  Fraudulent job offers  Contact us Stay connected\n\nLegal  Privacy notice  Fraudulent job offers  Contact us Stay connected",
  "date": "",
  "source_type": "other",
  "extracted_at": "2025-04-07T14:28:05.422831",
  "metadata": {
    "og:site_name": "IFAD",
    "og:type": "website"
  },
  "relevance_score": 0.5,
  "summary": "Knowledge &amp; Data - IFAD\n\n\n\n\n\n\n\n\n\n\n\n\n\n\n\n\n\n\n\n\n\n\n\n\n\n\n\n\nAll Publications\n\n\n\n\n\n\n\n\n Theme \nSelect\n\n\n\n\n\n\n\n Year \nSelect\n\n\n\n\n\n\n\n Country \nSelect\n\n\n\n\n\n\n\n\n\n\n\n  Show more  \n\n\n\n\n\n  \n\n\n\n\n\n\n\n\n\n\n\n\n\n\n\n\n\nPublication\n\n How to do note: The ecosystem approach to decent rural youth employment and entrepreneurship This practical guide provides actionable strategies to strengthen agribusiness ecosystems that support rural youth employment and entrepreneurship, enhance collaboration among governments, private sector actors and youth organizations, and scale innovative approaches that create decent wages and self-employment opportunities for rural youth. Read now \n            \n \n\n\n\n\n\n\n\n\n\n\n\n\n\n\n\n\n\nPublication\n\n Photobook: Growing stronger rural futures in Türkiye This photobook showcases the impact of two projects in Türkiye that were financed by IFAD alongside the Government of Türkiye: the Uplands Rural Development Programme (URDP) and the Göksu Taşeli Watershed Development Project (GTWDP). 154\n\n\n\n\n\n\n\n\n\n\n\n\n\n\n\n\n\n       Please configure the desktop menu widget below\n      \n\n\n\n\n\n\n\n\n About IFAD \n Who we are   Where we work   What we do   Action Areas   Knowledge & Data \n\n\n For Member States \n Member States interactive platform \n\n\n For Investors \n Investors   Finance \n\n\n For Job seekers \n Work with us   Frequently Asked Questions \n\n\n For Media \n News   Media Contacts   Image Bank \n\n\n Get Involved \n Join an event   Rural Voices   Opinions & Insights \n\n\n\n\n\n\n\n\n\n\n\n\n\n       Please configure the mobile menu widget below\n      \n\n\n\n\n\n\n\n\n Who we are \n\n\n\n What we do \n\n\n\n Where we work \n\n\n\n Action Areas \n\n\n\n Knowledge & Data \n\n\n\n Get Involved \n\n\n\n News and Stories \n\n\n\n\n\n\n\n\n\n\n\n\n\n  \n Legal  Privacy notice  Fraudulent job offers  Contact us Stay connected\n\n\n\n  \n\n  \n\n  \n\n  \n\n  \n\n \n\n\n\n\n\n\n\n\nHidden\n\nKnowledge &amp; Data - IFAD\n\n\n\n\n\n\n\n\n\n\n\n\n\n\n\n\n\n\n\n\n\n\n\n\n\n\n\n\nAll Publications\n\n\n\n\n\n\n\n\n Theme \nSelect\n\n\n\n\n\n\n\n Year \nSelect\n\n\n\n\n\n\n\n Country \nSelect\n\n\n\n\n\n\n\n\n\n\n\n  Show more  \n\n\n\n\n\n  \n\n\n\n\n\n\n\n\n\n\n\n\n\n\n\n\n\nPublication\n\n How to do note: The ecosystem approach to decent rural youth employment and entrepreneurship This practical guide provides actionable strategies to strengthen agribusiness ecosystems that support rural youth employment and entrepreneurship, enhance collaboration among governments, private sector actors and youth organizations, and scale innovative approaches that create decent wages and self-employment opportunities for rural youth. Read now \n            \n \n\n\n\n\n\n\n\n\n\n\n\n\n\n\n\n\n\nPublication\n\n Photobook: Growing stronger rural futures in Türkiye This photobook showcases the impact of two projects in Türkiye that were financed by IFAD alongside the Government of Türkiye: the Uplands Rural Development Programme (URDP) and the Göksu Taşeli Watershed Development Project (GTWDP). 154\n\n\n\n\n\n\n\n\n\n\n\n\n\n\n\n\n\n       Please configure the desktop menu widget below\n      \n\n\n\n\n\n\n\n\n About IFAD \n Who we are   Where we work   What we do   Action Areas   Knowledge & Data \n\n\n For Member States \n Member States interactive platform \n\n\n For Investors \n Investors   Finance \n\n\n For Job seekers \n Work with us   Frequently Asked Questions \n\n\n For Media \n News   Media Contacts   Image Bank \n\n\n Get Involved \n Join an event   Rural Voices   Opinions & Insights \n\n\n\n\n\n\n\n\n\n\n\n\n\n       Please configure the mobile menu widget below\n      \n\n\n\n\n\n\n\n\n Who we are \n\n\n\n What we do \n\n\n\n Where we work \n\n\n\n Action Areas \n\n\n\n Knowledge & Data \n\n\n\n Get Involved \n\n\n\n News and Stories \n\n\n\n\n\n\n\n\n\n\n\n\n\n  \n Legal  Privacy notice  Fraudulent job offers  Contact us Stay connected\n\n\n\n  \n\n  \n\n  \n\n  \n\n  \n\n \n\n\n\n\n\n\n\n\nHidden\n\nKnowledge &amp; Data - IFAD\n\n\n\n\n\n\n\n\n\n\n\n\n\n\n\n\n\n\n\n\n\n\n\n\n\n\n\n\nAll Publications\n\n\n\n\n\n\n\n\n Theme \nSelect\n\n\n\n\n\n\n\n Year \nSelect\n\n\n\n\n\n\n\n Country \nSelect\n\n\n\n\n\n\n\n\n\n\n\n  Show more  \n\n\n\n\n\n  \n\n\n\n\n\n\n\n\n\n\n\n\n\n\n\n\n\nPublication\n\n How to do note: The ecosystem approach to decent rural youth employment and entrepreneurship This practical guide provides actionable strategies to strengthen agribusiness ecosystems that support rural youth employment and entrepreneurship, enhance collaboration among governments, private sector actors and youth organizations, and scale innovative approaches that create decent wages and self-employment opportunities for rural youth. Read now \n            \n \n\n\n\n\n\n\n\n\n\n\n\n\n\n\n\n\n\nPublication\n\n Photobook: Growing stronger rural futures in Türkiye This photobook showcases the impact of two projects in Türkiye that were financed by IFAD alongside the Government of Türkiye: the Uplands Rural Development Programme (URDP) and the Göksu Taşeli Watershed Development Project (GTWDP). 154\n\n\n\n\n\n\n\n\n\n\n\n\n\n\n\n\n\n       Please configure the desktop menu widget below\n      \n\n\n\n\n\n\n\n\n About IFAD \n Who we are   Where we work   What we do   Action Areas   Knowledge & Data \n\n\n For Member States \n Member States interactive platform \n\n\n For Investors \n Investors   Finance \n\n\n For Job seekers \n Work with us   Frequently Asked Questions \n\n\n For Media \n News   Media Contacts   Image Bank \n\n\n Get Involved \n Join an event   Rural Voices   Opinions & Insights \n\n\n\n\n\n\n\n\n\n\n\n\n\n       Please configure the mobile menu widget below\n      \n\n\n\n\n\n\n\n\n Who we are \n\n\n\n What we do \n\n\n\n Where we work \n\n\n\n Action Areas \n\n\n\n Knowledge & Data \n\n\n\n Get Involved \n\n\n\n News and Stories \n\n\n\n\n\n\n\n\n\n\n\n\n\n  \n Legal  Privacy notice  Fraudulent job offers  Contact us Stay connected\n\n\n\n  \n\n  \n\n  \n\n  \n\n  \n\n \n\n\n\n\n\n\n\n\nHidden\n\nAll Publications\n\n\n\n\n\n\n\n\n Theme \nSelect\n\n\n\n\n\n\n\n Year \nSelect\n\n\n\n\n\n\n\n Country \nSelect\n\n\n\n\n\n\n\n\n\n\n\n  Show more  \n\n\n\n\n\n  \n\n\n\n\n\n\n\n\n\n\n\n\n\n\n\n\n\nPublication\n\n How to do note: The ecosystem approach to decent rural youth employment and entrepreneurship This practical guide provides actionable strategies to strengthen agribusiness ecosystems that support rural youth employment and entrepreneurship, enhance collaboration among governments, private sector actors and youth organizations, and scale innovative approaches that create decent wages and self-employment opportunities for rural youth. Read now \n            \n \n\n\n\n\n\n\n\n\n\n\n\n\n\n\n\n\n\nPublication\n\n Photobook: Growing stronger rural futures in Türkiye This photobook showcases the impact of two projects in Türkiye that were financed by IFAD alongside the Government of Türkiye: the Uplands Rural Development Programme (URDP) and the Göksu Taşeli Watershed Development Project (GTWDP). 154\n\n\n\n\n\n\n\n\n\n\n\n\n\n\n\n\n\n       Please configure the desktop menu widget below\n      \n\n\n\n\n\n\n\n\n About IFAD \n Who we are   Where we work   What we do   Action Areas   Knowledge & Data \n\n\n For Member States \n Member States interactive platform \n\n\n For Investors \n Investors   Finance \n\n\n For Job seekers \n Work with us   Frequently Asked Questions \n\n\n For Media \n News   Media Contacts   Image Bank \n\n\n Get Involved \n Join an event   Rural Voices   Opinions & Insights \n\n\n\n\n\n\n\n\n\n\n\n\n\n       Please configure the mobile menu widget below\n      \n\n\n\n\n\n\n\n\n Who we are \n\n\n\n What we do \n\n\n\n Where we work \n\n\n\n Action Areas \n\n\n\n Knowledge & Data \n\n\n\n Get Involved \n\n\n\n News and Stories \n\n\n\n\n\n\n\n\n\n\n\n\n\n  \n Legal  Privacy notice  Fraudulent job offers  Contact us Stay connected\n\nAll Publications\n\n\n\n\n\n\n\n\n Theme \nSelect\n\n\n\n\n\n\n\n Year \nSelect\n\n\n\n\n\n\n\n Country \nSelect\n\n\n\n\n\n\n\n\n\n\n\n  Show more  \n\n\n\n\n\n  \n\n\n\n\n\n\n\n\n\n\n\n\n\n\n\n\n\nPublication\n\n How to do note: The ecosystem approach to decent rural youth employment and entrepreneurship This practical guide provides actionable strategies to strengthen agribusiness ecosystems that support rural youth employment and entrepreneurship, enhance collaboration among governments, private sector actors and youth organizations, and scale innovative approaches that create decent wages and self-employment opportunities for rural youth. Read now \n            \n \n\n\n\n\n\n\n\n\n\n\n\n\n\n\n\n\n\nPublication\n\n Photobook: Growing stronger rural futures in Türkiye This photobook showcases the impact of two projects in Türkiye that were financed by IFAD alongside the Government of Türkiye: the Uplands Rural Development Programme (URDP) and the Göksu Taşeli Watershed Development Project (GTWDP). 154\n\n\n\n\n\n\n\n\n\n\n\n\n\n\n\n\n\n       Please configure the desktop menu widget below\n      \n\n\n\n\n\n\n\n\n About IFAD \n Who we are   Where we work   What we do   Action Areas   Knowledge & Data \n\n\n For Member States \n Member States interactive platform \n\n\n For Investors \n Investors   Finance \n\n\n For Job seekers \n Work with us   Frequently Asked Questions \n\n\n For Media \n News   Media Contacts   Image Bank \n\n\n Get Involved \n Join an event   Rural Voices   Opinions & Insights \n\n\n\n\n\n\n\n\n\n\n\n\n\n       Please configure the mobile menu widget below\n      \n\n\n\n\n\n\n\n\n Who we are \n\n\n\n What we do \n\n\n\n Where we work \n\n\n\n Action Areas \n\n\n\n Knowledge & Data \n\n\n\n Get Involved \n\n\n\n News and Stories \n\n\n\n\n\n\n\n\n\n\n\n\n\n  \n Legal  Privacy notice  Fraudulent job offers  Contact us Stay connected\n\nAll Publications\n\n\n\n\n\n\n\n\n Theme \nSelect\n\n\n\n\n\n\n\n Year \nSelect\n\n\n\n\n\n\n\n Country \nSelect\n\n\n\n\n\n\n\n\n\n\n\n  Show more  \n\n\n\n\n\n  \n\n\n\n\n\n\n\n\n\n\n\n\n\n\n\n\n\nPublication\n\n How to do note: The ecosystem approach to decent rural youth employment and entrepreneurship This practical guide provides actionable strategies to strengthen agribusiness ecosystems that support rural youth employment and entrepreneurship, enhance collaboration among governments, private sector actors and youth organizations, and scale innovative approaches that create decent wages and self-employment opportunities for rural youth. Read now \n            \n \n\n\n\n\n\n\n\n\n\n\n\n\n\n\n\n\n\nPublication\n\n Photobook: Growing stronger rural futures in Türkiye This photobook showcases the impact of two projects in Türkiye that were financed by IFAD alongside the Government of Türkiye: the Uplands Rural Development Programme (URDP) and the Göksu Taşeli Watershed Development Project (GTWDP). 154\n\nAll Publications\n\n\n\n\n\n\n\n\n Theme \nSelect\n\n\n\n\n\n\n\n Year \nSelect\n\n\n\n\n\n\n\n Country \nSelect\n\n\n\n\n\n\n\n\n\n\n\n  Show more  \n\n\n\n\n\n  \n\n\n\n\n\n\n\n\n\n\n\n\n\n\n\n\n\nPublication\n\n How to do note: The ecosystem approach to decent rural youth employment and entrepreneurship This practical guide provides actionable strategies to strengthen agribusiness ecosystems that support rural youth employment and entrepreneurship, enhance collaboration among governments, private sector actors and youth organizations, and scale innovative approaches that create decent wages and self-employment opportunities for rural youth. Read now \n            \n \n\n\n\n\n\n\n\n\n\n\n\n\n\n\n\n\n\nPublication\n\n Photobook: Growing stronger rural futures in Türkiye This photobook showcases the impact of two projects in Türkiye that were financed by IFAD alongside the Government of Türkiye: the Uplands Rural Development Programme (URDP) and the Göksu Taşeli Watershed Development Project (GTWDP). 154\n\nAll Publications\n\nAll Publications\n\nTheme \nSelect\n\n\n\n\n\n\n\n Year \nSelect\n\n\n\n\n\n\n\n Country \nSelect\n\n\n\n\n\n\n\n\n\n\n\n  Show more\n\nTheme \nSelect\n\n\n\n\n\n\n\n Year \nSelect\n\n\n\n\n\n\n\n Country \nSelect\n\nTheme \nSelect\n\n\n\n\n\n\n\n Year \nSelect\n\n\n\n\n\n\n\n Country \nSelect\n\nTheme \nSelect\n\nTheme \nSelect\n\nTheme \nSelect\n\nSelect\n\nYear \nSelect\n\nYear \nSelect\n\nYear \nSelect\n\nSelect\n\nCountry \nSelect\n\nCountry \nSelect\n\nCountry \nSelect\n\nSelect\n\nShow more\n\nShow more\n\nShow more\n\nPublication\n\n How to do note: The ecosystem approach to decent rural youth employment and entrepreneurship This practical guide provides actionable strategies to strengthen agribusiness ecosystems that support rural youth employment and entrepreneurship, enhance collaboration among governments, private sector actors and youth organizations, and scale innovative approaches that create decent wages and self-employment opportunities for rural youth. Read now \n            \n \n\n\n\n\n\n\n\n\n\n\n\n\n\n\n\n\n\nPublication\n\n Photobook: Growing stronger rural futures in Türkiye This photobook showcases the impact of two projects in Türkiye that were financed by IFAD alongside the Government of Türkiye: the Uplands Rural Development Programme (URDP) and the Göksu Taşeli Watershed Development Project (GTWDP). 154\n\nPublication\n\n How to do note: The ecosystem approach to decent rural youth employment and entrepreneurship This practical guide provides actionable strategies to strengthen agribusiness ecosystems that support rural youth employment and entrepreneurship, enhance collaboration among governments, private sector actors and youth organizations, and scale innovative approaches that create decent wages and self-employment opportunities for rural youth. Read now \n            \n \n\n\n\n\n\n\n\n\n\n\n\n\n\n\n\n\n\nPublication\n\n Photobook: Growing stronger rural futures in Türkiye This photobook showcases the impact of two projects in Türkiye that were financed by IFAD alongside the Government of Türkiye: the Uplands Rural Development Programme (URDP) and the Göksu Taşeli Watershed Development Project (GTWDP). Read now\n\nPublication\n\n How to do note: The ecosystem approach to decent rural youth employment and entrepreneurship This practical guide provides actionable strategies to strengthen agribusiness ecosystems that support rural youth employment and entrepreneurship, enhance collaboration among governments, private sector actors and youth organizations, and scale innovative approaches that create decent wages and self-employment opportunities for rural youth. Read now\n\nPublication\n\n How to do note: The ecosystem approach to decent rural youth employment and entrepreneurship This practical guide provides actionable strategies to strengthen agribusiness ecosystems that support rural youth employment and entrepreneurship, enhance collaboration among governments, private sector actors and youth organizations, and scale innovative approaches that create decent wages and self-employment opportunities for rural youth. Read now\n\nPublication\n\n How to do note: The ecosystem approach to decent rural youth employment and entrepreneurship This practical guide provides actionable strategies to strengthen agribusiness ecosystems that support rural youth employment and entrepreneurship, enhance collaboration among governments, private sector actors and youth organizations, and scale innovative approaches that create decent wages and self-employment opportunities for rural youth. Read now\n\nPublication\n\n How to do note: The ecosystem approach to decent rural youth employment and entrepreneurship This practical guide provides actionable strategies to strengthen agribusiness ecosystems that support rural youth employment and entrepreneurship, enhance collaboration among governments, private sector actors and youth organizations, and scale innovative approaches that create decent wages and self-employment opportunities for rural youth. Read now\n\nPublication\n\n How to do note: The ecosystem approach to decent rural youth employment and entrepreneurship This practical guide provides actionable strategies to strengthen agribusiness ecosystems that support rural youth employment and entrepreneurship, enhance collaboration among governments, private sector actors and youth organizations, and scale innovative approaches that create decent wages and self-employment opportunities for rural youth. Read now\n\nPublication\n\n How to do note: The ecosystem approach to decent rural youth employment and entrepreneurship This practical guide provides actionable strategies to strengthen agribusiness ecosystems that support rural youth employment and entrepreneurship, enhance collaboration among governments, private sector actors and youth organizations, and scale innovative approaches that create decent wages and self-employment opportunities for rural youth. Read now\n\nPublication\n\n How to do note: The ecosystem approach to decent rural youth employment and entrepreneurship This practical guide provides actionable strategies to strengthen agribusiness ecosystems that support rural youth employment and entrepreneurship, enhance collaboration among governments, private sector actors and youth organizations, and scale innovative approaches that create decent wages and self-employment opportunities for rural youth. Publication\n\nPublication\n\nHow to do note: The ecosystem approach to decent rural youth employment and entrepreneurship This practical guide provides actionable strategies to strengthen agribusiness ecosystems that support rural youth employment and entrepreneurship, enhance collaboration among governments, private sector actors and youth organizations, and scale innovative approaches that create decent wages and self-employment opportunities for rural youth. Read now\n\nPublication\n\n Photobook: Growing stronger rural futures in Türkiye This photobook showcases the impact of two projects in Türkiye that were financed by IFAD alongside the Government of Türkiye: the Uplands Rural Development Programme (URDP) and the Göksu Taşeli Watershed Development Project (GTWDP). Read now\n\nPublication\n\n Photobook: Growing stronger rural futures in Türkiye This photobook showcases the impact of two projects in Türkiye that were financed by IFAD alongside the Government of Türkiye: the Uplands Rural Development Programme (URDP) and the Göksu Taşeli Watershed Development Project (GTWDP). Read now\n\nPublication\n\n Photobook: Growing stronger rural futures in Türkiye This photobook showcases the impact of two projects in Türkiye that were financed by IFAD alongside the Government of Türkiye: the Uplands Rural Development Programme (URDP) and the Göksu Taşeli Watershed Development Project (GTWDP). Read now\n\nPublication\n\n Photobook: Growing stronger rural futures in Türkiye This photobook showcases the impact of two projects in Türkiye that were financed by IFAD alongside the Government of Türkiye: the Uplands Rural Development Programme (URDP) and the Göksu Taşeli Watershed Development Project (GTWDP). Read now\n\nPublication\n\n Photobook: Growing stronger rural futures in Türkiye This photobook showcases the impact of two projects in Türkiye that were financed by IFAD alongside the Government of Türkiye: the Uplands Rural Development Programme (URDP) and the Göksu Taşeli Watershed Development Project (GTWDP). Read now\n\nPublication\n\n Photobook: Growing stronger rural futures in Türkiye This photobook showcases the impact of two projects in Türkiye that were financed by IFAD alongside the Government of Türkiye: the Uplands Rural Development Programme (URDP) and the Göksu Taşeli Watershed Development Project (GTWDP). Publication\n\nPublication\n\nPhotobook: Growing stronger rural futures in Türkiye This photobook showcases the impact of two projects in Türkiye that were financed by IFAD alongside the Government of Türkiye: the Uplands Rural Development Programme (URDP) and the Göksu Taşeli Watershed Development Project (GTWDP). 154\n\nShowing 1 to 9 of 1380\n\nPlease configure the desktop menu widget below\n      \n\n\n\n\n\n\n\n\n About IFAD \n Who we are   Where we work   What we do   Action Areas   Knowledge & Data \n\n\n For Member States \n Member States interactive platform \n\n\n For Investors \n Investors   Finance \n\n\n For Job seekers \n Work with us   Frequently Asked Questions \n\n\n For Media \n News   Media Contacts   Image Bank \n\n\n Get Involved \n Join an event   Rural Voices   Opinions & Insights \n\n\n\n\n\n\n\n\n\n\n\n\n\n       Please configure the mobile menu widget below\n      \n\n\n\n\n\n\n\n\n Who we are \n\n\n\n What we do \n\n\n\n Where we work \n\n\n\n Action Areas \n\n\n\n Knowledge & Data \n\n\n\n Get Involved \n\n\n\n News and Stories \n\n\n\n\n\n\n\n\n\n\n\n\n\n  \n Legal  Privacy notice  Fraudulent job offers  Contact us Stay connected\n\nPlease configure the desktop menu widget below\n      \n\n\n\n\n\n\n\n\n About IFAD \n Who we are   Where we work   What we do   Action Areas   Knowledge & Data \n\n\n For Member States \n Member States interactive platform \n\n\n For Investors \n Investors   Finance \n\n\n For Job seekers \n Work with us   Frequently Asked Questions \n\n\n For Media \n News   Media Contacts   Image Bank \n\n\n Get Involved \n Join an event   Rural Voices   Opinions & Insights \n\n\n\n\n\n\n\n\n\n\n\n\n\n       Please configure the mobile menu widget below\n      \n\n\n\n\n\n\n\n\n Who we are \n\n\n\n What we do \n\n\n\n Where we work \n\n\n\n Action Areas \n\n\n\n Knowledge & Data \n\n\n\n Get Involved \n\n\n\n News and Stories \n\n\n\n\n\n\n\n\n\n\n\n\n\n  \n Legal  Privacy notice  Fraudulent job offers  Contact us Stay connected\n\nPlease configure the desktop menu widget below\n      \n\n\n\n\n\n\n\n\n About IFAD \n Who we are   Where we work   What we do   Action Areas   Knowledge & Data \n\n\n For Member States \n Member States interactive platform \n\n\n For Investors \n Investors   Finance \n\n\n For Job seekers \n Work with us   Frequently Asked Questions \n\n\n For Media \n News   Media Contacts   Image Bank \n\n\n Get Involved \n Join an event   Rural Voices   Opinions & Insights \n\n\n\n\n\n\n\n\n\n\n\n\n\n       Please configure the mobile menu widget below\n      \n\n\n\n\n\n\n\n\n Who we are \n\n\n\n What we do \n\n\n\n Where we work \n\n\n\n Action Areas \n\n\n\n Knowledge & Data \n\n\n\n Get Involved \n\n\n\n News and Stories \n\n\n\n\n\n\n\n\n\n\n\n\n\n  \n Legal  Privacy notice  Fraudulent job offers  Contact us Stay connected\n\nPlease configure the desktop menu widget below\n      \n\n\n\n\n\n\n\n\n About IFAD \n Who we are   Where we work   What we do   Action Areas   Knowledge & Data \n\n\n For Member States \n Member States interactive platform \n\n\n For Investors \n Investors   Finance \n\n\n For Job seekers \n Work with us   Frequently Asked Questions \n\n\n For Media \n News   Media Contacts   Image Bank \n\n\n Get Involved \n Join an event   Rural Voices   Opinions & Insights \n\n\n\n\n\n\n\n\n\n\n\n\n\n       Please configure the mobile menu widget below\n      \n\n\n\n\n\n\n\n\n Who we are \n\n\n\n What we do \n\n\n\n Where we work \n\n\n\n Action Areas \n\n\n\n Knowledge & Data \n\n\n\n Get Involved \n\n\n\n News and Stories\n\nPlease configure the desktop menu widget below\n      \n\n\n\n\n\n\n\n\n About IFAD \n Who we are   Where we work   What we do   Action Areas   Knowledge & Data \n\n\n For Member States \n Member States interactive platform \n\n\n For Investors \n Investors   Finance \n\n\n For Job seekers \n Work with us   Frequently Asked Questions \n\n\n For Media \n News   Media Contacts   Image Bank \n\n\n Get Involved \n Join an event   Rural Voices   Opinions & Insights\n\nPlease configure the desktop menu widget below\n\nAbout IFAD \n Who we are   Where we work   What we do   Action Areas   Knowledge & Data \n\n\n For Member States \n Member States interactive platform \n\n\n For Investors \n Investors   Finance \n\n\n For Job seekers \n Work with us   Frequently Asked Questions \n\n\n For Media \n News   Media Contacts   Image Bank \n\n\n Get Involved \n Join an event   Rural Voices   Opinions & Insights\n\nAbout IFAD \n Who we are   Where we work   What we do   Action Areas   Knowledge & Data \n\n\n For Member States \n Member States interactive platform \n\n\n For Investors \n Investors   Finance \n\n\n For Job seekers \n Work with us   Frequently Asked Questions \n\n\n For Media \n News   Media Contacts   Image Bank \n\n\n Get Involved \n Join an event   Rural Voices   Opinions & Insights\n\nAbout IFAD \n Who we are   Where we work   What we do   Action Areas   Knowledge & Data \n\n\n For Member States \n Member States interactive platform \n\n\n For Investors \n Investors   Finance \n\n\n For Job seekers \n Work with us   Frequently Asked Questions \n\n\n For Media \n News   Media Contacts   Image Bank \n\n\n Get Involved \n Join an event   Rural Voices   Opinions & Insights\n\nAbout IFAD \n Who we are   Where we work   What we do   Action Areas   Knowledge & Data \n\n\n For Member States \n Member States interactive platform \n\n\n For Investors \n Investors   Finance \n\n\n For Job seekers \n Work with us   Frequently Asked Questions \n\n\n For Media \n News   Media Contacts   Image Bank \n\n\n Get Involved \n Join an event   Rural Voices   Opinions & Insights\n\nAbout IFAD \n Who we are   Where we work   What we do   Action Areas   Knowledge & Data \n\n\n For Member States \n Member States interactive platform \n\n\n For Investors \n Investors   Finance \n\n\n For Job seekers \n Work with us   Frequently Asked Questions \n\n\n For Media \n News   Media Contacts   Image Bank \n\n\n Get Involved \n Join an event   Rural Voices   Opinions & Insights\n\nAbout IFAD \n Who we are   Where we work   What we do   Action Areas   Knowledge & Data \n\n\n For Member States \n Member States interactive platform \n\n\n For Investors \n Investors   Finance \n\n\n For Job seekers \n Work with us   Frequently Asked Questions \n\n\n For Media \n News   Media Contacts   Image Bank \n\n\n Get Involved \n Join an event   Rural Voices   Opinions & Insights\n\nAbout IFAD \n Who we are   Where we work   What we do   Action Areas   Knowledge & Data \n\n\n For Member States \n Member States interactive platform \n\n\n For Investors \n Investors   Finance \n\n\n For Job seekers \n Work with us   Frequently Asked Questions \n\n\n For Media \n News   Media Contacts   Image Bank \n\n\n Get Involved \n Join an event   Rural Voices   Opinions & Insights\n\nAbout IFAD \n Who we are   Where we work   What we do   Action Areas   Knowledge & Data \n\n\n For Member States \n Member States interactive platform \n\n\n For Investors \n Investors   Finance \n\n\n For Job seekers \n Work with us   Frequently Asked Questions \n\n\n For Media \n News   Media Contacts   Image Bank \n\n\n Get Involved \n Join an event   Rural Voices   Opinions & Insights\n\nAbout IFAD \n Who we are   Where we work   What we do   Action Areas   Knowledge & Data\n\nWho we are   Where we work   What we do   Action Areas   Knowledge & Data\n\nFor Member States \n Member States interactive platform\n\nMember States interactive platform\n\nFor Investors \n Investors   Finance\n\nInvestors   Finance\n\nFor Job seekers \n Work with us   Frequently Asked Questions\n\nWork with us   Frequently Asked Questions\n\nFor Media \n News   Media Contacts   Image Bank\n\nNews   Media Contacts   Image Bank\n\nGet Involved \n Join an event   Rural Voices   Opinions & Insights\n\nJoin an event   Rural Voices   Opinions & Insights\n\nPlease configure the mobile menu widget below\n      \n\n\n\n\n\n\n\n\n Who we are \n\n\n\n What we do \n\n\n\n Where we work \n\n\n\n Action Areas \n\n\n\n Knowledge & Data \n\n\n\n Get Involved \n\n\n\n News and Stories\n\nPlease configure the mobile menu widget below\n\nWho we are \n\n\n\n What we do \n\n\n\n Where we work \n\n\n\n Action Areas \n\n\n\n Knowledge & Data \n\n\n\n Get Involved \n\n\n\n News and Stories\n\nWho we are \n\n\n\n What we do \n\n\n\n Where we work \n\n\n\n Action Areas \n\n\n\n Knowledge & Data \n\n\n\n Get Involved \n\n\n\n News and Stories\n\nWho we are \n\n\n\n What we do \n\n\n\n Where we work \n\n\n\n Action Areas \n\n\n\n Knowledge & Data \n\n\n\n Get Involved \n\n\n\n News and Stories\n\nWho we are \n\n\n\n What we do \n\n\n\n Where we work \n\n\n\n Action Areas \n\n\n\n Knowledge & Data \n\n\n\n Get Involved \n\n\n\n News and Stories\n\nWho we are \n\n\n\n What we do \n\n\n\n Where we work \n\n\n\n Action Areas \n\n\n\n Knowledge & Data \n\n\n\n Get Involved \n\n\n\n News and Stories\n\nWho we are \n\n\n\n What we do \n\n\n\n Where we work \n\n\n\n Action Areas \n\n\n\n Knowledge & Data \n\n\n\n Get Involved \n\n\n\n News and Stories\n\nWho we are \n\n\n\n What we do \n\n\n\n Where we work \n\n\n\n Action Areas \n\n\n\n Knowledge & Data \n\n\n\n Get Involved \n\n\n\n News and Stories\n\nWho we are \n\n\n\n What we do \n\n\n\n Where we work \n\n\n\n Action Areas \n\n\n\n Knowledge & Data \n\n\n\n Get Involved \n\n\n\n News and Stories\n\nWho we are\n\nWhat we do\n\nWhere we work\n\nAction Areas\n\nKnowledge & Data\n\nGet Involved\n\nNews and Stories\n\nLegal  Privacy notice  Fraudulent job offers  Contact us Stay connected\n\nLegal  Privacy notice  Fraudulent job offers  Contact us Stay connected",
  "entities": {
    "countries": [
      "yemen"
    ],
    "organizations": [
      "un",
      "who"
    ],
    "key_issues": [
      "crisis",
      "country",
      "state",
      "government",
      "approach",
      "strategy",
      "initiative",
      "program",
      "action",
      "context",
      "development",
      "un",
      "ngo",
      "organization"
    ]
  },
  "committee": "Economic and Social Council",
  "topic": "Promoting rural development in Africa"
}