{
  "url": "https://www.ifad.org/en/who-we-are",
  "title": "Who we are",
  "text": "Who we are - IFAD\n\n\n\n\n\n\n\n\n\n\n\n\n\n\n\n\n\n\n\n\n\n\n\n\n\n\n\n\n\n\n\n\n\n\n\nWho we are\n\n\n\n\n\n\n\n\n\n©IFAD/GMB Akash \n\n\n\n\n\n\n\n\n\nIFAD\n\n\n\n\n\n\n\n\n\n\n\n\n is the world’s fund for transforming agriculture, rural economies and food systems.\n\n\n\n\n\n\nWe invest \n\n\n\n\n\n\n\n\n\n\n\nin rural people, who are often the world’s poorest and most vulnerable.\n\n\n\n\n\n\n\n\n\n\n\n\n\n\n\n\n\n\n\n\n\n\n\n\n\n\nThe road to a better future runs through rural areas\n\n\n\n\n\n\n\n\n\n\nAt the International Fund for Agricultural Development, we envision vibrant, inclusive and sustainable rural communities, where people live free from poverty and hunger. The best way to achieve this is by investing in small scale rural producers.\nWith these investments, rural people can take charge of their own future and produce enough nutritious food for their communities.\nBy leading their own development, the change is long-lasting.\n\n\n\n\n\n See more about the world we envisage\n\n\n\n \n\n\n\n\n\n\n\n\n\n\n\n\n\n\n\n\n\n\n\n\n\n\n\n\n\n\nTransforming rural communities for almost 50 years\n\n\n\n\n\n\n\n\n\n\n\nIFAD was established in the 1970s in response to a global food crises. \nSince then we have supported millions of rural people pull themselves out of poverty and thrive.\n\n\n\n\n\n Learn more about our history\n\n\n\n \n\n\n\n\n\n\n\n\n\n\n\n\n\n\n\n\n\n\n\n\n\n\n\n\n\n\nCatalyzing funds for greater impact\n\n\n\n\n\n\n\n\n\n\n\nWe use the contribution from our Member States to generate and assemble additional finance for rural people. \n\n\n\nAs part of this we adhere to the highest transparency and governance standards.\n\n\n\n\n\n\n\n\n How we finance our life-changing work\n\n\n\n \n\n\n\n\n\n\n\n\n\n\n\n\n\n\n\n\n\n\n\n\n\n\n\n\n\n\nCollaborating for lasting change\n\n\n\n\n\n\n\n\n\n\n\nOnly by working together can we ensure scalable impact and achieve the Sustainable Development Goals. That's why IFAD works with a flourishing ecosystem of partners - from foundations to farmers' organizations.\n\n\n\n\n\n Browse all our partners\n\n\n\n \n\n\n\n\n\n\n\n\n\n\n\n\n\n\n\n\n\n\n\n\n\n\n\n\n\n\nAdvocating for rural people\n\n\n\n\n\n\n\n\n\n\n\nOur experts work alongside governments to develop projects so rural people can thrive.\nOur leadership team partners with stakeholders to scale up this change.\nOur President ensures that the world knows the invaluable contribution rural people make to each of our lives. \n\n\n\n\n\n\n\n\n\n\n\nKeep exploring\n\n\n\n\n\n\n\n\n\n\n\n\n\n\n\n\n Where we work Spanning five regions and 92 countries, IFAD works where poverty and hunger are deepest. \n\n  Explore more \n           \n \n\n\n\n\n\n\n\n\n\n\n\n\n\n\n\n\n\n What we do Simply put, IFAD invests in rural people. We do this by financing programmes, measuring results, innovating and working with rural people themselves. \n\n  Explore more \n           \n \n\n\n\n\n\n\n\n\n\n\n\n\n\n\n\n\n Action areas From building resilience to empowering rural people and protecting the environment, explore our main areas of work. \n\n  Explore more \n           \n \n\n\n\n\n\n\n\n\n\n\n\n\n\n\n\n       Please configure the desktop menu widget below\n      \n\n\n\n\n\n\n\n\n About IFAD \n Who we are   Where we work   What we do   Action Areas   Knowledge & Data \n\n\n For Member States \n Member States interactive platform \n\n\n For Investors \n Investors   Finance \n\n\n For Job seekers \n Work with us   Frequently Asked Questions \n\n\n For Media \n News   Media Contacts   Image Bank \n\n\n Get Involved \n Join an event   Rural Voices   Opinions & Insights \n\n\n\n\n\n\n\n\n\n\n\n\n\n       Please configure the mobile menu widget below\n      \n\n\n\n\n\n\n\n\n Who we are \n\n\n\n What we do \n\n\n\n Where we work \n\n\n\n Action Areas \n\n\n\n Knowledge & Data \n\n\n\n Get Involved \n\n\n\n News and Stories \n\n\n\n\n\n\n\n\n\n\n\n\n\n  \n Legal  Privacy notice  Fraudulent job offers  Contact us Stay connected\n\n\n\n  \n\n  \n\n  \n\n  \n\n  \n\n \n\n\n\n\n\n\n\n\nHidden\n\nWho we are - IFAD\n\n\n\n\n\n\n\n\n\n\n\n\n\n\n\n\n\n\n\n\n\n\n\n\n\n\n\n\n\n\n\n\n\n\n\nWho we are\n\n\n\n\n\n\n\n\n\n©IFAD/GMB Akash \n\n\n\n\n\n\n\n\n\nIFAD\n\n\n\n\n\n\n\n\n\n\n\n\n is the world’s fund for transforming agriculture, rural economies and food systems.\n\n\n\n\n\n\nWe invest \n\n\n\n\n\n\n\n\n\n\n\nin rural people, who are often the world’s poorest and most vulnerable.\n\n\n\n\n\n\n\n\n\n\n\n\n\n\n\n\n\n\n\n\n\n\n\n\n\n\nThe road to a better future runs through rural areas\n\n\n\n\n\n\n\n\n\n\nAt the International Fund for Agricultural Development, we envision vibrant, inclusive and sustainable rural communities, where people live free from poverty and hunger. The best way to achieve this is by investing in small scale rural producers.\nWith these investments, rural people can take charge of their own future and produce enough nutritious food for their communities.\nBy leading their own development, the change is long-lasting.\n\n\n\n\n\n See more about the world we envisage\n\n\n\n \n\n\n\n\n\n\n\n\n\n\n\n\n\n\n\n\n\n\n\n\n\n\n\n\n\n\nTransforming rural communities for almost 50 years\n\n\n\n\n\n\n\n\n\n\n\nIFAD was established in the 1970s in response to a global food crises. \nSince then we have supported millions of rural people pull themselves out of poverty and thrive.\n\n\n\n\n\n Learn more about our history\n\n\n\n \n\n\n\n\n\n\n\n\n\n\n\n\n\n\n\n\n\n\n\n\n\n\n\n\n\n\nCatalyzing funds for greater impact\n\n\n\n\n\n\n\n\n\n\n\nWe use the contribution from our Member States to generate and assemble additional finance for rural people. \n\n\n\nAs part of this we adhere to the highest transparency and governance standards.\n\n\n\n\n\n\n\n\n How we finance our life-changing work\n\n\n\n \n\n\n\n\n\n\n\n\n\n\n\n\n\n\n\n\n\n\n\n\n\n\n\n\n\n\nCollaborating for lasting change\n\n\n\n\n\n\n\n\n\n\n\nOnly by working together can we ensure scalable impact and achieve the Sustainable Development Goals. That's why IFAD works with a flourishing ecosystem of partners - from foundations to farmers' organizations.\n\n\n\n\n\n Browse all our partners\n\n\n\n \n\n\n\n\n\n\n\n\n\n\n\n\n\n\n\n\n\n\n\n\n\n\n\n\n\n\nAdvocating for rural people\n\n\n\n\n\n\n\n\n\n\n\nOur experts work alongside governments to develop projects so rural people can thrive.\nOur leadership team partners with stakeholders to scale up this change.\nOur President ensures that the world knows the invaluable contribution rural people make to each of our lives. \n\n\n\n\n\n\n\n\n\n\n\nKeep exploring\n\n\n\n\n\n\n\n\n\n\n\n\n\n\n\n\n Where we work Spanning five regions and 92 countries, IFAD works where poverty and hunger are deepest. \n\n  Explore more \n           \n \n\n\n\n\n\n\n\n\n\n\n\n\n\n\n\n\n\n What we do Simply put, IFAD invests in rural people. We do this by financing programmes, measuring results, innovating and working with rural people themselves. \n\n  Explore more \n           \n \n\n\n\n\n\n\n\n\n\n\n\n\n\n\n\n\n Action areas From building resilience to empowering rural people and protecting the environment, explore our main areas of work. \n\n  Explore more \n           \n \n\n\n\n\n\n\n\n\n\n\n\n\n\n\n\n       Please configure the desktop menu widget below\n      \n\n\n\n\n\n\n\n\n About IFAD \n Who we are   Where we work   What we do   Action Areas   Knowledge & Data \n\n\n For Member States \n Member States interactive platform \n\n\n For Investors \n Investors   Finance \n\n\n For Job seekers \n Work with us   Frequently Asked Questions \n\n\n For Media \n News   Media Contacts   Image Bank \n\n\n Get Involved \n Join an event   Rural Voices   Opinions & Insights \n\n\n\n\n\n\n\n\n\n\n\n\n\n       Please configure the mobile menu widget below\n      \n\n\n\n\n\n\n\n\n Who we are \n\n\n\n What we do \n\n\n\n Where we work \n\n\n\n Action Areas \n\n\n\n Knowledge & Data \n\n\n\n Get Involved \n\n\n\n News and Stories \n\n\n\n\n\n\n\n\n\n\n\n\n\n  \n Legal  Privacy notice  Fraudulent job offers  Contact us Stay connected\n\n\n\n  \n\n  \n\n  \n\n  \n\n  \n\n \n\n\n\n\n\n\n\n\nHidden\n\nWho we are - IFAD\n\n\n\n\n\n\n\n\n\n\n\n\n\n\n\n\n\n\n\n\n\n\n\n\n\n\n\n\n\n\n\n\n\n\n\nWho we are\n\n\n\n\n\n\n\n\n\n©IFAD/GMB Akash \n\n\n\n\n\n\n\n\n\nIFAD\n\n\n\n\n\n\n\n\n\n\n\n\n is the world’s fund for transforming agriculture, rural economies and food systems.\n\n\n\n\n\n\nWe invest \n\n\n\n\n\n\n\n\n\n\n\nin rural people, who are often the world’s poorest and most vulnerable.\n\n\n\n\n\n\n\n\n\n\n\n\n\n\n\n\n\n\n\n\n\n\n\n\n\n\nThe road to a better future runs through rural areas\n\n\n\n\n\n\n\n\n\n\nAt the International Fund for Agricultural Development, we envision vibrant, inclusive and sustainable rural communities, where people live free from poverty and hunger. The best way to achieve this is by investing in small scale rural producers.\nWith these investments, rural people can take charge of their own future and produce enough nutritious food for their communities.\nBy leading their own development, the change is long-lasting.\n\n\n\n\n\n See more about the world we envisage\n\n\n\n \n\n\n\n\n\n\n\n\n\n\n\n\n\n\n\n\n\n\n\n\n\n\n\n\n\n\nTransforming rural communities for almost 50 years\n\n\n\n\n\n\n\n\n\n\n\nIFAD was established in the 1970s in response to a global food crises. \nSince then we have supported millions of rural people pull themselves out of poverty and thrive.\n\n\n\n\n\n Learn more about our history\n\n\n\n \n\n\n\n\n\n\n\n\n\n\n\n\n\n\n\n\n\n\n\n\n\n\n\n\n\n\nCatalyzing funds for greater impact\n\n\n\n\n\n\n\n\n\n\n\nWe use the contribution from our Member States to generate and assemble additional finance for rural people. \n\n\n\nAs part of this we adhere to the highest transparency and governance standards.\n\n\n\n\n\n\n\n\n How we finance our life-changing work\n\n\n\n \n\n\n\n\n\n\n\n\n\n\n\n\n\n\n\n\n\n\n\n\n\n\n\n\n\n\nCollaborating for lasting change\n\n\n\n\n\n\n\n\n\n\n\nOnly by working together can we ensure scalable impact and achieve the Sustainable Development Goals. That's why IFAD works with a flourishing ecosystem of partners - from foundations to farmers' organizations.\n\n\n\n\n\n Browse all our partners\n\n\n\n \n\n\n\n\n\n\n\n\n\n\n\n\n\n\n\n\n\n\n\n\n\n\n\n\n\n\nAdvocating for rural people\n\n\n\n\n\n\n\n\n\n\n\nOur experts work alongside governments to develop projects so rural people can thrive.\nOur leadership team partners with stakeholders to scale up this change.\nOur President ensures that the world knows the invaluable contribution rural people make to each of our lives. \n\n\n\n\n\n\n\n\n\n\n\nKeep exploring\n\n\n\n\n\n\n\n\n\n\n\n\n\n\n\n\n Where we work Spanning five regions and 92 countries, IFAD works where poverty and hunger are deepest. \n\n  Explore more \n           \n \n\n\n\n\n\n\n\n\n\n\n\n\n\n\n\n\n\n What we do Simply put, IFAD invests in rural people. We do this by financing programmes, measuring results, innovating and working with rural people themselves. \n\n  Explore more \n           \n \n\n\n\n\n\n\n\n\n\n\n\n\n\n\n\n\n Action areas From building resilience to empowering rural people and protecting the environment, explore our main areas of work. \n\n  Explore more \n           \n \n\n\n\n\n\n\n\n\n\n\n\n\n\n\n\n       Please configure the desktop menu widget below\n      \n\n\n\n\n\n\n\n\n About IFAD \n Who we are   Where we work   What we do   Action Areas   Knowledge & Data \n\n\n For Member States \n Member States interactive platform \n\n\n For Investors \n Investors   Finance \n\n\n For Job seekers \n Work with us   Frequently Asked Questions \n\n\n For Media \n News   Media Contacts   Image Bank \n\n\n Get Involved \n Join an event   Rural Voices   Opinions & Insights \n\n\n\n\n\n\n\n\n\n\n\n\n\n       Please configure the mobile menu widget below\n      \n\n\n\n\n\n\n\n\n Who we are \n\n\n\n What we do \n\n\n\n Where we work \n\n\n\n Action Areas \n\n\n\n Knowledge & Data \n\n\n\n Get Involved \n\n\n\n News and Stories \n\n\n\n\n\n\n\n\n\n\n\n\n\n  \n Legal  Privacy notice  Fraudulent job offers  Contact us Stay connected\n\n\n\n  \n\n  \n\n  \n\n  \n\n  \n\n \n\n\n\n\n\n\n\n\nHidden\n\nWho we are\n\n\n\n\n\n\n\n\n\n©IFAD/GMB Akash \n\n\n\n\n\n\n\n\n\nIFAD\n\n\n\n\n\n\n\n\n\n\n\n\n is the world’s fund for transforming agriculture, rural economies and food systems.\n\n\n\n\n\n\nWe invest \n\n\n\n\n\n\n\n\n\n\n\nin rural people, who are often the world’s poorest and most vulnerable.\n\n\n\n\n\n\n\n\n\n\n\n\n\n\n\n\n\n\n\n\n\n\n\n\n\n\nThe road to a better future runs through rural areas\n\n\n\n\n\n\n\n\n\n\nAt the International Fund for Agricultural Development, we envision vibrant, inclusive and sustainable rural communities, where people live free from poverty and hunger. The best way to achieve this is by investing in small scale rural producers.\nWith these investments, rural people can take charge of their own future and produce enough nutritious food for their communities.\nBy leading their own development, the change is long-lasting.\n\n\n\n\n\n See more about the world we envisage\n\n\n\n \n\n\n\n\n\n\n\n\n\n\n\n\n\n\n\n\n\n\n\n\n\n\n\n\n\n\nTransforming rural communities for almost 50 years\n\n\n\n\n\n\n\n\n\n\n\nIFAD was established in the 1970s in response to a global food crises. \nSince then we have supported millions of rural people pull themselves out of poverty and thrive.\n\n\n\n\n\n Learn more about our history\n\n\n\n \n\n\n\n\n\n\n\n\n\n\n\n\n\n\n\n\n\n\n\n\n\n\n\n\n\n\nCatalyzing funds for greater impact\n\n\n\n\n\n\n\n\n\n\n\nWe use the contribution from our Member States to generate and assemble additional finance for rural people. \n\n\n\nAs part of this we adhere to the highest transparency and governance standards.\n\n\n\n\n\n\n\n\n How we finance our life-changing work\n\n\n\n \n\n\n\n\n\n\n\n\n\n\n\n\n\n\n\n\n\n\n\n\n\n\n\n\n\n\nCollaborating for lasting change\n\n\n\n\n\n\n\n\n\n\n\nOnly by working together can we ensure scalable impact and achieve the Sustainable Development Goals. That's why IFAD works with a flourishing ecosystem of partners - from foundations to farmers' organizations.\n\n\n\n\n\n Browse all our partners\n\n\n\n \n\n\n\n\n\n\n\n\n\n\n\n\n\n\n\n\n\n\n\n\n\n\n\n\n\n\nAdvocating for rural people\n\n\n\n\n\n\n\n\n\n\n\nOur experts work alongside governments to develop projects so rural people can thrive.\nOur leadership team partners with stakeholders to scale up this change.\nOur President ensures that the world knows the invaluable contribution rural people make to each of our lives. \n\n\n\n\n\n\n\n\n\n\n\nKeep exploring\n\n\n\n\n\n\n\n\n\n\n\n\n\n\n\n\n Where we work Spanning five regions and 92 countries, IFAD works where poverty and hunger are deepest. \n\n  Explore more \n           \n \n\n\n\n\n\n\n\n\n\n\n\n\n\n\n\n\n\n What we do Simply put, IFAD invests in rural people. We do this by financing programmes, measuring results, innovating and working with rural people themselves. \n\n  Explore more \n           \n \n\n\n\n\n\n\n\n\n\n\n\n\n\n\n\n\n Action areas From building resilience to empowering rural people and protecting the environment, explore our main areas of work. \n\n  Explore more \n           \n \n\n\n\n\n\n\n\n\n\n\n\n\n\n\n\n       Please configure the desktop menu widget below\n      \n\n\n\n\n\n\n\n\n About IFAD \n Who we are   Where we work   What we do   Action Areas   Knowledge & Data \n\n\n For Member States \n Member States interactive platform \n\n\n For Investors \n Investors   Finance \n\n\n For Job seekers \n Work with us   Frequently Asked Questions \n\n\n For Media \n News   Media Contacts   Image Bank \n\n\n Get Involved \n Join an event   Rural Voices   Opinions & Insights \n\n\n\n\n\n\n\n\n\n\n\n\n\n       Please configure the mobile menu widget below\n      \n\n\n\n\n\n\n\n\n Who we are \n\n\n\n What we do \n\n\n\n Where we work \n\n\n\n Action Areas \n\n\n\n Knowledge & Data \n\n\n\n Get Involved \n\n\n\n News and Stories \n\n\n\n\n\n\n\n\n\n\n\n\n\n  \n Legal  Privacy notice  Fraudulent job offers  Contact us Stay connected\n\nWho we are\n\n\n\n\n\n\n\n\n\n©IFAD/GMB Akash \n\n\n\n\n\n\n\n\n\nIFAD\n\n\n\n\n\n\n\n\n\n\n\n\n is the world’s fund for transforming agriculture, rural economies and food systems.\n\n\n\n\n\n\nWe invest \n\n\n\n\n\n\n\n\n\n\n\nin rural people, who are often the world’s poorest and most vulnerable.\n\n\n\n\n\n\n\n\n\n\n\n\n\n\n\n\n\n\n\n\n\n\n\n\n\n\nThe road to a better future runs through rural areas\n\n\n\n\n\n\n\n\n\n\nAt the International Fund for Agricultural Development, we envision vibrant, inclusive and sustainable rural communities, where people live free from poverty and hunger. The best way to achieve this is by investing in small scale rural producers.\nWith these investments, rural people can take charge of their own future and produce enough nutritious food for their communities.\nBy leading their own development, the change is long-lasting.\n\n\n\n\n\n See more about the world we envisage\n\n\n\n \n\n\n\n\n\n\n\n\n\n\n\n\n\n\n\n\n\n\n\n\n\n\n\n\n\n\nTransforming rural communities for almost 50 years\n\n\n\n\n\n\n\n\n\n\n\nIFAD was established in the 1970s in response to a global food crises. \nSince then we have supported millions of rural people pull themselves out of poverty and thrive.\n\n\n\n\n\n Learn more about our history\n\n\n\n \n\n\n\n\n\n\n\n\n\n\n\n\n\n\n\n\n\n\n\n\n\n\n\n\n\n\nCatalyzing funds for greater impact\n\n\n\n\n\n\n\n\n\n\n\nWe use the contribution from our Member States to generate and assemble additional finance for rural people. \n\n\n\nAs part of this we adhere to the highest transparency and governance standards.\n\n\n\n\n\n\n\n\n How we finance our life-changing work\n\n\n\n \n\n\n\n\n\n\n\n\n\n\n\n\n\n\n\n\n\n\n\n\n\n\n\n\n\n\nCollaborating for lasting change\n\n\n\n\n\n\n\n\n\n\n\nOnly by working together can we ensure scalable impact and achieve the Sustainable Development Goals. That's why IFAD works with a flourishing ecosystem of partners - from foundations to farmers' organizations.\n\n\n\n\n\n Browse all our partners\n\n\n\n \n\n\n\n\n\n\n\n\n\n\n\n\n\n\n\n\n\n\n\n\n\n\n\n\n\n\nAdvocating for rural people\n\n\n\n\n\n\n\n\n\n\n\nOur experts work alongside governments to develop projects so rural people can thrive.\nOur leadership team partners with stakeholders to scale up this change.\nOur President ensures that the world knows the invaluable contribution rural people make to each of our lives. \n\n\n\n\n\n\n\n\n\n\n\nKeep exploring\n\n\n\n\n\n\n\n\n\n\n\n\n\n\n\n\n Where we work Spanning five regions and 92 countries, IFAD works where poverty and hunger are deepest. \n\n  Explore more \n           \n \n\n\n\n\n\n\n\n\n\n\n\n\n\n\n\n\n\n What we do Simply put, IFAD invests in rural people. We do this by financing programmes, measuring results, innovating and working with rural people themselves. \n\n  Explore more \n           \n \n\n\n\n\n\n\n\n\n\n\n\n\n\n\n\n\n Action areas From building resilience to empowering rural people and protecting the environment, explore our main areas of work. \n\n  Explore more \n           \n \n\n\n\n\n\n\n\n\n\n\n\n\n\n\n\n       Please configure the desktop menu widget below\n      \n\n\n\n\n\n\n\n\n About IFAD \n Who we are   Where we work   What we do   Action Areas   Knowledge & Data \n\n\n For Member States \n Member States interactive platform \n\n\n For Investors \n Investors   Finance \n\n\n For Job seekers \n Work with us   Frequently Asked Questions \n\n\n For Media \n News   Media Contacts   Image Bank \n\n\n Get Involved \n Join an event   Rural Voices   Opinions & Insights \n\n\n\n\n\n\n\n\n\n\n\n\n\n       Please configure the mobile menu widget below\n      \n\n\n\n\n\n\n\n\n Who we are \n\n\n\n What we do \n\n\n\n Where we work \n\n\n\n Action Areas \n\n\n\n Knowledge & Data \n\n\n\n Get Involved \n\n\n\n News and Stories \n\n\n\n\n\n\n\n\n\n\n\n\n\n  \n Legal  Privacy notice  Fraudulent job offers  Contact us Stay connected\n\nWho we are\n\n\n\n\n\n\n\n\n\n©IFAD/GMB Akash \n\n\n\n\n\n\n\n\n\nIFAD\n\n\n\n\n\n\n\n\n\n\n\n\n is the world’s fund for transforming agriculture, rural economies and food systems.\n\n\n\n\n\n\nWe invest \n\n\n\n\n\n\n\n\n\n\n\nin rural people, who are often the world’s poorest and most vulnerable.\n\n\n\n\n\n\n\n\n\n\n\n\n\n\n\n\n\n\n\n\n\n\n\n\n\n\nThe road to a better future runs through rural areas\n\n\n\n\n\n\n\n\n\n\nAt the International Fund for Agricultural Development, we envision vibrant, inclusive and sustainable rural communities, where people live free from poverty and hunger. The best way to achieve this is by investing in small scale rural producers.\nWith these investments, rural people can take charge of their own future and produce enough nutritious food for their communities.\nBy leading their own development, the change is long-lasting.\n\n\n\n\n\n See more about the world we envisage\n\n\n\n \n\n\n\n\n\n\n\n\n\n\n\n\n\n\n\n\n\n\n\n\n\n\n\n\n\n\nTransforming rural communities for almost 50 years\n\n\n\n\n\n\n\n\n\n\n\nIFAD was established in the 1970s in response to a global food crises. \nSince then we have supported millions of rural people pull themselves out of poverty and thrive.\n\n\n\n\n\n Learn more about our history\n\n\n\n \n\n\n\n\n\n\n\n\n\n\n\n\n\n\n\n\n\n\n\n\n\n\n\n\n\n\nCatalyzing funds for greater impact\n\n\n\n\n\n\n\n\n\n\n\nWe use the contribution from our Member States to generate and assemble additional finance for rural people. \n\n\n\nAs part of this we adhere to the highest transparency and governance standards.\n\n\n\n\n\n\n\n\n How we finance our life-changing work\n\n\n\n \n\n\n\n\n\n\n\n\n\n\n\n\n\n\n\n\n\n\n\n\n\n\n\n\n\n\nCollaborating for lasting change\n\n\n\n\n\n\n\n\n\n\n\nOnly by working together can we ensure scalable impact and achieve the Sustainable Development Goals. That's why IFAD works with a flourishing ecosystem of partners - from foundations to farmers' organizations.\n\n\n\n\n\n Browse all our partners\n\n\n\n \n\n\n\n\n\n\n\n\n\n\n\n\n\n\n\n\n\n\n\n\n\n\n\n\n\n\nAdvocating for rural people\n\n\n\n\n\n\n\n\n\n\n\nOur experts work alongside governments to develop projects so rural people can thrive.\nOur leadership team partners with stakeholders to scale up this change.\nOur President ensures that the world knows the invaluable contribution rural people make to each of our lives. \n\n\n\n\n\n\n\n\n\n\n\nKeep exploring\n\n\n\n\n\n\n\n\n\n\n\n\n\n\n\n\n Where we work Spanning five regions and 92 countries, IFAD works where poverty and hunger are deepest. \n\n  Explore more \n           \n \n\n\n\n\n\n\n\n\n\n\n\n\n\n\n\n\n\n What we do Simply put, IFAD invests in rural people. We do this by financing programmes, measuring results, innovating and working with rural people themselves. \n\n  Explore more \n           \n \n\n\n\n\n\n\n\n\n\n\n\n\n\n\n\n\n Action areas From building resilience to empowering rural people and protecting the environment, explore our main areas of work. \n\n  Explore more\n\nWho we are\n\nWho we are\n\nWho we are\n\nWho we are\n\n©IFAD/GMB Akash\n\n©IFAD/GMB Akash\n\n©IFAD/GMB Akash\n\nIFAD\n\n\n\n\n\n\n\n\n\n\n\n\n is the world’s fund for transforming agriculture, rural economies and food systems.\n\n\n\n\n\n\nWe invest \n\n\n\n\n\n\n\n\n\n\n\nin rural people, who are often the world’s poorest and most vulnerable.\n\nIFAD\n\n\n\n\n\n\n\n\n\n\n\n\n is the world’s fund for transforming agriculture, rural economies and food systems.\n\n\n\n\n\n\nWe invest \n\n\n\n\n\n\n\n\n\n\n\nin rural people, who are often the world’s poorest and most vulnerable.\n\nIFAD\n\n\n\n\n\n\n\n\n\n\n\n\n is the world’s fund for transforming agriculture, rural economies and food systems.\n\nIFAD\n\nIFAD\n\nis the world’s fund for transforming agriculture, rural economies and food systems.\n\nis the world’s fund for transforming agriculture, rural economies and food systems.\n\nWe invest \n\n\n\n\n\n\n\n\n\n\n\nin rural people, who are often the world’s poorest and most vulnerable.\n\nWe invest\n\nWe invest\n\nin rural people, who are often the world’s poorest and most vulnerable.\n\nin rural people, who are often the world’s poorest and most vulnerable.\n\nThe road to a better future runs through rural areas\n\n\n\n\n\n\n\n\n\n\nAt the International Fund for Agricultural Development, we envision vibrant, inclusive and sustainable rural communities, where people live free from poverty and hunger. The best way to achieve this is by investing in small scale rural producers.\nWith these investments, rural people can take charge of their own future and produce enough nutritious food for their communities.\nBy leading their own development, the change is long-lasting.\n\n\n\n\n\n See more about the world we envisage\n\n\n\n \n\n\n\n\n\n\n\n\n\n\n\n\n\n\n\n\n\n\n\n\n\n\n\n\n\n\nTransforming rural communities for almost 50 years\n\n\n\n\n\n\n\n\n\n\n\nIFAD was established in the 1970s in response to a global food crises. \nSince then we have supported millions of rural people pull themselves out of poverty and thrive.\n\n\n\n\n\n Learn more about our history\n\n\n\n \n\n\n\n\n\n\n\n\n\n\n\n\n\n\n\n\n\n\n\n\n\n\n\n\n\n\nCatalyzing funds for greater impact\n\n\n\n\n\n\n\n\n\n\n\nWe use the contribution from our Member States to generate and assemble additional finance for rural people. \n\n\n\nAs part of this we adhere to the highest transparency and governance standards.\n\n\n\n\n\n\n\n\n How we finance our life-changing work\n\n\n\n \n\n\n\n\n\n\n\n\n\n\n\n\n\n\n\n\n\n\n\n\n\n\n\n\n\n\nCollaborating for lasting change\n\n\n\n\n\n\n\n\n\n\n\nOnly by working together can we ensure scalable impact and achieve the Sustainable Development Goals. That's why IFAD works with a flourishing ecosystem of partners - from foundations to farmers' organizations.\n\n\n\n\n\n Browse all our partners\n\n\n\n \n\n\n\n\n\n\n\n\n\n\n\n\n\n\n\n\n\n\n\n\n\n\n\n\n\n\nAdvocating for rural people\n\n\n\n\n\n\n\n\n\n\n\nOur experts work alongside governments to develop projects so rural people can thrive.\nOur leadership team partners with stakeholders to scale up this change.\nOur President ensures that the world knows the invaluable contribution rural people make to each of our lives.\n\nThe road to a better future runs through rural areas\n\n\n\n\n\n\n\n\n\n\nAt the International Fund for Agricultural Development, we envision vibrant, inclusive and sustainable rural communities, where people live free from poverty and hunger. The best way to achieve this is by investing in small scale rural producers.\nWith these investments, rural people can take charge of their own future and produce enough nutritious food for their communities.\nBy leading their own development, the change is long-lasting.\n\n\n\n\n\n See more about the world we envisage\n\nThe road to a better future runs through rural areas\n\n\n\n\n\n\n\n\n\n\nAt the International Fund for Agricultural Development, we envision vibrant, inclusive and sustainable rural communities, where people live free from poverty and hunger. The best way to achieve this is by investing in small scale rural producers.\nWith these investments, rural people can take charge of their own future and produce enough nutritious food for their communities.\nBy leading their own development, the change is long-lasting.\n\n\n\n\n\n See more about the world we envisage\n\nThe road to a better future runs through rural areas\n\nThe road to a better future runs through rural areas\n\nThe road to a better future runs through rural areas\n\nThe road to a better future runs through rural areas\n\nThe road to a better future runs through rural areas\n\nThe road to a better future runs through rural areas\n\nAt the International Fund for Agricultural Development, we envision vibrant, inclusive and sustainable rural communities, where people live free from poverty and hunger. The best way to achieve this is by investing in small scale rural producers.\nWith these investments, rural people can take charge of their own future and produce enough nutritious food for their communities.\nBy leading their own development, the change is long-lasting.\n\n\n\n\n\n See more about the world we envisage\n\nAt the International Fund for Agricultural Development, we envision vibrant, inclusive and sustainable rural communities, where people live free from poverty and hunger. The best way to achieve this is by investing in small scale rural producers.\nWith these investments, rural people can take charge of their own future and produce enough nutritious food for their communities.\nBy leading their own development, the change is long-lasting.\n\nAt the International Fund for Agricultural Development, we envision vibrant, inclusive and sustainable rural communities, where people live free from poverty and hunger. The best way to achieve this is by investing in small scale rural producers.\nWith these investments, rural people can take charge of their own future and produce enough nutritious food for their communities.\nBy leading their own development, the change is long-lasting.\n\nAt the International Fund for Agricultural Development, we envision vibrant, inclusive and sustainable rural communities, where people live free from poverty and hunger. The best way to achieve this is by investing in small scale rural producers.\nWith these investments, rural people can take charge of their own future and produce enough nutritious food for their communities.\nBy leading their own development, the change is long-lasting.\n\nAt the International Fund for Agricultural Development, we envision vibrant, inclusive and sustainable rural communities, where people live free from poverty and hunger. The best way to achieve this is by investing in small scale rural producers.\n\nWith these investments, rural people can take charge of their own future and produce enough nutritious food for their communities.\n\nBy leading their own development, the change is long-lasting.\n\nSee more about the world we envisage\n\nSee more about the world we envisage\n\nTransforming rural communities for almost 50 years\n\n\n\n\n\n\n\n\n\n\n\nIFAD was established in the 1970s in response to a global food crises. \nSince then we have supported millions of rural people pull themselves out of poverty and thrive.\n\n\n\n\n\n Learn more about our history\n\nTransforming rural communities for almost 50 years\n\n\n\n\n\n\n\n\n\n\n\nIFAD was established in the 1970s in response to a global food crises. \nSince then we have supported millions of rural people pull themselves out of poverty and thrive.\n\n\n\n\n\n Learn more about our history\n\nTransforming rural communities for almost 50 years\n\nTransforming rural communities for almost 50 years\n\nTransforming rural communities for almost 50 years\n\nTransforming rural communities for almost 50 years\n\nTransforming rural communities for almost 50 years\n\nTransforming rural communities for almost 50 years\n\nIFAD was established in the 1970s in response to a global food crises. \nSince then we have supported millions of rural people pull themselves out of poverty and thrive.\n\n\n\n\n\n Learn more about our history\n\nIFAD was established in the 1970s in response to a global food crises. \nSince then we have supported millions of rural people pull themselves out of poverty and thrive.\n\nIFAD was established in the 1970s in response to a global food crises. \nSince then we have supported millions of rural people pull themselves out of poverty and thrive.\n\nIFAD was established in the 1970s in response to a global food crises. \nSince then we have supported millions of rural people pull themselves out of poverty and thrive.\n\nIFAD was established in the 1970s in response to a global food crises.\n\nSince then we have supported millions of rural people pull themselves out of poverty and thrive.\n\nLearn more about our history\n\nLearn more about our history\n\nCatalyzing funds for greater impact\n\n\n\n\n\n\n\n\n\n\n\nWe use the contribution from our Member States to generate and assemble additional finance for rural people. \n\n\n\nAs part of this we adhere to the highest transparency and governance standards.\n\n\n\n\n\n\n\n\n How we finance our life-changing work\n\nCatalyzing funds for greater impact\n\n\n\n\n\n\n\n\n\n\n\nWe use the contribution from our Member States to generate and assemble additional finance for rural people. \n\n\n\nAs part of this we adhere to the highest transparency and governance standards.\n\n\n\n\n\n\n\n\n How we finance our life-changing work\n\nCatalyzing funds for greater impact\n\nCatalyzing funds for greater impact\n\nCatalyzing funds for greater impact\n\nCatalyzing funds for greater impact\n\nCatalyzing funds for greater impact\n\nCatalyzing funds for greater impact\n\nWe use the contribution from our Member States to generate and assemble additional finance for rural people. \n\n\n\nAs part of this we adhere to the highest transparency and governance standards.\n\n\n\n\n\n\n\n\n How we finance our life-changing work\n\nWe use the contribution from our Member States to generate and assemble additional finance for rural people. \n\n\n\nAs part of this we adhere to the highest transparency and governance standards.\n\nWe use the contribution from our Member States to generate and assemble additional finance for rural people. \n\n\n\nAs part of this we adhere to the highest transparency and governance standards.\n\nWe use the contribution from our Member States to generate and assemble additional finance for rural people. \n\n\n\nAs part of this we adhere to the highest transparency and governance standards.\n\nWe use the contribution from our Member States to generate and assemble additional finance for rural people.\n\nAs part of this we adhere to the highest transparency and governance standards.\n\nAs part of this we adhere to the highest transparency and governance standards.\n\nAs part of this we adhere to the highest transparency and governance standards.\n\nAs part of this we adhere to the highest transparency and governance standards.\n\nHow we finance our life-changing work\n\nHow we finance our life-changing work\n\nCollaborating for lasting change\n\n\n\n\n\n\n\n\n\n\n\nOnly by working together can we ensure scalable impact and achieve the Sustainable Development Goals. That's why IFAD works with a flourishing ecosystem of partners - from foundations to farmers' organizations.\n\n\n\n\n\n Browse all our partners\n\nCollaborating for lasting change\n\n\n\n\n\n\n\n\n\n\n\nOnly by working together can we ensure scalable impact and achieve the Sustainable Development Goals. That's why IFAD works with a flourishing ecosystem of partners - from foundations to farmers' organizations.\n\n\n\n\n\n Browse all our partners\n\nCollaborating for lasting change\n\nCollaborating for lasting change\n\nCollaborating for lasting change\n\nCollaborating for lasting change\n\nCollaborating for lasting change\n\nCollaborating for lasting change\n\nOnly by working together can we ensure scalable impact and achieve the Sustainable Development Goals. That's why IFAD works with a flourishing ecosystem of partners - from foundations to farmers' organizations.\n\n\n\n\n\n Browse all our partners\n\nOnly by working together can we ensure scalable impact and achieve the Sustainable Development Goals. That's why IFAD works with a flourishing ecosystem of partners - from foundations to farmers' organizations.\n\nOnly by working together can we ensure scalable impact and achieve the Sustainable Development Goals. That's why IFAD works with a flourishing ecosystem of partners - from foundations to farmers' organizations.\n\nOnly by working together can we ensure scalable impact and achieve the Sustainable Development Goals. That's why IFAD works with a flourishing ecosystem of partners - from foundations to farmers' organizations.\n\nOnly by working together can we ensure scalable impact and achieve the Sustainable Development Goals. That's why IFAD works with a flourishing ecosystem of partners - from foundations to farmers' organizations.\n\nBrowse all our partners\n\nBrowse all our partners\n\nAdvocating for rural people\n\n\n\n\n\n\n\n\n\n\n\nOur experts work alongside governments to develop projects so rural people can thrive.\nOur leadership team partners with stakeholders to scale up this change.\nOur President ensures that the world knows the invaluable contribution rural people make to each of our lives.\n\nAdvocating for rural people\n\n\n\n\n\n\n\n\n\n\n\nOur experts work alongside governments to develop projects so rural people can thrive.\nOur leadership team partners with stakeholders to scale up this change.\nOur President ensures that the world knows the invaluable contribution rural people make to each of our lives.\n\nAdvocating for rural people\n\nAdvocating for rural people\n\nAdvocating for rural people\n\nAdvocating for rural people\n\nAdvocating for rural people\n\nAdvocating for rural people\n\nOur experts work alongside governments to develop projects so rural people can thrive.\nOur leadership team partners with stakeholders to scale up this change.\nOur President ensures that the world knows the invaluable contribution rural people make to each of our lives.\n\nOur experts work alongside governments to develop projects so rural people can thrive.\nOur leadership team partners with stakeholders to scale up this change.\nOur President ensures that the world knows the invaluable contribution rural people make to each of our lives.\n\nOur experts work alongside governments to develop projects so rural people can thrive.\nOur leadership team partners with stakeholders to scale up this change.\nOur President ensures that the world knows the invaluable contribution rural people make to each of our lives.\n\nOur experts work alongside governments to develop projects so rural people can thrive.\nOur leadership team partners with stakeholders to scale up this change.\nOur President ensures that the world knows the invaluable contribution rural people make to each of our lives.\n\nOur experts work alongside governments to develop projects so rural people can thrive.\n\nOur leadership team partners with stakeholders to scale up this change.\n\nOur President ensures that the world knows the invaluable contribution rural people make to each of our lives.\n\nKeep exploring\n\n\n\n\n\n\n\n\n\n\n\n\n\n\n\n\n Where we work Spanning five regions and 92 countries, IFAD works where poverty and hunger are deepest. \n\n  Explore more \n           \n \n\n\n\n\n\n\n\n\n\n\n\n\n\n\n\n\n\n What we do Simply put, IFAD invests in rural people. We do this by financing programmes, measuring results, innovating and working with rural people themselves. \n\n  Explore more \n           \n \n\n\n\n\n\n\n\n\n\n\n\n\n\n\n\n\n Action areas From building resilience to empowering rural people and protecting the environment, explore our main areas of work. \n\n  Explore more\n\nKeep exploring\n\nKeep exploring\n\nWhere we work Spanning five regions and 92 countries, IFAD works where poverty and hunger are deepest. \n\n  Explore more \n           \n \n\n\n\n\n\n\n\n\n\n\n\n\n\n\n\n\n\n What we do Simply put, IFAD invests in rural people. We do this by financing programmes, measuring results, innovating and working with rural people themselves. \n\n  Explore more \n           \n \n\n\n\n\n\n\n\n\n\n\n\n\n\n\n\n\n Action areas From building resilience to empowering rural people and protecting the environment, explore our main areas of work. \n\n  Explore more\n\nWhere we work Spanning five regions and 92 countries, IFAD works where poverty and hunger are deepest. \n\n  Explore more \n           \n \n\n\n\n\n\n\n\n\n\n\n\n\n\n\n\n\n\n What we do Simply put, IFAD invests in rural people. We do this by financing programmes, measuring results, innovating and working with rural people themselves. \n\n  Explore more \n           \n \n\n\n\n\n\n\n\n\n\n\n\n\n\n\n\n\n Action areas From building resilience to empowering rural people and protecting the environment, explore our main areas of work. \n\n  Explore more\n\nWhere we work Spanning five regions and 92 countries, IFAD works where poverty and hunger are deepest. \n\n  Explore more\n\nWhere we work Spanning five regions and 92 countries, IFAD works where poverty and hunger are deepest. \n\n  Explore more\n\nWhere we work Spanning five regions and 92 countries, IFAD works where poverty and hunger are deepest. \n\n  Explore more\n\nWhere we work Spanning five regions and 92 countries, IFAD works where poverty and hunger are deepest. \n\n  Explore more\n\nWhere we work Spanning five regions and 92 countries, IFAD works where poverty and hunger are deepest. \n\n  Explore more\n\nWhere we work Spanning five regions and 92 countries, IFAD works where poverty and hunger are deepest.\n\nWhere we work Spanning five regions and 92 countries, IFAD works where poverty and hunger are deepest.\n\nWhere we work\n\nSpanning five regions and 92 countries, IFAD works where poverty and hunger are deepest.\n\nWhat we do Simply put, IFAD invests in rural people. We do this by financing programmes, measuring results, innovating and working with rural people themselves. \n\n  Explore more\n\nWhat we do Simply put, IFAD invests in rural people. We do this by financing programmes, measuring results, innovating and working with rural people themselves. \n\n  Explore more\n\nWhat we do Simply put, IFAD invests in rural people. We do this by financing programmes, measuring results, innovating and working with rural people themselves. \n\n  Explore more\n\nWhat we do Simply put, IFAD invests in rural people. We do this by financing programmes, measuring results, innovating and working with rural people themselves. \n\n  Explore more\n\nWhat we do Simply put, IFAD invests in rural people. We do this by financing programmes, measuring results, innovating and working with rural people themselves. \n\n  Explore more\n\nWhat we do Simply put, IFAD invests in rural people. We do this by financing programmes, measuring results, innovating and working with rural people themselves.\n\nWhat we do Simply put, IFAD invests in rural people. We do this by financing programmes, measuring results, innovating and working with rural people themselves.\n\nWhat we do\n\nSimply put, IFAD invests in rural people. We do this by financing programmes, measuring results, innovating and working with rural people themselves.\n\nAction areas From building resilience to empowering rural people and protecting the environment, explore our main areas of work. \n\n  Explore more\n\nAction areas From building resilience to empowering rural people and protecting the environment, explore our main areas of work. \n\n  Explore more\n\nAction areas From building resilience to empowering rural people and protecting the environment, explore our main areas of work. \n\n  Explore more\n\nAction areas From building resilience to empowering rural people and protecting the environment, explore our main areas of work. \n\n  Explore more\n\nAction areas From building resilience to empowering rural people and protecting the environment, explore our main areas of work. \n\n  Explore more\n\nAction areas From building resilience to empowering rural people and protecting the environment, explore our main areas of work.\n\nAction areas From building resilience to empowering rural people and protecting the environment, explore our main areas of work.\n\nAction areas\n\nFrom building resilience to empowering rural people and protecting the environment, explore our main areas of work.\n\nPlease configure the desktop menu widget below\n      \n\n\n\n\n\n\n\n\n About IFAD \n Who we are   Where we work   What we do   Action Areas   Knowledge & Data \n\n\n For Member States \n Member States interactive platform \n\n\n For Investors \n Investors   Finance \n\n\n For Job seekers \n Work with us   Frequently Asked Questions \n\n\n For Media \n News   Media Contacts   Image Bank \n\n\n Get Involved \n Join an event   Rural Voices   Opinions & Insights \n\n\n\n\n\n\n\n\n\n\n\n\n\n       Please configure the mobile menu widget below\n      \n\n\n\n\n\n\n\n\n Who we are \n\n\n\n What we do \n\n\n\n Where we work \n\n\n\n Action Areas \n\n\n\n Knowledge & Data \n\n\n\n Get Involved \n\n\n\n News and Stories \n\n\n\n\n\n\n\n\n\n\n\n\n\n  \n Legal  Privacy notice  Fraudulent job offers  Contact us Stay connected\n\nPlease configure the desktop menu widget below\n      \n\n\n\n\n\n\n\n\n About IFAD \n Who we are   Where we work   What we do   Action Areas   Knowledge & Data \n\n\n For Member States \n Member States interactive platform \n\n\n For Investors \n Investors   Finance \n\n\n For Job seekers \n Work with us   Frequently Asked Questions \n\n\n For Media \n News   Media Contacts   Image Bank \n\n\n Get Involved \n Join an event   Rural Voices   Opinions & Insights \n\n\n\n\n\n\n\n\n\n\n\n\n\n       Please configure the mobile menu widget below\n      \n\n\n\n\n\n\n\n\n Who we are \n\n\n\n What we do \n\n\n\n Where we work \n\n\n\n Action Areas \n\n\n\n Knowledge & Data \n\n\n\n Get Involved \n\n\n\n News and Stories \n\n\n\n\n\n\n\n\n\n\n\n\n\n  \n Legal  Privacy notice  Fraudulent job offers  Contact us Stay connected\n\nPlease configure the desktop menu widget below\n      \n\n\n\n\n\n\n\n\n About IFAD \n Who we are   Where we work   What we do   Action Areas   Knowledge & Data \n\n\n For Member States \n Member States interactive platform \n\n\n For Investors \n Investors   Finance \n\n\n For Job seekers \n Work with us   Frequently Asked Questions \n\n\n For Media \n News   Media Contacts   Image Bank \n\n\n Get Involved \n Join an event   Rural Voices   Opinions & Insights \n\n\n\n\n\n\n\n\n\n\n\n\n\n       Please configure the mobile menu widget below\n      \n\n\n\n\n\n\n\n\n Who we are \n\n\n\n What we do \n\n\n\n Where we work \n\n\n\n Action Areas \n\n\n\n Knowledge & Data \n\n\n\n Get Involved \n\n\n\n News and Stories \n\n\n\n\n\n\n\n\n\n\n\n\n\n  \n Legal  Privacy notice  Fraudulent job offers  Contact us Stay connected\n\nPlease configure the desktop menu widget below\n      \n\n\n\n\n\n\n\n\n About IFAD \n Who we are   Where we work   What we do   Action Areas   Knowledge & Data \n\n\n For Member States \n Member States interactive platform \n\n\n For Investors \n Investors   Finance \n\n\n For Job seekers \n Work with us   Frequently Asked Questions \n\n\n For Media \n News   Media Contacts   Image Bank \n\n\n Get Involved \n Join an event   Rural Voices   Opinions & Insights \n\n\n\n\n\n\n\n\n\n\n\n\n\n       Please configure the mobile menu widget below\n      \n\n\n\n\n\n\n\n\n Who we are \n\n\n\n What we do \n\n\n\n Where we work \n\n\n\n Action Areas \n\n\n\n Knowledge & Data \n\n\n\n Get Involved \n\n\n\n News and Stories\n\nPlease configure the desktop menu widget below\n      \n\n\n\n\n\n\n\n\n About IFAD \n Who we are   Where we work   What we do   Action Areas   Knowledge & Data \n\n\n For Member States \n Member States interactive platform \n\n\n For Investors \n Investors   Finance \n\n\n For Job seekers \n Work with us   Frequently Asked Questions \n\n\n For Media \n News   Media Contacts   Image Bank \n\n\n Get Involved \n Join an event   Rural Voices   Opinions & Insights\n\nPlease configure the desktop menu widget below\n\nAbout IFAD \n Who we are   Where we work   What we do   Action Areas   Knowledge & Data \n\n\n For Member States \n Member States interactive platform \n\n\n For Investors \n Investors   Finance \n\n\n For Job seekers \n Work with us   Frequently Asked Questions \n\n\n For Media \n News   Media Contacts   Image Bank \n\n\n Get Involved \n Join an event   Rural Voices   Opinions & Insights\n\nAbout IFAD \n Who we are   Where we work   What we do   Action Areas   Knowledge & Data \n\n\n For Member States \n Member States interactive platform \n\n\n For Investors \n Investors   Finance \n\n\n For Job seekers \n Work with us   Frequently Asked Questions \n\n\n For Media \n News   Media Contacts   Image Bank \n\n\n Get Involved \n Join an event   Rural Voices   Opinions & Insights\n\nAbout IFAD \n Who we are   Where we work   What we do   Action Areas   Knowledge & Data \n\n\n For Member States \n Member States interactive platform \n\n\n For Investors \n Investors   Finance \n\n\n For Job seekers \n Work with us   Frequently Asked Questions \n\n\n For Media \n News   Media Contacts   Image Bank \n\n\n Get Involved \n Join an event   Rural Voices   Opinions & Insights\n\nAbout IFAD \n Who we are   Where we work   What we do   Action Areas   Knowledge & Data \n\n\n For Member States \n Member States interactive platform \n\n\n For Investors \n Investors   Finance \n\n\n For Job seekers \n Work with us   Frequently Asked Questions \n\n\n For Media \n News   Media Contacts   Image Bank \n\n\n Get Involved \n Join an event   Rural Voices   Opinions & Insights\n\nAbout IFAD \n Who we are   Where we work   What we do   Action Areas   Knowledge & Data \n\n\n For Member States \n Member States interactive platform \n\n\n For Investors \n Investors   Finance \n\n\n For Job seekers \n Work with us   Frequently Asked Questions \n\n\n For Media \n News   Media Contacts   Image Bank \n\n\n Get Involved \n Join an event   Rural Voices   Opinions & Insights\n\nAbout IFAD \n Who we are   Where we work   What we do   Action Areas   Knowledge & Data \n\n\n For Member States \n Member States interactive platform \n\n\n For Investors \n Investors   Finance \n\n\n For Job seekers \n Work with us   Frequently Asked Questions \n\n\n For Media \n News   Media Contacts   Image Bank \n\n\n Get Involved \n Join an event   Rural Voices   Opinions & Insights\n\nAbout IFAD \n Who we are   Where we work   What we do   Action Areas   Knowledge & Data \n\n\n For Member States \n Member States interactive platform \n\n\n For Investors \n Investors   Finance \n\n\n For Job seekers \n Work with us   Frequently Asked Questions \n\n\n For Media \n News   Media Contacts   Image Bank \n\n\n Get Involved \n Join an event   Rural Voices   Opinions & Insights\n\nAbout IFAD \n Who we are   Where we work   What we do   Action Areas   Knowledge & Data \n\n\n For Member States \n Member States interactive platform \n\n\n For Investors \n Investors   Finance \n\n\n For Job seekers \n Work with us   Frequently Asked Questions \n\n\n For Media \n News   Media Contacts   Image Bank \n\n\n Get Involved \n Join an event   Rural Voices   Opinions & Insights\n\nAbout IFAD \n Who we are   Where we work   What we do   Action Areas   Knowledge & Data\n\nWho we are   Where we work   What we do   Action Areas   Knowledge & Data\n\nFor Member States \n Member States interactive platform\n\nMember States interactive platform\n\nFor Investors \n Investors   Finance\n\nInvestors   Finance\n\nFor Job seekers \n Work with us   Frequently Asked Questions\n\nWork with us   Frequently Asked Questions\n\nFor Media \n News   Media Contacts   Image Bank\n\nNews   Media Contacts   Image Bank\n\nGet Involved \n Join an event   Rural Voices   Opinions & Insights\n\nJoin an event   Rural Voices   Opinions & Insights\n\nPlease configure the mobile menu widget below\n      \n\n\n\n\n\n\n\n\n Who we are \n\n\n\n What we do \n\n\n\n Where we work \n\n\n\n Action Areas \n\n\n\n Knowledge & Data \n\n\n\n Get Involved \n\n\n\n News and Stories\n\nPlease configure the mobile menu widget below\n\nWho we are \n\n\n\n What we do \n\n\n\n Where we work \n\n\n\n Action Areas \n\n\n\n Knowledge & Data \n\n\n\n Get Involved \n\n\n\n News and Stories\n\nWho we are \n\n\n\n What we do \n\n\n\n Where we work \n\n\n\n Action Areas \n\n\n\n Knowledge & Data \n\n\n\n Get Involved \n\n\n\n News and Stories\n\nWho we are \n\n\n\n What we do \n\n\n\n Where we work \n\n\n\n Action Areas \n\n\n\n Knowledge & Data \n\n\n\n Get Involved \n\n\n\n News and Stories\n\nWho we are \n\n\n\n What we do \n\n\n\n Where we work \n\n\n\n Action Areas \n\n\n\n Knowledge & Data \n\n\n\n Get Involved \n\n\n\n News and Stories\n\nWho we are \n\n\n\n What we do \n\n\n\n Where we work \n\n\n\n Action Areas \n\n\n\n Knowledge & Data \n\n\n\n Get Involved \n\n\n\n News and Stories\n\nWho we are \n\n\n\n What we do \n\n\n\n Where we work \n\n\n\n Action Areas \n\n\n\n Knowledge & Data \n\n\n\n Get Involved \n\n\n\n News and Stories\n\nWho we are \n\n\n\n What we do \n\n\n\n Where we work \n\n\n\n Action Areas \n\n\n\n Knowledge & Data \n\n\n\n Get Involved \n\n\n\n News and Stories\n\nWho we are \n\n\n\n What we do \n\n\n\n Where we work \n\n\n\n Action Areas \n\n\n\n Knowledge & Data \n\n\n\n Get Involved \n\n\n\n News and Stories\n\nWho we are\n\nWhat we do\n\nWhere we work\n\nAction Areas\n\nKnowledge & Data\n\nGet Involved\n\nNews and Stories\n\nLegal  Privacy notice  Fraudulent job offers  Contact us Stay connected\n\nLegal  Privacy notice  Fraudulent job offers  Contact us Stay connected",
  "date": "",
  "source_type": "other",
  "extracted_at": "2025-04-07T14:27:50.639544",
  "metadata": {
    "description": "IFAD is the world’s fund for transforming agriculture, rural economies and food systems.",
    "keywords": "Who we are",
    "og:site_name": "IFAD",
    "og:type": "website"
  },
  "relevance_score": 0.4,
  "summary": "The road to a better future runs through rural areas\n\n\n\n\n\n\n\n\n\n\nAt the International Fund for Agricultural Development, we envision vibrant, inclusive and sustainable rural communities, where people live free from poverty and hunger. Learn more about our history\n\n\n\n \n\n\n\n\n\n\n\n\n\n\n\n\n\n\n\n\n\n\n\n\n\n\n\n\n\n\nCatalyzing funds for greater impact\n\n\n\n\n\n\n\n\n\n\n\nWe use the contribution from our Member States to generate and assemble additional finance for rural people. Browse all our partners\n\n\n\n \n\n\n\n\n\n\n\n\n\n\n\n\n\n\n\n\n\n\n\n\n\n\n\n\n\n\nAdvocating for rural people\n\n\n\n\n\n\n\n\n\n\n\nOur experts work alongside governments to develop projects so rural people can thrive. Explore more \n           \n \n\n\n\n\n\n\n\n\n\n\n\n\n\n\n\n\n Action areas From building resilience to empowering rural people and protecting the environment, explore our main areas of work. Explore more \n           \n \n\n\n\n\n\n\n\n\n\n\n\n\n\n\n\n       Please configure the desktop menu widget below\n      \n\n\n\n\n\n\n\n\n About IFAD \n Who we are   Where we work   What we do   Action Areas   Knowledge & Data \n\n\n For Member States \n Member States interactive platform \n\n\n For Investors \n Investors   Finance \n\n\n For Job seekers \n Work with us   Frequently Asked Questions \n\n\n For Media \n News   Media Contacts   Image Bank \n\n\n Get Involved \n Join an event   Rural Voices   Opinions & Insights \n\n\n\n\n\n\n\n\n\n\n\n\n\n       Please configure the mobile menu widget below\n      \n\n\n\n\n\n\n\n\n Who we are \n\n\n\n What we do \n\n\n\n Where we work \n\n\n\n Action Areas \n\n\n\n Knowledge & Data \n\n\n\n Get Involved \n\n\n\n News and Stories \n\n\n\n\n\n\n\n\n\n\n\n\n\n  \n Legal  Privacy notice  Fraudulent job offers  Contact us Stay connected\n\n\n\n  \n\n  \n\n  \n\n  \n\n  \n\n \n\n\n\n\n\n\n\n\nHidden\n\nWho we are - IFAD\n\n\n\n\n\n\n\n\n\n\n\n\n\n\n\n\n\n\n\n\n\n\n\n\n\n\n\n\n\n\n\n\n\n\n\nWho we are\n\n\n\n\n\n\n\n\n\n©IFAD/GMB Akash \n\n\n\n\n\n\n\n\n\nIFAD\n\n\n\n\n\n\n\n\n\n\n\n\n is the world’s fund for transforming agriculture, rural economies and food systems. The road to a better future runs through rural areas\n\n\n\n\n\n\n\n\n\n\nAt the International Fund for Agricultural Development, we envision vibrant, inclusive and sustainable rural communities, where people live free from poverty and hunger. Learn more about our history\n\n\n\n \n\n\n\n\n\n\n\n\n\n\n\n\n\n\n\n\n\n\n\n\n\n\n\n\n\n\nCatalyzing funds for greater impact\n\n\n\n\n\n\n\n\n\n\n\nWe use the contribution from our Member States to generate and assemble additional finance for rural people. Browse all our partners\n\n\n\n \n\n\n\n\n\n\n\n\n\n\n\n\n\n\n\n\n\n\n\n\n\n\n\n\n\n\nAdvocating for rural people\n\n\n\n\n\n\n\n\n\n\n\nOur experts work alongside governments to develop projects so rural people can thrive. Explore more \n           \n \n\n\n\n\n\n\n\n\n\n\n\n\n\n\n\n\n Action areas From building resilience to empowering rural people and protecting the environment, explore our main areas of work. Explore more \n           \n \n\n\n\n\n\n\n\n\n\n\n\n\n\n\n\n       Please configure the desktop menu widget below\n      \n\n\n\n\n\n\n\n\n About IFAD \n Who we are   Where we work   What we do   Action Areas   Knowledge & Data \n\n\n For Member States \n Member States interactive platform \n\n\n For Investors \n Investors   Finance \n\n\n For Job seekers \n Work with us   Frequently Asked Questions \n\n\n For Media \n News   Media Contacts   Image Bank \n\n\n Get Involved \n Join an event   Rural Voices   Opinions & Insights \n\n\n\n\n\n\n\n\n\n\n\n\n\n       Please configure the mobile menu widget below\n      \n\n\n\n\n\n\n\n\n Who we are \n\n\n\n What we do \n\n\n\n Where we work \n\n\n\n Action Areas \n\n\n\n Knowledge & Data \n\n\n\n Get Involved \n\n\n\n News and Stories \n\n\n\n\n\n\n\n\n\n\n\n\n\n  \n Legal  Privacy notice  Fraudulent job offers  Contact us Stay connected\n\n\n\n  \n\n  \n\n  \n\n  \n\n  \n\n \n\n\n\n\n\n\n\n\nHidden\n\nWho we are - IFAD\n\n\n\n\n\n\n\n\n\n\n\n\n\n\n\n\n\n\n\n\n\n\n\n\n\n\n\n\n\n\n\n\n\n\n\nWho we are\n\n\n\n\n\n\n\n\n\n©IFAD/GMB Akash \n\n\n\n\n\n\n\n\n\nIFAD\n\n\n\n\n\n\n\n\n\n\n\n\n is the world’s fund for transforming agriculture, rural economies and food systems. The road to a better future runs through rural areas\n\n\n\n\n\n\n\n\n\n\nAt the International Fund for Agricultural Development, we envision vibrant, inclusive and sustainable rural communities, where people live free from poverty and hunger. Learn more about our history\n\n\n\n \n\n\n\n\n\n\n\n\n\n\n\n\n\n\n\n\n\n\n\n\n\n\n\n\n\n\nCatalyzing funds for greater impact\n\n\n\n\n\n\n\n\n\n\n\nWe use the contribution from our Member States to generate and assemble additional finance for rural people. Browse all our partners\n\n\n\n \n\n\n\n\n\n\n\n\n\n\n\n\n\n\n\n\n\n\n\n\n\n\n\n\n\n\nAdvocating for rural people\n\n\n\n\n\n\n\n\n\n\n\nOur experts work alongside governments to develop projects so rural people can thrive. Explore more \n           \n \n\n\n\n\n\n\n\n\n\n\n\n\n\n\n\n\n Action areas From building resilience to empowering rural people and protecting the environment, explore our main areas of work. Explore more \n           \n \n\n\n\n\n\n\n\n\n\n\n\n\n\n\n\n       Please configure the desktop menu widget below\n      \n\n\n\n\n\n\n\n\n About IFAD \n Who we are   Where we work   What we do   Action Areas   Knowledge & Data \n\n\n For Member States \n Member States interactive platform \n\n\n For Investors \n Investors   Finance \n\n\n For Job seekers \n Work with us   Frequently Asked Questions \n\n\n For Media \n News   Media Contacts   Image Bank \n\n\n Get Involved \n Join an event   Rural Voices   Opinions & Insights \n\n\n\n\n\n\n\n\n\n\n\n\n\n       Please configure the mobile menu widget below\n      \n\n\n\n\n\n\n\n\n Who we are \n\n\n\n What we do \n\n\n\n Where we work \n\n\n\n Action Areas \n\n\n\n Knowledge & Data \n\n\n\n Get Involved \n\n\n\n News and Stories \n\n\n\n\n\n\n\n\n\n\n\n\n\n  \n Legal  Privacy notice  Fraudulent job offers  Contact us Stay connected\n\n\n\n  \n\n  \n\n  \n\n  \n\n  \n\n \n\n\n\n\n\n\n\n\nHidden\n\nWho we are\n\n\n\n\n\n\n\n\n\n©IFAD/GMB Akash \n\n\n\n\n\n\n\n\n\nIFAD\n\n\n\n\n\n\n\n\n\n\n\n\n is the world’s fund for transforming agriculture, rural economies and food systems. The road to a better future runs through rural areas\n\n\n\n\n\n\n\n\n\n\nAt the International Fund for Agricultural Development, we envision vibrant, inclusive and sustainable rural communities, where people live free from poverty and hunger. Learn more about our history\n\n\n\n \n\n\n\n\n\n\n\n\n\n\n\n\n\n\n\n\n\n\n\n\n\n\n\n\n\n\nCatalyzing funds for greater impact\n\n\n\n\n\n\n\n\n\n\n\nWe use the contribution from our Member States to generate and assemble additional finance for rural people. Browse all our partners\n\n\n\n \n\n\n\n\n\n\n\n\n\n\n\n\n\n\n\n\n\n\n\n\n\n\n\n\n\n\nAdvocating for rural people\n\n\n\n\n\n\n\n\n\n\n\nOur experts work alongside governments to develop projects so rural people can thrive. Explore more \n           \n \n\n\n\n\n\n\n\n\n\n\n\n\n\n\n\n\n Action areas From building resilience to empowering rural people and protecting the environment, explore our main areas of work. Explore more \n           \n \n\n\n\n\n\n\n\n\n\n\n\n\n\n\n\n       Please configure the desktop menu widget below\n      \n\n\n\n\n\n\n\n\n About IFAD \n Who we are   Where we work   What we do   Action Areas   Knowledge & Data \n\n\n For Member States \n Member States interactive platform \n\n\n For Investors \n Investors   Finance \n\n\n For Job seekers \n Work with us   Frequently Asked Questions \n\n\n For Media \n News   Media Contacts   Image Bank \n\n\n Get Involved \n Join an event   Rural Voices   Opinions & Insights \n\n\n\n\n\n\n\n\n\n\n\n\n\n       Please configure the mobile menu widget below\n      \n\n\n\n\n\n\n\n\n Who we are \n\n\n\n What we do \n\n\n\n Where we work \n\n\n\n Action Areas \n\n\n\n Knowledge & Data \n\n\n\n Get Involved \n\n\n\n News and Stories \n\n\n\n\n\n\n\n\n\n\n\n\n\n  \n Legal  Privacy notice  Fraudulent job offers  Contact us Stay connected\n\nWho we are\n\n\n\n\n\n\n\n\n\n©IFAD/GMB Akash \n\n\n\n\n\n\n\n\n\nIFAD\n\n\n\n\n\n\n\n\n\n\n\n\n is the world’s fund for transforming agriculture, rural economies and food systems. The road to a better future runs through rural areas\n\n\n\n\n\n\n\n\n\n\nAt the International Fund for Agricultural Development, we envision vibrant, inclusive and sustainable rural communities, where people live free from poverty and hunger. Learn more about our history\n\n\n\n \n\n\n\n\n\n\n\n\n\n\n\n\n\n\n\n\n\n\n\n\n\n\n\n\n\n\nCatalyzing funds for greater impact\n\n\n\n\n\n\n\n\n\n\n\nWe use the contribution from our Member States to generate and assemble additional finance for rural people. Browse all our partners\n\n\n\n \n\n\n\n\n\n\n\n\n\n\n\n\n\n\n\n\n\n\n\n\n\n\n\n\n\n\nAdvocating for rural people\n\n\n\n\n\n\n\n\n\n\n\nOur experts work alongside governments to develop projects so rural people can thrive. Explore more \n           \n \n\n\n\n\n\n\n\n\n\n\n\n\n\n\n\n\n Action areas From building resilience to empowering rural people and protecting the environment, explore our main areas of work. Explore more \n           \n \n\n\n\n\n\n\n\n\n\n\n\n\n\n\n\n       Please configure the desktop menu widget below\n      \n\n\n\n\n\n\n\n\n About IFAD \n Who we are   Where we work   What we do   Action Areas   Knowledge & Data \n\n\n For Member States \n Member States interactive platform \n\n\n For Investors \n Investors   Finance \n\n\n For Job seekers \n Work with us   Frequently Asked Questions \n\n\n For Media \n News   Media Contacts   Image Bank \n\n\n Get Involved \n Join an event   Rural Voices   Opinions & Insights \n\n\n\n\n\n\n\n\n\n\n\n\n\n       Please configure the mobile menu widget below\n      \n\n\n\n\n\n\n\n\n Who we are \n\n\n\n What we do \n\n\n\n Where we work \n\n\n\n Action Areas \n\n\n\n Knowledge & Data \n\n\n\n Get Involved \n\n\n\n News and Stories \n\n\n\n\n\n\n\n\n\n\n\n\n\n  \n Legal  Privacy notice  Fraudulent job offers  Contact us Stay connected\n\nWho we are\n\n\n\n\n\n\n\n\n\n©IFAD/GMB Akash \n\n\n\n\n\n\n\n\n\nIFAD\n\n\n\n\n\n\n\n\n\n\n\n\n is the world’s fund for transforming agriculture, rural economies and food systems. The road to a better future runs through rural areas\n\n\n\n\n\n\n\n\n\n\nAt the International Fund for Agricultural Development, we envision vibrant, inclusive and sustainable rural communities, where people live free from poverty and hunger. Learn more about our history\n\n\n\n \n\n\n\n\n\n\n\n\n\n\n\n\n\n\n\n\n\n\n\n\n\n\n\n\n\n\nCatalyzing funds for greater impact\n\n\n\n\n\n\n\n\n\n\n\nWe use the contribution from our Member States to generate and assemble additional finance for rural people. Browse all our partners\n\n\n\n \n\n\n\n\n\n\n\n\n\n\n\n\n\n\n\n\n\n\n\n\n\n\n\n\n\n\nAdvocating for rural people\n\n\n\n\n\n\n\n\n\n\n\nOur experts work alongside governments to develop projects so rural people can thrive. Explore more \n           \n \n\n\n\n\n\n\n\n\n\n\n\n\n\n\n\n\n Action areas From building resilience to empowering rural people and protecting the environment, explore our main areas of work. The road to a better future runs through rural areas\n\n\n\n\n\n\n\n\n\n\nAt the International Fund for Agricultural Development, we envision vibrant, inclusive and sustainable rural communities, where people live free from poverty and hunger. Browse all our partners\n\n\n\n \n\n\n\n\n\n\n\n\n\n\n\n\n\n\n\n\n\n\n\n\n\n\n\n\n\n\nAdvocating for rural people\n\n\n\n\n\n\n\n\n\n\n\nOur experts work alongside governments to develop projects so rural people can thrive. The road to a better future runs through rural areas\n\n\n\n\n\n\n\n\n\n\nAt the International Fund for Agricultural Development, we envision vibrant, inclusive and sustainable rural communities, where people live free from poverty and hunger. See more about the world we envisage\n\nThe road to a better future runs through rural areas\n\n\n\n\n\n\n\n\n\n\nAt the International Fund for Agricultural Development, we envision vibrant, inclusive and sustainable rural communities, where people live free from poverty and hunger. See more about the world we envisage\n\nThe road to a better future runs through rural areas\n\nThe road to a better future runs through rural areas\n\nThe road to a better future runs through rural areas\n\nThe road to a better future runs through rural areas\n\nThe road to a better future runs through rural areas\n\nThe road to a better future runs through rural areas\n\nAt the International Fund for Agricultural Development, we envision vibrant, inclusive and sustainable rural communities, where people live free from poverty and hunger. See more about the world we envisage\n\nAt the International Fund for Agricultural Development, we envision vibrant, inclusive and sustainable rural communities, where people live free from poverty and hunger. Learn more about our history\n\nTransforming rural communities for almost 50 years\n\nTransforming rural communities for almost 50 years\n\nTransforming rural communities for almost 50 years\n\nTransforming rural communities for almost 50 years\n\nTransforming rural communities for almost 50 years\n\nTransforming rural communities for almost 50 years\n\nIFAD was established in the 1970s in response to a global food crises. Learn more about our history\n\nLearn more about our history\n\nCatalyzing funds for greater impact\n\n\n\n\n\n\n\n\n\n\n\nWe use the contribution from our Member States to generate and assemble additional finance for rural people. How we finance our life-changing work\n\nCatalyzing funds for greater impact\n\n\n\n\n\n\n\n\n\n\n\nWe use the contribution from our Member States to generate and assemble additional finance for rural people. How we finance our life-changing work\n\nCatalyzing funds for greater impact\n\nCatalyzing funds for greater impact\n\nCatalyzing funds for greater impact\n\nCatalyzing funds for greater impact\n\nCatalyzing funds for greater impact\n\nCatalyzing funds for greater impact\n\nWe use the contribution from our Member States to generate and assemble additional finance for rural people. How we finance our life-changing work\n\nWe use the contribution from our Member States to generate and assemble additional finance for rural people. Browse all our partners\n\nBrowse all our partners\n\nAdvocating for rural people\n\n\n\n\n\n\n\n\n\n\n\nOur experts work alongside governments to develop projects so rural people can thrive. Advocating for rural people\n\n\n\n\n\n\n\n\n\n\n\nOur experts work alongside governments to develop projects so rural people can thrive. Advocating for rural people\n\nAdvocating for rural people\n\nAdvocating for rural people\n\nAdvocating for rural people\n\nAdvocating for rural people\n\nAdvocating for rural people\n\nOur experts work alongside governments to develop projects so rural people can thrive. Explore more \n           \n \n\n\n\n\n\n\n\n\n\n\n\n\n\n\n\n\n Action areas From building resilience to empowering rural people and protecting the environment, explore our main areas of work. Explore more \n           \n \n\n\n\n\n\n\n\n\n\n\n\n\n\n\n\n\n Action areas From building resilience to empowering rural people and protecting the environment, explore our main areas of work. Explore more \n           \n \n\n\n\n\n\n\n\n\n\n\n\n\n\n\n\n\n Action areas From building resilience to empowering rural people and protecting the environment, explore our main areas of work. Action areas From building resilience to empowering rural people and protecting the environment, explore our main areas of work. Explore more\n\nAction areas From building resilience to empowering rural people and protecting the environment, explore our main areas of work. Explore more\n\nAction areas From building resilience to empowering rural people and protecting the environment, explore our main areas of work. Explore more\n\nAction areas From building resilience to empowering rural people and protecting the environment, explore our main areas of work. Explore more\n\nAction areas From building resilience to empowering rural people and protecting the environment, explore our main areas of work. Explore more\n\nAction areas From building resilience to empowering rural people and protecting the environment, explore our main areas of work. Action areas From building resilience to empowering rural people and protecting the environment, explore our main areas of work. Action areas\n\nFrom building resilience to empowering rural people and protecting the environment, explore our main areas of work. Please configure the desktop menu widget below\n      \n\n\n\n\n\n\n\n\n About IFAD \n Who we are   Where we work   What we do   Action Areas   Knowledge & Data \n\n\n For Member States \n Member States interactive platform \n\n\n For Investors \n Investors   Finance \n\n\n For Job seekers \n Work with us   Frequently Asked Questions \n\n\n For Media \n News   Media Contacts   Image Bank \n\n\n Get Involved \n Join an event   Rural Voices   Opinions & Insights \n\n\n\n\n\n\n\n\n\n\n\n\n\n       Please configure the mobile menu widget below\n      \n\n\n\n\n\n\n\n\n Who we are \n\n\n\n What we do \n\n\n\n Where we work \n\n\n\n Action Areas \n\n\n\n Knowledge & Data \n\n\n\n Get Involved \n\n\n\n News and Stories \n\n\n\n\n\n\n\n\n\n\n\n\n\n  \n Legal  Privacy notice  Fraudulent job offers  Contact us Stay connected\n\nPlease configure the desktop menu widget below\n      \n\n\n\n\n\n\n\n\n About IFAD \n Who we are   Where we work   What we do   Action Areas   Knowledge & Data \n\n\n For Member States \n Member States interactive platform \n\n\n For Investors \n Investors   Finance \n\n\n For Job seekers \n Work with us   Frequently Asked Questions \n\n\n For Media \n News   Media Contacts   Image Bank \n\n\n Get Involved \n Join an event   Rural Voices   Opinions & Insights \n\n\n\n\n\n\n\n\n\n\n\n\n\n       Please configure the mobile menu widget below\n      \n\n\n\n\n\n\n\n\n Who we are \n\n\n\n What we do \n\n\n\n Where we work \n\n\n\n Action Areas \n\n\n\n Knowledge & Data \n\n\n\n Get Involved \n\n\n\n News and Stories \n\n\n\n\n\n\n\n\n\n\n\n\n\n  \n Legal  Privacy notice  Fraudulent job offers  Contact us Stay connected\n\nPlease configure the desktop menu widget below\n      \n\n\n\n\n\n\n\n\n About IFAD \n Who we are   Where we work   What we do   Action Areas   Knowledge & Data \n\n\n For Member States \n Member States interactive platform \n\n\n For Investors \n Investors   Finance \n\n\n For Job seekers \n Work with us   Frequently Asked Questions \n\n\n For Media \n News   Media Contacts   Image Bank \n\n\n Get Involved \n Join an event   Rural Voices   Opinions & Insights \n\n\n\n\n\n\n\n\n\n\n\n\n\n       Please configure the mobile menu widget below\n      \n\n\n\n\n\n\n\n\n Who we are \n\n\n\n What we do \n\n\n\n Where we work \n\n\n\n Action Areas \n\n\n\n Knowledge & Data \n\n\n\n Get Involved \n\n\n\n News and Stories \n\n\n\n\n\n\n\n\n\n\n\n\n\n  \n Legal  Privacy notice  Fraudulent job offers  Contact us Stay connected\n\nPlease configure the desktop menu widget below\n      \n\n\n\n\n\n\n\n\n About IFAD \n Who we are   Where we work   What we do   Action Areas   Knowledge & Data \n\n\n For Member States \n Member States interactive platform \n\n\n For Investors \n Investors   Finance \n\n\n For Job seekers \n Work with us   Frequently Asked Questions \n\n\n For Media \n News   Media Contacts   Image Bank \n\n\n Get Involved \n Join an event   Rural Voices   Opinions & Insights \n\n\n\n\n\n\n\n\n\n\n\n\n\n       Please configure the mobile menu widget below\n      \n\n\n\n\n\n\n\n\n Who we are \n\n\n\n What we do \n\n\n\n Where we work \n\n\n\n Action Areas \n\n\n\n Knowledge & Data \n\n\n\n Get Involved \n\n\n\n News and Stories\n\nPlease configure the desktop menu widget below\n      \n\n\n\n\n\n\n\n\n About IFAD \n Who we are   Where we work   What we do   Action Areas   Knowledge & Data \n\n\n For Member States \n Member States interactive platform \n\n\n For Investors \n Investors   Finance \n\n\n For Job seekers \n Work with us   Frequently Asked Questions \n\n\n For Media \n News   Media Contacts   Image Bank \n\n\n Get Involved \n Join an event   Rural Voices   Opinions & Insights\n\nPlease configure the desktop menu widget below\n\nAbout IFAD \n Who we are   Where we work   What we do   Action Areas   Knowledge & Data \n\n\n For Member States \n Member States interactive platform \n\n\n For Investors \n Investors   Finance \n\n\n For Job seekers \n Work with us   Frequently Asked Questions \n\n\n For Media \n News   Media Contacts   Image Bank \n\n\n Get Involved \n Join an event   Rural Voices   Opinions & Insights\n\nAbout IFAD \n Who we are   Where we work   What we do   Action Areas   Knowledge & Data \n\n\n For Member States \n Member States interactive platform \n\n\n For Investors \n Investors   Finance \n\n\n For Job seekers \n Work with us   Frequently Asked Questions \n\n\n For Media \n News   Media Contacts   Image Bank \n\n\n Get Involved \n Join an event   Rural Voices   Opinions & Insights\n\nAbout IFAD \n Who we are   Where we work   What we do   Action Areas   Knowledge & Data \n\n\n For Member States \n Member States interactive platform \n\n\n For Investors \n Investors   Finance \n\n\n For Job seekers \n Work with us   Frequently Asked Questions \n\n\n For Media \n News   Media Contacts   Image Bank \n\n\n Get Involved \n Join an event   Rural Voices   Opinions & Insights\n\nAbout IFAD \n Who we are   Where we work   What we do   Action Areas   Knowledge & Data \n\n\n For Member States \n Member States interactive platform \n\n\n For Investors \n Investors   Finance \n\n\n For Job seekers \n Work with us   Frequently Asked Questions \n\n\n For Media \n News   Media Contacts   Image Bank \n\n\n Get Involved \n Join an event   Rural Voices   Opinions & Insights\n\nAbout IFAD \n Who we are   Where we work   What we do   Action Areas   Knowledge & Data \n\n\n For Member States \n Member States interactive platform \n\n\n For Investors \n Investors   Finance \n\n\n For Job seekers \n Work with us   Frequently Asked Questions \n\n\n For Media \n News   Media Contacts   Image Bank \n\n\n Get Involved \n Join an event   Rural Voices   Opinions & Insights\n\nAbout IFAD \n Who we are   Where we work   What we do   Action Areas   Knowledge & Data \n\n\n For Member States \n Member States interactive platform \n\n\n For Investors \n Investors   Finance \n\n\n For Job seekers \n Work with us   Frequently Asked Questions \n\n\n For Media \n News   Media Contacts   Image Bank \n\n\n Get Involved \n Join an event   Rural Voices   Opinions & Insights\n\nAbout IFAD \n Who we are   Where we work   What we do   Action Areas   Knowledge & Data \n\n\n For Member States \n Member States interactive platform \n\n\n For Investors \n Investors   Finance \n\n\n For Job seekers \n Work with us   Frequently Asked Questions \n\n\n For Media \n News   Media Contacts   Image Bank \n\n\n Get Involved \n Join an event   Rural Voices   Opinions & Insights\n\nAbout IFAD \n Who we are   Where we work   What we do   Action Areas   Knowledge & Data \n\n\n For Member States \n Member States interactive platform \n\n\n For Investors \n Investors   Finance \n\n\n For Job seekers \n Work with us   Frequently Asked Questions \n\n\n For Media \n News   Media Contacts   Image Bank \n\n\n Get Involved \n Join an event   Rural Voices   Opinions & Insights\n\nAbout IFAD \n Who we are   Where we work   What we do   Action Areas   Knowledge & Data\n\nWho we are   Where we work   What we do   Action Areas   Knowledge & Data\n\nFor Member States \n Member States interactive platform\n\nMember States interactive platform\n\nFor Investors \n Investors   Finance\n\nInvestors   Finance\n\nFor Job seekers \n Work with us   Frequently Asked Questions\n\nWork with us   Frequently Asked Questions\n\nFor Media \n News   Media Contacts   Image Bank\n\nNews   Media Contacts   Image Bank\n\nGet Involved \n Join an event   Rural Voices   Opinions & Insights\n\nJoin an event   Rural Voices   Opinions & Insights\n\nPlease configure the mobile menu widget below\n      \n\n\n\n\n\n\n\n\n Who we are \n\n\n\n What we do \n\n\n\n Where we work \n\n\n\n Action Areas \n\n\n\n Knowledge & Data \n\n\n\n Get Involved \n\n\n\n News and Stories\n\nPlease configure the mobile menu widget below\n\nWho we are \n\n\n\n What we do \n\n\n\n Where we work \n\n\n\n Action Areas \n\n\n\n Knowledge & Data \n\n\n\n Get Involved \n\n\n\n News and Stories\n\nWho we are \n\n\n\n What we do \n\n\n\n Where we work \n\n\n\n Action Areas \n\n\n\n Knowledge & Data \n\n\n\n Get Involved \n\n\n\n News and Stories\n\nWho we are \n\n\n\n What we do \n\n\n\n Where we work \n\n\n\n Action Areas \n\n\n\n Knowledge & Data \n\n\n\n Get Involved \n\n\n\n News and Stories\n\nWho we are \n\n\n\n What we do \n\n\n\n Where we work \n\n\n\n Action Areas \n\n\n\n Knowledge & Data \n\n\n\n Get Involved \n\n\n\n News and Stories\n\nWho we are \n\n\n\n What we do \n\n\n\n Where we work \n\n\n\n Action Areas \n\n\n\n Knowledge & Data \n\n\n\n Get Involved \n\n\n\n News and Stories\n\nWho we are \n\n\n\n What we do \n\n\n\n Where we work \n\n\n\n Action Areas \n\n\n\n Knowledge & Data \n\n\n\n Get Involved \n\n\n\n News and Stories\n\nWho we are \n\n\n\n What we do \n\n\n\n Where we work \n\n\n\n Action Areas \n\n\n\n Knowledge & Data \n\n\n\n Get Involved \n\n\n\n News and Stories\n\nWho we are \n\n\n\n What we do \n\n\n\n Where we work \n\n\n\n Action Areas \n\n\n\n Knowledge & Data \n\n\n\n Get Involved \n\n\n\n News and Stories\n\nWho we are\n\nWhat we do\n\nWhere we work\n\nAction Areas\n\nKnowledge & Data\n\nGet Involved\n\nNews and Stories\n\nLegal  Privacy notice  Fraudulent job offers  Contact us Stay connected\n\nLegal  Privacy notice  Fraudulent job offers  Contact us Stay connected",
  "entities": {
    "countries": [],
    "organizations": [
      "un",
      "who"
    ],
    "key_issues": [
      "nation",
      "state",
      "government",
      "region",
      "program",
      "action",
      "history",
      "development",
      "investment",
      "un",
      "organization",
      "foundation"
    ]
  },
  "committee": "Economic and Social Council",
  "topic": "Promoting rural development in Africa"
}