{
  "url": "https://www.crisisgroup.org",
  "title": "Crisis Group",
  "text": "\n\nQ&A\n                    / Myanmar\n\n\n\nSupport Vital for Myanmar’s Quake Victims, Despite Military Obstacles \n\n\n\nThe massive earthquake in Myanmar has taken a terrible toll. In this Q&A, Crisis Group expert Richard Horsey discusses the urgent need for international assistance, the challenges facing aid delivery against a backdrop of civil war and the importance of a humanitarian pause in fighting.\n\n\n\n\n\n\n\n\n\n\n\n\nWill Myanmar’s Devastating Earthquake Impact its Civil War?\n\n\n\n\n\n\n\nPodcast\n\n                                  / Asia\n\n\n\n                \n                Will Myanmar’s Devastating Earthquake Impact its Civil War?\n              \n\n\nThis week on Hold Your Fire!, Richard Atwood speaks with Crisis Group’s Myanmar expert Richard Horsey about the devastating earthquake that struck Myanmar last week, challenges facing relief efforts and implications for the country’s civil war and its military leaders.\n\n\n\n\n\n\n\nThe Houthis’ Red Sea Attacks Explained\n\n\n\n\n\n\nVisual Explainers\n\n                                  / Middle East & North Africa\n\n\n\n                \n                The Houthis’ Red Sea Attacks Explained\n              \n\n\n\n\n\n\nThe New Syria: Halting a Dangerous Drift\n\n\n\n\n\n\nBriefing\n\n                                  / Middle East & North Africa\n\n\n\n                \n                The New Syria: Halting a Dangerous Drift\n              \n\n\n\n\n\n                Also available in Arabic\n\n\n\n\n\n\nMarch Trends and April Alerts 2025\n\n\n\n\n\n\n                \n                March Trends and April Alerts 2025\n              \n\n\n\n\n\n\n\n            Middle East Tensions\n          \n\n            Read more on the issue\n            \n\n\n\n\n\n\n\n\n\n\n\n\n\n\n\n\n\n\n                  Alert\n                \n\n                              / Middle East & North Africa\n\nStopping Israel’s War in Gaza\n\n\nOn 18 March, Israel resumed bombing Gaza, upending a two-month ceasefire. Returning to war promises little but more death and destruction. The U.S. should insist on restoring the truce and endorse the Arab League plan for Gaza as the basis for a more permanent peace.\n\n\n\n\n\n\n\n\n                        Q&A\n                      \n\n                                          / Middle East & North Africa\n\nA Glimmer of Peace in Syria’s North East\n\n\n\n\n\n\n\n                        Podcast\n                      \n\n                                          / Middle East & North Africa\n\nIsrael Goes Back to War in Gaza\n\n\n\n\n\n\n\n                        Commentary\n                      \n\n                                          / Middle East & North Africa\n\nHow Israel’s Overreach in Syria May Backfire\n\n\n\n\n\n\n\n            Sudan\n          \n\n            Read more on Sudan\n            \n\n\n\n\n\n\n\n\n\n\n\n\n\n\n\n\n\n\n                  Statement\n                \n\n                              / Africa\n\nBattle for Khartoum Marks a Crossroads in Sudan’s Civil War\n\n\nThe Sudanese army is pushing to take over Khartoum. Should it prevail, it would record a major victory, though one that would be unlikely to end the country’s devastating conflict. Mediators should keep exploring openings for peace talks. \n\n\n\n\n\n\n\n\n                        Op-Ed\n                      \n\n                                          / Africa\n\nPeace talks remain the only way out of Sudan’s nightmare \n\n\n\n\n\n\n\n                        Podcast\n                      \n\n                                          / Africa\n\nA Decisive Turn in Sudan’s War?\n\n\n\n\n\n\n\n                        Briefing\n                      \n\n                                          / Africa\n\nSudan’s Calamitous War: Finding a Path toward Peace\n\n\n\n\n\n\n\n        Videos & Photography\n      \n\n\n\n \n\n\n\n\n\n\n\n\n\n\n\n\nVideo\n\n                                                / Ukraine\n                                              \n\n\nEuropean Security Three Years On From Russia's Full-scale Invasion of Ukraine\n\n\n\n\n\n \n\n\n\n\n\n\n\n\n\n\n\n\nVideo\n\n                                                / Global\n                                              \n\n\nMapping Conflict\n\n\n\n\n\n \n\n\n\n\n\n\n\n\n\n\n\n\nVideo\n\n                                                / Global\n                                              \n\n\nVIDEO | 10 Conflicts to Watch in 2025\n\n\n\n\n\n \n\n\n\n\n\n\n\n\n\n\n\n\nVideo\n\n                                                / Israel/Palestine\n                                              \n\n\nVideo | The Rise of Israeli Settler Violence in the West Bank\n\n\n\n\n\n \n\n\n\n\n\n\n\n\n\n\n\n\nVideo\n\n                                                / Mali\n                                              \n\n\nIbrahim Maiga on Mali's Sovereign Turn\n\n\n\n\n\n \n\n\n\n\n\n\n\n\n\n\n\n\nVideo\n\n                                                / South East Asia\n                                              \n\n\nThe Mekong's Troubled Waters\n\n\n\n\n\n \n\n\n\n\n\n\n\n\n\n\n\n\nVideo\n\n                                                / Morocco\n                                              \n\n\nAlgeria-Morocco Tensions\n\n\n\n\n\n \n\n\n\n\n\n\n\n\n\n\n\n\nVideo\n\n                                                / Mali\n                                              \n\n\nJean-Hervé Jezequel on Mali’s Sovereign Turn\n\n\n\n\n\n \n\n\n\n\n\n\n\n\n\n\n\n\nVideo\n\n                                                / Saudi Arabia\n                                              \n\n\nAbdulaziz Sager: Saudi Arabia's Perspective on the Escalation in the Middle East\n\n\n\n\n\n \n\n\n\n\n\n\n\n\n\n\n\n\nVideo\n\n                                                / Niger\n                                              \n\n\nLa vie des femmes sous l'État islamique dans l'ouest du Niger\n\n\n\n\n\n\n\n\n\n\n\n        Visual Explainers\n      \n\n\n\n \n\n\n\n\n\n\n\n\nUkraine War Map: Tracking the Frontlines\n\n\n\n \n\n\n\n\n\n\n\n\nVisual Explainer: Ten Conflicts to Watch in 2024\n\n\n\n \n\n\n\n\n\n\n\n\nThe U.S. Containment Strategy in Somalia\n\n\n\n \n\n\n\n\n\n\n\n\nWhich Conflicts Should the UNGA Look at?\n\n\n\n\n\n\n\n\n\n\n        In The News\n      \n\n\n\n\n      4 Apr 2025\n    \n\n            Airstrikes don't directly affect relief efforts [in Myanmar]. But they create a context in which it's clear the regime isn't willing to pause its attacks.\n    \n\n      DW\n      \n\n\n\n\n\n\n\n\n\n\nRichard Horsey\n\nSenior Adviser, Myanmar\n\n\n\n\n\n      3 Apr 2025\n    \n\n            What we're seeing very explicitly from the Israeli political echelon is that they actually want to lay the groundwork and begin moving towards the de-population of Gaza.\n    \n\n      DW\n      \n\n\n\n\n\n\n\n\n\n                      —\n                                Amjad Iraqi\n                  \n\n\n\n\n\n\n\n\n      2 Apr 2025\n    \n\n            There is a red line in the Palestinian national discourse. You don’t criticize armed resistance. To do that will provide the kind of pretext that Israel and the internati...\n    \n\n      AP\n      \n\n\n\n\n\n\n\n\n\n\nTahani Mustafa\n\nSenior Analyst, Palestine\n\n\n\n\n\n      27 Mar 2025\n    \n\n            There are plenty within the opposition who are opposed to the government [in South Sudan]. If this escalates to violence, this could be very decentralised.\n    \n\n      Al Jazeera\n      \n\n\n\n\n\n\n\n\n\n\nDaniel Akech\n\nSenior Analyst, South Sudan\n\n\n\n\n\n\n\n      25 Mar 2025\n    \n\n            The idea that [Israeli] military strikes will pressure Hamas to release hostages without an end to the war [in Gaza] is unrealistic at best, and disingenuous at worst.\n    \n\n      Arab News\n      \n\n\n\n\n\n\n\n\n\n\nMairav Zonszein\n\nSenior Analyst, Israel\n\n\n\n\n\n      24 Mar 2025\n    \n\n            There's obviously a fork in the road ahead after the Sudanese army takes Khartoum. Either more war, or a pivot to try and end this through peace talks.\r\n\n    \n\n      AFP\n      \n\n\n\n\n\n\n\n\n\n\nAlan Boswell\n\nProject Director, Horn of Africa\n\n\n\n\n\n\n\n\n\n\n      Regional Updates\n    \n\n\n\nGlobal \n\n\n\n\n\n\n\n\n\nSpecial Coverage\nOn Our Radar\n\n\n\n\nQ&A\nUnpacking the Use of U.S. Wartime Powers against a Criminal “Invasion”\n\n\nSpecial Coverage\nComfort Ero’s 2025 Top Picks on Gender and Conflict\n\n\n\n\n\nAfrica \n\n\n\n\n\n\n\n\n\nPodcast\nSouth Sudan on the Brink of Another War\n\n\n\n\nAlert\nEthiopia and Eritrea Slide Closer to War amid Tigray Upheaval \n\n\nPodcast\nWhich Way Will Trump Go on Somalia?\n\n\n\n\n\nAsia \n\n\n\n\n\n\n\n\n\nPodcast\nWill Myanmar’s Devastating Earthquake Impact its Civil War?\n\n\n\n\nQ&A\nSupport Vital for Myanmar’s Quake Victims, Despite Military Obstacles \n\n\nBriefing\nDisquiet on the Western Front: A Divided Resistance in Myanmar’s Chin State\n\n\n\n\n\nEurope & Central Asia \n\n\n\n\n\n\n\n\n\nQ&A\nA Glimmer of Peace in Syria’s North East\n\n\n\n\nPodcast\nLatin America’s Evolving Drug Trade. Why It Matters for Europe\n\n\nPodcast\nTrump, France and European Security\n\n\n\n\n\nLatin America & Caribbean \n\n\n\n\n\nQ&A\nUnpacking the Use of U.S. Wartime Powers against a Criminal “Invasion”\n\n\n\nPodcast\nLatin America’s Evolving Drug Trade. Why It Matters for Europe\n\n\nVisual Explainers\nHow a New Drug Trafficking Landscape Fuels Violence in Latin America\n\n\n\n\n\nMiddle East & North Africa \n\n\n\n\n\n\n\n\n\nVisual Explainers\nThe Houthis’ Red Sea Attacks Explained\n\n\n\n\n\n\n\n\nQ&A\nA Glimmer of Peace in Syria’s North East\n\n\n\nBriefing\nThe New Syria: Halting a Dangerous Drift\n\n\n\n\n\nUnited States \n\n\n\n\n\n\n\n\n\nQ&A\nA Glimmer of Peace in Syria’s North East\n\n\n\n\nPodcast\nWhich Way Will Trump Go on Somalia?\n\n\nQ&A\nUnpacking the Use of U.S. Wartime Powers against a Criminal “Invasion”\n\n\n\n\n\n\n\n\n\nSupport Us\n\nYour investment helps us to meet the growing demand for our work as we confront a terrible trend toward more wars, more civilians killed and more people displaced worldwide.\n\n\n        Donate now\n      \n\n        Learn What We Do\n        \n\n\n\n\n\n    Our Supporters\n  \n\n\n\n\n\nAustralia (Department of Foreign Affairs and Trade)\n\n\n\n\n\nAustria (Austrian Development Agency)\n\n\n\n\n\nCanada (Global Affairs Canada and Canadian Department of National Defence)\n\n\n\n\n\nCarnegie Corporation of New York\n\n\n\n\n\nChevron\n\n\n\n\n\nChris Bake\n\n\n\n\n\nDenmark (Ministry of Foreign Affairs)\n\n\n\n\n\nEni\n\n\n\n\n\nEuropean Union (Instrument contributing to Stability and Peace, Emergency Trust Fund for Africa)\n\n\n\n\n\nFinland (Ministry for Foreign Affairs)\n\n\n\n\n\nFrance (Ministry of Foreign Affairs and French Development Agency)\n\n\n\n\n\nFrank Giustra\n\n\n\n\n\nGlobal Challenges Foundation\n\n\n\n\n\nHerman De Bode\n\n\n\n\n\nIreland (Department of Foreign Affairs)\n\n\n\n\n\nLuxembourg (Ministry of Foreign and European Affairs)\n\n\n\n\n\nNeil Woodyer\n\n\n\n\n\nNew Zealand (Ministry of Foreign Affairs and Trade)\n\n\n\n\n\nNorway (Ministry of Foreign Affairs)\n\n\n\n\n\nOpen Society Foundations\n\n\n\n\n\nQatar (Ministry of Foreign Affairs)\n\n\n\n\n\nRobert Bosch Stiftung\n\n\n\n\n\nRockefeller Brothers Fund\n\n\n\n\n\nStand Together Trust\n\n\n\n\n\nStiftung Mercator\n\n\n\n\n\nSweden (Ministry of Foreign Affairs)\n\n\n\n\n\nSwitzerland (Federal Department of Foreign Affairs)\n\n\n\n\n\nThe Bergman Family Foundation\n\n\n\n\n\nThe Netherlands (Ministry of Foreign Affairs)\n\n\n\n\n\nUnited Arab Emirates (Ministry of Foreign Affairs and International Cooperation and Anwar Gargash Diplomatic Academy)\n\n\n\n\n\nWadah Khanfar\n\n\n\n\n        Learn more about supporting Crisis Group\n        \n\n\n\n\n\n\n\n\n\n\n\nSubscribe to Crisis Group’s Email Updates\n\n\n\nReceive the best source of conflict analysis right in your inbox.\n\n\nSubscribe here\n\n\n\n\n\n\n\n\n\n\n\n\n\nThis site uses cookies. By continuing to browse the site you are agreeing to our use of cookies. Review our privacy policy for more details.\n\n\nYes, I Agree\n\nQ&A\n                    / Myanmar\n\n\n\nSupport Vital for Myanmar’s Quake Victims, Despite Military Obstacles \n\n\n\nThe massive earthquake in Myanmar has taken a terrible toll. In this Q&A, Crisis Group expert Richard Horsey discusses the urgent need for international assistance, the challenges facing aid delivery against a backdrop of civil war and the importance of a humanitarian pause in fighting.\n\n\n\n\n\n\n\n\n\n\n\n\nWill Myanmar’s Devastating Earthquake Impact its Civil War?\n\n\n\n\n\n\n\nPodcast\n\n                                  / Asia\n\n\n\n                \n                Will Myanmar’s Devastating Earthquake Impact its Civil War?\n              \n\n\nThis week on Hold Your Fire!, Richard Atwood speaks with Crisis Group’s Myanmar expert Richard Horsey about the devastating earthquake that struck Myanmar last week, challenges facing relief efforts and implications for the country’s civil war and its military leaders.\n\n\n\n\n\n\n\nThe Houthis’ Red Sea Attacks Explained\n\n\n\n\n\n\nVisual Explainers\n\n                                  / Middle East & North Africa\n\n\n\n                \n                The Houthis’ Red Sea Attacks Explained\n              \n\n\n\n\n\n\nThe New Syria: Halting a Dangerous Drift\n\n\n\n\n\n\nBriefing\n\n                                  / Middle East & North Africa\n\n\n\n                \n                The New Syria: Halting a Dangerous Drift\n              \n\n\n\n\n\n                Also available in Arabic\n\n\n\n\n\n\nMarch Trends and April Alerts 2025\n\n\n\n\n\n\n                \n                March Trends and April Alerts 2025\n              \n\n\n\n\n\n\n\n            Middle East Tensions\n          \n\n            Read more on the issue\n            \n\n\n\n\n\n\n\n\n\n\n\n\n\n\n\n\n\n\n                  Alert\n                \n\n                              / Middle East & North Africa\n\nStopping Israel’s War in Gaza\n\n\nOn 18 March, Israel resumed bombing Gaza, upending a two-month ceasefire. Returning to war promises little but more death and destruction. The U.S. should insist on restoring the truce and endorse the Arab League plan for Gaza as the basis for a more permanent peace.\n\n\n\n\n\n\n\n\n                        Q&A\n                      \n\n                                          / Middle East & North Africa\n\nA Glimmer of Peace in Syria’s North East\n\n\n\n\n\n\n\n                        Podcast\n                      \n\n                                          / Middle East & North Africa\n\nIsrael Goes Back to War in Gaza\n\n\n\n\n\n\n\n                        Commentary\n                      \n\n                                          / Middle East & North Africa\n\nHow Israel’s Overreach in Syria May Backfire\n\n\n\n\n\n\n\n            Sudan\n          \n\n            Read more on Sudan\n            \n\n\n\n\n\n\n\n\n\n\n\n\n\n\n\n\n\n\n                  Statement\n                \n\n                              / Africa\n\nBattle for Khartoum Marks a Crossroads in Sudan’s Civil War\n\n\nThe Sudanese army is pushing to take over Khartoum. Should it prevail, it would record a major victory, though one that would be unlikely to end the country’s devastating conflict. Mediators should keep exploring openings for peace talks. \n\n\n\n\n\n\n\n\n                        Op-Ed\n                      \n\n                                          / Africa\n\nPeace talks remain the only way out of Sudan’s nightmare \n\n\n\n\n\n\n\n                        Podcast\n                      \n\n                                          / Africa\n\nA Decisive Turn in Sudan’s War?\n\n\n\n\n\n\n\n                        Briefing\n                      \n\n                                          / Africa\n\nSudan’s Calamitous War: Finding a Path toward Peace\n\n\n\n\n\n\n\n        Videos & Photography\n      \n\n\n\n \n\n\n\n\n\n\n\n\n\n\n\n\nVideo\n\n                                                / Ukraine\n                                              \n\n\nEuropean Security Three Years On From Russia's Full-scale Invasion of Ukraine\n\n\n\n\n\n \n\n\n\n\n\n\n\n\n\n\n\n\nVideo\n\n                                                / Global\n                                              \n\n\nMapping Conflict\n\n\n\n\n\n \n\n\n\n\n\n\n\n\n\n\n\n\nVideo\n\n                                                / Global\n                                              \n\n\nVIDEO | 10 Conflicts to Watch in 2025\n\n\n\n\n\n \n\n\n\n\n\n\n\n\n\n\n\n\nVideo\n\n                                                / Israel/Palestine\n                                              \n\n\nVideo | The Rise of Israeli Settler Violence in the West Bank\n\n\n\n\n\n \n\n\n\n\n\n\n\n\n\n\n\n\nVideo\n\n                                                / Mali\n                                              \n\n\nIbrahim Maiga on Mali's Sovereign Turn\n\n\n\n\n\n \n\n\n\n\n\n\n\n\n\n\n\n\nVideo\n\n                                                / South East Asia\n                                              \n\n\nThe Mekong's Troubled Waters\n\n\n\n\n\n \n\n\n\n\n\n\n\n\n\n\n\n\nVideo\n\n                                                / Morocco\n                                              \n\n\nAlgeria-Morocco Tensions\n\n\n\n\n\n \n\n\n\n\n\n\n\n\n\n\n\n\nVideo\n\n                                                / Mali\n                                              \n\n\nJean-Hervé Jezequel on Mali’s Sovereign Turn\n\n\n\n\n\n \n\n\n\n\n\n\n\n\n\n\n\n\nVideo\n\n                                                / Saudi Arabia\n                                              \n\n\nAbdulaziz Sager: Saudi Arabia's Perspective on the Escalation in the Middle East\n\n\n\n\n\n \n\n\n\n\n\n\n\n\n\n\n\n\nVideo\n\n                                                / Niger\n                                              \n\n\nLa vie des femmes sous l'État islamique dans l'ouest du Niger\n\n\n\n\n\n\n\n\n\n\n\n        Visual Explainers\n      \n\n\n\n \n\n\n\n\n\n\n\n\nUkraine War Map: Tracking the Frontlines\n\n\n\n \n\n\n\n\n\n\n\n\nVisual Explainer: Ten Conflicts to Watch in 2024\n\n\n\n \n\n\n\n\n\n\n\n\nThe U.S. Containment Strategy in Somalia\n\n\n\n \n\n\n\n\n\n\n\n\nWhich Conflicts Should the UNGA Look at?\n\n\n\n\n\n\n\n\n\n\n        In The News\n      \n\n\n\n\n      4 Apr 2025\n    \n\n            Airstrikes don't directly affect relief efforts [in Myanmar]. But they create a context in which it's clear the regime isn't willing to pause its attacks.\n    \n\n      DW\n      \n\n\n\n\n\n\n\n\n\n\nRichard Horsey\n\nSenior Adviser, Myanmar\n\n\n\n\n\n      3 Apr 2025\n    \n\n            What we're seeing very explicitly from the Israeli political echelon is that they actually want to lay the groundwork and begin moving towards the de-population of Gaza.\n    \n\n      DW\n      \n\n\n\n\n\n\n\n\n\n                      —\n                                Amjad Iraqi\n                  \n\n\n\n\n\n\n\n\n      2 Apr 2025\n    \n\n            There is a red line in the Palestinian national discourse. You don’t criticize armed resistance. To do that will provide the kind of pretext that Israel and the internati...\n    \n\n      AP\n      \n\n\n\n\n\n\n\n\n\n\nTahani Mustafa\n\nSenior Analyst, Palestine\n\n\n\n\n\n      27 Mar 2025\n    \n\n            There are plenty within the opposition who are opposed to the government [in South Sudan]. If this escalates to violence, this could be very decentralised.\n    \n\n      Al Jazeera\n      \n\n\n\n\n\n\n\n\n\n\nDaniel Akech\n\nSenior Analyst, South Sudan\n\n\n\n\n\n\n\n      25 Mar 2025\n    \n\n            The idea that [Israeli] military strikes will pressure Hamas to release hostages without an end to the war [in Gaza] is unrealistic at best, and disingenuous at worst.\n    \n\n      Arab News\n      \n\n\n\n\n\n\n\n\n\n\nMairav Zonszein\n\nSenior Analyst, Israel\n\n\n\n\n\n      24 Mar 2025\n    \n\n            There's obviously a fork in the road ahead after the Sudanese army takes Khartoum. Either more war, or a pivot to try and end this through peace talks.\r\n\n    \n\n      AFP\n      \n\n\n\n\n\n\n\n\n\n\nAlan Boswell\n\nProject Director, Horn of Africa\n\n\n\n\n\n\n\n\n\n\n      Regional Updates\n    \n\n\n\nGlobal \n\n\n\n\n\n\n\n\n\nSpecial Coverage\nOn Our Radar\n\n\n\n\nQ&A\nUnpacking the Use of U.S. Wartime Powers against a Criminal “Invasion”\n\n\nSpecial Coverage\nComfort Ero’s 2025 Top Picks on Gender and Conflict\n\n\n\n\n\nAfrica \n\n\n\n\n\n\n\n\n\nPodcast\nSouth Sudan on the Brink of Another War\n\n\n\n\nAlert\nEthiopia and Eritrea Slide Closer to War amid Tigray Upheaval \n\n\nPodcast\nWhich Way Will Trump Go on Somalia?\n\n\n\n\n\nAsia \n\n\n\n\n\n\n\n\n\nPodcast\nWill Myanmar’s Devastating Earthquake Impact its Civil War?\n\n\n\n\nQ&A\nSupport Vital for Myanmar’s Quake Victims, Despite Military Obstacles \n\n\nBriefing\nDisquiet on the Western Front: A Divided Resistance in Myanmar’s Chin State\n\n\n\n\n\nEurope & Central Asia \n\n\n\n\n\n\n\n\n\nQ&A\nA Glimmer of Peace in Syria’s North East\n\n\n\n\nPodcast\nLatin America’s Evolving Drug Trade. Why It Matters for Europe\n\n\nPodcast\nTrump, France and European Security\n\n\n\n\n\nLatin America & Caribbean \n\n\n\n\n\nQ&A\nUnpacking the Use of U.S. Wartime Powers against a Criminal “Invasion”\n\n\n\nPodcast\nLatin America’s Evolving Drug Trade. Why It Matters for Europe\n\n\nVisual Explainers\nHow a New Drug Trafficking Landscape Fuels Violence in Latin America\n\n\n\n\n\nMiddle East & North Africa \n\n\n\n\n\n\n\n\n\nVisual Explainers\nThe Houthis’ Red Sea Attacks Explained\n\n\n\n\n\n\n\n\nQ&A\nA Glimmer of Peace in Syria’s North East\n\n\n\nBriefing\nThe New Syria: Halting a Dangerous Drift\n\n\n\n\n\nUnited States \n\n\n\n\n\n\n\n\n\nQ&A\nA Glimmer of Peace in Syria’s North East\n\n\n\n\nPodcast\nWhich Way Will Trump Go on Somalia?\n\n\nQ&A\nUnpacking the Use of U.S. Wartime Powers against a Criminal “Invasion”\n\n\n\n\n\n\n\n\n\nSupport Us\n\nYour investment helps us to meet the growing demand for our work as we confront a terrible trend toward more wars, more civilians killed and more people displaced worldwide.\n\n\n        Donate now\n      \n\n        Learn What We Do\n        \n\n\n\n\n\n    Our Supporters\n  \n\n\n\n\n\nAustralia (Department of Foreign Affairs and Trade)\n\n\n\n\n\nAustria (Austrian Development Agency)\n\n\n\n\n\nCanada (Global Affairs Canada and Canadian Department of National Defence)\n\n\n\n\n\nCarnegie Corporation of New York\n\n\n\n\n\nChevron\n\n\n\n\n\nChris Bake\n\n\n\n\n\nDenmark (Ministry of Foreign Affairs)\n\n\n\n\n\nEni\n\n\n\n\n\nEuropean Union (Instrument contributing to Stability and Peace, Emergency Trust Fund for Africa)\n\n\n\n\n\nFinland (Ministry for Foreign Affairs)\n\n\n\n\n\nFrance (Ministry of Foreign Affairs and French Development Agency)\n\n\n\n\n\nFrank Giustra\n\n\n\n\n\nGlobal Challenges Foundation\n\n\n\n\n\nHerman De Bode\n\n\n\n\n\nIreland (Department of Foreign Affairs)\n\n\n\n\n\nLuxembourg (Ministry of Foreign and European Affairs)\n\n\n\n\n\nNeil Woodyer\n\n\n\n\n\nNew Zealand (Ministry of Foreign Affairs and Trade)\n\n\n\n\n\nNorway (Ministry of Foreign Affairs)\n\n\n\n\n\nOpen Society Foundations\n\n\n\n\n\nQatar (Ministry of Foreign Affairs)\n\n\n\n\n\nRobert Bosch Stiftung\n\n\n\n\n\nRockefeller Brothers Fund\n\n\n\n\n\nStand Together Trust\n\n\n\n\n\nStiftung Mercator\n\n\n\n\n\nSweden (Ministry of Foreign Affairs)\n\n\n\n\n\nSwitzerland (Federal Department of Foreign Affairs)\n\n\n\n\n\nThe Bergman Family Foundation\n\n\n\n\n\nThe Netherlands (Ministry of Foreign Affairs)\n\n\n\n\n\nUnited Arab Emirates (Ministry of Foreign Affairs and International Cooperation and Anwar Gargash Diplomatic Academy)\n\n\n\n\n\nWadah Khanfar\n\n\n\n\n        Learn more about supporting Crisis Group\n        \n\n\n\n\n\n\n\n\n\n\n\nSubscribe to Crisis Group’s Email Updates\n\n\n\nReceive the best source of conflict analysis right in your inbox.\n\n\nSubscribe here\n\nQ&A\n                    / Myanmar\n\n\n\nSupport Vital for Myanmar’s Quake Victims, Despite Military Obstacles \n\n\n\nThe massive earthquake in Myanmar has taken a terrible toll. In this Q&A, Crisis Group expert Richard Horsey discusses the urgent need for international assistance, the challenges facing aid delivery against a backdrop of civil war and the importance of a humanitarian pause in fighting.\n\n\n\n\n\n\n\n\n\n\n\n\nWill Myanmar’s Devastating Earthquake Impact its Civil War?\n\n\n\n\n\n\n\nPodcast\n\n                                  / Asia\n\n\n\n                \n                Will Myanmar’s Devastating Earthquake Impact its Civil War?\n              \n\n\nThis week on Hold Your Fire!, Richard Atwood speaks with Crisis Group’s Myanmar expert Richard Horsey about the devastating earthquake that struck Myanmar last week, challenges facing relief efforts and implications for the country’s civil war and its military leaders.\n\n\n\n\n\n\n\nThe Houthis’ Red Sea Attacks Explained\n\n\n\n\n\n\nVisual Explainers\n\n                                  / Middle East & North Africa\n\n\n\n                \n                The Houthis’ Red Sea Attacks Explained\n              \n\n\n\n\n\n\nThe New Syria: Halting a Dangerous Drift\n\n\n\n\n\n\nBriefing\n\n                                  / Middle East & North Africa\n\n\n\n                \n                The New Syria: Halting a Dangerous Drift\n              \n\n\n\n\n\n                Also available in Arabic\n\n\n\n\n\n\nMarch Trends and April Alerts 2025\n\n\n\n\n\n\n                \n                March Trends and April Alerts 2025\n              \n\n\n\n\n\n\n\n            Middle East Tensions\n          \n\n            Read more on the issue\n            \n\n\n\n\n\n\n\n\n\n\n\n\n\n\n\n\n\n\n                  Alert\n                \n\n                              / Middle East & North Africa\n\nStopping Israel’s War in Gaza\n\n\nOn 18 March, Israel resumed bombing Gaza, upending a two-month ceasefire. Returning to war promises little but more death and destruction. The U.S. should insist on restoring the truce and endorse the Arab League plan for Gaza as the basis for a more permanent peace.\n\n\n\n\n\n\n\n\n                        Q&A\n                      \n\n                                          / Middle East & North Africa\n\nA Glimmer of Peace in Syria’s North East\n\n\n\n\n\n\n\n                        Podcast\n                      \n\n                                          / Middle East & North Africa\n\nIsrael Goes Back to War in Gaza\n\n\n\n\n\n\n\n                        Commentary\n                      \n\n                                          / Middle East & North Africa\n\nHow Israel’s Overreach in Syria May Backfire\n\n\n\n\n\n\n\n            Sudan\n          \n\n            Read more on Sudan\n            \n\n\n\n\n\n\n\n\n\n\n\n\n\n\n\n\n\n\n                  Statement\n                \n\n                              / Africa\n\nBattle for Khartoum Marks a Crossroads in Sudan’s Civil War\n\n\nThe Sudanese army is pushing to take over Khartoum. Should it prevail, it would record a major victory, though one that would be unlikely to end the country’s devastating conflict. Mediators should keep exploring openings for peace talks. \n\n\n\n\n\n\n\n\n                        Op-Ed\n                      \n\n                                          / Africa\n\nPeace talks remain the only way out of Sudan’s nightmare \n\n\n\n\n\n\n\n                        Podcast\n                      \n\n                                          / Africa\n\nA Decisive Turn in Sudan’s War?\n\n\n\n\n\n\n\n                        Briefing\n                      \n\n                                          / Africa\n\nSudan’s Calamitous War: Finding a Path toward Peace\n\n\n\n\n\n\n\n        Videos & Photography\n      \n\n\n\n \n\n\n\n\n\n\n\n\n\n\n\n\nVideo\n\n                                                / Ukraine\n                                              \n\n\nEuropean Security Three Years On From Russia's Full-scale Invasion of Ukraine\n\n\n\n\n\n \n\n\n\n\n\n\n\n\n\n\n\n\nVideo\n\n                                                / Global\n                                              \n\n\nMapping Conflict\n\n\n\n\n\n \n\n\n\n\n\n\n\n\n\n\n\n\nVideo\n\n                                                / Global\n                                              \n\n\nVIDEO | 10 Conflicts to Watch in 2025\n\n\n\n\n\n \n\n\n\n\n\n\n\n\n\n\n\n\nVideo\n\n                                                / Israel/Palestine\n                                              \n\n\nVideo | The Rise of Israeli Settler Violence in the West Bank\n\n\n\n\n\n \n\n\n\n\n\n\n\n\n\n\n\n\nVideo\n\n                                                / Mali\n                                              \n\n\nIbrahim Maiga on Mali's Sovereign Turn\n\n\n\n\n\n \n\n\n\n\n\n\n\n\n\n\n\n\nVideo\n\n                                                / South East Asia\n                                              \n\n\nThe Mekong's Troubled Waters\n\n\n\n\n\n \n\n\n\n\n\n\n\n\n\n\n\n\nVideo\n\n                                                / Morocco\n                                              \n\n\nAlgeria-Morocco Tensions\n\n\n\n\n\n \n\n\n\n\n\n\n\n\n\n\n\n\nVideo\n\n                                                / Mali\n                                              \n\n\nJean-Hervé Jezequel on Mali’s Sovereign Turn\n\n\n\n\n\n \n\n\n\n\n\n\n\n\n\n\n\n\nVideo\n\n                                                / Saudi Arabia\n                                              \n\n\nAbdulaziz Sager: Saudi Arabia's Perspective on the Escalation in the Middle East\n\n\n\n\n\n \n\n\n\n\n\n\n\n\n\n\n\n\nVideo\n\n                                                / Niger\n                                              \n\n\nLa vie des femmes sous l'État islamique dans l'ouest du Niger\n\n\n\n\n\n\n\n\n\n\n\n        Visual Explainers\n      \n\n\n\n \n\n\n\n\n\n\n\n\nUkraine War Map: Tracking the Frontlines\n\n\n\n \n\n\n\n\n\n\n\n\nVisual Explainer: Ten Conflicts to Watch in 2024\n\n\n\n \n\n\n\n\n\n\n\n\nThe U.S. Containment Strategy in Somalia\n\n\n\n \n\n\n\n\n\n\n\n\nWhich Conflicts Should the UNGA Look at?\n\n\n\n\n\n\n\n\n\n\n        In The News\n      \n\n\n\n\n      4 Apr 2025\n    \n\n            Airstrikes don't directly affect relief efforts [in Myanmar]. But they create a context in which it's clear the regime isn't willing to pause its attacks.\n    \n\n      DW\n      \n\n\n\n\n\n\n\n\n\n\nRichard Horsey\n\nSenior Adviser, Myanmar\n\n\n\n\n\n      3 Apr 2025\n    \n\n            What we're seeing very explicitly from the Israeli political echelon is that they actually want to lay the groundwork and begin moving towards the de-population of Gaza.\n    \n\n      DW\n      \n\n\n\n\n\n\n\n\n\n                      —\n                                Amjad Iraqi\n                  \n\n\n\n\n\n\n\n\n      2 Apr 2025\n    \n\n            There is a red line in the Palestinian national discourse. You don’t criticize armed resistance. To do that will provide the kind of pretext that Israel and the internati...\n    \n\n      AP\n      \n\n\n\n\n\n\n\n\n\n\nTahani Mustafa\n\nSenior Analyst, Palestine\n\n\n\n\n\n      27 Mar 2025\n    \n\n            There are plenty within the opposition who are opposed to the government [in South Sudan]. If this escalates to violence, this could be very decentralised.\n    \n\n      Al Jazeera\n      \n\n\n\n\n\n\n\n\n\n\nDaniel Akech\n\nSenior Analyst, South Sudan\n\n\n\n\n\n\n\n      25 Mar 2025\n    \n\n            The idea that [Israeli] military strikes will pressure Hamas to release hostages without an end to the war [in Gaza] is unrealistic at best, and disingenuous at worst.\n    \n\n      Arab News\n      \n\n\n\n\n\n\n\n\n\n\nMairav Zonszein\n\nSenior Analyst, Israel\n\n\n\n\n\n      24 Mar 2025\n    \n\n            There's obviously a fork in the road ahead after the Sudanese army takes Khartoum. Either more war, or a pivot to try and end this through peace talks.\r\n\n    \n\n      AFP\n      \n\n\n\n\n\n\n\n\n\n\nAlan Boswell\n\nProject Director, Horn of Africa\n\n\n\n\n\n\n\n\n\n\n      Regional Updates\n    \n\n\n\nGlobal \n\n\n\n\n\n\n\n\n\nSpecial Coverage\nOn Our Radar\n\n\n\n\nQ&A\nUnpacking the Use of U.S. Wartime Powers against a Criminal “Invasion”\n\n\nSpecial Coverage\nComfort Ero’s 2025 Top Picks on Gender and Conflict\n\n\n\n\n\nAfrica \n\n\n\n\n\n\n\n\n\nPodcast\nSouth Sudan on the Brink of Another War\n\n\n\n\nAlert\nEthiopia and Eritrea Slide Closer to War amid Tigray Upheaval \n\n\nPodcast\nWhich Way Will Trump Go on Somalia?\n\n\n\n\n\nAsia \n\n\n\n\n\n\n\n\n\nPodcast\nWill Myanmar’s Devastating Earthquake Impact its Civil War?\n\n\n\n\nQ&A\nSupport Vital for Myanmar’s Quake Victims, Despite Military Obstacles \n\n\nBriefing\nDisquiet on the Western Front: A Divided Resistance in Myanmar’s Chin State\n\n\n\n\n\nEurope & Central Asia \n\n\n\n\n\n\n\n\n\nQ&A\nA Glimmer of Peace in Syria’s North East\n\n\n\n\nPodcast\nLatin America’s Evolving Drug Trade. Why It Matters for Europe\n\n\nPodcast\nTrump, France and European Security\n\n\n\n\n\nLatin America & Caribbean \n\n\n\n\n\nQ&A\nUnpacking the Use of U.S. Wartime Powers against a Criminal “Invasion”\n\n\n\nPodcast\nLatin America’s Evolving Drug Trade. Why It Matters for Europe\n\n\nVisual Explainers\nHow a New Drug Trafficking Landscape Fuels Violence in Latin America\n\n\n\n\n\nMiddle East & North Africa \n\n\n\n\n\n\n\n\n\nVisual Explainers\nThe Houthis’ Red Sea Attacks Explained\n\n\n\n\n\n\n\n\nQ&A\nA Glimmer of Peace in Syria’s North East\n\n\n\nBriefing\nThe New Syria: Halting a Dangerous Drift\n\n\n\n\n\nUnited States \n\n\n\n\n\n\n\n\n\nQ&A\nA Glimmer of Peace in Syria’s North East\n\n\n\n\nPodcast\nWhich Way Will Trump Go on Somalia?\n\n\nQ&A\nUnpacking the Use of U.S. Wartime Powers against a Criminal “Invasion”\n\n\n\n\n\n\n\n\n\nSupport Us\n\nYour investment helps us to meet the growing demand for our work as we confront a terrible trend toward more wars, more civilians killed and more people displaced worldwide.\n\n\n        Donate now\n      \n\n        Learn What We Do\n        \n\n\n\n\n\n    Our Supporters\n  \n\n\n\n\n\nAustralia (Department of Foreign Affairs and Trade)\n\n\n\n\n\nAustria (Austrian Development Agency)\n\n\n\n\n\nCanada (Global Affairs Canada and Canadian Department of National Defence)\n\n\n\n\n\nCarnegie Corporation of New York\n\n\n\n\n\nChevron\n\n\n\n\n\nChris Bake\n\n\n\n\n\nDenmark (Ministry of Foreign Affairs)\n\n\n\n\n\nEni\n\n\n\n\n\nEuropean Union (Instrument contributing to Stability and Peace, Emergency Trust Fund for Africa)\n\n\n\n\n\nFinland (Ministry for Foreign Affairs)\n\n\n\n\n\nFrance (Ministry of Foreign Affairs and French Development Agency)\n\n\n\n\n\nFrank Giustra\n\n\n\n\n\nGlobal Challenges Foundation\n\n\n\n\n\nHerman De Bode\n\n\n\n\n\nIreland (Department of Foreign Affairs)\n\n\n\n\n\nLuxembourg (Ministry of Foreign and European Affairs)\n\n\n\n\n\nNeil Woodyer\n\n\n\n\n\nNew Zealand (Ministry of Foreign Affairs and Trade)\n\n\n\n\n\nNorway (Ministry of Foreign Affairs)\n\n\n\n\n\nOpen Society Foundations\n\n\n\n\n\nQatar (Ministry of Foreign Affairs)\n\n\n\n\n\nRobert Bosch Stiftung\n\n\n\n\n\nRockefeller Brothers Fund\n\n\n\n\n\nStand Together Trust\n\n\n\n\n\nStiftung Mercator\n\n\n\n\n\nSweden (Ministry of Foreign Affairs)\n\n\n\n\n\nSwitzerland (Federal Department of Foreign Affairs)\n\n\n\n\n\nThe Bergman Family Foundation\n\n\n\n\n\nThe Netherlands (Ministry of Foreign Affairs)\n\n\n\n\n\nUnited Arab Emirates (Ministry of Foreign Affairs and International Cooperation and Anwar Gargash Diplomatic Academy)\n\n\n\n\n\nWadah Khanfar\n\n\n\n\n        Learn more about supporting Crisis Group\n\nQ&A\n                    / Myanmar\n\n\n\nSupport Vital for Myanmar’s Quake Victims, Despite Military Obstacles \n\n\n\nThe massive earthquake in Myanmar has taken a terrible toll. In this Q&A, Crisis Group expert Richard Horsey discusses the urgent need for international assistance, the challenges facing aid delivery against a backdrop of civil war and the importance of a humanitarian pause in fighting.\n\n\n\n\n\n\n\n\n\n\n\n\nWill Myanmar’s Devastating Earthquake Impact its Civil War?\n\n\n\n\n\n\n\nPodcast\n\n                                  / Asia\n\n\n\n                \n                Will Myanmar’s Devastating Earthquake Impact its Civil War?\n              \n\n\nThis week on Hold Your Fire!, Richard Atwood speaks with Crisis Group’s Myanmar expert Richard Horsey about the devastating earthquake that struck Myanmar last week, challenges facing relief efforts and implications for the country’s civil war and its military leaders.\n\n\n\n\n\n\n\nThe Houthis’ Red Sea Attacks Explained\n\n\n\n\n\n\nVisual Explainers\n\n                                  / Middle East & North Africa\n\n\n\n                \n                The Houthis’ Red Sea Attacks Explained\n              \n\n\n\n\n\n\nThe New Syria: Halting a Dangerous Drift\n\n\n\n\n\n\nBriefing\n\n                                  / Middle East & North Africa\n\n\n\n                \n                The New Syria: Halting a Dangerous Drift\n              \n\n\n\n\n\n                Also available in Arabic\n\n\n\n\n\n\nMarch Trends and April Alerts 2025\n\n\n\n\n\n\n                \n                March Trends and April Alerts 2025\n              \n\n\n\n\n\n\n\n            Middle East Tensions\n          \n\n            Read more on the issue\n            \n\n\n\n\n\n\n\n\n\n\n\n\n\n\n\n\n\n\n                  Alert\n                \n\n                              / Middle East & North Africa\n\nStopping Israel’s War in Gaza\n\n\nOn 18 March, Israel resumed bombing Gaza, upending a two-month ceasefire. Returning to war promises little but more death and destruction. The U.S. should insist on restoring the truce and endorse the Arab League plan for Gaza as the basis for a more permanent peace.\n\n\n\n\n\n\n\n\n                        Q&A\n                      \n\n                                          / Middle East & North Africa\n\nA Glimmer of Peace in Syria’s North East\n\n\n\n\n\n\n\n                        Podcast\n                      \n\n                                          / Middle East & North Africa\n\nIsrael Goes Back to War in Gaza\n\n\n\n\n\n\n\n                        Commentary\n                      \n\n                                          / Middle East & North Africa\n\nHow Israel’s Overreach in Syria May Backfire\n\n\n\n\n\n\n\n            Sudan\n          \n\n            Read more on Sudan\n            \n\n\n\n\n\n\n\n\n\n\n\n\n\n\n\n\n\n\n                  Statement\n                \n\n                              / Africa\n\nBattle for Khartoum Marks a Crossroads in Sudan’s Civil War\n\n\nThe Sudanese army is pushing to take over Khartoum. Should it prevail, it would record a major victory, though one that would be unlikely to end the country’s devastating conflict. Mediators should keep exploring openings for peace talks. \n\n\n\n\n\n\n\n\n                        Op-Ed\n                      \n\n                                          / Africa\n\nPeace talks remain the only way out of Sudan’s nightmare \n\n\n\n\n\n\n\n                        Podcast\n                      \n\n                                          / Africa\n\nA Decisive Turn in Sudan’s War?\n\n\n\n\n\n\n\n                        Briefing\n                      \n\n                                          / Africa\n\nSudan’s Calamitous War: Finding a Path toward Peace\n\n\n\n\n\n\n\n        Videos & Photography\n      \n\n\n\n \n\n\n\n\n\n\n\n\n\n\n\n\nVideo\n\n                                                / Ukraine\n                                              \n\n\nEuropean Security Three Years On From Russia's Full-scale Invasion of Ukraine\n\n\n\n\n\n \n\n\n\n\n\n\n\n\n\n\n\n\nVideo\n\n                                                / Global\n                                              \n\n\nMapping Conflict\n\n\n\n\n\n \n\n\n\n\n\n\n\n\n\n\n\n\nVideo\n\n                                                / Global\n                                              \n\n\nVIDEO | 10 Conflicts to Watch in 2025\n\n\n\n\n\n \n\n\n\n\n\n\n\n\n\n\n\n\nVideo\n\n                                                / Israel/Palestine\n                                              \n\n\nVideo | The Rise of Israeli Settler Violence in the West Bank\n\n\n\n\n\n \n\n\n\n\n\n\n\n\n\n\n\n\nVideo\n\n                                                / Mali\n                                              \n\n\nIbrahim Maiga on Mali's Sovereign Turn\n\n\n\n\n\n \n\n\n\n\n\n\n\n\n\n\n\n\nVideo\n\n                                                / South East Asia\n                                              \n\n\nThe Mekong's Troubled Waters\n\n\n\n\n\n \n\n\n\n\n\n\n\n\n\n\n\n\nVideo\n\n                                                / Morocco\n                                              \n\n\nAlgeria-Morocco Tensions\n\n\n\n\n\n \n\n\n\n\n\n\n\n\n\n\n\n\nVideo\n\n                                                / Mali\n                                              \n\n\nJean-Hervé Jezequel on Mali’s Sovereign Turn\n\n\n\n\n\n \n\n\n\n\n\n\n\n\n\n\n\n\nVideo\n\n                                                / Saudi Arabia\n                                              \n\n\nAbdulaziz Sager: Saudi Arabia's Perspective on the Escalation in the Middle East\n\n\n\n\n\n \n\n\n\n\n\n\n\n\n\n\n\n\nVideo\n\n                                                / Niger\n                                              \n\n\nLa vie des femmes sous l'État islamique dans l'ouest du Niger\n\n\n\n\n\n\n\n\n\n\n\n        Visual Explainers\n      \n\n\n\n \n\n\n\n\n\n\n\n\nUkraine War Map: Tracking the Frontlines\n\n\n\n \n\n\n\n\n\n\n\n\nVisual Explainer: Ten Conflicts to Watch in 2024\n\n\n\n \n\n\n\n\n\n\n\n\nThe U.S. Containment Strategy in Somalia\n\n\n\n \n\n\n\n\n\n\n\n\nWhich Conflicts Should the UNGA Look at?\n\n\n\n\n\n\n\n\n\n\n        In The News\n      \n\n\n\n\n      4 Apr 2025\n    \n\n            Airstrikes don't directly affect relief efforts [in Myanmar]. But they create a context in which it's clear the regime isn't willing to pause its attacks.\n    \n\n      DW\n      \n\n\n\n\n\n\n\n\n\n\nRichard Horsey\n\nSenior Adviser, Myanmar\n\n\n\n\n\n      3 Apr 2025\n    \n\n            What we're seeing very explicitly from the Israeli political echelon is that they actually want to lay the groundwork and begin moving towards the de-population of Gaza.\n    \n\n      DW\n      \n\n\n\n\n\n\n\n\n\n                      —\n                                Amjad Iraqi\n                  \n\n\n\n\n\n\n\n\n      2 Apr 2025\n    \n\n            There is a red line in the Palestinian national discourse. You don’t criticize armed resistance. To do that will provide the kind of pretext that Israel and the internati...\n    \n\n      AP\n      \n\n\n\n\n\n\n\n\n\n\nTahani Mustafa\n\nSenior Analyst, Palestine\n\n\n\n\n\n      27 Mar 2025\n    \n\n            There are plenty within the opposition who are opposed to the government [in South Sudan]. If this escalates to violence, this could be very decentralised.\n    \n\n      Al Jazeera\n      \n\n\n\n\n\n\n\n\n\n\nDaniel Akech\n\nSenior Analyst, South Sudan\n\n\n\n\n\n\n\n      25 Mar 2025\n    \n\n            The idea that [Israeli] military strikes will pressure Hamas to release hostages without an end to the war [in Gaza] is unrealistic at best, and disingenuous at worst.\n    \n\n      Arab News\n      \n\n\n\n\n\n\n\n\n\n\nMairav Zonszein\n\nSenior Analyst, Israel\n\n\n\n\n\n      24 Mar 2025\n    \n\n            There's obviously a fork in the road ahead after the Sudanese army takes Khartoum. Either more war, or a pivot to try and end this through peace talks.\r\n\n    \n\n      AFP\n      \n\n\n\n\n\n\n\n\n\n\nAlan Boswell\n\nProject Director, Horn of Africa\n\n\n\n\n\n\n\n\n\n\n      Regional Updates\n    \n\n\n\nGlobal \n\n\n\n\n\n\n\n\n\nSpecial Coverage\nOn Our Radar\n\n\n\n\nQ&A\nUnpacking the Use of U.S. Wartime Powers against a Criminal “Invasion”\n\n\nSpecial Coverage\nComfort Ero’s 2025 Top Picks on Gender and Conflict\n\n\n\n\n\nAfrica \n\n\n\n\n\n\n\n\n\nPodcast\nSouth Sudan on the Brink of Another War\n\n\n\n\nAlert\nEthiopia and Eritrea Slide Closer to War amid Tigray Upheaval \n\n\nPodcast\nWhich Way Will Trump Go on Somalia?\n\n\n\n\n\nAsia \n\n\n\n\n\n\n\n\n\nPodcast\nWill Myanmar’s Devastating Earthquake Impact its Civil War?\n\n\n\n\nQ&A\nSupport Vital for Myanmar’s Quake Victims, Despite Military Obstacles \n\n\nBriefing\nDisquiet on the Western Front: A Divided Resistance in Myanmar’s Chin State\n\n\n\n\n\nEurope & Central Asia \n\n\n\n\n\n\n\n\n\nQ&A\nA Glimmer of Peace in Syria’s North East\n\n\n\n\nPodcast\nLatin America’s Evolving Drug Trade. Why It Matters for Europe\n\n\nPodcast\nTrump, France and European Security\n\n\n\n\n\nLatin America & Caribbean \n\n\n\n\n\nQ&A\nUnpacking the Use of U.S. Wartime Powers against a Criminal “Invasion”\n\n\n\nPodcast\nLatin America’s Evolving Drug Trade. Why It Matters for Europe\n\n\nVisual Explainers\nHow a New Drug Trafficking Landscape Fuels Violence in Latin America\n\n\n\n\n\nMiddle East & North Africa \n\n\n\n\n\n\n\n\n\nVisual Explainers\nThe Houthis’ Red Sea Attacks Explained\n\n\n\n\n\n\n\n\nQ&A\nA Glimmer of Peace in Syria’s North East\n\n\n\nBriefing\nThe New Syria: Halting a Dangerous Drift\n\n\n\n\n\nUnited States \n\n\n\n\n\n\n\n\n\nQ&A\nA Glimmer of Peace in Syria’s North East\n\n\n\n\nPodcast\nWhich Way Will Trump Go on Somalia?\n\n\nQ&A\nUnpacking the Use of U.S. Wartime Powers against a Criminal “Invasion”\n\n\n\n\n\n\n\n\n\nSupport Us\n\nYour investment helps us to meet the growing demand for our work as we confront a terrible trend toward more wars, more civilians killed and more people displaced worldwide.\n\n\n        Donate now\n      \n\n        Learn What We Do\n        \n\n\n\n\n\n    Our Supporters\n  \n\n\n\n\n\nAustralia (Department of Foreign Affairs and Trade)\n\n\n\n\n\nAustria (Austrian Development Agency)\n\n\n\n\n\nCanada (Global Affairs Canada and Canadian Department of National Defence)\n\n\n\n\n\nCarnegie Corporation of New York\n\n\n\n\n\nChevron\n\n\n\n\n\nChris Bake\n\n\n\n\n\nDenmark (Ministry of Foreign Affairs)\n\n\n\n\n\nEni\n\n\n\n\n\nEuropean Union (Instrument contributing to Stability and Peace, Emergency Trust Fund for Africa)\n\n\n\n\n\nFinland (Ministry for Foreign Affairs)\n\n\n\n\n\nFrance (Ministry of Foreign Affairs and French Development Agency)\n\n\n\n\n\nFrank Giustra\n\n\n\n\n\nGlobal Challenges Foundation\n\n\n\n\n\nHerman De Bode\n\n\n\n\n\nIreland (Department of Foreign Affairs)\n\n\n\n\n\nLuxembourg (Ministry of Foreign and European Affairs)\n\n\n\n\n\nNeil Woodyer\n\n\n\n\n\nNew Zealand (Ministry of Foreign Affairs and Trade)\n\n\n\n\n\nNorway (Ministry of Foreign Affairs)\n\n\n\n\n\nOpen Society Foundations\n\n\n\n\n\nQatar (Ministry of Foreign Affairs)\n\n\n\n\n\nRobert Bosch Stiftung\n\n\n\n\n\nRockefeller Brothers Fund\n\n\n\n\n\nStand Together Trust\n\n\n\n\n\nStiftung Mercator\n\n\n\n\n\nSweden (Ministry of Foreign Affairs)\n\n\n\n\n\nSwitzerland (Federal Department of Foreign Affairs)\n\n\n\n\n\nThe Bergman Family Foundation\n\n\n\n\n\nThe Netherlands (Ministry of Foreign Affairs)\n\n\n\n\n\nUnited Arab Emirates (Ministry of Foreign Affairs and International Cooperation and Anwar Gargash Diplomatic Academy)\n\n\n\n\n\nWadah Khanfar\n\n\n\n\n        Learn more about supporting Crisis Group\n\nQ&A\n                    / Myanmar\n\n\n\nSupport Vital for Myanmar’s Quake Victims, Despite Military Obstacles \n\n\n\nThe massive earthquake in Myanmar has taken a terrible toll. In this Q&A, Crisis Group expert Richard Horsey discusses the urgent need for international assistance, the challenges facing aid delivery against a backdrop of civil war and the importance of a humanitarian pause in fighting.\n\nQ&A\n                    / Myanmar\n\n\n\nSupport Vital for Myanmar’s Quake Victims, Despite Military Obstacles \n\n\n\nThe massive earthquake in Myanmar has taken a terrible toll. In this Q&A, Crisis Group expert Richard Horsey discusses the urgent need for international assistance, the challenges facing aid delivery against a backdrop of civil war and the importance of a humanitarian pause in fighting.\n\nQ&A\n                    / Myanmar\n\nThe massive earthquake in Myanmar has taken a terrible toll. In this Q&A, Crisis Group expert Richard Horsey discusses the urgent need for international assistance, the challenges facing aid delivery against a backdrop of civil war and the importance of a humanitarian pause in fighting.\n\nThe massive earthquake in Myanmar has taken a terrible toll. In this Q&A, Crisis Group expert Richard Horsey discusses the urgent need for international assistance, the challenges facing aid delivery against a backdrop of civil war and the importance of a humanitarian pause in fighting.\n\nWill Myanmar’s Devastating Earthquake Impact its Civil War?\n\n\n\n\n\n\n\nPodcast\n\n                                  / Asia\n\n\n\n                \n                Will Myanmar’s Devastating Earthquake Impact its Civil War?\n              \n\n\nThis week on Hold Your Fire!, Richard Atwood speaks with Crisis Group’s Myanmar expert Richard Horsey about the devastating earthquake that struck Myanmar last week, challenges facing relief efforts and implications for the country’s civil war and its military leaders.\n\n\n\n\n\n\n\nThe Houthis’ Red Sea Attacks Explained\n\n\n\n\n\n\nVisual Explainers\n\n                                  / Middle East & North Africa\n\n\n\n                \n                The Houthis’ Red Sea Attacks Explained\n              \n\n\n\n\n\n\nThe New Syria: Halting a Dangerous Drift\n\n\n\n\n\n\nBriefing\n\n                                  / Middle East & North Africa\n\n\n\n                \n                The New Syria: Halting a Dangerous Drift\n              \n\n\n\n\n\n                Also available in Arabic\n\n\n\n\n\n\nMarch Trends and April Alerts 2025\n\n\n\n\n\n\n                \n                March Trends and April Alerts 2025\n              \n\n\n\n\n\n\n\n            Middle East Tensions\n          \n\n            Read more on the issue\n            \n\n\n\n\n\n\n\n\n\n\n\n\n\n\n\n\n\n\n                  Alert\n                \n\n                              / Middle East & North Africa\n\nStopping Israel’s War in Gaza\n\n\nOn 18 March, Israel resumed bombing Gaza, upending a two-month ceasefire. Returning to war promises little but more death and destruction. The U.S. should insist on restoring the truce and endorse the Arab League plan for Gaza as the basis for a more permanent peace.\n\n\n\n\n\n\n\n\n                        Q&A\n                      \n\n                                          / Middle East & North Africa\n\nA Glimmer of Peace in Syria’s North East\n\n\n\n\n\n\n\n                        Podcast\n                      \n\n                                          / Middle East & North Africa\n\nIsrael Goes Back to War in Gaza\n\n\n\n\n\n\n\n                        Commentary\n                      \n\n                                          / Middle East & North Africa\n\nHow Israel’s Overreach in Syria May Backfire\n\n\n\n\n\n\n\n            Sudan\n          \n\n            Read more on Sudan\n            \n\n\n\n\n\n\n\n\n\n\n\n\n\n\n\n\n\n\n                  Statement\n                \n\n                              / Africa\n\nBattle for Khartoum Marks a Crossroads in Sudan’s Civil War\n\n\nThe Sudanese army is pushing to take over Khartoum. Should it prevail, it would record a major victory, though one that would be unlikely to end the country’s devastating conflict. Mediators should keep exploring openings for peace talks. \n\n\n\n\n\n\n\n\n                        Op-Ed\n                      \n\n                                          / Africa\n\nPeace talks remain the only way out of Sudan’s nightmare \n\n\n\n\n\n\n\n                        Podcast\n                      \n\n                                          / Africa\n\nA Decisive Turn in Sudan’s War?\n\n\n\n\n\n\n\n                        Briefing\n                      \n\n                                          / Africa\n\nSudan’s Calamitous War: Finding a Path toward Peace\n\n\n\n\n\n\n\n        Videos & Photography\n      \n\n\n\n \n\n\n\n\n\n\n\n\n\n\n\n\nVideo\n\n                                                / Ukraine\n                                              \n\n\nEuropean Security Three Years On From Russia's Full-scale Invasion of Ukraine\n\n\n\n\n\n \n\n\n\n\n\n\n\n\n\n\n\n\nVideo\n\n                                                / Global\n                                              \n\n\nMapping Conflict\n\n\n\n\n\n \n\n\n\n\n\n\n\n\n\n\n\n\nVideo\n\n                                                / Global\n                                              \n\n\nVIDEO | 10 Conflicts to Watch in 2025\n\n\n\n\n\n \n\n\n\n\n\n\n\n\n\n\n\n\nVideo\n\n                                                / Israel/Palestine\n                                              \n\n\nVideo | The Rise of Israeli Settler Violence in the West Bank\n\n\n\n\n\n \n\n\n\n\n\n\n\n\n\n\n\n\nVideo\n\n                                                / Mali\n                                              \n\n\nIbrahim Maiga on Mali's Sovereign Turn\n\n\n\n\n\n \n\n\n\n\n\n\n\n\n\n\n\n\nVideo\n\n                                                / South East Asia\n                                              \n\n\nThe Mekong's Troubled Waters\n\n\n\n\n\n \n\n\n\n\n\n\n\n\n\n\n\n\nVideo\n\n                                                / Morocco\n                                              \n\n\nAlgeria-Morocco Tensions\n\n\n\n\n\n \n\n\n\n\n\n\n\n\n\n\n\n\nVideo\n\n                                                / Mali\n                                              \n\n\nJean-Hervé Jezequel on Mali’s Sovereign Turn\n\n\n\n\n\n \n\n\n\n\n\n\n\n\n\n\n\n\nVideo\n\n                                                / Saudi Arabia\n                                              \n\n\nAbdulaziz Sager: Saudi Arabia's Perspective on the Escalation in the Middle East\n\n\n\n\n\n \n\n\n\n\n\n\n\n\n\n\n\n\nVideo\n\n                                                / Niger\n                                              \n\n\nLa vie des femmes sous l'État islamique dans l'ouest du Niger\n\n\n\n\n\n\n\n\n\n\n\n        Visual Explainers\n      \n\n\n\n \n\n\n\n\n\n\n\n\nUkraine War Map: Tracking the Frontlines\n\n\n\n \n\n\n\n\n\n\n\n\nVisual Explainer: Ten Conflicts to Watch in 2024\n\n\n\n \n\n\n\n\n\n\n\n\nThe U.S. Containment Strategy in Somalia\n\n\n\n \n\n\n\n\n\n\n\n\nWhich Conflicts Should the UNGA Look at?\n\n\n\n\n\n\n\n\n\n\n        In The News\n      \n\n\n\n\n      4 Apr 2025\n    \n\n            Airstrikes don't directly affect relief efforts [in Myanmar]. But they create a context in which it's clear the regime isn't willing to pause its attacks.\n    \n\n      DW\n      \n\n\n\n\n\n\n\n\n\n\nRichard Horsey\n\nSenior Adviser, Myanmar\n\n\n\n\n\n      3 Apr 2025\n    \n\n            What we're seeing very explicitly from the Israeli political echelon is that they actually want to lay the groundwork and begin moving towards the de-population of Gaza.\n    \n\n      DW\n      \n\n\n\n\n\n\n\n\n\n                      —\n                                Amjad Iraqi\n                  \n\n\n\n\n\n\n\n\n      2 Apr 2025\n    \n\n            There is a red line in the Palestinian national discourse. You don’t criticize armed resistance. To do that will provide the kind of pretext that Israel and the internati...\n    \n\n      AP\n      \n\n\n\n\n\n\n\n\n\n\nTahani Mustafa\n\nSenior Analyst, Palestine\n\n\n\n\n\n      27 Mar 2025\n    \n\n            There are plenty within the opposition who are opposed to the government [in South Sudan]. If this escalates to violence, this could be very decentralised.\n    \n\n      Al Jazeera\n      \n\n\n\n\n\n\n\n\n\n\nDaniel Akech\n\nSenior Analyst, South Sudan\n\n\n\n\n\n\n\n      25 Mar 2025\n    \n\n            The idea that [Israeli] military strikes will pressure Hamas to release hostages without an end to the war [in Gaza] is unrealistic at best, and disingenuous at worst.\n    \n\n      Arab News\n      \n\n\n\n\n\n\n\n\n\n\nMairav Zonszein\n\nSenior Analyst, Israel\n\n\n\n\n\n      24 Mar 2025\n    \n\n            There's obviously a fork in the road ahead after the Sudanese army takes Khartoum. Either more war, or a pivot to try and end this through peace talks.\r\n\n    \n\n      AFP\n      \n\n\n\n\n\n\n\n\n\n\nAlan Boswell\n\nProject Director, Horn of Africa\n\n\n\n\n\n\n\n\n\n\n      Regional Updates\n    \n\n\n\nGlobal \n\n\n\n\n\n\n\n\n\nSpecial Coverage\nOn Our Radar\n\n\n\n\nQ&A\nUnpacking the Use of U.S. Wartime Powers against a Criminal “Invasion”\n\n\nSpecial Coverage\nComfort Ero’s 2025 Top Picks on Gender and Conflict\n\n\n\n\n\nAfrica \n\n\n\n\n\n\n\n\n\nPodcast\nSouth Sudan on the Brink of Another War\n\n\n\n\nAlert\nEthiopia and Eritrea Slide Closer to War amid Tigray Upheaval \n\n\nPodcast\nWhich Way Will Trump Go on Somalia?\n\n\n\n\n\nAsia \n\n\n\n\n\n\n\n\n\nPodcast\nWill Myanmar’s Devastating Earthquake Impact its Civil War?\n\n\n\n\nQ&A\nSupport Vital for Myanmar’s Quake Victims, Despite Military Obstacles \n\n\nBriefing\nDisquiet on the Western Front: A Divided Resistance in Myanmar’s Chin State\n\n\n\n\n\nEurope & Central Asia \n\n\n\n\n\n\n\n\n\nQ&A\nA Glimmer of Peace in Syria’s North East\n\n\n\n\nPodcast\nLatin America’s Evolving Drug Trade. Why It Matters for Europe\n\n\nPodcast\nTrump, France and European Security\n\n\n\n\n\nLatin America & Caribbean \n\n\n\n\n\nQ&A\nUnpacking the Use of U.S. Wartime Powers against a Criminal “Invasion”\n\n\n\nPodcast\nLatin America’s Evolving Drug Trade. Why It Matters for Europe\n\n\nVisual Explainers\nHow a New Drug Trafficking Landscape Fuels Violence in Latin America\n\n\n\n\n\nMiddle East & North Africa \n\n\n\n\n\n\n\n\n\nVisual Explainers\nThe Houthis’ Red Sea Attacks Explained\n\n\n\n\n\n\n\n\nQ&A\nA Glimmer of Peace in Syria’s North East\n\n\n\nBriefing\nThe New Syria: Halting a Dangerous Drift\n\n\n\n\n\nUnited States \n\n\n\n\n\n\n\n\n\nQ&A\nA Glimmer of Peace in Syria’s North East\n\n\n\n\nPodcast\nWhich Way Will Trump Go on Somalia?\n\n\nQ&A\nUnpacking the Use of U.S. Wartime Powers against a Criminal “Invasion”\n\n\n\n\n\n\n\n\n\nSupport Us\n\nYour investment helps us to meet the growing demand for our work as we confront a terrible trend toward more wars, more civilians killed and more people displaced worldwide.\n\n\n        Donate now\n      \n\n        Learn What We Do\n        \n\n\n\n\n\n    Our Supporters\n  \n\n\n\n\n\nAustralia (Department of Foreign Affairs and Trade)\n\n\n\n\n\nAustria (Austrian Development Agency)\n\n\n\n\n\nCanada (Global Affairs Canada and Canadian Department of National Defence)\n\n\n\n\n\nCarnegie Corporation of New York\n\n\n\n\n\nChevron\n\n\n\n\n\nChris Bake\n\n\n\n\n\nDenmark (Ministry of Foreign Affairs)\n\n\n\n\n\nEni\n\n\n\n\n\nEuropean Union (Instrument contributing to Stability and Peace, Emergency Trust Fund for Africa)\n\n\n\n\n\nFinland (Ministry for Foreign Affairs)\n\n\n\n\n\nFrance (Ministry of Foreign Affairs and French Development Agency)\n\n\n\n\n\nFrank Giustra\n\n\n\n\n\nGlobal Challenges Foundation\n\n\n\n\n\nHerman De Bode\n\n\n\n\n\nIreland (Department of Foreign Affairs)\n\n\n\n\n\nLuxembourg (Ministry of Foreign and European Affairs)\n\n\n\n\n\nNeil Woodyer\n\n\n\n\n\nNew Zealand (Ministry of Foreign Affairs and Trade)\n\n\n\n\n\nNorway (Ministry of Foreign Affairs)\n\n\n\n\n\nOpen Society Foundations\n\n\n\n\n\nQatar (Ministry of Foreign Affairs)\n\n\n\n\n\nRobert Bosch Stiftung\n\n\n\n\n\nRockefeller Brothers Fund\n\n\n\n\n\nStand Together Trust\n\n\n\n\n\nStiftung Mercator\n\n\n\n\n\nSweden (Ministry of Foreign Affairs)\n\n\n\n\n\nSwitzerland (Federal Department of Foreign Affairs)\n\n\n\n\n\nThe Bergman Family Foundation\n\n\n\n\n\nThe Netherlands (Ministry of Foreign Affairs)\n\n\n\n\n\nUnited Arab Emirates (Ministry of Foreign Affairs and International Cooperation and Anwar Gargash Diplomatic Academy)\n\n\n\n\n\nWadah Khanfar\n\n\n\n\n        Learn more about supporting Crisis Group\n\nWill Myanmar’s Devastating Earthquake Impact its Civil War?\n\n\n\n\n\n\n\nPodcast\n\n                                  / Asia\n\n\n\n                \n                Will Myanmar’s Devastating Earthquake Impact its Civil War?\n              \n\n\nThis week on Hold Your Fire!, Richard Atwood speaks with Crisis Group’s Myanmar expert Richard Horsey about the devastating earthquake that struck Myanmar last week, challenges facing relief efforts and implications for the country’s civil war and its military leaders.\n\n\n\n\n\n\n\nThe Houthis’ Red Sea Attacks Explained\n\n\n\n\n\n\nVisual Explainers\n\n                                  / Middle East & North Africa\n\n\n\n                \n                The Houthis’ Red Sea Attacks Explained\n              \n\n\n\n\n\n\nThe New Syria: Halting a Dangerous Drift\n\n\n\n\n\n\nBriefing\n\n                                  / Middle East & North Africa\n\n\n\n                \n                The New Syria: Halting a Dangerous Drift\n              \n\n\n\n\n\n                Also available in Arabic\n\n\n\n\n\n\nMarch Trends and April Alerts 2025\n\n\n\n\n\n\n                \n                March Trends and April Alerts 2025\n\nWill Myanmar’s Devastating Earthquake Impact its Civil War?\n\n\n\n\n\n\n\nPodcast\n\n                                  / Asia\n\n\n\n                \n                Will Myanmar’s Devastating Earthquake Impact its Civil War?\n              \n\n\nThis week on Hold Your Fire!, Richard Atwood speaks with Crisis Group’s Myanmar expert Richard Horsey about the devastating earthquake that struck Myanmar last week, challenges facing relief efforts and implications for the country’s civil war and its military leaders.\n\nWill Myanmar’s Devastating Earthquake Impact its Civil War?\n\nWill Myanmar’s Devastating Earthquake Impact its Civil War?\n\nPodcast\n\n                                  / Asia\n\n\n\n                \n                Will Myanmar’s Devastating Earthquake Impact its Civil War?\n              \n\n\nThis week on Hold Your Fire!, Richard Atwood speaks with Crisis Group’s Myanmar expert Richard Horsey about the devastating earthquake that struck Myanmar last week, challenges facing relief efforts and implications for the country’s civil war and its military leaders.\n\nPodcast\n\n                                  / Asia\n\n\n\n                \n                Will Myanmar’s Devastating Earthquake Impact its Civil War?\n              \n\n\nThis week on Hold Your Fire!, Richard Atwood speaks with Crisis Group’s Myanmar expert Richard Horsey about the devastating earthquake that struck Myanmar last week, challenges facing relief efforts and implications for the country’s civil war and its military leaders.\n\nPodcast\n\n                                  / Asia\n\nThis week on Hold Your Fire!, Richard Atwood speaks with Crisis Group’s Myanmar expert Richard Horsey about the devastating earthquake that struck Myanmar last week, challenges facing relief efforts and implications for the country’s civil war and its military leaders.\n\nThis week on Hold Your Fire!, Richard Atwood speaks with Crisis Group’s Myanmar expert Richard Horsey about the devastating earthquake that struck Myanmar last week, challenges facing relief efforts and implications for the country’s civil war and its military leaders.\n\nThe Houthis’ Red Sea Attacks Explained\n\n\n\n\n\n\nVisual Explainers\n\n                                  / Middle East & North Africa\n\n\n\n                \n                The Houthis’ Red Sea Attacks Explained\n\nThe Houthis’ Red Sea Attacks Explained\n\nThe Houthis’ Red Sea Attacks Explained\n\nVisual Explainers\n\n                                  / Middle East & North Africa\n\n\n\n                \n                The Houthis’ Red Sea Attacks Explained\n\nVisual Explainers\n\n                                  / Middle East & North Africa\n\nThe New Syria: Halting a Dangerous Drift\n\n\n\n\n\n\nBriefing\n\n                                  / Middle East & North Africa\n\n\n\n                \n                The New Syria: Halting a Dangerous Drift\n              \n\n\n\n\n\n                Also available in Arabic\n\nThe New Syria: Halting a Dangerous Drift\n\nThe New Syria: Halting a Dangerous Drift\n\nBriefing\n\n                                  / Middle East & North Africa\n\n\n\n                \n                The New Syria: Halting a Dangerous Drift\n              \n\n\n\n\n\n                Also available in Arabic\n\nBriefing\n\n                                  / Middle East & North Africa\n\nAlso available in Arabic\n\nMarch Trends and April Alerts 2025\n\n\n\n\n\n\n                \n                March Trends and April Alerts 2025\n\nMarch Trends and April Alerts 2025\n\nMarch Trends and April Alerts 2025\n\nMarch Trends and April Alerts 2025\n\nMiddle East Tensions\n          \n\n            Read more on the issue\n            \n\n\n\n\n\n\n\n\n\n\n\n\n\n\n\n\n\n\n                  Alert\n                \n\n                              / Middle East & North Africa\n\nStopping Israel’s War in Gaza\n\n\nOn 18 March, Israel resumed bombing Gaza, upending a two-month ceasefire. Returning to war promises little but more death and destruction. The U.S. should insist on restoring the truce and endorse the Arab League plan for Gaza as the basis for a more permanent peace.\n\n\n\n\n\n\n\n\n                        Q&A\n                      \n\n                                          / Middle East & North Africa\n\nA Glimmer of Peace in Syria’s North East\n\n\n\n\n\n\n\n                        Podcast\n                      \n\n                                          / Middle East & North Africa\n\nIsrael Goes Back to War in Gaza\n\n\n\n\n\n\n\n                        Commentary\n                      \n\n                                          / Middle East & North Africa\n\nHow Israel’s Overreach in Syria May Backfire\n\nMiddle East Tensions\n          \n\n            Read more on the issue\n\nAlert\n                \n\n                              / Middle East & North Africa\n\nStopping Israel’s War in Gaza\n\n\nOn 18 March, Israel resumed bombing Gaza, upending a two-month ceasefire. Returning to war promises little but more death and destruction. The U.S. should insist on restoring the truce and endorse the Arab League plan for Gaza as the basis for a more permanent peace.\n\nAlert\n                \n\n                              / Middle East & North Africa\n\nStopping Israel’s War in Gaza\n\nAlert\n                \n\n                              / Middle East & North Africa\n\nOn 18 March, Israel resumed bombing Gaza, upending a two-month ceasefire. Returning to war promises little but more death and destruction. The U.S. should insist on restoring the truce and endorse the Arab League plan for Gaza as the basis for a more permanent peace.\n\nOn 18 March, Israel resumed bombing Gaza, upending a two-month ceasefire. Returning to war promises little but more death and destruction. The U.S. should insist on restoring the truce and endorse the Arab League plan for Gaza as the basis for a more permanent peace.\n\nQ&A\n                      \n\n                                          / Middle East & North Africa\n\nA Glimmer of Peace in Syria’s North East\n\n\n\n\n\n\n\n                        Podcast\n                      \n\n                                          / Middle East & North Africa\n\nIsrael Goes Back to War in Gaza\n\n\n\n\n\n\n\n                        Commentary\n                      \n\n                                          / Middle East & North Africa\n\nHow Israel’s Overreach in Syria May Backfire\n\nQ&A\n                      \n\n                                          / Middle East & North Africa\n\nA Glimmer of Peace in Syria’s North East\n\nQ&A\n                      \n\n                                          / Middle East & North Africa\n\nA Glimmer of Peace in Syria’s North East\n\nQ&A\n                      \n\n                                          / Middle East & North Africa\n\nPodcast\n                      \n\n                                          / Middle East & North Africa\n\nIsrael Goes Back to War in Gaza\n\nPodcast\n                      \n\n                                          / Middle East & North Africa\n\nIsrael Goes Back to War in Gaza\n\nPodcast\n                      \n\n                                          / Middle East & North Africa\n\nCommentary\n                      \n\n                                          / Middle East & North Africa\n\nHow Israel’s Overreach in Syria May Backfire\n\nCommentary\n                      \n\n                                          / Middle East & North Africa\n\nHow Israel’s Overreach in Syria May Backfire\n\nCommentary\n                      \n\n                                          / Middle East & North Africa\n\nSudan\n          \n\n            Read more on Sudan\n            \n\n\n\n\n\n\n\n\n\n\n\n\n\n\n\n\n\n\n                  Statement\n                \n\n                              / Africa\n\nBattle for Khartoum Marks a Crossroads in Sudan’s Civil War\n\n\nThe Sudanese army is pushing to take over Khartoum. Should it prevail, it would record a major victory, though one that would be unlikely to end the country’s devastating conflict. Mediators should keep exploring openings for peace talks. \n\n\n\n\n\n\n\n\n                        Op-Ed\n                      \n\n                                          / Africa\n\nPeace talks remain the only way out of Sudan’s nightmare \n\n\n\n\n\n\n\n                        Podcast\n                      \n\n                                          / Africa\n\nA Decisive Turn in Sudan’s War?\n\n\n\n\n\n\n\n                        Briefing\n                      \n\n                                          / Africa\n\nSudan’s Calamitous War: Finding a Path toward Peace\n\nSudan\n          \n\n            Read more on Sudan\n\nStatement\n                \n\n                              / Africa\n\nBattle for Khartoum Marks a Crossroads in Sudan’s Civil War\n\n\nThe Sudanese army is pushing to take over Khartoum. Should it prevail, it would record a major victory, though one that would be unlikely to end the country’s devastating conflict. Mediators should keep exploring openings for peace talks.\n\nStatement\n                \n\n                              / Africa\n\nBattle for Khartoum Marks a Crossroads in Sudan’s Civil War\n\nStatement\n                \n\n                              / Africa\n\nThe Sudanese army is pushing to take over Khartoum. Should it prevail, it would record a major victory, though one that would be unlikely to end the country’s devastating conflict. Mediators should keep exploring openings for peace talks.\n\nThe Sudanese army is pushing to take over Khartoum. Should it prevail, it would record a major victory, though one that would be unlikely to end the country’s devastating conflict. Mediators should keep exploring openings for peace talks.\n\nOp-Ed\n                      \n\n                                          / Africa\n\nPeace talks remain the only way out of Sudan’s nightmare \n\n\n\n\n\n\n\n                        Podcast\n                      \n\n                                          / Africa\n\nA Decisive Turn in Sudan’s War?\n\n\n\n\n\n\n\n                        Briefing\n                      \n\n                                          / Africa\n\nSudan’s Calamitous War: Finding a Path toward Peace\n\nOp-Ed\n                      \n\n                                          / Africa\n\nPeace talks remain the only way out of Sudan’s nightmare\n\nOp-Ed\n                      \n\n                                          / Africa\n\nPeace talks remain the only way out of Sudan’s nightmare\n\nOp-Ed\n                      \n\n                                          / Africa\n\nPodcast\n                      \n\n                                          / Africa\n\nA Decisive Turn in Sudan’s War?\n\nPodcast\n                      \n\n                                          / Africa\n\nA Decisive Turn in Sudan’s War?\n\nPodcast\n                      \n\n                                          / Africa\n\nBriefing\n                      \n\n                                          / Africa\n\nSudan’s Calamitous War: Finding a Path toward Peace\n\nBriefing\n                      \n\n                                          / Africa\n\nSudan’s Calamitous War: Finding a Path toward Peace\n\nBriefing\n                      \n\n                                          / Africa\n\nVideos & Photography\n      \n\n\n\n \n\n\n\n\n\n\n\n\n\n\n\n\nVideo\n\n                                                / Ukraine\n                                              \n\n\nEuropean Security Three Years On From Russia's Full-scale Invasion of Ukraine\n\n\n\n\n\n \n\n\n\n\n\n\n\n\n\n\n\n\nVideo\n\n                                                / Global\n                                              \n\n\nMapping Conflict\n\n\n\n\n\n \n\n\n\n\n\n\n\n\n\n\n\n\nVideo\n\n                                                / Global\n                                              \n\n\nVIDEO | 10 Conflicts to Watch in 2025\n\n\n\n\n\n \n\n\n\n\n\n\n\n\n\n\n\n\nVideo\n\n                                                / Israel/Palestine\n                                              \n\n\nVideo | The Rise of Israeli Settler Violence in the West Bank\n\n\n\n\n\n \n\n\n\n\n\n\n\n\n\n\n\n\nVideo\n\n                                                / Mali\n                                              \n\n\nIbrahim Maiga on Mali's Sovereign Turn\n\n\n\n\n\n \n\n\n\n\n\n\n\n\n\n\n\n\nVideo\n\n                                                / South East Asia\n                                              \n\n\nThe Mekong's Troubled Waters\n\n\n\n\n\n \n\n\n\n\n\n\n\n\n\n\n\n\nVideo\n\n                                                / Morocco\n                                              \n\n\nAlgeria-Morocco Tensions\n\n\n\n\n\n \n\n\n\n\n\n\n\n\n\n\n\n\nVideo\n\n                                                / Mali\n                                              \n\n\nJean-Hervé Jezequel on Mali’s Sovereign Turn\n\n\n\n\n\n \n\n\n\n\n\n\n\n\n\n\n\n\nVideo\n\n                                                / Saudi Arabia\n                                              \n\n\nAbdulaziz Sager: Saudi Arabia's Perspective on the Escalation in the Middle East\n\n\n\n\n\n \n\n\n\n\n\n\n\n\n\n\n\n\nVideo\n\n                                                / Niger\n                                              \n\n\nLa vie des femmes sous l'État islamique dans l'ouest du Niger\n\nVideos & Photography\n      \n\n\n\n \n\n\n\n\n\n\n\n\n\n\n\n\nVideo\n\n                                                / Ukraine\n                                              \n\n\nEuropean Security Three Years On From Russia's Full-scale Invasion of Ukraine\n\n\n\n\n\n \n\n\n\n\n\n\n\n\n\n\n\n\nVideo\n\n                                                / Global\n                                              \n\n\nMapping Conflict\n\n\n\n\n\n \n\n\n\n\n\n\n\n\n\n\n\n\nVideo\n\n                                                / Global\n                                              \n\n\nVIDEO | 10 Conflicts to Watch in 2025\n\n\n\n\n\n \n\n\n\n\n\n\n\n\n\n\n\n\nVideo\n\n                                                / Israel/Palestine\n                                              \n\n\nVideo | The Rise of Israeli Settler Violence in the West Bank\n\n\n\n\n\n \n\n\n\n\n\n\n\n\n\n\n\n\nVideo\n\n                                                / Mali\n                                              \n\n\nIbrahim Maiga on Mali's Sovereign Turn\n\n\n\n\n\n \n\n\n\n\n\n\n\n\n\n\n\n\nVideo\n\n                                                / South East Asia\n                                              \n\n\nThe Mekong's Troubled Waters\n\n\n\n\n\n \n\n\n\n\n\n\n\n\n\n\n\n\nVideo\n\n                                                / Morocco\n                                              \n\n\nAlgeria-Morocco Tensions\n\n\n\n\n\n \n\n\n\n\n\n\n\n\n\n\n\n\nVideo\n\n                                                / Mali\n                                              \n\n\nJean-Hervé Jezequel on Mali’s Sovereign Turn\n\n\n\n\n\n \n\n\n\n\n\n\n\n\n\n\n\n\nVideo\n\n                                                / Saudi Arabia\n                                              \n\n\nAbdulaziz Sager: Saudi Arabia's Perspective on the Escalation in the Middle East\n\n\n\n\n\n \n\n\n\n\n\n\n\n\n\n\n\n\nVideo\n\n                                                / Niger\n                                              \n\n\nLa vie des femmes sous l'État islamique dans l'ouest du Niger\n\nVideo\n\n                                                / Ukraine\n                                              \n\n\nEuropean Security Three Years On From Russia's Full-scale Invasion of Ukraine\n\n\n\n\n\n \n\n\n\n\n\n\n\n\n\n\n\n\nVideo\n\n                                                / Global\n                                              \n\n\nMapping Conflict\n\n\n\n\n\n \n\n\n\n\n\n\n\n\n\n\n\n\nVideo\n\n                                                / Global\n                                              \n\n\nVIDEO | 10 Conflicts to Watch in 2025\n\n\n\n\n\n \n\n\n\n\n\n\n\n\n\n\n\n\nVideo\n\n                                                / Israel/Palestine\n                                              \n\n\nVideo | The Rise of Israeli Settler Violence in the West Bank\n\n\n\n\n\n \n\n\n\n\n\n\n\n\n\n\n\n\nVideo\n\n                                                / Mali\n                                              \n\n\nIbrahim Maiga on Mali's Sovereign Turn\n\n\n\n\n\n \n\n\n\n\n\n\n\n\n\n\n\n\nVideo\n\n                                                / South East Asia\n                                              \n\n\nThe Mekong's Troubled Waters\n\n\n\n\n\n \n\n\n\n\n\n\n\n\n\n\n\n\nVideo\n\n                                                / Morocco\n                                              \n\n\nAlgeria-Morocco Tensions\n\n\n\n\n\n \n\n\n\n\n\n\n\n\n\n\n\n\nVideo\n\n                                                / Mali\n                                              \n\n\nJean-Hervé Jezequel on Mali’s Sovereign Turn\n\n\n\n\n\n \n\n\n\n\n\n\n\n\n\n\n\n\nVideo\n\n                                                / Saudi Arabia\n                                              \n\n\nAbdulaziz Sager: Saudi Arabia's Perspective on the Escalation in the Middle East\n\n\n\n\n\n \n\n\n\n\n\n\n\n\n\n\n\n\nVideo\n\n                                                / Niger\n                                              \n\n\nLa vie des femmes sous l'État islamique dans l'ouest du Niger\n\nVideo\n\n                                                / Ukraine\n                                              \n\n\nEuropean Security Three Years On From Russia's Full-scale Invasion of Ukraine\n\n\n\n\n\n \n\n\n\n\n\n\n\n\n\n\n\n\nVideo\n\n                                                / Global\n                                              \n\n\nMapping Conflict\n\n\n\n\n\n \n\n\n\n\n\n\n\n\n\n\n\n\nVideo\n\n                                                / Global\n                                              \n\n\nVIDEO | 10 Conflicts to Watch in 2025\n\n\n\n\n\n \n\n\n\n\n\n\n\n\n\n\n\n\nVideo\n\n                                                / Israel/Palestine\n                                              \n\n\nVideo | The Rise of Israeli Settler Violence in the West Bank\n\n\n\n\n\n \n\n\n\n\n\n\n\n\n\n\n\n\nVideo\n\n                                                / Mali\n                                              \n\n\nIbrahim Maiga on Mali's Sovereign Turn\n\n\n\n\n\n \n\n\n\n\n\n\n\n\n\n\n\n\nVideo\n\n                                                / South East Asia\n                                              \n\n\nThe Mekong's Troubled Waters\n\n\n\n\n\n \n\n\n\n\n\n\n\n\n\n\n\n\nVideo\n\n                                                / Morocco\n                                              \n\n\nAlgeria-Morocco Tensions\n\n\n\n\n\n \n\n\n\n\n\n\n\n\n\n\n\n\nVideo\n\n                                                / Mali\n                                              \n\n\nJean-Hervé Jezequel on Mali’s Sovereign Turn\n\n\n\n\n\n \n\n\n\n\n\n\n\n\n\n\n\n\nVideo\n\n                                                / Saudi Arabia\n                                              \n\n\nAbdulaziz Sager: Saudi Arabia's Perspective on the Escalation in the Middle East\n\n\n\n\n\n \n\n\n\n\n\n\n\n\n\n\n\n\nVideo\n\n                                                / Niger\n                                              \n\n\nLa vie des femmes sous l'État islamique dans l'ouest du Niger\n\nVideo\n\n                                                / Ukraine\n                                              \n\n\nEuropean Security Three Years On From Russia's Full-scale Invasion of Ukraine\n\nVideo\n\n                                                / Ukraine\n                                              \n\n\nEuropean Security Three Years On From Russia's Full-scale Invasion of Ukraine\n\nVideo\n\n                                                / Ukraine\n                                              \n\n\nEuropean Security Three Years On From Russia's Full-scale Invasion of Ukraine\n\nVideo\n\n                                                / Ukraine\n\nVideo\n\n                                                / Global\n                                              \n\n\nMapping Conflict\n\nVideo\n\n                                                / Global\n                                              \n\n\nMapping Conflict\n\nVideo\n\n                                                / Global\n                                              \n\n\nMapping Conflict\n\nVideo\n\n                                                / Global\n\nVideo\n\n                                                / Global\n                                              \n\n\nVIDEO | 10 Conflicts to Watch in 2025\n\nVideo\n\n                                                / Global\n                                              \n\n\nVIDEO | 10 Conflicts to Watch in 2025\n\nVideo\n\n                                                / Global\n                                              \n\n\nVIDEO | 10 Conflicts to Watch in 2025\n\nVideo\n\n                                                / Global\n\nVideo\n\n                                                / Israel/Palestine\n                                              \n\n\nVideo | The Rise of Israeli Settler Violence in the West Bank\n\nVideo\n\n                                                / Israel/Palestine\n                                              \n\n\nVideo | The Rise of Israeli Settler Violence in the West Bank\n\nVideo\n\n                                                / Israel/Palestine\n                                              \n\n\nVideo | The Rise of Israeli Settler Violence in the West Bank\n\nVideo\n\n                                                / Israel/Palestine\n\nVideo\n\n                                                / Mali\n                                              \n\n\nIbrahim Maiga on Mali's Sovereign Turn\n\nVideo\n\n                                                / Mali\n                                              \n\n\nIbrahim Maiga on Mali's Sovereign Turn\n\nVideo\n\n                                                / Mali\n                                              \n\n\nIbrahim Maiga on Mali's Sovereign Turn\n\nVideo\n\n                                                / Mali\n\nVideo\n\n                                                / South East Asia\n                                              \n\n\nThe Mekong's Troubled Waters\n\nVideo\n\n                                                / South East Asia\n                                              \n\n\nThe Mekong's Troubled Waters\n\nVideo\n\n                                                / South East Asia\n                                              \n\n\nThe Mekong's Troubled Waters\n\nVideo\n\n                                                / South East Asia\n\nVideo\n\n                                                / Morocco\n                                              \n\n\nAlgeria-Morocco Tensions\n\nVideo\n\n                                                / Morocco\n                                              \n\n\nAlgeria-Morocco Tensions\n\nVideo\n\n                                                / Morocco\n                                              \n\n\nAlgeria-Morocco Tensions\n\nVideo\n\n                                                / Morocco\n\nVideo\n\n                                                / Mali\n                                              \n\n\nJean-Hervé Jezequel on Mali’s Sovereign Turn\n\nVideo\n\n                                                / Mali\n                                              \n\n\nJean-Hervé Jezequel on Mali’s Sovereign Turn\n\nVideo\n\n                                                / Mali\n                                              \n\n\nJean-Hervé Jezequel on Mali’s Sovereign Turn\n\nVideo\n\n                                                / Mali\n\nVideo\n\n                                                / Saudi Arabia\n                                              \n\n\nAbdulaziz Sager: Saudi Arabia's Perspective on the Escalation in the Middle East\n\nVideo\n\n                                                / Saudi Arabia\n                                              \n\n\nAbdulaziz Sager: Saudi Arabia's Perspective on the Escalation in the Middle East\n\nVideo\n\n                                                / Saudi Arabia\n                                              \n\n\nAbdulaziz Sager: Saudi Arabia's Perspective on the Escalation in the Middle East\n\nVideo\n\n                                                / Saudi Arabia\n\nVideo\n\n                                                / Niger\n                                              \n\n\nLa vie des femmes sous l'État islamique dans l'ouest du Niger\n\nVideo\n\n                                                / Niger\n                                              \n\n\nLa vie des femmes sous l'État islamique dans l'ouest du Niger\n\nVideo\n\n                                                / Niger\n                                              \n\n\nLa vie des femmes sous l'État islamique dans l'ouest du Niger\n\nVideo\n\n                                                / Niger\n\nVisual Explainers\n      \n\n\n\n \n\n\n\n\n\n\n\n\nUkraine War Map: Tracking the Frontlines\n\n\n\n \n\n\n\n\n\n\n\n\nVisual Explainer: Ten Conflicts to Watch in 2024\n\n\n\n \n\n\n\n\n\n\n\n\nThe U.S. Containment Strategy in Somalia\n\n\n\n \n\n\n\n\n\n\n\n\nWhich Conflicts Should the UNGA Look at?\n\nVisual Explainers\n      \n\n\n\n \n\n\n\n\n\n\n\n\nUkraine War Map: Tracking the Frontlines\n\n\n\n \n\n\n\n\n\n\n\n\nVisual Explainer: Ten Conflicts to Watch in 2024\n\n\n\n \n\n\n\n\n\n\n\n\nThe U.S. Containment Strategy in Somalia\n\n\n\n \n\n\n\n\n\n\n\n\nWhich Conflicts Should the UNGA Look at?\n\nUkraine War Map: Tracking the Frontlines\n\n\n\n \n\n\n\n\n\n\n\n\nVisual Explainer: Ten Conflicts to Watch in 2024\n\n\n\n \n\n\n\n\n\n\n\n\nThe U.S. Containment Strategy in Somalia\n\n\n\n \n\n\n\n\n\n\n\n\nWhich Conflicts Should the UNGA Look at?\n\nUkraine War Map: Tracking the Frontlines\n\n\n\n \n\n\n\n\n\n\n\n\nVisual Explainer: Ten Conflicts to Watch in 2024\n\n\n\n \n\n\n\n\n\n\n\n\nThe U.S. Containment Strategy in Somalia\n\n\n\n \n\n\n\n\n\n\n\n\nWhich Conflicts Should the UNGA Look at?\n\nUkraine War Map: Tracking the Frontlines\n\nUkraine War Map: Tracking the Frontlines\n\nVisual Explainer: Ten Conflicts to Watch in 2024\n\nVisual Explainer: Ten Conflicts to Watch in 2024\n\nThe U.S. Containment Strategy in Somalia\n\nThe U.S. Containment Strategy in Somalia\n\nWhich Conflicts Should the UNGA Look at?\n\nWhich Conflicts Should the UNGA Look at?\n\nIn The News\n      \n\n\n\n\n      4 Apr 2025\n    \n\n            Airstrikes don't directly affect relief efforts [in Myanmar]. But they create a context in which it's clear the regime isn't willing to pause its attacks.\n    \n\n      DW\n      \n\n\n\n\n\n\n\n\n\n\nRichard Horsey\n\nSenior Adviser, Myanmar\n\n\n\n\n\n      3 Apr 2025\n    \n\n            What we're seeing very explicitly from the Israeli political echelon is that they actually want to lay the groundwork and begin moving towards the de-population of Gaza.\n    \n\n      DW\n      \n\n\n\n\n\n\n\n\n\n                      —\n                                Amjad Iraqi\n                  \n\n\n\n\n\n\n\n\n      2 Apr 2025\n    \n\n            There is a red line in the Palestinian national discourse. You don’t criticize armed resistance. To do that will provide the kind of pretext that Israel and the internati...\n    \n\n      AP\n      \n\n\n\n\n\n\n\n\n\n\nTahani Mustafa\n\nSenior Analyst, Palestine\n\n\n\n\n\n      27 Mar 2025\n    \n\n            There are plenty within the opposition who are opposed to the government [in South Sudan]. If this escalates to violence, this could be very decentralised.\n    \n\n      Al Jazeera\n      \n\n\n\n\n\n\n\n\n\n\nDaniel Akech\n\nSenior Analyst, South Sudan\n\n\n\n\n\n\n\n      25 Mar 2025\n    \n\n            The idea that [Israeli] military strikes will pressure Hamas to release hostages without an end to the war [in Gaza] is unrealistic at best, and disingenuous at worst.\n    \n\n      Arab News\n      \n\n\n\n\n\n\n\n\n\n\nMairav Zonszein\n\nSenior Analyst, Israel\n\n\n\n\n\n      24 Mar 2025\n    \n\n            There's obviously a fork in the road ahead after the Sudanese army takes Khartoum. Either more war, or a pivot to try and end this through peace talks.\r\n\n    \n\n      AFP\n      \n\n\n\n\n\n\n\n\n\n\nAlan Boswell\n\nProject Director, Horn of Africa\n\nIn The News\n      \n\n\n\n\n      4 Apr 2025\n    \n\n            Airstrikes don't directly affect relief efforts [in Myanmar]. But they create a context in which it's clear the regime isn't willing to pause its attacks.\n    \n\n      DW\n      \n\n\n\n\n\n\n\n\n\n\nRichard Horsey\n\nSenior Adviser, Myanmar\n\n\n\n\n\n      3 Apr 2025\n    \n\n            What we're seeing very explicitly from the Israeli political echelon is that they actually want to lay the groundwork and begin moving towards the de-population of Gaza.\n    \n\n      DW\n      \n\n\n\n\n\n\n\n\n\n                      —\n                                Amjad Iraqi\n                  \n\n\n\n\n\n\n\n\n      2 Apr 2025\n    \n\n            There is a red line in the Palestinian national discourse. You don’t criticize armed resistance. To do that will provide the kind of pretext that Israel and the internati...\n    \n\n      AP\n      \n\n\n\n\n\n\n\n\n\n\nTahani Mustafa\n\nSenior Analyst, Palestine\n\n\n\n\n\n      27 Mar 2025\n    \n\n            There are plenty within the opposition who are opposed to the government [in South Sudan]. If this escalates to violence, this could be very decentralised.\n    \n\n      Al Jazeera\n      \n\n\n\n\n\n\n\n\n\n\nDaniel Akech\n\nSenior Analyst, South Sudan\n\n\n\n\n\n\n\n      25 Mar 2025\n    \n\n            The idea that [Israeli] military strikes will pressure Hamas to release hostages without an end to the war [in Gaza] is unrealistic at best, and disingenuous at worst.\n    \n\n      Arab News\n      \n\n\n\n\n\n\n\n\n\n\nMairav Zonszein\n\nSenior Analyst, Israel\n\n\n\n\n\n      24 Mar 2025\n    \n\n            There's obviously a fork in the road ahead after the Sudanese army takes Khartoum. Either more war, or a pivot to try and end this through peace talks.\r\n\n    \n\n      AFP\n      \n\n\n\n\n\n\n\n\n\n\nAlan Boswell\n\nProject Director, Horn of Africa\n\n4 Apr 2025\n    \n\n            Airstrikes don't directly affect relief efforts [in Myanmar]. But they create a context in which it's clear the regime isn't willing to pause its attacks.\n    \n\n      DW\n      \n\n\n\n\n\n\n\n\n\n\nRichard Horsey\n\nSenior Adviser, Myanmar\n\n\n\n\n\n      3 Apr 2025\n    \n\n            What we're seeing very explicitly from the Israeli political echelon is that they actually want to lay the groundwork and begin moving towards the de-population of Gaza.\n    \n\n      DW\n      \n\n\n\n\n\n\n\n\n\n                      —\n                                Amjad Iraqi\n                  \n\n\n\n\n\n\n\n\n      2 Apr 2025\n    \n\n            There is a red line in the Palestinian national discourse. You don’t criticize armed resistance. To do that will provide the kind of pretext that Israel and the internati...\n    \n\n      AP\n      \n\n\n\n\n\n\n\n\n\n\nTahani Mustafa\n\nSenior Analyst, Palestine\n\n\n\n\n\n      27 Mar 2025\n    \n\n            There are plenty within the opposition who are opposed to the government [in South Sudan]. If this escalates to violence, this could be very decentralised.\n    \n\n      Al Jazeera\n      \n\n\n\n\n\n\n\n\n\n\nDaniel Akech\n\nSenior Analyst, South Sudan\n\n\n\n\n\n\n\n      25 Mar 2025\n    \n\n            The idea that [Israeli] military strikes will pressure Hamas to release hostages without an end to the war [in Gaza] is unrealistic at best, and disingenuous at worst.\n    \n\n      Arab News\n      \n\n\n\n\n\n\n\n\n\n\nMairav Zonszein\n\nSenior Analyst, Israel\n\n\n\n\n\n      24 Mar 2025\n    \n\n            There's obviously a fork in the road ahead after the Sudanese army takes Khartoum. Either more war, or a pivot to try and end this through peace talks.\r\n\n    \n\n      AFP\n      \n\n\n\n\n\n\n\n\n\n\nAlan Boswell\n\nProject Director, Horn of Africa\n\n4 Apr 2025\n    \n\n            Airstrikes don't directly affect relief efforts [in Myanmar]. But they create a context in which it's clear the regime isn't willing to pause its attacks.\n    \n\n      DW\n      \n\n\n\n\n\n\n\n\n\n\nRichard Horsey\n\nSenior Adviser, Myanmar\n\n\n\n\n\n      3 Apr 2025\n    \n\n            What we're seeing very explicitly from the Israeli political echelon is that they actually want to lay the groundwork and begin moving towards the de-population of Gaza.\n    \n\n      DW\n      \n\n\n\n\n\n\n\n\n\n                      —\n                                Amjad Iraqi\n\n4 Apr 2025\n    \n\n            Airstrikes don't directly affect relief efforts [in Myanmar]. But they create a context in which it's clear the regime isn't willing to pause its attacks.\n    \n\n      DW\n      \n\n\n\n\n\n\n\n\n\n\nRichard Horsey\n\nSenior Adviser, Myanmar\n\n4 Apr 2025\n\nRichard Horsey\n\nSenior Adviser, Myanmar\n\nRichard Horsey\n\nSenior Adviser, Myanmar\n\nSenior Adviser, Myanmar\n\n3 Apr 2025\n    \n\n            What we're seeing very explicitly from the Israeli political echelon is that they actually want to lay the groundwork and begin moving towards the de-population of Gaza.\n    \n\n      DW\n      \n\n\n\n\n\n\n\n\n\n                      —\n                                Amjad Iraqi\n\n3 Apr 2025\n\n—\n                                Amjad Iraqi\n\n—\n                                Amjad Iraqi\n\n2 Apr 2025\n    \n\n            There is a red line in the Palestinian national discourse. You don’t criticize armed resistance. To do that will provide the kind of pretext that Israel and the internati...\n    \n\n      AP\n      \n\n\n\n\n\n\n\n\n\n\nTahani Mustafa\n\nSenior Analyst, Palestine\n\n\n\n\n\n      27 Mar 2025\n    \n\n            There are plenty within the opposition who are opposed to the government [in South Sudan]. If this escalates to violence, this could be very decentralised.\n    \n\n      Al Jazeera\n      \n\n\n\n\n\n\n\n\n\n\nDaniel Akech\n\nSenior Analyst, South Sudan\n\n2 Apr 2025\n    \n\n            There is a red line in the Palestinian national discourse. You don’t criticize armed resistance. To do that will provide the kind of pretext that Israel and the internati...\n    \n\n      AP\n      \n\n\n\n\n\n\n\n\n\n\nTahani Mustafa\n\nSenior Analyst, Palestine\n\n2 Apr 2025\n\nTahani Mustafa\n\nSenior Analyst, Palestine\n\nTahani Mustafa\n\nSenior Analyst, Palestine\n\nSenior Analyst, Palestine\n\n27 Mar 2025\n    \n\n            There are plenty within the opposition who are opposed to the government [in South Sudan]. If this escalates to violence, this could be very decentralised.\n    \n\n      Al Jazeera\n      \n\n\n\n\n\n\n\n\n\n\nDaniel Akech\n\nSenior Analyst, South Sudan\n\n27 Mar 2025\n\nDaniel Akech\n\nSenior Analyst, South Sudan\n\nDaniel Akech\n\nSenior Analyst, South Sudan\n\nSenior Analyst, South Sudan\n\n25 Mar 2025\n    \n\n            The idea that [Israeli] military strikes will pressure Hamas to release hostages without an end to the war [in Gaza] is unrealistic at best, and disingenuous at worst.\n    \n\n      Arab News\n      \n\n\n\n\n\n\n\n\n\n\nMairav Zonszein\n\nSenior Analyst, Israel\n\n\n\n\n\n      24 Mar 2025\n    \n\n            There's obviously a fork in the road ahead after the Sudanese army takes Khartoum. Either more war, or a pivot to try and end this through peace talks.\r\n\n    \n\n      AFP\n      \n\n\n\n\n\n\n\n\n\n\nAlan Boswell\n\nProject Director, Horn of Africa\n\n25 Mar 2025\n    \n\n            The idea that [Israeli] military strikes will pressure Hamas to release hostages without an end to the war [in Gaza] is unrealistic at best, and disingenuous at worst.\n    \n\n      Arab News\n      \n\n\n\n\n\n\n\n\n\n\nMairav Zonszein\n\nSenior Analyst, Israel\n\n25 Mar 2025\n\nMairav Zonszein\n\nSenior Analyst, Israel\n\nMairav Zonszein\n\nSenior Analyst, Israel\n\nSenior Analyst, Israel\n\n24 Mar 2025\n    \n\n            There's obviously a fork in the road ahead after the Sudanese army takes Khartoum. Either more war, or a pivot to try and end this through peace talks.\r\n\n    \n\n      AFP\n      \n\n\n\n\n\n\n\n\n\n\nAlan Boswell\n\nProject Director, Horn of Africa\n\n24 Mar 2025\n\nAlan Boswell\n\nProject Director, Horn of Africa\n\nAlan Boswell\n\nProject Director, Horn of Africa\n\nProject Director, Horn of Africa\n\nRegional Updates\n    \n\n\n\nGlobal \n\n\n\n\n\n\n\n\n\nSpecial Coverage\nOn Our Radar\n\n\n\n\nQ&A\nUnpacking the Use of U.S. Wartime Powers against a Criminal “Invasion”\n\n\nSpecial Coverage\nComfort Ero’s 2025 Top Picks on Gender and Conflict\n\n\n\n\n\nAfrica \n\n\n\n\n\n\n\n\n\nPodcast\nSouth Sudan on the Brink of Another War\n\n\n\n\nAlert\nEthiopia and Eritrea Slide Closer to War amid Tigray Upheaval \n\n\nPodcast\nWhich Way Will Trump Go on Somalia?\n\n\n\n\n\nAsia \n\n\n\n\n\n\n\n\n\nPodcast\nWill Myanmar’s Devastating Earthquake Impact its Civil War?\n\n\n\n\nQ&A\nSupport Vital for Myanmar’s Quake Victims, Despite Military Obstacles \n\n\nBriefing\nDisquiet on the Western Front: A Divided Resistance in Myanmar’s Chin State\n\n\n\n\n\nEurope & Central Asia \n\n\n\n\n\n\n\n\n\nQ&A\nA Glimmer of Peace in Syria’s North East\n\n\n\n\nPodcast\nLatin America’s Evolving Drug Trade. Why It Matters for Europe\n\n\nPodcast\nTrump, France and European Security\n\n\n\n\n\nLatin America & Caribbean \n\n\n\n\n\nQ&A\nUnpacking the Use of U.S. Wartime Powers against a Criminal “Invasion”\n\n\n\nPodcast\nLatin America’s Evolving Drug Trade. Why It Matters for Europe\n\n\nVisual Explainers\nHow a New Drug Trafficking Landscape Fuels Violence in Latin America\n\n\n\n\n\nMiddle East & North Africa \n\n\n\n\n\n\n\n\n\nVisual Explainers\nThe Houthis’ Red Sea Attacks Explained\n\n\n\n\n\n\n\n\nQ&A\nA Glimmer of Peace in Syria’s North East\n\n\n\nBriefing\nThe New Syria: Halting a Dangerous Drift\n\n\n\n\n\nUnited States \n\n\n\n\n\n\n\n\n\nQ&A\nA Glimmer of Peace in Syria’s North East\n\n\n\n\nPodcast\nWhich Way Will Trump Go on Somalia?\n\n\nQ&A\nUnpacking the Use of U.S. Wartime Powers against a Criminal “Invasion”\n\nGlobal \n\n\n\n\n\n\n\n\n\nSpecial Coverage\nOn Our Radar\n\n\n\n\nQ&A\nUnpacking the Use of U.S. Wartime Powers against a Criminal “Invasion”\n\n\nSpecial Coverage\nComfort Ero’s 2025 Top Picks on Gender and Conflict\n\n\n\n\n\nAfrica \n\n\n\n\n\n\n\n\n\nPodcast\nSouth Sudan on the Brink of Another War\n\n\n\n\nAlert\nEthiopia and Eritrea Slide Closer to War amid Tigray Upheaval \n\n\nPodcast\nWhich Way Will Trump Go on Somalia?\n\n\n\n\n\nAsia \n\n\n\n\n\n\n\n\n\nPodcast\nWill Myanmar’s Devastating Earthquake Impact its Civil War?\n\n\n\n\nQ&A\nSupport Vital for Myanmar’s Quake Victims, Despite Military Obstacles \n\n\nBriefing\nDisquiet on the Western Front: A Divided Resistance in Myanmar’s Chin State\n\n\n\n\n\nEurope & Central Asia \n\n\n\n\n\n\n\n\n\nQ&A\nA Glimmer of Peace in Syria’s North East\n\n\n\n\nPodcast\nLatin America’s Evolving Drug Trade. Why It Matters for Europe\n\n\nPodcast\nTrump, France and European Security\n\n\n\n\n\nLatin America & Caribbean \n\n\n\n\n\nQ&A\nUnpacking the Use of U.S. Wartime Powers against a Criminal “Invasion”\n\n\n\nPodcast\nLatin America’s Evolving Drug Trade. Why It Matters for Europe\n\n\nVisual Explainers\nHow a New Drug Trafficking Landscape Fuels Violence in Latin America\n\n\n\n\n\nMiddle East & North Africa \n\n\n\n\n\n\n\n\n\nVisual Explainers\nThe Houthis’ Red Sea Attacks Explained\n\n\n\n\n\n\n\n\nQ&A\nA Glimmer of Peace in Syria’s North East\n\n\n\nBriefing\nThe New Syria: Halting a Dangerous Drift\n\n\n\n\n\nUnited States \n\n\n\n\n\n\n\n\n\nQ&A\nA Glimmer of Peace in Syria’s North East\n\n\n\n\nPodcast\nWhich Way Will Trump Go on Somalia?\n\n\nQ&A\nUnpacking the Use of U.S. Wartime Powers against a Criminal “Invasion”\n\nGlobal \n\n\n\n\n\n\n\n\n\nSpecial Coverage\nOn Our Radar\n\n\n\n\nQ&A\nUnpacking the Use of U.S. Wartime Powers against a Criminal “Invasion”\n\n\nSpecial Coverage\nComfort Ero’s 2025 Top Picks on Gender and Conflict\n\nSpecial Coverage\nOn Our Radar\n\nQ&A\nUnpacking the Use of U.S. Wartime Powers against a Criminal “Invasion”\n\n\nSpecial Coverage\nComfort Ero’s 2025 Top Picks on Gender and Conflict\n\nQ&A\nUnpacking the Use of U.S. Wartime Powers against a Criminal “Invasion”\n\nSpecial Coverage\nComfort Ero’s 2025 Top Picks on Gender and Conflict\n\nAfrica \n\n\n\n\n\n\n\n\n\nPodcast\nSouth Sudan on the Brink of Another War\n\n\n\n\nAlert\nEthiopia and Eritrea Slide Closer to War amid Tigray Upheaval \n\n\nPodcast\nWhich Way Will Trump Go on Somalia?\n\nPodcast\nSouth Sudan on the Brink of Another War\n\nAlert\nEthiopia and Eritrea Slide Closer to War amid Tigray Upheaval \n\n\nPodcast\nWhich Way Will Trump Go on Somalia?\n\nAlert\nEthiopia and Eritrea Slide Closer to War amid Tigray Upheaval\n\nPodcast\nWhich Way Will Trump Go on Somalia?\n\nAsia \n\n\n\n\n\n\n\n\n\nPodcast\nWill Myanmar’s Devastating Earthquake Impact its Civil War?\n\n\n\n\nQ&A\nSupport Vital for Myanmar’s Quake Victims, Despite Military Obstacles \n\n\nBriefing\nDisquiet on the Western Front: A Divided Resistance in Myanmar’s Chin State\n\nPodcast\nWill Myanmar’s Devastating Earthquake Impact its Civil War?\n\nQ&A\nSupport Vital for Myanmar’s Quake Victims, Despite Military Obstacles \n\n\nBriefing\nDisquiet on the Western Front: A Divided Resistance in Myanmar’s Chin State\n\nQ&A\nSupport Vital for Myanmar’s Quake Victims, Despite Military Obstacles\n\nBriefing\nDisquiet on the Western Front: A Divided Resistance in Myanmar’s Chin State\n\nEurope & Central Asia \n\n\n\n\n\n\n\n\n\nQ&A\nA Glimmer of Peace in Syria’s North East\n\n\n\n\nPodcast\nLatin America’s Evolving Drug Trade. Why It Matters for Europe\n\n\nPodcast\nTrump, France and European Security\n\nQ&A\nA Glimmer of Peace in Syria’s North East\n\nPodcast\nLatin America’s Evolving Drug Trade. Why It Matters for Europe\n\n\nPodcast\nTrump, France and European Security\n\nPodcast\nLatin America’s Evolving Drug Trade. Why It Matters for Europe\n\nPodcast\nTrump, France and European Security\n\nLatin America & Caribbean \n\n\n\n\n\nQ&A\nUnpacking the Use of U.S. Wartime Powers against a Criminal “Invasion”\n\n\n\nPodcast\nLatin America’s Evolving Drug Trade. Why It Matters for Europe\n\n\nVisual Explainers\nHow a New Drug Trafficking Landscape Fuels Violence in Latin America\n\nQ&A\nUnpacking the Use of U.S. Wartime Powers against a Criminal “Invasion”\n\nPodcast\nLatin America’s Evolving Drug Trade. Why It Matters for Europe\n\n\nVisual Explainers\nHow a New Drug Trafficking Landscape Fuels Violence in Latin America\n\nPodcast\nLatin America’s Evolving Drug Trade. Why It Matters for Europe\n\nVisual Explainers\nHow a New Drug Trafficking Landscape Fuels Violence in Latin America\n\nMiddle East & North Africa \n\n\n\n\n\n\n\n\n\nVisual Explainers\nThe Houthis’ Red Sea Attacks Explained\n\n\n\n\n\n\n\n\nQ&A\nA Glimmer of Peace in Syria’s North East\n\n\n\nBriefing\nThe New Syria: Halting a Dangerous Drift\n\nVisual Explainers\nThe Houthis’ Red Sea Attacks Explained\n\nQ&A\nA Glimmer of Peace in Syria’s North East\n\n\n\nBriefing\nThe New Syria: Halting a Dangerous Drift\n\nQ&A\nA Glimmer of Peace in Syria’s North East\n\nBriefing\nThe New Syria: Halting a Dangerous Drift\n\nUnited States \n\n\n\n\n\n\n\n\n\nQ&A\nA Glimmer of Peace in Syria’s North East\n\n\n\n\nPodcast\nWhich Way Will Trump Go on Somalia?\n\n\nQ&A\nUnpacking the Use of U.S. Wartime Powers against a Criminal “Invasion”\n\nQ&A\nA Glimmer of Peace in Syria’s North East\n\nPodcast\nWhich Way Will Trump Go on Somalia?\n\n\nQ&A\nUnpacking the Use of U.S. Wartime Powers against a Criminal “Invasion”\n\nPodcast\nWhich Way Will Trump Go on Somalia?\n\nQ&A\nUnpacking the Use of U.S. Wartime Powers against a Criminal “Invasion”\n\nSupport Us\n\nYour investment helps us to meet the growing demand for our work as we confront a terrible trend toward more wars, more civilians killed and more people displaced worldwide.\n\n\n        Donate now\n      \n\n        Learn What We Do\n        \n\n\n\n\n\n    Our Supporters\n  \n\n\n\n\n\nAustralia (Department of Foreign Affairs and Trade)\n\n\n\n\n\nAustria (Austrian Development Agency)\n\n\n\n\n\nCanada (Global Affairs Canada and Canadian Department of National Defence)\n\n\n\n\n\nCarnegie Corporation of New York\n\n\n\n\n\nChevron\n\n\n\n\n\nChris Bake\n\n\n\n\n\nDenmark (Ministry of Foreign Affairs)\n\n\n\n\n\nEni\n\n\n\n\n\nEuropean Union (Instrument contributing to Stability and Peace, Emergency Trust Fund for Africa)\n\n\n\n\n\nFinland (Ministry for Foreign Affairs)\n\n\n\n\n\nFrance (Ministry of Foreign Affairs and French Development Agency)\n\n\n\n\n\nFrank Giustra\n\n\n\n\n\nGlobal Challenges Foundation\n\n\n\n\n\nHerman De Bode\n\n\n\n\n\nIreland (Department of Foreign Affairs)\n\n\n\n\n\nLuxembourg (Ministry of Foreign and European Affairs)\n\n\n\n\n\nNeil Woodyer\n\n\n\n\n\nNew Zealand (Ministry of Foreign Affairs and Trade)\n\n\n\n\n\nNorway (Ministry of Foreign Affairs)\n\n\n\n\n\nOpen Society Foundations\n\n\n\n\n\nQatar (Ministry of Foreign Affairs)\n\n\n\n\n\nRobert Bosch Stiftung\n\n\n\n\n\nRockefeller Brothers Fund\n\n\n\n\n\nStand Together Trust\n\n\n\n\n\nStiftung Mercator\n\n\n\n\n\nSweden (Ministry of Foreign Affairs)\n\n\n\n\n\nSwitzerland (Federal Department of Foreign Affairs)\n\n\n\n\n\nThe Bergman Family Foundation\n\n\n\n\n\nThe Netherlands (Ministry of Foreign Affairs)\n\n\n\n\n\nUnited Arab Emirates (Ministry of Foreign Affairs and International Cooperation and Anwar Gargash Diplomatic Academy)\n\n\n\n\n\nWadah Khanfar\n\n\n\n\n        Learn more about supporting Crisis Group\n\nSupport Us\n\nYour investment helps us to meet the growing demand for our work as we confront a terrible trend toward more wars, more civilians killed and more people displaced worldwide.\n\n\n        Donate now\n      \n\n        Learn What We Do\n\nSupport Us\n\nYour investment helps us to meet the growing demand for our work as we confront a terrible trend toward more wars, more civilians killed and more people displaced worldwide.\n\n\n        Donate now\n      \n\n        Learn What We Do\n\nYour investment helps us to meet the growing demand for our work as we confront a terrible trend toward more wars, more civilians killed and more people displaced worldwide.\n\nYour investment helps us to meet the growing demand for our work as we confront a terrible trend toward more wars, more civilians killed and more people displaced worldwide.\n\nOur Supporters\n  \n\n\n\n\n\nAustralia (Department of Foreign Affairs and Trade)\n\n\n\n\n\nAustria (Austrian Development Agency)\n\n\n\n\n\nCanada (Global Affairs Canada and Canadian Department of National Defence)\n\n\n\n\n\nCarnegie Corporation of New York\n\n\n\n\n\nChevron\n\n\n\n\n\nChris Bake\n\n\n\n\n\nDenmark (Ministry of Foreign Affairs)\n\n\n\n\n\nEni\n\n\n\n\n\nEuropean Union (Instrument contributing to Stability and Peace, Emergency Trust Fund for Africa)\n\n\n\n\n\nFinland (Ministry for Foreign Affairs)\n\n\n\n\n\nFrance (Ministry of Foreign Affairs and French Development Agency)\n\n\n\n\n\nFrank Giustra\n\n\n\n\n\nGlobal Challenges Foundation\n\n\n\n\n\nHerman De Bode\n\n\n\n\n\nIreland (Department of Foreign Affairs)\n\n\n\n\n\nLuxembourg (Ministry of Foreign and European Affairs)\n\n\n\n\n\nNeil Woodyer\n\n\n\n\n\nNew Zealand (Ministry of Foreign Affairs and Trade)\n\n\n\n\n\nNorway (Ministry of Foreign Affairs)\n\n\n\n\n\nOpen Society Foundations\n\n\n\n\n\nQatar (Ministry of Foreign Affairs)\n\n\n\n\n\nRobert Bosch Stiftung\n\n\n\n\n\nRockefeller Brothers Fund\n\n\n\n\n\nStand Together Trust\n\n\n\n\n\nStiftung Mercator\n\n\n\n\n\nSweden (Ministry of Foreign Affairs)\n\n\n\n\n\nSwitzerland (Federal Department of Foreign Affairs)\n\n\n\n\n\nThe Bergman Family Foundation\n\n\n\n\n\nThe Netherlands (Ministry of Foreign Affairs)\n\n\n\n\n\nUnited Arab Emirates (Ministry of Foreign Affairs and International Cooperation and Anwar Gargash Diplomatic Academy)\n\n\n\n\n\nWadah Khanfar\n\n\n\n\n        Learn more about supporting Crisis Group\n\nAustralia (Department of Foreign Affairs and Trade)\n\n\n\n\n\nAustria (Austrian Development Agency)\n\n\n\n\n\nCanada (Global Affairs Canada and Canadian Department of National Defence)\n\n\n\n\n\nCarnegie Corporation of New York\n\n\n\n\n\nChevron\n\n\n\n\n\nChris Bake\n\n\n\n\n\nDenmark (Ministry of Foreign Affairs)\n\n\n\n\n\nEni\n\n\n\n\n\nEuropean Union (Instrument contributing to Stability and Peace, Emergency Trust Fund for Africa)\n\n\n\n\n\nFinland (Ministry for Foreign Affairs)\n\n\n\n\n\nFrance (Ministry of Foreign Affairs and French Development Agency)\n\n\n\n\n\nFrank Giustra\n\n\n\n\n\nGlobal Challenges Foundation\n\n\n\n\n\nHerman De Bode\n\n\n\n\n\nIreland (Department of Foreign Affairs)\n\n\n\n\n\nLuxembourg (Ministry of Foreign and European Affairs)\n\n\n\n\n\nNeil Woodyer\n\n\n\n\n\nNew Zealand (Ministry of Foreign Affairs and Trade)\n\n\n\n\n\nNorway (Ministry of Foreign Affairs)\n\n\n\n\n\nOpen Society Foundations\n\n\n\n\n\nQatar (Ministry of Foreign Affairs)\n\n\n\n\n\nRobert Bosch Stiftung\n\n\n\n\n\nRockefeller Brothers Fund\n\n\n\n\n\nStand Together Trust\n\n\n\n\n\nStiftung Mercator\n\n\n\n\n\nSweden (Ministry of Foreign Affairs)\n\n\n\n\n\nSwitzerland (Federal Department of Foreign Affairs)\n\n\n\n\n\nThe Bergman Family Foundation\n\n\n\n\n\nThe Netherlands (Ministry of Foreign Affairs)\n\n\n\n\n\nUnited Arab Emirates (Ministry of Foreign Affairs and International Cooperation and Anwar Gargash Diplomatic Academy)\n\n\n\n\n\nWadah Khanfar\n\nAustralia (Department of Foreign Affairs and Trade)\n\nAustralia (Department of Foreign Affairs and Trade)\n\nAustria (Austrian Development Agency)\n\nAustria (Austrian Development Agency)\n\nCanada (Global Affairs Canada and Canadian Department of National Defence)\n\nCanada (Global Affairs Canada and Canadian Department of National Defence)\n\nCarnegie Corporation of New York\n\nCarnegie Corporation of New York\n\nChevron\n\nChevron\n\nChris Bake\n\nChris Bake\n\nDenmark (Ministry of Foreign Affairs)\n\nDenmark (Ministry of Foreign Affairs)\n\nEni\n\nEni\n\nEuropean Union (Instrument contributing to Stability and Peace, Emergency Trust Fund for Africa)\n\nEuropean Union (Instrument contributing to Stability and Peace, Emergency Trust Fund for Africa)\n\nFinland (Ministry for Foreign Affairs)\n\nFinland (Ministry for Foreign Affairs)\n\nFrance (Ministry of Foreign Affairs and French Development Agency)\n\nFrance (Ministry of Foreign Affairs and French Development Agency)\n\nFrank Giustra\n\nFrank Giustra\n\nGlobal Challenges Foundation\n\nGlobal Challenges Foundation\n\nHerman De Bode\n\nHerman De Bode\n\nIreland (Department of Foreign Affairs)\n\nIreland (Department of Foreign Affairs)\n\nLuxembourg (Ministry of Foreign and European Affairs)\n\nLuxembourg (Ministry of Foreign and European Affairs)\n\nNeil Woodyer\n\nNeil Woodyer\n\nNew Zealand (Ministry of Foreign Affairs and Trade)\n\nNew Zealand (Ministry of Foreign Affairs and Trade)\n\nNorway (Ministry of Foreign Affairs)\n\nNorway (Ministry of Foreign Affairs)\n\nOpen Society Foundations\n\nOpen Society Foundations\n\nQatar (Ministry of Foreign Affairs)\n\nQatar (Ministry of Foreign Affairs)\n\nRobert Bosch Stiftung\n\nRobert Bosch Stiftung\n\nRockefeller Brothers Fund\n\nRockefeller Brothers Fund\n\nStand Together Trust\n\nStand Together Trust\n\nStiftung Mercator\n\nStiftung Mercator\n\nSweden (Ministry of Foreign Affairs)\n\nSweden (Ministry of Foreign Affairs)\n\nSwitzerland (Federal Department of Foreign Affairs)\n\nSwitzerland (Federal Department of Foreign Affairs)\n\nThe Bergman Family Foundation\n\nThe Bergman Family Foundation\n\nThe Netherlands (Ministry of Foreign Affairs)\n\nThe Netherlands (Ministry of Foreign Affairs)\n\nUnited Arab Emirates (Ministry of Foreign Affairs and International Cooperation and Anwar Gargash Diplomatic Academy)\n\nUnited Arab Emirates (Ministry of Foreign Affairs and International Cooperation and Anwar Gargash Diplomatic Academy)\n\nWadah Khanfar\n\nWadah Khanfar\n\nLearn more about supporting Crisis Group\n\nSubscribe to Crisis Group’s Email Updates\n\n\n\nReceive the best source of conflict analysis right in your inbox.\n\n\nSubscribe here\n\nSubscribe to Crisis Group’s Email Updates\n\nReceive the best source of conflict analysis right in your inbox.\n\nReceive the best source of conflict analysis right in your inbox.\n\nSubscribe here\n\nThis site uses cookies. By continuing to browse the site you are agreeing to our use of cookies. Review our privacy policy for more details.\n\n\nYes, I Agree\n\nThis site uses cookies. By continuing to browse the site you are agreeing to our use of cookies. Review our privacy policy for more details.\n\n\nYes, I Agree\n\nThis site uses cookies. By continuing to browse the site you are agreeing to our use of cookies. Review our privacy policy for more details.\n\nThis site uses cookies. By continuing to browse the site you are agreeing to our use of cookies. Review our privacy policy for more details.\n\nYes, I Agree",
  "date": "",
  "source_type": "other",
  "extracted_at": "2025-04-07T13:46:42.686384",
  "metadata": {
    "description": "The International Crisis Group is an independent, non-profit, non-governmental organisation committed to preventing and resolving deadly conflict",
    "og:type": "article"
  },
  "relevance_score": 0.4,
  "summary": "This week on Hold Your Fire!, Richard Atwood speaks with Crisis Group’s Myanmar expert Richard Horsey about the devastating earthquake that struck Myanmar last week, challenges facing relief efforts and implications for the country’s civil war and its military leaders. The Houthis’ Red Sea Attacks Explained\n\n\n\n\n\n\nVisual Explainers\n\n                                  / Middle East & North Africa\n\n\n\n                \n                The Houthis’ Red Sea Attacks Explained\n              \n\n\n\n\n\n\nThe New Syria: Halting a Dangerous Drift\n\n\n\n\n\n\nBriefing\n\n                                  / Middle East & North Africa\n\n\n\n                \n                The New Syria: Halting a Dangerous Drift\n              \n\n\n\n\n\n                Also available in Arabic\n\n\n\n\n\n\nMarch Trends and April Alerts 2025\n\n\n\n\n\n\n                \n                March Trends and April Alerts 2025\n              \n\n\n\n\n\n\n\n            Middle East Tensions\n          \n\n            Read more on the issue\n            \n\n\n\n\n\n\n\n\n\n\n\n\n\n\n\n\n\n\n                  Alert\n                \n\n                              / Middle East & North Africa\n\nStopping Israel’s War in Gaza\n\n\nOn 18 March, Israel resumed bombing Gaza, upending a two-month ceasefire. Q&A\n                      \n\n                                          / Middle East & North Africa\n\nA Glimmer of Peace in Syria’s North East\n\n\n\n\n\n\n\n                        Podcast\n                      \n\n                                          / Middle East & North Africa\n\nIsrael Goes Back to War in Gaza\n\n\n\n\n\n\n\n                        Commentary\n                      \n\n                                          / Middle East & North Africa\n\nHow Israel’s Overreach in Syria May Backfire\n\n\n\n\n\n\n\n            Sudan\n          \n\n            Read more on Sudan\n            \n\n\n\n\n\n\n\n\n\n\n\n\n\n\n\n\n\n\n                  Statement\n                \n\n                              / Africa\n\nBattle for Khartoum Marks a Crossroads in Sudan’s Civil War\n\n\nThe Sudanese army is pushing to take over Khartoum. Briefing\n                      \n\n                                          / Africa\n\nSudan’s Calamitous War: Finding a Path toward Peace\n\n\n\n\n\n\n\n        Videos & Photography\n      \n\n\n\n \n\n\n\n\n\n\n\n\n\n\n\n\nVideo\n\n                                                / Ukraine\n                                              \n\n\nEuropean Security Three Years On From Russia's Full-scale Invasion of Ukraine\n\n\n\n\n\n \n\n\n\n\n\n\n\n\n\n\n\n\nVideo\n\n                                                / Global\n                                              \n\n\nMapping Conflict\n\n\n\n\n\n \n\n\n\n\n\n\n\n\n\n\n\n\nVideo\n\n                                                / Global\n                                              \n\n\nVIDEO | 10 Conflicts to Watch in 2025\n\n\n\n\n\n \n\n\n\n\n\n\n\n\n\n\n\n\nVideo\n\n                                                / Israel/Palestine\n                                              \n\n\nVideo | The Rise of Israeli Settler Violence in the West Bank\n\n\n\n\n\n \n\n\n\n\n\n\n\n\n\n\n\n\nVideo\n\n                                                / Mali\n                                              \n\n\nIbrahim Maiga on Mali's Sovereign Turn\n\n\n\n\n\n \n\n\n\n\n\n\n\n\n\n\n\n\nVideo\n\n                                                / South East Asia\n                                              \n\n\nThe Mekong's Troubled Waters\n\n\n\n\n\n \n\n\n\n\n\n\n\n\n\n\n\n\nVideo\n\n                                                / Morocco\n                                              \n\n\nAlgeria-Morocco Tensions\n\n\n\n\n\n \n\n\n\n\n\n\n\n\n\n\n\n\nVideo\n\n                                                / Mali\n                                              \n\n\nJean-Hervé Jezequel on Mali’s Sovereign Turn\n\n\n\n\n\n \n\n\n\n\n\n\n\n\n\n\n\n\nVideo\n\n                                                / Saudi Arabia\n                                              \n\n\nAbdulaziz Sager: Saudi Arabia's Perspective on the Escalation in the Middle East\n\n\n\n\n\n \n\n\n\n\n\n\n\n\n\n\n\n\nVideo\n\n                                                / Niger\n                                              \n\n\nLa vie des femmes sous l'État islamique dans l'ouest du Niger\n\n\n\n\n\n\n\n\n\n\n\n        Visual Explainers\n      \n\n\n\n \n\n\n\n\n\n\n\n\nUkraine War Map: Tracking the Frontlines\n\n\n\n \n\n\n\n\n\n\n\n\nVisual Explainer: Ten Conflicts to Watch in 2024\n\n\n\n \n\n\n\n\n\n\n\n\nThe U.S. Wartime Powers against a Criminal “Invasion”\n\n\nSpecial Coverage\nComfort Ero’s 2025 Top Picks on Gender and Conflict\n\n\n\n\n\nAfrica \n\n\n\n\n\n\n\n\n\nPodcast\nSouth Sudan on the Brink of Another War\n\n\n\n\nAlert\nEthiopia and Eritrea Slide Closer to War amid Tigray Upheaval \n\n\nPodcast\nWhich Way Will Trump Go on Somalia? Q&A\nSupport Vital for Myanmar’s Quake Victims, Despite Military Obstacles \n\n\nBriefing\nDisquiet on the Western Front: A Divided Resistance in Myanmar’s Chin State\n\n\n\n\n\nEurope & Central Asia \n\n\n\n\n\n\n\n\n\nQ&A\nA Glimmer of Peace in Syria’s North East\n\n\n\n\nPodcast\nLatin America’s Evolving Drug Trade. Why It Matters for Europe\n\n\nVisual Explainers\nHow a New Drug Trafficking Landscape Fuels Violence in Latin America\n\n\n\n\n\nMiddle East & North Africa \n\n\n\n\n\n\n\n\n\nVisual Explainers\nThe Houthis’ Red Sea Attacks Explained\n\n\n\n\n\n\n\n\nQ&A\nA Glimmer of Peace in Syria’s North East\n\n\n\nBriefing\nThe New Syria: Halting a Dangerous Drift\n\n\n\n\n\nUnited States \n\n\n\n\n\n\n\n\n\nQ&A\nA Glimmer of Peace in Syria’s North East\n\n\n\n\nPodcast\nWhich Way Will Trump Go on Somalia? Donate now\n      \n\n        Learn What We Do\n        \n\n\n\n\n\n    Our Supporters\n  \n\n\n\n\n\nAustralia (Department of Foreign Affairs and Trade)\n\n\n\n\n\nAustria (Austrian Development Agency)\n\n\n\n\n\nCanada (Global Affairs Canada and Canadian Department of National Defence)\n\n\n\n\n\nCarnegie Corporation of New York\n\n\n\n\n\nChevron\n\n\n\n\n\nChris Bake\n\n\n\n\n\nDenmark (Ministry of Foreign Affairs)\n\n\n\n\n\nEni\n\n\n\n\n\nEuropean Union (Instrument contributing to Stability and Peace, Emergency Trust Fund for Africa)\n\n\n\n\n\nFinland (Ministry for Foreign Affairs)\n\n\n\n\n\nFrance (Ministry of Foreign Affairs and French Development Agency)\n\n\n\n\n\nFrank Giustra\n\n\n\n\n\nGlobal Challenges Foundation\n\n\n\n\n\nHerman De Bode\n\n\n\n\n\nIreland (Department of Foreign Affairs)\n\n\n\n\n\nLuxembourg (Ministry of Foreign and European Affairs)\n\n\n\n\n\nNeil Woodyer\n\n\n\n\n\nNew Zealand (Ministry of Foreign Affairs and Trade)\n\n\n\n\n\nNorway (Ministry of Foreign Affairs)\n\n\n\n\n\nOpen Society Foundations\n\n\n\n\n\nQatar (Ministry of Foreign Affairs)\n\n\n\n\n\nRobert Bosch Stiftung\n\n\n\n\n\nRockefeller Brothers Fund\n\n\n\n\n\nStand Together Trust\n\n\n\n\n\nStiftung Mercator\n\n\n\n\n\nSweden (Ministry of Foreign Affairs)\n\n\n\n\n\nSwitzerland (Federal Department of Foreign Affairs)\n\n\n\n\n\nThe Bergman Family Foundation\n\n\n\n\n\nThe Netherlands (Ministry of Foreign Affairs)\n\n\n\n\n\nUnited Arab Emirates (Ministry of Foreign Affairs and International Cooperation and Anwar Gargash Diplomatic Academy)\n\n\n\n\n\nWadah Khanfar\n\n\n\n\n        Learn more about supporting Crisis Group\n        \n\n\n\n\n\n\n\n\n\n\n\nSubscribe to Crisis Group’s Email Updates\n\n\n\nReceive the best source of conflict analysis right in your inbox. This week on Hold Your Fire!, Richard Atwood speaks with Crisis Group’s Myanmar expert Richard Horsey about the devastating earthquake that struck Myanmar last week, challenges facing relief efforts and implications for the country’s civil war and its military leaders. The Houthis’ Red Sea Attacks Explained\n\n\n\n\n\n\nVisual Explainers\n\n                                  / Middle East & North Africa\n\n\n\n                \n                The Houthis’ Red Sea Attacks Explained\n              \n\n\n\n\n\n\nThe New Syria: Halting a Dangerous Drift\n\n\n\n\n\n\nBriefing\n\n                                  / Middle East & North Africa\n\n\n\n                \n                The New Syria: Halting a Dangerous Drift\n              \n\n\n\n\n\n                Also available in Arabic\n\n\n\n\n\n\nMarch Trends and April Alerts 2025\n\n\n\n\n\n\n                \n                March Trends and April Alerts 2025\n              \n\n\n\n\n\n\n\n            Middle East Tensions\n          \n\n            Read more on the issue\n            \n\n\n\n\n\n\n\n\n\n\n\n\n\n\n\n\n\n\n                  Alert\n                \n\n                              / Middle East & North Africa\n\nStopping Israel’s War in Gaza\n\n\nOn 18 March, Israel resumed bombing Gaza, upending a two-month ceasefire. Q&A\n                      \n\n                                          / Middle East & North Africa\n\nA Glimmer of Peace in Syria’s North East\n\n\n\n\n\n\n\n                        Podcast\n                      \n\n                                          / Middle East & North Africa\n\nIsrael Goes Back to War in Gaza\n\n\n\n\n\n\n\n                        Commentary\n                      \n\n                                          / Middle East & North Africa\n\nHow Israel’s Overreach in Syria May Backfire\n\n\n\n\n\n\n\n            Sudan\n          \n\n            Read more on Sudan\n            \n\n\n\n\n\n\n\n\n\n\n\n\n\n\n\n\n\n\n                  Statement\n                \n\n                              / Africa\n\nBattle for Khartoum Marks a Crossroads in Sudan’s Civil War\n\n\nThe Sudanese army is pushing to take over Khartoum. Briefing\n                      \n\n                                          / Africa\n\nSudan’s Calamitous War: Finding a Path toward Peace\n\n\n\n\n\n\n\n        Videos & Photography\n      \n\n\n\n \n\n\n\n\n\n\n\n\n\n\n\n\nVideo\n\n                                                / Ukraine\n                                              \n\n\nEuropean Security Three Years On From Russia's Full-scale Invasion of Ukraine\n\n\n\n\n\n \n\n\n\n\n\n\n\n\n\n\n\n\nVideo\n\n                                                / Global\n                                              \n\n\nMapping Conflict\n\n\n\n\n\n \n\n\n\n\n\n\n\n\n\n\n\n\nVideo\n\n                                                / Global\n                                              \n\n\nVIDEO | 10 Conflicts to Watch in 2025\n\n\n\n\n\n \n\n\n\n\n\n\n\n\n\n\n\n\nVideo\n\n                                                / Israel/Palestine\n                                              \n\n\nVideo | The Rise of Israeli Settler Violence in the West Bank\n\n\n\n\n\n \n\n\n\n\n\n\n\n\n\n\n\n\nVideo\n\n                                                / Mali\n                                              \n\n\nIbrahim Maiga on Mali's Sovereign Turn\n\n\n\n\n\n \n\n\n\n\n\n\n\n\n\n\n\n\nVideo\n\n                                                / South East Asia\n                                              \n\n\nThe Mekong's Troubled Waters\n\n\n\n\n\n \n\n\n\n\n\n\n\n\n\n\n\n\nVideo\n\n                                                / Morocco\n                                              \n\n\nAlgeria-Morocco Tensions\n\n\n\n\n\n \n\n\n\n\n\n\n\n\n\n\n\n\nVideo\n\n                                                / Mali\n                                              \n\n\nJean-Hervé Jezequel on Mali’s Sovereign Turn\n\n\n\n\n\n \n\n\n\n\n\n\n\n\n\n\n\n\nVideo\n\n                                                / Saudi Arabia\n                                              \n\n\nAbdulaziz Sager: Saudi Arabia's Perspective on the Escalation in the Middle East\n\n\n\n\n\n \n\n\n\n\n\n\n\n\n\n\n\n\nVideo\n\n                                                / Niger\n                                              \n\n\nLa vie des femmes sous l'État islamique dans l'ouest du Niger\n\n\n\n\n\n\n\n\n\n\n\n        Visual Explainers\n      \n\n\n\n \n\n\n\n\n\n\n\n\nUkraine War Map: Tracking the Frontlines\n\n\n\n \n\n\n\n\n\n\n\n\nVisual Explainer: Ten Conflicts to Watch in 2024\n\n\n\n \n\n\n\n\n\n\n\n\nThe U.S. Wartime Powers against a Criminal “Invasion”\n\n\nSpecial Coverage\nComfort Ero’s 2025 Top Picks on Gender and Conflict\n\n\n\n\n\nAfrica \n\n\n\n\n\n\n\n\n\nPodcast\nSouth Sudan on the Brink of Another War\n\n\n\n\nAlert\nEthiopia and Eritrea Slide Closer to War amid Tigray Upheaval \n\n\nPodcast\nWhich Way Will Trump Go on Somalia? Q&A\nSupport Vital for Myanmar’s Quake Victims, Despite Military Obstacles \n\n\nBriefing\nDisquiet on the Western Front: A Divided Resistance in Myanmar’s Chin State\n\n\n\n\n\nEurope & Central Asia \n\n\n\n\n\n\n\n\n\nQ&A\nA Glimmer of Peace in Syria’s North East\n\n\n\n\nPodcast\nLatin America’s Evolving Drug Trade. Why It Matters for Europe\n\n\nVisual Explainers\nHow a New Drug Trafficking Landscape Fuels Violence in Latin America\n\n\n\n\n\nMiddle East & North Africa \n\n\n\n\n\n\n\n\n\nVisual Explainers\nThe Houthis’ Red Sea Attacks Explained\n\n\n\n\n\n\n\n\nQ&A\nA Glimmer of Peace in Syria’s North East\n\n\n\nBriefing\nThe New Syria: Halting a Dangerous Drift\n\n\n\n\n\nUnited States \n\n\n\n\n\n\n\n\n\nQ&A\nA Glimmer of Peace in Syria’s North East\n\n\n\n\nPodcast\nWhich Way Will Trump Go on Somalia? Donate now\n      \n\n        Learn What We Do\n        \n\n\n\n\n\n    Our Supporters\n  \n\n\n\n\n\nAustralia (Department of Foreign Affairs and Trade)\n\n\n\n\n\nAustria (Austrian Development Agency)\n\n\n\n\n\nCanada (Global Affairs Canada and Canadian Department of National Defence)\n\n\n\n\n\nCarnegie Corporation of New York\n\n\n\n\n\nChevron\n\n\n\n\n\nChris Bake\n\n\n\n\n\nDenmark (Ministry of Foreign Affairs)\n\n\n\n\n\nEni\n\n\n\n\n\nEuropean Union (Instrument contributing to Stability and Peace, Emergency Trust Fund for Africa)\n\n\n\n\n\nFinland (Ministry for Foreign Affairs)\n\n\n\n\n\nFrance (Ministry of Foreign Affairs and French Development Agency)\n\n\n\n\n\nFrank Giustra\n\n\n\n\n\nGlobal Challenges Foundation\n\n\n\n\n\nHerman De Bode\n\n\n\n\n\nIreland (Department of Foreign Affairs)\n\n\n\n\n\nLuxembourg (Ministry of Foreign and European Affairs)\n\n\n\n\n\nNeil Woodyer\n\n\n\n\n\nNew Zealand (Ministry of Foreign Affairs and Trade)\n\n\n\n\n\nNorway (Ministry of Foreign Affairs)\n\n\n\n\n\nOpen Society Foundations\n\n\n\n\n\nQatar (Ministry of Foreign Affairs)\n\n\n\n\n\nRobert Bosch Stiftung\n\n\n\n\n\nRockefeller Brothers Fund\n\n\n\n\n\nStand Together Trust\n\n\n\n\n\nStiftung Mercator\n\n\n\n\n\nSweden (Ministry of Foreign Affairs)\n\n\n\n\n\nSwitzerland (Federal Department of Foreign Affairs)\n\n\n\n\n\nThe Bergman Family Foundation\n\n\n\n\n\nThe Netherlands (Ministry of Foreign Affairs)\n\n\n\n\n\nUnited Arab Emirates (Ministry of Foreign Affairs and International Cooperation and Anwar Gargash Diplomatic Academy)\n\n\n\n\n\nWadah Khanfar\n\n\n\n\n        Learn more about supporting Crisis Group\n        \n\n\n\n\n\n\n\n\n\n\n\nSubscribe to Crisis Group’s Email Updates\n\n\n\nReceive the best source of conflict analysis right in your inbox. This week on Hold Your Fire!, Richard Atwood speaks with Crisis Group’s Myanmar expert Richard Horsey about the devastating earthquake that struck Myanmar last week, challenges facing relief efforts and implications for the country’s civil war and its military leaders. The Houthis’ Red Sea Attacks Explained\n\n\n\n\n\n\nVisual Explainers\n\n                                  / Middle East & North Africa\n\n\n\n                \n                The Houthis’ Red Sea Attacks Explained\n              \n\n\n\n\n\n\nThe New Syria: Halting a Dangerous Drift\n\n\n\n\n\n\nBriefing\n\n                                  / Middle East & North Africa\n\n\n\n                \n                The New Syria: Halting a Dangerous Drift\n              \n\n\n\n\n\n                Also available in Arabic\n\n\n\n\n\n\nMarch Trends and April Alerts 2025\n\n\n\n\n\n\n                \n                March Trends and April Alerts 2025\n              \n\n\n\n\n\n\n\n            Middle East Tensions\n          \n\n            Read more on the issue\n            \n\n\n\n\n\n\n\n\n\n\n\n\n\n\n\n\n\n\n                  Alert\n                \n\n                              / Middle East & North Africa\n\nStopping Israel’s War in Gaza\n\n\nOn 18 March, Israel resumed bombing Gaza, upending a two-month ceasefire. Q&A\n                      \n\n                                          / Middle East & North Africa\n\nA Glimmer of Peace in Syria’s North East\n\n\n\n\n\n\n\n                        Podcast\n                      \n\n                                          / Middle East & North Africa\n\nIsrael Goes Back to War in Gaza\n\n\n\n\n\n\n\n                        Commentary\n                      \n\n                                          / Middle East & North Africa\n\nHow Israel’s Overreach in Syria May Backfire\n\n\n\n\n\n\n\n            Sudan\n          \n\n            Read more on Sudan\n            \n\n\n\n\n\n\n\n\n\n\n\n\n\n\n\n\n\n\n                  Statement\n                \n\n                              / Africa\n\nBattle for Khartoum Marks a Crossroads in Sudan’s Civil War\n\n\nThe Sudanese army is pushing to take over Khartoum. Briefing\n                      \n\n                                          / Africa\n\nSudan’s Calamitous War: Finding a Path toward Peace\n\n\n\n\n\n\n\n        Videos & Photography\n      \n\n\n\n \n\n\n\n\n\n\n\n\n\n\n\n\nVideo\n\n                                                / Ukraine\n                                              \n\n\nEuropean Security Three Years On From Russia's Full-scale Invasion of Ukraine\n\n\n\n\n\n \n\n\n\n\n\n\n\n\n\n\n\n\nVideo\n\n                                                / Global\n                                              \n\n\nMapping Conflict\n\n\n\n\n\n \n\n\n\n\n\n\n\n\n\n\n\n\nVideo\n\n                                                / Global\n                                              \n\n\nVIDEO | 10 Conflicts to Watch in 2025\n\n\n\n\n\n \n\n\n\n\n\n\n\n\n\n\n\n\nVideo\n\n                                                / Israel/Palestine\n                                              \n\n\nVideo | The Rise of Israeli Settler Violence in the West Bank\n\n\n\n\n\n \n\n\n\n\n\n\n\n\n\n\n\n\nVideo\n\n                                                / Mali\n                                              \n\n\nIbrahim Maiga on Mali's Sovereign Turn\n\n\n\n\n\n \n\n\n\n\n\n\n\n\n\n\n\n\nVideo\n\n                                                / South East Asia\n                                              \n\n\nThe Mekong's Troubled Waters\n\n\n\n\n\n \n\n\n\n\n\n\n\n\n\n\n\n\nVideo\n\n                                                / Morocco\n                                              \n\n\nAlgeria-Morocco Tensions\n\n\n\n\n\n \n\n\n\n\n\n\n\n\n\n\n\n\nVideo\n\n                                                / Mali\n                                              \n\n\nJean-Hervé Jezequel on Mali’s Sovereign Turn\n\n\n\n\n\n \n\n\n\n\n\n\n\n\n\n\n\n\nVideo\n\n                                                / Saudi Arabia\n                                              \n\n\nAbdulaziz Sager: Saudi Arabia's Perspective on the Escalation in the Middle East\n\n\n\n\n\n \n\n\n\n\n\n\n\n\n\n\n\n\nVideo\n\n                                                / Niger\n                                              \n\n\nLa vie des femmes sous l'État islamique dans l'ouest du Niger\n\n\n\n\n\n\n\n\n\n\n\n        Visual Explainers\n      \n\n\n\n \n\n\n\n\n\n\n\n\nUkraine War Map: Tracking the Frontlines\n\n\n\n \n\n\n\n\n\n\n\n\nVisual Explainer: Ten Conflicts to Watch in 2024\n\n\n\n \n\n\n\n\n\n\n\n\nThe U.S. Wartime Powers against a Criminal “Invasion”\n\n\nSpecial Coverage\nComfort Ero’s 2025 Top Picks on Gender and Conflict\n\n\n\n\n\nAfrica \n\n\n\n\n\n\n\n\n\nPodcast\nSouth Sudan on the Brink of Another War\n\n\n\n\nAlert\nEthiopia and Eritrea Slide Closer to War amid Tigray Upheaval \n\n\nPodcast\nWhich Way Will Trump Go on Somalia? Q&A\nSupport Vital for Myanmar’s Quake Victims, Despite Military Obstacles \n\n\nBriefing\nDisquiet on the Western Front: A Divided Resistance in Myanmar’s Chin State\n\n\n\n\n\nEurope & Central Asia \n\n\n\n\n\n\n\n\n\nQ&A\nA Glimmer of Peace in Syria’s North East\n\n\n\n\nPodcast\nLatin America’s Evolving Drug Trade. Why It Matters for Europe\n\n\nVisual Explainers\nHow a New Drug Trafficking Landscape Fuels Violence in Latin America\n\n\n\n\n\nMiddle East & North Africa \n\n\n\n\n\n\n\n\n\nVisual Explainers\nThe Houthis’ Red Sea Attacks Explained\n\n\n\n\n\n\n\n\nQ&A\nA Glimmer of Peace in Syria’s North East\n\n\n\nBriefing\nThe New Syria: Halting a Dangerous Drift\n\n\n\n\n\nUnited States \n\n\n\n\n\n\n\n\n\nQ&A\nA Glimmer of Peace in Syria’s North East\n\n\n\n\nPodcast\nWhich Way Will Trump Go on Somalia? Donate now\n      \n\n        Learn What We Do\n        \n\n\n\n\n\n    Our Supporters\n  \n\n\n\n\n\nAustralia (Department of Foreign Affairs and Trade)\n\n\n\n\n\nAustria (Austrian Development Agency)\n\n\n\n\n\nCanada (Global Affairs Canada and Canadian Department of National Defence)\n\n\n\n\n\nCarnegie Corporation of New York\n\n\n\n\n\nChevron\n\n\n\n\n\nChris Bake\n\n\n\n\n\nDenmark (Ministry of Foreign Affairs)\n\n\n\n\n\nEni\n\n\n\n\n\nEuropean Union (Instrument contributing to Stability and Peace, Emergency Trust Fund for Africa)\n\n\n\n\n\nFinland (Ministry for Foreign Affairs)\n\n\n\n\n\nFrance (Ministry of Foreign Affairs and French Development Agency)\n\n\n\n\n\nFrank Giustra\n\n\n\n\n\nGlobal Challenges Foundation\n\n\n\n\n\nHerman De Bode\n\n\n\n\n\nIreland (Department of Foreign Affairs)\n\n\n\n\n\nLuxembourg (Ministry of Foreign and European Affairs)\n\n\n\n\n\nNeil Woodyer\n\n\n\n\n\nNew Zealand (Ministry of Foreign Affairs and Trade)\n\n\n\n\n\nNorway (Ministry of Foreign Affairs)\n\n\n\n\n\nOpen Society Foundations\n\n\n\n\n\nQatar (Ministry of Foreign Affairs)\n\n\n\n\n\nRobert Bosch Stiftung\n\n\n\n\n\nRockefeller Brothers Fund\n\n\n\n\n\nStand Together Trust\n\n\n\n\n\nStiftung Mercator\n\n\n\n\n\nSweden (Ministry of Foreign Affairs)\n\n\n\n\n\nSwitzerland (Federal Department of Foreign Affairs)\n\n\n\n\n\nThe Bergman Family Foundation\n\n\n\n\n\nThe Netherlands (Ministry of Foreign Affairs)\n\n\n\n\n\nUnited Arab Emirates (Ministry of Foreign Affairs and International Cooperation and Anwar Gargash Diplomatic Academy)\n\n\n\n\n\nWadah Khanfar\n\n\n\n\n        Learn more about supporting Crisis Group\n\nQ&A\n                    / Myanmar\n\n\n\nSupport Vital for Myanmar’s Quake Victims, Despite Military Obstacles \n\n\n\nThe massive earthquake in Myanmar has taken a terrible toll. This week on Hold Your Fire!, Richard Atwood speaks with Crisis Group’s Myanmar expert Richard Horsey about the devastating earthquake that struck Myanmar last week, challenges facing relief efforts and implications for the country’s civil war and its military leaders. The Houthis’ Red Sea Attacks Explained\n\n\n\n\n\n\nVisual Explainers\n\n                                  / Middle East & North Africa\n\n\n\n                \n                The Houthis’ Red Sea Attacks Explained\n              \n\n\n\n\n\n\nThe New Syria: Halting a Dangerous Drift\n\n\n\n\n\n\nBriefing\n\n                                  / Middle East & North Africa\n\n\n\n                \n                The New Syria: Halting a Dangerous Drift\n              \n\n\n\n\n\n                Also available in Arabic\n\n\n\n\n\n\nMarch Trends and April Alerts 2025\n\n\n\n\n\n\n                \n                March Trends and April Alerts 2025\n              \n\n\n\n\n\n\n\n            Middle East Tensions\n          \n\n            Read more on the issue\n            \n\n\n\n\n\n\n\n\n\n\n\n\n\n\n\n\n\n\n                  Alert\n                \n\n                              / Middle East & North Africa\n\nStopping Israel’s War in Gaza\n\n\nOn 18 March, Israel resumed bombing Gaza, upending a two-month ceasefire. Q&A\n                      \n\n                                          / Middle East & North Africa\n\nA Glimmer of Peace in Syria’s North East\n\n\n\n\n\n\n\n                        Podcast\n                      \n\n                                          / Middle East & North Africa\n\nIsrael Goes Back to War in Gaza\n\n\n\n\n\n\n\n                        Commentary\n                      \n\n                                          / Middle East & North Africa\n\nHow Israel’s Overreach in Syria May Backfire\n\n\n\n\n\n\n\n            Sudan\n          \n\n            Read more on Sudan\n            \n\n\n\n\n\n\n\n\n\n\n\n\n\n\n\n\n\n\n                  Statement\n                \n\n                              / Africa\n\nBattle for Khartoum Marks a Crossroads in Sudan’s Civil War\n\n\nThe Sudanese army is pushing to take over Khartoum. Briefing\n                      \n\n                                          / Africa\n\nSudan’s Calamitous War: Finding a Path toward Peace\n\n\n\n\n\n\n\n        Videos & Photography\n      \n\n\n\n \n\n\n\n\n\n\n\n\n\n\n\n\nVideo\n\n                                                / Ukraine\n                                              \n\n\nEuropean Security Three Years On From Russia's Full-scale Invasion of Ukraine\n\n\n\n\n\n \n\n\n\n\n\n\n\n\n\n\n\n\nVideo\n\n                                                / Global\n                                              \n\n\nMapping Conflict\n\n\n\n\n\n \n\n\n\n\n\n\n\n\n\n\n\n\nVideo\n\n                                                / Global\n                                              \n\n\nVIDEO | 10 Conflicts to Watch in 2025\n\n\n\n\n\n \n\n\n\n\n\n\n\n\n\n\n\n\nVideo\n\n                                                / Israel/Palestine\n                                              \n\n\nVideo | The Rise of Israeli Settler Violence in the West Bank\n\n\n\n\n\n \n\n\n\n\n\n\n\n\n\n\n\n\nVideo\n\n                                                / Mali\n                                              \n\n\nIbrahim Maiga on Mali's Sovereign Turn\n\n\n\n\n\n \n\n\n\n\n\n\n\n\n\n\n\n\nVideo\n\n                                                / South East Asia\n                                              \n\n\nThe Mekong's Troubled Waters\n\n\n\n\n\n \n\n\n\n\n\n\n\n\n\n\n\n\nVideo\n\n                                                / Morocco\n                                              \n\n\nAlgeria-Morocco Tensions\n\n\n\n\n\n \n\n\n\n\n\n\n\n\n\n\n\n\nVideo\n\n                                                / Mali\n                                              \n\n\nJean-Hervé Jezequel on Mali’s Sovereign Turn\n\n\n\n\n\n \n\n\n\n\n\n\n\n\n\n\n\n\nVideo\n\n                                                / Saudi Arabia\n                                              \n\n\nAbdulaziz Sager: Saudi Arabia's Perspective on the Escalation in the Middle East\n\n\n\n\n\n \n\n\n\n\n\n\n\n\n\n\n\n\nVideo\n\n                                                / Niger\n                                              \n\n\nLa vie des femmes sous l'État islamique dans l'ouest du Niger\n\n\n\n\n\n\n\n\n\n\n\n        Visual Explainers\n      \n\n\n\n \n\n\n\n\n\n\n\n\nUkraine War Map: Tracking the Frontlines\n\n\n\n \n\n\n\n\n\n\n\n\nVisual Explainer: Ten Conflicts to Watch in 2024\n\n\n\n \n\n\n\n\n\n\n\n\nThe U.S. Wartime Powers against a Criminal “Invasion”\n\n\nSpecial Coverage\nComfort Ero’s 2025 Top Picks on Gender and Conflict\n\n\n\n\n\nAfrica \n\n\n\n\n\n\n\n\n\nPodcast\nSouth Sudan on the Brink of Another War\n\n\n\n\nAlert\nEthiopia and Eritrea Slide Closer to War amid Tigray Upheaval \n\n\nPodcast\nWhich Way Will Trump Go on Somalia? Q&A\nSupport Vital for Myanmar’s Quake Victims, Despite Military Obstacles \n\n\nBriefing\nDisquiet on the Western Front: A Divided Resistance in Myanmar’s Chin State\n\n\n\n\n\nEurope & Central Asia \n\n\n\n\n\n\n\n\n\nQ&A\nA Glimmer of Peace in Syria’s North East\n\n\n\n\nPodcast\nLatin America’s Evolving Drug Trade. Why It Matters for Europe\n\n\nVisual Explainers\nHow a New Drug Trafficking Landscape Fuels Violence in Latin America\n\n\n\n\n\nMiddle East & North Africa \n\n\n\n\n\n\n\n\n\nVisual Explainers\nThe Houthis’ Red Sea Attacks Explained\n\n\n\n\n\n\n\n\nQ&A\nA Glimmer of Peace in Syria’s North East\n\n\n\nBriefing\nThe New Syria: Halting a Dangerous Drift\n\n\n\n\n\nUnited States \n\n\n\n\n\n\n\n\n\nQ&A\nA Glimmer of Peace in Syria’s North East\n\n\n\n\nPodcast\nWhich Way Will Trump Go on Somalia? Donate now\n      \n\n        Learn What We Do\n        \n\n\n\n\n\n    Our Supporters\n  \n\n\n\n\n\nAustralia (Department of Foreign Affairs and Trade)\n\n\n\n\n\nAustria (Austrian Development Agency)\n\n\n\n\n\nCanada (Global Affairs Canada and Canadian Department of National Defence)\n\n\n\n\n\nCarnegie Corporation of New York\n\n\n\n\n\nChevron\n\n\n\n\n\nChris Bake\n\n\n\n\n\nDenmark (Ministry of Foreign Affairs)\n\n\n\n\n\nEni\n\n\n\n\n\nEuropean Union (Instrument contributing to Stability and Peace, Emergency Trust Fund for Africa)\n\n\n\n\n\nFinland (Ministry for Foreign Affairs)\n\n\n\n\n\nFrance (Ministry of Foreign Affairs and French Development Agency)\n\n\n\n\n\nFrank Giustra\n\n\n\n\n\nGlobal Challenges Foundation\n\n\n\n\n\nHerman De Bode\n\n\n\n\n\nIreland (Department of Foreign Affairs)\n\n\n\n\n\nLuxembourg (Ministry of Foreign and European Affairs)\n\n\n\n\n\nNeil Woodyer\n\n\n\n\n\nNew Zealand (Ministry of Foreign Affairs and Trade)\n\n\n\n\n\nNorway (Ministry of Foreign Affairs)\n\n\n\n\n\nOpen Society Foundations\n\n\n\n\n\nQatar (Ministry of Foreign Affairs)\n\n\n\n\n\nRobert Bosch Stiftung\n\n\n\n\n\nRockefeller Brothers Fund\n\n\n\n\n\nStand Together Trust\n\n\n\n\n\nStiftung Mercator\n\n\n\n\n\nSweden (Ministry of Foreign Affairs)\n\n\n\n\n\nSwitzerland (Federal Department of Foreign Affairs)\n\n\n\n\n\nThe Bergman Family Foundation\n\n\n\n\n\nThe Netherlands (Ministry of Foreign Affairs)\n\n\n\n\n\nUnited Arab Emirates (Ministry of Foreign Affairs and International Cooperation and Anwar Gargash Diplomatic Academy)\n\n\n\n\n\nWadah Khanfar\n\n\n\n\n        Learn more about supporting Crisis Group\n\nQ&A\n                    / Myanmar\n\n\n\nSupport Vital for Myanmar’s Quake Victims, Despite Military Obstacles \n\n\n\nThe massive earthquake in Myanmar has taken a terrible toll. This week on Hold Your Fire!, Richard Atwood speaks with Crisis Group’s Myanmar expert Richard Horsey about the devastating earthquake that struck Myanmar last week, challenges facing relief efforts and implications for the country’s civil war and its military leaders. The Houthis’ Red Sea Attacks Explained\n\n\n\n\n\n\nVisual Explainers\n\n                                  / Middle East & North Africa\n\n\n\n                \n                The Houthis’ Red Sea Attacks Explained\n              \n\n\n\n\n\n\nThe New Syria: Halting a Dangerous Drift\n\n\n\n\n\n\nBriefing\n\n                                  / Middle East & North Africa\n\n\n\n                \n                The New Syria: Halting a Dangerous Drift\n              \n\n\n\n\n\n                Also available in Arabic\n\n\n\n\n\n\nMarch Trends and April Alerts 2025\n\n\n\n\n\n\n                \n                March Trends and April Alerts 2025\n              \n\n\n\n\n\n\n\n            Middle East Tensions\n          \n\n            Read more on the issue\n            \n\n\n\n\n\n\n\n\n\n\n\n\n\n\n\n\n\n\n                  Alert\n                \n\n                              / Middle East & North Africa\n\nStopping Israel’s War in Gaza\n\n\nOn 18 March, Israel resumed bombing Gaza, upending a two-month ceasefire. Q&A\n                      \n\n                                          / Middle East & North Africa\n\nA Glimmer of Peace in Syria’s North East\n\n\n\n\n\n\n\n                        Podcast\n                      \n\n                                          / Middle East & North Africa\n\nIsrael Goes Back to War in Gaza\n\n\n\n\n\n\n\n                        Commentary\n                      \n\n                                          / Middle East & North Africa\n\nHow Israel’s Overreach in Syria May Backfire\n\n\n\n\n\n\n\n            Sudan\n          \n\n            Read more on Sudan\n            \n\n\n\n\n\n\n\n\n\n\n\n\n\n\n\n\n\n\n                  Statement\n                \n\n                              / Africa\n\nBattle for Khartoum Marks a Crossroads in Sudan’s Civil War\n\n\nThe Sudanese army is pushing to take over Khartoum. Briefing\n                      \n\n                                          / Africa\n\nSudan’s Calamitous War: Finding a Path toward Peace\n\n\n\n\n\n\n\n        Videos & Photography\n      \n\n\n\n \n\n\n\n\n\n\n\n\n\n\n\n\nVideo\n\n                                                / Ukraine\n                                              \n\n\nEuropean Security Three Years On From Russia's Full-scale Invasion of Ukraine\n\n\n\n\n\n \n\n\n\n\n\n\n\n\n\n\n\n\nVideo\n\n                                                / Global\n                                              \n\n\nMapping Conflict\n\n\n\n\n\n \n\n\n\n\n\n\n\n\n\n\n\n\nVideo\n\n                                                / Global\n                                              \n\n\nVIDEO | 10 Conflicts to Watch in 2025\n\n\n\n\n\n \n\n\n\n\n\n\n\n\n\n\n\n\nVideo\n\n                                                / Israel/Palestine\n                                              \n\n\nVideo | The Rise of Israeli Settler Violence in the West Bank\n\n\n\n\n\n \n\n\n\n\n\n\n\n\n\n\n\n\nVideo\n\n                                                / Mali\n                                              \n\n\nIbrahim Maiga on Mali's Sovereign Turn\n\n\n\n\n\n \n\n\n\n\n\n\n\n\n\n\n\n\nVideo\n\n                                                / South East Asia\n                                              \n\n\nThe Mekong's Troubled Waters\n\n\n\n\n\n \n\n\n\n\n\n\n\n\n\n\n\n\nVideo\n\n                                                / Morocco\n                                              \n\n\nAlgeria-Morocco Tensions\n\n\n\n\n\n \n\n\n\n\n\n\n\n\n\n\n\n\nVideo\n\n                                                / Mali\n                                              \n\n\nJean-Hervé Jezequel on Mali’s Sovereign Turn\n\n\n\n\n\n \n\n\n\n\n\n\n\n\n\n\n\n\nVideo\n\n                                                / Saudi Arabia\n                                              \n\n\nAbdulaziz Sager: Saudi Arabia's Perspective on the Escalation in the Middle East\n\n\n\n\n\n \n\n\n\n\n\n\n\n\n\n\n\n\nVideo\n\n                                                / Niger\n                                              \n\n\nLa vie des femmes sous l'État islamique dans l'ouest du Niger\n\n\n\n\n\n\n\n\n\n\n\n        Visual Explainers\n      \n\n\n\n \n\n\n\n\n\n\n\n\nUkraine War Map: Tracking the Frontlines\n\n\n\n \n\n\n\n\n\n\n\n\nVisual Explainer: Ten Conflicts to Watch in 2024\n\n\n\n \n\n\n\n\n\n\n\n\nThe U.S. Wartime Powers against a Criminal “Invasion”\n\n\nSpecial Coverage\nComfort Ero’s 2025 Top Picks on Gender and Conflict\n\n\n\n\n\nAfrica \n\n\n\n\n\n\n\n\n\nPodcast\nSouth Sudan on the Brink of Another War\n\n\n\n\nAlert\nEthiopia and Eritrea Slide Closer to War amid Tigray Upheaval \n\n\nPodcast\nWhich Way Will Trump Go on Somalia? Q&A\nSupport Vital for Myanmar’s Quake Victims, Despite Military Obstacles \n\n\nBriefing\nDisquiet on the Western Front: A Divided Resistance in Myanmar’s Chin State\n\n\n\n\n\nEurope & Central Asia \n\n\n\n\n\n\n\n\n\nQ&A\nA Glimmer of Peace in Syria’s North East\n\n\n\n\nPodcast\nLatin America’s Evolving Drug Trade. Why It Matters for Europe\n\n\nVisual Explainers\nHow a New Drug Trafficking Landscape Fuels Violence in Latin America\n\n\n\n\n\nMiddle East & North Africa \n\n\n\n\n\n\n\n\n\nVisual Explainers\nThe Houthis’ Red Sea Attacks Explained\n\n\n\n\n\n\n\n\nQ&A\nA Glimmer of Peace in Syria’s North East\n\n\n\nBriefing\nThe New Syria: Halting a Dangerous Drift\n\n\n\n\n\nUnited States \n\n\n\n\n\n\n\n\n\nQ&A\nA Glimmer of Peace in Syria’s North East\n\n\n\n\nPodcast\nWhich Way Will Trump Go on Somalia? Donate now\n      \n\n        Learn What We Do\n        \n\n\n\n\n\n    Our Supporters\n  \n\n\n\n\n\nAustralia (Department of Foreign Affairs and Trade)\n\n\n\n\n\nAustria (Austrian Development Agency)\n\n\n\n\n\nCanada (Global Affairs Canada and Canadian Department of National Defence)\n\n\n\n\n\nCarnegie Corporation of New York\n\n\n\n\n\nChevron\n\n\n\n\n\nChris Bake\n\n\n\n\n\nDenmark (Ministry of Foreign Affairs)\n\n\n\n\n\nEni\n\n\n\n\n\nEuropean Union (Instrument contributing to Stability and Peace, Emergency Trust Fund for Africa)\n\n\n\n\n\nFinland (Ministry for Foreign Affairs)\n\n\n\n\n\nFrance (Ministry of Foreign Affairs and French Development Agency)\n\n\n\n\n\nFrank Giustra\n\n\n\n\n\nGlobal Challenges Foundation\n\n\n\n\n\nHerman De Bode\n\n\n\n\n\nIreland (Department of Foreign Affairs)\n\n\n\n\n\nLuxembourg (Ministry of Foreign and European Affairs)\n\n\n\n\n\nNeil Woodyer\n\n\n\n\n\nNew Zealand (Ministry of Foreign Affairs and Trade)\n\n\n\n\n\nNorway (Ministry of Foreign Affairs)\n\n\n\n\n\nOpen Society Foundations\n\n\n\n\n\nQatar (Ministry of Foreign Affairs)\n\n\n\n\n\nRobert Bosch Stiftung\n\n\n\n\n\nRockefeller Brothers Fund\n\n\n\n\n\nStand Together Trust\n\n\n\n\n\nStiftung Mercator\n\n\n\n\n\nSweden (Ministry of Foreign Affairs)\n\n\n\n\n\nSwitzerland (Federal Department of Foreign Affairs)\n\n\n\n\n\nThe Bergman Family Foundation\n\n\n\n\n\nThe Netherlands (Ministry of Foreign Affairs)\n\n\n\n\n\nUnited Arab Emirates (Ministry of Foreign Affairs and International Cooperation and Anwar Gargash Diplomatic Academy)\n\n\n\n\n\nWadah Khanfar\n\n\n\n\n        Learn more about supporting Crisis Group\n\nWill Myanmar’s Devastating Earthquake Impact its Civil War? This week on Hold Your Fire!, Richard Atwood speaks with Crisis Group’s Myanmar expert Richard Horsey about the devastating earthquake that struck Myanmar last week, challenges facing relief efforts and implications for the country’s civil war and its military leaders. The Houthis’ Red Sea Attacks Explained\n\n\n\n\n\n\nVisual Explainers\n\n                                  / Middle East & North Africa\n\n\n\n                \n                The Houthis’ Red Sea Attacks Explained\n              \n\n\n\n\n\n\nThe New Syria: Halting a Dangerous Drift\n\n\n\n\n\n\nBriefing\n\n                                  / Middle East & North Africa\n\n\n\n                \n                The New Syria: Halting a Dangerous Drift\n              \n\n\n\n\n\n                Also available in Arabic\n\n\n\n\n\n\nMarch Trends and April Alerts 2025\n\n\n\n\n\n\n                \n                March Trends and April Alerts 2025\n\nWill Myanmar’s Devastating Earthquake Impact its Civil War? This week on Hold Your Fire!, Richard Atwood speaks with Crisis Group’s Myanmar expert Richard Horsey about the devastating earthquake that struck Myanmar last week, challenges facing relief efforts and implications for the country’s civil war and its military leaders. This week on Hold Your Fire!, Richard Atwood speaks with Crisis Group’s Myanmar expert Richard Horsey about the devastating earthquake that struck Myanmar last week, challenges facing relief efforts and implications for the country’s civil war and its military leaders. This week on Hold Your Fire!, Richard Atwood speaks with Crisis Group’s Myanmar expert Richard Horsey about the devastating earthquake that struck Myanmar last week, challenges facing relief efforts and implications for the country’s civil war and its military leaders. Podcast\n\n                                  / Asia\n\nThis week on Hold Your Fire!, Richard Atwood speaks with Crisis Group’s Myanmar expert Richard Horsey about the devastating earthquake that struck Myanmar last week, challenges facing relief efforts and implications for the country’s civil war and its military leaders. This week on Hold Your Fire!, Richard Atwood speaks with Crisis Group’s Myanmar expert Richard Horsey about the devastating earthquake that struck Myanmar last week, challenges facing relief efforts and implications for the country’s civil war and its military leaders. The Houthis’ Red Sea Attacks Explained\n\n\n\n\n\n\nVisual Explainers\n\n                                  / Middle East & North Africa\n\n\n\n                \n                The Houthis’ Red Sea Attacks Explained\n\nThe Houthis’ Red Sea Attacks Explained\n\nThe Houthis’ Red Sea Attacks Explained\n\nVisual Explainers\n\n                                  / Middle East & North Africa\n\n\n\n                \n                The Houthis’ Red Sea Attacks Explained\n\nVisual Explainers\n\n                                  / Middle East & North Africa\n\nThe New Syria: Halting a Dangerous Drift\n\n\n\n\n\n\nBriefing\n\n                                  / Middle East & North Africa\n\n\n\n                \n                The New Syria: Halting a Dangerous Drift\n              \n\n\n\n\n\n                Also available in Arabic\n\nThe New Syria: Halting a Dangerous Drift\n\nThe New Syria: Halting a Dangerous Drift\n\nBriefing\n\n                                  / Middle East & North Africa\n\n\n\n                \n                The New Syria: Halting a Dangerous Drift\n              \n\n\n\n\n\n                Also available in Arabic\n\nBriefing\n\n                                  / Middle East & North Africa\n\nAlso available in Arabic\n\nMarch Trends and April Alerts 2025\n\n\n\n\n\n\n                \n                March Trends and April Alerts 2025\n\nMarch Trends and April Alerts 2025\n\nMarch Trends and April Alerts 2025\n\nMarch Trends and April Alerts 2025\n\nMiddle East Tensions\n          \n\n            Read more on the issue\n            \n\n\n\n\n\n\n\n\n\n\n\n\n\n\n\n\n\n\n                  Alert\n                \n\n                              / Middle East & North Africa\n\nStopping Israel’s War in Gaza\n\n\nOn 18 March, Israel resumed bombing Gaza, upending a two-month ceasefire. Q&A\n                      \n\n                                          / Middle East & North Africa\n\nA Glimmer of Peace in Syria’s North East\n\n\n\n\n\n\n\n                        Podcast\n                      \n\n                                          / Middle East & North Africa\n\nIsrael Goes Back to War in Gaza\n\n\n\n\n\n\n\n                        Commentary\n                      \n\n                                          / Middle East & North Africa\n\nHow Israel’s Overreach in Syria May Backfire\n\nMiddle East Tensions\n          \n\n            Read more on the issue\n\nAlert\n                \n\n                              / Middle East & North Africa\n\nStopping Israel’s War in Gaza\n\n\nOn 18 March, Israel resumed bombing Gaza, upending a two-month ceasefire. Alert\n                \n\n                              / Middle East & North Africa\n\nStopping Israel’s War in Gaza\n\nAlert\n                \n\n                              / Middle East & North Africa\n\nOn 18 March, Israel resumed bombing Gaza, upending a two-month ceasefire. Q&A\n                      \n\n                                          / Middle East & North Africa\n\nA Glimmer of Peace in Syria’s North East\n\n\n\n\n\n\n\n                        Podcast\n                      \n\n                                          / Middle East & North Africa\n\nIsrael Goes Back to War in Gaza\n\n\n\n\n\n\n\n                        Commentary\n                      \n\n                                          / Middle East & North Africa\n\nHow Israel’s Overreach in Syria May Backfire\n\nQ&A\n                      \n\n                                          / Middle East & North Africa\n\nA Glimmer of Peace in Syria’s North East\n\nQ&A\n                      \n\n                                          / Middle East & North Africa\n\nA Glimmer of Peace in Syria’s North East\n\nQ&A\n                      \n\n                                          / Middle East & North Africa\n\nPodcast\n                      \n\n                                          / Middle East & North Africa\n\nIsrael Goes Back to War in Gaza\n\nPodcast\n                      \n\n                                          / Middle East & North Africa\n\nIsrael Goes Back to War in Gaza\n\nPodcast\n                      \n\n                                          / Middle East & North Africa\n\nCommentary\n                      \n\n                                          / Middle East & North Africa\n\nHow Israel’s Overreach in Syria May Backfire\n\nCommentary\n                      \n\n                                          / Middle East & North Africa\n\nHow Israel’s Overreach in Syria May Backfire\n\nCommentary\n                      \n\n                                          / Middle East & North Africa\n\nSudan\n          \n\n            Read more on Sudan\n            \n\n\n\n\n\n\n\n\n\n\n\n\n\n\n\n\n\n\n                  Statement\n                \n\n                              / Africa\n\nBattle for Khartoum Marks a Crossroads in Sudan’s Civil War\n\n\nThe Sudanese army is pushing to take over Khartoum. Briefing\n                      \n\n                                          / Africa\n\nSudan’s Calamitous War: Finding a Path toward Peace\n\nSudan\n          \n\n            Read more on Sudan\n\nStatement\n                \n\n                              / Africa\n\nBattle for Khartoum Marks a Crossroads in Sudan’s Civil War\n\n\nThe Sudanese army is pushing to take over Khartoum. Briefing\n                      \n\n                                          / Africa\n\nSudan’s Calamitous War: Finding a Path toward Peace\n\nOp-Ed\n                      \n\n                                          / Africa\n\nPeace talks remain the only way out of Sudan’s nightmare\n\nOp-Ed\n                      \n\n                                          / Africa\n\nPeace talks remain the only way out of Sudan’s nightmare\n\nOp-Ed\n                      \n\n                                          / Africa\n\nPodcast\n                      \n\n                                          / Africa\n\nA Decisive Turn in Sudan’s War? Podcast\n                      \n\n                                          / Africa\n\nBriefing\n                      \n\n                                          / Africa\n\nSudan’s Calamitous War: Finding a Path toward Peace\n\nBriefing\n                      \n\n                                          / Africa\n\nSudan’s Calamitous War: Finding a Path toward Peace\n\nBriefing\n                      \n\n                                          / Africa\n\nVideos & Photography\n      \n\n\n\n \n\n\n\n\n\n\n\n\n\n\n\n\nVideo\n\n                                                / Ukraine\n                                              \n\n\nEuropean Security Three Years On From Russia's Full-scale Invasion of Ukraine\n\n\n\n\n\n \n\n\n\n\n\n\n\n\n\n\n\n\nVideo\n\n                                                / Global\n                                              \n\n\nMapping Conflict\n\n\n\n\n\n \n\n\n\n\n\n\n\n\n\n\n\n\nVideo\n\n                                                / Global\n                                              \n\n\nVIDEO | 10 Conflicts to Watch in 2025\n\n\n\n\n\n \n\n\n\n\n\n\n\n\n\n\n\n\nVideo\n\n                                                / Israel/Palestine\n                                              \n\n\nVideo | The Rise of Israeli Settler Violence in the West Bank\n\n\n\n\n\n \n\n\n\n\n\n\n\n\n\n\n\n\nVideo\n\n                                                / Mali\n                                              \n\n\nIbrahim Maiga on Mali's Sovereign Turn\n\n\n\n\n\n \n\n\n\n\n\n\n\n\n\n\n\n\nVideo\n\n                                                / South East Asia\n                                              \n\n\nThe Mekong's Troubled Waters\n\n\n\n\n\n \n\n\n\n\n\n\n\n\n\n\n\n\nVideo\n\n                                                / Morocco\n                                              \n\n\nAlgeria-Morocco Tensions\n\n\n\n\n\n \n\n\n\n\n\n\n\n\n\n\n\n\nVideo\n\n                                                / Mali\n                                              \n\n\nJean-Hervé Jezequel on Mali’s Sovereign Turn\n\n\n\n\n\n \n\n\n\n\n\n\n\n\n\n\n\n\nVideo\n\n                                                / Saudi Arabia\n                                              \n\n\nAbdulaziz Sager: Saudi Arabia's Perspective on the Escalation in the Middle East\n\n\n\n\n\n \n\n\n\n\n\n\n\n\n\n\n\n\nVideo\n\n                                                / Niger\n                                              \n\n\nLa vie des femmes sous l'État islamique dans l'ouest du Niger\n\nVideos & Photography\n      \n\n\n\n \n\n\n\n\n\n\n\n\n\n\n\n\nVideo\n\n                                                / Ukraine\n                                              \n\n\nEuropean Security Three Years On From Russia's Full-scale Invasion of Ukraine\n\n\n\n\n\n \n\n\n\n\n\n\n\n\n\n\n\n\nVideo\n\n                                                / Global\n                                              \n\n\nMapping Conflict\n\n\n\n\n\n \n\n\n\n\n\n\n\n\n\n\n\n\nVideo\n\n                                                / Global\n                                              \n\n\nVIDEO | 10 Conflicts to Watch in 2025\n\n\n\n\n\n \n\n\n\n\n\n\n\n\n\n\n\n\nVideo\n\n                                                / Israel/Palestine\n                                              \n\n\nVideo | The Rise of Israeli Settler Violence in the West Bank\n\n\n\n\n\n \n\n\n\n\n\n\n\n\n\n\n\n\nVideo\n\n                                                / Mali\n                                              \n\n\nIbrahim Maiga on Mali's Sovereign Turn\n\n\n\n\n\n \n\n\n\n\n\n\n\n\n\n\n\n\nVideo\n\n                                                / South East Asia\n                                              \n\n\nThe Mekong's Troubled Waters\n\n\n\n\n\n \n\n\n\n\n\n\n\n\n\n\n\n\nVideo\n\n                                                / Morocco\n                                              \n\n\nAlgeria-Morocco Tensions\n\n\n\n\n\n \n\n\n\n\n\n\n\n\n\n\n\n\nVideo\n\n                                                / Mali\n                                              \n\n\nJean-Hervé Jezequel on Mali’s Sovereign Turn\n\n\n\n\n\n \n\n\n\n\n\n\n\n\n\n\n\n\nVideo\n\n                                                / Saudi Arabia\n                                              \n\n\nAbdulaziz Sager: Saudi Arabia's Perspective on the Escalation in the Middle East\n\n\n\n\n\n \n\n\n\n\n\n\n\n\n\n\n\n\nVideo\n\n                                                / Niger\n                                              \n\n\nLa vie des femmes sous l'État islamique dans l'ouest du Niger\n\nVideo\n\n                                                / Ukraine\n                                              \n\n\nEuropean Security Three Years On From Russia's Full-scale Invasion of Ukraine\n\n\n\n\n\n \n\n\n\n\n\n\n\n\n\n\n\n\nVideo\n\n                                                / Global\n                                              \n\n\nMapping Conflict\n\n\n\n\n\n \n\n\n\n\n\n\n\n\n\n\n\n\nVideo\n\n                                                / Global\n                                              \n\n\nVIDEO | 10 Conflicts to Watch in 2025\n\n\n\n\n\n \n\n\n\n\n\n\n\n\n\n\n\n\nVideo\n\n                                                / Israel/Palestine\n                                              \n\n\nVideo | The Rise of Israeli Settler Violence in the West Bank\n\n\n\n\n\n \n\n\n\n\n\n\n\n\n\n\n\n\nVideo\n\n                                                / Mali\n                                              \n\n\nIbrahim Maiga on Mali's Sovereign Turn\n\n\n\n\n\n \n\n\n\n\n\n\n\n\n\n\n\n\nVideo\n\n                                                / South East Asia\n                                              \n\n\nThe Mekong's Troubled Waters\n\n\n\n\n\n \n\n\n\n\n\n\n\n\n\n\n\n\nVideo\n\n                                                / Morocco\n                                              \n\n\nAlgeria-Morocco Tensions\n\n\n\n\n\n \n\n\n\n\n\n\n\n\n\n\n\n\nVideo\n\n                                                / Mali\n                                              \n\n\nJean-Hervé Jezequel on Mali’s Sovereign Turn\n\n\n\n\n\n \n\n\n\n\n\n\n\n\n\n\n\n\nVideo\n\n                                                / Saudi Arabia\n                                              \n\n\nAbdulaziz Sager: Saudi Arabia's Perspective on the Escalation in the Middle East\n\n\n\n\n\n \n\n\n\n\n\n\n\n\n\n\n\n\nVideo\n\n                                                / Niger\n                                              \n\n\nLa vie des femmes sous l'État islamique dans l'ouest du Niger\n\nVideo\n\n                                                / Ukraine\n                                              \n\n\nEuropean Security Three Years On From Russia's Full-scale Invasion of Ukraine\n\n\n\n\n\n \n\n\n\n\n\n\n\n\n\n\n\n\nVideo\n\n                                                / Global\n                                              \n\n\nMapping Conflict\n\n\n\n\n\n \n\n\n\n\n\n\n\n\n\n\n\n\nVideo\n\n                                                / Global\n                                              \n\n\nVIDEO | 10 Conflicts to Watch in 2025\n\n\n\n\n\n \n\n\n\n\n\n\n\n\n\n\n\n\nVideo\n\n                                                / Israel/Palestine\n                                              \n\n\nVideo | The Rise of Israeli Settler Violence in the West Bank\n\n\n\n\n\n \n\n\n\n\n\n\n\n\n\n\n\n\nVideo\n\n                                                / Mali\n                                              \n\n\nIbrahim Maiga on Mali's Sovereign Turn\n\n\n\n\n\n \n\n\n\n\n\n\n\n\n\n\n\n\nVideo\n\n                                                / South East Asia\n                                              \n\n\nThe Mekong's Troubled Waters\n\n\n\n\n\n \n\n\n\n\n\n\n\n\n\n\n\n\nVideo\n\n                                                / Morocco\n                                              \n\n\nAlgeria-Morocco Tensions\n\n\n\n\n\n \n\n\n\n\n\n\n\n\n\n\n\n\nVideo\n\n                                                / Mali\n                                              \n\n\nJean-Hervé Jezequel on Mali’s Sovereign Turn\n\n\n\n\n\n \n\n\n\n\n\n\n\n\n\n\n\n\nVideo\n\n                                                / Saudi Arabia\n                                              \n\n\nAbdulaziz Sager: Saudi Arabia's Perspective on the Escalation in the Middle East\n\n\n\n\n\n \n\n\n\n\n\n\n\n\n\n\n\n\nVideo\n\n                                                / Niger\n                                              \n\n\nLa vie des femmes sous l'État islamique dans l'ouest du Niger\n\nVideo\n\n                                                / Ukraine\n                                              \n\n\nEuropean Security Three Years On From Russia's Full-scale Invasion of Ukraine\n\nVideo\n\n                                                / Ukraine\n                                              \n\n\nEuropean Security Three Years On From Russia's Full-scale Invasion of Ukraine\n\nVideo\n\n                                                / Ukraine\n                                              \n\n\nEuropean Security Three Years On From Russia's Full-scale Invasion of Ukraine\n\nVideo\n\n                                                / Ukraine\n\nVideo\n\n                                                / Global\n                                              \n\n\nMapping Conflict\n\nVideo\n\n                                                / Global\n                                              \n\n\nMapping Conflict\n\nVideo\n\n                                                / Global\n                                              \n\n\nMapping Conflict\n\nVideo\n\n                                                / Global\n\nVideo\n\n                                                / Global\n                                              \n\n\nVIDEO | 10 Conflicts to Watch in 2025\n\nVideo\n\n                                                / Global\n                                              \n\n\nVIDEO | 10 Conflicts to Watch in 2025\n\nVideo\n\n                                                / Global\n                                              \n\n\nVIDEO | 10 Conflicts to Watch in 2025\n\nVideo\n\n                                                / Global\n\nVideo\n\n                                                / Israel/Palestine\n                                              \n\n\nVideo | The Rise of Israeli Settler Violence in the West Bank\n\nVideo\n\n                                                / Israel/Palestine\n                                              \n\n\nVideo | The Rise of Israeli Settler Violence in the West Bank\n\nVideo\n\n                                                / Israel/Palestine\n                                              \n\n\nVideo | The Rise of Israeli Settler Violence in the West Bank\n\nVideo\n\n                                                / Israel/Palestine\n\nVideo\n\n                                                / Mali\n                                              \n\n\nIbrahim Maiga on Mali's Sovereign Turn\n\nVideo\n\n                                                / Mali\n                                              \n\n\nIbrahim Maiga on Mali's Sovereign Turn\n\nVideo\n\n                                                / Mali\n                                              \n\n\nIbrahim Maiga on Mali's Sovereign Turn\n\nVideo\n\n                                                / Mali\n\nVideo\n\n                                                / South East Asia\n                                              \n\n\nThe Mekong's Troubled Waters\n\nVideo\n\n                                                / South East Asia\n                                              \n\n\nThe Mekong's Troubled Waters\n\nVideo\n\n                                                / South East Asia\n                                              \n\n\nThe Mekong's Troubled Waters\n\nVideo\n\n                                                / South East Asia\n\nVideo\n\n                                                / Morocco\n                                              \n\n\nAlgeria-Morocco Tensions\n\nVideo\n\n                                                / Morocco\n                                              \n\n\nAlgeria-Morocco Tensions\n\nVideo\n\n                                                / Morocco\n                                              \n\n\nAlgeria-Morocco Tensions\n\nVideo\n\n                                                / Morocco\n\nVideo\n\n                                                / Mali\n                                              \n\n\nJean-Hervé Jezequel on Mali’s Sovereign Turn\n\nVideo\n\n                                                / Mali\n                                              \n\n\nJean-Hervé Jezequel on Mali’s Sovereign Turn\n\nVideo\n\n                                                / Mali\n                                              \n\n\nJean-Hervé Jezequel on Mali’s Sovereign Turn\n\nVideo\n\n                                                / Mali\n\nVideo\n\n                                                / Saudi Arabia\n                                              \n\n\nAbdulaziz Sager: Saudi Arabia's Perspective on the Escalation in the Middle East\n\nVideo\n\n                                                / Saudi Arabia\n                                              \n\n\nAbdulaziz Sager: Saudi Arabia's Perspective on the Escalation in the Middle East\n\nVideo\n\n                                                / Saudi Arabia\n                                              \n\n\nAbdulaziz Sager: Saudi Arabia's Perspective on the Escalation in the Middle East\n\nVideo\n\n                                                / Saudi Arabia\n\nVideo\n\n                                                / Niger\n                                              \n\n\nLa vie des femmes sous l'État islamique dans l'ouest du Niger\n\nVideo\n\n                                                / Niger\n                                              \n\n\nLa vie des femmes sous l'État islamique dans l'ouest du Niger\n\nVideo\n\n                                                / Niger\n                                              \n\n\nLa vie des femmes sous l'État islamique dans l'ouest du Niger\n\nVideo\n\n                                                / Niger\n\nVisual Explainers\n      \n\n\n\n \n\n\n\n\n\n\n\n\nUkraine War Map: Tracking the Frontlines\n\n\n\n \n\n\n\n\n\n\n\n\nVisual Explainer: Ten Conflicts to Watch in 2024\n\n\n\n \n\n\n\n\n\n\n\n\nThe U.S. DW\n      \n\n\n\n\n\n\n\n\n\n\nRichard Horsey\n\nSenior Adviser, Myanmar\n\n4 Apr 2025\n\nRichard Horsey\n\nSenior Adviser, Myanmar\n\nRichard Horsey\n\nSenior Adviser, Myanmar\n\nSenior Adviser, Myanmar\n\n3 Apr 2025\n    \n\n            What we're seeing very explicitly from the Israeli political echelon is that they actually want to lay the groundwork and begin moving towards the de-population of Gaza. Al Jazeera\n      \n\n\n\n\n\n\n\n\n\n\nDaniel Akech\n\nSenior Analyst, South Sudan\n\n27 Mar 2025\n\nDaniel Akech\n\nSenior Analyst, South Sudan\n\nDaniel Akech\n\nSenior Analyst, South Sudan\n\nSenior Analyst, South Sudan\n\n25 Mar 2025\n    \n\n            The idea that [Israeli] military strikes will pressure Hamas to release hostages without an end to the war [in Gaza] is unrealistic at best, and disingenuous at worst. Arab News\n      \n\n\n\n\n\n\n\n\n\n\nMairav Zonszein\n\nSenior Analyst, Israel\n\n25 Mar 2025\n\nMairav Zonszein\n\nSenior Analyst, Israel\n\nMairav Zonszein\n\nSenior Analyst, Israel\n\nSenior Analyst, Israel\n\n24 Mar 2025\n    \n\n            There's obviously a fork in the road ahead after the Sudanese army takes Khartoum. AFP\n      \n\n\n\n\n\n\n\n\n\n\nAlan Boswell\n\nProject Director, Horn of Africa\n\n24 Mar 2025\n\nAlan Boswell\n\nProject Director, Horn of Africa\n\nAlan Boswell\n\nProject Director, Horn of Africa\n\nProject Director, Horn of Africa\n\nRegional Updates\n    \n\n\n\nGlobal \n\n\n\n\n\n\n\n\n\nSpecial Coverage\nOn Our Radar\n\n\n\n\nQ&A\nUnpacking the Use of U.S. Wartime Powers against a Criminal “Invasion”\n\n\nSpecial Coverage\nComfort Ero’s 2025 Top Picks on Gender and Conflict\n\n\n\n\n\nAfrica \n\n\n\n\n\n\n\n\n\nPodcast\nSouth Sudan on the Brink of Another War\n\n\n\n\nAlert\nEthiopia and Eritrea Slide Closer to War amid Tigray Upheaval \n\n\nPodcast\nWhich Way Will Trump Go on Somalia? Q&A\nSupport Vital for Myanmar’s Quake Victims, Despite Military Obstacles \n\n\nBriefing\nDisquiet on the Western Front: A Divided Resistance in Myanmar’s Chin State\n\n\n\n\n\nEurope & Central Asia \n\n\n\n\n\n\n\n\n\nQ&A\nA Glimmer of Peace in Syria’s North East\n\n\n\n\nPodcast\nLatin America’s Evolving Drug Trade. Why It Matters for Europe\n\n\nVisual Explainers\nHow a New Drug Trafficking Landscape Fuels Violence in Latin America\n\n\n\n\n\nMiddle East & North Africa \n\n\n\n\n\n\n\n\n\nVisual Explainers\nThe Houthis’ Red Sea Attacks Explained\n\n\n\n\n\n\n\n\nQ&A\nA Glimmer of Peace in Syria’s North East\n\n\n\nBriefing\nThe New Syria: Halting a Dangerous Drift\n\n\n\n\n\nUnited States \n\n\n\n\n\n\n\n\n\nQ&A\nA Glimmer of Peace in Syria’s North East\n\n\n\n\nPodcast\nWhich Way Will Trump Go on Somalia? Wartime Powers against a Criminal “Invasion”\n\n\nSpecial Coverage\nComfort Ero’s 2025 Top Picks on Gender and Conflict\n\n\n\n\n\nAfrica \n\n\n\n\n\n\n\n\n\nPodcast\nSouth Sudan on the Brink of Another War\n\n\n\n\nAlert\nEthiopia and Eritrea Slide Closer to War amid Tigray Upheaval \n\n\nPodcast\nWhich Way Will Trump Go on Somalia? Q&A\nSupport Vital for Myanmar’s Quake Victims, Despite Military Obstacles \n\n\nBriefing\nDisquiet on the Western Front: A Divided Resistance in Myanmar’s Chin State\n\n\n\n\n\nEurope & Central Asia \n\n\n\n\n\n\n\n\n\nQ&A\nA Glimmer of Peace in Syria’s North East\n\n\n\n\nPodcast\nLatin America’s Evolving Drug Trade. Why It Matters for Europe\n\n\nVisual Explainers\nHow a New Drug Trafficking Landscape Fuels Violence in Latin America\n\n\n\n\n\nMiddle East & North Africa \n\n\n\n\n\n\n\n\n\nVisual Explainers\nThe Houthis’ Red Sea Attacks Explained\n\n\n\n\n\n\n\n\nQ&A\nA Glimmer of Peace in Syria’s North East\n\n\n\nBriefing\nThe New Syria: Halting a Dangerous Drift\n\n\n\n\n\nUnited States \n\n\n\n\n\n\n\n\n\nQ&A\nA Glimmer of Peace in Syria’s North East\n\n\n\n\nPodcast\nWhich Way Will Trump Go on Somalia? Wartime Powers against a Criminal “Invasion”\n\nSpecial Coverage\nComfort Ero’s 2025 Top Picks on Gender and Conflict\n\nAfrica \n\n\n\n\n\n\n\n\n\nPodcast\nSouth Sudan on the Brink of Another War\n\n\n\n\nAlert\nEthiopia and Eritrea Slide Closer to War amid Tigray Upheaval \n\n\nPodcast\nWhich Way Will Trump Go on Somalia? Q&A\nSupport Vital for Myanmar’s Quake Victims, Despite Military Obstacles \n\n\nBriefing\nDisquiet on the Western Front: A Divided Resistance in Myanmar’s Chin State\n\nPodcast\nWill Myanmar’s Devastating Earthquake Impact its Civil War? Q&A\nSupport Vital for Myanmar’s Quake Victims, Despite Military Obstacles \n\n\nBriefing\nDisquiet on the Western Front: A Divided Resistance in Myanmar’s Chin State\n\nQ&A\nSupport Vital for Myanmar’s Quake Victims, Despite Military Obstacles\n\nBriefing\nDisquiet on the Western Front: A Divided Resistance in Myanmar’s Chin State\n\nEurope & Central Asia \n\n\n\n\n\n\n\n\n\nQ&A\nA Glimmer of Peace in Syria’s North East\n\n\n\n\nPodcast\nLatin America’s Evolving Drug Trade. Why It Matters for Europe\n\n\nPodcast\nTrump, France and European Security\n\nQ&A\nA Glimmer of Peace in Syria’s North East\n\nPodcast\nLatin America’s Evolving Drug Trade. Why It Matters for Europe\n\nVisual Explainers\nHow a New Drug Trafficking Landscape Fuels Violence in Latin America\n\nMiddle East & North Africa \n\n\n\n\n\n\n\n\n\nVisual Explainers\nThe Houthis’ Red Sea Attacks Explained\n\n\n\n\n\n\n\n\nQ&A\nA Glimmer of Peace in Syria’s North East\n\n\n\nBriefing\nThe New Syria: Halting a Dangerous Drift\n\nVisual Explainers\nThe Houthis’ Red Sea Attacks Explained\n\nQ&A\nA Glimmer of Peace in Syria’s North East\n\n\n\nBriefing\nThe New Syria: Halting a Dangerous Drift\n\nQ&A\nA Glimmer of Peace in Syria’s North East\n\nBriefing\nThe New Syria: Halting a Dangerous Drift\n\nUnited States \n\n\n\n\n\n\n\n\n\nQ&A\nA Glimmer of Peace in Syria’s North East\n\n\n\n\nPodcast\nWhich Way Will Trump Go on Somalia? Donate now\n      \n\n        Learn What We Do\n        \n\n\n\n\n\n    Our Supporters\n  \n\n\n\n\n\nAustralia (Department of Foreign Affairs and Trade)\n\n\n\n\n\nAustria (Austrian Development Agency)\n\n\n\n\n\nCanada (Global Affairs Canada and Canadian Department of National Defence)\n\n\n\n\n\nCarnegie Corporation of New York\n\n\n\n\n\nChevron\n\n\n\n\n\nChris Bake\n\n\n\n\n\nDenmark (Ministry of Foreign Affairs)\n\n\n\n\n\nEni\n\n\n\n\n\nEuropean Union (Instrument contributing to Stability and Peace, Emergency Trust Fund for Africa)\n\n\n\n\n\nFinland (Ministry for Foreign Affairs)\n\n\n\n\n\nFrance (Ministry of Foreign Affairs and French Development Agency)\n\n\n\n\n\nFrank Giustra\n\n\n\n\n\nGlobal Challenges Foundation\n\n\n\n\n\nHerman De Bode\n\n\n\n\n\nIreland (Department of Foreign Affairs)\n\n\n\n\n\nLuxembourg (Ministry of Foreign and European Affairs)\n\n\n\n\n\nNeil Woodyer\n\n\n\n\n\nNew Zealand (Ministry of Foreign Affairs and Trade)\n\n\n\n\n\nNorway (Ministry of Foreign Affairs)\n\n\n\n\n\nOpen Society Foundations\n\n\n\n\n\nQatar (Ministry of Foreign Affairs)\n\n\n\n\n\nRobert Bosch Stiftung\n\n\n\n\n\nRockefeller Brothers Fund\n\n\n\n\n\nStand Together Trust\n\n\n\n\n\nStiftung Mercator\n\n\n\n\n\nSweden (Ministry of Foreign Affairs)\n\n\n\n\n\nSwitzerland (Federal Department of Foreign Affairs)\n\n\n\n\n\nThe Bergman Family Foundation\n\n\n\n\n\nThe Netherlands (Ministry of Foreign Affairs)\n\n\n\n\n\nUnited Arab Emirates (Ministry of Foreign Affairs and International Cooperation and Anwar Gargash Diplomatic Academy)\n\n\n\n\n\nWadah Khanfar\n\n\n\n\n        Learn more about supporting Crisis Group\n\nSupport Us\n\nYour investment helps us to meet the growing demand for our work as we confront a terrible trend toward more wars, more civilians killed and more people displaced worldwide. Our Supporters\n  \n\n\n\n\n\nAustralia (Department of Foreign Affairs and Trade)\n\n\n\n\n\nAustria (Austrian Development Agency)\n\n\n\n\n\nCanada (Global Affairs Canada and Canadian Department of National Defence)\n\n\n\n\n\nCarnegie Corporation of New York\n\n\n\n\n\nChevron\n\n\n\n\n\nChris Bake\n\n\n\n\n\nDenmark (Ministry of Foreign Affairs)\n\n\n\n\n\nEni\n\n\n\n\n\nEuropean Union (Instrument contributing to Stability and Peace, Emergency Trust Fund for Africa)\n\n\n\n\n\nFinland (Ministry for Foreign Affairs)\n\n\n\n\n\nFrance (Ministry of Foreign Affairs and French Development Agency)\n\n\n\n\n\nFrank Giustra\n\n\n\n\n\nGlobal Challenges Foundation\n\n\n\n\n\nHerman De Bode\n\n\n\n\n\nIreland (Department of Foreign Affairs)\n\n\n\n\n\nLuxembourg (Ministry of Foreign and European Affairs)\n\n\n\n\n\nNeil Woodyer\n\n\n\n\n\nNew Zealand (Ministry of Foreign Affairs and Trade)\n\n\n\n\n\nNorway (Ministry of Foreign Affairs)\n\n\n\n\n\nOpen Society Foundations\n\n\n\n\n\nQatar (Ministry of Foreign Affairs)\n\n\n\n\n\nRobert Bosch Stiftung\n\n\n\n\n\nRockefeller Brothers Fund\n\n\n\n\n\nStand Together Trust\n\n\n\n\n\nStiftung Mercator\n\n\n\n\n\nSweden (Ministry of Foreign Affairs)\n\n\n\n\n\nSwitzerland (Federal Department of Foreign Affairs)\n\n\n\n\n\nThe Bergman Family Foundation\n\n\n\n\n\nThe Netherlands (Ministry of Foreign Affairs)\n\n\n\n\n\nUnited Arab Emirates (Ministry of Foreign Affairs and International Cooperation and Anwar Gargash Diplomatic Academy)\n\n\n\n\n\nWadah Khanfar\n\n\n\n\n        Learn more about supporting Crisis Group\n\nAustralia (Department of Foreign Affairs and Trade)\n\n\n\n\n\nAustria (Austrian Development Agency)\n\n\n\n\n\nCanada (Global Affairs Canada and Canadian Department of National Defence)\n\n\n\n\n\nCarnegie Corporation of New York\n\n\n\n\n\nChevron\n\n\n\n\n\nChris Bake\n\n\n\n\n\nDenmark (Ministry of Foreign Affairs)\n\n\n\n\n\nEni\n\n\n\n\n\nEuropean Union (Instrument contributing to Stability and Peace, Emergency Trust Fund for Africa)\n\n\n\n\n\nFinland (Ministry for Foreign Affairs)\n\n\n\n\n\nFrance (Ministry of Foreign Affairs and French Development Agency)\n\n\n\n\n\nFrank Giustra\n\n\n\n\n\nGlobal Challenges Foundation\n\n\n\n\n\nHerman De Bode\n\n\n\n\n\nIreland (Department of Foreign Affairs)\n\n\n\n\n\nLuxembourg (Ministry of Foreign and European Affairs)\n\n\n\n\n\nNeil Woodyer\n\n\n\n\n\nNew Zealand (Ministry of Foreign Affairs and Trade)\n\n\n\n\n\nNorway (Ministry of Foreign Affairs)\n\n\n\n\n\nOpen Society Foundations\n\n\n\n\n\nQatar (Ministry of Foreign Affairs)\n\n\n\n\n\nRobert Bosch Stiftung\n\n\n\n\n\nRockefeller Brothers Fund\n\n\n\n\n\nStand Together Trust\n\n\n\n\n\nStiftung Mercator\n\n\n\n\n\nSweden (Ministry of Foreign Affairs)\n\n\n\n\n\nSwitzerland (Federal Department of Foreign Affairs)\n\n\n\n\n\nThe Bergman Family Foundation\n\n\n\n\n\nThe Netherlands (Ministry of Foreign Affairs)\n\n\n\n\n\nUnited Arab Emirates (Ministry of Foreign Affairs and International Cooperation and Anwar Gargash Diplomatic Academy)\n\n\n\n\n\nWadah Khanfar\n\nAustralia (Department of Foreign Affairs and Trade)\n\nAustralia (Department of Foreign Affairs and Trade)\n\nAustria (Austrian Development Agency)\n\nAustria (Austrian Development Agency)\n\nCanada (Global Affairs Canada and Canadian Department of National Defence)\n\nCanada (Global Affairs Canada and Canadian Department of National Defence)\n\nCarnegie Corporation of New York\n\nCarnegie Corporation of New York\n\nChevron\n\nChevron\n\nChris Bake\n\nChris Bake\n\nDenmark (Ministry of Foreign Affairs)\n\nDenmark (Ministry of Foreign Affairs)\n\nEni\n\nEni\n\nEuropean Union (Instrument contributing to Stability and Peace, Emergency Trust Fund for Africa)\n\nEuropean Union (Instrument contributing to Stability and Peace, Emergency Trust Fund for Africa)\n\nFinland (Ministry for Foreign Affairs)\n\nFinland (Ministry for Foreign Affairs)\n\nFrance (Ministry of Foreign Affairs and French Development Agency)\n\nFrance (Ministry of Foreign Affairs and French Development Agency)\n\nFrank Giustra\n\nFrank Giustra\n\nGlobal Challenges Foundation\n\nGlobal Challenges Foundation\n\nHerman De Bode\n\nHerman De Bode\n\nIreland (Department of Foreign Affairs)\n\nIreland (Department of Foreign Affairs)\n\nLuxembourg (Ministry of Foreign and European Affairs)\n\nLuxembourg (Ministry of Foreign and European Affairs)\n\nNeil Woodyer\n\nNeil Woodyer\n\nNew Zealand (Ministry of Foreign Affairs and Trade)\n\nNew Zealand (Ministry of Foreign Affairs and Trade)\n\nNorway (Ministry of Foreign Affairs)\n\nNorway (Ministry of Foreign Affairs)\n\nOpen Society Foundations\n\nOpen Society Foundations\n\nQatar (Ministry of Foreign Affairs)\n\nQatar (Ministry of Foreign Affairs)\n\nRobert Bosch Stiftung\n\nRobert Bosch Stiftung\n\nRockefeller Brothers Fund\n\nRockefeller Brothers Fund\n\nStand Together Trust\n\nStand Together Trust\n\nStiftung Mercator\n\nStiftung Mercator\n\nSweden (Ministry of Foreign Affairs)\n\nSweden (Ministry of Foreign Affairs)\n\nSwitzerland (Federal Department of Foreign Affairs)\n\nSwitzerland (Federal Department of Foreign Affairs)\n\nThe Bergman Family Foundation\n\nThe Bergman Family Foundation\n\nThe Netherlands (Ministry of Foreign Affairs)\n\nThe Netherlands (Ministry of Foreign Affairs)\n\nUnited Arab Emirates (Ministry of Foreign Affairs and International Cooperation and Anwar Gargash Diplomatic Academy)\n\nUnited Arab Emirates (Ministry of Foreign Affairs and International Cooperation and Anwar Gargash Diplomatic Academy)\n\nWadah Khanfar\n\nWadah Khanfar\n\nLearn more about supporting Crisis Group\n\nSubscribe to Crisis Group’s Email Updates\n\n\n\nReceive the best source of conflict analysis right in your inbox.",
  "entities": {
    "countries": [
      "australia",
      "canada",
      "france",
      "iraq",
      "israel",
      "russia",
      "syria",
      "united states"
    ],
    "organizations": [
      "un",
      "who"
    ],
    "key_issues": [
      "issue",
      "challenge",
      "crisis",
      "matter",
      "country",
      "nation",
      "state",
      "government",
      "region",
      "strategy",
      "policy",
      "context",
      "development",
      "humanitarian",
      "aid",
      "assistance",
      "relief",
      "trade",
      "investment",
      "un",
      "agency",
      "foundation"
    ]
  },
  "committee": "First Committee",
  "topic": "Combating the rise of extremist groups in the Sahel"
}