{
  "url": "https://www.accessnow.org/grants/",
  "title": "Access Now Grants - Access Now",
  "text": "Back to content\n\nACCESS NOW GRANTS\n\n\n\n\n\n\nWho We Fund\nWhat We Fund\nHow We Fund\n\n\nWe provide flexible and grantee-driven funding to grassroots and frontline organizations fighting for human rights in the digital age. We pursue this work at a time when civil society around the world is working under increasingly difficult circumstances, from targeted censorship, to restrictions on operations, to threats to physical safety. It is also a time when the digital space has become a critical battleground in broader human rights struggles, as well as a place where marginalization, societal discrimination, and violence can be reproduced and even amplified. We aim to strengthen the global digital rights community by expanding, diversifying, and empowering the movement at the grassroots.\n\n\nWho we Fund\nOur grantees work with users and communities most at risk of and most detrimentally impacted, online or off, by digital rights violations.\n\n\n\n\n\n\nWhere We Fund\n\n\nWe fund work in low- and middle-income countries, parts of the world receiving the least amount of human rights funding. In rare cases, we support efforts that directly support people in one of these countries, even if the grantee is not based there.\n\n\n\n\nWhere We Fund\n\n\nWe fund work in low- and middle-income countries, parts of the world receiving the least amount of human rights funding. In rare cases, we support efforts that directly support people in one of these countries, even if the grantee is not based there.\n\n\n\nWe Prioritize\n\nGrassroots organizations rooted in at-risk communities with limited access to funding\n\n\nFrontline organizations working in contexts where the impacts of digital rights violations are most severe\n\n\nOrganizations working at the intersection of digital rights and other human rights issues\n\n\nFeminist organizations working to protect the digital rights of women, LGBTQ+ people, and gender nonconforming people\n\n\n\n\nFeatured Grantees\n\n\n\n\n\n\n\n\n\nAcoso.Online\nBuilding Latin America’s first context-specific resource for victims of online harassment, including dissemination of nonconsensual pornography. From reporting to online platforms, to pursuing legal remedies, to opening community dialogue and defending sexual freedoms, Acoso.Online empowers women, LGBTQ+ people, and their supporters to report, recover, and resist. The tool is localized in 14 countries, with coverage expanding throughout the region.\n\n\n\n\n\n\n\n\n\n\n\nSursiendo\nConducting participatory research to uncover the digital security needs of activists and human rights defenders in Chiapas, Mexico, as well as the broader context of surveillance and other digital threats to human rights and the state.\nSursiendo supports at-risk users in a region with a history of violent repression of social movements and indigenous communities.\n\n\n\n\n\n\n\n\n\n\n\n7amleh\nResearching issues including censorship, surveillance, and profiling of Palestinians on social media, and advocating for better policies to protect Palestinians’ freedom of expression. 7amleh has integrated digital rights into the broader Palestinian rights movement and has led the charge within Palestinian civil society to hold tech companies accountable for the human rights impact of their policies.\n\n\n\n\n\n\n\n\n\n\n\niFreedom Uganda\nTraining sex workers and LGBTQ+ individuals on digital security, and advocating for internet freedoms from a human rights perspective. iFreedom Uganda — a network of 28 member organizations — was founded to ensure that marginalized groups in Uganda are able to freely express themselves without fear of reprisal from state agencies and dangerous hacking groups.\n\n\n\n\n\n\n\n\n\n\n\nFundación Acceso\nProviding systematic physical, technological, legal, and psychosocial assistance to human rights defenders, journalists, environmental and indigenous rights activists, and feminist and LGBTQ+ leaders across Central America, who face violence and criminalization of their activism. Acceso coordinates efforts to document and investigate digital attacks on civil society through its Regional Digital Security Observatory.\n\n\n\n\n\n\n\n\n\nSee full list of grantees\n\n\n\n\nWHAT WE FUND\nThreats to digital rights take many forms, depending on the context and unique challenges specific users or communities face, ranging from censorship and network disruption, to communications surveillance, to lack of protections for personal data, to online harassment, and beyond. Likewise, Access Now grantees are tackling a diverse array of digital rights challenges with an equally diverse set of approaches depending on their context and the opportunities they see to create positive change.\nSome examples of what Access Now Grants supports include:\n\n\nResearch, monitoring, advocacy, and public campaigns to fight internet shutdowns\n\n\nDigital security accompaniment for users at risk, such as women, LGBTQ+ people, human rights defenders, and minority communities\n\n\nEfforts to combat online violence through direct interventions with at-risk users and tech companies\n\n\nDocumentation and advocacy to fight impunity for digital attacks on human rights defenders, journalists, activists, and other at-risk groups\n\n\nProtection of digital civic space during elections and conflict, and in the face of content takedowns, surveillance, troll armies, etc.\n\n\nProjects to integrate digital rights into broader human rights movements to ensure they are effective and protected in the digital space\n\n\nStrategies for advancing individual control of our digital identities that center the experiences of those most detrimentally impacted by violations of privacy rights\n\n\nAnd more!\n\n\n\n\nHOW WE FUND\nOur grantmaking is grounded in international human rights frameworks and takes an intersectional approach that recognizes that threats to digital rights are compounded when they intersect with other human rights abuses or discrimination based on ethnicity, religion, gender, sexuality, class, or other means of marginalization. Our commitment to communities and users most at risk manifests itself in different ways in different contexts and focuses on these intersections.\nAccess Now’s Digital Security Helpline, global team, and Advisory Board are integral to our ability to identify and understand the needs of grassroots activists and organizations.\n\n\n\n\n\n\nTRANSPARENCY\nBe transparent about criteria, internal processes, and decisions\n\n\nACCOUNTABILITY\nEnsure respect for and accountability to our grantees through our processes and communications, while acknowledging and working to flatten the power imbalances between funder and grantee\n\n\nSIMPLICITY\nUse clear and simple procedures and language that can be understood by applicants and the broader community\n\n\n\n\n\n\n\n\nCONTEXT\nAllow local actors and communities to define priorities and set their own goals\n\n\nFLEXIBILITY\nProvide flexibility to respond to emerging opportunities and external needs\n\n\nLIMITED BUREAUCRACY\nRequire limited paperwork and reduce the administrative burden on grantees whenever possible\n\n\n\n\n\n\n\n\nENGAGEMENT\nContinuously self-evaluate and engage within the sector to identify how Access Now can most effectively operate, fund, and contribute\n\n\n\n\n\n\n\n\n\nTypes of Grants\n\n\nPROJECT GRANTS\nFunds projects with explicit end goals, finite timelines, and clear objectives.\nAVERAGE GRANT: $29,000\n\n\nCORE GRANTS\nAwarded to organizations whose activities are closely aligned with the mission of Access Now Grants, and who have a demonstrated body of programmatic work.\n\nFunds can be used for any general operating costs.\nAVERAGE GRANT: $54,000\n\n\nDISCRETIONARY GRANTS\nFunds initiatives responding to emergencies and emerging needs or capturing imminent opportunities.\n\nFunds are small and short term.\n\nMaximum grant size is $10,000.\nAVERAGE GRANT: $7,000\n\n\nDIGITAL SAFE SPACES GRANTS\nFunds human rights organizations that are amplifying the voices of marginalized groups online and want to improve their digital security. The nature of their work and the communities they work on behalf of may make them particularly at risk online or particularly effective online.\nAVERAGE GRANT: $9,000\n\n\n\nApplication Process\n\n\n\nWANT TO KNOW MORE? Email us at [email protected]\n\n\n\nAdvisory Board\nAccess Now has assembled an Advisory Board to provide strategic guidance and oversight of grant recipients. This board is made up of experts in the regions and fields in which Access Now gives grants, and helps us ensure accountability, local relevance, and community engagement in our program. We would like to thank the following individuals for donating their time and energy:\n\nAbir Ghattas (Lebanon)Information Security Technologist, Human Rights Watch\n\nArzu Geybullyeva (Azerbaijan / Turkey)Regional Analyst & Blogger, Global Voices\n\nSaadat Baigazieva (Kyrgyzstan)Feminist activist in fields ranging from gender justice, digital security, and cyberfeminism, to climate and environmental justice, sexual and reproductive rights, and disability rights. Co-lead of the CEECCNA collaborative fund.\n\nHarlo Holmes (U.S.)Digital Security Trainer, Freedom of the Press Foundation\n\nLoreto Bravo (Mexico)Consultant in feminist psychosocial accompaniment in the defense of human rights, technological sovereignty, and digital protection.\n\nBerhan Taye (Ethiopia / Kenya)Tech and Social Justice Researcher and Advisor\n\n\n\nStatement on Grantee Autonomy: While Access Now Grants works closely with Access Now’s other programmatic teams, Access Now Grantees are under no requirement to collaborate with Access Now’s Policy, Advocacy, Tech, or RightsCon teams or to agree with Access Now’s positions and tactics on specific issues. The grants program has the independence to support grantees’ efforts regardless of whether they are aligned with Access Now’s policy positions. We take the aim of diversifying the digital rights movement seriously, and this includes diversity of perspectives, analysis, and tactics.\n\n\n\nCREDITS\nAccess Now Grants is supported by the Swedish International Development Agency, the Dutch Ministry of Foreign Affairs, and other funders. Please contact us at [email protected] if you are interested in supporting our grants program.\n\n\n\n\n\n \n\n\n\n\n\n\nHelp keep the internet open and secure.\nSubscribe to our action alerts and weekly newsletter\n\"*\" indicates required fields\n\nThis field is hidden when viewing the form\n\nSubscribe to Access Express\nThis field is hidden when viewing the form\n\nSubscribe to Action Alerts\nName\n\n\nFirst\n\n\n\nLast\n\nEmail*\n\nCountryCountryAfghanistanÅland IslandsAlbaniaAlgeriaAmerican SamoaAndorraAngolaAnguillaAntigua and BarbudaArgentinaArmeniaArubaAustraliaAustriaAzerbaijanBahamasBahrainBangladeshBarbadosBelarusBelgiumBelizeBeninBermudaBhutanBoliviaBonaire, Sint Eustatius and SabaBosnia and HerzegovinaBotswanaBrazilBritish Indian Ocean TerritoryBritish Virgin IslandsBruneiBulgariaBurkina FasoBurundiCambodiaCameroonCanadaCape VerdeCayman IslandsCentral African RepublicChadChileChinaChristmas IslandColombiaComorosCook IslandsCosta RicaCôte d'IvoireCroatiaCubaCuraçaoCyprusCzech RepublicDemocratic Republic of the CongoDenmarkDjiboutiDominicaDominican RepublicEast TimorEcuadorEgyptEl SalvadorEquatorial GuineaEritreaEstoniaEswatiniEthiopiaFalkland IslandsFaroe IslandsFijiFinlandFranceFrench GuianaFrench PolynesiaFrench Southern TerritoriesGabonGeorgiaGermanyGhanaGibraltarGreeceGreenlandGrenadaGuadeloupeGuamGuatemalaGuernseyGuineaGuinea-BissauGuyanaHaitiHondurasHong KongHungaryIcelandIndiaIndonesiaIranIraqIrelandIsraelItalyJamaicaJapanJordanKazakhstanKenyaKiribatiKosovoKuwaitKyrgyzstanLaosLatviaLebanonLesothoLiberiaLibyaLiechtensteinLithuaniaLuxembourgMacauMadagascarMalawiMalaysiaMaldivesMaliMaltaMarshall IslandsMartiniqueMauritaniaMauritiusMayotteMexicoMicronesiaMoldovaMonacoMongoliaMontenegroMontserratMoroccoMozambiqueMyanmarNamibiaNauruNepalNetherlands AntillesNew CaledoniaNew ZealandNicaraguaNigerNigeriaNiueNorfolk IslandNorth KoreaNorth MacedoniaNorthern Mariana IslandsNorwayOmanPakistanPalauPalestinePanamaPapua New GuineaParaguayPeruPhilippinesPitcairn IslandPolandPortugalPuerto RicoQatarRepublic of the CongoReunionRomaniaRussiaRwandaSaint BarthélemySaint Kitts and NevisSaint LuciaSaint Vincent and the GrenadinesSamoaSan MarinoSão Tomé and PríncipeSaudi ArabiaSenegalSerbiaSeychellesSierra LeoneSingaporeSlovakiaSloveniaSolomon IslandsSomaliaSomalilandSouth AfricaSouth KoreaSouth SudanSpainSri LankaSt. HelenaSt. Pierre and MiquelonSudanSurinameSwedenSwitzerlandSyriaTaiwanTajikistanTanzaniaThailandThe GambiaThe NetherlandsTogoTokelauTongaTrinidad and TobagoTunisiaTurkeyTurkmenistanTurks and Caicos IslandsTuvaluUgandaUkraineUnited Arab EmiratesUnited KingdomUnited StatesUruguayUzbekistanVanuatuVatican CityVenezuelaVietnamVirgin Islands (U.S.)Wallis and Futuna IslandsWestern SaharaYemenZambiaZimbabwePostal CodeCommentsThis field is for validation purposes and should be left unchanged.\n \n\n\n\n\n\n\n\n\n\n\n\n\n\n\n\nYour info is secure with us\n\nACCESS NOW GRANTS\n\n\n\n\n\n\nWho We Fund\nWhat We Fund\nHow We Fund\n\n\nWe provide flexible and grantee-driven funding to grassroots and frontline organizations fighting for human rights in the digital age. We pursue this work at a time when civil society around the world is working under increasingly difficult circumstances, from targeted censorship, to restrictions on operations, to threats to physical safety. It is also a time when the digital space has become a critical battleground in broader human rights struggles, as well as a place where marginalization, societal discrimination, and violence can be reproduced and even amplified. We aim to strengthen the global digital rights community by expanding, diversifying, and empowering the movement at the grassroots.\n\n\nWho we Fund\nOur grantees work with users and communities most at risk of and most detrimentally impacted, online or off, by digital rights violations.\n\n\n\n\n\n\nWhere We Fund\n\n\nWe fund work in low- and middle-income countries, parts of the world receiving the least amount of human rights funding. In rare cases, we support efforts that directly support people in one of these countries, even if the grantee is not based there.\n\n\n\n\nWhere We Fund\n\n\nWe fund work in low- and middle-income countries, parts of the world receiving the least amount of human rights funding. In rare cases, we support efforts that directly support people in one of these countries, even if the grantee is not based there.\n\n\n\nWe Prioritize\n\nGrassroots organizations rooted in at-risk communities with limited access to funding\n\n\nFrontline organizations working in contexts where the impacts of digital rights violations are most severe\n\n\nOrganizations working at the intersection of digital rights and other human rights issues\n\n\nFeminist organizations working to protect the digital rights of women, LGBTQ+ people, and gender nonconforming people\n\n\n\n\nFeatured Grantees\n\n\n\n\n\n\n\n\n\nAcoso.Online\nBuilding Latin America’s first context-specific resource for victims of online harassment, including dissemination of nonconsensual pornography. From reporting to online platforms, to pursuing legal remedies, to opening community dialogue and defending sexual freedoms, Acoso.Online empowers women, LGBTQ+ people, and their supporters to report, recover, and resist. The tool is localized in 14 countries, with coverage expanding throughout the region.\n\n\n\n\n\n\n\n\n\n\n\nSursiendo\nConducting participatory research to uncover the digital security needs of activists and human rights defenders in Chiapas, Mexico, as well as the broader context of surveillance and other digital threats to human rights and the state.\nSursiendo supports at-risk users in a region with a history of violent repression of social movements and indigenous communities.\n\n\n\n\n\n\n\n\n\n\n\n7amleh\nResearching issues including censorship, surveillance, and profiling of Palestinians on social media, and advocating for better policies to protect Palestinians’ freedom of expression. 7amleh has integrated digital rights into the broader Palestinian rights movement and has led the charge within Palestinian civil society to hold tech companies accountable for the human rights impact of their policies.\n\n\n\n\n\n\n\n\n\n\n\niFreedom Uganda\nTraining sex workers and LGBTQ+ individuals on digital security, and advocating for internet freedoms from a human rights perspective. iFreedom Uganda — a network of 28 member organizations — was founded to ensure that marginalized groups in Uganda are able to freely express themselves without fear of reprisal from state agencies and dangerous hacking groups.\n\n\n\n\n\n\n\n\n\n\n\nFundación Acceso\nProviding systematic physical, technological, legal, and psychosocial assistance to human rights defenders, journalists, environmental and indigenous rights activists, and feminist and LGBTQ+ leaders across Central America, who face violence and criminalization of their activism. Acceso coordinates efforts to document and investigate digital attacks on civil society through its Regional Digital Security Observatory.\n\n\n\n\n\n\n\n\n\nSee full list of grantees\n\n\n\n\nWHAT WE FUND\nThreats to digital rights take many forms, depending on the context and unique challenges specific users or communities face, ranging from censorship and network disruption, to communications surveillance, to lack of protections for personal data, to online harassment, and beyond. Likewise, Access Now grantees are tackling a diverse array of digital rights challenges with an equally diverse set of approaches depending on their context and the opportunities they see to create positive change.\nSome examples of what Access Now Grants supports include:\n\n\nResearch, monitoring, advocacy, and public campaigns to fight internet shutdowns\n\n\nDigital security accompaniment for users at risk, such as women, LGBTQ+ people, human rights defenders, and minority communities\n\n\nEfforts to combat online violence through direct interventions with at-risk users and tech companies\n\n\nDocumentation and advocacy to fight impunity for digital attacks on human rights defenders, journalists, activists, and other at-risk groups\n\n\nProtection of digital civic space during elections and conflict, and in the face of content takedowns, surveillance, troll armies, etc.\n\n\nProjects to integrate digital rights into broader human rights movements to ensure they are effective and protected in the digital space\n\n\nStrategies for advancing individual control of our digital identities that center the experiences of those most detrimentally impacted by violations of privacy rights\n\n\nAnd more!\n\n\n\n\nHOW WE FUND\nOur grantmaking is grounded in international human rights frameworks and takes an intersectional approach that recognizes that threats to digital rights are compounded when they intersect with other human rights abuses or discrimination based on ethnicity, religion, gender, sexuality, class, or other means of marginalization. Our commitment to communities and users most at risk manifests itself in different ways in different contexts and focuses on these intersections.\nAccess Now’s Digital Security Helpline, global team, and Advisory Board are integral to our ability to identify and understand the needs of grassroots activists and organizations.\n\n\n\n\n\n\nTRANSPARENCY\nBe transparent about criteria, internal processes, and decisions\n\n\nACCOUNTABILITY\nEnsure respect for and accountability to our grantees through our processes and communications, while acknowledging and working to flatten the power imbalances between funder and grantee\n\n\nSIMPLICITY\nUse clear and simple procedures and language that can be understood by applicants and the broader community\n\n\n\n\n\n\n\n\nCONTEXT\nAllow local actors and communities to define priorities and set their own goals\n\n\nFLEXIBILITY\nProvide flexibility to respond to emerging opportunities and external needs\n\n\nLIMITED BUREAUCRACY\nRequire limited paperwork and reduce the administrative burden on grantees whenever possible\n\n\n\n\n\n\n\n\nENGAGEMENT\nContinuously self-evaluate and engage within the sector to identify how Access Now can most effectively operate, fund, and contribute\n\n\n\n\n\n\n\n\n\nTypes of Grants\n\n\nPROJECT GRANTS\nFunds projects with explicit end goals, finite timelines, and clear objectives.\nAVERAGE GRANT: $29,000\n\n\nCORE GRANTS\nAwarded to organizations whose activities are closely aligned with the mission of Access Now Grants, and who have a demonstrated body of programmatic work.\n\nFunds can be used for any general operating costs.\nAVERAGE GRANT: $54,000\n\n\nDISCRETIONARY GRANTS\nFunds initiatives responding to emergencies and emerging needs or capturing imminent opportunities.\n\nFunds are small and short term.\n\nMaximum grant size is $10,000.\nAVERAGE GRANT: $7,000\n\n\nDIGITAL SAFE SPACES GRANTS\nFunds human rights organizations that are amplifying the voices of marginalized groups online and want to improve their digital security. The nature of their work and the communities they work on behalf of may make them particularly at risk online or particularly effective online.\nAVERAGE GRANT: $9,000\n\n\n\nApplication Process\n\n\n\nWANT TO KNOW MORE? Email us at [email protected]\n\n\n\nAdvisory Board\nAccess Now has assembled an Advisory Board to provide strategic guidance and oversight of grant recipients. This board is made up of experts in the regions and fields in which Access Now gives grants, and helps us ensure accountability, local relevance, and community engagement in our program. We would like to thank the following individuals for donating their time and energy:\n\nAbir Ghattas (Lebanon)Information Security Technologist, Human Rights Watch\n\nArzu Geybullyeva (Azerbaijan / Turkey)Regional Analyst & Blogger, Global Voices\n\nSaadat Baigazieva (Kyrgyzstan)Feminist activist in fields ranging from gender justice, digital security, and cyberfeminism, to climate and environmental justice, sexual and reproductive rights, and disability rights. Co-lead of the CEECCNA collaborative fund.\n\nHarlo Holmes (U.S.)Digital Security Trainer, Freedom of the Press Foundation\n\nLoreto Bravo (Mexico)Consultant in feminist psychosocial accompaniment in the defense of human rights, technological sovereignty, and digital protection.\n\nBerhan Taye (Ethiopia / Kenya)Tech and Social Justice Researcher and Advisor\n\n\n\nStatement on Grantee Autonomy: While Access Now Grants works closely with Access Now’s other programmatic teams, Access Now Grantees are under no requirement to collaborate with Access Now’s Policy, Advocacy, Tech, or RightsCon teams or to agree with Access Now’s positions and tactics on specific issues. The grants program has the independence to support grantees’ efforts regardless of whether they are aligned with Access Now’s policy positions. We take the aim of diversifying the digital rights movement seriously, and this includes diversity of perspectives, analysis, and tactics.\n\n\n\nCREDITS\nAccess Now Grants is supported by the Swedish International Development Agency, the Dutch Ministry of Foreign Affairs, and other funders. Please contact us at [email protected] if you are interested in supporting our grants program.\n\nACCESS NOW GRANTS\n\n\n\n\n\n\nWho We Fund\nWhat We Fund\nHow We Fund\n\n\nWe provide flexible and grantee-driven funding to grassroots and frontline organizations fighting for human rights in the digital age. We pursue this work at a time when civil society around the world is working under increasingly difficult circumstances, from targeted censorship, to restrictions on operations, to threats to physical safety. It is also a time when the digital space has become a critical battleground in broader human rights struggles, as well as a place where marginalization, societal discrimination, and violence can be reproduced and even amplified. We aim to strengthen the global digital rights community by expanding, diversifying, and empowering the movement at the grassroots.\n\n\nWho we Fund\nOur grantees work with users and communities most at risk of and most detrimentally impacted, online or off, by digital rights violations.\n\n\n\n\n\n\nWhere We Fund\n\n\nWe fund work in low- and middle-income countries, parts of the world receiving the least amount of human rights funding. In rare cases, we support efforts that directly support people in one of these countries, even if the grantee is not based there.\n\n\n\n\nWhere We Fund\n\n\nWe fund work in low- and middle-income countries, parts of the world receiving the least amount of human rights funding. In rare cases, we support efforts that directly support people in one of these countries, even if the grantee is not based there.\n\n\n\nWe Prioritize\n\nGrassroots organizations rooted in at-risk communities with limited access to funding\n\n\nFrontline organizations working in contexts where the impacts of digital rights violations are most severe\n\n\nOrganizations working at the intersection of digital rights and other human rights issues\n\n\nFeminist organizations working to protect the digital rights of women, LGBTQ+ people, and gender nonconforming people\n\n\n\n\nFeatured Grantees\n\n\n\n\n\n\n\n\n\nAcoso.Online\nBuilding Latin America’s first context-specific resource for victims of online harassment, including dissemination of nonconsensual pornography. From reporting to online platforms, to pursuing legal remedies, to opening community dialogue and defending sexual freedoms, Acoso.Online empowers women, LGBTQ+ people, and their supporters to report, recover, and resist. The tool is localized in 14 countries, with coverage expanding throughout the region.\n\n\n\n\n\n\n\n\n\n\n\nSursiendo\nConducting participatory research to uncover the digital security needs of activists and human rights defenders in Chiapas, Mexico, as well as the broader context of surveillance and other digital threats to human rights and the state.\nSursiendo supports at-risk users in a region with a history of violent repression of social movements and indigenous communities.\n\n\n\n\n\n\n\n\n\n\n\n7amleh\nResearching issues including censorship, surveillance, and profiling of Palestinians on social media, and advocating for better policies to protect Palestinians’ freedom of expression. 7amleh has integrated digital rights into the broader Palestinian rights movement and has led the charge within Palestinian civil society to hold tech companies accountable for the human rights impact of their policies.\n\n\n\n\n\n\n\n\n\n\n\niFreedom Uganda\nTraining sex workers and LGBTQ+ individuals on digital security, and advocating for internet freedoms from a human rights perspective. iFreedom Uganda — a network of 28 member organizations — was founded to ensure that marginalized groups in Uganda are able to freely express themselves without fear of reprisal from state agencies and dangerous hacking groups.\n\n\n\n\n\n\n\n\n\n\n\nFundación Acceso\nProviding systematic physical, technological, legal, and psychosocial assistance to human rights defenders, journalists, environmental and indigenous rights activists, and feminist and LGBTQ+ leaders across Central America, who face violence and criminalization of their activism. Acceso coordinates efforts to document and investigate digital attacks on civil society through its Regional Digital Security Observatory.\n\n\n\n\n\n\n\n\n\nSee full list of grantees\n\n\n\n\nWHAT WE FUND\nThreats to digital rights take many forms, depending on the context and unique challenges specific users or communities face, ranging from censorship and network disruption, to communications surveillance, to lack of protections for personal data, to online harassment, and beyond. Likewise, Access Now grantees are tackling a diverse array of digital rights challenges with an equally diverse set of approaches depending on their context and the opportunities they see to create positive change.\nSome examples of what Access Now Grants supports include:\n\n\nResearch, monitoring, advocacy, and public campaigns to fight internet shutdowns\n\n\nDigital security accompaniment for users at risk, such as women, LGBTQ+ people, human rights defenders, and minority communities\n\n\nEfforts to combat online violence through direct interventions with at-risk users and tech companies\n\n\nDocumentation and advocacy to fight impunity for digital attacks on human rights defenders, journalists, activists, and other at-risk groups\n\n\nProtection of digital civic space during elections and conflict, and in the face of content takedowns, surveillance, troll armies, etc.\n\n\nProjects to integrate digital rights into broader human rights movements to ensure they are effective and protected in the digital space\n\n\nStrategies for advancing individual control of our digital identities that center the experiences of those most detrimentally impacted by violations of privacy rights\n\n\nAnd more!\n\n\n\n\nHOW WE FUND\nOur grantmaking is grounded in international human rights frameworks and takes an intersectional approach that recognizes that threats to digital rights are compounded when they intersect with other human rights abuses or discrimination based on ethnicity, religion, gender, sexuality, class, or other means of marginalization. Our commitment to communities and users most at risk manifests itself in different ways in different contexts and focuses on these intersections.\nAccess Now’s Digital Security Helpline, global team, and Advisory Board are integral to our ability to identify and understand the needs of grassroots activists and organizations.\n\n\n\n\n\n\nTRANSPARENCY\nBe transparent about criteria, internal processes, and decisions\n\n\nACCOUNTABILITY\nEnsure respect for and accountability to our grantees through our processes and communications, while acknowledging and working to flatten the power imbalances between funder and grantee\n\n\nSIMPLICITY\nUse clear and simple procedures and language that can be understood by applicants and the broader community\n\n\n\n\n\n\n\n\nCONTEXT\nAllow local actors and communities to define priorities and set their own goals\n\n\nFLEXIBILITY\nProvide flexibility to respond to emerging opportunities and external needs\n\n\nLIMITED BUREAUCRACY\nRequire limited paperwork and reduce the administrative burden on grantees whenever possible\n\n\n\n\n\n\n\n\nENGAGEMENT\nContinuously self-evaluate and engage within the sector to identify how Access Now can most effectively operate, fund, and contribute\n\n\n\n\n\n\n\n\n\nTypes of Grants\n\n\nPROJECT GRANTS\nFunds projects with explicit end goals, finite timelines, and clear objectives.\nAVERAGE GRANT: $29,000\n\n\nCORE GRANTS\nAwarded to organizations whose activities are closely aligned with the mission of Access Now Grants, and who have a demonstrated body of programmatic work.\n\nFunds can be used for any general operating costs.\nAVERAGE GRANT: $54,000\n\n\nDISCRETIONARY GRANTS\nFunds initiatives responding to emergencies and emerging needs or capturing imminent opportunities.\n\nFunds are small and short term.\n\nMaximum grant size is $10,000.\nAVERAGE GRANT: $7,000\n\n\nDIGITAL SAFE SPACES GRANTS\nFunds human rights organizations that are amplifying the voices of marginalized groups online and want to improve their digital security. The nature of their work and the communities they work on behalf of may make them particularly at risk online or particularly effective online.\nAVERAGE GRANT: $9,000\n\n\n\nApplication Process\n\n\n\nWANT TO KNOW MORE? Email us at [email protected]\n\n\n\nAdvisory Board\nAccess Now has assembled an Advisory Board to provide strategic guidance and oversight of grant recipients. This board is made up of experts in the regions and fields in which Access Now gives grants, and helps us ensure accountability, local relevance, and community engagement in our program. We would like to thank the following individuals for donating their time and energy:\n\nAbir Ghattas (Lebanon)Information Security Technologist, Human Rights Watch\n\nArzu Geybullyeva (Azerbaijan / Turkey)Regional Analyst & Blogger, Global Voices\n\nSaadat Baigazieva (Kyrgyzstan)Feminist activist in fields ranging from gender justice, digital security, and cyberfeminism, to climate and environmental justice, sexual and reproductive rights, and disability rights. Co-lead of the CEECCNA collaborative fund.\n\nHarlo Holmes (U.S.)Digital Security Trainer, Freedom of the Press Foundation\n\nLoreto Bravo (Mexico)Consultant in feminist psychosocial accompaniment in the defense of human rights, technological sovereignty, and digital protection.\n\nBerhan Taye (Ethiopia / Kenya)Tech and Social Justice Researcher and Advisor\n\n\n\nStatement on Grantee Autonomy: While Access Now Grants works closely with Access Now’s other programmatic teams, Access Now Grantees are under no requirement to collaborate with Access Now’s Policy, Advocacy, Tech, or RightsCon teams or to agree with Access Now’s positions and tactics on specific issues. The grants program has the independence to support grantees’ efforts regardless of whether they are aligned with Access Now’s policy positions. We take the aim of diversifying the digital rights movement seriously, and this includes diversity of perspectives, analysis, and tactics.\n\n\n\nCREDITS\nAccess Now Grants is supported by the Swedish International Development Agency, the Dutch Ministry of Foreign Affairs, and other funders. Please contact us at [email protected] if you are interested in supporting our grants program.\n\nACCESS NOW GRANTS\n\n\n\n\n\n\nWho We Fund\nWhat We Fund\nHow We Fund\n\n\nWe provide flexible and grantee-driven funding to grassroots and frontline organizations fighting for human rights in the digital age. We pursue this work at a time when civil society around the world is working under increasingly difficult circumstances, from targeted censorship, to restrictions on operations, to threats to physical safety. It is also a time when the digital space has become a critical battleground in broader human rights struggles, as well as a place where marginalization, societal discrimination, and violence can be reproduced and even amplified. We aim to strengthen the global digital rights community by expanding, diversifying, and empowering the movement at the grassroots.\n\n\nWho we Fund\nOur grantees work with users and communities most at risk of and most detrimentally impacted, online or off, by digital rights violations.\n\n\n\n\n\n\nWhere We Fund\n\n\nWe fund work in low- and middle-income countries, parts of the world receiving the least amount of human rights funding. In rare cases, we support efforts that directly support people in one of these countries, even if the grantee is not based there.\n\n\n\n\nWhere We Fund\n\n\nWe fund work in low- and middle-income countries, parts of the world receiving the least amount of human rights funding. In rare cases, we support efforts that directly support people in one of these countries, even if the grantee is not based there.\n\n\n\nWe Prioritize\n\nGrassroots organizations rooted in at-risk communities with limited access to funding\n\n\nFrontline organizations working in contexts where the impacts of digital rights violations are most severe\n\n\nOrganizations working at the intersection of digital rights and other human rights issues\n\n\nFeminist organizations working to protect the digital rights of women, LGBTQ+ people, and gender nonconforming people\n\n\n\n\nFeatured Grantees\n\n\n\n\n\n\n\n\n\nAcoso.Online\nBuilding Latin America’s first context-specific resource for victims of online harassment, including dissemination of nonconsensual pornography. From reporting to online platforms, to pursuing legal remedies, to opening community dialogue and defending sexual freedoms, Acoso.Online empowers women, LGBTQ+ people, and their supporters to report, recover, and resist. The tool is localized in 14 countries, with coverage expanding throughout the region.\n\n\n\n\n\n\n\n\n\n\n\nSursiendo\nConducting participatory research to uncover the digital security needs of activists and human rights defenders in Chiapas, Mexico, as well as the broader context of surveillance and other digital threats to human rights and the state.\nSursiendo supports at-risk users in a region with a history of violent repression of social movements and indigenous communities.\n\n\n\n\n\n\n\n\n\n\n\n7amleh\nResearching issues including censorship, surveillance, and profiling of Palestinians on social media, and advocating for better policies to protect Palestinians’ freedom of expression. 7amleh has integrated digital rights into the broader Palestinian rights movement and has led the charge within Palestinian civil society to hold tech companies accountable for the human rights impact of their policies.\n\n\n\n\n\n\n\n\n\n\n\niFreedom Uganda\nTraining sex workers and LGBTQ+ individuals on digital security, and advocating for internet freedoms from a human rights perspective. iFreedom Uganda — a network of 28 member organizations — was founded to ensure that marginalized groups in Uganda are able to freely express themselves without fear of reprisal from state agencies and dangerous hacking groups.\n\n\n\n\n\n\n\n\n\n\n\nFundación Acceso\nProviding systematic physical, technological, legal, and psychosocial assistance to human rights defenders, journalists, environmental and indigenous rights activists, and feminist and LGBTQ+ leaders across Central America, who face violence and criminalization of their activism. Acceso coordinates efforts to document and investigate digital attacks on civil society through its Regional Digital Security Observatory.\n\n\n\n\n\n\n\n\n\nSee full list of grantees\n\n\n\n\nWHAT WE FUND\nThreats to digital rights take many forms, depending on the context and unique challenges specific users or communities face, ranging from censorship and network disruption, to communications surveillance, to lack of protections for personal data, to online harassment, and beyond. Likewise, Access Now grantees are tackling a diverse array of digital rights challenges with an equally diverse set of approaches depending on their context and the opportunities they see to create positive change.\nSome examples of what Access Now Grants supports include:\n\n\nResearch, monitoring, advocacy, and public campaigns to fight internet shutdowns\n\n\nDigital security accompaniment for users at risk, such as women, LGBTQ+ people, human rights defenders, and minority communities\n\n\nEfforts to combat online violence through direct interventions with at-risk users and tech companies\n\n\nDocumentation and advocacy to fight impunity for digital attacks on human rights defenders, journalists, activists, and other at-risk groups\n\n\nProtection of digital civic space during elections and conflict, and in the face of content takedowns, surveillance, troll armies, etc.\n\n\nProjects to integrate digital rights into broader human rights movements to ensure they are effective and protected in the digital space\n\n\nStrategies for advancing individual control of our digital identities that center the experiences of those most detrimentally impacted by violations of privacy rights\n\n\nAnd more!\n\n\n\n\nHOW WE FUND\nOur grantmaking is grounded in international human rights frameworks and takes an intersectional approach that recognizes that threats to digital rights are compounded when they intersect with other human rights abuses or discrimination based on ethnicity, religion, gender, sexuality, class, or other means of marginalization. Our commitment to communities and users most at risk manifests itself in different ways in different contexts and focuses on these intersections.\nAccess Now’s Digital Security Helpline, global team, and Advisory Board are integral to our ability to identify and understand the needs of grassroots activists and organizations.\n\n\n\n\n\n\nTRANSPARENCY\nBe transparent about criteria, internal processes, and decisions\n\n\nACCOUNTABILITY\nEnsure respect for and accountability to our grantees through our processes and communications, while acknowledging and working to flatten the power imbalances between funder and grantee\n\n\nSIMPLICITY\nUse clear and simple procedures and language that can be understood by applicants and the broader community\n\n\n\n\n\n\n\n\nCONTEXT\nAllow local actors and communities to define priorities and set their own goals\n\n\nFLEXIBILITY\nProvide flexibility to respond to emerging opportunities and external needs\n\n\nLIMITED BUREAUCRACY\nRequire limited paperwork and reduce the administrative burden on grantees whenever possible\n\n\n\n\n\n\n\n\nENGAGEMENT\nContinuously self-evaluate and engage within the sector to identify how Access Now can most effectively operate, fund, and contribute\n\n\n\n\n\n\n\n\n\nTypes of Grants\n\n\nPROJECT GRANTS\nFunds projects with explicit end goals, finite timelines, and clear objectives.\nAVERAGE GRANT: $29,000\n\n\nCORE GRANTS\nAwarded to organizations whose activities are closely aligned with the mission of Access Now Grants, and who have a demonstrated body of programmatic work.\n\nFunds can be used for any general operating costs.\nAVERAGE GRANT: $54,000\n\n\nDISCRETIONARY GRANTS\nFunds initiatives responding to emergencies and emerging needs or capturing imminent opportunities.\n\nFunds are small and short term.\n\nMaximum grant size is $10,000.\nAVERAGE GRANT: $7,000\n\n\nDIGITAL SAFE SPACES GRANTS\nFunds human rights organizations that are amplifying the voices of marginalized groups online and want to improve their digital security. The nature of their work and the communities they work on behalf of may make them particularly at risk online or particularly effective online.\nAVERAGE GRANT: $9,000\n\n\n\nApplication Process\n\n\n\nWANT TO KNOW MORE? Email us at [email protected]\n\n\n\nAdvisory Board\nAccess Now has assembled an Advisory Board to provide strategic guidance and oversight of grant recipients. This board is made up of experts in the regions and fields in which Access Now gives grants, and helps us ensure accountability, local relevance, and community engagement in our program. We would like to thank the following individuals for donating their time and energy:\n\nAbir Ghattas (Lebanon)Information Security Technologist, Human Rights Watch\n\nArzu Geybullyeva (Azerbaijan / Turkey)Regional Analyst & Blogger, Global Voices\n\nSaadat Baigazieva (Kyrgyzstan)Feminist activist in fields ranging from gender justice, digital security, and cyberfeminism, to climate and environmental justice, sexual and reproductive rights, and disability rights. Co-lead of the CEECCNA collaborative fund.\n\nHarlo Holmes (U.S.)Digital Security Trainer, Freedom of the Press Foundation\n\nLoreto Bravo (Mexico)Consultant in feminist psychosocial accompaniment in the defense of human rights, technological sovereignty, and digital protection.\n\nBerhan Taye (Ethiopia / Kenya)Tech and Social Justice Researcher and Advisor\n\n\n\nStatement on Grantee Autonomy: While Access Now Grants works closely with Access Now’s other programmatic teams, Access Now Grantees are under no requirement to collaborate with Access Now’s Policy, Advocacy, Tech, or RightsCon teams or to agree with Access Now’s positions and tactics on specific issues. The grants program has the independence to support grantees’ efforts regardless of whether they are aligned with Access Now’s policy positions. We take the aim of diversifying the digital rights movement seriously, and this includes diversity of perspectives, analysis, and tactics.\n\n\n\nCREDITS\nAccess Now Grants is supported by the Swedish International Development Agency, the Dutch Ministry of Foreign Affairs, and other funders. Please contact us at [email protected] if you are interested in supporting our grants program.\n\nACCESS NOW GRANTS\n\n\n\n\n\n\nWho We Fund\nWhat We Fund\nHow We Fund\n\n\nWe provide flexible and grantee-driven funding to grassroots and frontline organizations fighting for human rights in the digital age. We pursue this work at a time when civil society around the world is working under increasingly difficult circumstances, from targeted censorship, to restrictions on operations, to threats to physical safety. It is also a time when the digital space has become a critical battleground in broader human rights struggles, as well as a place where marginalization, societal discrimination, and violence can be reproduced and even amplified. We aim to strengthen the global digital rights community by expanding, diversifying, and empowering the movement at the grassroots.\n\n\nWho we Fund\nOur grantees work with users and communities most at risk of and most detrimentally impacted, online or off, by digital rights violations.\n\n\n\n\n\n\nWhere We Fund\n\n\nWe fund work in low- and middle-income countries, parts of the world receiving the least amount of human rights funding. In rare cases, we support efforts that directly support people in one of these countries, even if the grantee is not based there.\n\n\n\n\nWhere We Fund\n\n\nWe fund work in low- and middle-income countries, parts of the world receiving the least amount of human rights funding. In rare cases, we support efforts that directly support people in one of these countries, even if the grantee is not based there.\n\n\n\nWe Prioritize\n\nGrassroots organizations rooted in at-risk communities with limited access to funding\n\n\nFrontline organizations working in contexts where the impacts of digital rights violations are most severe\n\n\nOrganizations working at the intersection of digital rights and other human rights issues\n\n\nFeminist organizations working to protect the digital rights of women, LGBTQ+ people, and gender nonconforming people\n\n\n\n\nFeatured Grantees\n\n\n\n\n\n\n\n\n\nAcoso.Online\nBuilding Latin America’s first context-specific resource for victims of online harassment, including dissemination of nonconsensual pornography. From reporting to online platforms, to pursuing legal remedies, to opening community dialogue and defending sexual freedoms, Acoso.Online empowers women, LGBTQ+ people, and their supporters to report, recover, and resist. The tool is localized in 14 countries, with coverage expanding throughout the region.\n\n\n\n\n\n\n\n\n\n\n\nSursiendo\nConducting participatory research to uncover the digital security needs of activists and human rights defenders in Chiapas, Mexico, as well as the broader context of surveillance and other digital threats to human rights and the state.\nSursiendo supports at-risk users in a region with a history of violent repression of social movements and indigenous communities.\n\n\n\n\n\n\n\n\n\n\n\n7amleh\nResearching issues including censorship, surveillance, and profiling of Palestinians on social media, and advocating for better policies to protect Palestinians’ freedom of expression. 7amleh has integrated digital rights into the broader Palestinian rights movement and has led the charge within Palestinian civil society to hold tech companies accountable for the human rights impact of their policies.\n\n\n\n\n\n\n\n\n\n\n\niFreedom Uganda\nTraining sex workers and LGBTQ+ individuals on digital security, and advocating for internet freedoms from a human rights perspective. iFreedom Uganda — a network of 28 member organizations — was founded to ensure that marginalized groups in Uganda are able to freely express themselves without fear of reprisal from state agencies and dangerous hacking groups.\n\n\n\n\n\n\n\n\n\n\n\nFundación Acceso\nProviding systematic physical, technological, legal, and psychosocial assistance to human rights defenders, journalists, environmental and indigenous rights activists, and feminist and LGBTQ+ leaders across Central America, who face violence and criminalization of their activism. Acceso coordinates efforts to document and investigate digital attacks on civil society through its Regional Digital Security Observatory.\n\n\n\n\n\n\n\n\n\nSee full list of grantees\n\n\n\n\nWHAT WE FUND\nThreats to digital rights take many forms, depending on the context and unique challenges specific users or communities face, ranging from censorship and network disruption, to communications surveillance, to lack of protections for personal data, to online harassment, and beyond. Likewise, Access Now grantees are tackling a diverse array of digital rights challenges with an equally diverse set of approaches depending on their context and the opportunities they see to create positive change.\nSome examples of what Access Now Grants supports include:\n\n\nResearch, monitoring, advocacy, and public campaigns to fight internet shutdowns\n\n\nDigital security accompaniment for users at risk, such as women, LGBTQ+ people, human rights defenders, and minority communities\n\n\nEfforts to combat online violence through direct interventions with at-risk users and tech companies\n\n\nDocumentation and advocacy to fight impunity for digital attacks on human rights defenders, journalists, activists, and other at-risk groups\n\n\nProtection of digital civic space during elections and conflict, and in the face of content takedowns, surveillance, troll armies, etc.\n\n\nProjects to integrate digital rights into broader human rights movements to ensure they are effective and protected in the digital space\n\n\nStrategies for advancing individual control of our digital identities that center the experiences of those most detrimentally impacted by violations of privacy rights\n\n\nAnd more!\n\n\n\n\nHOW WE FUND\nOur grantmaking is grounded in international human rights frameworks and takes an intersectional approach that recognizes that threats to digital rights are compounded when they intersect with other human rights abuses or discrimination based on ethnicity, religion, gender, sexuality, class, or other means of marginalization. Our commitment to communities and users most at risk manifests itself in different ways in different contexts and focuses on these intersections.\nAccess Now’s Digital Security Helpline, global team, and Advisory Board are integral to our ability to identify and understand the needs of grassroots activists and organizations.\n\n\n\n\n\n\nTRANSPARENCY\nBe transparent about criteria, internal processes, and decisions\n\n\nACCOUNTABILITY\nEnsure respect for and accountability to our grantees through our processes and communications, while acknowledging and working to flatten the power imbalances between funder and grantee\n\n\nSIMPLICITY\nUse clear and simple procedures and language that can be understood by applicants and the broader community\n\n\n\n\n\n\n\n\nCONTEXT\nAllow local actors and communities to define priorities and set their own goals\n\n\nFLEXIBILITY\nProvide flexibility to respond to emerging opportunities and external needs\n\n\nLIMITED BUREAUCRACY\nRequire limited paperwork and reduce the administrative burden on grantees whenever possible\n\n\n\n\n\n\n\n\nENGAGEMENT\nContinuously self-evaluate and engage within the sector to identify how Access Now can most effectively operate, fund, and contribute\n\n\n\n\n\n\n\n\n\nTypes of Grants\n\n\nPROJECT GRANTS\nFunds projects with explicit end goals, finite timelines, and clear objectives.\nAVERAGE GRANT: $29,000\n\n\nCORE GRANTS\nAwarded to organizations whose activities are closely aligned with the mission of Access Now Grants, and who have a demonstrated body of programmatic work.\n\nFunds can be used for any general operating costs.\nAVERAGE GRANT: $54,000\n\n\nDISCRETIONARY GRANTS\nFunds initiatives responding to emergencies and emerging needs or capturing imminent opportunities.\n\nFunds are small and short term.\n\nMaximum grant size is $10,000.\nAVERAGE GRANT: $7,000\n\n\nDIGITAL SAFE SPACES GRANTS\nFunds human rights organizations that are amplifying the voices of marginalized groups online and want to improve their digital security. The nature of their work and the communities they work on behalf of may make them particularly at risk online or particularly effective online.\nAVERAGE GRANT: $9,000\n\n\n\nApplication Process\n\n\n\nWANT TO KNOW MORE? Email us at [email protected]\n\n\n\nAdvisory Board\nAccess Now has assembled an Advisory Board to provide strategic guidance and oversight of grant recipients. This board is made up of experts in the regions and fields in which Access Now gives grants, and helps us ensure accountability, local relevance, and community engagement in our program. We would like to thank the following individuals for donating their time and energy:\n\nAbir Ghattas (Lebanon)Information Security Technologist, Human Rights Watch\n\nArzu Geybullyeva (Azerbaijan / Turkey)Regional Analyst & Blogger, Global Voices\n\nSaadat Baigazieva (Kyrgyzstan)Feminist activist in fields ranging from gender justice, digital security, and cyberfeminism, to climate and environmental justice, sexual and reproductive rights, and disability rights. Co-lead of the CEECCNA collaborative fund.\n\nHarlo Holmes (U.S.)Digital Security Trainer, Freedom of the Press Foundation\n\nLoreto Bravo (Mexico)Consultant in feminist psychosocial accompaniment in the defense of human rights, technological sovereignty, and digital protection.\n\nBerhan Taye (Ethiopia / Kenya)Tech and Social Justice Researcher and Advisor\n\n\n\nStatement on Grantee Autonomy: While Access Now Grants works closely with Access Now’s other programmatic teams, Access Now Grantees are under no requirement to collaborate with Access Now’s Policy, Advocacy, Tech, or RightsCon teams or to agree with Access Now’s positions and tactics on specific issues. The grants program has the independence to support grantees’ efforts regardless of whether they are aligned with Access Now’s policy positions. We take the aim of diversifying the digital rights movement seriously, and this includes diversity of perspectives, analysis, and tactics.\n\n\n\nCREDITS\nAccess Now Grants is supported by the Swedish International Development Agency, the Dutch Ministry of Foreign Affairs, and other funders. Please contact us at [email protected] if you are interested in supporting our grants program.\n\nACCESS NOW GRANTS\n\n\n\n\n\n\nWho We Fund\nWhat We Fund\nHow We Fund\n\n\nWe provide flexible and grantee-driven funding to grassroots and frontline organizations fighting for human rights in the digital age. We pursue this work at a time when civil society around the world is working under increasingly difficult circumstances, from targeted censorship, to restrictions on operations, to threats to physical safety. It is also a time when the digital space has become a critical battleground in broader human rights struggles, as well as a place where marginalization, societal discrimination, and violence can be reproduced and even amplified. We aim to strengthen the global digital rights community by expanding, diversifying, and empowering the movement at the grassroots.\n\n\nWho we Fund\nOur grantees work with users and communities most at risk of and most detrimentally impacted, online or off, by digital rights violations.\n\n\n\n\n\n\nWhere We Fund\n\n\nWe fund work in low- and middle-income countries, parts of the world receiving the least amount of human rights funding. In rare cases, we support efforts that directly support people in one of these countries, even if the grantee is not based there.\n\n\n\n\nWhere We Fund\n\n\nWe fund work in low- and middle-income countries, parts of the world receiving the least amount of human rights funding. In rare cases, we support efforts that directly support people in one of these countries, even if the grantee is not based there.\n\n\n\nWe Prioritize\n\nGrassroots organizations rooted in at-risk communities with limited access to funding\n\n\nFrontline organizations working in contexts where the impacts of digital rights violations are most severe\n\n\nOrganizations working at the intersection of digital rights and other human rights issues\n\n\nFeminist organizations working to protect the digital rights of women, LGBTQ+ people, and gender nonconforming people\n\n\n\n\nFeatured Grantees\n\n\n\n\n\n\n\n\n\nAcoso.Online\nBuilding Latin America’s first context-specific resource for victims of online harassment, including dissemination of nonconsensual pornography. From reporting to online platforms, to pursuing legal remedies, to opening community dialogue and defending sexual freedoms, Acoso.Online empowers women, LGBTQ+ people, and their supporters to report, recover, and resist. The tool is localized in 14 countries, with coverage expanding throughout the region.\n\n\n\n\n\n\n\n\n\n\n\nSursiendo\nConducting participatory research to uncover the digital security needs of activists and human rights defenders in Chiapas, Mexico, as well as the broader context of surveillance and other digital threats to human rights and the state.\nSursiendo supports at-risk users in a region with a history of violent repression of social movements and indigenous communities.\n\n\n\n\n\n\n\n\n\n\n\n7amleh\nResearching issues including censorship, surveillance, and profiling of Palestinians on social media, and advocating for better policies to protect Palestinians’ freedom of expression. 7amleh has integrated digital rights into the broader Palestinian rights movement and has led the charge within Palestinian civil society to hold tech companies accountable for the human rights impact of their policies.\n\n\n\n\n\n\n\n\n\n\n\niFreedom Uganda\nTraining sex workers and LGBTQ+ individuals on digital security, and advocating for internet freedoms from a human rights perspective. iFreedom Uganda — a network of 28 member organizations — was founded to ensure that marginalized groups in Uganda are able to freely express themselves without fear of reprisal from state agencies and dangerous hacking groups.\n\n\n\n\n\n\n\n\n\n\n\nFundación Acceso\nProviding systematic physical, technological, legal, and psychosocial assistance to human rights defenders, journalists, environmental and indigenous rights activists, and feminist and LGBTQ+ leaders across Central America, who face violence and criminalization of their activism. Acceso coordinates efforts to document and investigate digital attacks on civil society through its Regional Digital Security Observatory.\n\n\n\n\n\n\n\n\n\nSee full list of grantees\n\n\n\n\nWHAT WE FUND\nThreats to digital rights take many forms, depending on the context and unique challenges specific users or communities face, ranging from censorship and network disruption, to communications surveillance, to lack of protections for personal data, to online harassment, and beyond. Likewise, Access Now grantees are tackling a diverse array of digital rights challenges with an equally diverse set of approaches depending on their context and the opportunities they see to create positive change.\nSome examples of what Access Now Grants supports include:\n\n\nResearch, monitoring, advocacy, and public campaigns to fight internet shutdowns\n\n\nDigital security accompaniment for users at risk, such as women, LGBTQ+ people, human rights defenders, and minority communities\n\n\nEfforts to combat online violence through direct interventions with at-risk users and tech companies\n\n\nDocumentation and advocacy to fight impunity for digital attacks on human rights defenders, journalists, activists, and other at-risk groups\n\n\nProtection of digital civic space during elections and conflict, and in the face of content takedowns, surveillance, troll armies, etc.\n\n\nProjects to integrate digital rights into broader human rights movements to ensure they are effective and protected in the digital space\n\n\nStrategies for advancing individual control of our digital identities that center the experiences of those most detrimentally impacted by violations of privacy rights\n\n\nAnd more!\n\n\n\n\nHOW WE FUND\nOur grantmaking is grounded in international human rights frameworks and takes an intersectional approach that recognizes that threats to digital rights are compounded when they intersect with other human rights abuses or discrimination based on ethnicity, religion, gender, sexuality, class, or other means of marginalization. Our commitment to communities and users most at risk manifests itself in different ways in different contexts and focuses on these intersections.\nAccess Now’s Digital Security Helpline, global team, and Advisory Board are integral to our ability to identify and understand the needs of grassroots activists and organizations.\n\n\n\n\n\n\nTRANSPARENCY\nBe transparent about criteria, internal processes, and decisions\n\n\nACCOUNTABILITY\nEnsure respect for and accountability to our grantees through our processes and communications, while acknowledging and working to flatten the power imbalances between funder and grantee\n\n\nSIMPLICITY\nUse clear and simple procedures and language that can be understood by applicants and the broader community\n\n\n\n\n\n\n\n\nCONTEXT\nAllow local actors and communities to define priorities and set their own goals\n\n\nFLEXIBILITY\nProvide flexibility to respond to emerging opportunities and external needs\n\n\nLIMITED BUREAUCRACY\nRequire limited paperwork and reduce the administrative burden on grantees whenever possible\n\n\n\n\n\n\n\n\nENGAGEMENT\nContinuously self-evaluate and engage within the sector to identify how Access Now can most effectively operate, fund, and contribute\n\n\n\n\n\n\n\n\n\nTypes of Grants\n\n\nPROJECT GRANTS\nFunds projects with explicit end goals, finite timelines, and clear objectives.\nAVERAGE GRANT: $29,000\n\n\nCORE GRANTS\nAwarded to organizations whose activities are closely aligned with the mission of Access Now Grants, and who have a demonstrated body of programmatic work.\n\nFunds can be used for any general operating costs.\nAVERAGE GRANT: $54,000\n\n\nDISCRETIONARY GRANTS\nFunds initiatives responding to emergencies and emerging needs or capturing imminent opportunities.\n\nFunds are small and short term.\n\nMaximum grant size is $10,000.\nAVERAGE GRANT: $7,000\n\n\nDIGITAL SAFE SPACES GRANTS\nFunds human rights organizations that are amplifying the voices of marginalized groups online and want to improve their digital security. The nature of their work and the communities they work on behalf of may make them particularly at risk online or particularly effective online.\nAVERAGE GRANT: $9,000\n\n\n\nApplication Process\n\n\n\nWANT TO KNOW MORE? Email us at [email protected]\n\n\n\nAdvisory Board\nAccess Now has assembled an Advisory Board to provide strategic guidance and oversight of grant recipients. This board is made up of experts in the regions and fields in which Access Now gives grants, and helps us ensure accountability, local relevance, and community engagement in our program. We would like to thank the following individuals for donating their time and energy:\n\nAbir Ghattas (Lebanon)Information Security Technologist, Human Rights Watch\n\nArzu Geybullyeva (Azerbaijan / Turkey)Regional Analyst & Blogger, Global Voices\n\nSaadat Baigazieva (Kyrgyzstan)Feminist activist in fields ranging from gender justice, digital security, and cyberfeminism, to climate and environmental justice, sexual and reproductive rights, and disability rights. Co-lead of the CEECCNA collaborative fund.\n\nHarlo Holmes (U.S.)Digital Security Trainer, Freedom of the Press Foundation\n\nLoreto Bravo (Mexico)Consultant in feminist psychosocial accompaniment in the defense of human rights, technological sovereignty, and digital protection.\n\nBerhan Taye (Ethiopia / Kenya)Tech and Social Justice Researcher and Advisor\n\n\n\nStatement on Grantee Autonomy: While Access Now Grants works closely with Access Now’s other programmatic teams, Access Now Grantees are under no requirement to collaborate with Access Now’s Policy, Advocacy, Tech, or RightsCon teams or to agree with Access Now’s positions and tactics on specific issues. The grants program has the independence to support grantees’ efforts regardless of whether they are aligned with Access Now’s policy positions. We take the aim of diversifying the digital rights movement seriously, and this includes diversity of perspectives, analysis, and tactics.\n\n\n\nCREDITS\nAccess Now Grants is supported by the Swedish International Development Agency, the Dutch Ministry of Foreign Affairs, and other funders. Please contact us at [email protected] if you are interested in supporting our grants program.\n\nACCESS NOW GRANTS\n\nACCESS NOW GRANTS\n\nACCESS NOW GRANTS\n\nACCESS NOW GRANTS\n\nWho We Fund\nWhat We Fund\nHow We Fund\n\nWho We Fund\n\nWhat We Fund\n\nHow We Fund\n\nWe provide flexible and grantee-driven funding to grassroots and frontline organizations fighting for human rights in the digital age. We pursue this work at a time when civil society around the world is working under increasingly difficult circumstances, from targeted censorship, to restrictions on operations, to threats to physical safety. It is also a time when the digital space has become a critical battleground in broader human rights struggles, as well as a place where marginalization, societal discrimination, and violence can be reproduced and even amplified. We aim to strengthen the global digital rights community by expanding, diversifying, and empowering the movement at the grassroots.\n\nWe provide flexible and grantee-driven funding to grassroots and frontline organizations fighting for human rights in the digital age. We pursue this work at a time when civil society around the world is working under increasingly difficult circumstances, from targeted censorship, to restrictions on operations, to threats to physical safety. It is also a time when the digital space has become a critical battleground in broader human rights struggles, as well as a place where marginalization, societal discrimination, and violence can be reproduced and even amplified. We aim to strengthen the global digital rights community by expanding, diversifying, and empowering the movement at the grassroots.\n\nWho we Fund\nOur grantees work with users and communities most at risk of and most detrimentally impacted, online or off, by digital rights violations.\n\n\n\n\n\n\nWhere We Fund\n\n\nWe fund work in low- and middle-income countries, parts of the world receiving the least amount of human rights funding. In rare cases, we support efforts that directly support people in one of these countries, even if the grantee is not based there.\n\n\n\n\nWhere We Fund\n\n\nWe fund work in low- and middle-income countries, parts of the world receiving the least amount of human rights funding. In rare cases, we support efforts that directly support people in one of these countries, even if the grantee is not based there.\n\n\n\nWe Prioritize\n\nGrassroots organizations rooted in at-risk communities with limited access to funding\n\n\nFrontline organizations working in contexts where the impacts of digital rights violations are most severe\n\n\nOrganizations working at the intersection of digital rights and other human rights issues\n\n\nFeminist organizations working to protect the digital rights of women, LGBTQ+ people, and gender nonconforming people\n\nOur grantees work with users and communities most at risk of and most detrimentally impacted, online or off, by digital rights violations.\n\nWhere We Fund\n\n\nWe fund work in low- and middle-income countries, parts of the world receiving the least amount of human rights funding. In rare cases, we support efforts that directly support people in one of these countries, even if the grantee is not based there.\n\nWhere We Fund\n\nWe fund work in low- and middle-income countries, parts of the world receiving the least amount of human rights funding. In rare cases, we support efforts that directly support people in one of these countries, even if the grantee is not based there.\n\nWe fund work in low- and middle-income countries, parts of the world receiving the least amount of human rights funding. In rare cases, we support efforts that directly support people in one of these countries, even if the grantee is not based there.\n\nWhere We Fund\n\n\nWe fund work in low- and middle-income countries, parts of the world receiving the least amount of human rights funding. In rare cases, we support efforts that directly support people in one of these countries, even if the grantee is not based there.\n\nWhere We Fund\n\nWe fund work in low- and middle-income countries, parts of the world receiving the least amount of human rights funding. In rare cases, we support efforts that directly support people in one of these countries, even if the grantee is not based there.\n\nWe fund work in low- and middle-income countries, parts of the world receiving the least amount of human rights funding. In rare cases, we support efforts that directly support people in one of these countries, even if the grantee is not based there.\n\nGrassroots organizations rooted in at-risk communities with limited access to funding\n\nGrassroots organizations rooted in at-risk communities with limited access to funding\n\nFrontline organizations working in contexts where the impacts of digital rights violations are most severe\n\nFrontline organizations working in contexts where the impacts of digital rights violations are most severe\n\nOrganizations working at the intersection of digital rights and other human rights issues\n\nOrganizations working at the intersection of digital rights and other human rights issues\n\nFeminist organizations working to protect the digital rights of women, LGBTQ+ people, and gender nonconforming people\n\nFeminist organizations working to protect the digital rights of women, LGBTQ+ people, and gender nonconforming people\n\nFeatured Grantees\n\n\n\n\n\n\n\n\n\nAcoso.Online\nBuilding Latin America’s first context-specific resource for victims of online harassment, including dissemination of nonconsensual pornography. From reporting to online platforms, to pursuing legal remedies, to opening community dialogue and defending sexual freedoms, Acoso.Online empowers women, LGBTQ+ people, and their supporters to report, recover, and resist. The tool is localized in 14 countries, with coverage expanding throughout the region.\n\n\n\n\n\n\n\n\n\n\n\nSursiendo\nConducting participatory research to uncover the digital security needs of activists and human rights defenders in Chiapas, Mexico, as well as the broader context of surveillance and other digital threats to human rights and the state.\nSursiendo supports at-risk users in a region with a history of violent repression of social movements and indigenous communities.\n\n\n\n\n\n\n\n\n\n\n\n7amleh\nResearching issues including censorship, surveillance, and profiling of Palestinians on social media, and advocating for better policies to protect Palestinians’ freedom of expression. 7amleh has integrated digital rights into the broader Palestinian rights movement and has led the charge within Palestinian civil society to hold tech companies accountable for the human rights impact of their policies.\n\n\n\n\n\n\n\n\n\n\n\niFreedom Uganda\nTraining sex workers and LGBTQ+ individuals on digital security, and advocating for internet freedoms from a human rights perspective. iFreedom Uganda — a network of 28 member organizations — was founded to ensure that marginalized groups in Uganda are able to freely express themselves without fear of reprisal from state agencies and dangerous hacking groups.\n\n\n\n\n\n\n\n\n\n\n\nFundación Acceso\nProviding systematic physical, technological, legal, and psychosocial assistance to human rights defenders, journalists, environmental and indigenous rights activists, and feminist and LGBTQ+ leaders across Central America, who face violence and criminalization of their activism. Acceso coordinates efforts to document and investigate digital attacks on civil society through its Regional Digital Security Observatory.\n\nAcoso.Online\nBuilding Latin America’s first context-specific resource for victims of online harassment, including dissemination of nonconsensual pornography. From reporting to online platforms, to pursuing legal remedies, to opening community dialogue and defending sexual freedoms, Acoso.Online empowers women, LGBTQ+ people, and their supporters to report, recover, and resist. The tool is localized in 14 countries, with coverage expanding throughout the region.\n\n\n\n\n\n\n\n\n\n\n\nSursiendo\nConducting participatory research to uncover the digital security needs of activists and human rights defenders in Chiapas, Mexico, as well as the broader context of surveillance and other digital threats to human rights and the state.\nSursiendo supports at-risk users in a region with a history of violent repression of social movements and indigenous communities.\n\n\n\n\n\n\n\n\n\n\n\n7amleh\nResearching issues including censorship, surveillance, and profiling of Palestinians on social media, and advocating for better policies to protect Palestinians’ freedom of expression. 7amleh has integrated digital rights into the broader Palestinian rights movement and has led the charge within Palestinian civil society to hold tech companies accountable for the human rights impact of their policies.\n\n\n\n\n\n\n\n\n\n\n\niFreedom Uganda\nTraining sex workers and LGBTQ+ individuals on digital security, and advocating for internet freedoms from a human rights perspective. iFreedom Uganda — a network of 28 member organizations — was founded to ensure that marginalized groups in Uganda are able to freely express themselves without fear of reprisal from state agencies and dangerous hacking groups.\n\n\n\n\n\n\n\n\n\n\n\nFundación Acceso\nProviding systematic physical, technological, legal, and psychosocial assistance to human rights defenders, journalists, environmental and indigenous rights activists, and feminist and LGBTQ+ leaders across Central America, who face violence and criminalization of their activism. Acceso coordinates efforts to document and investigate digital attacks on civil society through its Regional Digital Security Observatory.\n\nAcoso.Online\nBuilding Latin America’s first context-specific resource for victims of online harassment, including dissemination of nonconsensual pornography. From reporting to online platforms, to pursuing legal remedies, to opening community dialogue and defending sexual freedoms, Acoso.Online empowers women, LGBTQ+ people, and their supporters to report, recover, and resist. The tool is localized in 14 countries, with coverage expanding throughout the region.\n\n\n\n\n\n\n\n\n\n\n\nSursiendo\nConducting participatory research to uncover the digital security needs of activists and human rights defenders in Chiapas, Mexico, as well as the broader context of surveillance and other digital threats to human rights and the state.\nSursiendo supports at-risk users in a region with a history of violent repression of social movements and indigenous communities.\n\n\n\n\n\n\n\n\n\n\n\n7amleh\nResearching issues including censorship, surveillance, and profiling of Palestinians on social media, and advocating for better policies to protect Palestinians’ freedom of expression. 7amleh has integrated digital rights into the broader Palestinian rights movement and has led the charge within Palestinian civil society to hold tech companies accountable for the human rights impact of their policies.\n\n\n\n\n\n\n\n\n\n\n\niFreedom Uganda\nTraining sex workers and LGBTQ+ individuals on digital security, and advocating for internet freedoms from a human rights perspective. iFreedom Uganda — a network of 28 member organizations — was founded to ensure that marginalized groups in Uganda are able to freely express themselves without fear of reprisal from state agencies and dangerous hacking groups.\n\n\n\n\n\n\n\n\n\n\n\nFundación Acceso\nProviding systematic physical, technological, legal, and psychosocial assistance to human rights defenders, journalists, environmental and indigenous rights activists, and feminist and LGBTQ+ leaders across Central America, who face violence and criminalization of their activism. Acceso coordinates efforts to document and investigate digital attacks on civil society through its Regional Digital Security Observatory.\n\nAcoso.Online\nBuilding Latin America’s first context-specific resource for victims of online harassment, including dissemination of nonconsensual pornography. From reporting to online platforms, to pursuing legal remedies, to opening community dialogue and defending sexual freedoms, Acoso.Online empowers women, LGBTQ+ people, and their supporters to report, recover, and resist. The tool is localized in 14 countries, with coverage expanding throughout the region.\n\nAcoso.Online\nBuilding Latin America’s first context-specific resource for victims of online harassment, including dissemination of nonconsensual pornography. From reporting to online platforms, to pursuing legal remedies, to opening community dialogue and defending sexual freedoms, Acoso.Online empowers women, LGBTQ+ people, and their supporters to report, recover, and resist. The tool is localized in 14 countries, with coverage expanding throughout the region.\n\nAcoso.Online\nBuilding Latin America’s first context-specific resource for victims of online harassment, including dissemination of nonconsensual pornography. From reporting to online platforms, to pursuing legal remedies, to opening community dialogue and defending sexual freedoms, Acoso.Online empowers women, LGBTQ+ people, and their supporters to report, recover, and resist. The tool is localized in 14 countries, with coverage expanding throughout the region.\n\nAcoso.Online\nBuilding Latin America’s first context-specific resource for victims of online harassment, including dissemination of nonconsensual pornography. From reporting to online platforms, to pursuing legal remedies, to opening community dialogue and defending sexual freedoms, Acoso.Online empowers women, LGBTQ+ people, and their supporters to report, recover, and resist. The tool is localized in 14 countries, with coverage expanding throughout the region.\n\nAcoso.Online\nBuilding Latin America’s first context-specific resource for victims of online harassment, including dissemination of nonconsensual pornography. From reporting to online platforms, to pursuing legal remedies, to opening community dialogue and defending sexual freedoms, Acoso.Online empowers women, LGBTQ+ people, and their supporters to report, recover, and resist. The tool is localized in 14 countries, with coverage expanding throughout the region.\n\nBuilding Latin America’s first context-specific resource for victims of online harassment, including dissemination of nonconsensual pornography. From reporting to online platforms, to pursuing legal remedies, to opening community dialogue and defending sexual freedoms, Acoso.Online empowers women, LGBTQ+ people, and their supporters to report, recover, and resist. The tool is localized in 14 countries, with coverage expanding throughout the region.\n\nSursiendo\nConducting participatory research to uncover the digital security needs of activists and human rights defenders in Chiapas, Mexico, as well as the broader context of surveillance and other digital threats to human rights and the state.\nSursiendo supports at-risk users in a region with a history of violent repression of social movements and indigenous communities.\n\nSursiendo\nConducting participatory research to uncover the digital security needs of activists and human rights defenders in Chiapas, Mexico, as well as the broader context of surveillance and other digital threats to human rights and the state.\nSursiendo supports at-risk users in a region with a history of violent repression of social movements and indigenous communities.\n\nSursiendo\nConducting participatory research to uncover the digital security needs of activists and human rights defenders in Chiapas, Mexico, as well as the broader context of surveillance and other digital threats to human rights and the state.\nSursiendo supports at-risk users in a region with a history of violent repression of social movements and indigenous communities.\n\nSursiendo\nConducting participatory research to uncover the digital security needs of activists and human rights defenders in Chiapas, Mexico, as well as the broader context of surveillance and other digital threats to human rights and the state.\nSursiendo supports at-risk users in a region with a history of violent repression of social movements and indigenous communities.\n\nSursiendo\nConducting participatory research to uncover the digital security needs of activists and human rights defenders in Chiapas, Mexico, as well as the broader context of surveillance and other digital threats to human rights and the state.\nSursiendo supports at-risk users in a region with a history of violent repression of social movements and indigenous communities.\n\nConducting participatory research to uncover the digital security needs of activists and human rights defenders in Chiapas, Mexico, as well as the broader context of surveillance and other digital threats to human rights and the state.\n\nSursiendo supports at-risk users in a region with a history of violent repression of social movements and indigenous communities.\n\n7amleh\nResearching issues including censorship, surveillance, and profiling of Palestinians on social media, and advocating for better policies to protect Palestinians’ freedom of expression. 7amleh has integrated digital rights into the broader Palestinian rights movement and has led the charge within Palestinian civil society to hold tech companies accountable for the human rights impact of their policies.\n\n7amleh\nResearching issues including censorship, surveillance, and profiling of Palestinians on social media, and advocating for better policies to protect Palestinians’ freedom of expression. 7amleh has integrated digital rights into the broader Palestinian rights movement and has led the charge within Palestinian civil society to hold tech companies accountable for the human rights impact of their policies.\n\n7amleh\nResearching issues including censorship, surveillance, and profiling of Palestinians on social media, and advocating for better policies to protect Palestinians’ freedom of expression. 7amleh has integrated digital rights into the broader Palestinian rights movement and has led the charge within Palestinian civil society to hold tech companies accountable for the human rights impact of their policies.\n\n7amleh\nResearching issues including censorship, surveillance, and profiling of Palestinians on social media, and advocating for better policies to protect Palestinians’ freedom of expression. 7amleh has integrated digital rights into the broader Palestinian rights movement and has led the charge within Palestinian civil society to hold tech companies accountable for the human rights impact of their policies.\n\n7amleh\nResearching issues including censorship, surveillance, and profiling of Palestinians on social media, and advocating for better policies to protect Palestinians’ freedom of expression. 7amleh has integrated digital rights into the broader Palestinian rights movement and has led the charge within Palestinian civil society to hold tech companies accountable for the human rights impact of their policies.\n\nResearching issues including censorship, surveillance, and profiling of Palestinians on social media, and advocating for better policies to protect Palestinians’ freedom of expression. 7amleh has integrated digital rights into the broader Palestinian rights movement and has led the charge within Palestinian civil society to hold tech companies accountable for the human rights impact of their policies.\n\niFreedom Uganda\nTraining sex workers and LGBTQ+ individuals on digital security, and advocating for internet freedoms from a human rights perspective. iFreedom Uganda — a network of 28 member organizations — was founded to ensure that marginalized groups in Uganda are able to freely express themselves without fear of reprisal from state agencies and dangerous hacking groups.\n\niFreedom Uganda\nTraining sex workers and LGBTQ+ individuals on digital security, and advocating for internet freedoms from a human rights perspective. iFreedom Uganda — a network of 28 member organizations — was founded to ensure that marginalized groups in Uganda are able to freely express themselves without fear of reprisal from state agencies and dangerous hacking groups.\n\niFreedom Uganda\nTraining sex workers and LGBTQ+ individuals on digital security, and advocating for internet freedoms from a human rights perspective. iFreedom Uganda — a network of 28 member organizations — was founded to ensure that marginalized groups in Uganda are able to freely express themselves without fear of reprisal from state agencies and dangerous hacking groups.\n\niFreedom Uganda\nTraining sex workers and LGBTQ+ individuals on digital security, and advocating for internet freedoms from a human rights perspective. iFreedom Uganda — a network of 28 member organizations — was founded to ensure that marginalized groups in Uganda are able to freely express themselves without fear of reprisal from state agencies and dangerous hacking groups.\n\niFreedom Uganda\nTraining sex workers and LGBTQ+ individuals on digital security, and advocating for internet freedoms from a human rights perspective. iFreedom Uganda — a network of 28 member organizations — was founded to ensure that marginalized groups in Uganda are able to freely express themselves without fear of reprisal from state agencies and dangerous hacking groups.\n\nTraining sex workers and LGBTQ+ individuals on digital security, and advocating for internet freedoms from a human rights perspective. iFreedom Uganda — a network of 28 member organizations — was founded to ensure that marginalized groups in Uganda are able to freely express themselves without fear of reprisal from state agencies and dangerous hacking groups.\n\nFundación Acceso\nProviding systematic physical, technological, legal, and psychosocial assistance to human rights defenders, journalists, environmental and indigenous rights activists, and feminist and LGBTQ+ leaders across Central America, who face violence and criminalization of their activism. Acceso coordinates efforts to document and investigate digital attacks on civil society through its Regional Digital Security Observatory.\n\nFundación Acceso\nProviding systematic physical, technological, legal, and psychosocial assistance to human rights defenders, journalists, environmental and indigenous rights activists, and feminist and LGBTQ+ leaders across Central America, who face violence and criminalization of their activism. Acceso coordinates efforts to document and investigate digital attacks on civil society through its Regional Digital Security Observatory.\n\nFundación Acceso\nProviding systematic physical, technological, legal, and psychosocial assistance to human rights defenders, journalists, environmental and indigenous rights activists, and feminist and LGBTQ+ leaders across Central America, who face violence and criminalization of their activism. Acceso coordinates efforts to document and investigate digital attacks on civil society through its Regional Digital Security Observatory.\n\nFundación Acceso\nProviding systematic physical, technological, legal, and psychosocial assistance to human rights defenders, journalists, environmental and indigenous rights activists, and feminist and LGBTQ+ leaders across Central America, who face violence and criminalization of their activism. Acceso coordinates efforts to document and investigate digital attacks on civil society through its Regional Digital Security Observatory.\n\nFundación Acceso\nProviding systematic physical, technological, legal, and psychosocial assistance to human rights defenders, journalists, environmental and indigenous rights activists, and feminist and LGBTQ+ leaders across Central America, who face violence and criminalization of their activism. Acceso coordinates efforts to document and investigate digital attacks on civil society through its Regional Digital Security Observatory.\n\nProviding systematic physical, technological, legal, and psychosocial assistance to human rights defenders, journalists, environmental and indigenous rights activists, and feminist and LGBTQ+ leaders across Central America, who face violence and criminalization of their activism. Acceso coordinates efforts to document and investigate digital attacks on civil society through its Regional Digital Security Observatory.\n\nSee full list of grantees\n\nSee full list of grantees\n\nSee full list of grantees\n\nSee full list of grantees\n\nWHAT WE FUND\nThreats to digital rights take many forms, depending on the context and unique challenges specific users or communities face, ranging from censorship and network disruption, to communications surveillance, to lack of protections for personal data, to online harassment, and beyond. Likewise, Access Now grantees are tackling a diverse array of digital rights challenges with an equally diverse set of approaches depending on their context and the opportunities they see to create positive change.\nSome examples of what Access Now Grants supports include:\n\n\nResearch, monitoring, advocacy, and public campaigns to fight internet shutdowns\n\n\nDigital security accompaniment for users at risk, such as women, LGBTQ+ people, human rights defenders, and minority communities\n\n\nEfforts to combat online violence through direct interventions with at-risk users and tech companies\n\n\nDocumentation and advocacy to fight impunity for digital attacks on human rights defenders, journalists, activists, and other at-risk groups\n\n\nProtection of digital civic space during elections and conflict, and in the face of content takedowns, surveillance, troll armies, etc.\n\n\nProjects to integrate digital rights into broader human rights movements to ensure they are effective and protected in the digital space\n\n\nStrategies for advancing individual control of our digital identities that center the experiences of those most detrimentally impacted by violations of privacy rights\n\n\nAnd more!\n\nThreats to digital rights take many forms, depending on the context and unique challenges specific users or communities face, ranging from censorship and network disruption, to communications surveillance, to lack of protections for personal data, to online harassment, and beyond. Likewise, Access Now grantees are tackling a diverse array of digital rights challenges with an equally diverse set of approaches depending on their context and the opportunities they see to create positive change.\n\nSome examples of what Access Now Grants supports include:\n\nResearch, monitoring, advocacy, and public campaigns to fight internet shutdowns\n\n\nDigital security accompaniment for users at risk, such as women, LGBTQ+ people, human rights defenders, and minority communities\n\n\nEfforts to combat online violence through direct interventions with at-risk users and tech companies\n\n\nDocumentation and advocacy to fight impunity for digital attacks on human rights defenders, journalists, activists, and other at-risk groups\n\n\nProtection of digital civic space during elections and conflict, and in the face of content takedowns, surveillance, troll armies, etc.\n\n\nProjects to integrate digital rights into broader human rights movements to ensure they are effective and protected in the digital space\n\n\nStrategies for advancing individual control of our digital identities that center the experiences of those most detrimentally impacted by violations of privacy rights\n\n\nAnd more!\n\nResearch, monitoring, advocacy, and public campaigns to fight internet shutdowns\n\nResearch, monitoring, advocacy, and public campaigns to fight internet shutdowns\n\nDigital security accompaniment for users at risk, such as women, LGBTQ+ people, human rights defenders, and minority communities\n\nDigital security accompaniment for users at risk, such as women, LGBTQ+ people, human rights defenders, and minority communities\n\nEfforts to combat online violence through direct interventions with at-risk users and tech companies\n\nEfforts to combat online violence through direct interventions with at-risk users and tech companies\n\nDocumentation and advocacy to fight impunity for digital attacks on human rights defenders, journalists, activists, and other at-risk groups\n\nDocumentation and advocacy to fight impunity for digital attacks on human rights defenders, journalists, activists, and other at-risk groups\n\nProtection of digital civic space during elections and conflict, and in the face of content takedowns, surveillance, troll armies, etc.\n\nProtection of digital civic space during elections and conflict, and in the face of content takedowns, surveillance, troll armies, etc.\n\nProjects to integrate digital rights into broader human rights movements to ensure they are effective and protected in the digital space\n\nProjects to integrate digital rights into broader human rights movements to ensure they are effective and protected in the digital space\n\nStrategies for advancing individual control of our digital identities that center the experiences of those most detrimentally impacted by violations of privacy rights\n\nStrategies for advancing individual control of our digital identities that center the experiences of those most detrimentally impacted by violations of privacy rights\n\nAnd more!\n\nAnd more!\n\nHOW WE FUND\nOur grantmaking is grounded in international human rights frameworks and takes an intersectional approach that recognizes that threats to digital rights are compounded when they intersect with other human rights abuses or discrimination based on ethnicity, religion, gender, sexuality, class, or other means of marginalization. Our commitment to communities and users most at risk manifests itself in different ways in different contexts and focuses on these intersections.\nAccess Now’s Digital Security Helpline, global team, and Advisory Board are integral to our ability to identify and understand the needs of grassroots activists and organizations.\n\n\n\n\n\n\nTRANSPARENCY\nBe transparent about criteria, internal processes, and decisions\n\n\nACCOUNTABILITY\nEnsure respect for and accountability to our grantees through our processes and communications, while acknowledging and working to flatten the power imbalances between funder and grantee\n\n\nSIMPLICITY\nUse clear and simple procedures and language that can be understood by applicants and the broader community\n\n\n\n\n\n\n\n\nCONTEXT\nAllow local actors and communities to define priorities and set their own goals\n\n\nFLEXIBILITY\nProvide flexibility to respond to emerging opportunities and external needs\n\n\nLIMITED BUREAUCRACY\nRequire limited paperwork and reduce the administrative burden on grantees whenever possible\n\n\n\n\n\n\n\n\nENGAGEMENT\nContinuously self-evaluate and engage within the sector to identify how Access Now can most effectively operate, fund, and contribute\n\n\n\n\n\n\n\n\n\nTypes of Grants\n\n\nPROJECT GRANTS\nFunds projects with explicit end goals, finite timelines, and clear objectives.\nAVERAGE GRANT: $29,000\n\n\nCORE GRANTS\nAwarded to organizations whose activities are closely aligned with the mission of Access Now Grants, and who have a demonstrated body of programmatic work.\n\nFunds can be used for any general operating costs.\nAVERAGE GRANT: $54,000\n\n\nDISCRETIONARY GRANTS\nFunds initiatives responding to emergencies and emerging needs or capturing imminent opportunities.\n\nFunds are small and short term.\n\nMaximum grant size is $10,000.\nAVERAGE GRANT: $7,000\n\n\nDIGITAL SAFE SPACES GRANTS\nFunds human rights organizations that are amplifying the voices of marginalized groups online and want to improve their digital security. The nature of their work and the communities they work on behalf of may make them particularly at risk online or particularly effective online.\nAVERAGE GRANT: $9,000\n\n\n\nApplication Process\n\nOur grantmaking is grounded in international human rights frameworks and takes an intersectional approach that recognizes that threats to digital rights are compounded when they intersect with other human rights abuses or discrimination based on ethnicity, religion, gender, sexuality, class, or other means of marginalization. Our commitment to communities and users most at risk manifests itself in different ways in different contexts and focuses on these intersections.\n\nAccess Now’s Digital Security Helpline, global team, and Advisory Board are integral to our ability to identify and understand the needs of grassroots activists and organizations.\n\nTRANSPARENCY\nBe transparent about criteria, internal processes, and decisions\n\n\nACCOUNTABILITY\nEnsure respect for and accountability to our grantees through our processes and communications, while acknowledging and working to flatten the power imbalances between funder and grantee\n\n\nSIMPLICITY\nUse clear and simple procedures and language that can be understood by applicants and the broader community\n\n\n\n\n\n\n\n\nCONTEXT\nAllow local actors and communities to define priorities and set their own goals\n\n\nFLEXIBILITY\nProvide flexibility to respond to emerging opportunities and external needs\n\n\nLIMITED BUREAUCRACY\nRequire limited paperwork and reduce the administrative burden on grantees whenever possible\n\n\n\n\n\n\n\n\nENGAGEMENT\nContinuously self-evaluate and engage within the sector to identify how Access Now can most effectively operate, fund, and contribute\n\nTRANSPARENCY\nBe transparent about criteria, internal processes, and decisions\n\n\nACCOUNTABILITY\nEnsure respect for and accountability to our grantees through our processes and communications, while acknowledging and working to flatten the power imbalances between funder and grantee\n\n\nSIMPLICITY\nUse clear and simple procedures and language that can be understood by applicants and the broader community\n\n\n\n\n\n\n\n\nCONTEXT\nAllow local actors and communities to define priorities and set their own goals\n\n\nFLEXIBILITY\nProvide flexibility to respond to emerging opportunities and external needs\n\n\nLIMITED BUREAUCRACY\nRequire limited paperwork and reduce the administrative burden on grantees whenever possible\n\n\n\n\n\n\n\n\nENGAGEMENT\nContinuously self-evaluate and engage within the sector to identify how Access Now can most effectively operate, fund, and contribute\n\nTRANSPARENCY\nBe transparent about criteria, internal processes, and decisions\n\n\nACCOUNTABILITY\nEnsure respect for and accountability to our grantees through our processes and communications, while acknowledging and working to flatten the power imbalances between funder and grantee\n\n\nSIMPLICITY\nUse clear and simple procedures and language that can be understood by applicants and the broader community\n\nTRANSPARENCY\nBe transparent about criteria, internal processes, and decisions\n\n\nACCOUNTABILITY\nEnsure respect for and accountability to our grantees through our processes and communications, while acknowledging and working to flatten the power imbalances between funder and grantee\n\n\nSIMPLICITY\nUse clear and simple procedures and language that can be understood by applicants and the broader community\n\nTRANSPARENCY\nBe transparent about criteria, internal processes, and decisions\n\n\nACCOUNTABILITY\nEnsure respect for and accountability to our grantees through our processes and communications, while acknowledging and working to flatten the power imbalances between funder and grantee\n\n\nSIMPLICITY\nUse clear and simple procedures and language that can be understood by applicants and the broader community\n\nTRANSPARENCY\nBe transparent about criteria, internal processes, and decisions\n\n\nACCOUNTABILITY\nEnsure respect for and accountability to our grantees through our processes and communications, while acknowledging and working to flatten the power imbalances between funder and grantee\n\n\nSIMPLICITY\nUse clear and simple procedures and language that can be understood by applicants and the broader community\n\nTRANSPARENCY\nBe transparent about criteria, internal processes, and decisions\n\nTRANSPARENCY\n\nBe transparent about criteria, internal processes, and decisions\n\nACCOUNTABILITY\nEnsure respect for and accountability to our grantees through our processes and communications, while acknowledging and working to flatten the power imbalances between funder and grantee\n\nACCOUNTABILITY\n\nEnsure respect for and accountability to our grantees through our processes and communications, while acknowledging and working to flatten the power imbalances between funder and grantee\n\nSIMPLICITY\nUse clear and simple procedures and language that can be understood by applicants and the broader community\n\nSIMPLICITY\n\nUse clear and simple procedures and language that can be understood by applicants and the broader community\n\nCONTEXT\nAllow local actors and communities to define priorities and set their own goals\n\n\nFLEXIBILITY\nProvide flexibility to respond to emerging opportunities and external needs\n\n\nLIMITED BUREAUCRACY\nRequire limited paperwork and reduce the administrative burden on grantees whenever possible\n\nCONTEXT\nAllow local actors and communities to define priorities and set their own goals\n\n\nFLEXIBILITY\nProvide flexibility to respond to emerging opportunities and external needs\n\n\nLIMITED BUREAUCRACY\nRequire limited paperwork and reduce the administrative burden on grantees whenever possible\n\nCONTEXT\nAllow local actors and communities to define priorities and set their own goals\n\n\nFLEXIBILITY\nProvide flexibility to respond to emerging opportunities and external needs\n\n\nLIMITED BUREAUCRACY\nRequire limited paperwork and reduce the administrative burden on grantees whenever possible\n\nCONTEXT\nAllow local actors and communities to define priorities and set their own goals\n\n\nFLEXIBILITY\nProvide flexibility to respond to emerging opportunities and external needs\n\n\nLIMITED BUREAUCRACY\nRequire limited paperwork and reduce the administrative burden on grantees whenever possible\n\nCONTEXT\nAllow local actors and communities to define priorities and set their own goals\n\nCONTEXT\n\nAllow local actors and communities to define priorities and set their own goals\n\nFLEXIBILITY\nProvide flexibility to respond to emerging opportunities and external needs\n\nFLEXIBILITY\n\nProvide flexibility to respond to emerging opportunities and external needs\n\nLIMITED BUREAUCRACY\nRequire limited paperwork and reduce the administrative burden on grantees whenever possible\n\nLIMITED BUREAUCRACY\n\nRequire limited paperwork and reduce the administrative burden on grantees whenever possible\n\nENGAGEMENT\nContinuously self-evaluate and engage within the sector to identify how Access Now can most effectively operate, fund, and contribute\n\nENGAGEMENT\nContinuously self-evaluate and engage within the sector to identify how Access Now can most effectively operate, fund, and contribute\n\nENGAGEMENT\nContinuously self-evaluate and engage within the sector to identify how Access Now can most effectively operate, fund, and contribute\n\nENGAGEMENT\nContinuously self-evaluate and engage within the sector to identify how Access Now can most effectively operate, fund, and contribute\n\nENGAGEMENT\nContinuously self-evaluate and engage within the sector to identify how Access Now can most effectively operate, fund, and contribute\n\nENGAGEMENT\n\nContinuously self-evaluate and engage within the sector to identify how Access Now can most effectively operate, fund, and contribute\n\nPROJECT GRANTS\nFunds projects with explicit end goals, finite timelines, and clear objectives.\nAVERAGE GRANT: $29,000\n\n\nCORE GRANTS\nAwarded to organizations whose activities are closely aligned with the mission of Access Now Grants, and who have a demonstrated body of programmatic work.\n\nFunds can be used for any general operating costs.\nAVERAGE GRANT: $54,000\n\n\nDISCRETIONARY GRANTS\nFunds initiatives responding to emergencies and emerging needs or capturing imminent opportunities.\n\nFunds are small and short term.\n\nMaximum grant size is $10,000.\nAVERAGE GRANT: $7,000\n\n\nDIGITAL SAFE SPACES GRANTS\nFunds human rights organizations that are amplifying the voices of marginalized groups online and want to improve their digital security. The nature of their work and the communities they work on behalf of may make them particularly at risk online or particularly effective online.\nAVERAGE GRANT: $9,000\n\nPROJECT GRANTS\nFunds projects with explicit end goals, finite timelines, and clear objectives.\nAVERAGE GRANT: $29,000\n\nPROJECT GRANTS\n\nFunds projects with explicit end goals, finite timelines, and clear objectives.\n\nAVERAGE GRANT: $29,000\n\nCORE GRANTS\nAwarded to organizations whose activities are closely aligned with the mission of Access Now Grants, and who have a demonstrated body of programmatic work.\n\nFunds can be used for any general operating costs.\nAVERAGE GRANT: $54,000\n\nCORE GRANTS\n\nAwarded to organizations whose activities are closely aligned with the mission of Access Now Grants, and who have a demonstrated body of programmatic work.\n\nFunds can be used for any general operating costs.\n\nAVERAGE GRANT: $54,000\n\nDISCRETIONARY GRANTS\nFunds initiatives responding to emergencies and emerging needs or capturing imminent opportunities.\n\nFunds are small and short term.\n\nMaximum grant size is $10,000.\nAVERAGE GRANT: $7,000\n\nDISCRETIONARY GRANTS\n\nFunds initiatives responding to emergencies and emerging needs or capturing imminent opportunities.\n\nFunds are small and short term.\n\nMaximum grant size is $10,000.\n\nAVERAGE GRANT: $7,000\n\nDIGITAL SAFE SPACES GRANTS\nFunds human rights organizations that are amplifying the voices of marginalized groups online and want to improve their digital security. The nature of their work and the communities they work on behalf of may make them particularly at risk online or particularly effective online.\nAVERAGE GRANT: $9,000\n\nDIGITAL SAFE SPACES GRANTS\n\nFunds human rights organizations that are amplifying the voices of marginalized groups online and want to improve their digital security. The nature of their work and the communities they work on behalf of may make them particularly at risk online or particularly effective online.\n\nAVERAGE GRANT: $9,000\n\nWANT TO KNOW MORE? Email us at [email protected]\n\nWANT TO KNOW MORE? Email us at [email protected]\n\nWANT TO KNOW MORE? Email us at [email protected]\n\nAdvisory Board\nAccess Now has assembled an Advisory Board to provide strategic guidance and oversight of grant recipients. This board is made up of experts in the regions and fields in which Access Now gives grants, and helps us ensure accountability, local relevance, and community engagement in our program. We would like to thank the following individuals for donating their time and energy:\n\nAbir Ghattas (Lebanon)Information Security Technologist, Human Rights Watch\n\nArzu Geybullyeva (Azerbaijan / Turkey)Regional Analyst & Blogger, Global Voices\n\nSaadat Baigazieva (Kyrgyzstan)Feminist activist in fields ranging from gender justice, digital security, and cyberfeminism, to climate and environmental justice, sexual and reproductive rights, and disability rights. Co-lead of the CEECCNA collaborative fund.\n\nHarlo Holmes (U.S.)Digital Security Trainer, Freedom of the Press Foundation\n\nLoreto Bravo (Mexico)Consultant in feminist psychosocial accompaniment in the defense of human rights, technological sovereignty, and digital protection.\n\nBerhan Taye (Ethiopia / Kenya)Tech and Social Justice Researcher and Advisor\n\nAccess Now has assembled an Advisory Board to provide strategic guidance and oversight of grant recipients. This board is made up of experts in the regions and fields in which Access Now gives grants, and helps us ensure accountability, local relevance, and community engagement in our program. We would like to thank the following individuals for donating their time and energy:\n\nAbir Ghattas (Lebanon)Information Security Technologist, Human Rights Watch\n\nArzu Geybullyeva (Azerbaijan / Turkey)Regional Analyst & Blogger, Global Voices\n\nSaadat Baigazieva (Kyrgyzstan)Feminist activist in fields ranging from gender justice, digital security, and cyberfeminism, to climate and environmental justice, sexual and reproductive rights, and disability rights. Co-lead of the CEECCNA collaborative fund.\n\nHarlo Holmes (U.S.)Digital Security Trainer, Freedom of the Press Foundation\n\nLoreto Bravo (Mexico)Consultant in feminist psychosocial accompaniment in the defense of human rights, technological sovereignty, and digital protection.\n\nBerhan Taye (Ethiopia / Kenya)Tech and Social Justice Researcher and Advisor\n\nStatement on Grantee Autonomy: While Access Now Grants works closely with Access Now’s other programmatic teams, Access Now Grantees are under no requirement to collaborate with Access Now’s Policy, Advocacy, Tech, or RightsCon teams or to agree with Access Now’s positions and tactics on specific issues. The grants program has the independence to support grantees’ efforts regardless of whether they are aligned with Access Now’s policy positions. We take the aim of diversifying the digital rights movement seriously, and this includes diversity of perspectives, analysis, and tactics.\n\nStatement on Grantee Autonomy: While Access Now Grants works closely with Access Now’s other programmatic teams, Access Now Grantees are under no requirement to collaborate with Access Now’s Policy, Advocacy, Tech, or RightsCon teams or to agree with Access Now’s positions and tactics on specific issues. The grants program has the independence to support grantees’ efforts regardless of whether they are aligned with Access Now’s policy positions. We take the aim of diversifying the digital rights movement seriously, and this includes diversity of perspectives, analysis, and tactics.\n\nCREDITS\nAccess Now Grants is supported by the Swedish International Development Agency, the Dutch Ministry of Foreign Affairs, and other funders. Please contact us at [email protected] if you are interested in supporting our grants program.\n\nAccess Now Grants is supported by the Swedish International Development Agency, the Dutch Ministry of Foreign Affairs, and other funders. Please contact us at [email protected] if you are interested in supporting our grants program.\n\nHelp keep the internet open and secure.\nSubscribe to our action alerts and weekly newsletter\n\"*\" indicates required fields\n\nThis field is hidden when viewing the form\n\nSubscribe to Access Express\nThis field is hidden when viewing the form\n\nSubscribe to Action Alerts\nName\n\n\nFirst\n\n\n\nLast\n\nEmail*\n\nCountryCountryAfghanistanÅland IslandsAlbaniaAlgeriaAmerican SamoaAndorraAngolaAnguillaAntigua and BarbudaArgentinaArmeniaArubaAustraliaAustriaAzerbaijanBahamasBahrainBangladeshBarbadosBelarusBelgiumBelizeBeninBermudaBhutanBoliviaBonaire, Sint Eustatius and SabaBosnia and HerzegovinaBotswanaBrazilBritish Indian Ocean TerritoryBritish Virgin IslandsBruneiBulgariaBurkina FasoBurundiCambodiaCameroonCanadaCape VerdeCayman IslandsCentral African RepublicChadChileChinaChristmas IslandColombiaComorosCook IslandsCosta RicaCôte d'IvoireCroatiaCubaCuraçaoCyprusCzech RepublicDemocratic Republic of the CongoDenmarkDjiboutiDominicaDominican RepublicEast TimorEcuadorEgyptEl SalvadorEquatorial GuineaEritreaEstoniaEswatiniEthiopiaFalkland IslandsFaroe IslandsFijiFinlandFranceFrench GuianaFrench PolynesiaFrench Southern TerritoriesGabonGeorgiaGermanyGhanaGibraltarGreeceGreenlandGrenadaGuadeloupeGuamGuatemalaGuernseyGuineaGuinea-BissauGuyanaHaitiHondurasHong KongHungaryIcelandIndiaIndonesiaIranIraqIrelandIsraelItalyJamaicaJapanJordanKazakhstanKenyaKiribatiKosovoKuwaitKyrgyzstanLaosLatviaLebanonLesothoLiberiaLibyaLiechtensteinLithuaniaLuxembourgMacauMadagascarMalawiMalaysiaMaldivesMaliMaltaMarshall IslandsMartiniqueMauritaniaMauritiusMayotteMexicoMicronesiaMoldovaMonacoMongoliaMontenegroMontserratMoroccoMozambiqueMyanmarNamibiaNauruNepalNetherlands AntillesNew CaledoniaNew ZealandNicaraguaNigerNigeriaNiueNorfolk IslandNorth KoreaNorth MacedoniaNorthern Mariana IslandsNorwayOmanPakistanPalauPalestinePanamaPapua New GuineaParaguayPeruPhilippinesPitcairn IslandPolandPortugalPuerto RicoQatarRepublic of the CongoReunionRomaniaRussiaRwandaSaint BarthélemySaint Kitts and NevisSaint LuciaSaint Vincent and the GrenadinesSamoaSan MarinoSão Tomé and PríncipeSaudi ArabiaSenegalSerbiaSeychellesSierra LeoneSingaporeSlovakiaSloveniaSolomon IslandsSomaliaSomalilandSouth AfricaSouth KoreaSouth SudanSpainSri LankaSt. HelenaSt. Pierre and MiquelonSudanSurinameSwedenSwitzerlandSyriaTaiwanTajikistanTanzaniaThailandThe GambiaThe NetherlandsTogoTokelauTongaTrinidad and TobagoTunisiaTurkeyTurkmenistanTurks and Caicos IslandsTuvaluUgandaUkraineUnited Arab EmiratesUnited KingdomUnited StatesUruguayUzbekistanVanuatuVatican CityVenezuelaVietnamVirgin Islands (U.S.)Wallis and Futuna IslandsWestern SaharaYemenZambiaZimbabwePostal CodeCommentsThis field is for validation purposes and should be left unchanged.\n \n\n\n\n\n\n\n\n\n\n\n\n\n\n\n\nYour info is secure with us\n\nHelp keep the internet open and secure.\nSubscribe to our action alerts and weekly newsletter\n\"*\" indicates required fields\n\nThis field is hidden when viewing the form\n\nSubscribe to Access Express\nThis field is hidden when viewing the form\n\nSubscribe to Action Alerts\nName\n\n\nFirst\n\n\n\nLast\n\nEmail*\n\nCountryCountryAfghanistanÅland IslandsAlbaniaAlgeriaAmerican SamoaAndorraAngolaAnguillaAntigua and BarbudaArgentinaArmeniaArubaAustraliaAustriaAzerbaijanBahamasBahrainBangladeshBarbadosBelarusBelgiumBelizeBeninBermudaBhutanBoliviaBonaire, Sint Eustatius and SabaBosnia and HerzegovinaBotswanaBrazilBritish Indian Ocean TerritoryBritish Virgin IslandsBruneiBulgariaBurkina FasoBurundiCambodiaCameroonCanadaCape VerdeCayman IslandsCentral African RepublicChadChileChinaChristmas IslandColombiaComorosCook IslandsCosta RicaCôte d'IvoireCroatiaCubaCuraçaoCyprusCzech RepublicDemocratic Republic of the CongoDenmarkDjiboutiDominicaDominican RepublicEast TimorEcuadorEgyptEl SalvadorEquatorial GuineaEritreaEstoniaEswatiniEthiopiaFalkland IslandsFaroe IslandsFijiFinlandFranceFrench GuianaFrench PolynesiaFrench Southern TerritoriesGabonGeorgiaGermanyGhanaGibraltarGreeceGreenlandGrenadaGuadeloupeGuamGuatemalaGuernseyGuineaGuinea-BissauGuyanaHaitiHondurasHong KongHungaryIcelandIndiaIndonesiaIranIraqIrelandIsraelItalyJamaicaJapanJordanKazakhstanKenyaKiribatiKosovoKuwaitKyrgyzstanLaosLatviaLebanonLesothoLiberiaLibyaLiechtensteinLithuaniaLuxembourgMacauMadagascarMalawiMalaysiaMaldivesMaliMaltaMarshall IslandsMartiniqueMauritaniaMauritiusMayotteMexicoMicronesiaMoldovaMonacoMongoliaMontenegroMontserratMoroccoMozambiqueMyanmarNamibiaNauruNepalNetherlands AntillesNew CaledoniaNew ZealandNicaraguaNigerNigeriaNiueNorfolk IslandNorth KoreaNorth MacedoniaNorthern Mariana IslandsNorwayOmanPakistanPalauPalestinePanamaPapua New GuineaParaguayPeruPhilippinesPitcairn IslandPolandPortugalPuerto RicoQatarRepublic of the CongoReunionRomaniaRussiaRwandaSaint BarthélemySaint Kitts and NevisSaint LuciaSaint Vincent and the GrenadinesSamoaSan MarinoSão Tomé and PríncipeSaudi ArabiaSenegalSerbiaSeychellesSierra LeoneSingaporeSlovakiaSloveniaSolomon IslandsSomaliaSomalilandSouth AfricaSouth KoreaSouth SudanSpainSri LankaSt. HelenaSt. Pierre and MiquelonSudanSurinameSwedenSwitzerlandSyriaTaiwanTajikistanTanzaniaThailandThe GambiaThe NetherlandsTogoTokelauTongaTrinidad and TobagoTunisiaTurkeyTurkmenistanTurks and Caicos IslandsTuvaluUgandaUkraineUnited Arab EmiratesUnited KingdomUnited StatesUruguayUzbekistanVanuatuVatican CityVenezuelaVietnamVirgin Islands (U.S.)Wallis and Futuna IslandsWestern SaharaYemenZambiaZimbabwePostal CodeCommentsThis field is for validation purposes and should be left unchanged.\n \n\n\n\n\n\n\n\n\n\n\n\n\n\n\n\nYour info is secure with us\n\nHelp keep the internet open and secure.\nSubscribe to our action alerts and weekly newsletter\n\"*\" indicates required fields\n\nThis field is hidden when viewing the form\n\nSubscribe to Access Express\nThis field is hidden when viewing the form\n\nSubscribe to Action Alerts\nName\n\n\nFirst\n\n\n\nLast\n\nEmail*\n\nCountryCountryAfghanistanÅland IslandsAlbaniaAlgeriaAmerican SamoaAndorraAngolaAnguillaAntigua and BarbudaArgentinaArmeniaArubaAustraliaAustriaAzerbaijanBahamasBahrainBangladeshBarbadosBelarusBelgiumBelizeBeninBermudaBhutanBoliviaBonaire, Sint Eustatius and SabaBosnia and HerzegovinaBotswanaBrazilBritish Indian Ocean TerritoryBritish Virgin IslandsBruneiBulgariaBurkina FasoBurundiCambodiaCameroonCanadaCape VerdeCayman IslandsCentral African RepublicChadChileChinaChristmas IslandColombiaComorosCook IslandsCosta RicaCôte d'IvoireCroatiaCubaCuraçaoCyprusCzech RepublicDemocratic Republic of the CongoDenmarkDjiboutiDominicaDominican RepublicEast TimorEcuadorEgyptEl SalvadorEquatorial GuineaEritreaEstoniaEswatiniEthiopiaFalkland IslandsFaroe IslandsFijiFinlandFranceFrench GuianaFrench PolynesiaFrench Southern TerritoriesGabonGeorgiaGermanyGhanaGibraltarGreeceGreenlandGrenadaGuadeloupeGuamGuatemalaGuernseyGuineaGuinea-BissauGuyanaHaitiHondurasHong KongHungaryIcelandIndiaIndonesiaIranIraqIrelandIsraelItalyJamaicaJapanJordanKazakhstanKenyaKiribatiKosovoKuwaitKyrgyzstanLaosLatviaLebanonLesothoLiberiaLibyaLiechtensteinLithuaniaLuxembourgMacauMadagascarMalawiMalaysiaMaldivesMaliMaltaMarshall IslandsMartiniqueMauritaniaMauritiusMayotteMexicoMicronesiaMoldovaMonacoMongoliaMontenegroMontserratMoroccoMozambiqueMyanmarNamibiaNauruNepalNetherlands AntillesNew CaledoniaNew ZealandNicaraguaNigerNigeriaNiueNorfolk IslandNorth KoreaNorth MacedoniaNorthern Mariana IslandsNorwayOmanPakistanPalauPalestinePanamaPapua New GuineaParaguayPeruPhilippinesPitcairn IslandPolandPortugalPuerto RicoQatarRepublic of the CongoReunionRomaniaRussiaRwandaSaint BarthélemySaint Kitts and NevisSaint LuciaSaint Vincent and the GrenadinesSamoaSan MarinoSão Tomé and PríncipeSaudi ArabiaSenegalSerbiaSeychellesSierra LeoneSingaporeSlovakiaSloveniaSolomon IslandsSomaliaSomalilandSouth AfricaSouth KoreaSouth SudanSpainSri LankaSt. HelenaSt. Pierre and MiquelonSudanSurinameSwedenSwitzerlandSyriaTaiwanTajikistanTanzaniaThailandThe GambiaThe NetherlandsTogoTokelauTongaTrinidad and TobagoTunisiaTurkeyTurkmenistanTurks and Caicos IslandsTuvaluUgandaUkraineUnited Arab EmiratesUnited KingdomUnited StatesUruguayUzbekistanVanuatuVatican CityVenezuelaVietnamVirgin Islands (U.S.)Wallis and Futuna IslandsWestern SaharaYemenZambiaZimbabwePostal CodeCommentsThis field is for validation purposes and should be left unchanged.\n\nHelp keep the internet open and secure.\nSubscribe to our action alerts and weekly newsletter\n\"*\" indicates required fields\n\nSubscribe to our action alerts and weekly newsletter\n\n\"*\" indicates required fields\n\nThis field is hidden when viewing the form\n\nSubscribe to Access Express\nThis field is hidden when viewing the form\n\nSubscribe to Action Alerts\nName\n\n\nFirst\n\n\n\nLast\n\nEmail*\n\nCountryCountryAfghanistanÅland IslandsAlbaniaAlgeriaAmerican SamoaAndorraAngolaAnguillaAntigua and BarbudaArgentinaArmeniaArubaAustraliaAustriaAzerbaijanBahamasBahrainBangladeshBarbadosBelarusBelgiumBelizeBeninBermudaBhutanBoliviaBonaire, Sint Eustatius and SabaBosnia and HerzegovinaBotswanaBrazilBritish Indian Ocean TerritoryBritish Virgin IslandsBruneiBulgariaBurkina FasoBurundiCambodiaCameroonCanadaCape VerdeCayman IslandsCentral African RepublicChadChileChinaChristmas IslandColombiaComorosCook IslandsCosta RicaCôte d'IvoireCroatiaCubaCuraçaoCyprusCzech RepublicDemocratic Republic of the CongoDenmarkDjiboutiDominicaDominican RepublicEast TimorEcuadorEgyptEl SalvadorEquatorial GuineaEritreaEstoniaEswatiniEthiopiaFalkland IslandsFaroe IslandsFijiFinlandFranceFrench GuianaFrench PolynesiaFrench Southern TerritoriesGabonGeorgiaGermanyGhanaGibraltarGreeceGreenlandGrenadaGuadeloupeGuamGuatemalaGuernseyGuineaGuinea-BissauGuyanaHaitiHondurasHong KongHungaryIcelandIndiaIndonesiaIranIraqIrelandIsraelItalyJamaicaJapanJordanKazakhstanKenyaKiribatiKosovoKuwaitKyrgyzstanLaosLatviaLebanonLesothoLiberiaLibyaLiechtensteinLithuaniaLuxembourgMacauMadagascarMalawiMalaysiaMaldivesMaliMaltaMarshall IslandsMartiniqueMauritaniaMauritiusMayotteMexicoMicronesiaMoldovaMonacoMongoliaMontenegroMontserratMoroccoMozambiqueMyanmarNamibiaNauruNepalNetherlands AntillesNew CaledoniaNew ZealandNicaraguaNigerNigeriaNiueNorfolk IslandNorth KoreaNorth MacedoniaNorthern Mariana IslandsNorwayOmanPakistanPalauPalestinePanamaPapua New GuineaParaguayPeruPhilippinesPitcairn IslandPolandPortugalPuerto RicoQatarRepublic of the CongoReunionRomaniaRussiaRwandaSaint BarthélemySaint Kitts and NevisSaint LuciaSaint Vincent and the GrenadinesSamoaSan MarinoSão Tomé and PríncipeSaudi ArabiaSenegalSerbiaSeychellesSierra LeoneSingaporeSlovakiaSloveniaSolomon IslandsSomaliaSomalilandSouth AfricaSouth KoreaSouth SudanSpainSri LankaSt. HelenaSt. Pierre and MiquelonSudanSurinameSwedenSwitzerlandSyriaTaiwanTajikistanTanzaniaThailandThe GambiaThe NetherlandsTogoTokelauTongaTrinidad and TobagoTunisiaTurkeyTurkmenistanTurks and Caicos IslandsTuvaluUgandaUkraineUnited Arab EmiratesUnited KingdomUnited StatesUruguayUzbekistanVanuatuVatican CityVenezuelaVietnamVirgin Islands (U.S.)Wallis and Futuna IslandsWestern SaharaYemenZambiaZimbabwePostal CodeCommentsThis field is for validation purposes and should be left unchanged.\n\nThis field is hidden when viewing the form\n\nSubscribe to Access Express\nThis field is hidden when viewing the form\n\nSubscribe to Action Alerts\nName\n\n\nFirst\n\n\n\nLast\n\nEmail*\n\nCountryCountryAfghanistanÅland IslandsAlbaniaAlgeriaAmerican SamoaAndorraAngolaAnguillaAntigua and BarbudaArgentinaArmeniaArubaAustraliaAustriaAzerbaijanBahamasBahrainBangladeshBarbadosBelarusBelgiumBelizeBeninBermudaBhutanBoliviaBonaire, Sint Eustatius and SabaBosnia and HerzegovinaBotswanaBrazilBritish Indian Ocean TerritoryBritish Virgin IslandsBruneiBulgariaBurkina FasoBurundiCambodiaCameroonCanadaCape VerdeCayman IslandsCentral African RepublicChadChileChinaChristmas IslandColombiaComorosCook IslandsCosta RicaCôte d'IvoireCroatiaCubaCuraçaoCyprusCzech RepublicDemocratic Republic of the CongoDenmarkDjiboutiDominicaDominican RepublicEast TimorEcuadorEgyptEl SalvadorEquatorial GuineaEritreaEstoniaEswatiniEthiopiaFalkland IslandsFaroe IslandsFijiFinlandFranceFrench GuianaFrench PolynesiaFrench Southern TerritoriesGabonGeorgiaGermanyGhanaGibraltarGreeceGreenlandGrenadaGuadeloupeGuamGuatemalaGuernseyGuineaGuinea-BissauGuyanaHaitiHondurasHong KongHungaryIcelandIndiaIndonesiaIranIraqIrelandIsraelItalyJamaicaJapanJordanKazakhstanKenyaKiribatiKosovoKuwaitKyrgyzstanLaosLatviaLebanonLesothoLiberiaLibyaLiechtensteinLithuaniaLuxembourgMacauMadagascarMalawiMalaysiaMaldivesMaliMaltaMarshall IslandsMartiniqueMauritaniaMauritiusMayotteMexicoMicronesiaMoldovaMonacoMongoliaMontenegroMontserratMoroccoMozambiqueMyanmarNamibiaNauruNepalNetherlands AntillesNew CaledoniaNew ZealandNicaraguaNigerNigeriaNiueNorfolk IslandNorth KoreaNorth MacedoniaNorthern Mariana IslandsNorwayOmanPakistanPalauPalestinePanamaPapua New GuineaParaguayPeruPhilippinesPitcairn IslandPolandPortugalPuerto RicoQatarRepublic of the CongoReunionRomaniaRussiaRwandaSaint BarthélemySaint Kitts and NevisSaint LuciaSaint Vincent and the GrenadinesSamoaSan MarinoSão Tomé and PríncipeSaudi ArabiaSenegalSerbiaSeychellesSierra LeoneSingaporeSlovakiaSloveniaSolomon IslandsSomaliaSomalilandSouth AfricaSouth KoreaSouth SudanSpainSri LankaSt. HelenaSt. Pierre and MiquelonSudanSurinameSwedenSwitzerlandSyriaTaiwanTajikistanTanzaniaThailandThe GambiaThe NetherlandsTogoTokelauTongaTrinidad and TobagoTunisiaTurkeyTurkmenistanTurks and Caicos IslandsTuvaluUgandaUkraineUnited Arab EmiratesUnited KingdomUnited StatesUruguayUzbekistanVanuatuVatican CityVenezuelaVietnamVirgin Islands (U.S.)Wallis and Futuna IslandsWestern SaharaYemenZambiaZimbabwePostal CodeCommentsThis field is for validation purposes and should be left unchanged.\n\nThis field is hidden when viewing the form\n\nSubscribe to Access Express\n\nSubscribe to Access Express\n\nSubscribe to Access Express\n\nThis field is hidden when viewing the form\n\nSubscribe to Action Alerts\n\nSubscribe to Action Alerts\n\nSubscribe to Action Alerts\n\nFirst\n\n\n\nLast\n\nEmail*\n\nCountryCountryAfghanistanÅland IslandsAlbaniaAlgeriaAmerican SamoaAndorraAngolaAnguillaAntigua and BarbudaArgentinaArmeniaArubaAustraliaAustriaAzerbaijanBahamasBahrainBangladeshBarbadosBelarusBelgiumBelizeBeninBermudaBhutanBoliviaBonaire, Sint Eustatius and SabaBosnia and HerzegovinaBotswanaBrazilBritish Indian Ocean TerritoryBritish Virgin IslandsBruneiBulgariaBurkina FasoBurundiCambodiaCameroonCanadaCape VerdeCayman IslandsCentral African RepublicChadChileChinaChristmas IslandColombiaComorosCook IslandsCosta RicaCôte d'IvoireCroatiaCubaCuraçaoCyprusCzech RepublicDemocratic Republic of the CongoDenmarkDjiboutiDominicaDominican RepublicEast TimorEcuadorEgyptEl SalvadorEquatorial GuineaEritreaEstoniaEswatiniEthiopiaFalkland IslandsFaroe IslandsFijiFinlandFranceFrench GuianaFrench PolynesiaFrench Southern TerritoriesGabonGeorgiaGermanyGhanaGibraltarGreeceGreenlandGrenadaGuadeloupeGuamGuatemalaGuernseyGuineaGuinea-BissauGuyanaHaitiHondurasHong KongHungaryIcelandIndiaIndonesiaIranIraqIrelandIsraelItalyJamaicaJapanJordanKazakhstanKenyaKiribatiKosovoKuwaitKyrgyzstanLaosLatviaLebanonLesothoLiberiaLibyaLiechtensteinLithuaniaLuxembourgMacauMadagascarMalawiMalaysiaMaldivesMaliMaltaMarshall IslandsMartiniqueMauritaniaMauritiusMayotteMexicoMicronesiaMoldovaMonacoMongoliaMontenegroMontserratMoroccoMozambiqueMyanmarNamibiaNauruNepalNetherlands AntillesNew CaledoniaNew ZealandNicaraguaNigerNigeriaNiueNorfolk IslandNorth KoreaNorth MacedoniaNorthern Mariana IslandsNorwayOmanPakistanPalauPalestinePanamaPapua New GuineaParaguayPeruPhilippinesPitcairn IslandPolandPortugalPuerto RicoQatarRepublic of the CongoReunionRomaniaRussiaRwandaSaint BarthélemySaint Kitts and NevisSaint LuciaSaint Vincent and the GrenadinesSamoaSan MarinoSão Tomé and PríncipeSaudi ArabiaSenegalSerbiaSeychellesSierra LeoneSingaporeSlovakiaSloveniaSolomon IslandsSomaliaSomalilandSouth AfricaSouth KoreaSouth SudanSpainSri LankaSt. HelenaSt. Pierre and MiquelonSudanSurinameSwedenSwitzerlandSyriaTaiwanTajikistanTanzaniaThailandThe GambiaThe NetherlandsTogoTokelauTongaTrinidad and TobagoTunisiaTurkeyTurkmenistanTurks and Caicos IslandsTuvaluUgandaUkraineUnited Arab EmiratesUnited KingdomUnited StatesUruguayUzbekistanVanuatuVatican CityVenezuelaVietnamVirgin Islands (U.S.)Wallis and Futuna IslandsWestern SaharaYemenZambiaZimbabwe\n\nCountryAfghanistanÅland IslandsAlbaniaAlgeriaAmerican SamoaAndorraAngolaAnguillaAntigua and BarbudaArgentinaArmeniaArubaAustraliaAustriaAzerbaijanBahamasBahrainBangladeshBarbadosBelarusBelgiumBelizeBeninBermudaBhutanBoliviaBonaire, Sint Eustatius and SabaBosnia and HerzegovinaBotswanaBrazilBritish Indian Ocean TerritoryBritish Virgin IslandsBruneiBulgariaBurkina FasoBurundiCambodiaCameroonCanadaCape VerdeCayman IslandsCentral African RepublicChadChileChinaChristmas IslandColombiaComorosCook IslandsCosta RicaCôte d'IvoireCroatiaCubaCuraçaoCyprusCzech RepublicDemocratic Republic of the CongoDenmarkDjiboutiDominicaDominican RepublicEast TimorEcuadorEgyptEl SalvadorEquatorial GuineaEritreaEstoniaEswatiniEthiopiaFalkland IslandsFaroe IslandsFijiFinlandFranceFrench GuianaFrench PolynesiaFrench Southern TerritoriesGabonGeorgiaGermanyGhanaGibraltarGreeceGreenlandGrenadaGuadeloupeGuamGuatemalaGuernseyGuineaGuinea-BissauGuyanaHaitiHondurasHong KongHungaryIcelandIndiaIndonesiaIranIraqIrelandIsraelItalyJamaicaJapanJordanKazakhstanKenyaKiribatiKosovoKuwaitKyrgyzstanLaosLatviaLebanonLesothoLiberiaLibyaLiechtensteinLithuaniaLuxembourgMacauMadagascarMalawiMalaysiaMaldivesMaliMaltaMarshall IslandsMartiniqueMauritaniaMauritiusMayotteMexicoMicronesiaMoldovaMonacoMongoliaMontenegroMontserratMoroccoMozambiqueMyanmarNamibiaNauruNepalNetherlands AntillesNew CaledoniaNew ZealandNicaraguaNigerNigeriaNiueNorfolk IslandNorth KoreaNorth MacedoniaNorthern Mariana IslandsNorwayOmanPakistanPalauPalestinePanamaPapua New GuineaParaguayPeruPhilippinesPitcairn IslandPolandPortugalPuerto RicoQatarRepublic of the CongoReunionRomaniaRussiaRwandaSaint BarthélemySaint Kitts and NevisSaint LuciaSaint Vincent and the GrenadinesSamoaSan MarinoSão Tomé and PríncipeSaudi ArabiaSenegalSerbiaSeychellesSierra LeoneSingaporeSlovakiaSloveniaSolomon IslandsSomaliaSomalilandSouth AfricaSouth KoreaSouth SudanSpainSri LankaSt. HelenaSt. Pierre and MiquelonSudanSurinameSwedenSwitzerlandSyriaTaiwanTajikistanTanzaniaThailandThe GambiaThe NetherlandsTogoTokelauTongaTrinidad and TobagoTunisiaTurkeyTurkmenistanTurks and Caicos IslandsTuvaluUgandaUkraineUnited Arab EmiratesUnited KingdomUnited StatesUruguayUzbekistanVanuatuVatican CityVenezuelaVietnamVirgin Islands (U.S.)Wallis and Futuna IslandsWestern SaharaYemenZambiaZimbabwe\n\nPostal Code\n\nCommentsThis field is for validation purposes and should be left unchanged.\n\nThis field is for validation purposes and should be left unchanged.\n\nYour info is secure with us",
  "date": "",
  "source_type": "other",
  "extracted_at": "2025-04-07T13:46:15.290732",
  "metadata": {
    "description": "ACCESS NOW GRANTS Who We Fund What We Fund How We Fund We provide flexible and grantee-driven funding to grassroots and frontline organizations fighting",
    "og:type": "article",
    "og:site_name": "Access Now"
  },
  "relevance_score": 0.5416666666666667,
  "summary": "Back to content\n\nACCESS NOW GRANTS\n\n\n\n\n\n\nWho We Fund\nWhat We Fund\nHow We Fund\n\n\nWe provide flexible and grantee-driven funding to grassroots and frontline organizations fighting for human rights in the digital age. We Prioritize\n\nGrassroots organizations rooted in at-risk communities with limited access to funding\n\n\nFrontline organizations working in contexts where the impacts of digital rights violations are most severe\n\n\nOrganizations working at the intersection of digital rights and other human rights issues\n\n\nFeminist organizations working to protect the digital rights of women, LGBTQ+ people, and gender nonconforming people\n\n\n\n\nFeatured Grantees\n\n\n\n\n\n\n\n\n\nAcoso.Online\nBuilding Latin America’s first context-specific resource for victims of online harassment, including dissemination of nonconsensual pornography. Sursiendo\nConducting participatory research to uncover the digital security needs of activists and human rights defenders in Chiapas, Mexico, as well as the broader context of surveillance and other digital threats to human rights and the state. 7amleh has integrated digital rights into the broader Palestinian rights movement and has led the charge within Palestinian civil society to hold tech companies accountable for the human rights impact of their policies. See full list of grantees\n\n\n\n\nWHAT WE FUND\nThreats to digital rights take many forms, depending on the context and unique challenges specific users or communities face, ranging from censorship and network disruption, to communications surveillance, to lack of protections for personal data, to online harassment, and beyond. Some examples of what Access Now Grants supports include:\n\n\nResearch, monitoring, advocacy, and public campaigns to fight internet shutdowns\n\n\nDigital security accompaniment for users at risk, such as women, LGBTQ+ people, human rights defenders, and minority communities\n\n\nEfforts to combat online violence through direct interventions with at-risk users and tech companies\n\n\nDocumentation and advocacy to fight impunity for digital attacks on human rights defenders, journalists, activists, and other at-risk groups\n\n\nProtection of digital civic space during elections and conflict, and in the face of content takedowns, surveillance, troll armies, etc. Projects to integrate digital rights into broader human rights movements to ensure they are effective and protected in the digital space\n\n\nStrategies for advancing individual control of our digital identities that center the experiences of those most detrimentally impacted by violations of privacy rights\n\n\nAnd more! HOW WE FUND\nOur grantmaking is grounded in international human rights frameworks and takes an intersectional approach that recognizes that threats to digital rights are compounded when they intersect with other human rights abuses or discrimination based on ethnicity, religion, gender, sexuality, class, or other means of marginalization. TRANSPARENCY\nBe transparent about criteria, internal processes, and decisions\n\n\nACCOUNTABILITY\nEnsure respect for and accountability to our grantees through our processes and communications, while acknowledging and working to flatten the power imbalances between funder and grantee\n\n\nSIMPLICITY\nUse clear and simple procedures and language that can be understood by applicants and the broader community\n\n\n\n\n\n\n\n\nCONTEXT\nAllow local actors and communities to define priorities and set their own goals\n\n\nFLEXIBILITY\nProvide flexibility to respond to emerging opportunities and external needs\n\n\nLIMITED BUREAUCRACY\nRequire limited paperwork and reduce the administrative burden on grantees whenever possible\n\n\n\n\n\n\n\n\nENGAGEMENT\nContinuously self-evaluate and engage within the sector to identify how Access Now can most effectively operate, fund, and contribute\n\n\n\n\n\n\n\n\n\nTypes of Grants\n\n\nPROJECT GRANTS\nFunds projects with explicit end goals, finite timelines, and clear objectives. AVERAGE GRANT: $7,000\n\n\nDIGITAL SAFE SPACES GRANTS\nFunds human rights organizations that are amplifying the voices of marginalized groups online and want to improve their digital security. We would like to thank the following individuals for donating their time and energy:\n\nAbir Ghattas (Lebanon)Information Security Technologist, Human Rights Watch\n\nArzu Geybullyeva (Azerbaijan / Turkey)Regional Analyst & Blogger, Global Voices\n\nSaadat Baigazieva (Kyrgyzstan)Feminist activist in fields ranging from gender justice, digital security, and cyberfeminism, to climate and environmental justice, sexual and reproductive rights, and disability rights. Your info is secure with us\n\nACCESS NOW GRANTS\n\n\n\n\n\n\nWho We Fund\nWhat We Fund\nHow We Fund\n\n\nWe provide flexible and grantee-driven funding to grassroots and frontline organizations fighting for human rights in the digital age. We Prioritize\n\nGrassroots organizations rooted in at-risk communities with limited access to funding\n\n\nFrontline organizations working in contexts where the impacts of digital rights violations are most severe\n\n\nOrganizations working at the intersection of digital rights and other human rights issues\n\n\nFeminist organizations working to protect the digital rights of women, LGBTQ+ people, and gender nonconforming people\n\n\n\n\nFeatured Grantees\n\n\n\n\n\n\n\n\n\nAcoso.Online\nBuilding Latin America’s first context-specific resource for victims of online harassment, including dissemination of nonconsensual pornography. Sursiendo\nConducting participatory research to uncover the digital security needs of activists and human rights defenders in Chiapas, Mexico, as well as the broader context of surveillance and other digital threats to human rights and the state. 7amleh has integrated digital rights into the broader Palestinian rights movement and has led the charge within Palestinian civil society to hold tech companies accountable for the human rights impact of their policies. See full list of grantees\n\n\n\n\nWHAT WE FUND\nThreats to digital rights take many forms, depending on the context and unique challenges specific users or communities face, ranging from censorship and network disruption, to communications surveillance, to lack of protections for personal data, to online harassment, and beyond. Some examples of what Access Now Grants supports include:\n\n\nResearch, monitoring, advocacy, and public campaigns to fight internet shutdowns\n\n\nDigital security accompaniment for users at risk, such as women, LGBTQ+ people, human rights defenders, and minority communities\n\n\nEfforts to combat online violence through direct interventions with at-risk users and tech companies\n\n\nDocumentation and advocacy to fight impunity for digital attacks on human rights defenders, journalists, activists, and other at-risk groups\n\n\nProtection of digital civic space during elections and conflict, and in the face of content takedowns, surveillance, troll armies, etc. Projects to integrate digital rights into broader human rights movements to ensure they are effective and protected in the digital space\n\n\nStrategies for advancing individual control of our digital identities that center the experiences of those most detrimentally impacted by violations of privacy rights\n\n\nAnd more! HOW WE FUND\nOur grantmaking is grounded in international human rights frameworks and takes an intersectional approach that recognizes that threats to digital rights are compounded when they intersect with other human rights abuses or discrimination based on ethnicity, religion, gender, sexuality, class, or other means of marginalization. TRANSPARENCY\nBe transparent about criteria, internal processes, and decisions\n\n\nACCOUNTABILITY\nEnsure respect for and accountability to our grantees through our processes and communications, while acknowledging and working to flatten the power imbalances between funder and grantee\n\n\nSIMPLICITY\nUse clear and simple procedures and language that can be understood by applicants and the broader community\n\n\n\n\n\n\n\n\nCONTEXT\nAllow local actors and communities to define priorities and set their own goals\n\n\nFLEXIBILITY\nProvide flexibility to respond to emerging opportunities and external needs\n\n\nLIMITED BUREAUCRACY\nRequire limited paperwork and reduce the administrative burden on grantees whenever possible\n\n\n\n\n\n\n\n\nENGAGEMENT\nContinuously self-evaluate and engage within the sector to identify how Access Now can most effectively operate, fund, and contribute\n\n\n\n\n\n\n\n\n\nTypes of Grants\n\n\nPROJECT GRANTS\nFunds projects with explicit end goals, finite timelines, and clear objectives. AVERAGE GRANT: $7,000\n\n\nDIGITAL SAFE SPACES GRANTS\nFunds human rights organizations that are amplifying the voices of marginalized groups online and want to improve their digital security. We would like to thank the following individuals for donating their time and energy:\n\nAbir Ghattas (Lebanon)Information Security Technologist, Human Rights Watch\n\nArzu Geybullyeva (Azerbaijan / Turkey)Regional Analyst & Blogger, Global Voices\n\nSaadat Baigazieva (Kyrgyzstan)Feminist activist in fields ranging from gender justice, digital security, and cyberfeminism, to climate and environmental justice, sexual and reproductive rights, and disability rights. ACCESS NOW GRANTS\n\n\n\n\n\n\nWho We Fund\nWhat We Fund\nHow We Fund\n\n\nWe provide flexible and grantee-driven funding to grassroots and frontline organizations fighting for human rights in the digital age. We Prioritize\n\nGrassroots organizations rooted in at-risk communities with limited access to funding\n\n\nFrontline organizations working in contexts where the impacts of digital rights violations are most severe\n\n\nOrganizations working at the intersection of digital rights and other human rights issues\n\n\nFeminist organizations working to protect the digital rights of women, LGBTQ+ people, and gender nonconforming people\n\n\n\n\nFeatured Grantees\n\n\n\n\n\n\n\n\n\nAcoso.Online\nBuilding Latin America’s first context-specific resource for victims of online harassment, including dissemination of nonconsensual pornography. Sursiendo\nConducting participatory research to uncover the digital security needs of activists and human rights defenders in Chiapas, Mexico, as well as the broader context of surveillance and other digital threats to human rights and the state. 7amleh has integrated digital rights into the broader Palestinian rights movement and has led the charge within Palestinian civil society to hold tech companies accountable for the human rights impact of their policies. Some examples of what Access Now Grants supports include:\n\n\nResearch, monitoring, advocacy, and public campaigns to fight internet shutdowns\n\n\nDigital security accompaniment for users at risk, such as women, LGBTQ+ people, human rights defenders, and minority communities\n\n\nEfforts to combat online violence through direct interventions with at-risk users and tech companies\n\n\nDocumentation and advocacy to fight impunity for digital attacks on human rights defenders, journalists, activists, and other at-risk groups\n\n\nProtection of digital civic space during elections and conflict, and in the face of content takedowns, surveillance, troll armies, etc. Projects to integrate digital rights into broader human rights movements to ensure they are effective and protected in the digital space\n\n\nStrategies for advancing individual control of our digital identities that center the experiences of those most detrimentally impacted by violations of privacy rights\n\n\nAnd more! HOW WE FUND\nOur grantmaking is grounded in international human rights frameworks and takes an intersectional approach that recognizes that threats to digital rights are compounded when they intersect with other human rights abuses or discrimination based on ethnicity, religion, gender, sexuality, class, or other means of marginalization. TRANSPARENCY\nBe transparent about criteria, internal processes, and decisions\n\n\nACCOUNTABILITY\nEnsure respect for and accountability to our grantees through our processes and communications, while acknowledging and working to flatten the power imbalances between funder and grantee\n\n\nSIMPLICITY\nUse clear and simple procedures and language that can be understood by applicants and the broader community\n\n\n\n\n\n\n\n\nCONTEXT\nAllow local actors and communities to define priorities and set their own goals\n\n\nFLEXIBILITY\nProvide flexibility to respond to emerging opportunities and external needs\n\n\nLIMITED BUREAUCRACY\nRequire limited paperwork and reduce the administrative burden on grantees whenever possible\n\n\n\n\n\n\n\n\nENGAGEMENT\nContinuously self-evaluate and engage within the sector to identify how Access Now can most effectively operate, fund, and contribute\n\n\n\n\n\n\n\n\n\nTypes of Grants\n\n\nPROJECT GRANTS\nFunds projects with explicit end goals, finite timelines, and clear objectives. AVERAGE GRANT: $7,000\n\n\nDIGITAL SAFE SPACES GRANTS\nFunds human rights organizations that are amplifying the voices of marginalized groups online and want to improve their digital security. We would like to thank the following individuals for donating their time and energy:\n\nAbir Ghattas (Lebanon)Information Security Technologist, Human Rights Watch\n\nArzu Geybullyeva (Azerbaijan / Turkey)Regional Analyst & Blogger, Global Voices\n\nSaadat Baigazieva (Kyrgyzstan)Feminist activist in fields ranging from gender justice, digital security, and cyberfeminism, to climate and environmental justice, sexual and reproductive rights, and disability rights. ACCESS NOW GRANTS\n\n\n\n\n\n\nWho We Fund\nWhat We Fund\nHow We Fund\n\n\nWe provide flexible and grantee-driven funding to grassroots and frontline organizations fighting for human rights in the digital age. We Prioritize\n\nGrassroots organizations rooted in at-risk communities with limited access to funding\n\n\nFrontline organizations working in contexts where the impacts of digital rights violations are most severe\n\n\nOrganizations working at the intersection of digital rights and other human rights issues\n\n\nFeminist organizations working to protect the digital rights of women, LGBTQ+ people, and gender nonconforming people\n\n\n\n\nFeatured Grantees\n\n\n\n\n\n\n\n\n\nAcoso.Online\nBuilding Latin America’s first context-specific resource for victims of online harassment, including dissemination of nonconsensual pornography. Sursiendo\nConducting participatory research to uncover the digital security needs of activists and human rights defenders in Chiapas, Mexico, as well as the broader context of surveillance and other digital threats to human rights and the state. 7amleh has integrated digital rights into the broader Palestinian rights movement and has led the charge within Palestinian civil society to hold tech companies accountable for the human rights impact of their policies. Some examples of what Access Now Grants supports include:\n\n\nResearch, monitoring, advocacy, and public campaigns to fight internet shutdowns\n\n\nDigital security accompaniment for users at risk, such as women, LGBTQ+ people, human rights defenders, and minority communities\n\n\nEfforts to combat online violence through direct interventions with at-risk users and tech companies\n\n\nDocumentation and advocacy to fight impunity for digital attacks on human rights defenders, journalists, activists, and other at-risk groups\n\n\nProtection of digital civic space during elections and conflict, and in the face of content takedowns, surveillance, troll armies, etc. Projects to integrate digital rights into broader human rights movements to ensure they are effective and protected in the digital space\n\n\nStrategies for advancing individual control of our digital identities that center the experiences of those most detrimentally impacted by violations of privacy rights\n\n\nAnd more! HOW WE FUND\nOur grantmaking is grounded in international human rights frameworks and takes an intersectional approach that recognizes that threats to digital rights are compounded when they intersect with other human rights abuses or discrimination based on ethnicity, religion, gender, sexuality, class, or other means of marginalization. TRANSPARENCY\nBe transparent about criteria, internal processes, and decisions\n\n\nACCOUNTABILITY\nEnsure respect for and accountability to our grantees through our processes and communications, while acknowledging and working to flatten the power imbalances between funder and grantee\n\n\nSIMPLICITY\nUse clear and simple procedures and language that can be understood by applicants and the broader community\n\n\n\n\n\n\n\n\nCONTEXT\nAllow local actors and communities to define priorities and set their own goals\n\n\nFLEXIBILITY\nProvide flexibility to respond to emerging opportunities and external needs\n\n\nLIMITED BUREAUCRACY\nRequire limited paperwork and reduce the administrative burden on grantees whenever possible\n\n\n\n\n\n\n\n\nENGAGEMENT\nContinuously self-evaluate and engage within the sector to identify how Access Now can most effectively operate, fund, and contribute\n\n\n\n\n\n\n\n\n\nTypes of Grants\n\n\nPROJECT GRANTS\nFunds projects with explicit end goals, finite timelines, and clear objectives. AVERAGE GRANT: $7,000\n\n\nDIGITAL SAFE SPACES GRANTS\nFunds human rights organizations that are amplifying the voices of marginalized groups online and want to improve their digital security. We would like to thank the following individuals for donating their time and energy:\n\nAbir Ghattas (Lebanon)Information Security Technologist, Human Rights Watch\n\nArzu Geybullyeva (Azerbaijan / Turkey)Regional Analyst & Blogger, Global Voices\n\nSaadat Baigazieva (Kyrgyzstan)Feminist activist in fields ranging from gender justice, digital security, and cyberfeminism, to climate and environmental justice, sexual and reproductive rights, and disability rights. ACCESS NOW GRANTS\n\n\n\n\n\n\nWho We Fund\nWhat We Fund\nHow We Fund\n\n\nWe provide flexible and grantee-driven funding to grassroots and frontline organizations fighting for human rights in the digital age. We Prioritize\n\nGrassroots organizations rooted in at-risk communities with limited access to funding\n\n\nFrontline organizations working in contexts where the impacts of digital rights violations are most severe\n\n\nOrganizations working at the intersection of digital rights and other human rights issues\n\n\nFeminist organizations working to protect the digital rights of women, LGBTQ+ people, and gender nonconforming people\n\n\n\n\nFeatured Grantees\n\n\n\n\n\n\n\n\n\nAcoso.Online\nBuilding Latin America’s first context-specific resource for victims of online harassment, including dissemination of nonconsensual pornography. Sursiendo\nConducting participatory research to uncover the digital security needs of activists and human rights defenders in Chiapas, Mexico, as well as the broader context of surveillance and other digital threats to human rights and the state. 7amleh has integrated digital rights into the broader Palestinian rights movement and has led the charge within Palestinian civil society to hold tech companies accountable for the human rights impact of their policies. Some examples of what Access Now Grants supports include:\n\n\nResearch, monitoring, advocacy, and public campaigns to fight internet shutdowns\n\n\nDigital security accompaniment for users at risk, such as women, LGBTQ+ people, human rights defenders, and minority communities\n\n\nEfforts to combat online violence through direct interventions with at-risk users and tech companies\n\n\nDocumentation and advocacy to fight impunity for digital attacks on human rights defenders, journalists, activists, and other at-risk groups\n\n\nProtection of digital civic space during elections and conflict, and in the face of content takedowns, surveillance, troll armies, etc. Projects to integrate digital rights into broader human rights movements to ensure they are effective and protected in the digital space\n\n\nStrategies for advancing individual control of our digital identities that center the experiences of those most detrimentally impacted by violations of privacy rights\n\n\nAnd more! HOW WE FUND\nOur grantmaking is grounded in international human rights frameworks and takes an intersectional approach that recognizes that threats to digital rights are compounded when they intersect with other human rights abuses or discrimination based on ethnicity, religion, gender, sexuality, class, or other means of marginalization. TRANSPARENCY\nBe transparent about criteria, internal processes, and decisions\n\n\nACCOUNTABILITY\nEnsure respect for and accountability to our grantees through our processes and communications, while acknowledging and working to flatten the power imbalances between funder and grantee\n\n\nSIMPLICITY\nUse clear and simple procedures and language that can be understood by applicants and the broader community\n\n\n\n\n\n\n\n\nCONTEXT\nAllow local actors and communities to define priorities and set their own goals\n\n\nFLEXIBILITY\nProvide flexibility to respond to emerging opportunities and external needs\n\n\nLIMITED BUREAUCRACY\nRequire limited paperwork and reduce the administrative burden on grantees whenever possible\n\n\n\n\n\n\n\n\nENGAGEMENT\nContinuously self-evaluate and engage within the sector to identify how Access Now can most effectively operate, fund, and contribute\n\n\n\n\n\n\n\n\n\nTypes of Grants\n\n\nPROJECT GRANTS\nFunds projects with explicit end goals, finite timelines, and clear objectives. AVERAGE GRANT: $7,000\n\n\nDIGITAL SAFE SPACES GRANTS\nFunds human rights organizations that are amplifying the voices of marginalized groups online and want to improve their digital security. We would like to thank the following individuals for donating their time and energy:\n\nAbir Ghattas (Lebanon)Information Security Technologist, Human Rights Watch\n\nArzu Geybullyeva (Azerbaijan / Turkey)Regional Analyst & Blogger, Global Voices\n\nSaadat Baigazieva (Kyrgyzstan)Feminist activist in fields ranging from gender justice, digital security, and cyberfeminism, to climate and environmental justice, sexual and reproductive rights, and disability rights. ACCESS NOW GRANTS\n\n\n\n\n\n\nWho We Fund\nWhat We Fund\nHow We Fund\n\n\nWe provide flexible and grantee-driven funding to grassroots and frontline organizations fighting for human rights in the digital age. We Prioritize\n\nGrassroots organizations rooted in at-risk communities with limited access to funding\n\n\nFrontline organizations working in contexts where the impacts of digital rights violations are most severe\n\n\nOrganizations working at the intersection of digital rights and other human rights issues\n\n\nFeminist organizations working to protect the digital rights of women, LGBTQ+ people, and gender nonconforming people\n\n\n\n\nFeatured Grantees\n\n\n\n\n\n\n\n\n\nAcoso.Online\nBuilding Latin America’s first context-specific resource for victims of online harassment, including dissemination of nonconsensual pornography. Sursiendo\nConducting participatory research to uncover the digital security needs of activists and human rights defenders in Chiapas, Mexico, as well as the broader context of surveillance and other digital threats to human rights and the state. 7amleh has integrated digital rights into the broader Palestinian rights movement and has led the charge within Palestinian civil society to hold tech companies accountable for the human rights impact of their policies. Some examples of what Access Now Grants supports include:\n\n\nResearch, monitoring, advocacy, and public campaigns to fight internet shutdowns\n\n\nDigital security accompaniment for users at risk, such as women, LGBTQ+ people, human rights defenders, and minority communities\n\n\nEfforts to combat online violence through direct interventions with at-risk users and tech companies\n\n\nDocumentation and advocacy to fight impunity for digital attacks on human rights defenders, journalists, activists, and other at-risk groups\n\n\nProtection of digital civic space during elections and conflict, and in the face of content takedowns, surveillance, troll armies, etc. Projects to integrate digital rights into broader human rights movements to ensure they are effective and protected in the digital space\n\n\nStrategies for advancing individual control of our digital identities that center the experiences of those most detrimentally impacted by violations of privacy rights\n\n\nAnd more! HOW WE FUND\nOur grantmaking is grounded in international human rights frameworks and takes an intersectional approach that recognizes that threats to digital rights are compounded when they intersect with other human rights abuses or discrimination based on ethnicity, religion, gender, sexuality, class, or other means of marginalization. TRANSPARENCY\nBe transparent about criteria, internal processes, and decisions\n\n\nACCOUNTABILITY\nEnsure respect for and accountability to our grantees through our processes and communications, while acknowledging and working to flatten the power imbalances between funder and grantee\n\n\nSIMPLICITY\nUse clear and simple procedures and language that can be understood by applicants and the broader community\n\n\n\n\n\n\n\n\nCONTEXT\nAllow local actors and communities to define priorities and set their own goals\n\n\nFLEXIBILITY\nProvide flexibility to respond to emerging opportunities and external needs\n\n\nLIMITED BUREAUCRACY\nRequire limited paperwork and reduce the administrative burden on grantees whenever possible\n\n\n\n\n\n\n\n\nENGAGEMENT\nContinuously self-evaluate and engage within the sector to identify how Access Now can most effectively operate, fund, and contribute\n\n\n\n\n\n\n\n\n\nTypes of Grants\n\n\nPROJECT GRANTS\nFunds projects with explicit end goals, finite timelines, and clear objectives. AVERAGE GRANT: $7,000\n\n\nDIGITAL SAFE SPACES GRANTS\nFunds human rights organizations that are amplifying the voices of marginalized groups online and want to improve their digital security. We would like to thank the following individuals for donating their time and energy:\n\nAbir Ghattas (Lebanon)Information Security Technologist, Human Rights Watch\n\nArzu Geybullyeva (Azerbaijan / Turkey)Regional Analyst & Blogger, Global Voices\n\nSaadat Baigazieva (Kyrgyzstan)Feminist activist in fields ranging from gender justice, digital security, and cyberfeminism, to climate and environmental justice, sexual and reproductive rights, and disability rights. ACCESS NOW GRANTS\n\nACCESS NOW GRANTS\n\nACCESS NOW GRANTS\n\nACCESS NOW GRANTS\n\nWho We Fund\nWhat We Fund\nHow We Fund\n\nWho We Fund\n\nWhat We Fund\n\nHow We Fund\n\nWe provide flexible and grantee-driven funding to grassroots and frontline organizations fighting for human rights in the digital age. We Prioritize\n\nGrassroots organizations rooted in at-risk communities with limited access to funding\n\n\nFrontline organizations working in contexts where the impacts of digital rights violations are most severe\n\n\nOrganizations working at the intersection of digital rights and other human rights issues\n\n\nFeminist organizations working to protect the digital rights of women, LGBTQ+ people, and gender nonconforming people\n\nOur grantees work with users and communities most at risk of and most detrimentally impacted, online or off, by digital rights violations. Grassroots organizations rooted in at-risk communities with limited access to funding\n\nGrassroots organizations rooted in at-risk communities with limited access to funding\n\nFrontline organizations working in contexts where the impacts of digital rights violations are most severe\n\nFrontline organizations working in contexts where the impacts of digital rights violations are most severe\n\nOrganizations working at the intersection of digital rights and other human rights issues\n\nOrganizations working at the intersection of digital rights and other human rights issues\n\nFeminist organizations working to protect the digital rights of women, LGBTQ+ people, and gender nonconforming people\n\nFeminist organizations working to protect the digital rights of women, LGBTQ+ people, and gender nonconforming people\n\nFeatured Grantees\n\n\n\n\n\n\n\n\n\nAcoso.Online\nBuilding Latin America’s first context-specific resource for victims of online harassment, including dissemination of nonconsensual pornography. Sursiendo\nConducting participatory research to uncover the digital security needs of activists and human rights defenders in Chiapas, Mexico, as well as the broader context of surveillance and other digital threats to human rights and the state. 7amleh has integrated digital rights into the broader Palestinian rights movement and has led the charge within Palestinian civil society to hold tech companies accountable for the human rights impact of their policies. Sursiendo\nConducting participatory research to uncover the digital security needs of activists and human rights defenders in Chiapas, Mexico, as well as the broader context of surveillance and other digital threats to human rights and the state. 7amleh has integrated digital rights into the broader Palestinian rights movement and has led the charge within Palestinian civil society to hold tech companies accountable for the human rights impact of their policies. Sursiendo\nConducting participatory research to uncover the digital security needs of activists and human rights defenders in Chiapas, Mexico, as well as the broader context of surveillance and other digital threats to human rights and the state. 7amleh has integrated digital rights into the broader Palestinian rights movement and has led the charge within Palestinian civil society to hold tech companies accountable for the human rights impact of their policies. Sursiendo\nConducting participatory research to uncover the digital security needs of activists and human rights defenders in Chiapas, Mexico, as well as the broader context of surveillance and other digital threats to human rights and the state. Sursiendo\nConducting participatory research to uncover the digital security needs of activists and human rights defenders in Chiapas, Mexico, as well as the broader context of surveillance and other digital threats to human rights and the state. Sursiendo\nConducting participatory research to uncover the digital security needs of activists and human rights defenders in Chiapas, Mexico, as well as the broader context of surveillance and other digital threats to human rights and the state. Sursiendo\nConducting participatory research to uncover the digital security needs of activists and human rights defenders in Chiapas, Mexico, as well as the broader context of surveillance and other digital threats to human rights and the state. Sursiendo\nConducting participatory research to uncover the digital security needs of activists and human rights defenders in Chiapas, Mexico, as well as the broader context of surveillance and other digital threats to human rights and the state. Conducting participatory research to uncover the digital security needs of activists and human rights defenders in Chiapas, Mexico, as well as the broader context of surveillance and other digital threats to human rights and the state. 7amleh has integrated digital rights into the broader Palestinian rights movement and has led the charge within Palestinian civil society to hold tech companies accountable for the human rights impact of their policies. 7amleh has integrated digital rights into the broader Palestinian rights movement and has led the charge within Palestinian civil society to hold tech companies accountable for the human rights impact of their policies. 7amleh has integrated digital rights into the broader Palestinian rights movement and has led the charge within Palestinian civil society to hold tech companies accountable for the human rights impact of their policies. 7amleh has integrated digital rights into the broader Palestinian rights movement and has led the charge within Palestinian civil society to hold tech companies accountable for the human rights impact of their policies. 7amleh has integrated digital rights into the broader Palestinian rights movement and has led the charge within Palestinian civil society to hold tech companies accountable for the human rights impact of their policies. 7amleh has integrated digital rights into the broader Palestinian rights movement and has led the charge within Palestinian civil society to hold tech companies accountable for the human rights impact of their policies. See full list of grantees\n\nSee full list of grantees\n\nSee full list of grantees\n\nSee full list of grantees\n\nWHAT WE FUND\nThreats to digital rights take many forms, depending on the context and unique challenges specific users or communities face, ranging from censorship and network disruption, to communications surveillance, to lack of protections for personal data, to online harassment, and beyond. Some examples of what Access Now Grants supports include:\n\n\nResearch, monitoring, advocacy, and public campaigns to fight internet shutdowns\n\n\nDigital security accompaniment for users at risk, such as women, LGBTQ+ people, human rights defenders, and minority communities\n\n\nEfforts to combat online violence through direct interventions with at-risk users and tech companies\n\n\nDocumentation and advocacy to fight impunity for digital attacks on human rights defenders, journalists, activists, and other at-risk groups\n\n\nProtection of digital civic space during elections and conflict, and in the face of content takedowns, surveillance, troll armies, etc. Projects to integrate digital rights into broader human rights movements to ensure they are effective and protected in the digital space\n\n\nStrategies for advancing individual control of our digital identities that center the experiences of those most detrimentally impacted by violations of privacy rights\n\n\nAnd more! Some examples of what Access Now Grants supports include:\n\nResearch, monitoring, advocacy, and public campaigns to fight internet shutdowns\n\n\nDigital security accompaniment for users at risk, such as women, LGBTQ+ people, human rights defenders, and minority communities\n\n\nEfforts to combat online violence through direct interventions with at-risk users and tech companies\n\n\nDocumentation and advocacy to fight impunity for digital attacks on human rights defenders, journalists, activists, and other at-risk groups\n\n\nProtection of digital civic space during elections and conflict, and in the face of content takedowns, surveillance, troll armies, etc. Projects to integrate digital rights into broader human rights movements to ensure they are effective and protected in the digital space\n\n\nStrategies for advancing individual control of our digital identities that center the experiences of those most detrimentally impacted by violations of privacy rights\n\n\nAnd more! Research, monitoring, advocacy, and public campaigns to fight internet shutdowns\n\nResearch, monitoring, advocacy, and public campaigns to fight internet shutdowns\n\nDigital security accompaniment for users at risk, such as women, LGBTQ+ people, human rights defenders, and minority communities\n\nDigital security accompaniment for users at risk, such as women, LGBTQ+ people, human rights defenders, and minority communities\n\nEfforts to combat online violence through direct interventions with at-risk users and tech companies\n\nEfforts to combat online violence through direct interventions with at-risk users and tech companies\n\nDocumentation and advocacy to fight impunity for digital attacks on human rights defenders, journalists, activists, and other at-risk groups\n\nDocumentation and advocacy to fight impunity for digital attacks on human rights defenders, journalists, activists, and other at-risk groups\n\nProtection of digital civic space during elections and conflict, and in the face of content takedowns, surveillance, troll armies, etc. Projects to integrate digital rights into broader human rights movements to ensure they are effective and protected in the digital space\n\nProjects to integrate digital rights into broader human rights movements to ensure they are effective and protected in the digital space\n\nStrategies for advancing individual control of our digital identities that center the experiences of those most detrimentally impacted by violations of privacy rights\n\nStrategies for advancing individual control of our digital identities that center the experiences of those most detrimentally impacted by violations of privacy rights\n\nAnd more! HOW WE FUND\nOur grantmaking is grounded in international human rights frameworks and takes an intersectional approach that recognizes that threats to digital rights are compounded when they intersect with other human rights abuses or discrimination based on ethnicity, religion, gender, sexuality, class, or other means of marginalization. TRANSPARENCY\nBe transparent about criteria, internal processes, and decisions\n\n\nACCOUNTABILITY\nEnsure respect for and accountability to our grantees through our processes and communications, while acknowledging and working to flatten the power imbalances between funder and grantee\n\n\nSIMPLICITY\nUse clear and simple procedures and language that can be understood by applicants and the broader community\n\n\n\n\n\n\n\n\nCONTEXT\nAllow local actors and communities to define priorities and set their own goals\n\n\nFLEXIBILITY\nProvide flexibility to respond to emerging opportunities and external needs\n\n\nLIMITED BUREAUCRACY\nRequire limited paperwork and reduce the administrative burden on grantees whenever possible\n\n\n\n\n\n\n\n\nENGAGEMENT\nContinuously self-evaluate and engage within the sector to identify how Access Now can most effectively operate, fund, and contribute\n\n\n\n\n\n\n\n\n\nTypes of Grants\n\n\nPROJECT GRANTS\nFunds projects with explicit end goals, finite timelines, and clear objectives. AVERAGE GRANT: $7,000\n\n\nDIGITAL SAFE SPACES GRANTS\nFunds human rights organizations that are amplifying the voices of marginalized groups online and want to improve their digital security. AVERAGE GRANT: $9,000\n\n\n\nApplication Process\n\nOur grantmaking is grounded in international human rights frameworks and takes an intersectional approach that recognizes that threats to digital rights are compounded when they intersect with other human rights abuses or discrimination based on ethnicity, religion, gender, sexuality, class, or other means of marginalization. TRANSPARENCY\nBe transparent about criteria, internal processes, and decisions\n\n\nACCOUNTABILITY\nEnsure respect for and accountability to our grantees through our processes and communications, while acknowledging and working to flatten the power imbalances between funder and grantee\n\n\nSIMPLICITY\nUse clear and simple procedures and language that can be understood by applicants and the broader community\n\n\n\n\n\n\n\n\nCONTEXT\nAllow local actors and communities to define priorities and set their own goals\n\n\nFLEXIBILITY\nProvide flexibility to respond to emerging opportunities and external needs\n\n\nLIMITED BUREAUCRACY\nRequire limited paperwork and reduce the administrative burden on grantees whenever possible\n\n\n\n\n\n\n\n\nENGAGEMENT\nContinuously self-evaluate and engage within the sector to identify how Access Now can most effectively operate, fund, and contribute\n\nTRANSPARENCY\nBe transparent about criteria, internal processes, and decisions\n\n\nACCOUNTABILITY\nEnsure respect for and accountability to our grantees through our processes and communications, while acknowledging and working to flatten the power imbalances between funder and grantee\n\n\nSIMPLICITY\nUse clear and simple procedures and language that can be understood by applicants and the broader community\n\n\n\n\n\n\n\n\nCONTEXT\nAllow local actors and communities to define priorities and set their own goals\n\n\nFLEXIBILITY\nProvide flexibility to respond to emerging opportunities and external needs\n\n\nLIMITED BUREAUCRACY\nRequire limited paperwork and reduce the administrative burden on grantees whenever possible\n\n\n\n\n\n\n\n\nENGAGEMENT\nContinuously self-evaluate and engage within the sector to identify how Access Now can most effectively operate, fund, and contribute\n\nTRANSPARENCY\nBe transparent about criteria, internal processes, and decisions\n\n\nACCOUNTABILITY\nEnsure respect for and accountability to our grantees through our processes and communications, while acknowledging and working to flatten the power imbalances between funder and grantee\n\n\nSIMPLICITY\nUse clear and simple procedures and language that can be understood by applicants and the broader community\n\nTRANSPARENCY\nBe transparent about criteria, internal processes, and decisions\n\n\nACCOUNTABILITY\nEnsure respect for and accountability to our grantees through our processes and communications, while acknowledging and working to flatten the power imbalances between funder and grantee\n\n\nSIMPLICITY\nUse clear and simple procedures and language that can be understood by applicants and the broader community\n\nTRANSPARENCY\nBe transparent about criteria, internal processes, and decisions\n\n\nACCOUNTABILITY\nEnsure respect for and accountability to our grantees through our processes and communications, while acknowledging and working to flatten the power imbalances between funder and grantee\n\n\nSIMPLICITY\nUse clear and simple procedures and language that can be understood by applicants and the broader community\n\nTRANSPARENCY\nBe transparent about criteria, internal processes, and decisions\n\n\nACCOUNTABILITY\nEnsure respect for and accountability to our grantees through our processes and communications, while acknowledging and working to flatten the power imbalances between funder and grantee\n\n\nSIMPLICITY\nUse clear and simple procedures and language that can be understood by applicants and the broader community\n\nTRANSPARENCY\nBe transparent about criteria, internal processes, and decisions\n\nTRANSPARENCY\n\nBe transparent about criteria, internal processes, and decisions\n\nACCOUNTABILITY\nEnsure respect for and accountability to our grantees through our processes and communications, while acknowledging and working to flatten the power imbalances between funder and grantee\n\nACCOUNTABILITY\n\nEnsure respect for and accountability to our grantees through our processes and communications, while acknowledging and working to flatten the power imbalances between funder and grantee\n\nSIMPLICITY\nUse clear and simple procedures and language that can be understood by applicants and the broader community\n\nSIMPLICITY\n\nUse clear and simple procedures and language that can be understood by applicants and the broader community\n\nCONTEXT\nAllow local actors and communities to define priorities and set their own goals\n\n\nFLEXIBILITY\nProvide flexibility to respond to emerging opportunities and external needs\n\n\nLIMITED BUREAUCRACY\nRequire limited paperwork and reduce the administrative burden on grantees whenever possible\n\nCONTEXT\nAllow local actors and communities to define priorities and set their own goals\n\n\nFLEXIBILITY\nProvide flexibility to respond to emerging opportunities and external needs\n\n\nLIMITED BUREAUCRACY\nRequire limited paperwork and reduce the administrative burden on grantees whenever possible\n\nCONTEXT\nAllow local actors and communities to define priorities and set their own goals\n\n\nFLEXIBILITY\nProvide flexibility to respond to emerging opportunities and external needs\n\n\nLIMITED BUREAUCRACY\nRequire limited paperwork and reduce the administrative burden on grantees whenever possible\n\nCONTEXT\nAllow local actors and communities to define priorities and set their own goals\n\n\nFLEXIBILITY\nProvide flexibility to respond to emerging opportunities and external needs\n\n\nLIMITED BUREAUCRACY\nRequire limited paperwork and reduce the administrative burden on grantees whenever possible\n\nCONTEXT\nAllow local actors and communities to define priorities and set their own goals\n\nCONTEXT\n\nAllow local actors and communities to define priorities and set their own goals\n\nFLEXIBILITY\nProvide flexibility to respond to emerging opportunities and external needs\n\nFLEXIBILITY\n\nProvide flexibility to respond to emerging opportunities and external needs\n\nLIMITED BUREAUCRACY\nRequire limited paperwork and reduce the administrative burden on grantees whenever possible\n\nLIMITED BUREAUCRACY\n\nRequire limited paperwork and reduce the administrative burden on grantees whenever possible\n\nENGAGEMENT\nContinuously self-evaluate and engage within the sector to identify how Access Now can most effectively operate, fund, and contribute\n\nENGAGEMENT\nContinuously self-evaluate and engage within the sector to identify how Access Now can most effectively operate, fund, and contribute\n\nENGAGEMENT\nContinuously self-evaluate and engage within the sector to identify how Access Now can most effectively operate, fund, and contribute\n\nENGAGEMENT\nContinuously self-evaluate and engage within the sector to identify how Access Now can most effectively operate, fund, and contribute\n\nENGAGEMENT\nContinuously self-evaluate and engage within the sector to identify how Access Now can most effectively operate, fund, and contribute\n\nENGAGEMENT\n\nContinuously self-evaluate and engage within the sector to identify how Access Now can most effectively operate, fund, and contribute\n\nPROJECT GRANTS\nFunds projects with explicit end goals, finite timelines, and clear objectives. AVERAGE GRANT: $7,000\n\n\nDIGITAL SAFE SPACES GRANTS\nFunds human rights organizations that are amplifying the voices of marginalized groups online and want to improve their digital security. AVERAGE GRANT: $7,000\n\nDIGITAL SAFE SPACES GRANTS\nFunds human rights organizations that are amplifying the voices of marginalized groups online and want to improve their digital security. AVERAGE GRANT: $9,000\n\nDIGITAL SAFE SPACES GRANTS\n\nFunds human rights organizations that are amplifying the voices of marginalized groups online and want to improve their digital security. We would like to thank the following individuals for donating their time and energy:\n\nAbir Ghattas (Lebanon)Information Security Technologist, Human Rights Watch\n\nArzu Geybullyeva (Azerbaijan / Turkey)Regional Analyst & Blogger, Global Voices\n\nSaadat Baigazieva (Kyrgyzstan)Feminist activist in fields ranging from gender justice, digital security, and cyberfeminism, to climate and environmental justice, sexual and reproductive rights, and disability rights. We would like to thank the following individuals for donating their time and energy:\n\nAbir Ghattas (Lebanon)Information Security Technologist, Human Rights Watch\n\nArzu Geybullyeva (Azerbaijan / Turkey)Regional Analyst & Blogger, Global Voices\n\nSaadat Baigazieva (Kyrgyzstan)Feminist activist in fields ranging from gender justice, digital security, and cyberfeminism, to climate and environmental justice, sexual and reproductive rights, and disability rights.",
  "entities": {
    "countries": [
      "afghanistan",
      "australia",
      "brazil",
      "canada",
      "china",
      "france",
      "germany",
      "india",
      "iran",
      "iraq",
      "israel",
      "japan",
      "mexico",
      "north korea",
      "pakistan",
      "russia",
      "south korea",
      "syria",
      "united kingdom",
      "united states",
      "yemen"
    ],
    "organizations": [
      "un",
      "who",
      "human rights watch"
    ],
    "key_issues": [
      "issue",
      "challenge",
      "country",
      "nation",
      "state",
      "region",
      "territory",
      "approach",
      "policy",
      "initiative",
      "program",
      "action",
      "history",
      "context",
      "development",
      "human rights",
      "assistance",
      "un",
      "ngo",
      "organization",
      "agency",
      "foundation"
    ]
  },
  "committee": "First Committee",
  "topic": "Creating systems to protect against state-sponsored cyber attacks"
}