{
  "url": "https://www.accessnow.org/issue/content-governance/",
  "title": "Content Governance - Access Now",
  "text": "Back to content\n\nRights-Based Approaches to Online Content\n\n\n\nGovernments and companies are under increasing pressure to address illegal or undesirable content and expression online, but hasty or poorly crafted solutions threaten human rights. We advocate for policies and practices to defend free expression and access to information and  ensure people who are most at risk are protected.\n\n\n\n\n\n\n\n\n\n\n\n\nPlatform Accountability: a rule-of-law checklist for policymakers\nPlatform regulations can be a minefield for human rights. Here’s a checklist to help policymakers examine the need for platform regulations, and where necessary, enact regulations that are fit-for-purpose and protect human rights. \n\nLearn more\n\n\n\n\n\nResources\n\n\n\n\n\n\n\n\n\n\n\n\n\nContent Governance\n\n\n\t\t\t\n\t\t\t\tOur rights are at stake: it’s time to reclaim freedom of expression\n\t\t\t\t\t\t\t\n\n\nGiven the escalating use of free speech claims as a shield for inciting hatred and violence, it is more urgent than ever to reaffirm what freedom of expression truly stands for. \n\n\n\n\n\n\n\n\n\n\n\n\n\nContent Governance\n\n\n\t\t\t\n\t\t\t\tContent governance in times of crisis: how platforms can protect human rights\n\t\t\t\t\t\t\t\n\n\nThe “Declaration for content and platform governance principles in times of crisis” lays out principles for social media platforms to help ensure privacy, freedom of expression, and access to information during crises.\n\n\n\n\n\n\n\n\n\n\n\n\n\nContent Governance\n\n\n\t\t\t\n\t\t\t\tRainbow-burning: how social media companies increase risks for LGBTQ+ people in Africa\n\t\t\t\t\t\t\t\n\n\nColonial-era laws and a global anti-rights movement are fueling LGBTQ+ repression across Africa. Access Now documented 214 threats on platforms like TikTok, X, Facebook, YouTube, and WhatsApp, underscoring widespread risks.\n\n\n\n\n\n\n\n\n\n\n\n\n\nContent Governance\n\n\n\t\t\t\n\t\t\t\tGuide: how to protect human rights in content governance\n\t\t\t\t\t\t\t\n\n\nWe offer 26 recommendations on content governance to help lawmakers, regulators, and company leaders make decisions that will safeguard human rights.\n\n\n\n\n\n\n\n\n\n\n\n\n\n\n\n\n\n\n\n\n\nContent Governance\n\n\n\t\t\t\n\t\t\t\tDigital Security Helpline: our approach to content-related cases\n\t\t\t\t\t\t\t\n\n\nCritical voices from civil society are being censored. Here’s how the Digital Security Helpline addresses cases related to content governance.\n\n\n\n\n\n\n\n\n\n\n\n\n\nContent Governance\n\n\n\t\t\t\n\t\t\t\tWhat is disinformation, why it spreads, and how to stop it\n\t\t\t\t\t\t\t\n\n\nOur new report explores what disinformation is, and how lawmakers can address the harms it poses to democracy.\n\n\n\n\n\n\n\n\n\n\n\n\n\nContent Governance\n\n\n\t\t\t\n\t\t\t\tThe Digital Services Act: your guide to the EU’s new content moderation rules\n\t\t\t\t\t\t\t\n\n\nThe EU Digital Services Act has finally arrived. We unpack what this law contains and the changes people can expect to see from 2024 onwards.\n\n\n\n\n\n\n\n\n\n\n\n\n\nContent Governance\n\n\n\t\t\t\n\t\t\t\tAccess Now releases “Fighting misinformation and defending free expression during COVID-19: recommendations for states”\n\t\t\t\t\t\t\t\n\n\nWe have identified practical examples and promising practices to support policy makers in respecting human rights while developing measures to address disinformation and misinformation during the COVID-19 crisis.\n\n\n\n\n\n\n\n\n\n\n\n\n\n\nLatest Updates\n\n\n\n     \n\n\n\n\n\nGrid View\nList View\n\n\n\n\n\n\n\n\n\n\n\n\n\n\t\t\t\t\tContent Governance\t\t\t\t\n\n\n\n\nContent Governance \n\n\n\t\t\t\t‘Profiting from misery’: how TikTok makes money from child begging livestreams\t\t\t\n\n6 Apr 2025\n\n\n\n\nNews\n‘Profiting from misery’: how TikTok makes money from child begging livestreams\n\n\t\t\t\t\t\t\t\t\tThe Guardian ↗\t\t\t\t\t\t\t\n↗\n6 Apr 2025\n\n‘Profiting from misery’: how TikTok makes money from child begging livestreams\n\n\n\n\n \n\t\t\t\t\tInternet Shutdowns\t\t\t\t\n\n\n\n\nInternet Shutdowns \n\n\n\t\t\t\tEmboldened offenders, endangered communities: internet shutdowns in 2024\t\t\t\n\n23 Feb 2025\n • \nAccess Now and the #KeepItOn coalition documented 296 internet shutdowns in 2024 — the highest number since 2016.\n\n\n\n\nPublication\nEmboldened offenders, endangered communities: internet shutdowns in 2024\n\n\n↗\n23 Feb 2025\n\nEmboldened offenders, endangered communities: internet shutdowns in 2024\n\n\n\n\n\n\n\n\n\n\t\t\t\t\tFreedom of Expression\t\t\t\t\n\n\n\n\nFreedom of Expression \n\n\n\t\t\t\tOur rights are at stake: it’s time to reclaim freedom of expression\t\t\t\n\n21 Feb 2025\n • \nGiven the escalating use of free speech claims as a shield for inciting hatred and violence, it is more urgent than ever to reaffirm what freedom of expression truly stands for. \n\n\n\n\nPress Release\nOur rights are at stake: it’s time to reclaim freedom of expression\n21 Feb 2025\n\nOur rights are at stake: it’s time to reclaim freedom of expression\n\n\n\n\n\n\n\n\n\n\t\t\t\t\tContent Governance\t\t\t\t\n\n\n\n\nContent Governance \n\n\n\t\t\t\tPoised to take over TikTok, Oracle is accused of clamping down on Pro-Palestine dissent\t\t\t\n\n19 Feb 2025\n\n\n\n\nNews\nPoised to take over TikTok, Oracle is accused of clamping down on Pro-Palestine dissent\n\n\t\t\t\t\t\t\t\t\tThe Intercept ↗\t\t\t\t\t\t\t\n↗\n19 Feb 2025\n\nPoised to take over TikTok, Oracle is accused of clamping down on Pro-Palestine dissent\n\n\n\n\n\n\n\n\n\n\t\t\t\t\tContent Governance\t\t\t\t\n\n\n\n\nContent Governance \n\n\n\t\t\t\tTamil website Vikatan inaccessible after It posted cartoon of PM, no official takedown order confirmed\t\t\t\n\n19 Feb 2025\n\n\n\n\nNews\nTamil website Vikatan inaccessible after It posted cartoon of PM, no official takedown order confirmed\n\n\t\t\t\t\t\t\t\t\tMedianama ↗\t\t\t\t\t\t\t\n↗\n19 Feb 2025\n\nTamil website Vikatan inaccessible after It posted cartoon of PM, no official takedown order confirmed\n\n\n\n\n\n\n\n\n\n\t\t\t\t\tInternet Shutdowns\t\t\t\t\n\n\n\n\nInternet Shutdowns \n\n\n\t\t\t\t2025 elections and internet shutdowns watch\t\t\t\n\n30 Jan 2025\n • \nGovernments around the world continue to shut down the internet during elections. Join our 2025 elections watch to #KeepItOn.\n\n\n\n\nCampaign\n2025 elections and internet shutdowns watch\n30 Jan 2025\n\n2025 elections and internet shutdowns watch\n\n\n\n\n\n\n\n\n\n\t\t\t\t\tContent Governance\t\t\t\t\n\n\n\n\nContent Governance \n\n\n\t\t\t\tTrump stand on online speech divides free speech ecosystem\t\t\t\n\n22 Jan 2025\n\n\n\n\nNews\nTrump stand on online speech divides free speech ecosystem\n\n\t\t\t\t\t\t\t\t\tHindu Businessline ↗\t\t\t\t\t\t\t\n↗\n22 Jan 2025\n\nTrump stand on online speech divides free speech ecosystem\n\n\n\n\n\n\n\n\n\n\t\t\t\t\tFreedom of Expression\t\t\t\t\n\n\n\n\nFreedom of Expression \n\n\n\t\t\t\tCeasefire in Gaza: it’s time to end digital harms and deliver justice\t\t\t\n\n20 Jan 2025\n • \nAs physical violence appears to be coming to a halt after 15 months in Gaza, Access Now further calls for a digital ceasefire.\n\n\n\n\nPress Release\nCeasefire in Gaza: it’s time to end digital harms and deliver justice\n20 Jan 2025\n\nCeasefire in Gaza: it’s time to end digital harms and deliver justice\n\n\n\n\n\n\n\n\n\n\t\t\t\t\tContent Governance\t\t\t\t\n\n\n\n\nContent Governance \n\n\n\t\t\t\tMetino ukidanje provjere činjenica ‘politička odluka sa stvarnim posljedicama’\t\t\t\n\n20 Jan 2025\n\n\n\n\nNews\nMetino ukidanje provjere činjenica ‘politička odluka sa stvarnim posljedicama’\n\n\t\t\t\t\t\t\t\t\tRadio Free Europe ↗\t\t\t\t\t\t\t\n↗\n20 Jan 2025\n\nMetino ukidanje provjere činjenica ‘politička odluka sa stvarnim posljedicama’\n\n\n\n\n\n\n\n\n\n\t\t\t\t\tFreedom of Expression\t\t\t\t\n\n\n\n\nFreedom of Expression \n\n\n\t\t\t\tTackling the “black snakes” undermining digital rights worldwide \t\t\t\n\n16 Jan 2025\n • \nAs 2025 gets underway, Access Now’s new Executive Director, Alejandro Mayoral Baños, PhD, shares his reflections on the “black snakes” threatening the digital rights movement. \n\n\n\n\nPost\nTackling the “black snakes” undermining digital rights worldwide \n16 Jan 2025\n\nTackling the “black snakes” undermining digital rights worldwide \n\n\n\n\n\n\n\n\n\n\t\t\t\t\tContent Governance\t\t\t\t\n\n\n\n\nContent Governance \n\n\n\t\t\t\tWhy Facebook ending fact checking in US is a warning sign for India\t\t\t\n\n14 Jan 2025\n\n\n\n\nNews\nWhy Facebook ending fact checking in US is a warning sign for India\n\n\t\t\t\t\t\t\t\t\tScroll ↗\t\t\t\t\t\t\t\n↗\n14 Jan 2025\n\nWhy Facebook ending fact checking in US is a warning sign for India\n\n\n\n\n\n\n\n\n\n\t\t\t\t\tContent Governance\t\t\t\t\n\n\n\n\nContent Governance \n\n\n\t\t\t\tEU regulators take a hard look at Elon Musk and X\t\t\t\n\n14 Jan 2025\n\n\n\n\nNews\nEU regulators take a hard look at Elon Musk and X\n\n\t\t\t\t\t\t\t\t\tDeutsche Welle ↗\t\t\t\t\t\t\t\n↗\n14 Jan 2025\n\nEU regulators take a hard look at Elon Musk and X\n\n\n\n\n\n\n\n\n\n\t\t\t\t\tContent Governance\t\t\t\t\n\n\n\n\nContent Governance \n\n\n\t\t\t\tPlatform accountability: a rule-of-law checklist for policymakers\t\t\t\n\n13 Jan 2025\n • \nIn this report, Access Now proposes a rule-of-law checklist to enable states to enact platform accountability regulations that are fit for purpose and protect human rights.\n\n\n\n\nPublication\nPlatform accountability: a rule-of-law checklist for policymakers\n\n\n↗\n13 Jan 2025\n\nPlatform accountability: a rule-of-law checklist for policymakers\n\n\n\n\n\n\n\n\n\n\t\t\t\t\tContent Governance\t\t\t\t\n\n\n\n\nContent Governance \n\n\n\t\t\t\tPlatform accountability and human rights: a rule-of-law checklist\t\t\t\n\n13 Jan 2025\n • \nAs policymakers around the world seek to rein in Big Tech, we define the safeguards necessary to ensure rule of law and protect human rights and democracy.\n\n\n\n\nPost\nPlatform accountability and human rights: a rule-of-law checklist\n13 Jan 2025\n\nPlatform accountability and human rights: a rule-of-law checklist\n\n\n\n\n\n\n\n\n\n\t\t\t\t\tContent Governance\t\t\t\t\n\n\n\n\nContent Governance \n\n\n\t\t\t\tGlobal fact-checkers were disappointed, not surprised, Meta ended its program\t\t\t\n\n10 Jan 2025\n\n\n\n\nNews\nGlobal fact-checkers were disappointed, not surprised, Meta ended its program\n\n\t\t\t\t\t\t\t\t\tRest of World ↗\t\t\t\t\t\t\t\n↗\n10 Jan 2025\n\nGlobal fact-checkers were disappointed, not surprised, Meta ended its program\n\n\n\n\n\n\n\n\n\n\t\t\t\t\tContent Governance\t\t\t\t\n\n\n\n\nContent Governance \n\n\n\t\t\t\tBrussels will be watching whether Musk breaks EU law in far-right livestream\t\t\t\n\n9 Jan 2025\n\n\n\n\nNews\nBrussels will be watching whether Musk breaks EU law in far-right livestream\n\n\t\t\t\t\t\t\t\t\tPOLITICO ↗\t\t\t\t\t\t\t\n↗\n9 Jan 2025\n\nBrussels will be watching whether Musk breaks EU law in far-right livestream\n\n\n\n\n\n\n\n\n \n\n\n\n\n\n\nHelp keep the internet open and secure.\nSubscribe to our action alerts and weekly newsletter\n\"*\" indicates required fields\n\nThis field is hidden when viewing the form\n\nSubscribe to Access Express\nThis field is hidden when viewing the form\n\nSubscribe to Action Alerts\nName\n\n\nFirst\n\n\n\nLast\n\nEmail*\n\nCountryCountryAfghanistanÅland IslandsAlbaniaAlgeriaAmerican SamoaAndorraAngolaAnguillaAntigua and BarbudaArgentinaArmeniaArubaAustraliaAustriaAzerbaijanBahamasBahrainBangladeshBarbadosBelarusBelgiumBelizeBeninBermudaBhutanBoliviaBonaire, Sint Eustatius and SabaBosnia and HerzegovinaBotswanaBrazilBritish Indian Ocean TerritoryBritish Virgin IslandsBruneiBulgariaBurkina FasoBurundiCambodiaCameroonCanadaCape VerdeCayman IslandsCentral African RepublicChadChileChinaChristmas IslandColombiaComorosCook IslandsCosta RicaCôte d'IvoireCroatiaCubaCuraçaoCyprusCzech RepublicDemocratic Republic of the CongoDenmarkDjiboutiDominicaDominican RepublicEast TimorEcuadorEgyptEl SalvadorEquatorial GuineaEritreaEstoniaEswatiniEthiopiaFalkland IslandsFaroe IslandsFijiFinlandFranceFrench GuianaFrench PolynesiaFrench Southern TerritoriesGabonGeorgiaGermanyGhanaGibraltarGreeceGreenlandGrenadaGuadeloupeGuamGuatemalaGuernseyGuineaGuinea-BissauGuyanaHaitiHondurasHong KongHungaryIcelandIndiaIndonesiaIranIraqIrelandIsraelItalyJamaicaJapanJordanKazakhstanKenyaKiribatiKosovoKuwaitKyrgyzstanLaosLatviaLebanonLesothoLiberiaLibyaLiechtensteinLithuaniaLuxembourgMacauMadagascarMalawiMalaysiaMaldivesMaliMaltaMarshall IslandsMartiniqueMauritaniaMauritiusMayotteMexicoMicronesiaMoldovaMonacoMongoliaMontenegroMontserratMoroccoMozambiqueMyanmarNamibiaNauruNepalNetherlands AntillesNew CaledoniaNew ZealandNicaraguaNigerNigeriaNiueNorfolk IslandNorth KoreaNorth MacedoniaNorthern Mariana IslandsNorwayOmanPakistanPalauPalestinePanamaPapua New GuineaParaguayPeruPhilippinesPitcairn IslandPolandPortugalPuerto RicoQatarRepublic of the CongoReunionRomaniaRussiaRwandaSaint BarthélemySaint Kitts and NevisSaint LuciaSaint Vincent and the GrenadinesSamoaSan MarinoSão Tomé and PríncipeSaudi ArabiaSenegalSerbiaSeychellesSierra LeoneSingaporeSlovakiaSloveniaSolomon IslandsSomaliaSomalilandSouth AfricaSouth KoreaSouth SudanSpainSri LankaSt. HelenaSt. Pierre and MiquelonSudanSurinameSwedenSwitzerlandSyriaTaiwanTajikistanTanzaniaThailandThe GambiaThe NetherlandsTogoTokelauTongaTrinidad and TobagoTunisiaTurkeyTurkmenistanTurks and Caicos IslandsTuvaluUgandaUkraineUnited Arab EmiratesUnited KingdomUnited StatesUruguayUzbekistanVanuatuVatican CityVenezuelaVietnamVirgin Islands (U.S.)Wallis and Futuna IslandsWestern SaharaYemenZambiaZimbabwePostal CodeEmailThis field is for validation purposes and should be left unchanged.\n \n\n\n\n\n\n\n\n\n\n\n\n\n\n\n\nYour info is secure with us\n\nRights-Based Approaches to Online Content\n\n\n\nGovernments and companies are under increasing pressure to address illegal or undesirable content and expression online, but hasty or poorly crafted solutions threaten human rights. We advocate for policies and practices to defend free expression and access to information and  ensure people who are most at risk are protected.\n\n\n\n\n\n\n\n\n\n\n\n\nPlatform Accountability: a rule-of-law checklist for policymakers\nPlatform regulations can be a minefield for human rights. Here’s a checklist to help policymakers examine the need for platform regulations, and where necessary, enact regulations that are fit-for-purpose and protect human rights. \n\nLearn more\n\n\n\n\n\nResources\n\n\n\n\n\n\n\n\n\n\n\n\n\nContent Governance\n\n\n\t\t\t\n\t\t\t\tOur rights are at stake: it’s time to reclaim freedom of expression\n\t\t\t\t\t\t\t\n\n\nGiven the escalating use of free speech claims as a shield for inciting hatred and violence, it is more urgent than ever to reaffirm what freedom of expression truly stands for. \n\n\n\n\n\n\n\n\n\n\n\n\n\nContent Governance\n\n\n\t\t\t\n\t\t\t\tContent governance in times of crisis: how platforms can protect human rights\n\t\t\t\t\t\t\t\n\n\nThe “Declaration for content and platform governance principles in times of crisis” lays out principles for social media platforms to help ensure privacy, freedom of expression, and access to information during crises.\n\n\n\n\n\n\n\n\n\n\n\n\n\nContent Governance\n\n\n\t\t\t\n\t\t\t\tRainbow-burning: how social media companies increase risks for LGBTQ+ people in Africa\n\t\t\t\t\t\t\t\n\n\nColonial-era laws and a global anti-rights movement are fueling LGBTQ+ repression across Africa. Access Now documented 214 threats on platforms like TikTok, X, Facebook, YouTube, and WhatsApp, underscoring widespread risks.\n\n\n\n\n\n\n\n\n\n\n\n\n\nContent Governance\n\n\n\t\t\t\n\t\t\t\tGuide: how to protect human rights in content governance\n\t\t\t\t\t\t\t\n\n\nWe offer 26 recommendations on content governance to help lawmakers, regulators, and company leaders make decisions that will safeguard human rights.\n\n\n\n\n\n\n\n\n\n\n\n\n\n\n\n\n\n\n\n\n\nContent Governance\n\n\n\t\t\t\n\t\t\t\tDigital Security Helpline: our approach to content-related cases\n\t\t\t\t\t\t\t\n\n\nCritical voices from civil society are being censored. Here’s how the Digital Security Helpline addresses cases related to content governance.\n\n\n\n\n\n\n\n\n\n\n\n\n\nContent Governance\n\n\n\t\t\t\n\t\t\t\tWhat is disinformation, why it spreads, and how to stop it\n\t\t\t\t\t\t\t\n\n\nOur new report explores what disinformation is, and how lawmakers can address the harms it poses to democracy.\n\n\n\n\n\n\n\n\n\n\n\n\n\nContent Governance\n\n\n\t\t\t\n\t\t\t\tThe Digital Services Act: your guide to the EU’s new content moderation rules\n\t\t\t\t\t\t\t\n\n\nThe EU Digital Services Act has finally arrived. We unpack what this law contains and the changes people can expect to see from 2024 onwards.\n\n\n\n\n\n\n\n\n\n\n\n\n\nContent Governance\n\n\n\t\t\t\n\t\t\t\tAccess Now releases “Fighting misinformation and defending free expression during COVID-19: recommendations for states”\n\t\t\t\t\t\t\t\n\n\nWe have identified practical examples and promising practices to support policy makers in respecting human rights while developing measures to address disinformation and misinformation during the COVID-19 crisis.\n\n\n\n\n\n\n\n\n\n\n\n\n\n\nLatest Updates\n\n\n\n     \n\n\n\n\n\nGrid View\nList View\n\n\n\n\n\n\n\n\n\n\n\n\n\n\t\t\t\t\tContent Governance\t\t\t\t\n\n\n\n\nContent Governance \n\n\n\t\t\t\t‘Profiting from misery’: how TikTok makes money from child begging livestreams\t\t\t\n\n6 Apr 2025\n\n\n\n\nNews\n‘Profiting from misery’: how TikTok makes money from child begging livestreams\n\n\t\t\t\t\t\t\t\t\tThe Guardian ↗\t\t\t\t\t\t\t\n↗\n6 Apr 2025\n\n‘Profiting from misery’: how TikTok makes money from child begging livestreams\n\n\n\n\n \n\t\t\t\t\tInternet Shutdowns\t\t\t\t\n\n\n\n\nInternet Shutdowns \n\n\n\t\t\t\tEmboldened offenders, endangered communities: internet shutdowns in 2024\t\t\t\n\n23 Feb 2025\n • \nAccess Now and the #KeepItOn coalition documented 296 internet shutdowns in 2024 — the highest number since 2016.\n\n\n\n\nPublication\nEmboldened offenders, endangered communities: internet shutdowns in 2024\n\n\n↗\n23 Feb 2025\n\nEmboldened offenders, endangered communities: internet shutdowns in 2024\n\n\n\n\n\n\n\n\n\n\t\t\t\t\tFreedom of Expression\t\t\t\t\n\n\n\n\nFreedom of Expression \n\n\n\t\t\t\tOur rights are at stake: it’s time to reclaim freedom of expression\t\t\t\n\n21 Feb 2025\n • \nGiven the escalating use of free speech claims as a shield for inciting hatred and violence, it is more urgent than ever to reaffirm what freedom of expression truly stands for. \n\n\n\n\nPress Release\nOur rights are at stake: it’s time to reclaim freedom of expression\n21 Feb 2025\n\nOur rights are at stake: it’s time to reclaim freedom of expression\n\n\n\n\n\n\n\n\n\n\t\t\t\t\tContent Governance\t\t\t\t\n\n\n\n\nContent Governance \n\n\n\t\t\t\tPoised to take over TikTok, Oracle is accused of clamping down on Pro-Palestine dissent\t\t\t\n\n19 Feb 2025\n\n\n\n\nNews\nPoised to take over TikTok, Oracle is accused of clamping down on Pro-Palestine dissent\n\n\t\t\t\t\t\t\t\t\tThe Intercept ↗\t\t\t\t\t\t\t\n↗\n19 Feb 2025\n\nPoised to take over TikTok, Oracle is accused of clamping down on Pro-Palestine dissent\n\n\n\n\n\n\n\n\n\n\t\t\t\t\tContent Governance\t\t\t\t\n\n\n\n\nContent Governance \n\n\n\t\t\t\tTamil website Vikatan inaccessible after It posted cartoon of PM, no official takedown order confirmed\t\t\t\n\n19 Feb 2025\n\n\n\n\nNews\nTamil website Vikatan inaccessible after It posted cartoon of PM, no official takedown order confirmed\n\n\t\t\t\t\t\t\t\t\tMedianama ↗\t\t\t\t\t\t\t\n↗\n19 Feb 2025\n\nTamil website Vikatan inaccessible after It posted cartoon of PM, no official takedown order confirmed\n\n\n\n\n\n\n\n\n\n\t\t\t\t\tInternet Shutdowns\t\t\t\t\n\n\n\n\nInternet Shutdowns \n\n\n\t\t\t\t2025 elections and internet shutdowns watch\t\t\t\n\n30 Jan 2025\n • \nGovernments around the world continue to shut down the internet during elections. Join our 2025 elections watch to #KeepItOn.\n\n\n\n\nCampaign\n2025 elections and internet shutdowns watch\n30 Jan 2025\n\n2025 elections and internet shutdowns watch\n\n\n\n\n\n\n\n\n\n\t\t\t\t\tContent Governance\t\t\t\t\n\n\n\n\nContent Governance \n\n\n\t\t\t\tTrump stand on online speech divides free speech ecosystem\t\t\t\n\n22 Jan 2025\n\n\n\n\nNews\nTrump stand on online speech divides free speech ecosystem\n\n\t\t\t\t\t\t\t\t\tHindu Businessline ↗\t\t\t\t\t\t\t\n↗\n22 Jan 2025\n\nTrump stand on online speech divides free speech ecosystem\n\n\n\n\n\n\n\n\n\n\t\t\t\t\tFreedom of Expression\t\t\t\t\n\n\n\n\nFreedom of Expression \n\n\n\t\t\t\tCeasefire in Gaza: it’s time to end digital harms and deliver justice\t\t\t\n\n20 Jan 2025\n • \nAs physical violence appears to be coming to a halt after 15 months in Gaza, Access Now further calls for a digital ceasefire.\n\n\n\n\nPress Release\nCeasefire in Gaza: it’s time to end digital harms and deliver justice\n20 Jan 2025\n\nCeasefire in Gaza: it’s time to end digital harms and deliver justice\n\n\n\n\n\n\n\n\n\n\t\t\t\t\tContent Governance\t\t\t\t\n\n\n\n\nContent Governance \n\n\n\t\t\t\tMetino ukidanje provjere činjenica ‘politička odluka sa stvarnim posljedicama’\t\t\t\n\n20 Jan 2025\n\n\n\n\nNews\nMetino ukidanje provjere činjenica ‘politička odluka sa stvarnim posljedicama’\n\n\t\t\t\t\t\t\t\t\tRadio Free Europe ↗\t\t\t\t\t\t\t\n↗\n20 Jan 2025\n\nMetino ukidanje provjere činjenica ‘politička odluka sa stvarnim posljedicama’\n\n\n\n\n\n\n\n\n\n\t\t\t\t\tFreedom of Expression\t\t\t\t\n\n\n\n\nFreedom of Expression \n\n\n\t\t\t\tTackling the “black snakes” undermining digital rights worldwide \t\t\t\n\n16 Jan 2025\n • \nAs 2025 gets underway, Access Now’s new Executive Director, Alejandro Mayoral Baños, PhD, shares his reflections on the “black snakes” threatening the digital rights movement. \n\n\n\n\nPost\nTackling the “black snakes” undermining digital rights worldwide \n16 Jan 2025\n\nTackling the “black snakes” undermining digital rights worldwide \n\n\n\n\n\n\n\n\n\n\t\t\t\t\tContent Governance\t\t\t\t\n\n\n\n\nContent Governance \n\n\n\t\t\t\tWhy Facebook ending fact checking in US is a warning sign for India\t\t\t\n\n14 Jan 2025\n\n\n\n\nNews\nWhy Facebook ending fact checking in US is a warning sign for India\n\n\t\t\t\t\t\t\t\t\tScroll ↗\t\t\t\t\t\t\t\n↗\n14 Jan 2025\n\nWhy Facebook ending fact checking in US is a warning sign for India\n\n\n\n\n\n\n\n\n\n\t\t\t\t\tContent Governance\t\t\t\t\n\n\n\n\nContent Governance \n\n\n\t\t\t\tEU regulators take a hard look at Elon Musk and X\t\t\t\n\n14 Jan 2025\n\n\n\n\nNews\nEU regulators take a hard look at Elon Musk and X\n\n\t\t\t\t\t\t\t\t\tDeutsche Welle ↗\t\t\t\t\t\t\t\n↗\n14 Jan 2025\n\nEU regulators take a hard look at Elon Musk and X\n\n\n\n\n\n\n\n\n\n\t\t\t\t\tContent Governance\t\t\t\t\n\n\n\n\nContent Governance \n\n\n\t\t\t\tPlatform accountability: a rule-of-law checklist for policymakers\t\t\t\n\n13 Jan 2025\n • \nIn this report, Access Now proposes a rule-of-law checklist to enable states to enact platform accountability regulations that are fit for purpose and protect human rights.\n\n\n\n\nPublication\nPlatform accountability: a rule-of-law checklist for policymakers\n\n\n↗\n13 Jan 2025\n\nPlatform accountability: a rule-of-law checklist for policymakers\n\n\n\n\n\n\n\n\n\n\t\t\t\t\tContent Governance\t\t\t\t\n\n\n\n\nContent Governance \n\n\n\t\t\t\tPlatform accountability and human rights: a rule-of-law checklist\t\t\t\n\n13 Jan 2025\n • \nAs policymakers around the world seek to rein in Big Tech, we define the safeguards necessary to ensure rule of law and protect human rights and democracy.\n\n\n\n\nPost\nPlatform accountability and human rights: a rule-of-law checklist\n13 Jan 2025\n\nPlatform accountability and human rights: a rule-of-law checklist\n\n\n\n\n\n\n\n\n\n\t\t\t\t\tContent Governance\t\t\t\t\n\n\n\n\nContent Governance \n\n\n\t\t\t\tGlobal fact-checkers were disappointed, not surprised, Meta ended its program\t\t\t\n\n10 Jan 2025\n\n\n\n\nNews\nGlobal fact-checkers were disappointed, not surprised, Meta ended its program\n\n\t\t\t\t\t\t\t\t\tRest of World ↗\t\t\t\t\t\t\t\n↗\n10 Jan 2025\n\nGlobal fact-checkers were disappointed, not surprised, Meta ended its program\n\n\n\n\n\n\n\n\n\n\t\t\t\t\tContent Governance\t\t\t\t\n\n\n\n\nContent Governance \n\n\n\t\t\t\tBrussels will be watching whether Musk breaks EU law in far-right livestream\t\t\t\n\n9 Jan 2025\n\n\n\n\nNews\nBrussels will be watching whether Musk breaks EU law in far-right livestream\n\n\t\t\t\t\t\t\t\t\tPOLITICO ↗\t\t\t\t\t\t\t\n↗\n9 Jan 2025\n\nBrussels will be watching whether Musk breaks EU law in far-right livestream\n\nRights-Based Approaches to Online Content\n\n\n\nGovernments and companies are under increasing pressure to address illegal or undesirable content and expression online, but hasty or poorly crafted solutions threaten human rights. We advocate for policies and practices to defend free expression and access to information and  ensure people who are most at risk are protected.\n\n\n\n\n\n\n\n\n\n\n\n\nPlatform Accountability: a rule-of-law checklist for policymakers\nPlatform regulations can be a minefield for human rights. Here’s a checklist to help policymakers examine the need for platform regulations, and where necessary, enact regulations that are fit-for-purpose and protect human rights. \n\nLearn more\n\n\n\n\n\nResources\n\n\n\n\n\n\n\n\n\n\n\n\n\nContent Governance\n\n\n\t\t\t\n\t\t\t\tOur rights are at stake: it’s time to reclaim freedom of expression\n\t\t\t\t\t\t\t\n\n\nGiven the escalating use of free speech claims as a shield for inciting hatred and violence, it is more urgent than ever to reaffirm what freedom of expression truly stands for. \n\n\n\n\n\n\n\n\n\n\n\n\n\nContent Governance\n\n\n\t\t\t\n\t\t\t\tContent governance in times of crisis: how platforms can protect human rights\n\t\t\t\t\t\t\t\n\n\nThe “Declaration for content and platform governance principles in times of crisis” lays out principles for social media platforms to help ensure privacy, freedom of expression, and access to information during crises.\n\n\n\n\n\n\n\n\n\n\n\n\n\nContent Governance\n\n\n\t\t\t\n\t\t\t\tRainbow-burning: how social media companies increase risks for LGBTQ+ people in Africa\n\t\t\t\t\t\t\t\n\n\nColonial-era laws and a global anti-rights movement are fueling LGBTQ+ repression across Africa. Access Now documented 214 threats on platforms like TikTok, X, Facebook, YouTube, and WhatsApp, underscoring widespread risks.\n\n\n\n\n\n\n\n\n\n\n\n\n\nContent Governance\n\n\n\t\t\t\n\t\t\t\tGuide: how to protect human rights in content governance\n\t\t\t\t\t\t\t\n\n\nWe offer 26 recommendations on content governance to help lawmakers, regulators, and company leaders make decisions that will safeguard human rights.\n\n\n\n\n\n\n\n\n\n\n\n\n\n\n\n\n\n\n\n\n\nContent Governance\n\n\n\t\t\t\n\t\t\t\tDigital Security Helpline: our approach to content-related cases\n\t\t\t\t\t\t\t\n\n\nCritical voices from civil society are being censored. Here’s how the Digital Security Helpline addresses cases related to content governance.\n\n\n\n\n\n\n\n\n\n\n\n\n\nContent Governance\n\n\n\t\t\t\n\t\t\t\tWhat is disinformation, why it spreads, and how to stop it\n\t\t\t\t\t\t\t\n\n\nOur new report explores what disinformation is, and how lawmakers can address the harms it poses to democracy.\n\n\n\n\n\n\n\n\n\n\n\n\n\nContent Governance\n\n\n\t\t\t\n\t\t\t\tThe Digital Services Act: your guide to the EU’s new content moderation rules\n\t\t\t\t\t\t\t\n\n\nThe EU Digital Services Act has finally arrived. We unpack what this law contains and the changes people can expect to see from 2024 onwards.\n\n\n\n\n\n\n\n\n\n\n\n\n\nContent Governance\n\n\n\t\t\t\n\t\t\t\tAccess Now releases “Fighting misinformation and defending free expression during COVID-19: recommendations for states”\n\t\t\t\t\t\t\t\n\n\nWe have identified practical examples and promising practices to support policy makers in respecting human rights while developing measures to address disinformation and misinformation during the COVID-19 crisis.\n\n\n\n\n\n\n\n\n\n\n\n\n\n\nLatest Updates\n\n\n\n     \n\n\n\n\n\nGrid View\nList View\n\n\n\n\n\n\n\n\n\n\n\n\n\n\t\t\t\t\tContent Governance\t\t\t\t\n\n\n\n\nContent Governance \n\n\n\t\t\t\t‘Profiting from misery’: how TikTok makes money from child begging livestreams\t\t\t\n\n6 Apr 2025\n\n\n\n\nNews\n‘Profiting from misery’: how TikTok makes money from child begging livestreams\n\n\t\t\t\t\t\t\t\t\tThe Guardian ↗\t\t\t\t\t\t\t\n↗\n6 Apr 2025\n\n‘Profiting from misery’: how TikTok makes money from child begging livestreams\n\n\n\n\n \n\t\t\t\t\tInternet Shutdowns\t\t\t\t\n\n\n\n\nInternet Shutdowns \n\n\n\t\t\t\tEmboldened offenders, endangered communities: internet shutdowns in 2024\t\t\t\n\n23 Feb 2025\n • \nAccess Now and the #KeepItOn coalition documented 296 internet shutdowns in 2024 — the highest number since 2016.\n\n\n\n\nPublication\nEmboldened offenders, endangered communities: internet shutdowns in 2024\n\n\n↗\n23 Feb 2025\n\nEmboldened offenders, endangered communities: internet shutdowns in 2024\n\n\n\n\n\n\n\n\n\n\t\t\t\t\tFreedom of Expression\t\t\t\t\n\n\n\n\nFreedom of Expression \n\n\n\t\t\t\tOur rights are at stake: it’s time to reclaim freedom of expression\t\t\t\n\n21 Feb 2025\n • \nGiven the escalating use of free speech claims as a shield for inciting hatred and violence, it is more urgent than ever to reaffirm what freedom of expression truly stands for. \n\n\n\n\nPress Release\nOur rights are at stake: it’s time to reclaim freedom of expression\n21 Feb 2025\n\nOur rights are at stake: it’s time to reclaim freedom of expression\n\n\n\n\n\n\n\n\n\n\t\t\t\t\tContent Governance\t\t\t\t\n\n\n\n\nContent Governance \n\n\n\t\t\t\tPoised to take over TikTok, Oracle is accused of clamping down on Pro-Palestine dissent\t\t\t\n\n19 Feb 2025\n\n\n\n\nNews\nPoised to take over TikTok, Oracle is accused of clamping down on Pro-Palestine dissent\n\n\t\t\t\t\t\t\t\t\tThe Intercept ↗\t\t\t\t\t\t\t\n↗\n19 Feb 2025\n\nPoised to take over TikTok, Oracle is accused of clamping down on Pro-Palestine dissent\n\n\n\n\n\n\n\n\n\n\t\t\t\t\tContent Governance\t\t\t\t\n\n\n\n\nContent Governance \n\n\n\t\t\t\tTamil website Vikatan inaccessible after It posted cartoon of PM, no official takedown order confirmed\t\t\t\n\n19 Feb 2025\n\n\n\n\nNews\nTamil website Vikatan inaccessible after It posted cartoon of PM, no official takedown order confirmed\n\n\t\t\t\t\t\t\t\t\tMedianama ↗\t\t\t\t\t\t\t\n↗\n19 Feb 2025\n\nTamil website Vikatan inaccessible after It posted cartoon of PM, no official takedown order confirmed\n\n\n\n\n\n\n\n\n\n\t\t\t\t\tInternet Shutdowns\t\t\t\t\n\n\n\n\nInternet Shutdowns \n\n\n\t\t\t\t2025 elections and internet shutdowns watch\t\t\t\n\n30 Jan 2025\n • \nGovernments around the world continue to shut down the internet during elections. Join our 2025 elections watch to #KeepItOn.\n\n\n\n\nCampaign\n2025 elections and internet shutdowns watch\n30 Jan 2025\n\n2025 elections and internet shutdowns watch\n\n\n\n\n\n\n\n\n\n\t\t\t\t\tContent Governance\t\t\t\t\n\n\n\n\nContent Governance \n\n\n\t\t\t\tTrump stand on online speech divides free speech ecosystem\t\t\t\n\n22 Jan 2025\n\n\n\n\nNews\nTrump stand on online speech divides free speech ecosystem\n\n\t\t\t\t\t\t\t\t\tHindu Businessline ↗\t\t\t\t\t\t\t\n↗\n22 Jan 2025\n\nTrump stand on online speech divides free speech ecosystem\n\n\n\n\n\n\n\n\n\n\t\t\t\t\tFreedom of Expression\t\t\t\t\n\n\n\n\nFreedom of Expression \n\n\n\t\t\t\tCeasefire in Gaza: it’s time to end digital harms and deliver justice\t\t\t\n\n20 Jan 2025\n • \nAs physical violence appears to be coming to a halt after 15 months in Gaza, Access Now further calls for a digital ceasefire.\n\n\n\n\nPress Release\nCeasefire in Gaza: it’s time to end digital harms and deliver justice\n20 Jan 2025\n\nCeasefire in Gaza: it’s time to end digital harms and deliver justice\n\n\n\n\n\n\n\n\n\n\t\t\t\t\tContent Governance\t\t\t\t\n\n\n\n\nContent Governance \n\n\n\t\t\t\tMetino ukidanje provjere činjenica ‘politička odluka sa stvarnim posljedicama’\t\t\t\n\n20 Jan 2025\n\n\n\n\nNews\nMetino ukidanje provjere činjenica ‘politička odluka sa stvarnim posljedicama’\n\n\t\t\t\t\t\t\t\t\tRadio Free Europe ↗\t\t\t\t\t\t\t\n↗\n20 Jan 2025\n\nMetino ukidanje provjere činjenica ‘politička odluka sa stvarnim posljedicama’\n\n\n\n\n\n\n\n\n\n\t\t\t\t\tFreedom of Expression\t\t\t\t\n\n\n\n\nFreedom of Expression \n\n\n\t\t\t\tTackling the “black snakes” undermining digital rights worldwide \t\t\t\n\n16 Jan 2025\n • \nAs 2025 gets underway, Access Now’s new Executive Director, Alejandro Mayoral Baños, PhD, shares his reflections on the “black snakes” threatening the digital rights movement. \n\n\n\n\nPost\nTackling the “black snakes” undermining digital rights worldwide \n16 Jan 2025\n\nTackling the “black snakes” undermining digital rights worldwide \n\n\n\n\n\n\n\n\n\n\t\t\t\t\tContent Governance\t\t\t\t\n\n\n\n\nContent Governance \n\n\n\t\t\t\tWhy Facebook ending fact checking in US is a warning sign for India\t\t\t\n\n14 Jan 2025\n\n\n\n\nNews\nWhy Facebook ending fact checking in US is a warning sign for India\n\n\t\t\t\t\t\t\t\t\tScroll ↗\t\t\t\t\t\t\t\n↗\n14 Jan 2025\n\nWhy Facebook ending fact checking in US is a warning sign for India\n\n\n\n\n\n\n\n\n\n\t\t\t\t\tContent Governance\t\t\t\t\n\n\n\n\nContent Governance \n\n\n\t\t\t\tEU regulators take a hard look at Elon Musk and X\t\t\t\n\n14 Jan 2025\n\n\n\n\nNews\nEU regulators take a hard look at Elon Musk and X\n\n\t\t\t\t\t\t\t\t\tDeutsche Welle ↗\t\t\t\t\t\t\t\n↗\n14 Jan 2025\n\nEU regulators take a hard look at Elon Musk and X\n\n\n\n\n\n\n\n\n\n\t\t\t\t\tContent Governance\t\t\t\t\n\n\n\n\nContent Governance \n\n\n\t\t\t\tPlatform accountability: a rule-of-law checklist for policymakers\t\t\t\n\n13 Jan 2025\n • \nIn this report, Access Now proposes a rule-of-law checklist to enable states to enact platform accountability regulations that are fit for purpose and protect human rights.\n\n\n\n\nPublication\nPlatform accountability: a rule-of-law checklist for policymakers\n\n\n↗\n13 Jan 2025\n\nPlatform accountability: a rule-of-law checklist for policymakers\n\n\n\n\n\n\n\n\n\n\t\t\t\t\tContent Governance\t\t\t\t\n\n\n\n\nContent Governance \n\n\n\t\t\t\tPlatform accountability and human rights: a rule-of-law checklist\t\t\t\n\n13 Jan 2025\n • \nAs policymakers around the world seek to rein in Big Tech, we define the safeguards necessary to ensure rule of law and protect human rights and democracy.\n\n\n\n\nPost\nPlatform accountability and human rights: a rule-of-law checklist\n13 Jan 2025\n\nPlatform accountability and human rights: a rule-of-law checklist\n\n\n\n\n\n\n\n\n\n\t\t\t\t\tContent Governance\t\t\t\t\n\n\n\n\nContent Governance \n\n\n\t\t\t\tGlobal fact-checkers were disappointed, not surprised, Meta ended its program\t\t\t\n\n10 Jan 2025\n\n\n\n\nNews\nGlobal fact-checkers were disappointed, not surprised, Meta ended its program\n\n\t\t\t\t\t\t\t\t\tRest of World ↗\t\t\t\t\t\t\t\n↗\n10 Jan 2025\n\nGlobal fact-checkers were disappointed, not surprised, Meta ended its program\n\n\n\n\n\n\n\n\n\n\t\t\t\t\tContent Governance\t\t\t\t\n\n\n\n\nContent Governance \n\n\n\t\t\t\tBrussels will be watching whether Musk breaks EU law in far-right livestream\t\t\t\n\n9 Jan 2025\n\n\n\n\nNews\nBrussels will be watching whether Musk breaks EU law in far-right livestream\n\n\t\t\t\t\t\t\t\t\tPOLITICO ↗\t\t\t\t\t\t\t\n↗\n9 Jan 2025\n\nBrussels will be watching whether Musk breaks EU law in far-right livestream\n\nRights-Based Approaches to Online Content\n\n\n\nGovernments and companies are under increasing pressure to address illegal or undesirable content and expression online, but hasty or poorly crafted solutions threaten human rights. We advocate for policies and practices to defend free expression and access to information and  ensure people who are most at risk are protected.\n\n\n\n\n\n\n\n\n\n\n\n\nPlatform Accountability: a rule-of-law checklist for policymakers\nPlatform regulations can be a minefield for human rights. Here’s a checklist to help policymakers examine the need for platform regulations, and where necessary, enact regulations that are fit-for-purpose and protect human rights. \n\nLearn more\n\n\n\n\n\nResources\n\n\n\n\n\n\n\n\n\n\n\n\n\nContent Governance\n\n\n\t\t\t\n\t\t\t\tOur rights are at stake: it’s time to reclaim freedom of expression\n\t\t\t\t\t\t\t\n\n\nGiven the escalating use of free speech claims as a shield for inciting hatred and violence, it is more urgent than ever to reaffirm what freedom of expression truly stands for. \n\n\n\n\n\n\n\n\n\n\n\n\n\nContent Governance\n\n\n\t\t\t\n\t\t\t\tContent governance in times of crisis: how platforms can protect human rights\n\t\t\t\t\t\t\t\n\n\nThe “Declaration for content and platform governance principles in times of crisis” lays out principles for social media platforms to help ensure privacy, freedom of expression, and access to information during crises.\n\n\n\n\n\n\n\n\n\n\n\n\n\nContent Governance\n\n\n\t\t\t\n\t\t\t\tRainbow-burning: how social media companies increase risks for LGBTQ+ people in Africa\n\t\t\t\t\t\t\t\n\n\nColonial-era laws and a global anti-rights movement are fueling LGBTQ+ repression across Africa. Access Now documented 214 threats on platforms like TikTok, X, Facebook, YouTube, and WhatsApp, underscoring widespread risks.\n\n\n\n\n\n\n\n\n\n\n\n\n\nContent Governance\n\n\n\t\t\t\n\t\t\t\tGuide: how to protect human rights in content governance\n\t\t\t\t\t\t\t\n\n\nWe offer 26 recommendations on content governance to help lawmakers, regulators, and company leaders make decisions that will safeguard human rights.\n\n\n\n\n\n\n\n\n\n\n\n\n\n\n\n\n\n\n\n\n\nContent Governance\n\n\n\t\t\t\n\t\t\t\tDigital Security Helpline: our approach to content-related cases\n\t\t\t\t\t\t\t\n\n\nCritical voices from civil society are being censored. Here’s how the Digital Security Helpline addresses cases related to content governance.\n\n\n\n\n\n\n\n\n\n\n\n\n\nContent Governance\n\n\n\t\t\t\n\t\t\t\tWhat is disinformation, why it spreads, and how to stop it\n\t\t\t\t\t\t\t\n\n\nOur new report explores what disinformation is, and how lawmakers can address the harms it poses to democracy.\n\n\n\n\n\n\n\n\n\n\n\n\n\nContent Governance\n\n\n\t\t\t\n\t\t\t\tThe Digital Services Act: your guide to the EU’s new content moderation rules\n\t\t\t\t\t\t\t\n\n\nThe EU Digital Services Act has finally arrived. We unpack what this law contains and the changes people can expect to see from 2024 onwards.\n\n\n\n\n\n\n\n\n\n\n\n\n\nContent Governance\n\n\n\t\t\t\n\t\t\t\tAccess Now releases “Fighting misinformation and defending free expression during COVID-19: recommendations for states”\n\t\t\t\t\t\t\t\n\n\nWe have identified practical examples and promising practices to support policy makers in respecting human rights while developing measures to address disinformation and misinformation during the COVID-19 crisis.\n\n\n\n\n\n\n\n\n\n\n\n\n\n\nLatest Updates\n\n\n\n     \n\n\n\n\n\nGrid View\nList View\n\n\n\n\n\n\n\n\n\n\n\n\n\n\t\t\t\t\tContent Governance\t\t\t\t\n\n\n\n\nContent Governance \n\n\n\t\t\t\t‘Profiting from misery’: how TikTok makes money from child begging livestreams\t\t\t\n\n6 Apr 2025\n\n\n\n\nNews\n‘Profiting from misery’: how TikTok makes money from child begging livestreams\n\n\t\t\t\t\t\t\t\t\tThe Guardian ↗\t\t\t\t\t\t\t\n↗\n6 Apr 2025\n\n‘Profiting from misery’: how TikTok makes money from child begging livestreams\n\n\n\n\n \n\t\t\t\t\tInternet Shutdowns\t\t\t\t\n\n\n\n\nInternet Shutdowns \n\n\n\t\t\t\tEmboldened offenders, endangered communities: internet shutdowns in 2024\t\t\t\n\n23 Feb 2025\n • \nAccess Now and the #KeepItOn coalition documented 296 internet shutdowns in 2024 — the highest number since 2016.\n\n\n\n\nPublication\nEmboldened offenders, endangered communities: internet shutdowns in 2024\n\n\n↗\n23 Feb 2025\n\nEmboldened offenders, endangered communities: internet shutdowns in 2024\n\n\n\n\n\n\n\n\n\n\t\t\t\t\tFreedom of Expression\t\t\t\t\n\n\n\n\nFreedom of Expression \n\n\n\t\t\t\tOur rights are at stake: it’s time to reclaim freedom of expression\t\t\t\n\n21 Feb 2025\n • \nGiven the escalating use of free speech claims as a shield for inciting hatred and violence, it is more urgent than ever to reaffirm what freedom of expression truly stands for. \n\n\n\n\nPress Release\nOur rights are at stake: it’s time to reclaim freedom of expression\n21 Feb 2025\n\nOur rights are at stake: it’s time to reclaim freedom of expression\n\n\n\n\n\n\n\n\n\n\t\t\t\t\tContent Governance\t\t\t\t\n\n\n\n\nContent Governance \n\n\n\t\t\t\tPoised to take over TikTok, Oracle is accused of clamping down on Pro-Palestine dissent\t\t\t\n\n19 Feb 2025\n\n\n\n\nNews\nPoised to take over TikTok, Oracle is accused of clamping down on Pro-Palestine dissent\n\n\t\t\t\t\t\t\t\t\tThe Intercept ↗\t\t\t\t\t\t\t\n↗\n19 Feb 2025\n\nPoised to take over TikTok, Oracle is accused of clamping down on Pro-Palestine dissent\n\n\n\n\n\n\n\n\n\n\t\t\t\t\tContent Governance\t\t\t\t\n\n\n\n\nContent Governance \n\n\n\t\t\t\tTamil website Vikatan inaccessible after It posted cartoon of PM, no official takedown order confirmed\t\t\t\n\n19 Feb 2025\n\n\n\n\nNews\nTamil website Vikatan inaccessible after It posted cartoon of PM, no official takedown order confirmed\n\n\t\t\t\t\t\t\t\t\tMedianama ↗\t\t\t\t\t\t\t\n↗\n19 Feb 2025\n\nTamil website Vikatan inaccessible after It posted cartoon of PM, no official takedown order confirmed\n\n\n\n\n\n\n\n\n\n\t\t\t\t\tInternet Shutdowns\t\t\t\t\n\n\n\n\nInternet Shutdowns \n\n\n\t\t\t\t2025 elections and internet shutdowns watch\t\t\t\n\n30 Jan 2025\n • \nGovernments around the world continue to shut down the internet during elections. Join our 2025 elections watch to #KeepItOn.\n\n\n\n\nCampaign\n2025 elections and internet shutdowns watch\n30 Jan 2025\n\n2025 elections and internet shutdowns watch\n\n\n\n\n\n\n\n\n\n\t\t\t\t\tContent Governance\t\t\t\t\n\n\n\n\nContent Governance \n\n\n\t\t\t\tTrump stand on online speech divides free speech ecosystem\t\t\t\n\n22 Jan 2025\n\n\n\n\nNews\nTrump stand on online speech divides free speech ecosystem\n\n\t\t\t\t\t\t\t\t\tHindu Businessline ↗\t\t\t\t\t\t\t\n↗\n22 Jan 2025\n\nTrump stand on online speech divides free speech ecosystem\n\n\n\n\n\n\n\n\n\n\t\t\t\t\tFreedom of Expression\t\t\t\t\n\n\n\n\nFreedom of Expression \n\n\n\t\t\t\tCeasefire in Gaza: it’s time to end digital harms and deliver justice\t\t\t\n\n20 Jan 2025\n • \nAs physical violence appears to be coming to a halt after 15 months in Gaza, Access Now further calls for a digital ceasefire.\n\n\n\n\nPress Release\nCeasefire in Gaza: it’s time to end digital harms and deliver justice\n20 Jan 2025\n\nCeasefire in Gaza: it’s time to end digital harms and deliver justice\n\n\n\n\n\n\n\n\n\n\t\t\t\t\tContent Governance\t\t\t\t\n\n\n\n\nContent Governance \n\n\n\t\t\t\tMetino ukidanje provjere činjenica ‘politička odluka sa stvarnim posljedicama’\t\t\t\n\n20 Jan 2025\n\n\n\n\nNews\nMetino ukidanje provjere činjenica ‘politička odluka sa stvarnim posljedicama’\n\n\t\t\t\t\t\t\t\t\tRadio Free Europe ↗\t\t\t\t\t\t\t\n↗\n20 Jan 2025\n\nMetino ukidanje provjere činjenica ‘politička odluka sa stvarnim posljedicama’\n\n\n\n\n\n\n\n\n\n\t\t\t\t\tFreedom of Expression\t\t\t\t\n\n\n\n\nFreedom of Expression \n\n\n\t\t\t\tTackling the “black snakes” undermining digital rights worldwide \t\t\t\n\n16 Jan 2025\n • \nAs 2025 gets underway, Access Now’s new Executive Director, Alejandro Mayoral Baños, PhD, shares his reflections on the “black snakes” threatening the digital rights movement. \n\n\n\n\nPost\nTackling the “black snakes” undermining digital rights worldwide \n16 Jan 2025\n\nTackling the “black snakes” undermining digital rights worldwide \n\n\n\n\n\n\n\n\n\n\t\t\t\t\tContent Governance\t\t\t\t\n\n\n\n\nContent Governance \n\n\n\t\t\t\tWhy Facebook ending fact checking in US is a warning sign for India\t\t\t\n\n14 Jan 2025\n\n\n\n\nNews\nWhy Facebook ending fact checking in US is a warning sign for India\n\n\t\t\t\t\t\t\t\t\tScroll ↗\t\t\t\t\t\t\t\n↗\n14 Jan 2025\n\nWhy Facebook ending fact checking in US is a warning sign for India\n\n\n\n\n\n\n\n\n\n\t\t\t\t\tContent Governance\t\t\t\t\n\n\n\n\nContent Governance \n\n\n\t\t\t\tEU regulators take a hard look at Elon Musk and X\t\t\t\n\n14 Jan 2025\n\n\n\n\nNews\nEU regulators take a hard look at Elon Musk and X\n\n\t\t\t\t\t\t\t\t\tDeutsche Welle ↗\t\t\t\t\t\t\t\n↗\n14 Jan 2025\n\nEU regulators take a hard look at Elon Musk and X\n\n\n\n\n\n\n\n\n\n\t\t\t\t\tContent Governance\t\t\t\t\n\n\n\n\nContent Governance \n\n\n\t\t\t\tPlatform accountability: a rule-of-law checklist for policymakers\t\t\t\n\n13 Jan 2025\n • \nIn this report, Access Now proposes a rule-of-law checklist to enable states to enact platform accountability regulations that are fit for purpose and protect human rights.\n\n\n\n\nPublication\nPlatform accountability: a rule-of-law checklist for policymakers\n\n\n↗\n13 Jan 2025\n\nPlatform accountability: a rule-of-law checklist for policymakers\n\n\n\n\n\n\n\n\n\n\t\t\t\t\tContent Governance\t\t\t\t\n\n\n\n\nContent Governance \n\n\n\t\t\t\tPlatform accountability and human rights: a rule-of-law checklist\t\t\t\n\n13 Jan 2025\n • \nAs policymakers around the world seek to rein in Big Tech, we define the safeguards necessary to ensure rule of law and protect human rights and democracy.\n\n\n\n\nPost\nPlatform accountability and human rights: a rule-of-law checklist\n13 Jan 2025\n\nPlatform accountability and human rights: a rule-of-law checklist\n\n\n\n\n\n\n\n\n\n\t\t\t\t\tContent Governance\t\t\t\t\n\n\n\n\nContent Governance \n\n\n\t\t\t\tGlobal fact-checkers were disappointed, not surprised, Meta ended its program\t\t\t\n\n10 Jan 2025\n\n\n\n\nNews\nGlobal fact-checkers were disappointed, not surprised, Meta ended its program\n\n\t\t\t\t\t\t\t\t\tRest of World ↗\t\t\t\t\t\t\t\n↗\n10 Jan 2025\n\nGlobal fact-checkers were disappointed, not surprised, Meta ended its program\n\n\n\n\n\n\n\n\n\n\t\t\t\t\tContent Governance\t\t\t\t\n\n\n\n\nContent Governance \n\n\n\t\t\t\tBrussels will be watching whether Musk breaks EU law in far-right livestream\t\t\t\n\n9 Jan 2025\n\n\n\n\nNews\nBrussels will be watching whether Musk breaks EU law in far-right livestream\n\n\t\t\t\t\t\t\t\t\tPOLITICO ↗\t\t\t\t\t\t\t\n↗\n9 Jan 2025\n\nBrussels will be watching whether Musk breaks EU law in far-right livestream\n\nRights-Based Approaches to Online Content\n\n\n\nGovernments and companies are under increasing pressure to address illegal or undesirable content and expression online, but hasty or poorly crafted solutions threaten human rights. We advocate for policies and practices to defend free expression and access to information and  ensure people who are most at risk are protected.\n\n\n\n\n\n\n\n\n\n\n\n\nPlatform Accountability: a rule-of-law checklist for policymakers\nPlatform regulations can be a minefield for human rights. Here’s a checklist to help policymakers examine the need for platform regulations, and where necessary, enact regulations that are fit-for-purpose and protect human rights. \n\nLearn more\n\n\n\n\n\nResources\n\n\n\n\n\n\n\n\n\n\n\n\n\nContent Governance\n\n\n\t\t\t\n\t\t\t\tOur rights are at stake: it’s time to reclaim freedom of expression\n\t\t\t\t\t\t\t\n\n\nGiven the escalating use of free speech claims as a shield for inciting hatred and violence, it is more urgent than ever to reaffirm what freedom of expression truly stands for. \n\n\n\n\n\n\n\n\n\n\n\n\n\nContent Governance\n\n\n\t\t\t\n\t\t\t\tContent governance in times of crisis: how platforms can protect human rights\n\t\t\t\t\t\t\t\n\n\nThe “Declaration for content and platform governance principles in times of crisis” lays out principles for social media platforms to help ensure privacy, freedom of expression, and access to information during crises.\n\n\n\n\n\n\n\n\n\n\n\n\n\nContent Governance\n\n\n\t\t\t\n\t\t\t\tRainbow-burning: how social media companies increase risks for LGBTQ+ people in Africa\n\t\t\t\t\t\t\t\n\n\nColonial-era laws and a global anti-rights movement are fueling LGBTQ+ repression across Africa. Access Now documented 214 threats on platforms like TikTok, X, Facebook, YouTube, and WhatsApp, underscoring widespread risks.\n\n\n\n\n\n\n\n\n\n\n\n\n\nContent Governance\n\n\n\t\t\t\n\t\t\t\tGuide: how to protect human rights in content governance\n\t\t\t\t\t\t\t\n\n\nWe offer 26 recommendations on content governance to help lawmakers, regulators, and company leaders make decisions that will safeguard human rights.\n\n\n\n\n\n\n\n\n\n\n\n\n\n\n\n\n\n\n\n\n\nContent Governance\n\n\n\t\t\t\n\t\t\t\tDigital Security Helpline: our approach to content-related cases\n\t\t\t\t\t\t\t\n\n\nCritical voices from civil society are being censored. Here’s how the Digital Security Helpline addresses cases related to content governance.\n\n\n\n\n\n\n\n\n\n\n\n\n\nContent Governance\n\n\n\t\t\t\n\t\t\t\tWhat is disinformation, why it spreads, and how to stop it\n\t\t\t\t\t\t\t\n\n\nOur new report explores what disinformation is, and how lawmakers can address the harms it poses to democracy.\n\n\n\n\n\n\n\n\n\n\n\n\n\nContent Governance\n\n\n\t\t\t\n\t\t\t\tThe Digital Services Act: your guide to the EU’s new content moderation rules\n\t\t\t\t\t\t\t\n\n\nThe EU Digital Services Act has finally arrived. We unpack what this law contains and the changes people can expect to see from 2024 onwards.\n\n\n\n\n\n\n\n\n\n\n\n\n\nContent Governance\n\n\n\t\t\t\n\t\t\t\tAccess Now releases “Fighting misinformation and defending free expression during COVID-19: recommendations for states”\n\t\t\t\t\t\t\t\n\n\nWe have identified practical examples and promising practices to support policy makers in respecting human rights while developing measures to address disinformation and misinformation during the COVID-19 crisis.\n\n\n\n\n\n\n\n\n\n\n\n\n\n\nLatest Updates\n\n\n\n     \n\n\n\n\n\nGrid View\nList View\n\n\n\n\n\n\n\n\n\n\n\n\n\n\t\t\t\t\tContent Governance\t\t\t\t\n\n\n\n\nContent Governance \n\n\n\t\t\t\t‘Profiting from misery’: how TikTok makes money from child begging livestreams\t\t\t\n\n6 Apr 2025\n\n\n\n\nNews\n‘Profiting from misery’: how TikTok makes money from child begging livestreams\n\n\t\t\t\t\t\t\t\t\tThe Guardian ↗\t\t\t\t\t\t\t\n↗\n6 Apr 2025\n\n‘Profiting from misery’: how TikTok makes money from child begging livestreams\n\n\n\n\n \n\t\t\t\t\tInternet Shutdowns\t\t\t\t\n\n\n\n\nInternet Shutdowns \n\n\n\t\t\t\tEmboldened offenders, endangered communities: internet shutdowns in 2024\t\t\t\n\n23 Feb 2025\n • \nAccess Now and the #KeepItOn coalition documented 296 internet shutdowns in 2024 — the highest number since 2016.\n\n\n\n\nPublication\nEmboldened offenders, endangered communities: internet shutdowns in 2024\n\n\n↗\n23 Feb 2025\n\nEmboldened offenders, endangered communities: internet shutdowns in 2024\n\n\n\n\n\n\n\n\n\n\t\t\t\t\tFreedom of Expression\t\t\t\t\n\n\n\n\nFreedom of Expression \n\n\n\t\t\t\tOur rights are at stake: it’s time to reclaim freedom of expression\t\t\t\n\n21 Feb 2025\n • \nGiven the escalating use of free speech claims as a shield for inciting hatred and violence, it is more urgent than ever to reaffirm what freedom of expression truly stands for. \n\n\n\n\nPress Release\nOur rights are at stake: it’s time to reclaim freedom of expression\n21 Feb 2025\n\nOur rights are at stake: it’s time to reclaim freedom of expression\n\n\n\n\n\n\n\n\n\n\t\t\t\t\tContent Governance\t\t\t\t\n\n\n\n\nContent Governance \n\n\n\t\t\t\tPoised to take over TikTok, Oracle is accused of clamping down on Pro-Palestine dissent\t\t\t\n\n19 Feb 2025\n\n\n\n\nNews\nPoised to take over TikTok, Oracle is accused of clamping down on Pro-Palestine dissent\n\n\t\t\t\t\t\t\t\t\tThe Intercept ↗\t\t\t\t\t\t\t\n↗\n19 Feb 2025\n\nPoised to take over TikTok, Oracle is accused of clamping down on Pro-Palestine dissent\n\n\n\n\n\n\n\n\n\n\t\t\t\t\tContent Governance\t\t\t\t\n\n\n\n\nContent Governance \n\n\n\t\t\t\tTamil website Vikatan inaccessible after It posted cartoon of PM, no official takedown order confirmed\t\t\t\n\n19 Feb 2025\n\n\n\n\nNews\nTamil website Vikatan inaccessible after It posted cartoon of PM, no official takedown order confirmed\n\n\t\t\t\t\t\t\t\t\tMedianama ↗\t\t\t\t\t\t\t\n↗\n19 Feb 2025\n\nTamil website Vikatan inaccessible after It posted cartoon of PM, no official takedown order confirmed\n\n\n\n\n\n\n\n\n\n\t\t\t\t\tInternet Shutdowns\t\t\t\t\n\n\n\n\nInternet Shutdowns \n\n\n\t\t\t\t2025 elections and internet shutdowns watch\t\t\t\n\n30 Jan 2025\n • \nGovernments around the world continue to shut down the internet during elections. Join our 2025 elections watch to #KeepItOn.\n\n\n\n\nCampaign\n2025 elections and internet shutdowns watch\n30 Jan 2025\n\n2025 elections and internet shutdowns watch\n\n\n\n\n\n\n\n\n\n\t\t\t\t\tContent Governance\t\t\t\t\n\n\n\n\nContent Governance \n\n\n\t\t\t\tTrump stand on online speech divides free speech ecosystem\t\t\t\n\n22 Jan 2025\n\n\n\n\nNews\nTrump stand on online speech divides free speech ecosystem\n\n\t\t\t\t\t\t\t\t\tHindu Businessline ↗\t\t\t\t\t\t\t\n↗\n22 Jan 2025\n\nTrump stand on online speech divides free speech ecosystem\n\n\n\n\n\n\n\n\n\n\t\t\t\t\tFreedom of Expression\t\t\t\t\n\n\n\n\nFreedom of Expression \n\n\n\t\t\t\tCeasefire in Gaza: it’s time to end digital harms and deliver justice\t\t\t\n\n20 Jan 2025\n • \nAs physical violence appears to be coming to a halt after 15 months in Gaza, Access Now further calls for a digital ceasefire.\n\n\n\n\nPress Release\nCeasefire in Gaza: it’s time to end digital harms and deliver justice\n20 Jan 2025\n\nCeasefire in Gaza: it’s time to end digital harms and deliver justice\n\n\n\n\n\n\n\n\n\n\t\t\t\t\tContent Governance\t\t\t\t\n\n\n\n\nContent Governance \n\n\n\t\t\t\tMetino ukidanje provjere činjenica ‘politička odluka sa stvarnim posljedicama’\t\t\t\n\n20 Jan 2025\n\n\n\n\nNews\nMetino ukidanje provjere činjenica ‘politička odluka sa stvarnim posljedicama’\n\n\t\t\t\t\t\t\t\t\tRadio Free Europe ↗\t\t\t\t\t\t\t\n↗\n20 Jan 2025\n\nMetino ukidanje provjere činjenica ‘politička odluka sa stvarnim posljedicama’\n\n\n\n\n\n\n\n\n\n\t\t\t\t\tFreedom of Expression\t\t\t\t\n\n\n\n\nFreedom of Expression \n\n\n\t\t\t\tTackling the “black snakes” undermining digital rights worldwide \t\t\t\n\n16 Jan 2025\n • \nAs 2025 gets underway, Access Now’s new Executive Director, Alejandro Mayoral Baños, PhD, shares his reflections on the “black snakes” threatening the digital rights movement. \n\n\n\n\nPost\nTackling the “black snakes” undermining digital rights worldwide \n16 Jan 2025\n\nTackling the “black snakes” undermining digital rights worldwide \n\n\n\n\n\n\n\n\n\n\t\t\t\t\tContent Governance\t\t\t\t\n\n\n\n\nContent Governance \n\n\n\t\t\t\tWhy Facebook ending fact checking in US is a warning sign for India\t\t\t\n\n14 Jan 2025\n\n\n\n\nNews\nWhy Facebook ending fact checking in US is a warning sign for India\n\n\t\t\t\t\t\t\t\t\tScroll ↗\t\t\t\t\t\t\t\n↗\n14 Jan 2025\n\nWhy Facebook ending fact checking in US is a warning sign for India\n\n\n\n\n\n\n\n\n\n\t\t\t\t\tContent Governance\t\t\t\t\n\n\n\n\nContent Governance \n\n\n\t\t\t\tEU regulators take a hard look at Elon Musk and X\t\t\t\n\n14 Jan 2025\n\n\n\n\nNews\nEU regulators take a hard look at Elon Musk and X\n\n\t\t\t\t\t\t\t\t\tDeutsche Welle ↗\t\t\t\t\t\t\t\n↗\n14 Jan 2025\n\nEU regulators take a hard look at Elon Musk and X\n\n\n\n\n\n\n\n\n\n\t\t\t\t\tContent Governance\t\t\t\t\n\n\n\n\nContent Governance \n\n\n\t\t\t\tPlatform accountability: a rule-of-law checklist for policymakers\t\t\t\n\n13 Jan 2025\n • \nIn this report, Access Now proposes a rule-of-law checklist to enable states to enact platform accountability regulations that are fit for purpose and protect human rights.\n\n\n\n\nPublication\nPlatform accountability: a rule-of-law checklist for policymakers\n\n\n↗\n13 Jan 2025\n\nPlatform accountability: a rule-of-law checklist for policymakers\n\n\n\n\n\n\n\n\n\n\t\t\t\t\tContent Governance\t\t\t\t\n\n\n\n\nContent Governance \n\n\n\t\t\t\tPlatform accountability and human rights: a rule-of-law checklist\t\t\t\n\n13 Jan 2025\n • \nAs policymakers around the world seek to rein in Big Tech, we define the safeguards necessary to ensure rule of law and protect human rights and democracy.\n\n\n\n\nPost\nPlatform accountability and human rights: a rule-of-law checklist\n13 Jan 2025\n\nPlatform accountability and human rights: a rule-of-law checklist\n\n\n\n\n\n\n\n\n\n\t\t\t\t\tContent Governance\t\t\t\t\n\n\n\n\nContent Governance \n\n\n\t\t\t\tGlobal fact-checkers were disappointed, not surprised, Meta ended its program\t\t\t\n\n10 Jan 2025\n\n\n\n\nNews\nGlobal fact-checkers were disappointed, not surprised, Meta ended its program\n\n\t\t\t\t\t\t\t\t\tRest of World ↗\t\t\t\t\t\t\t\n↗\n10 Jan 2025\n\nGlobal fact-checkers were disappointed, not surprised, Meta ended its program\n\n\n\n\n\n\n\n\n\n\t\t\t\t\tContent Governance\t\t\t\t\n\n\n\n\nContent Governance \n\n\n\t\t\t\tBrussels will be watching whether Musk breaks EU law in far-right livestream\t\t\t\n\n9 Jan 2025\n\n\n\n\nNews\nBrussels will be watching whether Musk breaks EU law in far-right livestream\n\n\t\t\t\t\t\t\t\t\tPOLITICO ↗\t\t\t\t\t\t\t\n↗\n9 Jan 2025\n\nBrussels will be watching whether Musk breaks EU law in far-right livestream\n\nRights-Based Approaches to Online Content\n\n\n\nGovernments and companies are under increasing pressure to address illegal or undesirable content and expression online, but hasty or poorly crafted solutions threaten human rights. We advocate for policies and practices to defend free expression and access to information and  ensure people who are most at risk are protected.\n\n\n\n\n\n\n\n\n\n\n\n\nPlatform Accountability: a rule-of-law checklist for policymakers\nPlatform regulations can be a minefield for human rights. Here’s a checklist to help policymakers examine the need for platform regulations, and where necessary, enact regulations that are fit-for-purpose and protect human rights. \n\nLearn more\n\n\n\n\n\nResources\n\n\n\n\n\n\n\n\n\n\n\n\n\nContent Governance\n\n\n\t\t\t\n\t\t\t\tOur rights are at stake: it’s time to reclaim freedom of expression\n\t\t\t\t\t\t\t\n\n\nGiven the escalating use of free speech claims as a shield for inciting hatred and violence, it is more urgent than ever to reaffirm what freedom of expression truly stands for. \n\n\n\n\n\n\n\n\n\n\n\n\n\nContent Governance\n\n\n\t\t\t\n\t\t\t\tContent governance in times of crisis: how platforms can protect human rights\n\t\t\t\t\t\t\t\n\n\nThe “Declaration for content and platform governance principles in times of crisis” lays out principles for social media platforms to help ensure privacy, freedom of expression, and access to information during crises.\n\n\n\n\n\n\n\n\n\n\n\n\n\nContent Governance\n\n\n\t\t\t\n\t\t\t\tRainbow-burning: how social media companies increase risks for LGBTQ+ people in Africa\n\t\t\t\t\t\t\t\n\n\nColonial-era laws and a global anti-rights movement are fueling LGBTQ+ repression across Africa. Access Now documented 214 threats on platforms like TikTok, X, Facebook, YouTube, and WhatsApp, underscoring widespread risks.\n\n\n\n\n\n\n\n\n\n\n\n\n\nContent Governance\n\n\n\t\t\t\n\t\t\t\tGuide: how to protect human rights in content governance\n\t\t\t\t\t\t\t\n\n\nWe offer 26 recommendations on content governance to help lawmakers, regulators, and company leaders make decisions that will safeguard human rights.\n\n\n\n\n\n\n\n\n\n\n\n\n\n\n\n\n\n\n\n\n\nContent Governance\n\n\n\t\t\t\n\t\t\t\tDigital Security Helpline: our approach to content-related cases\n\t\t\t\t\t\t\t\n\n\nCritical voices from civil society are being censored. Here’s how the Digital Security Helpline addresses cases related to content governance.\n\n\n\n\n\n\n\n\n\n\n\n\n\nContent Governance\n\n\n\t\t\t\n\t\t\t\tWhat is disinformation, why it spreads, and how to stop it\n\t\t\t\t\t\t\t\n\n\nOur new report explores what disinformation is, and how lawmakers can address the harms it poses to democracy.\n\n\n\n\n\n\n\n\n\n\n\n\n\nContent Governance\n\n\n\t\t\t\n\t\t\t\tThe Digital Services Act: your guide to the EU’s new content moderation rules\n\t\t\t\t\t\t\t\n\n\nThe EU Digital Services Act has finally arrived. We unpack what this law contains and the changes people can expect to see from 2024 onwards.\n\n\n\n\n\n\n\n\n\n\n\n\n\nContent Governance\n\n\n\t\t\t\n\t\t\t\tAccess Now releases “Fighting misinformation and defending free expression during COVID-19: recommendations for states”\n\t\t\t\t\t\t\t\n\n\nWe have identified practical examples and promising practices to support policy makers in respecting human rights while developing measures to address disinformation and misinformation during the COVID-19 crisis.\n\n\n\n\n\n\n\n\n\n\n\n\n\n\nLatest Updates\n\n\n\n     \n\n\n\n\n\nGrid View\nList View\n\n\n\n\n\n\n\n\n\n\n\n\n\n\t\t\t\t\tContent Governance\t\t\t\t\n\n\n\n\nContent Governance \n\n\n\t\t\t\t‘Profiting from misery’: how TikTok makes money from child begging livestreams\t\t\t\n\n6 Apr 2025\n\n\n\n\nNews\n‘Profiting from misery’: how TikTok makes money from child begging livestreams\n\n\t\t\t\t\t\t\t\t\tThe Guardian ↗\t\t\t\t\t\t\t\n↗\n6 Apr 2025\n\n‘Profiting from misery’: how TikTok makes money from child begging livestreams\n\n\n\n\n \n\t\t\t\t\tInternet Shutdowns\t\t\t\t\n\n\n\n\nInternet Shutdowns \n\n\n\t\t\t\tEmboldened offenders, endangered communities: internet shutdowns in 2024\t\t\t\n\n23 Feb 2025\n • \nAccess Now and the #KeepItOn coalition documented 296 internet shutdowns in 2024 — the highest number since 2016.\n\n\n\n\nPublication\nEmboldened offenders, endangered communities: internet shutdowns in 2024\n\n\n↗\n23 Feb 2025\n\nEmboldened offenders, endangered communities: internet shutdowns in 2024\n\n\n\n\n\n\n\n\n\n\t\t\t\t\tFreedom of Expression\t\t\t\t\n\n\n\n\nFreedom of Expression \n\n\n\t\t\t\tOur rights are at stake: it’s time to reclaim freedom of expression\t\t\t\n\n21 Feb 2025\n • \nGiven the escalating use of free speech claims as a shield for inciting hatred and violence, it is more urgent than ever to reaffirm what freedom of expression truly stands for. \n\n\n\n\nPress Release\nOur rights are at stake: it’s time to reclaim freedom of expression\n21 Feb 2025\n\nOur rights are at stake: it’s time to reclaim freedom of expression\n\n\n\n\n\n\n\n\n\n\t\t\t\t\tContent Governance\t\t\t\t\n\n\n\n\nContent Governance \n\n\n\t\t\t\tPoised to take over TikTok, Oracle is accused of clamping down on Pro-Palestine dissent\t\t\t\n\n19 Feb 2025\n\n\n\n\nNews\nPoised to take over TikTok, Oracle is accused of clamping down on Pro-Palestine dissent\n\n\t\t\t\t\t\t\t\t\tThe Intercept ↗\t\t\t\t\t\t\t\n↗\n19 Feb 2025\n\nPoised to take over TikTok, Oracle is accused of clamping down on Pro-Palestine dissent\n\n\n\n\n\n\n\n\n\n\t\t\t\t\tContent Governance\t\t\t\t\n\n\n\n\nContent Governance \n\n\n\t\t\t\tTamil website Vikatan inaccessible after It posted cartoon of PM, no official takedown order confirmed\t\t\t\n\n19 Feb 2025\n\n\n\n\nNews\nTamil website Vikatan inaccessible after It posted cartoon of PM, no official takedown order confirmed\n\n\t\t\t\t\t\t\t\t\tMedianama ↗\t\t\t\t\t\t\t\n↗\n19 Feb 2025\n\nTamil website Vikatan inaccessible after It posted cartoon of PM, no official takedown order confirmed\n\n\n\n\n\n\n\n\n\n\t\t\t\t\tInternet Shutdowns\t\t\t\t\n\n\n\n\nInternet Shutdowns \n\n\n\t\t\t\t2025 elections and internet shutdowns watch\t\t\t\n\n30 Jan 2025\n • \nGovernments around the world continue to shut down the internet during elections. Join our 2025 elections watch to #KeepItOn.\n\n\n\n\nCampaign\n2025 elections and internet shutdowns watch\n30 Jan 2025\n\n2025 elections and internet shutdowns watch\n\n\n\n\n\n\n\n\n\n\t\t\t\t\tContent Governance\t\t\t\t\n\n\n\n\nContent Governance \n\n\n\t\t\t\tTrump stand on online speech divides free speech ecosystem\t\t\t\n\n22 Jan 2025\n\n\n\n\nNews\nTrump stand on online speech divides free speech ecosystem\n\n\t\t\t\t\t\t\t\t\tHindu Businessline ↗\t\t\t\t\t\t\t\n↗\n22 Jan 2025\n\nTrump stand on online speech divides free speech ecosystem\n\n\n\n\n\n\n\n\n\n\t\t\t\t\tFreedom of Expression\t\t\t\t\n\n\n\n\nFreedom of Expression \n\n\n\t\t\t\tCeasefire in Gaza: it’s time to end digital harms and deliver justice\t\t\t\n\n20 Jan 2025\n • \nAs physical violence appears to be coming to a halt after 15 months in Gaza, Access Now further calls for a digital ceasefire.\n\n\n\n\nPress Release\nCeasefire in Gaza: it’s time to end digital harms and deliver justice\n20 Jan 2025\n\nCeasefire in Gaza: it’s time to end digital harms and deliver justice\n\n\n\n\n\n\n\n\n\n\t\t\t\t\tContent Governance\t\t\t\t\n\n\n\n\nContent Governance \n\n\n\t\t\t\tMetino ukidanje provjere činjenica ‘politička odluka sa stvarnim posljedicama’\t\t\t\n\n20 Jan 2025\n\n\n\n\nNews\nMetino ukidanje provjere činjenica ‘politička odluka sa stvarnim posljedicama’\n\n\t\t\t\t\t\t\t\t\tRadio Free Europe ↗\t\t\t\t\t\t\t\n↗\n20 Jan 2025\n\nMetino ukidanje provjere činjenica ‘politička odluka sa stvarnim posljedicama’\n\n\n\n\n\n\n\n\n\n\t\t\t\t\tFreedom of Expression\t\t\t\t\n\n\n\n\nFreedom of Expression \n\n\n\t\t\t\tTackling the “black snakes” undermining digital rights worldwide \t\t\t\n\n16 Jan 2025\n • \nAs 2025 gets underway, Access Now’s new Executive Director, Alejandro Mayoral Baños, PhD, shares his reflections on the “black snakes” threatening the digital rights movement. \n\n\n\n\nPost\nTackling the “black snakes” undermining digital rights worldwide \n16 Jan 2025\n\nTackling the “black snakes” undermining digital rights worldwide \n\n\n\n\n\n\n\n\n\n\t\t\t\t\tContent Governance\t\t\t\t\n\n\n\n\nContent Governance \n\n\n\t\t\t\tWhy Facebook ending fact checking in US is a warning sign for India\t\t\t\n\n14 Jan 2025\n\n\n\n\nNews\nWhy Facebook ending fact checking in US is a warning sign for India\n\n\t\t\t\t\t\t\t\t\tScroll ↗\t\t\t\t\t\t\t\n↗\n14 Jan 2025\n\nWhy Facebook ending fact checking in US is a warning sign for India\n\n\n\n\n\n\n\n\n\n\t\t\t\t\tContent Governance\t\t\t\t\n\n\n\n\nContent Governance \n\n\n\t\t\t\tEU regulators take a hard look at Elon Musk and X\t\t\t\n\n14 Jan 2025\n\n\n\n\nNews\nEU regulators take a hard look at Elon Musk and X\n\n\t\t\t\t\t\t\t\t\tDeutsche Welle ↗\t\t\t\t\t\t\t\n↗\n14 Jan 2025\n\nEU regulators take a hard look at Elon Musk and X\n\n\n\n\n\n\n\n\n\n\t\t\t\t\tContent Governance\t\t\t\t\n\n\n\n\nContent Governance \n\n\n\t\t\t\tPlatform accountability: a rule-of-law checklist for policymakers\t\t\t\n\n13 Jan 2025\n • \nIn this report, Access Now proposes a rule-of-law checklist to enable states to enact platform accountability regulations that are fit for purpose and protect human rights.\n\n\n\n\nPublication\nPlatform accountability: a rule-of-law checklist for policymakers\n\n\n↗\n13 Jan 2025\n\nPlatform accountability: a rule-of-law checklist for policymakers\n\n\n\n\n\n\n\n\n\n\t\t\t\t\tContent Governance\t\t\t\t\n\n\n\n\nContent Governance \n\n\n\t\t\t\tPlatform accountability and human rights: a rule-of-law checklist\t\t\t\n\n13 Jan 2025\n • \nAs policymakers around the world seek to rein in Big Tech, we define the safeguards necessary to ensure rule of law and protect human rights and democracy.\n\n\n\n\nPost\nPlatform accountability and human rights: a rule-of-law checklist\n13 Jan 2025\n\nPlatform accountability and human rights: a rule-of-law checklist\n\n\n\n\n\n\n\n\n\n\t\t\t\t\tContent Governance\t\t\t\t\n\n\n\n\nContent Governance \n\n\n\t\t\t\tGlobal fact-checkers were disappointed, not surprised, Meta ended its program\t\t\t\n\n10 Jan 2025\n\n\n\n\nNews\nGlobal fact-checkers were disappointed, not surprised, Meta ended its program\n\n\t\t\t\t\t\t\t\t\tRest of World ↗\t\t\t\t\t\t\t\n↗\n10 Jan 2025\n\nGlobal fact-checkers were disappointed, not surprised, Meta ended its program\n\n\n\n\n\n\n\n\n\n\t\t\t\t\tContent Governance\t\t\t\t\n\n\n\n\nContent Governance \n\n\n\t\t\t\tBrussels will be watching whether Musk breaks EU law in far-right livestream\t\t\t\n\n9 Jan 2025\n\n\n\n\nNews\nBrussels will be watching whether Musk breaks EU law in far-right livestream\n\n\t\t\t\t\t\t\t\t\tPOLITICO ↗\t\t\t\t\t\t\t\n↗\n9 Jan 2025\n\nBrussels will be watching whether Musk breaks EU law in far-right livestream\n\nRights-Based Approaches to Online Content\n\nRights-Based Approaches to Online Content\n\nGovernments and companies are under increasing pressure to address illegal or undesirable content and expression online, but hasty or poorly crafted solutions threaten human rights. We advocate for policies and practices to defend free expression and access to information and  ensure people who are most at risk are protected.\n\nGovernments and companies are under increasing pressure to address illegal or undesirable content and expression online, but hasty or poorly crafted solutions threaten human rights. We advocate for policies and practices to defend free expression and access to information and  ensure people who are most at risk are protected.\n\nGovernments and companies are under increasing pressure to address illegal or undesirable content and expression online, but hasty or poorly crafted solutions threaten human rights. We advocate for policies and practices to defend free expression and access to information and  ensure people who are most at risk are protected.\n\nPlatform Accountability: a rule-of-law checklist for policymakers\nPlatform regulations can be a minefield for human rights. Here’s a checklist to help policymakers examine the need for platform regulations, and where necessary, enact regulations that are fit-for-purpose and protect human rights. \n\nLearn more\n\n\n\n\n\nResources\n\n\n\n\n\n\n\n\n\n\n\n\n\nContent Governance\n\n\n\t\t\t\n\t\t\t\tOur rights are at stake: it’s time to reclaim freedom of expression\n\t\t\t\t\t\t\t\n\n\nGiven the escalating use of free speech claims as a shield for inciting hatred and violence, it is more urgent than ever to reaffirm what freedom of expression truly stands for. \n\n\n\n\n\n\n\n\n\n\n\n\n\nContent Governance\n\n\n\t\t\t\n\t\t\t\tContent governance in times of crisis: how platforms can protect human rights\n\t\t\t\t\t\t\t\n\n\nThe “Declaration for content and platform governance principles in times of crisis” lays out principles for social media platforms to help ensure privacy, freedom of expression, and access to information during crises.\n\n\n\n\n\n\n\n\n\n\n\n\n\nContent Governance\n\n\n\t\t\t\n\t\t\t\tRainbow-burning: how social media companies increase risks for LGBTQ+ people in Africa\n\t\t\t\t\t\t\t\n\n\nColonial-era laws and a global anti-rights movement are fueling LGBTQ+ repression across Africa. Access Now documented 214 threats on platforms like TikTok, X, Facebook, YouTube, and WhatsApp, underscoring widespread risks.\n\n\n\n\n\n\n\n\n\n\n\n\n\nContent Governance\n\n\n\t\t\t\n\t\t\t\tGuide: how to protect human rights in content governance\n\t\t\t\t\t\t\t\n\n\nWe offer 26 recommendations on content governance to help lawmakers, regulators, and company leaders make decisions that will safeguard human rights.\n\n\n\n\n\n\n\n\n\n\n\n\n\n\n\n\n\n\n\n\n\nContent Governance\n\n\n\t\t\t\n\t\t\t\tDigital Security Helpline: our approach to content-related cases\n\t\t\t\t\t\t\t\n\n\nCritical voices from civil society are being censored. Here’s how the Digital Security Helpline addresses cases related to content governance.\n\n\n\n\n\n\n\n\n\n\n\n\n\nContent Governance\n\n\n\t\t\t\n\t\t\t\tWhat is disinformation, why it spreads, and how to stop it\n\t\t\t\t\t\t\t\n\n\nOur new report explores what disinformation is, and how lawmakers can address the harms it poses to democracy.\n\n\n\n\n\n\n\n\n\n\n\n\n\nContent Governance\n\n\n\t\t\t\n\t\t\t\tThe Digital Services Act: your guide to the EU’s new content moderation rules\n\t\t\t\t\t\t\t\n\n\nThe EU Digital Services Act has finally arrived. We unpack what this law contains and the changes people can expect to see from 2024 onwards.\n\n\n\n\n\n\n\n\n\n\n\n\n\nContent Governance\n\n\n\t\t\t\n\t\t\t\tAccess Now releases “Fighting misinformation and defending free expression during COVID-19: recommendations for states”\n\t\t\t\t\t\t\t\n\n\nWe have identified practical examples and promising practices to support policy makers in respecting human rights while developing measures to address disinformation and misinformation during the COVID-19 crisis.\n\nPlatform Accountability: a rule-of-law checklist for policymakers\nPlatform regulations can be a minefield for human rights. Here’s a checklist to help policymakers examine the need for platform regulations, and where necessary, enact regulations that are fit-for-purpose and protect human rights. \n\nLearn more\n\nPlatform Accountability: a rule-of-law checklist for policymakers\nPlatform regulations can be a minefield for human rights. Here’s a checklist to help policymakers examine the need for platform regulations, and where necessary, enact regulations that are fit-for-purpose and protect human rights. \n\nLearn more\n\nPlatform regulations can be a minefield for human rights. Here’s a checklist to help policymakers examine the need for platform regulations, and where necessary, enact regulations that are fit-for-purpose and protect human rights.\n\nLearn more\n\nLearn more\n\nResources\n\n\n\n\n\n\n\n\n\n\n\n\n\nContent Governance\n\n\n\t\t\t\n\t\t\t\tOur rights are at stake: it’s time to reclaim freedom of expression\n\t\t\t\t\t\t\t\n\n\nGiven the escalating use of free speech claims as a shield for inciting hatred and violence, it is more urgent than ever to reaffirm what freedom of expression truly stands for. \n\n\n\n\n\n\n\n\n\n\n\n\n\nContent Governance\n\n\n\t\t\t\n\t\t\t\tContent governance in times of crisis: how platforms can protect human rights\n\t\t\t\t\t\t\t\n\n\nThe “Declaration for content and platform governance principles in times of crisis” lays out principles for social media platforms to help ensure privacy, freedom of expression, and access to information during crises.\n\n\n\n\n\n\n\n\n\n\n\n\n\nContent Governance\n\n\n\t\t\t\n\t\t\t\tRainbow-burning: how social media companies increase risks for LGBTQ+ people in Africa\n\t\t\t\t\t\t\t\n\n\nColonial-era laws and a global anti-rights movement are fueling LGBTQ+ repression across Africa. Access Now documented 214 threats on platforms like TikTok, X, Facebook, YouTube, and WhatsApp, underscoring widespread risks.\n\n\n\n\n\n\n\n\n\n\n\n\n\nContent Governance\n\n\n\t\t\t\n\t\t\t\tGuide: how to protect human rights in content governance\n\t\t\t\t\t\t\t\n\n\nWe offer 26 recommendations on content governance to help lawmakers, regulators, and company leaders make decisions that will safeguard human rights.\n\n\n\n\n\n\n\n\n\n\n\n\n\n\n\n\n\n\n\n\n\nContent Governance\n\n\n\t\t\t\n\t\t\t\tDigital Security Helpline: our approach to content-related cases\n\t\t\t\t\t\t\t\n\n\nCritical voices from civil society are being censored. Here’s how the Digital Security Helpline addresses cases related to content governance.\n\n\n\n\n\n\n\n\n\n\n\n\n\nContent Governance\n\n\n\t\t\t\n\t\t\t\tWhat is disinformation, why it spreads, and how to stop it\n\t\t\t\t\t\t\t\n\n\nOur new report explores what disinformation is, and how lawmakers can address the harms it poses to democracy.\n\n\n\n\n\n\n\n\n\n\n\n\n\nContent Governance\n\n\n\t\t\t\n\t\t\t\tThe Digital Services Act: your guide to the EU’s new content moderation rules\n\t\t\t\t\t\t\t\n\n\nThe EU Digital Services Act has finally arrived. We unpack what this law contains and the changes people can expect to see from 2024 onwards.\n\n\n\n\n\n\n\n\n\n\n\n\n\nContent Governance\n\n\n\t\t\t\n\t\t\t\tAccess Now releases “Fighting misinformation and defending free expression during COVID-19: recommendations for states”\n\t\t\t\t\t\t\t\n\n\nWe have identified practical examples and promising practices to support policy makers in respecting human rights while developing measures to address disinformation and misinformation during the COVID-19 crisis.\n\nResources\n\n\n\n\n\n\n\n\n\n\n\n\n\nContent Governance\n\n\n\t\t\t\n\t\t\t\tOur rights are at stake: it’s time to reclaim freedom of expression\n\t\t\t\t\t\t\t\n\n\nGiven the escalating use of free speech claims as a shield for inciting hatred and violence, it is more urgent than ever to reaffirm what freedom of expression truly stands for. \n\n\n\n\n\n\n\n\n\n\n\n\n\nContent Governance\n\n\n\t\t\t\n\t\t\t\tContent governance in times of crisis: how platforms can protect human rights\n\t\t\t\t\t\t\t\n\n\nThe “Declaration for content and platform governance principles in times of crisis” lays out principles for social media platforms to help ensure privacy, freedom of expression, and access to information during crises.\n\n\n\n\n\n\n\n\n\n\n\n\n\nContent Governance\n\n\n\t\t\t\n\t\t\t\tRainbow-burning: how social media companies increase risks for LGBTQ+ people in Africa\n\t\t\t\t\t\t\t\n\n\nColonial-era laws and a global anti-rights movement are fueling LGBTQ+ repression across Africa. Access Now documented 214 threats on platforms like TikTok, X, Facebook, YouTube, and WhatsApp, underscoring widespread risks.\n\n\n\n\n\n\n\n\n\n\n\n\n\nContent Governance\n\n\n\t\t\t\n\t\t\t\tGuide: how to protect human rights in content governance\n\t\t\t\t\t\t\t\n\n\nWe offer 26 recommendations on content governance to help lawmakers, regulators, and company leaders make decisions that will safeguard human rights.\n\n\n\n\n\n\n\n\n\n\n\n\n\n\n\n\n\n\n\n\n\nContent Governance\n\n\n\t\t\t\n\t\t\t\tDigital Security Helpline: our approach to content-related cases\n\t\t\t\t\t\t\t\n\n\nCritical voices from civil society are being censored. Here’s how the Digital Security Helpline addresses cases related to content governance.\n\n\n\n\n\n\n\n\n\n\n\n\n\nContent Governance\n\n\n\t\t\t\n\t\t\t\tWhat is disinformation, why it spreads, and how to stop it\n\t\t\t\t\t\t\t\n\n\nOur new report explores what disinformation is, and how lawmakers can address the harms it poses to democracy.\n\n\n\n\n\n\n\n\n\n\n\n\n\nContent Governance\n\n\n\t\t\t\n\t\t\t\tThe Digital Services Act: your guide to the EU’s new content moderation rules\n\t\t\t\t\t\t\t\n\n\nThe EU Digital Services Act has finally arrived. We unpack what this law contains and the changes people can expect to see from 2024 onwards.\n\n\n\n\n\n\n\n\n\n\n\n\n\nContent Governance\n\n\n\t\t\t\n\t\t\t\tAccess Now releases “Fighting misinformation and defending free expression during COVID-19: recommendations for states”\n\t\t\t\t\t\t\t\n\n\nWe have identified practical examples and promising practices to support policy makers in respecting human rights while developing measures to address disinformation and misinformation during the COVID-19 crisis.\n\nResources\n\n\n\n\n\n\n\n\n\n\n\n\n\nContent Governance\n\n\n\t\t\t\n\t\t\t\tOur rights are at stake: it’s time to reclaim freedom of expression\n\t\t\t\t\t\t\t\n\n\nGiven the escalating use of free speech claims as a shield for inciting hatred and violence, it is more urgent than ever to reaffirm what freedom of expression truly stands for. \n\n\n\n\n\n\n\n\n\n\n\n\n\nContent Governance\n\n\n\t\t\t\n\t\t\t\tContent governance in times of crisis: how platforms can protect human rights\n\t\t\t\t\t\t\t\n\n\nThe “Declaration for content and platform governance principles in times of crisis” lays out principles for social media platforms to help ensure privacy, freedom of expression, and access to information during crises.\n\n\n\n\n\n\n\n\n\n\n\n\n\nContent Governance\n\n\n\t\t\t\n\t\t\t\tRainbow-burning: how social media companies increase risks for LGBTQ+ people in Africa\n\t\t\t\t\t\t\t\n\n\nColonial-era laws and a global anti-rights movement are fueling LGBTQ+ repression across Africa. Access Now documented 214 threats on platforms like TikTok, X, Facebook, YouTube, and WhatsApp, underscoring widespread risks.\n\n\n\n\n\n\n\n\n\n\n\n\n\nContent Governance\n\n\n\t\t\t\n\t\t\t\tGuide: how to protect human rights in content governance\n\t\t\t\t\t\t\t\n\n\nWe offer 26 recommendations on content governance to help lawmakers, regulators, and company leaders make decisions that will safeguard human rights.\n\n\n\n\n\n\n\n\n\n\n\n\n\n\n\n\n\n\n\n\n\nContent Governance\n\n\n\t\t\t\n\t\t\t\tDigital Security Helpline: our approach to content-related cases\n\t\t\t\t\t\t\t\n\n\nCritical voices from civil society are being censored. Here’s how the Digital Security Helpline addresses cases related to content governance.\n\n\n\n\n\n\n\n\n\n\n\n\n\nContent Governance\n\n\n\t\t\t\n\t\t\t\tWhat is disinformation, why it spreads, and how to stop it\n\t\t\t\t\t\t\t\n\n\nOur new report explores what disinformation is, and how lawmakers can address the harms it poses to democracy.\n\n\n\n\n\n\n\n\n\n\n\n\n\nContent Governance\n\n\n\t\t\t\n\t\t\t\tThe Digital Services Act: your guide to the EU’s new content moderation rules\n\t\t\t\t\t\t\t\n\n\nThe EU Digital Services Act has finally arrived. We unpack what this law contains and the changes people can expect to see from 2024 onwards.\n\n\n\n\n\n\n\n\n\n\n\n\n\nContent Governance\n\n\n\t\t\t\n\t\t\t\tAccess Now releases “Fighting misinformation and defending free expression during COVID-19: recommendations for states”\n\t\t\t\t\t\t\t\n\n\nWe have identified practical examples and promising practices to support policy makers in respecting human rights while developing measures to address disinformation and misinformation during the COVID-19 crisis.\n\nContent Governance\n\n\n\t\t\t\n\t\t\t\tOur rights are at stake: it’s time to reclaim freedom of expression\n\t\t\t\t\t\t\t\n\n\nGiven the escalating use of free speech claims as a shield for inciting hatred and violence, it is more urgent than ever to reaffirm what freedom of expression truly stands for. \n\n\n\n\n\n\n\n\n\n\n\n\n\nContent Governance\n\n\n\t\t\t\n\t\t\t\tContent governance in times of crisis: how platforms can protect human rights\n\t\t\t\t\t\t\t\n\n\nThe “Declaration for content and platform governance principles in times of crisis” lays out principles for social media platforms to help ensure privacy, freedom of expression, and access to information during crises.\n\n\n\n\n\n\n\n\n\n\n\n\n\nContent Governance\n\n\n\t\t\t\n\t\t\t\tRainbow-burning: how social media companies increase risks for LGBTQ+ people in Africa\n\t\t\t\t\t\t\t\n\n\nColonial-era laws and a global anti-rights movement are fueling LGBTQ+ repression across Africa. Access Now documented 214 threats on platforms like TikTok, X, Facebook, YouTube, and WhatsApp, underscoring widespread risks.\n\n\n\n\n\n\n\n\n\n\n\n\n\nContent Governance\n\n\n\t\t\t\n\t\t\t\tGuide: how to protect human rights in content governance\n\t\t\t\t\t\t\t\n\n\nWe offer 26 recommendations on content governance to help lawmakers, regulators, and company leaders make decisions that will safeguard human rights.\n\nContent Governance\n\n\n\t\t\t\n\t\t\t\tOur rights are at stake: it’s time to reclaim freedom of expression\n\t\t\t\t\t\t\t\n\n\nGiven the escalating use of free speech claims as a shield for inciting hatred and violence, it is more urgent than ever to reaffirm what freedom of expression truly stands for. \n\n\n\n\n\n\n\n\n\n\n\n\n\nContent Governance\n\n\n\t\t\t\n\t\t\t\tContent governance in times of crisis: how platforms can protect human rights\n\t\t\t\t\t\t\t\n\n\nThe “Declaration for content and platform governance principles in times of crisis” lays out principles for social media platforms to help ensure privacy, freedom of expression, and access to information during crises.\n\n\n\n\n\n\n\n\n\n\n\n\n\nContent Governance\n\n\n\t\t\t\n\t\t\t\tRainbow-burning: how social media companies increase risks for LGBTQ+ people in Africa\n\t\t\t\t\t\t\t\n\n\nColonial-era laws and a global anti-rights movement are fueling LGBTQ+ repression across Africa. Access Now documented 214 threats on platforms like TikTok, X, Facebook, YouTube, and WhatsApp, underscoring widespread risks.\n\n\n\n\n\n\n\n\n\n\n\n\n\nContent Governance\n\n\n\t\t\t\n\t\t\t\tGuide: how to protect human rights in content governance\n\t\t\t\t\t\t\t\n\n\nWe offer 26 recommendations on content governance to help lawmakers, regulators, and company leaders make decisions that will safeguard human rights.\n\nContent Governance\n\n\n\t\t\t\n\t\t\t\tOur rights are at stake: it’s time to reclaim freedom of expression\n\t\t\t\t\t\t\t\n\n\nGiven the escalating use of free speech claims as a shield for inciting hatred and violence, it is more urgent than ever to reaffirm what freedom of expression truly stands for. \n\n\n\n\n\n\n\n\n\n\n\n\n\nContent Governance\n\n\n\t\t\t\n\t\t\t\tContent governance in times of crisis: how platforms can protect human rights\n\t\t\t\t\t\t\t\n\n\nThe “Declaration for content and platform governance principles in times of crisis” lays out principles for social media platforms to help ensure privacy, freedom of expression, and access to information during crises.\n\n\n\n\n\n\n\n\n\n\n\n\n\nContent Governance\n\n\n\t\t\t\n\t\t\t\tRainbow-burning: how social media companies increase risks for LGBTQ+ people in Africa\n\t\t\t\t\t\t\t\n\n\nColonial-era laws and a global anti-rights movement are fueling LGBTQ+ repression across Africa. Access Now documented 214 threats on platforms like TikTok, X, Facebook, YouTube, and WhatsApp, underscoring widespread risks.\n\n\n\n\n\n\n\n\n\n\n\n\n\nContent Governance\n\n\n\t\t\t\n\t\t\t\tGuide: how to protect human rights in content governance\n\t\t\t\t\t\t\t\n\n\nWe offer 26 recommendations on content governance to help lawmakers, regulators, and company leaders make decisions that will safeguard human rights.\n\nContent Governance\n\n\n\t\t\t\n\t\t\t\tOur rights are at stake: it’s time to reclaim freedom of expression\n\t\t\t\t\t\t\t\n\n\nGiven the escalating use of free speech claims as a shield for inciting hatred and violence, it is more urgent than ever to reaffirm what freedom of expression truly stands for. \n\n\n\n\n\n\n\n\n\n\n\n\n\nContent Governance\n\n\n\t\t\t\n\t\t\t\tContent governance in times of crisis: how platforms can protect human rights\n\t\t\t\t\t\t\t\n\n\nThe “Declaration for content and platform governance principles in times of crisis” lays out principles for social media platforms to help ensure privacy, freedom of expression, and access to information during crises.\n\n\n\n\n\n\n\n\n\n\n\n\n\nContent Governance\n\n\n\t\t\t\n\t\t\t\tRainbow-burning: how social media companies increase risks for LGBTQ+ people in Africa\n\t\t\t\t\t\t\t\n\n\nColonial-era laws and a global anti-rights movement are fueling LGBTQ+ repression across Africa. Access Now documented 214 threats on platforms like TikTok, X, Facebook, YouTube, and WhatsApp, underscoring widespread risks.\n\n\n\n\n\n\n\n\n\n\n\n\n\nContent Governance\n\n\n\t\t\t\n\t\t\t\tGuide: how to protect human rights in content governance\n\t\t\t\t\t\t\t\n\n\nWe offer 26 recommendations on content governance to help lawmakers, regulators, and company leaders make decisions that will safeguard human rights.\n\nContent Governance\n\n\n\t\t\t\n\t\t\t\tOur rights are at stake: it’s time to reclaim freedom of expression\n\t\t\t\t\t\t\t\n\n\nGiven the escalating use of free speech claims as a shield for inciting hatred and violence, it is more urgent than ever to reaffirm what freedom of expression truly stands for.\n\nContent Governance\n\n\n\t\t\t\n\t\t\t\tOur rights are at stake: it’s time to reclaim freedom of expression\n\t\t\t\t\t\t\t\n\n\nGiven the escalating use of free speech claims as a shield for inciting hatred and violence, it is more urgent than ever to reaffirm what freedom of expression truly stands for.\n\nContent Governance\n\n\n\t\t\t\n\t\t\t\tOur rights are at stake: it’s time to reclaim freedom of expression\n\t\t\t\t\t\t\t\n\n\nGiven the escalating use of free speech claims as a shield for inciting hatred and violence, it is more urgent than ever to reaffirm what freedom of expression truly stands for.\n\nContent Governance\n\nGiven the escalating use of free speech claims as a shield for inciting hatred and violence, it is more urgent than ever to reaffirm what freedom of expression truly stands for.\n\nGiven the escalating use of free speech claims as a shield for inciting hatred and violence, it is more urgent than ever to reaffirm what freedom of expression truly stands for.\n\nContent Governance\n\n\n\t\t\t\n\t\t\t\tContent governance in times of crisis: how platforms can protect human rights\n\t\t\t\t\t\t\t\n\n\nThe “Declaration for content and platform governance principles in times of crisis” lays out principles for social media platforms to help ensure privacy, freedom of expression, and access to information during crises.\n\nContent Governance\n\n\n\t\t\t\n\t\t\t\tContent governance in times of crisis: how platforms can protect human rights\n\t\t\t\t\t\t\t\n\n\nThe “Declaration for content and platform governance principles in times of crisis” lays out principles for social media platforms to help ensure privacy, freedom of expression, and access to information during crises.\n\nContent Governance\n\n\n\t\t\t\n\t\t\t\tContent governance in times of crisis: how platforms can protect human rights\n\t\t\t\t\t\t\t\n\n\nThe “Declaration for content and platform governance principles in times of crisis” lays out principles for social media platforms to help ensure privacy, freedom of expression, and access to information during crises.\n\nContent Governance\n\nThe “Declaration for content and platform governance principles in times of crisis” lays out principles for social media platforms to help ensure privacy, freedom of expression, and access to information during crises.\n\nThe “Declaration for content and platform governance principles in times of crisis” lays out principles for social media platforms to help ensure privacy, freedom of expression, and access to information during crises.\n\nContent Governance\n\n\n\t\t\t\n\t\t\t\tRainbow-burning: how social media companies increase risks for LGBTQ+ people in Africa\n\t\t\t\t\t\t\t\n\n\nColonial-era laws and a global anti-rights movement are fueling LGBTQ+ repression across Africa. Access Now documented 214 threats on platforms like TikTok, X, Facebook, YouTube, and WhatsApp, underscoring widespread risks.\n\nContent Governance\n\n\n\t\t\t\n\t\t\t\tRainbow-burning: how social media companies increase risks for LGBTQ+ people in Africa\n\t\t\t\t\t\t\t\n\n\nColonial-era laws and a global anti-rights movement are fueling LGBTQ+ repression across Africa. Access Now documented 214 threats on platforms like TikTok, X, Facebook, YouTube, and WhatsApp, underscoring widespread risks.\n\nContent Governance\n\n\n\t\t\t\n\t\t\t\tRainbow-burning: how social media companies increase risks for LGBTQ+ people in Africa\n\t\t\t\t\t\t\t\n\n\nColonial-era laws and a global anti-rights movement are fueling LGBTQ+ repression across Africa. Access Now documented 214 threats on platforms like TikTok, X, Facebook, YouTube, and WhatsApp, underscoring widespread risks.\n\nContent Governance\n\nColonial-era laws and a global anti-rights movement are fueling LGBTQ+ repression across Africa. Access Now documented 214 threats on platforms like TikTok, X, Facebook, YouTube, and WhatsApp, underscoring widespread risks.\n\nColonial-era laws and a global anti-rights movement are fueling LGBTQ+ repression across Africa. Access Now documented 214 threats on platforms like TikTok, X, Facebook, YouTube, and WhatsApp, underscoring widespread risks.\n\nContent Governance\n\n\n\t\t\t\n\t\t\t\tGuide: how to protect human rights in content governance\n\t\t\t\t\t\t\t\n\n\nWe offer 26 recommendations on content governance to help lawmakers, regulators, and company leaders make decisions that will safeguard human rights.\n\nContent Governance\n\n\n\t\t\t\n\t\t\t\tGuide: how to protect human rights in content governance\n\t\t\t\t\t\t\t\n\n\nWe offer 26 recommendations on content governance to help lawmakers, regulators, and company leaders make decisions that will safeguard human rights.\n\nContent Governance\n\n\n\t\t\t\n\t\t\t\tGuide: how to protect human rights in content governance\n\t\t\t\t\t\t\t\n\n\nWe offer 26 recommendations on content governance to help lawmakers, regulators, and company leaders make decisions that will safeguard human rights.\n\nContent Governance\n\nWe offer 26 recommendations on content governance to help lawmakers, regulators, and company leaders make decisions that will safeguard human rights.\n\nWe offer 26 recommendations on content governance to help lawmakers, regulators, and company leaders make decisions that will safeguard human rights.\n\nContent Governance\n\n\n\t\t\t\n\t\t\t\tDigital Security Helpline: our approach to content-related cases\n\t\t\t\t\t\t\t\n\n\nCritical voices from civil society are being censored. Here’s how the Digital Security Helpline addresses cases related to content governance.\n\n\n\n\n\n\n\n\n\n\n\n\n\nContent Governance\n\n\n\t\t\t\n\t\t\t\tWhat is disinformation, why it spreads, and how to stop it\n\t\t\t\t\t\t\t\n\n\nOur new report explores what disinformation is, and how lawmakers can address the harms it poses to democracy.\n\n\n\n\n\n\n\n\n\n\n\n\n\nContent Governance\n\n\n\t\t\t\n\t\t\t\tThe Digital Services Act: your guide to the EU’s new content moderation rules\n\t\t\t\t\t\t\t\n\n\nThe EU Digital Services Act has finally arrived. We unpack what this law contains and the changes people can expect to see from 2024 onwards.\n\n\n\n\n\n\n\n\n\n\n\n\n\nContent Governance\n\n\n\t\t\t\n\t\t\t\tAccess Now releases “Fighting misinformation and defending free expression during COVID-19: recommendations for states”\n\t\t\t\t\t\t\t\n\n\nWe have identified practical examples and promising practices to support policy makers in respecting human rights while developing measures to address disinformation and misinformation during the COVID-19 crisis.\n\nContent Governance\n\n\n\t\t\t\n\t\t\t\tDigital Security Helpline: our approach to content-related cases\n\t\t\t\t\t\t\t\n\n\nCritical voices from civil society are being censored. Here’s how the Digital Security Helpline addresses cases related to content governance.\n\n\n\n\n\n\n\n\n\n\n\n\n\nContent Governance\n\n\n\t\t\t\n\t\t\t\tWhat is disinformation, why it spreads, and how to stop it\n\t\t\t\t\t\t\t\n\n\nOur new report explores what disinformation is, and how lawmakers can address the harms it poses to democracy.\n\n\n\n\n\n\n\n\n\n\n\n\n\nContent Governance\n\n\n\t\t\t\n\t\t\t\tThe Digital Services Act: your guide to the EU’s new content moderation rules\n\t\t\t\t\t\t\t\n\n\nThe EU Digital Services Act has finally arrived. We unpack what this law contains and the changes people can expect to see from 2024 onwards.\n\n\n\n\n\n\n\n\n\n\n\n\n\nContent Governance\n\n\n\t\t\t\n\t\t\t\tAccess Now releases “Fighting misinformation and defending free expression during COVID-19: recommendations for states”\n\t\t\t\t\t\t\t\n\n\nWe have identified practical examples and promising practices to support policy makers in respecting human rights while developing measures to address disinformation and misinformation during the COVID-19 crisis.\n\nContent Governance\n\n\n\t\t\t\n\t\t\t\tDigital Security Helpline: our approach to content-related cases\n\t\t\t\t\t\t\t\n\n\nCritical voices from civil society are being censored. Here’s how the Digital Security Helpline addresses cases related to content governance.\n\n\n\n\n\n\n\n\n\n\n\n\n\nContent Governance\n\n\n\t\t\t\n\t\t\t\tWhat is disinformation, why it spreads, and how to stop it\n\t\t\t\t\t\t\t\n\n\nOur new report explores what disinformation is, and how lawmakers can address the harms it poses to democracy.\n\n\n\n\n\n\n\n\n\n\n\n\n\nContent Governance\n\n\n\t\t\t\n\t\t\t\tThe Digital Services Act: your guide to the EU’s new content moderation rules\n\t\t\t\t\t\t\t\n\n\nThe EU Digital Services Act has finally arrived. We unpack what this law contains and the changes people can expect to see from 2024 onwards.\n\n\n\n\n\n\n\n\n\n\n\n\n\nContent Governance\n\n\n\t\t\t\n\t\t\t\tAccess Now releases “Fighting misinformation and defending free expression during COVID-19: recommendations for states”\n\t\t\t\t\t\t\t\n\n\nWe have identified practical examples and promising practices to support policy makers in respecting human rights while developing measures to address disinformation and misinformation during the COVID-19 crisis.\n\nContent Governance\n\n\n\t\t\t\n\t\t\t\tDigital Security Helpline: our approach to content-related cases\n\t\t\t\t\t\t\t\n\n\nCritical voices from civil society are being censored. Here’s how the Digital Security Helpline addresses cases related to content governance.\n\n\n\n\n\n\n\n\n\n\n\n\n\nContent Governance\n\n\n\t\t\t\n\t\t\t\tWhat is disinformation, why it spreads, and how to stop it\n\t\t\t\t\t\t\t\n\n\nOur new report explores what disinformation is, and how lawmakers can address the harms it poses to democracy.\n\n\n\n\n\n\n\n\n\n\n\n\n\nContent Governance\n\n\n\t\t\t\n\t\t\t\tThe Digital Services Act: your guide to the EU’s new content moderation rules\n\t\t\t\t\t\t\t\n\n\nThe EU Digital Services Act has finally arrived. We unpack what this law contains and the changes people can expect to see from 2024 onwards.\n\n\n\n\n\n\n\n\n\n\n\n\n\nContent Governance\n\n\n\t\t\t\n\t\t\t\tAccess Now releases “Fighting misinformation and defending free expression during COVID-19: recommendations for states”\n\t\t\t\t\t\t\t\n\n\nWe have identified practical examples and promising practices to support policy makers in respecting human rights while developing measures to address disinformation and misinformation during the COVID-19 crisis.\n\nContent Governance\n\n\n\t\t\t\n\t\t\t\tDigital Security Helpline: our approach to content-related cases\n\t\t\t\t\t\t\t\n\n\nCritical voices from civil society are being censored. Here’s how the Digital Security Helpline addresses cases related to content governance.\n\nContent Governance\n\n\n\t\t\t\n\t\t\t\tDigital Security Helpline: our approach to content-related cases\n\t\t\t\t\t\t\t\n\n\nCritical voices from civil society are being censored. Here’s how the Digital Security Helpline addresses cases related to content governance.\n\nContent Governance\n\n\n\t\t\t\n\t\t\t\tDigital Security Helpline: our approach to content-related cases\n\t\t\t\t\t\t\t\n\n\nCritical voices from civil society are being censored. Here’s how the Digital Security Helpline addresses cases related to content governance.\n\nContent Governance\n\nCritical voices from civil society are being censored. Here’s how the Digital Security Helpline addresses cases related to content governance.\n\nCritical voices from civil society are being censored. Here’s how the Digital Security Helpline addresses cases related to content governance.\n\nContent Governance\n\n\n\t\t\t\n\t\t\t\tWhat is disinformation, why it spreads, and how to stop it\n\t\t\t\t\t\t\t\n\n\nOur new report explores what disinformation is, and how lawmakers can address the harms it poses to democracy.\n\nContent Governance\n\n\n\t\t\t\n\t\t\t\tWhat is disinformation, why it spreads, and how to stop it\n\t\t\t\t\t\t\t\n\n\nOur new report explores what disinformation is, and how lawmakers can address the harms it poses to democracy.\n\nContent Governance\n\n\n\t\t\t\n\t\t\t\tWhat is disinformation, why it spreads, and how to stop it\n\t\t\t\t\t\t\t\n\n\nOur new report explores what disinformation is, and how lawmakers can address the harms it poses to democracy.\n\nContent Governance\n\nOur new report explores what disinformation is, and how lawmakers can address the harms it poses to democracy.\n\nOur new report explores what disinformation is, and how lawmakers can address the harms it poses to democracy.\n\nContent Governance\n\n\n\t\t\t\n\t\t\t\tThe Digital Services Act: your guide to the EU’s new content moderation rules\n\t\t\t\t\t\t\t\n\n\nThe EU Digital Services Act has finally arrived. We unpack what this law contains and the changes people can expect to see from 2024 onwards.\n\nContent Governance\n\n\n\t\t\t\n\t\t\t\tThe Digital Services Act: your guide to the EU’s new content moderation rules\n\t\t\t\t\t\t\t\n\n\nThe EU Digital Services Act has finally arrived. We unpack what this law contains and the changes people can expect to see from 2024 onwards.\n\nContent Governance\n\n\n\t\t\t\n\t\t\t\tThe Digital Services Act: your guide to the EU’s new content moderation rules\n\t\t\t\t\t\t\t\n\n\nThe EU Digital Services Act has finally arrived. We unpack what this law contains and the changes people can expect to see from 2024 onwards.\n\nContent Governance\n\nThe EU Digital Services Act has finally arrived. We unpack what this law contains and the changes people can expect to see from 2024 onwards.\n\nThe EU Digital Services Act has finally arrived. We unpack what this law contains and the changes people can expect to see from 2024 onwards.\n\nContent Governance\n\n\n\t\t\t\n\t\t\t\tAccess Now releases “Fighting misinformation and defending free expression during COVID-19: recommendations for states”\n\t\t\t\t\t\t\t\n\n\nWe have identified practical examples and promising practices to support policy makers in respecting human rights while developing measures to address disinformation and misinformation during the COVID-19 crisis.\n\nContent Governance\n\n\n\t\t\t\n\t\t\t\tAccess Now releases “Fighting misinformation and defending free expression during COVID-19: recommendations for states”\n\t\t\t\t\t\t\t\n\n\nWe have identified practical examples and promising practices to support policy makers in respecting human rights while developing measures to address disinformation and misinformation during the COVID-19 crisis.\n\nContent Governance\n\n\n\t\t\t\n\t\t\t\tAccess Now releases “Fighting misinformation and defending free expression during COVID-19: recommendations for states”\n\t\t\t\t\t\t\t\n\n\nWe have identified practical examples and promising practices to support policy makers in respecting human rights while developing measures to address disinformation and misinformation during the COVID-19 crisis.\n\nContent Governance\n\nWe have identified practical examples and promising practices to support policy makers in respecting human rights while developing measures to address disinformation and misinformation during the COVID-19 crisis.\n\nWe have identified practical examples and promising practices to support policy makers in respecting human rights while developing measures to address disinformation and misinformation during the COVID-19 crisis.\n\nLatest Updates\n\n\n\n     \n\n\n\n\n\nGrid View\nList View\n\n\n\n\n\n\n\n\n\n\n\n\n\n\t\t\t\t\tContent Governance\t\t\t\t\n\n\n\n\nContent Governance \n\n\n\t\t\t\t‘Profiting from misery’: how TikTok makes money from child begging livestreams\t\t\t\n\n6 Apr 2025\n\n\n\n\nNews\n‘Profiting from misery’: how TikTok makes money from child begging livestreams\n\n\t\t\t\t\t\t\t\t\tThe Guardian ↗\t\t\t\t\t\t\t\n↗\n6 Apr 2025\n\n‘Profiting from misery’: how TikTok makes money from child begging livestreams\n\n\n\n\n \n\t\t\t\t\tInternet Shutdowns\t\t\t\t\n\n\n\n\nInternet Shutdowns \n\n\n\t\t\t\tEmboldened offenders, endangered communities: internet shutdowns in 2024\t\t\t\n\n23 Feb 2025\n • \nAccess Now and the #KeepItOn coalition documented 296 internet shutdowns in 2024 — the highest number since 2016.\n\n\n\n\nPublication\nEmboldened offenders, endangered communities: internet shutdowns in 2024\n\n\n↗\n23 Feb 2025\n\nEmboldened offenders, endangered communities: internet shutdowns in 2024\n\n\n\n\n\n\n\n\n\n\t\t\t\t\tFreedom of Expression\t\t\t\t\n\n\n\n\nFreedom of Expression \n\n\n\t\t\t\tOur rights are at stake: it’s time to reclaim freedom of expression\t\t\t\n\n21 Feb 2025\n • \nGiven the escalating use of free speech claims as a shield for inciting hatred and violence, it is more urgent than ever to reaffirm what freedom of expression truly stands for. \n\n\n\n\nPress Release\nOur rights are at stake: it’s time to reclaim freedom of expression\n21 Feb 2025\n\nOur rights are at stake: it’s time to reclaim freedom of expression\n\n\n\n\n\n\n\n\n\n\t\t\t\t\tContent Governance\t\t\t\t\n\n\n\n\nContent Governance \n\n\n\t\t\t\tPoised to take over TikTok, Oracle is accused of clamping down on Pro-Palestine dissent\t\t\t\n\n19 Feb 2025\n\n\n\n\nNews\nPoised to take over TikTok, Oracle is accused of clamping down on Pro-Palestine dissent\n\n\t\t\t\t\t\t\t\t\tThe Intercept ↗\t\t\t\t\t\t\t\n↗\n19 Feb 2025\n\nPoised to take over TikTok, Oracle is accused of clamping down on Pro-Palestine dissent\n\n\n\n\n\n\n\n\n\n\t\t\t\t\tContent Governance\t\t\t\t\n\n\n\n\nContent Governance \n\n\n\t\t\t\tTamil website Vikatan inaccessible after It posted cartoon of PM, no official takedown order confirmed\t\t\t\n\n19 Feb 2025\n\n\n\n\nNews\nTamil website Vikatan inaccessible after It posted cartoon of PM, no official takedown order confirmed\n\n\t\t\t\t\t\t\t\t\tMedianama ↗\t\t\t\t\t\t\t\n↗\n19 Feb 2025\n\nTamil website Vikatan inaccessible after It posted cartoon of PM, no official takedown order confirmed\n\n\n\n\n\n\n\n\n\n\t\t\t\t\tInternet Shutdowns\t\t\t\t\n\n\n\n\nInternet Shutdowns \n\n\n\t\t\t\t2025 elections and internet shutdowns watch\t\t\t\n\n30 Jan 2025\n • \nGovernments around the world continue to shut down the internet during elections. Join our 2025 elections watch to #KeepItOn.\n\n\n\n\nCampaign\n2025 elections and internet shutdowns watch\n30 Jan 2025\n\n2025 elections and internet shutdowns watch\n\n\n\n\n\n\n\n\n\n\t\t\t\t\tContent Governance\t\t\t\t\n\n\n\n\nContent Governance \n\n\n\t\t\t\tTrump stand on online speech divides free speech ecosystem\t\t\t\n\n22 Jan 2025\n\n\n\n\nNews\nTrump stand on online speech divides free speech ecosystem\n\n\t\t\t\t\t\t\t\t\tHindu Businessline ↗\t\t\t\t\t\t\t\n↗\n22 Jan 2025\n\nTrump stand on online speech divides free speech ecosystem\n\n\n\n\n\n\n\n\n\n\t\t\t\t\tFreedom of Expression\t\t\t\t\n\n\n\n\nFreedom of Expression \n\n\n\t\t\t\tCeasefire in Gaza: it’s time to end digital harms and deliver justice\t\t\t\n\n20 Jan 2025\n • \nAs physical violence appears to be coming to a halt after 15 months in Gaza, Access Now further calls for a digital ceasefire.\n\n\n\n\nPress Release\nCeasefire in Gaza: it’s time to end digital harms and deliver justice\n20 Jan 2025\n\nCeasefire in Gaza: it’s time to end digital harms and deliver justice\n\n\n\n\n\n\n\n\n\n\t\t\t\t\tContent Governance\t\t\t\t\n\n\n\n\nContent Governance \n\n\n\t\t\t\tMetino ukidanje provjere činjenica ‘politička odluka sa stvarnim posljedicama’\t\t\t\n\n20 Jan 2025\n\n\n\n\nNews\nMetino ukidanje provjere činjenica ‘politička odluka sa stvarnim posljedicama’\n\n\t\t\t\t\t\t\t\t\tRadio Free Europe ↗\t\t\t\t\t\t\t\n↗\n20 Jan 2025\n\nMetino ukidanje provjere činjenica ‘politička odluka sa stvarnim posljedicama’\n\n\n\n\n\n\n\n\n\n\t\t\t\t\tFreedom of Expression\t\t\t\t\n\n\n\n\nFreedom of Expression \n\n\n\t\t\t\tTackling the “black snakes” undermining digital rights worldwide \t\t\t\n\n16 Jan 2025\n • \nAs 2025 gets underway, Access Now’s new Executive Director, Alejandro Mayoral Baños, PhD, shares his reflections on the “black snakes” threatening the digital rights movement. \n\n\n\n\nPost\nTackling the “black snakes” undermining digital rights worldwide \n16 Jan 2025\n\nTackling the “black snakes” undermining digital rights worldwide \n\n\n\n\n\n\n\n\n\n\t\t\t\t\tContent Governance\t\t\t\t\n\n\n\n\nContent Governance \n\n\n\t\t\t\tWhy Facebook ending fact checking in US is a warning sign for India\t\t\t\n\n14 Jan 2025\n\n\n\n\nNews\nWhy Facebook ending fact checking in US is a warning sign for India\n\n\t\t\t\t\t\t\t\t\tScroll ↗\t\t\t\t\t\t\t\n↗\n14 Jan 2025\n\nWhy Facebook ending fact checking in US is a warning sign for India\n\n\n\n\n\n\n\n\n\n\t\t\t\t\tContent Governance\t\t\t\t\n\n\n\n\nContent Governance \n\n\n\t\t\t\tEU regulators take a hard look at Elon Musk and X\t\t\t\n\n14 Jan 2025\n\n\n\n\nNews\nEU regulators take a hard look at Elon Musk and X\n\n\t\t\t\t\t\t\t\t\tDeutsche Welle ↗\t\t\t\t\t\t\t\n↗\n14 Jan 2025\n\nEU regulators take a hard look at Elon Musk and X\n\n\n\n\n\n\n\n\n\n\t\t\t\t\tContent Governance\t\t\t\t\n\n\n\n\nContent Governance \n\n\n\t\t\t\tPlatform accountability: a rule-of-law checklist for policymakers\t\t\t\n\n13 Jan 2025\n • \nIn this report, Access Now proposes a rule-of-law checklist to enable states to enact platform accountability regulations that are fit for purpose and protect human rights.\n\n\n\n\nPublication\nPlatform accountability: a rule-of-law checklist for policymakers\n\n\n↗\n13 Jan 2025\n\nPlatform accountability: a rule-of-law checklist for policymakers\n\n\n\n\n\n\n\n\n\n\t\t\t\t\tContent Governance\t\t\t\t\n\n\n\n\nContent Governance \n\n\n\t\t\t\tPlatform accountability and human rights: a rule-of-law checklist\t\t\t\n\n13 Jan 2025\n • \nAs policymakers around the world seek to rein in Big Tech, we define the safeguards necessary to ensure rule of law and protect human rights and democracy.\n\n\n\n\nPost\nPlatform accountability and human rights: a rule-of-law checklist\n13 Jan 2025\n\nPlatform accountability and human rights: a rule-of-law checklist\n\n\n\n\n\n\n\n\n\n\t\t\t\t\tContent Governance\t\t\t\t\n\n\n\n\nContent Governance \n\n\n\t\t\t\tGlobal fact-checkers were disappointed, not surprised, Meta ended its program\t\t\t\n\n10 Jan 2025\n\n\n\n\nNews\nGlobal fact-checkers were disappointed, not surprised, Meta ended its program\n\n\t\t\t\t\t\t\t\t\tRest of World ↗\t\t\t\t\t\t\t\n↗\n10 Jan 2025\n\nGlobal fact-checkers were disappointed, not surprised, Meta ended its program\n\n\n\n\n\n\n\n\n\n\t\t\t\t\tContent Governance\t\t\t\t\n\n\n\n\nContent Governance \n\n\n\t\t\t\tBrussels will be watching whether Musk breaks EU law in far-right livestream\t\t\t\n\n9 Jan 2025\n\n\n\n\nNews\nBrussels will be watching whether Musk breaks EU law in far-right livestream\n\n\t\t\t\t\t\t\t\t\tPOLITICO ↗\t\t\t\t\t\t\t\n↗\n9 Jan 2025\n\nBrussels will be watching whether Musk breaks EU law in far-right livestream\n\nLatest Updates\n\n\n\n     \n\n\n\n\n\nGrid View\nList View\n\n\n\n\n\n\n\n\n\n\n\n\n\n\t\t\t\t\tContent Governance\t\t\t\t\n\n\n\n\nContent Governance \n\n\n\t\t\t\t‘Profiting from misery’: how TikTok makes money from child begging livestreams\t\t\t\n\n6 Apr 2025\n\n\n\n\nNews\n‘Profiting from misery’: how TikTok makes money from child begging livestreams\n\n\t\t\t\t\t\t\t\t\tThe Guardian ↗\t\t\t\t\t\t\t\n↗\n6 Apr 2025\n\n‘Profiting from misery’: how TikTok makes money from child begging livestreams\n\n\n\n\n \n\t\t\t\t\tInternet Shutdowns\t\t\t\t\n\n\n\n\nInternet Shutdowns \n\n\n\t\t\t\tEmboldened offenders, endangered communities: internet shutdowns in 2024\t\t\t\n\n23 Feb 2025\n • \nAccess Now and the #KeepItOn coalition documented 296 internet shutdowns in 2024 — the highest number since 2016.\n\n\n\n\nPublication\nEmboldened offenders, endangered communities: internet shutdowns in 2024\n\n\n↗\n23 Feb 2025\n\nEmboldened offenders, endangered communities: internet shutdowns in 2024\n\n\n\n\n\n\n\n\n\n\t\t\t\t\tFreedom of Expression\t\t\t\t\n\n\n\n\nFreedom of Expression \n\n\n\t\t\t\tOur rights are at stake: it’s time to reclaim freedom of expression\t\t\t\n\n21 Feb 2025\n • \nGiven the escalating use of free speech claims as a shield for inciting hatred and violence, it is more urgent than ever to reaffirm what freedom of expression truly stands for. \n\n\n\n\nPress Release\nOur rights are at stake: it’s time to reclaim freedom of expression\n21 Feb 2025\n\nOur rights are at stake: it’s time to reclaim freedom of expression\n\n\n\n\n\n\n\n\n\n\t\t\t\t\tContent Governance\t\t\t\t\n\n\n\n\nContent Governance \n\n\n\t\t\t\tPoised to take over TikTok, Oracle is accused of clamping down on Pro-Palestine dissent\t\t\t\n\n19 Feb 2025\n\n\n\n\nNews\nPoised to take over TikTok, Oracle is accused of clamping down on Pro-Palestine dissent\n\n\t\t\t\t\t\t\t\t\tThe Intercept ↗\t\t\t\t\t\t\t\n↗\n19 Feb 2025\n\nPoised to take over TikTok, Oracle is accused of clamping down on Pro-Palestine dissent\n\n\n\n\n\n\n\n\n\n\t\t\t\t\tContent Governance\t\t\t\t\n\n\n\n\nContent Governance \n\n\n\t\t\t\tTamil website Vikatan inaccessible after It posted cartoon of PM, no official takedown order confirmed\t\t\t\n\n19 Feb 2025\n\n\n\n\nNews\nTamil website Vikatan inaccessible after It posted cartoon of PM, no official takedown order confirmed\n\n\t\t\t\t\t\t\t\t\tMedianama ↗\t\t\t\t\t\t\t\n↗\n19 Feb 2025\n\nTamil website Vikatan inaccessible after It posted cartoon of PM, no official takedown order confirmed\n\n\n\n\n\n\n\n\n\n\t\t\t\t\tInternet Shutdowns\t\t\t\t\n\n\n\n\nInternet Shutdowns \n\n\n\t\t\t\t2025 elections and internet shutdowns watch\t\t\t\n\n30 Jan 2025\n • \nGovernments around the world continue to shut down the internet during elections. Join our 2025 elections watch to #KeepItOn.\n\n\n\n\nCampaign\n2025 elections and internet shutdowns watch\n30 Jan 2025\n\n2025 elections and internet shutdowns watch\n\n\n\n\n\n\n\n\n\n\t\t\t\t\tContent Governance\t\t\t\t\n\n\n\n\nContent Governance \n\n\n\t\t\t\tTrump stand on online speech divides free speech ecosystem\t\t\t\n\n22 Jan 2025\n\n\n\n\nNews\nTrump stand on online speech divides free speech ecosystem\n\n\t\t\t\t\t\t\t\t\tHindu Businessline ↗\t\t\t\t\t\t\t\n↗\n22 Jan 2025\n\nTrump stand on online speech divides free speech ecosystem\n\n\n\n\n\n\n\n\n\n\t\t\t\t\tFreedom of Expression\t\t\t\t\n\n\n\n\nFreedom of Expression \n\n\n\t\t\t\tCeasefire in Gaza: it’s time to end digital harms and deliver justice\t\t\t\n\n20 Jan 2025\n • \nAs physical violence appears to be coming to a halt after 15 months in Gaza, Access Now further calls for a digital ceasefire.\n\n\n\n\nPress Release\nCeasefire in Gaza: it’s time to end digital harms and deliver justice\n20 Jan 2025\n\nCeasefire in Gaza: it’s time to end digital harms and deliver justice\n\n\n\n\n\n\n\n\n\n\t\t\t\t\tContent Governance\t\t\t\t\n\n\n\n\nContent Governance \n\n\n\t\t\t\tMetino ukidanje provjere činjenica ‘politička odluka sa stvarnim posljedicama’\t\t\t\n\n20 Jan 2025\n\n\n\n\nNews\nMetino ukidanje provjere činjenica ‘politička odluka sa stvarnim posljedicama’\n\n\t\t\t\t\t\t\t\t\tRadio Free Europe ↗\t\t\t\t\t\t\t\n↗\n20 Jan 2025\n\nMetino ukidanje provjere činjenica ‘politička odluka sa stvarnim posljedicama’\n\n\n\n\n\n\n\n\n\n\t\t\t\t\tFreedom of Expression\t\t\t\t\n\n\n\n\nFreedom of Expression \n\n\n\t\t\t\tTackling the “black snakes” undermining digital rights worldwide \t\t\t\n\n16 Jan 2025\n • \nAs 2025 gets underway, Access Now’s new Executive Director, Alejandro Mayoral Baños, PhD, shares his reflections on the “black snakes” threatening the digital rights movement. \n\n\n\n\nPost\nTackling the “black snakes” undermining digital rights worldwide \n16 Jan 2025\n\nTackling the “black snakes” undermining digital rights worldwide \n\n\n\n\n\n\n\n\n\n\t\t\t\t\tContent Governance\t\t\t\t\n\n\n\n\nContent Governance \n\n\n\t\t\t\tWhy Facebook ending fact checking in US is a warning sign for India\t\t\t\n\n14 Jan 2025\n\n\n\n\nNews\nWhy Facebook ending fact checking in US is a warning sign for India\n\n\t\t\t\t\t\t\t\t\tScroll ↗\t\t\t\t\t\t\t\n↗\n14 Jan 2025\n\nWhy Facebook ending fact checking in US is a warning sign for India\n\n\n\n\n\n\n\n\n\n\t\t\t\t\tContent Governance\t\t\t\t\n\n\n\n\nContent Governance \n\n\n\t\t\t\tEU regulators take a hard look at Elon Musk and X\t\t\t\n\n14 Jan 2025\n\n\n\n\nNews\nEU regulators take a hard look at Elon Musk and X\n\n\t\t\t\t\t\t\t\t\tDeutsche Welle ↗\t\t\t\t\t\t\t\n↗\n14 Jan 2025\n\nEU regulators take a hard look at Elon Musk and X\n\n\n\n\n\n\n\n\n\n\t\t\t\t\tContent Governance\t\t\t\t\n\n\n\n\nContent Governance \n\n\n\t\t\t\tPlatform accountability: a rule-of-law checklist for policymakers\t\t\t\n\n13 Jan 2025\n • \nIn this report, Access Now proposes a rule-of-law checklist to enable states to enact platform accountability regulations that are fit for purpose and protect human rights.\n\n\n\n\nPublication\nPlatform accountability: a rule-of-law checklist for policymakers\n\n\n↗\n13 Jan 2025\n\nPlatform accountability: a rule-of-law checklist for policymakers\n\n\n\n\n\n\n\n\n\n\t\t\t\t\tContent Governance\t\t\t\t\n\n\n\n\nContent Governance \n\n\n\t\t\t\tPlatform accountability and human rights: a rule-of-law checklist\t\t\t\n\n13 Jan 2025\n • \nAs policymakers around the world seek to rein in Big Tech, we define the safeguards necessary to ensure rule of law and protect human rights and democracy.\n\n\n\n\nPost\nPlatform accountability and human rights: a rule-of-law checklist\n13 Jan 2025\n\nPlatform accountability and human rights: a rule-of-law checklist\n\n\n\n\n\n\n\n\n\n\t\t\t\t\tContent Governance\t\t\t\t\n\n\n\n\nContent Governance \n\n\n\t\t\t\tGlobal fact-checkers were disappointed, not surprised, Meta ended its program\t\t\t\n\n10 Jan 2025\n\n\n\n\nNews\nGlobal fact-checkers were disappointed, not surprised, Meta ended its program\n\n\t\t\t\t\t\t\t\t\tRest of World ↗\t\t\t\t\t\t\t\n↗\n10 Jan 2025\n\nGlobal fact-checkers were disappointed, not surprised, Meta ended its program\n\n\n\n\n\n\n\n\n\n\t\t\t\t\tContent Governance\t\t\t\t\n\n\n\n\nContent Governance \n\n\n\t\t\t\tBrussels will be watching whether Musk breaks EU law in far-right livestream\t\t\t\n\n9 Jan 2025\n\n\n\n\nNews\nBrussels will be watching whether Musk breaks EU law in far-right livestream\n\n\t\t\t\t\t\t\t\t\tPOLITICO ↗\t\t\t\t\t\t\t\n↗\n9 Jan 2025\n\nBrussels will be watching whether Musk breaks EU law in far-right livestream\n\nLatest Updates\n\n\n\n     \n\n\n\n\n\nGrid View\nList View\n\nLatest Updates\n\nGrid View\nList View\n\nGrid View\nList View\n\nContent Governance\t\t\t\t\n\n\n\n\nContent Governance \n\n\n\t\t\t\t‘Profiting from misery’: how TikTok makes money from child begging livestreams\t\t\t\n\n6 Apr 2025\n\n\n\n\nNews\n‘Profiting from misery’: how TikTok makes money from child begging livestreams\n\n\t\t\t\t\t\t\t\t\tThe Guardian ↗\t\t\t\t\t\t\t\n↗\n6 Apr 2025\n\n‘Profiting from misery’: how TikTok makes money from child begging livestreams\n\n\n\n\n \n\t\t\t\t\tInternet Shutdowns\t\t\t\t\n\n\n\n\nInternet Shutdowns \n\n\n\t\t\t\tEmboldened offenders, endangered communities: internet shutdowns in 2024\t\t\t\n\n23 Feb 2025\n • \nAccess Now and the #KeepItOn coalition documented 296 internet shutdowns in 2024 — the highest number since 2016.\n\n\n\n\nPublication\nEmboldened offenders, endangered communities: internet shutdowns in 2024\n\n\n↗\n23 Feb 2025\n\nEmboldened offenders, endangered communities: internet shutdowns in 2024\n\n\n\n\n\n\n\n\n\n\t\t\t\t\tFreedom of Expression\t\t\t\t\n\n\n\n\nFreedom of Expression \n\n\n\t\t\t\tOur rights are at stake: it’s time to reclaim freedom of expression\t\t\t\n\n21 Feb 2025\n • \nGiven the escalating use of free speech claims as a shield for inciting hatred and violence, it is more urgent than ever to reaffirm what freedom of expression truly stands for. \n\n\n\n\nPress Release\nOur rights are at stake: it’s time to reclaim freedom of expression\n21 Feb 2025\n\nOur rights are at stake: it’s time to reclaim freedom of expression\n\n\n\n\n\n\n\n\n\n\t\t\t\t\tContent Governance\t\t\t\t\n\n\n\n\nContent Governance \n\n\n\t\t\t\tPoised to take over TikTok, Oracle is accused of clamping down on Pro-Palestine dissent\t\t\t\n\n19 Feb 2025\n\n\n\n\nNews\nPoised to take over TikTok, Oracle is accused of clamping down on Pro-Palestine dissent\n\n\t\t\t\t\t\t\t\t\tThe Intercept ↗\t\t\t\t\t\t\t\n↗\n19 Feb 2025\n\nPoised to take over TikTok, Oracle is accused of clamping down on Pro-Palestine dissent\n\n\n\n\n\n\n\n\n\n\t\t\t\t\tContent Governance\t\t\t\t\n\n\n\n\nContent Governance \n\n\n\t\t\t\tTamil website Vikatan inaccessible after It posted cartoon of PM, no official takedown order confirmed\t\t\t\n\n19 Feb 2025\n\n\n\n\nNews\nTamil website Vikatan inaccessible after It posted cartoon of PM, no official takedown order confirmed\n\n\t\t\t\t\t\t\t\t\tMedianama ↗\t\t\t\t\t\t\t\n↗\n19 Feb 2025\n\nTamil website Vikatan inaccessible after It posted cartoon of PM, no official takedown order confirmed\n\n\n\n\n\n\n\n\n\n\t\t\t\t\tInternet Shutdowns\t\t\t\t\n\n\n\n\nInternet Shutdowns \n\n\n\t\t\t\t2025 elections and internet shutdowns watch\t\t\t\n\n30 Jan 2025\n • \nGovernments around the world continue to shut down the internet during elections. Join our 2025 elections watch to #KeepItOn.\n\n\n\n\nCampaign\n2025 elections and internet shutdowns watch\n30 Jan 2025\n\n2025 elections and internet shutdowns watch\n\n\n\n\n\n\n\n\n\n\t\t\t\t\tContent Governance\t\t\t\t\n\n\n\n\nContent Governance \n\n\n\t\t\t\tTrump stand on online speech divides free speech ecosystem\t\t\t\n\n22 Jan 2025\n\n\n\n\nNews\nTrump stand on online speech divides free speech ecosystem\n\n\t\t\t\t\t\t\t\t\tHindu Businessline ↗\t\t\t\t\t\t\t\n↗\n22 Jan 2025\n\nTrump stand on online speech divides free speech ecosystem\n\n\n\n\n\n\n\n\n\n\t\t\t\t\tFreedom of Expression\t\t\t\t\n\n\n\n\nFreedom of Expression \n\n\n\t\t\t\tCeasefire in Gaza: it’s time to end digital harms and deliver justice\t\t\t\n\n20 Jan 2025\n • \nAs physical violence appears to be coming to a halt after 15 months in Gaza, Access Now further calls for a digital ceasefire.\n\n\n\n\nPress Release\nCeasefire in Gaza: it’s time to end digital harms and deliver justice\n20 Jan 2025\n\nCeasefire in Gaza: it’s time to end digital harms and deliver justice\n\n\n\n\n\n\n\n\n\n\t\t\t\t\tContent Governance\t\t\t\t\n\n\n\n\nContent Governance \n\n\n\t\t\t\tMetino ukidanje provjere činjenica ‘politička odluka sa stvarnim posljedicama’\t\t\t\n\n20 Jan 2025\n\n\n\n\nNews\nMetino ukidanje provjere činjenica ‘politička odluka sa stvarnim posljedicama’\n\n\t\t\t\t\t\t\t\t\tRadio Free Europe ↗\t\t\t\t\t\t\t\n↗\n20 Jan 2025\n\nMetino ukidanje provjere činjenica ‘politička odluka sa stvarnim posljedicama’\n\n\n\n\n\n\n\n\n\n\t\t\t\t\tFreedom of Expression\t\t\t\t\n\n\n\n\nFreedom of Expression \n\n\n\t\t\t\tTackling the “black snakes” undermining digital rights worldwide \t\t\t\n\n16 Jan 2025\n • \nAs 2025 gets underway, Access Now’s new Executive Director, Alejandro Mayoral Baños, PhD, shares his reflections on the “black snakes” threatening the digital rights movement. \n\n\n\n\nPost\nTackling the “black snakes” undermining digital rights worldwide \n16 Jan 2025\n\nTackling the “black snakes” undermining digital rights worldwide \n\n\n\n\n\n\n\n\n\n\t\t\t\t\tContent Governance\t\t\t\t\n\n\n\n\nContent Governance \n\n\n\t\t\t\tWhy Facebook ending fact checking in US is a warning sign for India\t\t\t\n\n14 Jan 2025\n\n\n\n\nNews\nWhy Facebook ending fact checking in US is a warning sign for India\n\n\t\t\t\t\t\t\t\t\tScroll ↗\t\t\t\t\t\t\t\n↗\n14 Jan 2025\n\nWhy Facebook ending fact checking in US is a warning sign for India\n\n\n\n\n\n\n\n\n\n\t\t\t\t\tContent Governance\t\t\t\t\n\n\n\n\nContent Governance \n\n\n\t\t\t\tEU regulators take a hard look at Elon Musk and X\t\t\t\n\n14 Jan 2025\n\n\n\n\nNews\nEU regulators take a hard look at Elon Musk and X\n\n\t\t\t\t\t\t\t\t\tDeutsche Welle ↗\t\t\t\t\t\t\t\n↗\n14 Jan 2025\n\nEU regulators take a hard look at Elon Musk and X\n\n\n\n\n\n\n\n\n\n\t\t\t\t\tContent Governance\t\t\t\t\n\n\n\n\nContent Governance \n\n\n\t\t\t\tPlatform accountability: a rule-of-law checklist for policymakers\t\t\t\n\n13 Jan 2025\n • \nIn this report, Access Now proposes a rule-of-law checklist to enable states to enact platform accountability regulations that are fit for purpose and protect human rights.\n\n\n\n\nPublication\nPlatform accountability: a rule-of-law checklist for policymakers\n\n\n↗\n13 Jan 2025\n\nPlatform accountability: a rule-of-law checklist for policymakers\n\n\n\n\n\n\n\n\n\n\t\t\t\t\tContent Governance\t\t\t\t\n\n\n\n\nContent Governance \n\n\n\t\t\t\tPlatform accountability and human rights: a rule-of-law checklist\t\t\t\n\n13 Jan 2025\n • \nAs policymakers around the world seek to rein in Big Tech, we define the safeguards necessary to ensure rule of law and protect human rights and democracy.\n\n\n\n\nPost\nPlatform accountability and human rights: a rule-of-law checklist\n13 Jan 2025\n\nPlatform accountability and human rights: a rule-of-law checklist\n\n\n\n\n\n\n\n\n\n\t\t\t\t\tContent Governance\t\t\t\t\n\n\n\n\nContent Governance \n\n\n\t\t\t\tGlobal fact-checkers were disappointed, not surprised, Meta ended its program\t\t\t\n\n10 Jan 2025\n\n\n\n\nNews\nGlobal fact-checkers were disappointed, not surprised, Meta ended its program\n\n\t\t\t\t\t\t\t\t\tRest of World ↗\t\t\t\t\t\t\t\n↗\n10 Jan 2025\n\nGlobal fact-checkers were disappointed, not surprised, Meta ended its program\n\n\n\n\n\n\n\n\n\n\t\t\t\t\tContent Governance\t\t\t\t\n\n\n\n\nContent Governance \n\n\n\t\t\t\tBrussels will be watching whether Musk breaks EU law in far-right livestream\t\t\t\n\n9 Jan 2025\n\n\n\n\nNews\nBrussels will be watching whether Musk breaks EU law in far-right livestream\n\n\t\t\t\t\t\t\t\t\tPOLITICO ↗\t\t\t\t\t\t\t\n↗\n9 Jan 2025\n\nBrussels will be watching whether Musk breaks EU law in far-right livestream\n\nContent Governance\t\t\t\t\n\n\n\n\nContent Governance \n\n\n\t\t\t\t‘Profiting from misery’: how TikTok makes money from child begging livestreams\t\t\t\n\n6 Apr 2025\n\n\n\n\nNews\n‘Profiting from misery’: how TikTok makes money from child begging livestreams\n\n\t\t\t\t\t\t\t\t\tThe Guardian ↗\t\t\t\t\t\t\t\n↗\n6 Apr 2025\n\n‘Profiting from misery’: how TikTok makes money from child begging livestreams\n\nContent Governance\t\t\t\t\n\n\n\n\nContent Governance \n\n\n\t\t\t\t‘Profiting from misery’: how TikTok makes money from child begging livestreams\t\t\t\n\n6 Apr 2025\n\nContent Governance\n\nContent Governance\n\nContent Governance \n\n\n\t\t\t\t‘Profiting from misery’: how TikTok makes money from child begging livestreams\t\t\t\n\n6 Apr 2025\n\nContent Governance\n\nContent Governance\n\n6 Apr 2025\n\nNews\n‘Profiting from misery’: how TikTok makes money from child begging livestreams\n\n\t\t\t\t\t\t\t\t\tThe Guardian ↗\t\t\t\t\t\t\t\n↗\n6 Apr 2025\n\nNews\n\n‘Profiting from misery’: how TikTok makes money from child begging livestreams\n\nThe Guardian ↗\n\n↗\n\n6 Apr 2025\n\nInternet Shutdowns\t\t\t\t\n\n\n\n\nInternet Shutdowns \n\n\n\t\t\t\tEmboldened offenders, endangered communities: internet shutdowns in 2024\t\t\t\n\n23 Feb 2025\n • \nAccess Now and the #KeepItOn coalition documented 296 internet shutdowns in 2024 — the highest number since 2016.\n\n\n\n\nPublication\nEmboldened offenders, endangered communities: internet shutdowns in 2024\n\n\n↗\n23 Feb 2025\n\nEmboldened offenders, endangered communities: internet shutdowns in 2024\n\nInternet Shutdowns\t\t\t\t\n\n\n\n\nInternet Shutdowns \n\n\n\t\t\t\tEmboldened offenders, endangered communities: internet shutdowns in 2024\t\t\t\n\n23 Feb 2025\n • \nAccess Now and the #KeepItOn coalition documented 296 internet shutdowns in 2024 — the highest number since 2016.\n\nInternet Shutdowns\n\nInternet Shutdowns\n\nInternet Shutdowns \n\n\n\t\t\t\tEmboldened offenders, endangered communities: internet shutdowns in 2024\t\t\t\n\n23 Feb 2025\n • \nAccess Now and the #KeepItOn coalition documented 296 internet shutdowns in 2024 — the highest number since 2016.\n\nInternet Shutdowns\n\nInternet Shutdowns\n\n23 Feb 2025\n • \nAccess Now and the #KeepItOn coalition documented 296 internet shutdowns in 2024 — the highest number since 2016.\n\nAccess Now and the #KeepItOn coalition documented 296 internet shutdowns in 2024 — the highest number since 2016.\n\nPublication\nEmboldened offenders, endangered communities: internet shutdowns in 2024\n\n\n↗\n23 Feb 2025\n\nPublication\n\nEmboldened offenders, endangered communities: internet shutdowns in 2024\n\n↗\n\n23 Feb 2025\n\nFreedom of Expression\t\t\t\t\n\n\n\n\nFreedom of Expression \n\n\n\t\t\t\tOur rights are at stake: it’s time to reclaim freedom of expression\t\t\t\n\n21 Feb 2025\n • \nGiven the escalating use of free speech claims as a shield for inciting hatred and violence, it is more urgent than ever to reaffirm what freedom of expression truly stands for. \n\n\n\n\nPress Release\nOur rights are at stake: it’s time to reclaim freedom of expression\n21 Feb 2025\n\nOur rights are at stake: it’s time to reclaim freedom of expression\n\nFreedom of Expression\t\t\t\t\n\n\n\n\nFreedom of Expression \n\n\n\t\t\t\tOur rights are at stake: it’s time to reclaim freedom of expression\t\t\t\n\n21 Feb 2025\n • \nGiven the escalating use of free speech claims as a shield for inciting hatred and violence, it is more urgent than ever to reaffirm what freedom of expression truly stands for.\n\nFreedom of Expression\n\nFreedom of Expression\n\nFreedom of Expression \n\n\n\t\t\t\tOur rights are at stake: it’s time to reclaim freedom of expression\t\t\t\n\n21 Feb 2025\n • \nGiven the escalating use of free speech claims as a shield for inciting hatred and violence, it is more urgent than ever to reaffirm what freedom of expression truly stands for.\n\nFreedom of Expression\n\nFreedom of Expression\n\n21 Feb 2025\n • \nGiven the escalating use of free speech claims as a shield for inciting hatred and violence, it is more urgent than ever to reaffirm what freedom of expression truly stands for.\n\nGiven the escalating use of free speech claims as a shield for inciting hatred and violence, it is more urgent than ever to reaffirm what freedom of expression truly stands for.\n\nPress Release\nOur rights are at stake: it’s time to reclaim freedom of expression\n21 Feb 2025\n\nPress Release\n\nOur rights are at stake: it’s time to reclaim freedom of expression\n\n21 Feb 2025\n\nContent Governance\t\t\t\t\n\n\n\n\nContent Governance \n\n\n\t\t\t\tPoised to take over TikTok, Oracle is accused of clamping down on Pro-Palestine dissent\t\t\t\n\n19 Feb 2025\n\n\n\n\nNews\nPoised to take over TikTok, Oracle is accused of clamping down on Pro-Palestine dissent\n\n\t\t\t\t\t\t\t\t\tThe Intercept ↗\t\t\t\t\t\t\t\n↗\n19 Feb 2025\n\nPoised to take over TikTok, Oracle is accused of clamping down on Pro-Palestine dissent\n\nContent Governance\t\t\t\t\n\n\n\n\nContent Governance \n\n\n\t\t\t\tPoised to take over TikTok, Oracle is accused of clamping down on Pro-Palestine dissent\t\t\t\n\n19 Feb 2025\n\nContent Governance\n\nContent Governance\n\nContent Governance \n\n\n\t\t\t\tPoised to take over TikTok, Oracle is accused of clamping down on Pro-Palestine dissent\t\t\t\n\n19 Feb 2025\n\nContent Governance\n\nContent Governance\n\n19 Feb 2025\n\nNews\nPoised to take over TikTok, Oracle is accused of clamping down on Pro-Palestine dissent\n\n\t\t\t\t\t\t\t\t\tThe Intercept ↗\t\t\t\t\t\t\t\n↗\n19 Feb 2025\n\nNews\n\nPoised to take over TikTok, Oracle is accused of clamping down on Pro-Palestine dissent\n\nThe Intercept ↗\n\n↗\n\n19 Feb 2025\n\nContent Governance\t\t\t\t\n\n\n\n\nContent Governance \n\n\n\t\t\t\tTamil website Vikatan inaccessible after It posted cartoon of PM, no official takedown order confirmed\t\t\t\n\n19 Feb 2025\n\n\n\n\nNews\nTamil website Vikatan inaccessible after It posted cartoon of PM, no official takedown order confirmed\n\n\t\t\t\t\t\t\t\t\tMedianama ↗\t\t\t\t\t\t\t\n↗\n19 Feb 2025\n\nTamil website Vikatan inaccessible after It posted cartoon of PM, no official takedown order confirmed\n\nContent Governance\t\t\t\t\n\n\n\n\nContent Governance \n\n\n\t\t\t\tTamil website Vikatan inaccessible after It posted cartoon of PM, no official takedown order confirmed\t\t\t\n\n19 Feb 2025\n\nContent Governance\n\nContent Governance\n\nContent Governance \n\n\n\t\t\t\tTamil website Vikatan inaccessible after It posted cartoon of PM, no official takedown order confirmed\t\t\t\n\n19 Feb 2025\n\nContent Governance\n\nContent Governance\n\n19 Feb 2025\n\nNews\nTamil website Vikatan inaccessible after It posted cartoon of PM, no official takedown order confirmed\n\n\t\t\t\t\t\t\t\t\tMedianama ↗\t\t\t\t\t\t\t\n↗\n19 Feb 2025\n\nNews\n\nTamil website Vikatan inaccessible after It posted cartoon of PM, no official takedown order confirmed\n\nMedianama ↗\n\n↗\n\n19 Feb 2025\n\nInternet Shutdowns\t\t\t\t\n\n\n\n\nInternet Shutdowns \n\n\n\t\t\t\t2025 elections and internet shutdowns watch\t\t\t\n\n30 Jan 2025\n • \nGovernments around the world continue to shut down the internet during elections. Join our 2025 elections watch to #KeepItOn.\n\n\n\n\nCampaign\n2025 elections and internet shutdowns watch\n30 Jan 2025\n\n2025 elections and internet shutdowns watch\n\nInternet Shutdowns\t\t\t\t\n\n\n\n\nInternet Shutdowns \n\n\n\t\t\t\t2025 elections and internet shutdowns watch\t\t\t\n\n30 Jan 2025\n • \nGovernments around the world continue to shut down the internet during elections. Join our 2025 elections watch to #KeepItOn.\n\nInternet Shutdowns\n\nInternet Shutdowns\n\nInternet Shutdowns \n\n\n\t\t\t\t2025 elections and internet shutdowns watch\t\t\t\n\n30 Jan 2025\n • \nGovernments around the world continue to shut down the internet during elections. Join our 2025 elections watch to #KeepItOn.\n\nInternet Shutdowns\n\nInternet Shutdowns\n\n30 Jan 2025\n • \nGovernments around the world continue to shut down the internet during elections. Join our 2025 elections watch to #KeepItOn.\n\nGovernments around the world continue to shut down the internet during elections. Join our 2025 elections watch to #KeepItOn.\n\nCampaign\n2025 elections and internet shutdowns watch\n30 Jan 2025\n\nCampaign\n\n2025 elections and internet shutdowns watch\n\n30 Jan 2025\n\nContent Governance\t\t\t\t\n\n\n\n\nContent Governance \n\n\n\t\t\t\tTrump stand on online speech divides free speech ecosystem\t\t\t\n\n22 Jan 2025\n\n\n\n\nNews\nTrump stand on online speech divides free speech ecosystem\n\n\t\t\t\t\t\t\t\t\tHindu Businessline ↗\t\t\t\t\t\t\t\n↗\n22 Jan 2025\n\nTrump stand on online speech divides free speech ecosystem\n\nContent Governance\t\t\t\t\n\n\n\n\nContent Governance \n\n\n\t\t\t\tTrump stand on online speech divides free speech ecosystem\t\t\t\n\n22 Jan 2025\n\nContent Governance\n\nContent Governance\n\nContent Governance \n\n\n\t\t\t\tTrump stand on online speech divides free speech ecosystem\t\t\t\n\n22 Jan 2025\n\nContent Governance\n\nContent Governance\n\n22 Jan 2025\n\nNews\nTrump stand on online speech divides free speech ecosystem\n\n\t\t\t\t\t\t\t\t\tHindu Businessline ↗\t\t\t\t\t\t\t\n↗\n22 Jan 2025\n\nNews\n\nTrump stand on online speech divides free speech ecosystem\n\nHindu Businessline ↗\n\n↗\n\n22 Jan 2025\n\nFreedom of Expression\t\t\t\t\n\n\n\n\nFreedom of Expression \n\n\n\t\t\t\tCeasefire in Gaza: it’s time to end digital harms and deliver justice\t\t\t\n\n20 Jan 2025\n • \nAs physical violence appears to be coming to a halt after 15 months in Gaza, Access Now further calls for a digital ceasefire.\n\n\n\n\nPress Release\nCeasefire in Gaza: it’s time to end digital harms and deliver justice\n20 Jan 2025\n\nCeasefire in Gaza: it’s time to end digital harms and deliver justice\n\nFreedom of Expression\t\t\t\t\n\n\n\n\nFreedom of Expression \n\n\n\t\t\t\tCeasefire in Gaza: it’s time to end digital harms and deliver justice\t\t\t\n\n20 Jan 2025\n • \nAs physical violence appears to be coming to a halt after 15 months in Gaza, Access Now further calls for a digital ceasefire.\n\nFreedom of Expression\n\nFreedom of Expression\n\nFreedom of Expression \n\n\n\t\t\t\tCeasefire in Gaza: it’s time to end digital harms and deliver justice\t\t\t\n\n20 Jan 2025\n • \nAs physical violence appears to be coming to a halt after 15 months in Gaza, Access Now further calls for a digital ceasefire.\n\nFreedom of Expression\n\nFreedom of Expression\n\n20 Jan 2025\n • \nAs physical violence appears to be coming to a halt after 15 months in Gaza, Access Now further calls for a digital ceasefire.\n\nAs physical violence appears to be coming to a halt after 15 months in Gaza, Access Now further calls for a digital ceasefire.\n\nPress Release\nCeasefire in Gaza: it’s time to end digital harms and deliver justice\n20 Jan 2025\n\nPress Release\n\nCeasefire in Gaza: it’s time to end digital harms and deliver justice\n\n20 Jan 2025\n\nContent Governance\t\t\t\t\n\n\n\n\nContent Governance \n\n\n\t\t\t\tMetino ukidanje provjere činjenica ‘politička odluka sa stvarnim posljedicama’\t\t\t\n\n20 Jan 2025\n\n\n\n\nNews\nMetino ukidanje provjere činjenica ‘politička odluka sa stvarnim posljedicama’\n\n\t\t\t\t\t\t\t\t\tRadio Free Europe ↗\t\t\t\t\t\t\t\n↗\n20 Jan 2025\n\nMetino ukidanje provjere činjenica ‘politička odluka sa stvarnim posljedicama’\n\nContent Governance\t\t\t\t\n\n\n\n\nContent Governance \n\n\n\t\t\t\tMetino ukidanje provjere činjenica ‘politička odluka sa stvarnim posljedicama’\t\t\t\n\n20 Jan 2025\n\nContent Governance\n\nContent Governance\n\nContent Governance \n\n\n\t\t\t\tMetino ukidanje provjere činjenica ‘politička odluka sa stvarnim posljedicama’\t\t\t\n\n20 Jan 2025\n\nContent Governance\n\nContent Governance\n\n20 Jan 2025\n\nNews\nMetino ukidanje provjere činjenica ‘politička odluka sa stvarnim posljedicama’\n\n\t\t\t\t\t\t\t\t\tRadio Free Europe ↗\t\t\t\t\t\t\t\n↗\n20 Jan 2025\n\nNews\n\nMetino ukidanje provjere činjenica ‘politička odluka sa stvarnim posljedicama’\n\nRadio Free Europe ↗\n\n↗\n\n20 Jan 2025\n\nFreedom of Expression\t\t\t\t\n\n\n\n\nFreedom of Expression \n\n\n\t\t\t\tTackling the “black snakes” undermining digital rights worldwide \t\t\t\n\n16 Jan 2025\n • \nAs 2025 gets underway, Access Now’s new Executive Director, Alejandro Mayoral Baños, PhD, shares his reflections on the “black snakes” threatening the digital rights movement. \n\n\n\n\nPost\nTackling the “black snakes” undermining digital rights worldwide \n16 Jan 2025\n\nTackling the “black snakes” undermining digital rights worldwide\n\nFreedom of Expression\t\t\t\t\n\n\n\n\nFreedom of Expression \n\n\n\t\t\t\tTackling the “black snakes” undermining digital rights worldwide \t\t\t\n\n16 Jan 2025\n • \nAs 2025 gets underway, Access Now’s new Executive Director, Alejandro Mayoral Baños, PhD, shares his reflections on the “black snakes” threatening the digital rights movement.\n\nFreedom of Expression\n\nFreedom of Expression\n\nFreedom of Expression \n\n\n\t\t\t\tTackling the “black snakes” undermining digital rights worldwide \t\t\t\n\n16 Jan 2025\n • \nAs 2025 gets underway, Access Now’s new Executive Director, Alejandro Mayoral Baños, PhD, shares his reflections on the “black snakes” threatening the digital rights movement.\n\nFreedom of Expression\n\nFreedom of Expression\n\n16 Jan 2025\n • \nAs 2025 gets underway, Access Now’s new Executive Director, Alejandro Mayoral Baños, PhD, shares his reflections on the “black snakes” threatening the digital rights movement.\n\nAs 2025 gets underway, Access Now’s new Executive Director, Alejandro Mayoral Baños, PhD, shares his reflections on the “black snakes” threatening the digital rights movement.\n\nPost\nTackling the “black snakes” undermining digital rights worldwide \n16 Jan 2025\n\nPost\n\nTackling the “black snakes” undermining digital rights worldwide\n\n16 Jan 2025\n\nContent Governance\t\t\t\t\n\n\n\n\nContent Governance \n\n\n\t\t\t\tWhy Facebook ending fact checking in US is a warning sign for India\t\t\t\n\n14 Jan 2025\n\n\n\n\nNews\nWhy Facebook ending fact checking in US is a warning sign for India\n\n\t\t\t\t\t\t\t\t\tScroll ↗\t\t\t\t\t\t\t\n↗\n14 Jan 2025\n\nWhy Facebook ending fact checking in US is a warning sign for India\n\nContent Governance\t\t\t\t\n\n\n\n\nContent Governance \n\n\n\t\t\t\tWhy Facebook ending fact checking in US is a warning sign for India\t\t\t\n\n14 Jan 2025\n\nContent Governance\n\nContent Governance\n\nContent Governance \n\n\n\t\t\t\tWhy Facebook ending fact checking in US is a warning sign for India\t\t\t\n\n14 Jan 2025\n\nContent Governance\n\nContent Governance\n\n14 Jan 2025\n\nNews\nWhy Facebook ending fact checking in US is a warning sign for India\n\n\t\t\t\t\t\t\t\t\tScroll ↗\t\t\t\t\t\t\t\n↗\n14 Jan 2025\n\nNews\n\nWhy Facebook ending fact checking in US is a warning sign for India\n\nScroll ↗\n\n↗\n\n14 Jan 2025\n\nContent Governance\t\t\t\t\n\n\n\n\nContent Governance \n\n\n\t\t\t\tEU regulators take a hard look at Elon Musk and X\t\t\t\n\n14 Jan 2025\n\n\n\n\nNews\nEU regulators take a hard look at Elon Musk and X\n\n\t\t\t\t\t\t\t\t\tDeutsche Welle ↗\t\t\t\t\t\t\t\n↗\n14 Jan 2025\n\nEU regulators take a hard look at Elon Musk and X\n\nContent Governance\t\t\t\t\n\n\n\n\nContent Governance \n\n\n\t\t\t\tEU regulators take a hard look at Elon Musk and X\t\t\t\n\n14 Jan 2025\n\nContent Governance\n\nContent Governance\n\nContent Governance \n\n\n\t\t\t\tEU regulators take a hard look at Elon Musk and X\t\t\t\n\n14 Jan 2025\n\nContent Governance\n\nContent Governance\n\n14 Jan 2025\n\nNews\nEU regulators take a hard look at Elon Musk and X\n\n\t\t\t\t\t\t\t\t\tDeutsche Welle ↗\t\t\t\t\t\t\t\n↗\n14 Jan 2025\n\nNews\n\nEU regulators take a hard look at Elon Musk and X\n\nDeutsche Welle ↗\n\n↗\n\n14 Jan 2025\n\nContent Governance\t\t\t\t\n\n\n\n\nContent Governance \n\n\n\t\t\t\tPlatform accountability: a rule-of-law checklist for policymakers\t\t\t\n\n13 Jan 2025\n • \nIn this report, Access Now proposes a rule-of-law checklist to enable states to enact platform accountability regulations that are fit for purpose and protect human rights.\n\n\n\n\nPublication\nPlatform accountability: a rule-of-law checklist for policymakers\n\n\n↗\n13 Jan 2025\n\nPlatform accountability: a rule-of-law checklist for policymakers\n\nContent Governance\t\t\t\t\n\n\n\n\nContent Governance \n\n\n\t\t\t\tPlatform accountability: a rule-of-law checklist for policymakers\t\t\t\n\n13 Jan 2025\n • \nIn this report, Access Now proposes a rule-of-law checklist to enable states to enact platform accountability regulations that are fit for purpose and protect human rights.\n\nContent Governance\n\nContent Governance\n\nContent Governance \n\n\n\t\t\t\tPlatform accountability: a rule-of-law checklist for policymakers\t\t\t\n\n13 Jan 2025\n • \nIn this report, Access Now proposes a rule-of-law checklist to enable states to enact platform accountability regulations that are fit for purpose and protect human rights.\n\nContent Governance\n\nContent Governance\n\n13 Jan 2025\n • \nIn this report, Access Now proposes a rule-of-law checklist to enable states to enact platform accountability regulations that are fit for purpose and protect human rights.\n\nIn this report, Access Now proposes a rule-of-law checklist to enable states to enact platform accountability regulations that are fit for purpose and protect human rights.\n\nPublication\nPlatform accountability: a rule-of-law checklist for policymakers\n\n\n↗\n13 Jan 2025\n\nPublication\n\nPlatform accountability: a rule-of-law checklist for policymakers\n\n↗\n\n13 Jan 2025\n\nContent Governance\t\t\t\t\n\n\n\n\nContent Governance \n\n\n\t\t\t\tPlatform accountability and human rights: a rule-of-law checklist\t\t\t\n\n13 Jan 2025\n • \nAs policymakers around the world seek to rein in Big Tech, we define the safeguards necessary to ensure rule of law and protect human rights and democracy.\n\n\n\n\nPost\nPlatform accountability and human rights: a rule-of-law checklist\n13 Jan 2025\n\nPlatform accountability and human rights: a rule-of-law checklist\n\nContent Governance\t\t\t\t\n\n\n\n\nContent Governance \n\n\n\t\t\t\tPlatform accountability and human rights: a rule-of-law checklist\t\t\t\n\n13 Jan 2025\n • \nAs policymakers around the world seek to rein in Big Tech, we define the safeguards necessary to ensure rule of law and protect human rights and democracy.\n\nContent Governance\n\nContent Governance\n\nContent Governance \n\n\n\t\t\t\tPlatform accountability and human rights: a rule-of-law checklist\t\t\t\n\n13 Jan 2025\n • \nAs policymakers around the world seek to rein in Big Tech, we define the safeguards necessary to ensure rule of law and protect human rights and democracy.\n\nContent Governance\n\nContent Governance\n\n13 Jan 2025\n • \nAs policymakers around the world seek to rein in Big Tech, we define the safeguards necessary to ensure rule of law and protect human rights and democracy.\n\nAs policymakers around the world seek to rein in Big Tech, we define the safeguards necessary to ensure rule of law and protect human rights and democracy.\n\nPost\nPlatform accountability and human rights: a rule-of-law checklist\n13 Jan 2025\n\nPost\n\nPlatform accountability and human rights: a rule-of-law checklist\n\n13 Jan 2025\n\nContent Governance\t\t\t\t\n\n\n\n\nContent Governance \n\n\n\t\t\t\tGlobal fact-checkers were disappointed, not surprised, Meta ended its program\t\t\t\n\n10 Jan 2025\n\n\n\n\nNews\nGlobal fact-checkers were disappointed, not surprised, Meta ended its program\n\n\t\t\t\t\t\t\t\t\tRest of World ↗\t\t\t\t\t\t\t\n↗\n10 Jan 2025\n\nGlobal fact-checkers were disappointed, not surprised, Meta ended its program\n\nContent Governance\t\t\t\t\n\n\n\n\nContent Governance \n\n\n\t\t\t\tGlobal fact-checkers were disappointed, not surprised, Meta ended its program\t\t\t\n\n10 Jan 2025\n\nContent Governance\n\nContent Governance\n\nContent Governance \n\n\n\t\t\t\tGlobal fact-checkers were disappointed, not surprised, Meta ended its program\t\t\t\n\n10 Jan 2025\n\nContent Governance\n\nContent Governance\n\n10 Jan 2025\n\nNews\nGlobal fact-checkers were disappointed, not surprised, Meta ended its program\n\n\t\t\t\t\t\t\t\t\tRest of World ↗\t\t\t\t\t\t\t\n↗\n10 Jan 2025\n\nNews\n\nGlobal fact-checkers were disappointed, not surprised, Meta ended its program\n\nRest of World ↗\n\n↗\n\n10 Jan 2025\n\nContent Governance\t\t\t\t\n\n\n\n\nContent Governance \n\n\n\t\t\t\tBrussels will be watching whether Musk breaks EU law in far-right livestream\t\t\t\n\n9 Jan 2025\n\n\n\n\nNews\nBrussels will be watching whether Musk breaks EU law in far-right livestream\n\n\t\t\t\t\t\t\t\t\tPOLITICO ↗\t\t\t\t\t\t\t\n↗\n9 Jan 2025\n\nBrussels will be watching whether Musk breaks EU law in far-right livestream\n\nContent Governance\t\t\t\t\n\n\n\n\nContent Governance \n\n\n\t\t\t\tBrussels will be watching whether Musk breaks EU law in far-right livestream\t\t\t\n\n9 Jan 2025\n\nContent Governance\n\nContent Governance\n\nContent Governance \n\n\n\t\t\t\tBrussels will be watching whether Musk breaks EU law in far-right livestream\t\t\t\n\n9 Jan 2025\n\nContent Governance\n\nContent Governance\n\n9 Jan 2025\n\nNews\nBrussels will be watching whether Musk breaks EU law in far-right livestream\n\n\t\t\t\t\t\t\t\t\tPOLITICO ↗\t\t\t\t\t\t\t\n↗\n9 Jan 2025\n\nNews\n\nBrussels will be watching whether Musk breaks EU law in far-right livestream\n\nPOLITICO ↗\n\n↗\n\n9 Jan 2025\n\nHelp keep the internet open and secure.\nSubscribe to our action alerts and weekly newsletter\n\"*\" indicates required fields\n\nThis field is hidden when viewing the form\n\nSubscribe to Access Express\nThis field is hidden when viewing the form\n\nSubscribe to Action Alerts\nName\n\n\nFirst\n\n\n\nLast\n\nEmail*\n\nCountryCountryAfghanistanÅland IslandsAlbaniaAlgeriaAmerican SamoaAndorraAngolaAnguillaAntigua and BarbudaArgentinaArmeniaArubaAustraliaAustriaAzerbaijanBahamasBahrainBangladeshBarbadosBelarusBelgiumBelizeBeninBermudaBhutanBoliviaBonaire, Sint Eustatius and SabaBosnia and HerzegovinaBotswanaBrazilBritish Indian Ocean TerritoryBritish Virgin IslandsBruneiBulgariaBurkina FasoBurundiCambodiaCameroonCanadaCape VerdeCayman IslandsCentral African RepublicChadChileChinaChristmas IslandColombiaComorosCook IslandsCosta RicaCôte d'IvoireCroatiaCubaCuraçaoCyprusCzech RepublicDemocratic Republic of the CongoDenmarkDjiboutiDominicaDominican RepublicEast TimorEcuadorEgyptEl SalvadorEquatorial GuineaEritreaEstoniaEswatiniEthiopiaFalkland IslandsFaroe IslandsFijiFinlandFranceFrench GuianaFrench PolynesiaFrench Southern TerritoriesGabonGeorgiaGermanyGhanaGibraltarGreeceGreenlandGrenadaGuadeloupeGuamGuatemalaGuernseyGuineaGuinea-BissauGuyanaHaitiHondurasHong KongHungaryIcelandIndiaIndonesiaIranIraqIrelandIsraelItalyJamaicaJapanJordanKazakhstanKenyaKiribatiKosovoKuwaitKyrgyzstanLaosLatviaLebanonLesothoLiberiaLibyaLiechtensteinLithuaniaLuxembourgMacauMadagascarMalawiMalaysiaMaldivesMaliMaltaMarshall IslandsMartiniqueMauritaniaMauritiusMayotteMexicoMicronesiaMoldovaMonacoMongoliaMontenegroMontserratMoroccoMozambiqueMyanmarNamibiaNauruNepalNetherlands AntillesNew CaledoniaNew ZealandNicaraguaNigerNigeriaNiueNorfolk IslandNorth KoreaNorth MacedoniaNorthern Mariana IslandsNorwayOmanPakistanPalauPalestinePanamaPapua New GuineaParaguayPeruPhilippinesPitcairn IslandPolandPortugalPuerto RicoQatarRepublic of the CongoReunionRomaniaRussiaRwandaSaint BarthélemySaint Kitts and NevisSaint LuciaSaint Vincent and the GrenadinesSamoaSan MarinoSão Tomé and PríncipeSaudi ArabiaSenegalSerbiaSeychellesSierra LeoneSingaporeSlovakiaSloveniaSolomon IslandsSomaliaSomalilandSouth AfricaSouth KoreaSouth SudanSpainSri LankaSt. HelenaSt. Pierre and MiquelonSudanSurinameSwedenSwitzerlandSyriaTaiwanTajikistanTanzaniaThailandThe GambiaThe NetherlandsTogoTokelauTongaTrinidad and TobagoTunisiaTurkeyTurkmenistanTurks and Caicos IslandsTuvaluUgandaUkraineUnited Arab EmiratesUnited KingdomUnited StatesUruguayUzbekistanVanuatuVatican CityVenezuelaVietnamVirgin Islands (U.S.)Wallis and Futuna IslandsWestern SaharaYemenZambiaZimbabwePostal CodeEmailThis field is for validation purposes and should be left unchanged.\n \n\n\n\n\n\n\n\n\n\n\n\n\n\n\n\nYour info is secure with us\n\nHelp keep the internet open and secure.\nSubscribe to our action alerts and weekly newsletter\n\"*\" indicates required fields\n\nThis field is hidden when viewing the form\n\nSubscribe to Access Express\nThis field is hidden when viewing the form\n\nSubscribe to Action Alerts\nName\n\n\nFirst\n\n\n\nLast\n\nEmail*\n\nCountryCountryAfghanistanÅland IslandsAlbaniaAlgeriaAmerican SamoaAndorraAngolaAnguillaAntigua and BarbudaArgentinaArmeniaArubaAustraliaAustriaAzerbaijanBahamasBahrainBangladeshBarbadosBelarusBelgiumBelizeBeninBermudaBhutanBoliviaBonaire, Sint Eustatius and SabaBosnia and HerzegovinaBotswanaBrazilBritish Indian Ocean TerritoryBritish Virgin IslandsBruneiBulgariaBurkina FasoBurundiCambodiaCameroonCanadaCape VerdeCayman IslandsCentral African RepublicChadChileChinaChristmas IslandColombiaComorosCook IslandsCosta RicaCôte d'IvoireCroatiaCubaCuraçaoCyprusCzech RepublicDemocratic Republic of the CongoDenmarkDjiboutiDominicaDominican RepublicEast TimorEcuadorEgyptEl SalvadorEquatorial GuineaEritreaEstoniaEswatiniEthiopiaFalkland IslandsFaroe IslandsFijiFinlandFranceFrench GuianaFrench PolynesiaFrench Southern TerritoriesGabonGeorgiaGermanyGhanaGibraltarGreeceGreenlandGrenadaGuadeloupeGuamGuatemalaGuernseyGuineaGuinea-BissauGuyanaHaitiHondurasHong KongHungaryIcelandIndiaIndonesiaIranIraqIrelandIsraelItalyJamaicaJapanJordanKazakhstanKenyaKiribatiKosovoKuwaitKyrgyzstanLaosLatviaLebanonLesothoLiberiaLibyaLiechtensteinLithuaniaLuxembourgMacauMadagascarMalawiMalaysiaMaldivesMaliMaltaMarshall IslandsMartiniqueMauritaniaMauritiusMayotteMexicoMicronesiaMoldovaMonacoMongoliaMontenegroMontserratMoroccoMozambiqueMyanmarNamibiaNauruNepalNetherlands AntillesNew CaledoniaNew ZealandNicaraguaNigerNigeriaNiueNorfolk IslandNorth KoreaNorth MacedoniaNorthern Mariana IslandsNorwayOmanPakistanPalauPalestinePanamaPapua New GuineaParaguayPeruPhilippinesPitcairn IslandPolandPortugalPuerto RicoQatarRepublic of the CongoReunionRomaniaRussiaRwandaSaint BarthélemySaint Kitts and NevisSaint LuciaSaint Vincent and the GrenadinesSamoaSan MarinoSão Tomé and PríncipeSaudi ArabiaSenegalSerbiaSeychellesSierra LeoneSingaporeSlovakiaSloveniaSolomon IslandsSomaliaSomalilandSouth AfricaSouth KoreaSouth SudanSpainSri LankaSt. HelenaSt. Pierre and MiquelonSudanSurinameSwedenSwitzerlandSyriaTaiwanTajikistanTanzaniaThailandThe GambiaThe NetherlandsTogoTokelauTongaTrinidad and TobagoTunisiaTurkeyTurkmenistanTurks and Caicos IslandsTuvaluUgandaUkraineUnited Arab EmiratesUnited KingdomUnited StatesUruguayUzbekistanVanuatuVatican CityVenezuelaVietnamVirgin Islands (U.S.)Wallis and Futuna IslandsWestern SaharaYemenZambiaZimbabwePostal CodeEmailThis field is for validation purposes and should be left unchanged.\n \n\n\n\n\n\n\n\n\n\n\n\n\n\n\n\nYour info is secure with us\n\nHelp keep the internet open and secure.\nSubscribe to our action alerts and weekly newsletter\n\"*\" indicates required fields\n\nThis field is hidden when viewing the form\n\nSubscribe to Access Express\nThis field is hidden when viewing the form\n\nSubscribe to Action Alerts\nName\n\n\nFirst\n\n\n\nLast\n\nEmail*\n\nCountryCountryAfghanistanÅland IslandsAlbaniaAlgeriaAmerican SamoaAndorraAngolaAnguillaAntigua and BarbudaArgentinaArmeniaArubaAustraliaAustriaAzerbaijanBahamasBahrainBangladeshBarbadosBelarusBelgiumBelizeBeninBermudaBhutanBoliviaBonaire, Sint Eustatius and SabaBosnia and HerzegovinaBotswanaBrazilBritish Indian Ocean TerritoryBritish Virgin IslandsBruneiBulgariaBurkina FasoBurundiCambodiaCameroonCanadaCape VerdeCayman IslandsCentral African RepublicChadChileChinaChristmas IslandColombiaComorosCook IslandsCosta RicaCôte d'IvoireCroatiaCubaCuraçaoCyprusCzech RepublicDemocratic Republic of the CongoDenmarkDjiboutiDominicaDominican RepublicEast TimorEcuadorEgyptEl SalvadorEquatorial GuineaEritreaEstoniaEswatiniEthiopiaFalkland IslandsFaroe IslandsFijiFinlandFranceFrench GuianaFrench PolynesiaFrench Southern TerritoriesGabonGeorgiaGermanyGhanaGibraltarGreeceGreenlandGrenadaGuadeloupeGuamGuatemalaGuernseyGuineaGuinea-BissauGuyanaHaitiHondurasHong KongHungaryIcelandIndiaIndonesiaIranIraqIrelandIsraelItalyJamaicaJapanJordanKazakhstanKenyaKiribatiKosovoKuwaitKyrgyzstanLaosLatviaLebanonLesothoLiberiaLibyaLiechtensteinLithuaniaLuxembourgMacauMadagascarMalawiMalaysiaMaldivesMaliMaltaMarshall IslandsMartiniqueMauritaniaMauritiusMayotteMexicoMicronesiaMoldovaMonacoMongoliaMontenegroMontserratMoroccoMozambiqueMyanmarNamibiaNauruNepalNetherlands AntillesNew CaledoniaNew ZealandNicaraguaNigerNigeriaNiueNorfolk IslandNorth KoreaNorth MacedoniaNorthern Mariana IslandsNorwayOmanPakistanPalauPalestinePanamaPapua New GuineaParaguayPeruPhilippinesPitcairn IslandPolandPortugalPuerto RicoQatarRepublic of the CongoReunionRomaniaRussiaRwandaSaint BarthélemySaint Kitts and NevisSaint LuciaSaint Vincent and the GrenadinesSamoaSan MarinoSão Tomé and PríncipeSaudi ArabiaSenegalSerbiaSeychellesSierra LeoneSingaporeSlovakiaSloveniaSolomon IslandsSomaliaSomalilandSouth AfricaSouth KoreaSouth SudanSpainSri LankaSt. HelenaSt. Pierre and MiquelonSudanSurinameSwedenSwitzerlandSyriaTaiwanTajikistanTanzaniaThailandThe GambiaThe NetherlandsTogoTokelauTongaTrinidad and TobagoTunisiaTurkeyTurkmenistanTurks and Caicos IslandsTuvaluUgandaUkraineUnited Arab EmiratesUnited KingdomUnited StatesUruguayUzbekistanVanuatuVatican CityVenezuelaVietnamVirgin Islands (U.S.)Wallis and Futuna IslandsWestern SaharaYemenZambiaZimbabwePostal CodeEmailThis field is for validation purposes and should be left unchanged.\n\nHelp keep the internet open and secure.\nSubscribe to our action alerts and weekly newsletter\n\"*\" indicates required fields\n\nSubscribe to our action alerts and weekly newsletter\n\n\"*\" indicates required fields\n\nThis field is hidden when viewing the form\n\nSubscribe to Access Express\nThis field is hidden when viewing the form\n\nSubscribe to Action Alerts\nName\n\n\nFirst\n\n\n\nLast\n\nEmail*\n\nCountryCountryAfghanistanÅland IslandsAlbaniaAlgeriaAmerican SamoaAndorraAngolaAnguillaAntigua and BarbudaArgentinaArmeniaArubaAustraliaAustriaAzerbaijanBahamasBahrainBangladeshBarbadosBelarusBelgiumBelizeBeninBermudaBhutanBoliviaBonaire, Sint Eustatius and SabaBosnia and HerzegovinaBotswanaBrazilBritish Indian Ocean TerritoryBritish Virgin IslandsBruneiBulgariaBurkina FasoBurundiCambodiaCameroonCanadaCape VerdeCayman IslandsCentral African RepublicChadChileChinaChristmas IslandColombiaComorosCook IslandsCosta RicaCôte d'IvoireCroatiaCubaCuraçaoCyprusCzech RepublicDemocratic Republic of the CongoDenmarkDjiboutiDominicaDominican RepublicEast TimorEcuadorEgyptEl SalvadorEquatorial GuineaEritreaEstoniaEswatiniEthiopiaFalkland IslandsFaroe IslandsFijiFinlandFranceFrench GuianaFrench PolynesiaFrench Southern TerritoriesGabonGeorgiaGermanyGhanaGibraltarGreeceGreenlandGrenadaGuadeloupeGuamGuatemalaGuernseyGuineaGuinea-BissauGuyanaHaitiHondurasHong KongHungaryIcelandIndiaIndonesiaIranIraqIrelandIsraelItalyJamaicaJapanJordanKazakhstanKenyaKiribatiKosovoKuwaitKyrgyzstanLaosLatviaLebanonLesothoLiberiaLibyaLiechtensteinLithuaniaLuxembourgMacauMadagascarMalawiMalaysiaMaldivesMaliMaltaMarshall IslandsMartiniqueMauritaniaMauritiusMayotteMexicoMicronesiaMoldovaMonacoMongoliaMontenegroMontserratMoroccoMozambiqueMyanmarNamibiaNauruNepalNetherlands AntillesNew CaledoniaNew ZealandNicaraguaNigerNigeriaNiueNorfolk IslandNorth KoreaNorth MacedoniaNorthern Mariana IslandsNorwayOmanPakistanPalauPalestinePanamaPapua New GuineaParaguayPeruPhilippinesPitcairn IslandPolandPortugalPuerto RicoQatarRepublic of the CongoReunionRomaniaRussiaRwandaSaint BarthélemySaint Kitts and NevisSaint LuciaSaint Vincent and the GrenadinesSamoaSan MarinoSão Tomé and PríncipeSaudi ArabiaSenegalSerbiaSeychellesSierra LeoneSingaporeSlovakiaSloveniaSolomon IslandsSomaliaSomalilandSouth AfricaSouth KoreaSouth SudanSpainSri LankaSt. HelenaSt. Pierre and MiquelonSudanSurinameSwedenSwitzerlandSyriaTaiwanTajikistanTanzaniaThailandThe GambiaThe NetherlandsTogoTokelauTongaTrinidad and TobagoTunisiaTurkeyTurkmenistanTurks and Caicos IslandsTuvaluUgandaUkraineUnited Arab EmiratesUnited KingdomUnited StatesUruguayUzbekistanVanuatuVatican CityVenezuelaVietnamVirgin Islands (U.S.)Wallis and Futuna IslandsWestern SaharaYemenZambiaZimbabwePostal CodeEmailThis field is for validation purposes and should be left unchanged.\n\nThis field is hidden when viewing the form\n\nSubscribe to Access Express\nThis field is hidden when viewing the form\n\nSubscribe to Action Alerts\nName\n\n\nFirst\n\n\n\nLast\n\nEmail*\n\nCountryCountryAfghanistanÅland IslandsAlbaniaAlgeriaAmerican SamoaAndorraAngolaAnguillaAntigua and BarbudaArgentinaArmeniaArubaAustraliaAustriaAzerbaijanBahamasBahrainBangladeshBarbadosBelarusBelgiumBelizeBeninBermudaBhutanBoliviaBonaire, Sint Eustatius and SabaBosnia and HerzegovinaBotswanaBrazilBritish Indian Ocean TerritoryBritish Virgin IslandsBruneiBulgariaBurkina FasoBurundiCambodiaCameroonCanadaCape VerdeCayman IslandsCentral African RepublicChadChileChinaChristmas IslandColombiaComorosCook IslandsCosta RicaCôte d'IvoireCroatiaCubaCuraçaoCyprusCzech RepublicDemocratic Republic of the CongoDenmarkDjiboutiDominicaDominican RepublicEast TimorEcuadorEgyptEl SalvadorEquatorial GuineaEritreaEstoniaEswatiniEthiopiaFalkland IslandsFaroe IslandsFijiFinlandFranceFrench GuianaFrench PolynesiaFrench Southern TerritoriesGabonGeorgiaGermanyGhanaGibraltarGreeceGreenlandGrenadaGuadeloupeGuamGuatemalaGuernseyGuineaGuinea-BissauGuyanaHaitiHondurasHong KongHungaryIcelandIndiaIndonesiaIranIraqIrelandIsraelItalyJamaicaJapanJordanKazakhstanKenyaKiribatiKosovoKuwaitKyrgyzstanLaosLatviaLebanonLesothoLiberiaLibyaLiechtensteinLithuaniaLuxembourgMacauMadagascarMalawiMalaysiaMaldivesMaliMaltaMarshall IslandsMartiniqueMauritaniaMauritiusMayotteMexicoMicronesiaMoldovaMonacoMongoliaMontenegroMontserratMoroccoMozambiqueMyanmarNamibiaNauruNepalNetherlands AntillesNew CaledoniaNew ZealandNicaraguaNigerNigeriaNiueNorfolk IslandNorth KoreaNorth MacedoniaNorthern Mariana IslandsNorwayOmanPakistanPalauPalestinePanamaPapua New GuineaParaguayPeruPhilippinesPitcairn IslandPolandPortugalPuerto RicoQatarRepublic of the CongoReunionRomaniaRussiaRwandaSaint BarthélemySaint Kitts and NevisSaint LuciaSaint Vincent and the GrenadinesSamoaSan MarinoSão Tomé and PríncipeSaudi ArabiaSenegalSerbiaSeychellesSierra LeoneSingaporeSlovakiaSloveniaSolomon IslandsSomaliaSomalilandSouth AfricaSouth KoreaSouth SudanSpainSri LankaSt. HelenaSt. Pierre and MiquelonSudanSurinameSwedenSwitzerlandSyriaTaiwanTajikistanTanzaniaThailandThe GambiaThe NetherlandsTogoTokelauTongaTrinidad and TobagoTunisiaTurkeyTurkmenistanTurks and Caicos IslandsTuvaluUgandaUkraineUnited Arab EmiratesUnited KingdomUnited StatesUruguayUzbekistanVanuatuVatican CityVenezuelaVietnamVirgin Islands (U.S.)Wallis and Futuna IslandsWestern SaharaYemenZambiaZimbabwePostal CodeEmailThis field is for validation purposes and should be left unchanged.\n\nThis field is hidden when viewing the form\n\nSubscribe to Access Express\n\nSubscribe to Access Express\n\nSubscribe to Access Express\n\nThis field is hidden when viewing the form\n\nSubscribe to Action Alerts\n\nSubscribe to Action Alerts\n\nSubscribe to Action Alerts\n\nFirst\n\n\n\nLast\n\nEmail*\n\nCountryCountryAfghanistanÅland IslandsAlbaniaAlgeriaAmerican SamoaAndorraAngolaAnguillaAntigua and BarbudaArgentinaArmeniaArubaAustraliaAustriaAzerbaijanBahamasBahrainBangladeshBarbadosBelarusBelgiumBelizeBeninBermudaBhutanBoliviaBonaire, Sint Eustatius and SabaBosnia and HerzegovinaBotswanaBrazilBritish Indian Ocean TerritoryBritish Virgin IslandsBruneiBulgariaBurkina FasoBurundiCambodiaCameroonCanadaCape VerdeCayman IslandsCentral African RepublicChadChileChinaChristmas IslandColombiaComorosCook IslandsCosta RicaCôte d'IvoireCroatiaCubaCuraçaoCyprusCzech RepublicDemocratic Republic of the CongoDenmarkDjiboutiDominicaDominican RepublicEast TimorEcuadorEgyptEl SalvadorEquatorial GuineaEritreaEstoniaEswatiniEthiopiaFalkland IslandsFaroe IslandsFijiFinlandFranceFrench GuianaFrench PolynesiaFrench Southern TerritoriesGabonGeorgiaGermanyGhanaGibraltarGreeceGreenlandGrenadaGuadeloupeGuamGuatemalaGuernseyGuineaGuinea-BissauGuyanaHaitiHondurasHong KongHungaryIcelandIndiaIndonesiaIranIraqIrelandIsraelItalyJamaicaJapanJordanKazakhstanKenyaKiribatiKosovoKuwaitKyrgyzstanLaosLatviaLebanonLesothoLiberiaLibyaLiechtensteinLithuaniaLuxembourgMacauMadagascarMalawiMalaysiaMaldivesMaliMaltaMarshall IslandsMartiniqueMauritaniaMauritiusMayotteMexicoMicronesiaMoldovaMonacoMongoliaMontenegroMontserratMoroccoMozambiqueMyanmarNamibiaNauruNepalNetherlands AntillesNew CaledoniaNew ZealandNicaraguaNigerNigeriaNiueNorfolk IslandNorth KoreaNorth MacedoniaNorthern Mariana IslandsNorwayOmanPakistanPalauPalestinePanamaPapua New GuineaParaguayPeruPhilippinesPitcairn IslandPolandPortugalPuerto RicoQatarRepublic of the CongoReunionRomaniaRussiaRwandaSaint BarthélemySaint Kitts and NevisSaint LuciaSaint Vincent and the GrenadinesSamoaSan MarinoSão Tomé and PríncipeSaudi ArabiaSenegalSerbiaSeychellesSierra LeoneSingaporeSlovakiaSloveniaSolomon IslandsSomaliaSomalilandSouth AfricaSouth KoreaSouth SudanSpainSri LankaSt. HelenaSt. Pierre and MiquelonSudanSurinameSwedenSwitzerlandSyriaTaiwanTajikistanTanzaniaThailandThe GambiaThe NetherlandsTogoTokelauTongaTrinidad and TobagoTunisiaTurkeyTurkmenistanTurks and Caicos IslandsTuvaluUgandaUkraineUnited Arab EmiratesUnited KingdomUnited StatesUruguayUzbekistanVanuatuVatican CityVenezuelaVietnamVirgin Islands (U.S.)Wallis and Futuna IslandsWestern SaharaYemenZambiaZimbabwe\n\nCountryAfghanistanÅland IslandsAlbaniaAlgeriaAmerican SamoaAndorraAngolaAnguillaAntigua and BarbudaArgentinaArmeniaArubaAustraliaAustriaAzerbaijanBahamasBahrainBangladeshBarbadosBelarusBelgiumBelizeBeninBermudaBhutanBoliviaBonaire, Sint Eustatius and SabaBosnia and HerzegovinaBotswanaBrazilBritish Indian Ocean TerritoryBritish Virgin IslandsBruneiBulgariaBurkina FasoBurundiCambodiaCameroonCanadaCape VerdeCayman IslandsCentral African RepublicChadChileChinaChristmas IslandColombiaComorosCook IslandsCosta RicaCôte d'IvoireCroatiaCubaCuraçaoCyprusCzech RepublicDemocratic Republic of the CongoDenmarkDjiboutiDominicaDominican RepublicEast TimorEcuadorEgyptEl SalvadorEquatorial GuineaEritreaEstoniaEswatiniEthiopiaFalkland IslandsFaroe IslandsFijiFinlandFranceFrench GuianaFrench PolynesiaFrench Southern TerritoriesGabonGeorgiaGermanyGhanaGibraltarGreeceGreenlandGrenadaGuadeloupeGuamGuatemalaGuernseyGuineaGuinea-BissauGuyanaHaitiHondurasHong KongHungaryIcelandIndiaIndonesiaIranIraqIrelandIsraelItalyJamaicaJapanJordanKazakhstanKenyaKiribatiKosovoKuwaitKyrgyzstanLaosLatviaLebanonLesothoLiberiaLibyaLiechtensteinLithuaniaLuxembourgMacauMadagascarMalawiMalaysiaMaldivesMaliMaltaMarshall IslandsMartiniqueMauritaniaMauritiusMayotteMexicoMicronesiaMoldovaMonacoMongoliaMontenegroMontserratMoroccoMozambiqueMyanmarNamibiaNauruNepalNetherlands AntillesNew CaledoniaNew ZealandNicaraguaNigerNigeriaNiueNorfolk IslandNorth KoreaNorth MacedoniaNorthern Mariana IslandsNorwayOmanPakistanPalauPalestinePanamaPapua New GuineaParaguayPeruPhilippinesPitcairn IslandPolandPortugalPuerto RicoQatarRepublic of the CongoReunionRomaniaRussiaRwandaSaint BarthélemySaint Kitts and NevisSaint LuciaSaint Vincent and the GrenadinesSamoaSan MarinoSão Tomé and PríncipeSaudi ArabiaSenegalSerbiaSeychellesSierra LeoneSingaporeSlovakiaSloveniaSolomon IslandsSomaliaSomalilandSouth AfricaSouth KoreaSouth SudanSpainSri LankaSt. HelenaSt. Pierre and MiquelonSudanSurinameSwedenSwitzerlandSyriaTaiwanTajikistanTanzaniaThailandThe GambiaThe NetherlandsTogoTokelauTongaTrinidad and TobagoTunisiaTurkeyTurkmenistanTurks and Caicos IslandsTuvaluUgandaUkraineUnited Arab EmiratesUnited KingdomUnited StatesUruguayUzbekistanVanuatuVatican CityVenezuelaVietnamVirgin Islands (U.S.)Wallis and Futuna IslandsWestern SaharaYemenZambiaZimbabwe\n\nPostal Code\n\nEmailThis field is for validation purposes and should be left unchanged.\n\nThis field is for validation purposes and should be left unchanged.\n\nYour info is secure with us",
  "date": "",
  "source_type": "other",
  "extracted_at": "2025-04-07T13:46:36.751211",
  "metadata": {
    "description": "Rights-Based Approaches to Online Content Governments and companies are under increasing pressure to address illegal or undesirable content and expression",
    "og:type": "article",
    "og:site_name": "Access Now"
  },
  "relevance_score": 0.38333333333333336,
  "summary": "Content Governance\n\n\n\t\t\t\n\t\t\t\tContent governance in times of crisis: how platforms can protect human rights\n\t\t\t\t\t\t\t\n\n\nThe “Declaration for content and platform governance principles in times of crisis” lays out principles for social media platforms to help ensure privacy, freedom of expression, and access to information during crises. Latest Updates\n\n\n\n     \n\n\n\n\n\nGrid View\nList View\n\n\n\n\n\n\n\n\n\n\n\n\n\n\t\t\t\t\tContent Governance\t\t\t\t\n\n\n\n\nContent Governance \n\n\n\t\t\t\t‘Profiting from misery’: how TikTok makes money from child begging livestreams\t\t\t\n\n6 Apr 2025\n\n\n\n\nNews\n‘Profiting from misery’: how TikTok makes money from child begging livestreams\n\n\t\t\t\t\t\t\t\t\tThe Guardian ↗\t\t\t\t\t\t\t\n↗\n6 Apr 2025\n\n‘Profiting from misery’: how TikTok makes money from child begging livestreams\n\n\n\n\n \n\t\t\t\t\tInternet Shutdowns\t\t\t\t\n\n\n\n\nInternet Shutdowns \n\n\n\t\t\t\tEmboldened offenders, endangered communities: internet shutdowns in 2024\t\t\t\n\n23 Feb 2025\n • \nAccess Now and the #KeepItOn coalition documented 296 internet shutdowns in 2024 — the highest number since 2016. Press Release\nOur rights are at stake: it’s time to reclaim freedom of expression\n21 Feb 2025\n\nOur rights are at stake: it’s time to reclaim freedom of expression\n\n\n\n\n\n\n\n\n\n\t\t\t\t\tContent Governance\t\t\t\t\n\n\n\n\nContent Governance \n\n\n\t\t\t\tPoised to take over TikTok, Oracle is accused of clamping down on Pro-Palestine dissent\t\t\t\n\n19 Feb 2025\n\n\n\n\nNews\nPoised to take over TikTok, Oracle is accused of clamping down on Pro-Palestine dissent\n\n\t\t\t\t\t\t\t\t\tThe Intercept ↗\t\t\t\t\t\t\t\n↗\n19 Feb 2025\n\nPoised to take over TikTok, Oracle is accused of clamping down on Pro-Palestine dissent\n\n\n\n\n\n\n\n\n\n\t\t\t\t\tContent Governance\t\t\t\t\n\n\n\n\nContent Governance \n\n\n\t\t\t\tTamil website Vikatan inaccessible after It posted cartoon of PM, no official takedown order confirmed\t\t\t\n\n19 Feb 2025\n\n\n\n\nNews\nTamil website Vikatan inaccessible after It posted cartoon of PM, no official takedown order confirmed\n\n\t\t\t\t\t\t\t\t\tMedianama ↗\t\t\t\t\t\t\t\n↗\n19 Feb 2025\n\nTamil website Vikatan inaccessible after It posted cartoon of PM, no official takedown order confirmed\n\n\n\n\n\n\n\n\n\n\t\t\t\t\tInternet Shutdowns\t\t\t\t\n\n\n\n\nInternet Shutdowns \n\n\n\t\t\t\t2025 elections and internet shutdowns watch\t\t\t\n\n30 Jan 2025\n • \nGovernments around the world continue to shut down the internet during elections. Campaign\n2025 elections and internet shutdowns watch\n30 Jan 2025\n\n2025 elections and internet shutdowns watch\n\n\n\n\n\n\n\n\n\n\t\t\t\t\tContent Governance\t\t\t\t\n\n\n\n\nContent Governance \n\n\n\t\t\t\tTrump stand on online speech divides free speech ecosystem\t\t\t\n\n22 Jan 2025\n\n\n\n\nNews\nTrump stand on online speech divides free speech ecosystem\n\n\t\t\t\t\t\t\t\t\tHindu Businessline ↗\t\t\t\t\t\t\t\n↗\n22 Jan 2025\n\nTrump stand on online speech divides free speech ecosystem\n\n\n\n\n\n\n\n\n\n\t\t\t\t\tFreedom of Expression\t\t\t\t\n\n\n\n\nFreedom of Expression \n\n\n\t\t\t\tCeasefire in Gaza: it’s time to end digital harms and deliver justice\t\t\t\n\n20 Jan 2025\n • \nAs physical violence appears to be coming to a halt after 15 months in Gaza, Access Now further calls for a digital ceasefire. Press Release\nCeasefire in Gaza: it’s time to end digital harms and deliver justice\n20 Jan 2025\n\nCeasefire in Gaza: it’s time to end digital harms and deliver justice\n\n\n\n\n\n\n\n\n\n\t\t\t\t\tContent Governance\t\t\t\t\n\n\n\n\nContent Governance \n\n\n\t\t\t\tMetino ukidanje provjere činjenica ‘politička odluka sa stvarnim posljedicama’\t\t\t\n\n20 Jan 2025\n\n\n\n\nNews\nMetino ukidanje provjere činjenica ‘politička odluka sa stvarnim posljedicama’\n\n\t\t\t\t\t\t\t\t\tRadio Free Europe ↗\t\t\t\t\t\t\t\n↗\n20 Jan 2025\n\nMetino ukidanje provjere činjenica ‘politička odluka sa stvarnim posljedicama’\n\n\n\n\n\n\n\n\n\n\t\t\t\t\tFreedom of Expression\t\t\t\t\n\n\n\n\nFreedom of Expression \n\n\n\t\t\t\tTackling the “black snakes” undermining digital rights worldwide \t\t\t\n\n16 Jan 2025\n • \nAs 2025 gets underway, Access Now’s new Executive Director, Alejandro Mayoral Baños, PhD, shares his reflections on the “black snakes” threatening the digital rights movement. Post\nTackling the “black snakes” undermining digital rights worldwide \n16 Jan 2025\n\nTackling the “black snakes” undermining digital rights worldwide \n\n\n\n\n\n\n\n\n\n\t\t\t\t\tContent Governance\t\t\t\t\n\n\n\n\nContent Governance \n\n\n\t\t\t\tWhy Facebook ending fact checking in US is a warning sign for India\t\t\t\n\n14 Jan 2025\n\n\n\n\nNews\nWhy Facebook ending fact checking in US is a warning sign for India\n\n\t\t\t\t\t\t\t\t\tScroll ↗\t\t\t\t\t\t\t\n↗\n14 Jan 2025\n\nWhy Facebook ending fact checking in US is a warning sign for India\n\n\n\n\n\n\n\n\n\n\t\t\t\t\tContent Governance\t\t\t\t\n\n\n\n\nContent Governance \n\n\n\t\t\t\tEU regulators take a hard look at Elon Musk and X\t\t\t\n\n14 Jan 2025\n\n\n\n\nNews\nEU regulators take a hard look at Elon Musk and X\n\n\t\t\t\t\t\t\t\t\tDeutsche Welle ↗\t\t\t\t\t\t\t\n↗\n14 Jan 2025\n\nEU regulators take a hard look at Elon Musk and X\n\n\n\n\n\n\n\n\n\n\t\t\t\t\tContent Governance\t\t\t\t\n\n\n\n\nContent Governance \n\n\n\t\t\t\tPlatform accountability: a rule-of-law checklist for policymakers\t\t\t\n\n13 Jan 2025\n • \nIn this report, Access Now proposes a rule-of-law checklist to enable states to enact platform accountability regulations that are fit for purpose and protect human rights. Publication\nPlatform accountability: a rule-of-law checklist for policymakers\n\n\n↗\n13 Jan 2025\n\nPlatform accountability: a rule-of-law checklist for policymakers\n\n\n\n\n\n\n\n\n\n\t\t\t\t\tContent Governance\t\t\t\t\n\n\n\n\nContent Governance \n\n\n\t\t\t\tPlatform accountability and human rights: a rule-of-law checklist\t\t\t\n\n13 Jan 2025\n • \nAs policymakers around the world seek to rein in Big Tech, we define the safeguards necessary to ensure rule of law and protect human rights and democracy. Post\nPlatform accountability and human rights: a rule-of-law checklist\n13 Jan 2025\n\nPlatform accountability and human rights: a rule-of-law checklist\n\n\n\n\n\n\n\n\n\n\t\t\t\t\tContent Governance\t\t\t\t\n\n\n\n\nContent Governance \n\n\n\t\t\t\tGlobal fact-checkers were disappointed, not surprised, Meta ended its program\t\t\t\n\n10 Jan 2025\n\n\n\n\nNews\nGlobal fact-checkers were disappointed, not surprised, Meta ended its program\n\n\t\t\t\t\t\t\t\t\tRest of World ↗\t\t\t\t\t\t\t\n↗\n10 Jan 2025\n\nGlobal fact-checkers were disappointed, not surprised, Meta ended its program\n\n\n\n\n\n\n\n\n\n\t\t\t\t\tContent Governance\t\t\t\t\n\n\n\n\nContent Governance \n\n\n\t\t\t\tBrussels will be watching whether Musk breaks EU law in far-right livestream\t\t\t\n\n9 Jan 2025\n\n\n\n\nNews\nBrussels will be watching whether Musk breaks EU law in far-right livestream\n\n\t\t\t\t\t\t\t\t\tPOLITICO ↗\t\t\t\t\t\t\t\n↗\n9 Jan 2025\n\nBrussels will be watching whether Musk breaks EU law in far-right livestream\n\n\n\n\n\n\n\n\n \n\n\n\n\n\n\nHelp keep the internet open and secure. Content Governance\n\n\n\t\t\t\n\t\t\t\tContent governance in times of crisis: how platforms can protect human rights\n\t\t\t\t\t\t\t\n\n\nThe “Declaration for content and platform governance principles in times of crisis” lays out principles for social media platforms to help ensure privacy, freedom of expression, and access to information during crises. Latest Updates\n\n\n\n     \n\n\n\n\n\nGrid View\nList View\n\n\n\n\n\n\n\n\n\n\n\n\n\n\t\t\t\t\tContent Governance\t\t\t\t\n\n\n\n\nContent Governance \n\n\n\t\t\t\t‘Profiting from misery’: how TikTok makes money from child begging livestreams\t\t\t\n\n6 Apr 2025\n\n\n\n\nNews\n‘Profiting from misery’: how TikTok makes money from child begging livestreams\n\n\t\t\t\t\t\t\t\t\tThe Guardian ↗\t\t\t\t\t\t\t\n↗\n6 Apr 2025\n\n‘Profiting from misery’: how TikTok makes money from child begging livestreams\n\n\n\n\n \n\t\t\t\t\tInternet Shutdowns\t\t\t\t\n\n\n\n\nInternet Shutdowns \n\n\n\t\t\t\tEmboldened offenders, endangered communities: internet shutdowns in 2024\t\t\t\n\n23 Feb 2025\n • \nAccess Now and the #KeepItOn coalition documented 296 internet shutdowns in 2024 — the highest number since 2016. Press Release\nOur rights are at stake: it’s time to reclaim freedom of expression\n21 Feb 2025\n\nOur rights are at stake: it’s time to reclaim freedom of expression\n\n\n\n\n\n\n\n\n\n\t\t\t\t\tContent Governance\t\t\t\t\n\n\n\n\nContent Governance \n\n\n\t\t\t\tPoised to take over TikTok, Oracle is accused of clamping down on Pro-Palestine dissent\t\t\t\n\n19 Feb 2025\n\n\n\n\nNews\nPoised to take over TikTok, Oracle is accused of clamping down on Pro-Palestine dissent\n\n\t\t\t\t\t\t\t\t\tThe Intercept ↗\t\t\t\t\t\t\t\n↗\n19 Feb 2025\n\nPoised to take over TikTok, Oracle is accused of clamping down on Pro-Palestine dissent\n\n\n\n\n\n\n\n\n\n\t\t\t\t\tContent Governance\t\t\t\t\n\n\n\n\nContent Governance \n\n\n\t\t\t\tTamil website Vikatan inaccessible after It posted cartoon of PM, no official takedown order confirmed\t\t\t\n\n19 Feb 2025\n\n\n\n\nNews\nTamil website Vikatan inaccessible after It posted cartoon of PM, no official takedown order confirmed\n\n\t\t\t\t\t\t\t\t\tMedianama ↗\t\t\t\t\t\t\t\n↗\n19 Feb 2025\n\nTamil website Vikatan inaccessible after It posted cartoon of PM, no official takedown order confirmed\n\n\n\n\n\n\n\n\n\n\t\t\t\t\tInternet Shutdowns\t\t\t\t\n\n\n\n\nInternet Shutdowns \n\n\n\t\t\t\t2025 elections and internet shutdowns watch\t\t\t\n\n30 Jan 2025\n • \nGovernments around the world continue to shut down the internet during elections. Campaign\n2025 elections and internet shutdowns watch\n30 Jan 2025\n\n2025 elections and internet shutdowns watch\n\n\n\n\n\n\n\n\n\n\t\t\t\t\tContent Governance\t\t\t\t\n\n\n\n\nContent Governance \n\n\n\t\t\t\tTrump stand on online speech divides free speech ecosystem\t\t\t\n\n22 Jan 2025\n\n\n\n\nNews\nTrump stand on online speech divides free speech ecosystem\n\n\t\t\t\t\t\t\t\t\tHindu Businessline ↗\t\t\t\t\t\t\t\n↗\n22 Jan 2025\n\nTrump stand on online speech divides free speech ecosystem\n\n\n\n\n\n\n\n\n\n\t\t\t\t\tFreedom of Expression\t\t\t\t\n\n\n\n\nFreedom of Expression \n\n\n\t\t\t\tCeasefire in Gaza: it’s time to end digital harms and deliver justice\t\t\t\n\n20 Jan 2025\n • \nAs physical violence appears to be coming to a halt after 15 months in Gaza, Access Now further calls for a digital ceasefire. Press Release\nCeasefire in Gaza: it’s time to end digital harms and deliver justice\n20 Jan 2025\n\nCeasefire in Gaza: it’s time to end digital harms and deliver justice\n\n\n\n\n\n\n\n\n\n\t\t\t\t\tContent Governance\t\t\t\t\n\n\n\n\nContent Governance \n\n\n\t\t\t\tMetino ukidanje provjere činjenica ‘politička odluka sa stvarnim posljedicama’\t\t\t\n\n20 Jan 2025\n\n\n\n\nNews\nMetino ukidanje provjere činjenica ‘politička odluka sa stvarnim posljedicama’\n\n\t\t\t\t\t\t\t\t\tRadio Free Europe ↗\t\t\t\t\t\t\t\n↗\n20 Jan 2025\n\nMetino ukidanje provjere činjenica ‘politička odluka sa stvarnim posljedicama’\n\n\n\n\n\n\n\n\n\n\t\t\t\t\tFreedom of Expression\t\t\t\t\n\n\n\n\nFreedom of Expression \n\n\n\t\t\t\tTackling the “black snakes” undermining digital rights worldwide \t\t\t\n\n16 Jan 2025\n • \nAs 2025 gets underway, Access Now’s new Executive Director, Alejandro Mayoral Baños, PhD, shares his reflections on the “black snakes” threatening the digital rights movement. Post\nTackling the “black snakes” undermining digital rights worldwide \n16 Jan 2025\n\nTackling the “black snakes” undermining digital rights worldwide \n\n\n\n\n\n\n\n\n\n\t\t\t\t\tContent Governance\t\t\t\t\n\n\n\n\nContent Governance \n\n\n\t\t\t\tWhy Facebook ending fact checking in US is a warning sign for India\t\t\t\n\n14 Jan 2025\n\n\n\n\nNews\nWhy Facebook ending fact checking in US is a warning sign for India\n\n\t\t\t\t\t\t\t\t\tScroll ↗\t\t\t\t\t\t\t\n↗\n14 Jan 2025\n\nWhy Facebook ending fact checking in US is a warning sign for India\n\n\n\n\n\n\n\n\n\n\t\t\t\t\tContent Governance\t\t\t\t\n\n\n\n\nContent Governance \n\n\n\t\t\t\tEU regulators take a hard look at Elon Musk and X\t\t\t\n\n14 Jan 2025\n\n\n\n\nNews\nEU regulators take a hard look at Elon Musk and X\n\n\t\t\t\t\t\t\t\t\tDeutsche Welle ↗\t\t\t\t\t\t\t\n↗\n14 Jan 2025\n\nEU regulators take a hard look at Elon Musk and X\n\n\n\n\n\n\n\n\n\n\t\t\t\t\tContent Governance\t\t\t\t\n\n\n\n\nContent Governance \n\n\n\t\t\t\tPlatform accountability: a rule-of-law checklist for policymakers\t\t\t\n\n13 Jan 2025\n • \nIn this report, Access Now proposes a rule-of-law checklist to enable states to enact platform accountability regulations that are fit for purpose and protect human rights. Publication\nPlatform accountability: a rule-of-law checklist for policymakers\n\n\n↗\n13 Jan 2025\n\nPlatform accountability: a rule-of-law checklist for policymakers\n\n\n\n\n\n\n\n\n\n\t\t\t\t\tContent Governance\t\t\t\t\n\n\n\n\nContent Governance \n\n\n\t\t\t\tPlatform accountability and human rights: a rule-of-law checklist\t\t\t\n\n13 Jan 2025\n • \nAs policymakers around the world seek to rein in Big Tech, we define the safeguards necessary to ensure rule of law and protect human rights and democracy. Post\nPlatform accountability and human rights: a rule-of-law checklist\n13 Jan 2025\n\nPlatform accountability and human rights: a rule-of-law checklist\n\n\n\n\n\n\n\n\n\n\t\t\t\t\tContent Governance\t\t\t\t\n\n\n\n\nContent Governance \n\n\n\t\t\t\tGlobal fact-checkers were disappointed, not surprised, Meta ended its program\t\t\t\n\n10 Jan 2025\n\n\n\n\nNews\nGlobal fact-checkers were disappointed, not surprised, Meta ended its program\n\n\t\t\t\t\t\t\t\t\tRest of World ↗\t\t\t\t\t\t\t\n↗\n10 Jan 2025\n\nGlobal fact-checkers were disappointed, not surprised, Meta ended its program\n\n\n\n\n\n\n\n\n\n\t\t\t\t\tContent Governance\t\t\t\t\n\n\n\n\nContent Governance \n\n\n\t\t\t\tBrussels will be watching whether Musk breaks EU law in far-right livestream\t\t\t\n\n9 Jan 2025\n\n\n\n\nNews\nBrussels will be watching whether Musk breaks EU law in far-right livestream\n\n\t\t\t\t\t\t\t\t\tPOLITICO ↗\t\t\t\t\t\t\t\n↗\n9 Jan 2025\n\nBrussels will be watching whether Musk breaks EU law in far-right livestream\n\nRights-Based Approaches to Online Content\n\n\n\nGovernments and companies are under increasing pressure to address illegal or undesirable content and expression online, but hasty or poorly crafted solutions threaten human rights. Content Governance\n\n\n\t\t\t\n\t\t\t\tContent governance in times of crisis: how platforms can protect human rights\n\t\t\t\t\t\t\t\n\n\nThe “Declaration for content and platform governance principles in times of crisis” lays out principles for social media platforms to help ensure privacy, freedom of expression, and access to information during crises. Latest Updates\n\n\n\n     \n\n\n\n\n\nGrid View\nList View\n\n\n\n\n\n\n\n\n\n\n\n\n\n\t\t\t\t\tContent Governance\t\t\t\t\n\n\n\n\nContent Governance \n\n\n\t\t\t\t‘Profiting from misery’: how TikTok makes money from child begging livestreams\t\t\t\n\n6 Apr 2025\n\n\n\n\nNews\n‘Profiting from misery’: how TikTok makes money from child begging livestreams\n\n\t\t\t\t\t\t\t\t\tThe Guardian ↗\t\t\t\t\t\t\t\n↗\n6 Apr 2025\n\n‘Profiting from misery’: how TikTok makes money from child begging livestreams\n\n\n\n\n \n\t\t\t\t\tInternet Shutdowns\t\t\t\t\n\n\n\n\nInternet Shutdowns \n\n\n\t\t\t\tEmboldened offenders, endangered communities: internet shutdowns in 2024\t\t\t\n\n23 Feb 2025\n • \nAccess Now and the #KeepItOn coalition documented 296 internet shutdowns in 2024 — the highest number since 2016. Press Release\nOur rights are at stake: it’s time to reclaim freedom of expression\n21 Feb 2025\n\nOur rights are at stake: it’s time to reclaim freedom of expression\n\n\n\n\n\n\n\n\n\n\t\t\t\t\tContent Governance\t\t\t\t\n\n\n\n\nContent Governance \n\n\n\t\t\t\tPoised to take over TikTok, Oracle is accused of clamping down on Pro-Palestine dissent\t\t\t\n\n19 Feb 2025\n\n\n\n\nNews\nPoised to take over TikTok, Oracle is accused of clamping down on Pro-Palestine dissent\n\n\t\t\t\t\t\t\t\t\tThe Intercept ↗\t\t\t\t\t\t\t\n↗\n19 Feb 2025\n\nPoised to take over TikTok, Oracle is accused of clamping down on Pro-Palestine dissent\n\n\n\n\n\n\n\n\n\n\t\t\t\t\tContent Governance\t\t\t\t\n\n\n\n\nContent Governance \n\n\n\t\t\t\tTamil website Vikatan inaccessible after It posted cartoon of PM, no official takedown order confirmed\t\t\t\n\n19 Feb 2025\n\n\n\n\nNews\nTamil website Vikatan inaccessible after It posted cartoon of PM, no official takedown order confirmed\n\n\t\t\t\t\t\t\t\t\tMedianama ↗\t\t\t\t\t\t\t\n↗\n19 Feb 2025\n\nTamil website Vikatan inaccessible after It posted cartoon of PM, no official takedown order confirmed\n\n\n\n\n\n\n\n\n\n\t\t\t\t\tInternet Shutdowns\t\t\t\t\n\n\n\n\nInternet Shutdowns \n\n\n\t\t\t\t2025 elections and internet shutdowns watch\t\t\t\n\n30 Jan 2025\n • \nGovernments around the world continue to shut down the internet during elections. Campaign\n2025 elections and internet shutdowns watch\n30 Jan 2025\n\n2025 elections and internet shutdowns watch\n\n\n\n\n\n\n\n\n\n\t\t\t\t\tContent Governance\t\t\t\t\n\n\n\n\nContent Governance \n\n\n\t\t\t\tTrump stand on online speech divides free speech ecosystem\t\t\t\n\n22 Jan 2025\n\n\n\n\nNews\nTrump stand on online speech divides free speech ecosystem\n\n\t\t\t\t\t\t\t\t\tHindu Businessline ↗\t\t\t\t\t\t\t\n↗\n22 Jan 2025\n\nTrump stand on online speech divides free speech ecosystem\n\n\n\n\n\n\n\n\n\n\t\t\t\t\tFreedom of Expression\t\t\t\t\n\n\n\n\nFreedom of Expression \n\n\n\t\t\t\tCeasefire in Gaza: it’s time to end digital harms and deliver justice\t\t\t\n\n20 Jan 2025\n • \nAs physical violence appears to be coming to a halt after 15 months in Gaza, Access Now further calls for a digital ceasefire. Press Release\nCeasefire in Gaza: it’s time to end digital harms and deliver justice\n20 Jan 2025\n\nCeasefire in Gaza: it’s time to end digital harms and deliver justice\n\n\n\n\n\n\n\n\n\n\t\t\t\t\tContent Governance\t\t\t\t\n\n\n\n\nContent Governance \n\n\n\t\t\t\tMetino ukidanje provjere činjenica ‘politička odluka sa stvarnim posljedicama’\t\t\t\n\n20 Jan 2025\n\n\n\n\nNews\nMetino ukidanje provjere činjenica ‘politička odluka sa stvarnim posljedicama’\n\n\t\t\t\t\t\t\t\t\tRadio Free Europe ↗\t\t\t\t\t\t\t\n↗\n20 Jan 2025\n\nMetino ukidanje provjere činjenica ‘politička odluka sa stvarnim posljedicama’\n\n\n\n\n\n\n\n\n\n\t\t\t\t\tFreedom of Expression\t\t\t\t\n\n\n\n\nFreedom of Expression \n\n\n\t\t\t\tTackling the “black snakes” undermining digital rights worldwide \t\t\t\n\n16 Jan 2025\n • \nAs 2025 gets underway, Access Now’s new Executive Director, Alejandro Mayoral Baños, PhD, shares his reflections on the “black snakes” threatening the digital rights movement. Post\nTackling the “black snakes” undermining digital rights worldwide \n16 Jan 2025\n\nTackling the “black snakes” undermining digital rights worldwide \n\n\n\n\n\n\n\n\n\n\t\t\t\t\tContent Governance\t\t\t\t\n\n\n\n\nContent Governance \n\n\n\t\t\t\tWhy Facebook ending fact checking in US is a warning sign for India\t\t\t\n\n14 Jan 2025\n\n\n\n\nNews\nWhy Facebook ending fact checking in US is a warning sign for India\n\n\t\t\t\t\t\t\t\t\tScroll ↗\t\t\t\t\t\t\t\n↗\n14 Jan 2025\n\nWhy Facebook ending fact checking in US is a warning sign for India\n\n\n\n\n\n\n\n\n\n\t\t\t\t\tContent Governance\t\t\t\t\n\n\n\n\nContent Governance \n\n\n\t\t\t\tEU regulators take a hard look at Elon Musk and X\t\t\t\n\n14 Jan 2025\n\n\n\n\nNews\nEU regulators take a hard look at Elon Musk and X\n\n\t\t\t\t\t\t\t\t\tDeutsche Welle ↗\t\t\t\t\t\t\t\n↗\n14 Jan 2025\n\nEU regulators take a hard look at Elon Musk and X\n\n\n\n\n\n\n\n\n\n\t\t\t\t\tContent Governance\t\t\t\t\n\n\n\n\nContent Governance \n\n\n\t\t\t\tPlatform accountability: a rule-of-law checklist for policymakers\t\t\t\n\n13 Jan 2025\n • \nIn this report, Access Now proposes a rule-of-law checklist to enable states to enact platform accountability regulations that are fit for purpose and protect human rights. Publication\nPlatform accountability: a rule-of-law checklist for policymakers\n\n\n↗\n13 Jan 2025\n\nPlatform accountability: a rule-of-law checklist for policymakers\n\n\n\n\n\n\n\n\n\n\t\t\t\t\tContent Governance\t\t\t\t\n\n\n\n\nContent Governance \n\n\n\t\t\t\tPlatform accountability and human rights: a rule-of-law checklist\t\t\t\n\n13 Jan 2025\n • \nAs policymakers around the world seek to rein in Big Tech, we define the safeguards necessary to ensure rule of law and protect human rights and democracy. Post\nPlatform accountability and human rights: a rule-of-law checklist\n13 Jan 2025\n\nPlatform accountability and human rights: a rule-of-law checklist\n\n\n\n\n\n\n\n\n\n\t\t\t\t\tContent Governance\t\t\t\t\n\n\n\n\nContent Governance \n\n\n\t\t\t\tGlobal fact-checkers were disappointed, not surprised, Meta ended its program\t\t\t\n\n10 Jan 2025\n\n\n\n\nNews\nGlobal fact-checkers were disappointed, not surprised, Meta ended its program\n\n\t\t\t\t\t\t\t\t\tRest of World ↗\t\t\t\t\t\t\t\n↗\n10 Jan 2025\n\nGlobal fact-checkers were disappointed, not surprised, Meta ended its program\n\n\n\n\n\n\n\n\n\n\t\t\t\t\tContent Governance\t\t\t\t\n\n\n\n\nContent Governance \n\n\n\t\t\t\tBrussels will be watching whether Musk breaks EU law in far-right livestream\t\t\t\n\n9 Jan 2025\n\n\n\n\nNews\nBrussels will be watching whether Musk breaks EU law in far-right livestream\n\n\t\t\t\t\t\t\t\t\tPOLITICO ↗\t\t\t\t\t\t\t\n↗\n9 Jan 2025\n\nBrussels will be watching whether Musk breaks EU law in far-right livestream\n\nRights-Based Approaches to Online Content\n\n\n\nGovernments and companies are under increasing pressure to address illegal or undesirable content and expression online, but hasty or poorly crafted solutions threaten human rights. Latest Updates\n\n\n\n     \n\n\n\n\n\nGrid View\nList View\n\n\n\n\n\n\n\n\n\n\n\n\n\n\t\t\t\t\tContent Governance\t\t\t\t\n\n\n\n\nContent Governance \n\n\n\t\t\t\t‘Profiting from misery’: how TikTok makes money from child begging livestreams\t\t\t\n\n6 Apr 2025\n\n\n\n\nNews\n‘Profiting from misery’: how TikTok makes money from child begging livestreams\n\n\t\t\t\t\t\t\t\t\tThe Guardian ↗\t\t\t\t\t\t\t\n↗\n6 Apr 2025\n\n‘Profiting from misery’: how TikTok makes money from child begging livestreams\n\n\n\n\n \n\t\t\t\t\tInternet Shutdowns\t\t\t\t\n\n\n\n\nInternet Shutdowns \n\n\n\t\t\t\tEmboldened offenders, endangered communities: internet shutdowns in 2024\t\t\t\n\n23 Feb 2025\n • \nAccess Now and the #KeepItOn coalition documented 296 internet shutdowns in 2024 — the highest number since 2016. Press Release\nOur rights are at stake: it’s time to reclaim freedom of expression\n21 Feb 2025\n\nOur rights are at stake: it’s time to reclaim freedom of expression\n\n\n\n\n\n\n\n\n\n\t\t\t\t\tContent Governance\t\t\t\t\n\n\n\n\nContent Governance \n\n\n\t\t\t\tPoised to take over TikTok, Oracle is accused of clamping down on Pro-Palestine dissent\t\t\t\n\n19 Feb 2025\n\n\n\n\nNews\nPoised to take over TikTok, Oracle is accused of clamping down on Pro-Palestine dissent\n\n\t\t\t\t\t\t\t\t\tThe Intercept ↗\t\t\t\t\t\t\t\n↗\n19 Feb 2025\n\nPoised to take over TikTok, Oracle is accused of clamping down on Pro-Palestine dissent\n\n\n\n\n\n\n\n\n\n\t\t\t\t\tContent Governance\t\t\t\t\n\n\n\n\nContent Governance \n\n\n\t\t\t\tTamil website Vikatan inaccessible after It posted cartoon of PM, no official takedown order confirmed\t\t\t\n\n19 Feb 2025\n\n\n\n\nNews\nTamil website Vikatan inaccessible after It posted cartoon of PM, no official takedown order confirmed\n\n\t\t\t\t\t\t\t\t\tMedianama ↗\t\t\t\t\t\t\t\n↗\n19 Feb 2025\n\nTamil website Vikatan inaccessible after It posted cartoon of PM, no official takedown order confirmed\n\n\n\n\n\n\n\n\n\n\t\t\t\t\tInternet Shutdowns\t\t\t\t\n\n\n\n\nInternet Shutdowns \n\n\n\t\t\t\t2025 elections and internet shutdowns watch\t\t\t\n\n30 Jan 2025\n • \nGovernments around the world continue to shut down the internet during elections. Campaign\n2025 elections and internet shutdowns watch\n30 Jan 2025\n\n2025 elections and internet shutdowns watch\n\n\n\n\n\n\n\n\n\n\t\t\t\t\tContent Governance\t\t\t\t\n\n\n\n\nContent Governance \n\n\n\t\t\t\tTrump stand on online speech divides free speech ecosystem\t\t\t\n\n22 Jan 2025\n\n\n\n\nNews\nTrump stand on online speech divides free speech ecosystem\n\n\t\t\t\t\t\t\t\t\tHindu Businessline ↗\t\t\t\t\t\t\t\n↗\n22 Jan 2025\n\nTrump stand on online speech divides free speech ecosystem\n\n\n\n\n\n\n\n\n\n\t\t\t\t\tFreedom of Expression\t\t\t\t\n\n\n\n\nFreedom of Expression \n\n\n\t\t\t\tCeasefire in Gaza: it’s time to end digital harms and deliver justice\t\t\t\n\n20 Jan 2025\n • \nAs physical violence appears to be coming to a halt after 15 months in Gaza, Access Now further calls for a digital ceasefire. Press Release\nCeasefire in Gaza: it’s time to end digital harms and deliver justice\n20 Jan 2025\n\nCeasefire in Gaza: it’s time to end digital harms and deliver justice\n\n\n\n\n\n\n\n\n\n\t\t\t\t\tContent Governance\t\t\t\t\n\n\n\n\nContent Governance \n\n\n\t\t\t\tMetino ukidanje provjere činjenica ‘politička odluka sa stvarnim posljedicama’\t\t\t\n\n20 Jan 2025\n\n\n\n\nNews\nMetino ukidanje provjere činjenica ‘politička odluka sa stvarnim posljedicama’\n\n\t\t\t\t\t\t\t\t\tRadio Free Europe ↗\t\t\t\t\t\t\t\n↗\n20 Jan 2025\n\nMetino ukidanje provjere činjenica ‘politička odluka sa stvarnim posljedicama’\n\n\n\n\n\n\n\n\n\n\t\t\t\t\tFreedom of Expression\t\t\t\t\n\n\n\n\nFreedom of Expression \n\n\n\t\t\t\tTackling the “black snakes” undermining digital rights worldwide \t\t\t\n\n16 Jan 2025\n • \nAs 2025 gets underway, Access Now’s new Executive Director, Alejandro Mayoral Baños, PhD, shares his reflections on the “black snakes” threatening the digital rights movement. Post\nTackling the “black snakes” undermining digital rights worldwide \n16 Jan 2025\n\nTackling the “black snakes” undermining digital rights worldwide \n\n\n\n\n\n\n\n\n\n\t\t\t\t\tContent Governance\t\t\t\t\n\n\n\n\nContent Governance \n\n\n\t\t\t\tWhy Facebook ending fact checking in US is a warning sign for India\t\t\t\n\n14 Jan 2025\n\n\n\n\nNews\nWhy Facebook ending fact checking in US is a warning sign for India\n\n\t\t\t\t\t\t\t\t\tScroll ↗\t\t\t\t\t\t\t\n↗\n14 Jan 2025\n\nWhy Facebook ending fact checking in US is a warning sign for India\n\n\n\n\n\n\n\n\n\n\t\t\t\t\tContent Governance\t\t\t\t\n\n\n\n\nContent Governance \n\n\n\t\t\t\tEU regulators take a hard look at Elon Musk and X\t\t\t\n\n14 Jan 2025\n\n\n\n\nNews\nEU regulators take a hard look at Elon Musk and X\n\n\t\t\t\t\t\t\t\t\tDeutsche Welle ↗\t\t\t\t\t\t\t\n↗\n14 Jan 2025\n\nEU regulators take a hard look at Elon Musk and X\n\n\n\n\n\n\n\n\n\n\t\t\t\t\tContent Governance\t\t\t\t\n\n\n\n\nContent Governance \n\n\n\t\t\t\tPlatform accountability: a rule-of-law checklist for policymakers\t\t\t\n\n13 Jan 2025\n • \nIn this report, Access Now proposes a rule-of-law checklist to enable states to enact platform accountability regulations that are fit for purpose and protect human rights. Publication\nPlatform accountability: a rule-of-law checklist for policymakers\n\n\n↗\n13 Jan 2025\n\nPlatform accountability: a rule-of-law checklist for policymakers\n\n\n\n\n\n\n\n\n\n\t\t\t\t\tContent Governance\t\t\t\t\n\n\n\n\nContent Governance \n\n\n\t\t\t\tPlatform accountability and human rights: a rule-of-law checklist\t\t\t\n\n13 Jan 2025\n • \nAs policymakers around the world seek to rein in Big Tech, we define the safeguards necessary to ensure rule of law and protect human rights and democracy. Post\nPlatform accountability and human rights: a rule-of-law checklist\n13 Jan 2025\n\nPlatform accountability and human rights: a rule-of-law checklist\n\n\n\n\n\n\n\n\n\n\t\t\t\t\tContent Governance\t\t\t\t\n\n\n\n\nContent Governance \n\n\n\t\t\t\tGlobal fact-checkers were disappointed, not surprised, Meta ended its program\t\t\t\n\n10 Jan 2025\n\n\n\n\nNews\nGlobal fact-checkers were disappointed, not surprised, Meta ended its program\n\n\t\t\t\t\t\t\t\t\tRest of World ↗\t\t\t\t\t\t\t\n↗\n10 Jan 2025\n\nGlobal fact-checkers were disappointed, not surprised, Meta ended its program\n\n\n\n\n\n\n\n\n\n\t\t\t\t\tContent Governance\t\t\t\t\n\n\n\n\nContent Governance \n\n\n\t\t\t\tBrussels will be watching whether Musk breaks EU law in far-right livestream\t\t\t\n\n9 Jan 2025\n\n\n\n\nNews\nBrussels will be watching whether Musk breaks EU law in far-right livestream\n\n\t\t\t\t\t\t\t\t\tPOLITICO ↗\t\t\t\t\t\t\t\n↗\n9 Jan 2025\n\nBrussels will be watching whether Musk breaks EU law in far-right livestream\n\nRights-Based Approaches to Online Content\n\n\n\nGovernments and companies are under increasing pressure to address illegal or undesirable content and expression online, but hasty or poorly crafted solutions threaten human rights. Latest Updates\n\n\n\n     \n\n\n\n\n\nGrid View\nList View\n\n\n\n\n\n\n\n\n\n\n\n\n\n\t\t\t\t\tContent Governance\t\t\t\t\n\n\n\n\nContent Governance \n\n\n\t\t\t\t‘Profiting from misery’: how TikTok makes money from child begging livestreams\t\t\t\n\n6 Apr 2025\n\n\n\n\nNews\n‘Profiting from misery’: how TikTok makes money from child begging livestreams\n\n\t\t\t\t\t\t\t\t\tThe Guardian ↗\t\t\t\t\t\t\t\n↗\n6 Apr 2025\n\n‘Profiting from misery’: how TikTok makes money from child begging livestreams\n\n\n\n\n \n\t\t\t\t\tInternet Shutdowns\t\t\t\t\n\n\n\n\nInternet Shutdowns \n\n\n\t\t\t\tEmboldened offenders, endangered communities: internet shutdowns in 2024\t\t\t\n\n23 Feb 2025\n • \nAccess Now and the #KeepItOn coalition documented 296 internet shutdowns in 2024 — the highest number since 2016. Press Release\nOur rights are at stake: it’s time to reclaim freedom of expression\n21 Feb 2025\n\nOur rights are at stake: it’s time to reclaim freedom of expression\n\n\n\n\n\n\n\n\n\n\t\t\t\t\tContent Governance\t\t\t\t\n\n\n\n\nContent Governance \n\n\n\t\t\t\tPoised to take over TikTok, Oracle is accused of clamping down on Pro-Palestine dissent\t\t\t\n\n19 Feb 2025\n\n\n\n\nNews\nPoised to take over TikTok, Oracle is accused of clamping down on Pro-Palestine dissent\n\n\t\t\t\t\t\t\t\t\tThe Intercept ↗\t\t\t\t\t\t\t\n↗\n19 Feb 2025\n\nPoised to take over TikTok, Oracle is accused of clamping down on Pro-Palestine dissent\n\n\n\n\n\n\n\n\n\n\t\t\t\t\tContent Governance\t\t\t\t\n\n\n\n\nContent Governance \n\n\n\t\t\t\tTamil website Vikatan inaccessible after It posted cartoon of PM, no official takedown order confirmed\t\t\t\n\n19 Feb 2025\n\n\n\n\nNews\nTamil website Vikatan inaccessible after It posted cartoon of PM, no official takedown order confirmed\n\n\t\t\t\t\t\t\t\t\tMedianama ↗\t\t\t\t\t\t\t\n↗\n19 Feb 2025\n\nTamil website Vikatan inaccessible after It posted cartoon of PM, no official takedown order confirmed\n\n\n\n\n\n\n\n\n\n\t\t\t\t\tInternet Shutdowns\t\t\t\t\n\n\n\n\nInternet Shutdowns \n\n\n\t\t\t\t2025 elections and internet shutdowns watch\t\t\t\n\n30 Jan 2025\n • \nGovernments around the world continue to shut down the internet during elections. Campaign\n2025 elections and internet shutdowns watch\n30 Jan 2025\n\n2025 elections and internet shutdowns watch\n\n\n\n\n\n\n\n\n\n\t\t\t\t\tContent Governance\t\t\t\t\n\n\n\n\nContent Governance \n\n\n\t\t\t\tTrump stand on online speech divides free speech ecosystem\t\t\t\n\n22 Jan 2025\n\n\n\n\nNews\nTrump stand on online speech divides free speech ecosystem\n\n\t\t\t\t\t\t\t\t\tHindu Businessline ↗\t\t\t\t\t\t\t\n↗\n22 Jan 2025\n\nTrump stand on online speech divides free speech ecosystem\n\n\n\n\n\n\n\n\n\n\t\t\t\t\tFreedom of Expression\t\t\t\t\n\n\n\n\nFreedom of Expression \n\n\n\t\t\t\tCeasefire in Gaza: it’s time to end digital harms and deliver justice\t\t\t\n\n20 Jan 2025\n • \nAs physical violence appears to be coming to a halt after 15 months in Gaza, Access Now further calls for a digital ceasefire. Press Release\nCeasefire in Gaza: it’s time to end digital harms and deliver justice\n20 Jan 2025\n\nCeasefire in Gaza: it’s time to end digital harms and deliver justice\n\n\n\n\n\n\n\n\n\n\t\t\t\t\tContent Governance\t\t\t\t\n\n\n\n\nContent Governance \n\n\n\t\t\t\tMetino ukidanje provjere činjenica ‘politička odluka sa stvarnim posljedicama’\t\t\t\n\n20 Jan 2025\n\n\n\n\nNews\nMetino ukidanje provjere činjenica ‘politička odluka sa stvarnim posljedicama’\n\n\t\t\t\t\t\t\t\t\tRadio Free Europe ↗\t\t\t\t\t\t\t\n↗\n20 Jan 2025\n\nMetino ukidanje provjere činjenica ‘politička odluka sa stvarnim posljedicama’\n\n\n\n\n\n\n\n\n\n\t\t\t\t\tFreedom of Expression\t\t\t\t\n\n\n\n\nFreedom of Expression \n\n\n\t\t\t\tTackling the “black snakes” undermining digital rights worldwide \t\t\t\n\n16 Jan 2025\n • \nAs 2025 gets underway, Access Now’s new Executive Director, Alejandro Mayoral Baños, PhD, shares his reflections on the “black snakes” threatening the digital rights movement. Post\nTackling the “black snakes” undermining digital rights worldwide \n16 Jan 2025\n\nTackling the “black snakes” undermining digital rights worldwide \n\n\n\n\n\n\n\n\n\n\t\t\t\t\tContent Governance\t\t\t\t\n\n\n\n\nContent Governance \n\n\n\t\t\t\tWhy Facebook ending fact checking in US is a warning sign for India\t\t\t\n\n14 Jan 2025\n\n\n\n\nNews\nWhy Facebook ending fact checking in US is a warning sign for India\n\n\t\t\t\t\t\t\t\t\tScroll ↗\t\t\t\t\t\t\t\n↗\n14 Jan 2025\n\nWhy Facebook ending fact checking in US is a warning sign for India\n\n\n\n\n\n\n\n\n\n\t\t\t\t\tContent Governance\t\t\t\t\n\n\n\n\nContent Governance \n\n\n\t\t\t\tEU regulators take a hard look at Elon Musk and X\t\t\t\n\n14 Jan 2025\n\n\n\n\nNews\nEU regulators take a hard look at Elon Musk and X\n\n\t\t\t\t\t\t\t\t\tDeutsche Welle ↗\t\t\t\t\t\t\t\n↗\n14 Jan 2025\n\nEU regulators take a hard look at Elon Musk and X\n\n\n\n\n\n\n\n\n\n\t\t\t\t\tContent Governance\t\t\t\t\n\n\n\n\nContent Governance \n\n\n\t\t\t\tPlatform accountability: a rule-of-law checklist for policymakers\t\t\t\n\n13 Jan 2025\n • \nIn this report, Access Now proposes a rule-of-law checklist to enable states to enact platform accountability regulations that are fit for purpose and protect human rights. Publication\nPlatform accountability: a rule-of-law checklist for policymakers\n\n\n↗\n13 Jan 2025\n\nPlatform accountability: a rule-of-law checklist for policymakers\n\n\n\n\n\n\n\n\n\n\t\t\t\t\tContent Governance\t\t\t\t\n\n\n\n\nContent Governance \n\n\n\t\t\t\tPlatform accountability and human rights: a rule-of-law checklist\t\t\t\n\n13 Jan 2025\n • \nAs policymakers around the world seek to rein in Big Tech, we define the safeguards necessary to ensure rule of law and protect human rights and democracy. Post\nPlatform accountability and human rights: a rule-of-law checklist\n13 Jan 2025\n\nPlatform accountability and human rights: a rule-of-law checklist\n\n\n\n\n\n\n\n\n\n\t\t\t\t\tContent Governance\t\t\t\t\n\n\n\n\nContent Governance \n\n\n\t\t\t\tGlobal fact-checkers were disappointed, not surprised, Meta ended its program\t\t\t\n\n10 Jan 2025\n\n\n\n\nNews\nGlobal fact-checkers were disappointed, not surprised, Meta ended its program\n\n\t\t\t\t\t\t\t\t\tRest of World ↗\t\t\t\t\t\t\t\n↗\n10 Jan 2025\n\nGlobal fact-checkers were disappointed, not surprised, Meta ended its program\n\n\n\n\n\n\n\n\n\n\t\t\t\t\tContent Governance\t\t\t\t\n\n\n\n\nContent Governance \n\n\n\t\t\t\tBrussels will be watching whether Musk breaks EU law in far-right livestream\t\t\t\n\n9 Jan 2025\n\n\n\n\nNews\nBrussels will be watching whether Musk breaks EU law in far-right livestream\n\n\t\t\t\t\t\t\t\t\tPOLITICO ↗\t\t\t\t\t\t\t\n↗\n9 Jan 2025\n\nBrussels will be watching whether Musk breaks EU law in far-right livestream\n\nRights-Based Approaches to Online Content\n\n\n\nGovernments and companies are under increasing pressure to address illegal or undesirable content and expression online, but hasty or poorly crafted solutions threaten human rights. Latest Updates\n\n\n\n     \n\n\n\n\n\nGrid View\nList View\n\n\n\n\n\n\n\n\n\n\n\n\n\n\t\t\t\t\tContent Governance\t\t\t\t\n\n\n\n\nContent Governance \n\n\n\t\t\t\t‘Profiting from misery’: how TikTok makes money from child begging livestreams\t\t\t\n\n6 Apr 2025\n\n\n\n\nNews\n‘Profiting from misery’: how TikTok makes money from child begging livestreams\n\n\t\t\t\t\t\t\t\t\tThe Guardian ↗\t\t\t\t\t\t\t\n↗\n6 Apr 2025\n\n‘Profiting from misery’: how TikTok makes money from child begging livestreams\n\n\n\n\n \n\t\t\t\t\tInternet Shutdowns\t\t\t\t\n\n\n\n\nInternet Shutdowns \n\n\n\t\t\t\tEmboldened offenders, endangered communities: internet shutdowns in 2024\t\t\t\n\n23 Feb 2025\n • \nAccess Now and the #KeepItOn coalition documented 296 internet shutdowns in 2024 — the highest number since 2016. Press Release\nOur rights are at stake: it’s time to reclaim freedom of expression\n21 Feb 2025\n\nOur rights are at stake: it’s time to reclaim freedom of expression\n\n\n\n\n\n\n\n\n\n\t\t\t\t\tContent Governance\t\t\t\t\n\n\n\n\nContent Governance \n\n\n\t\t\t\tPoised to take over TikTok, Oracle is accused of clamping down on Pro-Palestine dissent\t\t\t\n\n19 Feb 2025\n\n\n\n\nNews\nPoised to take over TikTok, Oracle is accused of clamping down on Pro-Palestine dissent\n\n\t\t\t\t\t\t\t\t\tThe Intercept ↗\t\t\t\t\t\t\t\n↗\n19 Feb 2025\n\nPoised to take over TikTok, Oracle is accused of clamping down on Pro-Palestine dissent\n\n\n\n\n\n\n\n\n\n\t\t\t\t\tContent Governance\t\t\t\t\n\n\n\n\nContent Governance \n\n\n\t\t\t\tTamil website Vikatan inaccessible after It posted cartoon of PM, no official takedown order confirmed\t\t\t\n\n19 Feb 2025\n\n\n\n\nNews\nTamil website Vikatan inaccessible after It posted cartoon of PM, no official takedown order confirmed\n\n\t\t\t\t\t\t\t\t\tMedianama ↗\t\t\t\t\t\t\t\n↗\n19 Feb 2025\n\nTamil website Vikatan inaccessible after It posted cartoon of PM, no official takedown order confirmed\n\n\n\n\n\n\n\n\n\n\t\t\t\t\tInternet Shutdowns\t\t\t\t\n\n\n\n\nInternet Shutdowns \n\n\n\t\t\t\t2025 elections and internet shutdowns watch\t\t\t\n\n30 Jan 2025\n • \nGovernments around the world continue to shut down the internet during elections. Campaign\n2025 elections and internet shutdowns watch\n30 Jan 2025\n\n2025 elections and internet shutdowns watch\n\n\n\n\n\n\n\n\n\n\t\t\t\t\tContent Governance\t\t\t\t\n\n\n\n\nContent Governance \n\n\n\t\t\t\tTrump stand on online speech divides free speech ecosystem\t\t\t\n\n22 Jan 2025\n\n\n\n\nNews\nTrump stand on online speech divides free speech ecosystem\n\n\t\t\t\t\t\t\t\t\tHindu Businessline ↗\t\t\t\t\t\t\t\n↗\n22 Jan 2025\n\nTrump stand on online speech divides free speech ecosystem\n\n\n\n\n\n\n\n\n\n\t\t\t\t\tFreedom of Expression\t\t\t\t\n\n\n\n\nFreedom of Expression \n\n\n\t\t\t\tCeasefire in Gaza: it’s time to end digital harms and deliver justice\t\t\t\n\n20 Jan 2025\n • \nAs physical violence appears to be coming to a halt after 15 months in Gaza, Access Now further calls for a digital ceasefire. Press Release\nCeasefire in Gaza: it’s time to end digital harms and deliver justice\n20 Jan 2025\n\nCeasefire in Gaza: it’s time to end digital harms and deliver justice\n\n\n\n\n\n\n\n\n\n\t\t\t\t\tContent Governance\t\t\t\t\n\n\n\n\nContent Governance \n\n\n\t\t\t\tMetino ukidanje provjere činjenica ‘politička odluka sa stvarnim posljedicama’\t\t\t\n\n20 Jan 2025\n\n\n\n\nNews\nMetino ukidanje provjere činjenica ‘politička odluka sa stvarnim posljedicama’\n\n\t\t\t\t\t\t\t\t\tRadio Free Europe ↗\t\t\t\t\t\t\t\n↗\n20 Jan 2025\n\nMetino ukidanje provjere činjenica ‘politička odluka sa stvarnim posljedicama’\n\n\n\n\n\n\n\n\n\n\t\t\t\t\tFreedom of Expression\t\t\t\t\n\n\n\n\nFreedom of Expression \n\n\n\t\t\t\tTackling the “black snakes” undermining digital rights worldwide \t\t\t\n\n16 Jan 2025\n • \nAs 2025 gets underway, Access Now’s new Executive Director, Alejandro Mayoral Baños, PhD, shares his reflections on the “black snakes” threatening the digital rights movement. Post\nTackling the “black snakes” undermining digital rights worldwide \n16 Jan 2025\n\nTackling the “black snakes” undermining digital rights worldwide \n\n\n\n\n\n\n\n\n\n\t\t\t\t\tContent Governance\t\t\t\t\n\n\n\n\nContent Governance \n\n\n\t\t\t\tWhy Facebook ending fact checking in US is a warning sign for India\t\t\t\n\n14 Jan 2025\n\n\n\n\nNews\nWhy Facebook ending fact checking in US is a warning sign for India\n\n\t\t\t\t\t\t\t\t\tScroll ↗\t\t\t\t\t\t\t\n↗\n14 Jan 2025\n\nWhy Facebook ending fact checking in US is a warning sign for India\n\n\n\n\n\n\n\n\n\n\t\t\t\t\tContent Governance\t\t\t\t\n\n\n\n\nContent Governance \n\n\n\t\t\t\tEU regulators take a hard look at Elon Musk and X\t\t\t\n\n14 Jan 2025\n\n\n\n\nNews\nEU regulators take a hard look at Elon Musk and X\n\n\t\t\t\t\t\t\t\t\tDeutsche Welle ↗\t\t\t\t\t\t\t\n↗\n14 Jan 2025\n\nEU regulators take a hard look at Elon Musk and X\n\n\n\n\n\n\n\n\n\n\t\t\t\t\tContent Governance\t\t\t\t\n\n\n\n\nContent Governance \n\n\n\t\t\t\tPlatform accountability: a rule-of-law checklist for policymakers\t\t\t\n\n13 Jan 2025\n • \nIn this report, Access Now proposes a rule-of-law checklist to enable states to enact platform accountability regulations that are fit for purpose and protect human rights. Publication\nPlatform accountability: a rule-of-law checklist for policymakers\n\n\n↗\n13 Jan 2025\n\nPlatform accountability: a rule-of-law checklist for policymakers\n\n\n\n\n\n\n\n\n\n\t\t\t\t\tContent Governance\t\t\t\t\n\n\n\n\nContent Governance \n\n\n\t\t\t\tPlatform accountability and human rights: a rule-of-law checklist\t\t\t\n\n13 Jan 2025\n • \nAs policymakers around the world seek to rein in Big Tech, we define the safeguards necessary to ensure rule of law and protect human rights and democracy. Post\nPlatform accountability and human rights: a rule-of-law checklist\n13 Jan 2025\n\nPlatform accountability and human rights: a rule-of-law checklist\n\n\n\n\n\n\n\n\n\n\t\t\t\t\tContent Governance\t\t\t\t\n\n\n\n\nContent Governance \n\n\n\t\t\t\tGlobal fact-checkers were disappointed, not surprised, Meta ended its program\t\t\t\n\n10 Jan 2025\n\n\n\n\nNews\nGlobal fact-checkers were disappointed, not surprised, Meta ended its program\n\n\t\t\t\t\t\t\t\t\tRest of World ↗\t\t\t\t\t\t\t\n↗\n10 Jan 2025\n\nGlobal fact-checkers were disappointed, not surprised, Meta ended its program\n\n\n\n\n\n\n\n\n\n\t\t\t\t\tContent Governance\t\t\t\t\n\n\n\n\nContent Governance \n\n\n\t\t\t\tBrussels will be watching whether Musk breaks EU law in far-right livestream\t\t\t\n\n9 Jan 2025\n\n\n\n\nNews\nBrussels will be watching whether Musk breaks EU law in far-right livestream\n\n\t\t\t\t\t\t\t\t\tPOLITICO ↗\t\t\t\t\t\t\t\n↗\n9 Jan 2025\n\nBrussels will be watching whether Musk breaks EU law in far-right livestream\n\nRights-Based Approaches to Online Content\n\nRights-Based Approaches to Online Content\n\nGovernments and companies are under increasing pressure to address illegal or undesirable content and expression online, but hasty or poorly crafted solutions threaten human rights. Latest Updates\n\n\n\n     \n\n\n\n\n\nGrid View\nList View\n\n\n\n\n\n\n\n\n\n\n\n\n\n\t\t\t\t\tContent Governance\t\t\t\t\n\n\n\n\nContent Governance \n\n\n\t\t\t\t‘Profiting from misery’: how TikTok makes money from child begging livestreams\t\t\t\n\n6 Apr 2025\n\n\n\n\nNews\n‘Profiting from misery’: how TikTok makes money from child begging livestreams\n\n\t\t\t\t\t\t\t\t\tThe Guardian ↗\t\t\t\t\t\t\t\n↗\n6 Apr 2025\n\n‘Profiting from misery’: how TikTok makes money from child begging livestreams\n\n\n\n\n \n\t\t\t\t\tInternet Shutdowns\t\t\t\t\n\n\n\n\nInternet Shutdowns \n\n\n\t\t\t\tEmboldened offenders, endangered communities: internet shutdowns in 2024\t\t\t\n\n23 Feb 2025\n • \nAccess Now and the #KeepItOn coalition documented 296 internet shutdowns in 2024 — the highest number since 2016. Press Release\nOur rights are at stake: it’s time to reclaim freedom of expression\n21 Feb 2025\n\nOur rights are at stake: it’s time to reclaim freedom of expression\n\n\n\n\n\n\n\n\n\n\t\t\t\t\tContent Governance\t\t\t\t\n\n\n\n\nContent Governance \n\n\n\t\t\t\tPoised to take over TikTok, Oracle is accused of clamping down on Pro-Palestine dissent\t\t\t\n\n19 Feb 2025\n\n\n\n\nNews\nPoised to take over TikTok, Oracle is accused of clamping down on Pro-Palestine dissent\n\n\t\t\t\t\t\t\t\t\tThe Intercept ↗\t\t\t\t\t\t\t\n↗\n19 Feb 2025\n\nPoised to take over TikTok, Oracle is accused of clamping down on Pro-Palestine dissent\n\n\n\n\n\n\n\n\n\n\t\t\t\t\tContent Governance\t\t\t\t\n\n\n\n\nContent Governance \n\n\n\t\t\t\tTamil website Vikatan inaccessible after It posted cartoon of PM, no official takedown order confirmed\t\t\t\n\n19 Feb 2025\n\n\n\n\nNews\nTamil website Vikatan inaccessible after It posted cartoon of PM, no official takedown order confirmed\n\n\t\t\t\t\t\t\t\t\tMedianama ↗\t\t\t\t\t\t\t\n↗\n19 Feb 2025\n\nTamil website Vikatan inaccessible after It posted cartoon of PM, no official takedown order confirmed\n\n\n\n\n\n\n\n\n\n\t\t\t\t\tInternet Shutdowns\t\t\t\t\n\n\n\n\nInternet Shutdowns \n\n\n\t\t\t\t2025 elections and internet shutdowns watch\t\t\t\n\n30 Jan 2025\n • \nGovernments around the world continue to shut down the internet during elections. Campaign\n2025 elections and internet shutdowns watch\n30 Jan 2025\n\n2025 elections and internet shutdowns watch\n\n\n\n\n\n\n\n\n\n\t\t\t\t\tContent Governance\t\t\t\t\n\n\n\n\nContent Governance \n\n\n\t\t\t\tTrump stand on online speech divides free speech ecosystem\t\t\t\n\n22 Jan 2025\n\n\n\n\nNews\nTrump stand on online speech divides free speech ecosystem\n\n\t\t\t\t\t\t\t\t\tHindu Businessline ↗\t\t\t\t\t\t\t\n↗\n22 Jan 2025\n\nTrump stand on online speech divides free speech ecosystem\n\n\n\n\n\n\n\n\n\n\t\t\t\t\tFreedom of Expression\t\t\t\t\n\n\n\n\nFreedom of Expression \n\n\n\t\t\t\tCeasefire in Gaza: it’s time to end digital harms and deliver justice\t\t\t\n\n20 Jan 2025\n • \nAs physical violence appears to be coming to a halt after 15 months in Gaza, Access Now further calls for a digital ceasefire. Press Release\nCeasefire in Gaza: it’s time to end digital harms and deliver justice\n20 Jan 2025\n\nCeasefire in Gaza: it’s time to end digital harms and deliver justice\n\n\n\n\n\n\n\n\n\n\t\t\t\t\tContent Governance\t\t\t\t\n\n\n\n\nContent Governance \n\n\n\t\t\t\tMetino ukidanje provjere činjenica ‘politička odluka sa stvarnim posljedicama’\t\t\t\n\n20 Jan 2025\n\n\n\n\nNews\nMetino ukidanje provjere činjenica ‘politička odluka sa stvarnim posljedicama’\n\n\t\t\t\t\t\t\t\t\tRadio Free Europe ↗\t\t\t\t\t\t\t\n↗\n20 Jan 2025\n\nMetino ukidanje provjere činjenica ‘politička odluka sa stvarnim posljedicama’\n\n\n\n\n\n\n\n\n\n\t\t\t\t\tFreedom of Expression\t\t\t\t\n\n\n\n\nFreedom of Expression \n\n\n\t\t\t\tTackling the “black snakes” undermining digital rights worldwide \t\t\t\n\n16 Jan 2025\n • \nAs 2025 gets underway, Access Now’s new Executive Director, Alejandro Mayoral Baños, PhD, shares his reflections on the “black snakes” threatening the digital rights movement. Post\nTackling the “black snakes” undermining digital rights worldwide \n16 Jan 2025\n\nTackling the “black snakes” undermining digital rights worldwide \n\n\n\n\n\n\n\n\n\n\t\t\t\t\tContent Governance\t\t\t\t\n\n\n\n\nContent Governance \n\n\n\t\t\t\tWhy Facebook ending fact checking in US is a warning sign for India\t\t\t\n\n14 Jan 2025\n\n\n\n\nNews\nWhy Facebook ending fact checking in US is a warning sign for India\n\n\t\t\t\t\t\t\t\t\tScroll ↗\t\t\t\t\t\t\t\n↗\n14 Jan 2025\n\nWhy Facebook ending fact checking in US is a warning sign for India\n\n\n\n\n\n\n\n\n\n\t\t\t\t\tContent Governance\t\t\t\t\n\n\n\n\nContent Governance \n\n\n\t\t\t\tEU regulators take a hard look at Elon Musk and X\t\t\t\n\n14 Jan 2025\n\n\n\n\nNews\nEU regulators take a hard look at Elon Musk and X\n\n\t\t\t\t\t\t\t\t\tDeutsche Welle ↗\t\t\t\t\t\t\t\n↗\n14 Jan 2025\n\nEU regulators take a hard look at Elon Musk and X\n\n\n\n\n\n\n\n\n\n\t\t\t\t\tContent Governance\t\t\t\t\n\n\n\n\nContent Governance \n\n\n\t\t\t\tPlatform accountability: a rule-of-law checklist for policymakers\t\t\t\n\n13 Jan 2025\n • \nIn this report, Access Now proposes a rule-of-law checklist to enable states to enact platform accountability regulations that are fit for purpose and protect human rights. Publication\nPlatform accountability: a rule-of-law checklist for policymakers\n\n\n↗\n13 Jan 2025\n\nPlatform accountability: a rule-of-law checklist for policymakers\n\n\n\n\n\n\n\n\n\n\t\t\t\t\tContent Governance\t\t\t\t\n\n\n\n\nContent Governance \n\n\n\t\t\t\tPlatform accountability and human rights: a rule-of-law checklist\t\t\t\n\n13 Jan 2025\n • \nAs policymakers around the world seek to rein in Big Tech, we define the safeguards necessary to ensure rule of law and protect human rights and democracy. Post\nPlatform accountability and human rights: a rule-of-law checklist\n13 Jan 2025\n\nPlatform accountability and human rights: a rule-of-law checklist\n\n\n\n\n\n\n\n\n\n\t\t\t\t\tContent Governance\t\t\t\t\n\n\n\n\nContent Governance \n\n\n\t\t\t\tGlobal fact-checkers were disappointed, not surprised, Meta ended its program\t\t\t\n\n10 Jan 2025\n\n\n\n\nNews\nGlobal fact-checkers were disappointed, not surprised, Meta ended its program\n\n\t\t\t\t\t\t\t\t\tRest of World ↗\t\t\t\t\t\t\t\n↗\n10 Jan 2025\n\nGlobal fact-checkers were disappointed, not surprised, Meta ended its program\n\n\n\n\n\n\n\n\n\n\t\t\t\t\tContent Governance\t\t\t\t\n\n\n\n\nContent Governance \n\n\n\t\t\t\tBrussels will be watching whether Musk breaks EU law in far-right livestream\t\t\t\n\n9 Jan 2025\n\n\n\n\nNews\nBrussels will be watching whether Musk breaks EU law in far-right livestream\n\n\t\t\t\t\t\t\t\t\tPOLITICO ↗\t\t\t\t\t\t\t\n↗\n9 Jan 2025\n\nBrussels will be watching whether Musk breaks EU law in far-right livestream\n\nLatest Updates\n\n\n\n     \n\n\n\n\n\nGrid View\nList View\n\n\n\n\n\n\n\n\n\n\n\n\n\n\t\t\t\t\tContent Governance\t\t\t\t\n\n\n\n\nContent Governance \n\n\n\t\t\t\t‘Profiting from misery’: how TikTok makes money from child begging livestreams\t\t\t\n\n6 Apr 2025\n\n\n\n\nNews\n‘Profiting from misery’: how TikTok makes money from child begging livestreams\n\n\t\t\t\t\t\t\t\t\tThe Guardian ↗\t\t\t\t\t\t\t\n↗\n6 Apr 2025\n\n‘Profiting from misery’: how TikTok makes money from child begging livestreams\n\n\n\n\n \n\t\t\t\t\tInternet Shutdowns\t\t\t\t\n\n\n\n\nInternet Shutdowns \n\n\n\t\t\t\tEmboldened offenders, endangered communities: internet shutdowns in 2024\t\t\t\n\n23 Feb 2025\n • \nAccess Now and the #KeepItOn coalition documented 296 internet shutdowns in 2024 — the highest number since 2016. Press Release\nOur rights are at stake: it’s time to reclaim freedom of expression\n21 Feb 2025\n\nOur rights are at stake: it’s time to reclaim freedom of expression\n\n\n\n\n\n\n\n\n\n\t\t\t\t\tContent Governance\t\t\t\t\n\n\n\n\nContent Governance \n\n\n\t\t\t\tPoised to take over TikTok, Oracle is accused of clamping down on Pro-Palestine dissent\t\t\t\n\n19 Feb 2025\n\n\n\n\nNews\nPoised to take over TikTok, Oracle is accused of clamping down on Pro-Palestine dissent\n\n\t\t\t\t\t\t\t\t\tThe Intercept ↗\t\t\t\t\t\t\t\n↗\n19 Feb 2025\n\nPoised to take over TikTok, Oracle is accused of clamping down on Pro-Palestine dissent\n\n\n\n\n\n\n\n\n\n\t\t\t\t\tContent Governance\t\t\t\t\n\n\n\n\nContent Governance \n\n\n\t\t\t\tTamil website Vikatan inaccessible after It posted cartoon of PM, no official takedown order confirmed\t\t\t\n\n19 Feb 2025\n\n\n\n\nNews\nTamil website Vikatan inaccessible after It posted cartoon of PM, no official takedown order confirmed\n\n\t\t\t\t\t\t\t\t\tMedianama ↗\t\t\t\t\t\t\t\n↗\n19 Feb 2025\n\nTamil website Vikatan inaccessible after It posted cartoon of PM, no official takedown order confirmed\n\n\n\n\n\n\n\n\n\n\t\t\t\t\tInternet Shutdowns\t\t\t\t\n\n\n\n\nInternet Shutdowns \n\n\n\t\t\t\t2025 elections and internet shutdowns watch\t\t\t\n\n30 Jan 2025\n • \nGovernments around the world continue to shut down the internet during elections. Campaign\n2025 elections and internet shutdowns watch\n30 Jan 2025\n\n2025 elections and internet shutdowns watch\n\n\n\n\n\n\n\n\n\n\t\t\t\t\tContent Governance\t\t\t\t\n\n\n\n\nContent Governance \n\n\n\t\t\t\tTrump stand on online speech divides free speech ecosystem\t\t\t\n\n22 Jan 2025\n\n\n\n\nNews\nTrump stand on online speech divides free speech ecosystem\n\n\t\t\t\t\t\t\t\t\tHindu Businessline ↗\t\t\t\t\t\t\t\n↗\n22 Jan 2025\n\nTrump stand on online speech divides free speech ecosystem\n\n\n\n\n\n\n\n\n\n\t\t\t\t\tFreedom of Expression\t\t\t\t\n\n\n\n\nFreedom of Expression \n\n\n\t\t\t\tCeasefire in Gaza: it’s time to end digital harms and deliver justice\t\t\t\n\n20 Jan 2025\n • \nAs physical violence appears to be coming to a halt after 15 months in Gaza, Access Now further calls for a digital ceasefire. Press Release\nCeasefire in Gaza: it’s time to end digital harms and deliver justice\n20 Jan 2025\n\nCeasefire in Gaza: it’s time to end digital harms and deliver justice\n\n\n\n\n\n\n\n\n\n\t\t\t\t\tContent Governance\t\t\t\t\n\n\n\n\nContent Governance \n\n\n\t\t\t\tMetino ukidanje provjere činjenica ‘politička odluka sa stvarnim posljedicama’\t\t\t\n\n20 Jan 2025\n\n\n\n\nNews\nMetino ukidanje provjere činjenica ‘politička odluka sa stvarnim posljedicama’\n\n\t\t\t\t\t\t\t\t\tRadio Free Europe ↗\t\t\t\t\t\t\t\n↗\n20 Jan 2025\n\nMetino ukidanje provjere činjenica ‘politička odluka sa stvarnim posljedicama’\n\n\n\n\n\n\n\n\n\n\t\t\t\t\tFreedom of Expression\t\t\t\t\n\n\n\n\nFreedom of Expression \n\n\n\t\t\t\tTackling the “black snakes” undermining digital rights worldwide \t\t\t\n\n16 Jan 2025\n • \nAs 2025 gets underway, Access Now’s new Executive Director, Alejandro Mayoral Baños, PhD, shares his reflections on the “black snakes” threatening the digital rights movement. Post\nTackling the “black snakes” undermining digital rights worldwide \n16 Jan 2025\n\nTackling the “black snakes” undermining digital rights worldwide \n\n\n\n\n\n\n\n\n\n\t\t\t\t\tContent Governance\t\t\t\t\n\n\n\n\nContent Governance \n\n\n\t\t\t\tWhy Facebook ending fact checking in US is a warning sign for India\t\t\t\n\n14 Jan 2025\n\n\n\n\nNews\nWhy Facebook ending fact checking in US is a warning sign for India\n\n\t\t\t\t\t\t\t\t\tScroll ↗\t\t\t\t\t\t\t\n↗\n14 Jan 2025\n\nWhy Facebook ending fact checking in US is a warning sign for India\n\n\n\n\n\n\n\n\n\n\t\t\t\t\tContent Governance\t\t\t\t\n\n\n\n\nContent Governance \n\n\n\t\t\t\tEU regulators take a hard look at Elon Musk and X\t\t\t\n\n14 Jan 2025\n\n\n\n\nNews\nEU regulators take a hard look at Elon Musk and X\n\n\t\t\t\t\t\t\t\t\tDeutsche Welle ↗\t\t\t\t\t\t\t\n↗\n14 Jan 2025\n\nEU regulators take a hard look at Elon Musk and X\n\n\n\n\n\n\n\n\n\n\t\t\t\t\tContent Governance\t\t\t\t\n\n\n\n\nContent Governance \n\n\n\t\t\t\tPlatform accountability: a rule-of-law checklist for policymakers\t\t\t\n\n13 Jan 2025\n • \nIn this report, Access Now proposes a rule-of-law checklist to enable states to enact platform accountability regulations that are fit for purpose and protect human rights. Publication\nPlatform accountability: a rule-of-law checklist for policymakers\n\n\n↗\n13 Jan 2025\n\nPlatform accountability: a rule-of-law checklist for policymakers\n\n\n\n\n\n\n\n\n\n\t\t\t\t\tContent Governance\t\t\t\t\n\n\n\n\nContent Governance \n\n\n\t\t\t\tPlatform accountability and human rights: a rule-of-law checklist\t\t\t\n\n13 Jan 2025\n • \nAs policymakers around the world seek to rein in Big Tech, we define the safeguards necessary to ensure rule of law and protect human rights and democracy. Post\nPlatform accountability and human rights: a rule-of-law checklist\n13 Jan 2025\n\nPlatform accountability and human rights: a rule-of-law checklist\n\n\n\n\n\n\n\n\n\n\t\t\t\t\tContent Governance\t\t\t\t\n\n\n\n\nContent Governance \n\n\n\t\t\t\tGlobal fact-checkers were disappointed, not surprised, Meta ended its program\t\t\t\n\n10 Jan 2025\n\n\n\n\nNews\nGlobal fact-checkers were disappointed, not surprised, Meta ended its program\n\n\t\t\t\t\t\t\t\t\tRest of World ↗\t\t\t\t\t\t\t\n↗\n10 Jan 2025\n\nGlobal fact-checkers were disappointed, not surprised, Meta ended its program\n\n\n\n\n\n\n\n\n\n\t\t\t\t\tContent Governance\t\t\t\t\n\n\n\n\nContent Governance \n\n\n\t\t\t\tBrussels will be watching whether Musk breaks EU law in far-right livestream\t\t\t\n\n9 Jan 2025\n\n\n\n\nNews\nBrussels will be watching whether Musk breaks EU law in far-right livestream\n\n\t\t\t\t\t\t\t\t\tPOLITICO ↗\t\t\t\t\t\t\t\n↗\n9 Jan 2025\n\nBrussels will be watching whether Musk breaks EU law in far-right livestream\n\nLatest Updates\n\n\n\n     \n\n\n\n\n\nGrid View\nList View\n\nLatest Updates\n\nGrid View\nList View\n\nGrid View\nList View\n\nContent Governance\t\t\t\t\n\n\n\n\nContent Governance \n\n\n\t\t\t\t‘Profiting from misery’: how TikTok makes money from child begging livestreams\t\t\t\n\n6 Apr 2025\n\n\n\n\nNews\n‘Profiting from misery’: how TikTok makes money from child begging livestreams\n\n\t\t\t\t\t\t\t\t\tThe Guardian ↗\t\t\t\t\t\t\t\n↗\n6 Apr 2025\n\n‘Profiting from misery’: how TikTok makes money from child begging livestreams\n\n\n\n\n \n\t\t\t\t\tInternet Shutdowns\t\t\t\t\n\n\n\n\nInternet Shutdowns \n\n\n\t\t\t\tEmboldened offenders, endangered communities: internet shutdowns in 2024\t\t\t\n\n23 Feb 2025\n • \nAccess Now and the #KeepItOn coalition documented 296 internet shutdowns in 2024 — the highest number since 2016. Press Release\nOur rights are at stake: it’s time to reclaim freedom of expression\n21 Feb 2025\n\nOur rights are at stake: it’s time to reclaim freedom of expression\n\n\n\n\n\n\n\n\n\n\t\t\t\t\tContent Governance\t\t\t\t\n\n\n\n\nContent Governance \n\n\n\t\t\t\tPoised to take over TikTok, Oracle is accused of clamping down on Pro-Palestine dissent\t\t\t\n\n19 Feb 2025\n\n\n\n\nNews\nPoised to take over TikTok, Oracle is accused of clamping down on Pro-Palestine dissent\n\n\t\t\t\t\t\t\t\t\tThe Intercept ↗\t\t\t\t\t\t\t\n↗\n19 Feb 2025\n\nPoised to take over TikTok, Oracle is accused of clamping down on Pro-Palestine dissent\n\n\n\n\n\n\n\n\n\n\t\t\t\t\tContent Governance\t\t\t\t\n\n\n\n\nContent Governance \n\n\n\t\t\t\tTamil website Vikatan inaccessible after It posted cartoon of PM, no official takedown order confirmed\t\t\t\n\n19 Feb 2025\n\n\n\n\nNews\nTamil website Vikatan inaccessible after It posted cartoon of PM, no official takedown order confirmed\n\n\t\t\t\t\t\t\t\t\tMedianama ↗\t\t\t\t\t\t\t\n↗\n19 Feb 2025\n\nTamil website Vikatan inaccessible after It posted cartoon of PM, no official takedown order confirmed\n\n\n\n\n\n\n\n\n\n\t\t\t\t\tInternet Shutdowns\t\t\t\t\n\n\n\n\nInternet Shutdowns \n\n\n\t\t\t\t2025 elections and internet shutdowns watch\t\t\t\n\n30 Jan 2025\n • \nGovernments around the world continue to shut down the internet during elections. Campaign\n2025 elections and internet shutdowns watch\n30 Jan 2025\n\n2025 elections and internet shutdowns watch\n\n\n\n\n\n\n\n\n\n\t\t\t\t\tContent Governance\t\t\t\t\n\n\n\n\nContent Governance \n\n\n\t\t\t\tTrump stand on online speech divides free speech ecosystem\t\t\t\n\n22 Jan 2025\n\n\n\n\nNews\nTrump stand on online speech divides free speech ecosystem\n\n\t\t\t\t\t\t\t\t\tHindu Businessline ↗\t\t\t\t\t\t\t\n↗\n22 Jan 2025\n\nTrump stand on online speech divides free speech ecosystem\n\n\n\n\n\n\n\n\n\n\t\t\t\t\tFreedom of Expression\t\t\t\t\n\n\n\n\nFreedom of Expression \n\n\n\t\t\t\tCeasefire in Gaza: it’s time to end digital harms and deliver justice\t\t\t\n\n20 Jan 2025\n • \nAs physical violence appears to be coming to a halt after 15 months in Gaza, Access Now further calls for a digital ceasefire. Press Release\nCeasefire in Gaza: it’s time to end digital harms and deliver justice\n20 Jan 2025\n\nCeasefire in Gaza: it’s time to end digital harms and deliver justice\n\n\n\n\n\n\n\n\n\n\t\t\t\t\tContent Governance\t\t\t\t\n\n\n\n\nContent Governance \n\n\n\t\t\t\tMetino ukidanje provjere činjenica ‘politička odluka sa stvarnim posljedicama’\t\t\t\n\n20 Jan 2025\n\n\n\n\nNews\nMetino ukidanje provjere činjenica ‘politička odluka sa stvarnim posljedicama’\n\n\t\t\t\t\t\t\t\t\tRadio Free Europe ↗\t\t\t\t\t\t\t\n↗\n20 Jan 2025\n\nMetino ukidanje provjere činjenica ‘politička odluka sa stvarnim posljedicama’\n\n\n\n\n\n\n\n\n\n\t\t\t\t\tFreedom of Expression\t\t\t\t\n\n\n\n\nFreedom of Expression \n\n\n\t\t\t\tTackling the “black snakes” undermining digital rights worldwide \t\t\t\n\n16 Jan 2025\n • \nAs 2025 gets underway, Access Now’s new Executive Director, Alejandro Mayoral Baños, PhD, shares his reflections on the “black snakes” threatening the digital rights movement. Post\nTackling the “black snakes” undermining digital rights worldwide \n16 Jan 2025\n\nTackling the “black snakes” undermining digital rights worldwide \n\n\n\n\n\n\n\n\n\n\t\t\t\t\tContent Governance\t\t\t\t\n\n\n\n\nContent Governance \n\n\n\t\t\t\tWhy Facebook ending fact checking in US is a warning sign for India\t\t\t\n\n14 Jan 2025\n\n\n\n\nNews\nWhy Facebook ending fact checking in US is a warning sign for India\n\n\t\t\t\t\t\t\t\t\tScroll ↗\t\t\t\t\t\t\t\n↗\n14 Jan 2025\n\nWhy Facebook ending fact checking in US is a warning sign for India\n\n\n\n\n\n\n\n\n\n\t\t\t\t\tContent Governance\t\t\t\t\n\n\n\n\nContent Governance \n\n\n\t\t\t\tEU regulators take a hard look at Elon Musk and X\t\t\t\n\n14 Jan 2025\n\n\n\n\nNews\nEU regulators take a hard look at Elon Musk and X\n\n\t\t\t\t\t\t\t\t\tDeutsche Welle ↗\t\t\t\t\t\t\t\n↗\n14 Jan 2025\n\nEU regulators take a hard look at Elon Musk and X\n\n\n\n\n\n\n\n\n\n\t\t\t\t\tContent Governance\t\t\t\t\n\n\n\n\nContent Governance \n\n\n\t\t\t\tPlatform accountability: a rule-of-law checklist for policymakers\t\t\t\n\n13 Jan 2025\n • \nIn this report, Access Now proposes a rule-of-law checklist to enable states to enact platform accountability regulations that are fit for purpose and protect human rights. Publication\nPlatform accountability: a rule-of-law checklist for policymakers\n\n\n↗\n13 Jan 2025\n\nPlatform accountability: a rule-of-law checklist for policymakers\n\n\n\n\n\n\n\n\n\n\t\t\t\t\tContent Governance\t\t\t\t\n\n\n\n\nContent Governance \n\n\n\t\t\t\tPlatform accountability and human rights: a rule-of-law checklist\t\t\t\n\n13 Jan 2025\n • \nAs policymakers around the world seek to rein in Big Tech, we define the safeguards necessary to ensure rule of law and protect human rights and democracy. Post\nPlatform accountability and human rights: a rule-of-law checklist\n13 Jan 2025\n\nPlatform accountability and human rights: a rule-of-law checklist\n\n\n\n\n\n\n\n\n\n\t\t\t\t\tContent Governance\t\t\t\t\n\n\n\n\nContent Governance \n\n\n\t\t\t\tGlobal fact-checkers were disappointed, not surprised, Meta ended its program\t\t\t\n\n10 Jan 2025\n\n\n\n\nNews\nGlobal fact-checkers were disappointed, not surprised, Meta ended its program\n\n\t\t\t\t\t\t\t\t\tRest of World ↗\t\t\t\t\t\t\t\n↗\n10 Jan 2025\n\nGlobal fact-checkers were disappointed, not surprised, Meta ended its program\n\n\n\n\n\n\n\n\n\n\t\t\t\t\tContent Governance\t\t\t\t\n\n\n\n\nContent Governance \n\n\n\t\t\t\tBrussels will be watching whether Musk breaks EU law in far-right livestream\t\t\t\n\n9 Jan 2025\n\n\n\n\nNews\nBrussels will be watching whether Musk breaks EU law in far-right livestream\n\n\t\t\t\t\t\t\t\t\tPOLITICO ↗\t\t\t\t\t\t\t\n↗\n9 Jan 2025\n\nBrussels will be watching whether Musk breaks EU law in far-right livestream\n\nContent Governance\t\t\t\t\n\n\n\n\nContent Governance \n\n\n\t\t\t\t‘Profiting from misery’: how TikTok makes money from child begging livestreams\t\t\t\n\n6 Apr 2025\n\n\n\n\nNews\n‘Profiting from misery’: how TikTok makes money from child begging livestreams\n\n\t\t\t\t\t\t\t\t\tThe Guardian ↗\t\t\t\t\t\t\t\n↗\n6 Apr 2025\n\n‘Profiting from misery’: how TikTok makes money from child begging livestreams\n\nContent Governance\t\t\t\t\n\n\n\n\nContent Governance \n\n\n\t\t\t\t‘Profiting from misery’: how TikTok makes money from child begging livestreams\t\t\t\n\n6 Apr 2025\n\nContent Governance\n\nContent Governance\n\nContent Governance \n\n\n\t\t\t\t‘Profiting from misery’: how TikTok makes money from child begging livestreams\t\t\t\n\n6 Apr 2025\n\nContent Governance\n\nContent Governance\n\n6 Apr 2025\n\nNews\n‘Profiting from misery’: how TikTok makes money from child begging livestreams\n\n\t\t\t\t\t\t\t\t\tThe Guardian ↗\t\t\t\t\t\t\t\n↗\n6 Apr 2025\n\nNews\n\n‘Profiting from misery’: how TikTok makes money from child begging livestreams\n\nThe Guardian ↗\n\n↗\n\n6 Apr 2025\n\nInternet Shutdowns\t\t\t\t\n\n\n\n\nInternet Shutdowns \n\n\n\t\t\t\tEmboldened offenders, endangered communities: internet shutdowns in 2024\t\t\t\n\n23 Feb 2025\n • \nAccess Now and the #KeepItOn coalition documented 296 internet shutdowns in 2024 — the highest number since 2016. Publication\nEmboldened offenders, endangered communities: internet shutdowns in 2024\n\n\n↗\n23 Feb 2025\n\nPublication\n\nEmboldened offenders, endangered communities: internet shutdowns in 2024\n\n↗\n\n23 Feb 2025\n\nFreedom of Expression\t\t\t\t\n\n\n\n\nFreedom of Expression \n\n\n\t\t\t\tOur rights are at stake: it’s time to reclaim freedom of expression\t\t\t\n\n21 Feb 2025\n • \nGiven the escalating use of free speech claims as a shield for inciting hatred and violence, it is more urgent than ever to reaffirm what freedom of expression truly stands for. Press Release\nOur rights are at stake: it’s time to reclaim freedom of expression\n21 Feb 2025\n\nOur rights are at stake: it’s time to reclaim freedom of expression\n\nFreedom of Expression\t\t\t\t\n\n\n\n\nFreedom of Expression \n\n\n\t\t\t\tOur rights are at stake: it’s time to reclaim freedom of expression\t\t\t\n\n21 Feb 2025\n • \nGiven the escalating use of free speech claims as a shield for inciting hatred and violence, it is more urgent than ever to reaffirm what freedom of expression truly stands for. Press Release\nOur rights are at stake: it’s time to reclaim freedom of expression\n21 Feb 2025\n\nPress Release\n\nOur rights are at stake: it’s time to reclaim freedom of expression\n\n21 Feb 2025\n\nContent Governance\t\t\t\t\n\n\n\n\nContent Governance \n\n\n\t\t\t\tPoised to take over TikTok, Oracle is accused of clamping down on Pro-Palestine dissent\t\t\t\n\n19 Feb 2025\n\n\n\n\nNews\nPoised to take over TikTok, Oracle is accused of clamping down on Pro-Palestine dissent\n\n\t\t\t\t\t\t\t\t\tThe Intercept ↗\t\t\t\t\t\t\t\n↗\n19 Feb 2025\n\nPoised to take over TikTok, Oracle is accused of clamping down on Pro-Palestine dissent\n\nContent Governance\t\t\t\t\n\n\n\n\nContent Governance \n\n\n\t\t\t\tPoised to take over TikTok, Oracle is accused of clamping down on Pro-Palestine dissent\t\t\t\n\n19 Feb 2025\n\nContent Governance\n\nContent Governance\n\nContent Governance \n\n\n\t\t\t\tPoised to take over TikTok, Oracle is accused of clamping down on Pro-Palestine dissent\t\t\t\n\n19 Feb 2025\n\nContent Governance\n\nContent Governance\n\n19 Feb 2025\n\nNews\nPoised to take over TikTok, Oracle is accused of clamping down on Pro-Palestine dissent\n\n\t\t\t\t\t\t\t\t\tThe Intercept ↗\t\t\t\t\t\t\t\n↗\n19 Feb 2025\n\nNews\n\nPoised to take over TikTok, Oracle is accused of clamping down on Pro-Palestine dissent\n\nThe Intercept ↗\n\n↗\n\n19 Feb 2025\n\nContent Governance\t\t\t\t\n\n\n\n\nContent Governance \n\n\n\t\t\t\tTamil website Vikatan inaccessible after It posted cartoon of PM, no official takedown order confirmed\t\t\t\n\n19 Feb 2025\n\n\n\n\nNews\nTamil website Vikatan inaccessible after It posted cartoon of PM, no official takedown order confirmed\n\n\t\t\t\t\t\t\t\t\tMedianama ↗\t\t\t\t\t\t\t\n↗\n19 Feb 2025\n\nTamil website Vikatan inaccessible after It posted cartoon of PM, no official takedown order confirmed\n\nContent Governance\t\t\t\t\n\n\n\n\nContent Governance \n\n\n\t\t\t\tTamil website Vikatan inaccessible after It posted cartoon of PM, no official takedown order confirmed\t\t\t\n\n19 Feb 2025\n\nContent Governance\n\nContent Governance\n\nContent Governance \n\n\n\t\t\t\tTamil website Vikatan inaccessible after It posted cartoon of PM, no official takedown order confirmed\t\t\t\n\n19 Feb 2025\n\nContent Governance\n\nContent Governance\n\n19 Feb 2025\n\nNews\nTamil website Vikatan inaccessible after It posted cartoon of PM, no official takedown order confirmed\n\n\t\t\t\t\t\t\t\t\tMedianama ↗\t\t\t\t\t\t\t\n↗\n19 Feb 2025\n\nNews\n\nTamil website Vikatan inaccessible after It posted cartoon of PM, no official takedown order confirmed\n\nMedianama ↗\n\n↗\n\n19 Feb 2025\n\nInternet Shutdowns\t\t\t\t\n\n\n\n\nInternet Shutdowns \n\n\n\t\t\t\t2025 elections and internet shutdowns watch\t\t\t\n\n30 Jan 2025\n • \nGovernments around the world continue to shut down the internet during elections. Campaign\n2025 elections and internet shutdowns watch\n30 Jan 2025\n\nCampaign\n\n2025 elections and internet shutdowns watch\n\n30 Jan 2025\n\nContent Governance\t\t\t\t\n\n\n\n\nContent Governance \n\n\n\t\t\t\tTrump stand on online speech divides free speech ecosystem\t\t\t\n\n22 Jan 2025\n\n\n\n\nNews\nTrump stand on online speech divides free speech ecosystem\n\n\t\t\t\t\t\t\t\t\tHindu Businessline ↗\t\t\t\t\t\t\t\n↗\n22 Jan 2025\n\nTrump stand on online speech divides free speech ecosystem\n\nContent Governance\t\t\t\t\n\n\n\n\nContent Governance \n\n\n\t\t\t\tTrump stand on online speech divides free speech ecosystem\t\t\t\n\n22 Jan 2025\n\nContent Governance\n\nContent Governance\n\nContent Governance \n\n\n\t\t\t\tTrump stand on online speech divides free speech ecosystem\t\t\t\n\n22 Jan 2025\n\nContent Governance\n\nContent Governance\n\n22 Jan 2025\n\nNews\nTrump stand on online speech divides free speech ecosystem\n\n\t\t\t\t\t\t\t\t\tHindu Businessline ↗\t\t\t\t\t\t\t\n↗\n22 Jan 2025\n\nNews\n\nTrump stand on online speech divides free speech ecosystem\n\nHindu Businessline ↗\n\n↗\n\n22 Jan 2025\n\nFreedom of Expression\t\t\t\t\n\n\n\n\nFreedom of Expression \n\n\n\t\t\t\tCeasefire in Gaza: it’s time to end digital harms and deliver justice\t\t\t\n\n20 Jan 2025\n • \nAs physical violence appears to be coming to a halt after 15 months in Gaza, Access Now further calls for a digital ceasefire. Press Release\nCeasefire in Gaza: it’s time to end digital harms and deliver justice\n20 Jan 2025\n\nPress Release\n\nCeasefire in Gaza: it’s time to end digital harms and deliver justice\n\n20 Jan 2025\n\nContent Governance\t\t\t\t\n\n\n\n\nContent Governance \n\n\n\t\t\t\tMetino ukidanje provjere činjenica ‘politička odluka sa stvarnim posljedicama’\t\t\t\n\n20 Jan 2025\n\n\n\n\nNews\nMetino ukidanje provjere činjenica ‘politička odluka sa stvarnim posljedicama’\n\n\t\t\t\t\t\t\t\t\tRadio Free Europe ↗\t\t\t\t\t\t\t\n↗\n20 Jan 2025\n\nMetino ukidanje provjere činjenica ‘politička odluka sa stvarnim posljedicama’\n\nContent Governance\t\t\t\t\n\n\n\n\nContent Governance \n\n\n\t\t\t\tMetino ukidanje provjere činjenica ‘politička odluka sa stvarnim posljedicama’\t\t\t\n\n20 Jan 2025\n\nContent Governance\n\nContent Governance\n\nContent Governance \n\n\n\t\t\t\tMetino ukidanje provjere činjenica ‘politička odluka sa stvarnim posljedicama’\t\t\t\n\n20 Jan 2025\n\nContent Governance\n\nContent Governance\n\n20 Jan 2025\n\nNews\nMetino ukidanje provjere činjenica ‘politička odluka sa stvarnim posljedicama’\n\n\t\t\t\t\t\t\t\t\tRadio Free Europe ↗\t\t\t\t\t\t\t\n↗\n20 Jan 2025\n\nNews\n\nMetino ukidanje provjere činjenica ‘politička odluka sa stvarnim posljedicama’\n\nRadio Free Europe ↗\n\n↗\n\n20 Jan 2025\n\nFreedom of Expression\t\t\t\t\n\n\n\n\nFreedom of Expression \n\n\n\t\t\t\tTackling the “black snakes” undermining digital rights worldwide \t\t\t\n\n16 Jan 2025\n • \nAs 2025 gets underway, Access Now’s new Executive Director, Alejandro Mayoral Baños, PhD, shares his reflections on the “black snakes” threatening the digital rights movement. Post\nTackling the “black snakes” undermining digital rights worldwide \n16 Jan 2025\n\nTackling the “black snakes” undermining digital rights worldwide\n\nFreedom of Expression\t\t\t\t\n\n\n\n\nFreedom of Expression \n\n\n\t\t\t\tTackling the “black snakes” undermining digital rights worldwide \t\t\t\n\n16 Jan 2025\n • \nAs 2025 gets underway, Access Now’s new Executive Director, Alejandro Mayoral Baños, PhD, shares his reflections on the “black snakes” threatening the digital rights movement. Post\nTackling the “black snakes” undermining digital rights worldwide \n16 Jan 2025\n\nPost\n\nTackling the “black snakes” undermining digital rights worldwide\n\n16 Jan 2025\n\nContent Governance\t\t\t\t\n\n\n\n\nContent Governance \n\n\n\t\t\t\tWhy Facebook ending fact checking in US is a warning sign for India\t\t\t\n\n14 Jan 2025\n\n\n\n\nNews\nWhy Facebook ending fact checking in US is a warning sign for India\n\n\t\t\t\t\t\t\t\t\tScroll ↗\t\t\t\t\t\t\t\n↗\n14 Jan 2025\n\nWhy Facebook ending fact checking in US is a warning sign for India\n\nContent Governance\t\t\t\t\n\n\n\n\nContent Governance \n\n\n\t\t\t\tWhy Facebook ending fact checking in US is a warning sign for India\t\t\t\n\n14 Jan 2025\n\nContent Governance\n\nContent Governance\n\nContent Governance \n\n\n\t\t\t\tWhy Facebook ending fact checking in US is a warning sign for India\t\t\t\n\n14 Jan 2025\n\nContent Governance\n\nContent Governance\n\n14 Jan 2025\n\nNews\nWhy Facebook ending fact checking in US is a warning sign for India\n\n\t\t\t\t\t\t\t\t\tScroll ↗\t\t\t\t\t\t\t\n↗\n14 Jan 2025\n\nNews\n\nWhy Facebook ending fact checking in US is a warning sign for India\n\nScroll ↗\n\n↗\n\n14 Jan 2025\n\nContent Governance\t\t\t\t\n\n\n\n\nContent Governance \n\n\n\t\t\t\tEU regulators take a hard look at Elon Musk and X\t\t\t\n\n14 Jan 2025\n\n\n\n\nNews\nEU regulators take a hard look at Elon Musk and X\n\n\t\t\t\t\t\t\t\t\tDeutsche Welle ↗\t\t\t\t\t\t\t\n↗\n14 Jan 2025\n\nEU regulators take a hard look at Elon Musk and X\n\nContent Governance\t\t\t\t\n\n\n\n\nContent Governance \n\n\n\t\t\t\tEU regulators take a hard look at Elon Musk and X\t\t\t\n\n14 Jan 2025\n\nContent Governance\n\nContent Governance\n\nContent Governance \n\n\n\t\t\t\tEU regulators take a hard look at Elon Musk and X\t\t\t\n\n14 Jan 2025\n\nContent Governance\n\nContent Governance\n\n14 Jan 2025\n\nNews\nEU regulators take a hard look at Elon Musk and X\n\n\t\t\t\t\t\t\t\t\tDeutsche Welle ↗\t\t\t\t\t\t\t\n↗\n14 Jan 2025\n\nNews\n\nEU regulators take a hard look at Elon Musk and X\n\nDeutsche Welle ↗\n\n↗\n\n14 Jan 2025\n\nContent Governance\t\t\t\t\n\n\n\n\nContent Governance \n\n\n\t\t\t\tPlatform accountability: a rule-of-law checklist for policymakers\t\t\t\n\n13 Jan 2025\n • \nIn this report, Access Now proposes a rule-of-law checklist to enable states to enact platform accountability regulations that are fit for purpose and protect human rights. Publication\nPlatform accountability: a rule-of-law checklist for policymakers\n\n\n↗\n13 Jan 2025\n\nPlatform accountability: a rule-of-law checklist for policymakers\n\nContent Governance\t\t\t\t\n\n\n\n\nContent Governance \n\n\n\t\t\t\tPlatform accountability: a rule-of-law checklist for policymakers\t\t\t\n\n13 Jan 2025\n • \nIn this report, Access Now proposes a rule-of-law checklist to enable states to enact platform accountability regulations that are fit for purpose and protect human rights. Content Governance\n\nContent Governance\n\nContent Governance \n\n\n\t\t\t\tPlatform accountability: a rule-of-law checklist for policymakers\t\t\t\n\n13 Jan 2025\n • \nIn this report, Access Now proposes a rule-of-law checklist to enable states to enact platform accountability regulations that are fit for purpose and protect human rights. Publication\nPlatform accountability: a rule-of-law checklist for policymakers\n\n\n↗\n13 Jan 2025\n\nPublication\n\nPlatform accountability: a rule-of-law checklist for policymakers\n\n↗\n\n13 Jan 2025\n\nContent Governance\t\t\t\t\n\n\n\n\nContent Governance \n\n\n\t\t\t\tPlatform accountability and human rights: a rule-of-law checklist\t\t\t\n\n13 Jan 2025\n • \nAs policymakers around the world seek to rein in Big Tech, we define the safeguards necessary to ensure rule of law and protect human rights and democracy. Post\nPlatform accountability and human rights: a rule-of-law checklist\n13 Jan 2025\n\nPlatform accountability and human rights: a rule-of-law checklist\n\nContent Governance\t\t\t\t\n\n\n\n\nContent Governance \n\n\n\t\t\t\tPlatform accountability and human rights: a rule-of-law checklist\t\t\t\n\n13 Jan 2025\n • \nAs policymakers around the world seek to rein in Big Tech, we define the safeguards necessary to ensure rule of law and protect human rights and democracy. Content Governance\n\nContent Governance\n\nContent Governance \n\n\n\t\t\t\tPlatform accountability and human rights: a rule-of-law checklist\t\t\t\n\n13 Jan 2025\n • \nAs policymakers around the world seek to rein in Big Tech, we define the safeguards necessary to ensure rule of law and protect human rights and democracy. Post\nPlatform accountability and human rights: a rule-of-law checklist\n13 Jan 2025\n\nPost\n\nPlatform accountability and human rights: a rule-of-law checklist\n\n13 Jan 2025\n\nContent Governance\t\t\t\t\n\n\n\n\nContent Governance \n\n\n\t\t\t\tGlobal fact-checkers were disappointed, not surprised, Meta ended its program\t\t\t\n\n10 Jan 2025\n\n\n\n\nNews\nGlobal fact-checkers were disappointed, not surprised, Meta ended its program\n\n\t\t\t\t\t\t\t\t\tRest of World ↗\t\t\t\t\t\t\t\n↗\n10 Jan 2025\n\nGlobal fact-checkers were disappointed, not surprised, Meta ended its program\n\nContent Governance\t\t\t\t\n\n\n\n\nContent Governance \n\n\n\t\t\t\tGlobal fact-checkers were disappointed, not surprised, Meta ended its program\t\t\t\n\n10 Jan 2025\n\nContent Governance\n\nContent Governance\n\nContent Governance \n\n\n\t\t\t\tGlobal fact-checkers were disappointed, not surprised, Meta ended its program\t\t\t\n\n10 Jan 2025\n\nContent Governance\n\nContent Governance\n\n10 Jan 2025\n\nNews\nGlobal fact-checkers were disappointed, not surprised, Meta ended its program\n\n\t\t\t\t\t\t\t\t\tRest of World ↗\t\t\t\t\t\t\t\n↗\n10 Jan 2025\n\nNews\n\nGlobal fact-checkers were disappointed, not surprised, Meta ended its program\n\nRest of World ↗\n\n↗\n\n10 Jan 2025\n\nContent Governance\t\t\t\t\n\n\n\n\nContent Governance \n\n\n\t\t\t\tBrussels will be watching whether Musk breaks EU law in far-right livestream\t\t\t\n\n9 Jan 2025\n\n\n\n\nNews\nBrussels will be watching whether Musk breaks EU law in far-right livestream\n\n\t\t\t\t\t\t\t\t\tPOLITICO ↗\t\t\t\t\t\t\t\n↗\n9 Jan 2025\n\nBrussels will be watching whether Musk breaks EU law in far-right livestream\n\nContent Governance\t\t\t\t\n\n\n\n\nContent Governance \n\n\n\t\t\t\tBrussels will be watching whether Musk breaks EU law in far-right livestream\t\t\t\n\n9 Jan 2025\n\nContent Governance\n\nContent Governance\n\nContent Governance \n\n\n\t\t\t\tBrussels will be watching whether Musk breaks EU law in far-right livestream\t\t\t\n\n9 Jan 2025\n\nContent Governance\n\nContent Governance\n\n9 Jan 2025\n\nNews\nBrussels will be watching whether Musk breaks EU law in far-right livestream\n\n\t\t\t\t\t\t\t\t\tPOLITICO ↗\t\t\t\t\t\t\t\n↗\n9 Jan 2025\n\nNews\n\nBrussels will be watching whether Musk breaks EU law in far-right livestream\n\nPOLITICO ↗\n\n↗\n\n9 Jan 2025\n\nHelp keep the internet open and secure.",
  "entities": {
    "countries": [
      "afghanistan",
      "australia",
      "brazil",
      "canada",
      "china",
      "france",
      "germany",
      "india",
      "iran",
      "iraq",
      "israel",
      "japan",
      "mexico",
      "north korea",
      "pakistan",
      "russia",
      "south korea",
      "syria",
      "united kingdom",
      "united states",
      "yemen"
    ],
    "organizations": [
      "un",
      "who"
    ],
    "key_issues": [
      "crisis",
      "country",
      "state",
      "government",
      "territory",
      "solution",
      "approach",
      "policy",
      "program",
      "action",
      "human rights",
      "un",
      "ngo"
    ]
  },
  "committee": "First Committee",
  "topic": "Creating systems to protect against state-sponsored cyber attacks"
}