{
  "url": "https://www.accessnow.org/issue/connectivity/",
  "title": "Connectivity - Access Now",
  "text": "Back to content\n\nEquitable Internet Access For All\n\n\n\nToday, affordable and meaningful access to the internet is an essential enabler of human rights. We advocate for policies and technologies to support equitable access to a free, open, and secure internet, and capacity-building to enable marginalized people and communities to make the most of it.\n\n\n\n\n\n\n\n\n\n\n\n\n\nMore than 3.5 billion left in the dark: why we’re still fighting to reach U.N. targets for internet access\nImagine the world coming together to envision, plan, and commit to creating a better future — for everyone, everywhere. \n\nLearn more\n\n\n\n\n\n\nResources\n\n\n\n\n\n\n\n\n\n\n\n\n\n\n\n\t\t\t\n\t\t\t\tExpanding connectivity to fight COVID-19: recommendations for governments and telcos \n\t\t\t\t\t\t\t\n\n\n\n\n\n\n\n\n\n\n\n\n\nFreedom of Expression\n\n\n\t\t\t\n\t\t\t\tTunisia: Access to online conferencing platforms and networks is a constitutional right\n\t\t\t\t\t\t\t\n\n\nAccess Now joins civil society organizations in calling for safe and open access to online conferencing platforms in Tunisia.\n\n\n\n\n\n\n\n\n\n\n\n\n\nFreedom of Expression\n\n\n\t\t\t\n\t\t\t\tVictory! U.S. Senate passes infrastructure bill, critical to get people online\n\t\t\t\t\t\t\t\n\n\nAccess Now applauds the U.S. Senate for passing an infrastructure bill that would help get people online.\n\n\n\n\n\n\n\n\n\n\n\n\n\nFreedom of Expression\n\n\n\t\t\t\n\t\t\t\tWhat the tech sector can do to respect human rights in Ukraine, Russia, Belarus, and beyond\n\t\t\t\t\t\t\t\n\n\nAs the Russia-Ukraine crisis escalates to war, the tech sector must do more than merely comply with sanctions. Here are our recommendations for mitigating human rights harms. \n\n\n\n\n\n\n\n\n\n\n\nLatest Updates\n\n\n\n     \n\n\n\n\n\nGrid View\nList View\n\n\n\n\n\n\n\n\n\n\n\n\n\n\t\t\t\t\tConnectivity\t\t\t\t\n\n\n\n\nConnectivity \n\n\n\t\t\t\tJoint statement: five-point plan for an inclusive WSIS+20 review\t\t\t\n\n29 Mar 2025\n\n\n\n\nPress Release\nJoint statement: five-point plan for an inclusive WSIS+20 review\n\n\n↗\n29 Mar 2025\n\nJoint statement: five-point plan for an inclusive WSIS+20 review\n\n\n\n\n\n\n\n\n\n\t\t\t\t\tConnectivity\t\t\t\t\n\n\n\n\nConnectivity \n\n\n\t\t\t\tOral statement at 10th Session of the UN Open Ended Working Group on ICTs\t\t\t\n\n21 Feb 2025\n • \nAccess Now’s oral statement at the 10th Session of the UN Open Ended Working Group on information and communication technology.\n\n\n\n\nPublication\nOral statement at 10th Session of the UN Open Ended Working Group on ICTs\n\n\n↗\n21 Feb 2025\n\nOral statement at 10th Session of the UN Open Ended Working Group on ICTs\n\n\n\n\n\n\n\n\n\n\t\t\t\t\tConnectivity\t\t\t\t\n\n\n\n\nConnectivity \n\n\n\t\t\t\tHolding space for human rights: improving the governance of satellite internet connectivity\t\t\t\n\n5 Feb 2025\n • \nFrom obstructed humanitarian access to the weaponization of personal digital devices, internet connectivity is an issue that carries multiple layers of harms\n— one that we are only just starting to unpack.\n\n\n\n\nPublication\nHolding space for human rights: improving the governance of satellite internet connectivity\n\n\n↗\n5 Feb 2025\n\nHolding space for human rights: improving the governance of satellite internet connectivity\n\n\n\n\n\n\n\n\n\n\t\t\t\t\tFreedom of Expression\t\t\t\t\n\n\n\n\nFreedom of Expression \n\n\n\t\t\t\tCeasefire in Gaza: it’s time to end digital harms and deliver justice\t\t\t\n\n20 Jan 2025\n • \nAs physical violence appears to be coming to a halt after 15 months in Gaza, Access Now further calls for a digital ceasefire.\n\n\n\n\nPress Release\nCeasefire in Gaza: it’s time to end digital harms and deliver justice\n20 Jan 2025\n\nCeasefire in Gaza: it’s time to end digital harms and deliver justice\n\n\n\n\n\n\n\n\n\n\t\t\t\t\tFreedom of Expression\t\t\t\t\n\n\n\n\nFreedom of Expression \n\n\n\t\t\t\tTackling the “black snakes” undermining digital rights worldwide \t\t\t\n\n16 Jan 2025\n • \nAs 2025 gets underway, Access Now’s new Executive Director, Alejandro Mayoral Baños, PhD, shares his reflections on the “black snakes” threatening the digital rights movement. \n\n\n\n\nPost\nTackling the “black snakes” undermining digital rights worldwide \n16 Jan 2025\n\nTackling the “black snakes” undermining digital rights worldwide \n\n\n\n\n\n\n\n\n\n\t\t\t\t\tInternet Shutdowns\t\t\t\t\n\n\n\n\nInternet Shutdowns \n\n\n\t\t\t\t#KeepItOn in Tanzania: authorities must ensure connectivity during local elections\t\t\t\n\n21 Nov 2024\n • \nThe #KeepItOn coalition demands that the Government of Tanzania ensure unhindered access to the internet during the upcoming elections.\n\n\n\n\nPress Release\n#KeepItOn in Tanzania: authorities must ensure connectivity during local elections\n21 Nov 2024\n\n#KeepItOn in Tanzania: authorities must ensure connectivity during local elections\n\n\n\n\n\n\n\n\n\n\t\t\t\t\tInternet Shutdowns\t\t\t\t\n\n\n\n\nInternet Shutdowns \n\n\n\t\t\t\t#KeepItOn: the Government of Tanzania and internet service providers must ensure open and secure internet access throughout the 2024 local elections\t\t\t\n\n21 Nov 2024\n • \nThe #KeepItOn coalition calls on authorities and ISPs in Tanzania to ensure internet access during the upcoming elections. \n\n\n\n\nPress Release\n#KeepItOn: the Government of Tanzania and internet service providers must ensure open and secure internet access throughout the 2024 local elections\n21 Nov 2024\n\n#KeepItOn: the Government of Tanzania and internet service providers must ensure open and secure internet access throughout the 2024 local elections\n\n\n\n\n\n\n\n\n\n\t\t\t\t\tConnectivity\t\t\t\t\n\n\n\n\nConnectivity \n\n\n\t\t\t\tAs Israel destroys infrastructure, will Lebanon be cut off from outside world?\t\t\t\n\n15 Nov 2024\n\n\n\n\nNews\nAs Israel destroys infrastructure, will Lebanon be cut off from outside world?\n\n\t\t\t\t\t\t\t\t\tThe New Arab ↗\t\t\t\t\t\t\t\n↗\n15 Nov 2024\n\nAs Israel destroys infrastructure, will Lebanon be cut off from outside world?\n\n\n\n\n\n\n\n\n\n\t\t\t\t\tConnectivity\t\t\t\t\n\n\n\n\nConnectivity \n\n\n\t\t\t\tApple keeps killing VPN apps upon Russia’s orders – Amnezia VPN is the last victim\t\t\t\n\n4 Nov 2024\n\n\n\n\nNews\nApple keeps killing VPN apps upon Russia’s orders – Amnezia VPN is the last victim\n\n\t\t\t\t\t\t\t\t\tTechRadar ↗\t\t\t\t\t\t\t\n↗\n4 Nov 2024\n\nApple keeps killing VPN apps upon Russia’s orders – Amnezia VPN is the last victim\n\n\n\n\n\n\n\n\n\n\t\t\t\t\tInternet Shutdowns\t\t\t\t\n\n\n\n\nInternet Shutdowns \n\n\n\t\t\t\t#KeepItOn Mauritius: global coalition urges first-time offender to end crackdown on social media\t\t\t\n\n1 Nov 2024\n\n\n\n\nPress Release\n#KeepItOn Mauritius: global coalition urges first-time offender to end crackdown on social media\n1 Nov 2024\n\n#KeepItOn Mauritius: global coalition urges first-time offender to end crackdown on social media\n\n\n\n\n\n\n\n\n\n\t\t\t\t\tConnectivity\t\t\t\t\n\n\n\n\nConnectivity \n\n\n\t\t\t\tMyanmar residents struggle to overcome severe internet blackouts with Starlink\t\t\t\n\n23 Oct 2024\n\n\n\n\nNews\nMyanmar residents struggle to overcome severe internet blackouts with Starlink\n\n\t\t\t\t\t\t\t\t\tRest of World ↗\t\t\t\t\t\t\t\n↗\n23 Oct 2024\n\nMyanmar residents struggle to overcome severe internet blackouts with Starlink\n\n\n\n\n\n\n\n\n\n\t\t\t\t\tConnectivity\t\t\t\t\n\n\n\n\nConnectivity \n\n\n\t\t\t\tستارلينك في اليمن: لماذا يعارض الحوثيون تفعيل الإنترنت الفضائي؟\t\t\t\n\n1 Oct 2024\n\n\n\n\nNews\nستارلينك في اليمن: لماذا يعارض الحوثيون تفعيل الإنترنت الفضائي؟\n\n\t\t\t\t\t\t\t\t\tBBC ↗\t\t\t\t\t\t\t\n↗\n1 Oct 2024\n\nستارلينك في اليمن: لماذا يعارض الحوثيون تفعيل الإنترنت الفضائي؟\n\n\n\n\n\n\n\n\n\n\t\t\t\t\tInternet Shutdowns\t\t\t\t\n\n\n\n\nInternet Shutdowns \n\n\n\t\t\t\tJoint statement: Sudan has suffered in silence for over 500 days\t\t\t\n\n5 Sep 2024\n • \nAfter more than 500 days of brutal conflict in Sudan, the #KeepItOn coalition reiterates calls to reactivate telecommunication services.\n\n\n\n\nPress Release\nJoint statement: Sudan has suffered in silence for over 500 days\n5 Sep 2024\n\nJoint statement: Sudan has suffered in silence for over 500 days\n\n\n\n\n\n\n\n\n\n\t\t\t\t\tInternet Shutdowns\t\t\t\t\n\n\n\n\nInternet Shutdowns \n\n\n\t\t\t\tAfrica in 2023: internet shutdowns attack democracy\t\t\t\n\n26 Aug 2024\n\n\n\n\nPress Release\nAfrica in 2023: internet shutdowns attack democracy\n26 Aug 2024\n\nAfrica in 2023: internet shutdowns attack democracy\n\n\n\n\n\n\n\n\n\n\t\t\t\t\tInternet Shutdowns\t\t\t\t\n\n\n\n\nInternet Shutdowns \n\n\n\t\t\t\t#KeepItOn in Annobón: Authorities in Equatorial Guinea must end internet shutdown and other human rights abuses\t\t\t\n\n13 Aug 2024\n • \nAccess Now and the #KeepItOn coalition are calling on authorities in Equatorial Guinea to immediately restore internet and telecom services in Annobón.\n\n\n\n\nPress Release\n#KeepItOn in Annobón: Authorities in Equatorial Guinea must end internet shutdown and other human rights abuses\n13 Aug 2024\n\n#KeepItOn in Annobón: Authorities in Equatorial Guinea must end internet shutdown and other human rights abuses\n\n\n\n\n\n\n\n\n\n\t\t\t\t\tInternet Shutdowns\t\t\t\t\n\n\n\n\nInternet Shutdowns \n\n\n\t\t\t\t#KeepItOn en Annobón: Las autoridades de Guinea Ecuatorial deben poner fin al corte de internet y otros abusos a los derechos humanos\t\t\t\n\n13 Aug 2024\n • \nLa coalición #KeepItOn instan a las autoridades de Guinea Ecuatorial a restablecer de inmediato el acceso a internet en Annobón.\n\n\n\n\nPress Release\n#KeepItOn en Annobón: Las autoridades de Guinea Ecuatorial deben poner fin al corte de internet y otros abusos a los derechos humanos\n13 Aug 2024\n\n#KeepItOn en Annobón: Las autoridades de Guinea Ecuatorial deben poner fin al corte de internet y otros abusos a los derechos humanos\n\n\n\n\n\n\n\n\n \n\n\n\n\n\n\nHelp keep the internet open and secure.\nSubscribe to our action alerts and weekly newsletter\n\"*\" indicates required fields\n\nThis field is hidden when viewing the form\n\nSubscribe to Access Express\nThis field is hidden when viewing the form\n\nSubscribe to Action Alerts\nName\n\n\nFirst\n\n\n\nLast\n\nEmail*\n\nCountryCountryAfghanistanÅland IslandsAlbaniaAlgeriaAmerican SamoaAndorraAngolaAnguillaAntigua and BarbudaArgentinaArmeniaArubaAustraliaAustriaAzerbaijanBahamasBahrainBangladeshBarbadosBelarusBelgiumBelizeBeninBermudaBhutanBoliviaBonaire, Sint Eustatius and SabaBosnia and HerzegovinaBotswanaBrazilBritish Indian Ocean TerritoryBritish Virgin IslandsBruneiBulgariaBurkina FasoBurundiCambodiaCameroonCanadaCape VerdeCayman IslandsCentral African RepublicChadChileChinaChristmas IslandColombiaComorosCook IslandsCosta RicaCôte d'IvoireCroatiaCubaCuraçaoCyprusCzech RepublicDemocratic Republic of the CongoDenmarkDjiboutiDominicaDominican RepublicEast TimorEcuadorEgyptEl SalvadorEquatorial GuineaEritreaEstoniaEswatiniEthiopiaFalkland IslandsFaroe IslandsFijiFinlandFranceFrench GuianaFrench PolynesiaFrench Southern TerritoriesGabonGeorgiaGermanyGhanaGibraltarGreeceGreenlandGrenadaGuadeloupeGuamGuatemalaGuernseyGuineaGuinea-BissauGuyanaHaitiHondurasHong KongHungaryIcelandIndiaIndonesiaIranIraqIrelandIsraelItalyJamaicaJapanJordanKazakhstanKenyaKiribatiKosovoKuwaitKyrgyzstanLaosLatviaLebanonLesothoLiberiaLibyaLiechtensteinLithuaniaLuxembourgMacauMadagascarMalawiMalaysiaMaldivesMaliMaltaMarshall IslandsMartiniqueMauritaniaMauritiusMayotteMexicoMicronesiaMoldovaMonacoMongoliaMontenegroMontserratMoroccoMozambiqueMyanmarNamibiaNauruNepalNetherlands AntillesNew CaledoniaNew ZealandNicaraguaNigerNigeriaNiueNorfolk IslandNorth KoreaNorth MacedoniaNorthern Mariana IslandsNorwayOmanPakistanPalauPalestinePanamaPapua New GuineaParaguayPeruPhilippinesPitcairn IslandPolandPortugalPuerto RicoQatarRepublic of the CongoReunionRomaniaRussiaRwandaSaint BarthélemySaint Kitts and NevisSaint LuciaSaint Vincent and the GrenadinesSamoaSan MarinoSão Tomé and PríncipeSaudi ArabiaSenegalSerbiaSeychellesSierra LeoneSingaporeSlovakiaSloveniaSolomon IslandsSomaliaSomalilandSouth AfricaSouth KoreaSouth SudanSpainSri LankaSt. HelenaSt. Pierre and MiquelonSudanSurinameSwedenSwitzerlandSyriaTaiwanTajikistanTanzaniaThailandThe GambiaThe NetherlandsTogoTokelauTongaTrinidad and TobagoTunisiaTurkeyTurkmenistanTurks and Caicos IslandsTuvaluUgandaUkraineUnited Arab EmiratesUnited KingdomUnited StatesUruguayUzbekistanVanuatuVatican CityVenezuelaVietnamVirgin Islands (U.S.)Wallis and Futuna IslandsWestern SaharaYemenZambiaZimbabwePostal CodeEmailThis field is for validation purposes and should be left unchanged.\n \n\n\n\n\n\n\n\n\n\n\n\n\n\n\n\nYour info is secure with us\n\nEquitable Internet Access For All\n\n\n\nToday, affordable and meaningful access to the internet is an essential enabler of human rights. We advocate for policies and technologies to support equitable access to a free, open, and secure internet, and capacity-building to enable marginalized people and communities to make the most of it.\n\n\n\n\n\n\n\n\n\n\n\n\n\nMore than 3.5 billion left in the dark: why we’re still fighting to reach U.N. targets for internet access\nImagine the world coming together to envision, plan, and commit to creating a better future — for everyone, everywhere. \n\nLearn more\n\n\n\n\n\n\nResources\n\n\n\n\n\n\n\n\n\n\n\n\n\n\n\n\t\t\t\n\t\t\t\tExpanding connectivity to fight COVID-19: recommendations for governments and telcos \n\t\t\t\t\t\t\t\n\n\n\n\n\n\n\n\n\n\n\n\n\nFreedom of Expression\n\n\n\t\t\t\n\t\t\t\tTunisia: Access to online conferencing platforms and networks is a constitutional right\n\t\t\t\t\t\t\t\n\n\nAccess Now joins civil society organizations in calling for safe and open access to online conferencing platforms in Tunisia.\n\n\n\n\n\n\n\n\n\n\n\n\n\nFreedom of Expression\n\n\n\t\t\t\n\t\t\t\tVictory! U.S. Senate passes infrastructure bill, critical to get people online\n\t\t\t\t\t\t\t\n\n\nAccess Now applauds the U.S. Senate for passing an infrastructure bill that would help get people online.\n\n\n\n\n\n\n\n\n\n\n\n\n\nFreedom of Expression\n\n\n\t\t\t\n\t\t\t\tWhat the tech sector can do to respect human rights in Ukraine, Russia, Belarus, and beyond\n\t\t\t\t\t\t\t\n\n\nAs the Russia-Ukraine crisis escalates to war, the tech sector must do more than merely comply with sanctions. Here are our recommendations for mitigating human rights harms. \n\n\n\n\n\n\n\n\n\n\n\nLatest Updates\n\n\n\n     \n\n\n\n\n\nGrid View\nList View\n\n\n\n\n\n\n\n\n\n\n\n\n\n\t\t\t\t\tConnectivity\t\t\t\t\n\n\n\n\nConnectivity \n\n\n\t\t\t\tJoint statement: five-point plan for an inclusive WSIS+20 review\t\t\t\n\n29 Mar 2025\n\n\n\n\nPress Release\nJoint statement: five-point plan for an inclusive WSIS+20 review\n\n\n↗\n29 Mar 2025\n\nJoint statement: five-point plan for an inclusive WSIS+20 review\n\n\n\n\n\n\n\n\n\n\t\t\t\t\tConnectivity\t\t\t\t\n\n\n\n\nConnectivity \n\n\n\t\t\t\tOral statement at 10th Session of the UN Open Ended Working Group on ICTs\t\t\t\n\n21 Feb 2025\n • \nAccess Now’s oral statement at the 10th Session of the UN Open Ended Working Group on information and communication technology.\n\n\n\n\nPublication\nOral statement at 10th Session of the UN Open Ended Working Group on ICTs\n\n\n↗\n21 Feb 2025\n\nOral statement at 10th Session of the UN Open Ended Working Group on ICTs\n\n\n\n\n\n\n\n\n\n\t\t\t\t\tConnectivity\t\t\t\t\n\n\n\n\nConnectivity \n\n\n\t\t\t\tHolding space for human rights: improving the governance of satellite internet connectivity\t\t\t\n\n5 Feb 2025\n • \nFrom obstructed humanitarian access to the weaponization of personal digital devices, internet connectivity is an issue that carries multiple layers of harms\n— one that we are only just starting to unpack.\n\n\n\n\nPublication\nHolding space for human rights: improving the governance of satellite internet connectivity\n\n\n↗\n5 Feb 2025\n\nHolding space for human rights: improving the governance of satellite internet connectivity\n\n\n\n\n\n\n\n\n\n\t\t\t\t\tFreedom of Expression\t\t\t\t\n\n\n\n\nFreedom of Expression \n\n\n\t\t\t\tCeasefire in Gaza: it’s time to end digital harms and deliver justice\t\t\t\n\n20 Jan 2025\n • \nAs physical violence appears to be coming to a halt after 15 months in Gaza, Access Now further calls for a digital ceasefire.\n\n\n\n\nPress Release\nCeasefire in Gaza: it’s time to end digital harms and deliver justice\n20 Jan 2025\n\nCeasefire in Gaza: it’s time to end digital harms and deliver justice\n\n\n\n\n\n\n\n\n\n\t\t\t\t\tFreedom of Expression\t\t\t\t\n\n\n\n\nFreedom of Expression \n\n\n\t\t\t\tTackling the “black snakes” undermining digital rights worldwide \t\t\t\n\n16 Jan 2025\n • \nAs 2025 gets underway, Access Now’s new Executive Director, Alejandro Mayoral Baños, PhD, shares his reflections on the “black snakes” threatening the digital rights movement. \n\n\n\n\nPost\nTackling the “black snakes” undermining digital rights worldwide \n16 Jan 2025\n\nTackling the “black snakes” undermining digital rights worldwide \n\n\n\n\n\n\n\n\n\n\t\t\t\t\tInternet Shutdowns\t\t\t\t\n\n\n\n\nInternet Shutdowns \n\n\n\t\t\t\t#KeepItOn in Tanzania: authorities must ensure connectivity during local elections\t\t\t\n\n21 Nov 2024\n • \nThe #KeepItOn coalition demands that the Government of Tanzania ensure unhindered access to the internet during the upcoming elections.\n\n\n\n\nPress Release\n#KeepItOn in Tanzania: authorities must ensure connectivity during local elections\n21 Nov 2024\n\n#KeepItOn in Tanzania: authorities must ensure connectivity during local elections\n\n\n\n\n\n\n\n\n\n\t\t\t\t\tInternet Shutdowns\t\t\t\t\n\n\n\n\nInternet Shutdowns \n\n\n\t\t\t\t#KeepItOn: the Government of Tanzania and internet service providers must ensure open and secure internet access throughout the 2024 local elections\t\t\t\n\n21 Nov 2024\n • \nThe #KeepItOn coalition calls on authorities and ISPs in Tanzania to ensure internet access during the upcoming elections. \n\n\n\n\nPress Release\n#KeepItOn: the Government of Tanzania and internet service providers must ensure open and secure internet access throughout the 2024 local elections\n21 Nov 2024\n\n#KeepItOn: the Government of Tanzania and internet service providers must ensure open and secure internet access throughout the 2024 local elections\n\n\n\n\n\n\n\n\n\n\t\t\t\t\tConnectivity\t\t\t\t\n\n\n\n\nConnectivity \n\n\n\t\t\t\tAs Israel destroys infrastructure, will Lebanon be cut off from outside world?\t\t\t\n\n15 Nov 2024\n\n\n\n\nNews\nAs Israel destroys infrastructure, will Lebanon be cut off from outside world?\n\n\t\t\t\t\t\t\t\t\tThe New Arab ↗\t\t\t\t\t\t\t\n↗\n15 Nov 2024\n\nAs Israel destroys infrastructure, will Lebanon be cut off from outside world?\n\n\n\n\n\n\n\n\n\n\t\t\t\t\tConnectivity\t\t\t\t\n\n\n\n\nConnectivity \n\n\n\t\t\t\tApple keeps killing VPN apps upon Russia’s orders – Amnezia VPN is the last victim\t\t\t\n\n4 Nov 2024\n\n\n\n\nNews\nApple keeps killing VPN apps upon Russia’s orders – Amnezia VPN is the last victim\n\n\t\t\t\t\t\t\t\t\tTechRadar ↗\t\t\t\t\t\t\t\n↗\n4 Nov 2024\n\nApple keeps killing VPN apps upon Russia’s orders – Amnezia VPN is the last victim\n\n\n\n\n\n\n\n\n\n\t\t\t\t\tInternet Shutdowns\t\t\t\t\n\n\n\n\nInternet Shutdowns \n\n\n\t\t\t\t#KeepItOn Mauritius: global coalition urges first-time offender to end crackdown on social media\t\t\t\n\n1 Nov 2024\n\n\n\n\nPress Release\n#KeepItOn Mauritius: global coalition urges first-time offender to end crackdown on social media\n1 Nov 2024\n\n#KeepItOn Mauritius: global coalition urges first-time offender to end crackdown on social media\n\n\n\n\n\n\n\n\n\n\t\t\t\t\tConnectivity\t\t\t\t\n\n\n\n\nConnectivity \n\n\n\t\t\t\tMyanmar residents struggle to overcome severe internet blackouts with Starlink\t\t\t\n\n23 Oct 2024\n\n\n\n\nNews\nMyanmar residents struggle to overcome severe internet blackouts with Starlink\n\n\t\t\t\t\t\t\t\t\tRest of World ↗\t\t\t\t\t\t\t\n↗\n23 Oct 2024\n\nMyanmar residents struggle to overcome severe internet blackouts with Starlink\n\n\n\n\n\n\n\n\n\n\t\t\t\t\tConnectivity\t\t\t\t\n\n\n\n\nConnectivity \n\n\n\t\t\t\tستارلينك في اليمن: لماذا يعارض الحوثيون تفعيل الإنترنت الفضائي؟\t\t\t\n\n1 Oct 2024\n\n\n\n\nNews\nستارلينك في اليمن: لماذا يعارض الحوثيون تفعيل الإنترنت الفضائي؟\n\n\t\t\t\t\t\t\t\t\tBBC ↗\t\t\t\t\t\t\t\n↗\n1 Oct 2024\n\nستارلينك في اليمن: لماذا يعارض الحوثيون تفعيل الإنترنت الفضائي؟\n\n\n\n\n\n\n\n\n\n\t\t\t\t\tInternet Shutdowns\t\t\t\t\n\n\n\n\nInternet Shutdowns \n\n\n\t\t\t\tJoint statement: Sudan has suffered in silence for over 500 days\t\t\t\n\n5 Sep 2024\n • \nAfter more than 500 days of brutal conflict in Sudan, the #KeepItOn coalition reiterates calls to reactivate telecommunication services.\n\n\n\n\nPress Release\nJoint statement: Sudan has suffered in silence for over 500 days\n5 Sep 2024\n\nJoint statement: Sudan has suffered in silence for over 500 days\n\n\n\n\n\n\n\n\n\n\t\t\t\t\tInternet Shutdowns\t\t\t\t\n\n\n\n\nInternet Shutdowns \n\n\n\t\t\t\tAfrica in 2023: internet shutdowns attack democracy\t\t\t\n\n26 Aug 2024\n\n\n\n\nPress Release\nAfrica in 2023: internet shutdowns attack democracy\n26 Aug 2024\n\nAfrica in 2023: internet shutdowns attack democracy\n\n\n\n\n\n\n\n\n\n\t\t\t\t\tInternet Shutdowns\t\t\t\t\n\n\n\n\nInternet Shutdowns \n\n\n\t\t\t\t#KeepItOn in Annobón: Authorities in Equatorial Guinea must end internet shutdown and other human rights abuses\t\t\t\n\n13 Aug 2024\n • \nAccess Now and the #KeepItOn coalition are calling on authorities in Equatorial Guinea to immediately restore internet and telecom services in Annobón.\n\n\n\n\nPress Release\n#KeepItOn in Annobón: Authorities in Equatorial Guinea must end internet shutdown and other human rights abuses\n13 Aug 2024\n\n#KeepItOn in Annobón: Authorities in Equatorial Guinea must end internet shutdown and other human rights abuses\n\n\n\n\n\n\n\n\n\n\t\t\t\t\tInternet Shutdowns\t\t\t\t\n\n\n\n\nInternet Shutdowns \n\n\n\t\t\t\t#KeepItOn en Annobón: Las autoridades de Guinea Ecuatorial deben poner fin al corte de internet y otros abusos a los derechos humanos\t\t\t\n\n13 Aug 2024\n • \nLa coalición #KeepItOn instan a las autoridades de Guinea Ecuatorial a restablecer de inmediato el acceso a internet en Annobón.\n\n\n\n\nPress Release\n#KeepItOn en Annobón: Las autoridades de Guinea Ecuatorial deben poner fin al corte de internet y otros abusos a los derechos humanos\n13 Aug 2024\n\n#KeepItOn en Annobón: Las autoridades de Guinea Ecuatorial deben poner fin al corte de internet y otros abusos a los derechos humanos\n\nEquitable Internet Access For All\n\n\n\nToday, affordable and meaningful access to the internet is an essential enabler of human rights. We advocate for policies and technologies to support equitable access to a free, open, and secure internet, and capacity-building to enable marginalized people and communities to make the most of it.\n\n\n\n\n\n\n\n\n\n\n\n\n\nMore than 3.5 billion left in the dark: why we’re still fighting to reach U.N. targets for internet access\nImagine the world coming together to envision, plan, and commit to creating a better future — for everyone, everywhere. \n\nLearn more\n\n\n\n\n\n\nResources\n\n\n\n\n\n\n\n\n\n\n\n\n\n\n\n\t\t\t\n\t\t\t\tExpanding connectivity to fight COVID-19: recommendations for governments and telcos \n\t\t\t\t\t\t\t\n\n\n\n\n\n\n\n\n\n\n\n\n\nFreedom of Expression\n\n\n\t\t\t\n\t\t\t\tTunisia: Access to online conferencing platforms and networks is a constitutional right\n\t\t\t\t\t\t\t\n\n\nAccess Now joins civil society organizations in calling for safe and open access to online conferencing platforms in Tunisia.\n\n\n\n\n\n\n\n\n\n\n\n\n\nFreedom of Expression\n\n\n\t\t\t\n\t\t\t\tVictory! U.S. Senate passes infrastructure bill, critical to get people online\n\t\t\t\t\t\t\t\n\n\nAccess Now applauds the U.S. Senate for passing an infrastructure bill that would help get people online.\n\n\n\n\n\n\n\n\n\n\n\n\n\nFreedom of Expression\n\n\n\t\t\t\n\t\t\t\tWhat the tech sector can do to respect human rights in Ukraine, Russia, Belarus, and beyond\n\t\t\t\t\t\t\t\n\n\nAs the Russia-Ukraine crisis escalates to war, the tech sector must do more than merely comply with sanctions. Here are our recommendations for mitigating human rights harms. \n\n\n\n\n\n\n\n\n\n\n\nLatest Updates\n\n\n\n     \n\n\n\n\n\nGrid View\nList View\n\n\n\n\n\n\n\n\n\n\n\n\n\n\t\t\t\t\tConnectivity\t\t\t\t\n\n\n\n\nConnectivity \n\n\n\t\t\t\tJoint statement: five-point plan for an inclusive WSIS+20 review\t\t\t\n\n29 Mar 2025\n\n\n\n\nPress Release\nJoint statement: five-point plan for an inclusive WSIS+20 review\n\n\n↗\n29 Mar 2025\n\nJoint statement: five-point plan for an inclusive WSIS+20 review\n\n\n\n\n\n\n\n\n\n\t\t\t\t\tConnectivity\t\t\t\t\n\n\n\n\nConnectivity \n\n\n\t\t\t\tOral statement at 10th Session of the UN Open Ended Working Group on ICTs\t\t\t\n\n21 Feb 2025\n • \nAccess Now’s oral statement at the 10th Session of the UN Open Ended Working Group on information and communication technology.\n\n\n\n\nPublication\nOral statement at 10th Session of the UN Open Ended Working Group on ICTs\n\n\n↗\n21 Feb 2025\n\nOral statement at 10th Session of the UN Open Ended Working Group on ICTs\n\n\n\n\n\n\n\n\n\n\t\t\t\t\tConnectivity\t\t\t\t\n\n\n\n\nConnectivity \n\n\n\t\t\t\tHolding space for human rights: improving the governance of satellite internet connectivity\t\t\t\n\n5 Feb 2025\n • \nFrom obstructed humanitarian access to the weaponization of personal digital devices, internet connectivity is an issue that carries multiple layers of harms\n— one that we are only just starting to unpack.\n\n\n\n\nPublication\nHolding space for human rights: improving the governance of satellite internet connectivity\n\n\n↗\n5 Feb 2025\n\nHolding space for human rights: improving the governance of satellite internet connectivity\n\n\n\n\n\n\n\n\n\n\t\t\t\t\tFreedom of Expression\t\t\t\t\n\n\n\n\nFreedom of Expression \n\n\n\t\t\t\tCeasefire in Gaza: it’s time to end digital harms and deliver justice\t\t\t\n\n20 Jan 2025\n • \nAs physical violence appears to be coming to a halt after 15 months in Gaza, Access Now further calls for a digital ceasefire.\n\n\n\n\nPress Release\nCeasefire in Gaza: it’s time to end digital harms and deliver justice\n20 Jan 2025\n\nCeasefire in Gaza: it’s time to end digital harms and deliver justice\n\n\n\n\n\n\n\n\n\n\t\t\t\t\tFreedom of Expression\t\t\t\t\n\n\n\n\nFreedom of Expression \n\n\n\t\t\t\tTackling the “black snakes” undermining digital rights worldwide \t\t\t\n\n16 Jan 2025\n • \nAs 2025 gets underway, Access Now’s new Executive Director, Alejandro Mayoral Baños, PhD, shares his reflections on the “black snakes” threatening the digital rights movement. \n\n\n\n\nPost\nTackling the “black snakes” undermining digital rights worldwide \n16 Jan 2025\n\nTackling the “black snakes” undermining digital rights worldwide \n\n\n\n\n\n\n\n\n\n\t\t\t\t\tInternet Shutdowns\t\t\t\t\n\n\n\n\nInternet Shutdowns \n\n\n\t\t\t\t#KeepItOn in Tanzania: authorities must ensure connectivity during local elections\t\t\t\n\n21 Nov 2024\n • \nThe #KeepItOn coalition demands that the Government of Tanzania ensure unhindered access to the internet during the upcoming elections.\n\n\n\n\nPress Release\n#KeepItOn in Tanzania: authorities must ensure connectivity during local elections\n21 Nov 2024\n\n#KeepItOn in Tanzania: authorities must ensure connectivity during local elections\n\n\n\n\n\n\n\n\n\n\t\t\t\t\tInternet Shutdowns\t\t\t\t\n\n\n\n\nInternet Shutdowns \n\n\n\t\t\t\t#KeepItOn: the Government of Tanzania and internet service providers must ensure open and secure internet access throughout the 2024 local elections\t\t\t\n\n21 Nov 2024\n • \nThe #KeepItOn coalition calls on authorities and ISPs in Tanzania to ensure internet access during the upcoming elections. \n\n\n\n\nPress Release\n#KeepItOn: the Government of Tanzania and internet service providers must ensure open and secure internet access throughout the 2024 local elections\n21 Nov 2024\n\n#KeepItOn: the Government of Tanzania and internet service providers must ensure open and secure internet access throughout the 2024 local elections\n\n\n\n\n\n\n\n\n\n\t\t\t\t\tConnectivity\t\t\t\t\n\n\n\n\nConnectivity \n\n\n\t\t\t\tAs Israel destroys infrastructure, will Lebanon be cut off from outside world?\t\t\t\n\n15 Nov 2024\n\n\n\n\nNews\nAs Israel destroys infrastructure, will Lebanon be cut off from outside world?\n\n\t\t\t\t\t\t\t\t\tThe New Arab ↗\t\t\t\t\t\t\t\n↗\n15 Nov 2024\n\nAs Israel destroys infrastructure, will Lebanon be cut off from outside world?\n\n\n\n\n\n\n\n\n\n\t\t\t\t\tConnectivity\t\t\t\t\n\n\n\n\nConnectivity \n\n\n\t\t\t\tApple keeps killing VPN apps upon Russia’s orders – Amnezia VPN is the last victim\t\t\t\n\n4 Nov 2024\n\n\n\n\nNews\nApple keeps killing VPN apps upon Russia’s orders – Amnezia VPN is the last victim\n\n\t\t\t\t\t\t\t\t\tTechRadar ↗\t\t\t\t\t\t\t\n↗\n4 Nov 2024\n\nApple keeps killing VPN apps upon Russia’s orders – Amnezia VPN is the last victim\n\n\n\n\n\n\n\n\n\n\t\t\t\t\tInternet Shutdowns\t\t\t\t\n\n\n\n\nInternet Shutdowns \n\n\n\t\t\t\t#KeepItOn Mauritius: global coalition urges first-time offender to end crackdown on social media\t\t\t\n\n1 Nov 2024\n\n\n\n\nPress Release\n#KeepItOn Mauritius: global coalition urges first-time offender to end crackdown on social media\n1 Nov 2024\n\n#KeepItOn Mauritius: global coalition urges first-time offender to end crackdown on social media\n\n\n\n\n\n\n\n\n\n\t\t\t\t\tConnectivity\t\t\t\t\n\n\n\n\nConnectivity \n\n\n\t\t\t\tMyanmar residents struggle to overcome severe internet blackouts with Starlink\t\t\t\n\n23 Oct 2024\n\n\n\n\nNews\nMyanmar residents struggle to overcome severe internet blackouts with Starlink\n\n\t\t\t\t\t\t\t\t\tRest of World ↗\t\t\t\t\t\t\t\n↗\n23 Oct 2024\n\nMyanmar residents struggle to overcome severe internet blackouts with Starlink\n\n\n\n\n\n\n\n\n\n\t\t\t\t\tConnectivity\t\t\t\t\n\n\n\n\nConnectivity \n\n\n\t\t\t\tستارلينك في اليمن: لماذا يعارض الحوثيون تفعيل الإنترنت الفضائي؟\t\t\t\n\n1 Oct 2024\n\n\n\n\nNews\nستارلينك في اليمن: لماذا يعارض الحوثيون تفعيل الإنترنت الفضائي؟\n\n\t\t\t\t\t\t\t\t\tBBC ↗\t\t\t\t\t\t\t\n↗\n1 Oct 2024\n\nستارلينك في اليمن: لماذا يعارض الحوثيون تفعيل الإنترنت الفضائي؟\n\n\n\n\n\n\n\n\n\n\t\t\t\t\tInternet Shutdowns\t\t\t\t\n\n\n\n\nInternet Shutdowns \n\n\n\t\t\t\tJoint statement: Sudan has suffered in silence for over 500 days\t\t\t\n\n5 Sep 2024\n • \nAfter more than 500 days of brutal conflict in Sudan, the #KeepItOn coalition reiterates calls to reactivate telecommunication services.\n\n\n\n\nPress Release\nJoint statement: Sudan has suffered in silence for over 500 days\n5 Sep 2024\n\nJoint statement: Sudan has suffered in silence for over 500 days\n\n\n\n\n\n\n\n\n\n\t\t\t\t\tInternet Shutdowns\t\t\t\t\n\n\n\n\nInternet Shutdowns \n\n\n\t\t\t\tAfrica in 2023: internet shutdowns attack democracy\t\t\t\n\n26 Aug 2024\n\n\n\n\nPress Release\nAfrica in 2023: internet shutdowns attack democracy\n26 Aug 2024\n\nAfrica in 2023: internet shutdowns attack democracy\n\n\n\n\n\n\n\n\n\n\t\t\t\t\tInternet Shutdowns\t\t\t\t\n\n\n\n\nInternet Shutdowns \n\n\n\t\t\t\t#KeepItOn in Annobón: Authorities in Equatorial Guinea must end internet shutdown and other human rights abuses\t\t\t\n\n13 Aug 2024\n • \nAccess Now and the #KeepItOn coalition are calling on authorities in Equatorial Guinea to immediately restore internet and telecom services in Annobón.\n\n\n\n\nPress Release\n#KeepItOn in Annobón: Authorities in Equatorial Guinea must end internet shutdown and other human rights abuses\n13 Aug 2024\n\n#KeepItOn in Annobón: Authorities in Equatorial Guinea must end internet shutdown and other human rights abuses\n\n\n\n\n\n\n\n\n\n\t\t\t\t\tInternet Shutdowns\t\t\t\t\n\n\n\n\nInternet Shutdowns \n\n\n\t\t\t\t#KeepItOn en Annobón: Las autoridades de Guinea Ecuatorial deben poner fin al corte de internet y otros abusos a los derechos humanos\t\t\t\n\n13 Aug 2024\n • \nLa coalición #KeepItOn instan a las autoridades de Guinea Ecuatorial a restablecer de inmediato el acceso a internet en Annobón.\n\n\n\n\nPress Release\n#KeepItOn en Annobón: Las autoridades de Guinea Ecuatorial deben poner fin al corte de internet y otros abusos a los derechos humanos\n13 Aug 2024\n\n#KeepItOn en Annobón: Las autoridades de Guinea Ecuatorial deben poner fin al corte de internet y otros abusos a los derechos humanos\n\nEquitable Internet Access For All\n\n\n\nToday, affordable and meaningful access to the internet is an essential enabler of human rights. We advocate for policies and technologies to support equitable access to a free, open, and secure internet, and capacity-building to enable marginalized people and communities to make the most of it.\n\n\n\n\n\n\n\n\n\n\n\n\n\nMore than 3.5 billion left in the dark: why we’re still fighting to reach U.N. targets for internet access\nImagine the world coming together to envision, plan, and commit to creating a better future — for everyone, everywhere. \n\nLearn more\n\n\n\n\n\n\nResources\n\n\n\n\n\n\n\n\n\n\n\n\n\n\n\n\t\t\t\n\t\t\t\tExpanding connectivity to fight COVID-19: recommendations for governments and telcos \n\t\t\t\t\t\t\t\n\n\n\n\n\n\n\n\n\n\n\n\n\nFreedom of Expression\n\n\n\t\t\t\n\t\t\t\tTunisia: Access to online conferencing platforms and networks is a constitutional right\n\t\t\t\t\t\t\t\n\n\nAccess Now joins civil society organizations in calling for safe and open access to online conferencing platforms in Tunisia.\n\n\n\n\n\n\n\n\n\n\n\n\n\nFreedom of Expression\n\n\n\t\t\t\n\t\t\t\tVictory! U.S. Senate passes infrastructure bill, critical to get people online\n\t\t\t\t\t\t\t\n\n\nAccess Now applauds the U.S. Senate for passing an infrastructure bill that would help get people online.\n\n\n\n\n\n\n\n\n\n\n\n\n\nFreedom of Expression\n\n\n\t\t\t\n\t\t\t\tWhat the tech sector can do to respect human rights in Ukraine, Russia, Belarus, and beyond\n\t\t\t\t\t\t\t\n\n\nAs the Russia-Ukraine crisis escalates to war, the tech sector must do more than merely comply with sanctions. Here are our recommendations for mitigating human rights harms. \n\n\n\n\n\n\n\n\n\n\n\nLatest Updates\n\n\n\n     \n\n\n\n\n\nGrid View\nList View\n\n\n\n\n\n\n\n\n\n\n\n\n\n\t\t\t\t\tConnectivity\t\t\t\t\n\n\n\n\nConnectivity \n\n\n\t\t\t\tJoint statement: five-point plan for an inclusive WSIS+20 review\t\t\t\n\n29 Mar 2025\n\n\n\n\nPress Release\nJoint statement: five-point plan for an inclusive WSIS+20 review\n\n\n↗\n29 Mar 2025\n\nJoint statement: five-point plan for an inclusive WSIS+20 review\n\n\n\n\n\n\n\n\n\n\t\t\t\t\tConnectivity\t\t\t\t\n\n\n\n\nConnectivity \n\n\n\t\t\t\tOral statement at 10th Session of the UN Open Ended Working Group on ICTs\t\t\t\n\n21 Feb 2025\n • \nAccess Now’s oral statement at the 10th Session of the UN Open Ended Working Group on information and communication technology.\n\n\n\n\nPublication\nOral statement at 10th Session of the UN Open Ended Working Group on ICTs\n\n\n↗\n21 Feb 2025\n\nOral statement at 10th Session of the UN Open Ended Working Group on ICTs\n\n\n\n\n\n\n\n\n\n\t\t\t\t\tConnectivity\t\t\t\t\n\n\n\n\nConnectivity \n\n\n\t\t\t\tHolding space for human rights: improving the governance of satellite internet connectivity\t\t\t\n\n5 Feb 2025\n • \nFrom obstructed humanitarian access to the weaponization of personal digital devices, internet connectivity is an issue that carries multiple layers of harms\n— one that we are only just starting to unpack.\n\n\n\n\nPublication\nHolding space for human rights: improving the governance of satellite internet connectivity\n\n\n↗\n5 Feb 2025\n\nHolding space for human rights: improving the governance of satellite internet connectivity\n\n\n\n\n\n\n\n\n\n\t\t\t\t\tFreedom of Expression\t\t\t\t\n\n\n\n\nFreedom of Expression \n\n\n\t\t\t\tCeasefire in Gaza: it’s time to end digital harms and deliver justice\t\t\t\n\n20 Jan 2025\n • \nAs physical violence appears to be coming to a halt after 15 months in Gaza, Access Now further calls for a digital ceasefire.\n\n\n\n\nPress Release\nCeasefire in Gaza: it’s time to end digital harms and deliver justice\n20 Jan 2025\n\nCeasefire in Gaza: it’s time to end digital harms and deliver justice\n\n\n\n\n\n\n\n\n\n\t\t\t\t\tFreedom of Expression\t\t\t\t\n\n\n\n\nFreedom of Expression \n\n\n\t\t\t\tTackling the “black snakes” undermining digital rights worldwide \t\t\t\n\n16 Jan 2025\n • \nAs 2025 gets underway, Access Now’s new Executive Director, Alejandro Mayoral Baños, PhD, shares his reflections on the “black snakes” threatening the digital rights movement. \n\n\n\n\nPost\nTackling the “black snakes” undermining digital rights worldwide \n16 Jan 2025\n\nTackling the “black snakes” undermining digital rights worldwide \n\n\n\n\n\n\n\n\n\n\t\t\t\t\tInternet Shutdowns\t\t\t\t\n\n\n\n\nInternet Shutdowns \n\n\n\t\t\t\t#KeepItOn in Tanzania: authorities must ensure connectivity during local elections\t\t\t\n\n21 Nov 2024\n • \nThe #KeepItOn coalition demands that the Government of Tanzania ensure unhindered access to the internet during the upcoming elections.\n\n\n\n\nPress Release\n#KeepItOn in Tanzania: authorities must ensure connectivity during local elections\n21 Nov 2024\n\n#KeepItOn in Tanzania: authorities must ensure connectivity during local elections\n\n\n\n\n\n\n\n\n\n\t\t\t\t\tInternet Shutdowns\t\t\t\t\n\n\n\n\nInternet Shutdowns \n\n\n\t\t\t\t#KeepItOn: the Government of Tanzania and internet service providers must ensure open and secure internet access throughout the 2024 local elections\t\t\t\n\n21 Nov 2024\n • \nThe #KeepItOn coalition calls on authorities and ISPs in Tanzania to ensure internet access during the upcoming elections. \n\n\n\n\nPress Release\n#KeepItOn: the Government of Tanzania and internet service providers must ensure open and secure internet access throughout the 2024 local elections\n21 Nov 2024\n\n#KeepItOn: the Government of Tanzania and internet service providers must ensure open and secure internet access throughout the 2024 local elections\n\n\n\n\n\n\n\n\n\n\t\t\t\t\tConnectivity\t\t\t\t\n\n\n\n\nConnectivity \n\n\n\t\t\t\tAs Israel destroys infrastructure, will Lebanon be cut off from outside world?\t\t\t\n\n15 Nov 2024\n\n\n\n\nNews\nAs Israel destroys infrastructure, will Lebanon be cut off from outside world?\n\n\t\t\t\t\t\t\t\t\tThe New Arab ↗\t\t\t\t\t\t\t\n↗\n15 Nov 2024\n\nAs Israel destroys infrastructure, will Lebanon be cut off from outside world?\n\n\n\n\n\n\n\n\n\n\t\t\t\t\tConnectivity\t\t\t\t\n\n\n\n\nConnectivity \n\n\n\t\t\t\tApple keeps killing VPN apps upon Russia’s orders – Amnezia VPN is the last victim\t\t\t\n\n4 Nov 2024\n\n\n\n\nNews\nApple keeps killing VPN apps upon Russia’s orders – Amnezia VPN is the last victim\n\n\t\t\t\t\t\t\t\t\tTechRadar ↗\t\t\t\t\t\t\t\n↗\n4 Nov 2024\n\nApple keeps killing VPN apps upon Russia’s orders – Amnezia VPN is the last victim\n\n\n\n\n\n\n\n\n\n\t\t\t\t\tInternet Shutdowns\t\t\t\t\n\n\n\n\nInternet Shutdowns \n\n\n\t\t\t\t#KeepItOn Mauritius: global coalition urges first-time offender to end crackdown on social media\t\t\t\n\n1 Nov 2024\n\n\n\n\nPress Release\n#KeepItOn Mauritius: global coalition urges first-time offender to end crackdown on social media\n1 Nov 2024\n\n#KeepItOn Mauritius: global coalition urges first-time offender to end crackdown on social media\n\n\n\n\n\n\n\n\n\n\t\t\t\t\tConnectivity\t\t\t\t\n\n\n\n\nConnectivity \n\n\n\t\t\t\tMyanmar residents struggle to overcome severe internet blackouts with Starlink\t\t\t\n\n23 Oct 2024\n\n\n\n\nNews\nMyanmar residents struggle to overcome severe internet blackouts with Starlink\n\n\t\t\t\t\t\t\t\t\tRest of World ↗\t\t\t\t\t\t\t\n↗\n23 Oct 2024\n\nMyanmar residents struggle to overcome severe internet blackouts with Starlink\n\n\n\n\n\n\n\n\n\n\t\t\t\t\tConnectivity\t\t\t\t\n\n\n\n\nConnectivity \n\n\n\t\t\t\tستارلينك في اليمن: لماذا يعارض الحوثيون تفعيل الإنترنت الفضائي؟\t\t\t\n\n1 Oct 2024\n\n\n\n\nNews\nستارلينك في اليمن: لماذا يعارض الحوثيون تفعيل الإنترنت الفضائي؟\n\n\t\t\t\t\t\t\t\t\tBBC ↗\t\t\t\t\t\t\t\n↗\n1 Oct 2024\n\nستارلينك في اليمن: لماذا يعارض الحوثيون تفعيل الإنترنت الفضائي؟\n\n\n\n\n\n\n\n\n\n\t\t\t\t\tInternet Shutdowns\t\t\t\t\n\n\n\n\nInternet Shutdowns \n\n\n\t\t\t\tJoint statement: Sudan has suffered in silence for over 500 days\t\t\t\n\n5 Sep 2024\n • \nAfter more than 500 days of brutal conflict in Sudan, the #KeepItOn coalition reiterates calls to reactivate telecommunication services.\n\n\n\n\nPress Release\nJoint statement: Sudan has suffered in silence for over 500 days\n5 Sep 2024\n\nJoint statement: Sudan has suffered in silence for over 500 days\n\n\n\n\n\n\n\n\n\n\t\t\t\t\tInternet Shutdowns\t\t\t\t\n\n\n\n\nInternet Shutdowns \n\n\n\t\t\t\tAfrica in 2023: internet shutdowns attack democracy\t\t\t\n\n26 Aug 2024\n\n\n\n\nPress Release\nAfrica in 2023: internet shutdowns attack democracy\n26 Aug 2024\n\nAfrica in 2023: internet shutdowns attack democracy\n\n\n\n\n\n\n\n\n\n\t\t\t\t\tInternet Shutdowns\t\t\t\t\n\n\n\n\nInternet Shutdowns \n\n\n\t\t\t\t#KeepItOn in Annobón: Authorities in Equatorial Guinea must end internet shutdown and other human rights abuses\t\t\t\n\n13 Aug 2024\n • \nAccess Now and the #KeepItOn coalition are calling on authorities in Equatorial Guinea to immediately restore internet and telecom services in Annobón.\n\n\n\n\nPress Release\n#KeepItOn in Annobón: Authorities in Equatorial Guinea must end internet shutdown and other human rights abuses\n13 Aug 2024\n\n#KeepItOn in Annobón: Authorities in Equatorial Guinea must end internet shutdown and other human rights abuses\n\n\n\n\n\n\n\n\n\n\t\t\t\t\tInternet Shutdowns\t\t\t\t\n\n\n\n\nInternet Shutdowns \n\n\n\t\t\t\t#KeepItOn en Annobón: Las autoridades de Guinea Ecuatorial deben poner fin al corte de internet y otros abusos a los derechos humanos\t\t\t\n\n13 Aug 2024\n • \nLa coalición #KeepItOn instan a las autoridades de Guinea Ecuatorial a restablecer de inmediato el acceso a internet en Annobón.\n\n\n\n\nPress Release\n#KeepItOn en Annobón: Las autoridades de Guinea Ecuatorial deben poner fin al corte de internet y otros abusos a los derechos humanos\n13 Aug 2024\n\n#KeepItOn en Annobón: Las autoridades de Guinea Ecuatorial deben poner fin al corte de internet y otros abusos a los derechos humanos\n\nEquitable Internet Access For All\n\n\n\nToday, affordable and meaningful access to the internet is an essential enabler of human rights. We advocate for policies and technologies to support equitable access to a free, open, and secure internet, and capacity-building to enable marginalized people and communities to make the most of it.\n\n\n\n\n\n\n\n\n\n\n\n\n\nMore than 3.5 billion left in the dark: why we’re still fighting to reach U.N. targets for internet access\nImagine the world coming together to envision, plan, and commit to creating a better future — for everyone, everywhere. \n\nLearn more\n\n\n\n\n\n\nResources\n\n\n\n\n\n\n\n\n\n\n\n\n\n\n\n\t\t\t\n\t\t\t\tExpanding connectivity to fight COVID-19: recommendations for governments and telcos \n\t\t\t\t\t\t\t\n\n\n\n\n\n\n\n\n\n\n\n\n\nFreedom of Expression\n\n\n\t\t\t\n\t\t\t\tTunisia: Access to online conferencing platforms and networks is a constitutional right\n\t\t\t\t\t\t\t\n\n\nAccess Now joins civil society organizations in calling for safe and open access to online conferencing platforms in Tunisia.\n\n\n\n\n\n\n\n\n\n\n\n\n\nFreedom of Expression\n\n\n\t\t\t\n\t\t\t\tVictory! U.S. Senate passes infrastructure bill, critical to get people online\n\t\t\t\t\t\t\t\n\n\nAccess Now applauds the U.S. Senate for passing an infrastructure bill that would help get people online.\n\n\n\n\n\n\n\n\n\n\n\n\n\nFreedom of Expression\n\n\n\t\t\t\n\t\t\t\tWhat the tech sector can do to respect human rights in Ukraine, Russia, Belarus, and beyond\n\t\t\t\t\t\t\t\n\n\nAs the Russia-Ukraine crisis escalates to war, the tech sector must do more than merely comply with sanctions. Here are our recommendations for mitigating human rights harms. \n\n\n\n\n\n\n\n\n\n\n\nLatest Updates\n\n\n\n     \n\n\n\n\n\nGrid View\nList View\n\n\n\n\n\n\n\n\n\n\n\n\n\n\t\t\t\t\tConnectivity\t\t\t\t\n\n\n\n\nConnectivity \n\n\n\t\t\t\tJoint statement: five-point plan for an inclusive WSIS+20 review\t\t\t\n\n29 Mar 2025\n\n\n\n\nPress Release\nJoint statement: five-point plan for an inclusive WSIS+20 review\n\n\n↗\n29 Mar 2025\n\nJoint statement: five-point plan for an inclusive WSIS+20 review\n\n\n\n\n\n\n\n\n\n\t\t\t\t\tConnectivity\t\t\t\t\n\n\n\n\nConnectivity \n\n\n\t\t\t\tOral statement at 10th Session of the UN Open Ended Working Group on ICTs\t\t\t\n\n21 Feb 2025\n • \nAccess Now’s oral statement at the 10th Session of the UN Open Ended Working Group on information and communication technology.\n\n\n\n\nPublication\nOral statement at 10th Session of the UN Open Ended Working Group on ICTs\n\n\n↗\n21 Feb 2025\n\nOral statement at 10th Session of the UN Open Ended Working Group on ICTs\n\n\n\n\n\n\n\n\n\n\t\t\t\t\tConnectivity\t\t\t\t\n\n\n\n\nConnectivity \n\n\n\t\t\t\tHolding space for human rights: improving the governance of satellite internet connectivity\t\t\t\n\n5 Feb 2025\n • \nFrom obstructed humanitarian access to the weaponization of personal digital devices, internet connectivity is an issue that carries multiple layers of harms\n— one that we are only just starting to unpack.\n\n\n\n\nPublication\nHolding space for human rights: improving the governance of satellite internet connectivity\n\n\n↗\n5 Feb 2025\n\nHolding space for human rights: improving the governance of satellite internet connectivity\n\n\n\n\n\n\n\n\n\n\t\t\t\t\tFreedom of Expression\t\t\t\t\n\n\n\n\nFreedom of Expression \n\n\n\t\t\t\tCeasefire in Gaza: it’s time to end digital harms and deliver justice\t\t\t\n\n20 Jan 2025\n • \nAs physical violence appears to be coming to a halt after 15 months in Gaza, Access Now further calls for a digital ceasefire.\n\n\n\n\nPress Release\nCeasefire in Gaza: it’s time to end digital harms and deliver justice\n20 Jan 2025\n\nCeasefire in Gaza: it’s time to end digital harms and deliver justice\n\n\n\n\n\n\n\n\n\n\t\t\t\t\tFreedom of Expression\t\t\t\t\n\n\n\n\nFreedom of Expression \n\n\n\t\t\t\tTackling the “black snakes” undermining digital rights worldwide \t\t\t\n\n16 Jan 2025\n • \nAs 2025 gets underway, Access Now’s new Executive Director, Alejandro Mayoral Baños, PhD, shares his reflections on the “black snakes” threatening the digital rights movement. \n\n\n\n\nPost\nTackling the “black snakes” undermining digital rights worldwide \n16 Jan 2025\n\nTackling the “black snakes” undermining digital rights worldwide \n\n\n\n\n\n\n\n\n\n\t\t\t\t\tInternet Shutdowns\t\t\t\t\n\n\n\n\nInternet Shutdowns \n\n\n\t\t\t\t#KeepItOn in Tanzania: authorities must ensure connectivity during local elections\t\t\t\n\n21 Nov 2024\n • \nThe #KeepItOn coalition demands that the Government of Tanzania ensure unhindered access to the internet during the upcoming elections.\n\n\n\n\nPress Release\n#KeepItOn in Tanzania: authorities must ensure connectivity during local elections\n21 Nov 2024\n\n#KeepItOn in Tanzania: authorities must ensure connectivity during local elections\n\n\n\n\n\n\n\n\n\n\t\t\t\t\tInternet Shutdowns\t\t\t\t\n\n\n\n\nInternet Shutdowns \n\n\n\t\t\t\t#KeepItOn: the Government of Tanzania and internet service providers must ensure open and secure internet access throughout the 2024 local elections\t\t\t\n\n21 Nov 2024\n • \nThe #KeepItOn coalition calls on authorities and ISPs in Tanzania to ensure internet access during the upcoming elections. \n\n\n\n\nPress Release\n#KeepItOn: the Government of Tanzania and internet service providers must ensure open and secure internet access throughout the 2024 local elections\n21 Nov 2024\n\n#KeepItOn: the Government of Tanzania and internet service providers must ensure open and secure internet access throughout the 2024 local elections\n\n\n\n\n\n\n\n\n\n\t\t\t\t\tConnectivity\t\t\t\t\n\n\n\n\nConnectivity \n\n\n\t\t\t\tAs Israel destroys infrastructure, will Lebanon be cut off from outside world?\t\t\t\n\n15 Nov 2024\n\n\n\n\nNews\nAs Israel destroys infrastructure, will Lebanon be cut off from outside world?\n\n\t\t\t\t\t\t\t\t\tThe New Arab ↗\t\t\t\t\t\t\t\n↗\n15 Nov 2024\n\nAs Israel destroys infrastructure, will Lebanon be cut off from outside world?\n\n\n\n\n\n\n\n\n\n\t\t\t\t\tConnectivity\t\t\t\t\n\n\n\n\nConnectivity \n\n\n\t\t\t\tApple keeps killing VPN apps upon Russia’s orders – Amnezia VPN is the last victim\t\t\t\n\n4 Nov 2024\n\n\n\n\nNews\nApple keeps killing VPN apps upon Russia’s orders – Amnezia VPN is the last victim\n\n\t\t\t\t\t\t\t\t\tTechRadar ↗\t\t\t\t\t\t\t\n↗\n4 Nov 2024\n\nApple keeps killing VPN apps upon Russia’s orders – Amnezia VPN is the last victim\n\n\n\n\n\n\n\n\n\n\t\t\t\t\tInternet Shutdowns\t\t\t\t\n\n\n\n\nInternet Shutdowns \n\n\n\t\t\t\t#KeepItOn Mauritius: global coalition urges first-time offender to end crackdown on social media\t\t\t\n\n1 Nov 2024\n\n\n\n\nPress Release\n#KeepItOn Mauritius: global coalition urges first-time offender to end crackdown on social media\n1 Nov 2024\n\n#KeepItOn Mauritius: global coalition urges first-time offender to end crackdown on social media\n\n\n\n\n\n\n\n\n\n\t\t\t\t\tConnectivity\t\t\t\t\n\n\n\n\nConnectivity \n\n\n\t\t\t\tMyanmar residents struggle to overcome severe internet blackouts with Starlink\t\t\t\n\n23 Oct 2024\n\n\n\n\nNews\nMyanmar residents struggle to overcome severe internet blackouts with Starlink\n\n\t\t\t\t\t\t\t\t\tRest of World ↗\t\t\t\t\t\t\t\n↗\n23 Oct 2024\n\nMyanmar residents struggle to overcome severe internet blackouts with Starlink\n\n\n\n\n\n\n\n\n\n\t\t\t\t\tConnectivity\t\t\t\t\n\n\n\n\nConnectivity \n\n\n\t\t\t\tستارلينك في اليمن: لماذا يعارض الحوثيون تفعيل الإنترنت الفضائي؟\t\t\t\n\n1 Oct 2024\n\n\n\n\nNews\nستارلينك في اليمن: لماذا يعارض الحوثيون تفعيل الإنترنت الفضائي؟\n\n\t\t\t\t\t\t\t\t\tBBC ↗\t\t\t\t\t\t\t\n↗\n1 Oct 2024\n\nستارلينك في اليمن: لماذا يعارض الحوثيون تفعيل الإنترنت الفضائي؟\n\n\n\n\n\n\n\n\n\n\t\t\t\t\tInternet Shutdowns\t\t\t\t\n\n\n\n\nInternet Shutdowns \n\n\n\t\t\t\tJoint statement: Sudan has suffered in silence for over 500 days\t\t\t\n\n5 Sep 2024\n • \nAfter more than 500 days of brutal conflict in Sudan, the #KeepItOn coalition reiterates calls to reactivate telecommunication services.\n\n\n\n\nPress Release\nJoint statement: Sudan has suffered in silence for over 500 days\n5 Sep 2024\n\nJoint statement: Sudan has suffered in silence for over 500 days\n\n\n\n\n\n\n\n\n\n\t\t\t\t\tInternet Shutdowns\t\t\t\t\n\n\n\n\nInternet Shutdowns \n\n\n\t\t\t\tAfrica in 2023: internet shutdowns attack democracy\t\t\t\n\n26 Aug 2024\n\n\n\n\nPress Release\nAfrica in 2023: internet shutdowns attack democracy\n26 Aug 2024\n\nAfrica in 2023: internet shutdowns attack democracy\n\n\n\n\n\n\n\n\n\n\t\t\t\t\tInternet Shutdowns\t\t\t\t\n\n\n\n\nInternet Shutdowns \n\n\n\t\t\t\t#KeepItOn in Annobón: Authorities in Equatorial Guinea must end internet shutdown and other human rights abuses\t\t\t\n\n13 Aug 2024\n • \nAccess Now and the #KeepItOn coalition are calling on authorities in Equatorial Guinea to immediately restore internet and telecom services in Annobón.\n\n\n\n\nPress Release\n#KeepItOn in Annobón: Authorities in Equatorial Guinea must end internet shutdown and other human rights abuses\n13 Aug 2024\n\n#KeepItOn in Annobón: Authorities in Equatorial Guinea must end internet shutdown and other human rights abuses\n\n\n\n\n\n\n\n\n\n\t\t\t\t\tInternet Shutdowns\t\t\t\t\n\n\n\n\nInternet Shutdowns \n\n\n\t\t\t\t#KeepItOn en Annobón: Las autoridades de Guinea Ecuatorial deben poner fin al corte de internet y otros abusos a los derechos humanos\t\t\t\n\n13 Aug 2024\n • \nLa coalición #KeepItOn instan a las autoridades de Guinea Ecuatorial a restablecer de inmediato el acceso a internet en Annobón.\n\n\n\n\nPress Release\n#KeepItOn en Annobón: Las autoridades de Guinea Ecuatorial deben poner fin al corte de internet y otros abusos a los derechos humanos\n13 Aug 2024\n\n#KeepItOn en Annobón: Las autoridades de Guinea Ecuatorial deben poner fin al corte de internet y otros abusos a los derechos humanos\n\nEquitable Internet Access For All\n\n\n\nToday, affordable and meaningful access to the internet is an essential enabler of human rights. We advocate for policies and technologies to support equitable access to a free, open, and secure internet, and capacity-building to enable marginalized people and communities to make the most of it.\n\n\n\n\n\n\n\n\n\n\n\n\n\nMore than 3.5 billion left in the dark: why we’re still fighting to reach U.N. targets for internet access\nImagine the world coming together to envision, plan, and commit to creating a better future — for everyone, everywhere. \n\nLearn more\n\n\n\n\n\n\nResources\n\n\n\n\n\n\n\n\n\n\n\n\n\n\n\n\t\t\t\n\t\t\t\tExpanding connectivity to fight COVID-19: recommendations for governments and telcos \n\t\t\t\t\t\t\t\n\n\n\n\n\n\n\n\n\n\n\n\n\nFreedom of Expression\n\n\n\t\t\t\n\t\t\t\tTunisia: Access to online conferencing platforms and networks is a constitutional right\n\t\t\t\t\t\t\t\n\n\nAccess Now joins civil society organizations in calling for safe and open access to online conferencing platforms in Tunisia.\n\n\n\n\n\n\n\n\n\n\n\n\n\nFreedom of Expression\n\n\n\t\t\t\n\t\t\t\tVictory! U.S. Senate passes infrastructure bill, critical to get people online\n\t\t\t\t\t\t\t\n\n\nAccess Now applauds the U.S. Senate for passing an infrastructure bill that would help get people online.\n\n\n\n\n\n\n\n\n\n\n\n\n\nFreedom of Expression\n\n\n\t\t\t\n\t\t\t\tWhat the tech sector can do to respect human rights in Ukraine, Russia, Belarus, and beyond\n\t\t\t\t\t\t\t\n\n\nAs the Russia-Ukraine crisis escalates to war, the tech sector must do more than merely comply with sanctions. Here are our recommendations for mitigating human rights harms. \n\n\n\n\n\n\n\n\n\n\n\nLatest Updates\n\n\n\n     \n\n\n\n\n\nGrid View\nList View\n\n\n\n\n\n\n\n\n\n\n\n\n\n\t\t\t\t\tConnectivity\t\t\t\t\n\n\n\n\nConnectivity \n\n\n\t\t\t\tJoint statement: five-point plan for an inclusive WSIS+20 review\t\t\t\n\n29 Mar 2025\n\n\n\n\nPress Release\nJoint statement: five-point plan for an inclusive WSIS+20 review\n\n\n↗\n29 Mar 2025\n\nJoint statement: five-point plan for an inclusive WSIS+20 review\n\n\n\n\n\n\n\n\n\n\t\t\t\t\tConnectivity\t\t\t\t\n\n\n\n\nConnectivity \n\n\n\t\t\t\tOral statement at 10th Session of the UN Open Ended Working Group on ICTs\t\t\t\n\n21 Feb 2025\n • \nAccess Now’s oral statement at the 10th Session of the UN Open Ended Working Group on information and communication technology.\n\n\n\n\nPublication\nOral statement at 10th Session of the UN Open Ended Working Group on ICTs\n\n\n↗\n21 Feb 2025\n\nOral statement at 10th Session of the UN Open Ended Working Group on ICTs\n\n\n\n\n\n\n\n\n\n\t\t\t\t\tConnectivity\t\t\t\t\n\n\n\n\nConnectivity \n\n\n\t\t\t\tHolding space for human rights: improving the governance of satellite internet connectivity\t\t\t\n\n5 Feb 2025\n • \nFrom obstructed humanitarian access to the weaponization of personal digital devices, internet connectivity is an issue that carries multiple layers of harms\n— one that we are only just starting to unpack.\n\n\n\n\nPublication\nHolding space for human rights: improving the governance of satellite internet connectivity\n\n\n↗\n5 Feb 2025\n\nHolding space for human rights: improving the governance of satellite internet connectivity\n\n\n\n\n\n\n\n\n\n\t\t\t\t\tFreedom of Expression\t\t\t\t\n\n\n\n\nFreedom of Expression \n\n\n\t\t\t\tCeasefire in Gaza: it’s time to end digital harms and deliver justice\t\t\t\n\n20 Jan 2025\n • \nAs physical violence appears to be coming to a halt after 15 months in Gaza, Access Now further calls for a digital ceasefire.\n\n\n\n\nPress Release\nCeasefire in Gaza: it’s time to end digital harms and deliver justice\n20 Jan 2025\n\nCeasefire in Gaza: it’s time to end digital harms and deliver justice\n\n\n\n\n\n\n\n\n\n\t\t\t\t\tFreedom of Expression\t\t\t\t\n\n\n\n\nFreedom of Expression \n\n\n\t\t\t\tTackling the “black snakes” undermining digital rights worldwide \t\t\t\n\n16 Jan 2025\n • \nAs 2025 gets underway, Access Now’s new Executive Director, Alejandro Mayoral Baños, PhD, shares his reflections on the “black snakes” threatening the digital rights movement. \n\n\n\n\nPost\nTackling the “black snakes” undermining digital rights worldwide \n16 Jan 2025\n\nTackling the “black snakes” undermining digital rights worldwide \n\n\n\n\n\n\n\n\n\n\t\t\t\t\tInternet Shutdowns\t\t\t\t\n\n\n\n\nInternet Shutdowns \n\n\n\t\t\t\t#KeepItOn in Tanzania: authorities must ensure connectivity during local elections\t\t\t\n\n21 Nov 2024\n • \nThe #KeepItOn coalition demands that the Government of Tanzania ensure unhindered access to the internet during the upcoming elections.\n\n\n\n\nPress Release\n#KeepItOn in Tanzania: authorities must ensure connectivity during local elections\n21 Nov 2024\n\n#KeepItOn in Tanzania: authorities must ensure connectivity during local elections\n\n\n\n\n\n\n\n\n\n\t\t\t\t\tInternet Shutdowns\t\t\t\t\n\n\n\n\nInternet Shutdowns \n\n\n\t\t\t\t#KeepItOn: the Government of Tanzania and internet service providers must ensure open and secure internet access throughout the 2024 local elections\t\t\t\n\n21 Nov 2024\n • \nThe #KeepItOn coalition calls on authorities and ISPs in Tanzania to ensure internet access during the upcoming elections. \n\n\n\n\nPress Release\n#KeepItOn: the Government of Tanzania and internet service providers must ensure open and secure internet access throughout the 2024 local elections\n21 Nov 2024\n\n#KeepItOn: the Government of Tanzania and internet service providers must ensure open and secure internet access throughout the 2024 local elections\n\n\n\n\n\n\n\n\n\n\t\t\t\t\tConnectivity\t\t\t\t\n\n\n\n\nConnectivity \n\n\n\t\t\t\tAs Israel destroys infrastructure, will Lebanon be cut off from outside world?\t\t\t\n\n15 Nov 2024\n\n\n\n\nNews\nAs Israel destroys infrastructure, will Lebanon be cut off from outside world?\n\n\t\t\t\t\t\t\t\t\tThe New Arab ↗\t\t\t\t\t\t\t\n↗\n15 Nov 2024\n\nAs Israel destroys infrastructure, will Lebanon be cut off from outside world?\n\n\n\n\n\n\n\n\n\n\t\t\t\t\tConnectivity\t\t\t\t\n\n\n\n\nConnectivity \n\n\n\t\t\t\tApple keeps killing VPN apps upon Russia’s orders – Amnezia VPN is the last victim\t\t\t\n\n4 Nov 2024\n\n\n\n\nNews\nApple keeps killing VPN apps upon Russia’s orders – Amnezia VPN is the last victim\n\n\t\t\t\t\t\t\t\t\tTechRadar ↗\t\t\t\t\t\t\t\n↗\n4 Nov 2024\n\nApple keeps killing VPN apps upon Russia’s orders – Amnezia VPN is the last victim\n\n\n\n\n\n\n\n\n\n\t\t\t\t\tInternet Shutdowns\t\t\t\t\n\n\n\n\nInternet Shutdowns \n\n\n\t\t\t\t#KeepItOn Mauritius: global coalition urges first-time offender to end crackdown on social media\t\t\t\n\n1 Nov 2024\n\n\n\n\nPress Release\n#KeepItOn Mauritius: global coalition urges first-time offender to end crackdown on social media\n1 Nov 2024\n\n#KeepItOn Mauritius: global coalition urges first-time offender to end crackdown on social media\n\n\n\n\n\n\n\n\n\n\t\t\t\t\tConnectivity\t\t\t\t\n\n\n\n\nConnectivity \n\n\n\t\t\t\tMyanmar residents struggle to overcome severe internet blackouts with Starlink\t\t\t\n\n23 Oct 2024\n\n\n\n\nNews\nMyanmar residents struggle to overcome severe internet blackouts with Starlink\n\n\t\t\t\t\t\t\t\t\tRest of World ↗\t\t\t\t\t\t\t\n↗\n23 Oct 2024\n\nMyanmar residents struggle to overcome severe internet blackouts with Starlink\n\n\n\n\n\n\n\n\n\n\t\t\t\t\tConnectivity\t\t\t\t\n\n\n\n\nConnectivity \n\n\n\t\t\t\tستارلينك في اليمن: لماذا يعارض الحوثيون تفعيل الإنترنت الفضائي؟\t\t\t\n\n1 Oct 2024\n\n\n\n\nNews\nستارلينك في اليمن: لماذا يعارض الحوثيون تفعيل الإنترنت الفضائي؟\n\n\t\t\t\t\t\t\t\t\tBBC ↗\t\t\t\t\t\t\t\n↗\n1 Oct 2024\n\nستارلينك في اليمن: لماذا يعارض الحوثيون تفعيل الإنترنت الفضائي؟\n\n\n\n\n\n\n\n\n\n\t\t\t\t\tInternet Shutdowns\t\t\t\t\n\n\n\n\nInternet Shutdowns \n\n\n\t\t\t\tJoint statement: Sudan has suffered in silence for over 500 days\t\t\t\n\n5 Sep 2024\n • \nAfter more than 500 days of brutal conflict in Sudan, the #KeepItOn coalition reiterates calls to reactivate telecommunication services.\n\n\n\n\nPress Release\nJoint statement: Sudan has suffered in silence for over 500 days\n5 Sep 2024\n\nJoint statement: Sudan has suffered in silence for over 500 days\n\n\n\n\n\n\n\n\n\n\t\t\t\t\tInternet Shutdowns\t\t\t\t\n\n\n\n\nInternet Shutdowns \n\n\n\t\t\t\tAfrica in 2023: internet shutdowns attack democracy\t\t\t\n\n26 Aug 2024\n\n\n\n\nPress Release\nAfrica in 2023: internet shutdowns attack democracy\n26 Aug 2024\n\nAfrica in 2023: internet shutdowns attack democracy\n\n\n\n\n\n\n\n\n\n\t\t\t\t\tInternet Shutdowns\t\t\t\t\n\n\n\n\nInternet Shutdowns \n\n\n\t\t\t\t#KeepItOn in Annobón: Authorities in Equatorial Guinea must end internet shutdown and other human rights abuses\t\t\t\n\n13 Aug 2024\n • \nAccess Now and the #KeepItOn coalition are calling on authorities in Equatorial Guinea to immediately restore internet and telecom services in Annobón.\n\n\n\n\nPress Release\n#KeepItOn in Annobón: Authorities in Equatorial Guinea must end internet shutdown and other human rights abuses\n13 Aug 2024\n\n#KeepItOn in Annobón: Authorities in Equatorial Guinea must end internet shutdown and other human rights abuses\n\n\n\n\n\n\n\n\n\n\t\t\t\t\tInternet Shutdowns\t\t\t\t\n\n\n\n\nInternet Shutdowns \n\n\n\t\t\t\t#KeepItOn en Annobón: Las autoridades de Guinea Ecuatorial deben poner fin al corte de internet y otros abusos a los derechos humanos\t\t\t\n\n13 Aug 2024\n • \nLa coalición #KeepItOn instan a las autoridades de Guinea Ecuatorial a restablecer de inmediato el acceso a internet en Annobón.\n\n\n\n\nPress Release\n#KeepItOn en Annobón: Las autoridades de Guinea Ecuatorial deben poner fin al corte de internet y otros abusos a los derechos humanos\n13 Aug 2024\n\n#KeepItOn en Annobón: Las autoridades de Guinea Ecuatorial deben poner fin al corte de internet y otros abusos a los derechos humanos\n\nEquitable Internet Access For All\n\nEquitable Internet Access For All\n\nToday, affordable and meaningful access to the internet is an essential enabler of human rights. We advocate for policies and technologies to support equitable access to a free, open, and secure internet, and capacity-building to enable marginalized people and communities to make the most of it.\n\nToday, affordable and meaningful access to the internet is an essential enabler of human rights. We advocate for policies and technologies to support equitable access to a free, open, and secure internet, and capacity-building to enable marginalized people and communities to make the most of it.\n\nToday, affordable and meaningful access to the internet is an essential enabler of human rights. We advocate for policies and technologies to support equitable access to a free, open, and secure internet, and capacity-building to enable marginalized people and communities to make the most of it.\n\nMore than 3.5 billion left in the dark: why we’re still fighting to reach U.N. targets for internet access\nImagine the world coming together to envision, plan, and commit to creating a better future — for everyone, everywhere. \n\nLearn more\n\nMore than 3.5 billion left in the dark: why we’re still fighting to reach U.N. targets for internet access\nImagine the world coming together to envision, plan, and commit to creating a better future — for everyone, everywhere. \n\nLearn more\n\nMore than 3.5 billion left in the dark: why we’re still fighting to reach U.N. targets for internet access\nImagine the world coming together to envision, plan, and commit to creating a better future — for everyone, everywhere. \n\nLearn more\n\nMore than 3.5 billion left in the dark: why we’re still fighting to reach U.N. targets for internet access\nImagine the world coming together to envision, plan, and commit to creating a better future — for everyone, everywhere. \n\nLearn more\n\nImagine the world coming together to envision, plan, and commit to creating a better future — for everyone, everywhere.\n\nLearn more\n\nLearn more\n\nExpanding connectivity to fight COVID-19: recommendations for governments and telcos \n\t\t\t\t\t\t\t\n\n\n\n\n\n\n\n\n\n\n\n\n\nFreedom of Expression\n\n\n\t\t\t\n\t\t\t\tTunisia: Access to online conferencing platforms and networks is a constitutional right\n\t\t\t\t\t\t\t\n\n\nAccess Now joins civil society organizations in calling for safe and open access to online conferencing platforms in Tunisia.\n\n\n\n\n\n\n\n\n\n\n\n\n\nFreedom of Expression\n\n\n\t\t\t\n\t\t\t\tVictory! U.S. Senate passes infrastructure bill, critical to get people online\n\t\t\t\t\t\t\t\n\n\nAccess Now applauds the U.S. Senate for passing an infrastructure bill that would help get people online.\n\n\n\n\n\n\n\n\n\n\n\n\n\nFreedom of Expression\n\n\n\t\t\t\n\t\t\t\tWhat the tech sector can do to respect human rights in Ukraine, Russia, Belarus, and beyond\n\t\t\t\t\t\t\t\n\n\nAs the Russia-Ukraine crisis escalates to war, the tech sector must do more than merely comply with sanctions. Here are our recommendations for mitigating human rights harms.\n\nExpanding connectivity to fight COVID-19: recommendations for governments and telcos \n\t\t\t\t\t\t\t\n\n\n\n\n\n\n\n\n\n\n\n\n\nFreedom of Expression\n\n\n\t\t\t\n\t\t\t\tTunisia: Access to online conferencing platforms and networks is a constitutional right\n\t\t\t\t\t\t\t\n\n\nAccess Now joins civil society organizations in calling for safe and open access to online conferencing platforms in Tunisia.\n\n\n\n\n\n\n\n\n\n\n\n\n\nFreedom of Expression\n\n\n\t\t\t\n\t\t\t\tVictory! U.S. Senate passes infrastructure bill, critical to get people online\n\t\t\t\t\t\t\t\n\n\nAccess Now applauds the U.S. Senate for passing an infrastructure bill that would help get people online.\n\n\n\n\n\n\n\n\n\n\n\n\n\nFreedom of Expression\n\n\n\t\t\t\n\t\t\t\tWhat the tech sector can do to respect human rights in Ukraine, Russia, Belarus, and beyond\n\t\t\t\t\t\t\t\n\n\nAs the Russia-Ukraine crisis escalates to war, the tech sector must do more than merely comply with sanctions. Here are our recommendations for mitigating human rights harms.\n\nExpanding connectivity to fight COVID-19: recommendations for governments and telcos \n\t\t\t\t\t\t\t\n\n\n\n\n\n\n\n\n\n\n\n\n\nFreedom of Expression\n\n\n\t\t\t\n\t\t\t\tTunisia: Access to online conferencing platforms and networks is a constitutional right\n\t\t\t\t\t\t\t\n\n\nAccess Now joins civil society organizations in calling for safe and open access to online conferencing platforms in Tunisia.\n\n\n\n\n\n\n\n\n\n\n\n\n\nFreedom of Expression\n\n\n\t\t\t\n\t\t\t\tVictory! U.S. Senate passes infrastructure bill, critical to get people online\n\t\t\t\t\t\t\t\n\n\nAccess Now applauds the U.S. Senate for passing an infrastructure bill that would help get people online.\n\n\n\n\n\n\n\n\n\n\n\n\n\nFreedom of Expression\n\n\n\t\t\t\n\t\t\t\tWhat the tech sector can do to respect human rights in Ukraine, Russia, Belarus, and beyond\n\t\t\t\t\t\t\t\n\n\nAs the Russia-Ukraine crisis escalates to war, the tech sector must do more than merely comply with sanctions. Here are our recommendations for mitigating human rights harms.\n\nExpanding connectivity to fight COVID-19: recommendations for governments and telcos \n\t\t\t\t\t\t\t\n\n\n\n\n\n\n\n\n\n\n\n\n\nFreedom of Expression\n\n\n\t\t\t\n\t\t\t\tTunisia: Access to online conferencing platforms and networks is a constitutional right\n\t\t\t\t\t\t\t\n\n\nAccess Now joins civil society organizations in calling for safe and open access to online conferencing platforms in Tunisia.\n\n\n\n\n\n\n\n\n\n\n\n\n\nFreedom of Expression\n\n\n\t\t\t\n\t\t\t\tVictory! U.S. Senate passes infrastructure bill, critical to get people online\n\t\t\t\t\t\t\t\n\n\nAccess Now applauds the U.S. Senate for passing an infrastructure bill that would help get people online.\n\n\n\n\n\n\n\n\n\n\n\n\n\nFreedom of Expression\n\n\n\t\t\t\n\t\t\t\tWhat the tech sector can do to respect human rights in Ukraine, Russia, Belarus, and beyond\n\t\t\t\t\t\t\t\n\n\nAs the Russia-Ukraine crisis escalates to war, the tech sector must do more than merely comply with sanctions. Here are our recommendations for mitigating human rights harms.\n\nExpanding connectivity to fight COVID-19: recommendations for governments and telcos\n\nExpanding connectivity to fight COVID-19: recommendations for governments and telcos\n\nExpanding connectivity to fight COVID-19: recommendations for governments and telcos\n\nFreedom of Expression\n\n\n\t\t\t\n\t\t\t\tTunisia: Access to online conferencing platforms and networks is a constitutional right\n\t\t\t\t\t\t\t\n\n\nAccess Now joins civil society organizations in calling for safe and open access to online conferencing platforms in Tunisia.\n\nFreedom of Expression\n\n\n\t\t\t\n\t\t\t\tTunisia: Access to online conferencing platforms and networks is a constitutional right\n\t\t\t\t\t\t\t\n\n\nAccess Now joins civil society organizations in calling for safe and open access to online conferencing platforms in Tunisia.\n\nFreedom of Expression\n\n\n\t\t\t\n\t\t\t\tTunisia: Access to online conferencing platforms and networks is a constitutional right\n\t\t\t\t\t\t\t\n\n\nAccess Now joins civil society organizations in calling for safe and open access to online conferencing platforms in Tunisia.\n\nFreedom of Expression\n\nAccess Now joins civil society organizations in calling for safe and open access to online conferencing platforms in Tunisia.\n\nAccess Now joins civil society organizations in calling for safe and open access to online conferencing platforms in Tunisia.\n\nFreedom of Expression\n\n\n\t\t\t\n\t\t\t\tVictory! U.S. Senate passes infrastructure bill, critical to get people online\n\t\t\t\t\t\t\t\n\n\nAccess Now applauds the U.S. Senate for passing an infrastructure bill that would help get people online.\n\nFreedom of Expression\n\n\n\t\t\t\n\t\t\t\tVictory! U.S. Senate passes infrastructure bill, critical to get people online\n\t\t\t\t\t\t\t\n\n\nAccess Now applauds the U.S. Senate for passing an infrastructure bill that would help get people online.\n\nFreedom of Expression\n\n\n\t\t\t\n\t\t\t\tVictory! U.S. Senate passes infrastructure bill, critical to get people online\n\t\t\t\t\t\t\t\n\n\nAccess Now applauds the U.S. Senate for passing an infrastructure bill that would help get people online.\n\nFreedom of Expression\n\nAccess Now applauds the U.S. Senate for passing an infrastructure bill that would help get people online.\n\nAccess Now applauds the U.S. Senate for passing an infrastructure bill that would help get people online.\n\nFreedom of Expression\n\n\n\t\t\t\n\t\t\t\tWhat the tech sector can do to respect human rights in Ukraine, Russia, Belarus, and beyond\n\t\t\t\t\t\t\t\n\n\nAs the Russia-Ukraine crisis escalates to war, the tech sector must do more than merely comply with sanctions. Here are our recommendations for mitigating human rights harms.\n\nFreedom of Expression\n\n\n\t\t\t\n\t\t\t\tWhat the tech sector can do to respect human rights in Ukraine, Russia, Belarus, and beyond\n\t\t\t\t\t\t\t\n\n\nAs the Russia-Ukraine crisis escalates to war, the tech sector must do more than merely comply with sanctions. Here are our recommendations for mitigating human rights harms.\n\nFreedom of Expression\n\n\n\t\t\t\n\t\t\t\tWhat the tech sector can do to respect human rights in Ukraine, Russia, Belarus, and beyond\n\t\t\t\t\t\t\t\n\n\nAs the Russia-Ukraine crisis escalates to war, the tech sector must do more than merely comply with sanctions. Here are our recommendations for mitigating human rights harms.\n\nFreedom of Expression\n\nAs the Russia-Ukraine crisis escalates to war, the tech sector must do more than merely comply with sanctions. Here are our recommendations for mitigating human rights harms.\n\nAs the Russia-Ukraine crisis escalates to war, the tech sector must do more than merely comply with sanctions. Here are our recommendations for mitigating human rights harms.\n\nLatest Updates\n\n\n\n     \n\n\n\n\n\nGrid View\nList View\n\n\n\n\n\n\n\n\n\n\n\n\n\n\t\t\t\t\tConnectivity\t\t\t\t\n\n\n\n\nConnectivity \n\n\n\t\t\t\tJoint statement: five-point plan for an inclusive WSIS+20 review\t\t\t\n\n29 Mar 2025\n\n\n\n\nPress Release\nJoint statement: five-point plan for an inclusive WSIS+20 review\n\n\n↗\n29 Mar 2025\n\nJoint statement: five-point plan for an inclusive WSIS+20 review\n\n\n\n\n\n\n\n\n\n\t\t\t\t\tConnectivity\t\t\t\t\n\n\n\n\nConnectivity \n\n\n\t\t\t\tOral statement at 10th Session of the UN Open Ended Working Group on ICTs\t\t\t\n\n21 Feb 2025\n • \nAccess Now’s oral statement at the 10th Session of the UN Open Ended Working Group on information and communication technology.\n\n\n\n\nPublication\nOral statement at 10th Session of the UN Open Ended Working Group on ICTs\n\n\n↗\n21 Feb 2025\n\nOral statement at 10th Session of the UN Open Ended Working Group on ICTs\n\n\n\n\n\n\n\n\n\n\t\t\t\t\tConnectivity\t\t\t\t\n\n\n\n\nConnectivity \n\n\n\t\t\t\tHolding space for human rights: improving the governance of satellite internet connectivity\t\t\t\n\n5 Feb 2025\n • \nFrom obstructed humanitarian access to the weaponization of personal digital devices, internet connectivity is an issue that carries multiple layers of harms\n— one that we are only just starting to unpack.\n\n\n\n\nPublication\nHolding space for human rights: improving the governance of satellite internet connectivity\n\n\n↗\n5 Feb 2025\n\nHolding space for human rights: improving the governance of satellite internet connectivity\n\n\n\n\n\n\n\n\n\n\t\t\t\t\tFreedom of Expression\t\t\t\t\n\n\n\n\nFreedom of Expression \n\n\n\t\t\t\tCeasefire in Gaza: it’s time to end digital harms and deliver justice\t\t\t\n\n20 Jan 2025\n • \nAs physical violence appears to be coming to a halt after 15 months in Gaza, Access Now further calls for a digital ceasefire.\n\n\n\n\nPress Release\nCeasefire in Gaza: it’s time to end digital harms and deliver justice\n20 Jan 2025\n\nCeasefire in Gaza: it’s time to end digital harms and deliver justice\n\n\n\n\n\n\n\n\n\n\t\t\t\t\tFreedom of Expression\t\t\t\t\n\n\n\n\nFreedom of Expression \n\n\n\t\t\t\tTackling the “black snakes” undermining digital rights worldwide \t\t\t\n\n16 Jan 2025\n • \nAs 2025 gets underway, Access Now’s new Executive Director, Alejandro Mayoral Baños, PhD, shares his reflections on the “black snakes” threatening the digital rights movement. \n\n\n\n\nPost\nTackling the “black snakes” undermining digital rights worldwide \n16 Jan 2025\n\nTackling the “black snakes” undermining digital rights worldwide \n\n\n\n\n\n\n\n\n\n\t\t\t\t\tInternet Shutdowns\t\t\t\t\n\n\n\n\nInternet Shutdowns \n\n\n\t\t\t\t#KeepItOn in Tanzania: authorities must ensure connectivity during local elections\t\t\t\n\n21 Nov 2024\n • \nThe #KeepItOn coalition demands that the Government of Tanzania ensure unhindered access to the internet during the upcoming elections.\n\n\n\n\nPress Release\n#KeepItOn in Tanzania: authorities must ensure connectivity during local elections\n21 Nov 2024\n\n#KeepItOn in Tanzania: authorities must ensure connectivity during local elections\n\n\n\n\n\n\n\n\n\n\t\t\t\t\tInternet Shutdowns\t\t\t\t\n\n\n\n\nInternet Shutdowns \n\n\n\t\t\t\t#KeepItOn: the Government of Tanzania and internet service providers must ensure open and secure internet access throughout the 2024 local elections\t\t\t\n\n21 Nov 2024\n • \nThe #KeepItOn coalition calls on authorities and ISPs in Tanzania to ensure internet access during the upcoming elections. \n\n\n\n\nPress Release\n#KeepItOn: the Government of Tanzania and internet service providers must ensure open and secure internet access throughout the 2024 local elections\n21 Nov 2024\n\n#KeepItOn: the Government of Tanzania and internet service providers must ensure open and secure internet access throughout the 2024 local elections\n\n\n\n\n\n\n\n\n\n\t\t\t\t\tConnectivity\t\t\t\t\n\n\n\n\nConnectivity \n\n\n\t\t\t\tAs Israel destroys infrastructure, will Lebanon be cut off from outside world?\t\t\t\n\n15 Nov 2024\n\n\n\n\nNews\nAs Israel destroys infrastructure, will Lebanon be cut off from outside world?\n\n\t\t\t\t\t\t\t\t\tThe New Arab ↗\t\t\t\t\t\t\t\n↗\n15 Nov 2024\n\nAs Israel destroys infrastructure, will Lebanon be cut off from outside world?\n\n\n\n\n\n\n\n\n\n\t\t\t\t\tConnectivity\t\t\t\t\n\n\n\n\nConnectivity \n\n\n\t\t\t\tApple keeps killing VPN apps upon Russia’s orders – Amnezia VPN is the last victim\t\t\t\n\n4 Nov 2024\n\n\n\n\nNews\nApple keeps killing VPN apps upon Russia’s orders – Amnezia VPN is the last victim\n\n\t\t\t\t\t\t\t\t\tTechRadar ↗\t\t\t\t\t\t\t\n↗\n4 Nov 2024\n\nApple keeps killing VPN apps upon Russia’s orders – Amnezia VPN is the last victim\n\n\n\n\n\n\n\n\n\n\t\t\t\t\tInternet Shutdowns\t\t\t\t\n\n\n\n\nInternet Shutdowns \n\n\n\t\t\t\t#KeepItOn Mauritius: global coalition urges first-time offender to end crackdown on social media\t\t\t\n\n1 Nov 2024\n\n\n\n\nPress Release\n#KeepItOn Mauritius: global coalition urges first-time offender to end crackdown on social media\n1 Nov 2024\n\n#KeepItOn Mauritius: global coalition urges first-time offender to end crackdown on social media\n\n\n\n\n\n\n\n\n\n\t\t\t\t\tConnectivity\t\t\t\t\n\n\n\n\nConnectivity \n\n\n\t\t\t\tMyanmar residents struggle to overcome severe internet blackouts with Starlink\t\t\t\n\n23 Oct 2024\n\n\n\n\nNews\nMyanmar residents struggle to overcome severe internet blackouts with Starlink\n\n\t\t\t\t\t\t\t\t\tRest of World ↗\t\t\t\t\t\t\t\n↗\n23 Oct 2024\n\nMyanmar residents struggle to overcome severe internet blackouts with Starlink\n\n\n\n\n\n\n\n\n\n\t\t\t\t\tConnectivity\t\t\t\t\n\n\n\n\nConnectivity \n\n\n\t\t\t\tستارلينك في اليمن: لماذا يعارض الحوثيون تفعيل الإنترنت الفضائي؟\t\t\t\n\n1 Oct 2024\n\n\n\n\nNews\nستارلينك في اليمن: لماذا يعارض الحوثيون تفعيل الإنترنت الفضائي؟\n\n\t\t\t\t\t\t\t\t\tBBC ↗\t\t\t\t\t\t\t\n↗\n1 Oct 2024\n\nستارلينك في اليمن: لماذا يعارض الحوثيون تفعيل الإنترنت الفضائي؟\n\n\n\n\n\n\n\n\n\n\t\t\t\t\tInternet Shutdowns\t\t\t\t\n\n\n\n\nInternet Shutdowns \n\n\n\t\t\t\tJoint statement: Sudan has suffered in silence for over 500 days\t\t\t\n\n5 Sep 2024\n • \nAfter more than 500 days of brutal conflict in Sudan, the #KeepItOn coalition reiterates calls to reactivate telecommunication services.\n\n\n\n\nPress Release\nJoint statement: Sudan has suffered in silence for over 500 days\n5 Sep 2024\n\nJoint statement: Sudan has suffered in silence for over 500 days\n\n\n\n\n\n\n\n\n\n\t\t\t\t\tInternet Shutdowns\t\t\t\t\n\n\n\n\nInternet Shutdowns \n\n\n\t\t\t\tAfrica in 2023: internet shutdowns attack democracy\t\t\t\n\n26 Aug 2024\n\n\n\n\nPress Release\nAfrica in 2023: internet shutdowns attack democracy\n26 Aug 2024\n\nAfrica in 2023: internet shutdowns attack democracy\n\n\n\n\n\n\n\n\n\n\t\t\t\t\tInternet Shutdowns\t\t\t\t\n\n\n\n\nInternet Shutdowns \n\n\n\t\t\t\t#KeepItOn in Annobón: Authorities in Equatorial Guinea must end internet shutdown and other human rights abuses\t\t\t\n\n13 Aug 2024\n • \nAccess Now and the #KeepItOn coalition are calling on authorities in Equatorial Guinea to immediately restore internet and telecom services in Annobón.\n\n\n\n\nPress Release\n#KeepItOn in Annobón: Authorities in Equatorial Guinea must end internet shutdown and other human rights abuses\n13 Aug 2024\n\n#KeepItOn in Annobón: Authorities in Equatorial Guinea must end internet shutdown and other human rights abuses\n\n\n\n\n\n\n\n\n\n\t\t\t\t\tInternet Shutdowns\t\t\t\t\n\n\n\n\nInternet Shutdowns \n\n\n\t\t\t\t#KeepItOn en Annobón: Las autoridades de Guinea Ecuatorial deben poner fin al corte de internet y otros abusos a los derechos humanos\t\t\t\n\n13 Aug 2024\n • \nLa coalición #KeepItOn instan a las autoridades de Guinea Ecuatorial a restablecer de inmediato el acceso a internet en Annobón.\n\n\n\n\nPress Release\n#KeepItOn en Annobón: Las autoridades de Guinea Ecuatorial deben poner fin al corte de internet y otros abusos a los derechos humanos\n13 Aug 2024\n\n#KeepItOn en Annobón: Las autoridades de Guinea Ecuatorial deben poner fin al corte de internet y otros abusos a los derechos humanos\n\nLatest Updates\n\n\n\n     \n\n\n\n\n\nGrid View\nList View\n\n\n\n\n\n\n\n\n\n\n\n\n\n\t\t\t\t\tConnectivity\t\t\t\t\n\n\n\n\nConnectivity \n\n\n\t\t\t\tJoint statement: five-point plan for an inclusive WSIS+20 review\t\t\t\n\n29 Mar 2025\n\n\n\n\nPress Release\nJoint statement: five-point plan for an inclusive WSIS+20 review\n\n\n↗\n29 Mar 2025\n\nJoint statement: five-point plan for an inclusive WSIS+20 review\n\n\n\n\n\n\n\n\n\n\t\t\t\t\tConnectivity\t\t\t\t\n\n\n\n\nConnectivity \n\n\n\t\t\t\tOral statement at 10th Session of the UN Open Ended Working Group on ICTs\t\t\t\n\n21 Feb 2025\n • \nAccess Now’s oral statement at the 10th Session of the UN Open Ended Working Group on information and communication technology.\n\n\n\n\nPublication\nOral statement at 10th Session of the UN Open Ended Working Group on ICTs\n\n\n↗\n21 Feb 2025\n\nOral statement at 10th Session of the UN Open Ended Working Group on ICTs\n\n\n\n\n\n\n\n\n\n\t\t\t\t\tConnectivity\t\t\t\t\n\n\n\n\nConnectivity \n\n\n\t\t\t\tHolding space for human rights: improving the governance of satellite internet connectivity\t\t\t\n\n5 Feb 2025\n • \nFrom obstructed humanitarian access to the weaponization of personal digital devices, internet connectivity is an issue that carries multiple layers of harms\n— one that we are only just starting to unpack.\n\n\n\n\nPublication\nHolding space for human rights: improving the governance of satellite internet connectivity\n\n\n↗\n5 Feb 2025\n\nHolding space for human rights: improving the governance of satellite internet connectivity\n\n\n\n\n\n\n\n\n\n\t\t\t\t\tFreedom of Expression\t\t\t\t\n\n\n\n\nFreedom of Expression \n\n\n\t\t\t\tCeasefire in Gaza: it’s time to end digital harms and deliver justice\t\t\t\n\n20 Jan 2025\n • \nAs physical violence appears to be coming to a halt after 15 months in Gaza, Access Now further calls for a digital ceasefire.\n\n\n\n\nPress Release\nCeasefire in Gaza: it’s time to end digital harms and deliver justice\n20 Jan 2025\n\nCeasefire in Gaza: it’s time to end digital harms and deliver justice\n\n\n\n\n\n\n\n\n\n\t\t\t\t\tFreedom of Expression\t\t\t\t\n\n\n\n\nFreedom of Expression \n\n\n\t\t\t\tTackling the “black snakes” undermining digital rights worldwide \t\t\t\n\n16 Jan 2025\n • \nAs 2025 gets underway, Access Now’s new Executive Director, Alejandro Mayoral Baños, PhD, shares his reflections on the “black snakes” threatening the digital rights movement. \n\n\n\n\nPost\nTackling the “black snakes” undermining digital rights worldwide \n16 Jan 2025\n\nTackling the “black snakes” undermining digital rights worldwide \n\n\n\n\n\n\n\n\n\n\t\t\t\t\tInternet Shutdowns\t\t\t\t\n\n\n\n\nInternet Shutdowns \n\n\n\t\t\t\t#KeepItOn in Tanzania: authorities must ensure connectivity during local elections\t\t\t\n\n21 Nov 2024\n • \nThe #KeepItOn coalition demands that the Government of Tanzania ensure unhindered access to the internet during the upcoming elections.\n\n\n\n\nPress Release\n#KeepItOn in Tanzania: authorities must ensure connectivity during local elections\n21 Nov 2024\n\n#KeepItOn in Tanzania: authorities must ensure connectivity during local elections\n\n\n\n\n\n\n\n\n\n\t\t\t\t\tInternet Shutdowns\t\t\t\t\n\n\n\n\nInternet Shutdowns \n\n\n\t\t\t\t#KeepItOn: the Government of Tanzania and internet service providers must ensure open and secure internet access throughout the 2024 local elections\t\t\t\n\n21 Nov 2024\n • \nThe #KeepItOn coalition calls on authorities and ISPs in Tanzania to ensure internet access during the upcoming elections. \n\n\n\n\nPress Release\n#KeepItOn: the Government of Tanzania and internet service providers must ensure open and secure internet access throughout the 2024 local elections\n21 Nov 2024\n\n#KeepItOn: the Government of Tanzania and internet service providers must ensure open and secure internet access throughout the 2024 local elections\n\n\n\n\n\n\n\n\n\n\t\t\t\t\tConnectivity\t\t\t\t\n\n\n\n\nConnectivity \n\n\n\t\t\t\tAs Israel destroys infrastructure, will Lebanon be cut off from outside world?\t\t\t\n\n15 Nov 2024\n\n\n\n\nNews\nAs Israel destroys infrastructure, will Lebanon be cut off from outside world?\n\n\t\t\t\t\t\t\t\t\tThe New Arab ↗\t\t\t\t\t\t\t\n↗\n15 Nov 2024\n\nAs Israel destroys infrastructure, will Lebanon be cut off from outside world?\n\n\n\n\n\n\n\n\n\n\t\t\t\t\tConnectivity\t\t\t\t\n\n\n\n\nConnectivity \n\n\n\t\t\t\tApple keeps killing VPN apps upon Russia’s orders – Amnezia VPN is the last victim\t\t\t\n\n4 Nov 2024\n\n\n\n\nNews\nApple keeps killing VPN apps upon Russia’s orders – Amnezia VPN is the last victim\n\n\t\t\t\t\t\t\t\t\tTechRadar ↗\t\t\t\t\t\t\t\n↗\n4 Nov 2024\n\nApple keeps killing VPN apps upon Russia’s orders – Amnezia VPN is the last victim\n\n\n\n\n\n\n\n\n\n\t\t\t\t\tInternet Shutdowns\t\t\t\t\n\n\n\n\nInternet Shutdowns \n\n\n\t\t\t\t#KeepItOn Mauritius: global coalition urges first-time offender to end crackdown on social media\t\t\t\n\n1 Nov 2024\n\n\n\n\nPress Release\n#KeepItOn Mauritius: global coalition urges first-time offender to end crackdown on social media\n1 Nov 2024\n\n#KeepItOn Mauritius: global coalition urges first-time offender to end crackdown on social media\n\n\n\n\n\n\n\n\n\n\t\t\t\t\tConnectivity\t\t\t\t\n\n\n\n\nConnectivity \n\n\n\t\t\t\tMyanmar residents struggle to overcome severe internet blackouts with Starlink\t\t\t\n\n23 Oct 2024\n\n\n\n\nNews\nMyanmar residents struggle to overcome severe internet blackouts with Starlink\n\n\t\t\t\t\t\t\t\t\tRest of World ↗\t\t\t\t\t\t\t\n↗\n23 Oct 2024\n\nMyanmar residents struggle to overcome severe internet blackouts with Starlink\n\n\n\n\n\n\n\n\n\n\t\t\t\t\tConnectivity\t\t\t\t\n\n\n\n\nConnectivity \n\n\n\t\t\t\tستارلينك في اليمن: لماذا يعارض الحوثيون تفعيل الإنترنت الفضائي؟\t\t\t\n\n1 Oct 2024\n\n\n\n\nNews\nستارلينك في اليمن: لماذا يعارض الحوثيون تفعيل الإنترنت الفضائي؟\n\n\t\t\t\t\t\t\t\t\tBBC ↗\t\t\t\t\t\t\t\n↗\n1 Oct 2024\n\nستارلينك في اليمن: لماذا يعارض الحوثيون تفعيل الإنترنت الفضائي؟\n\n\n\n\n\n\n\n\n\n\t\t\t\t\tInternet Shutdowns\t\t\t\t\n\n\n\n\nInternet Shutdowns \n\n\n\t\t\t\tJoint statement: Sudan has suffered in silence for over 500 days\t\t\t\n\n5 Sep 2024\n • \nAfter more than 500 days of brutal conflict in Sudan, the #KeepItOn coalition reiterates calls to reactivate telecommunication services.\n\n\n\n\nPress Release\nJoint statement: Sudan has suffered in silence for over 500 days\n5 Sep 2024\n\nJoint statement: Sudan has suffered in silence for over 500 days\n\n\n\n\n\n\n\n\n\n\t\t\t\t\tInternet Shutdowns\t\t\t\t\n\n\n\n\nInternet Shutdowns \n\n\n\t\t\t\tAfrica in 2023: internet shutdowns attack democracy\t\t\t\n\n26 Aug 2024\n\n\n\n\nPress Release\nAfrica in 2023: internet shutdowns attack democracy\n26 Aug 2024\n\nAfrica in 2023: internet shutdowns attack democracy\n\n\n\n\n\n\n\n\n\n\t\t\t\t\tInternet Shutdowns\t\t\t\t\n\n\n\n\nInternet Shutdowns \n\n\n\t\t\t\t#KeepItOn in Annobón: Authorities in Equatorial Guinea must end internet shutdown and other human rights abuses\t\t\t\n\n13 Aug 2024\n • \nAccess Now and the #KeepItOn coalition are calling on authorities in Equatorial Guinea to immediately restore internet and telecom services in Annobón.\n\n\n\n\nPress Release\n#KeepItOn in Annobón: Authorities in Equatorial Guinea must end internet shutdown and other human rights abuses\n13 Aug 2024\n\n#KeepItOn in Annobón: Authorities in Equatorial Guinea must end internet shutdown and other human rights abuses\n\n\n\n\n\n\n\n\n\n\t\t\t\t\tInternet Shutdowns\t\t\t\t\n\n\n\n\nInternet Shutdowns \n\n\n\t\t\t\t#KeepItOn en Annobón: Las autoridades de Guinea Ecuatorial deben poner fin al corte de internet y otros abusos a los derechos humanos\t\t\t\n\n13 Aug 2024\n • \nLa coalición #KeepItOn instan a las autoridades de Guinea Ecuatorial a restablecer de inmediato el acceso a internet en Annobón.\n\n\n\n\nPress Release\n#KeepItOn en Annobón: Las autoridades de Guinea Ecuatorial deben poner fin al corte de internet y otros abusos a los derechos humanos\n13 Aug 2024\n\n#KeepItOn en Annobón: Las autoridades de Guinea Ecuatorial deben poner fin al corte de internet y otros abusos a los derechos humanos\n\nLatest Updates\n\n\n\n     \n\n\n\n\n\nGrid View\nList View\n\nLatest Updates\n\nGrid View\nList View\n\nGrid View\nList View\n\nConnectivity\t\t\t\t\n\n\n\n\nConnectivity \n\n\n\t\t\t\tJoint statement: five-point plan for an inclusive WSIS+20 review\t\t\t\n\n29 Mar 2025\n\n\n\n\nPress Release\nJoint statement: five-point plan for an inclusive WSIS+20 review\n\n\n↗\n29 Mar 2025\n\nJoint statement: five-point plan for an inclusive WSIS+20 review\n\n\n\n\n\n\n\n\n\n\t\t\t\t\tConnectivity\t\t\t\t\n\n\n\n\nConnectivity \n\n\n\t\t\t\tOral statement at 10th Session of the UN Open Ended Working Group on ICTs\t\t\t\n\n21 Feb 2025\n • \nAccess Now’s oral statement at the 10th Session of the UN Open Ended Working Group on information and communication technology.\n\n\n\n\nPublication\nOral statement at 10th Session of the UN Open Ended Working Group on ICTs\n\n\n↗\n21 Feb 2025\n\nOral statement at 10th Session of the UN Open Ended Working Group on ICTs\n\n\n\n\n\n\n\n\n\n\t\t\t\t\tConnectivity\t\t\t\t\n\n\n\n\nConnectivity \n\n\n\t\t\t\tHolding space for human rights: improving the governance of satellite internet connectivity\t\t\t\n\n5 Feb 2025\n • \nFrom obstructed humanitarian access to the weaponization of personal digital devices, internet connectivity is an issue that carries multiple layers of harms\n— one that we are only just starting to unpack.\n\n\n\n\nPublication\nHolding space for human rights: improving the governance of satellite internet connectivity\n\n\n↗\n5 Feb 2025\n\nHolding space for human rights: improving the governance of satellite internet connectivity\n\n\n\n\n\n\n\n\n\n\t\t\t\t\tFreedom of Expression\t\t\t\t\n\n\n\n\nFreedom of Expression \n\n\n\t\t\t\tCeasefire in Gaza: it’s time to end digital harms and deliver justice\t\t\t\n\n20 Jan 2025\n • \nAs physical violence appears to be coming to a halt after 15 months in Gaza, Access Now further calls for a digital ceasefire.\n\n\n\n\nPress Release\nCeasefire in Gaza: it’s time to end digital harms and deliver justice\n20 Jan 2025\n\nCeasefire in Gaza: it’s time to end digital harms and deliver justice\n\n\n\n\n\n\n\n\n\n\t\t\t\t\tFreedom of Expression\t\t\t\t\n\n\n\n\nFreedom of Expression \n\n\n\t\t\t\tTackling the “black snakes” undermining digital rights worldwide \t\t\t\n\n16 Jan 2025\n • \nAs 2025 gets underway, Access Now’s new Executive Director, Alejandro Mayoral Baños, PhD, shares his reflections on the “black snakes” threatening the digital rights movement. \n\n\n\n\nPost\nTackling the “black snakes” undermining digital rights worldwide \n16 Jan 2025\n\nTackling the “black snakes” undermining digital rights worldwide \n\n\n\n\n\n\n\n\n\n\t\t\t\t\tInternet Shutdowns\t\t\t\t\n\n\n\n\nInternet Shutdowns \n\n\n\t\t\t\t#KeepItOn in Tanzania: authorities must ensure connectivity during local elections\t\t\t\n\n21 Nov 2024\n • \nThe #KeepItOn coalition demands that the Government of Tanzania ensure unhindered access to the internet during the upcoming elections.\n\n\n\n\nPress Release\n#KeepItOn in Tanzania: authorities must ensure connectivity during local elections\n21 Nov 2024\n\n#KeepItOn in Tanzania: authorities must ensure connectivity during local elections\n\n\n\n\n\n\n\n\n\n\t\t\t\t\tInternet Shutdowns\t\t\t\t\n\n\n\n\nInternet Shutdowns \n\n\n\t\t\t\t#KeepItOn: the Government of Tanzania and internet service providers must ensure open and secure internet access throughout the 2024 local elections\t\t\t\n\n21 Nov 2024\n • \nThe #KeepItOn coalition calls on authorities and ISPs in Tanzania to ensure internet access during the upcoming elections. \n\n\n\n\nPress Release\n#KeepItOn: the Government of Tanzania and internet service providers must ensure open and secure internet access throughout the 2024 local elections\n21 Nov 2024\n\n#KeepItOn: the Government of Tanzania and internet service providers must ensure open and secure internet access throughout the 2024 local elections\n\n\n\n\n\n\n\n\n\n\t\t\t\t\tConnectivity\t\t\t\t\n\n\n\n\nConnectivity \n\n\n\t\t\t\tAs Israel destroys infrastructure, will Lebanon be cut off from outside world?\t\t\t\n\n15 Nov 2024\n\n\n\n\nNews\nAs Israel destroys infrastructure, will Lebanon be cut off from outside world?\n\n\t\t\t\t\t\t\t\t\tThe New Arab ↗\t\t\t\t\t\t\t\n↗\n15 Nov 2024\n\nAs Israel destroys infrastructure, will Lebanon be cut off from outside world?\n\n\n\n\n\n\n\n\n\n\t\t\t\t\tConnectivity\t\t\t\t\n\n\n\n\nConnectivity \n\n\n\t\t\t\tApple keeps killing VPN apps upon Russia’s orders – Amnezia VPN is the last victim\t\t\t\n\n4 Nov 2024\n\n\n\n\nNews\nApple keeps killing VPN apps upon Russia’s orders – Amnezia VPN is the last victim\n\n\t\t\t\t\t\t\t\t\tTechRadar ↗\t\t\t\t\t\t\t\n↗\n4 Nov 2024\n\nApple keeps killing VPN apps upon Russia’s orders – Amnezia VPN is the last victim\n\n\n\n\n\n\n\n\n\n\t\t\t\t\tInternet Shutdowns\t\t\t\t\n\n\n\n\nInternet Shutdowns \n\n\n\t\t\t\t#KeepItOn Mauritius: global coalition urges first-time offender to end crackdown on social media\t\t\t\n\n1 Nov 2024\n\n\n\n\nPress Release\n#KeepItOn Mauritius: global coalition urges first-time offender to end crackdown on social media\n1 Nov 2024\n\n#KeepItOn Mauritius: global coalition urges first-time offender to end crackdown on social media\n\n\n\n\n\n\n\n\n\n\t\t\t\t\tConnectivity\t\t\t\t\n\n\n\n\nConnectivity \n\n\n\t\t\t\tMyanmar residents struggle to overcome severe internet blackouts with Starlink\t\t\t\n\n23 Oct 2024\n\n\n\n\nNews\nMyanmar residents struggle to overcome severe internet blackouts with Starlink\n\n\t\t\t\t\t\t\t\t\tRest of World ↗\t\t\t\t\t\t\t\n↗\n23 Oct 2024\n\nMyanmar residents struggle to overcome severe internet blackouts with Starlink\n\n\n\n\n\n\n\n\n\n\t\t\t\t\tConnectivity\t\t\t\t\n\n\n\n\nConnectivity \n\n\n\t\t\t\tستارلينك في اليمن: لماذا يعارض الحوثيون تفعيل الإنترنت الفضائي؟\t\t\t\n\n1 Oct 2024\n\n\n\n\nNews\nستارلينك في اليمن: لماذا يعارض الحوثيون تفعيل الإنترنت الفضائي؟\n\n\t\t\t\t\t\t\t\t\tBBC ↗\t\t\t\t\t\t\t\n↗\n1 Oct 2024\n\nستارلينك في اليمن: لماذا يعارض الحوثيون تفعيل الإنترنت الفضائي؟\n\n\n\n\n\n\n\n\n\n\t\t\t\t\tInternet Shutdowns\t\t\t\t\n\n\n\n\nInternet Shutdowns \n\n\n\t\t\t\tJoint statement: Sudan has suffered in silence for over 500 days\t\t\t\n\n5 Sep 2024\n • \nAfter more than 500 days of brutal conflict in Sudan, the #KeepItOn coalition reiterates calls to reactivate telecommunication services.\n\n\n\n\nPress Release\nJoint statement: Sudan has suffered in silence for over 500 days\n5 Sep 2024\n\nJoint statement: Sudan has suffered in silence for over 500 days\n\n\n\n\n\n\n\n\n\n\t\t\t\t\tInternet Shutdowns\t\t\t\t\n\n\n\n\nInternet Shutdowns \n\n\n\t\t\t\tAfrica in 2023: internet shutdowns attack democracy\t\t\t\n\n26 Aug 2024\n\n\n\n\nPress Release\nAfrica in 2023: internet shutdowns attack democracy\n26 Aug 2024\n\nAfrica in 2023: internet shutdowns attack democracy\n\n\n\n\n\n\n\n\n\n\t\t\t\t\tInternet Shutdowns\t\t\t\t\n\n\n\n\nInternet Shutdowns \n\n\n\t\t\t\t#KeepItOn in Annobón: Authorities in Equatorial Guinea must end internet shutdown and other human rights abuses\t\t\t\n\n13 Aug 2024\n • \nAccess Now and the #KeepItOn coalition are calling on authorities in Equatorial Guinea to immediately restore internet and telecom services in Annobón.\n\n\n\n\nPress Release\n#KeepItOn in Annobón: Authorities in Equatorial Guinea must end internet shutdown and other human rights abuses\n13 Aug 2024\n\n#KeepItOn in Annobón: Authorities in Equatorial Guinea must end internet shutdown and other human rights abuses\n\n\n\n\n\n\n\n\n\n\t\t\t\t\tInternet Shutdowns\t\t\t\t\n\n\n\n\nInternet Shutdowns \n\n\n\t\t\t\t#KeepItOn en Annobón: Las autoridades de Guinea Ecuatorial deben poner fin al corte de internet y otros abusos a los derechos humanos\t\t\t\n\n13 Aug 2024\n • \nLa coalición #KeepItOn instan a las autoridades de Guinea Ecuatorial a restablecer de inmediato el acceso a internet en Annobón.\n\n\n\n\nPress Release\n#KeepItOn en Annobón: Las autoridades de Guinea Ecuatorial deben poner fin al corte de internet y otros abusos a los derechos humanos\n13 Aug 2024\n\n#KeepItOn en Annobón: Las autoridades de Guinea Ecuatorial deben poner fin al corte de internet y otros abusos a los derechos humanos\n\nConnectivity\t\t\t\t\n\n\n\n\nConnectivity \n\n\n\t\t\t\tJoint statement: five-point plan for an inclusive WSIS+20 review\t\t\t\n\n29 Mar 2025\n\n\n\n\nPress Release\nJoint statement: five-point plan for an inclusive WSIS+20 review\n\n\n↗\n29 Mar 2025\n\nJoint statement: five-point plan for an inclusive WSIS+20 review\n\nConnectivity\t\t\t\t\n\n\n\n\nConnectivity \n\n\n\t\t\t\tJoint statement: five-point plan for an inclusive WSIS+20 review\t\t\t\n\n29 Mar 2025\n\nConnectivity\n\nConnectivity\n\nConnectivity \n\n\n\t\t\t\tJoint statement: five-point plan for an inclusive WSIS+20 review\t\t\t\n\n29 Mar 2025\n\nConnectivity\n\nConnectivity\n\n29 Mar 2025\n\nPress Release\nJoint statement: five-point plan for an inclusive WSIS+20 review\n\n\n↗\n29 Mar 2025\n\nPress Release\n\nJoint statement: five-point plan for an inclusive WSIS+20 review\n\n↗\n\n29 Mar 2025\n\nConnectivity\t\t\t\t\n\n\n\n\nConnectivity \n\n\n\t\t\t\tOral statement at 10th Session of the UN Open Ended Working Group on ICTs\t\t\t\n\n21 Feb 2025\n • \nAccess Now’s oral statement at the 10th Session of the UN Open Ended Working Group on information and communication technology.\n\n\n\n\nPublication\nOral statement at 10th Session of the UN Open Ended Working Group on ICTs\n\n\n↗\n21 Feb 2025\n\nOral statement at 10th Session of the UN Open Ended Working Group on ICTs\n\nConnectivity\t\t\t\t\n\n\n\n\nConnectivity \n\n\n\t\t\t\tOral statement at 10th Session of the UN Open Ended Working Group on ICTs\t\t\t\n\n21 Feb 2025\n • \nAccess Now’s oral statement at the 10th Session of the UN Open Ended Working Group on information and communication technology.\n\nConnectivity\n\nConnectivity\n\nConnectivity \n\n\n\t\t\t\tOral statement at 10th Session of the UN Open Ended Working Group on ICTs\t\t\t\n\n21 Feb 2025\n • \nAccess Now’s oral statement at the 10th Session of the UN Open Ended Working Group on information and communication technology.\n\nConnectivity\n\nConnectivity\n\n21 Feb 2025\n • \nAccess Now’s oral statement at the 10th Session of the UN Open Ended Working Group on information and communication technology.\n\nAccess Now’s oral statement at the 10th Session of the UN Open Ended Working Group on information and communication technology.\n\nPublication\nOral statement at 10th Session of the UN Open Ended Working Group on ICTs\n\n\n↗\n21 Feb 2025\n\nPublication\n\nOral statement at 10th Session of the UN Open Ended Working Group on ICTs\n\n↗\n\n21 Feb 2025\n\nConnectivity\t\t\t\t\n\n\n\n\nConnectivity \n\n\n\t\t\t\tHolding space for human rights: improving the governance of satellite internet connectivity\t\t\t\n\n5 Feb 2025\n • \nFrom obstructed humanitarian access to the weaponization of personal digital devices, internet connectivity is an issue that carries multiple layers of harms\n— one that we are only just starting to unpack.\n\n\n\n\nPublication\nHolding space for human rights: improving the governance of satellite internet connectivity\n\n\n↗\n5 Feb 2025\n\nHolding space for human rights: improving the governance of satellite internet connectivity\n\nConnectivity\t\t\t\t\n\n\n\n\nConnectivity \n\n\n\t\t\t\tHolding space for human rights: improving the governance of satellite internet connectivity\t\t\t\n\n5 Feb 2025\n • \nFrom obstructed humanitarian access to the weaponization of personal digital devices, internet connectivity is an issue that carries multiple layers of harms\n— one that we are only just starting to unpack.\n\nConnectivity\n\nConnectivity\n\nConnectivity \n\n\n\t\t\t\tHolding space for human rights: improving the governance of satellite internet connectivity\t\t\t\n\n5 Feb 2025\n • \nFrom obstructed humanitarian access to the weaponization of personal digital devices, internet connectivity is an issue that carries multiple layers of harms\n— one that we are only just starting to unpack.\n\nConnectivity\n\nConnectivity\n\n5 Feb 2025\n • \nFrom obstructed humanitarian access to the weaponization of personal digital devices, internet connectivity is an issue that carries multiple layers of harms\n— one that we are only just starting to unpack.\n\nFrom obstructed humanitarian access to the weaponization of personal digital devices, internet connectivity is an issue that carries multiple layers of harms\n— one that we are only just starting to unpack.\n\nPublication\nHolding space for human rights: improving the governance of satellite internet connectivity\n\n\n↗\n5 Feb 2025\n\nPublication\n\nHolding space for human rights: improving the governance of satellite internet connectivity\n\n↗\n\n5 Feb 2025\n\nFreedom of Expression\t\t\t\t\n\n\n\n\nFreedom of Expression \n\n\n\t\t\t\tCeasefire in Gaza: it’s time to end digital harms and deliver justice\t\t\t\n\n20 Jan 2025\n • \nAs physical violence appears to be coming to a halt after 15 months in Gaza, Access Now further calls for a digital ceasefire.\n\n\n\n\nPress Release\nCeasefire in Gaza: it’s time to end digital harms and deliver justice\n20 Jan 2025\n\nCeasefire in Gaza: it’s time to end digital harms and deliver justice\n\nFreedom of Expression\t\t\t\t\n\n\n\n\nFreedom of Expression \n\n\n\t\t\t\tCeasefire in Gaza: it’s time to end digital harms and deliver justice\t\t\t\n\n20 Jan 2025\n • \nAs physical violence appears to be coming to a halt after 15 months in Gaza, Access Now further calls for a digital ceasefire.\n\nFreedom of Expression\n\nFreedom of Expression\n\nFreedom of Expression \n\n\n\t\t\t\tCeasefire in Gaza: it’s time to end digital harms and deliver justice\t\t\t\n\n20 Jan 2025\n • \nAs physical violence appears to be coming to a halt after 15 months in Gaza, Access Now further calls for a digital ceasefire.\n\nFreedom of Expression\n\nFreedom of Expression\n\n20 Jan 2025\n • \nAs physical violence appears to be coming to a halt after 15 months in Gaza, Access Now further calls for a digital ceasefire.\n\nAs physical violence appears to be coming to a halt after 15 months in Gaza, Access Now further calls for a digital ceasefire.\n\nPress Release\nCeasefire in Gaza: it’s time to end digital harms and deliver justice\n20 Jan 2025\n\nPress Release\n\nCeasefire in Gaza: it’s time to end digital harms and deliver justice\n\n20 Jan 2025\n\nFreedom of Expression\t\t\t\t\n\n\n\n\nFreedom of Expression \n\n\n\t\t\t\tTackling the “black snakes” undermining digital rights worldwide \t\t\t\n\n16 Jan 2025\n • \nAs 2025 gets underway, Access Now’s new Executive Director, Alejandro Mayoral Baños, PhD, shares his reflections on the “black snakes” threatening the digital rights movement. \n\n\n\n\nPost\nTackling the “black snakes” undermining digital rights worldwide \n16 Jan 2025\n\nTackling the “black snakes” undermining digital rights worldwide\n\nFreedom of Expression\t\t\t\t\n\n\n\n\nFreedom of Expression \n\n\n\t\t\t\tTackling the “black snakes” undermining digital rights worldwide \t\t\t\n\n16 Jan 2025\n • \nAs 2025 gets underway, Access Now’s new Executive Director, Alejandro Mayoral Baños, PhD, shares his reflections on the “black snakes” threatening the digital rights movement.\n\nFreedom of Expression\n\nFreedom of Expression\n\nFreedom of Expression \n\n\n\t\t\t\tTackling the “black snakes” undermining digital rights worldwide \t\t\t\n\n16 Jan 2025\n • \nAs 2025 gets underway, Access Now’s new Executive Director, Alejandro Mayoral Baños, PhD, shares his reflections on the “black snakes” threatening the digital rights movement.\n\nFreedom of Expression\n\nFreedom of Expression\n\n16 Jan 2025\n • \nAs 2025 gets underway, Access Now’s new Executive Director, Alejandro Mayoral Baños, PhD, shares his reflections on the “black snakes” threatening the digital rights movement.\n\nAs 2025 gets underway, Access Now’s new Executive Director, Alejandro Mayoral Baños, PhD, shares his reflections on the “black snakes” threatening the digital rights movement.\n\nPost\nTackling the “black snakes” undermining digital rights worldwide \n16 Jan 2025\n\nPost\n\nTackling the “black snakes” undermining digital rights worldwide\n\n16 Jan 2025\n\nInternet Shutdowns\t\t\t\t\n\n\n\n\nInternet Shutdowns \n\n\n\t\t\t\t#KeepItOn in Tanzania: authorities must ensure connectivity during local elections\t\t\t\n\n21 Nov 2024\n • \nThe #KeepItOn coalition demands that the Government of Tanzania ensure unhindered access to the internet during the upcoming elections.\n\n\n\n\nPress Release\n#KeepItOn in Tanzania: authorities must ensure connectivity during local elections\n21 Nov 2024\n\n#KeepItOn in Tanzania: authorities must ensure connectivity during local elections\n\nInternet Shutdowns\t\t\t\t\n\n\n\n\nInternet Shutdowns \n\n\n\t\t\t\t#KeepItOn in Tanzania: authorities must ensure connectivity during local elections\t\t\t\n\n21 Nov 2024\n • \nThe #KeepItOn coalition demands that the Government of Tanzania ensure unhindered access to the internet during the upcoming elections.\n\nInternet Shutdowns\n\nInternet Shutdowns\n\nInternet Shutdowns \n\n\n\t\t\t\t#KeepItOn in Tanzania: authorities must ensure connectivity during local elections\t\t\t\n\n21 Nov 2024\n • \nThe #KeepItOn coalition demands that the Government of Tanzania ensure unhindered access to the internet during the upcoming elections.\n\nInternet Shutdowns\n\nInternet Shutdowns\n\n21 Nov 2024\n • \nThe #KeepItOn coalition demands that the Government of Tanzania ensure unhindered access to the internet during the upcoming elections.\n\nThe #KeepItOn coalition demands that the Government of Tanzania ensure unhindered access to the internet during the upcoming elections.\n\nPress Release\n#KeepItOn in Tanzania: authorities must ensure connectivity during local elections\n21 Nov 2024\n\nPress Release\n\n#KeepItOn in Tanzania: authorities must ensure connectivity during local elections\n\n21 Nov 2024\n\nInternet Shutdowns\t\t\t\t\n\n\n\n\nInternet Shutdowns \n\n\n\t\t\t\t#KeepItOn: the Government of Tanzania and internet service providers must ensure open and secure internet access throughout the 2024 local elections\t\t\t\n\n21 Nov 2024\n • \nThe #KeepItOn coalition calls on authorities and ISPs in Tanzania to ensure internet access during the upcoming elections. \n\n\n\n\nPress Release\n#KeepItOn: the Government of Tanzania and internet service providers must ensure open and secure internet access throughout the 2024 local elections\n21 Nov 2024\n\n#KeepItOn: the Government of Tanzania and internet service providers must ensure open and secure internet access throughout the 2024 local elections\n\nInternet Shutdowns\t\t\t\t\n\n\n\n\nInternet Shutdowns \n\n\n\t\t\t\t#KeepItOn: the Government of Tanzania and internet service providers must ensure open and secure internet access throughout the 2024 local elections\t\t\t\n\n21 Nov 2024\n • \nThe #KeepItOn coalition calls on authorities and ISPs in Tanzania to ensure internet access during the upcoming elections.\n\nInternet Shutdowns\n\nInternet Shutdowns\n\nInternet Shutdowns \n\n\n\t\t\t\t#KeepItOn: the Government of Tanzania and internet service providers must ensure open and secure internet access throughout the 2024 local elections\t\t\t\n\n21 Nov 2024\n • \nThe #KeepItOn coalition calls on authorities and ISPs in Tanzania to ensure internet access during the upcoming elections.\n\nInternet Shutdowns\n\nInternet Shutdowns\n\n21 Nov 2024\n • \nThe #KeepItOn coalition calls on authorities and ISPs in Tanzania to ensure internet access during the upcoming elections.\n\nThe #KeepItOn coalition calls on authorities and ISPs in Tanzania to ensure internet access during the upcoming elections.\n\nPress Release\n#KeepItOn: the Government of Tanzania and internet service providers must ensure open and secure internet access throughout the 2024 local elections\n21 Nov 2024\n\nPress Release\n\n#KeepItOn: the Government of Tanzania and internet service providers must ensure open and secure internet access throughout the 2024 local elections\n\n21 Nov 2024\n\nConnectivity\t\t\t\t\n\n\n\n\nConnectivity \n\n\n\t\t\t\tAs Israel destroys infrastructure, will Lebanon be cut off from outside world?\t\t\t\n\n15 Nov 2024\n\n\n\n\nNews\nAs Israel destroys infrastructure, will Lebanon be cut off from outside world?\n\n\t\t\t\t\t\t\t\t\tThe New Arab ↗\t\t\t\t\t\t\t\n↗\n15 Nov 2024\n\nAs Israel destroys infrastructure, will Lebanon be cut off from outside world?\n\nConnectivity\t\t\t\t\n\n\n\n\nConnectivity \n\n\n\t\t\t\tAs Israel destroys infrastructure, will Lebanon be cut off from outside world?\t\t\t\n\n15 Nov 2024\n\nConnectivity\n\nConnectivity\n\nConnectivity \n\n\n\t\t\t\tAs Israel destroys infrastructure, will Lebanon be cut off from outside world?\t\t\t\n\n15 Nov 2024\n\nConnectivity\n\nConnectivity\n\n15 Nov 2024\n\nNews\nAs Israel destroys infrastructure, will Lebanon be cut off from outside world?\n\n\t\t\t\t\t\t\t\t\tThe New Arab ↗\t\t\t\t\t\t\t\n↗\n15 Nov 2024\n\nNews\n\nAs Israel destroys infrastructure, will Lebanon be cut off from outside world?\n\nThe New Arab ↗\n\n↗\n\n15 Nov 2024\n\nConnectivity\t\t\t\t\n\n\n\n\nConnectivity \n\n\n\t\t\t\tApple keeps killing VPN apps upon Russia’s orders – Amnezia VPN is the last victim\t\t\t\n\n4 Nov 2024\n\n\n\n\nNews\nApple keeps killing VPN apps upon Russia’s orders – Amnezia VPN is the last victim\n\n\t\t\t\t\t\t\t\t\tTechRadar ↗\t\t\t\t\t\t\t\n↗\n4 Nov 2024\n\nApple keeps killing VPN apps upon Russia’s orders – Amnezia VPN is the last victim\n\nConnectivity\t\t\t\t\n\n\n\n\nConnectivity \n\n\n\t\t\t\tApple keeps killing VPN apps upon Russia’s orders – Amnezia VPN is the last victim\t\t\t\n\n4 Nov 2024\n\nConnectivity\n\nConnectivity\n\nConnectivity \n\n\n\t\t\t\tApple keeps killing VPN apps upon Russia’s orders – Amnezia VPN is the last victim\t\t\t\n\n4 Nov 2024\n\nConnectivity\n\nConnectivity\n\n4 Nov 2024\n\nNews\nApple keeps killing VPN apps upon Russia’s orders – Amnezia VPN is the last victim\n\n\t\t\t\t\t\t\t\t\tTechRadar ↗\t\t\t\t\t\t\t\n↗\n4 Nov 2024\n\nNews\n\nApple keeps killing VPN apps upon Russia’s orders – Amnezia VPN is the last victim\n\nTechRadar ↗\n\n↗\n\n4 Nov 2024\n\nInternet Shutdowns\t\t\t\t\n\n\n\n\nInternet Shutdowns \n\n\n\t\t\t\t#KeepItOn Mauritius: global coalition urges first-time offender to end crackdown on social media\t\t\t\n\n1 Nov 2024\n\n\n\n\nPress Release\n#KeepItOn Mauritius: global coalition urges first-time offender to end crackdown on social media\n1 Nov 2024\n\n#KeepItOn Mauritius: global coalition urges first-time offender to end crackdown on social media\n\nInternet Shutdowns\t\t\t\t\n\n\n\n\nInternet Shutdowns \n\n\n\t\t\t\t#KeepItOn Mauritius: global coalition urges first-time offender to end crackdown on social media\t\t\t\n\n1 Nov 2024\n\nInternet Shutdowns\n\nInternet Shutdowns\n\nInternet Shutdowns \n\n\n\t\t\t\t#KeepItOn Mauritius: global coalition urges first-time offender to end crackdown on social media\t\t\t\n\n1 Nov 2024\n\nInternet Shutdowns\n\nInternet Shutdowns\n\n1 Nov 2024\n\nPress Release\n#KeepItOn Mauritius: global coalition urges first-time offender to end crackdown on social media\n1 Nov 2024\n\nPress Release\n\n#KeepItOn Mauritius: global coalition urges first-time offender to end crackdown on social media\n\n1 Nov 2024\n\nConnectivity\t\t\t\t\n\n\n\n\nConnectivity \n\n\n\t\t\t\tMyanmar residents struggle to overcome severe internet blackouts with Starlink\t\t\t\n\n23 Oct 2024\n\n\n\n\nNews\nMyanmar residents struggle to overcome severe internet blackouts with Starlink\n\n\t\t\t\t\t\t\t\t\tRest of World ↗\t\t\t\t\t\t\t\n↗\n23 Oct 2024\n\nMyanmar residents struggle to overcome severe internet blackouts with Starlink\n\nConnectivity\t\t\t\t\n\n\n\n\nConnectivity \n\n\n\t\t\t\tMyanmar residents struggle to overcome severe internet blackouts with Starlink\t\t\t\n\n23 Oct 2024\n\nConnectivity\n\nConnectivity\n\nConnectivity \n\n\n\t\t\t\tMyanmar residents struggle to overcome severe internet blackouts with Starlink\t\t\t\n\n23 Oct 2024\n\nConnectivity\n\nConnectivity\n\n23 Oct 2024\n\nNews\nMyanmar residents struggle to overcome severe internet blackouts with Starlink\n\n\t\t\t\t\t\t\t\t\tRest of World ↗\t\t\t\t\t\t\t\n↗\n23 Oct 2024\n\nNews\n\nMyanmar residents struggle to overcome severe internet blackouts with Starlink\n\nRest of World ↗\n\n↗\n\n23 Oct 2024\n\nConnectivity\t\t\t\t\n\n\n\n\nConnectivity \n\n\n\t\t\t\tستارلينك في اليمن: لماذا يعارض الحوثيون تفعيل الإنترنت الفضائي؟\t\t\t\n\n1 Oct 2024\n\n\n\n\nNews\nستارلينك في اليمن: لماذا يعارض الحوثيون تفعيل الإنترنت الفضائي؟\n\n\t\t\t\t\t\t\t\t\tBBC ↗\t\t\t\t\t\t\t\n↗\n1 Oct 2024\n\nستارلينك في اليمن: لماذا يعارض الحوثيون تفعيل الإنترنت الفضائي؟\n\nConnectivity\t\t\t\t\n\n\n\n\nConnectivity \n\n\n\t\t\t\tستارلينك في اليمن: لماذا يعارض الحوثيون تفعيل الإنترنت الفضائي؟\t\t\t\n\n1 Oct 2024\n\nConnectivity\n\nConnectivity\n\nConnectivity \n\n\n\t\t\t\tستارلينك في اليمن: لماذا يعارض الحوثيون تفعيل الإنترنت الفضائي؟\t\t\t\n\n1 Oct 2024\n\nConnectivity\n\nConnectivity\n\n1 Oct 2024\n\nNews\nستارلينك في اليمن: لماذا يعارض الحوثيون تفعيل الإنترنت الفضائي؟\n\n\t\t\t\t\t\t\t\t\tBBC ↗\t\t\t\t\t\t\t\n↗\n1 Oct 2024\n\nNews\n\nستارلينك في اليمن: لماذا يعارض الحوثيون تفعيل الإنترنت الفضائي؟\n\nBBC ↗\n\n↗\n\n1 Oct 2024\n\nInternet Shutdowns\t\t\t\t\n\n\n\n\nInternet Shutdowns \n\n\n\t\t\t\tJoint statement: Sudan has suffered in silence for over 500 days\t\t\t\n\n5 Sep 2024\n • \nAfter more than 500 days of brutal conflict in Sudan, the #KeepItOn coalition reiterates calls to reactivate telecommunication services.\n\n\n\n\nPress Release\nJoint statement: Sudan has suffered in silence for over 500 days\n5 Sep 2024\n\nJoint statement: Sudan has suffered in silence for over 500 days\n\nInternet Shutdowns\t\t\t\t\n\n\n\n\nInternet Shutdowns \n\n\n\t\t\t\tJoint statement: Sudan has suffered in silence for over 500 days\t\t\t\n\n5 Sep 2024\n • \nAfter more than 500 days of brutal conflict in Sudan, the #KeepItOn coalition reiterates calls to reactivate telecommunication services.\n\nInternet Shutdowns\n\nInternet Shutdowns\n\nInternet Shutdowns \n\n\n\t\t\t\tJoint statement: Sudan has suffered in silence for over 500 days\t\t\t\n\n5 Sep 2024\n • \nAfter more than 500 days of brutal conflict in Sudan, the #KeepItOn coalition reiterates calls to reactivate telecommunication services.\n\nInternet Shutdowns\n\nInternet Shutdowns\n\n5 Sep 2024\n • \nAfter more than 500 days of brutal conflict in Sudan, the #KeepItOn coalition reiterates calls to reactivate telecommunication services.\n\nAfter more than 500 days of brutal conflict in Sudan, the #KeepItOn coalition reiterates calls to reactivate telecommunication services.\n\nPress Release\nJoint statement: Sudan has suffered in silence for over 500 days\n5 Sep 2024\n\nPress Release\n\nJoint statement: Sudan has suffered in silence for over 500 days\n\n5 Sep 2024\n\nInternet Shutdowns\t\t\t\t\n\n\n\n\nInternet Shutdowns \n\n\n\t\t\t\tAfrica in 2023: internet shutdowns attack democracy\t\t\t\n\n26 Aug 2024\n\n\n\n\nPress Release\nAfrica in 2023: internet shutdowns attack democracy\n26 Aug 2024\n\nAfrica in 2023: internet shutdowns attack democracy\n\nInternet Shutdowns\t\t\t\t\n\n\n\n\nInternet Shutdowns \n\n\n\t\t\t\tAfrica in 2023: internet shutdowns attack democracy\t\t\t\n\n26 Aug 2024\n\nInternet Shutdowns\n\nInternet Shutdowns\n\nInternet Shutdowns \n\n\n\t\t\t\tAfrica in 2023: internet shutdowns attack democracy\t\t\t\n\n26 Aug 2024\n\nInternet Shutdowns\n\nInternet Shutdowns\n\n26 Aug 2024\n\nPress Release\nAfrica in 2023: internet shutdowns attack democracy\n26 Aug 2024\n\nPress Release\n\nAfrica in 2023: internet shutdowns attack democracy\n\n26 Aug 2024\n\nInternet Shutdowns\t\t\t\t\n\n\n\n\nInternet Shutdowns \n\n\n\t\t\t\t#KeepItOn in Annobón: Authorities in Equatorial Guinea must end internet shutdown and other human rights abuses\t\t\t\n\n13 Aug 2024\n • \nAccess Now and the #KeepItOn coalition are calling on authorities in Equatorial Guinea to immediately restore internet and telecom services in Annobón.\n\n\n\n\nPress Release\n#KeepItOn in Annobón: Authorities in Equatorial Guinea must end internet shutdown and other human rights abuses\n13 Aug 2024\n\n#KeepItOn in Annobón: Authorities in Equatorial Guinea must end internet shutdown and other human rights abuses\n\nInternet Shutdowns\t\t\t\t\n\n\n\n\nInternet Shutdowns \n\n\n\t\t\t\t#KeepItOn in Annobón: Authorities in Equatorial Guinea must end internet shutdown and other human rights abuses\t\t\t\n\n13 Aug 2024\n • \nAccess Now and the #KeepItOn coalition are calling on authorities in Equatorial Guinea to immediately restore internet and telecom services in Annobón.\n\nInternet Shutdowns\n\nInternet Shutdowns\n\nInternet Shutdowns \n\n\n\t\t\t\t#KeepItOn in Annobón: Authorities in Equatorial Guinea must end internet shutdown and other human rights abuses\t\t\t\n\n13 Aug 2024\n • \nAccess Now and the #KeepItOn coalition are calling on authorities in Equatorial Guinea to immediately restore internet and telecom services in Annobón.\n\nInternet Shutdowns\n\nInternet Shutdowns\n\n13 Aug 2024\n • \nAccess Now and the #KeepItOn coalition are calling on authorities in Equatorial Guinea to immediately restore internet and telecom services in Annobón.\n\nAccess Now and the #KeepItOn coalition are calling on authorities in Equatorial Guinea to immediately restore internet and telecom services in Annobón.\n\nPress Release\n#KeepItOn in Annobón: Authorities in Equatorial Guinea must end internet shutdown and other human rights abuses\n13 Aug 2024\n\nPress Release\n\n#KeepItOn in Annobón: Authorities in Equatorial Guinea must end internet shutdown and other human rights abuses\n\n13 Aug 2024\n\nInternet Shutdowns\t\t\t\t\n\n\n\n\nInternet Shutdowns \n\n\n\t\t\t\t#KeepItOn en Annobón: Las autoridades de Guinea Ecuatorial deben poner fin al corte de internet y otros abusos a los derechos humanos\t\t\t\n\n13 Aug 2024\n • \nLa coalición #KeepItOn instan a las autoridades de Guinea Ecuatorial a restablecer de inmediato el acceso a internet en Annobón.\n\n\n\n\nPress Release\n#KeepItOn en Annobón: Las autoridades de Guinea Ecuatorial deben poner fin al corte de internet y otros abusos a los derechos humanos\n13 Aug 2024\n\n#KeepItOn en Annobón: Las autoridades de Guinea Ecuatorial deben poner fin al corte de internet y otros abusos a los derechos humanos\n\nInternet Shutdowns\t\t\t\t\n\n\n\n\nInternet Shutdowns \n\n\n\t\t\t\t#KeepItOn en Annobón: Las autoridades de Guinea Ecuatorial deben poner fin al corte de internet y otros abusos a los derechos humanos\t\t\t\n\n13 Aug 2024\n • \nLa coalición #KeepItOn instan a las autoridades de Guinea Ecuatorial a restablecer de inmediato el acceso a internet en Annobón.\n\nInternet Shutdowns\n\nInternet Shutdowns\n\nInternet Shutdowns \n\n\n\t\t\t\t#KeepItOn en Annobón: Las autoridades de Guinea Ecuatorial deben poner fin al corte de internet y otros abusos a los derechos humanos\t\t\t\n\n13 Aug 2024\n • \nLa coalición #KeepItOn instan a las autoridades de Guinea Ecuatorial a restablecer de inmediato el acceso a internet en Annobón.\n\nInternet Shutdowns\n\nInternet Shutdowns\n\n13 Aug 2024\n • \nLa coalición #KeepItOn instan a las autoridades de Guinea Ecuatorial a restablecer de inmediato el acceso a internet en Annobón.\n\nLa coalición #KeepItOn instan a las autoridades de Guinea Ecuatorial a restablecer de inmediato el acceso a internet en Annobón.\n\nPress Release\n#KeepItOn en Annobón: Las autoridades de Guinea Ecuatorial deben poner fin al corte de internet y otros abusos a los derechos humanos\n13 Aug 2024\n\nPress Release\n\n#KeepItOn en Annobón: Las autoridades de Guinea Ecuatorial deben poner fin al corte de internet y otros abusos a los derechos humanos\n\n13 Aug 2024\n\nHelp keep the internet open and secure.\nSubscribe to our action alerts and weekly newsletter\n\"*\" indicates required fields\n\nThis field is hidden when viewing the form\n\nSubscribe to Access Express\nThis field is hidden when viewing the form\n\nSubscribe to Action Alerts\nName\n\n\nFirst\n\n\n\nLast\n\nEmail*\n\nCountryCountryAfghanistanÅland IslandsAlbaniaAlgeriaAmerican SamoaAndorraAngolaAnguillaAntigua and BarbudaArgentinaArmeniaArubaAustraliaAustriaAzerbaijanBahamasBahrainBangladeshBarbadosBelarusBelgiumBelizeBeninBermudaBhutanBoliviaBonaire, Sint Eustatius and SabaBosnia and HerzegovinaBotswanaBrazilBritish Indian Ocean TerritoryBritish Virgin IslandsBruneiBulgariaBurkina FasoBurundiCambodiaCameroonCanadaCape VerdeCayman IslandsCentral African RepublicChadChileChinaChristmas IslandColombiaComorosCook IslandsCosta RicaCôte d'IvoireCroatiaCubaCuraçaoCyprusCzech RepublicDemocratic Republic of the CongoDenmarkDjiboutiDominicaDominican RepublicEast TimorEcuadorEgyptEl SalvadorEquatorial GuineaEritreaEstoniaEswatiniEthiopiaFalkland IslandsFaroe IslandsFijiFinlandFranceFrench GuianaFrench PolynesiaFrench Southern TerritoriesGabonGeorgiaGermanyGhanaGibraltarGreeceGreenlandGrenadaGuadeloupeGuamGuatemalaGuernseyGuineaGuinea-BissauGuyanaHaitiHondurasHong KongHungaryIcelandIndiaIndonesiaIranIraqIrelandIsraelItalyJamaicaJapanJordanKazakhstanKenyaKiribatiKosovoKuwaitKyrgyzstanLaosLatviaLebanonLesothoLiberiaLibyaLiechtensteinLithuaniaLuxembourgMacauMadagascarMalawiMalaysiaMaldivesMaliMaltaMarshall IslandsMartiniqueMauritaniaMauritiusMayotteMexicoMicronesiaMoldovaMonacoMongoliaMontenegroMontserratMoroccoMozambiqueMyanmarNamibiaNauruNepalNetherlands AntillesNew CaledoniaNew ZealandNicaraguaNigerNigeriaNiueNorfolk IslandNorth KoreaNorth MacedoniaNorthern Mariana IslandsNorwayOmanPakistanPalauPalestinePanamaPapua New GuineaParaguayPeruPhilippinesPitcairn IslandPolandPortugalPuerto RicoQatarRepublic of the CongoReunionRomaniaRussiaRwandaSaint BarthélemySaint Kitts and NevisSaint LuciaSaint Vincent and the GrenadinesSamoaSan MarinoSão Tomé and PríncipeSaudi ArabiaSenegalSerbiaSeychellesSierra LeoneSingaporeSlovakiaSloveniaSolomon IslandsSomaliaSomalilandSouth AfricaSouth KoreaSouth SudanSpainSri LankaSt. HelenaSt. Pierre and MiquelonSudanSurinameSwedenSwitzerlandSyriaTaiwanTajikistanTanzaniaThailandThe GambiaThe NetherlandsTogoTokelauTongaTrinidad and TobagoTunisiaTurkeyTurkmenistanTurks and Caicos IslandsTuvaluUgandaUkraineUnited Arab EmiratesUnited KingdomUnited StatesUruguayUzbekistanVanuatuVatican CityVenezuelaVietnamVirgin Islands (U.S.)Wallis and Futuna IslandsWestern SaharaYemenZambiaZimbabwePostal CodeEmailThis field is for validation purposes and should be left unchanged.\n \n\n\n\n\n\n\n\n\n\n\n\n\n\n\n\nYour info is secure with us\n\nHelp keep the internet open and secure.\nSubscribe to our action alerts and weekly newsletter\n\"*\" indicates required fields\n\nThis field is hidden when viewing the form\n\nSubscribe to Access Express\nThis field is hidden when viewing the form\n\nSubscribe to Action Alerts\nName\n\n\nFirst\n\n\n\nLast\n\nEmail*\n\nCountryCountryAfghanistanÅland IslandsAlbaniaAlgeriaAmerican SamoaAndorraAngolaAnguillaAntigua and BarbudaArgentinaArmeniaArubaAustraliaAustriaAzerbaijanBahamasBahrainBangladeshBarbadosBelarusBelgiumBelizeBeninBermudaBhutanBoliviaBonaire, Sint Eustatius and SabaBosnia and HerzegovinaBotswanaBrazilBritish Indian Ocean TerritoryBritish Virgin IslandsBruneiBulgariaBurkina FasoBurundiCambodiaCameroonCanadaCape VerdeCayman IslandsCentral African RepublicChadChileChinaChristmas IslandColombiaComorosCook IslandsCosta RicaCôte d'IvoireCroatiaCubaCuraçaoCyprusCzech RepublicDemocratic Republic of the CongoDenmarkDjiboutiDominicaDominican RepublicEast TimorEcuadorEgyptEl SalvadorEquatorial GuineaEritreaEstoniaEswatiniEthiopiaFalkland IslandsFaroe IslandsFijiFinlandFranceFrench GuianaFrench PolynesiaFrench Southern TerritoriesGabonGeorgiaGermanyGhanaGibraltarGreeceGreenlandGrenadaGuadeloupeGuamGuatemalaGuernseyGuineaGuinea-BissauGuyanaHaitiHondurasHong KongHungaryIcelandIndiaIndonesiaIranIraqIrelandIsraelItalyJamaicaJapanJordanKazakhstanKenyaKiribatiKosovoKuwaitKyrgyzstanLaosLatviaLebanonLesothoLiberiaLibyaLiechtensteinLithuaniaLuxembourgMacauMadagascarMalawiMalaysiaMaldivesMaliMaltaMarshall IslandsMartiniqueMauritaniaMauritiusMayotteMexicoMicronesiaMoldovaMonacoMongoliaMontenegroMontserratMoroccoMozambiqueMyanmarNamibiaNauruNepalNetherlands AntillesNew CaledoniaNew ZealandNicaraguaNigerNigeriaNiueNorfolk IslandNorth KoreaNorth MacedoniaNorthern Mariana IslandsNorwayOmanPakistanPalauPalestinePanamaPapua New GuineaParaguayPeruPhilippinesPitcairn IslandPolandPortugalPuerto RicoQatarRepublic of the CongoReunionRomaniaRussiaRwandaSaint BarthélemySaint Kitts and NevisSaint LuciaSaint Vincent and the GrenadinesSamoaSan MarinoSão Tomé and PríncipeSaudi ArabiaSenegalSerbiaSeychellesSierra LeoneSingaporeSlovakiaSloveniaSolomon IslandsSomaliaSomalilandSouth AfricaSouth KoreaSouth SudanSpainSri LankaSt. HelenaSt. Pierre and MiquelonSudanSurinameSwedenSwitzerlandSyriaTaiwanTajikistanTanzaniaThailandThe GambiaThe NetherlandsTogoTokelauTongaTrinidad and TobagoTunisiaTurkeyTurkmenistanTurks and Caicos IslandsTuvaluUgandaUkraineUnited Arab EmiratesUnited KingdomUnited StatesUruguayUzbekistanVanuatuVatican CityVenezuelaVietnamVirgin Islands (U.S.)Wallis and Futuna IslandsWestern SaharaYemenZambiaZimbabwePostal CodeEmailThis field is for validation purposes and should be left unchanged.\n \n\n\n\n\n\n\n\n\n\n\n\n\n\n\n\nYour info is secure with us\n\nHelp keep the internet open and secure.\nSubscribe to our action alerts and weekly newsletter\n\"*\" indicates required fields\n\nThis field is hidden when viewing the form\n\nSubscribe to Access Express\nThis field is hidden when viewing the form\n\nSubscribe to Action Alerts\nName\n\n\nFirst\n\n\n\nLast\n\nEmail*\n\nCountryCountryAfghanistanÅland IslandsAlbaniaAlgeriaAmerican SamoaAndorraAngolaAnguillaAntigua and BarbudaArgentinaArmeniaArubaAustraliaAustriaAzerbaijanBahamasBahrainBangladeshBarbadosBelarusBelgiumBelizeBeninBermudaBhutanBoliviaBonaire, Sint Eustatius and SabaBosnia and HerzegovinaBotswanaBrazilBritish Indian Ocean TerritoryBritish Virgin IslandsBruneiBulgariaBurkina FasoBurundiCambodiaCameroonCanadaCape VerdeCayman IslandsCentral African RepublicChadChileChinaChristmas IslandColombiaComorosCook IslandsCosta RicaCôte d'IvoireCroatiaCubaCuraçaoCyprusCzech RepublicDemocratic Republic of the CongoDenmarkDjiboutiDominicaDominican RepublicEast TimorEcuadorEgyptEl SalvadorEquatorial GuineaEritreaEstoniaEswatiniEthiopiaFalkland IslandsFaroe IslandsFijiFinlandFranceFrench GuianaFrench PolynesiaFrench Southern TerritoriesGabonGeorgiaGermanyGhanaGibraltarGreeceGreenlandGrenadaGuadeloupeGuamGuatemalaGuernseyGuineaGuinea-BissauGuyanaHaitiHondurasHong KongHungaryIcelandIndiaIndonesiaIranIraqIrelandIsraelItalyJamaicaJapanJordanKazakhstanKenyaKiribatiKosovoKuwaitKyrgyzstanLaosLatviaLebanonLesothoLiberiaLibyaLiechtensteinLithuaniaLuxembourgMacauMadagascarMalawiMalaysiaMaldivesMaliMaltaMarshall IslandsMartiniqueMauritaniaMauritiusMayotteMexicoMicronesiaMoldovaMonacoMongoliaMontenegroMontserratMoroccoMozambiqueMyanmarNamibiaNauruNepalNetherlands AntillesNew CaledoniaNew ZealandNicaraguaNigerNigeriaNiueNorfolk IslandNorth KoreaNorth MacedoniaNorthern Mariana IslandsNorwayOmanPakistanPalauPalestinePanamaPapua New GuineaParaguayPeruPhilippinesPitcairn IslandPolandPortugalPuerto RicoQatarRepublic of the CongoReunionRomaniaRussiaRwandaSaint BarthélemySaint Kitts and NevisSaint LuciaSaint Vincent and the GrenadinesSamoaSan MarinoSão Tomé and PríncipeSaudi ArabiaSenegalSerbiaSeychellesSierra LeoneSingaporeSlovakiaSloveniaSolomon IslandsSomaliaSomalilandSouth AfricaSouth KoreaSouth SudanSpainSri LankaSt. HelenaSt. Pierre and MiquelonSudanSurinameSwedenSwitzerlandSyriaTaiwanTajikistanTanzaniaThailandThe GambiaThe NetherlandsTogoTokelauTongaTrinidad and TobagoTunisiaTurkeyTurkmenistanTurks and Caicos IslandsTuvaluUgandaUkraineUnited Arab EmiratesUnited KingdomUnited StatesUruguayUzbekistanVanuatuVatican CityVenezuelaVietnamVirgin Islands (U.S.)Wallis and Futuna IslandsWestern SaharaYemenZambiaZimbabwePostal CodeEmailThis field is for validation purposes and should be left unchanged.\n\nHelp keep the internet open and secure.\nSubscribe to our action alerts and weekly newsletter\n\"*\" indicates required fields\n\nSubscribe to our action alerts and weekly newsletter\n\n\"*\" indicates required fields\n\nThis field is hidden when viewing the form\n\nSubscribe to Access Express\nThis field is hidden when viewing the form\n\nSubscribe to Action Alerts\nName\n\n\nFirst\n\n\n\nLast\n\nEmail*\n\nCountryCountryAfghanistanÅland IslandsAlbaniaAlgeriaAmerican SamoaAndorraAngolaAnguillaAntigua and BarbudaArgentinaArmeniaArubaAustraliaAustriaAzerbaijanBahamasBahrainBangladeshBarbadosBelarusBelgiumBelizeBeninBermudaBhutanBoliviaBonaire, Sint Eustatius and SabaBosnia and HerzegovinaBotswanaBrazilBritish Indian Ocean TerritoryBritish Virgin IslandsBruneiBulgariaBurkina FasoBurundiCambodiaCameroonCanadaCape VerdeCayman IslandsCentral African RepublicChadChileChinaChristmas IslandColombiaComorosCook IslandsCosta RicaCôte d'IvoireCroatiaCubaCuraçaoCyprusCzech RepublicDemocratic Republic of the CongoDenmarkDjiboutiDominicaDominican RepublicEast TimorEcuadorEgyptEl SalvadorEquatorial GuineaEritreaEstoniaEswatiniEthiopiaFalkland IslandsFaroe IslandsFijiFinlandFranceFrench GuianaFrench PolynesiaFrench Southern TerritoriesGabonGeorgiaGermanyGhanaGibraltarGreeceGreenlandGrenadaGuadeloupeGuamGuatemalaGuernseyGuineaGuinea-BissauGuyanaHaitiHondurasHong KongHungaryIcelandIndiaIndonesiaIranIraqIrelandIsraelItalyJamaicaJapanJordanKazakhstanKenyaKiribatiKosovoKuwaitKyrgyzstanLaosLatviaLebanonLesothoLiberiaLibyaLiechtensteinLithuaniaLuxembourgMacauMadagascarMalawiMalaysiaMaldivesMaliMaltaMarshall IslandsMartiniqueMauritaniaMauritiusMayotteMexicoMicronesiaMoldovaMonacoMongoliaMontenegroMontserratMoroccoMozambiqueMyanmarNamibiaNauruNepalNetherlands AntillesNew CaledoniaNew ZealandNicaraguaNigerNigeriaNiueNorfolk IslandNorth KoreaNorth MacedoniaNorthern Mariana IslandsNorwayOmanPakistanPalauPalestinePanamaPapua New GuineaParaguayPeruPhilippinesPitcairn IslandPolandPortugalPuerto RicoQatarRepublic of the CongoReunionRomaniaRussiaRwandaSaint BarthélemySaint Kitts and NevisSaint LuciaSaint Vincent and the GrenadinesSamoaSan MarinoSão Tomé and PríncipeSaudi ArabiaSenegalSerbiaSeychellesSierra LeoneSingaporeSlovakiaSloveniaSolomon IslandsSomaliaSomalilandSouth AfricaSouth KoreaSouth SudanSpainSri LankaSt. HelenaSt. Pierre and MiquelonSudanSurinameSwedenSwitzerlandSyriaTaiwanTajikistanTanzaniaThailandThe GambiaThe NetherlandsTogoTokelauTongaTrinidad and TobagoTunisiaTurkeyTurkmenistanTurks and Caicos IslandsTuvaluUgandaUkraineUnited Arab EmiratesUnited KingdomUnited StatesUruguayUzbekistanVanuatuVatican CityVenezuelaVietnamVirgin Islands (U.S.)Wallis and Futuna IslandsWestern SaharaYemenZambiaZimbabwePostal CodeEmailThis field is for validation purposes and should be left unchanged.\n\nThis field is hidden when viewing the form\n\nSubscribe to Access Express\nThis field is hidden when viewing the form\n\nSubscribe to Action Alerts\nName\n\n\nFirst\n\n\n\nLast\n\nEmail*\n\nCountryCountryAfghanistanÅland IslandsAlbaniaAlgeriaAmerican SamoaAndorraAngolaAnguillaAntigua and BarbudaArgentinaArmeniaArubaAustraliaAustriaAzerbaijanBahamasBahrainBangladeshBarbadosBelarusBelgiumBelizeBeninBermudaBhutanBoliviaBonaire, Sint Eustatius and SabaBosnia and HerzegovinaBotswanaBrazilBritish Indian Ocean TerritoryBritish Virgin IslandsBruneiBulgariaBurkina FasoBurundiCambodiaCameroonCanadaCape VerdeCayman IslandsCentral African RepublicChadChileChinaChristmas IslandColombiaComorosCook IslandsCosta RicaCôte d'IvoireCroatiaCubaCuraçaoCyprusCzech RepublicDemocratic Republic of the CongoDenmarkDjiboutiDominicaDominican RepublicEast TimorEcuadorEgyptEl SalvadorEquatorial GuineaEritreaEstoniaEswatiniEthiopiaFalkland IslandsFaroe IslandsFijiFinlandFranceFrench GuianaFrench PolynesiaFrench Southern TerritoriesGabonGeorgiaGermanyGhanaGibraltarGreeceGreenlandGrenadaGuadeloupeGuamGuatemalaGuernseyGuineaGuinea-BissauGuyanaHaitiHondurasHong KongHungaryIcelandIndiaIndonesiaIranIraqIrelandIsraelItalyJamaicaJapanJordanKazakhstanKenyaKiribatiKosovoKuwaitKyrgyzstanLaosLatviaLebanonLesothoLiberiaLibyaLiechtensteinLithuaniaLuxembourgMacauMadagascarMalawiMalaysiaMaldivesMaliMaltaMarshall IslandsMartiniqueMauritaniaMauritiusMayotteMexicoMicronesiaMoldovaMonacoMongoliaMontenegroMontserratMoroccoMozambiqueMyanmarNamibiaNauruNepalNetherlands AntillesNew CaledoniaNew ZealandNicaraguaNigerNigeriaNiueNorfolk IslandNorth KoreaNorth MacedoniaNorthern Mariana IslandsNorwayOmanPakistanPalauPalestinePanamaPapua New GuineaParaguayPeruPhilippinesPitcairn IslandPolandPortugalPuerto RicoQatarRepublic of the CongoReunionRomaniaRussiaRwandaSaint BarthélemySaint Kitts and NevisSaint LuciaSaint Vincent and the GrenadinesSamoaSan MarinoSão Tomé and PríncipeSaudi ArabiaSenegalSerbiaSeychellesSierra LeoneSingaporeSlovakiaSloveniaSolomon IslandsSomaliaSomalilandSouth AfricaSouth KoreaSouth SudanSpainSri LankaSt. HelenaSt. Pierre and MiquelonSudanSurinameSwedenSwitzerlandSyriaTaiwanTajikistanTanzaniaThailandThe GambiaThe NetherlandsTogoTokelauTongaTrinidad and TobagoTunisiaTurkeyTurkmenistanTurks and Caicos IslandsTuvaluUgandaUkraineUnited Arab EmiratesUnited KingdomUnited StatesUruguayUzbekistanVanuatuVatican CityVenezuelaVietnamVirgin Islands (U.S.)Wallis and Futuna IslandsWestern SaharaYemenZambiaZimbabwePostal CodeEmailThis field is for validation purposes and should be left unchanged.\n\nThis field is hidden when viewing the form\n\nSubscribe to Access Express\n\nSubscribe to Access Express\n\nSubscribe to Access Express\n\nThis field is hidden when viewing the form\n\nSubscribe to Action Alerts\n\nSubscribe to Action Alerts\n\nSubscribe to Action Alerts\n\nFirst\n\n\n\nLast\n\nEmail*\n\nCountryCountryAfghanistanÅland IslandsAlbaniaAlgeriaAmerican SamoaAndorraAngolaAnguillaAntigua and BarbudaArgentinaArmeniaArubaAustraliaAustriaAzerbaijanBahamasBahrainBangladeshBarbadosBelarusBelgiumBelizeBeninBermudaBhutanBoliviaBonaire, Sint Eustatius and SabaBosnia and HerzegovinaBotswanaBrazilBritish Indian Ocean TerritoryBritish Virgin IslandsBruneiBulgariaBurkina FasoBurundiCambodiaCameroonCanadaCape VerdeCayman IslandsCentral African RepublicChadChileChinaChristmas IslandColombiaComorosCook IslandsCosta RicaCôte d'IvoireCroatiaCubaCuraçaoCyprusCzech RepublicDemocratic Republic of the CongoDenmarkDjiboutiDominicaDominican RepublicEast TimorEcuadorEgyptEl SalvadorEquatorial GuineaEritreaEstoniaEswatiniEthiopiaFalkland IslandsFaroe IslandsFijiFinlandFranceFrench GuianaFrench PolynesiaFrench Southern TerritoriesGabonGeorgiaGermanyGhanaGibraltarGreeceGreenlandGrenadaGuadeloupeGuamGuatemalaGuernseyGuineaGuinea-BissauGuyanaHaitiHondurasHong KongHungaryIcelandIndiaIndonesiaIranIraqIrelandIsraelItalyJamaicaJapanJordanKazakhstanKenyaKiribatiKosovoKuwaitKyrgyzstanLaosLatviaLebanonLesothoLiberiaLibyaLiechtensteinLithuaniaLuxembourgMacauMadagascarMalawiMalaysiaMaldivesMaliMaltaMarshall IslandsMartiniqueMauritaniaMauritiusMayotteMexicoMicronesiaMoldovaMonacoMongoliaMontenegroMontserratMoroccoMozambiqueMyanmarNamibiaNauruNepalNetherlands AntillesNew CaledoniaNew ZealandNicaraguaNigerNigeriaNiueNorfolk IslandNorth KoreaNorth MacedoniaNorthern Mariana IslandsNorwayOmanPakistanPalauPalestinePanamaPapua New GuineaParaguayPeruPhilippinesPitcairn IslandPolandPortugalPuerto RicoQatarRepublic of the CongoReunionRomaniaRussiaRwandaSaint BarthélemySaint Kitts and NevisSaint LuciaSaint Vincent and the GrenadinesSamoaSan MarinoSão Tomé and PríncipeSaudi ArabiaSenegalSerbiaSeychellesSierra LeoneSingaporeSlovakiaSloveniaSolomon IslandsSomaliaSomalilandSouth AfricaSouth KoreaSouth SudanSpainSri LankaSt. HelenaSt. Pierre and MiquelonSudanSurinameSwedenSwitzerlandSyriaTaiwanTajikistanTanzaniaThailandThe GambiaThe NetherlandsTogoTokelauTongaTrinidad and TobagoTunisiaTurkeyTurkmenistanTurks and Caicos IslandsTuvaluUgandaUkraineUnited Arab EmiratesUnited KingdomUnited StatesUruguayUzbekistanVanuatuVatican CityVenezuelaVietnamVirgin Islands (U.S.)Wallis and Futuna IslandsWestern SaharaYemenZambiaZimbabwe\n\nCountryAfghanistanÅland IslandsAlbaniaAlgeriaAmerican SamoaAndorraAngolaAnguillaAntigua and BarbudaArgentinaArmeniaArubaAustraliaAustriaAzerbaijanBahamasBahrainBangladeshBarbadosBelarusBelgiumBelizeBeninBermudaBhutanBoliviaBonaire, Sint Eustatius and SabaBosnia and HerzegovinaBotswanaBrazilBritish Indian Ocean TerritoryBritish Virgin IslandsBruneiBulgariaBurkina FasoBurundiCambodiaCameroonCanadaCape VerdeCayman IslandsCentral African RepublicChadChileChinaChristmas IslandColombiaComorosCook IslandsCosta RicaCôte d'IvoireCroatiaCubaCuraçaoCyprusCzech RepublicDemocratic Republic of the CongoDenmarkDjiboutiDominicaDominican RepublicEast TimorEcuadorEgyptEl SalvadorEquatorial GuineaEritreaEstoniaEswatiniEthiopiaFalkland IslandsFaroe IslandsFijiFinlandFranceFrench GuianaFrench PolynesiaFrench Southern TerritoriesGabonGeorgiaGermanyGhanaGibraltarGreeceGreenlandGrenadaGuadeloupeGuamGuatemalaGuernseyGuineaGuinea-BissauGuyanaHaitiHondurasHong KongHungaryIcelandIndiaIndonesiaIranIraqIrelandIsraelItalyJamaicaJapanJordanKazakhstanKenyaKiribatiKosovoKuwaitKyrgyzstanLaosLatviaLebanonLesothoLiberiaLibyaLiechtensteinLithuaniaLuxembourgMacauMadagascarMalawiMalaysiaMaldivesMaliMaltaMarshall IslandsMartiniqueMauritaniaMauritiusMayotteMexicoMicronesiaMoldovaMonacoMongoliaMontenegroMontserratMoroccoMozambiqueMyanmarNamibiaNauruNepalNetherlands AntillesNew CaledoniaNew ZealandNicaraguaNigerNigeriaNiueNorfolk IslandNorth KoreaNorth MacedoniaNorthern Mariana IslandsNorwayOmanPakistanPalauPalestinePanamaPapua New GuineaParaguayPeruPhilippinesPitcairn IslandPolandPortugalPuerto RicoQatarRepublic of the CongoReunionRomaniaRussiaRwandaSaint BarthélemySaint Kitts and NevisSaint LuciaSaint Vincent and the GrenadinesSamoaSan MarinoSão Tomé and PríncipeSaudi ArabiaSenegalSerbiaSeychellesSierra LeoneSingaporeSlovakiaSloveniaSolomon IslandsSomaliaSomalilandSouth AfricaSouth KoreaSouth SudanSpainSri LankaSt. HelenaSt. Pierre and MiquelonSudanSurinameSwedenSwitzerlandSyriaTaiwanTajikistanTanzaniaThailandThe GambiaThe NetherlandsTogoTokelauTongaTrinidad and TobagoTunisiaTurkeyTurkmenistanTurks and Caicos IslandsTuvaluUgandaUkraineUnited Arab EmiratesUnited KingdomUnited StatesUruguayUzbekistanVanuatuVatican CityVenezuelaVietnamVirgin Islands (U.S.)Wallis and Futuna IslandsWestern SaharaYemenZambiaZimbabwe\n\nPostal Code\n\nEmailThis field is for validation purposes and should be left unchanged.\n\nThis field is for validation purposes and should be left unchanged.\n\nYour info is secure with us",
  "date": "",
  "source_type": "other",
  "extracted_at": "2025-04-07T13:46:33.776765",
  "metadata": {
    "description": "Equitable Internet Access For All Today, affordable and meaningful access to the internet is an essential enabler of human rights. We advocate for",
    "og:type": "article",
    "og:site_name": "Access Now"
  },
  "relevance_score": 0.3166666666666667,
  "summary": "Press Release\n#KeepItOn in Tanzania: authorities must ensure connectivity during local elections\n21 Nov 2024\n\n#KeepItOn in Tanzania: authorities must ensure connectivity during local elections\n\n\n\n\n\n\n\n\n\n\t\t\t\t\tInternet Shutdowns\t\t\t\t\n\n\n\n\nInternet Shutdowns \n\n\n\t\t\t\t#KeepItOn: the Government of Tanzania and internet service providers must ensure open and secure internet access throughout the 2024 local elections\t\t\t\n\n21 Nov 2024\n • \nThe #KeepItOn coalition calls on authorities and ISPs in Tanzania to ensure internet access during the upcoming elections. Press Release\n#KeepItOn: the Government of Tanzania and internet service providers must ensure open and secure internet access throughout the 2024 local elections\n21 Nov 2024\n\n#KeepItOn: the Government of Tanzania and internet service providers must ensure open and secure internet access throughout the 2024 local elections\n\n\n\n\n\n\n\n\n\n\t\t\t\t\tConnectivity\t\t\t\t\n\n\n\n\nConnectivity \n\n\n\t\t\t\tAs Israel destroys infrastructure, will Lebanon be cut off from outside world? Connectivity\t\t\t\t\n\n\n\n\nConnectivity \n\n\n\t\t\t\tApple keeps killing VPN apps upon Russia’s orders – Amnezia VPN is the last victim\t\t\t\n\n4 Nov 2024\n\n\n\n\nNews\nApple keeps killing VPN apps upon Russia’s orders – Amnezia VPN is the last victim\n\n\t\t\t\t\t\t\t\t\tTechRadar ↗\t\t\t\t\t\t\t\n↗\n4 Nov 2024\n\nApple keeps killing VPN apps upon Russia’s orders – Amnezia VPN is the last victim\n\n\n\n\n\n\n\n\n\n\t\t\t\t\tInternet Shutdowns\t\t\t\t\n\n\n\n\nInternet Shutdowns \n\n\n\t\t\t\t#KeepItOn Mauritius: global coalition urges first-time offender to end crackdown on social media\t\t\t\n\n1 Nov 2024\n\n\n\n\nPress Release\n#KeepItOn Mauritius: global coalition urges first-time offender to end crackdown on social media\n1 Nov 2024\n\n#KeepItOn Mauritius: global coalition urges first-time offender to end crackdown on social media\n\n\n\n\n\n\n\n\n\n\t\t\t\t\tConnectivity\t\t\t\t\n\n\n\n\nConnectivity \n\n\n\t\t\t\tMyanmar residents struggle to overcome severe internet blackouts with Starlink\t\t\t\n\n23 Oct 2024\n\n\n\n\nNews\nMyanmar residents struggle to overcome severe internet blackouts with Starlink\n\n\t\t\t\t\t\t\t\t\tRest of World ↗\t\t\t\t\t\t\t\n↗\n23 Oct 2024\n\nMyanmar residents struggle to overcome severe internet blackouts with Starlink\n\n\n\n\n\n\n\n\n\n\t\t\t\t\tConnectivity\t\t\t\t\n\n\n\n\nConnectivity \n\n\n\t\t\t\tستارلينك في اليمن: لماذا يعارض الحوثيون تفعيل الإنترنت الفضائي؟\t\t\t\n\n1 Oct 2024\n\n\n\n\nNews\nستارلينك في اليمن: لماذا يعارض الحوثيون تفعيل الإنترنت الفضائي؟\n\n\t\t\t\t\t\t\t\t\tBBC ↗\t\t\t\t\t\t\t\n↗\n1 Oct 2024\n\nستارلينك في اليمن: لماذا يعارض الحوثيون تفعيل الإنترنت الفضائي؟\n\n\n\n\n\n\n\n\n\n\t\t\t\t\tInternet Shutdowns\t\t\t\t\n\n\n\n\nInternet Shutdowns \n\n\n\t\t\t\tJoint statement: Sudan has suffered in silence for over 500 days\t\t\t\n\n5 Sep 2024\n • \nAfter more than 500 days of brutal conflict in Sudan, the #KeepItOn coalition reiterates calls to reactivate telecommunication services. Press Release\nJoint statement: Sudan has suffered in silence for over 500 days\n5 Sep 2024\n\nJoint statement: Sudan has suffered in silence for over 500 days\n\n\n\n\n\n\n\n\n\n\t\t\t\t\tInternet Shutdowns\t\t\t\t\n\n\n\n\nInternet Shutdowns \n\n\n\t\t\t\tAfrica in 2023: internet shutdowns attack democracy\t\t\t\n\n26 Aug 2024\n\n\n\n\nPress Release\nAfrica in 2023: internet shutdowns attack democracy\n26 Aug 2024\n\nAfrica in 2023: internet shutdowns attack democracy\n\n\n\n\n\n\n\n\n\n\t\t\t\t\tInternet Shutdowns\t\t\t\t\n\n\n\n\nInternet Shutdowns \n\n\n\t\t\t\t#KeepItOn in Annobón: Authorities in Equatorial Guinea must end internet shutdown and other human rights abuses\t\t\t\n\n13 Aug 2024\n • \nAccess Now and the #KeepItOn coalition are calling on authorities in Equatorial Guinea to immediately restore internet and telecom services in Annobón. Press Release\n#KeepItOn in Annobón: Authorities in Equatorial Guinea must end internet shutdown and other human rights abuses\n13 Aug 2024\n\n#KeepItOn in Annobón: Authorities in Equatorial Guinea must end internet shutdown and other human rights abuses\n\n\n\n\n\n\n\n\n\n\t\t\t\t\tInternet Shutdowns\t\t\t\t\n\n\n\n\nInternet Shutdowns \n\n\n\t\t\t\t#KeepItOn en Annobón: Las autoridades de Guinea Ecuatorial deben poner fin al corte de internet y otros abusos a los derechos humanos\t\t\t\n\n13 Aug 2024\n • \nLa coalición #KeepItOn instan a las autoridades de Guinea Ecuatorial a restablecer de inmediato el acceso a internet en Annobón. Press Release\n#KeepItOn in Tanzania: authorities must ensure connectivity during local elections\n21 Nov 2024\n\n#KeepItOn in Tanzania: authorities must ensure connectivity during local elections\n\n\n\n\n\n\n\n\n\n\t\t\t\t\tInternet Shutdowns\t\t\t\t\n\n\n\n\nInternet Shutdowns \n\n\n\t\t\t\t#KeepItOn: the Government of Tanzania and internet service providers must ensure open and secure internet access throughout the 2024 local elections\t\t\t\n\n21 Nov 2024\n • \nThe #KeepItOn coalition calls on authorities and ISPs in Tanzania to ensure internet access during the upcoming elections. Press Release\n#KeepItOn: the Government of Tanzania and internet service providers must ensure open and secure internet access throughout the 2024 local elections\n21 Nov 2024\n\n#KeepItOn: the Government of Tanzania and internet service providers must ensure open and secure internet access throughout the 2024 local elections\n\n\n\n\n\n\n\n\n\n\t\t\t\t\tConnectivity\t\t\t\t\n\n\n\n\nConnectivity \n\n\n\t\t\t\tAs Israel destroys infrastructure, will Lebanon be cut off from outside world? Connectivity\t\t\t\t\n\n\n\n\nConnectivity \n\n\n\t\t\t\tApple keeps killing VPN apps upon Russia’s orders – Amnezia VPN is the last victim\t\t\t\n\n4 Nov 2024\n\n\n\n\nNews\nApple keeps killing VPN apps upon Russia’s orders – Amnezia VPN is the last victim\n\n\t\t\t\t\t\t\t\t\tTechRadar ↗\t\t\t\t\t\t\t\n↗\n4 Nov 2024\n\nApple keeps killing VPN apps upon Russia’s orders – Amnezia VPN is the last victim\n\n\n\n\n\n\n\n\n\n\t\t\t\t\tInternet Shutdowns\t\t\t\t\n\n\n\n\nInternet Shutdowns \n\n\n\t\t\t\t#KeepItOn Mauritius: global coalition urges first-time offender to end crackdown on social media\t\t\t\n\n1 Nov 2024\n\n\n\n\nPress Release\n#KeepItOn Mauritius: global coalition urges first-time offender to end crackdown on social media\n1 Nov 2024\n\n#KeepItOn Mauritius: global coalition urges first-time offender to end crackdown on social media\n\n\n\n\n\n\n\n\n\n\t\t\t\t\tConnectivity\t\t\t\t\n\n\n\n\nConnectivity \n\n\n\t\t\t\tMyanmar residents struggle to overcome severe internet blackouts with Starlink\t\t\t\n\n23 Oct 2024\n\n\n\n\nNews\nMyanmar residents struggle to overcome severe internet blackouts with Starlink\n\n\t\t\t\t\t\t\t\t\tRest of World ↗\t\t\t\t\t\t\t\n↗\n23 Oct 2024\n\nMyanmar residents struggle to overcome severe internet blackouts with Starlink\n\n\n\n\n\n\n\n\n\n\t\t\t\t\tConnectivity\t\t\t\t\n\n\n\n\nConnectivity \n\n\n\t\t\t\tستارلينك في اليمن: لماذا يعارض الحوثيون تفعيل الإنترنت الفضائي؟\t\t\t\n\n1 Oct 2024\n\n\n\n\nNews\nستارلينك في اليمن: لماذا يعارض الحوثيون تفعيل الإنترنت الفضائي؟\n\n\t\t\t\t\t\t\t\t\tBBC ↗\t\t\t\t\t\t\t\n↗\n1 Oct 2024\n\nستارلينك في اليمن: لماذا يعارض الحوثيون تفعيل الإنترنت الفضائي؟\n\n\n\n\n\n\n\n\n\n\t\t\t\t\tInternet Shutdowns\t\t\t\t\n\n\n\n\nInternet Shutdowns \n\n\n\t\t\t\tJoint statement: Sudan has suffered in silence for over 500 days\t\t\t\n\n5 Sep 2024\n • \nAfter more than 500 days of brutal conflict in Sudan, the #KeepItOn coalition reiterates calls to reactivate telecommunication services. Press Release\nJoint statement: Sudan has suffered in silence for over 500 days\n5 Sep 2024\n\nJoint statement: Sudan has suffered in silence for over 500 days\n\n\n\n\n\n\n\n\n\n\t\t\t\t\tInternet Shutdowns\t\t\t\t\n\n\n\n\nInternet Shutdowns \n\n\n\t\t\t\tAfrica in 2023: internet shutdowns attack democracy\t\t\t\n\n26 Aug 2024\n\n\n\n\nPress Release\nAfrica in 2023: internet shutdowns attack democracy\n26 Aug 2024\n\nAfrica in 2023: internet shutdowns attack democracy\n\n\n\n\n\n\n\n\n\n\t\t\t\t\tInternet Shutdowns\t\t\t\t\n\n\n\n\nInternet Shutdowns \n\n\n\t\t\t\t#KeepItOn in Annobón: Authorities in Equatorial Guinea must end internet shutdown and other human rights abuses\t\t\t\n\n13 Aug 2024\n • \nAccess Now and the #KeepItOn coalition are calling on authorities in Equatorial Guinea to immediately restore internet and telecom services in Annobón. Press Release\n#KeepItOn in Annobón: Authorities in Equatorial Guinea must end internet shutdown and other human rights abuses\n13 Aug 2024\n\n#KeepItOn in Annobón: Authorities in Equatorial Guinea must end internet shutdown and other human rights abuses\n\n\n\n\n\n\n\n\n\n\t\t\t\t\tInternet Shutdowns\t\t\t\t\n\n\n\n\nInternet Shutdowns \n\n\n\t\t\t\t#KeepItOn en Annobón: Las autoridades de Guinea Ecuatorial deben poner fin al corte de internet y otros abusos a los derechos humanos\t\t\t\n\n13 Aug 2024\n • \nLa coalición #KeepItOn instan a las autoridades de Guinea Ecuatorial a restablecer de inmediato el acceso a internet en Annobón. Press Release\n#KeepItOn en Annobón: Las autoridades de Guinea Ecuatorial deben poner fin al corte de internet y otros abusos a los derechos humanos\n13 Aug 2024\n\n#KeepItOn en Annobón: Las autoridades de Guinea Ecuatorial deben poner fin al corte de internet y otros abusos a los derechos humanos\n\nEquitable Internet Access For All\n\n\n\nToday, affordable and meaningful access to the internet is an essential enabler of human rights. Press Release\n#KeepItOn in Tanzania: authorities must ensure connectivity during local elections\n21 Nov 2024\n\n#KeepItOn in Tanzania: authorities must ensure connectivity during local elections\n\n\n\n\n\n\n\n\n\n\t\t\t\t\tInternet Shutdowns\t\t\t\t\n\n\n\n\nInternet Shutdowns \n\n\n\t\t\t\t#KeepItOn: the Government of Tanzania and internet service providers must ensure open and secure internet access throughout the 2024 local elections\t\t\t\n\n21 Nov 2024\n • \nThe #KeepItOn coalition calls on authorities and ISPs in Tanzania to ensure internet access during the upcoming elections. Press Release\n#KeepItOn: the Government of Tanzania and internet service providers must ensure open and secure internet access throughout the 2024 local elections\n21 Nov 2024\n\n#KeepItOn: the Government of Tanzania and internet service providers must ensure open and secure internet access throughout the 2024 local elections\n\n\n\n\n\n\n\n\n\n\t\t\t\t\tConnectivity\t\t\t\t\n\n\n\n\nConnectivity \n\n\n\t\t\t\tAs Israel destroys infrastructure, will Lebanon be cut off from outside world? Connectivity\t\t\t\t\n\n\n\n\nConnectivity \n\n\n\t\t\t\tApple keeps killing VPN apps upon Russia’s orders – Amnezia VPN is the last victim\t\t\t\n\n4 Nov 2024\n\n\n\n\nNews\nApple keeps killing VPN apps upon Russia’s orders – Amnezia VPN is the last victim\n\n\t\t\t\t\t\t\t\t\tTechRadar ↗\t\t\t\t\t\t\t\n↗\n4 Nov 2024\n\nApple keeps killing VPN apps upon Russia’s orders – Amnezia VPN is the last victim\n\n\n\n\n\n\n\n\n\n\t\t\t\t\tInternet Shutdowns\t\t\t\t\n\n\n\n\nInternet Shutdowns \n\n\n\t\t\t\t#KeepItOn Mauritius: global coalition urges first-time offender to end crackdown on social media\t\t\t\n\n1 Nov 2024\n\n\n\n\nPress Release\n#KeepItOn Mauritius: global coalition urges first-time offender to end crackdown on social media\n1 Nov 2024\n\n#KeepItOn Mauritius: global coalition urges first-time offender to end crackdown on social media\n\n\n\n\n\n\n\n\n\n\t\t\t\t\tConnectivity\t\t\t\t\n\n\n\n\nConnectivity \n\n\n\t\t\t\tMyanmar residents struggle to overcome severe internet blackouts with Starlink\t\t\t\n\n23 Oct 2024\n\n\n\n\nNews\nMyanmar residents struggle to overcome severe internet blackouts with Starlink\n\n\t\t\t\t\t\t\t\t\tRest of World ↗\t\t\t\t\t\t\t\n↗\n23 Oct 2024\n\nMyanmar residents struggle to overcome severe internet blackouts with Starlink\n\n\n\n\n\n\n\n\n\n\t\t\t\t\tConnectivity\t\t\t\t\n\n\n\n\nConnectivity \n\n\n\t\t\t\tستارلينك في اليمن: لماذا يعارض الحوثيون تفعيل الإنترنت الفضائي؟\t\t\t\n\n1 Oct 2024\n\n\n\n\nNews\nستارلينك في اليمن: لماذا يعارض الحوثيون تفعيل الإنترنت الفضائي؟\n\n\t\t\t\t\t\t\t\t\tBBC ↗\t\t\t\t\t\t\t\n↗\n1 Oct 2024\n\nستارلينك في اليمن: لماذا يعارض الحوثيون تفعيل الإنترنت الفضائي؟\n\n\n\n\n\n\n\n\n\n\t\t\t\t\tInternet Shutdowns\t\t\t\t\n\n\n\n\nInternet Shutdowns \n\n\n\t\t\t\tJoint statement: Sudan has suffered in silence for over 500 days\t\t\t\n\n5 Sep 2024\n • \nAfter more than 500 days of brutal conflict in Sudan, the #KeepItOn coalition reiterates calls to reactivate telecommunication services. Press Release\nJoint statement: Sudan has suffered in silence for over 500 days\n5 Sep 2024\n\nJoint statement: Sudan has suffered in silence for over 500 days\n\n\n\n\n\n\n\n\n\n\t\t\t\t\tInternet Shutdowns\t\t\t\t\n\n\n\n\nInternet Shutdowns \n\n\n\t\t\t\tAfrica in 2023: internet shutdowns attack democracy\t\t\t\n\n26 Aug 2024\n\n\n\n\nPress Release\nAfrica in 2023: internet shutdowns attack democracy\n26 Aug 2024\n\nAfrica in 2023: internet shutdowns attack democracy\n\n\n\n\n\n\n\n\n\n\t\t\t\t\tInternet Shutdowns\t\t\t\t\n\n\n\n\nInternet Shutdowns \n\n\n\t\t\t\t#KeepItOn in Annobón: Authorities in Equatorial Guinea must end internet shutdown and other human rights abuses\t\t\t\n\n13 Aug 2024\n • \nAccess Now and the #KeepItOn coalition are calling on authorities in Equatorial Guinea to immediately restore internet and telecom services in Annobón. Press Release\n#KeepItOn in Annobón: Authorities in Equatorial Guinea must end internet shutdown and other human rights abuses\n13 Aug 2024\n\n#KeepItOn in Annobón: Authorities in Equatorial Guinea must end internet shutdown and other human rights abuses\n\n\n\n\n\n\n\n\n\n\t\t\t\t\tInternet Shutdowns\t\t\t\t\n\n\n\n\nInternet Shutdowns \n\n\n\t\t\t\t#KeepItOn en Annobón: Las autoridades de Guinea Ecuatorial deben poner fin al corte de internet y otros abusos a los derechos humanos\t\t\t\n\n13 Aug 2024\n • \nLa coalición #KeepItOn instan a las autoridades de Guinea Ecuatorial a restablecer de inmediato el acceso a internet en Annobón. Press Release\n#KeepItOn en Annobón: Las autoridades de Guinea Ecuatorial deben poner fin al corte de internet y otros abusos a los derechos humanos\n13 Aug 2024\n\n#KeepItOn en Annobón: Las autoridades de Guinea Ecuatorial deben poner fin al corte de internet y otros abusos a los derechos humanos\n\nEquitable Internet Access For All\n\n\n\nToday, affordable and meaningful access to the internet is an essential enabler of human rights. Press Release\n#KeepItOn in Tanzania: authorities must ensure connectivity during local elections\n21 Nov 2024\n\n#KeepItOn in Tanzania: authorities must ensure connectivity during local elections\n\n\n\n\n\n\n\n\n\n\t\t\t\t\tInternet Shutdowns\t\t\t\t\n\n\n\n\nInternet Shutdowns \n\n\n\t\t\t\t#KeepItOn: the Government of Tanzania and internet service providers must ensure open and secure internet access throughout the 2024 local elections\t\t\t\n\n21 Nov 2024\n • \nThe #KeepItOn coalition calls on authorities and ISPs in Tanzania to ensure internet access during the upcoming elections. Press Release\n#KeepItOn: the Government of Tanzania and internet service providers must ensure open and secure internet access throughout the 2024 local elections\n21 Nov 2024\n\n#KeepItOn: the Government of Tanzania and internet service providers must ensure open and secure internet access throughout the 2024 local elections\n\n\n\n\n\n\n\n\n\n\t\t\t\t\tConnectivity\t\t\t\t\n\n\n\n\nConnectivity \n\n\n\t\t\t\tAs Israel destroys infrastructure, will Lebanon be cut off from outside world? Connectivity\t\t\t\t\n\n\n\n\nConnectivity \n\n\n\t\t\t\tApple keeps killing VPN apps upon Russia’s orders – Amnezia VPN is the last victim\t\t\t\n\n4 Nov 2024\n\n\n\n\nNews\nApple keeps killing VPN apps upon Russia’s orders – Amnezia VPN is the last victim\n\n\t\t\t\t\t\t\t\t\tTechRadar ↗\t\t\t\t\t\t\t\n↗\n4 Nov 2024\n\nApple keeps killing VPN apps upon Russia’s orders – Amnezia VPN is the last victim\n\n\n\n\n\n\n\n\n\n\t\t\t\t\tInternet Shutdowns\t\t\t\t\n\n\n\n\nInternet Shutdowns \n\n\n\t\t\t\t#KeepItOn Mauritius: global coalition urges first-time offender to end crackdown on social media\t\t\t\n\n1 Nov 2024\n\n\n\n\nPress Release\n#KeepItOn Mauritius: global coalition urges first-time offender to end crackdown on social media\n1 Nov 2024\n\n#KeepItOn Mauritius: global coalition urges first-time offender to end crackdown on social media\n\n\n\n\n\n\n\n\n\n\t\t\t\t\tConnectivity\t\t\t\t\n\n\n\n\nConnectivity \n\n\n\t\t\t\tMyanmar residents struggle to overcome severe internet blackouts with Starlink\t\t\t\n\n23 Oct 2024\n\n\n\n\nNews\nMyanmar residents struggle to overcome severe internet blackouts with Starlink\n\n\t\t\t\t\t\t\t\t\tRest of World ↗\t\t\t\t\t\t\t\n↗\n23 Oct 2024\n\nMyanmar residents struggle to overcome severe internet blackouts with Starlink\n\n\n\n\n\n\n\n\n\n\t\t\t\t\tConnectivity\t\t\t\t\n\n\n\n\nConnectivity \n\n\n\t\t\t\tستارلينك في اليمن: لماذا يعارض الحوثيون تفعيل الإنترنت الفضائي؟\t\t\t\n\n1 Oct 2024\n\n\n\n\nNews\nستارلينك في اليمن: لماذا يعارض الحوثيون تفعيل الإنترنت الفضائي؟\n\n\t\t\t\t\t\t\t\t\tBBC ↗\t\t\t\t\t\t\t\n↗\n1 Oct 2024\n\nستارلينك في اليمن: لماذا يعارض الحوثيون تفعيل الإنترنت الفضائي؟\n\n\n\n\n\n\n\n\n\n\t\t\t\t\tInternet Shutdowns\t\t\t\t\n\n\n\n\nInternet Shutdowns \n\n\n\t\t\t\tJoint statement: Sudan has suffered in silence for over 500 days\t\t\t\n\n5 Sep 2024\n • \nAfter more than 500 days of brutal conflict in Sudan, the #KeepItOn coalition reiterates calls to reactivate telecommunication services. Press Release\nJoint statement: Sudan has suffered in silence for over 500 days\n5 Sep 2024\n\nJoint statement: Sudan has suffered in silence for over 500 days\n\n\n\n\n\n\n\n\n\n\t\t\t\t\tInternet Shutdowns\t\t\t\t\n\n\n\n\nInternet Shutdowns \n\n\n\t\t\t\tAfrica in 2023: internet shutdowns attack democracy\t\t\t\n\n26 Aug 2024\n\n\n\n\nPress Release\nAfrica in 2023: internet shutdowns attack democracy\n26 Aug 2024\n\nAfrica in 2023: internet shutdowns attack democracy\n\n\n\n\n\n\n\n\n\n\t\t\t\t\tInternet Shutdowns\t\t\t\t\n\n\n\n\nInternet Shutdowns \n\n\n\t\t\t\t#KeepItOn in Annobón: Authorities in Equatorial Guinea must end internet shutdown and other human rights abuses\t\t\t\n\n13 Aug 2024\n • \nAccess Now and the #KeepItOn coalition are calling on authorities in Equatorial Guinea to immediately restore internet and telecom services in Annobón. Press Release\n#KeepItOn in Annobón: Authorities in Equatorial Guinea must end internet shutdown and other human rights abuses\n13 Aug 2024\n\n#KeepItOn in Annobón: Authorities in Equatorial Guinea must end internet shutdown and other human rights abuses\n\n\n\n\n\n\n\n\n\n\t\t\t\t\tInternet Shutdowns\t\t\t\t\n\n\n\n\nInternet Shutdowns \n\n\n\t\t\t\t#KeepItOn en Annobón: Las autoridades de Guinea Ecuatorial deben poner fin al corte de internet y otros abusos a los derechos humanos\t\t\t\n\n13 Aug 2024\n • \nLa coalición #KeepItOn instan a las autoridades de Guinea Ecuatorial a restablecer de inmediato el acceso a internet en Annobón. Press Release\n#KeepItOn en Annobón: Las autoridades de Guinea Ecuatorial deben poner fin al corte de internet y otros abusos a los derechos humanos\n13 Aug 2024\n\n#KeepItOn en Annobón: Las autoridades de Guinea Ecuatorial deben poner fin al corte de internet y otros abusos a los derechos humanos\n\nEquitable Internet Access For All\n\n\n\nToday, affordable and meaningful access to the internet is an essential enabler of human rights. Press Release\n#KeepItOn in Tanzania: authorities must ensure connectivity during local elections\n21 Nov 2024\n\n#KeepItOn in Tanzania: authorities must ensure connectivity during local elections\n\n\n\n\n\n\n\n\n\n\t\t\t\t\tInternet Shutdowns\t\t\t\t\n\n\n\n\nInternet Shutdowns \n\n\n\t\t\t\t#KeepItOn: the Government of Tanzania and internet service providers must ensure open and secure internet access throughout the 2024 local elections\t\t\t\n\n21 Nov 2024\n • \nThe #KeepItOn coalition calls on authorities and ISPs in Tanzania to ensure internet access during the upcoming elections. Press Release\n#KeepItOn: the Government of Tanzania and internet service providers must ensure open and secure internet access throughout the 2024 local elections\n21 Nov 2024\n\n#KeepItOn: the Government of Tanzania and internet service providers must ensure open and secure internet access throughout the 2024 local elections\n\n\n\n\n\n\n\n\n\n\t\t\t\t\tConnectivity\t\t\t\t\n\n\n\n\nConnectivity \n\n\n\t\t\t\tAs Israel destroys infrastructure, will Lebanon be cut off from outside world? Connectivity\t\t\t\t\n\n\n\n\nConnectivity \n\n\n\t\t\t\tApple keeps killing VPN apps upon Russia’s orders – Amnezia VPN is the last victim\t\t\t\n\n4 Nov 2024\n\n\n\n\nNews\nApple keeps killing VPN apps upon Russia’s orders – Amnezia VPN is the last victim\n\n\t\t\t\t\t\t\t\t\tTechRadar ↗\t\t\t\t\t\t\t\n↗\n4 Nov 2024\n\nApple keeps killing VPN apps upon Russia’s orders – Amnezia VPN is the last victim\n\n\n\n\n\n\n\n\n\n\t\t\t\t\tInternet Shutdowns\t\t\t\t\n\n\n\n\nInternet Shutdowns \n\n\n\t\t\t\t#KeepItOn Mauritius: global coalition urges first-time offender to end crackdown on social media\t\t\t\n\n1 Nov 2024\n\n\n\n\nPress Release\n#KeepItOn Mauritius: global coalition urges first-time offender to end crackdown on social media\n1 Nov 2024\n\n#KeepItOn Mauritius: global coalition urges first-time offender to end crackdown on social media\n\n\n\n\n\n\n\n\n\n\t\t\t\t\tConnectivity\t\t\t\t\n\n\n\n\nConnectivity \n\n\n\t\t\t\tMyanmar residents struggle to overcome severe internet blackouts with Starlink\t\t\t\n\n23 Oct 2024\n\n\n\n\nNews\nMyanmar residents struggle to overcome severe internet blackouts with Starlink\n\n\t\t\t\t\t\t\t\t\tRest of World ↗\t\t\t\t\t\t\t\n↗\n23 Oct 2024\n\nMyanmar residents struggle to overcome severe internet blackouts with Starlink\n\n\n\n\n\n\n\n\n\n\t\t\t\t\tConnectivity\t\t\t\t\n\n\n\n\nConnectivity \n\n\n\t\t\t\tستارلينك في اليمن: لماذا يعارض الحوثيون تفعيل الإنترنت الفضائي؟\t\t\t\n\n1 Oct 2024\n\n\n\n\nNews\nستارلينك في اليمن: لماذا يعارض الحوثيون تفعيل الإنترنت الفضائي؟\n\n\t\t\t\t\t\t\t\t\tBBC ↗\t\t\t\t\t\t\t\n↗\n1 Oct 2024\n\nستارلينك في اليمن: لماذا يعارض الحوثيون تفعيل الإنترنت الفضائي؟\n\n\n\n\n\n\n\n\n\n\t\t\t\t\tInternet Shutdowns\t\t\t\t\n\n\n\n\nInternet Shutdowns \n\n\n\t\t\t\tJoint statement: Sudan has suffered in silence for over 500 days\t\t\t\n\n5 Sep 2024\n • \nAfter more than 500 days of brutal conflict in Sudan, the #KeepItOn coalition reiterates calls to reactivate telecommunication services. Press Release\nJoint statement: Sudan has suffered in silence for over 500 days\n5 Sep 2024\n\nJoint statement: Sudan has suffered in silence for over 500 days\n\n\n\n\n\n\n\n\n\n\t\t\t\t\tInternet Shutdowns\t\t\t\t\n\n\n\n\nInternet Shutdowns \n\n\n\t\t\t\tAfrica in 2023: internet shutdowns attack democracy\t\t\t\n\n26 Aug 2024\n\n\n\n\nPress Release\nAfrica in 2023: internet shutdowns attack democracy\n26 Aug 2024\n\nAfrica in 2023: internet shutdowns attack democracy\n\n\n\n\n\n\n\n\n\n\t\t\t\t\tInternet Shutdowns\t\t\t\t\n\n\n\n\nInternet Shutdowns \n\n\n\t\t\t\t#KeepItOn in Annobón: Authorities in Equatorial Guinea must end internet shutdown and other human rights abuses\t\t\t\n\n13 Aug 2024\n • \nAccess Now and the #KeepItOn coalition are calling on authorities in Equatorial Guinea to immediately restore internet and telecom services in Annobón. Press Release\n#KeepItOn in Annobón: Authorities in Equatorial Guinea must end internet shutdown and other human rights abuses\n13 Aug 2024\n\n#KeepItOn in Annobón: Authorities in Equatorial Guinea must end internet shutdown and other human rights abuses\n\n\n\n\n\n\n\n\n\n\t\t\t\t\tInternet Shutdowns\t\t\t\t\n\n\n\n\nInternet Shutdowns \n\n\n\t\t\t\t#KeepItOn en Annobón: Las autoridades de Guinea Ecuatorial deben poner fin al corte de internet y otros abusos a los derechos humanos\t\t\t\n\n13 Aug 2024\n • \nLa coalición #KeepItOn instan a las autoridades de Guinea Ecuatorial a restablecer de inmediato el acceso a internet en Annobón. Press Release\n#KeepItOn en Annobón: Las autoridades de Guinea Ecuatorial deben poner fin al corte de internet y otros abusos a los derechos humanos\n13 Aug 2024\n\n#KeepItOn en Annobón: Las autoridades de Guinea Ecuatorial deben poner fin al corte de internet y otros abusos a los derechos humanos\n\nEquitable Internet Access For All\n\n\n\nToday, affordable and meaningful access to the internet is an essential enabler of human rights. Press Release\n#KeepItOn in Tanzania: authorities must ensure connectivity during local elections\n21 Nov 2024\n\n#KeepItOn in Tanzania: authorities must ensure connectivity during local elections\n\n\n\n\n\n\n\n\n\n\t\t\t\t\tInternet Shutdowns\t\t\t\t\n\n\n\n\nInternet Shutdowns \n\n\n\t\t\t\t#KeepItOn: the Government of Tanzania and internet service providers must ensure open and secure internet access throughout the 2024 local elections\t\t\t\n\n21 Nov 2024\n • \nThe #KeepItOn coalition calls on authorities and ISPs in Tanzania to ensure internet access during the upcoming elections. Press Release\n#KeepItOn: the Government of Tanzania and internet service providers must ensure open and secure internet access throughout the 2024 local elections\n21 Nov 2024\n\n#KeepItOn: the Government of Tanzania and internet service providers must ensure open and secure internet access throughout the 2024 local elections\n\n\n\n\n\n\n\n\n\n\t\t\t\t\tConnectivity\t\t\t\t\n\n\n\n\nConnectivity \n\n\n\t\t\t\tAs Israel destroys infrastructure, will Lebanon be cut off from outside world? Connectivity\t\t\t\t\n\n\n\n\nConnectivity \n\n\n\t\t\t\tApple keeps killing VPN apps upon Russia’s orders – Amnezia VPN is the last victim\t\t\t\n\n4 Nov 2024\n\n\n\n\nNews\nApple keeps killing VPN apps upon Russia’s orders – Amnezia VPN is the last victim\n\n\t\t\t\t\t\t\t\t\tTechRadar ↗\t\t\t\t\t\t\t\n↗\n4 Nov 2024\n\nApple keeps killing VPN apps upon Russia’s orders – Amnezia VPN is the last victim\n\n\n\n\n\n\n\n\n\n\t\t\t\t\tInternet Shutdowns\t\t\t\t\n\n\n\n\nInternet Shutdowns \n\n\n\t\t\t\t#KeepItOn Mauritius: global coalition urges first-time offender to end crackdown on social media\t\t\t\n\n1 Nov 2024\n\n\n\n\nPress Release\n#KeepItOn Mauritius: global coalition urges first-time offender to end crackdown on social media\n1 Nov 2024\n\n#KeepItOn Mauritius: global coalition urges first-time offender to end crackdown on social media\n\n\n\n\n\n\n\n\n\n\t\t\t\t\tConnectivity\t\t\t\t\n\n\n\n\nConnectivity \n\n\n\t\t\t\tMyanmar residents struggle to overcome severe internet blackouts with Starlink\t\t\t\n\n23 Oct 2024\n\n\n\n\nNews\nMyanmar residents struggle to overcome severe internet blackouts with Starlink\n\n\t\t\t\t\t\t\t\t\tRest of World ↗\t\t\t\t\t\t\t\n↗\n23 Oct 2024\n\nMyanmar residents struggle to overcome severe internet blackouts with Starlink\n\n\n\n\n\n\n\n\n\n\t\t\t\t\tConnectivity\t\t\t\t\n\n\n\n\nConnectivity \n\n\n\t\t\t\tستارلينك في اليمن: لماذا يعارض الحوثيون تفعيل الإنترنت الفضائي؟\t\t\t\n\n1 Oct 2024\n\n\n\n\nNews\nستارلينك في اليمن: لماذا يعارض الحوثيون تفعيل الإنترنت الفضائي؟\n\n\t\t\t\t\t\t\t\t\tBBC ↗\t\t\t\t\t\t\t\n↗\n1 Oct 2024\n\nستارلينك في اليمن: لماذا يعارض الحوثيون تفعيل الإنترنت الفضائي؟\n\n\n\n\n\n\n\n\n\n\t\t\t\t\tInternet Shutdowns\t\t\t\t\n\n\n\n\nInternet Shutdowns \n\n\n\t\t\t\tJoint statement: Sudan has suffered in silence for over 500 days\t\t\t\n\n5 Sep 2024\n • \nAfter more than 500 days of brutal conflict in Sudan, the #KeepItOn coalition reiterates calls to reactivate telecommunication services. Press Release\nJoint statement: Sudan has suffered in silence for over 500 days\n5 Sep 2024\n\nJoint statement: Sudan has suffered in silence for over 500 days\n\n\n\n\n\n\n\n\n\n\t\t\t\t\tInternet Shutdowns\t\t\t\t\n\n\n\n\nInternet Shutdowns \n\n\n\t\t\t\tAfrica in 2023: internet shutdowns attack democracy\t\t\t\n\n26 Aug 2024\n\n\n\n\nPress Release\nAfrica in 2023: internet shutdowns attack democracy\n26 Aug 2024\n\nAfrica in 2023: internet shutdowns attack democracy\n\n\n\n\n\n\n\n\n\n\t\t\t\t\tInternet Shutdowns\t\t\t\t\n\n\n\n\nInternet Shutdowns \n\n\n\t\t\t\t#KeepItOn in Annobón: Authorities in Equatorial Guinea must end internet shutdown and other human rights abuses\t\t\t\n\n13 Aug 2024\n • \nAccess Now and the #KeepItOn coalition are calling on authorities in Equatorial Guinea to immediately restore internet and telecom services in Annobón. Press Release\n#KeepItOn in Annobón: Authorities in Equatorial Guinea must end internet shutdown and other human rights abuses\n13 Aug 2024\n\n#KeepItOn in Annobón: Authorities in Equatorial Guinea must end internet shutdown and other human rights abuses\n\n\n\n\n\n\n\n\n\n\t\t\t\t\tInternet Shutdowns\t\t\t\t\n\n\n\n\nInternet Shutdowns \n\n\n\t\t\t\t#KeepItOn en Annobón: Las autoridades de Guinea Ecuatorial deben poner fin al corte de internet y otros abusos a los derechos humanos\t\t\t\n\n13 Aug 2024\n • \nLa coalición #KeepItOn instan a las autoridades de Guinea Ecuatorial a restablecer de inmediato el acceso a internet en Annobón. Press Release\n#KeepItOn en Annobón: Las autoridades de Guinea Ecuatorial deben poner fin al corte de internet y otros abusos a los derechos humanos\n13 Aug 2024\n\n#KeepItOn en Annobón: Las autoridades de Guinea Ecuatorial deben poner fin al corte de internet y otros abusos a los derechos humanos\n\nEquitable Internet Access For All\n\nEquitable Internet Access For All\n\nToday, affordable and meaningful access to the internet is an essential enabler of human rights. Press Release\n#KeepItOn in Tanzania: authorities must ensure connectivity during local elections\n21 Nov 2024\n\n#KeepItOn in Tanzania: authorities must ensure connectivity during local elections\n\n\n\n\n\n\n\n\n\n\t\t\t\t\tInternet Shutdowns\t\t\t\t\n\n\n\n\nInternet Shutdowns \n\n\n\t\t\t\t#KeepItOn: the Government of Tanzania and internet service providers must ensure open and secure internet access throughout the 2024 local elections\t\t\t\n\n21 Nov 2024\n • \nThe #KeepItOn coalition calls on authorities and ISPs in Tanzania to ensure internet access during the upcoming elections. Press Release\n#KeepItOn: the Government of Tanzania and internet service providers must ensure open and secure internet access throughout the 2024 local elections\n21 Nov 2024\n\n#KeepItOn: the Government of Tanzania and internet service providers must ensure open and secure internet access throughout the 2024 local elections\n\n\n\n\n\n\n\n\n\n\t\t\t\t\tConnectivity\t\t\t\t\n\n\n\n\nConnectivity \n\n\n\t\t\t\tAs Israel destroys infrastructure, will Lebanon be cut off from outside world? Connectivity\t\t\t\t\n\n\n\n\nConnectivity \n\n\n\t\t\t\tApple keeps killing VPN apps upon Russia’s orders – Amnezia VPN is the last victim\t\t\t\n\n4 Nov 2024\n\n\n\n\nNews\nApple keeps killing VPN apps upon Russia’s orders – Amnezia VPN is the last victim\n\n\t\t\t\t\t\t\t\t\tTechRadar ↗\t\t\t\t\t\t\t\n↗\n4 Nov 2024\n\nApple keeps killing VPN apps upon Russia’s orders – Amnezia VPN is the last victim\n\n\n\n\n\n\n\n\n\n\t\t\t\t\tInternet Shutdowns\t\t\t\t\n\n\n\n\nInternet Shutdowns \n\n\n\t\t\t\t#KeepItOn Mauritius: global coalition urges first-time offender to end crackdown on social media\t\t\t\n\n1 Nov 2024\n\n\n\n\nPress Release\n#KeepItOn Mauritius: global coalition urges first-time offender to end crackdown on social media\n1 Nov 2024\n\n#KeepItOn Mauritius: global coalition urges first-time offender to end crackdown on social media\n\n\n\n\n\n\n\n\n\n\t\t\t\t\tConnectivity\t\t\t\t\n\n\n\n\nConnectivity \n\n\n\t\t\t\tMyanmar residents struggle to overcome severe internet blackouts with Starlink\t\t\t\n\n23 Oct 2024\n\n\n\n\nNews\nMyanmar residents struggle to overcome severe internet blackouts with Starlink\n\n\t\t\t\t\t\t\t\t\tRest of World ↗\t\t\t\t\t\t\t\n↗\n23 Oct 2024\n\nMyanmar residents struggle to overcome severe internet blackouts with Starlink\n\n\n\n\n\n\n\n\n\n\t\t\t\t\tConnectivity\t\t\t\t\n\n\n\n\nConnectivity \n\n\n\t\t\t\tستارلينك في اليمن: لماذا يعارض الحوثيون تفعيل الإنترنت الفضائي؟\t\t\t\n\n1 Oct 2024\n\n\n\n\nNews\nستارلينك في اليمن: لماذا يعارض الحوثيون تفعيل الإنترنت الفضائي؟\n\n\t\t\t\t\t\t\t\t\tBBC ↗\t\t\t\t\t\t\t\n↗\n1 Oct 2024\n\nستارلينك في اليمن: لماذا يعارض الحوثيون تفعيل الإنترنت الفضائي؟\n\n\n\n\n\n\n\n\n\n\t\t\t\t\tInternet Shutdowns\t\t\t\t\n\n\n\n\nInternet Shutdowns \n\n\n\t\t\t\tJoint statement: Sudan has suffered in silence for over 500 days\t\t\t\n\n5 Sep 2024\n • \nAfter more than 500 days of brutal conflict in Sudan, the #KeepItOn coalition reiterates calls to reactivate telecommunication services. Press Release\nJoint statement: Sudan has suffered in silence for over 500 days\n5 Sep 2024\n\nJoint statement: Sudan has suffered in silence for over 500 days\n\n\n\n\n\n\n\n\n\n\t\t\t\t\tInternet Shutdowns\t\t\t\t\n\n\n\n\nInternet Shutdowns \n\n\n\t\t\t\tAfrica in 2023: internet shutdowns attack democracy\t\t\t\n\n26 Aug 2024\n\n\n\n\nPress Release\nAfrica in 2023: internet shutdowns attack democracy\n26 Aug 2024\n\nAfrica in 2023: internet shutdowns attack democracy\n\n\n\n\n\n\n\n\n\n\t\t\t\t\tInternet Shutdowns\t\t\t\t\n\n\n\n\nInternet Shutdowns \n\n\n\t\t\t\t#KeepItOn in Annobón: Authorities in Equatorial Guinea must end internet shutdown and other human rights abuses\t\t\t\n\n13 Aug 2024\n • \nAccess Now and the #KeepItOn coalition are calling on authorities in Equatorial Guinea to immediately restore internet and telecom services in Annobón. Press Release\n#KeepItOn in Annobón: Authorities in Equatorial Guinea must end internet shutdown and other human rights abuses\n13 Aug 2024\n\n#KeepItOn in Annobón: Authorities in Equatorial Guinea must end internet shutdown and other human rights abuses\n\n\n\n\n\n\n\n\n\n\t\t\t\t\tInternet Shutdowns\t\t\t\t\n\n\n\n\nInternet Shutdowns \n\n\n\t\t\t\t#KeepItOn en Annobón: Las autoridades de Guinea Ecuatorial deben poner fin al corte de internet y otros abusos a los derechos humanos\t\t\t\n\n13 Aug 2024\n • \nLa coalición #KeepItOn instan a las autoridades de Guinea Ecuatorial a restablecer de inmediato el acceso a internet en Annobón. Press Release\n#KeepItOn en Annobón: Las autoridades de Guinea Ecuatorial deben poner fin al corte de internet y otros abusos a los derechos humanos\n13 Aug 2024\n\n#KeepItOn en Annobón: Las autoridades de Guinea Ecuatorial deben poner fin al corte de internet y otros abusos a los derechos humanos\n\nLatest Updates\n\n\n\n     \n\n\n\n\n\nGrid View\nList View\n\n\n\n\n\n\n\n\n\n\n\n\n\n\t\t\t\t\tConnectivity\t\t\t\t\n\n\n\n\nConnectivity \n\n\n\t\t\t\tJoint statement: five-point plan for an inclusive WSIS+20 review\t\t\t\n\n29 Mar 2025\n\n\n\n\nPress Release\nJoint statement: five-point plan for an inclusive WSIS+20 review\n\n\n↗\n29 Mar 2025\n\nJoint statement: five-point plan for an inclusive WSIS+20 review\n\n\n\n\n\n\n\n\n\n\t\t\t\t\tConnectivity\t\t\t\t\n\n\n\n\nConnectivity \n\n\n\t\t\t\tOral statement at 10th Session of the UN Open Ended Working Group on ICTs\t\t\t\n\n21 Feb 2025\n • \nAccess Now’s oral statement at the 10th Session of the UN Open Ended Working Group on information and communication technology. Press Release\n#KeepItOn in Tanzania: authorities must ensure connectivity during local elections\n21 Nov 2024\n\n#KeepItOn in Tanzania: authorities must ensure connectivity during local elections\n\n\n\n\n\n\n\n\n\n\t\t\t\t\tInternet Shutdowns\t\t\t\t\n\n\n\n\nInternet Shutdowns \n\n\n\t\t\t\t#KeepItOn: the Government of Tanzania and internet service providers must ensure open and secure internet access throughout the 2024 local elections\t\t\t\n\n21 Nov 2024\n • \nThe #KeepItOn coalition calls on authorities and ISPs in Tanzania to ensure internet access during the upcoming elections. Press Release\n#KeepItOn: the Government of Tanzania and internet service providers must ensure open and secure internet access throughout the 2024 local elections\n21 Nov 2024\n\n#KeepItOn: the Government of Tanzania and internet service providers must ensure open and secure internet access throughout the 2024 local elections\n\n\n\n\n\n\n\n\n\n\t\t\t\t\tConnectivity\t\t\t\t\n\n\n\n\nConnectivity \n\n\n\t\t\t\tAs Israel destroys infrastructure, will Lebanon be cut off from outside world? Connectivity\t\t\t\t\n\n\n\n\nConnectivity \n\n\n\t\t\t\tApple keeps killing VPN apps upon Russia’s orders – Amnezia VPN is the last victim\t\t\t\n\n4 Nov 2024\n\n\n\n\nNews\nApple keeps killing VPN apps upon Russia’s orders – Amnezia VPN is the last victim\n\n\t\t\t\t\t\t\t\t\tTechRadar ↗\t\t\t\t\t\t\t\n↗\n4 Nov 2024\n\nApple keeps killing VPN apps upon Russia’s orders – Amnezia VPN is the last victim\n\n\n\n\n\n\n\n\n\n\t\t\t\t\tInternet Shutdowns\t\t\t\t\n\n\n\n\nInternet Shutdowns \n\n\n\t\t\t\t#KeepItOn Mauritius: global coalition urges first-time offender to end crackdown on social media\t\t\t\n\n1 Nov 2024\n\n\n\n\nPress Release\n#KeepItOn Mauritius: global coalition urges first-time offender to end crackdown on social media\n1 Nov 2024\n\n#KeepItOn Mauritius: global coalition urges first-time offender to end crackdown on social media\n\n\n\n\n\n\n\n\n\n\t\t\t\t\tConnectivity\t\t\t\t\n\n\n\n\nConnectivity \n\n\n\t\t\t\tMyanmar residents struggle to overcome severe internet blackouts with Starlink\t\t\t\n\n23 Oct 2024\n\n\n\n\nNews\nMyanmar residents struggle to overcome severe internet blackouts with Starlink\n\n\t\t\t\t\t\t\t\t\tRest of World ↗\t\t\t\t\t\t\t\n↗\n23 Oct 2024\n\nMyanmar residents struggle to overcome severe internet blackouts with Starlink\n\n\n\n\n\n\n\n\n\n\t\t\t\t\tConnectivity\t\t\t\t\n\n\n\n\nConnectivity \n\n\n\t\t\t\tستارلينك في اليمن: لماذا يعارض الحوثيون تفعيل الإنترنت الفضائي؟\t\t\t\n\n1 Oct 2024\n\n\n\n\nNews\nستارلينك في اليمن: لماذا يعارض الحوثيون تفعيل الإنترنت الفضائي؟\n\n\t\t\t\t\t\t\t\t\tBBC ↗\t\t\t\t\t\t\t\n↗\n1 Oct 2024\n\nستارلينك في اليمن: لماذا يعارض الحوثيون تفعيل الإنترنت الفضائي؟\n\n\n\n\n\n\n\n\n\n\t\t\t\t\tInternet Shutdowns\t\t\t\t\n\n\n\n\nInternet Shutdowns \n\n\n\t\t\t\tJoint statement: Sudan has suffered in silence for over 500 days\t\t\t\n\n5 Sep 2024\n • \nAfter more than 500 days of brutal conflict in Sudan, the #KeepItOn coalition reiterates calls to reactivate telecommunication services. Press Release\nJoint statement: Sudan has suffered in silence for over 500 days\n5 Sep 2024\n\nJoint statement: Sudan has suffered in silence for over 500 days\n\n\n\n\n\n\n\n\n\n\t\t\t\t\tInternet Shutdowns\t\t\t\t\n\n\n\n\nInternet Shutdowns \n\n\n\t\t\t\tAfrica in 2023: internet shutdowns attack democracy\t\t\t\n\n26 Aug 2024\n\n\n\n\nPress Release\nAfrica in 2023: internet shutdowns attack democracy\n26 Aug 2024\n\nAfrica in 2023: internet shutdowns attack democracy\n\n\n\n\n\n\n\n\n\n\t\t\t\t\tInternet Shutdowns\t\t\t\t\n\n\n\n\nInternet Shutdowns \n\n\n\t\t\t\t#KeepItOn in Annobón: Authorities in Equatorial Guinea must end internet shutdown and other human rights abuses\t\t\t\n\n13 Aug 2024\n • \nAccess Now and the #KeepItOn coalition are calling on authorities in Equatorial Guinea to immediately restore internet and telecom services in Annobón. Press Release\n#KeepItOn in Annobón: Authorities in Equatorial Guinea must end internet shutdown and other human rights abuses\n13 Aug 2024\n\n#KeepItOn in Annobón: Authorities in Equatorial Guinea must end internet shutdown and other human rights abuses\n\n\n\n\n\n\n\n\n\n\t\t\t\t\tInternet Shutdowns\t\t\t\t\n\n\n\n\nInternet Shutdowns \n\n\n\t\t\t\t#KeepItOn en Annobón: Las autoridades de Guinea Ecuatorial deben poner fin al corte de internet y otros abusos a los derechos humanos\t\t\t\n\n13 Aug 2024\n • \nLa coalición #KeepItOn instan a las autoridades de Guinea Ecuatorial a restablecer de inmediato el acceso a internet en Annobón. Press Release\n#KeepItOn en Annobón: Las autoridades de Guinea Ecuatorial deben poner fin al corte de internet y otros abusos a los derechos humanos\n13 Aug 2024\n\n#KeepItOn en Annobón: Las autoridades de Guinea Ecuatorial deben poner fin al corte de internet y otros abusos a los derechos humanos\n\nLatest Updates\n\n\n\n     \n\n\n\n\n\nGrid View\nList View\n\nLatest Updates\n\nGrid View\nList View\n\nGrid View\nList View\n\nConnectivity\t\t\t\t\n\n\n\n\nConnectivity \n\n\n\t\t\t\tJoint statement: five-point plan for an inclusive WSIS+20 review\t\t\t\n\n29 Mar 2025\n\n\n\n\nPress Release\nJoint statement: five-point plan for an inclusive WSIS+20 review\n\n\n↗\n29 Mar 2025\n\nJoint statement: five-point plan for an inclusive WSIS+20 review\n\n\n\n\n\n\n\n\n\n\t\t\t\t\tConnectivity\t\t\t\t\n\n\n\n\nConnectivity \n\n\n\t\t\t\tOral statement at 10th Session of the UN Open Ended Working Group on ICTs\t\t\t\n\n21 Feb 2025\n • \nAccess Now’s oral statement at the 10th Session of the UN Open Ended Working Group on information and communication technology. Press Release\n#KeepItOn in Tanzania: authorities must ensure connectivity during local elections\n21 Nov 2024\n\n#KeepItOn in Tanzania: authorities must ensure connectivity during local elections\n\n\n\n\n\n\n\n\n\n\t\t\t\t\tInternet Shutdowns\t\t\t\t\n\n\n\n\nInternet Shutdowns \n\n\n\t\t\t\t#KeepItOn: the Government of Tanzania and internet service providers must ensure open and secure internet access throughout the 2024 local elections\t\t\t\n\n21 Nov 2024\n • \nThe #KeepItOn coalition calls on authorities and ISPs in Tanzania to ensure internet access during the upcoming elections. Press Release\n#KeepItOn: the Government of Tanzania and internet service providers must ensure open and secure internet access throughout the 2024 local elections\n21 Nov 2024\n\n#KeepItOn: the Government of Tanzania and internet service providers must ensure open and secure internet access throughout the 2024 local elections\n\n\n\n\n\n\n\n\n\n\t\t\t\t\tConnectivity\t\t\t\t\n\n\n\n\nConnectivity \n\n\n\t\t\t\tAs Israel destroys infrastructure, will Lebanon be cut off from outside world? Connectivity\t\t\t\t\n\n\n\n\nConnectivity \n\n\n\t\t\t\tApple keeps killing VPN apps upon Russia’s orders – Amnezia VPN is the last victim\t\t\t\n\n4 Nov 2024\n\n\n\n\nNews\nApple keeps killing VPN apps upon Russia’s orders – Amnezia VPN is the last victim\n\n\t\t\t\t\t\t\t\t\tTechRadar ↗\t\t\t\t\t\t\t\n↗\n4 Nov 2024\n\nApple keeps killing VPN apps upon Russia’s orders – Amnezia VPN is the last victim\n\n\n\n\n\n\n\n\n\n\t\t\t\t\tInternet Shutdowns\t\t\t\t\n\n\n\n\nInternet Shutdowns \n\n\n\t\t\t\t#KeepItOn Mauritius: global coalition urges first-time offender to end crackdown on social media\t\t\t\n\n1 Nov 2024\n\n\n\n\nPress Release\n#KeepItOn Mauritius: global coalition urges first-time offender to end crackdown on social media\n1 Nov 2024\n\n#KeepItOn Mauritius: global coalition urges first-time offender to end crackdown on social media\n\n\n\n\n\n\n\n\n\n\t\t\t\t\tConnectivity\t\t\t\t\n\n\n\n\nConnectivity \n\n\n\t\t\t\tMyanmar residents struggle to overcome severe internet blackouts with Starlink\t\t\t\n\n23 Oct 2024\n\n\n\n\nNews\nMyanmar residents struggle to overcome severe internet blackouts with Starlink\n\n\t\t\t\t\t\t\t\t\tRest of World ↗\t\t\t\t\t\t\t\n↗\n23 Oct 2024\n\nMyanmar residents struggle to overcome severe internet blackouts with Starlink\n\n\n\n\n\n\n\n\n\n\t\t\t\t\tConnectivity\t\t\t\t\n\n\n\n\nConnectivity \n\n\n\t\t\t\tستارلينك في اليمن: لماذا يعارض الحوثيون تفعيل الإنترنت الفضائي؟\t\t\t\n\n1 Oct 2024\n\n\n\n\nNews\nستارلينك في اليمن: لماذا يعارض الحوثيون تفعيل الإنترنت الفضائي؟\n\n\t\t\t\t\t\t\t\t\tBBC ↗\t\t\t\t\t\t\t\n↗\n1 Oct 2024\n\nستارلينك في اليمن: لماذا يعارض الحوثيون تفعيل الإنترنت الفضائي؟\n\n\n\n\n\n\n\n\n\n\t\t\t\t\tInternet Shutdowns\t\t\t\t\n\n\n\n\nInternet Shutdowns \n\n\n\t\t\t\tJoint statement: Sudan has suffered in silence for over 500 days\t\t\t\n\n5 Sep 2024\n • \nAfter more than 500 days of brutal conflict in Sudan, the #KeepItOn coalition reiterates calls to reactivate telecommunication services. Press Release\nJoint statement: Sudan has suffered in silence for over 500 days\n5 Sep 2024\n\nJoint statement: Sudan has suffered in silence for over 500 days\n\n\n\n\n\n\n\n\n\n\t\t\t\t\tInternet Shutdowns\t\t\t\t\n\n\n\n\nInternet Shutdowns \n\n\n\t\t\t\tAfrica in 2023: internet shutdowns attack democracy\t\t\t\n\n26 Aug 2024\n\n\n\n\nPress Release\nAfrica in 2023: internet shutdowns attack democracy\n26 Aug 2024\n\nAfrica in 2023: internet shutdowns attack democracy\n\n\n\n\n\n\n\n\n\n\t\t\t\t\tInternet Shutdowns\t\t\t\t\n\n\n\n\nInternet Shutdowns \n\n\n\t\t\t\t#KeepItOn in Annobón: Authorities in Equatorial Guinea must end internet shutdown and other human rights abuses\t\t\t\n\n13 Aug 2024\n • \nAccess Now and the #KeepItOn coalition are calling on authorities in Equatorial Guinea to immediately restore internet and telecom services in Annobón. Press Release\n#KeepItOn in Annobón: Authorities in Equatorial Guinea must end internet shutdown and other human rights abuses\n13 Aug 2024\n\n#KeepItOn in Annobón: Authorities in Equatorial Guinea must end internet shutdown and other human rights abuses\n\n\n\n\n\n\n\n\n\n\t\t\t\t\tInternet Shutdowns\t\t\t\t\n\n\n\n\nInternet Shutdowns \n\n\n\t\t\t\t#KeepItOn en Annobón: Las autoridades de Guinea Ecuatorial deben poner fin al corte de internet y otros abusos a los derechos humanos\t\t\t\n\n13 Aug 2024\n • \nLa coalición #KeepItOn instan a las autoridades de Guinea Ecuatorial a restablecer de inmediato el acceso a internet en Annobón. Press Release\n#KeepItOn en Annobón: Las autoridades de Guinea Ecuatorial deben poner fin al corte de internet y otros abusos a los derechos humanos\n13 Aug 2024\n\n#KeepItOn en Annobón: Las autoridades de Guinea Ecuatorial deben poner fin al corte de internet y otros abusos a los derechos humanos\n\nConnectivity\t\t\t\t\n\n\n\n\nConnectivity \n\n\n\t\t\t\tJoint statement: five-point plan for an inclusive WSIS+20 review\t\t\t\n\n29 Mar 2025\n\n\n\n\nPress Release\nJoint statement: five-point plan for an inclusive WSIS+20 review\n\n\n↗\n29 Mar 2025\n\nJoint statement: five-point plan for an inclusive WSIS+20 review\n\nConnectivity\t\t\t\t\n\n\n\n\nConnectivity \n\n\n\t\t\t\tJoint statement: five-point plan for an inclusive WSIS+20 review\t\t\t\n\n29 Mar 2025\n\nConnectivity\n\nConnectivity\n\nConnectivity \n\n\n\t\t\t\tJoint statement: five-point plan for an inclusive WSIS+20 review\t\t\t\n\n29 Mar 2025\n\nConnectivity\n\nConnectivity\n\n29 Mar 2025\n\nPress Release\nJoint statement: five-point plan for an inclusive WSIS+20 review\n\n\n↗\n29 Mar 2025\n\nPress Release\n\nJoint statement: five-point plan for an inclusive WSIS+20 review\n\n↗\n\n29 Mar 2025\n\nConnectivity\t\t\t\t\n\n\n\n\nConnectivity \n\n\n\t\t\t\tOral statement at 10th Session of the UN Open Ended Working Group on ICTs\t\t\t\n\n21 Feb 2025\n • \nAccess Now’s oral statement at the 10th Session of the UN Open Ended Working Group on information and communication technology. Publication\nHolding space for human rights: improving the governance of satellite internet connectivity\n\n\n↗\n5 Feb 2025\n\nHolding space for human rights: improving the governance of satellite internet connectivity\n\nConnectivity\t\t\t\t\n\n\n\n\nConnectivity \n\n\n\t\t\t\tHolding space for human rights: improving the governance of satellite internet connectivity\t\t\t\n\n5 Feb 2025\n • \nFrom obstructed humanitarian access to the weaponization of personal digital devices, internet connectivity is an issue that carries multiple layers of harms\n— one that we are only just starting to unpack. Post\nTackling the “black snakes” undermining digital rights worldwide \n16 Jan 2025\n\nPost\n\nTackling the “black snakes” undermining digital rights worldwide\n\n16 Jan 2025\n\nInternet Shutdowns\t\t\t\t\n\n\n\n\nInternet Shutdowns \n\n\n\t\t\t\t#KeepItOn in Tanzania: authorities must ensure connectivity during local elections\t\t\t\n\n21 Nov 2024\n • \nThe #KeepItOn coalition demands that the Government of Tanzania ensure unhindered access to the internet during the upcoming elections. Press Release\n#KeepItOn in Tanzania: authorities must ensure connectivity during local elections\n21 Nov 2024\n\n#KeepItOn in Tanzania: authorities must ensure connectivity during local elections\n\nInternet Shutdowns\t\t\t\t\n\n\n\n\nInternet Shutdowns \n\n\n\t\t\t\t#KeepItOn in Tanzania: authorities must ensure connectivity during local elections\t\t\t\n\n21 Nov 2024\n • \nThe #KeepItOn coalition demands that the Government of Tanzania ensure unhindered access to the internet during the upcoming elections. Press Release\n#KeepItOn in Tanzania: authorities must ensure connectivity during local elections\n21 Nov 2024\n\nPress Release\n\n#KeepItOn in Tanzania: authorities must ensure connectivity during local elections\n\n21 Nov 2024\n\nInternet Shutdowns\t\t\t\t\n\n\n\n\nInternet Shutdowns \n\n\n\t\t\t\t#KeepItOn: the Government of Tanzania and internet service providers must ensure open and secure internet access throughout the 2024 local elections\t\t\t\n\n21 Nov 2024\n • \nThe #KeepItOn coalition calls on authorities and ISPs in Tanzania to ensure internet access during the upcoming elections. Press Release\n#KeepItOn: the Government of Tanzania and internet service providers must ensure open and secure internet access throughout the 2024 local elections\n21 Nov 2024\n\n#KeepItOn: the Government of Tanzania and internet service providers must ensure open and secure internet access throughout the 2024 local elections\n\nInternet Shutdowns\t\t\t\t\n\n\n\n\nInternet Shutdowns \n\n\n\t\t\t\t#KeepItOn: the Government of Tanzania and internet service providers must ensure open and secure internet access throughout the 2024 local elections\t\t\t\n\n21 Nov 2024\n • \nThe #KeepItOn coalition calls on authorities and ISPs in Tanzania to ensure internet access during the upcoming elections. Internet Shutdowns\n\nInternet Shutdowns\n\nInternet Shutdowns \n\n\n\t\t\t\t#KeepItOn: the Government of Tanzania and internet service providers must ensure open and secure internet access throughout the 2024 local elections\t\t\t\n\n21 Nov 2024\n • \nThe #KeepItOn coalition calls on authorities and ISPs in Tanzania to ensure internet access during the upcoming elections. Press Release\n#KeepItOn: the Government of Tanzania and internet service providers must ensure open and secure internet access throughout the 2024 local elections\n21 Nov 2024\n\nPress Release\n\n#KeepItOn: the Government of Tanzania and internet service providers must ensure open and secure internet access throughout the 2024 local elections\n\n21 Nov 2024\n\nConnectivity\t\t\t\t\n\n\n\n\nConnectivity \n\n\n\t\t\t\tAs Israel destroys infrastructure, will Lebanon be cut off from outside world? The New Arab ↗\n\n↗\n\n15 Nov 2024\n\nConnectivity\t\t\t\t\n\n\n\n\nConnectivity \n\n\n\t\t\t\tApple keeps killing VPN apps upon Russia’s orders – Amnezia VPN is the last victim\t\t\t\n\n4 Nov 2024\n\n\n\n\nNews\nApple keeps killing VPN apps upon Russia’s orders – Amnezia VPN is the last victim\n\n\t\t\t\t\t\t\t\t\tTechRadar ↗\t\t\t\t\t\t\t\n↗\n4 Nov 2024\n\nApple keeps killing VPN apps upon Russia’s orders – Amnezia VPN is the last victim\n\nConnectivity\t\t\t\t\n\n\n\n\nConnectivity \n\n\n\t\t\t\tApple keeps killing VPN apps upon Russia’s orders – Amnezia VPN is the last victim\t\t\t\n\n4 Nov 2024\n\nConnectivity\n\nConnectivity\n\nConnectivity \n\n\n\t\t\t\tApple keeps killing VPN apps upon Russia’s orders – Amnezia VPN is the last victim\t\t\t\n\n4 Nov 2024\n\nConnectivity\n\nConnectivity\n\n4 Nov 2024\n\nNews\nApple keeps killing VPN apps upon Russia’s orders – Amnezia VPN is the last victim\n\n\t\t\t\t\t\t\t\t\tTechRadar ↗\t\t\t\t\t\t\t\n↗\n4 Nov 2024\n\nNews\n\nApple keeps killing VPN apps upon Russia’s orders – Amnezia VPN is the last victim\n\nTechRadar ↗\n\n↗\n\n4 Nov 2024\n\nInternet Shutdowns\t\t\t\t\n\n\n\n\nInternet Shutdowns \n\n\n\t\t\t\t#KeepItOn Mauritius: global coalition urges first-time offender to end crackdown on social media\t\t\t\n\n1 Nov 2024\n\n\n\n\nPress Release\n#KeepItOn Mauritius: global coalition urges first-time offender to end crackdown on social media\n1 Nov 2024\n\n#KeepItOn Mauritius: global coalition urges first-time offender to end crackdown on social media\n\nInternet Shutdowns\t\t\t\t\n\n\n\n\nInternet Shutdowns \n\n\n\t\t\t\t#KeepItOn Mauritius: global coalition urges first-time offender to end crackdown on social media\t\t\t\n\n1 Nov 2024\n\nInternet Shutdowns\n\nInternet Shutdowns\n\nInternet Shutdowns \n\n\n\t\t\t\t#KeepItOn Mauritius: global coalition urges first-time offender to end crackdown on social media\t\t\t\n\n1 Nov 2024\n\nInternet Shutdowns\n\nInternet Shutdowns\n\n1 Nov 2024\n\nPress Release\n#KeepItOn Mauritius: global coalition urges first-time offender to end crackdown on social media\n1 Nov 2024\n\nPress Release\n\n#KeepItOn Mauritius: global coalition urges first-time offender to end crackdown on social media\n\n1 Nov 2024\n\nConnectivity\t\t\t\t\n\n\n\n\nConnectivity \n\n\n\t\t\t\tMyanmar residents struggle to overcome severe internet blackouts with Starlink\t\t\t\n\n23 Oct 2024\n\n\n\n\nNews\nMyanmar residents struggle to overcome severe internet blackouts with Starlink\n\n\t\t\t\t\t\t\t\t\tRest of World ↗\t\t\t\t\t\t\t\n↗\n23 Oct 2024\n\nMyanmar residents struggle to overcome severe internet blackouts with Starlink\n\nConnectivity\t\t\t\t\n\n\n\n\nConnectivity \n\n\n\t\t\t\tMyanmar residents struggle to overcome severe internet blackouts with Starlink\t\t\t\n\n23 Oct 2024\n\nConnectivity\n\nConnectivity\n\nConnectivity \n\n\n\t\t\t\tMyanmar residents struggle to overcome severe internet blackouts with Starlink\t\t\t\n\n23 Oct 2024\n\nConnectivity\n\nConnectivity\n\n23 Oct 2024\n\nNews\nMyanmar residents struggle to overcome severe internet blackouts with Starlink\n\n\t\t\t\t\t\t\t\t\tRest of World ↗\t\t\t\t\t\t\t\n↗\n23 Oct 2024\n\nNews\n\nMyanmar residents struggle to overcome severe internet blackouts with Starlink\n\nRest of World ↗\n\n↗\n\n23 Oct 2024\n\nConnectivity\t\t\t\t\n\n\n\n\nConnectivity \n\n\n\t\t\t\tستارلينك في اليمن: لماذا يعارض الحوثيون تفعيل الإنترنت الفضائي؟\t\t\t\n\n1 Oct 2024\n\n\n\n\nNews\nستارلينك في اليمن: لماذا يعارض الحوثيون تفعيل الإنترنت الفضائي؟\n\n\t\t\t\t\t\t\t\t\tBBC ↗\t\t\t\t\t\t\t\n↗\n1 Oct 2024\n\nستارلينك في اليمن: لماذا يعارض الحوثيون تفعيل الإنترنت الفضائي؟\n\nConnectivity\t\t\t\t\n\n\n\n\nConnectivity \n\n\n\t\t\t\tستارلينك في اليمن: لماذا يعارض الحوثيون تفعيل الإنترنت الفضائي؟\t\t\t\n\n1 Oct 2024\n\nConnectivity\n\nConnectivity\n\nConnectivity \n\n\n\t\t\t\tستارلينك في اليمن: لماذا يعارض الحوثيون تفعيل الإنترنت الفضائي؟\t\t\t\n\n1 Oct 2024\n\nConnectivity\n\nConnectivity\n\n1 Oct 2024\n\nNews\nستارلينك في اليمن: لماذا يعارض الحوثيون تفعيل الإنترنت الفضائي؟\n\n\t\t\t\t\t\t\t\t\tBBC ↗\t\t\t\t\t\t\t\n↗\n1 Oct 2024\n\nNews\n\nستارلينك في اليمن: لماذا يعارض الحوثيون تفعيل الإنترنت الفضائي؟\n\nBBC ↗\n\n↗\n\n1 Oct 2024\n\nInternet Shutdowns\t\t\t\t\n\n\n\n\nInternet Shutdowns \n\n\n\t\t\t\tJoint statement: Sudan has suffered in silence for over 500 days\t\t\t\n\n5 Sep 2024\n • \nAfter more than 500 days of brutal conflict in Sudan, the #KeepItOn coalition reiterates calls to reactivate telecommunication services. Press Release\nJoint statement: Sudan has suffered in silence for over 500 days\n5 Sep 2024\n\nPress Release\n\nJoint statement: Sudan has suffered in silence for over 500 days\n\n5 Sep 2024\n\nInternet Shutdowns\t\t\t\t\n\n\n\n\nInternet Shutdowns \n\n\n\t\t\t\tAfrica in 2023: internet shutdowns attack democracy\t\t\t\n\n26 Aug 2024\n\n\n\n\nPress Release\nAfrica in 2023: internet shutdowns attack democracy\n26 Aug 2024\n\nAfrica in 2023: internet shutdowns attack democracy\n\nInternet Shutdowns\t\t\t\t\n\n\n\n\nInternet Shutdowns \n\n\n\t\t\t\tAfrica in 2023: internet shutdowns attack democracy\t\t\t\n\n26 Aug 2024\n\nInternet Shutdowns\n\nInternet Shutdowns\n\nInternet Shutdowns \n\n\n\t\t\t\tAfrica in 2023: internet shutdowns attack democracy\t\t\t\n\n26 Aug 2024\n\nInternet Shutdowns\n\nInternet Shutdowns\n\n26 Aug 2024\n\nPress Release\nAfrica in 2023: internet shutdowns attack democracy\n26 Aug 2024\n\nPress Release\n\nAfrica in 2023: internet shutdowns attack democracy\n\n26 Aug 2024\n\nInternet Shutdowns\t\t\t\t\n\n\n\n\nInternet Shutdowns \n\n\n\t\t\t\t#KeepItOn in Annobón: Authorities in Equatorial Guinea must end internet shutdown and other human rights abuses\t\t\t\n\n13 Aug 2024\n • \nAccess Now and the #KeepItOn coalition are calling on authorities in Equatorial Guinea to immediately restore internet and telecom services in Annobón. Press Release\n#KeepItOn in Annobón: Authorities in Equatorial Guinea must end internet shutdown and other human rights abuses\n13 Aug 2024\n\n#KeepItOn in Annobón: Authorities in Equatorial Guinea must end internet shutdown and other human rights abuses\n\nInternet Shutdowns\t\t\t\t\n\n\n\n\nInternet Shutdowns \n\n\n\t\t\t\t#KeepItOn in Annobón: Authorities in Equatorial Guinea must end internet shutdown and other human rights abuses\t\t\t\n\n13 Aug 2024\n • \nAccess Now and the #KeepItOn coalition are calling on authorities in Equatorial Guinea to immediately restore internet and telecom services in Annobón. Internet Shutdowns\n\nInternet Shutdowns\n\nInternet Shutdowns \n\n\n\t\t\t\t#KeepItOn in Annobón: Authorities in Equatorial Guinea must end internet shutdown and other human rights abuses\t\t\t\n\n13 Aug 2024\n • \nAccess Now and the #KeepItOn coalition are calling on authorities in Equatorial Guinea to immediately restore internet and telecom services in Annobón. Press Release\n#KeepItOn in Annobón: Authorities in Equatorial Guinea must end internet shutdown and other human rights abuses\n13 Aug 2024\n\nPress Release\n\n#KeepItOn in Annobón: Authorities in Equatorial Guinea must end internet shutdown and other human rights abuses\n\n13 Aug 2024\n\nInternet Shutdowns\t\t\t\t\n\n\n\n\nInternet Shutdowns \n\n\n\t\t\t\t#KeepItOn en Annobón: Las autoridades de Guinea Ecuatorial deben poner fin al corte de internet y otros abusos a los derechos humanos\t\t\t\n\n13 Aug 2024\n • \nLa coalición #KeepItOn instan a las autoridades de Guinea Ecuatorial a restablecer de inmediato el acceso a internet en Annobón. Press Release\n#KeepItOn en Annobón: Las autoridades de Guinea Ecuatorial deben poner fin al corte de internet y otros abusos a los derechos humanos\n13 Aug 2024\n\n#KeepItOn en Annobón: Las autoridades de Guinea Ecuatorial deben poner fin al corte de internet y otros abusos a los derechos humanos\n\nInternet Shutdowns\t\t\t\t\n\n\n\n\nInternet Shutdowns \n\n\n\t\t\t\t#KeepItOn en Annobón: Las autoridades de Guinea Ecuatorial deben poner fin al corte de internet y otros abusos a los derechos humanos\t\t\t\n\n13 Aug 2024\n • \nLa coalición #KeepItOn instan a las autoridades de Guinea Ecuatorial a restablecer de inmediato el acceso a internet en Annobón.",
  "entities": {
    "countries": [
      "afghanistan",
      "australia",
      "brazil",
      "canada",
      "china",
      "france",
      "germany",
      "india",
      "iran",
      "iraq",
      "israel",
      "japan",
      "mexico",
      "north korea",
      "pakistan",
      "russia",
      "south korea",
      "syria",
      "united kingdom",
      "united states",
      "yemen"
    ],
    "organizations": [
      "un"
    ],
    "key_issues": [
      "issue",
      "crisis",
      "country",
      "state",
      "government",
      "territory",
      "action",
      "humanitarian",
      "human rights",
      "un",
      "ngo",
      "organization"
    ]
  },
  "committee": "First Committee",
  "topic": "Creating systems to protect against state-sponsored cyber attacks"
}