{
  "url": "https://www.accessnow.org/help/",
  "title": "DIGITAL SECURITY HELPLINE - Access Now",
  "text": "Back to content\n\nDIGITAL SECURITY HELPLINE\n\n\n\n\n\nHow We Help\nWho Can We Help\nContact Us\nCommunity & Resources\n\n\n\nWHAT IS THE DIGITAL SECURITY HELPLINE?\n\n\nAvailable translations:\n\n Pусский Español Português العربية Français Deutsch Italiano Tagalog українська \n\n\n\n\nAccess Now’s Digital Security Helpline works with individuals and organizations around the world to keep them safe online. If you’re at risk, we can help you improve your digital security practices to keep out of harm’s way. If you’re already under attack, we provide rapid-response emergency assistance.\n\n\n\n\n\n\n\n\n\nCONTACT US\n\n\n\n\nOur 24/7 services are available with support in nine languages: English, Spanish, French, German, Portuguese, Russian, Tagalog, Arabic, and Italian. We respond to all requests within two hours.\n\n\n\n\nHOW CAN WE HELP YOU?\nWe are a free-of-charge resource for civil society around the world. We offer real-time, direct technical assistance and advice to civil society groups & activists, media organizations, journalists & bloggers, and human rights defenders.\nThe Helpline will walk you or your organization through assessing the risks you face in your work, and  together we’ll prioritize your digital security needs. We’ll help you resolve existing problems, teach you some of the most important best practices, and help you get into a secure mindset for the future.\n\n\n\n\nWHO CAN WE HELP?\nBefore we can provide any support, we will conduct an initial process to verify that supporting you is within our mandate. You can read more about our vetting process and determine whether you are elegible for support here. These are some of the groups we can assist:\n\n\n\n\n\n\n\n\n\n\n\nIf you are targeted based on your work or activism, we can help you protect your communications, secure your online accounts, and keep your sensitive information safe.            \n\n\n\n\n\nCase: Supporters of Mexico’s soda tax targeted with spyware Citizen Lab\n\n\n\n\n\n\n\n\n\n\n\n\n\n\n\n\nHas your news site been blocked or taken offline? Need help communicating securely with editors and sources? We can help.  \n\n\n\n\n\nCase: Journalists in Armenia locked out of Twitter accounts.Coda\n\n\n\n\n\n\n\n\n\n\n\n\n\n\n\n\nWhether you need to protect your communications with your partners, securely store evidence or other sensitive data, or stay safe when you travel, we’re here to assist you.\n\n\n\n\n\nCase: Human rights defenders in Azerbaijan fend off malware attacks – Amnesty International\n\n\n\n\n\n\n\n\n\nOUR SERVICES\n\n\n24/7, real-time, direct technical assistance and advice\n\n\n\n\n\n\n\n\n\n\n\nNo matter what digital security challenges you face, we offer a range of services and resources to help you be safe online:\n\n\n\n\n\n\n\n\n\n\n\n\nRapid response for digital security incidents\n\n\n\n\n\n\n\n\nPersonalized recommendations, instruction, and follow-up support for digital security issues\n\n\n\n\n\n\n\n\nHelp assessing risks and creating organizational or community security strategies\n\n\n\n\n\n\n\n\nGuidance and educational materials on security practices and tools for organizations, communities, groups, and individuals\n\n\n\n\n\n\n\n\nSupport for securing technical infrastructure, websites, and social media against attacks\n\n\n\n\n\n\n\n\nReferrals, capacity-building, in-person consultations, and training\n\n\n\n\n\n\n\n\n\nDIGITAL SECURITY CLINIC\n\n\n\nAccess Now’s Digital Security Clinic brings the Helpline to you.\nOur technologists run clinics at conferences and events around the world, where attendees can raise questions and get immediate help.\n\n\n\n\nHOW TO CONTACT US?\n\n\n\n\n\n[email protected]\n\nPGP PUBLIC KEY\n\nFingerprint: 6CE6 221C 98EC F399 A04C 41B8 C46B ED33 32E8 A2BC\n\n\nWe commit to using the best practices in the field when we collect, store, and use sensitive information. For more information about how we protect your personal data, and our Helpline Terms of Service, please read our Data Usage Policy.\n\n\n\n\n\n\n\n\n\n\nWHERE IS THE HELPLINE?\n\n\n\n\n\n\n\n\n\n\n\n\n\nLatin America and the Caribbean\nAlex Argüelles\nHolistic Security Lead\n\n\n\n\nLatin America and the Caribbean\nAlex Argüelles\nHolistic Security Lead\nHelpline\n\n\n\n\n\n\n\n\n\n\n\n\nEurope\nBeatrice Martini\nEducation and Communities Lead\n\n\n\n\nEurope\nBeatrice Martini\nEducation and Communities Lead\nHelpline\n\n\n\n\n\n\n\n\n\n\n\n\nAsia Pacific\nDhyta Caturani\nHelpline SEA Regional Coordinator\n\n\n\n\nAsia Pacific\nDhyta Caturani\nHelpline SEA Regional Coordinator\nHelpline\n\n\n\n\n\n\n\n\n\n\n\n\nAfrica\nDoreen Ochung\nSecurity Incident Handler\n\n\n\n\nAfrica\nDoreen Ochung\nSecurity Incident Handler\nHelpline\n\n\n\n\n\n\n\n\n\n\n\n\nInternational\nHassen Selmi\nIncident Response Lead\n\n\n\n\nInternational\nHassen Selmi\nIncident Response Lead\nHelpline\n\n\n\n\n\n\n\n\n\n\n\n\nLatin America and the Caribbean\nJean Carlo Lara\nSecurity Incident Handler\n\n\n\n\nLatin America and the Caribbean\nJean Carlo Lara\nSecurity Incident Handler\nHelpline\n\n\n\n\n\n\n\n\n\n\n\n\nEurope\nLuis Barrueto\nAdministrative and Communications Coordinator \n\n\n\n\nEurope\nLuis Barrueto\nAdministrative and Communications Coordinator \nHelpline\n\n\n\n\n\n\n\n\n\n\n\n\nInternational\nMag\nSecurity Incident Handler\n\n\n\n\nInternational\nMag\nSecurity Incident Handler\nHelpline\n\n\n\n\n\n\n\n\n\n\n\n\nInternational\nMaggie\nHelpline Documentation Coordinator\n\n\n\n\nInternational\nMaggie\nHelpline Documentation Coordinator\nHelpline\n\n\n\n\n\n\n\n\n\n\n\n\nInternational\nMalika Sharif\nSecurity Incident Handler\n\n\n\n\nInternational\nMalika Sharif\nSecurity Incident Handler\nHelpline\n\n\n\n\n\n\n\n\n\n\n\n\nAsia Pacific\nMarilou Maala\nIncident Response Analyst\n\n\n\n\nAsia Pacific\nMarilou Maala\nIncident Response Analyst\nHelpline\n\n\n\n\n\n\n\n\n\n\n\n\nAsia Pacific\nMarionne Sarmiento\nDigital Safety Specialist\n\n\n\n\nAsia Pacific\nMarionne Sarmiento\nDigital Safety Specialist\nHelpline\n\n\n\n\n\n\n\n\n\n\n\n\nInternational\nMaxim Petrov\nSafety Specialist\n\n\n\n\nInternational\nMaxim Petrov\nSafety Specialist\nHelpline\n\n\n\n\n\n\n\n\n\n\n\n\nInternational\nMohammed Al-Maskati\nDigital Security Helpline Director\n\n\n\n\nInternational\nMohammed Al-Maskati\nDigital Security Helpline Director\nHelpline\n\n\n\n\n\n\n\n\n\n\n\n\nInternational\nOleg Serov\nSecurity Incident Handler\n\n\n\n\nInternational\nOleg Serov\nSecurity Incident Handler\nHelpline\n\n\n\n\n\n\n\n\n\n\n\n\nLatin America and the Caribbean\nRocío\nSecurity Incident Handler\n\n\n\n\nLatin America and the Caribbean\nRocío\nSecurity Incident Handler\nHelpline\n\n\n\n\n\n\n\n\n\n\n\n\nLatin America and the Caribbean\nRogelio López\nSan José Security Shift Lead\n\n\n\n\nLatin America and the Caribbean\nRogelio López\nSan José Security Shift Lead\nHelpline\n\n\n\n\n\n\n\n\n\n\n\n\nAsia Pacific\nShinte Galeshka\nSecurity Incident Handler\n\n\n\n\nAsia Pacific\nShinte Galeshka\nSecurity Incident Handler\nHelpline\n\n\n\n\n\n\n\n\n\nEurope\nVeronica Zaboia\nPlatform Engagement Coordinator\n\n\n\n\nEurope\nVeronica Zaboia\nPlatform Engagement Coordinator\nHelpline\n\n\n\n\n\n\n\n\n\n\n\n\nInternational\nVictor Novikov\nDigital Security Helpline Manager\n\n\n\n\nInternational\nVictor Novikov\nDigital Security Helpline Manager\nHelpline\n\n\n\n\n\n\n\n\n\n\n\n\nInternational\nVlad\nSecurity Incident Handler\n\n\n\n\nInternational\nVlad\nSecurity Incident Handler\nHelpline\n\n\n\n\n\n\n\n\n\n\nCOMMUNITY & RESOURCES\n\n\n\n\n\n\n\n\n\n\n\n\n\n\n\n\n\n\n\nAccess Now’s Digital Security Helpline is a member of the Civil Society Computer Emergency Response Team (CiviCERT), an accredited CERT focused on improving the incident response capabilities of civil society groups and individuals around the world.\nCiviCERT is an initiative of Rapid Response Network (RaReNet), a network of non-governmental organizations, internet content and service providers, and individuals who contribute their time and resources to globally improve the security awareness of civil society groups.\n\n\n\nAs part of Access Now’s work and in collaboration with the broader community, we create and contribute to guides and materials to help communities, organizations, and individuals improve their digital security. These guides target a spectrum of users, from non-technical users to website administrators. Please find some guides below:\n\nDigital First Aid Kit\nA resource for emergency situations, such as when your social media account is compromised, your website is attacked, or your computer is infected \n\nHelpline PGP Email Encryption Guides (Windows | Mac | Linux)\nGuides for setting up encrypted email \n\nHelpline Safer Travel Guide\nHelping you prepare for travels to high-risk countries \n\nHelpline Self-Doxing Guide\nTips and resources for exploring open source intelligence on oneself to prevent online doxing \n\nHelpline Community Documentation\nThe procedures and documentation we create to aid our work on the Helpline \n\nPartner organizations have produced a number of guides and resources that we find valuable in our work, and you may too. They include: \n\nSecurity in a Box\nFrom Frontline Defenders and the Tactical Technology Collective \n\nSurveillance Self-Defense\nFrom the Electronic Frontier Foundation \n\nUmbrella\nFrom Security First \n\n\n\n\n\n\n\n \n\n\n\n\n\n\nHelp keep the internet open and secure.\nSubscribe to our action alerts and weekly newsletter\n\"*\" indicates required fields\n\nThis field is hidden when viewing the form\n\nSubscribe to Access Express\nThis field is hidden when viewing the form\n\nSubscribe to Action Alerts\nName\n\n\nFirst\n\n\n\nLast\n\nEmail*\n\nCountryCountryAfghanistanÅland IslandsAlbaniaAlgeriaAmerican SamoaAndorraAngolaAnguillaAntigua and BarbudaArgentinaArmeniaArubaAustraliaAustriaAzerbaijanBahamasBahrainBangladeshBarbadosBelarusBelgiumBelizeBeninBermudaBhutanBoliviaBonaire, Sint Eustatius and SabaBosnia and HerzegovinaBotswanaBrazilBritish Indian Ocean TerritoryBritish Virgin IslandsBruneiBulgariaBurkina FasoBurundiCambodiaCameroonCanadaCape VerdeCayman IslandsCentral African RepublicChadChileChinaChristmas IslandColombiaComorosCook IslandsCosta RicaCôte d'IvoireCroatiaCubaCuraçaoCyprusCzech RepublicDemocratic Republic of the CongoDenmarkDjiboutiDominicaDominican RepublicEast TimorEcuadorEgyptEl SalvadorEquatorial GuineaEritreaEstoniaEswatiniEthiopiaFalkland IslandsFaroe IslandsFijiFinlandFranceFrench GuianaFrench PolynesiaFrench Southern TerritoriesGabonGeorgiaGermanyGhanaGibraltarGreeceGreenlandGrenadaGuadeloupeGuamGuatemalaGuernseyGuineaGuinea-BissauGuyanaHaitiHondurasHong KongHungaryIcelandIndiaIndonesiaIranIraqIrelandIsraelItalyJamaicaJapanJordanKazakhstanKenyaKiribatiKosovoKuwaitKyrgyzstanLaosLatviaLebanonLesothoLiberiaLibyaLiechtensteinLithuaniaLuxembourgMacauMadagascarMalawiMalaysiaMaldivesMaliMaltaMarshall IslandsMartiniqueMauritaniaMauritiusMayotteMexicoMicronesiaMoldovaMonacoMongoliaMontenegroMontserratMoroccoMozambiqueMyanmarNamibiaNauruNepalNetherlands AntillesNew CaledoniaNew ZealandNicaraguaNigerNigeriaNiueNorfolk IslandNorth KoreaNorth MacedoniaNorthern Mariana IslandsNorwayOmanPakistanPalauPalestinePanamaPapua New GuineaParaguayPeruPhilippinesPitcairn IslandPolandPortugalPuerto RicoQatarRepublic of the CongoReunionRomaniaRussiaRwandaSaint BarthélemySaint Kitts and NevisSaint LuciaSaint Vincent and the GrenadinesSamoaSan MarinoSão Tomé and PríncipeSaudi ArabiaSenegalSerbiaSeychellesSierra LeoneSingaporeSlovakiaSloveniaSolomon IslandsSomaliaSomalilandSouth AfricaSouth KoreaSouth SudanSpainSri LankaSt. HelenaSt. Pierre and MiquelonSudanSurinameSwedenSwitzerlandSyriaTaiwanTajikistanTanzaniaThailandThe GambiaThe NetherlandsTogoTokelauTongaTrinidad and TobagoTunisiaTurkeyTurkmenistanTurks and Caicos IslandsTuvaluUgandaUkraineUnited Arab EmiratesUnited KingdomUnited StatesUruguayUzbekistanVanuatuVatican CityVenezuelaVietnamVirgin Islands (U.S.)Wallis and Futuna IslandsWestern SaharaYemenZambiaZimbabwePostal CodeCommentsThis field is for validation purposes and should be left unchanged.\n \n\n\n\n\n\n\n\n\n\n\n\n\n\n\n\nYour info is secure with us\n\nDIGITAL SECURITY HELPLINE\n\n\n\n\n\nHow We Help\nWho Can We Help\nContact Us\nCommunity & Resources\n\n\n\nWHAT IS THE DIGITAL SECURITY HELPLINE?\n\n\nAvailable translations:\n\n Pусский Español Português العربية Français Deutsch Italiano Tagalog українська \n\n\n\n\nAccess Now’s Digital Security Helpline works with individuals and organizations around the world to keep them safe online. If you’re at risk, we can help you improve your digital security practices to keep out of harm’s way. If you’re already under attack, we provide rapid-response emergency assistance.\n\n\n\n\n\n\n\n\n\nCONTACT US\n\n\n\n\nOur 24/7 services are available with support in nine languages: English, Spanish, French, German, Portuguese, Russian, Tagalog, Arabic, and Italian. We respond to all requests within two hours.\n\n\n\n\nHOW CAN WE HELP YOU?\nWe are a free-of-charge resource for civil society around the world. We offer real-time, direct technical assistance and advice to civil society groups & activists, media organizations, journalists & bloggers, and human rights defenders.\nThe Helpline will walk you or your organization through assessing the risks you face in your work, and  together we’ll prioritize your digital security needs. We’ll help you resolve existing problems, teach you some of the most important best practices, and help you get into a secure mindset for the future.\n\n\n\n\nWHO CAN WE HELP?\nBefore we can provide any support, we will conduct an initial process to verify that supporting you is within our mandate. You can read more about our vetting process and determine whether you are elegible for support here. These are some of the groups we can assist:\n\n\n\n\n\n\n\n\n\n\n\nIf you are targeted based on your work or activism, we can help you protect your communications, secure your online accounts, and keep your sensitive information safe.            \n\n\n\n\n\nCase: Supporters of Mexico’s soda tax targeted with spyware Citizen Lab\n\n\n\n\n\n\n\n\n\n\n\n\n\n\n\n\nHas your news site been blocked or taken offline? Need help communicating securely with editors and sources? We can help.  \n\n\n\n\n\nCase: Journalists in Armenia locked out of Twitter accounts.Coda\n\n\n\n\n\n\n\n\n\n\n\n\n\n\n\n\nWhether you need to protect your communications with your partners, securely store evidence or other sensitive data, or stay safe when you travel, we’re here to assist you.\n\n\n\n\n\nCase: Human rights defenders in Azerbaijan fend off malware attacks – Amnesty International\n\n\n\n\n\n\n\n\n\nOUR SERVICES\n\n\n24/7, real-time, direct technical assistance and advice\n\n\n\n\n\n\n\n\n\n\n\nNo matter what digital security challenges you face, we offer a range of services and resources to help you be safe online:\n\n\n\n\n\n\n\n\n\n\n\n\nRapid response for digital security incidents\n\n\n\n\n\n\n\n\nPersonalized recommendations, instruction, and follow-up support for digital security issues\n\n\n\n\n\n\n\n\nHelp assessing risks and creating organizational or community security strategies\n\n\n\n\n\n\n\n\nGuidance and educational materials on security practices and tools for organizations, communities, groups, and individuals\n\n\n\n\n\n\n\n\nSupport for securing technical infrastructure, websites, and social media against attacks\n\n\n\n\n\n\n\n\nReferrals, capacity-building, in-person consultations, and training\n\n\n\n\n\n\n\n\n\nDIGITAL SECURITY CLINIC\n\n\n\nAccess Now’s Digital Security Clinic brings the Helpline to you.\nOur technologists run clinics at conferences and events around the world, where attendees can raise questions and get immediate help.\n\n\n\n\nHOW TO CONTACT US?\n\n\n\n\n\n[email protected]\n\nPGP PUBLIC KEY\n\nFingerprint: 6CE6 221C 98EC F399 A04C 41B8 C46B ED33 32E8 A2BC\n\n\nWe commit to using the best practices in the field when we collect, store, and use sensitive information. For more information about how we protect your personal data, and our Helpline Terms of Service, please read our Data Usage Policy.\n\n\n\n\n\n\n\n\n\n\nWHERE IS THE HELPLINE?\n\n\n\n\n\n\n\n\n\n\n\n\n\nLatin America and the Caribbean\nAlex Argüelles\nHolistic Security Lead\n\n\n\n\nLatin America and the Caribbean\nAlex Argüelles\nHolistic Security Lead\nHelpline\n\n\n\n\n\n\n\n\n\n\n\n\nEurope\nBeatrice Martini\nEducation and Communities Lead\n\n\n\n\nEurope\nBeatrice Martini\nEducation and Communities Lead\nHelpline\n\n\n\n\n\n\n\n\n\n\n\n\nAsia Pacific\nDhyta Caturani\nHelpline SEA Regional Coordinator\n\n\n\n\nAsia Pacific\nDhyta Caturani\nHelpline SEA Regional Coordinator\nHelpline\n\n\n\n\n\n\n\n\n\n\n\n\nAfrica\nDoreen Ochung\nSecurity Incident Handler\n\n\n\n\nAfrica\nDoreen Ochung\nSecurity Incident Handler\nHelpline\n\n\n\n\n\n\n\n\n\n\n\n\nInternational\nHassen Selmi\nIncident Response Lead\n\n\n\n\nInternational\nHassen Selmi\nIncident Response Lead\nHelpline\n\n\n\n\n\n\n\n\n\n\n\n\nLatin America and the Caribbean\nJean Carlo Lara\nSecurity Incident Handler\n\n\n\n\nLatin America and the Caribbean\nJean Carlo Lara\nSecurity Incident Handler\nHelpline\n\n\n\n\n\n\n\n\n\n\n\n\nEurope\nLuis Barrueto\nAdministrative and Communications Coordinator \n\n\n\n\nEurope\nLuis Barrueto\nAdministrative and Communications Coordinator \nHelpline\n\n\n\n\n\n\n\n\n\n\n\n\nInternational\nMag\nSecurity Incident Handler\n\n\n\n\nInternational\nMag\nSecurity Incident Handler\nHelpline\n\n\n\n\n\n\n\n\n\n\n\n\nInternational\nMaggie\nHelpline Documentation Coordinator\n\n\n\n\nInternational\nMaggie\nHelpline Documentation Coordinator\nHelpline\n\n\n\n\n\n\n\n\n\n\n\n\nInternational\nMalika Sharif\nSecurity Incident Handler\n\n\n\n\nInternational\nMalika Sharif\nSecurity Incident Handler\nHelpline\n\n\n\n\n\n\n\n\n\n\n\n\nAsia Pacific\nMarilou Maala\nIncident Response Analyst\n\n\n\n\nAsia Pacific\nMarilou Maala\nIncident Response Analyst\nHelpline\n\n\n\n\n\n\n\n\n\n\n\n\nAsia Pacific\nMarionne Sarmiento\nDigital Safety Specialist\n\n\n\n\nAsia Pacific\nMarionne Sarmiento\nDigital Safety Specialist\nHelpline\n\n\n\n\n\n\n\n\n\n\n\n\nInternational\nMaxim Petrov\nSafety Specialist\n\n\n\n\nInternational\nMaxim Petrov\nSafety Specialist\nHelpline\n\n\n\n\n\n\n\n\n\n\n\n\nInternational\nMohammed Al-Maskati\nDigital Security Helpline Director\n\n\n\n\nInternational\nMohammed Al-Maskati\nDigital Security Helpline Director\nHelpline\n\n\n\n\n\n\n\n\n\n\n\n\nInternational\nOleg Serov\nSecurity Incident Handler\n\n\n\n\nInternational\nOleg Serov\nSecurity Incident Handler\nHelpline\n\n\n\n\n\n\n\n\n\n\n\n\nLatin America and the Caribbean\nRocío\nSecurity Incident Handler\n\n\n\n\nLatin America and the Caribbean\nRocío\nSecurity Incident Handler\nHelpline\n\n\n\n\n\n\n\n\n\n\n\n\nLatin America and the Caribbean\nRogelio López\nSan José Security Shift Lead\n\n\n\n\nLatin America and the Caribbean\nRogelio López\nSan José Security Shift Lead\nHelpline\n\n\n\n\n\n\n\n\n\n\n\n\nAsia Pacific\nShinte Galeshka\nSecurity Incident Handler\n\n\n\n\nAsia Pacific\nShinte Galeshka\nSecurity Incident Handler\nHelpline\n\n\n\n\n\n\n\n\n\nEurope\nVeronica Zaboia\nPlatform Engagement Coordinator\n\n\n\n\nEurope\nVeronica Zaboia\nPlatform Engagement Coordinator\nHelpline\n\n\n\n\n\n\n\n\n\n\n\n\nInternational\nVictor Novikov\nDigital Security Helpline Manager\n\n\n\n\nInternational\nVictor Novikov\nDigital Security Helpline Manager\nHelpline\n\n\n\n\n\n\n\n\n\n\n\n\nInternational\nVlad\nSecurity Incident Handler\n\n\n\n\nInternational\nVlad\nSecurity Incident Handler\nHelpline\n\n\n\n\n\n\n\n\n\n\nCOMMUNITY & RESOURCES\n\n\n\n\n\n\n\n\n\n\n\n\n\n\n\n\n\n\n\nAccess Now’s Digital Security Helpline is a member of the Civil Society Computer Emergency Response Team (CiviCERT), an accredited CERT focused on improving the incident response capabilities of civil society groups and individuals around the world.\nCiviCERT is an initiative of Rapid Response Network (RaReNet), a network of non-governmental organizations, internet content and service providers, and individuals who contribute their time and resources to globally improve the security awareness of civil society groups.\n\n\n\nAs part of Access Now’s work and in collaboration with the broader community, we create and contribute to guides and materials to help communities, organizations, and individuals improve their digital security. These guides target a spectrum of users, from non-technical users to website administrators. Please find some guides below:\n\nDigital First Aid Kit\nA resource for emergency situations, such as when your social media account is compromised, your website is attacked, or your computer is infected \n\nHelpline PGP Email Encryption Guides (Windows | Mac | Linux)\nGuides for setting up encrypted email \n\nHelpline Safer Travel Guide\nHelping you prepare for travels to high-risk countries \n\nHelpline Self-Doxing Guide\nTips and resources for exploring open source intelligence on oneself to prevent online doxing \n\nHelpline Community Documentation\nThe procedures and documentation we create to aid our work on the Helpline \n\nPartner organizations have produced a number of guides and resources that we find valuable in our work, and you may too. They include: \n\nSecurity in a Box\nFrom Frontline Defenders and the Tactical Technology Collective \n\nSurveillance Self-Defense\nFrom the Electronic Frontier Foundation \n\nUmbrella\nFrom Security First\n\nDIGITAL SECURITY HELPLINE\n\n\n\n\n\nHow We Help\nWho Can We Help\nContact Us\nCommunity & Resources\n\n\n\nWHAT IS THE DIGITAL SECURITY HELPLINE?\n\n\nAvailable translations:\n\n Pусский Español Português العربية Français Deutsch Italiano Tagalog українська \n\n\n\n\nAccess Now’s Digital Security Helpline works with individuals and organizations around the world to keep them safe online. If you’re at risk, we can help you improve your digital security practices to keep out of harm’s way. If you’re already under attack, we provide rapid-response emergency assistance.\n\n\n\n\n\n\n\n\n\nCONTACT US\n\n\n\n\nOur 24/7 services are available with support in nine languages: English, Spanish, French, German, Portuguese, Russian, Tagalog, Arabic, and Italian. We respond to all requests within two hours.\n\n\n\n\nHOW CAN WE HELP YOU?\nWe are a free-of-charge resource for civil society around the world. We offer real-time, direct technical assistance and advice to civil society groups & activists, media organizations, journalists & bloggers, and human rights defenders.\nThe Helpline will walk you or your organization through assessing the risks you face in your work, and  together we’ll prioritize your digital security needs. We’ll help you resolve existing problems, teach you some of the most important best practices, and help you get into a secure mindset for the future.\n\n\n\n\nWHO CAN WE HELP?\nBefore we can provide any support, we will conduct an initial process to verify that supporting you is within our mandate. You can read more about our vetting process and determine whether you are elegible for support here. These are some of the groups we can assist:\n\n\n\n\n\n\n\n\n\n\n\nIf you are targeted based on your work or activism, we can help you protect your communications, secure your online accounts, and keep your sensitive information safe.            \n\n\n\n\n\nCase: Supporters of Mexico’s soda tax targeted with spyware Citizen Lab\n\n\n\n\n\n\n\n\n\n\n\n\n\n\n\n\nHas your news site been blocked or taken offline? Need help communicating securely with editors and sources? We can help.  \n\n\n\n\n\nCase: Journalists in Armenia locked out of Twitter accounts.Coda\n\n\n\n\n\n\n\n\n\n\n\n\n\n\n\n\nWhether you need to protect your communications with your partners, securely store evidence or other sensitive data, or stay safe when you travel, we’re here to assist you.\n\n\n\n\n\nCase: Human rights defenders in Azerbaijan fend off malware attacks – Amnesty International\n\n\n\n\n\n\n\n\n\nOUR SERVICES\n\n\n24/7, real-time, direct technical assistance and advice\n\n\n\n\n\n\n\n\n\n\n\nNo matter what digital security challenges you face, we offer a range of services and resources to help you be safe online:\n\n\n\n\n\n\n\n\n\n\n\n\nRapid response for digital security incidents\n\n\n\n\n\n\n\n\nPersonalized recommendations, instruction, and follow-up support for digital security issues\n\n\n\n\n\n\n\n\nHelp assessing risks and creating organizational or community security strategies\n\n\n\n\n\n\n\n\nGuidance and educational materials on security practices and tools for organizations, communities, groups, and individuals\n\n\n\n\n\n\n\n\nSupport for securing technical infrastructure, websites, and social media against attacks\n\n\n\n\n\n\n\n\nReferrals, capacity-building, in-person consultations, and training\n\n\n\n\n\n\n\n\n\nDIGITAL SECURITY CLINIC\n\n\n\nAccess Now’s Digital Security Clinic brings the Helpline to you.\nOur technologists run clinics at conferences and events around the world, where attendees can raise questions and get immediate help.\n\n\n\n\nHOW TO CONTACT US?\n\n\n\n\n\n[email protected]\n\nPGP PUBLIC KEY\n\nFingerprint: 6CE6 221C 98EC F399 A04C 41B8 C46B ED33 32E8 A2BC\n\n\nWe commit to using the best practices in the field when we collect, store, and use sensitive information. For more information about how we protect your personal data, and our Helpline Terms of Service, please read our Data Usage Policy.\n\n\n\n\n\n\n\n\n\n\nWHERE IS THE HELPLINE?\n\n\n\n\n\n\n\n\n\n\n\n\n\nLatin America and the Caribbean\nAlex Argüelles\nHolistic Security Lead\n\n\n\n\nLatin America and the Caribbean\nAlex Argüelles\nHolistic Security Lead\nHelpline\n\n\n\n\n\n\n\n\n\n\n\n\nEurope\nBeatrice Martini\nEducation and Communities Lead\n\n\n\n\nEurope\nBeatrice Martini\nEducation and Communities Lead\nHelpline\n\n\n\n\n\n\n\n\n\n\n\n\nAsia Pacific\nDhyta Caturani\nHelpline SEA Regional Coordinator\n\n\n\n\nAsia Pacific\nDhyta Caturani\nHelpline SEA Regional Coordinator\nHelpline\n\n\n\n\n\n\n\n\n\n\n\n\nAfrica\nDoreen Ochung\nSecurity Incident Handler\n\n\n\n\nAfrica\nDoreen Ochung\nSecurity Incident Handler\nHelpline\n\n\n\n\n\n\n\n\n\n\n\n\nInternational\nHassen Selmi\nIncident Response Lead\n\n\n\n\nInternational\nHassen Selmi\nIncident Response Lead\nHelpline\n\n\n\n\n\n\n\n\n\n\n\n\nLatin America and the Caribbean\nJean Carlo Lara\nSecurity Incident Handler\n\n\n\n\nLatin America and the Caribbean\nJean Carlo Lara\nSecurity Incident Handler\nHelpline\n\n\n\n\n\n\n\n\n\n\n\n\nEurope\nLuis Barrueto\nAdministrative and Communications Coordinator \n\n\n\n\nEurope\nLuis Barrueto\nAdministrative and Communications Coordinator \nHelpline\n\n\n\n\n\n\n\n\n\n\n\n\nInternational\nMag\nSecurity Incident Handler\n\n\n\n\nInternational\nMag\nSecurity Incident Handler\nHelpline\n\n\n\n\n\n\n\n\n\n\n\n\nInternational\nMaggie\nHelpline Documentation Coordinator\n\n\n\n\nInternational\nMaggie\nHelpline Documentation Coordinator\nHelpline\n\n\n\n\n\n\n\n\n\n\n\n\nInternational\nMalika Sharif\nSecurity Incident Handler\n\n\n\n\nInternational\nMalika Sharif\nSecurity Incident Handler\nHelpline\n\n\n\n\n\n\n\n\n\n\n\n\nAsia Pacific\nMarilou Maala\nIncident Response Analyst\n\n\n\n\nAsia Pacific\nMarilou Maala\nIncident Response Analyst\nHelpline\n\n\n\n\n\n\n\n\n\n\n\n\nAsia Pacific\nMarionne Sarmiento\nDigital Safety Specialist\n\n\n\n\nAsia Pacific\nMarionne Sarmiento\nDigital Safety Specialist\nHelpline\n\n\n\n\n\n\n\n\n\n\n\n\nInternational\nMaxim Petrov\nSafety Specialist\n\n\n\n\nInternational\nMaxim Petrov\nSafety Specialist\nHelpline\n\n\n\n\n\n\n\n\n\n\n\n\nInternational\nMohammed Al-Maskati\nDigital Security Helpline Director\n\n\n\n\nInternational\nMohammed Al-Maskati\nDigital Security Helpline Director\nHelpline\n\n\n\n\n\n\n\n\n\n\n\n\nInternational\nOleg Serov\nSecurity Incident Handler\n\n\n\n\nInternational\nOleg Serov\nSecurity Incident Handler\nHelpline\n\n\n\n\n\n\n\n\n\n\n\n\nLatin America and the Caribbean\nRocío\nSecurity Incident Handler\n\n\n\n\nLatin America and the Caribbean\nRocío\nSecurity Incident Handler\nHelpline\n\n\n\n\n\n\n\n\n\n\n\n\nLatin America and the Caribbean\nRogelio López\nSan José Security Shift Lead\n\n\n\n\nLatin America and the Caribbean\nRogelio López\nSan José Security Shift Lead\nHelpline\n\n\n\n\n\n\n\n\n\n\n\n\nAsia Pacific\nShinte Galeshka\nSecurity Incident Handler\n\n\n\n\nAsia Pacific\nShinte Galeshka\nSecurity Incident Handler\nHelpline\n\n\n\n\n\n\n\n\n\nEurope\nVeronica Zaboia\nPlatform Engagement Coordinator\n\n\n\n\nEurope\nVeronica Zaboia\nPlatform Engagement Coordinator\nHelpline\n\n\n\n\n\n\n\n\n\n\n\n\nInternational\nVictor Novikov\nDigital Security Helpline Manager\n\n\n\n\nInternational\nVictor Novikov\nDigital Security Helpline Manager\nHelpline\n\n\n\n\n\n\n\n\n\n\n\n\nInternational\nVlad\nSecurity Incident Handler\n\n\n\n\nInternational\nVlad\nSecurity Incident Handler\nHelpline\n\n\n\n\n\n\n\n\n\n\nCOMMUNITY & RESOURCES\n\n\n\n\n\n\n\n\n\n\n\n\n\n\n\n\n\n\n\nAccess Now’s Digital Security Helpline is a member of the Civil Society Computer Emergency Response Team (CiviCERT), an accredited CERT focused on improving the incident response capabilities of civil society groups and individuals around the world.\nCiviCERT is an initiative of Rapid Response Network (RaReNet), a network of non-governmental organizations, internet content and service providers, and individuals who contribute their time and resources to globally improve the security awareness of civil society groups.\n\n\n\nAs part of Access Now’s work and in collaboration with the broader community, we create and contribute to guides and materials to help communities, organizations, and individuals improve their digital security. These guides target a spectrum of users, from non-technical users to website administrators. Please find some guides below:\n\nDigital First Aid Kit\nA resource for emergency situations, such as when your social media account is compromised, your website is attacked, or your computer is infected \n\nHelpline PGP Email Encryption Guides (Windows | Mac | Linux)\nGuides for setting up encrypted email \n\nHelpline Safer Travel Guide\nHelping you prepare for travels to high-risk countries \n\nHelpline Self-Doxing Guide\nTips and resources for exploring open source intelligence on oneself to prevent online doxing \n\nHelpline Community Documentation\nThe procedures and documentation we create to aid our work on the Helpline \n\nPartner organizations have produced a number of guides and resources that we find valuable in our work, and you may too. They include: \n\nSecurity in a Box\nFrom Frontline Defenders and the Tactical Technology Collective \n\nSurveillance Self-Defense\nFrom the Electronic Frontier Foundation \n\nUmbrella\nFrom Security First\n\nDIGITAL SECURITY HELPLINE\n\n\n\n\n\nHow We Help\nWho Can We Help\nContact Us\nCommunity & Resources\n\n\n\nWHAT IS THE DIGITAL SECURITY HELPLINE?\n\n\nAvailable translations:\n\n Pусский Español Português العربية Français Deutsch Italiano Tagalog українська \n\n\n\n\nAccess Now’s Digital Security Helpline works with individuals and organizations around the world to keep them safe online. If you’re at risk, we can help you improve your digital security practices to keep out of harm’s way. If you’re already under attack, we provide rapid-response emergency assistance.\n\n\n\n\n\n\n\n\n\nCONTACT US\n\n\n\n\nOur 24/7 services are available with support in nine languages: English, Spanish, French, German, Portuguese, Russian, Tagalog, Arabic, and Italian. We respond to all requests within two hours.\n\n\n\n\nHOW CAN WE HELP YOU?\nWe are a free-of-charge resource for civil society around the world. We offer real-time, direct technical assistance and advice to civil society groups & activists, media organizations, journalists & bloggers, and human rights defenders.\nThe Helpline will walk you or your organization through assessing the risks you face in your work, and  together we’ll prioritize your digital security needs. We’ll help you resolve existing problems, teach you some of the most important best practices, and help you get into a secure mindset for the future.\n\n\n\n\nWHO CAN WE HELP?\nBefore we can provide any support, we will conduct an initial process to verify that supporting you is within our mandate. You can read more about our vetting process and determine whether you are elegible for support here. These are some of the groups we can assist:\n\n\n\n\n\n\n\n\n\n\n\nIf you are targeted based on your work or activism, we can help you protect your communications, secure your online accounts, and keep your sensitive information safe.            \n\n\n\n\n\nCase: Supporters of Mexico’s soda tax targeted with spyware Citizen Lab\n\n\n\n\n\n\n\n\n\n\n\n\n\n\n\n\nHas your news site been blocked or taken offline? Need help communicating securely with editors and sources? We can help.  \n\n\n\n\n\nCase: Journalists in Armenia locked out of Twitter accounts.Coda\n\n\n\n\n\n\n\n\n\n\n\n\n\n\n\n\nWhether you need to protect your communications with your partners, securely store evidence or other sensitive data, or stay safe when you travel, we’re here to assist you.\n\n\n\n\n\nCase: Human rights defenders in Azerbaijan fend off malware attacks – Amnesty International\n\n\n\n\n\n\n\n\n\nOUR SERVICES\n\n\n24/7, real-time, direct technical assistance and advice\n\n\n\n\n\n\n\n\n\n\n\nNo matter what digital security challenges you face, we offer a range of services and resources to help you be safe online:\n\n\n\n\n\n\n\n\n\n\n\n\nRapid response for digital security incidents\n\n\n\n\n\n\n\n\nPersonalized recommendations, instruction, and follow-up support for digital security issues\n\n\n\n\n\n\n\n\nHelp assessing risks and creating organizational or community security strategies\n\n\n\n\n\n\n\n\nGuidance and educational materials on security practices and tools for organizations, communities, groups, and individuals\n\n\n\n\n\n\n\n\nSupport for securing technical infrastructure, websites, and social media against attacks\n\n\n\n\n\n\n\n\nReferrals, capacity-building, in-person consultations, and training\n\n\n\n\n\n\n\n\n\nDIGITAL SECURITY CLINIC\n\n\n\nAccess Now’s Digital Security Clinic brings the Helpline to you.\nOur technologists run clinics at conferences and events around the world, where attendees can raise questions and get immediate help.\n\n\n\n\nHOW TO CONTACT US?\n\n\n\n\n\n[email protected]\n\nPGP PUBLIC KEY\n\nFingerprint: 6CE6 221C 98EC F399 A04C 41B8 C46B ED33 32E8 A2BC\n\n\nWe commit to using the best practices in the field when we collect, store, and use sensitive information. For more information about how we protect your personal data, and our Helpline Terms of Service, please read our Data Usage Policy.\n\n\n\n\n\n\n\n\n\n\nWHERE IS THE HELPLINE?\n\n\n\n\n\n\n\n\n\n\n\n\n\nLatin America and the Caribbean\nAlex Argüelles\nHolistic Security Lead\n\n\n\n\nLatin America and the Caribbean\nAlex Argüelles\nHolistic Security Lead\nHelpline\n\n\n\n\n\n\n\n\n\n\n\n\nEurope\nBeatrice Martini\nEducation and Communities Lead\n\n\n\n\nEurope\nBeatrice Martini\nEducation and Communities Lead\nHelpline\n\n\n\n\n\n\n\n\n\n\n\n\nAsia Pacific\nDhyta Caturani\nHelpline SEA Regional Coordinator\n\n\n\n\nAsia Pacific\nDhyta Caturani\nHelpline SEA Regional Coordinator\nHelpline\n\n\n\n\n\n\n\n\n\n\n\n\nAfrica\nDoreen Ochung\nSecurity Incident Handler\n\n\n\n\nAfrica\nDoreen Ochung\nSecurity Incident Handler\nHelpline\n\n\n\n\n\n\n\n\n\n\n\n\nInternational\nHassen Selmi\nIncident Response Lead\n\n\n\n\nInternational\nHassen Selmi\nIncident Response Lead\nHelpline\n\n\n\n\n\n\n\n\n\n\n\n\nLatin America and the Caribbean\nJean Carlo Lara\nSecurity Incident Handler\n\n\n\n\nLatin America and the Caribbean\nJean Carlo Lara\nSecurity Incident Handler\nHelpline\n\n\n\n\n\n\n\n\n\n\n\n\nEurope\nLuis Barrueto\nAdministrative and Communications Coordinator \n\n\n\n\nEurope\nLuis Barrueto\nAdministrative and Communications Coordinator \nHelpline\n\n\n\n\n\n\n\n\n\n\n\n\nInternational\nMag\nSecurity Incident Handler\n\n\n\n\nInternational\nMag\nSecurity Incident Handler\nHelpline\n\n\n\n\n\n\n\n\n\n\n\n\nInternational\nMaggie\nHelpline Documentation Coordinator\n\n\n\n\nInternational\nMaggie\nHelpline Documentation Coordinator\nHelpline\n\n\n\n\n\n\n\n\n\n\n\n\nInternational\nMalika Sharif\nSecurity Incident Handler\n\n\n\n\nInternational\nMalika Sharif\nSecurity Incident Handler\nHelpline\n\n\n\n\n\n\n\n\n\n\n\n\nAsia Pacific\nMarilou Maala\nIncident Response Analyst\n\n\n\n\nAsia Pacific\nMarilou Maala\nIncident Response Analyst\nHelpline\n\n\n\n\n\n\n\n\n\n\n\n\nAsia Pacific\nMarionne Sarmiento\nDigital Safety Specialist\n\n\n\n\nAsia Pacific\nMarionne Sarmiento\nDigital Safety Specialist\nHelpline\n\n\n\n\n\n\n\n\n\n\n\n\nInternational\nMaxim Petrov\nSafety Specialist\n\n\n\n\nInternational\nMaxim Petrov\nSafety Specialist\nHelpline\n\n\n\n\n\n\n\n\n\n\n\n\nInternational\nMohammed Al-Maskati\nDigital Security Helpline Director\n\n\n\n\nInternational\nMohammed Al-Maskati\nDigital Security Helpline Director\nHelpline\n\n\n\n\n\n\n\n\n\n\n\n\nInternational\nOleg Serov\nSecurity Incident Handler\n\n\n\n\nInternational\nOleg Serov\nSecurity Incident Handler\nHelpline\n\n\n\n\n\n\n\n\n\n\n\n\nLatin America and the Caribbean\nRocío\nSecurity Incident Handler\n\n\n\n\nLatin America and the Caribbean\nRocío\nSecurity Incident Handler\nHelpline\n\n\n\n\n\n\n\n\n\n\n\n\nLatin America and the Caribbean\nRogelio López\nSan José Security Shift Lead\n\n\n\n\nLatin America and the Caribbean\nRogelio López\nSan José Security Shift Lead\nHelpline\n\n\n\n\n\n\n\n\n\n\n\n\nAsia Pacific\nShinte Galeshka\nSecurity Incident Handler\n\n\n\n\nAsia Pacific\nShinte Galeshka\nSecurity Incident Handler\nHelpline\n\n\n\n\n\n\n\n\n\nEurope\nVeronica Zaboia\nPlatform Engagement Coordinator\n\n\n\n\nEurope\nVeronica Zaboia\nPlatform Engagement Coordinator\nHelpline\n\n\n\n\n\n\n\n\n\n\n\n\nInternational\nVictor Novikov\nDigital Security Helpline Manager\n\n\n\n\nInternational\nVictor Novikov\nDigital Security Helpline Manager\nHelpline\n\n\n\n\n\n\n\n\n\n\n\n\nInternational\nVlad\nSecurity Incident Handler\n\n\n\n\nInternational\nVlad\nSecurity Incident Handler\nHelpline\n\n\n\n\n\n\n\n\n\n\nCOMMUNITY & RESOURCES\n\n\n\n\n\n\n\n\n\n\n\n\n\n\n\n\n\n\n\nAccess Now’s Digital Security Helpline is a member of the Civil Society Computer Emergency Response Team (CiviCERT), an accredited CERT focused on improving the incident response capabilities of civil society groups and individuals around the world.\nCiviCERT is an initiative of Rapid Response Network (RaReNet), a network of non-governmental organizations, internet content and service providers, and individuals who contribute their time and resources to globally improve the security awareness of civil society groups.\n\n\n\nAs part of Access Now’s work and in collaboration with the broader community, we create and contribute to guides and materials to help communities, organizations, and individuals improve their digital security. These guides target a spectrum of users, from non-technical users to website administrators. Please find some guides below:\n\nDigital First Aid Kit\nA resource for emergency situations, such as when your social media account is compromised, your website is attacked, or your computer is infected \n\nHelpline PGP Email Encryption Guides (Windows | Mac | Linux)\nGuides for setting up encrypted email \n\nHelpline Safer Travel Guide\nHelping you prepare for travels to high-risk countries \n\nHelpline Self-Doxing Guide\nTips and resources for exploring open source intelligence on oneself to prevent online doxing \n\nHelpline Community Documentation\nThe procedures and documentation we create to aid our work on the Helpline \n\nPartner organizations have produced a number of guides and resources that we find valuable in our work, and you may too. They include: \n\nSecurity in a Box\nFrom Frontline Defenders and the Tactical Technology Collective \n\nSurveillance Self-Defense\nFrom the Electronic Frontier Foundation \n\nUmbrella\nFrom Security First\n\nDIGITAL SECURITY HELPLINE\n\n\n\n\n\nHow We Help\nWho Can We Help\nContact Us\nCommunity & Resources\n\n\n\nWHAT IS THE DIGITAL SECURITY HELPLINE?\n\n\nAvailable translations:\n\n Pусский Español Português العربية Français Deutsch Italiano Tagalog українська \n\n\n\n\nAccess Now’s Digital Security Helpline works with individuals and organizations around the world to keep them safe online. If you’re at risk, we can help you improve your digital security practices to keep out of harm’s way. If you’re already under attack, we provide rapid-response emergency assistance.\n\n\n\n\n\n\n\n\n\nCONTACT US\n\n\n\n\nOur 24/7 services are available with support in nine languages: English, Spanish, French, German, Portuguese, Russian, Tagalog, Arabic, and Italian. We respond to all requests within two hours.\n\n\n\n\nHOW CAN WE HELP YOU?\nWe are a free-of-charge resource for civil society around the world. We offer real-time, direct technical assistance and advice to civil society groups & activists, media organizations, journalists & bloggers, and human rights defenders.\nThe Helpline will walk you or your organization through assessing the risks you face in your work, and  together we’ll prioritize your digital security needs. We’ll help you resolve existing problems, teach you some of the most important best practices, and help you get into a secure mindset for the future.\n\n\n\n\nWHO CAN WE HELP?\nBefore we can provide any support, we will conduct an initial process to verify that supporting you is within our mandate. You can read more about our vetting process and determine whether you are elegible for support here. These are some of the groups we can assist:\n\n\n\n\n\n\n\n\n\n\n\nIf you are targeted based on your work or activism, we can help you protect your communications, secure your online accounts, and keep your sensitive information safe.            \n\n\n\n\n\nCase: Supporters of Mexico’s soda tax targeted with spyware Citizen Lab\n\n\n\n\n\n\n\n\n\n\n\n\n\n\n\n\nHas your news site been blocked or taken offline? Need help communicating securely with editors and sources? We can help.  \n\n\n\n\n\nCase: Journalists in Armenia locked out of Twitter accounts.Coda\n\n\n\n\n\n\n\n\n\n\n\n\n\n\n\n\nWhether you need to protect your communications with your partners, securely store evidence or other sensitive data, or stay safe when you travel, we’re here to assist you.\n\n\n\n\n\nCase: Human rights defenders in Azerbaijan fend off malware attacks – Amnesty International\n\n\n\n\n\n\n\n\n\nOUR SERVICES\n\n\n24/7, real-time, direct technical assistance and advice\n\n\n\n\n\n\n\n\n\n\n\nNo matter what digital security challenges you face, we offer a range of services and resources to help you be safe online:\n\n\n\n\n\n\n\n\n\n\n\n\nRapid response for digital security incidents\n\n\n\n\n\n\n\n\nPersonalized recommendations, instruction, and follow-up support for digital security issues\n\n\n\n\n\n\n\n\nHelp assessing risks and creating organizational or community security strategies\n\n\n\n\n\n\n\n\nGuidance and educational materials on security practices and tools for organizations, communities, groups, and individuals\n\n\n\n\n\n\n\n\nSupport for securing technical infrastructure, websites, and social media against attacks\n\n\n\n\n\n\n\n\nReferrals, capacity-building, in-person consultations, and training\n\n\n\n\n\n\n\n\n\nDIGITAL SECURITY CLINIC\n\n\n\nAccess Now’s Digital Security Clinic brings the Helpline to you.\nOur technologists run clinics at conferences and events around the world, where attendees can raise questions and get immediate help.\n\n\n\n\nHOW TO CONTACT US?\n\n\n\n\n\n[email protected]\n\nPGP PUBLIC KEY\n\nFingerprint: 6CE6 221C 98EC F399 A04C 41B8 C46B ED33 32E8 A2BC\n\n\nWe commit to using the best practices in the field when we collect, store, and use sensitive information. For more information about how we protect your personal data, and our Helpline Terms of Service, please read our Data Usage Policy.\n\n\n\n\n\n\n\n\n\n\nWHERE IS THE HELPLINE?\n\n\n\n\n\n\n\n\n\n\n\n\n\nLatin America and the Caribbean\nAlex Argüelles\nHolistic Security Lead\n\n\n\n\nLatin America and the Caribbean\nAlex Argüelles\nHolistic Security Lead\nHelpline\n\n\n\n\n\n\n\n\n\n\n\n\nEurope\nBeatrice Martini\nEducation and Communities Lead\n\n\n\n\nEurope\nBeatrice Martini\nEducation and Communities Lead\nHelpline\n\n\n\n\n\n\n\n\n\n\n\n\nAsia Pacific\nDhyta Caturani\nHelpline SEA Regional Coordinator\n\n\n\n\nAsia Pacific\nDhyta Caturani\nHelpline SEA Regional Coordinator\nHelpline\n\n\n\n\n\n\n\n\n\n\n\n\nAfrica\nDoreen Ochung\nSecurity Incident Handler\n\n\n\n\nAfrica\nDoreen Ochung\nSecurity Incident Handler\nHelpline\n\n\n\n\n\n\n\n\n\n\n\n\nInternational\nHassen Selmi\nIncident Response Lead\n\n\n\n\nInternational\nHassen Selmi\nIncident Response Lead\nHelpline\n\n\n\n\n\n\n\n\n\n\n\n\nLatin America and the Caribbean\nJean Carlo Lara\nSecurity Incident Handler\n\n\n\n\nLatin America and the Caribbean\nJean Carlo Lara\nSecurity Incident Handler\nHelpline\n\n\n\n\n\n\n\n\n\n\n\n\nEurope\nLuis Barrueto\nAdministrative and Communications Coordinator \n\n\n\n\nEurope\nLuis Barrueto\nAdministrative and Communications Coordinator \nHelpline\n\n\n\n\n\n\n\n\n\n\n\n\nInternational\nMag\nSecurity Incident Handler\n\n\n\n\nInternational\nMag\nSecurity Incident Handler\nHelpline\n\n\n\n\n\n\n\n\n\n\n\n\nInternational\nMaggie\nHelpline Documentation Coordinator\n\n\n\n\nInternational\nMaggie\nHelpline Documentation Coordinator\nHelpline\n\n\n\n\n\n\n\n\n\n\n\n\nInternational\nMalika Sharif\nSecurity Incident Handler\n\n\n\n\nInternational\nMalika Sharif\nSecurity Incident Handler\nHelpline\n\n\n\n\n\n\n\n\n\n\n\n\nAsia Pacific\nMarilou Maala\nIncident Response Analyst\n\n\n\n\nAsia Pacific\nMarilou Maala\nIncident Response Analyst\nHelpline\n\n\n\n\n\n\n\n\n\n\n\n\nAsia Pacific\nMarionne Sarmiento\nDigital Safety Specialist\n\n\n\n\nAsia Pacific\nMarionne Sarmiento\nDigital Safety Specialist\nHelpline\n\n\n\n\n\n\n\n\n\n\n\n\nInternational\nMaxim Petrov\nSafety Specialist\n\n\n\n\nInternational\nMaxim Petrov\nSafety Specialist\nHelpline\n\n\n\n\n\n\n\n\n\n\n\n\nInternational\nMohammed Al-Maskati\nDigital Security Helpline Director\n\n\n\n\nInternational\nMohammed Al-Maskati\nDigital Security Helpline Director\nHelpline\n\n\n\n\n\n\n\n\n\n\n\n\nInternational\nOleg Serov\nSecurity Incident Handler\n\n\n\n\nInternational\nOleg Serov\nSecurity Incident Handler\nHelpline\n\n\n\n\n\n\n\n\n\n\n\n\nLatin America and the Caribbean\nRocío\nSecurity Incident Handler\n\n\n\n\nLatin America and the Caribbean\nRocío\nSecurity Incident Handler\nHelpline\n\n\n\n\n\n\n\n\n\n\n\n\nLatin America and the Caribbean\nRogelio López\nSan José Security Shift Lead\n\n\n\n\nLatin America and the Caribbean\nRogelio López\nSan José Security Shift Lead\nHelpline\n\n\n\n\n\n\n\n\n\n\n\n\nAsia Pacific\nShinte Galeshka\nSecurity Incident Handler\n\n\n\n\nAsia Pacific\nShinte Galeshka\nSecurity Incident Handler\nHelpline\n\n\n\n\n\n\n\n\n\nEurope\nVeronica Zaboia\nPlatform Engagement Coordinator\n\n\n\n\nEurope\nVeronica Zaboia\nPlatform Engagement Coordinator\nHelpline\n\n\n\n\n\n\n\n\n\n\n\n\nInternational\nVictor Novikov\nDigital Security Helpline Manager\n\n\n\n\nInternational\nVictor Novikov\nDigital Security Helpline Manager\nHelpline\n\n\n\n\n\n\n\n\n\n\n\n\nInternational\nVlad\nSecurity Incident Handler\n\n\n\n\nInternational\nVlad\nSecurity Incident Handler\nHelpline\n\n\n\n\n\n\n\n\n\n\nCOMMUNITY & RESOURCES\n\n\n\n\n\n\n\n\n\n\n\n\n\n\n\n\n\n\n\nAccess Now’s Digital Security Helpline is a member of the Civil Society Computer Emergency Response Team (CiviCERT), an accredited CERT focused on improving the incident response capabilities of civil society groups and individuals around the world.\nCiviCERT is an initiative of Rapid Response Network (RaReNet), a network of non-governmental organizations, internet content and service providers, and individuals who contribute their time and resources to globally improve the security awareness of civil society groups.\n\n\n\nAs part of Access Now’s work and in collaboration with the broader community, we create and contribute to guides and materials to help communities, organizations, and individuals improve their digital security. These guides target a spectrum of users, from non-technical users to website administrators. Please find some guides below:\n\nDigital First Aid Kit\nA resource for emergency situations, such as when your social media account is compromised, your website is attacked, or your computer is infected \n\nHelpline PGP Email Encryption Guides (Windows | Mac | Linux)\nGuides for setting up encrypted email \n\nHelpline Safer Travel Guide\nHelping you prepare for travels to high-risk countries \n\nHelpline Self-Doxing Guide\nTips and resources for exploring open source intelligence on oneself to prevent online doxing \n\nHelpline Community Documentation\nThe procedures and documentation we create to aid our work on the Helpline \n\nPartner organizations have produced a number of guides and resources that we find valuable in our work, and you may too. They include: \n\nSecurity in a Box\nFrom Frontline Defenders and the Tactical Technology Collective \n\nSurveillance Self-Defense\nFrom the Electronic Frontier Foundation \n\nUmbrella\nFrom Security First\n\nDIGITAL SECURITY HELPLINE\n\n\n\n\n\nHow We Help\nWho Can We Help\nContact Us\nCommunity & Resources\n\n\n\nWHAT IS THE DIGITAL SECURITY HELPLINE?\n\n\nAvailable translations:\n\n Pусский Español Português العربية Français Deutsch Italiano Tagalog українська \n\n\n\n\nAccess Now’s Digital Security Helpline works with individuals and organizations around the world to keep them safe online. If you’re at risk, we can help you improve your digital security practices to keep out of harm’s way. If you’re already under attack, we provide rapid-response emergency assistance.\n\n\n\n\n\n\n\n\n\nCONTACT US\n\n\n\n\nOur 24/7 services are available with support in nine languages: English, Spanish, French, German, Portuguese, Russian, Tagalog, Arabic, and Italian. We respond to all requests within two hours.\n\n\n\n\nHOW CAN WE HELP YOU?\nWe are a free-of-charge resource for civil society around the world. We offer real-time, direct technical assistance and advice to civil society groups & activists, media organizations, journalists & bloggers, and human rights defenders.\nThe Helpline will walk you or your organization through assessing the risks you face in your work, and  together we’ll prioritize your digital security needs. We’ll help you resolve existing problems, teach you some of the most important best practices, and help you get into a secure mindset for the future.\n\n\n\n\nWHO CAN WE HELP?\nBefore we can provide any support, we will conduct an initial process to verify that supporting you is within our mandate. You can read more about our vetting process and determine whether you are elegible for support here. These are some of the groups we can assist:\n\n\n\n\n\n\n\n\n\n\n\nIf you are targeted based on your work or activism, we can help you protect your communications, secure your online accounts, and keep your sensitive information safe.            \n\n\n\n\n\nCase: Supporters of Mexico’s soda tax targeted with spyware Citizen Lab\n\n\n\n\n\n\n\n\n\n\n\n\n\n\n\n\nHas your news site been blocked or taken offline? Need help communicating securely with editors and sources? We can help.  \n\n\n\n\n\nCase: Journalists in Armenia locked out of Twitter accounts.Coda\n\n\n\n\n\n\n\n\n\n\n\n\n\n\n\n\nWhether you need to protect your communications with your partners, securely store evidence or other sensitive data, or stay safe when you travel, we’re here to assist you.\n\n\n\n\n\nCase: Human rights defenders in Azerbaijan fend off malware attacks – Amnesty International\n\n\n\n\n\n\n\n\n\nOUR SERVICES\n\n\n24/7, real-time, direct technical assistance and advice\n\n\n\n\n\n\n\n\n\n\n\nNo matter what digital security challenges you face, we offer a range of services and resources to help you be safe online:\n\n\n\n\n\n\n\n\n\n\n\n\nRapid response for digital security incidents\n\n\n\n\n\n\n\n\nPersonalized recommendations, instruction, and follow-up support for digital security issues\n\n\n\n\n\n\n\n\nHelp assessing risks and creating organizational or community security strategies\n\n\n\n\n\n\n\n\nGuidance and educational materials on security practices and tools for organizations, communities, groups, and individuals\n\n\n\n\n\n\n\n\nSupport for securing technical infrastructure, websites, and social media against attacks\n\n\n\n\n\n\n\n\nReferrals, capacity-building, in-person consultations, and training\n\n\n\n\n\n\n\n\n\nDIGITAL SECURITY CLINIC\n\n\n\nAccess Now’s Digital Security Clinic brings the Helpline to you.\nOur technologists run clinics at conferences and events around the world, where attendees can raise questions and get immediate help.\n\n\n\n\nHOW TO CONTACT US?\n\n\n\n\n\n[email protected]\n\nPGP PUBLIC KEY\n\nFingerprint: 6CE6 221C 98EC F399 A04C 41B8 C46B ED33 32E8 A2BC\n\n\nWe commit to using the best practices in the field when we collect, store, and use sensitive information. For more information about how we protect your personal data, and our Helpline Terms of Service, please read our Data Usage Policy.\n\n\n\n\n\n\n\n\n\n\nWHERE IS THE HELPLINE?\n\n\n\n\n\n\n\n\n\n\n\n\n\nLatin America and the Caribbean\nAlex Argüelles\nHolistic Security Lead\n\n\n\n\nLatin America and the Caribbean\nAlex Argüelles\nHolistic Security Lead\nHelpline\n\n\n\n\n\n\n\n\n\n\n\n\nEurope\nBeatrice Martini\nEducation and Communities Lead\n\n\n\n\nEurope\nBeatrice Martini\nEducation and Communities Lead\nHelpline\n\n\n\n\n\n\n\n\n\n\n\n\nAsia Pacific\nDhyta Caturani\nHelpline SEA Regional Coordinator\n\n\n\n\nAsia Pacific\nDhyta Caturani\nHelpline SEA Regional Coordinator\nHelpline\n\n\n\n\n\n\n\n\n\n\n\n\nAfrica\nDoreen Ochung\nSecurity Incident Handler\n\n\n\n\nAfrica\nDoreen Ochung\nSecurity Incident Handler\nHelpline\n\n\n\n\n\n\n\n\n\n\n\n\nInternational\nHassen Selmi\nIncident Response Lead\n\n\n\n\nInternational\nHassen Selmi\nIncident Response Lead\nHelpline\n\n\n\n\n\n\n\n\n\n\n\n\nLatin America and the Caribbean\nJean Carlo Lara\nSecurity Incident Handler\n\n\n\n\nLatin America and the Caribbean\nJean Carlo Lara\nSecurity Incident Handler\nHelpline\n\n\n\n\n\n\n\n\n\n\n\n\nEurope\nLuis Barrueto\nAdministrative and Communications Coordinator \n\n\n\n\nEurope\nLuis Barrueto\nAdministrative and Communications Coordinator \nHelpline\n\n\n\n\n\n\n\n\n\n\n\n\nInternational\nMag\nSecurity Incident Handler\n\n\n\n\nInternational\nMag\nSecurity Incident Handler\nHelpline\n\n\n\n\n\n\n\n\n\n\n\n\nInternational\nMaggie\nHelpline Documentation Coordinator\n\n\n\n\nInternational\nMaggie\nHelpline Documentation Coordinator\nHelpline\n\n\n\n\n\n\n\n\n\n\n\n\nInternational\nMalika Sharif\nSecurity Incident Handler\n\n\n\n\nInternational\nMalika Sharif\nSecurity Incident Handler\nHelpline\n\n\n\n\n\n\n\n\n\n\n\n\nAsia Pacific\nMarilou Maala\nIncident Response Analyst\n\n\n\n\nAsia Pacific\nMarilou Maala\nIncident Response Analyst\nHelpline\n\n\n\n\n\n\n\n\n\n\n\n\nAsia Pacific\nMarionne Sarmiento\nDigital Safety Specialist\n\n\n\n\nAsia Pacific\nMarionne Sarmiento\nDigital Safety Specialist\nHelpline\n\n\n\n\n\n\n\n\n\n\n\n\nInternational\nMaxim Petrov\nSafety Specialist\n\n\n\n\nInternational\nMaxim Petrov\nSafety Specialist\nHelpline\n\n\n\n\n\n\n\n\n\n\n\n\nInternational\nMohammed Al-Maskati\nDigital Security Helpline Director\n\n\n\n\nInternational\nMohammed Al-Maskati\nDigital Security Helpline Director\nHelpline\n\n\n\n\n\n\n\n\n\n\n\n\nInternational\nOleg Serov\nSecurity Incident Handler\n\n\n\n\nInternational\nOleg Serov\nSecurity Incident Handler\nHelpline\n\n\n\n\n\n\n\n\n\n\n\n\nLatin America and the Caribbean\nRocío\nSecurity Incident Handler\n\n\n\n\nLatin America and the Caribbean\nRocío\nSecurity Incident Handler\nHelpline\n\n\n\n\n\n\n\n\n\n\n\n\nLatin America and the Caribbean\nRogelio López\nSan José Security Shift Lead\n\n\n\n\nLatin America and the Caribbean\nRogelio López\nSan José Security Shift Lead\nHelpline\n\n\n\n\n\n\n\n\n\n\n\n\nAsia Pacific\nShinte Galeshka\nSecurity Incident Handler\n\n\n\n\nAsia Pacific\nShinte Galeshka\nSecurity Incident Handler\nHelpline\n\n\n\n\n\n\n\n\n\nEurope\nVeronica Zaboia\nPlatform Engagement Coordinator\n\n\n\n\nEurope\nVeronica Zaboia\nPlatform Engagement Coordinator\nHelpline\n\n\n\n\n\n\n\n\n\n\n\n\nInternational\nVictor Novikov\nDigital Security Helpline Manager\n\n\n\n\nInternational\nVictor Novikov\nDigital Security Helpline Manager\nHelpline\n\n\n\n\n\n\n\n\n\n\n\n\nInternational\nVlad\nSecurity Incident Handler\n\n\n\n\nInternational\nVlad\nSecurity Incident Handler\nHelpline\n\n\n\n\n\n\n\n\n\n\nCOMMUNITY & RESOURCES\n\n\n\n\n\n\n\n\n\n\n\n\n\n\n\n\n\n\n\nAccess Now’s Digital Security Helpline is a member of the Civil Society Computer Emergency Response Team (CiviCERT), an accredited CERT focused on improving the incident response capabilities of civil society groups and individuals around the world.\nCiviCERT is an initiative of Rapid Response Network (RaReNet), a network of non-governmental organizations, internet content and service providers, and individuals who contribute their time and resources to globally improve the security awareness of civil society groups.\n\n\n\nAs part of Access Now’s work and in collaboration with the broader community, we create and contribute to guides and materials to help communities, organizations, and individuals improve their digital security. These guides target a spectrum of users, from non-technical users to website administrators. Please find some guides below:\n\nDigital First Aid Kit\nA resource for emergency situations, such as when your social media account is compromised, your website is attacked, or your computer is infected \n\nHelpline PGP Email Encryption Guides (Windows | Mac | Linux)\nGuides for setting up encrypted email \n\nHelpline Safer Travel Guide\nHelping you prepare for travels to high-risk countries \n\nHelpline Self-Doxing Guide\nTips and resources for exploring open source intelligence on oneself to prevent online doxing \n\nHelpline Community Documentation\nThe procedures and documentation we create to aid our work on the Helpline \n\nPartner organizations have produced a number of guides and resources that we find valuable in our work, and you may too. They include: \n\nSecurity in a Box\nFrom Frontline Defenders and the Tactical Technology Collective \n\nSurveillance Self-Defense\nFrom the Electronic Frontier Foundation \n\nUmbrella\nFrom Security First\n\nDIGITAL SECURITY HELPLINE\n\nDIGITAL SECURITY HELPLINE\n\nDIGITAL SECURITY HELPLINE\n\nDIGITAL SECURITY HELPLINE\n\nHow We Help\nWho Can We Help\nContact Us\nCommunity & Resources\n\nHow We Help\n\nWho Can We Help\n\nContact Us\n\nCommunity & Resources\n\nWHAT IS THE DIGITAL SECURITY HELPLINE?\n\n\nAvailable translations:\n\n Pусский Español Português العربية Français Deutsch Italiano Tagalog українська \n\n\n\n\nAccess Now’s Digital Security Helpline works with individuals and organizations around the world to keep them safe online. If you’re at risk, we can help you improve your digital security practices to keep out of harm’s way. If you’re already under attack, we provide rapid-response emergency assistance.\n\nWHAT IS THE DIGITAL SECURITY HELPLINE?\n\n\nAvailable translations:\n\n Pусский Español Português العربية Français Deutsch Italiano Tagalog українська \n\n\n\n\nAccess Now’s Digital Security Helpline works with individuals and organizations around the world to keep them safe online. If you’re at risk, we can help you improve your digital security practices to keep out of harm’s way. If you’re already under attack, we provide rapid-response emergency assistance.\n\nAvailable translations:\n\n Pусский Español Português العربية Français Deutsch Italiano Tagalog українська\n\nAvailable translations:\n\n Pусский Español Português العربية Français Deutsch Italiano Tagalog українська\n\nPусский Español Português العربية Français Deutsch Italiano Tagalog українська\n\nPусский\n\nEspañol\n\nPortuguês\n\nالعربية\n\nFrançais\n\nDeutsch\n\nItaliano\n\nTagalog\n\nукраїнська\n\nAccess Now’s Digital Security Helpline works with individuals and organizations around the world to keep them safe online. If you’re at risk, we can help you improve your digital security practices to keep out of harm’s way. If you’re already under attack, we provide rapid-response emergency assistance.\n\nAccess Now’s Digital Security Helpline works with individuals and organizations around the world to keep them safe online. If you’re at risk, we can help you improve your digital security practices to keep out of harm’s way. If you’re already under attack, we provide rapid-response emergency assistance.\n\nAccess Now’s Digital Security Helpline works with individuals and organizations around the world to keep them safe online. If you’re at risk, we can help you improve your digital security practices to keep out of harm’s way. If you’re already under attack, we provide rapid-response emergency assistance.\n\nCONTACT US\n\n\n\n\nOur 24/7 services are available with support in nine languages: English, Spanish, French, German, Portuguese, Russian, Tagalog, Arabic, and Italian. We respond to all requests within two hours.\n\nCONTACT US\n\nCONTACT US\n\nCONTACT US\n\nOur 24/7 services are available with support in nine languages: English, Spanish, French, German, Portuguese, Russian, Tagalog, Arabic, and Italian. We respond to all requests within two hours.\n\nHOW CAN WE HELP YOU?\nWe are a free-of-charge resource for civil society around the world. We offer real-time, direct technical assistance and advice to civil society groups & activists, media organizations, journalists & bloggers, and human rights defenders.\nThe Helpline will walk you or your organization through assessing the risks you face in your work, and  together we’ll prioritize your digital security needs. We’ll help you resolve existing problems, teach you some of the most important best practices, and help you get into a secure mindset for the future.\n\nHOW CAN WE HELP YOU?\nWe are a free-of-charge resource for civil society around the world. We offer real-time, direct technical assistance and advice to civil society groups & activists, media organizations, journalists & bloggers, and human rights defenders.\nThe Helpline will walk you or your organization through assessing the risks you face in your work, and  together we’ll prioritize your digital security needs. We’ll help you resolve existing problems, teach you some of the most important best practices, and help you get into a secure mindset for the future.\n\nWe are a free-of-charge resource for civil society around the world. We offer real-time, direct technical assistance and advice to civil society groups & activists, media organizations, journalists & bloggers, and human rights defenders.\n\nThe Helpline will walk you or your organization through assessing the risks you face in your work, and  together we’ll prioritize your digital security needs. We’ll help you resolve existing problems, teach you some of the most important best practices, and help you get into a secure mindset for the future.\n\nWHO CAN WE HELP?\nBefore we can provide any support, we will conduct an initial process to verify that supporting you is within our mandate. You can read more about our vetting process and determine whether you are elegible for support here. These are some of the groups we can assist:\n\n\n\n\n\n\n\n\n\n\n\nIf you are targeted based on your work or activism, we can help you protect your communications, secure your online accounts, and keep your sensitive information safe.            \n\n\n\n\n\nCase: Supporters of Mexico’s soda tax targeted with spyware Citizen Lab\n\n\n\n\n\n\n\n\n\n\n\n\n\n\n\n\nHas your news site been blocked or taken offline? Need help communicating securely with editors and sources? We can help.  \n\n\n\n\n\nCase: Journalists in Armenia locked out of Twitter accounts.Coda\n\n\n\n\n\n\n\n\n\n\n\n\n\n\n\n\nWhether you need to protect your communications with your partners, securely store evidence or other sensitive data, or stay safe when you travel, we’re here to assist you.\n\n\n\n\n\nCase: Human rights defenders in Azerbaijan fend off malware attacks – Amnesty International\n\n\n\n\n\n\n\n\n\nOUR SERVICES\n\n\n24/7, real-time, direct technical assistance and advice\n\n\n\n\n\n\n\n\n\n\n\nNo matter what digital security challenges you face, we offer a range of services and resources to help you be safe online:\n\nWHO CAN WE HELP?\nBefore we can provide any support, we will conduct an initial process to verify that supporting you is within our mandate. You can read more about our vetting process and determine whether you are elegible for support here. These are some of the groups we can assist:\n\n\n\n\n\n\n\n\n\n\n\nIf you are targeted based on your work or activism, we can help you protect your communications, secure your online accounts, and keep your sensitive information safe.            \n\n\n\n\n\nCase: Supporters of Mexico’s soda tax targeted with spyware Citizen Lab\n\n\n\n\n\n\n\n\n\n\n\n\n\n\n\n\nHas your news site been blocked or taken offline? Need help communicating securely with editors and sources? We can help.  \n\n\n\n\n\nCase: Journalists in Armenia locked out of Twitter accounts.Coda\n\n\n\n\n\n\n\n\n\n\n\n\n\n\n\n\nWhether you need to protect your communications with your partners, securely store evidence or other sensitive data, or stay safe when you travel, we’re here to assist you.\n\n\n\n\n\nCase: Human rights defenders in Azerbaijan fend off malware attacks – Amnesty International\n\n\n\n\n\n\n\n\n\nOUR SERVICES\n\n\n24/7, real-time, direct technical assistance and advice\n\n\n\n\n\n\n\n\n\n\n\nNo matter what digital security challenges you face, we offer a range of services and resources to help you be safe online:\n\nBefore we can provide any support, we will conduct an initial process to verify that supporting you is within our mandate. You can read more about our vetting process and determine whether you are elegible for support here. These are some of the groups we can assist:\n\nIf you are targeted based on your work or activism, we can help you protect your communications, secure your online accounts, and keep your sensitive information safe.            \n\n\n\n\n\nCase: Supporters of Mexico’s soda tax targeted with spyware Citizen Lab\n\n\n\n\n\n\n\n\n\n\n\n\n\n\n\n\nHas your news site been blocked or taken offline? Need help communicating securely with editors and sources? We can help.  \n\n\n\n\n\nCase: Journalists in Armenia locked out of Twitter accounts.Coda\n\n\n\n\n\n\n\n\n\n\n\n\n\n\n\n\nWhether you need to protect your communications with your partners, securely store evidence or other sensitive data, or stay safe when you travel, we’re here to assist you.\n\n\n\n\n\nCase: Human rights defenders in Azerbaijan fend off malware attacks – Amnesty International\n\nIf you are targeted based on your work or activism, we can help you protect your communications, secure your online accounts, and keep your sensitive information safe.            \n\n\n\n\n\nCase: Supporters of Mexico’s soda tax targeted with spyware Citizen Lab\n\nIf you are targeted based on your work or activism, we can help you protect your communications, secure your online accounts, and keep your sensitive information safe.            \n\n\n\n\n\nCase: Supporters of Mexico’s soda tax targeted with spyware Citizen Lab\n\nIf you are targeted based on your work or activism, we can help you protect your communications, secure your online accounts, and keep your sensitive information safe.            \n\n\n\n\n\nCase: Supporters of Mexico’s soda tax targeted with spyware Citizen Lab\n\nIf you are targeted based on your work or activism, we can help you protect your communications, secure your online accounts, and keep your sensitive information safe.\n\nIf you are targeted based on your work or activism, we can help you protect your communications, secure your online accounts, and keep your sensitive information safe.\n\nIf you are targeted based on your work or activism, we can help you protect your communications, secure your online accounts, and keep your sensitive information safe.\n\nCase: Supporters of Mexico’s soda tax targeted with spyware Citizen Lab\n\nCase: Supporters of Mexico’s soda tax targeted with spyware Citizen Lab\n\nCase: Supporters of Mexico’s soda tax targeted with spyware Citizen Lab\n\nCase: Supporters of Mexico’s soda tax targeted with spyware Citizen Lab\n\nHas your news site been blocked or taken offline? Need help communicating securely with editors and sources? We can help.  \n\n\n\n\n\nCase: Journalists in Armenia locked out of Twitter accounts.Coda\n\nHas your news site been blocked or taken offline? Need help communicating securely with editors and sources? We can help.  \n\n\n\n\n\nCase: Journalists in Armenia locked out of Twitter accounts.Coda\n\nHas your news site been blocked or taken offline? Need help communicating securely with editors and sources? We can help.  \n\n\n\n\n\nCase: Journalists in Armenia locked out of Twitter accounts.Coda\n\nHas your news site been blocked or taken offline? Need help communicating securely with editors and sources? We can help.\n\nHas your news site been blocked or taken offline? Need help communicating securely with editors and sources? We can help.\n\nHas your news site been blocked or taken offline? Need help communicating securely with editors and sources? We can help.\n\nCase: Journalists in Armenia locked out of Twitter accounts.Coda\n\nCase: Journalists in Armenia locked out of Twitter accounts.Coda\n\nCase: Journalists in Armenia locked out of Twitter accounts.Coda\n\nCase: Journalists in Armenia locked out of Twitter accounts.Coda\n\nWhether you need to protect your communications with your partners, securely store evidence or other sensitive data, or stay safe when you travel, we’re here to assist you.\n\n\n\n\n\nCase: Human rights defenders in Azerbaijan fend off malware attacks – Amnesty International\n\nWhether you need to protect your communications with your partners, securely store evidence or other sensitive data, or stay safe when you travel, we’re here to assist you.\n\n\n\n\n\nCase: Human rights defenders in Azerbaijan fend off malware attacks – Amnesty International\n\nWhether you need to protect your communications with your partners, securely store evidence or other sensitive data, or stay safe when you travel, we’re here to assist you.\n\n\n\n\n\nCase: Human rights defenders in Azerbaijan fend off malware attacks – Amnesty International\n\nWhether you need to protect your communications with your partners, securely store evidence or other sensitive data, or stay safe when you travel, we’re here to assist you.\n\nWhether you need to protect your communications with your partners, securely store evidence or other sensitive data, or stay safe when you travel, we’re here to assist you.\n\nWhether you need to protect your communications with your partners, securely store evidence or other sensitive data, or stay safe when you travel, we’re here to assist you.\n\nCase: Human rights defenders in Azerbaijan fend off malware attacks – Amnesty International\n\nCase: Human rights defenders in Azerbaijan fend off malware attacks – Amnesty International\n\nCase: Human rights defenders in Azerbaijan fend off malware attacks – Amnesty International\n\nCase: Human rights defenders in Azerbaijan fend off malware attacks – Amnesty International\n\nOUR SERVICES\n\n\n24/7, real-time, direct technical assistance and advice\n\nOUR SERVICES\n\nOUR SERVICES\n\n24/7, real-time, direct technical assistance and advice\n\n24/7, real-time, direct technical assistance and advice\n\nNo matter what digital security challenges you face, we offer a range of services and resources to help you be safe online:\n\nNo matter what digital security challenges you face, we offer a range of services and resources to help you be safe online:\n\nNo matter what digital security challenges you face, we offer a range of services and resources to help you be safe online:\n\nRapid response for digital security incidents\n\n\n\n\n\n\n\n\nPersonalized recommendations, instruction, and follow-up support for digital security issues\n\n\n\n\n\n\n\n\nHelp assessing risks and creating organizational or community security strategies\n\n\n\n\n\n\n\n\nGuidance and educational materials on security practices and tools for organizations, communities, groups, and individuals\n\n\n\n\n\n\n\n\nSupport for securing technical infrastructure, websites, and social media against attacks\n\n\n\n\n\n\n\n\nReferrals, capacity-building, in-person consultations, and training\n\n\n\n\n\n\n\n\n\nDIGITAL SECURITY CLINIC\n\n\n\nAccess Now’s Digital Security Clinic brings the Helpline to you.\nOur technologists run clinics at conferences and events around the world, where attendees can raise questions and get immediate help.\n\nRapid response for digital security incidents\n\n\n\n\n\n\n\n\nPersonalized recommendations, instruction, and follow-up support for digital security issues\n\n\n\n\n\n\n\n\nHelp assessing risks and creating organizational or community security strategies\n\n\n\n\n\n\n\n\nGuidance and educational materials on security practices and tools for organizations, communities, groups, and individuals\n\n\n\n\n\n\n\n\nSupport for securing technical infrastructure, websites, and social media against attacks\n\n\n\n\n\n\n\n\nReferrals, capacity-building, in-person consultations, and training\n\n\n\n\n\n\n\n\n\nDIGITAL SECURITY CLINIC\n\n\n\nAccess Now’s Digital Security Clinic brings the Helpline to you.\nOur technologists run clinics at conferences and events around the world, where attendees can raise questions and get immediate help.\n\nRapid response for digital security incidents\n\nRapid response for digital security incidents\n\nRapid response for digital security incidents\n\nPersonalized recommendations, instruction, and follow-up support for digital security issues\n\nPersonalized recommendations, instruction, and follow-up support for digital security issues\n\nPersonalized recommendations, instruction, and follow-up support for digital security issues\n\nHelp assessing risks and creating organizational or community security strategies\n\nHelp assessing risks and creating organizational or community security strategies\n\nHelp assessing risks and creating organizational or community security strategies\n\nGuidance and educational materials on security practices and tools for organizations, communities, groups, and individuals\n\nGuidance and educational materials on security practices and tools for organizations, communities, groups, and individuals\n\nGuidance and educational materials on security practices and tools for organizations, communities, groups, and individuals\n\nSupport for securing technical infrastructure, websites, and social media against attacks\n\nSupport for securing technical infrastructure, websites, and social media against attacks\n\nSupport for securing technical infrastructure, websites, and social media against attacks\n\nReferrals, capacity-building, in-person consultations, and training\n\nReferrals, capacity-building, in-person consultations, and training\n\nReferrals, capacity-building, in-person consultations, and training\n\nDIGITAL SECURITY CLINIC\n\n\n\nAccess Now’s Digital Security Clinic brings the Helpline to you.\nOur technologists run clinics at conferences and events around the world, where attendees can raise questions and get immediate help.\n\nDIGITAL SECURITY CLINIC\n\nDIGITAL SECURITY CLINIC\n\nDIGITAL SECURITY CLINIC\n\nAccess Now’s Digital Security Clinic brings the Helpline to you.\nOur technologists run clinics at conferences and events around the world, where attendees can raise questions and get immediate help.\n\nOur technologists run clinics at conferences and events around the world, where attendees can raise questions and get immediate help.\n\n[email protected]\n\nPGP PUBLIC KEY\n\nFingerprint: 6CE6 221C 98EC F399 A04C 41B8 C46B ED33 32E8 A2BC\n\n\nWe commit to using the best practices in the field when we collect, store, and use sensitive information. For more information about how we protect your personal data, and our Helpline Terms of Service, please read our Data Usage Policy.\n\n[email protected]\n\nPGP PUBLIC KEY\n\nFingerprint: 6CE6 221C 98EC F399 A04C 41B8 C46B ED33 32E8 A2BC\n\n\nWe commit to using the best practices in the field when we collect, store, and use sensitive information. For more information about how we protect your personal data, and our Helpline Terms of Service, please read our Data Usage Policy.\n\n[email protected]\n\nPGP PUBLIC KEY\n\nFingerprint: 6CE6 221C 98EC F399 A04C 41B8 C46B ED33 32E8 A2BC\n\n\nWe commit to using the best practices in the field when we collect, store, and use sensitive information. For more information about how we protect your personal data, and our Helpline Terms of Service, please read our Data Usage Policy.\n\n[email protected]\n\nPGP PUBLIC KEY\n\nFingerprint: 6CE6 221C 98EC F399 A04C 41B8 C46B ED33 32E8 A2BC\n\n\nWe commit to using the best practices in the field when we collect, store, and use sensitive information. For more information about how we protect your personal data, and our Helpline Terms of Service, please read our Data Usage Policy.\n\n[email protected]\n\nPGP PUBLIC KEY\n\nFingerprint: 6CE6 221C 98EC F399 A04C 41B8 C46B ED33 32E8 A2BC\n\n[email protected]\n\nPGP PUBLIC KEY\n\nPGP PUBLIC KEY\n\nFingerprint: 6CE6 221C 98EC F399 A04C 41B8 C46B ED33 32E8 A2BC\n\nWe commit to using the best practices in the field when we collect, store, and use sensitive information. For more information about how we protect your personal data, and our Helpline Terms of Service, please read our Data Usage Policy.\n\nWe commit to using the best practices in the field when we collect, store, and use sensitive information. For more information about how we protect your personal data, and our Helpline Terms of Service, please read our Data Usage Policy.\n\nLatin America and the Caribbean\nAlex Argüelles\nHolistic Security Lead\n\n\n\n\nLatin America and the Caribbean\nAlex Argüelles\nHolistic Security Lead\nHelpline\n\n\n\n\n\n\n\n\n\n\n\n\nEurope\nBeatrice Martini\nEducation and Communities Lead\n\n\n\n\nEurope\nBeatrice Martini\nEducation and Communities Lead\nHelpline\n\n\n\n\n\n\n\n\n\n\n\n\nAsia Pacific\nDhyta Caturani\nHelpline SEA Regional Coordinator\n\n\n\n\nAsia Pacific\nDhyta Caturani\nHelpline SEA Regional Coordinator\nHelpline\n\n\n\n\n\n\n\n\n\n\n\n\nAfrica\nDoreen Ochung\nSecurity Incident Handler\n\n\n\n\nAfrica\nDoreen Ochung\nSecurity Incident Handler\nHelpline\n\n\n\n\n\n\n\n\n\n\n\n\nInternational\nHassen Selmi\nIncident Response Lead\n\n\n\n\nInternational\nHassen Selmi\nIncident Response Lead\nHelpline\n\n\n\n\n\n\n\n\n\n\n\n\nLatin America and the Caribbean\nJean Carlo Lara\nSecurity Incident Handler\n\n\n\n\nLatin America and the Caribbean\nJean Carlo Lara\nSecurity Incident Handler\nHelpline\n\n\n\n\n\n\n\n\n\n\n\n\nEurope\nLuis Barrueto\nAdministrative and Communications Coordinator \n\n\n\n\nEurope\nLuis Barrueto\nAdministrative and Communications Coordinator \nHelpline\n\n\n\n\n\n\n\n\n\n\n\n\nInternational\nMag\nSecurity Incident Handler\n\n\n\n\nInternational\nMag\nSecurity Incident Handler\nHelpline\n\n\n\n\n\n\n\n\n\n\n\n\nInternational\nMaggie\nHelpline Documentation Coordinator\n\n\n\n\nInternational\nMaggie\nHelpline Documentation Coordinator\nHelpline\n\n\n\n\n\n\n\n\n\n\n\n\nInternational\nMalika Sharif\nSecurity Incident Handler\n\n\n\n\nInternational\nMalika Sharif\nSecurity Incident Handler\nHelpline\n\n\n\n\n\n\n\n\n\n\n\n\nAsia Pacific\nMarilou Maala\nIncident Response Analyst\n\n\n\n\nAsia Pacific\nMarilou Maala\nIncident Response Analyst\nHelpline\n\n\n\n\n\n\n\n\n\n\n\n\nAsia Pacific\nMarionne Sarmiento\nDigital Safety Specialist\n\n\n\n\nAsia Pacific\nMarionne Sarmiento\nDigital Safety Specialist\nHelpline\n\n\n\n\n\n\n\n\n\n\n\n\nInternational\nMaxim Petrov\nSafety Specialist\n\n\n\n\nInternational\nMaxim Petrov\nSafety Specialist\nHelpline\n\n\n\n\n\n\n\n\n\n\n\n\nInternational\nMohammed Al-Maskati\nDigital Security Helpline Director\n\n\n\n\nInternational\nMohammed Al-Maskati\nDigital Security Helpline Director\nHelpline\n\n\n\n\n\n\n\n\n\n\n\n\nInternational\nOleg Serov\nSecurity Incident Handler\n\n\n\n\nInternational\nOleg Serov\nSecurity Incident Handler\nHelpline\n\n\n\n\n\n\n\n\n\n\n\n\nLatin America and the Caribbean\nRocío\nSecurity Incident Handler\n\n\n\n\nLatin America and the Caribbean\nRocío\nSecurity Incident Handler\nHelpline\n\n\n\n\n\n\n\n\n\n\n\n\nLatin America and the Caribbean\nRogelio López\nSan José Security Shift Lead\n\n\n\n\nLatin America and the Caribbean\nRogelio López\nSan José Security Shift Lead\nHelpline\n\n\n\n\n\n\n\n\n\n\n\n\nAsia Pacific\nShinte Galeshka\nSecurity Incident Handler\n\n\n\n\nAsia Pacific\nShinte Galeshka\nSecurity Incident Handler\nHelpline\n\n\n\n\n\n\n\n\n\nEurope\nVeronica Zaboia\nPlatform Engagement Coordinator\n\n\n\n\nEurope\nVeronica Zaboia\nPlatform Engagement Coordinator\nHelpline\n\n\n\n\n\n\n\n\n\n\n\n\nInternational\nVictor Novikov\nDigital Security Helpline Manager\n\n\n\n\nInternational\nVictor Novikov\nDigital Security Helpline Manager\nHelpline\n\n\n\n\n\n\n\n\n\n\n\n\nInternational\nVlad\nSecurity Incident Handler\n\n\n\n\nInternational\nVlad\nSecurity Incident Handler\nHelpline\n\nLatin America and the Caribbean\nAlex Argüelles\nHolistic Security Lead\n\n\n\n\nLatin America and the Caribbean\nAlex Argüelles\nHolistic Security Lead\nHelpline\n\n\n\n\n\n\n\n\n\n\n\n\nEurope\nBeatrice Martini\nEducation and Communities Lead\n\n\n\n\nEurope\nBeatrice Martini\nEducation and Communities Lead\nHelpline\n\n\n\n\n\n\n\n\n\n\n\n\nAsia Pacific\nDhyta Caturani\nHelpline SEA Regional Coordinator\n\n\n\n\nAsia Pacific\nDhyta Caturani\nHelpline SEA Regional Coordinator\nHelpline\n\n\n\n\n\n\n\n\n\n\n\n\nAfrica\nDoreen Ochung\nSecurity Incident Handler\n\n\n\n\nAfrica\nDoreen Ochung\nSecurity Incident Handler\nHelpline\n\n\n\n\n\n\n\n\n\n\n\n\nInternational\nHassen Selmi\nIncident Response Lead\n\n\n\n\nInternational\nHassen Selmi\nIncident Response Lead\nHelpline\n\n\n\n\n\n\n\n\n\n\n\n\nLatin America and the Caribbean\nJean Carlo Lara\nSecurity Incident Handler\n\n\n\n\nLatin America and the Caribbean\nJean Carlo Lara\nSecurity Incident Handler\nHelpline\n\n\n\n\n\n\n\n\n\n\n\n\nEurope\nLuis Barrueto\nAdministrative and Communications Coordinator \n\n\n\n\nEurope\nLuis Barrueto\nAdministrative and Communications Coordinator \nHelpline\n\n\n\n\n\n\n\n\n\n\n\n\nInternational\nMag\nSecurity Incident Handler\n\n\n\n\nInternational\nMag\nSecurity Incident Handler\nHelpline\n\n\n\n\n\n\n\n\n\n\n\n\nInternational\nMaggie\nHelpline Documentation Coordinator\n\n\n\n\nInternational\nMaggie\nHelpline Documentation Coordinator\nHelpline\n\n\n\n\n\n\n\n\n\n\n\n\nInternational\nMalika Sharif\nSecurity Incident Handler\n\n\n\n\nInternational\nMalika Sharif\nSecurity Incident Handler\nHelpline\n\n\n\n\n\n\n\n\n\n\n\n\nAsia Pacific\nMarilou Maala\nIncident Response Analyst\n\n\n\n\nAsia Pacific\nMarilou Maala\nIncident Response Analyst\nHelpline\n\n\n\n\n\n\n\n\n\n\n\n\nAsia Pacific\nMarionne Sarmiento\nDigital Safety Specialist\n\n\n\n\nAsia Pacific\nMarionne Sarmiento\nDigital Safety Specialist\nHelpline\n\n\n\n\n\n\n\n\n\n\n\n\nInternational\nMaxim Petrov\nSafety Specialist\n\n\n\n\nInternational\nMaxim Petrov\nSafety Specialist\nHelpline\n\n\n\n\n\n\n\n\n\n\n\n\nInternational\nMohammed Al-Maskati\nDigital Security Helpline Director\n\n\n\n\nInternational\nMohammed Al-Maskati\nDigital Security Helpline Director\nHelpline\n\n\n\n\n\n\n\n\n\n\n\n\nInternational\nOleg Serov\nSecurity Incident Handler\n\n\n\n\nInternational\nOleg Serov\nSecurity Incident Handler\nHelpline\n\n\n\n\n\n\n\n\n\n\n\n\nLatin America and the Caribbean\nRocío\nSecurity Incident Handler\n\n\n\n\nLatin America and the Caribbean\nRocío\nSecurity Incident Handler\nHelpline\n\n\n\n\n\n\n\n\n\n\n\n\nLatin America and the Caribbean\nRogelio López\nSan José Security Shift Lead\n\n\n\n\nLatin America and the Caribbean\nRogelio López\nSan José Security Shift Lead\nHelpline\n\n\n\n\n\n\n\n\n\n\n\n\nAsia Pacific\nShinte Galeshka\nSecurity Incident Handler\n\n\n\n\nAsia Pacific\nShinte Galeshka\nSecurity Incident Handler\nHelpline\n\n\n\n\n\n\n\n\n\nEurope\nVeronica Zaboia\nPlatform Engagement Coordinator\n\n\n\n\nEurope\nVeronica Zaboia\nPlatform Engagement Coordinator\nHelpline\n\n\n\n\n\n\n\n\n\n\n\n\nInternational\nVictor Novikov\nDigital Security Helpline Manager\n\n\n\n\nInternational\nVictor Novikov\nDigital Security Helpline Manager\nHelpline\n\n\n\n\n\n\n\n\n\n\n\n\nInternational\nVlad\nSecurity Incident Handler\n\n\n\n\nInternational\nVlad\nSecurity Incident Handler\nHelpline\n\nLatin America and the Caribbean\nAlex Argüelles\nHolistic Security Lead\n\n\n\n\nLatin America and the Caribbean\nAlex Argüelles\nHolistic Security Lead\nHelpline\n\n\n\n\n\n\n\n\n\n\n\n\nEurope\nBeatrice Martini\nEducation and Communities Lead\n\n\n\n\nEurope\nBeatrice Martini\nEducation and Communities Lead\nHelpline\n\n\n\n\n\n\n\n\n\n\n\n\nAsia Pacific\nDhyta Caturani\nHelpline SEA Regional Coordinator\n\n\n\n\nAsia Pacific\nDhyta Caturani\nHelpline SEA Regional Coordinator\nHelpline\n\n\n\n\n\n\n\n\n\n\n\n\nAfrica\nDoreen Ochung\nSecurity Incident Handler\n\n\n\n\nAfrica\nDoreen Ochung\nSecurity Incident Handler\nHelpline\n\n\n\n\n\n\n\n\n\n\n\n\nInternational\nHassen Selmi\nIncident Response Lead\n\n\n\n\nInternational\nHassen Selmi\nIncident Response Lead\nHelpline\n\n\n\n\n\n\n\n\n\n\n\n\nLatin America and the Caribbean\nJean Carlo Lara\nSecurity Incident Handler\n\n\n\n\nLatin America and the Caribbean\nJean Carlo Lara\nSecurity Incident Handler\nHelpline\n\n\n\n\n\n\n\n\n\n\n\n\nEurope\nLuis Barrueto\nAdministrative and Communications Coordinator \n\n\n\n\nEurope\nLuis Barrueto\nAdministrative and Communications Coordinator \nHelpline\n\n\n\n\n\n\n\n\n\n\n\n\nInternational\nMag\nSecurity Incident Handler\n\n\n\n\nInternational\nMag\nSecurity Incident Handler\nHelpline\n\n\n\n\n\n\n\n\n\n\n\n\nInternational\nMaggie\nHelpline Documentation Coordinator\n\n\n\n\nInternational\nMaggie\nHelpline Documentation Coordinator\nHelpline\n\n\n\n\n\n\n\n\n\n\n\n\nInternational\nMalika Sharif\nSecurity Incident Handler\n\n\n\n\nInternational\nMalika Sharif\nSecurity Incident Handler\nHelpline\n\n\n\n\n\n\n\n\n\n\n\n\nAsia Pacific\nMarilou Maala\nIncident Response Analyst\n\n\n\n\nAsia Pacific\nMarilou Maala\nIncident Response Analyst\nHelpline\n\n\n\n\n\n\n\n\n\n\n\n\nAsia Pacific\nMarionne Sarmiento\nDigital Safety Specialist\n\n\n\n\nAsia Pacific\nMarionne Sarmiento\nDigital Safety Specialist\nHelpline\n\n\n\n\n\n\n\n\n\n\n\n\nInternational\nMaxim Petrov\nSafety Specialist\n\n\n\n\nInternational\nMaxim Petrov\nSafety Specialist\nHelpline\n\n\n\n\n\n\n\n\n\n\n\n\nInternational\nMohammed Al-Maskati\nDigital Security Helpline Director\n\n\n\n\nInternational\nMohammed Al-Maskati\nDigital Security Helpline Director\nHelpline\n\n\n\n\n\n\n\n\n\n\n\n\nInternational\nOleg Serov\nSecurity Incident Handler\n\n\n\n\nInternational\nOleg Serov\nSecurity Incident Handler\nHelpline\n\n\n\n\n\n\n\n\n\n\n\n\nLatin America and the Caribbean\nRocío\nSecurity Incident Handler\n\n\n\n\nLatin America and the Caribbean\nRocío\nSecurity Incident Handler\nHelpline\n\n\n\n\n\n\n\n\n\n\n\n\nLatin America and the Caribbean\nRogelio López\nSan José Security Shift Lead\n\n\n\n\nLatin America and the Caribbean\nRogelio López\nSan José Security Shift Lead\nHelpline\n\n\n\n\n\n\n\n\n\n\n\n\nAsia Pacific\nShinte Galeshka\nSecurity Incident Handler\n\n\n\n\nAsia Pacific\nShinte Galeshka\nSecurity Incident Handler\nHelpline\n\n\n\n\n\n\n\n\n\nEurope\nVeronica Zaboia\nPlatform Engagement Coordinator\n\n\n\n\nEurope\nVeronica Zaboia\nPlatform Engagement Coordinator\nHelpline\n\n\n\n\n\n\n\n\n\n\n\n\nInternational\nVictor Novikov\nDigital Security Helpline Manager\n\n\n\n\nInternational\nVictor Novikov\nDigital Security Helpline Manager\nHelpline\n\n\n\n\n\n\n\n\n\n\n\n\nInternational\nVlad\nSecurity Incident Handler\n\n\n\n\nInternational\nVlad\nSecurity Incident Handler\nHelpline\n\nLatin America and the Caribbean\nAlex Argüelles\nHolistic Security Lead\n\n\n\n\nLatin America and the Caribbean\nAlex Argüelles\nHolistic Security Lead\nHelpline\n\n\n\n\n\n\n\n\n\n\n\n\nEurope\nBeatrice Martini\nEducation and Communities Lead\n\n\n\n\nEurope\nBeatrice Martini\nEducation and Communities Lead\nHelpline\n\n\n\n\n\n\n\n\n\n\n\n\nAsia Pacific\nDhyta Caturani\nHelpline SEA Regional Coordinator\n\n\n\n\nAsia Pacific\nDhyta Caturani\nHelpline SEA Regional Coordinator\nHelpline\n\n\n\n\n\n\n\n\n\n\n\n\nAfrica\nDoreen Ochung\nSecurity Incident Handler\n\n\n\n\nAfrica\nDoreen Ochung\nSecurity Incident Handler\nHelpline\n\n\n\n\n\n\n\n\n\n\n\n\nInternational\nHassen Selmi\nIncident Response Lead\n\n\n\n\nInternational\nHassen Selmi\nIncident Response Lead\nHelpline\n\n\n\n\n\n\n\n\n\n\n\n\nLatin America and the Caribbean\nJean Carlo Lara\nSecurity Incident Handler\n\n\n\n\nLatin America and the Caribbean\nJean Carlo Lara\nSecurity Incident Handler\nHelpline\n\n\n\n\n\n\n\n\n\n\n\n\nEurope\nLuis Barrueto\nAdministrative and Communications Coordinator \n\n\n\n\nEurope\nLuis Barrueto\nAdministrative and Communications Coordinator \nHelpline\n\n\n\n\n\n\n\n\n\n\n\n\nInternational\nMag\nSecurity Incident Handler\n\n\n\n\nInternational\nMag\nSecurity Incident Handler\nHelpline\n\n\n\n\n\n\n\n\n\n\n\n\nInternational\nMaggie\nHelpline Documentation Coordinator\n\n\n\n\nInternational\nMaggie\nHelpline Documentation Coordinator\nHelpline\n\n\n\n\n\n\n\n\n\n\n\n\nInternational\nMalika Sharif\nSecurity Incident Handler\n\n\n\n\nInternational\nMalika Sharif\nSecurity Incident Handler\nHelpline\n\n\n\n\n\n\n\n\n\n\n\n\nAsia Pacific\nMarilou Maala\nIncident Response Analyst\n\n\n\n\nAsia Pacific\nMarilou Maala\nIncident Response Analyst\nHelpline\n\n\n\n\n\n\n\n\n\n\n\n\nAsia Pacific\nMarionne Sarmiento\nDigital Safety Specialist\n\n\n\n\nAsia Pacific\nMarionne Sarmiento\nDigital Safety Specialist\nHelpline\n\n\n\n\n\n\n\n\n\n\n\n\nInternational\nMaxim Petrov\nSafety Specialist\n\n\n\n\nInternational\nMaxim Petrov\nSafety Specialist\nHelpline\n\n\n\n\n\n\n\n\n\n\n\n\nInternational\nMohammed Al-Maskati\nDigital Security Helpline Director\n\n\n\n\nInternational\nMohammed Al-Maskati\nDigital Security Helpline Director\nHelpline\n\n\n\n\n\n\n\n\n\n\n\n\nInternational\nOleg Serov\nSecurity Incident Handler\n\n\n\n\nInternational\nOleg Serov\nSecurity Incident Handler\nHelpline\n\n\n\n\n\n\n\n\n\n\n\n\nLatin America and the Caribbean\nRocío\nSecurity Incident Handler\n\n\n\n\nLatin America and the Caribbean\nRocío\nSecurity Incident Handler\nHelpline\n\n\n\n\n\n\n\n\n\n\n\n\nLatin America and the Caribbean\nRogelio López\nSan José Security Shift Lead\n\n\n\n\nLatin America and the Caribbean\nRogelio López\nSan José Security Shift Lead\nHelpline\n\n\n\n\n\n\n\n\n\n\n\n\nAsia Pacific\nShinte Galeshka\nSecurity Incident Handler\n\n\n\n\nAsia Pacific\nShinte Galeshka\nSecurity Incident Handler\nHelpline\n\n\n\n\n\n\n\n\n\nEurope\nVeronica Zaboia\nPlatform Engagement Coordinator\n\n\n\n\nEurope\nVeronica Zaboia\nPlatform Engagement Coordinator\nHelpline\n\n\n\n\n\n\n\n\n\n\n\n\nInternational\nVictor Novikov\nDigital Security Helpline Manager\n\n\n\n\nInternational\nVictor Novikov\nDigital Security Helpline Manager\nHelpline\n\n\n\n\n\n\n\n\n\n\n\n\nInternational\nVlad\nSecurity Incident Handler\n\n\n\n\nInternational\nVlad\nSecurity Incident Handler\nHelpline\n\nLatin America and the Caribbean\nAlex Argüelles\nHolistic Security Lead\n\n\n\n\nLatin America and the Caribbean\nAlex Argüelles\nHolistic Security Lead\nHelpline\n\nLatin America and the Caribbean\nAlex Argüelles\nHolistic Security Lead\n\nHolistic Security Lead\n\nLatin America and the Caribbean\nAlex Argüelles\nHolistic Security Lead\nHelpline\n\nHolistic Security Lead\n\nHelpline\n\nEurope\nBeatrice Martini\nEducation and Communities Lead\n\n\n\n\nEurope\nBeatrice Martini\nEducation and Communities Lead\nHelpline\n\nEurope\nBeatrice Martini\nEducation and Communities Lead\n\nEducation and Communities Lead\n\nEurope\nBeatrice Martini\nEducation and Communities Lead\nHelpline\n\nEducation and Communities Lead\n\nHelpline\n\nAsia Pacific\nDhyta Caturani\nHelpline SEA Regional Coordinator\n\n\n\n\nAsia Pacific\nDhyta Caturani\nHelpline SEA Regional Coordinator\nHelpline\n\nAsia Pacific\nDhyta Caturani\nHelpline SEA Regional Coordinator\n\nHelpline SEA Regional Coordinator\n\nAsia Pacific\nDhyta Caturani\nHelpline SEA Regional Coordinator\nHelpline\n\nHelpline SEA Regional Coordinator\n\nHelpline\n\nAfrica\nDoreen Ochung\nSecurity Incident Handler\n\n\n\n\nAfrica\nDoreen Ochung\nSecurity Incident Handler\nHelpline\n\nAfrica\nDoreen Ochung\nSecurity Incident Handler\n\nSecurity Incident Handler\n\nAfrica\nDoreen Ochung\nSecurity Incident Handler\nHelpline\n\nSecurity Incident Handler\n\nHelpline\n\nInternational\nHassen Selmi\nIncident Response Lead\n\n\n\n\nInternational\nHassen Selmi\nIncident Response Lead\nHelpline\n\nInternational\nHassen Selmi\nIncident Response Lead\n\nIncident Response Lead\n\nInternational\nHassen Selmi\nIncident Response Lead\nHelpline\n\nIncident Response Lead\n\nHelpline\n\nLatin America and the Caribbean\nJean Carlo Lara\nSecurity Incident Handler\n\n\n\n\nLatin America and the Caribbean\nJean Carlo Lara\nSecurity Incident Handler\nHelpline\n\nLatin America and the Caribbean\nJean Carlo Lara\nSecurity Incident Handler\n\nSecurity Incident Handler\n\nLatin America and the Caribbean\nJean Carlo Lara\nSecurity Incident Handler\nHelpline\n\nSecurity Incident Handler\n\nHelpline\n\nEurope\nLuis Barrueto\nAdministrative and Communications Coordinator \n\n\n\n\nEurope\nLuis Barrueto\nAdministrative and Communications Coordinator \nHelpline\n\nEurope\nLuis Barrueto\nAdministrative and Communications Coordinator\n\nAdministrative and Communications Coordinator\n\nEurope\nLuis Barrueto\nAdministrative and Communications Coordinator \nHelpline\n\nAdministrative and Communications Coordinator\n\nHelpline\n\nInternational\nMag\nSecurity Incident Handler\n\n\n\n\nInternational\nMag\nSecurity Incident Handler\nHelpline\n\nInternational\nMag\nSecurity Incident Handler\n\nSecurity Incident Handler\n\nInternational\nMag\nSecurity Incident Handler\nHelpline\n\nSecurity Incident Handler\n\nHelpline\n\nInternational\nMaggie\nHelpline Documentation Coordinator\n\n\n\n\nInternational\nMaggie\nHelpline Documentation Coordinator\nHelpline\n\nInternational\nMaggie\nHelpline Documentation Coordinator\n\nHelpline Documentation Coordinator\n\nInternational\nMaggie\nHelpline Documentation Coordinator\nHelpline\n\nHelpline Documentation Coordinator\n\nHelpline\n\nInternational\nMalika Sharif\nSecurity Incident Handler\n\n\n\n\nInternational\nMalika Sharif\nSecurity Incident Handler\nHelpline\n\nInternational\nMalika Sharif\nSecurity Incident Handler\n\nSecurity Incident Handler\n\nInternational\nMalika Sharif\nSecurity Incident Handler\nHelpline\n\nSecurity Incident Handler\n\nHelpline\n\nAsia Pacific\nMarilou Maala\nIncident Response Analyst\n\n\n\n\nAsia Pacific\nMarilou Maala\nIncident Response Analyst\nHelpline\n\nAsia Pacific\nMarilou Maala\nIncident Response Analyst\n\nIncident Response Analyst\n\nAsia Pacific\nMarilou Maala\nIncident Response Analyst\nHelpline\n\nIncident Response Analyst\n\nHelpline\n\nAsia Pacific\nMarionne Sarmiento\nDigital Safety Specialist\n\n\n\n\nAsia Pacific\nMarionne Sarmiento\nDigital Safety Specialist\nHelpline\n\nAsia Pacific\nMarionne Sarmiento\nDigital Safety Specialist\n\nDigital Safety Specialist\n\nAsia Pacific\nMarionne Sarmiento\nDigital Safety Specialist\nHelpline\n\nDigital Safety Specialist\n\nHelpline\n\nInternational\nMaxim Petrov\nSafety Specialist\n\n\n\n\nInternational\nMaxim Petrov\nSafety Specialist\nHelpline\n\nInternational\nMaxim Petrov\nSafety Specialist\n\nSafety Specialist\n\nInternational\nMaxim Petrov\nSafety Specialist\nHelpline\n\nSafety Specialist\n\nHelpline\n\nInternational\nMohammed Al-Maskati\nDigital Security Helpline Director\n\n\n\n\nInternational\nMohammed Al-Maskati\nDigital Security Helpline Director\nHelpline\n\nInternational\nMohammed Al-Maskati\nDigital Security Helpline Director\n\nDigital Security Helpline Director\n\nInternational\nMohammed Al-Maskati\nDigital Security Helpline Director\nHelpline\n\nDigital Security Helpline Director\n\nHelpline\n\nInternational\nOleg Serov\nSecurity Incident Handler\n\n\n\n\nInternational\nOleg Serov\nSecurity Incident Handler\nHelpline\n\nInternational\nOleg Serov\nSecurity Incident Handler\n\nSecurity Incident Handler\n\nInternational\nOleg Serov\nSecurity Incident Handler\nHelpline\n\nSecurity Incident Handler\n\nHelpline\n\nLatin America and the Caribbean\nRocío\nSecurity Incident Handler\n\n\n\n\nLatin America and the Caribbean\nRocío\nSecurity Incident Handler\nHelpline\n\nLatin America and the Caribbean\nRocío\nSecurity Incident Handler\n\nSecurity Incident Handler\n\nLatin America and the Caribbean\nRocío\nSecurity Incident Handler\nHelpline\n\nSecurity Incident Handler\n\nHelpline\n\nLatin America and the Caribbean\nRogelio López\nSan José Security Shift Lead\n\n\n\n\nLatin America and the Caribbean\nRogelio López\nSan José Security Shift Lead\nHelpline\n\nLatin America and the Caribbean\nRogelio López\nSan José Security Shift Lead\n\nSan José Security Shift Lead\n\nLatin America and the Caribbean\nRogelio López\nSan José Security Shift Lead\nHelpline\n\nSan José Security Shift Lead\n\nHelpline\n\nAsia Pacific\nShinte Galeshka\nSecurity Incident Handler\n\n\n\n\nAsia Pacific\nShinte Galeshka\nSecurity Incident Handler\nHelpline\n\nAsia Pacific\nShinte Galeshka\nSecurity Incident Handler\n\nSecurity Incident Handler\n\nAsia Pacific\nShinte Galeshka\nSecurity Incident Handler\nHelpline\n\nSecurity Incident Handler\n\nHelpline\n\nEurope\nVeronica Zaboia\nPlatform Engagement Coordinator\n\n\n\n\nEurope\nVeronica Zaboia\nPlatform Engagement Coordinator\nHelpline\n\nEurope\nVeronica Zaboia\nPlatform Engagement Coordinator\n\nPlatform Engagement Coordinator\n\nEurope\nVeronica Zaboia\nPlatform Engagement Coordinator\nHelpline\n\nPlatform Engagement Coordinator\n\nHelpline\n\nInternational\nVictor Novikov\nDigital Security Helpline Manager\n\n\n\n\nInternational\nVictor Novikov\nDigital Security Helpline Manager\nHelpline\n\nInternational\nVictor Novikov\nDigital Security Helpline Manager\n\nDigital Security Helpline Manager\n\nInternational\nVictor Novikov\nDigital Security Helpline Manager\nHelpline\n\nDigital Security Helpline Manager\n\nHelpline\n\nInternational\nVlad\nSecurity Incident Handler\n\n\n\n\nInternational\nVlad\nSecurity Incident Handler\nHelpline\n\nInternational\nVlad\nSecurity Incident Handler\n\nSecurity Incident Handler\n\nInternational\nVlad\nSecurity Incident Handler\nHelpline\n\nSecurity Incident Handler\n\nHelpline\n\nCOMMUNITY & RESOURCES\n\n\n\n\n\n\n\n\n\n\n\n\n\n\n\n\n\n\n\nAccess Now’s Digital Security Helpline is a member of the Civil Society Computer Emergency Response Team (CiviCERT), an accredited CERT focused on improving the incident response capabilities of civil society groups and individuals around the world.\nCiviCERT is an initiative of Rapid Response Network (RaReNet), a network of non-governmental organizations, internet content and service providers, and individuals who contribute their time and resources to globally improve the security awareness of civil society groups.\n\n\n\nAs part of Access Now’s work and in collaboration with the broader community, we create and contribute to guides and materials to help communities, organizations, and individuals improve their digital security. These guides target a spectrum of users, from non-technical users to website administrators. Please find some guides below:\n\nDigital First Aid Kit\nA resource for emergency situations, such as when your social media account is compromised, your website is attacked, or your computer is infected \n\nHelpline PGP Email Encryption Guides (Windows | Mac | Linux)\nGuides for setting up encrypted email \n\nHelpline Safer Travel Guide\nHelping you prepare for travels to high-risk countries \n\nHelpline Self-Doxing Guide\nTips and resources for exploring open source intelligence on oneself to prevent online doxing \n\nHelpline Community Documentation\nThe procedures and documentation we create to aid our work on the Helpline \n\nPartner organizations have produced a number of guides and resources that we find valuable in our work, and you may too. They include: \n\nSecurity in a Box\nFrom Frontline Defenders and the Tactical Technology Collective \n\nSurveillance Self-Defense\nFrom the Electronic Frontier Foundation \n\nUmbrella\nFrom Security First\n\nCOMMUNITY & RESOURCES\n\n\n\n\n\n\n\n\n\n\n\n\n\n\n\n\n\n\n\nAccess Now’s Digital Security Helpline is a member of the Civil Society Computer Emergency Response Team (CiviCERT), an accredited CERT focused on improving the incident response capabilities of civil society groups and individuals around the world.\nCiviCERT is an initiative of Rapid Response Network (RaReNet), a network of non-governmental organizations, internet content and service providers, and individuals who contribute their time and resources to globally improve the security awareness of civil society groups.\n\n\n\nAs part of Access Now’s work and in collaboration with the broader community, we create and contribute to guides and materials to help communities, organizations, and individuals improve their digital security. These guides target a spectrum of users, from non-technical users to website administrators. Please find some guides below:\n\nDigital First Aid Kit\nA resource for emergency situations, such as when your social media account is compromised, your website is attacked, or your computer is infected \n\nHelpline PGP Email Encryption Guides (Windows | Mac | Linux)\nGuides for setting up encrypted email \n\nHelpline Safer Travel Guide\nHelping you prepare for travels to high-risk countries \n\nHelpline Self-Doxing Guide\nTips and resources for exploring open source intelligence on oneself to prevent online doxing \n\nHelpline Community Documentation\nThe procedures and documentation we create to aid our work on the Helpline \n\nPartner organizations have produced a number of guides and resources that we find valuable in our work, and you may too. They include: \n\nSecurity in a Box\nFrom Frontline Defenders and the Tactical Technology Collective \n\nSurveillance Self-Defense\nFrom the Electronic Frontier Foundation \n\nUmbrella\nFrom Security First\n\nAccess Now’s Digital Security Helpline is a member of the Civil Society Computer Emergency Response Team (CiviCERT), an accredited CERT focused on improving the incident response capabilities of civil society groups and individuals around the world.\nCiviCERT is an initiative of Rapid Response Network (RaReNet), a network of non-governmental organizations, internet content and service providers, and individuals who contribute their time and resources to globally improve the security awareness of civil society groups.\n\nAccess Now’s Digital Security Helpline is a member of the Civil Society Computer Emergency Response Team (CiviCERT), an accredited CERT focused on improving the incident response capabilities of civil society groups and individuals around the world.\nCiviCERT is an initiative of Rapid Response Network (RaReNet), a network of non-governmental organizations, internet content and service providers, and individuals who contribute their time and resources to globally improve the security awareness of civil society groups.\n\nAccess Now’s Digital Security Helpline is a member of the Civil Society Computer Emergency Response Team (CiviCERT), an accredited CERT focused on improving the incident response capabilities of civil society groups and individuals around the world.\nCiviCERT is an initiative of Rapid Response Network (RaReNet), a network of non-governmental organizations, internet content and service providers, and individuals who contribute their time and resources to globally improve the security awareness of civil society groups.\n\nAccess Now’s Digital Security Helpline is a member of the Civil Society Computer Emergency Response Team (CiviCERT), an accredited CERT focused on improving the incident response capabilities of civil society groups and individuals around the world.\n\nCiviCERT is an initiative of Rapid Response Network (RaReNet), a network of non-governmental organizations, internet content and service providers, and individuals who contribute their time and resources to globally improve the security awareness of civil society groups.\n\nAs part of Access Now’s work and in collaboration with the broader community, we create and contribute to guides and materials to help communities, organizations, and individuals improve their digital security. These guides target a spectrum of users, from non-technical users to website administrators. Please find some guides below:\n\nA resource for emergency situations, such as when your social media account is compromised, your website is attacked, or your computer is infected\n\nGuides for setting up encrypted email\n\nHelping you prepare for travels to high-risk countries\n\nTips and resources for exploring open source intelligence on oneself to prevent online doxing\n\nThe procedures and documentation we create to aid our work on the Helpline\n\nPartner organizations have produced a number of guides and resources that we find valuable in our work, and you may too. They include:\n\nFrom Frontline Defenders and the Tactical Technology Collective\n\nFrom the Electronic Frontier Foundation\n\nFrom Security First\n\nHelp keep the internet open and secure.\nSubscribe to our action alerts and weekly newsletter\n\"*\" indicates required fields\n\nThis field is hidden when viewing the form\n\nSubscribe to Access Express\nThis field is hidden when viewing the form\n\nSubscribe to Action Alerts\nName\n\n\nFirst\n\n\n\nLast\n\nEmail*\n\nCountryCountryAfghanistanÅland IslandsAlbaniaAlgeriaAmerican SamoaAndorraAngolaAnguillaAntigua and BarbudaArgentinaArmeniaArubaAustraliaAustriaAzerbaijanBahamasBahrainBangladeshBarbadosBelarusBelgiumBelizeBeninBermudaBhutanBoliviaBonaire, Sint Eustatius and SabaBosnia and HerzegovinaBotswanaBrazilBritish Indian Ocean TerritoryBritish Virgin IslandsBruneiBulgariaBurkina FasoBurundiCambodiaCameroonCanadaCape VerdeCayman IslandsCentral African RepublicChadChileChinaChristmas IslandColombiaComorosCook IslandsCosta RicaCôte d'IvoireCroatiaCubaCuraçaoCyprusCzech RepublicDemocratic Republic of the CongoDenmarkDjiboutiDominicaDominican RepublicEast TimorEcuadorEgyptEl SalvadorEquatorial GuineaEritreaEstoniaEswatiniEthiopiaFalkland IslandsFaroe IslandsFijiFinlandFranceFrench GuianaFrench PolynesiaFrench Southern TerritoriesGabonGeorgiaGermanyGhanaGibraltarGreeceGreenlandGrenadaGuadeloupeGuamGuatemalaGuernseyGuineaGuinea-BissauGuyanaHaitiHondurasHong KongHungaryIcelandIndiaIndonesiaIranIraqIrelandIsraelItalyJamaicaJapanJordanKazakhstanKenyaKiribatiKosovoKuwaitKyrgyzstanLaosLatviaLebanonLesothoLiberiaLibyaLiechtensteinLithuaniaLuxembourgMacauMadagascarMalawiMalaysiaMaldivesMaliMaltaMarshall IslandsMartiniqueMauritaniaMauritiusMayotteMexicoMicronesiaMoldovaMonacoMongoliaMontenegroMontserratMoroccoMozambiqueMyanmarNamibiaNauruNepalNetherlands AntillesNew CaledoniaNew ZealandNicaraguaNigerNigeriaNiueNorfolk IslandNorth KoreaNorth MacedoniaNorthern Mariana IslandsNorwayOmanPakistanPalauPalestinePanamaPapua New GuineaParaguayPeruPhilippinesPitcairn IslandPolandPortugalPuerto RicoQatarRepublic of the CongoReunionRomaniaRussiaRwandaSaint BarthélemySaint Kitts and NevisSaint LuciaSaint Vincent and the GrenadinesSamoaSan MarinoSão Tomé and PríncipeSaudi ArabiaSenegalSerbiaSeychellesSierra LeoneSingaporeSlovakiaSloveniaSolomon IslandsSomaliaSomalilandSouth AfricaSouth KoreaSouth SudanSpainSri LankaSt. HelenaSt. Pierre and MiquelonSudanSurinameSwedenSwitzerlandSyriaTaiwanTajikistanTanzaniaThailandThe GambiaThe NetherlandsTogoTokelauTongaTrinidad and TobagoTunisiaTurkeyTurkmenistanTurks and Caicos IslandsTuvaluUgandaUkraineUnited Arab EmiratesUnited KingdomUnited StatesUruguayUzbekistanVanuatuVatican CityVenezuelaVietnamVirgin Islands (U.S.)Wallis and Futuna IslandsWestern SaharaYemenZambiaZimbabwePostal CodeCommentsThis field is for validation purposes and should be left unchanged.\n \n\n\n\n\n\n\n\n\n\n\n\n\n\n\n\nYour info is secure with us\n\nHelp keep the internet open and secure.\nSubscribe to our action alerts and weekly newsletter\n\"*\" indicates required fields\n\nThis field is hidden when viewing the form\n\nSubscribe to Access Express\nThis field is hidden when viewing the form\n\nSubscribe to Action Alerts\nName\n\n\nFirst\n\n\n\nLast\n\nEmail*\n\nCountryCountryAfghanistanÅland IslandsAlbaniaAlgeriaAmerican SamoaAndorraAngolaAnguillaAntigua and BarbudaArgentinaArmeniaArubaAustraliaAustriaAzerbaijanBahamasBahrainBangladeshBarbadosBelarusBelgiumBelizeBeninBermudaBhutanBoliviaBonaire, Sint Eustatius and SabaBosnia and HerzegovinaBotswanaBrazilBritish Indian Ocean TerritoryBritish Virgin IslandsBruneiBulgariaBurkina FasoBurundiCambodiaCameroonCanadaCape VerdeCayman IslandsCentral African RepublicChadChileChinaChristmas IslandColombiaComorosCook IslandsCosta RicaCôte d'IvoireCroatiaCubaCuraçaoCyprusCzech RepublicDemocratic Republic of the CongoDenmarkDjiboutiDominicaDominican RepublicEast TimorEcuadorEgyptEl SalvadorEquatorial GuineaEritreaEstoniaEswatiniEthiopiaFalkland IslandsFaroe IslandsFijiFinlandFranceFrench GuianaFrench PolynesiaFrench Southern TerritoriesGabonGeorgiaGermanyGhanaGibraltarGreeceGreenlandGrenadaGuadeloupeGuamGuatemalaGuernseyGuineaGuinea-BissauGuyanaHaitiHondurasHong KongHungaryIcelandIndiaIndonesiaIranIraqIrelandIsraelItalyJamaicaJapanJordanKazakhstanKenyaKiribatiKosovoKuwaitKyrgyzstanLaosLatviaLebanonLesothoLiberiaLibyaLiechtensteinLithuaniaLuxembourgMacauMadagascarMalawiMalaysiaMaldivesMaliMaltaMarshall IslandsMartiniqueMauritaniaMauritiusMayotteMexicoMicronesiaMoldovaMonacoMongoliaMontenegroMontserratMoroccoMozambiqueMyanmarNamibiaNauruNepalNetherlands AntillesNew CaledoniaNew ZealandNicaraguaNigerNigeriaNiueNorfolk IslandNorth KoreaNorth MacedoniaNorthern Mariana IslandsNorwayOmanPakistanPalauPalestinePanamaPapua New GuineaParaguayPeruPhilippinesPitcairn IslandPolandPortugalPuerto RicoQatarRepublic of the CongoReunionRomaniaRussiaRwandaSaint BarthélemySaint Kitts and NevisSaint LuciaSaint Vincent and the GrenadinesSamoaSan MarinoSão Tomé and PríncipeSaudi ArabiaSenegalSerbiaSeychellesSierra LeoneSingaporeSlovakiaSloveniaSolomon IslandsSomaliaSomalilandSouth AfricaSouth KoreaSouth SudanSpainSri LankaSt. HelenaSt. Pierre and MiquelonSudanSurinameSwedenSwitzerlandSyriaTaiwanTajikistanTanzaniaThailandThe GambiaThe NetherlandsTogoTokelauTongaTrinidad and TobagoTunisiaTurkeyTurkmenistanTurks and Caicos IslandsTuvaluUgandaUkraineUnited Arab EmiratesUnited KingdomUnited StatesUruguayUzbekistanVanuatuVatican CityVenezuelaVietnamVirgin Islands (U.S.)Wallis and Futuna IslandsWestern SaharaYemenZambiaZimbabwePostal CodeCommentsThis field is for validation purposes and should be left unchanged.\n \n\n\n\n\n\n\n\n\n\n\n\n\n\n\n\nYour info is secure with us\n\nHelp keep the internet open and secure.\nSubscribe to our action alerts and weekly newsletter\n\"*\" indicates required fields\n\nThis field is hidden when viewing the form\n\nSubscribe to Access Express\nThis field is hidden when viewing the form\n\nSubscribe to Action Alerts\nName\n\n\nFirst\n\n\n\nLast\n\nEmail*\n\nCountryCountryAfghanistanÅland IslandsAlbaniaAlgeriaAmerican SamoaAndorraAngolaAnguillaAntigua and BarbudaArgentinaArmeniaArubaAustraliaAustriaAzerbaijanBahamasBahrainBangladeshBarbadosBelarusBelgiumBelizeBeninBermudaBhutanBoliviaBonaire, Sint Eustatius and SabaBosnia and HerzegovinaBotswanaBrazilBritish Indian Ocean TerritoryBritish Virgin IslandsBruneiBulgariaBurkina FasoBurundiCambodiaCameroonCanadaCape VerdeCayman IslandsCentral African RepublicChadChileChinaChristmas IslandColombiaComorosCook IslandsCosta RicaCôte d'IvoireCroatiaCubaCuraçaoCyprusCzech RepublicDemocratic Republic of the CongoDenmarkDjiboutiDominicaDominican RepublicEast TimorEcuadorEgyptEl SalvadorEquatorial GuineaEritreaEstoniaEswatiniEthiopiaFalkland IslandsFaroe IslandsFijiFinlandFranceFrench GuianaFrench PolynesiaFrench Southern TerritoriesGabonGeorgiaGermanyGhanaGibraltarGreeceGreenlandGrenadaGuadeloupeGuamGuatemalaGuernseyGuineaGuinea-BissauGuyanaHaitiHondurasHong KongHungaryIcelandIndiaIndonesiaIranIraqIrelandIsraelItalyJamaicaJapanJordanKazakhstanKenyaKiribatiKosovoKuwaitKyrgyzstanLaosLatviaLebanonLesothoLiberiaLibyaLiechtensteinLithuaniaLuxembourgMacauMadagascarMalawiMalaysiaMaldivesMaliMaltaMarshall IslandsMartiniqueMauritaniaMauritiusMayotteMexicoMicronesiaMoldovaMonacoMongoliaMontenegroMontserratMoroccoMozambiqueMyanmarNamibiaNauruNepalNetherlands AntillesNew CaledoniaNew ZealandNicaraguaNigerNigeriaNiueNorfolk IslandNorth KoreaNorth MacedoniaNorthern Mariana IslandsNorwayOmanPakistanPalauPalestinePanamaPapua New GuineaParaguayPeruPhilippinesPitcairn IslandPolandPortugalPuerto RicoQatarRepublic of the CongoReunionRomaniaRussiaRwandaSaint BarthélemySaint Kitts and NevisSaint LuciaSaint Vincent and the GrenadinesSamoaSan MarinoSão Tomé and PríncipeSaudi ArabiaSenegalSerbiaSeychellesSierra LeoneSingaporeSlovakiaSloveniaSolomon IslandsSomaliaSomalilandSouth AfricaSouth KoreaSouth SudanSpainSri LankaSt. HelenaSt. Pierre and MiquelonSudanSurinameSwedenSwitzerlandSyriaTaiwanTajikistanTanzaniaThailandThe GambiaThe NetherlandsTogoTokelauTongaTrinidad and TobagoTunisiaTurkeyTurkmenistanTurks and Caicos IslandsTuvaluUgandaUkraineUnited Arab EmiratesUnited KingdomUnited StatesUruguayUzbekistanVanuatuVatican CityVenezuelaVietnamVirgin Islands (U.S.)Wallis and Futuna IslandsWestern SaharaYemenZambiaZimbabwePostal CodeCommentsThis field is for validation purposes and should be left unchanged.\n\nHelp keep the internet open and secure.\nSubscribe to our action alerts and weekly newsletter\n\"*\" indicates required fields\n\nSubscribe to our action alerts and weekly newsletter\n\n\"*\" indicates required fields\n\nThis field is hidden when viewing the form\n\nSubscribe to Access Express\nThis field is hidden when viewing the form\n\nSubscribe to Action Alerts\nName\n\n\nFirst\n\n\n\nLast\n\nEmail*\n\nCountryCountryAfghanistanÅland IslandsAlbaniaAlgeriaAmerican SamoaAndorraAngolaAnguillaAntigua and BarbudaArgentinaArmeniaArubaAustraliaAustriaAzerbaijanBahamasBahrainBangladeshBarbadosBelarusBelgiumBelizeBeninBermudaBhutanBoliviaBonaire, Sint Eustatius and SabaBosnia and HerzegovinaBotswanaBrazilBritish Indian Ocean TerritoryBritish Virgin IslandsBruneiBulgariaBurkina FasoBurundiCambodiaCameroonCanadaCape VerdeCayman IslandsCentral African RepublicChadChileChinaChristmas IslandColombiaComorosCook IslandsCosta RicaCôte d'IvoireCroatiaCubaCuraçaoCyprusCzech RepublicDemocratic Republic of the CongoDenmarkDjiboutiDominicaDominican RepublicEast TimorEcuadorEgyptEl SalvadorEquatorial GuineaEritreaEstoniaEswatiniEthiopiaFalkland IslandsFaroe IslandsFijiFinlandFranceFrench GuianaFrench PolynesiaFrench Southern TerritoriesGabonGeorgiaGermanyGhanaGibraltarGreeceGreenlandGrenadaGuadeloupeGuamGuatemalaGuernseyGuineaGuinea-BissauGuyanaHaitiHondurasHong KongHungaryIcelandIndiaIndonesiaIranIraqIrelandIsraelItalyJamaicaJapanJordanKazakhstanKenyaKiribatiKosovoKuwaitKyrgyzstanLaosLatviaLebanonLesothoLiberiaLibyaLiechtensteinLithuaniaLuxembourgMacauMadagascarMalawiMalaysiaMaldivesMaliMaltaMarshall IslandsMartiniqueMauritaniaMauritiusMayotteMexicoMicronesiaMoldovaMonacoMongoliaMontenegroMontserratMoroccoMozambiqueMyanmarNamibiaNauruNepalNetherlands AntillesNew CaledoniaNew ZealandNicaraguaNigerNigeriaNiueNorfolk IslandNorth KoreaNorth MacedoniaNorthern Mariana IslandsNorwayOmanPakistanPalauPalestinePanamaPapua New GuineaParaguayPeruPhilippinesPitcairn IslandPolandPortugalPuerto RicoQatarRepublic of the CongoReunionRomaniaRussiaRwandaSaint BarthélemySaint Kitts and NevisSaint LuciaSaint Vincent and the GrenadinesSamoaSan MarinoSão Tomé and PríncipeSaudi ArabiaSenegalSerbiaSeychellesSierra LeoneSingaporeSlovakiaSloveniaSolomon IslandsSomaliaSomalilandSouth AfricaSouth KoreaSouth SudanSpainSri LankaSt. HelenaSt. Pierre and MiquelonSudanSurinameSwedenSwitzerlandSyriaTaiwanTajikistanTanzaniaThailandThe GambiaThe NetherlandsTogoTokelauTongaTrinidad and TobagoTunisiaTurkeyTurkmenistanTurks and Caicos IslandsTuvaluUgandaUkraineUnited Arab EmiratesUnited KingdomUnited StatesUruguayUzbekistanVanuatuVatican CityVenezuelaVietnamVirgin Islands (U.S.)Wallis and Futuna IslandsWestern SaharaYemenZambiaZimbabwePostal CodeCommentsThis field is for validation purposes and should be left unchanged.\n\nThis field is hidden when viewing the form\n\nSubscribe to Access Express\nThis field is hidden when viewing the form\n\nSubscribe to Action Alerts\nName\n\n\nFirst\n\n\n\nLast\n\nEmail*\n\nCountryCountryAfghanistanÅland IslandsAlbaniaAlgeriaAmerican SamoaAndorraAngolaAnguillaAntigua and BarbudaArgentinaArmeniaArubaAustraliaAustriaAzerbaijanBahamasBahrainBangladeshBarbadosBelarusBelgiumBelizeBeninBermudaBhutanBoliviaBonaire, Sint Eustatius and SabaBosnia and HerzegovinaBotswanaBrazilBritish Indian Ocean TerritoryBritish Virgin IslandsBruneiBulgariaBurkina FasoBurundiCambodiaCameroonCanadaCape VerdeCayman IslandsCentral African RepublicChadChileChinaChristmas IslandColombiaComorosCook IslandsCosta RicaCôte d'IvoireCroatiaCubaCuraçaoCyprusCzech RepublicDemocratic Republic of the CongoDenmarkDjiboutiDominicaDominican RepublicEast TimorEcuadorEgyptEl SalvadorEquatorial GuineaEritreaEstoniaEswatiniEthiopiaFalkland IslandsFaroe IslandsFijiFinlandFranceFrench GuianaFrench PolynesiaFrench Southern TerritoriesGabonGeorgiaGermanyGhanaGibraltarGreeceGreenlandGrenadaGuadeloupeGuamGuatemalaGuernseyGuineaGuinea-BissauGuyanaHaitiHondurasHong KongHungaryIcelandIndiaIndonesiaIranIraqIrelandIsraelItalyJamaicaJapanJordanKazakhstanKenyaKiribatiKosovoKuwaitKyrgyzstanLaosLatviaLebanonLesothoLiberiaLibyaLiechtensteinLithuaniaLuxembourgMacauMadagascarMalawiMalaysiaMaldivesMaliMaltaMarshall IslandsMartiniqueMauritaniaMauritiusMayotteMexicoMicronesiaMoldovaMonacoMongoliaMontenegroMontserratMoroccoMozambiqueMyanmarNamibiaNauruNepalNetherlands AntillesNew CaledoniaNew ZealandNicaraguaNigerNigeriaNiueNorfolk IslandNorth KoreaNorth MacedoniaNorthern Mariana IslandsNorwayOmanPakistanPalauPalestinePanamaPapua New GuineaParaguayPeruPhilippinesPitcairn IslandPolandPortugalPuerto RicoQatarRepublic of the CongoReunionRomaniaRussiaRwandaSaint BarthélemySaint Kitts and NevisSaint LuciaSaint Vincent and the GrenadinesSamoaSan MarinoSão Tomé and PríncipeSaudi ArabiaSenegalSerbiaSeychellesSierra LeoneSingaporeSlovakiaSloveniaSolomon IslandsSomaliaSomalilandSouth AfricaSouth KoreaSouth SudanSpainSri LankaSt. HelenaSt. Pierre and MiquelonSudanSurinameSwedenSwitzerlandSyriaTaiwanTajikistanTanzaniaThailandThe GambiaThe NetherlandsTogoTokelauTongaTrinidad and TobagoTunisiaTurkeyTurkmenistanTurks and Caicos IslandsTuvaluUgandaUkraineUnited Arab EmiratesUnited KingdomUnited StatesUruguayUzbekistanVanuatuVatican CityVenezuelaVietnamVirgin Islands (U.S.)Wallis and Futuna IslandsWestern SaharaYemenZambiaZimbabwePostal CodeCommentsThis field is for validation purposes and should be left unchanged.\n\nThis field is hidden when viewing the form\n\nSubscribe to Access Express\n\nSubscribe to Access Express\n\nSubscribe to Access Express\n\nThis field is hidden when viewing the form\n\nSubscribe to Action Alerts\n\nSubscribe to Action Alerts\n\nSubscribe to Action Alerts\n\nFirst\n\n\n\nLast\n\nEmail*\n\nCountryCountryAfghanistanÅland IslandsAlbaniaAlgeriaAmerican SamoaAndorraAngolaAnguillaAntigua and BarbudaArgentinaArmeniaArubaAustraliaAustriaAzerbaijanBahamasBahrainBangladeshBarbadosBelarusBelgiumBelizeBeninBermudaBhutanBoliviaBonaire, Sint Eustatius and SabaBosnia and HerzegovinaBotswanaBrazilBritish Indian Ocean TerritoryBritish Virgin IslandsBruneiBulgariaBurkina FasoBurundiCambodiaCameroonCanadaCape VerdeCayman IslandsCentral African RepublicChadChileChinaChristmas IslandColombiaComorosCook IslandsCosta RicaCôte d'IvoireCroatiaCubaCuraçaoCyprusCzech RepublicDemocratic Republic of the CongoDenmarkDjiboutiDominicaDominican RepublicEast TimorEcuadorEgyptEl SalvadorEquatorial GuineaEritreaEstoniaEswatiniEthiopiaFalkland IslandsFaroe IslandsFijiFinlandFranceFrench GuianaFrench PolynesiaFrench Southern TerritoriesGabonGeorgiaGermanyGhanaGibraltarGreeceGreenlandGrenadaGuadeloupeGuamGuatemalaGuernseyGuineaGuinea-BissauGuyanaHaitiHondurasHong KongHungaryIcelandIndiaIndonesiaIranIraqIrelandIsraelItalyJamaicaJapanJordanKazakhstanKenyaKiribatiKosovoKuwaitKyrgyzstanLaosLatviaLebanonLesothoLiberiaLibyaLiechtensteinLithuaniaLuxembourgMacauMadagascarMalawiMalaysiaMaldivesMaliMaltaMarshall IslandsMartiniqueMauritaniaMauritiusMayotteMexicoMicronesiaMoldovaMonacoMongoliaMontenegroMontserratMoroccoMozambiqueMyanmarNamibiaNauruNepalNetherlands AntillesNew CaledoniaNew ZealandNicaraguaNigerNigeriaNiueNorfolk IslandNorth KoreaNorth MacedoniaNorthern Mariana IslandsNorwayOmanPakistanPalauPalestinePanamaPapua New GuineaParaguayPeruPhilippinesPitcairn IslandPolandPortugalPuerto RicoQatarRepublic of the CongoReunionRomaniaRussiaRwandaSaint BarthélemySaint Kitts and NevisSaint LuciaSaint Vincent and the GrenadinesSamoaSan MarinoSão Tomé and PríncipeSaudi ArabiaSenegalSerbiaSeychellesSierra LeoneSingaporeSlovakiaSloveniaSolomon IslandsSomaliaSomalilandSouth AfricaSouth KoreaSouth SudanSpainSri LankaSt. HelenaSt. Pierre and MiquelonSudanSurinameSwedenSwitzerlandSyriaTaiwanTajikistanTanzaniaThailandThe GambiaThe NetherlandsTogoTokelauTongaTrinidad and TobagoTunisiaTurkeyTurkmenistanTurks and Caicos IslandsTuvaluUgandaUkraineUnited Arab EmiratesUnited KingdomUnited StatesUruguayUzbekistanVanuatuVatican CityVenezuelaVietnamVirgin Islands (U.S.)Wallis and Futuna IslandsWestern SaharaYemenZambiaZimbabwe\n\nCountryAfghanistanÅland IslandsAlbaniaAlgeriaAmerican SamoaAndorraAngolaAnguillaAntigua and BarbudaArgentinaArmeniaArubaAustraliaAustriaAzerbaijanBahamasBahrainBangladeshBarbadosBelarusBelgiumBelizeBeninBermudaBhutanBoliviaBonaire, Sint Eustatius and SabaBosnia and HerzegovinaBotswanaBrazilBritish Indian Ocean TerritoryBritish Virgin IslandsBruneiBulgariaBurkina FasoBurundiCambodiaCameroonCanadaCape VerdeCayman IslandsCentral African RepublicChadChileChinaChristmas IslandColombiaComorosCook IslandsCosta RicaCôte d'IvoireCroatiaCubaCuraçaoCyprusCzech RepublicDemocratic Republic of the CongoDenmarkDjiboutiDominicaDominican RepublicEast TimorEcuadorEgyptEl SalvadorEquatorial GuineaEritreaEstoniaEswatiniEthiopiaFalkland IslandsFaroe IslandsFijiFinlandFranceFrench GuianaFrench PolynesiaFrench Southern TerritoriesGabonGeorgiaGermanyGhanaGibraltarGreeceGreenlandGrenadaGuadeloupeGuamGuatemalaGuernseyGuineaGuinea-BissauGuyanaHaitiHondurasHong KongHungaryIcelandIndiaIndonesiaIranIraqIrelandIsraelItalyJamaicaJapanJordanKazakhstanKenyaKiribatiKosovoKuwaitKyrgyzstanLaosLatviaLebanonLesothoLiberiaLibyaLiechtensteinLithuaniaLuxembourgMacauMadagascarMalawiMalaysiaMaldivesMaliMaltaMarshall IslandsMartiniqueMauritaniaMauritiusMayotteMexicoMicronesiaMoldovaMonacoMongoliaMontenegroMontserratMoroccoMozambiqueMyanmarNamibiaNauruNepalNetherlands AntillesNew CaledoniaNew ZealandNicaraguaNigerNigeriaNiueNorfolk IslandNorth KoreaNorth MacedoniaNorthern Mariana IslandsNorwayOmanPakistanPalauPalestinePanamaPapua New GuineaParaguayPeruPhilippinesPitcairn IslandPolandPortugalPuerto RicoQatarRepublic of the CongoReunionRomaniaRussiaRwandaSaint BarthélemySaint Kitts and NevisSaint LuciaSaint Vincent and the GrenadinesSamoaSan MarinoSão Tomé and PríncipeSaudi ArabiaSenegalSerbiaSeychellesSierra LeoneSingaporeSlovakiaSloveniaSolomon IslandsSomaliaSomalilandSouth AfricaSouth KoreaSouth SudanSpainSri LankaSt. HelenaSt. Pierre and MiquelonSudanSurinameSwedenSwitzerlandSyriaTaiwanTajikistanTanzaniaThailandThe GambiaThe NetherlandsTogoTokelauTongaTrinidad and TobagoTunisiaTurkeyTurkmenistanTurks and Caicos IslandsTuvaluUgandaUkraineUnited Arab EmiratesUnited KingdomUnited StatesUruguayUzbekistanVanuatuVatican CityVenezuelaVietnamVirgin Islands (U.S.)Wallis and Futuna IslandsWestern SaharaYemenZambiaZimbabwe\n\nPostal Code\n\nCommentsThis field is for validation purposes and should be left unchanged.\n\nThis field is for validation purposes and should be left unchanged.\n\nYour info is secure with us",
  "date": "",
  "source_type": "other",
  "extracted_at": "2025-04-07T13:45:36.921204",
  "metadata": {
    "description": "Our Helpline provides 24/7 free of charge technical support for journalists, activists, and human rights defenders",
    "og:type": "article",
    "og:site_name": "Access Now"
  },
  "relevance_score": 0.5166666666666667,
  "summary": "Back to content\n\nDIGITAL SECURITY HELPLINE\n\n\n\n\n\nHow We Help\nWho Can We Help\nContact Us\nCommunity & Resources\n\n\n\nWHAT IS THE DIGITAL SECURITY HELPLINE? Available translations:\n\n Pусский Español Português العربية Français Deutsch Italiano Tagalog українська \n\n\n\n\nAccess Now’s Digital Security Helpline works with individuals and organizations around the world to keep them safe online. The Helpline will walk you or your organization through assessing the risks you face in your work, and  together we’ll prioritize your digital security needs. Case: Human rights defenders in Azerbaijan fend off malware attacks – Amnesty International\n\n\n\n\n\n\n\n\n\nOUR SERVICES\n\n\n24/7, real-time, direct technical assistance and advice\n\n\n\n\n\n\n\n\n\n\n\nNo matter what digital security challenges you face, we offer a range of services and resources to help you be safe online:\n\n\n\n\n\n\n\n\n\n\n\n\nRapid response for digital security incidents\n\n\n\n\n\n\n\n\nPersonalized recommendations, instruction, and follow-up support for digital security issues\n\n\n\n\n\n\n\n\nHelp assessing risks and creating organizational or community security strategies\n\n\n\n\n\n\n\n\nGuidance and educational materials on security practices and tools for organizations, communities, groups, and individuals\n\n\n\n\n\n\n\n\nSupport for securing technical infrastructure, websites, and social media against attacks\n\n\n\n\n\n\n\n\nReferrals, capacity-building, in-person consultations, and training\n\n\n\n\n\n\n\n\n\nDIGITAL SECURITY CLINIC\n\n\n\nAccess Now’s Digital Security Clinic brings the Helpline to you. Latin America and the Caribbean\nAlex Argüelles\nHolistic Security Lead\n\n\n\n\nLatin America and the Caribbean\nAlex Argüelles\nHolistic Security Lead\nHelpline\n\n\n\n\n\n\n\n\n\n\n\n\nEurope\nBeatrice Martini\nEducation and Communities Lead\n\n\n\n\nEurope\nBeatrice Martini\nEducation and Communities Lead\nHelpline\n\n\n\n\n\n\n\n\n\n\n\n\nAsia Pacific\nDhyta Caturani\nHelpline SEA Regional Coordinator\n\n\n\n\nAsia Pacific\nDhyta Caturani\nHelpline SEA Regional Coordinator\nHelpline\n\n\n\n\n\n\n\n\n\n\n\n\nAfrica\nDoreen Ochung\nSecurity Incident Handler\n\n\n\n\nAfrica\nDoreen Ochung\nSecurity Incident Handler\nHelpline\n\n\n\n\n\n\n\n\n\n\n\n\nInternational\nHassen Selmi\nIncident Response Lead\n\n\n\n\nInternational\nHassen Selmi\nIncident Response Lead\nHelpline\n\n\n\n\n\n\n\n\n\n\n\n\nLatin America and the Caribbean\nJean Carlo Lara\nSecurity Incident Handler\n\n\n\n\nLatin America and the Caribbean\nJean Carlo Lara\nSecurity Incident Handler\nHelpline\n\n\n\n\n\n\n\n\n\n\n\n\nEurope\nLuis Barrueto\nAdministrative and Communications Coordinator \n\n\n\n\nEurope\nLuis Barrueto\nAdministrative and Communications Coordinator \nHelpline\n\n\n\n\n\n\n\n\n\n\n\n\nInternational\nMag\nSecurity Incident Handler\n\n\n\n\nInternational\nMag\nSecurity Incident Handler\nHelpline\n\n\n\n\n\n\n\n\n\n\n\n\nInternational\nMaggie\nHelpline Documentation Coordinator\n\n\n\n\nInternational\nMaggie\nHelpline Documentation Coordinator\nHelpline\n\n\n\n\n\n\n\n\n\n\n\n\nInternational\nMalika Sharif\nSecurity Incident Handler\n\n\n\n\nInternational\nMalika Sharif\nSecurity Incident Handler\nHelpline\n\n\n\n\n\n\n\n\n\n\n\n\nAsia Pacific\nMarilou Maala\nIncident Response Analyst\n\n\n\n\nAsia Pacific\nMarilou Maala\nIncident Response Analyst\nHelpline\n\n\n\n\n\n\n\n\n\n\n\n\nAsia Pacific\nMarionne Sarmiento\nDigital Safety Specialist\n\n\n\n\nAsia Pacific\nMarionne Sarmiento\nDigital Safety Specialist\nHelpline\n\n\n\n\n\n\n\n\n\n\n\n\nInternational\nMaxim Petrov\nSafety Specialist\n\n\n\n\nInternational\nMaxim Petrov\nSafety Specialist\nHelpline\n\n\n\n\n\n\n\n\n\n\n\n\nInternational\nMohammed Al-Maskati\nDigital Security Helpline Director\n\n\n\n\nInternational\nMohammed Al-Maskati\nDigital Security Helpline Director\nHelpline\n\n\n\n\n\n\n\n\n\n\n\n\nInternational\nOleg Serov\nSecurity Incident Handler\n\n\n\n\nInternational\nOleg Serov\nSecurity Incident Handler\nHelpline\n\n\n\n\n\n\n\n\n\n\n\n\nLatin America and the Caribbean\nRocío\nSecurity Incident Handler\n\n\n\n\nLatin America and the Caribbean\nRocío\nSecurity Incident Handler\nHelpline\n\n\n\n\n\n\n\n\n\n\n\n\nLatin America and the Caribbean\nRogelio López\nSan José Security Shift Lead\n\n\n\n\nLatin America and the Caribbean\nRogelio López\nSan José Security Shift Lead\nHelpline\n\n\n\n\n\n\n\n\n\n\n\n\nAsia Pacific\nShinte Galeshka\nSecurity Incident Handler\n\n\n\n\nAsia Pacific\nShinte Galeshka\nSecurity Incident Handler\nHelpline\n\n\n\n\n\n\n\n\n\nEurope\nVeronica Zaboia\nPlatform Engagement Coordinator\n\n\n\n\nEurope\nVeronica Zaboia\nPlatform Engagement Coordinator\nHelpline\n\n\n\n\n\n\n\n\n\n\n\n\nInternational\nVictor Novikov\nDigital Security Helpline Manager\n\n\n\n\nInternational\nVictor Novikov\nDigital Security Helpline Manager\nHelpline\n\n\n\n\n\n\n\n\n\n\n\n\nInternational\nVlad\nSecurity Incident Handler\n\n\n\n\nInternational\nVlad\nSecurity Incident Handler\nHelpline\n\n\n\n\n\n\n\n\n\n\nCOMMUNITY & RESOURCES\n\n\n\n\n\n\n\n\n\n\n\n\n\n\n\n\n\n\n\nAccess Now’s Digital Security Helpline is a member of the Civil Society Computer Emergency Response Team (CiviCERT), an accredited CERT focused on improving the incident response capabilities of civil society groups and individuals around the world. As part of Access Now’s work and in collaboration with the broader community, we create and contribute to guides and materials to help communities, organizations, and individuals improve their digital security. Please find some guides below:\n\nDigital First Aid Kit\nA resource for emergency situations, such as when your social media account is compromised, your website is attacked, or your computer is infected \n\nHelpline PGP Email Encryption Guides (Windows | Mac | Linux)\nGuides for setting up encrypted email \n\nHelpline Safer Travel Guide\nHelping you prepare for travels to high-risk countries \n\nHelpline Self-Doxing Guide\nTips and resources for exploring open source intelligence on oneself to prevent online doxing \n\nHelpline Community Documentation\nThe procedures and documentation we create to aid our work on the Helpline \n\nPartner organizations have produced a number of guides and resources that we find valuable in our work, and you may too. They include: \n\nSecurity in a Box\nFrom Frontline Defenders and the Tactical Technology Collective \n\nSurveillance Self-Defense\nFrom the Electronic Frontier Foundation \n\nUmbrella\nFrom Security First \n\n\n\n\n\n\n\n \n\n\n\n\n\n\nHelp keep the internet open and secure. Your info is secure with us\n\nDIGITAL SECURITY HELPLINE\n\n\n\n\n\nHow We Help\nWho Can We Help\nContact Us\nCommunity & Resources\n\n\n\nWHAT IS THE DIGITAL SECURITY HELPLINE? Available translations:\n\n Pусский Español Português العربية Français Deutsch Italiano Tagalog українська \n\n\n\n\nAccess Now’s Digital Security Helpline works with individuals and organizations around the world to keep them safe online. The Helpline will walk you or your organization through assessing the risks you face in your work, and  together we’ll prioritize your digital security needs. Case: Human rights defenders in Azerbaijan fend off malware attacks – Amnesty International\n\n\n\n\n\n\n\n\n\nOUR SERVICES\n\n\n24/7, real-time, direct technical assistance and advice\n\n\n\n\n\n\n\n\n\n\n\nNo matter what digital security challenges you face, we offer a range of services and resources to help you be safe online:\n\n\n\n\n\n\n\n\n\n\n\n\nRapid response for digital security incidents\n\n\n\n\n\n\n\n\nPersonalized recommendations, instruction, and follow-up support for digital security issues\n\n\n\n\n\n\n\n\nHelp assessing risks and creating organizational or community security strategies\n\n\n\n\n\n\n\n\nGuidance and educational materials on security practices and tools for organizations, communities, groups, and individuals\n\n\n\n\n\n\n\n\nSupport for securing technical infrastructure, websites, and social media against attacks\n\n\n\n\n\n\n\n\nReferrals, capacity-building, in-person consultations, and training\n\n\n\n\n\n\n\n\n\nDIGITAL SECURITY CLINIC\n\n\n\nAccess Now’s Digital Security Clinic brings the Helpline to you. Latin America and the Caribbean\nAlex Argüelles\nHolistic Security Lead\n\n\n\n\nLatin America and the Caribbean\nAlex Argüelles\nHolistic Security Lead\nHelpline\n\n\n\n\n\n\n\n\n\n\n\n\nEurope\nBeatrice Martini\nEducation and Communities Lead\n\n\n\n\nEurope\nBeatrice Martini\nEducation and Communities Lead\nHelpline\n\n\n\n\n\n\n\n\n\n\n\n\nAsia Pacific\nDhyta Caturani\nHelpline SEA Regional Coordinator\n\n\n\n\nAsia Pacific\nDhyta Caturani\nHelpline SEA Regional Coordinator\nHelpline\n\n\n\n\n\n\n\n\n\n\n\n\nAfrica\nDoreen Ochung\nSecurity Incident Handler\n\n\n\n\nAfrica\nDoreen Ochung\nSecurity Incident Handler\nHelpline\n\n\n\n\n\n\n\n\n\n\n\n\nInternational\nHassen Selmi\nIncident Response Lead\n\n\n\n\nInternational\nHassen Selmi\nIncident Response Lead\nHelpline\n\n\n\n\n\n\n\n\n\n\n\n\nLatin America and the Caribbean\nJean Carlo Lara\nSecurity Incident Handler\n\n\n\n\nLatin America and the Caribbean\nJean Carlo Lara\nSecurity Incident Handler\nHelpline\n\n\n\n\n\n\n\n\n\n\n\n\nEurope\nLuis Barrueto\nAdministrative and Communications Coordinator \n\n\n\n\nEurope\nLuis Barrueto\nAdministrative and Communications Coordinator \nHelpline\n\n\n\n\n\n\n\n\n\n\n\n\nInternational\nMag\nSecurity Incident Handler\n\n\n\n\nInternational\nMag\nSecurity Incident Handler\nHelpline\n\n\n\n\n\n\n\n\n\n\n\n\nInternational\nMaggie\nHelpline Documentation Coordinator\n\n\n\n\nInternational\nMaggie\nHelpline Documentation Coordinator\nHelpline\n\n\n\n\n\n\n\n\n\n\n\n\nInternational\nMalika Sharif\nSecurity Incident Handler\n\n\n\n\nInternational\nMalika Sharif\nSecurity Incident Handler\nHelpline\n\n\n\n\n\n\n\n\n\n\n\n\nAsia Pacific\nMarilou Maala\nIncident Response Analyst\n\n\n\n\nAsia Pacific\nMarilou Maala\nIncident Response Analyst\nHelpline\n\n\n\n\n\n\n\n\n\n\n\n\nAsia Pacific\nMarionne Sarmiento\nDigital Safety Specialist\n\n\n\n\nAsia Pacific\nMarionne Sarmiento\nDigital Safety Specialist\nHelpline\n\n\n\n\n\n\n\n\n\n\n\n\nInternational\nMaxim Petrov\nSafety Specialist\n\n\n\n\nInternational\nMaxim Petrov\nSafety Specialist\nHelpline\n\n\n\n\n\n\n\n\n\n\n\n\nInternational\nMohammed Al-Maskati\nDigital Security Helpline Director\n\n\n\n\nInternational\nMohammed Al-Maskati\nDigital Security Helpline Director\nHelpline\n\n\n\n\n\n\n\n\n\n\n\n\nInternational\nOleg Serov\nSecurity Incident Handler\n\n\n\n\nInternational\nOleg Serov\nSecurity Incident Handler\nHelpline\n\n\n\n\n\n\n\n\n\n\n\n\nLatin America and the Caribbean\nRocío\nSecurity Incident Handler\n\n\n\n\nLatin America and the Caribbean\nRocío\nSecurity Incident Handler\nHelpline\n\n\n\n\n\n\n\n\n\n\n\n\nLatin America and the Caribbean\nRogelio López\nSan José Security Shift Lead\n\n\n\n\nLatin America and the Caribbean\nRogelio López\nSan José Security Shift Lead\nHelpline\n\n\n\n\n\n\n\n\n\n\n\n\nAsia Pacific\nShinte Galeshka\nSecurity Incident Handler\n\n\n\n\nAsia Pacific\nShinte Galeshka\nSecurity Incident Handler\nHelpline\n\n\n\n\n\n\n\n\n\nEurope\nVeronica Zaboia\nPlatform Engagement Coordinator\n\n\n\n\nEurope\nVeronica Zaboia\nPlatform Engagement Coordinator\nHelpline\n\n\n\n\n\n\n\n\n\n\n\n\nInternational\nVictor Novikov\nDigital Security Helpline Manager\n\n\n\n\nInternational\nVictor Novikov\nDigital Security Helpline Manager\nHelpline\n\n\n\n\n\n\n\n\n\n\n\n\nInternational\nVlad\nSecurity Incident Handler\n\n\n\n\nInternational\nVlad\nSecurity Incident Handler\nHelpline\n\n\n\n\n\n\n\n\n\n\nCOMMUNITY & RESOURCES\n\n\n\n\n\n\n\n\n\n\n\n\n\n\n\n\n\n\n\nAccess Now’s Digital Security Helpline is a member of the Civil Society Computer Emergency Response Team (CiviCERT), an accredited CERT focused on improving the incident response capabilities of civil society groups and individuals around the world. As part of Access Now’s work and in collaboration with the broader community, we create and contribute to guides and materials to help communities, organizations, and individuals improve their digital security. Please find some guides below:\n\nDigital First Aid Kit\nA resource for emergency situations, such as when your social media account is compromised, your website is attacked, or your computer is infected \n\nHelpline PGP Email Encryption Guides (Windows | Mac | Linux)\nGuides for setting up encrypted email \n\nHelpline Safer Travel Guide\nHelping you prepare for travels to high-risk countries \n\nHelpline Self-Doxing Guide\nTips and resources for exploring open source intelligence on oneself to prevent online doxing \n\nHelpline Community Documentation\nThe procedures and documentation we create to aid our work on the Helpline \n\nPartner organizations have produced a number of guides and resources that we find valuable in our work, and you may too. They include: \n\nSecurity in a Box\nFrom Frontline Defenders and the Tactical Technology Collective \n\nSurveillance Self-Defense\nFrom the Electronic Frontier Foundation \n\nUmbrella\nFrom Security First\n\nDIGITAL SECURITY HELPLINE\n\n\n\n\n\nHow We Help\nWho Can We Help\nContact Us\nCommunity & Resources\n\n\n\nWHAT IS THE DIGITAL SECURITY HELPLINE? Available translations:\n\n Pусский Español Português العربية Français Deutsch Italiano Tagalog українська \n\n\n\n\nAccess Now’s Digital Security Helpline works with individuals and organizations around the world to keep them safe online. The Helpline will walk you or your organization through assessing the risks you face in your work, and  together we’ll prioritize your digital security needs. Case: Human rights defenders in Azerbaijan fend off malware attacks – Amnesty International\n\n\n\n\n\n\n\n\n\nOUR SERVICES\n\n\n24/7, real-time, direct technical assistance and advice\n\n\n\n\n\n\n\n\n\n\n\nNo matter what digital security challenges you face, we offer a range of services and resources to help you be safe online:\n\n\n\n\n\n\n\n\n\n\n\n\nRapid response for digital security incidents\n\n\n\n\n\n\n\n\nPersonalized recommendations, instruction, and follow-up support for digital security issues\n\n\n\n\n\n\n\n\nHelp assessing risks and creating organizational or community security strategies\n\n\n\n\n\n\n\n\nGuidance and educational materials on security practices and tools for organizations, communities, groups, and individuals\n\n\n\n\n\n\n\n\nSupport for securing technical infrastructure, websites, and social media against attacks\n\n\n\n\n\n\n\n\nReferrals, capacity-building, in-person consultations, and training\n\n\n\n\n\n\n\n\n\nDIGITAL SECURITY CLINIC\n\n\n\nAccess Now’s Digital Security Clinic brings the Helpline to you. Latin America and the Caribbean\nAlex Argüelles\nHolistic Security Lead\n\n\n\n\nLatin America and the Caribbean\nAlex Argüelles\nHolistic Security Lead\nHelpline\n\n\n\n\n\n\n\n\n\n\n\n\nEurope\nBeatrice Martini\nEducation and Communities Lead\n\n\n\n\nEurope\nBeatrice Martini\nEducation and Communities Lead\nHelpline\n\n\n\n\n\n\n\n\n\n\n\n\nAsia Pacific\nDhyta Caturani\nHelpline SEA Regional Coordinator\n\n\n\n\nAsia Pacific\nDhyta Caturani\nHelpline SEA Regional Coordinator\nHelpline\n\n\n\n\n\n\n\n\n\n\n\n\nAfrica\nDoreen Ochung\nSecurity Incident Handler\n\n\n\n\nAfrica\nDoreen Ochung\nSecurity Incident Handler\nHelpline\n\n\n\n\n\n\n\n\n\n\n\n\nInternational\nHassen Selmi\nIncident Response Lead\n\n\n\n\nInternational\nHassen Selmi\nIncident Response Lead\nHelpline\n\n\n\n\n\n\n\n\n\n\n\n\nLatin America and the Caribbean\nJean Carlo Lara\nSecurity Incident Handler\n\n\n\n\nLatin America and the Caribbean\nJean Carlo Lara\nSecurity Incident Handler\nHelpline\n\n\n\n\n\n\n\n\n\n\n\n\nEurope\nLuis Barrueto\nAdministrative and Communications Coordinator \n\n\n\n\nEurope\nLuis Barrueto\nAdministrative and Communications Coordinator \nHelpline\n\n\n\n\n\n\n\n\n\n\n\n\nInternational\nMag\nSecurity Incident Handler\n\n\n\n\nInternational\nMag\nSecurity Incident Handler\nHelpline\n\n\n\n\n\n\n\n\n\n\n\n\nInternational\nMaggie\nHelpline Documentation Coordinator\n\n\n\n\nInternational\nMaggie\nHelpline Documentation Coordinator\nHelpline\n\n\n\n\n\n\n\n\n\n\n\n\nInternational\nMalika Sharif\nSecurity Incident Handler\n\n\n\n\nInternational\nMalika Sharif\nSecurity Incident Handler\nHelpline\n\n\n\n\n\n\n\n\n\n\n\n\nAsia Pacific\nMarilou Maala\nIncident Response Analyst\n\n\n\n\nAsia Pacific\nMarilou Maala\nIncident Response Analyst\nHelpline\n\n\n\n\n\n\n\n\n\n\n\n\nAsia Pacific\nMarionne Sarmiento\nDigital Safety Specialist\n\n\n\n\nAsia Pacific\nMarionne Sarmiento\nDigital Safety Specialist\nHelpline\n\n\n\n\n\n\n\n\n\n\n\n\nInternational\nMaxim Petrov\nSafety Specialist\n\n\n\n\nInternational\nMaxim Petrov\nSafety Specialist\nHelpline\n\n\n\n\n\n\n\n\n\n\n\n\nInternational\nMohammed Al-Maskati\nDigital Security Helpline Director\n\n\n\n\nInternational\nMohammed Al-Maskati\nDigital Security Helpline Director\nHelpline\n\n\n\n\n\n\n\n\n\n\n\n\nInternational\nOleg Serov\nSecurity Incident Handler\n\n\n\n\nInternational\nOleg Serov\nSecurity Incident Handler\nHelpline\n\n\n\n\n\n\n\n\n\n\n\n\nLatin America and the Caribbean\nRocío\nSecurity Incident Handler\n\n\n\n\nLatin America and the Caribbean\nRocío\nSecurity Incident Handler\nHelpline\n\n\n\n\n\n\n\n\n\n\n\n\nLatin America and the Caribbean\nRogelio López\nSan José Security Shift Lead\n\n\n\n\nLatin America and the Caribbean\nRogelio López\nSan José Security Shift Lead\nHelpline\n\n\n\n\n\n\n\n\n\n\n\n\nAsia Pacific\nShinte Galeshka\nSecurity Incident Handler\n\n\n\n\nAsia Pacific\nShinte Galeshka\nSecurity Incident Handler\nHelpline\n\n\n\n\n\n\n\n\n\nEurope\nVeronica Zaboia\nPlatform Engagement Coordinator\n\n\n\n\nEurope\nVeronica Zaboia\nPlatform Engagement Coordinator\nHelpline\n\n\n\n\n\n\n\n\n\n\n\n\nInternational\nVictor Novikov\nDigital Security Helpline Manager\n\n\n\n\nInternational\nVictor Novikov\nDigital Security Helpline Manager\nHelpline\n\n\n\n\n\n\n\n\n\n\n\n\nInternational\nVlad\nSecurity Incident Handler\n\n\n\n\nInternational\nVlad\nSecurity Incident Handler\nHelpline\n\n\n\n\n\n\n\n\n\n\nCOMMUNITY & RESOURCES\n\n\n\n\n\n\n\n\n\n\n\n\n\n\n\n\n\n\n\nAccess Now’s Digital Security Helpline is a member of the Civil Society Computer Emergency Response Team (CiviCERT), an accredited CERT focused on improving the incident response capabilities of civil society groups and individuals around the world. As part of Access Now’s work and in collaboration with the broader community, we create and contribute to guides and materials to help communities, organizations, and individuals improve their digital security. Please find some guides below:\n\nDigital First Aid Kit\nA resource for emergency situations, such as when your social media account is compromised, your website is attacked, or your computer is infected \n\nHelpline PGP Email Encryption Guides (Windows | Mac | Linux)\nGuides for setting up encrypted email \n\nHelpline Safer Travel Guide\nHelping you prepare for travels to high-risk countries \n\nHelpline Self-Doxing Guide\nTips and resources for exploring open source intelligence on oneself to prevent online doxing \n\nHelpline Community Documentation\nThe procedures and documentation we create to aid our work on the Helpline \n\nPartner organizations have produced a number of guides and resources that we find valuable in our work, and you may too. They include: \n\nSecurity in a Box\nFrom Frontline Defenders and the Tactical Technology Collective \n\nSurveillance Self-Defense\nFrom the Electronic Frontier Foundation \n\nUmbrella\nFrom Security First\n\nDIGITAL SECURITY HELPLINE\n\n\n\n\n\nHow We Help\nWho Can We Help\nContact Us\nCommunity & Resources\n\n\n\nWHAT IS THE DIGITAL SECURITY HELPLINE? Available translations:\n\n Pусский Español Português العربية Français Deutsch Italiano Tagalog українська \n\n\n\n\nAccess Now’s Digital Security Helpline works with individuals and organizations around the world to keep them safe online. The Helpline will walk you or your organization through assessing the risks you face in your work, and  together we’ll prioritize your digital security needs. Case: Human rights defenders in Azerbaijan fend off malware attacks – Amnesty International\n\n\n\n\n\n\n\n\n\nOUR SERVICES\n\n\n24/7, real-time, direct technical assistance and advice\n\n\n\n\n\n\n\n\n\n\n\nNo matter what digital security challenges you face, we offer a range of services and resources to help you be safe online:\n\n\n\n\n\n\n\n\n\n\n\n\nRapid response for digital security incidents\n\n\n\n\n\n\n\n\nPersonalized recommendations, instruction, and follow-up support for digital security issues\n\n\n\n\n\n\n\n\nHelp assessing risks and creating organizational or community security strategies\n\n\n\n\n\n\n\n\nGuidance and educational materials on security practices and tools for organizations, communities, groups, and individuals\n\n\n\n\n\n\n\n\nSupport for securing technical infrastructure, websites, and social media against attacks\n\n\n\n\n\n\n\n\nReferrals, capacity-building, in-person consultations, and training\n\n\n\n\n\n\n\n\n\nDIGITAL SECURITY CLINIC\n\n\n\nAccess Now’s Digital Security Clinic brings the Helpline to you. Latin America and the Caribbean\nAlex Argüelles\nHolistic Security Lead\n\n\n\n\nLatin America and the Caribbean\nAlex Argüelles\nHolistic Security Lead\nHelpline\n\n\n\n\n\n\n\n\n\n\n\n\nEurope\nBeatrice Martini\nEducation and Communities Lead\n\n\n\n\nEurope\nBeatrice Martini\nEducation and Communities Lead\nHelpline\n\n\n\n\n\n\n\n\n\n\n\n\nAsia Pacific\nDhyta Caturani\nHelpline SEA Regional Coordinator\n\n\n\n\nAsia Pacific\nDhyta Caturani\nHelpline SEA Regional Coordinator\nHelpline\n\n\n\n\n\n\n\n\n\n\n\n\nAfrica\nDoreen Ochung\nSecurity Incident Handler\n\n\n\n\nAfrica\nDoreen Ochung\nSecurity Incident Handler\nHelpline\n\n\n\n\n\n\n\n\n\n\n\n\nInternational\nHassen Selmi\nIncident Response Lead\n\n\n\n\nInternational\nHassen Selmi\nIncident Response Lead\nHelpline\n\n\n\n\n\n\n\n\n\n\n\n\nLatin America and the Caribbean\nJean Carlo Lara\nSecurity Incident Handler\n\n\n\n\nLatin America and the Caribbean\nJean Carlo Lara\nSecurity Incident Handler\nHelpline\n\n\n\n\n\n\n\n\n\n\n\n\nEurope\nLuis Barrueto\nAdministrative and Communications Coordinator \n\n\n\n\nEurope\nLuis Barrueto\nAdministrative and Communications Coordinator \nHelpline\n\n\n\n\n\n\n\n\n\n\n\n\nInternational\nMag\nSecurity Incident Handler\n\n\n\n\nInternational\nMag\nSecurity Incident Handler\nHelpline\n\n\n\n\n\n\n\n\n\n\n\n\nInternational\nMaggie\nHelpline Documentation Coordinator\n\n\n\n\nInternational\nMaggie\nHelpline Documentation Coordinator\nHelpline\n\n\n\n\n\n\n\n\n\n\n\n\nInternational\nMalika Sharif\nSecurity Incident Handler\n\n\n\n\nInternational\nMalika Sharif\nSecurity Incident Handler\nHelpline\n\n\n\n\n\n\n\n\n\n\n\n\nAsia Pacific\nMarilou Maala\nIncident Response Analyst\n\n\n\n\nAsia Pacific\nMarilou Maala\nIncident Response Analyst\nHelpline\n\n\n\n\n\n\n\n\n\n\n\n\nAsia Pacific\nMarionne Sarmiento\nDigital Safety Specialist\n\n\n\n\nAsia Pacific\nMarionne Sarmiento\nDigital Safety Specialist\nHelpline\n\n\n\n\n\n\n\n\n\n\n\n\nInternational\nMaxim Petrov\nSafety Specialist\n\n\n\n\nInternational\nMaxim Petrov\nSafety Specialist\nHelpline\n\n\n\n\n\n\n\n\n\n\n\n\nInternational\nMohammed Al-Maskati\nDigital Security Helpline Director\n\n\n\n\nInternational\nMohammed Al-Maskati\nDigital Security Helpline Director\nHelpline\n\n\n\n\n\n\n\n\n\n\n\n\nInternational\nOleg Serov\nSecurity Incident Handler\n\n\n\n\nInternational\nOleg Serov\nSecurity Incident Handler\nHelpline\n\n\n\n\n\n\n\n\n\n\n\n\nLatin America and the Caribbean\nRocío\nSecurity Incident Handler\n\n\n\n\nLatin America and the Caribbean\nRocío\nSecurity Incident Handler\nHelpline\n\n\n\n\n\n\n\n\n\n\n\n\nLatin America and the Caribbean\nRogelio López\nSan José Security Shift Lead\n\n\n\n\nLatin America and the Caribbean\nRogelio López\nSan José Security Shift Lead\nHelpline\n\n\n\n\n\n\n\n\n\n\n\n\nAsia Pacific\nShinte Galeshka\nSecurity Incident Handler\n\n\n\n\nAsia Pacific\nShinte Galeshka\nSecurity Incident Handler\nHelpline\n\n\n\n\n\n\n\n\n\nEurope\nVeronica Zaboia\nPlatform Engagement Coordinator\n\n\n\n\nEurope\nVeronica Zaboia\nPlatform Engagement Coordinator\nHelpline\n\n\n\n\n\n\n\n\n\n\n\n\nInternational\nVictor Novikov\nDigital Security Helpline Manager\n\n\n\n\nInternational\nVictor Novikov\nDigital Security Helpline Manager\nHelpline\n\n\n\n\n\n\n\n\n\n\n\n\nInternational\nVlad\nSecurity Incident Handler\n\n\n\n\nInternational\nVlad\nSecurity Incident Handler\nHelpline\n\n\n\n\n\n\n\n\n\n\nCOMMUNITY & RESOURCES\n\n\n\n\n\n\n\n\n\n\n\n\n\n\n\n\n\n\n\nAccess Now’s Digital Security Helpline is a member of the Civil Society Computer Emergency Response Team (CiviCERT), an accredited CERT focused on improving the incident response capabilities of civil society groups and individuals around the world. As part of Access Now’s work and in collaboration with the broader community, we create and contribute to guides and materials to help communities, organizations, and individuals improve their digital security. Please find some guides below:\n\nDigital First Aid Kit\nA resource for emergency situations, such as when your social media account is compromised, your website is attacked, or your computer is infected \n\nHelpline PGP Email Encryption Guides (Windows | Mac | Linux)\nGuides for setting up encrypted email \n\nHelpline Safer Travel Guide\nHelping you prepare for travels to high-risk countries \n\nHelpline Self-Doxing Guide\nTips and resources for exploring open source intelligence on oneself to prevent online doxing \n\nHelpline Community Documentation\nThe procedures and documentation we create to aid our work on the Helpline \n\nPartner organizations have produced a number of guides and resources that we find valuable in our work, and you may too. They include: \n\nSecurity in a Box\nFrom Frontline Defenders and the Tactical Technology Collective \n\nSurveillance Self-Defense\nFrom the Electronic Frontier Foundation \n\nUmbrella\nFrom Security First\n\nDIGITAL SECURITY HELPLINE\n\n\n\n\n\nHow We Help\nWho Can We Help\nContact Us\nCommunity & Resources\n\n\n\nWHAT IS THE DIGITAL SECURITY HELPLINE? Available translations:\n\n Pусский Español Português العربية Français Deutsch Italiano Tagalog українська \n\n\n\n\nAccess Now’s Digital Security Helpline works with individuals and organizations around the world to keep them safe online. The Helpline will walk you or your organization through assessing the risks you face in your work, and  together we’ll prioritize your digital security needs. Case: Human rights defenders in Azerbaijan fend off malware attacks – Amnesty International\n\n\n\n\n\n\n\n\n\nOUR SERVICES\n\n\n24/7, real-time, direct technical assistance and advice\n\n\n\n\n\n\n\n\n\n\n\nNo matter what digital security challenges you face, we offer a range of services and resources to help you be safe online:\n\n\n\n\n\n\n\n\n\n\n\n\nRapid response for digital security incidents\n\n\n\n\n\n\n\n\nPersonalized recommendations, instruction, and follow-up support for digital security issues\n\n\n\n\n\n\n\n\nHelp assessing risks and creating organizational or community security strategies\n\n\n\n\n\n\n\n\nGuidance and educational materials on security practices and tools for organizations, communities, groups, and individuals\n\n\n\n\n\n\n\n\nSupport for securing technical infrastructure, websites, and social media against attacks\n\n\n\n\n\n\n\n\nReferrals, capacity-building, in-person consultations, and training\n\n\n\n\n\n\n\n\n\nDIGITAL SECURITY CLINIC\n\n\n\nAccess Now’s Digital Security Clinic brings the Helpline to you. Latin America and the Caribbean\nAlex Argüelles\nHolistic Security Lead\n\n\n\n\nLatin America and the Caribbean\nAlex Argüelles\nHolistic Security Lead\nHelpline\n\n\n\n\n\n\n\n\n\n\n\n\nEurope\nBeatrice Martini\nEducation and Communities Lead\n\n\n\n\nEurope\nBeatrice Martini\nEducation and Communities Lead\nHelpline\n\n\n\n\n\n\n\n\n\n\n\n\nAsia Pacific\nDhyta Caturani\nHelpline SEA Regional Coordinator\n\n\n\n\nAsia Pacific\nDhyta Caturani\nHelpline SEA Regional Coordinator\nHelpline\n\n\n\n\n\n\n\n\n\n\n\n\nAfrica\nDoreen Ochung\nSecurity Incident Handler\n\n\n\n\nAfrica\nDoreen Ochung\nSecurity Incident Handler\nHelpline\n\n\n\n\n\n\n\n\n\n\n\n\nInternational\nHassen Selmi\nIncident Response Lead\n\n\n\n\nInternational\nHassen Selmi\nIncident Response Lead\nHelpline\n\n\n\n\n\n\n\n\n\n\n\n\nLatin America and the Caribbean\nJean Carlo Lara\nSecurity Incident Handler\n\n\n\n\nLatin America and the Caribbean\nJean Carlo Lara\nSecurity Incident Handler\nHelpline\n\n\n\n\n\n\n\n\n\n\n\n\nEurope\nLuis Barrueto\nAdministrative and Communications Coordinator \n\n\n\n\nEurope\nLuis Barrueto\nAdministrative and Communications Coordinator \nHelpline\n\n\n\n\n\n\n\n\n\n\n\n\nInternational\nMag\nSecurity Incident Handler\n\n\n\n\nInternational\nMag\nSecurity Incident Handler\nHelpline\n\n\n\n\n\n\n\n\n\n\n\n\nInternational\nMaggie\nHelpline Documentation Coordinator\n\n\n\n\nInternational\nMaggie\nHelpline Documentation Coordinator\nHelpline\n\n\n\n\n\n\n\n\n\n\n\n\nInternational\nMalika Sharif\nSecurity Incident Handler\n\n\n\n\nInternational\nMalika Sharif\nSecurity Incident Handler\nHelpline\n\n\n\n\n\n\n\n\n\n\n\n\nAsia Pacific\nMarilou Maala\nIncident Response Analyst\n\n\n\n\nAsia Pacific\nMarilou Maala\nIncident Response Analyst\nHelpline\n\n\n\n\n\n\n\n\n\n\n\n\nAsia Pacific\nMarionne Sarmiento\nDigital Safety Specialist\n\n\n\n\nAsia Pacific\nMarionne Sarmiento\nDigital Safety Specialist\nHelpline\n\n\n\n\n\n\n\n\n\n\n\n\nInternational\nMaxim Petrov\nSafety Specialist\n\n\n\n\nInternational\nMaxim Petrov\nSafety Specialist\nHelpline\n\n\n\n\n\n\n\n\n\n\n\n\nInternational\nMohammed Al-Maskati\nDigital Security Helpline Director\n\n\n\n\nInternational\nMohammed Al-Maskati\nDigital Security Helpline Director\nHelpline\n\n\n\n\n\n\n\n\n\n\n\n\nInternational\nOleg Serov\nSecurity Incident Handler\n\n\n\n\nInternational\nOleg Serov\nSecurity Incident Handler\nHelpline\n\n\n\n\n\n\n\n\n\n\n\n\nLatin America and the Caribbean\nRocío\nSecurity Incident Handler\n\n\n\n\nLatin America and the Caribbean\nRocío\nSecurity Incident Handler\nHelpline\n\n\n\n\n\n\n\n\n\n\n\n\nLatin America and the Caribbean\nRogelio López\nSan José Security Shift Lead\n\n\n\n\nLatin America and the Caribbean\nRogelio López\nSan José Security Shift Lead\nHelpline\n\n\n\n\n\n\n\n\n\n\n\n\nAsia Pacific\nShinte Galeshka\nSecurity Incident Handler\n\n\n\n\nAsia Pacific\nShinte Galeshka\nSecurity Incident Handler\nHelpline\n\n\n\n\n\n\n\n\n\nEurope\nVeronica Zaboia\nPlatform Engagement Coordinator\n\n\n\n\nEurope\nVeronica Zaboia\nPlatform Engagement Coordinator\nHelpline\n\n\n\n\n\n\n\n\n\n\n\n\nInternational\nVictor Novikov\nDigital Security Helpline Manager\n\n\n\n\nInternational\nVictor Novikov\nDigital Security Helpline Manager\nHelpline\n\n\n\n\n\n\n\n\n\n\n\n\nInternational\nVlad\nSecurity Incident Handler\n\n\n\n\nInternational\nVlad\nSecurity Incident Handler\nHelpline\n\n\n\n\n\n\n\n\n\n\nCOMMUNITY & RESOURCES\n\n\n\n\n\n\n\n\n\n\n\n\n\n\n\n\n\n\n\nAccess Now’s Digital Security Helpline is a member of the Civil Society Computer Emergency Response Team (CiviCERT), an accredited CERT focused on improving the incident response capabilities of civil society groups and individuals around the world. As part of Access Now’s work and in collaboration with the broader community, we create and contribute to guides and materials to help communities, organizations, and individuals improve their digital security. Please find some guides below:\n\nDigital First Aid Kit\nA resource for emergency situations, such as when your social media account is compromised, your website is attacked, or your computer is infected \n\nHelpline PGP Email Encryption Guides (Windows | Mac | Linux)\nGuides for setting up encrypted email \n\nHelpline Safer Travel Guide\nHelping you prepare for travels to high-risk countries \n\nHelpline Self-Doxing Guide\nTips and resources for exploring open source intelligence on oneself to prevent online doxing \n\nHelpline Community Documentation\nThe procedures and documentation we create to aid our work on the Helpline \n\nPartner organizations have produced a number of guides and resources that we find valuable in our work, and you may too. They include: \n\nSecurity in a Box\nFrom Frontline Defenders and the Tactical Technology Collective \n\nSurveillance Self-Defense\nFrom the Electronic Frontier Foundation \n\nUmbrella\nFrom Security First\n\nDIGITAL SECURITY HELPLINE\n\n\n\n\n\nHow We Help\nWho Can We Help\nContact Us\nCommunity & Resources\n\n\n\nWHAT IS THE DIGITAL SECURITY HELPLINE? Available translations:\n\n Pусский Español Português العربية Français Deutsch Italiano Tagalog українська \n\n\n\n\nAccess Now’s Digital Security Helpline works with individuals and organizations around the world to keep them safe online. The Helpline will walk you or your organization through assessing the risks you face in your work, and  together we’ll prioritize your digital security needs. Case: Human rights defenders in Azerbaijan fend off malware attacks – Amnesty International\n\n\n\n\n\n\n\n\n\nOUR SERVICES\n\n\n24/7, real-time, direct technical assistance and advice\n\n\n\n\n\n\n\n\n\n\n\nNo matter what digital security challenges you face, we offer a range of services and resources to help you be safe online:\n\n\n\n\n\n\n\n\n\n\n\n\nRapid response for digital security incidents\n\n\n\n\n\n\n\n\nPersonalized recommendations, instruction, and follow-up support for digital security issues\n\n\n\n\n\n\n\n\nHelp assessing risks and creating organizational or community security strategies\n\n\n\n\n\n\n\n\nGuidance and educational materials on security practices and tools for organizations, communities, groups, and individuals\n\n\n\n\n\n\n\n\nSupport for securing technical infrastructure, websites, and social media against attacks\n\n\n\n\n\n\n\n\nReferrals, capacity-building, in-person consultations, and training\n\n\n\n\n\n\n\n\n\nDIGITAL SECURITY CLINIC\n\n\n\nAccess Now’s Digital Security Clinic brings the Helpline to you. Latin America and the Caribbean\nAlex Argüelles\nHolistic Security Lead\n\n\n\n\nLatin America and the Caribbean\nAlex Argüelles\nHolistic Security Lead\nHelpline\n\n\n\n\n\n\n\n\n\n\n\n\nEurope\nBeatrice Martini\nEducation and Communities Lead\n\n\n\n\nEurope\nBeatrice Martini\nEducation and Communities Lead\nHelpline\n\n\n\n\n\n\n\n\n\n\n\n\nAsia Pacific\nDhyta Caturani\nHelpline SEA Regional Coordinator\n\n\n\n\nAsia Pacific\nDhyta Caturani\nHelpline SEA Regional Coordinator\nHelpline\n\n\n\n\n\n\n\n\n\n\n\n\nAfrica\nDoreen Ochung\nSecurity Incident Handler\n\n\n\n\nAfrica\nDoreen Ochung\nSecurity Incident Handler\nHelpline\n\n\n\n\n\n\n\n\n\n\n\n\nInternational\nHassen Selmi\nIncident Response Lead\n\n\n\n\nInternational\nHassen Selmi\nIncident Response Lead\nHelpline\n\n\n\n\n\n\n\n\n\n\n\n\nLatin America and the Caribbean\nJean Carlo Lara\nSecurity Incident Handler\n\n\n\n\nLatin America and the Caribbean\nJean Carlo Lara\nSecurity Incident Handler\nHelpline\n\n\n\n\n\n\n\n\n\n\n\n\nEurope\nLuis Barrueto\nAdministrative and Communications Coordinator \n\n\n\n\nEurope\nLuis Barrueto\nAdministrative and Communications Coordinator \nHelpline\n\n\n\n\n\n\n\n\n\n\n\n\nInternational\nMag\nSecurity Incident Handler\n\n\n\n\nInternational\nMag\nSecurity Incident Handler\nHelpline\n\n\n\n\n\n\n\n\n\n\n\n\nInternational\nMaggie\nHelpline Documentation Coordinator\n\n\n\n\nInternational\nMaggie\nHelpline Documentation Coordinator\nHelpline\n\n\n\n\n\n\n\n\n\n\n\n\nInternational\nMalika Sharif\nSecurity Incident Handler\n\n\n\n\nInternational\nMalika Sharif\nSecurity Incident Handler\nHelpline\n\n\n\n\n\n\n\n\n\n\n\n\nAsia Pacific\nMarilou Maala\nIncident Response Analyst\n\n\n\n\nAsia Pacific\nMarilou Maala\nIncident Response Analyst\nHelpline\n\n\n\n\n\n\n\n\n\n\n\n\nAsia Pacific\nMarionne Sarmiento\nDigital Safety Specialist\n\n\n\n\nAsia Pacific\nMarionne Sarmiento\nDigital Safety Specialist\nHelpline\n\n\n\n\n\n\n\n\n\n\n\n\nInternational\nMaxim Petrov\nSafety Specialist\n\n\n\n\nInternational\nMaxim Petrov\nSafety Specialist\nHelpline\n\n\n\n\n\n\n\n\n\n\n\n\nInternational\nMohammed Al-Maskati\nDigital Security Helpline Director\n\n\n\n\nInternational\nMohammed Al-Maskati\nDigital Security Helpline Director\nHelpline\n\n\n\n\n\n\n\n\n\n\n\n\nInternational\nOleg Serov\nSecurity Incident Handler\n\n\n\n\nInternational\nOleg Serov\nSecurity Incident Handler\nHelpline\n\n\n\n\n\n\n\n\n\n\n\n\nLatin America and the Caribbean\nRocío\nSecurity Incident Handler\n\n\n\n\nLatin America and the Caribbean\nRocío\nSecurity Incident Handler\nHelpline\n\n\n\n\n\n\n\n\n\n\n\n\nLatin America and the Caribbean\nRogelio López\nSan José Security Shift Lead\n\n\n\n\nLatin America and the Caribbean\nRogelio López\nSan José Security Shift Lead\nHelpline\n\n\n\n\n\n\n\n\n\n\n\n\nAsia Pacific\nShinte Galeshka\nSecurity Incident Handler\n\n\n\n\nAsia Pacific\nShinte Galeshka\nSecurity Incident Handler\nHelpline\n\n\n\n\n\n\n\n\n\nEurope\nVeronica Zaboia\nPlatform Engagement Coordinator\n\n\n\n\nEurope\nVeronica Zaboia\nPlatform Engagement Coordinator\nHelpline\n\n\n\n\n\n\n\n\n\n\n\n\nInternational\nVictor Novikov\nDigital Security Helpline Manager\n\n\n\n\nInternational\nVictor Novikov\nDigital Security Helpline Manager\nHelpline\n\n\n\n\n\n\n\n\n\n\n\n\nInternational\nVlad\nSecurity Incident Handler\n\n\n\n\nInternational\nVlad\nSecurity Incident Handler\nHelpline\n\n\n\n\n\n\n\n\n\n\nCOMMUNITY & RESOURCES\n\n\n\n\n\n\n\n\n\n\n\n\n\n\n\n\n\n\n\nAccess Now’s Digital Security Helpline is a member of the Civil Society Computer Emergency Response Team (CiviCERT), an accredited CERT focused on improving the incident response capabilities of civil society groups and individuals around the world. As part of Access Now’s work and in collaboration with the broader community, we create and contribute to guides and materials to help communities, organizations, and individuals improve their digital security. Please find some guides below:\n\nDigital First Aid Kit\nA resource for emergency situations, such as when your social media account is compromised, your website is attacked, or your computer is infected \n\nHelpline PGP Email Encryption Guides (Windows | Mac | Linux)\nGuides for setting up encrypted email \n\nHelpline Safer Travel Guide\nHelping you prepare for travels to high-risk countries \n\nHelpline Self-Doxing Guide\nTips and resources for exploring open source intelligence on oneself to prevent online doxing \n\nHelpline Community Documentation\nThe procedures and documentation we create to aid our work on the Helpline \n\nPartner organizations have produced a number of guides and resources that we find valuable in our work, and you may too. They include: \n\nSecurity in a Box\nFrom Frontline Defenders and the Tactical Technology Collective \n\nSurveillance Self-Defense\nFrom the Electronic Frontier Foundation \n\nUmbrella\nFrom Security First\n\nDIGITAL SECURITY HELPLINE\n\nDIGITAL SECURITY HELPLINE\n\nDIGITAL SECURITY HELPLINE\n\nDIGITAL SECURITY HELPLINE\n\nHow We Help\nWho Can We Help\nContact Us\nCommunity & Resources\n\nHow We Help\n\nWho Can We Help\n\nContact Us\n\nCommunity & Resources\n\nWHAT IS THE DIGITAL SECURITY HELPLINE? Available translations:\n\n Pусский Español Português العربية Français Deutsch Italiano Tagalog українська \n\n\n\n\nAccess Now’s Digital Security Helpline works with individuals and organizations around the world to keep them safe online. Available translations:\n\n Pусский Español Português العربية Français Deutsch Italiano Tagalog українська \n\n\n\n\nAccess Now’s Digital Security Helpline works with individuals and organizations around the world to keep them safe online. Available translations:\n\n Pусский Español Português العربية Français Deutsch Italiano Tagalog українська\n\nAvailable translations:\n\n Pусский Español Português العربية Français Deutsch Italiano Tagalog українська\n\nPусский Español Português العربية Français Deutsch Italiano Tagalog українська\n\nPусский\n\nEspañol\n\nPortuguês\n\nالعربية\n\nFrançais\n\nDeutsch\n\nItaliano\n\nTagalog\n\nукраїнська\n\nAccess Now’s Digital Security Helpline works with individuals and organizations around the world to keep them safe online. Access Now’s Digital Security Helpline works with individuals and organizations around the world to keep them safe online. Access Now’s Digital Security Helpline works with individuals and organizations around the world to keep them safe online. The Helpline will walk you or your organization through assessing the risks you face in your work, and  together we’ll prioritize your digital security needs. The Helpline will walk you or your organization through assessing the risks you face in your work, and  together we’ll prioritize your digital security needs. The Helpline will walk you or your organization through assessing the risks you face in your work, and  together we’ll prioritize your digital security needs. Case: Human rights defenders in Azerbaijan fend off malware attacks – Amnesty International\n\n\n\n\n\n\n\n\n\nOUR SERVICES\n\n\n24/7, real-time, direct technical assistance and advice\n\n\n\n\n\n\n\n\n\n\n\nNo matter what digital security challenges you face, we offer a range of services and resources to help you be safe online:\n\nWHO CAN WE HELP? Case: Human rights defenders in Azerbaijan fend off malware attacks – Amnesty International\n\n\n\n\n\n\n\n\n\nOUR SERVICES\n\n\n24/7, real-time, direct technical assistance and advice\n\n\n\n\n\n\n\n\n\n\n\nNo matter what digital security challenges you face, we offer a range of services and resources to help you be safe online:\n\nBefore we can provide any support, we will conduct an initial process to verify that supporting you is within our mandate. Case: Human rights defenders in Azerbaijan fend off malware attacks – Amnesty International\n\nCase: Human rights defenders in Azerbaijan fend off malware attacks – Amnesty International\n\nCase: Human rights defenders in Azerbaijan fend off malware attacks – Amnesty International\n\nCase: Human rights defenders in Azerbaijan fend off malware attacks – Amnesty International\n\nOUR SERVICES\n\n\n24/7, real-time, direct technical assistance and advice\n\nOUR SERVICES\n\nOUR SERVICES\n\n24/7, real-time, direct technical assistance and advice\n\n24/7, real-time, direct technical assistance and advice\n\nNo matter what digital security challenges you face, we offer a range of services and resources to help you be safe online:\n\nNo matter what digital security challenges you face, we offer a range of services and resources to help you be safe online:\n\nNo matter what digital security challenges you face, we offer a range of services and resources to help you be safe online:\n\nRapid response for digital security incidents\n\n\n\n\n\n\n\n\nPersonalized recommendations, instruction, and follow-up support for digital security issues\n\n\n\n\n\n\n\n\nHelp assessing risks and creating organizational or community security strategies\n\n\n\n\n\n\n\n\nGuidance and educational materials on security practices and tools for organizations, communities, groups, and individuals\n\n\n\n\n\n\n\n\nSupport for securing technical infrastructure, websites, and social media against attacks\n\n\n\n\n\n\n\n\nReferrals, capacity-building, in-person consultations, and training\n\n\n\n\n\n\n\n\n\nDIGITAL SECURITY CLINIC\n\n\n\nAccess Now’s Digital Security Clinic brings the Helpline to you. Rapid response for digital security incidents\n\n\n\n\n\n\n\n\nPersonalized recommendations, instruction, and follow-up support for digital security issues\n\n\n\n\n\n\n\n\nHelp assessing risks and creating organizational or community security strategies\n\n\n\n\n\n\n\n\nGuidance and educational materials on security practices and tools for organizations, communities, groups, and individuals\n\n\n\n\n\n\n\n\nSupport for securing technical infrastructure, websites, and social media against attacks\n\n\n\n\n\n\n\n\nReferrals, capacity-building, in-person consultations, and training\n\n\n\n\n\n\n\n\n\nDIGITAL SECURITY CLINIC\n\n\n\nAccess Now’s Digital Security Clinic brings the Helpline to you. Rapid response for digital security incidents\n\nRapid response for digital security incidents\n\nRapid response for digital security incidents\n\nPersonalized recommendations, instruction, and follow-up support for digital security issues\n\nPersonalized recommendations, instruction, and follow-up support for digital security issues\n\nPersonalized recommendations, instruction, and follow-up support for digital security issues\n\nHelp assessing risks and creating organizational or community security strategies\n\nHelp assessing risks and creating organizational or community security strategies\n\nHelp assessing risks and creating organizational or community security strategies\n\nGuidance and educational materials on security practices and tools for organizations, communities, groups, and individuals\n\nGuidance and educational materials on security practices and tools for organizations, communities, groups, and individuals\n\nGuidance and educational materials on security practices and tools for organizations, communities, groups, and individuals\n\nSupport for securing technical infrastructure, websites, and social media against attacks\n\nSupport for securing technical infrastructure, websites, and social media against attacks\n\nSupport for securing technical infrastructure, websites, and social media against attacks\n\nReferrals, capacity-building, in-person consultations, and training\n\nReferrals, capacity-building, in-person consultations, and training\n\nReferrals, capacity-building, in-person consultations, and training\n\nDIGITAL SECURITY CLINIC\n\n\n\nAccess Now’s Digital Security Clinic brings the Helpline to you. DIGITAL SECURITY CLINIC\n\nDIGITAL SECURITY CLINIC\n\nDIGITAL SECURITY CLINIC\n\nAccess Now’s Digital Security Clinic brings the Helpline to you. Latin America and the Caribbean\nAlex Argüelles\nHolistic Security Lead\n\n\n\n\nLatin America and the Caribbean\nAlex Argüelles\nHolistic Security Lead\nHelpline\n\n\n\n\n\n\n\n\n\n\n\n\nEurope\nBeatrice Martini\nEducation and Communities Lead\n\n\n\n\nEurope\nBeatrice Martini\nEducation and Communities Lead\nHelpline\n\n\n\n\n\n\n\n\n\n\n\n\nAsia Pacific\nDhyta Caturani\nHelpline SEA Regional Coordinator\n\n\n\n\nAsia Pacific\nDhyta Caturani\nHelpline SEA Regional Coordinator\nHelpline\n\n\n\n\n\n\n\n\n\n\n\n\nAfrica\nDoreen Ochung\nSecurity Incident Handler\n\n\n\n\nAfrica\nDoreen Ochung\nSecurity Incident Handler\nHelpline\n\n\n\n\n\n\n\n\n\n\n\n\nInternational\nHassen Selmi\nIncident Response Lead\n\n\n\n\nInternational\nHassen Selmi\nIncident Response Lead\nHelpline\n\n\n\n\n\n\n\n\n\n\n\n\nLatin America and the Caribbean\nJean Carlo Lara\nSecurity Incident Handler\n\n\n\n\nLatin America and the Caribbean\nJean Carlo Lara\nSecurity Incident Handler\nHelpline\n\n\n\n\n\n\n\n\n\n\n\n\nEurope\nLuis Barrueto\nAdministrative and Communications Coordinator \n\n\n\n\nEurope\nLuis Barrueto\nAdministrative and Communications Coordinator \nHelpline\n\n\n\n\n\n\n\n\n\n\n\n\nInternational\nMag\nSecurity Incident Handler\n\n\n\n\nInternational\nMag\nSecurity Incident Handler\nHelpline\n\n\n\n\n\n\n\n\n\n\n\n\nInternational\nMaggie\nHelpline Documentation Coordinator\n\n\n\n\nInternational\nMaggie\nHelpline Documentation Coordinator\nHelpline\n\n\n\n\n\n\n\n\n\n\n\n\nInternational\nMalika Sharif\nSecurity Incident Handler\n\n\n\n\nInternational\nMalika Sharif\nSecurity Incident Handler\nHelpline\n\n\n\n\n\n\n\n\n\n\n\n\nAsia Pacific\nMarilou Maala\nIncident Response Analyst\n\n\n\n\nAsia Pacific\nMarilou Maala\nIncident Response Analyst\nHelpline\n\n\n\n\n\n\n\n\n\n\n\n\nAsia Pacific\nMarionne Sarmiento\nDigital Safety Specialist\n\n\n\n\nAsia Pacific\nMarionne Sarmiento\nDigital Safety Specialist\nHelpline\n\n\n\n\n\n\n\n\n\n\n\n\nInternational\nMaxim Petrov\nSafety Specialist\n\n\n\n\nInternational\nMaxim Petrov\nSafety Specialist\nHelpline\n\n\n\n\n\n\n\n\n\n\n\n\nInternational\nMohammed Al-Maskati\nDigital Security Helpline Director\n\n\n\n\nInternational\nMohammed Al-Maskati\nDigital Security Helpline Director\nHelpline\n\n\n\n\n\n\n\n\n\n\n\n\nInternational\nOleg Serov\nSecurity Incident Handler\n\n\n\n\nInternational\nOleg Serov\nSecurity Incident Handler\nHelpline\n\n\n\n\n\n\n\n\n\n\n\n\nLatin America and the Caribbean\nRocío\nSecurity Incident Handler\n\n\n\n\nLatin America and the Caribbean\nRocío\nSecurity Incident Handler\nHelpline\n\n\n\n\n\n\n\n\n\n\n\n\nLatin America and the Caribbean\nRogelio López\nSan José Security Shift Lead\n\n\n\n\nLatin America and the Caribbean\nRogelio López\nSan José Security Shift Lead\nHelpline\n\n\n\n\n\n\n\n\n\n\n\n\nAsia Pacific\nShinte Galeshka\nSecurity Incident Handler\n\n\n\n\nAsia Pacific\nShinte Galeshka\nSecurity Incident Handler\nHelpline\n\n\n\n\n\n\n\n\n\nEurope\nVeronica Zaboia\nPlatform Engagement Coordinator\n\n\n\n\nEurope\nVeronica Zaboia\nPlatform Engagement Coordinator\nHelpline\n\n\n\n\n\n\n\n\n\n\n\n\nInternational\nVictor Novikov\nDigital Security Helpline Manager\n\n\n\n\nInternational\nVictor Novikov\nDigital Security Helpline Manager\nHelpline\n\n\n\n\n\n\n\n\n\n\n\n\nInternational\nVlad\nSecurity Incident Handler\n\n\n\n\nInternational\nVlad\nSecurity Incident Handler\nHelpline\n\nLatin America and the Caribbean\nAlex Argüelles\nHolistic Security Lead\n\n\n\n\nLatin America and the Caribbean\nAlex Argüelles\nHolistic Security Lead\nHelpline\n\n\n\n\n\n\n\n\n\n\n\n\nEurope\nBeatrice Martini\nEducation and Communities Lead\n\n\n\n\nEurope\nBeatrice Martini\nEducation and Communities Lead\nHelpline\n\n\n\n\n\n\n\n\n\n\n\n\nAsia Pacific\nDhyta Caturani\nHelpline SEA Regional Coordinator\n\n\n\n\nAsia Pacific\nDhyta Caturani\nHelpline SEA Regional Coordinator\nHelpline\n\n\n\n\n\n\n\n\n\n\n\n\nAfrica\nDoreen Ochung\nSecurity Incident Handler\n\n\n\n\nAfrica\nDoreen Ochung\nSecurity Incident Handler\nHelpline\n\n\n\n\n\n\n\n\n\n\n\n\nInternational\nHassen Selmi\nIncident Response Lead\n\n\n\n\nInternational\nHassen Selmi\nIncident Response Lead\nHelpline\n\n\n\n\n\n\n\n\n\n\n\n\nLatin America and the Caribbean\nJean Carlo Lara\nSecurity Incident Handler\n\n\n\n\nLatin America and the Caribbean\nJean Carlo Lara\nSecurity Incident Handler\nHelpline\n\n\n\n\n\n\n\n\n\n\n\n\nEurope\nLuis Barrueto\nAdministrative and Communications Coordinator \n\n\n\n\nEurope\nLuis Barrueto\nAdministrative and Communications Coordinator \nHelpline\n\n\n\n\n\n\n\n\n\n\n\n\nInternational\nMag\nSecurity Incident Handler\n\n\n\n\nInternational\nMag\nSecurity Incident Handler\nHelpline\n\n\n\n\n\n\n\n\n\n\n\n\nInternational\nMaggie\nHelpline Documentation Coordinator\n\n\n\n\nInternational\nMaggie\nHelpline Documentation Coordinator\nHelpline\n\n\n\n\n\n\n\n\n\n\n\n\nInternational\nMalika Sharif\nSecurity Incident Handler\n\n\n\n\nInternational\nMalika Sharif\nSecurity Incident Handler\nHelpline\n\n\n\n\n\n\n\n\n\n\n\n\nAsia Pacific\nMarilou Maala\nIncident Response Analyst\n\n\n\n\nAsia Pacific\nMarilou Maala\nIncident Response Analyst\nHelpline\n\n\n\n\n\n\n\n\n\n\n\n\nAsia Pacific\nMarionne Sarmiento\nDigital Safety Specialist\n\n\n\n\nAsia Pacific\nMarionne Sarmiento\nDigital Safety Specialist\nHelpline\n\n\n\n\n\n\n\n\n\n\n\n\nInternational\nMaxim Petrov\nSafety Specialist\n\n\n\n\nInternational\nMaxim Petrov\nSafety Specialist\nHelpline\n\n\n\n\n\n\n\n\n\n\n\n\nInternational\nMohammed Al-Maskati\nDigital Security Helpline Director\n\n\n\n\nInternational\nMohammed Al-Maskati\nDigital Security Helpline Director\nHelpline\n\n\n\n\n\n\n\n\n\n\n\n\nInternational\nOleg Serov\nSecurity Incident Handler\n\n\n\n\nInternational\nOleg Serov\nSecurity Incident Handler\nHelpline\n\n\n\n\n\n\n\n\n\n\n\n\nLatin America and the Caribbean\nRocío\nSecurity Incident Handler\n\n\n\n\nLatin America and the Caribbean\nRocío\nSecurity Incident Handler\nHelpline\n\n\n\n\n\n\n\n\n\n\n\n\nLatin America and the Caribbean\nRogelio López\nSan José Security Shift Lead\n\n\n\n\nLatin America and the Caribbean\nRogelio López\nSan José Security Shift Lead\nHelpline\n\n\n\n\n\n\n\n\n\n\n\n\nAsia Pacific\nShinte Galeshka\nSecurity Incident Handler\n\n\n\n\nAsia Pacific\nShinte Galeshka\nSecurity Incident Handler\nHelpline\n\n\n\n\n\n\n\n\n\nEurope\nVeronica Zaboia\nPlatform Engagement Coordinator\n\n\n\n\nEurope\nVeronica Zaboia\nPlatform Engagement Coordinator\nHelpline\n\n\n\n\n\n\n\n\n\n\n\n\nInternational\nVictor Novikov\nDigital Security Helpline Manager\n\n\n\n\nInternational\nVictor Novikov\nDigital Security Helpline Manager\nHelpline\n\n\n\n\n\n\n\n\n\n\n\n\nInternational\nVlad\nSecurity Incident Handler\n\n\n\n\nInternational\nVlad\nSecurity Incident Handler\nHelpline\n\nLatin America and the Caribbean\nAlex Argüelles\nHolistic Security Lead\n\n\n\n\nLatin America and the Caribbean\nAlex Argüelles\nHolistic Security Lead\nHelpline\n\n\n\n\n\n\n\n\n\n\n\n\nEurope\nBeatrice Martini\nEducation and Communities Lead\n\n\n\n\nEurope\nBeatrice Martini\nEducation and Communities Lead\nHelpline\n\n\n\n\n\n\n\n\n\n\n\n\nAsia Pacific\nDhyta Caturani\nHelpline SEA Regional Coordinator\n\n\n\n\nAsia Pacific\nDhyta Caturani\nHelpline SEA Regional Coordinator\nHelpline\n\n\n\n\n\n\n\n\n\n\n\n\nAfrica\nDoreen Ochung\nSecurity Incident Handler\n\n\n\n\nAfrica\nDoreen Ochung\nSecurity Incident Handler\nHelpline\n\n\n\n\n\n\n\n\n\n\n\n\nInternational\nHassen Selmi\nIncident Response Lead\n\n\n\n\nInternational\nHassen Selmi\nIncident Response Lead\nHelpline\n\n\n\n\n\n\n\n\n\n\n\n\nLatin America and the Caribbean\nJean Carlo Lara\nSecurity Incident Handler\n\n\n\n\nLatin America and the Caribbean\nJean Carlo Lara\nSecurity Incident Handler\nHelpline\n\n\n\n\n\n\n\n\n\n\n\n\nEurope\nLuis Barrueto\nAdministrative and Communications Coordinator \n\n\n\n\nEurope\nLuis Barrueto\nAdministrative and Communications Coordinator \nHelpline\n\n\n\n\n\n\n\n\n\n\n\n\nInternational\nMag\nSecurity Incident Handler\n\n\n\n\nInternational\nMag\nSecurity Incident Handler\nHelpline\n\n\n\n\n\n\n\n\n\n\n\n\nInternational\nMaggie\nHelpline Documentation Coordinator\n\n\n\n\nInternational\nMaggie\nHelpline Documentation Coordinator\nHelpline\n\n\n\n\n\n\n\n\n\n\n\n\nInternational\nMalika Sharif\nSecurity Incident Handler\n\n\n\n\nInternational\nMalika Sharif\nSecurity Incident Handler\nHelpline\n\n\n\n\n\n\n\n\n\n\n\n\nAsia Pacific\nMarilou Maala\nIncident Response Analyst\n\n\n\n\nAsia Pacific\nMarilou Maala\nIncident Response Analyst\nHelpline\n\n\n\n\n\n\n\n\n\n\n\n\nAsia Pacific\nMarionne Sarmiento\nDigital Safety Specialist\n\n\n\n\nAsia Pacific\nMarionne Sarmiento\nDigital Safety Specialist\nHelpline\n\n\n\n\n\n\n\n\n\n\n\n\nInternational\nMaxim Petrov\nSafety Specialist\n\n\n\n\nInternational\nMaxim Petrov\nSafety Specialist\nHelpline\n\n\n\n\n\n\n\n\n\n\n\n\nInternational\nMohammed Al-Maskati\nDigital Security Helpline Director\n\n\n\n\nInternational\nMohammed Al-Maskati\nDigital Security Helpline Director\nHelpline\n\n\n\n\n\n\n\n\n\n\n\n\nInternational\nOleg Serov\nSecurity Incident Handler\n\n\n\n\nInternational\nOleg Serov\nSecurity Incident Handler\nHelpline\n\n\n\n\n\n\n\n\n\n\n\n\nLatin America and the Caribbean\nRocío\nSecurity Incident Handler\n\n\n\n\nLatin America and the Caribbean\nRocío\nSecurity Incident Handler\nHelpline\n\n\n\n\n\n\n\n\n\n\n\n\nLatin America and the Caribbean\nRogelio López\nSan José Security Shift Lead\n\n\n\n\nLatin America and the Caribbean\nRogelio López\nSan José Security Shift Lead\nHelpline\n\n\n\n\n\n\n\n\n\n\n\n\nAsia Pacific\nShinte Galeshka\nSecurity Incident Handler\n\n\n\n\nAsia Pacific\nShinte Galeshka\nSecurity Incident Handler\nHelpline\n\n\n\n\n\n\n\n\n\nEurope\nVeronica Zaboia\nPlatform Engagement Coordinator\n\n\n\n\nEurope\nVeronica Zaboia\nPlatform Engagement Coordinator\nHelpline\n\n\n\n\n\n\n\n\n\n\n\n\nInternational\nVictor Novikov\nDigital Security Helpline Manager\n\n\n\n\nInternational\nVictor Novikov\nDigital Security Helpline Manager\nHelpline\n\n\n\n\n\n\n\n\n\n\n\n\nInternational\nVlad\nSecurity Incident Handler\n\n\n\n\nInternational\nVlad\nSecurity Incident Handler\nHelpline\n\nLatin America and the Caribbean\nAlex Argüelles\nHolistic Security Lead\n\n\n\n\nLatin America and the Caribbean\nAlex Argüelles\nHolistic Security Lead\nHelpline\n\n\n\n\n\n\n\n\n\n\n\n\nEurope\nBeatrice Martini\nEducation and Communities Lead\n\n\n\n\nEurope\nBeatrice Martini\nEducation and Communities Lead\nHelpline\n\n\n\n\n\n\n\n\n\n\n\n\nAsia Pacific\nDhyta Caturani\nHelpline SEA Regional Coordinator\n\n\n\n\nAsia Pacific\nDhyta Caturani\nHelpline SEA Regional Coordinator\nHelpline\n\n\n\n\n\n\n\n\n\n\n\n\nAfrica\nDoreen Ochung\nSecurity Incident Handler\n\n\n\n\nAfrica\nDoreen Ochung\nSecurity Incident Handler\nHelpline\n\n\n\n\n\n\n\n\n\n\n\n\nInternational\nHassen Selmi\nIncident Response Lead\n\n\n\n\nInternational\nHassen Selmi\nIncident Response Lead\nHelpline\n\n\n\n\n\n\n\n\n\n\n\n\nLatin America and the Caribbean\nJean Carlo Lara\nSecurity Incident Handler\n\n\n\n\nLatin America and the Caribbean\nJean Carlo Lara\nSecurity Incident Handler\nHelpline\n\n\n\n\n\n\n\n\n\n\n\n\nEurope\nLuis Barrueto\nAdministrative and Communications Coordinator \n\n\n\n\nEurope\nLuis Barrueto\nAdministrative and Communications Coordinator \nHelpline\n\n\n\n\n\n\n\n\n\n\n\n\nInternational\nMag\nSecurity Incident Handler\n\n\n\n\nInternational\nMag\nSecurity Incident Handler\nHelpline\n\n\n\n\n\n\n\n\n\n\n\n\nInternational\nMaggie\nHelpline Documentation Coordinator\n\n\n\n\nInternational\nMaggie\nHelpline Documentation Coordinator\nHelpline\n\n\n\n\n\n\n\n\n\n\n\n\nInternational\nMalika Sharif\nSecurity Incident Handler\n\n\n\n\nInternational\nMalika Sharif\nSecurity Incident Handler\nHelpline\n\n\n\n\n\n\n\n\n\n\n\n\nAsia Pacific\nMarilou Maala\nIncident Response Analyst\n\n\n\n\nAsia Pacific\nMarilou Maala\nIncident Response Analyst\nHelpline\n\n\n\n\n\n\n\n\n\n\n\n\nAsia Pacific\nMarionne Sarmiento\nDigital Safety Specialist\n\n\n\n\nAsia Pacific\nMarionne Sarmiento\nDigital Safety Specialist\nHelpline\n\n\n\n\n\n\n\n\n\n\n\n\nInternational\nMaxim Petrov\nSafety Specialist\n\n\n\n\nInternational\nMaxim Petrov\nSafety Specialist\nHelpline\n\n\n\n\n\n\n\n\n\n\n\n\nInternational\nMohammed Al-Maskati\nDigital Security Helpline Director\n\n\n\n\nInternational\nMohammed Al-Maskati\nDigital Security Helpline Director\nHelpline\n\n\n\n\n\n\n\n\n\n\n\n\nInternational\nOleg Serov\nSecurity Incident Handler\n\n\n\n\nInternational\nOleg Serov\nSecurity Incident Handler\nHelpline\n\n\n\n\n\n\n\n\n\n\n\n\nLatin America and the Caribbean\nRocío\nSecurity Incident Handler\n\n\n\n\nLatin America and the Caribbean\nRocío\nSecurity Incident Handler\nHelpline\n\n\n\n\n\n\n\n\n\n\n\n\nLatin America and the Caribbean\nRogelio López\nSan José Security Shift Lead\n\n\n\n\nLatin America and the Caribbean\nRogelio López\nSan José Security Shift Lead\nHelpline\n\n\n\n\n\n\n\n\n\n\n\n\nAsia Pacific\nShinte Galeshka\nSecurity Incident Handler\n\n\n\n\nAsia Pacific\nShinte Galeshka\nSecurity Incident Handler\nHelpline\n\n\n\n\n\n\n\n\n\nEurope\nVeronica Zaboia\nPlatform Engagement Coordinator\n\n\n\n\nEurope\nVeronica Zaboia\nPlatform Engagement Coordinator\nHelpline\n\n\n\n\n\n\n\n\n\n\n\n\nInternational\nVictor Novikov\nDigital Security Helpline Manager\n\n\n\n\nInternational\nVictor Novikov\nDigital Security Helpline Manager\nHelpline\n\n\n\n\n\n\n\n\n\n\n\n\nInternational\nVlad\nSecurity Incident Handler\n\n\n\n\nInternational\nVlad\nSecurity Incident Handler\nHelpline\n\nLatin America and the Caribbean\nAlex Argüelles\nHolistic Security Lead\n\n\n\n\nLatin America and the Caribbean\nAlex Argüelles\nHolistic Security Lead\nHelpline\n\nLatin America and the Caribbean\nAlex Argüelles\nHolistic Security Lead\n\nHolistic Security Lead\n\nLatin America and the Caribbean\nAlex Argüelles\nHolistic Security Lead\nHelpline\n\nHolistic Security Lead\n\nHelpline\n\nEurope\nBeatrice Martini\nEducation and Communities Lead\n\n\n\n\nEurope\nBeatrice Martini\nEducation and Communities Lead\nHelpline\n\nEurope\nBeatrice Martini\nEducation and Communities Lead\n\nEducation and Communities Lead\n\nEurope\nBeatrice Martini\nEducation and Communities Lead\nHelpline\n\nEducation and Communities Lead\n\nHelpline\n\nAsia Pacific\nDhyta Caturani\nHelpline SEA Regional Coordinator\n\n\n\n\nAsia Pacific\nDhyta Caturani\nHelpline SEA Regional Coordinator\nHelpline\n\nAsia Pacific\nDhyta Caturani\nHelpline SEA Regional Coordinator\n\nHelpline SEA Regional Coordinator\n\nAsia Pacific\nDhyta Caturani\nHelpline SEA Regional Coordinator\nHelpline\n\nHelpline SEA Regional Coordinator\n\nHelpline\n\nAfrica\nDoreen Ochung\nSecurity Incident Handler\n\n\n\n\nAfrica\nDoreen Ochung\nSecurity Incident Handler\nHelpline\n\nAfrica\nDoreen Ochung\nSecurity Incident Handler\n\nSecurity Incident Handler\n\nAfrica\nDoreen Ochung\nSecurity Incident Handler\nHelpline\n\nSecurity Incident Handler\n\nHelpline\n\nInternational\nHassen Selmi\nIncident Response Lead\n\n\n\n\nInternational\nHassen Selmi\nIncident Response Lead\nHelpline\n\nInternational\nHassen Selmi\nIncident Response Lead\n\nIncident Response Lead\n\nInternational\nHassen Selmi\nIncident Response Lead\nHelpline\n\nIncident Response Lead\n\nHelpline\n\nLatin America and the Caribbean\nJean Carlo Lara\nSecurity Incident Handler\n\n\n\n\nLatin America and the Caribbean\nJean Carlo Lara\nSecurity Incident Handler\nHelpline\n\nLatin America and the Caribbean\nJean Carlo Lara\nSecurity Incident Handler\n\nSecurity Incident Handler\n\nLatin America and the Caribbean\nJean Carlo Lara\nSecurity Incident Handler\nHelpline\n\nSecurity Incident Handler\n\nHelpline\n\nEurope\nLuis Barrueto\nAdministrative and Communications Coordinator \n\n\n\n\nEurope\nLuis Barrueto\nAdministrative and Communications Coordinator \nHelpline\n\nEurope\nLuis Barrueto\nAdministrative and Communications Coordinator\n\nAdministrative and Communications Coordinator\n\nEurope\nLuis Barrueto\nAdministrative and Communications Coordinator \nHelpline\n\nAdministrative and Communications Coordinator\n\nHelpline\n\nInternational\nMag\nSecurity Incident Handler\n\n\n\n\nInternational\nMag\nSecurity Incident Handler\nHelpline\n\nInternational\nMag\nSecurity Incident Handler\n\nSecurity Incident Handler\n\nInternational\nMag\nSecurity Incident Handler\nHelpline\n\nSecurity Incident Handler\n\nHelpline\n\nInternational\nMaggie\nHelpline Documentation Coordinator\n\n\n\n\nInternational\nMaggie\nHelpline Documentation Coordinator\nHelpline\n\nInternational\nMaggie\nHelpline Documentation Coordinator\n\nHelpline Documentation Coordinator\n\nInternational\nMaggie\nHelpline Documentation Coordinator\nHelpline\n\nHelpline Documentation Coordinator\n\nHelpline\n\nInternational\nMalika Sharif\nSecurity Incident Handler\n\n\n\n\nInternational\nMalika Sharif\nSecurity Incident Handler\nHelpline\n\nInternational\nMalika Sharif\nSecurity Incident Handler\n\nSecurity Incident Handler\n\nInternational\nMalika Sharif\nSecurity Incident Handler\nHelpline\n\nSecurity Incident Handler\n\nHelpline\n\nAsia Pacific\nMarilou Maala\nIncident Response Analyst\n\n\n\n\nAsia Pacific\nMarilou Maala\nIncident Response Analyst\nHelpline\n\nAsia Pacific\nMarilou Maala\nIncident Response Analyst\n\nIncident Response Analyst\n\nAsia Pacific\nMarilou Maala\nIncident Response Analyst\nHelpline\n\nIncident Response Analyst\n\nHelpline\n\nAsia Pacific\nMarionne Sarmiento\nDigital Safety Specialist\n\n\n\n\nAsia Pacific\nMarionne Sarmiento\nDigital Safety Specialist\nHelpline\n\nAsia Pacific\nMarionne Sarmiento\nDigital Safety Specialist\n\nDigital Safety Specialist\n\nAsia Pacific\nMarionne Sarmiento\nDigital Safety Specialist\nHelpline\n\nDigital Safety Specialist\n\nHelpline\n\nInternational\nMaxim Petrov\nSafety Specialist\n\n\n\n\nInternational\nMaxim Petrov\nSafety Specialist\nHelpline\n\nInternational\nMaxim Petrov\nSafety Specialist\n\nSafety Specialist\n\nInternational\nMaxim Petrov\nSafety Specialist\nHelpline\n\nSafety Specialist\n\nHelpline\n\nInternational\nMohammed Al-Maskati\nDigital Security Helpline Director\n\n\n\n\nInternational\nMohammed Al-Maskati\nDigital Security Helpline Director\nHelpline\n\nInternational\nMohammed Al-Maskati\nDigital Security Helpline Director\n\nDigital Security Helpline Director\n\nInternational\nMohammed Al-Maskati\nDigital Security Helpline Director\nHelpline\n\nDigital Security Helpline Director\n\nHelpline\n\nInternational\nOleg Serov\nSecurity Incident Handler\n\n\n\n\nInternational\nOleg Serov\nSecurity Incident Handler\nHelpline\n\nInternational\nOleg Serov\nSecurity Incident Handler\n\nSecurity Incident Handler\n\nInternational\nOleg Serov\nSecurity Incident Handler\nHelpline\n\nSecurity Incident Handler\n\nHelpline\n\nLatin America and the Caribbean\nRocío\nSecurity Incident Handler\n\n\n\n\nLatin America and the Caribbean\nRocío\nSecurity Incident Handler\nHelpline\n\nLatin America and the Caribbean\nRocío\nSecurity Incident Handler\n\nSecurity Incident Handler\n\nLatin America and the Caribbean\nRocío\nSecurity Incident Handler\nHelpline\n\nSecurity Incident Handler\n\nHelpline\n\nLatin America and the Caribbean\nRogelio López\nSan José Security Shift Lead\n\n\n\n\nLatin America and the Caribbean\nRogelio López\nSan José Security Shift Lead\nHelpline\n\nLatin America and the Caribbean\nRogelio López\nSan José Security Shift Lead\n\nSan José Security Shift Lead\n\nLatin America and the Caribbean\nRogelio López\nSan José Security Shift Lead\nHelpline\n\nSan José Security Shift Lead\n\nHelpline\n\nAsia Pacific\nShinte Galeshka\nSecurity Incident Handler\n\n\n\n\nAsia Pacific\nShinte Galeshka\nSecurity Incident Handler\nHelpline\n\nAsia Pacific\nShinte Galeshka\nSecurity Incident Handler\n\nSecurity Incident Handler\n\nAsia Pacific\nShinte Galeshka\nSecurity Incident Handler\nHelpline\n\nSecurity Incident Handler\n\nHelpline\n\nEurope\nVeronica Zaboia\nPlatform Engagement Coordinator\n\n\n\n\nEurope\nVeronica Zaboia\nPlatform Engagement Coordinator\nHelpline\n\nEurope\nVeronica Zaboia\nPlatform Engagement Coordinator\n\nPlatform Engagement Coordinator\n\nEurope\nVeronica Zaboia\nPlatform Engagement Coordinator\nHelpline\n\nPlatform Engagement Coordinator\n\nHelpline\n\nInternational\nVictor Novikov\nDigital Security Helpline Manager\n\n\n\n\nInternational\nVictor Novikov\nDigital Security Helpline Manager\nHelpline\n\nInternational\nVictor Novikov\nDigital Security Helpline Manager\n\nDigital Security Helpline Manager\n\nInternational\nVictor Novikov\nDigital Security Helpline Manager\nHelpline\n\nDigital Security Helpline Manager\n\nHelpline\n\nInternational\nVlad\nSecurity Incident Handler\n\n\n\n\nInternational\nVlad\nSecurity Incident Handler\nHelpline\n\nInternational\nVlad\nSecurity Incident Handler\n\nSecurity Incident Handler\n\nInternational\nVlad\nSecurity Incident Handler\nHelpline\n\nSecurity Incident Handler\n\nHelpline\n\nCOMMUNITY & RESOURCES\n\n\n\n\n\n\n\n\n\n\n\n\n\n\n\n\n\n\n\nAccess Now’s Digital Security Helpline is a member of the Civil Society Computer Emergency Response Team (CiviCERT), an accredited CERT focused on improving the incident response capabilities of civil society groups and individuals around the world. As part of Access Now’s work and in collaboration with the broader community, we create and contribute to guides and materials to help communities, organizations, and individuals improve their digital security. Please find some guides below:\n\nDigital First Aid Kit\nA resource for emergency situations, such as when your social media account is compromised, your website is attacked, or your computer is infected \n\nHelpline PGP Email Encryption Guides (Windows | Mac | Linux)\nGuides for setting up encrypted email \n\nHelpline Safer Travel Guide\nHelping you prepare for travels to high-risk countries \n\nHelpline Self-Doxing Guide\nTips and resources for exploring open source intelligence on oneself to prevent online doxing \n\nHelpline Community Documentation\nThe procedures and documentation we create to aid our work on the Helpline \n\nPartner organizations have produced a number of guides and resources that we find valuable in our work, and you may too. They include: \n\nSecurity in a Box\nFrom Frontline Defenders and the Tactical Technology Collective \n\nSurveillance Self-Defense\nFrom the Electronic Frontier Foundation \n\nUmbrella\nFrom Security First\n\nCOMMUNITY & RESOURCES\n\n\n\n\n\n\n\n\n\n\n\n\n\n\n\n\n\n\n\nAccess Now’s Digital Security Helpline is a member of the Civil Society Computer Emergency Response Team (CiviCERT), an accredited CERT focused on improving the incident response capabilities of civil society groups and individuals around the world. Please find some guides below:\n\nDigital First Aid Kit\nA resource for emergency situations, such as when your social media account is compromised, your website is attacked, or your computer is infected \n\nHelpline PGP Email Encryption Guides (Windows | Mac | Linux)\nGuides for setting up encrypted email \n\nHelpline Safer Travel Guide\nHelping you prepare for travels to high-risk countries \n\nHelpline Self-Doxing Guide\nTips and resources for exploring open source intelligence on oneself to prevent online doxing \n\nHelpline Community Documentation\nThe procedures and documentation we create to aid our work on the Helpline \n\nPartner organizations have produced a number of guides and resources that we find valuable in our work, and you may too. They include: \n\nSecurity in a Box\nFrom Frontline Defenders and the Tactical Technology Collective \n\nSurveillance Self-Defense\nFrom the Electronic Frontier Foundation \n\nUmbrella\nFrom Security First\n\nAccess Now’s Digital Security Helpline is a member of the Civil Society Computer Emergency Response Team (CiviCERT), an accredited CERT focused on improving the incident response capabilities of civil society groups and individuals around the world. Access Now’s Digital Security Helpline is a member of the Civil Society Computer Emergency Response Team (CiviCERT), an accredited CERT focused on improving the incident response capabilities of civil society groups and individuals around the world. Access Now’s Digital Security Helpline is a member of the Civil Society Computer Emergency Response Team (CiviCERT), an accredited CERT focused on improving the incident response capabilities of civil society groups and individuals around the world. Access Now’s Digital Security Helpline is a member of the Civil Society Computer Emergency Response Team (CiviCERT), an accredited CERT focused on improving the incident response capabilities of civil society groups and individuals around the world. Please find some guides below:\n\nA resource for emergency situations, such as when your social media account is compromised, your website is attacked, or your computer is infected\n\nGuides for setting up encrypted email\n\nHelping you prepare for travels to high-risk countries\n\nTips and resources for exploring open source intelligence on oneself to prevent online doxing\n\nThe procedures and documentation we create to aid our work on the Helpline\n\nPartner organizations have produced a number of guides and resources that we find valuable in our work, and you may too.",
  "entities": {
    "countries": [
      "afghanistan",
      "australia",
      "brazil",
      "canada",
      "china",
      "france",
      "germany",
      "india",
      "iran",
      "iraq",
      "israel",
      "japan",
      "mexico",
      "north korea",
      "pakistan",
      "russia",
      "south korea",
      "syria",
      "united kingdom",
      "united states",
      "yemen"
    ],
    "organizations": [
      "un",
      "who",
      "amnesty international"
    ],
    "key_issues": [
      "issue",
      "problem",
      "challenge",
      "situation",
      "matter",
      "country",
      "nation",
      "state",
      "government",
      "region",
      "territory",
      "policy",
      "initiative",
      "action",
      "human rights",
      "aid",
      "assistance",
      "un",
      "ngo",
      "non-governmental organization",
      "organization",
      "foundation"
    ]
  },
  "committee": "First Committee",
  "topic": "Creating systems to protect against state-sponsored cyber attacks"
}