{
  "url": "https://www.accessnow.org/issue/covid-19/",
  "title": "Digital Rights In The Covid-19 Fight - Access Now",
  "text": "Back to content\n\nDigital Rights In The Covid-19 Fight\n\n\n\nThe COVID-19 pandemic has impacted every part of our lives — including our human rights. Privacy, free expression, access to information, and other fundamental rights are even more essential in times of crisis, and Access Now is working to ensure responses to COVID-19 strengthen rather than undermine those rights.\n\n\n\n\n\n\n\n\n\n\n\n\nPRESS RELEASES\nProtocol for exclusion: why COVID-19 vaccine “passports” threaten human rights\nAs the global COVID-19 vaccine rollout gains momentum, governments are clamoring to implement measures to help the world return to pre-virus normality. This includes exploring digital vaccine certificates — or COVID-19 vaccine “passports”. Current proposals, however, threaten human rights.…\n\nLearn more\n\n\n\n\n\n\n\nHIGHLIGHTS\n\n\n\n\n\n\n\n\n\n\n\n\n\nCovid-19\n\n\n\t\t\t\n\t\t\t\tCivil society to WHO: let’s end government-ordered internet shutdowns\n\t\t\t\t\t\t\t\n\n\nToday the #KeepItOn coalition sent an open letter to the Deputy Director-General of the WHO, Dr. Zsuzsanna Jakab, calling on her to urge states to end the blatant and arbitrary internet shutdowns that are ongoing during COVID-19.\n\n\n\n\n\n\n\n\n\n\n\n\n\nCovid-19\n\n\n\t\t\t\n\t\t\t\tAccess Now releases recommendations on privacy and data protection in the fight against COVID-19\n\t\t\t\t\t\t\t\n\n\nOur message to governments is simple: protecting digital rights also promotes public health. We aim to ensure that the rule of law, and the rights to privacy and data protection, are protected throughout this crisis and in the future.\n\n\n\n\n\n\n\n\n\n\n\n\n\nCovid 19\n\n\n\t\t\t\n\t\t\t\tPrivacy and public health: the dos and don’ts for COVID-19 contact tracing apps\n\t\t\t\t\t\t\t\n\n\n\n\n\n\n\n\n\n\n\n\n\nContent Governance\n\n\n\t\t\t\n\t\t\t\tAccess Now releases “Fighting misinformation and defending free expression during COVID-19: recommendations for states”\n\t\t\t\t\t\t\t\n\n\nWe have identified practical examples and promising practices to support policy makers in respecting human rights while developing measures to address disinformation and misinformation during the COVID-19 crisis.\n\n\n\n\n\n\n\n\n\n\n\n\n     \n\n\n\n\n\nGrid View\nList View\n\n\n\n\n\n\n\n\n\n\n\n\n\n\t\t\t\t\tFreedom of Expression\t\t\t\t\n\n\n\n\nFreedom of Expression \n\n\n\t\t\t\tAccess Now oral statement to the UN Global Digital Compact Informal Consultations with Member States and Stakeholders\t\t\t\n\n3 Feb 2023\n • \nAccess Now’s Senior UN Advocacy Officer Laura O’Brien delivered an oral statement to the UN Global Digital Compact Informal Consultations with Member States and Stakeholders on Feb 3 2023.\n\n\n\n\nPublication\nAccess Now oral statement to the UN Global Digital Compact Informal Consultations with Member States and Stakeholders\n\n\n↗\n3 Feb 2023\n\nAccess Now oral statement to the UN Global Digital Compact Informal Consultations with Member States and Stakeholders\n\n\n\n\n\n\n\n\n\n\t\t\t\t\tInternet Shutdowns\t\t\t\t\n\n\n\n\nInternet Shutdowns \n\n\n\t\t\t\tዓፀቦ፣ ዓቕሊ ፅበትን ስቃይ: 15 ታሪኻት ከበባ ኢንተርነት ትግራይ\t\t\t\n\n25 Aug 2022\n\n\n\n\nPost\nዓፀቦ፣ ዓቕሊ ፅበትን ስቃይ: 15 ታሪኻት ከበባ ኢንተርነት ትግራይ\n25 Aug 2022\n\nዓፀቦ፣ ዓቕሊ ፅበትን ስቃይ: 15 ታሪኻት ከበባ ኢንተርነት ትግራይ\n\n\n\n\n\n\n\n\n\n\t\t\t\t\tInternet Shutdowns\t\t\t\t\n\n\n\n\nInternet Shutdowns \n\n\n\t\t\t\tStranded, suffocated, and in pain: 15 stories from Tigray’s internet siege\t\t\t\n\n28 Jul 2022\n • \nIt’s been two years since Tigray were cut off from the internet. Share the 15 stories from Tigrayans and help amplify their voices.\n\n\n\n\nPost\nStranded, suffocated, and in pain: 15 stories from Tigray’s internet siege\n28 Jul 2022\n\nStranded, suffocated, and in pain: 15 stories from Tigray’s internet siege\n\n\n\n\n\n\n\n\n\n\t\t\t\t\tContent Governance\t\t\t\t\n\n\n\n\nContent Governance \n\n\n\t\t\t\tJoin us June 6-10 for RightsCon 2022\t\t\t\n\n31 May 2022\n • \nLog in to the RightsCon platform to participate in the world’s leading summit on human rights in the digital age (June 6-10, 2022)!\n\n\n\n\nCampaign\nJoin us June 6-10 for RightsCon 2022\n\n\n↗\n31 May 2022\n\nJoin us June 6-10 for RightsCon 2022\n\n\n\n\n\n\n\n\n\n\t\t\t\t\tContent Governance\t\t\t\t\n\n\n\n\nContent Governance \n\n\n\t\t\t\tStop the misinformation experience: Spotify must intervene\t\t\t\n\n24 Feb 2022\n • \nThrough a letter to Daniel Ek, Co-Founder and CEO at Spotify, Access Now is urging the company to align with basic human rights principles.\n\n\n\n\nPress Release\nStop the misinformation experience: Spotify must intervene\n24 Feb 2022\n\nStop the misinformation experience: Spotify must intervene\n\n\n\n\n\n\n\n\n\n\t\t\t\t\tFreedom of Expression\t\t\t\t\n\n\n\n\nFreedom of Expression \n\n\n\t\t\t\tJoe Rogan and Spotify: Make content moderation about human rights\t\t\t\n\n10 Feb 2022\n • \nIs Spotify willing to allow harmful content like COVID misinformation to spread, prioritizing the companyʼs bottom line over public health?\n\n\n\n\nPost\nJoe Rogan and Spotify: Make content moderation about human rights\n10 Feb 2022\n\nJoe Rogan and Spotify: Make content moderation about human rights\n\n\n\n\n\n\n\n\n\n\t\t\t\t\tContent Governance\t\t\t\t\n\n\n\n\nContent Governance \n\n\n\t\t\t\tWhat is disinformation, why it spreads, and how to stop it\t\t\t\n\n21 Dec 2021\n • \nOur new report explores what disinformation is, and how lawmakers can address the harms it poses to democracy.\n\n\n\n\nPublication\nWhat is disinformation, why it spreads, and how to stop it\n21 Dec 2021\n\nWhat is disinformation, why it spreads, and how to stop it\n\n\n\n\n\n\n\n\n\n\t\t\t\t\tCovid-19\t\t\t\t\n\n\n\n\nCovid-19 \n\n\n\t\t\t\tOne Year Under COVID-19 Contact Tracing Apps: What Has Europe Learned? – A report by Access Now and Liberties\t\t\t\n\n28 Oct 2021\n • \nA year after the introduction of COVID-19 Contact Tracing Apps in Europe, Access Now and Liberties look at their impact on digital rights.\n\n\n\n\nPublication\nOne Year Under COVID-19 Contact Tracing Apps: What Has Europe Learned? – A report by Access Now and Liberties\n\n\n↗\n28 Oct 2021\n\nOne Year Under COVID-19 Contact Tracing Apps: What Has Europe Learned? – A report by Access Now and Liberties\n\n\n\n\n\n\n\n\n\n\t\t\t\t\tPrivacy\t\t\t\t\n\n\n\n\nPrivacy \n\n\n\t\t\t\tWhat you need to know about the Facebook Papers\t\t\t\n\n26 Oct 2021\n • \nThe Facebook Papers paint a grim picture of how Facebook has repeatedly and knowingly prioritized profit over people’s safety. Here’s a snapshot of what we know so far.\n\n\n\n\nPost\nWhat you need to know about the Facebook Papers\n26 Oct 2021\n\nWhat you need to know about the Facebook Papers\n\n\n\n\n\n\n\n\n\n\t\t\t\t\tNet Neutrality\t\t\t\t\n\n\n\n\nNet Neutrality \n\n\n\t\t\t\tDigital rights champions nominated to lead U.S. FCC and NTIA\t\t\t\n\n26 Oct 2021\n • \nAt long last, U.S. President Biden has nominated public interests advocates to lead the Federal Communications Commission and the National Telecommunications and Information Administration.\n\n\n\n\nPress Release\nDigital rights champions nominated to lead U.S. FCC and NTIA\n26 Oct 2021\n\nDigital rights champions nominated to lead U.S. FCC and NTIA\n\n\n\n\n\n\n\n\n\n\t\t\t\t\tContent Governance\t\t\t\t\n\n\n\n\nContent Governance \n\n\n\t\t\t\tWill the Right to Protest survive its migration online?\t\t\t\n\n20 Oct 2021\n • \nState-sanctioned internet shutdowns, increased surveillance, and unequal access to the internet are impacting communities globally. Will the Right to Protest survive its migration online?\n\n\n\n\nPost\nWill the Right to Protest survive its migration online?\n20 Oct 2021\n\nWill the Right to Protest survive its migration online?\n\n\n\n\n\n\n\n\n\n\t\t\t\t\tPrivacy\t\t\t\t\n\n\n\n\nPrivacy \n\n\n\t\t\t\tColombia’s mandatory CoronApp violates people’s privacy and freedom of movement\t\t\t\n\n23 Sep 2021\n\n\n\n\nPress Release\nColombia’s mandatory CoronApp violates people’s privacy and freedom of movement\n23 Sep 2021\n\nColombia’s mandatory CoronApp violates people’s privacy and freedom of movement\n\n\n\n\n\n\n\n\n\n\t\t\t\t\tPrivacy\t\t\t\t\n\n\n\n\nPrivacy \n\n\n\t\t\t\tColombia: CoronApp viola la privacidad y la libertad de movimiento de las personas\t\t\t\n\n23 Sep 2021\n\n\n\n\nPress Release\nColombia: CoronApp viola la privacidad y la libertad de movimiento de las personas\n23 Sep 2021\n\nColombia: CoronApp viola la privacidad y la libertad de movimiento de las personas\n\n\n\n\n\n\n\n\n\n\t\t\t\t\tFreedom of Expression\t\t\t\t\n\n\n\n\nFreedom of Expression \n\n\n\t\t\t\tThe internet shutdowns issue\t\t\t\n\n1 Sep 2021\n • \nWith support from the #KeepItOn coalition, Jigsaw is today publishing “The Current: The Internet Shutdowns Issue,” a deep-dive into internet shutdowns.\n\n\n\n\nPress Release\nThe internet shutdowns issue\n1 Sep 2021\n\nThe internet shutdowns issue\n\n\n\n\n\n\n\n\n\n\t\t\t\t\tFreedom of Expression\t\t\t\t\n\n\n\n\nFreedom of Expression \n\n\n\t\t\t\tHow Thailand handles COVID: it stokes fear among its critics\t\t\t\n\n24 Aug 2021\n • \nAmidst continuing protests, calls for political reform, and mass dissatisfaction with how Thailand handles COVID, Thailand’s government is doubling down on efforts to throttle dissent and protest online and off. It is relying on laws that it claims protect against “public fear.” In fact, by threatening to censor those who speak out, it is the government that is instigating fear – in a weak bid to distract from flailing governance. \n\n\n\n\nPost\nHow Thailand handles COVID: it stokes fear among its critics\n24 Aug 2021\n\nHow Thailand handles COVID: it stokes fear among its critics\n\n\n\n\n\n\n\n\n\n\t\t\t\t\tCovid-19\t\t\t\t\n\n\n\n\nCovid-19 \n\n\n\t\t\t\tHow to apply for the Emergency Broadband Benefit in the U.S.\t\t\t\n\n13 Aug 2021\n\n\n\n\nPost\nHow to apply for the Emergency Broadband Benefit in the U.S.\n13 Aug 2021\n\nHow to apply for the Emergency Broadband Benefit in the U.S.\n\n\n\n\n\n\n\n\n\n \n\n\n\n\n\n\nHelp keep the internet open and secure.\nSubscribe to our action alerts and weekly newsletter\n\"*\" indicates required fields\n\nThis field is hidden when viewing the form\n\nSubscribe to Access Express\nThis field is hidden when viewing the form\n\nSubscribe to Action Alerts\nName\n\n\nFirst\n\n\n\nLast\n\nEmail*\n\nCountryCountryAfghanistanÅland IslandsAlbaniaAlgeriaAmerican SamoaAndorraAngolaAnguillaAntigua and BarbudaArgentinaArmeniaArubaAustraliaAustriaAzerbaijanBahamasBahrainBangladeshBarbadosBelarusBelgiumBelizeBeninBermudaBhutanBoliviaBonaire, Sint Eustatius and SabaBosnia and HerzegovinaBotswanaBrazilBritish Indian Ocean TerritoryBritish Virgin IslandsBruneiBulgariaBurkina FasoBurundiCambodiaCameroonCanadaCape VerdeCayman IslandsCentral African RepublicChadChileChinaChristmas IslandColombiaComorosCook IslandsCosta RicaCôte d'IvoireCroatiaCubaCuraçaoCyprusCzech RepublicDemocratic Republic of the CongoDenmarkDjiboutiDominicaDominican RepublicEast TimorEcuadorEgyptEl SalvadorEquatorial GuineaEritreaEstoniaEswatiniEthiopiaFalkland IslandsFaroe IslandsFijiFinlandFranceFrench GuianaFrench PolynesiaFrench Southern TerritoriesGabonGeorgiaGermanyGhanaGibraltarGreeceGreenlandGrenadaGuadeloupeGuamGuatemalaGuernseyGuineaGuinea-BissauGuyanaHaitiHondurasHong KongHungaryIcelandIndiaIndonesiaIranIraqIrelandIsraelItalyJamaicaJapanJordanKazakhstanKenyaKiribatiKosovoKuwaitKyrgyzstanLaosLatviaLebanonLesothoLiberiaLibyaLiechtensteinLithuaniaLuxembourgMacauMadagascarMalawiMalaysiaMaldivesMaliMaltaMarshall IslandsMartiniqueMauritaniaMauritiusMayotteMexicoMicronesiaMoldovaMonacoMongoliaMontenegroMontserratMoroccoMozambiqueMyanmarNamibiaNauruNepalNetherlands AntillesNew CaledoniaNew ZealandNicaraguaNigerNigeriaNiueNorfolk IslandNorth KoreaNorth MacedoniaNorthern Mariana IslandsNorwayOmanPakistanPalauPalestinePanamaPapua New GuineaParaguayPeruPhilippinesPitcairn IslandPolandPortugalPuerto RicoQatarRepublic of the CongoReunionRomaniaRussiaRwandaSaint BarthélemySaint Kitts and NevisSaint LuciaSaint Vincent and the GrenadinesSamoaSan MarinoSão Tomé and PríncipeSaudi ArabiaSenegalSerbiaSeychellesSierra LeoneSingaporeSlovakiaSloveniaSolomon IslandsSomaliaSomalilandSouth AfricaSouth KoreaSouth SudanSpainSri LankaSt. HelenaSt. Pierre and MiquelonSudanSurinameSwedenSwitzerlandSyriaTaiwanTajikistanTanzaniaThailandThe GambiaThe NetherlandsTogoTokelauTongaTrinidad and TobagoTunisiaTurkeyTurkmenistanTurks and Caicos IslandsTuvaluUgandaUkraineUnited Arab EmiratesUnited KingdomUnited StatesUruguayUzbekistanVanuatuVatican CityVenezuelaVietnamVirgin Islands (U.S.)Wallis and Futuna IslandsWestern SaharaYemenZambiaZimbabwePostal CodePhoneThis field is for validation purposes and should be left unchanged.\n \n\n\n\n\n\n\n\n\n\n\n\n\n\n\n\nYour info is secure with us\n\nDigital Rights In The Covid-19 Fight\n\n\n\nThe COVID-19 pandemic has impacted every part of our lives — including our human rights. Privacy, free expression, access to information, and other fundamental rights are even more essential in times of crisis, and Access Now is working to ensure responses to COVID-19 strengthen rather than undermine those rights.\n\n\n\n\n\n\n\n\n\n\n\n\nPRESS RELEASES\nProtocol for exclusion: why COVID-19 vaccine “passports” threaten human rights\nAs the global COVID-19 vaccine rollout gains momentum, governments are clamoring to implement measures to help the world return to pre-virus normality. This includes exploring digital vaccine certificates — or COVID-19 vaccine “passports”. Current proposals, however, threaten human rights.…\n\nLearn more\n\n\n\n\n\n\n\nHIGHLIGHTS\n\n\n\n\n\n\n\n\n\n\n\n\n\nCovid-19\n\n\n\t\t\t\n\t\t\t\tCivil society to WHO: let’s end government-ordered internet shutdowns\n\t\t\t\t\t\t\t\n\n\nToday the #KeepItOn coalition sent an open letter to the Deputy Director-General of the WHO, Dr. Zsuzsanna Jakab, calling on her to urge states to end the blatant and arbitrary internet shutdowns that are ongoing during COVID-19.\n\n\n\n\n\n\n\n\n\n\n\n\n\nCovid-19\n\n\n\t\t\t\n\t\t\t\tAccess Now releases recommendations on privacy and data protection in the fight against COVID-19\n\t\t\t\t\t\t\t\n\n\nOur message to governments is simple: protecting digital rights also promotes public health. We aim to ensure that the rule of law, and the rights to privacy and data protection, are protected throughout this crisis and in the future.\n\n\n\n\n\n\n\n\n\n\n\n\n\nCovid 19\n\n\n\t\t\t\n\t\t\t\tPrivacy and public health: the dos and don’ts for COVID-19 contact tracing apps\n\t\t\t\t\t\t\t\n\n\n\n\n\n\n\n\n\n\n\n\n\nContent Governance\n\n\n\t\t\t\n\t\t\t\tAccess Now releases “Fighting misinformation and defending free expression during COVID-19: recommendations for states”\n\t\t\t\t\t\t\t\n\n\nWe have identified practical examples and promising practices to support policy makers in respecting human rights while developing measures to address disinformation and misinformation during the COVID-19 crisis.\n\n\n\n\n\n\n\n\n\n\n\n\n     \n\n\n\n\n\nGrid View\nList View\n\n\n\n\n\n\n\n\n\n\n\n\n\n\t\t\t\t\tFreedom of Expression\t\t\t\t\n\n\n\n\nFreedom of Expression \n\n\n\t\t\t\tAccess Now oral statement to the UN Global Digital Compact Informal Consultations with Member States and Stakeholders\t\t\t\n\n3 Feb 2023\n • \nAccess Now’s Senior UN Advocacy Officer Laura O’Brien delivered an oral statement to the UN Global Digital Compact Informal Consultations with Member States and Stakeholders on Feb 3 2023.\n\n\n\n\nPublication\nAccess Now oral statement to the UN Global Digital Compact Informal Consultations with Member States and Stakeholders\n\n\n↗\n3 Feb 2023\n\nAccess Now oral statement to the UN Global Digital Compact Informal Consultations with Member States and Stakeholders\n\n\n\n\n\n\n\n\n\n\t\t\t\t\tInternet Shutdowns\t\t\t\t\n\n\n\n\nInternet Shutdowns \n\n\n\t\t\t\tዓፀቦ፣ ዓቕሊ ፅበትን ስቃይ: 15 ታሪኻት ከበባ ኢንተርነት ትግራይ\t\t\t\n\n25 Aug 2022\n\n\n\n\nPost\nዓፀቦ፣ ዓቕሊ ፅበትን ስቃይ: 15 ታሪኻት ከበባ ኢንተርነት ትግራይ\n25 Aug 2022\n\nዓፀቦ፣ ዓቕሊ ፅበትን ስቃይ: 15 ታሪኻት ከበባ ኢንተርነት ትግራይ\n\n\n\n\n\n\n\n\n\n\t\t\t\t\tInternet Shutdowns\t\t\t\t\n\n\n\n\nInternet Shutdowns \n\n\n\t\t\t\tStranded, suffocated, and in pain: 15 stories from Tigray’s internet siege\t\t\t\n\n28 Jul 2022\n • \nIt’s been two years since Tigray were cut off from the internet. Share the 15 stories from Tigrayans and help amplify their voices.\n\n\n\n\nPost\nStranded, suffocated, and in pain: 15 stories from Tigray’s internet siege\n28 Jul 2022\n\nStranded, suffocated, and in pain: 15 stories from Tigray’s internet siege\n\n\n\n\n\n\n\n\n\n\t\t\t\t\tContent Governance\t\t\t\t\n\n\n\n\nContent Governance \n\n\n\t\t\t\tJoin us June 6-10 for RightsCon 2022\t\t\t\n\n31 May 2022\n • \nLog in to the RightsCon platform to participate in the world’s leading summit on human rights in the digital age (June 6-10, 2022)!\n\n\n\n\nCampaign\nJoin us June 6-10 for RightsCon 2022\n\n\n↗\n31 May 2022\n\nJoin us June 6-10 for RightsCon 2022\n\n\n\n\n\n\n\n\n\n\t\t\t\t\tContent Governance\t\t\t\t\n\n\n\n\nContent Governance \n\n\n\t\t\t\tStop the misinformation experience: Spotify must intervene\t\t\t\n\n24 Feb 2022\n • \nThrough a letter to Daniel Ek, Co-Founder and CEO at Spotify, Access Now is urging the company to align with basic human rights principles.\n\n\n\n\nPress Release\nStop the misinformation experience: Spotify must intervene\n24 Feb 2022\n\nStop the misinformation experience: Spotify must intervene\n\n\n\n\n\n\n\n\n\n\t\t\t\t\tFreedom of Expression\t\t\t\t\n\n\n\n\nFreedom of Expression \n\n\n\t\t\t\tJoe Rogan and Spotify: Make content moderation about human rights\t\t\t\n\n10 Feb 2022\n • \nIs Spotify willing to allow harmful content like COVID misinformation to spread, prioritizing the companyʼs bottom line over public health?\n\n\n\n\nPost\nJoe Rogan and Spotify: Make content moderation about human rights\n10 Feb 2022\n\nJoe Rogan and Spotify: Make content moderation about human rights\n\n\n\n\n\n\n\n\n\n\t\t\t\t\tContent Governance\t\t\t\t\n\n\n\n\nContent Governance \n\n\n\t\t\t\tWhat is disinformation, why it spreads, and how to stop it\t\t\t\n\n21 Dec 2021\n • \nOur new report explores what disinformation is, and how lawmakers can address the harms it poses to democracy.\n\n\n\n\nPublication\nWhat is disinformation, why it spreads, and how to stop it\n21 Dec 2021\n\nWhat is disinformation, why it spreads, and how to stop it\n\n\n\n\n\n\n\n\n\n\t\t\t\t\tCovid-19\t\t\t\t\n\n\n\n\nCovid-19 \n\n\n\t\t\t\tOne Year Under COVID-19 Contact Tracing Apps: What Has Europe Learned? – A report by Access Now and Liberties\t\t\t\n\n28 Oct 2021\n • \nA year after the introduction of COVID-19 Contact Tracing Apps in Europe, Access Now and Liberties look at their impact on digital rights.\n\n\n\n\nPublication\nOne Year Under COVID-19 Contact Tracing Apps: What Has Europe Learned? – A report by Access Now and Liberties\n\n\n↗\n28 Oct 2021\n\nOne Year Under COVID-19 Contact Tracing Apps: What Has Europe Learned? – A report by Access Now and Liberties\n\n\n\n\n\n\n\n\n\n\t\t\t\t\tPrivacy\t\t\t\t\n\n\n\n\nPrivacy \n\n\n\t\t\t\tWhat you need to know about the Facebook Papers\t\t\t\n\n26 Oct 2021\n • \nThe Facebook Papers paint a grim picture of how Facebook has repeatedly and knowingly prioritized profit over people’s safety. Here’s a snapshot of what we know so far.\n\n\n\n\nPost\nWhat you need to know about the Facebook Papers\n26 Oct 2021\n\nWhat you need to know about the Facebook Papers\n\n\n\n\n\n\n\n\n\n\t\t\t\t\tNet Neutrality\t\t\t\t\n\n\n\n\nNet Neutrality \n\n\n\t\t\t\tDigital rights champions nominated to lead U.S. FCC and NTIA\t\t\t\n\n26 Oct 2021\n • \nAt long last, U.S. President Biden has nominated public interests advocates to lead the Federal Communications Commission and the National Telecommunications and Information Administration.\n\n\n\n\nPress Release\nDigital rights champions nominated to lead U.S. FCC and NTIA\n26 Oct 2021\n\nDigital rights champions nominated to lead U.S. FCC and NTIA\n\n\n\n\n\n\n\n\n\n\t\t\t\t\tContent Governance\t\t\t\t\n\n\n\n\nContent Governance \n\n\n\t\t\t\tWill the Right to Protest survive its migration online?\t\t\t\n\n20 Oct 2021\n • \nState-sanctioned internet shutdowns, increased surveillance, and unequal access to the internet are impacting communities globally. Will the Right to Protest survive its migration online?\n\n\n\n\nPost\nWill the Right to Protest survive its migration online?\n20 Oct 2021\n\nWill the Right to Protest survive its migration online?\n\n\n\n\n\n\n\n\n\n\t\t\t\t\tPrivacy\t\t\t\t\n\n\n\n\nPrivacy \n\n\n\t\t\t\tColombia’s mandatory CoronApp violates people’s privacy and freedom of movement\t\t\t\n\n23 Sep 2021\n\n\n\n\nPress Release\nColombia’s mandatory CoronApp violates people’s privacy and freedom of movement\n23 Sep 2021\n\nColombia’s mandatory CoronApp violates people’s privacy and freedom of movement\n\n\n\n\n\n\n\n\n\n\t\t\t\t\tPrivacy\t\t\t\t\n\n\n\n\nPrivacy \n\n\n\t\t\t\tColombia: CoronApp viola la privacidad y la libertad de movimiento de las personas\t\t\t\n\n23 Sep 2021\n\n\n\n\nPress Release\nColombia: CoronApp viola la privacidad y la libertad de movimiento de las personas\n23 Sep 2021\n\nColombia: CoronApp viola la privacidad y la libertad de movimiento de las personas\n\n\n\n\n\n\n\n\n\n\t\t\t\t\tFreedom of Expression\t\t\t\t\n\n\n\n\nFreedom of Expression \n\n\n\t\t\t\tThe internet shutdowns issue\t\t\t\n\n1 Sep 2021\n • \nWith support from the #KeepItOn coalition, Jigsaw is today publishing “The Current: The Internet Shutdowns Issue,” a deep-dive into internet shutdowns.\n\n\n\n\nPress Release\nThe internet shutdowns issue\n1 Sep 2021\n\nThe internet shutdowns issue\n\n\n\n\n\n\n\n\n\n\t\t\t\t\tFreedom of Expression\t\t\t\t\n\n\n\n\nFreedom of Expression \n\n\n\t\t\t\tHow Thailand handles COVID: it stokes fear among its critics\t\t\t\n\n24 Aug 2021\n • \nAmidst continuing protests, calls for political reform, and mass dissatisfaction with how Thailand handles COVID, Thailand’s government is doubling down on efforts to throttle dissent and protest online and off. It is relying on laws that it claims protect against “public fear.” In fact, by threatening to censor those who speak out, it is the government that is instigating fear – in a weak bid to distract from flailing governance. \n\n\n\n\nPost\nHow Thailand handles COVID: it stokes fear among its critics\n24 Aug 2021\n\nHow Thailand handles COVID: it stokes fear among its critics\n\n\n\n\n\n\n\n\n\n\t\t\t\t\tCovid-19\t\t\t\t\n\n\n\n\nCovid-19 \n\n\n\t\t\t\tHow to apply for the Emergency Broadband Benefit in the U.S.\t\t\t\n\n13 Aug 2021\n\n\n\n\nPost\nHow to apply for the Emergency Broadband Benefit in the U.S.\n13 Aug 2021\n\nHow to apply for the Emergency Broadband Benefit in the U.S.\n\nDigital Rights In The Covid-19 Fight\n\n\n\nThe COVID-19 pandemic has impacted every part of our lives — including our human rights. Privacy, free expression, access to information, and other fundamental rights are even more essential in times of crisis, and Access Now is working to ensure responses to COVID-19 strengthen rather than undermine those rights.\n\n\n\n\n\n\n\n\n\n\n\n\nPRESS RELEASES\nProtocol for exclusion: why COVID-19 vaccine “passports” threaten human rights\nAs the global COVID-19 vaccine rollout gains momentum, governments are clamoring to implement measures to help the world return to pre-virus normality. This includes exploring digital vaccine certificates — or COVID-19 vaccine “passports”. Current proposals, however, threaten human rights.…\n\nLearn more\n\n\n\n\n\n\n\nHIGHLIGHTS\n\n\n\n\n\n\n\n\n\n\n\n\n\nCovid-19\n\n\n\t\t\t\n\t\t\t\tCivil society to WHO: let’s end government-ordered internet shutdowns\n\t\t\t\t\t\t\t\n\n\nToday the #KeepItOn coalition sent an open letter to the Deputy Director-General of the WHO, Dr. Zsuzsanna Jakab, calling on her to urge states to end the blatant and arbitrary internet shutdowns that are ongoing during COVID-19.\n\n\n\n\n\n\n\n\n\n\n\n\n\nCovid-19\n\n\n\t\t\t\n\t\t\t\tAccess Now releases recommendations on privacy and data protection in the fight against COVID-19\n\t\t\t\t\t\t\t\n\n\nOur message to governments is simple: protecting digital rights also promotes public health. We aim to ensure that the rule of law, and the rights to privacy and data protection, are protected throughout this crisis and in the future.\n\n\n\n\n\n\n\n\n\n\n\n\n\nCovid 19\n\n\n\t\t\t\n\t\t\t\tPrivacy and public health: the dos and don’ts for COVID-19 contact tracing apps\n\t\t\t\t\t\t\t\n\n\n\n\n\n\n\n\n\n\n\n\n\nContent Governance\n\n\n\t\t\t\n\t\t\t\tAccess Now releases “Fighting misinformation and defending free expression during COVID-19: recommendations for states”\n\t\t\t\t\t\t\t\n\n\nWe have identified practical examples and promising practices to support policy makers in respecting human rights while developing measures to address disinformation and misinformation during the COVID-19 crisis.\n\n\n\n\n\n\n\n\n\n\n\n\n     \n\n\n\n\n\nGrid View\nList View\n\n\n\n\n\n\n\n\n\n\n\n\n\n\t\t\t\t\tFreedom of Expression\t\t\t\t\n\n\n\n\nFreedom of Expression \n\n\n\t\t\t\tAccess Now oral statement to the UN Global Digital Compact Informal Consultations with Member States and Stakeholders\t\t\t\n\n3 Feb 2023\n • \nAccess Now’s Senior UN Advocacy Officer Laura O’Brien delivered an oral statement to the UN Global Digital Compact Informal Consultations with Member States and Stakeholders on Feb 3 2023.\n\n\n\n\nPublication\nAccess Now oral statement to the UN Global Digital Compact Informal Consultations with Member States and Stakeholders\n\n\n↗\n3 Feb 2023\n\nAccess Now oral statement to the UN Global Digital Compact Informal Consultations with Member States and Stakeholders\n\n\n\n\n\n\n\n\n\n\t\t\t\t\tInternet Shutdowns\t\t\t\t\n\n\n\n\nInternet Shutdowns \n\n\n\t\t\t\tዓፀቦ፣ ዓቕሊ ፅበትን ስቃይ: 15 ታሪኻት ከበባ ኢንተርነት ትግራይ\t\t\t\n\n25 Aug 2022\n\n\n\n\nPost\nዓፀቦ፣ ዓቕሊ ፅበትን ስቃይ: 15 ታሪኻት ከበባ ኢንተርነት ትግራይ\n25 Aug 2022\n\nዓፀቦ፣ ዓቕሊ ፅበትን ስቃይ: 15 ታሪኻት ከበባ ኢንተርነት ትግራይ\n\n\n\n\n\n\n\n\n\n\t\t\t\t\tInternet Shutdowns\t\t\t\t\n\n\n\n\nInternet Shutdowns \n\n\n\t\t\t\tStranded, suffocated, and in pain: 15 stories from Tigray’s internet siege\t\t\t\n\n28 Jul 2022\n • \nIt’s been two years since Tigray were cut off from the internet. Share the 15 stories from Tigrayans and help amplify their voices.\n\n\n\n\nPost\nStranded, suffocated, and in pain: 15 stories from Tigray’s internet siege\n28 Jul 2022\n\nStranded, suffocated, and in pain: 15 stories from Tigray’s internet siege\n\n\n\n\n\n\n\n\n\n\t\t\t\t\tContent Governance\t\t\t\t\n\n\n\n\nContent Governance \n\n\n\t\t\t\tJoin us June 6-10 for RightsCon 2022\t\t\t\n\n31 May 2022\n • \nLog in to the RightsCon platform to participate in the world’s leading summit on human rights in the digital age (June 6-10, 2022)!\n\n\n\n\nCampaign\nJoin us June 6-10 for RightsCon 2022\n\n\n↗\n31 May 2022\n\nJoin us June 6-10 for RightsCon 2022\n\n\n\n\n\n\n\n\n\n\t\t\t\t\tContent Governance\t\t\t\t\n\n\n\n\nContent Governance \n\n\n\t\t\t\tStop the misinformation experience: Spotify must intervene\t\t\t\n\n24 Feb 2022\n • \nThrough a letter to Daniel Ek, Co-Founder and CEO at Spotify, Access Now is urging the company to align with basic human rights principles.\n\n\n\n\nPress Release\nStop the misinformation experience: Spotify must intervene\n24 Feb 2022\n\nStop the misinformation experience: Spotify must intervene\n\n\n\n\n\n\n\n\n\n\t\t\t\t\tFreedom of Expression\t\t\t\t\n\n\n\n\nFreedom of Expression \n\n\n\t\t\t\tJoe Rogan and Spotify: Make content moderation about human rights\t\t\t\n\n10 Feb 2022\n • \nIs Spotify willing to allow harmful content like COVID misinformation to spread, prioritizing the companyʼs bottom line over public health?\n\n\n\n\nPost\nJoe Rogan and Spotify: Make content moderation about human rights\n10 Feb 2022\n\nJoe Rogan and Spotify: Make content moderation about human rights\n\n\n\n\n\n\n\n\n\n\t\t\t\t\tContent Governance\t\t\t\t\n\n\n\n\nContent Governance \n\n\n\t\t\t\tWhat is disinformation, why it spreads, and how to stop it\t\t\t\n\n21 Dec 2021\n • \nOur new report explores what disinformation is, and how lawmakers can address the harms it poses to democracy.\n\n\n\n\nPublication\nWhat is disinformation, why it spreads, and how to stop it\n21 Dec 2021\n\nWhat is disinformation, why it spreads, and how to stop it\n\n\n\n\n\n\n\n\n\n\t\t\t\t\tCovid-19\t\t\t\t\n\n\n\n\nCovid-19 \n\n\n\t\t\t\tOne Year Under COVID-19 Contact Tracing Apps: What Has Europe Learned? – A report by Access Now and Liberties\t\t\t\n\n28 Oct 2021\n • \nA year after the introduction of COVID-19 Contact Tracing Apps in Europe, Access Now and Liberties look at their impact on digital rights.\n\n\n\n\nPublication\nOne Year Under COVID-19 Contact Tracing Apps: What Has Europe Learned? – A report by Access Now and Liberties\n\n\n↗\n28 Oct 2021\n\nOne Year Under COVID-19 Contact Tracing Apps: What Has Europe Learned? – A report by Access Now and Liberties\n\n\n\n\n\n\n\n\n\n\t\t\t\t\tPrivacy\t\t\t\t\n\n\n\n\nPrivacy \n\n\n\t\t\t\tWhat you need to know about the Facebook Papers\t\t\t\n\n26 Oct 2021\n • \nThe Facebook Papers paint a grim picture of how Facebook has repeatedly and knowingly prioritized profit over people’s safety. Here’s a snapshot of what we know so far.\n\n\n\n\nPost\nWhat you need to know about the Facebook Papers\n26 Oct 2021\n\nWhat you need to know about the Facebook Papers\n\n\n\n\n\n\n\n\n\n\t\t\t\t\tNet Neutrality\t\t\t\t\n\n\n\n\nNet Neutrality \n\n\n\t\t\t\tDigital rights champions nominated to lead U.S. FCC and NTIA\t\t\t\n\n26 Oct 2021\n • \nAt long last, U.S. President Biden has nominated public interests advocates to lead the Federal Communications Commission and the National Telecommunications and Information Administration.\n\n\n\n\nPress Release\nDigital rights champions nominated to lead U.S. FCC and NTIA\n26 Oct 2021\n\nDigital rights champions nominated to lead U.S. FCC and NTIA\n\n\n\n\n\n\n\n\n\n\t\t\t\t\tContent Governance\t\t\t\t\n\n\n\n\nContent Governance \n\n\n\t\t\t\tWill the Right to Protest survive its migration online?\t\t\t\n\n20 Oct 2021\n • \nState-sanctioned internet shutdowns, increased surveillance, and unequal access to the internet are impacting communities globally. Will the Right to Protest survive its migration online?\n\n\n\n\nPost\nWill the Right to Protest survive its migration online?\n20 Oct 2021\n\nWill the Right to Protest survive its migration online?\n\n\n\n\n\n\n\n\n\n\t\t\t\t\tPrivacy\t\t\t\t\n\n\n\n\nPrivacy \n\n\n\t\t\t\tColombia’s mandatory CoronApp violates people’s privacy and freedom of movement\t\t\t\n\n23 Sep 2021\n\n\n\n\nPress Release\nColombia’s mandatory CoronApp violates people’s privacy and freedom of movement\n23 Sep 2021\n\nColombia’s mandatory CoronApp violates people’s privacy and freedom of movement\n\n\n\n\n\n\n\n\n\n\t\t\t\t\tPrivacy\t\t\t\t\n\n\n\n\nPrivacy \n\n\n\t\t\t\tColombia: CoronApp viola la privacidad y la libertad de movimiento de las personas\t\t\t\n\n23 Sep 2021\n\n\n\n\nPress Release\nColombia: CoronApp viola la privacidad y la libertad de movimiento de las personas\n23 Sep 2021\n\nColombia: CoronApp viola la privacidad y la libertad de movimiento de las personas\n\n\n\n\n\n\n\n\n\n\t\t\t\t\tFreedom of Expression\t\t\t\t\n\n\n\n\nFreedom of Expression \n\n\n\t\t\t\tThe internet shutdowns issue\t\t\t\n\n1 Sep 2021\n • \nWith support from the #KeepItOn coalition, Jigsaw is today publishing “The Current: The Internet Shutdowns Issue,” a deep-dive into internet shutdowns.\n\n\n\n\nPress Release\nThe internet shutdowns issue\n1 Sep 2021\n\nThe internet shutdowns issue\n\n\n\n\n\n\n\n\n\n\t\t\t\t\tFreedom of Expression\t\t\t\t\n\n\n\n\nFreedom of Expression \n\n\n\t\t\t\tHow Thailand handles COVID: it stokes fear among its critics\t\t\t\n\n24 Aug 2021\n • \nAmidst continuing protests, calls for political reform, and mass dissatisfaction with how Thailand handles COVID, Thailand’s government is doubling down on efforts to throttle dissent and protest online and off. It is relying on laws that it claims protect against “public fear.” In fact, by threatening to censor those who speak out, it is the government that is instigating fear – in a weak bid to distract from flailing governance. \n\n\n\n\nPost\nHow Thailand handles COVID: it stokes fear among its critics\n24 Aug 2021\n\nHow Thailand handles COVID: it stokes fear among its critics\n\n\n\n\n\n\n\n\n\n\t\t\t\t\tCovid-19\t\t\t\t\n\n\n\n\nCovid-19 \n\n\n\t\t\t\tHow to apply for the Emergency Broadband Benefit in the U.S.\t\t\t\n\n13 Aug 2021\n\n\n\n\nPost\nHow to apply for the Emergency Broadband Benefit in the U.S.\n13 Aug 2021\n\nHow to apply for the Emergency Broadband Benefit in the U.S.\n\nDigital Rights In The Covid-19 Fight\n\n\n\nThe COVID-19 pandemic has impacted every part of our lives — including our human rights. Privacy, free expression, access to information, and other fundamental rights are even more essential in times of crisis, and Access Now is working to ensure responses to COVID-19 strengthen rather than undermine those rights.\n\n\n\n\n\n\n\n\n\n\n\n\nPRESS RELEASES\nProtocol for exclusion: why COVID-19 vaccine “passports” threaten human rights\nAs the global COVID-19 vaccine rollout gains momentum, governments are clamoring to implement measures to help the world return to pre-virus normality. This includes exploring digital vaccine certificates — or COVID-19 vaccine “passports”. Current proposals, however, threaten human rights.…\n\nLearn more\n\n\n\n\n\n\n\nHIGHLIGHTS\n\n\n\n\n\n\n\n\n\n\n\n\n\nCovid-19\n\n\n\t\t\t\n\t\t\t\tCivil society to WHO: let’s end government-ordered internet shutdowns\n\t\t\t\t\t\t\t\n\n\nToday the #KeepItOn coalition sent an open letter to the Deputy Director-General of the WHO, Dr. Zsuzsanna Jakab, calling on her to urge states to end the blatant and arbitrary internet shutdowns that are ongoing during COVID-19.\n\n\n\n\n\n\n\n\n\n\n\n\n\nCovid-19\n\n\n\t\t\t\n\t\t\t\tAccess Now releases recommendations on privacy and data protection in the fight against COVID-19\n\t\t\t\t\t\t\t\n\n\nOur message to governments is simple: protecting digital rights also promotes public health. We aim to ensure that the rule of law, and the rights to privacy and data protection, are protected throughout this crisis and in the future.\n\n\n\n\n\n\n\n\n\n\n\n\n\nCovid 19\n\n\n\t\t\t\n\t\t\t\tPrivacy and public health: the dos and don’ts for COVID-19 contact tracing apps\n\t\t\t\t\t\t\t\n\n\n\n\n\n\n\n\n\n\n\n\n\nContent Governance\n\n\n\t\t\t\n\t\t\t\tAccess Now releases “Fighting misinformation and defending free expression during COVID-19: recommendations for states”\n\t\t\t\t\t\t\t\n\n\nWe have identified practical examples and promising practices to support policy makers in respecting human rights while developing measures to address disinformation and misinformation during the COVID-19 crisis.\n\n\n\n\n\n\n\n\n\n\n\n\n     \n\n\n\n\n\nGrid View\nList View\n\n\n\n\n\n\n\n\n\n\n\n\n\n\t\t\t\t\tFreedom of Expression\t\t\t\t\n\n\n\n\nFreedom of Expression \n\n\n\t\t\t\tAccess Now oral statement to the UN Global Digital Compact Informal Consultations with Member States and Stakeholders\t\t\t\n\n3 Feb 2023\n • \nAccess Now’s Senior UN Advocacy Officer Laura O’Brien delivered an oral statement to the UN Global Digital Compact Informal Consultations with Member States and Stakeholders on Feb 3 2023.\n\n\n\n\nPublication\nAccess Now oral statement to the UN Global Digital Compact Informal Consultations with Member States and Stakeholders\n\n\n↗\n3 Feb 2023\n\nAccess Now oral statement to the UN Global Digital Compact Informal Consultations with Member States and Stakeholders\n\n\n\n\n\n\n\n\n\n\t\t\t\t\tInternet Shutdowns\t\t\t\t\n\n\n\n\nInternet Shutdowns \n\n\n\t\t\t\tዓፀቦ፣ ዓቕሊ ፅበትን ስቃይ: 15 ታሪኻት ከበባ ኢንተርነት ትግራይ\t\t\t\n\n25 Aug 2022\n\n\n\n\nPost\nዓፀቦ፣ ዓቕሊ ፅበትን ስቃይ: 15 ታሪኻት ከበባ ኢንተርነት ትግራይ\n25 Aug 2022\n\nዓፀቦ፣ ዓቕሊ ፅበትን ስቃይ: 15 ታሪኻት ከበባ ኢንተርነት ትግራይ\n\n\n\n\n\n\n\n\n\n\t\t\t\t\tInternet Shutdowns\t\t\t\t\n\n\n\n\nInternet Shutdowns \n\n\n\t\t\t\tStranded, suffocated, and in pain: 15 stories from Tigray’s internet siege\t\t\t\n\n28 Jul 2022\n • \nIt’s been two years since Tigray were cut off from the internet. Share the 15 stories from Tigrayans and help amplify their voices.\n\n\n\n\nPost\nStranded, suffocated, and in pain: 15 stories from Tigray’s internet siege\n28 Jul 2022\n\nStranded, suffocated, and in pain: 15 stories from Tigray’s internet siege\n\n\n\n\n\n\n\n\n\n\t\t\t\t\tContent Governance\t\t\t\t\n\n\n\n\nContent Governance \n\n\n\t\t\t\tJoin us June 6-10 for RightsCon 2022\t\t\t\n\n31 May 2022\n • \nLog in to the RightsCon platform to participate in the world’s leading summit on human rights in the digital age (June 6-10, 2022)!\n\n\n\n\nCampaign\nJoin us June 6-10 for RightsCon 2022\n\n\n↗\n31 May 2022\n\nJoin us June 6-10 for RightsCon 2022\n\n\n\n\n\n\n\n\n\n\t\t\t\t\tContent Governance\t\t\t\t\n\n\n\n\nContent Governance \n\n\n\t\t\t\tStop the misinformation experience: Spotify must intervene\t\t\t\n\n24 Feb 2022\n • \nThrough a letter to Daniel Ek, Co-Founder and CEO at Spotify, Access Now is urging the company to align with basic human rights principles.\n\n\n\n\nPress Release\nStop the misinformation experience: Spotify must intervene\n24 Feb 2022\n\nStop the misinformation experience: Spotify must intervene\n\n\n\n\n\n\n\n\n\n\t\t\t\t\tFreedom of Expression\t\t\t\t\n\n\n\n\nFreedom of Expression \n\n\n\t\t\t\tJoe Rogan and Spotify: Make content moderation about human rights\t\t\t\n\n10 Feb 2022\n • \nIs Spotify willing to allow harmful content like COVID misinformation to spread, prioritizing the companyʼs bottom line over public health?\n\n\n\n\nPost\nJoe Rogan and Spotify: Make content moderation about human rights\n10 Feb 2022\n\nJoe Rogan and Spotify: Make content moderation about human rights\n\n\n\n\n\n\n\n\n\n\t\t\t\t\tContent Governance\t\t\t\t\n\n\n\n\nContent Governance \n\n\n\t\t\t\tWhat is disinformation, why it spreads, and how to stop it\t\t\t\n\n21 Dec 2021\n • \nOur new report explores what disinformation is, and how lawmakers can address the harms it poses to democracy.\n\n\n\n\nPublication\nWhat is disinformation, why it spreads, and how to stop it\n21 Dec 2021\n\nWhat is disinformation, why it spreads, and how to stop it\n\n\n\n\n\n\n\n\n\n\t\t\t\t\tCovid-19\t\t\t\t\n\n\n\n\nCovid-19 \n\n\n\t\t\t\tOne Year Under COVID-19 Contact Tracing Apps: What Has Europe Learned? – A report by Access Now and Liberties\t\t\t\n\n28 Oct 2021\n • \nA year after the introduction of COVID-19 Contact Tracing Apps in Europe, Access Now and Liberties look at their impact on digital rights.\n\n\n\n\nPublication\nOne Year Under COVID-19 Contact Tracing Apps: What Has Europe Learned? – A report by Access Now and Liberties\n\n\n↗\n28 Oct 2021\n\nOne Year Under COVID-19 Contact Tracing Apps: What Has Europe Learned? – A report by Access Now and Liberties\n\n\n\n\n\n\n\n\n\n\t\t\t\t\tPrivacy\t\t\t\t\n\n\n\n\nPrivacy \n\n\n\t\t\t\tWhat you need to know about the Facebook Papers\t\t\t\n\n26 Oct 2021\n • \nThe Facebook Papers paint a grim picture of how Facebook has repeatedly and knowingly prioritized profit over people’s safety. Here’s a snapshot of what we know so far.\n\n\n\n\nPost\nWhat you need to know about the Facebook Papers\n26 Oct 2021\n\nWhat you need to know about the Facebook Papers\n\n\n\n\n\n\n\n\n\n\t\t\t\t\tNet Neutrality\t\t\t\t\n\n\n\n\nNet Neutrality \n\n\n\t\t\t\tDigital rights champions nominated to lead U.S. FCC and NTIA\t\t\t\n\n26 Oct 2021\n • \nAt long last, U.S. President Biden has nominated public interests advocates to lead the Federal Communications Commission and the National Telecommunications and Information Administration.\n\n\n\n\nPress Release\nDigital rights champions nominated to lead U.S. FCC and NTIA\n26 Oct 2021\n\nDigital rights champions nominated to lead U.S. FCC and NTIA\n\n\n\n\n\n\n\n\n\n\t\t\t\t\tContent Governance\t\t\t\t\n\n\n\n\nContent Governance \n\n\n\t\t\t\tWill the Right to Protest survive its migration online?\t\t\t\n\n20 Oct 2021\n • \nState-sanctioned internet shutdowns, increased surveillance, and unequal access to the internet are impacting communities globally. Will the Right to Protest survive its migration online?\n\n\n\n\nPost\nWill the Right to Protest survive its migration online?\n20 Oct 2021\n\nWill the Right to Protest survive its migration online?\n\n\n\n\n\n\n\n\n\n\t\t\t\t\tPrivacy\t\t\t\t\n\n\n\n\nPrivacy \n\n\n\t\t\t\tColombia’s mandatory CoronApp violates people’s privacy and freedom of movement\t\t\t\n\n23 Sep 2021\n\n\n\n\nPress Release\nColombia’s mandatory CoronApp violates people’s privacy and freedom of movement\n23 Sep 2021\n\nColombia’s mandatory CoronApp violates people’s privacy and freedom of movement\n\n\n\n\n\n\n\n\n\n\t\t\t\t\tPrivacy\t\t\t\t\n\n\n\n\nPrivacy \n\n\n\t\t\t\tColombia: CoronApp viola la privacidad y la libertad de movimiento de las personas\t\t\t\n\n23 Sep 2021\n\n\n\n\nPress Release\nColombia: CoronApp viola la privacidad y la libertad de movimiento de las personas\n23 Sep 2021\n\nColombia: CoronApp viola la privacidad y la libertad de movimiento de las personas\n\n\n\n\n\n\n\n\n\n\t\t\t\t\tFreedom of Expression\t\t\t\t\n\n\n\n\nFreedom of Expression \n\n\n\t\t\t\tThe internet shutdowns issue\t\t\t\n\n1 Sep 2021\n • \nWith support from the #KeepItOn coalition, Jigsaw is today publishing “The Current: The Internet Shutdowns Issue,” a deep-dive into internet shutdowns.\n\n\n\n\nPress Release\nThe internet shutdowns issue\n1 Sep 2021\n\nThe internet shutdowns issue\n\n\n\n\n\n\n\n\n\n\t\t\t\t\tFreedom of Expression\t\t\t\t\n\n\n\n\nFreedom of Expression \n\n\n\t\t\t\tHow Thailand handles COVID: it stokes fear among its critics\t\t\t\n\n24 Aug 2021\n • \nAmidst continuing protests, calls for political reform, and mass dissatisfaction with how Thailand handles COVID, Thailand’s government is doubling down on efforts to throttle dissent and protest online and off. It is relying on laws that it claims protect against “public fear.” In fact, by threatening to censor those who speak out, it is the government that is instigating fear – in a weak bid to distract from flailing governance. \n\n\n\n\nPost\nHow Thailand handles COVID: it stokes fear among its critics\n24 Aug 2021\n\nHow Thailand handles COVID: it stokes fear among its critics\n\n\n\n\n\n\n\n\n\n\t\t\t\t\tCovid-19\t\t\t\t\n\n\n\n\nCovid-19 \n\n\n\t\t\t\tHow to apply for the Emergency Broadband Benefit in the U.S.\t\t\t\n\n13 Aug 2021\n\n\n\n\nPost\nHow to apply for the Emergency Broadband Benefit in the U.S.\n13 Aug 2021\n\nHow to apply for the Emergency Broadband Benefit in the U.S.\n\nDigital Rights In The Covid-19 Fight\n\n\n\nThe COVID-19 pandemic has impacted every part of our lives — including our human rights. Privacy, free expression, access to information, and other fundamental rights are even more essential in times of crisis, and Access Now is working to ensure responses to COVID-19 strengthen rather than undermine those rights.\n\n\n\n\n\n\n\n\n\n\n\n\nPRESS RELEASES\nProtocol for exclusion: why COVID-19 vaccine “passports” threaten human rights\nAs the global COVID-19 vaccine rollout gains momentum, governments are clamoring to implement measures to help the world return to pre-virus normality. This includes exploring digital vaccine certificates — or COVID-19 vaccine “passports”. Current proposals, however, threaten human rights.…\n\nLearn more\n\n\n\n\n\n\n\nHIGHLIGHTS\n\n\n\n\n\n\n\n\n\n\n\n\n\nCovid-19\n\n\n\t\t\t\n\t\t\t\tCivil society to WHO: let’s end government-ordered internet shutdowns\n\t\t\t\t\t\t\t\n\n\nToday the #KeepItOn coalition sent an open letter to the Deputy Director-General of the WHO, Dr. Zsuzsanna Jakab, calling on her to urge states to end the blatant and arbitrary internet shutdowns that are ongoing during COVID-19.\n\n\n\n\n\n\n\n\n\n\n\n\n\nCovid-19\n\n\n\t\t\t\n\t\t\t\tAccess Now releases recommendations on privacy and data protection in the fight against COVID-19\n\t\t\t\t\t\t\t\n\n\nOur message to governments is simple: protecting digital rights also promotes public health. We aim to ensure that the rule of law, and the rights to privacy and data protection, are protected throughout this crisis and in the future.\n\n\n\n\n\n\n\n\n\n\n\n\n\nCovid 19\n\n\n\t\t\t\n\t\t\t\tPrivacy and public health: the dos and don’ts for COVID-19 contact tracing apps\n\t\t\t\t\t\t\t\n\n\n\n\n\n\n\n\n\n\n\n\n\nContent Governance\n\n\n\t\t\t\n\t\t\t\tAccess Now releases “Fighting misinformation and defending free expression during COVID-19: recommendations for states”\n\t\t\t\t\t\t\t\n\n\nWe have identified practical examples and promising practices to support policy makers in respecting human rights while developing measures to address disinformation and misinformation during the COVID-19 crisis.\n\n\n\n\n\n\n\n\n\n\n\n\n     \n\n\n\n\n\nGrid View\nList View\n\n\n\n\n\n\n\n\n\n\n\n\n\n\t\t\t\t\tFreedom of Expression\t\t\t\t\n\n\n\n\nFreedom of Expression \n\n\n\t\t\t\tAccess Now oral statement to the UN Global Digital Compact Informal Consultations with Member States and Stakeholders\t\t\t\n\n3 Feb 2023\n • \nAccess Now’s Senior UN Advocacy Officer Laura O’Brien delivered an oral statement to the UN Global Digital Compact Informal Consultations with Member States and Stakeholders on Feb 3 2023.\n\n\n\n\nPublication\nAccess Now oral statement to the UN Global Digital Compact Informal Consultations with Member States and Stakeholders\n\n\n↗\n3 Feb 2023\n\nAccess Now oral statement to the UN Global Digital Compact Informal Consultations with Member States and Stakeholders\n\n\n\n\n\n\n\n\n\n\t\t\t\t\tInternet Shutdowns\t\t\t\t\n\n\n\n\nInternet Shutdowns \n\n\n\t\t\t\tዓፀቦ፣ ዓቕሊ ፅበትን ስቃይ: 15 ታሪኻት ከበባ ኢንተርነት ትግራይ\t\t\t\n\n25 Aug 2022\n\n\n\n\nPost\nዓፀቦ፣ ዓቕሊ ፅበትን ስቃይ: 15 ታሪኻት ከበባ ኢንተርነት ትግራይ\n25 Aug 2022\n\nዓፀቦ፣ ዓቕሊ ፅበትን ስቃይ: 15 ታሪኻት ከበባ ኢንተርነት ትግራይ\n\n\n\n\n\n\n\n\n\n\t\t\t\t\tInternet Shutdowns\t\t\t\t\n\n\n\n\nInternet Shutdowns \n\n\n\t\t\t\tStranded, suffocated, and in pain: 15 stories from Tigray’s internet siege\t\t\t\n\n28 Jul 2022\n • \nIt’s been two years since Tigray were cut off from the internet. Share the 15 stories from Tigrayans and help amplify their voices.\n\n\n\n\nPost\nStranded, suffocated, and in pain: 15 stories from Tigray’s internet siege\n28 Jul 2022\n\nStranded, suffocated, and in pain: 15 stories from Tigray’s internet siege\n\n\n\n\n\n\n\n\n\n\t\t\t\t\tContent Governance\t\t\t\t\n\n\n\n\nContent Governance \n\n\n\t\t\t\tJoin us June 6-10 for RightsCon 2022\t\t\t\n\n31 May 2022\n • \nLog in to the RightsCon platform to participate in the world’s leading summit on human rights in the digital age (June 6-10, 2022)!\n\n\n\n\nCampaign\nJoin us June 6-10 for RightsCon 2022\n\n\n↗\n31 May 2022\n\nJoin us June 6-10 for RightsCon 2022\n\n\n\n\n\n\n\n\n\n\t\t\t\t\tContent Governance\t\t\t\t\n\n\n\n\nContent Governance \n\n\n\t\t\t\tStop the misinformation experience: Spotify must intervene\t\t\t\n\n24 Feb 2022\n • \nThrough a letter to Daniel Ek, Co-Founder and CEO at Spotify, Access Now is urging the company to align with basic human rights principles.\n\n\n\n\nPress Release\nStop the misinformation experience: Spotify must intervene\n24 Feb 2022\n\nStop the misinformation experience: Spotify must intervene\n\n\n\n\n\n\n\n\n\n\t\t\t\t\tFreedom of Expression\t\t\t\t\n\n\n\n\nFreedom of Expression \n\n\n\t\t\t\tJoe Rogan and Spotify: Make content moderation about human rights\t\t\t\n\n10 Feb 2022\n • \nIs Spotify willing to allow harmful content like COVID misinformation to spread, prioritizing the companyʼs bottom line over public health?\n\n\n\n\nPost\nJoe Rogan and Spotify: Make content moderation about human rights\n10 Feb 2022\n\nJoe Rogan and Spotify: Make content moderation about human rights\n\n\n\n\n\n\n\n\n\n\t\t\t\t\tContent Governance\t\t\t\t\n\n\n\n\nContent Governance \n\n\n\t\t\t\tWhat is disinformation, why it spreads, and how to stop it\t\t\t\n\n21 Dec 2021\n • \nOur new report explores what disinformation is, and how lawmakers can address the harms it poses to democracy.\n\n\n\n\nPublication\nWhat is disinformation, why it spreads, and how to stop it\n21 Dec 2021\n\nWhat is disinformation, why it spreads, and how to stop it\n\n\n\n\n\n\n\n\n\n\t\t\t\t\tCovid-19\t\t\t\t\n\n\n\n\nCovid-19 \n\n\n\t\t\t\tOne Year Under COVID-19 Contact Tracing Apps: What Has Europe Learned? – A report by Access Now and Liberties\t\t\t\n\n28 Oct 2021\n • \nA year after the introduction of COVID-19 Contact Tracing Apps in Europe, Access Now and Liberties look at their impact on digital rights.\n\n\n\n\nPublication\nOne Year Under COVID-19 Contact Tracing Apps: What Has Europe Learned? – A report by Access Now and Liberties\n\n\n↗\n28 Oct 2021\n\nOne Year Under COVID-19 Contact Tracing Apps: What Has Europe Learned? – A report by Access Now and Liberties\n\n\n\n\n\n\n\n\n\n\t\t\t\t\tPrivacy\t\t\t\t\n\n\n\n\nPrivacy \n\n\n\t\t\t\tWhat you need to know about the Facebook Papers\t\t\t\n\n26 Oct 2021\n • \nThe Facebook Papers paint a grim picture of how Facebook has repeatedly and knowingly prioritized profit over people’s safety. Here’s a snapshot of what we know so far.\n\n\n\n\nPost\nWhat you need to know about the Facebook Papers\n26 Oct 2021\n\nWhat you need to know about the Facebook Papers\n\n\n\n\n\n\n\n\n\n\t\t\t\t\tNet Neutrality\t\t\t\t\n\n\n\n\nNet Neutrality \n\n\n\t\t\t\tDigital rights champions nominated to lead U.S. FCC and NTIA\t\t\t\n\n26 Oct 2021\n • \nAt long last, U.S. President Biden has nominated public interests advocates to lead the Federal Communications Commission and the National Telecommunications and Information Administration.\n\n\n\n\nPress Release\nDigital rights champions nominated to lead U.S. FCC and NTIA\n26 Oct 2021\n\nDigital rights champions nominated to lead U.S. FCC and NTIA\n\n\n\n\n\n\n\n\n\n\t\t\t\t\tContent Governance\t\t\t\t\n\n\n\n\nContent Governance \n\n\n\t\t\t\tWill the Right to Protest survive its migration online?\t\t\t\n\n20 Oct 2021\n • \nState-sanctioned internet shutdowns, increased surveillance, and unequal access to the internet are impacting communities globally. Will the Right to Protest survive its migration online?\n\n\n\n\nPost\nWill the Right to Protest survive its migration online?\n20 Oct 2021\n\nWill the Right to Protest survive its migration online?\n\n\n\n\n\n\n\n\n\n\t\t\t\t\tPrivacy\t\t\t\t\n\n\n\n\nPrivacy \n\n\n\t\t\t\tColombia’s mandatory CoronApp violates people’s privacy and freedom of movement\t\t\t\n\n23 Sep 2021\n\n\n\n\nPress Release\nColombia’s mandatory CoronApp violates people’s privacy and freedom of movement\n23 Sep 2021\n\nColombia’s mandatory CoronApp violates people’s privacy and freedom of movement\n\n\n\n\n\n\n\n\n\n\t\t\t\t\tPrivacy\t\t\t\t\n\n\n\n\nPrivacy \n\n\n\t\t\t\tColombia: CoronApp viola la privacidad y la libertad de movimiento de las personas\t\t\t\n\n23 Sep 2021\n\n\n\n\nPress Release\nColombia: CoronApp viola la privacidad y la libertad de movimiento de las personas\n23 Sep 2021\n\nColombia: CoronApp viola la privacidad y la libertad de movimiento de las personas\n\n\n\n\n\n\n\n\n\n\t\t\t\t\tFreedom of Expression\t\t\t\t\n\n\n\n\nFreedom of Expression \n\n\n\t\t\t\tThe internet shutdowns issue\t\t\t\n\n1 Sep 2021\n • \nWith support from the #KeepItOn coalition, Jigsaw is today publishing “The Current: The Internet Shutdowns Issue,” a deep-dive into internet shutdowns.\n\n\n\n\nPress Release\nThe internet shutdowns issue\n1 Sep 2021\n\nThe internet shutdowns issue\n\n\n\n\n\n\n\n\n\n\t\t\t\t\tFreedom of Expression\t\t\t\t\n\n\n\n\nFreedom of Expression \n\n\n\t\t\t\tHow Thailand handles COVID: it stokes fear among its critics\t\t\t\n\n24 Aug 2021\n • \nAmidst continuing protests, calls for political reform, and mass dissatisfaction with how Thailand handles COVID, Thailand’s government is doubling down on efforts to throttle dissent and protest online and off. It is relying on laws that it claims protect against “public fear.” In fact, by threatening to censor those who speak out, it is the government that is instigating fear – in a weak bid to distract from flailing governance. \n\n\n\n\nPost\nHow Thailand handles COVID: it stokes fear among its critics\n24 Aug 2021\n\nHow Thailand handles COVID: it stokes fear among its critics\n\n\n\n\n\n\n\n\n\n\t\t\t\t\tCovid-19\t\t\t\t\n\n\n\n\nCovid-19 \n\n\n\t\t\t\tHow to apply for the Emergency Broadband Benefit in the U.S.\t\t\t\n\n13 Aug 2021\n\n\n\n\nPost\nHow to apply for the Emergency Broadband Benefit in the U.S.\n13 Aug 2021\n\nHow to apply for the Emergency Broadband Benefit in the U.S.\n\nDigital Rights In The Covid-19 Fight\n\n\n\nThe COVID-19 pandemic has impacted every part of our lives — including our human rights. Privacy, free expression, access to information, and other fundamental rights are even more essential in times of crisis, and Access Now is working to ensure responses to COVID-19 strengthen rather than undermine those rights.\n\n\n\n\n\n\n\n\n\n\n\n\nPRESS RELEASES\nProtocol for exclusion: why COVID-19 vaccine “passports” threaten human rights\nAs the global COVID-19 vaccine rollout gains momentum, governments are clamoring to implement measures to help the world return to pre-virus normality. This includes exploring digital vaccine certificates — or COVID-19 vaccine “passports”. Current proposals, however, threaten human rights.…\n\nLearn more\n\n\n\n\n\n\n\nHIGHLIGHTS\n\n\n\n\n\n\n\n\n\n\n\n\n\nCovid-19\n\n\n\t\t\t\n\t\t\t\tCivil society to WHO: let’s end government-ordered internet shutdowns\n\t\t\t\t\t\t\t\n\n\nToday the #KeepItOn coalition sent an open letter to the Deputy Director-General of the WHO, Dr. Zsuzsanna Jakab, calling on her to urge states to end the blatant and arbitrary internet shutdowns that are ongoing during COVID-19.\n\n\n\n\n\n\n\n\n\n\n\n\n\nCovid-19\n\n\n\t\t\t\n\t\t\t\tAccess Now releases recommendations on privacy and data protection in the fight against COVID-19\n\t\t\t\t\t\t\t\n\n\nOur message to governments is simple: protecting digital rights also promotes public health. We aim to ensure that the rule of law, and the rights to privacy and data protection, are protected throughout this crisis and in the future.\n\n\n\n\n\n\n\n\n\n\n\n\n\nCovid 19\n\n\n\t\t\t\n\t\t\t\tPrivacy and public health: the dos and don’ts for COVID-19 contact tracing apps\n\t\t\t\t\t\t\t\n\n\n\n\n\n\n\n\n\n\n\n\n\nContent Governance\n\n\n\t\t\t\n\t\t\t\tAccess Now releases “Fighting misinformation and defending free expression during COVID-19: recommendations for states”\n\t\t\t\t\t\t\t\n\n\nWe have identified practical examples and promising practices to support policy makers in respecting human rights while developing measures to address disinformation and misinformation during the COVID-19 crisis.\n\n\n\n\n\n\n\n\n\n\n\n\n     \n\n\n\n\n\nGrid View\nList View\n\n\n\n\n\n\n\n\n\n\n\n\n\n\t\t\t\t\tFreedom of Expression\t\t\t\t\n\n\n\n\nFreedom of Expression \n\n\n\t\t\t\tAccess Now oral statement to the UN Global Digital Compact Informal Consultations with Member States and Stakeholders\t\t\t\n\n3 Feb 2023\n • \nAccess Now’s Senior UN Advocacy Officer Laura O’Brien delivered an oral statement to the UN Global Digital Compact Informal Consultations with Member States and Stakeholders on Feb 3 2023.\n\n\n\n\nPublication\nAccess Now oral statement to the UN Global Digital Compact Informal Consultations with Member States and Stakeholders\n\n\n↗\n3 Feb 2023\n\nAccess Now oral statement to the UN Global Digital Compact Informal Consultations with Member States and Stakeholders\n\n\n\n\n\n\n\n\n\n\t\t\t\t\tInternet Shutdowns\t\t\t\t\n\n\n\n\nInternet Shutdowns \n\n\n\t\t\t\tዓፀቦ፣ ዓቕሊ ፅበትን ስቃይ: 15 ታሪኻት ከበባ ኢንተርነት ትግራይ\t\t\t\n\n25 Aug 2022\n\n\n\n\nPost\nዓፀቦ፣ ዓቕሊ ፅበትን ስቃይ: 15 ታሪኻት ከበባ ኢንተርነት ትግራይ\n25 Aug 2022\n\nዓፀቦ፣ ዓቕሊ ፅበትን ስቃይ: 15 ታሪኻት ከበባ ኢንተርነት ትግራይ\n\n\n\n\n\n\n\n\n\n\t\t\t\t\tInternet Shutdowns\t\t\t\t\n\n\n\n\nInternet Shutdowns \n\n\n\t\t\t\tStranded, suffocated, and in pain: 15 stories from Tigray’s internet siege\t\t\t\n\n28 Jul 2022\n • \nIt’s been two years since Tigray were cut off from the internet. Share the 15 stories from Tigrayans and help amplify their voices.\n\n\n\n\nPost\nStranded, suffocated, and in pain: 15 stories from Tigray’s internet siege\n28 Jul 2022\n\nStranded, suffocated, and in pain: 15 stories from Tigray’s internet siege\n\n\n\n\n\n\n\n\n\n\t\t\t\t\tContent Governance\t\t\t\t\n\n\n\n\nContent Governance \n\n\n\t\t\t\tJoin us June 6-10 for RightsCon 2022\t\t\t\n\n31 May 2022\n • \nLog in to the RightsCon platform to participate in the world’s leading summit on human rights in the digital age (June 6-10, 2022)!\n\n\n\n\nCampaign\nJoin us June 6-10 for RightsCon 2022\n\n\n↗\n31 May 2022\n\nJoin us June 6-10 for RightsCon 2022\n\n\n\n\n\n\n\n\n\n\t\t\t\t\tContent Governance\t\t\t\t\n\n\n\n\nContent Governance \n\n\n\t\t\t\tStop the misinformation experience: Spotify must intervene\t\t\t\n\n24 Feb 2022\n • \nThrough a letter to Daniel Ek, Co-Founder and CEO at Spotify, Access Now is urging the company to align with basic human rights principles.\n\n\n\n\nPress Release\nStop the misinformation experience: Spotify must intervene\n24 Feb 2022\n\nStop the misinformation experience: Spotify must intervene\n\n\n\n\n\n\n\n\n\n\t\t\t\t\tFreedom of Expression\t\t\t\t\n\n\n\n\nFreedom of Expression \n\n\n\t\t\t\tJoe Rogan and Spotify: Make content moderation about human rights\t\t\t\n\n10 Feb 2022\n • \nIs Spotify willing to allow harmful content like COVID misinformation to spread, prioritizing the companyʼs bottom line over public health?\n\n\n\n\nPost\nJoe Rogan and Spotify: Make content moderation about human rights\n10 Feb 2022\n\nJoe Rogan and Spotify: Make content moderation about human rights\n\n\n\n\n\n\n\n\n\n\t\t\t\t\tContent Governance\t\t\t\t\n\n\n\n\nContent Governance \n\n\n\t\t\t\tWhat is disinformation, why it spreads, and how to stop it\t\t\t\n\n21 Dec 2021\n • \nOur new report explores what disinformation is, and how lawmakers can address the harms it poses to democracy.\n\n\n\n\nPublication\nWhat is disinformation, why it spreads, and how to stop it\n21 Dec 2021\n\nWhat is disinformation, why it spreads, and how to stop it\n\n\n\n\n\n\n\n\n\n\t\t\t\t\tCovid-19\t\t\t\t\n\n\n\n\nCovid-19 \n\n\n\t\t\t\tOne Year Under COVID-19 Contact Tracing Apps: What Has Europe Learned? – A report by Access Now and Liberties\t\t\t\n\n28 Oct 2021\n • \nA year after the introduction of COVID-19 Contact Tracing Apps in Europe, Access Now and Liberties look at their impact on digital rights.\n\n\n\n\nPublication\nOne Year Under COVID-19 Contact Tracing Apps: What Has Europe Learned? – A report by Access Now and Liberties\n\n\n↗\n28 Oct 2021\n\nOne Year Under COVID-19 Contact Tracing Apps: What Has Europe Learned? – A report by Access Now and Liberties\n\n\n\n\n\n\n\n\n\n\t\t\t\t\tPrivacy\t\t\t\t\n\n\n\n\nPrivacy \n\n\n\t\t\t\tWhat you need to know about the Facebook Papers\t\t\t\n\n26 Oct 2021\n • \nThe Facebook Papers paint a grim picture of how Facebook has repeatedly and knowingly prioritized profit over people’s safety. Here’s a snapshot of what we know so far.\n\n\n\n\nPost\nWhat you need to know about the Facebook Papers\n26 Oct 2021\n\nWhat you need to know about the Facebook Papers\n\n\n\n\n\n\n\n\n\n\t\t\t\t\tNet Neutrality\t\t\t\t\n\n\n\n\nNet Neutrality \n\n\n\t\t\t\tDigital rights champions nominated to lead U.S. FCC and NTIA\t\t\t\n\n26 Oct 2021\n • \nAt long last, U.S. President Biden has nominated public interests advocates to lead the Federal Communications Commission and the National Telecommunications and Information Administration.\n\n\n\n\nPress Release\nDigital rights champions nominated to lead U.S. FCC and NTIA\n26 Oct 2021\n\nDigital rights champions nominated to lead U.S. FCC and NTIA\n\n\n\n\n\n\n\n\n\n\t\t\t\t\tContent Governance\t\t\t\t\n\n\n\n\nContent Governance \n\n\n\t\t\t\tWill the Right to Protest survive its migration online?\t\t\t\n\n20 Oct 2021\n • \nState-sanctioned internet shutdowns, increased surveillance, and unequal access to the internet are impacting communities globally. Will the Right to Protest survive its migration online?\n\n\n\n\nPost\nWill the Right to Protest survive its migration online?\n20 Oct 2021\n\nWill the Right to Protest survive its migration online?\n\n\n\n\n\n\n\n\n\n\t\t\t\t\tPrivacy\t\t\t\t\n\n\n\n\nPrivacy \n\n\n\t\t\t\tColombia’s mandatory CoronApp violates people’s privacy and freedom of movement\t\t\t\n\n23 Sep 2021\n\n\n\n\nPress Release\nColombia’s mandatory CoronApp violates people’s privacy and freedom of movement\n23 Sep 2021\n\nColombia’s mandatory CoronApp violates people’s privacy and freedom of movement\n\n\n\n\n\n\n\n\n\n\t\t\t\t\tPrivacy\t\t\t\t\n\n\n\n\nPrivacy \n\n\n\t\t\t\tColombia: CoronApp viola la privacidad y la libertad de movimiento de las personas\t\t\t\n\n23 Sep 2021\n\n\n\n\nPress Release\nColombia: CoronApp viola la privacidad y la libertad de movimiento de las personas\n23 Sep 2021\n\nColombia: CoronApp viola la privacidad y la libertad de movimiento de las personas\n\n\n\n\n\n\n\n\n\n\t\t\t\t\tFreedom of Expression\t\t\t\t\n\n\n\n\nFreedom of Expression \n\n\n\t\t\t\tThe internet shutdowns issue\t\t\t\n\n1 Sep 2021\n • \nWith support from the #KeepItOn coalition, Jigsaw is today publishing “The Current: The Internet Shutdowns Issue,” a deep-dive into internet shutdowns.\n\n\n\n\nPress Release\nThe internet shutdowns issue\n1 Sep 2021\n\nThe internet shutdowns issue\n\n\n\n\n\n\n\n\n\n\t\t\t\t\tFreedom of Expression\t\t\t\t\n\n\n\n\nFreedom of Expression \n\n\n\t\t\t\tHow Thailand handles COVID: it stokes fear among its critics\t\t\t\n\n24 Aug 2021\n • \nAmidst continuing protests, calls for political reform, and mass dissatisfaction with how Thailand handles COVID, Thailand’s government is doubling down on efforts to throttle dissent and protest online and off. It is relying on laws that it claims protect against “public fear.” In fact, by threatening to censor those who speak out, it is the government that is instigating fear – in a weak bid to distract from flailing governance. \n\n\n\n\nPost\nHow Thailand handles COVID: it stokes fear among its critics\n24 Aug 2021\n\nHow Thailand handles COVID: it stokes fear among its critics\n\n\n\n\n\n\n\n\n\n\t\t\t\t\tCovid-19\t\t\t\t\n\n\n\n\nCovid-19 \n\n\n\t\t\t\tHow to apply for the Emergency Broadband Benefit in the U.S.\t\t\t\n\n13 Aug 2021\n\n\n\n\nPost\nHow to apply for the Emergency Broadband Benefit in the U.S.\n13 Aug 2021\n\nHow to apply for the Emergency Broadband Benefit in the U.S.\n\nDigital Rights In The Covid-19 Fight\n\nDigital Rights In The Covid-19 Fight\n\nThe COVID-19 pandemic has impacted every part of our lives — including our human rights. Privacy, free expression, access to information, and other fundamental rights are even more essential in times of crisis, and Access Now is working to ensure responses to COVID-19 strengthen rather than undermine those rights.\n\nThe COVID-19 pandemic has impacted every part of our lives — including our human rights. Privacy, free expression, access to information, and other fundamental rights are even more essential in times of crisis, and Access Now is working to ensure responses to COVID-19 strengthen rather than undermine those rights.\n\nThe COVID-19 pandemic has impacted every part of our lives — including our human rights. Privacy, free expression, access to information, and other fundamental rights are even more essential in times of crisis, and Access Now is working to ensure responses to COVID-19 strengthen rather than undermine those rights.\n\nPRESS RELEASES\nProtocol for exclusion: why COVID-19 vaccine “passports” threaten human rights\nAs the global COVID-19 vaccine rollout gains momentum, governments are clamoring to implement measures to help the world return to pre-virus normality. This includes exploring digital vaccine certificates — or COVID-19 vaccine “passports”. Current proposals, however, threaten human rights.…\n\nLearn more\n\nPRESS RELEASES\nProtocol for exclusion: why COVID-19 vaccine “passports” threaten human rights\nAs the global COVID-19 vaccine rollout gains momentum, governments are clamoring to implement measures to help the world return to pre-virus normality. This includes exploring digital vaccine certificates — or COVID-19 vaccine “passports”. Current proposals, however, threaten human rights.…\n\nLearn more\n\nPRESS RELEASES\nProtocol for exclusion: why COVID-19 vaccine “passports” threaten human rights\nAs the global COVID-19 vaccine rollout gains momentum, governments are clamoring to implement measures to help the world return to pre-virus normality. This includes exploring digital vaccine certificates — or COVID-19 vaccine “passports”. Current proposals, however, threaten human rights.…\n\nLearn more\n\nAs the global COVID-19 vaccine rollout gains momentum, governments are clamoring to implement measures to help the world return to pre-virus normality. This includes exploring digital vaccine certificates — or COVID-19 vaccine “passports”. Current proposals, however, threaten human rights.…\n\nLearn more\n\nLearn more\n\nHIGHLIGHTS\n\n\n\n\n\n\n\n\n\n\n\n\n\nCovid-19\n\n\n\t\t\t\n\t\t\t\tCivil society to WHO: let’s end government-ordered internet shutdowns\n\t\t\t\t\t\t\t\n\n\nToday the #KeepItOn coalition sent an open letter to the Deputy Director-General of the WHO, Dr. Zsuzsanna Jakab, calling on her to urge states to end the blatant and arbitrary internet shutdowns that are ongoing during COVID-19.\n\n\n\n\n\n\n\n\n\n\n\n\n\nCovid-19\n\n\n\t\t\t\n\t\t\t\tAccess Now releases recommendations on privacy and data protection in the fight against COVID-19\n\t\t\t\t\t\t\t\n\n\nOur message to governments is simple: protecting digital rights also promotes public health. We aim to ensure that the rule of law, and the rights to privacy and data protection, are protected throughout this crisis and in the future.\n\n\n\n\n\n\n\n\n\n\n\n\n\nCovid 19\n\n\n\t\t\t\n\t\t\t\tPrivacy and public health: the dos and don’ts for COVID-19 contact tracing apps\n\t\t\t\t\t\t\t\n\n\n\n\n\n\n\n\n\n\n\n\n\nContent Governance\n\n\n\t\t\t\n\t\t\t\tAccess Now releases “Fighting misinformation and defending free expression during COVID-19: recommendations for states”\n\t\t\t\t\t\t\t\n\n\nWe have identified practical examples and promising practices to support policy makers in respecting human rights while developing measures to address disinformation and misinformation during the COVID-19 crisis.\n\n\n\n\n\n\n\n\n\n\n\n\n     \n\n\n\n\n\nGrid View\nList View\n\n\n\n\n\n\n\n\n\n\n\n\n\n\t\t\t\t\tFreedom of Expression\t\t\t\t\n\n\n\n\nFreedom of Expression \n\n\n\t\t\t\tAccess Now oral statement to the UN Global Digital Compact Informal Consultations with Member States and Stakeholders\t\t\t\n\n3 Feb 2023\n • \nAccess Now’s Senior UN Advocacy Officer Laura O’Brien delivered an oral statement to the UN Global Digital Compact Informal Consultations with Member States and Stakeholders on Feb 3 2023.\n\n\n\n\nPublication\nAccess Now oral statement to the UN Global Digital Compact Informal Consultations with Member States and Stakeholders\n\n\n↗\n3 Feb 2023\n\nAccess Now oral statement to the UN Global Digital Compact Informal Consultations with Member States and Stakeholders\n\n\n\n\n\n\n\n\n\n\t\t\t\t\tInternet Shutdowns\t\t\t\t\n\n\n\n\nInternet Shutdowns \n\n\n\t\t\t\tዓፀቦ፣ ዓቕሊ ፅበትን ስቃይ: 15 ታሪኻት ከበባ ኢንተርነት ትግራይ\t\t\t\n\n25 Aug 2022\n\n\n\n\nPost\nዓፀቦ፣ ዓቕሊ ፅበትን ስቃይ: 15 ታሪኻት ከበባ ኢንተርነት ትግራይ\n25 Aug 2022\n\nዓፀቦ፣ ዓቕሊ ፅበትን ስቃይ: 15 ታሪኻት ከበባ ኢንተርነት ትግራይ\n\n\n\n\n\n\n\n\n\n\t\t\t\t\tInternet Shutdowns\t\t\t\t\n\n\n\n\nInternet Shutdowns \n\n\n\t\t\t\tStranded, suffocated, and in pain: 15 stories from Tigray’s internet siege\t\t\t\n\n28 Jul 2022\n • \nIt’s been two years since Tigray were cut off from the internet. Share the 15 stories from Tigrayans and help amplify their voices.\n\n\n\n\nPost\nStranded, suffocated, and in pain: 15 stories from Tigray’s internet siege\n28 Jul 2022\n\nStranded, suffocated, and in pain: 15 stories from Tigray’s internet siege\n\n\n\n\n\n\n\n\n\n\t\t\t\t\tContent Governance\t\t\t\t\n\n\n\n\nContent Governance \n\n\n\t\t\t\tJoin us June 6-10 for RightsCon 2022\t\t\t\n\n31 May 2022\n • \nLog in to the RightsCon platform to participate in the world’s leading summit on human rights in the digital age (June 6-10, 2022)!\n\n\n\n\nCampaign\nJoin us June 6-10 for RightsCon 2022\n\n\n↗\n31 May 2022\n\nJoin us June 6-10 for RightsCon 2022\n\n\n\n\n\n\n\n\n\n\t\t\t\t\tContent Governance\t\t\t\t\n\n\n\n\nContent Governance \n\n\n\t\t\t\tStop the misinformation experience: Spotify must intervene\t\t\t\n\n24 Feb 2022\n • \nThrough a letter to Daniel Ek, Co-Founder and CEO at Spotify, Access Now is urging the company to align with basic human rights principles.\n\n\n\n\nPress Release\nStop the misinformation experience: Spotify must intervene\n24 Feb 2022\n\nStop the misinformation experience: Spotify must intervene\n\n\n\n\n\n\n\n\n\n\t\t\t\t\tFreedom of Expression\t\t\t\t\n\n\n\n\nFreedom of Expression \n\n\n\t\t\t\tJoe Rogan and Spotify: Make content moderation about human rights\t\t\t\n\n10 Feb 2022\n • \nIs Spotify willing to allow harmful content like COVID misinformation to spread, prioritizing the companyʼs bottom line over public health?\n\n\n\n\nPost\nJoe Rogan and Spotify: Make content moderation about human rights\n10 Feb 2022\n\nJoe Rogan and Spotify: Make content moderation about human rights\n\n\n\n\n\n\n\n\n\n\t\t\t\t\tContent Governance\t\t\t\t\n\n\n\n\nContent Governance \n\n\n\t\t\t\tWhat is disinformation, why it spreads, and how to stop it\t\t\t\n\n21 Dec 2021\n • \nOur new report explores what disinformation is, and how lawmakers can address the harms it poses to democracy.\n\n\n\n\nPublication\nWhat is disinformation, why it spreads, and how to stop it\n21 Dec 2021\n\nWhat is disinformation, why it spreads, and how to stop it\n\n\n\n\n\n\n\n\n\n\t\t\t\t\tCovid-19\t\t\t\t\n\n\n\n\nCovid-19 \n\n\n\t\t\t\tOne Year Under COVID-19 Contact Tracing Apps: What Has Europe Learned? – A report by Access Now and Liberties\t\t\t\n\n28 Oct 2021\n • \nA year after the introduction of COVID-19 Contact Tracing Apps in Europe, Access Now and Liberties look at their impact on digital rights.\n\n\n\n\nPublication\nOne Year Under COVID-19 Contact Tracing Apps: What Has Europe Learned? – A report by Access Now and Liberties\n\n\n↗\n28 Oct 2021\n\nOne Year Under COVID-19 Contact Tracing Apps: What Has Europe Learned? – A report by Access Now and Liberties\n\n\n\n\n\n\n\n\n\n\t\t\t\t\tPrivacy\t\t\t\t\n\n\n\n\nPrivacy \n\n\n\t\t\t\tWhat you need to know about the Facebook Papers\t\t\t\n\n26 Oct 2021\n • \nThe Facebook Papers paint a grim picture of how Facebook has repeatedly and knowingly prioritized profit over people’s safety. Here’s a snapshot of what we know so far.\n\n\n\n\nPost\nWhat you need to know about the Facebook Papers\n26 Oct 2021\n\nWhat you need to know about the Facebook Papers\n\n\n\n\n\n\n\n\n\n\t\t\t\t\tNet Neutrality\t\t\t\t\n\n\n\n\nNet Neutrality \n\n\n\t\t\t\tDigital rights champions nominated to lead U.S. FCC and NTIA\t\t\t\n\n26 Oct 2021\n • \nAt long last, U.S. President Biden has nominated public interests advocates to lead the Federal Communications Commission and the National Telecommunications and Information Administration.\n\n\n\n\nPress Release\nDigital rights champions nominated to lead U.S. FCC and NTIA\n26 Oct 2021\n\nDigital rights champions nominated to lead U.S. FCC and NTIA\n\n\n\n\n\n\n\n\n\n\t\t\t\t\tContent Governance\t\t\t\t\n\n\n\n\nContent Governance \n\n\n\t\t\t\tWill the Right to Protest survive its migration online?\t\t\t\n\n20 Oct 2021\n • \nState-sanctioned internet shutdowns, increased surveillance, and unequal access to the internet are impacting communities globally. Will the Right to Protest survive its migration online?\n\n\n\n\nPost\nWill the Right to Protest survive its migration online?\n20 Oct 2021\n\nWill the Right to Protest survive its migration online?\n\n\n\n\n\n\n\n\n\n\t\t\t\t\tPrivacy\t\t\t\t\n\n\n\n\nPrivacy \n\n\n\t\t\t\tColombia’s mandatory CoronApp violates people’s privacy and freedom of movement\t\t\t\n\n23 Sep 2021\n\n\n\n\nPress Release\nColombia’s mandatory CoronApp violates people’s privacy and freedom of movement\n23 Sep 2021\n\nColombia’s mandatory CoronApp violates people’s privacy and freedom of movement\n\n\n\n\n\n\n\n\n\n\t\t\t\t\tPrivacy\t\t\t\t\n\n\n\n\nPrivacy \n\n\n\t\t\t\tColombia: CoronApp viola la privacidad y la libertad de movimiento de las personas\t\t\t\n\n23 Sep 2021\n\n\n\n\nPress Release\nColombia: CoronApp viola la privacidad y la libertad de movimiento de las personas\n23 Sep 2021\n\nColombia: CoronApp viola la privacidad y la libertad de movimiento de las personas\n\n\n\n\n\n\n\n\n\n\t\t\t\t\tFreedom of Expression\t\t\t\t\n\n\n\n\nFreedom of Expression \n\n\n\t\t\t\tThe internet shutdowns issue\t\t\t\n\n1 Sep 2021\n • \nWith support from the #KeepItOn coalition, Jigsaw is today publishing “The Current: The Internet Shutdowns Issue,” a deep-dive into internet shutdowns.\n\n\n\n\nPress Release\nThe internet shutdowns issue\n1 Sep 2021\n\nThe internet shutdowns issue\n\n\n\n\n\n\n\n\n\n\t\t\t\t\tFreedom of Expression\t\t\t\t\n\n\n\n\nFreedom of Expression \n\n\n\t\t\t\tHow Thailand handles COVID: it stokes fear among its critics\t\t\t\n\n24 Aug 2021\n • \nAmidst continuing protests, calls for political reform, and mass dissatisfaction with how Thailand handles COVID, Thailand’s government is doubling down on efforts to throttle dissent and protest online and off. It is relying on laws that it claims protect against “public fear.” In fact, by threatening to censor those who speak out, it is the government that is instigating fear – in a weak bid to distract from flailing governance. \n\n\n\n\nPost\nHow Thailand handles COVID: it stokes fear among its critics\n24 Aug 2021\n\nHow Thailand handles COVID: it stokes fear among its critics\n\n\n\n\n\n\n\n\n\n\t\t\t\t\tCovid-19\t\t\t\t\n\n\n\n\nCovid-19 \n\n\n\t\t\t\tHow to apply for the Emergency Broadband Benefit in the U.S.\t\t\t\n\n13 Aug 2021\n\n\n\n\nPost\nHow to apply for the Emergency Broadband Benefit in the U.S.\n13 Aug 2021\n\nHow to apply for the Emergency Broadband Benefit in the U.S.\n\nHIGHLIGHTS\n\n\n\n\n\n\n\n\n\n\n\n\n\nCovid-19\n\n\n\t\t\t\n\t\t\t\tCivil society to WHO: let’s end government-ordered internet shutdowns\n\t\t\t\t\t\t\t\n\n\nToday the #KeepItOn coalition sent an open letter to the Deputy Director-General of the WHO, Dr. Zsuzsanna Jakab, calling on her to urge states to end the blatant and arbitrary internet shutdowns that are ongoing during COVID-19.\n\n\n\n\n\n\n\n\n\n\n\n\n\nCovid-19\n\n\n\t\t\t\n\t\t\t\tAccess Now releases recommendations on privacy and data protection in the fight against COVID-19\n\t\t\t\t\t\t\t\n\n\nOur message to governments is simple: protecting digital rights also promotes public health. We aim to ensure that the rule of law, and the rights to privacy and data protection, are protected throughout this crisis and in the future.\n\n\n\n\n\n\n\n\n\n\n\n\n\nCovid 19\n\n\n\t\t\t\n\t\t\t\tPrivacy and public health: the dos and don’ts for COVID-19 contact tracing apps\n\t\t\t\t\t\t\t\n\n\n\n\n\n\n\n\n\n\n\n\n\nContent Governance\n\n\n\t\t\t\n\t\t\t\tAccess Now releases “Fighting misinformation and defending free expression during COVID-19: recommendations for states”\n\t\t\t\t\t\t\t\n\n\nWe have identified practical examples and promising practices to support policy makers in respecting human rights while developing measures to address disinformation and misinformation during the COVID-19 crisis.\n\n\n\n\n\n\n\n\n\n\n\n\n     \n\n\n\n\n\nGrid View\nList View\n\n\n\n\n\n\n\n\n\n\n\n\n\n\t\t\t\t\tFreedom of Expression\t\t\t\t\n\n\n\n\nFreedom of Expression \n\n\n\t\t\t\tAccess Now oral statement to the UN Global Digital Compact Informal Consultations with Member States and Stakeholders\t\t\t\n\n3 Feb 2023\n • \nAccess Now’s Senior UN Advocacy Officer Laura O’Brien delivered an oral statement to the UN Global Digital Compact Informal Consultations with Member States and Stakeholders on Feb 3 2023.\n\n\n\n\nPublication\nAccess Now oral statement to the UN Global Digital Compact Informal Consultations with Member States and Stakeholders\n\n\n↗\n3 Feb 2023\n\nAccess Now oral statement to the UN Global Digital Compact Informal Consultations with Member States and Stakeholders\n\n\n\n\n\n\n\n\n\n\t\t\t\t\tInternet Shutdowns\t\t\t\t\n\n\n\n\nInternet Shutdowns \n\n\n\t\t\t\tዓፀቦ፣ ዓቕሊ ፅበትን ስቃይ: 15 ታሪኻት ከበባ ኢንተርነት ትግራይ\t\t\t\n\n25 Aug 2022\n\n\n\n\nPost\nዓፀቦ፣ ዓቕሊ ፅበትን ስቃይ: 15 ታሪኻት ከበባ ኢንተርነት ትግራይ\n25 Aug 2022\n\nዓፀቦ፣ ዓቕሊ ፅበትን ስቃይ: 15 ታሪኻት ከበባ ኢንተርነት ትግራይ\n\n\n\n\n\n\n\n\n\n\t\t\t\t\tInternet Shutdowns\t\t\t\t\n\n\n\n\nInternet Shutdowns \n\n\n\t\t\t\tStranded, suffocated, and in pain: 15 stories from Tigray’s internet siege\t\t\t\n\n28 Jul 2022\n • \nIt’s been two years since Tigray were cut off from the internet. Share the 15 stories from Tigrayans and help amplify their voices.\n\n\n\n\nPost\nStranded, suffocated, and in pain: 15 stories from Tigray’s internet siege\n28 Jul 2022\n\nStranded, suffocated, and in pain: 15 stories from Tigray’s internet siege\n\n\n\n\n\n\n\n\n\n\t\t\t\t\tContent Governance\t\t\t\t\n\n\n\n\nContent Governance \n\n\n\t\t\t\tJoin us June 6-10 for RightsCon 2022\t\t\t\n\n31 May 2022\n • \nLog in to the RightsCon platform to participate in the world’s leading summit on human rights in the digital age (June 6-10, 2022)!\n\n\n\n\nCampaign\nJoin us June 6-10 for RightsCon 2022\n\n\n↗\n31 May 2022\n\nJoin us June 6-10 for RightsCon 2022\n\n\n\n\n\n\n\n\n\n\t\t\t\t\tContent Governance\t\t\t\t\n\n\n\n\nContent Governance \n\n\n\t\t\t\tStop the misinformation experience: Spotify must intervene\t\t\t\n\n24 Feb 2022\n • \nThrough a letter to Daniel Ek, Co-Founder and CEO at Spotify, Access Now is urging the company to align with basic human rights principles.\n\n\n\n\nPress Release\nStop the misinformation experience: Spotify must intervene\n24 Feb 2022\n\nStop the misinformation experience: Spotify must intervene\n\n\n\n\n\n\n\n\n\n\t\t\t\t\tFreedom of Expression\t\t\t\t\n\n\n\n\nFreedom of Expression \n\n\n\t\t\t\tJoe Rogan and Spotify: Make content moderation about human rights\t\t\t\n\n10 Feb 2022\n • \nIs Spotify willing to allow harmful content like COVID misinformation to spread, prioritizing the companyʼs bottom line over public health?\n\n\n\n\nPost\nJoe Rogan and Spotify: Make content moderation about human rights\n10 Feb 2022\n\nJoe Rogan and Spotify: Make content moderation about human rights\n\n\n\n\n\n\n\n\n\n\t\t\t\t\tContent Governance\t\t\t\t\n\n\n\n\nContent Governance \n\n\n\t\t\t\tWhat is disinformation, why it spreads, and how to stop it\t\t\t\n\n21 Dec 2021\n • \nOur new report explores what disinformation is, and how lawmakers can address the harms it poses to democracy.\n\n\n\n\nPublication\nWhat is disinformation, why it spreads, and how to stop it\n21 Dec 2021\n\nWhat is disinformation, why it spreads, and how to stop it\n\n\n\n\n\n\n\n\n\n\t\t\t\t\tCovid-19\t\t\t\t\n\n\n\n\nCovid-19 \n\n\n\t\t\t\tOne Year Under COVID-19 Contact Tracing Apps: What Has Europe Learned? – A report by Access Now and Liberties\t\t\t\n\n28 Oct 2021\n • \nA year after the introduction of COVID-19 Contact Tracing Apps in Europe, Access Now and Liberties look at their impact on digital rights.\n\n\n\n\nPublication\nOne Year Under COVID-19 Contact Tracing Apps: What Has Europe Learned? – A report by Access Now and Liberties\n\n\n↗\n28 Oct 2021\n\nOne Year Under COVID-19 Contact Tracing Apps: What Has Europe Learned? – A report by Access Now and Liberties\n\n\n\n\n\n\n\n\n\n\t\t\t\t\tPrivacy\t\t\t\t\n\n\n\n\nPrivacy \n\n\n\t\t\t\tWhat you need to know about the Facebook Papers\t\t\t\n\n26 Oct 2021\n • \nThe Facebook Papers paint a grim picture of how Facebook has repeatedly and knowingly prioritized profit over people’s safety. Here’s a snapshot of what we know so far.\n\n\n\n\nPost\nWhat you need to know about the Facebook Papers\n26 Oct 2021\n\nWhat you need to know about the Facebook Papers\n\n\n\n\n\n\n\n\n\n\t\t\t\t\tNet Neutrality\t\t\t\t\n\n\n\n\nNet Neutrality \n\n\n\t\t\t\tDigital rights champions nominated to lead U.S. FCC and NTIA\t\t\t\n\n26 Oct 2021\n • \nAt long last, U.S. President Biden has nominated public interests advocates to lead the Federal Communications Commission and the National Telecommunications and Information Administration.\n\n\n\n\nPress Release\nDigital rights champions nominated to lead U.S. FCC and NTIA\n26 Oct 2021\n\nDigital rights champions nominated to lead U.S. FCC and NTIA\n\n\n\n\n\n\n\n\n\n\t\t\t\t\tContent Governance\t\t\t\t\n\n\n\n\nContent Governance \n\n\n\t\t\t\tWill the Right to Protest survive its migration online?\t\t\t\n\n20 Oct 2021\n • \nState-sanctioned internet shutdowns, increased surveillance, and unequal access to the internet are impacting communities globally. Will the Right to Protest survive its migration online?\n\n\n\n\nPost\nWill the Right to Protest survive its migration online?\n20 Oct 2021\n\nWill the Right to Protest survive its migration online?\n\n\n\n\n\n\n\n\n\n\t\t\t\t\tPrivacy\t\t\t\t\n\n\n\n\nPrivacy \n\n\n\t\t\t\tColombia’s mandatory CoronApp violates people’s privacy and freedom of movement\t\t\t\n\n23 Sep 2021\n\n\n\n\nPress Release\nColombia’s mandatory CoronApp violates people’s privacy and freedom of movement\n23 Sep 2021\n\nColombia’s mandatory CoronApp violates people’s privacy and freedom of movement\n\n\n\n\n\n\n\n\n\n\t\t\t\t\tPrivacy\t\t\t\t\n\n\n\n\nPrivacy \n\n\n\t\t\t\tColombia: CoronApp viola la privacidad y la libertad de movimiento de las personas\t\t\t\n\n23 Sep 2021\n\n\n\n\nPress Release\nColombia: CoronApp viola la privacidad y la libertad de movimiento de las personas\n23 Sep 2021\n\nColombia: CoronApp viola la privacidad y la libertad de movimiento de las personas\n\n\n\n\n\n\n\n\n\n\t\t\t\t\tFreedom of Expression\t\t\t\t\n\n\n\n\nFreedom of Expression \n\n\n\t\t\t\tThe internet shutdowns issue\t\t\t\n\n1 Sep 2021\n • \nWith support from the #KeepItOn coalition, Jigsaw is today publishing “The Current: The Internet Shutdowns Issue,” a deep-dive into internet shutdowns.\n\n\n\n\nPress Release\nThe internet shutdowns issue\n1 Sep 2021\n\nThe internet shutdowns issue\n\n\n\n\n\n\n\n\n\n\t\t\t\t\tFreedom of Expression\t\t\t\t\n\n\n\n\nFreedom of Expression \n\n\n\t\t\t\tHow Thailand handles COVID: it stokes fear among its critics\t\t\t\n\n24 Aug 2021\n • \nAmidst continuing protests, calls for political reform, and mass dissatisfaction with how Thailand handles COVID, Thailand’s government is doubling down on efforts to throttle dissent and protest online and off. It is relying on laws that it claims protect against “public fear.” In fact, by threatening to censor those who speak out, it is the government that is instigating fear – in a weak bid to distract from flailing governance. \n\n\n\n\nPost\nHow Thailand handles COVID: it stokes fear among its critics\n24 Aug 2021\n\nHow Thailand handles COVID: it stokes fear among its critics\n\n\n\n\n\n\n\n\n\n\t\t\t\t\tCovid-19\t\t\t\t\n\n\n\n\nCovid-19 \n\n\n\t\t\t\tHow to apply for the Emergency Broadband Benefit in the U.S.\t\t\t\n\n13 Aug 2021\n\n\n\n\nPost\nHow to apply for the Emergency Broadband Benefit in the U.S.\n13 Aug 2021\n\nHow to apply for the Emergency Broadband Benefit in the U.S.\n\nHIGHLIGHTS\n\n\n\n\n\n\n\n\n\n\n\n\n\nCovid-19\n\n\n\t\t\t\n\t\t\t\tCivil society to WHO: let’s end government-ordered internet shutdowns\n\t\t\t\t\t\t\t\n\n\nToday the #KeepItOn coalition sent an open letter to the Deputy Director-General of the WHO, Dr. Zsuzsanna Jakab, calling on her to urge states to end the blatant and arbitrary internet shutdowns that are ongoing during COVID-19.\n\n\n\n\n\n\n\n\n\n\n\n\n\nCovid-19\n\n\n\t\t\t\n\t\t\t\tAccess Now releases recommendations on privacy and data protection in the fight against COVID-19\n\t\t\t\t\t\t\t\n\n\nOur message to governments is simple: protecting digital rights also promotes public health. We aim to ensure that the rule of law, and the rights to privacy and data protection, are protected throughout this crisis and in the future.\n\n\n\n\n\n\n\n\n\n\n\n\n\nCovid 19\n\n\n\t\t\t\n\t\t\t\tPrivacy and public health: the dos and don’ts for COVID-19 contact tracing apps\n\t\t\t\t\t\t\t\n\n\n\n\n\n\n\n\n\n\n\n\n\nContent Governance\n\n\n\t\t\t\n\t\t\t\tAccess Now releases “Fighting misinformation and defending free expression during COVID-19: recommendations for states”\n\t\t\t\t\t\t\t\n\n\nWe have identified practical examples and promising practices to support policy makers in respecting human rights while developing measures to address disinformation and misinformation during the COVID-19 crisis.\n\n\n\n\n\n\n\n\n\n\n\n\n     \n\n\n\n\n\nGrid View\nList View\n\n\n\n\n\n\n\n\n\n\n\n\n\n\t\t\t\t\tFreedom of Expression\t\t\t\t\n\n\n\n\nFreedom of Expression \n\n\n\t\t\t\tAccess Now oral statement to the UN Global Digital Compact Informal Consultations with Member States and Stakeholders\t\t\t\n\n3 Feb 2023\n • \nAccess Now’s Senior UN Advocacy Officer Laura O’Brien delivered an oral statement to the UN Global Digital Compact Informal Consultations with Member States and Stakeholders on Feb 3 2023.\n\n\n\n\nPublication\nAccess Now oral statement to the UN Global Digital Compact Informal Consultations with Member States and Stakeholders\n\n\n↗\n3 Feb 2023\n\nAccess Now oral statement to the UN Global Digital Compact Informal Consultations with Member States and Stakeholders\n\n\n\n\n\n\n\n\n\n\t\t\t\t\tInternet Shutdowns\t\t\t\t\n\n\n\n\nInternet Shutdowns \n\n\n\t\t\t\tዓፀቦ፣ ዓቕሊ ፅበትን ስቃይ: 15 ታሪኻት ከበባ ኢንተርነት ትግራይ\t\t\t\n\n25 Aug 2022\n\n\n\n\nPost\nዓፀቦ፣ ዓቕሊ ፅበትን ስቃይ: 15 ታሪኻት ከበባ ኢንተርነት ትግራይ\n25 Aug 2022\n\nዓፀቦ፣ ዓቕሊ ፅበትን ስቃይ: 15 ታሪኻት ከበባ ኢንተርነት ትግራይ\n\n\n\n\n\n\n\n\n\n\t\t\t\t\tInternet Shutdowns\t\t\t\t\n\n\n\n\nInternet Shutdowns \n\n\n\t\t\t\tStranded, suffocated, and in pain: 15 stories from Tigray’s internet siege\t\t\t\n\n28 Jul 2022\n • \nIt’s been two years since Tigray were cut off from the internet. Share the 15 stories from Tigrayans and help amplify their voices.\n\n\n\n\nPost\nStranded, suffocated, and in pain: 15 stories from Tigray’s internet siege\n28 Jul 2022\n\nStranded, suffocated, and in pain: 15 stories from Tigray’s internet siege\n\n\n\n\n\n\n\n\n\n\t\t\t\t\tContent Governance\t\t\t\t\n\n\n\n\nContent Governance \n\n\n\t\t\t\tJoin us June 6-10 for RightsCon 2022\t\t\t\n\n31 May 2022\n • \nLog in to the RightsCon platform to participate in the world’s leading summit on human rights in the digital age (June 6-10, 2022)!\n\n\n\n\nCampaign\nJoin us June 6-10 for RightsCon 2022\n\n\n↗\n31 May 2022\n\nJoin us June 6-10 for RightsCon 2022\n\n\n\n\n\n\n\n\n\n\t\t\t\t\tContent Governance\t\t\t\t\n\n\n\n\nContent Governance \n\n\n\t\t\t\tStop the misinformation experience: Spotify must intervene\t\t\t\n\n24 Feb 2022\n • \nThrough a letter to Daniel Ek, Co-Founder and CEO at Spotify, Access Now is urging the company to align with basic human rights principles.\n\n\n\n\nPress Release\nStop the misinformation experience: Spotify must intervene\n24 Feb 2022\n\nStop the misinformation experience: Spotify must intervene\n\n\n\n\n\n\n\n\n\n\t\t\t\t\tFreedom of Expression\t\t\t\t\n\n\n\n\nFreedom of Expression \n\n\n\t\t\t\tJoe Rogan and Spotify: Make content moderation about human rights\t\t\t\n\n10 Feb 2022\n • \nIs Spotify willing to allow harmful content like COVID misinformation to spread, prioritizing the companyʼs bottom line over public health?\n\n\n\n\nPost\nJoe Rogan and Spotify: Make content moderation about human rights\n10 Feb 2022\n\nJoe Rogan and Spotify: Make content moderation about human rights\n\n\n\n\n\n\n\n\n\n\t\t\t\t\tContent Governance\t\t\t\t\n\n\n\n\nContent Governance \n\n\n\t\t\t\tWhat is disinformation, why it spreads, and how to stop it\t\t\t\n\n21 Dec 2021\n • \nOur new report explores what disinformation is, and how lawmakers can address the harms it poses to democracy.\n\n\n\n\nPublication\nWhat is disinformation, why it spreads, and how to stop it\n21 Dec 2021\n\nWhat is disinformation, why it spreads, and how to stop it\n\n\n\n\n\n\n\n\n\n\t\t\t\t\tCovid-19\t\t\t\t\n\n\n\n\nCovid-19 \n\n\n\t\t\t\tOne Year Under COVID-19 Contact Tracing Apps: What Has Europe Learned? – A report by Access Now and Liberties\t\t\t\n\n28 Oct 2021\n • \nA year after the introduction of COVID-19 Contact Tracing Apps in Europe, Access Now and Liberties look at their impact on digital rights.\n\n\n\n\nPublication\nOne Year Under COVID-19 Contact Tracing Apps: What Has Europe Learned? – A report by Access Now and Liberties\n\n\n↗\n28 Oct 2021\n\nOne Year Under COVID-19 Contact Tracing Apps: What Has Europe Learned? – A report by Access Now and Liberties\n\n\n\n\n\n\n\n\n\n\t\t\t\t\tPrivacy\t\t\t\t\n\n\n\n\nPrivacy \n\n\n\t\t\t\tWhat you need to know about the Facebook Papers\t\t\t\n\n26 Oct 2021\n • \nThe Facebook Papers paint a grim picture of how Facebook has repeatedly and knowingly prioritized profit over people’s safety. Here’s a snapshot of what we know so far.\n\n\n\n\nPost\nWhat you need to know about the Facebook Papers\n26 Oct 2021\n\nWhat you need to know about the Facebook Papers\n\n\n\n\n\n\n\n\n\n\t\t\t\t\tNet Neutrality\t\t\t\t\n\n\n\n\nNet Neutrality \n\n\n\t\t\t\tDigital rights champions nominated to lead U.S. FCC and NTIA\t\t\t\n\n26 Oct 2021\n • \nAt long last, U.S. President Biden has nominated public interests advocates to lead the Federal Communications Commission and the National Telecommunications and Information Administration.\n\n\n\n\nPress Release\nDigital rights champions nominated to lead U.S. FCC and NTIA\n26 Oct 2021\n\nDigital rights champions nominated to lead U.S. FCC and NTIA\n\n\n\n\n\n\n\n\n\n\t\t\t\t\tContent Governance\t\t\t\t\n\n\n\n\nContent Governance \n\n\n\t\t\t\tWill the Right to Protest survive its migration online?\t\t\t\n\n20 Oct 2021\n • \nState-sanctioned internet shutdowns, increased surveillance, and unequal access to the internet are impacting communities globally. Will the Right to Protest survive its migration online?\n\n\n\n\nPost\nWill the Right to Protest survive its migration online?\n20 Oct 2021\n\nWill the Right to Protest survive its migration online?\n\n\n\n\n\n\n\n\n\n\t\t\t\t\tPrivacy\t\t\t\t\n\n\n\n\nPrivacy \n\n\n\t\t\t\tColombia’s mandatory CoronApp violates people’s privacy and freedom of movement\t\t\t\n\n23 Sep 2021\n\n\n\n\nPress Release\nColombia’s mandatory CoronApp violates people’s privacy and freedom of movement\n23 Sep 2021\n\nColombia’s mandatory CoronApp violates people’s privacy and freedom of movement\n\n\n\n\n\n\n\n\n\n\t\t\t\t\tPrivacy\t\t\t\t\n\n\n\n\nPrivacy \n\n\n\t\t\t\tColombia: CoronApp viola la privacidad y la libertad de movimiento de las personas\t\t\t\n\n23 Sep 2021\n\n\n\n\nPress Release\nColombia: CoronApp viola la privacidad y la libertad de movimiento de las personas\n23 Sep 2021\n\nColombia: CoronApp viola la privacidad y la libertad de movimiento de las personas\n\n\n\n\n\n\n\n\n\n\t\t\t\t\tFreedom of Expression\t\t\t\t\n\n\n\n\nFreedom of Expression \n\n\n\t\t\t\tThe internet shutdowns issue\t\t\t\n\n1 Sep 2021\n • \nWith support from the #KeepItOn coalition, Jigsaw is today publishing “The Current: The Internet Shutdowns Issue,” a deep-dive into internet shutdowns.\n\n\n\n\nPress Release\nThe internet shutdowns issue\n1 Sep 2021\n\nThe internet shutdowns issue\n\n\n\n\n\n\n\n\n\n\t\t\t\t\tFreedom of Expression\t\t\t\t\n\n\n\n\nFreedom of Expression \n\n\n\t\t\t\tHow Thailand handles COVID: it stokes fear among its critics\t\t\t\n\n24 Aug 2021\n • \nAmidst continuing protests, calls for political reform, and mass dissatisfaction with how Thailand handles COVID, Thailand’s government is doubling down on efforts to throttle dissent and protest online and off. It is relying on laws that it claims protect against “public fear.” In fact, by threatening to censor those who speak out, it is the government that is instigating fear – in a weak bid to distract from flailing governance. \n\n\n\n\nPost\nHow Thailand handles COVID: it stokes fear among its critics\n24 Aug 2021\n\nHow Thailand handles COVID: it stokes fear among its critics\n\n\n\n\n\n\n\n\n\n\t\t\t\t\tCovid-19\t\t\t\t\n\n\n\n\nCovid-19 \n\n\n\t\t\t\tHow to apply for the Emergency Broadband Benefit in the U.S.\t\t\t\n\n13 Aug 2021\n\n\n\n\nPost\nHow to apply for the Emergency Broadband Benefit in the U.S.\n13 Aug 2021\n\nHow to apply for the Emergency Broadband Benefit in the U.S.\n\nCovid-19\n\n\n\t\t\t\n\t\t\t\tCivil society to WHO: let’s end government-ordered internet shutdowns\n\t\t\t\t\t\t\t\n\n\nToday the #KeepItOn coalition sent an open letter to the Deputy Director-General of the WHO, Dr. Zsuzsanna Jakab, calling on her to urge states to end the blatant and arbitrary internet shutdowns that are ongoing during COVID-19.\n\n\n\n\n\n\n\n\n\n\n\n\n\nCovid-19\n\n\n\t\t\t\n\t\t\t\tAccess Now releases recommendations on privacy and data protection in the fight against COVID-19\n\t\t\t\t\t\t\t\n\n\nOur message to governments is simple: protecting digital rights also promotes public health. We aim to ensure that the rule of law, and the rights to privacy and data protection, are protected throughout this crisis and in the future.\n\n\n\n\n\n\n\n\n\n\n\n\n\nCovid 19\n\n\n\t\t\t\n\t\t\t\tPrivacy and public health: the dos and don’ts for COVID-19 contact tracing apps\n\t\t\t\t\t\t\t\n\n\n\n\n\n\n\n\n\n\n\n\n\nContent Governance\n\n\n\t\t\t\n\t\t\t\tAccess Now releases “Fighting misinformation and defending free expression during COVID-19: recommendations for states”\n\t\t\t\t\t\t\t\n\n\nWe have identified practical examples and promising practices to support policy makers in respecting human rights while developing measures to address disinformation and misinformation during the COVID-19 crisis.\n\nCovid-19\n\n\n\t\t\t\n\t\t\t\tCivil society to WHO: let’s end government-ordered internet shutdowns\n\t\t\t\t\t\t\t\n\n\nToday the #KeepItOn coalition sent an open letter to the Deputy Director-General of the WHO, Dr. Zsuzsanna Jakab, calling on her to urge states to end the blatant and arbitrary internet shutdowns that are ongoing during COVID-19.\n\n\n\n\n\n\n\n\n\n\n\n\n\nCovid-19\n\n\n\t\t\t\n\t\t\t\tAccess Now releases recommendations on privacy and data protection in the fight against COVID-19\n\t\t\t\t\t\t\t\n\n\nOur message to governments is simple: protecting digital rights also promotes public health. We aim to ensure that the rule of law, and the rights to privacy and data protection, are protected throughout this crisis and in the future.\n\n\n\n\n\n\n\n\n\n\n\n\n\nCovid 19\n\n\n\t\t\t\n\t\t\t\tPrivacy and public health: the dos and don’ts for COVID-19 contact tracing apps\n\t\t\t\t\t\t\t\n\n\n\n\n\n\n\n\n\n\n\n\n\nContent Governance\n\n\n\t\t\t\n\t\t\t\tAccess Now releases “Fighting misinformation and defending free expression during COVID-19: recommendations for states”\n\t\t\t\t\t\t\t\n\n\nWe have identified practical examples and promising practices to support policy makers in respecting human rights while developing measures to address disinformation and misinformation during the COVID-19 crisis.\n\nCovid-19\n\n\n\t\t\t\n\t\t\t\tCivil society to WHO: let’s end government-ordered internet shutdowns\n\t\t\t\t\t\t\t\n\n\nToday the #KeepItOn coalition sent an open letter to the Deputy Director-General of the WHO, Dr. Zsuzsanna Jakab, calling on her to urge states to end the blatant and arbitrary internet shutdowns that are ongoing during COVID-19.\n\n\n\n\n\n\n\n\n\n\n\n\n\nCovid-19\n\n\n\t\t\t\n\t\t\t\tAccess Now releases recommendations on privacy and data protection in the fight against COVID-19\n\t\t\t\t\t\t\t\n\n\nOur message to governments is simple: protecting digital rights also promotes public health. We aim to ensure that the rule of law, and the rights to privacy and data protection, are protected throughout this crisis and in the future.\n\n\n\n\n\n\n\n\n\n\n\n\n\nCovid 19\n\n\n\t\t\t\n\t\t\t\tPrivacy and public health: the dos and don’ts for COVID-19 contact tracing apps\n\t\t\t\t\t\t\t\n\n\n\n\n\n\n\n\n\n\n\n\n\nContent Governance\n\n\n\t\t\t\n\t\t\t\tAccess Now releases “Fighting misinformation and defending free expression during COVID-19: recommendations for states”\n\t\t\t\t\t\t\t\n\n\nWe have identified practical examples and promising practices to support policy makers in respecting human rights while developing measures to address disinformation and misinformation during the COVID-19 crisis.\n\nCovid-19\n\n\n\t\t\t\n\t\t\t\tCivil society to WHO: let’s end government-ordered internet shutdowns\n\t\t\t\t\t\t\t\n\n\nToday the #KeepItOn coalition sent an open letter to the Deputy Director-General of the WHO, Dr. Zsuzsanna Jakab, calling on her to urge states to end the blatant and arbitrary internet shutdowns that are ongoing during COVID-19.\n\n\n\n\n\n\n\n\n\n\n\n\n\nCovid-19\n\n\n\t\t\t\n\t\t\t\tAccess Now releases recommendations on privacy and data protection in the fight against COVID-19\n\t\t\t\t\t\t\t\n\n\nOur message to governments is simple: protecting digital rights also promotes public health. We aim to ensure that the rule of law, and the rights to privacy and data protection, are protected throughout this crisis and in the future.\n\n\n\n\n\n\n\n\n\n\n\n\n\nCovid 19\n\n\n\t\t\t\n\t\t\t\tPrivacy and public health: the dos and don’ts for COVID-19 contact tracing apps\n\t\t\t\t\t\t\t\n\n\n\n\n\n\n\n\n\n\n\n\n\nContent Governance\n\n\n\t\t\t\n\t\t\t\tAccess Now releases “Fighting misinformation and defending free expression during COVID-19: recommendations for states”\n\t\t\t\t\t\t\t\n\n\nWe have identified practical examples and promising practices to support policy makers in respecting human rights while developing measures to address disinformation and misinformation during the COVID-19 crisis.\n\nCovid-19\n\n\n\t\t\t\n\t\t\t\tCivil society to WHO: let’s end government-ordered internet shutdowns\n\t\t\t\t\t\t\t\n\n\nToday the #KeepItOn coalition sent an open letter to the Deputy Director-General of the WHO, Dr. Zsuzsanna Jakab, calling on her to urge states to end the blatant and arbitrary internet shutdowns that are ongoing during COVID-19.\n\nCovid-19\n\n\n\t\t\t\n\t\t\t\tCivil society to WHO: let’s end government-ordered internet shutdowns\n\t\t\t\t\t\t\t\n\n\nToday the #KeepItOn coalition sent an open letter to the Deputy Director-General of the WHO, Dr. Zsuzsanna Jakab, calling on her to urge states to end the blatant and arbitrary internet shutdowns that are ongoing during COVID-19.\n\nCovid-19\n\n\n\t\t\t\n\t\t\t\tCivil society to WHO: let’s end government-ordered internet shutdowns\n\t\t\t\t\t\t\t\n\n\nToday the #KeepItOn coalition sent an open letter to the Deputy Director-General of the WHO, Dr. Zsuzsanna Jakab, calling on her to urge states to end the blatant and arbitrary internet shutdowns that are ongoing during COVID-19.\n\nCovid-19\n\nToday the #KeepItOn coalition sent an open letter to the Deputy Director-General of the WHO, Dr. Zsuzsanna Jakab, calling on her to urge states to end the blatant and arbitrary internet shutdowns that are ongoing during COVID-19.\n\nToday the #KeepItOn coalition sent an open letter to the Deputy Director-General of the WHO, Dr. Zsuzsanna Jakab, calling on her to urge states to end the blatant and arbitrary internet shutdowns that are ongoing during COVID-19.\n\nCovid-19\n\n\n\t\t\t\n\t\t\t\tAccess Now releases recommendations on privacy and data protection in the fight against COVID-19\n\t\t\t\t\t\t\t\n\n\nOur message to governments is simple: protecting digital rights also promotes public health. We aim to ensure that the rule of law, and the rights to privacy and data protection, are protected throughout this crisis and in the future.\n\nCovid-19\n\n\n\t\t\t\n\t\t\t\tAccess Now releases recommendations on privacy and data protection in the fight against COVID-19\n\t\t\t\t\t\t\t\n\n\nOur message to governments is simple: protecting digital rights also promotes public health. We aim to ensure that the rule of law, and the rights to privacy and data protection, are protected throughout this crisis and in the future.\n\nCovid-19\n\n\n\t\t\t\n\t\t\t\tAccess Now releases recommendations on privacy and data protection in the fight against COVID-19\n\t\t\t\t\t\t\t\n\n\nOur message to governments is simple: protecting digital rights also promotes public health. We aim to ensure that the rule of law, and the rights to privacy and data protection, are protected throughout this crisis and in the future.\n\nCovid-19\n\nOur message to governments is simple: protecting digital rights also promotes public health. We aim to ensure that the rule of law, and the rights to privacy and data protection, are protected throughout this crisis and in the future.\n\nOur message to governments is simple: protecting digital rights also promotes public health. We aim to ensure that the rule of law, and the rights to privacy and data protection, are protected throughout this crisis and in the future.\n\nCovid 19\n\n\n\t\t\t\n\t\t\t\tPrivacy and public health: the dos and don’ts for COVID-19 contact tracing apps\n\nCovid 19\n\n\n\t\t\t\n\t\t\t\tPrivacy and public health: the dos and don’ts for COVID-19 contact tracing apps\n\nCovid 19\n\n\n\t\t\t\n\t\t\t\tPrivacy and public health: the dos and don’ts for COVID-19 contact tracing apps\n\nCovid 19\n\nContent Governance\n\n\n\t\t\t\n\t\t\t\tAccess Now releases “Fighting misinformation and defending free expression during COVID-19: recommendations for states”\n\t\t\t\t\t\t\t\n\n\nWe have identified practical examples and promising practices to support policy makers in respecting human rights while developing measures to address disinformation and misinformation during the COVID-19 crisis.\n\nContent Governance\n\n\n\t\t\t\n\t\t\t\tAccess Now releases “Fighting misinformation and defending free expression during COVID-19: recommendations for states”\n\t\t\t\t\t\t\t\n\n\nWe have identified practical examples and promising practices to support policy makers in respecting human rights while developing measures to address disinformation and misinformation during the COVID-19 crisis.\n\nContent Governance\n\n\n\t\t\t\n\t\t\t\tAccess Now releases “Fighting misinformation and defending free expression during COVID-19: recommendations for states”\n\t\t\t\t\t\t\t\n\n\nWe have identified practical examples and promising practices to support policy makers in respecting human rights while developing measures to address disinformation and misinformation during the COVID-19 crisis.\n\nContent Governance\n\nWe have identified practical examples and promising practices to support policy makers in respecting human rights while developing measures to address disinformation and misinformation during the COVID-19 crisis.\n\nWe have identified practical examples and promising practices to support policy makers in respecting human rights while developing measures to address disinformation and misinformation during the COVID-19 crisis.\n\nGrid View\nList View\n\n\n\n\n\n\n\n\n\n\n\n\n\n\t\t\t\t\tFreedom of Expression\t\t\t\t\n\n\n\n\nFreedom of Expression \n\n\n\t\t\t\tAccess Now oral statement to the UN Global Digital Compact Informal Consultations with Member States and Stakeholders\t\t\t\n\n3 Feb 2023\n • \nAccess Now’s Senior UN Advocacy Officer Laura O’Brien delivered an oral statement to the UN Global Digital Compact Informal Consultations with Member States and Stakeholders on Feb 3 2023.\n\n\n\n\nPublication\nAccess Now oral statement to the UN Global Digital Compact Informal Consultations with Member States and Stakeholders\n\n\n↗\n3 Feb 2023\n\nAccess Now oral statement to the UN Global Digital Compact Informal Consultations with Member States and Stakeholders\n\n\n\n\n\n\n\n\n\n\t\t\t\t\tInternet Shutdowns\t\t\t\t\n\n\n\n\nInternet Shutdowns \n\n\n\t\t\t\tዓፀቦ፣ ዓቕሊ ፅበትን ስቃይ: 15 ታሪኻት ከበባ ኢንተርነት ትግራይ\t\t\t\n\n25 Aug 2022\n\n\n\n\nPost\nዓፀቦ፣ ዓቕሊ ፅበትን ስቃይ: 15 ታሪኻት ከበባ ኢንተርነት ትግራይ\n25 Aug 2022\n\nዓፀቦ፣ ዓቕሊ ፅበትን ስቃይ: 15 ታሪኻት ከበባ ኢንተርነት ትግራይ\n\n\n\n\n\n\n\n\n\n\t\t\t\t\tInternet Shutdowns\t\t\t\t\n\n\n\n\nInternet Shutdowns \n\n\n\t\t\t\tStranded, suffocated, and in pain: 15 stories from Tigray’s internet siege\t\t\t\n\n28 Jul 2022\n • \nIt’s been two years since Tigray were cut off from the internet. Share the 15 stories from Tigrayans and help amplify their voices.\n\n\n\n\nPost\nStranded, suffocated, and in pain: 15 stories from Tigray’s internet siege\n28 Jul 2022\n\nStranded, suffocated, and in pain: 15 stories from Tigray’s internet siege\n\n\n\n\n\n\n\n\n\n\t\t\t\t\tContent Governance\t\t\t\t\n\n\n\n\nContent Governance \n\n\n\t\t\t\tJoin us June 6-10 for RightsCon 2022\t\t\t\n\n31 May 2022\n • \nLog in to the RightsCon platform to participate in the world’s leading summit on human rights in the digital age (June 6-10, 2022)!\n\n\n\n\nCampaign\nJoin us June 6-10 for RightsCon 2022\n\n\n↗\n31 May 2022\n\nJoin us June 6-10 for RightsCon 2022\n\n\n\n\n\n\n\n\n\n\t\t\t\t\tContent Governance\t\t\t\t\n\n\n\n\nContent Governance \n\n\n\t\t\t\tStop the misinformation experience: Spotify must intervene\t\t\t\n\n24 Feb 2022\n • \nThrough a letter to Daniel Ek, Co-Founder and CEO at Spotify, Access Now is urging the company to align with basic human rights principles.\n\n\n\n\nPress Release\nStop the misinformation experience: Spotify must intervene\n24 Feb 2022\n\nStop the misinformation experience: Spotify must intervene\n\n\n\n\n\n\n\n\n\n\t\t\t\t\tFreedom of Expression\t\t\t\t\n\n\n\n\nFreedom of Expression \n\n\n\t\t\t\tJoe Rogan and Spotify: Make content moderation about human rights\t\t\t\n\n10 Feb 2022\n • \nIs Spotify willing to allow harmful content like COVID misinformation to spread, prioritizing the companyʼs bottom line over public health?\n\n\n\n\nPost\nJoe Rogan and Spotify: Make content moderation about human rights\n10 Feb 2022\n\nJoe Rogan and Spotify: Make content moderation about human rights\n\n\n\n\n\n\n\n\n\n\t\t\t\t\tContent Governance\t\t\t\t\n\n\n\n\nContent Governance \n\n\n\t\t\t\tWhat is disinformation, why it spreads, and how to stop it\t\t\t\n\n21 Dec 2021\n • \nOur new report explores what disinformation is, and how lawmakers can address the harms it poses to democracy.\n\n\n\n\nPublication\nWhat is disinformation, why it spreads, and how to stop it\n21 Dec 2021\n\nWhat is disinformation, why it spreads, and how to stop it\n\n\n\n\n\n\n\n\n\n\t\t\t\t\tCovid-19\t\t\t\t\n\n\n\n\nCovid-19 \n\n\n\t\t\t\tOne Year Under COVID-19 Contact Tracing Apps: What Has Europe Learned? – A report by Access Now and Liberties\t\t\t\n\n28 Oct 2021\n • \nA year after the introduction of COVID-19 Contact Tracing Apps in Europe, Access Now and Liberties look at their impact on digital rights.\n\n\n\n\nPublication\nOne Year Under COVID-19 Contact Tracing Apps: What Has Europe Learned? – A report by Access Now and Liberties\n\n\n↗\n28 Oct 2021\n\nOne Year Under COVID-19 Contact Tracing Apps: What Has Europe Learned? – A report by Access Now and Liberties\n\n\n\n\n\n\n\n\n\n\t\t\t\t\tPrivacy\t\t\t\t\n\n\n\n\nPrivacy \n\n\n\t\t\t\tWhat you need to know about the Facebook Papers\t\t\t\n\n26 Oct 2021\n • \nThe Facebook Papers paint a grim picture of how Facebook has repeatedly and knowingly prioritized profit over people’s safety. Here’s a snapshot of what we know so far.\n\n\n\n\nPost\nWhat you need to know about the Facebook Papers\n26 Oct 2021\n\nWhat you need to know about the Facebook Papers\n\n\n\n\n\n\n\n\n\n\t\t\t\t\tNet Neutrality\t\t\t\t\n\n\n\n\nNet Neutrality \n\n\n\t\t\t\tDigital rights champions nominated to lead U.S. FCC and NTIA\t\t\t\n\n26 Oct 2021\n • \nAt long last, U.S. President Biden has nominated public interests advocates to lead the Federal Communications Commission and the National Telecommunications and Information Administration.\n\n\n\n\nPress Release\nDigital rights champions nominated to lead U.S. FCC and NTIA\n26 Oct 2021\n\nDigital rights champions nominated to lead U.S. FCC and NTIA\n\n\n\n\n\n\n\n\n\n\t\t\t\t\tContent Governance\t\t\t\t\n\n\n\n\nContent Governance \n\n\n\t\t\t\tWill the Right to Protest survive its migration online?\t\t\t\n\n20 Oct 2021\n • \nState-sanctioned internet shutdowns, increased surveillance, and unequal access to the internet are impacting communities globally. Will the Right to Protest survive its migration online?\n\n\n\n\nPost\nWill the Right to Protest survive its migration online?\n20 Oct 2021\n\nWill the Right to Protest survive its migration online?\n\n\n\n\n\n\n\n\n\n\t\t\t\t\tPrivacy\t\t\t\t\n\n\n\n\nPrivacy \n\n\n\t\t\t\tColombia’s mandatory CoronApp violates people’s privacy and freedom of movement\t\t\t\n\n23 Sep 2021\n\n\n\n\nPress Release\nColombia’s mandatory CoronApp violates people’s privacy and freedom of movement\n23 Sep 2021\n\nColombia’s mandatory CoronApp violates people’s privacy and freedom of movement\n\n\n\n\n\n\n\n\n\n\t\t\t\t\tPrivacy\t\t\t\t\n\n\n\n\nPrivacy \n\n\n\t\t\t\tColombia: CoronApp viola la privacidad y la libertad de movimiento de las personas\t\t\t\n\n23 Sep 2021\n\n\n\n\nPress Release\nColombia: CoronApp viola la privacidad y la libertad de movimiento de las personas\n23 Sep 2021\n\nColombia: CoronApp viola la privacidad y la libertad de movimiento de las personas\n\n\n\n\n\n\n\n\n\n\t\t\t\t\tFreedom of Expression\t\t\t\t\n\n\n\n\nFreedom of Expression \n\n\n\t\t\t\tThe internet shutdowns issue\t\t\t\n\n1 Sep 2021\n • \nWith support from the #KeepItOn coalition, Jigsaw is today publishing “The Current: The Internet Shutdowns Issue,” a deep-dive into internet shutdowns.\n\n\n\n\nPress Release\nThe internet shutdowns issue\n1 Sep 2021\n\nThe internet shutdowns issue\n\n\n\n\n\n\n\n\n\n\t\t\t\t\tFreedom of Expression\t\t\t\t\n\n\n\n\nFreedom of Expression \n\n\n\t\t\t\tHow Thailand handles COVID: it stokes fear among its critics\t\t\t\n\n24 Aug 2021\n • \nAmidst continuing protests, calls for political reform, and mass dissatisfaction with how Thailand handles COVID, Thailand’s government is doubling down on efforts to throttle dissent and protest online and off. It is relying on laws that it claims protect against “public fear.” In fact, by threatening to censor those who speak out, it is the government that is instigating fear – in a weak bid to distract from flailing governance. \n\n\n\n\nPost\nHow Thailand handles COVID: it stokes fear among its critics\n24 Aug 2021\n\nHow Thailand handles COVID: it stokes fear among its critics\n\n\n\n\n\n\n\n\n\n\t\t\t\t\tCovid-19\t\t\t\t\n\n\n\n\nCovid-19 \n\n\n\t\t\t\tHow to apply for the Emergency Broadband Benefit in the U.S.\t\t\t\n\n13 Aug 2021\n\n\n\n\nPost\nHow to apply for the Emergency Broadband Benefit in the U.S.\n13 Aug 2021\n\nHow to apply for the Emergency Broadband Benefit in the U.S.\n\nGrid View\nList View\n\nGrid View\nList View\n\nGrid View\nList View\n\nFreedom of Expression\t\t\t\t\n\n\n\n\nFreedom of Expression \n\n\n\t\t\t\tAccess Now oral statement to the UN Global Digital Compact Informal Consultations with Member States and Stakeholders\t\t\t\n\n3 Feb 2023\n • \nAccess Now’s Senior UN Advocacy Officer Laura O’Brien delivered an oral statement to the UN Global Digital Compact Informal Consultations with Member States and Stakeholders on Feb 3 2023.\n\n\n\n\nPublication\nAccess Now oral statement to the UN Global Digital Compact Informal Consultations with Member States and Stakeholders\n\n\n↗\n3 Feb 2023\n\nAccess Now oral statement to the UN Global Digital Compact Informal Consultations with Member States and Stakeholders\n\n\n\n\n\n\n\n\n\n\t\t\t\t\tInternet Shutdowns\t\t\t\t\n\n\n\n\nInternet Shutdowns \n\n\n\t\t\t\tዓፀቦ፣ ዓቕሊ ፅበትን ስቃይ: 15 ታሪኻት ከበባ ኢንተርነት ትግራይ\t\t\t\n\n25 Aug 2022\n\n\n\n\nPost\nዓፀቦ፣ ዓቕሊ ፅበትን ስቃይ: 15 ታሪኻት ከበባ ኢንተርነት ትግራይ\n25 Aug 2022\n\nዓፀቦ፣ ዓቕሊ ፅበትን ስቃይ: 15 ታሪኻት ከበባ ኢንተርነት ትግራይ\n\n\n\n\n\n\n\n\n\n\t\t\t\t\tInternet Shutdowns\t\t\t\t\n\n\n\n\nInternet Shutdowns \n\n\n\t\t\t\tStranded, suffocated, and in pain: 15 stories from Tigray’s internet siege\t\t\t\n\n28 Jul 2022\n • \nIt’s been two years since Tigray were cut off from the internet. Share the 15 stories from Tigrayans and help amplify their voices.\n\n\n\n\nPost\nStranded, suffocated, and in pain: 15 stories from Tigray’s internet siege\n28 Jul 2022\n\nStranded, suffocated, and in pain: 15 stories from Tigray’s internet siege\n\n\n\n\n\n\n\n\n\n\t\t\t\t\tContent Governance\t\t\t\t\n\n\n\n\nContent Governance \n\n\n\t\t\t\tJoin us June 6-10 for RightsCon 2022\t\t\t\n\n31 May 2022\n • \nLog in to the RightsCon platform to participate in the world’s leading summit on human rights in the digital age (June 6-10, 2022)!\n\n\n\n\nCampaign\nJoin us June 6-10 for RightsCon 2022\n\n\n↗\n31 May 2022\n\nJoin us June 6-10 for RightsCon 2022\n\n\n\n\n\n\n\n\n\n\t\t\t\t\tContent Governance\t\t\t\t\n\n\n\n\nContent Governance \n\n\n\t\t\t\tStop the misinformation experience: Spotify must intervene\t\t\t\n\n24 Feb 2022\n • \nThrough a letter to Daniel Ek, Co-Founder and CEO at Spotify, Access Now is urging the company to align with basic human rights principles.\n\n\n\n\nPress Release\nStop the misinformation experience: Spotify must intervene\n24 Feb 2022\n\nStop the misinformation experience: Spotify must intervene\n\n\n\n\n\n\n\n\n\n\t\t\t\t\tFreedom of Expression\t\t\t\t\n\n\n\n\nFreedom of Expression \n\n\n\t\t\t\tJoe Rogan and Spotify: Make content moderation about human rights\t\t\t\n\n10 Feb 2022\n • \nIs Spotify willing to allow harmful content like COVID misinformation to spread, prioritizing the companyʼs bottom line over public health?\n\n\n\n\nPost\nJoe Rogan and Spotify: Make content moderation about human rights\n10 Feb 2022\n\nJoe Rogan and Spotify: Make content moderation about human rights\n\n\n\n\n\n\n\n\n\n\t\t\t\t\tContent Governance\t\t\t\t\n\n\n\n\nContent Governance \n\n\n\t\t\t\tWhat is disinformation, why it spreads, and how to stop it\t\t\t\n\n21 Dec 2021\n • \nOur new report explores what disinformation is, and how lawmakers can address the harms it poses to democracy.\n\n\n\n\nPublication\nWhat is disinformation, why it spreads, and how to stop it\n21 Dec 2021\n\nWhat is disinformation, why it spreads, and how to stop it\n\n\n\n\n\n\n\n\n\n\t\t\t\t\tCovid-19\t\t\t\t\n\n\n\n\nCovid-19 \n\n\n\t\t\t\tOne Year Under COVID-19 Contact Tracing Apps: What Has Europe Learned? – A report by Access Now and Liberties\t\t\t\n\n28 Oct 2021\n • \nA year after the introduction of COVID-19 Contact Tracing Apps in Europe, Access Now and Liberties look at their impact on digital rights.\n\n\n\n\nPublication\nOne Year Under COVID-19 Contact Tracing Apps: What Has Europe Learned? – A report by Access Now and Liberties\n\n\n↗\n28 Oct 2021\n\nOne Year Under COVID-19 Contact Tracing Apps: What Has Europe Learned? – A report by Access Now and Liberties\n\n\n\n\n\n\n\n\n\n\t\t\t\t\tPrivacy\t\t\t\t\n\n\n\n\nPrivacy \n\n\n\t\t\t\tWhat you need to know about the Facebook Papers\t\t\t\n\n26 Oct 2021\n • \nThe Facebook Papers paint a grim picture of how Facebook has repeatedly and knowingly prioritized profit over people’s safety. Here’s a snapshot of what we know so far.\n\n\n\n\nPost\nWhat you need to know about the Facebook Papers\n26 Oct 2021\n\nWhat you need to know about the Facebook Papers\n\n\n\n\n\n\n\n\n\n\t\t\t\t\tNet Neutrality\t\t\t\t\n\n\n\n\nNet Neutrality \n\n\n\t\t\t\tDigital rights champions nominated to lead U.S. FCC and NTIA\t\t\t\n\n26 Oct 2021\n • \nAt long last, U.S. President Biden has nominated public interests advocates to lead the Federal Communications Commission and the National Telecommunications and Information Administration.\n\n\n\n\nPress Release\nDigital rights champions nominated to lead U.S. FCC and NTIA\n26 Oct 2021\n\nDigital rights champions nominated to lead U.S. FCC and NTIA\n\n\n\n\n\n\n\n\n\n\t\t\t\t\tContent Governance\t\t\t\t\n\n\n\n\nContent Governance \n\n\n\t\t\t\tWill the Right to Protest survive its migration online?\t\t\t\n\n20 Oct 2021\n • \nState-sanctioned internet shutdowns, increased surveillance, and unequal access to the internet are impacting communities globally. Will the Right to Protest survive its migration online?\n\n\n\n\nPost\nWill the Right to Protest survive its migration online?\n20 Oct 2021\n\nWill the Right to Protest survive its migration online?\n\n\n\n\n\n\n\n\n\n\t\t\t\t\tPrivacy\t\t\t\t\n\n\n\n\nPrivacy \n\n\n\t\t\t\tColombia’s mandatory CoronApp violates people’s privacy and freedom of movement\t\t\t\n\n23 Sep 2021\n\n\n\n\nPress Release\nColombia’s mandatory CoronApp violates people’s privacy and freedom of movement\n23 Sep 2021\n\nColombia’s mandatory CoronApp violates people’s privacy and freedom of movement\n\n\n\n\n\n\n\n\n\n\t\t\t\t\tPrivacy\t\t\t\t\n\n\n\n\nPrivacy \n\n\n\t\t\t\tColombia: CoronApp viola la privacidad y la libertad de movimiento de las personas\t\t\t\n\n23 Sep 2021\n\n\n\n\nPress Release\nColombia: CoronApp viola la privacidad y la libertad de movimiento de las personas\n23 Sep 2021\n\nColombia: CoronApp viola la privacidad y la libertad de movimiento de las personas\n\n\n\n\n\n\n\n\n\n\t\t\t\t\tFreedom of Expression\t\t\t\t\n\n\n\n\nFreedom of Expression \n\n\n\t\t\t\tThe internet shutdowns issue\t\t\t\n\n1 Sep 2021\n • \nWith support from the #KeepItOn coalition, Jigsaw is today publishing “The Current: The Internet Shutdowns Issue,” a deep-dive into internet shutdowns.\n\n\n\n\nPress Release\nThe internet shutdowns issue\n1 Sep 2021\n\nThe internet shutdowns issue\n\n\n\n\n\n\n\n\n\n\t\t\t\t\tFreedom of Expression\t\t\t\t\n\n\n\n\nFreedom of Expression \n\n\n\t\t\t\tHow Thailand handles COVID: it stokes fear among its critics\t\t\t\n\n24 Aug 2021\n • \nAmidst continuing protests, calls for political reform, and mass dissatisfaction with how Thailand handles COVID, Thailand’s government is doubling down on efforts to throttle dissent and protest online and off. It is relying on laws that it claims protect against “public fear.” In fact, by threatening to censor those who speak out, it is the government that is instigating fear – in a weak bid to distract from flailing governance. \n\n\n\n\nPost\nHow Thailand handles COVID: it stokes fear among its critics\n24 Aug 2021\n\nHow Thailand handles COVID: it stokes fear among its critics\n\n\n\n\n\n\n\n\n\n\t\t\t\t\tCovid-19\t\t\t\t\n\n\n\n\nCovid-19 \n\n\n\t\t\t\tHow to apply for the Emergency Broadband Benefit in the U.S.\t\t\t\n\n13 Aug 2021\n\n\n\n\nPost\nHow to apply for the Emergency Broadband Benefit in the U.S.\n13 Aug 2021\n\nHow to apply for the Emergency Broadband Benefit in the U.S.\n\nFreedom of Expression\t\t\t\t\n\n\n\n\nFreedom of Expression \n\n\n\t\t\t\tAccess Now oral statement to the UN Global Digital Compact Informal Consultations with Member States and Stakeholders\t\t\t\n\n3 Feb 2023\n • \nAccess Now’s Senior UN Advocacy Officer Laura O’Brien delivered an oral statement to the UN Global Digital Compact Informal Consultations with Member States and Stakeholders on Feb 3 2023.\n\n\n\n\nPublication\nAccess Now oral statement to the UN Global Digital Compact Informal Consultations with Member States and Stakeholders\n\n\n↗\n3 Feb 2023\n\nAccess Now oral statement to the UN Global Digital Compact Informal Consultations with Member States and Stakeholders\n\nFreedom of Expression\t\t\t\t\n\n\n\n\nFreedom of Expression \n\n\n\t\t\t\tAccess Now oral statement to the UN Global Digital Compact Informal Consultations with Member States and Stakeholders\t\t\t\n\n3 Feb 2023\n • \nAccess Now’s Senior UN Advocacy Officer Laura O’Brien delivered an oral statement to the UN Global Digital Compact Informal Consultations with Member States and Stakeholders on Feb 3 2023.\n\nFreedom of Expression\n\nFreedom of Expression\n\nFreedom of Expression \n\n\n\t\t\t\tAccess Now oral statement to the UN Global Digital Compact Informal Consultations with Member States and Stakeholders\t\t\t\n\n3 Feb 2023\n • \nAccess Now’s Senior UN Advocacy Officer Laura O’Brien delivered an oral statement to the UN Global Digital Compact Informal Consultations with Member States and Stakeholders on Feb 3 2023.\n\nFreedom of Expression\n\nFreedom of Expression\n\n3 Feb 2023\n • \nAccess Now’s Senior UN Advocacy Officer Laura O’Brien delivered an oral statement to the UN Global Digital Compact Informal Consultations with Member States and Stakeholders on Feb 3 2023.\n\nAccess Now’s Senior UN Advocacy Officer Laura O’Brien delivered an oral statement to the UN Global Digital Compact Informal Consultations with Member States and Stakeholders on Feb 3 2023.\n\nPublication\nAccess Now oral statement to the UN Global Digital Compact Informal Consultations with Member States and Stakeholders\n\n\n↗\n3 Feb 2023\n\nPublication\n\nAccess Now oral statement to the UN Global Digital Compact Informal Consultations with Member States and Stakeholders\n\n↗\n\n3 Feb 2023\n\nInternet Shutdowns\t\t\t\t\n\n\n\n\nInternet Shutdowns \n\n\n\t\t\t\tዓፀቦ፣ ዓቕሊ ፅበትን ስቃይ: 15 ታሪኻት ከበባ ኢንተርነት ትግራይ\t\t\t\n\n25 Aug 2022\n\n\n\n\nPost\nዓፀቦ፣ ዓቕሊ ፅበትን ስቃይ: 15 ታሪኻት ከበባ ኢንተርነት ትግራይ\n25 Aug 2022\n\nዓፀቦ፣ ዓቕሊ ፅበትን ስቃይ: 15 ታሪኻት ከበባ ኢንተርነት ትግራይ\n\nInternet Shutdowns\t\t\t\t\n\n\n\n\nInternet Shutdowns \n\n\n\t\t\t\tዓፀቦ፣ ዓቕሊ ፅበትን ስቃይ: 15 ታሪኻት ከበባ ኢንተርነት ትግራይ\t\t\t\n\n25 Aug 2022\n\nInternet Shutdowns\n\nInternet Shutdowns\n\nInternet Shutdowns \n\n\n\t\t\t\tዓፀቦ፣ ዓቕሊ ፅበትን ስቃይ: 15 ታሪኻት ከበባ ኢንተርነት ትግራይ\t\t\t\n\n25 Aug 2022\n\nInternet Shutdowns\n\nInternet Shutdowns\n\n25 Aug 2022\n\nPost\nዓፀቦ፣ ዓቕሊ ፅበትን ስቃይ: 15 ታሪኻት ከበባ ኢንተርነት ትግራይ\n25 Aug 2022\n\nPost\n\nዓፀቦ፣ ዓቕሊ ፅበትን ስቃይ: 15 ታሪኻት ከበባ ኢንተርነት ትግራይ\n\n25 Aug 2022\n\nInternet Shutdowns\t\t\t\t\n\n\n\n\nInternet Shutdowns \n\n\n\t\t\t\tStranded, suffocated, and in pain: 15 stories from Tigray’s internet siege\t\t\t\n\n28 Jul 2022\n • \nIt’s been two years since Tigray were cut off from the internet. Share the 15 stories from Tigrayans and help amplify their voices.\n\n\n\n\nPost\nStranded, suffocated, and in pain: 15 stories from Tigray’s internet siege\n28 Jul 2022\n\nStranded, suffocated, and in pain: 15 stories from Tigray’s internet siege\n\nInternet Shutdowns\t\t\t\t\n\n\n\n\nInternet Shutdowns \n\n\n\t\t\t\tStranded, suffocated, and in pain: 15 stories from Tigray’s internet siege\t\t\t\n\n28 Jul 2022\n • \nIt’s been two years since Tigray were cut off from the internet. Share the 15 stories from Tigrayans and help amplify their voices.\n\nInternet Shutdowns\n\nInternet Shutdowns\n\nInternet Shutdowns \n\n\n\t\t\t\tStranded, suffocated, and in pain: 15 stories from Tigray’s internet siege\t\t\t\n\n28 Jul 2022\n • \nIt’s been two years since Tigray were cut off from the internet. Share the 15 stories from Tigrayans and help amplify their voices.\n\nInternet Shutdowns\n\nInternet Shutdowns\n\n28 Jul 2022\n • \nIt’s been two years since Tigray were cut off from the internet. Share the 15 stories from Tigrayans and help amplify their voices.\n\nIt’s been two years since Tigray were cut off from the internet. Share the 15 stories from Tigrayans and help amplify their voices.\n\nPost\nStranded, suffocated, and in pain: 15 stories from Tigray’s internet siege\n28 Jul 2022\n\nPost\n\nStranded, suffocated, and in pain: 15 stories from Tigray’s internet siege\n\n28 Jul 2022\n\nContent Governance\t\t\t\t\n\n\n\n\nContent Governance \n\n\n\t\t\t\tJoin us June 6-10 for RightsCon 2022\t\t\t\n\n31 May 2022\n • \nLog in to the RightsCon platform to participate in the world’s leading summit on human rights in the digital age (June 6-10, 2022)!\n\n\n\n\nCampaign\nJoin us June 6-10 for RightsCon 2022\n\n\n↗\n31 May 2022\n\nJoin us June 6-10 for RightsCon 2022\n\nContent Governance\t\t\t\t\n\n\n\n\nContent Governance \n\n\n\t\t\t\tJoin us June 6-10 for RightsCon 2022\t\t\t\n\n31 May 2022\n • \nLog in to the RightsCon platform to participate in the world’s leading summit on human rights in the digital age (June 6-10, 2022)!\n\nContent Governance\n\nContent Governance\n\nContent Governance \n\n\n\t\t\t\tJoin us June 6-10 for RightsCon 2022\t\t\t\n\n31 May 2022\n • \nLog in to the RightsCon platform to participate in the world’s leading summit on human rights in the digital age (June 6-10, 2022)!\n\nContent Governance\n\nContent Governance\n\n31 May 2022\n • \nLog in to the RightsCon platform to participate in the world’s leading summit on human rights in the digital age (June 6-10, 2022)!\n\nLog in to the RightsCon platform to participate in the world’s leading summit on human rights in the digital age (June 6-10, 2022)!\n\nCampaign\nJoin us June 6-10 for RightsCon 2022\n\n\n↗\n31 May 2022\n\nCampaign\n\nJoin us June 6-10 for RightsCon 2022\n\n↗\n\n31 May 2022\n\nContent Governance\t\t\t\t\n\n\n\n\nContent Governance \n\n\n\t\t\t\tStop the misinformation experience: Spotify must intervene\t\t\t\n\n24 Feb 2022\n • \nThrough a letter to Daniel Ek, Co-Founder and CEO at Spotify, Access Now is urging the company to align with basic human rights principles.\n\n\n\n\nPress Release\nStop the misinformation experience: Spotify must intervene\n24 Feb 2022\n\nStop the misinformation experience: Spotify must intervene\n\nContent Governance\t\t\t\t\n\n\n\n\nContent Governance \n\n\n\t\t\t\tStop the misinformation experience: Spotify must intervene\t\t\t\n\n24 Feb 2022\n • \nThrough a letter to Daniel Ek, Co-Founder and CEO at Spotify, Access Now is urging the company to align with basic human rights principles.\n\nContent Governance\n\nContent Governance\n\nContent Governance \n\n\n\t\t\t\tStop the misinformation experience: Spotify must intervene\t\t\t\n\n24 Feb 2022\n • \nThrough a letter to Daniel Ek, Co-Founder and CEO at Spotify, Access Now is urging the company to align with basic human rights principles.\n\nContent Governance\n\nContent Governance\n\n24 Feb 2022\n • \nThrough a letter to Daniel Ek, Co-Founder and CEO at Spotify, Access Now is urging the company to align with basic human rights principles.\n\nThrough a letter to Daniel Ek, Co-Founder and CEO at Spotify, Access Now is urging the company to align with basic human rights principles.\n\nPress Release\nStop the misinformation experience: Spotify must intervene\n24 Feb 2022\n\nPress Release\n\nStop the misinformation experience: Spotify must intervene\n\n24 Feb 2022\n\nFreedom of Expression\t\t\t\t\n\n\n\n\nFreedom of Expression \n\n\n\t\t\t\tJoe Rogan and Spotify: Make content moderation about human rights\t\t\t\n\n10 Feb 2022\n • \nIs Spotify willing to allow harmful content like COVID misinformation to spread, prioritizing the companyʼs bottom line over public health?\n\n\n\n\nPost\nJoe Rogan and Spotify: Make content moderation about human rights\n10 Feb 2022\n\nJoe Rogan and Spotify: Make content moderation about human rights\n\nFreedom of Expression\t\t\t\t\n\n\n\n\nFreedom of Expression \n\n\n\t\t\t\tJoe Rogan and Spotify: Make content moderation about human rights\t\t\t\n\n10 Feb 2022\n • \nIs Spotify willing to allow harmful content like COVID misinformation to spread, prioritizing the companyʼs bottom line over public health?\n\nFreedom of Expression\n\nFreedom of Expression\n\nFreedom of Expression \n\n\n\t\t\t\tJoe Rogan and Spotify: Make content moderation about human rights\t\t\t\n\n10 Feb 2022\n • \nIs Spotify willing to allow harmful content like COVID misinformation to spread, prioritizing the companyʼs bottom line over public health?\n\nFreedom of Expression\n\nFreedom of Expression\n\n10 Feb 2022\n • \nIs Spotify willing to allow harmful content like COVID misinformation to spread, prioritizing the companyʼs bottom line over public health?\n\nIs Spotify willing to allow harmful content like COVID misinformation to spread, prioritizing the companyʼs bottom line over public health?\n\nPost\nJoe Rogan and Spotify: Make content moderation about human rights\n10 Feb 2022\n\nPost\n\nJoe Rogan and Spotify: Make content moderation about human rights\n\n10 Feb 2022\n\nContent Governance\t\t\t\t\n\n\n\n\nContent Governance \n\n\n\t\t\t\tWhat is disinformation, why it spreads, and how to stop it\t\t\t\n\n21 Dec 2021\n • \nOur new report explores what disinformation is, and how lawmakers can address the harms it poses to democracy.\n\n\n\n\nPublication\nWhat is disinformation, why it spreads, and how to stop it\n21 Dec 2021\n\nWhat is disinformation, why it spreads, and how to stop it\n\nContent Governance\t\t\t\t\n\n\n\n\nContent Governance \n\n\n\t\t\t\tWhat is disinformation, why it spreads, and how to stop it\t\t\t\n\n21 Dec 2021\n • \nOur new report explores what disinformation is, and how lawmakers can address the harms it poses to democracy.\n\nContent Governance\n\nContent Governance\n\nContent Governance \n\n\n\t\t\t\tWhat is disinformation, why it spreads, and how to stop it\t\t\t\n\n21 Dec 2021\n • \nOur new report explores what disinformation is, and how lawmakers can address the harms it poses to democracy.\n\nContent Governance\n\nContent Governance\n\n21 Dec 2021\n • \nOur new report explores what disinformation is, and how lawmakers can address the harms it poses to democracy.\n\nOur new report explores what disinformation is, and how lawmakers can address the harms it poses to democracy.\n\nPublication\nWhat is disinformation, why it spreads, and how to stop it\n21 Dec 2021\n\nPublication\n\nWhat is disinformation, why it spreads, and how to stop it\n\n21 Dec 2021\n\nCovid-19\t\t\t\t\n\n\n\n\nCovid-19 \n\n\n\t\t\t\tOne Year Under COVID-19 Contact Tracing Apps: What Has Europe Learned? – A report by Access Now and Liberties\t\t\t\n\n28 Oct 2021\n • \nA year after the introduction of COVID-19 Contact Tracing Apps in Europe, Access Now and Liberties look at their impact on digital rights.\n\n\n\n\nPublication\nOne Year Under COVID-19 Contact Tracing Apps: What Has Europe Learned? – A report by Access Now and Liberties\n\n\n↗\n28 Oct 2021\n\nOne Year Under COVID-19 Contact Tracing Apps: What Has Europe Learned? – A report by Access Now and Liberties\n\nCovid-19\t\t\t\t\n\n\n\n\nCovid-19 \n\n\n\t\t\t\tOne Year Under COVID-19 Contact Tracing Apps: What Has Europe Learned? – A report by Access Now and Liberties\t\t\t\n\n28 Oct 2021\n • \nA year after the introduction of COVID-19 Contact Tracing Apps in Europe, Access Now and Liberties look at their impact on digital rights.\n\nCovid-19\n\nCovid-19\n\nCovid-19 \n\n\n\t\t\t\tOne Year Under COVID-19 Contact Tracing Apps: What Has Europe Learned? – A report by Access Now and Liberties\t\t\t\n\n28 Oct 2021\n • \nA year after the introduction of COVID-19 Contact Tracing Apps in Europe, Access Now and Liberties look at their impact on digital rights.\n\nCovid-19\n\nCovid-19\n\n28 Oct 2021\n • \nA year after the introduction of COVID-19 Contact Tracing Apps in Europe, Access Now and Liberties look at their impact on digital rights.\n\nA year after the introduction of COVID-19 Contact Tracing Apps in Europe, Access Now and Liberties look at their impact on digital rights.\n\nPublication\nOne Year Under COVID-19 Contact Tracing Apps: What Has Europe Learned? – A report by Access Now and Liberties\n\n\n↗\n28 Oct 2021\n\nPublication\n\nOne Year Under COVID-19 Contact Tracing Apps: What Has Europe Learned? – A report by Access Now and Liberties\n\n↗\n\n28 Oct 2021\n\nPrivacy\t\t\t\t\n\n\n\n\nPrivacy \n\n\n\t\t\t\tWhat you need to know about the Facebook Papers\t\t\t\n\n26 Oct 2021\n • \nThe Facebook Papers paint a grim picture of how Facebook has repeatedly and knowingly prioritized profit over people’s safety. Here’s a snapshot of what we know so far.\n\n\n\n\nPost\nWhat you need to know about the Facebook Papers\n26 Oct 2021\n\nWhat you need to know about the Facebook Papers\n\nPrivacy\t\t\t\t\n\n\n\n\nPrivacy \n\n\n\t\t\t\tWhat you need to know about the Facebook Papers\t\t\t\n\n26 Oct 2021\n • \nThe Facebook Papers paint a grim picture of how Facebook has repeatedly and knowingly prioritized profit over people’s safety. Here’s a snapshot of what we know so far.\n\nPrivacy\n\nPrivacy\n\nPrivacy \n\n\n\t\t\t\tWhat you need to know about the Facebook Papers\t\t\t\n\n26 Oct 2021\n • \nThe Facebook Papers paint a grim picture of how Facebook has repeatedly and knowingly prioritized profit over people’s safety. Here’s a snapshot of what we know so far.\n\nPrivacy\n\nPrivacy\n\n26 Oct 2021\n • \nThe Facebook Papers paint a grim picture of how Facebook has repeatedly and knowingly prioritized profit over people’s safety. Here’s a snapshot of what we know so far.\n\nThe Facebook Papers paint a grim picture of how Facebook has repeatedly and knowingly prioritized profit over people’s safety. Here’s a snapshot of what we know so far.\n\nPost\nWhat you need to know about the Facebook Papers\n26 Oct 2021\n\nPost\n\nWhat you need to know about the Facebook Papers\n\n26 Oct 2021\n\nNet Neutrality\t\t\t\t\n\n\n\n\nNet Neutrality \n\n\n\t\t\t\tDigital rights champions nominated to lead U.S. FCC and NTIA\t\t\t\n\n26 Oct 2021\n • \nAt long last, U.S. President Biden has nominated public interests advocates to lead the Federal Communications Commission and the National Telecommunications and Information Administration.\n\n\n\n\nPress Release\nDigital rights champions nominated to lead U.S. FCC and NTIA\n26 Oct 2021\n\nDigital rights champions nominated to lead U.S. FCC and NTIA\n\nNet Neutrality\t\t\t\t\n\n\n\n\nNet Neutrality \n\n\n\t\t\t\tDigital rights champions nominated to lead U.S. FCC and NTIA\t\t\t\n\n26 Oct 2021\n • \nAt long last, U.S. President Biden has nominated public interests advocates to lead the Federal Communications Commission and the National Telecommunications and Information Administration.\n\nNet Neutrality\n\nNet Neutrality\n\nNet Neutrality \n\n\n\t\t\t\tDigital rights champions nominated to lead U.S. FCC and NTIA\t\t\t\n\n26 Oct 2021\n • \nAt long last, U.S. President Biden has nominated public interests advocates to lead the Federal Communications Commission and the National Telecommunications and Information Administration.\n\nNet Neutrality\n\nNet Neutrality\n\n26 Oct 2021\n • \nAt long last, U.S. President Biden has nominated public interests advocates to lead the Federal Communications Commission and the National Telecommunications and Information Administration.\n\nAt long last, U.S. President Biden has nominated public interests advocates to lead the Federal Communications Commission and the National Telecommunications and Information Administration.\n\nPress Release\nDigital rights champions nominated to lead U.S. FCC and NTIA\n26 Oct 2021\n\nPress Release\n\nDigital rights champions nominated to lead U.S. FCC and NTIA\n\n26 Oct 2021\n\nContent Governance\t\t\t\t\n\n\n\n\nContent Governance \n\n\n\t\t\t\tWill the Right to Protest survive its migration online?\t\t\t\n\n20 Oct 2021\n • \nState-sanctioned internet shutdowns, increased surveillance, and unequal access to the internet are impacting communities globally. Will the Right to Protest survive its migration online?\n\n\n\n\nPost\nWill the Right to Protest survive its migration online?\n20 Oct 2021\n\nWill the Right to Protest survive its migration online?\n\nContent Governance\t\t\t\t\n\n\n\n\nContent Governance \n\n\n\t\t\t\tWill the Right to Protest survive its migration online?\t\t\t\n\n20 Oct 2021\n • \nState-sanctioned internet shutdowns, increased surveillance, and unequal access to the internet are impacting communities globally. Will the Right to Protest survive its migration online?\n\nContent Governance\n\nContent Governance\n\nContent Governance \n\n\n\t\t\t\tWill the Right to Protest survive its migration online?\t\t\t\n\n20 Oct 2021\n • \nState-sanctioned internet shutdowns, increased surveillance, and unequal access to the internet are impacting communities globally. Will the Right to Protest survive its migration online?\n\nContent Governance\n\nContent Governance\n\n20 Oct 2021\n • \nState-sanctioned internet shutdowns, increased surveillance, and unequal access to the internet are impacting communities globally. Will the Right to Protest survive its migration online?\n\nState-sanctioned internet shutdowns, increased surveillance, and unequal access to the internet are impacting communities globally. Will the Right to Protest survive its migration online?\n\nPost\nWill the Right to Protest survive its migration online?\n20 Oct 2021\n\nPost\n\nWill the Right to Protest survive its migration online?\n\n20 Oct 2021\n\nPrivacy\t\t\t\t\n\n\n\n\nPrivacy \n\n\n\t\t\t\tColombia’s mandatory CoronApp violates people’s privacy and freedom of movement\t\t\t\n\n23 Sep 2021\n\n\n\n\nPress Release\nColombia’s mandatory CoronApp violates people’s privacy and freedom of movement\n23 Sep 2021\n\nColombia’s mandatory CoronApp violates people’s privacy and freedom of movement\n\nPrivacy\t\t\t\t\n\n\n\n\nPrivacy \n\n\n\t\t\t\tColombia’s mandatory CoronApp violates people’s privacy and freedom of movement\t\t\t\n\n23 Sep 2021\n\nPrivacy\n\nPrivacy\n\nPrivacy \n\n\n\t\t\t\tColombia’s mandatory CoronApp violates people’s privacy and freedom of movement\t\t\t\n\n23 Sep 2021\n\nPrivacy\n\nPrivacy\n\n23 Sep 2021\n\nPress Release\nColombia’s mandatory CoronApp violates people’s privacy and freedom of movement\n23 Sep 2021\n\nPress Release\n\nColombia’s mandatory CoronApp violates people’s privacy and freedom of movement\n\n23 Sep 2021\n\nPrivacy\t\t\t\t\n\n\n\n\nPrivacy \n\n\n\t\t\t\tColombia: CoronApp viola la privacidad y la libertad de movimiento de las personas\t\t\t\n\n23 Sep 2021\n\n\n\n\nPress Release\nColombia: CoronApp viola la privacidad y la libertad de movimiento de las personas\n23 Sep 2021\n\nColombia: CoronApp viola la privacidad y la libertad de movimiento de las personas\n\nPrivacy\t\t\t\t\n\n\n\n\nPrivacy \n\n\n\t\t\t\tColombia: CoronApp viola la privacidad y la libertad de movimiento de las personas\t\t\t\n\n23 Sep 2021\n\nPrivacy\n\nPrivacy\n\nPrivacy \n\n\n\t\t\t\tColombia: CoronApp viola la privacidad y la libertad de movimiento de las personas\t\t\t\n\n23 Sep 2021\n\nPrivacy\n\nPrivacy\n\n23 Sep 2021\n\nPress Release\nColombia: CoronApp viola la privacidad y la libertad de movimiento de las personas\n23 Sep 2021\n\nPress Release\n\nColombia: CoronApp viola la privacidad y la libertad de movimiento de las personas\n\n23 Sep 2021\n\nFreedom of Expression\t\t\t\t\n\n\n\n\nFreedom of Expression \n\n\n\t\t\t\tThe internet shutdowns issue\t\t\t\n\n1 Sep 2021\n • \nWith support from the #KeepItOn coalition, Jigsaw is today publishing “The Current: The Internet Shutdowns Issue,” a deep-dive into internet shutdowns.\n\n\n\n\nPress Release\nThe internet shutdowns issue\n1 Sep 2021\n\nThe internet shutdowns issue\n\nFreedom of Expression\t\t\t\t\n\n\n\n\nFreedom of Expression \n\n\n\t\t\t\tThe internet shutdowns issue\t\t\t\n\n1 Sep 2021\n • \nWith support from the #KeepItOn coalition, Jigsaw is today publishing “The Current: The Internet Shutdowns Issue,” a deep-dive into internet shutdowns.\n\nFreedom of Expression\n\nFreedom of Expression\n\nFreedom of Expression \n\n\n\t\t\t\tThe internet shutdowns issue\t\t\t\n\n1 Sep 2021\n • \nWith support from the #KeepItOn coalition, Jigsaw is today publishing “The Current: The Internet Shutdowns Issue,” a deep-dive into internet shutdowns.\n\nFreedom of Expression\n\nFreedom of Expression\n\n1 Sep 2021\n • \nWith support from the #KeepItOn coalition, Jigsaw is today publishing “The Current: The Internet Shutdowns Issue,” a deep-dive into internet shutdowns.\n\nWith support from the #KeepItOn coalition, Jigsaw is today publishing “The Current: The Internet Shutdowns Issue,” a deep-dive into internet shutdowns.\n\nPress Release\nThe internet shutdowns issue\n1 Sep 2021\n\nPress Release\n\nThe internet shutdowns issue\n\n1 Sep 2021\n\nFreedom of Expression\t\t\t\t\n\n\n\n\nFreedom of Expression \n\n\n\t\t\t\tHow Thailand handles COVID: it stokes fear among its critics\t\t\t\n\n24 Aug 2021\n • \nAmidst continuing protests, calls for political reform, and mass dissatisfaction with how Thailand handles COVID, Thailand’s government is doubling down on efforts to throttle dissent and protest online and off. It is relying on laws that it claims protect against “public fear.” In fact, by threatening to censor those who speak out, it is the government that is instigating fear – in a weak bid to distract from flailing governance. \n\n\n\n\nPost\nHow Thailand handles COVID: it stokes fear among its critics\n24 Aug 2021\n\nHow Thailand handles COVID: it stokes fear among its critics\n\nFreedom of Expression\t\t\t\t\n\n\n\n\nFreedom of Expression \n\n\n\t\t\t\tHow Thailand handles COVID: it stokes fear among its critics\t\t\t\n\n24 Aug 2021\n • \nAmidst continuing protests, calls for political reform, and mass dissatisfaction with how Thailand handles COVID, Thailand’s government is doubling down on efforts to throttle dissent and protest online and off. It is relying on laws that it claims protect against “public fear.” In fact, by threatening to censor those who speak out, it is the government that is instigating fear – in a weak bid to distract from flailing governance.\n\nFreedom of Expression\n\nFreedom of Expression\n\nFreedom of Expression \n\n\n\t\t\t\tHow Thailand handles COVID: it stokes fear among its critics\t\t\t\n\n24 Aug 2021\n • \nAmidst continuing protests, calls for political reform, and mass dissatisfaction with how Thailand handles COVID, Thailand’s government is doubling down on efforts to throttle dissent and protest online and off. It is relying on laws that it claims protect against “public fear.” In fact, by threatening to censor those who speak out, it is the government that is instigating fear – in a weak bid to distract from flailing governance.\n\nFreedom of Expression\n\nFreedom of Expression\n\n24 Aug 2021\n • \nAmidst continuing protests, calls for political reform, and mass dissatisfaction with how Thailand handles COVID, Thailand’s government is doubling down on efforts to throttle dissent and protest online and off. It is relying on laws that it claims protect against “public fear.” In fact, by threatening to censor those who speak out, it is the government that is instigating fear – in a weak bid to distract from flailing governance.\n\nAmidst continuing protests, calls for political reform, and mass dissatisfaction with how Thailand handles COVID, Thailand’s government is doubling down on efforts to throttle dissent and protest online and off. It is relying on laws that it claims protect against “public fear.” In fact, by threatening to censor those who speak out, it is the government that is instigating fear – in a weak bid to distract from flailing governance.\n\nPost\nHow Thailand handles COVID: it stokes fear among its critics\n24 Aug 2021\n\nPost\n\nHow Thailand handles COVID: it stokes fear among its critics\n\n24 Aug 2021\n\nCovid-19\t\t\t\t\n\n\n\n\nCovid-19 \n\n\n\t\t\t\tHow to apply for the Emergency Broadband Benefit in the U.S.\t\t\t\n\n13 Aug 2021\n\n\n\n\nPost\nHow to apply for the Emergency Broadband Benefit in the U.S.\n13 Aug 2021\n\nHow to apply for the Emergency Broadband Benefit in the U.S.\n\nCovid-19\t\t\t\t\n\n\n\n\nCovid-19 \n\n\n\t\t\t\tHow to apply for the Emergency Broadband Benefit in the U.S.\t\t\t\n\n13 Aug 2021\n\nCovid-19\n\nCovid-19\n\nCovid-19 \n\n\n\t\t\t\tHow to apply for the Emergency Broadband Benefit in the U.S.\t\t\t\n\n13 Aug 2021\n\nCovid-19\n\nCovid-19\n\n13 Aug 2021\n\nPost\nHow to apply for the Emergency Broadband Benefit in the U.S.\n13 Aug 2021\n\nPost\n\nHow to apply for the Emergency Broadband Benefit in the U.S.\n\n13 Aug 2021\n\nHelp keep the internet open and secure.\nSubscribe to our action alerts and weekly newsletter\n\"*\" indicates required fields\n\nThis field is hidden when viewing the form\n\nSubscribe to Access Express\nThis field is hidden when viewing the form\n\nSubscribe to Action Alerts\nName\n\n\nFirst\n\n\n\nLast\n\nEmail*\n\nCountryCountryAfghanistanÅland IslandsAlbaniaAlgeriaAmerican SamoaAndorraAngolaAnguillaAntigua and BarbudaArgentinaArmeniaArubaAustraliaAustriaAzerbaijanBahamasBahrainBangladeshBarbadosBelarusBelgiumBelizeBeninBermudaBhutanBoliviaBonaire, Sint Eustatius and SabaBosnia and HerzegovinaBotswanaBrazilBritish Indian Ocean TerritoryBritish Virgin IslandsBruneiBulgariaBurkina FasoBurundiCambodiaCameroonCanadaCape VerdeCayman IslandsCentral African RepublicChadChileChinaChristmas IslandColombiaComorosCook IslandsCosta RicaCôte d'IvoireCroatiaCubaCuraçaoCyprusCzech RepublicDemocratic Republic of the CongoDenmarkDjiboutiDominicaDominican RepublicEast TimorEcuadorEgyptEl SalvadorEquatorial GuineaEritreaEstoniaEswatiniEthiopiaFalkland IslandsFaroe IslandsFijiFinlandFranceFrench GuianaFrench PolynesiaFrench Southern TerritoriesGabonGeorgiaGermanyGhanaGibraltarGreeceGreenlandGrenadaGuadeloupeGuamGuatemalaGuernseyGuineaGuinea-BissauGuyanaHaitiHondurasHong KongHungaryIcelandIndiaIndonesiaIranIraqIrelandIsraelItalyJamaicaJapanJordanKazakhstanKenyaKiribatiKosovoKuwaitKyrgyzstanLaosLatviaLebanonLesothoLiberiaLibyaLiechtensteinLithuaniaLuxembourgMacauMadagascarMalawiMalaysiaMaldivesMaliMaltaMarshall IslandsMartiniqueMauritaniaMauritiusMayotteMexicoMicronesiaMoldovaMonacoMongoliaMontenegroMontserratMoroccoMozambiqueMyanmarNamibiaNauruNepalNetherlands AntillesNew CaledoniaNew ZealandNicaraguaNigerNigeriaNiueNorfolk IslandNorth KoreaNorth MacedoniaNorthern Mariana IslandsNorwayOmanPakistanPalauPalestinePanamaPapua New GuineaParaguayPeruPhilippinesPitcairn IslandPolandPortugalPuerto RicoQatarRepublic of the CongoReunionRomaniaRussiaRwandaSaint BarthélemySaint Kitts and NevisSaint LuciaSaint Vincent and the GrenadinesSamoaSan MarinoSão Tomé and PríncipeSaudi ArabiaSenegalSerbiaSeychellesSierra LeoneSingaporeSlovakiaSloveniaSolomon IslandsSomaliaSomalilandSouth AfricaSouth KoreaSouth SudanSpainSri LankaSt. HelenaSt. Pierre and MiquelonSudanSurinameSwedenSwitzerlandSyriaTaiwanTajikistanTanzaniaThailandThe GambiaThe NetherlandsTogoTokelauTongaTrinidad and TobagoTunisiaTurkeyTurkmenistanTurks and Caicos IslandsTuvaluUgandaUkraineUnited Arab EmiratesUnited KingdomUnited StatesUruguayUzbekistanVanuatuVatican CityVenezuelaVietnamVirgin Islands (U.S.)Wallis and Futuna IslandsWestern SaharaYemenZambiaZimbabwePostal CodePhoneThis field is for validation purposes and should be left unchanged.\n \n\n\n\n\n\n\n\n\n\n\n\n\n\n\n\nYour info is secure with us\n\nHelp keep the internet open and secure.\nSubscribe to our action alerts and weekly newsletter\n\"*\" indicates required fields\n\nThis field is hidden when viewing the form\n\nSubscribe to Access Express\nThis field is hidden when viewing the form\n\nSubscribe to Action Alerts\nName\n\n\nFirst\n\n\n\nLast\n\nEmail*\n\nCountryCountryAfghanistanÅland IslandsAlbaniaAlgeriaAmerican SamoaAndorraAngolaAnguillaAntigua and BarbudaArgentinaArmeniaArubaAustraliaAustriaAzerbaijanBahamasBahrainBangladeshBarbadosBelarusBelgiumBelizeBeninBermudaBhutanBoliviaBonaire, Sint Eustatius and SabaBosnia and HerzegovinaBotswanaBrazilBritish Indian Ocean TerritoryBritish Virgin IslandsBruneiBulgariaBurkina FasoBurundiCambodiaCameroonCanadaCape VerdeCayman IslandsCentral African RepublicChadChileChinaChristmas IslandColombiaComorosCook IslandsCosta RicaCôte d'IvoireCroatiaCubaCuraçaoCyprusCzech RepublicDemocratic Republic of the CongoDenmarkDjiboutiDominicaDominican RepublicEast TimorEcuadorEgyptEl SalvadorEquatorial GuineaEritreaEstoniaEswatiniEthiopiaFalkland IslandsFaroe IslandsFijiFinlandFranceFrench GuianaFrench PolynesiaFrench Southern TerritoriesGabonGeorgiaGermanyGhanaGibraltarGreeceGreenlandGrenadaGuadeloupeGuamGuatemalaGuernseyGuineaGuinea-BissauGuyanaHaitiHondurasHong KongHungaryIcelandIndiaIndonesiaIranIraqIrelandIsraelItalyJamaicaJapanJordanKazakhstanKenyaKiribatiKosovoKuwaitKyrgyzstanLaosLatviaLebanonLesothoLiberiaLibyaLiechtensteinLithuaniaLuxembourgMacauMadagascarMalawiMalaysiaMaldivesMaliMaltaMarshall IslandsMartiniqueMauritaniaMauritiusMayotteMexicoMicronesiaMoldovaMonacoMongoliaMontenegroMontserratMoroccoMozambiqueMyanmarNamibiaNauruNepalNetherlands AntillesNew CaledoniaNew ZealandNicaraguaNigerNigeriaNiueNorfolk IslandNorth KoreaNorth MacedoniaNorthern Mariana IslandsNorwayOmanPakistanPalauPalestinePanamaPapua New GuineaParaguayPeruPhilippinesPitcairn IslandPolandPortugalPuerto RicoQatarRepublic of the CongoReunionRomaniaRussiaRwandaSaint BarthélemySaint Kitts and NevisSaint LuciaSaint Vincent and the GrenadinesSamoaSan MarinoSão Tomé and PríncipeSaudi ArabiaSenegalSerbiaSeychellesSierra LeoneSingaporeSlovakiaSloveniaSolomon IslandsSomaliaSomalilandSouth AfricaSouth KoreaSouth SudanSpainSri LankaSt. HelenaSt. Pierre and MiquelonSudanSurinameSwedenSwitzerlandSyriaTaiwanTajikistanTanzaniaThailandThe GambiaThe NetherlandsTogoTokelauTongaTrinidad and TobagoTunisiaTurkeyTurkmenistanTurks and Caicos IslandsTuvaluUgandaUkraineUnited Arab EmiratesUnited KingdomUnited StatesUruguayUzbekistanVanuatuVatican CityVenezuelaVietnamVirgin Islands (U.S.)Wallis and Futuna IslandsWestern SaharaYemenZambiaZimbabwePostal CodePhoneThis field is for validation purposes and should be left unchanged.\n \n\n\n\n\n\n\n\n\n\n\n\n\n\n\n\nYour info is secure with us\n\nHelp keep the internet open and secure.\nSubscribe to our action alerts and weekly newsletter\n\"*\" indicates required fields\n\nThis field is hidden when viewing the form\n\nSubscribe to Access Express\nThis field is hidden when viewing the form\n\nSubscribe to Action Alerts\nName\n\n\nFirst\n\n\n\nLast\n\nEmail*\n\nCountryCountryAfghanistanÅland IslandsAlbaniaAlgeriaAmerican SamoaAndorraAngolaAnguillaAntigua and BarbudaArgentinaArmeniaArubaAustraliaAustriaAzerbaijanBahamasBahrainBangladeshBarbadosBelarusBelgiumBelizeBeninBermudaBhutanBoliviaBonaire, Sint Eustatius and SabaBosnia and HerzegovinaBotswanaBrazilBritish Indian Ocean TerritoryBritish Virgin IslandsBruneiBulgariaBurkina FasoBurundiCambodiaCameroonCanadaCape VerdeCayman IslandsCentral African RepublicChadChileChinaChristmas IslandColombiaComorosCook IslandsCosta RicaCôte d'IvoireCroatiaCubaCuraçaoCyprusCzech RepublicDemocratic Republic of the CongoDenmarkDjiboutiDominicaDominican RepublicEast TimorEcuadorEgyptEl SalvadorEquatorial GuineaEritreaEstoniaEswatiniEthiopiaFalkland IslandsFaroe IslandsFijiFinlandFranceFrench GuianaFrench PolynesiaFrench Southern TerritoriesGabonGeorgiaGermanyGhanaGibraltarGreeceGreenlandGrenadaGuadeloupeGuamGuatemalaGuernseyGuineaGuinea-BissauGuyanaHaitiHondurasHong KongHungaryIcelandIndiaIndonesiaIranIraqIrelandIsraelItalyJamaicaJapanJordanKazakhstanKenyaKiribatiKosovoKuwaitKyrgyzstanLaosLatviaLebanonLesothoLiberiaLibyaLiechtensteinLithuaniaLuxembourgMacauMadagascarMalawiMalaysiaMaldivesMaliMaltaMarshall IslandsMartiniqueMauritaniaMauritiusMayotteMexicoMicronesiaMoldovaMonacoMongoliaMontenegroMontserratMoroccoMozambiqueMyanmarNamibiaNauruNepalNetherlands AntillesNew CaledoniaNew ZealandNicaraguaNigerNigeriaNiueNorfolk IslandNorth KoreaNorth MacedoniaNorthern Mariana IslandsNorwayOmanPakistanPalauPalestinePanamaPapua New GuineaParaguayPeruPhilippinesPitcairn IslandPolandPortugalPuerto RicoQatarRepublic of the CongoReunionRomaniaRussiaRwandaSaint BarthélemySaint Kitts and NevisSaint LuciaSaint Vincent and the GrenadinesSamoaSan MarinoSão Tomé and PríncipeSaudi ArabiaSenegalSerbiaSeychellesSierra LeoneSingaporeSlovakiaSloveniaSolomon IslandsSomaliaSomalilandSouth AfricaSouth KoreaSouth SudanSpainSri LankaSt. HelenaSt. Pierre and MiquelonSudanSurinameSwedenSwitzerlandSyriaTaiwanTajikistanTanzaniaThailandThe GambiaThe NetherlandsTogoTokelauTongaTrinidad and TobagoTunisiaTurkeyTurkmenistanTurks and Caicos IslandsTuvaluUgandaUkraineUnited Arab EmiratesUnited KingdomUnited StatesUruguayUzbekistanVanuatuVatican CityVenezuelaVietnamVirgin Islands (U.S.)Wallis and Futuna IslandsWestern SaharaYemenZambiaZimbabwePostal CodePhoneThis field is for validation purposes and should be left unchanged.\n\nHelp keep the internet open and secure.\nSubscribe to our action alerts and weekly newsletter\n\"*\" indicates required fields\n\nSubscribe to our action alerts and weekly newsletter\n\n\"*\" indicates required fields\n\nThis field is hidden when viewing the form\n\nSubscribe to Access Express\nThis field is hidden when viewing the form\n\nSubscribe to Action Alerts\nName\n\n\nFirst\n\n\n\nLast\n\nEmail*\n\nCountryCountryAfghanistanÅland IslandsAlbaniaAlgeriaAmerican SamoaAndorraAngolaAnguillaAntigua and BarbudaArgentinaArmeniaArubaAustraliaAustriaAzerbaijanBahamasBahrainBangladeshBarbadosBelarusBelgiumBelizeBeninBermudaBhutanBoliviaBonaire, Sint Eustatius and SabaBosnia and HerzegovinaBotswanaBrazilBritish Indian Ocean TerritoryBritish Virgin IslandsBruneiBulgariaBurkina FasoBurundiCambodiaCameroonCanadaCape VerdeCayman IslandsCentral African RepublicChadChileChinaChristmas IslandColombiaComorosCook IslandsCosta RicaCôte d'IvoireCroatiaCubaCuraçaoCyprusCzech RepublicDemocratic Republic of the CongoDenmarkDjiboutiDominicaDominican RepublicEast TimorEcuadorEgyptEl SalvadorEquatorial GuineaEritreaEstoniaEswatiniEthiopiaFalkland IslandsFaroe IslandsFijiFinlandFranceFrench GuianaFrench PolynesiaFrench Southern TerritoriesGabonGeorgiaGermanyGhanaGibraltarGreeceGreenlandGrenadaGuadeloupeGuamGuatemalaGuernseyGuineaGuinea-BissauGuyanaHaitiHondurasHong KongHungaryIcelandIndiaIndonesiaIranIraqIrelandIsraelItalyJamaicaJapanJordanKazakhstanKenyaKiribatiKosovoKuwaitKyrgyzstanLaosLatviaLebanonLesothoLiberiaLibyaLiechtensteinLithuaniaLuxembourgMacauMadagascarMalawiMalaysiaMaldivesMaliMaltaMarshall IslandsMartiniqueMauritaniaMauritiusMayotteMexicoMicronesiaMoldovaMonacoMongoliaMontenegroMontserratMoroccoMozambiqueMyanmarNamibiaNauruNepalNetherlands AntillesNew CaledoniaNew ZealandNicaraguaNigerNigeriaNiueNorfolk IslandNorth KoreaNorth MacedoniaNorthern Mariana IslandsNorwayOmanPakistanPalauPalestinePanamaPapua New GuineaParaguayPeruPhilippinesPitcairn IslandPolandPortugalPuerto RicoQatarRepublic of the CongoReunionRomaniaRussiaRwandaSaint BarthélemySaint Kitts and NevisSaint LuciaSaint Vincent and the GrenadinesSamoaSan MarinoSão Tomé and PríncipeSaudi ArabiaSenegalSerbiaSeychellesSierra LeoneSingaporeSlovakiaSloveniaSolomon IslandsSomaliaSomalilandSouth AfricaSouth KoreaSouth SudanSpainSri LankaSt. HelenaSt. Pierre and MiquelonSudanSurinameSwedenSwitzerlandSyriaTaiwanTajikistanTanzaniaThailandThe GambiaThe NetherlandsTogoTokelauTongaTrinidad and TobagoTunisiaTurkeyTurkmenistanTurks and Caicos IslandsTuvaluUgandaUkraineUnited Arab EmiratesUnited KingdomUnited StatesUruguayUzbekistanVanuatuVatican CityVenezuelaVietnamVirgin Islands (U.S.)Wallis and Futuna IslandsWestern SaharaYemenZambiaZimbabwePostal CodePhoneThis field is for validation purposes and should be left unchanged.\n\nThis field is hidden when viewing the form\n\nSubscribe to Access Express\nThis field is hidden when viewing the form\n\nSubscribe to Action Alerts\nName\n\n\nFirst\n\n\n\nLast\n\nEmail*\n\nCountryCountryAfghanistanÅland IslandsAlbaniaAlgeriaAmerican SamoaAndorraAngolaAnguillaAntigua and BarbudaArgentinaArmeniaArubaAustraliaAustriaAzerbaijanBahamasBahrainBangladeshBarbadosBelarusBelgiumBelizeBeninBermudaBhutanBoliviaBonaire, Sint Eustatius and SabaBosnia and HerzegovinaBotswanaBrazilBritish Indian Ocean TerritoryBritish Virgin IslandsBruneiBulgariaBurkina FasoBurundiCambodiaCameroonCanadaCape VerdeCayman IslandsCentral African RepublicChadChileChinaChristmas IslandColombiaComorosCook IslandsCosta RicaCôte d'IvoireCroatiaCubaCuraçaoCyprusCzech RepublicDemocratic Republic of the CongoDenmarkDjiboutiDominicaDominican RepublicEast TimorEcuadorEgyptEl SalvadorEquatorial GuineaEritreaEstoniaEswatiniEthiopiaFalkland IslandsFaroe IslandsFijiFinlandFranceFrench GuianaFrench PolynesiaFrench Southern TerritoriesGabonGeorgiaGermanyGhanaGibraltarGreeceGreenlandGrenadaGuadeloupeGuamGuatemalaGuernseyGuineaGuinea-BissauGuyanaHaitiHondurasHong KongHungaryIcelandIndiaIndonesiaIranIraqIrelandIsraelItalyJamaicaJapanJordanKazakhstanKenyaKiribatiKosovoKuwaitKyrgyzstanLaosLatviaLebanonLesothoLiberiaLibyaLiechtensteinLithuaniaLuxembourgMacauMadagascarMalawiMalaysiaMaldivesMaliMaltaMarshall IslandsMartiniqueMauritaniaMauritiusMayotteMexicoMicronesiaMoldovaMonacoMongoliaMontenegroMontserratMoroccoMozambiqueMyanmarNamibiaNauruNepalNetherlands AntillesNew CaledoniaNew ZealandNicaraguaNigerNigeriaNiueNorfolk IslandNorth KoreaNorth MacedoniaNorthern Mariana IslandsNorwayOmanPakistanPalauPalestinePanamaPapua New GuineaParaguayPeruPhilippinesPitcairn IslandPolandPortugalPuerto RicoQatarRepublic of the CongoReunionRomaniaRussiaRwandaSaint BarthélemySaint Kitts and NevisSaint LuciaSaint Vincent and the GrenadinesSamoaSan MarinoSão Tomé and PríncipeSaudi ArabiaSenegalSerbiaSeychellesSierra LeoneSingaporeSlovakiaSloveniaSolomon IslandsSomaliaSomalilandSouth AfricaSouth KoreaSouth SudanSpainSri LankaSt. HelenaSt. Pierre and MiquelonSudanSurinameSwedenSwitzerlandSyriaTaiwanTajikistanTanzaniaThailandThe GambiaThe NetherlandsTogoTokelauTongaTrinidad and TobagoTunisiaTurkeyTurkmenistanTurks and Caicos IslandsTuvaluUgandaUkraineUnited Arab EmiratesUnited KingdomUnited StatesUruguayUzbekistanVanuatuVatican CityVenezuelaVietnamVirgin Islands (U.S.)Wallis and Futuna IslandsWestern SaharaYemenZambiaZimbabwePostal CodePhoneThis field is for validation purposes and should be left unchanged.\n\nThis field is hidden when viewing the form\n\nSubscribe to Access Express\n\nSubscribe to Access Express\n\nSubscribe to Access Express\n\nThis field is hidden when viewing the form\n\nSubscribe to Action Alerts\n\nSubscribe to Action Alerts\n\nSubscribe to Action Alerts\n\nFirst\n\n\n\nLast\n\nEmail*\n\nCountryCountryAfghanistanÅland IslandsAlbaniaAlgeriaAmerican SamoaAndorraAngolaAnguillaAntigua and BarbudaArgentinaArmeniaArubaAustraliaAustriaAzerbaijanBahamasBahrainBangladeshBarbadosBelarusBelgiumBelizeBeninBermudaBhutanBoliviaBonaire, Sint Eustatius and SabaBosnia and HerzegovinaBotswanaBrazilBritish Indian Ocean TerritoryBritish Virgin IslandsBruneiBulgariaBurkina FasoBurundiCambodiaCameroonCanadaCape VerdeCayman IslandsCentral African RepublicChadChileChinaChristmas IslandColombiaComorosCook IslandsCosta RicaCôte d'IvoireCroatiaCubaCuraçaoCyprusCzech RepublicDemocratic Republic of the CongoDenmarkDjiboutiDominicaDominican RepublicEast TimorEcuadorEgyptEl SalvadorEquatorial GuineaEritreaEstoniaEswatiniEthiopiaFalkland IslandsFaroe IslandsFijiFinlandFranceFrench GuianaFrench PolynesiaFrench Southern TerritoriesGabonGeorgiaGermanyGhanaGibraltarGreeceGreenlandGrenadaGuadeloupeGuamGuatemalaGuernseyGuineaGuinea-BissauGuyanaHaitiHondurasHong KongHungaryIcelandIndiaIndonesiaIranIraqIrelandIsraelItalyJamaicaJapanJordanKazakhstanKenyaKiribatiKosovoKuwaitKyrgyzstanLaosLatviaLebanonLesothoLiberiaLibyaLiechtensteinLithuaniaLuxembourgMacauMadagascarMalawiMalaysiaMaldivesMaliMaltaMarshall IslandsMartiniqueMauritaniaMauritiusMayotteMexicoMicronesiaMoldovaMonacoMongoliaMontenegroMontserratMoroccoMozambiqueMyanmarNamibiaNauruNepalNetherlands AntillesNew CaledoniaNew ZealandNicaraguaNigerNigeriaNiueNorfolk IslandNorth KoreaNorth MacedoniaNorthern Mariana IslandsNorwayOmanPakistanPalauPalestinePanamaPapua New GuineaParaguayPeruPhilippinesPitcairn IslandPolandPortugalPuerto RicoQatarRepublic of the CongoReunionRomaniaRussiaRwandaSaint BarthélemySaint Kitts and NevisSaint LuciaSaint Vincent and the GrenadinesSamoaSan MarinoSão Tomé and PríncipeSaudi ArabiaSenegalSerbiaSeychellesSierra LeoneSingaporeSlovakiaSloveniaSolomon IslandsSomaliaSomalilandSouth AfricaSouth KoreaSouth SudanSpainSri LankaSt. HelenaSt. Pierre and MiquelonSudanSurinameSwedenSwitzerlandSyriaTaiwanTajikistanTanzaniaThailandThe GambiaThe NetherlandsTogoTokelauTongaTrinidad and TobagoTunisiaTurkeyTurkmenistanTurks and Caicos IslandsTuvaluUgandaUkraineUnited Arab EmiratesUnited KingdomUnited StatesUruguayUzbekistanVanuatuVatican CityVenezuelaVietnamVirgin Islands (U.S.)Wallis and Futuna IslandsWestern SaharaYemenZambiaZimbabwe\n\nCountryAfghanistanÅland IslandsAlbaniaAlgeriaAmerican SamoaAndorraAngolaAnguillaAntigua and BarbudaArgentinaArmeniaArubaAustraliaAustriaAzerbaijanBahamasBahrainBangladeshBarbadosBelarusBelgiumBelizeBeninBermudaBhutanBoliviaBonaire, Sint Eustatius and SabaBosnia and HerzegovinaBotswanaBrazilBritish Indian Ocean TerritoryBritish Virgin IslandsBruneiBulgariaBurkina FasoBurundiCambodiaCameroonCanadaCape VerdeCayman IslandsCentral African RepublicChadChileChinaChristmas IslandColombiaComorosCook IslandsCosta RicaCôte d'IvoireCroatiaCubaCuraçaoCyprusCzech RepublicDemocratic Republic of the CongoDenmarkDjiboutiDominicaDominican RepublicEast TimorEcuadorEgyptEl SalvadorEquatorial GuineaEritreaEstoniaEswatiniEthiopiaFalkland IslandsFaroe IslandsFijiFinlandFranceFrench GuianaFrench PolynesiaFrench Southern TerritoriesGabonGeorgiaGermanyGhanaGibraltarGreeceGreenlandGrenadaGuadeloupeGuamGuatemalaGuernseyGuineaGuinea-BissauGuyanaHaitiHondurasHong KongHungaryIcelandIndiaIndonesiaIranIraqIrelandIsraelItalyJamaicaJapanJordanKazakhstanKenyaKiribatiKosovoKuwaitKyrgyzstanLaosLatviaLebanonLesothoLiberiaLibyaLiechtensteinLithuaniaLuxembourgMacauMadagascarMalawiMalaysiaMaldivesMaliMaltaMarshall IslandsMartiniqueMauritaniaMauritiusMayotteMexicoMicronesiaMoldovaMonacoMongoliaMontenegroMontserratMoroccoMozambiqueMyanmarNamibiaNauruNepalNetherlands AntillesNew CaledoniaNew ZealandNicaraguaNigerNigeriaNiueNorfolk IslandNorth KoreaNorth MacedoniaNorthern Mariana IslandsNorwayOmanPakistanPalauPalestinePanamaPapua New GuineaParaguayPeruPhilippinesPitcairn IslandPolandPortugalPuerto RicoQatarRepublic of the CongoReunionRomaniaRussiaRwandaSaint BarthélemySaint Kitts and NevisSaint LuciaSaint Vincent and the GrenadinesSamoaSan MarinoSão Tomé and PríncipeSaudi ArabiaSenegalSerbiaSeychellesSierra LeoneSingaporeSlovakiaSloveniaSolomon IslandsSomaliaSomalilandSouth AfricaSouth KoreaSouth SudanSpainSri LankaSt. HelenaSt. Pierre and MiquelonSudanSurinameSwedenSwitzerlandSyriaTaiwanTajikistanTanzaniaThailandThe GambiaThe NetherlandsTogoTokelauTongaTrinidad and TobagoTunisiaTurkeyTurkmenistanTurks and Caicos IslandsTuvaluUgandaUkraineUnited Arab EmiratesUnited KingdomUnited StatesUruguayUzbekistanVanuatuVatican CityVenezuelaVietnamVirgin Islands (U.S.)Wallis and Futuna IslandsWestern SaharaYemenZambiaZimbabwe\n\nPostal Code\n\nPhoneThis field is for validation purposes and should be left unchanged.\n\nThis field is for validation purposes and should be left unchanged.\n\nYour info is secure with us",
  "date": "",
  "source_type": "other",
  "extracted_at": "2025-04-07T13:46:39.518957",
  "metadata": {
    "description": "Digital Rights In The Covid-19 Fight The COVID-19 pandemic has impacted every part of our lives — including our human rights. Privacy, free expression,",
    "og:type": "article",
    "og:site_name": "Access Now"
  },
  "relevance_score": 0.3166666666666667,
  "summary": "Covid 19\n\n\n\t\t\t\n\t\t\t\tPrivacy and public health: the dos and don’ts for COVID-19 contact tracing apps\n\t\t\t\t\t\t\t\n\n\n\n\n\n\n\n\n\n\n\n\n\nContent Governance\n\n\n\t\t\t\n\t\t\t\tAccess Now releases “Fighting misinformation and defending free expression during COVID-19: recommendations for states”\n\t\t\t\t\t\t\t\n\n\nWe have identified practical examples and promising practices to support policy makers in respecting human rights while developing measures to address disinformation and misinformation during the COVID-19 crisis. Grid View\nList View\n\n\n\n\n\n\n\n\n\n\n\n\n\n\t\t\t\t\tFreedom of Expression\t\t\t\t\n\n\n\n\nFreedom of Expression \n\n\n\t\t\t\tAccess Now oral statement to the UN Global Digital Compact Informal Consultations with Member States and Stakeholders\t\t\t\n\n3 Feb 2023\n • \nAccess Now’s Senior UN Advocacy Officer Laura O’Brien delivered an oral statement to the UN Global Digital Compact Informal Consultations with Member States and Stakeholders on Feb 3 2023. Publication\nAccess Now oral statement to the UN Global Digital Compact Informal Consultations with Member States and Stakeholders\n\n\n↗\n3 Feb 2023\n\nAccess Now oral statement to the UN Global Digital Compact Informal Consultations with Member States and Stakeholders\n\n\n\n\n\n\n\n\n\n\t\t\t\t\tInternet Shutdowns\t\t\t\t\n\n\n\n\nInternet Shutdowns \n\n\n\t\t\t\tዓፀቦ፣ ዓቕሊ ፅበትን ስቃይ: 15 ታሪኻት ከበባ ኢንተርነት ትግራይ\t\t\t\n\n25 Aug 2022\n\n\n\n\nPost\nዓፀቦ፣ ዓቕሊ ፅበትን ስቃይ: 15 ታሪኻት ከበባ ኢንተርነት ትግራይ\n25 Aug 2022\n\nዓፀቦ፣ ዓቕሊ ፅበትን ስቃይ: 15 ታሪኻት ከበባ ኢንተርነት ትግራይ\n\n\n\n\n\n\n\n\n\n\t\t\t\t\tInternet Shutdowns\t\t\t\t\n\n\n\n\nInternet Shutdowns \n\n\n\t\t\t\tStranded, suffocated, and in pain: 15 stories from Tigray’s internet siege\t\t\t\n\n28 Jul 2022\n • \nIt’s been two years since Tigray were cut off from the internet. Post\nStranded, suffocated, and in pain: 15 stories from Tigray’s internet siege\n28 Jul 2022\n\nStranded, suffocated, and in pain: 15 stories from Tigray’s internet siege\n\n\n\n\n\n\n\n\n\n\t\t\t\t\tContent Governance\t\t\t\t\n\n\n\n\nContent Governance \n\n\n\t\t\t\tJoin us June 6-10 for RightsCon 2022\t\t\t\n\n31 May 2022\n • \nLog in to the RightsCon platform to participate in the world’s leading summit on human rights in the digital age (June 6-10, 2022)! Campaign\nJoin us June 6-10 for RightsCon 2022\n\n\n↗\n31 May 2022\n\nJoin us June 6-10 for RightsCon 2022\n\n\n\n\n\n\n\n\n\n\t\t\t\t\tContent Governance\t\t\t\t\n\n\n\n\nContent Governance \n\n\n\t\t\t\tStop the misinformation experience: Spotify must intervene\t\t\t\n\n24 Feb 2022\n • \nThrough a letter to Daniel Ek, Co-Founder and CEO at Spotify, Access Now is urging the company to align with basic human rights principles. Press Release\nStop the misinformation experience: Spotify must intervene\n24 Feb 2022\n\nStop the misinformation experience: Spotify must intervene\n\n\n\n\n\n\n\n\n\n\t\t\t\t\tFreedom of Expression\t\t\t\t\n\n\n\n\nFreedom of Expression \n\n\n\t\t\t\tJoe Rogan and Spotify: Make content moderation about human rights\t\t\t\n\n10 Feb 2022\n • \nIs Spotify willing to allow harmful content like COVID misinformation to spread, prioritizing the companyʼs bottom line over public health? Post\nJoe Rogan and Spotify: Make content moderation about human rights\n10 Feb 2022\n\nJoe Rogan and Spotify: Make content moderation about human rights\n\n\n\n\n\n\n\n\n\n\t\t\t\t\tContent Governance\t\t\t\t\n\n\n\n\nContent Governance \n\n\n\t\t\t\tWhat is disinformation, why it spreads, and how to stop it\t\t\t\n\n21 Dec 2021\n • \nOur new report explores what disinformation is, and how lawmakers can address the harms it poses to democracy. Privacy\t\t\t\t\n\n\n\n\nPrivacy \n\n\n\t\t\t\tColombia’s mandatory CoronApp violates people’s privacy and freedom of movement\t\t\t\n\n23 Sep 2021\n\n\n\n\nPress Release\nColombia’s mandatory CoronApp violates people’s privacy and freedom of movement\n23 Sep 2021\n\nColombia’s mandatory CoronApp violates people’s privacy and freedom of movement\n\n\n\n\n\n\n\n\n\n\t\t\t\t\tPrivacy\t\t\t\t\n\n\n\n\nPrivacy \n\n\n\t\t\t\tColombia: CoronApp viola la privacidad y la libertad de movimiento de las personas\t\t\t\n\n23 Sep 2021\n\n\n\n\nPress Release\nColombia: CoronApp viola la privacidad y la libertad de movimiento de las personas\n23 Sep 2021\n\nColombia: CoronApp viola la privacidad y la libertad de movimiento de las personas\n\n\n\n\n\n\n\n\n\n\t\t\t\t\tFreedom of Expression\t\t\t\t\n\n\n\n\nFreedom of Expression \n\n\n\t\t\t\tThe internet shutdowns issue\t\t\t\n\n1 Sep 2021\n • \nWith support from the #KeepItOn coalition, Jigsaw is today publishing “The Current: The Internet Shutdowns Issue,” a deep-dive into internet shutdowns. Press Release\nThe internet shutdowns issue\n1 Sep 2021\n\nThe internet shutdowns issue\n\n\n\n\n\n\n\n\n\n\t\t\t\t\tFreedom of Expression\t\t\t\t\n\n\n\n\nFreedom of Expression \n\n\n\t\t\t\tHow Thailand handles COVID: it stokes fear among its critics\t\t\t\n\n24 Aug 2021\n • \nAmidst continuing protests, calls for political reform, and mass dissatisfaction with how Thailand handles COVID, Thailand’s government is doubling down on efforts to throttle dissent and protest online and off. Covid 19\n\n\n\t\t\t\n\t\t\t\tPrivacy and public health: the dos and don’ts for COVID-19 contact tracing apps\n\t\t\t\t\t\t\t\n\n\n\n\n\n\n\n\n\n\n\n\n\nContent Governance\n\n\n\t\t\t\n\t\t\t\tAccess Now releases “Fighting misinformation and defending free expression during COVID-19: recommendations for states”\n\t\t\t\t\t\t\t\n\n\nWe have identified practical examples and promising practices to support policy makers in respecting human rights while developing measures to address disinformation and misinformation during the COVID-19 crisis. Grid View\nList View\n\n\n\n\n\n\n\n\n\n\n\n\n\n\t\t\t\t\tFreedom of Expression\t\t\t\t\n\n\n\n\nFreedom of Expression \n\n\n\t\t\t\tAccess Now oral statement to the UN Global Digital Compact Informal Consultations with Member States and Stakeholders\t\t\t\n\n3 Feb 2023\n • \nAccess Now’s Senior UN Advocacy Officer Laura O’Brien delivered an oral statement to the UN Global Digital Compact Informal Consultations with Member States and Stakeholders on Feb 3 2023. Publication\nAccess Now oral statement to the UN Global Digital Compact Informal Consultations with Member States and Stakeholders\n\n\n↗\n3 Feb 2023\n\nAccess Now oral statement to the UN Global Digital Compact Informal Consultations with Member States and Stakeholders\n\n\n\n\n\n\n\n\n\n\t\t\t\t\tInternet Shutdowns\t\t\t\t\n\n\n\n\nInternet Shutdowns \n\n\n\t\t\t\tዓፀቦ፣ ዓቕሊ ፅበትን ስቃይ: 15 ታሪኻት ከበባ ኢንተርነት ትግራይ\t\t\t\n\n25 Aug 2022\n\n\n\n\nPost\nዓፀቦ፣ ዓቕሊ ፅበትን ስቃይ: 15 ታሪኻት ከበባ ኢንተርነት ትግራይ\n25 Aug 2022\n\nዓፀቦ፣ ዓቕሊ ፅበትን ስቃይ: 15 ታሪኻት ከበባ ኢንተርነት ትግራይ\n\n\n\n\n\n\n\n\n\n\t\t\t\t\tInternet Shutdowns\t\t\t\t\n\n\n\n\nInternet Shutdowns \n\n\n\t\t\t\tStranded, suffocated, and in pain: 15 stories from Tigray’s internet siege\t\t\t\n\n28 Jul 2022\n • \nIt’s been two years since Tigray were cut off from the internet. Post\nStranded, suffocated, and in pain: 15 stories from Tigray’s internet siege\n28 Jul 2022\n\nStranded, suffocated, and in pain: 15 stories from Tigray’s internet siege\n\n\n\n\n\n\n\n\n\n\t\t\t\t\tContent Governance\t\t\t\t\n\n\n\n\nContent Governance \n\n\n\t\t\t\tJoin us June 6-10 for RightsCon 2022\t\t\t\n\n31 May 2022\n • \nLog in to the RightsCon platform to participate in the world’s leading summit on human rights in the digital age (June 6-10, 2022)! Campaign\nJoin us June 6-10 for RightsCon 2022\n\n\n↗\n31 May 2022\n\nJoin us June 6-10 for RightsCon 2022\n\n\n\n\n\n\n\n\n\n\t\t\t\t\tContent Governance\t\t\t\t\n\n\n\n\nContent Governance \n\n\n\t\t\t\tStop the misinformation experience: Spotify must intervene\t\t\t\n\n24 Feb 2022\n • \nThrough a letter to Daniel Ek, Co-Founder and CEO at Spotify, Access Now is urging the company to align with basic human rights principles. Press Release\nStop the misinformation experience: Spotify must intervene\n24 Feb 2022\n\nStop the misinformation experience: Spotify must intervene\n\n\n\n\n\n\n\n\n\n\t\t\t\t\tFreedom of Expression\t\t\t\t\n\n\n\n\nFreedom of Expression \n\n\n\t\t\t\tJoe Rogan and Spotify: Make content moderation about human rights\t\t\t\n\n10 Feb 2022\n • \nIs Spotify willing to allow harmful content like COVID misinformation to spread, prioritizing the companyʼs bottom line over public health? Post\nJoe Rogan and Spotify: Make content moderation about human rights\n10 Feb 2022\n\nJoe Rogan and Spotify: Make content moderation about human rights\n\n\n\n\n\n\n\n\n\n\t\t\t\t\tContent Governance\t\t\t\t\n\n\n\n\nContent Governance \n\n\n\t\t\t\tWhat is disinformation, why it spreads, and how to stop it\t\t\t\n\n21 Dec 2021\n • \nOur new report explores what disinformation is, and how lawmakers can address the harms it poses to democracy. Privacy\t\t\t\t\n\n\n\n\nPrivacy \n\n\n\t\t\t\tColombia’s mandatory CoronApp violates people’s privacy and freedom of movement\t\t\t\n\n23 Sep 2021\n\n\n\n\nPress Release\nColombia’s mandatory CoronApp violates people’s privacy and freedom of movement\n23 Sep 2021\n\nColombia’s mandatory CoronApp violates people’s privacy and freedom of movement\n\n\n\n\n\n\n\n\n\n\t\t\t\t\tPrivacy\t\t\t\t\n\n\n\n\nPrivacy \n\n\n\t\t\t\tColombia: CoronApp viola la privacidad y la libertad de movimiento de las personas\t\t\t\n\n23 Sep 2021\n\n\n\n\nPress Release\nColombia: CoronApp viola la privacidad y la libertad de movimiento de las personas\n23 Sep 2021\n\nColombia: CoronApp viola la privacidad y la libertad de movimiento de las personas\n\n\n\n\n\n\n\n\n\n\t\t\t\t\tFreedom of Expression\t\t\t\t\n\n\n\n\nFreedom of Expression \n\n\n\t\t\t\tThe internet shutdowns issue\t\t\t\n\n1 Sep 2021\n • \nWith support from the #KeepItOn coalition, Jigsaw is today publishing “The Current: The Internet Shutdowns Issue,” a deep-dive into internet shutdowns. Press Release\nThe internet shutdowns issue\n1 Sep 2021\n\nThe internet shutdowns issue\n\n\n\n\n\n\n\n\n\n\t\t\t\t\tFreedom of Expression\t\t\t\t\n\n\n\n\nFreedom of Expression \n\n\n\t\t\t\tHow Thailand handles COVID: it stokes fear among its critics\t\t\t\n\n24 Aug 2021\n • \nAmidst continuing protests, calls for political reform, and mass dissatisfaction with how Thailand handles COVID, Thailand’s government is doubling down on efforts to throttle dissent and protest online and off. Covid 19\n\n\n\t\t\t\n\t\t\t\tPrivacy and public health: the dos and don’ts for COVID-19 contact tracing apps\n\t\t\t\t\t\t\t\n\n\n\n\n\n\n\n\n\n\n\n\n\nContent Governance\n\n\n\t\t\t\n\t\t\t\tAccess Now releases “Fighting misinformation and defending free expression during COVID-19: recommendations for states”\n\t\t\t\t\t\t\t\n\n\nWe have identified practical examples and promising practices to support policy makers in respecting human rights while developing measures to address disinformation and misinformation during the COVID-19 crisis. Grid View\nList View\n\n\n\n\n\n\n\n\n\n\n\n\n\n\t\t\t\t\tFreedom of Expression\t\t\t\t\n\n\n\n\nFreedom of Expression \n\n\n\t\t\t\tAccess Now oral statement to the UN Global Digital Compact Informal Consultations with Member States and Stakeholders\t\t\t\n\n3 Feb 2023\n • \nAccess Now’s Senior UN Advocacy Officer Laura O’Brien delivered an oral statement to the UN Global Digital Compact Informal Consultations with Member States and Stakeholders on Feb 3 2023. Publication\nAccess Now oral statement to the UN Global Digital Compact Informal Consultations with Member States and Stakeholders\n\n\n↗\n3 Feb 2023\n\nAccess Now oral statement to the UN Global Digital Compact Informal Consultations with Member States and Stakeholders\n\n\n\n\n\n\n\n\n\n\t\t\t\t\tInternet Shutdowns\t\t\t\t\n\n\n\n\nInternet Shutdowns \n\n\n\t\t\t\tዓፀቦ፣ ዓቕሊ ፅበትን ስቃይ: 15 ታሪኻት ከበባ ኢንተርነት ትግራይ\t\t\t\n\n25 Aug 2022\n\n\n\n\nPost\nዓፀቦ፣ ዓቕሊ ፅበትን ስቃይ: 15 ታሪኻት ከበባ ኢንተርነት ትግራይ\n25 Aug 2022\n\nዓፀቦ፣ ዓቕሊ ፅበትን ስቃይ: 15 ታሪኻት ከበባ ኢንተርነት ትግራይ\n\n\n\n\n\n\n\n\n\n\t\t\t\t\tInternet Shutdowns\t\t\t\t\n\n\n\n\nInternet Shutdowns \n\n\n\t\t\t\tStranded, suffocated, and in pain: 15 stories from Tigray’s internet siege\t\t\t\n\n28 Jul 2022\n • \nIt’s been two years since Tigray were cut off from the internet. Post\nStranded, suffocated, and in pain: 15 stories from Tigray’s internet siege\n28 Jul 2022\n\nStranded, suffocated, and in pain: 15 stories from Tigray’s internet siege\n\n\n\n\n\n\n\n\n\n\t\t\t\t\tContent Governance\t\t\t\t\n\n\n\n\nContent Governance \n\n\n\t\t\t\tJoin us June 6-10 for RightsCon 2022\t\t\t\n\n31 May 2022\n • \nLog in to the RightsCon platform to participate in the world’s leading summit on human rights in the digital age (June 6-10, 2022)! Campaign\nJoin us June 6-10 for RightsCon 2022\n\n\n↗\n31 May 2022\n\nJoin us June 6-10 for RightsCon 2022\n\n\n\n\n\n\n\n\n\n\t\t\t\t\tContent Governance\t\t\t\t\n\n\n\n\nContent Governance \n\n\n\t\t\t\tStop the misinformation experience: Spotify must intervene\t\t\t\n\n24 Feb 2022\n • \nThrough a letter to Daniel Ek, Co-Founder and CEO at Spotify, Access Now is urging the company to align with basic human rights principles. Press Release\nStop the misinformation experience: Spotify must intervene\n24 Feb 2022\n\nStop the misinformation experience: Spotify must intervene\n\n\n\n\n\n\n\n\n\n\t\t\t\t\tFreedom of Expression\t\t\t\t\n\n\n\n\nFreedom of Expression \n\n\n\t\t\t\tJoe Rogan and Spotify: Make content moderation about human rights\t\t\t\n\n10 Feb 2022\n • \nIs Spotify willing to allow harmful content like COVID misinformation to spread, prioritizing the companyʼs bottom line over public health? Post\nJoe Rogan and Spotify: Make content moderation about human rights\n10 Feb 2022\n\nJoe Rogan and Spotify: Make content moderation about human rights\n\n\n\n\n\n\n\n\n\n\t\t\t\t\tContent Governance\t\t\t\t\n\n\n\n\nContent Governance \n\n\n\t\t\t\tWhat is disinformation, why it spreads, and how to stop it\t\t\t\n\n21 Dec 2021\n • \nOur new report explores what disinformation is, and how lawmakers can address the harms it poses to democracy. Privacy\t\t\t\t\n\n\n\n\nPrivacy \n\n\n\t\t\t\tColombia’s mandatory CoronApp violates people’s privacy and freedom of movement\t\t\t\n\n23 Sep 2021\n\n\n\n\nPress Release\nColombia’s mandatory CoronApp violates people’s privacy and freedom of movement\n23 Sep 2021\n\nColombia’s mandatory CoronApp violates people’s privacy and freedom of movement\n\n\n\n\n\n\n\n\n\n\t\t\t\t\tPrivacy\t\t\t\t\n\n\n\n\nPrivacy \n\n\n\t\t\t\tColombia: CoronApp viola la privacidad y la libertad de movimiento de las personas\t\t\t\n\n23 Sep 2021\n\n\n\n\nPress Release\nColombia: CoronApp viola la privacidad y la libertad de movimiento de las personas\n23 Sep 2021\n\nColombia: CoronApp viola la privacidad y la libertad de movimiento de las personas\n\n\n\n\n\n\n\n\n\n\t\t\t\t\tFreedom of Expression\t\t\t\t\n\n\n\n\nFreedom of Expression \n\n\n\t\t\t\tThe internet shutdowns issue\t\t\t\n\n1 Sep 2021\n • \nWith support from the #KeepItOn coalition, Jigsaw is today publishing “The Current: The Internet Shutdowns Issue,” a deep-dive into internet shutdowns. Press Release\nThe internet shutdowns issue\n1 Sep 2021\n\nThe internet shutdowns issue\n\n\n\n\n\n\n\n\n\n\t\t\t\t\tFreedom of Expression\t\t\t\t\n\n\n\n\nFreedom of Expression \n\n\n\t\t\t\tHow Thailand handles COVID: it stokes fear among its critics\t\t\t\n\n24 Aug 2021\n • \nAmidst continuing protests, calls for political reform, and mass dissatisfaction with how Thailand handles COVID, Thailand’s government is doubling down on efforts to throttle dissent and protest online and off. Covid 19\n\n\n\t\t\t\n\t\t\t\tPrivacy and public health: the dos and don’ts for COVID-19 contact tracing apps\n\t\t\t\t\t\t\t\n\n\n\n\n\n\n\n\n\n\n\n\n\nContent Governance\n\n\n\t\t\t\n\t\t\t\tAccess Now releases “Fighting misinformation and defending free expression during COVID-19: recommendations for states”\n\t\t\t\t\t\t\t\n\n\nWe have identified practical examples and promising practices to support policy makers in respecting human rights while developing measures to address disinformation and misinformation during the COVID-19 crisis. Grid View\nList View\n\n\n\n\n\n\n\n\n\n\n\n\n\n\t\t\t\t\tFreedom of Expression\t\t\t\t\n\n\n\n\nFreedom of Expression \n\n\n\t\t\t\tAccess Now oral statement to the UN Global Digital Compact Informal Consultations with Member States and Stakeholders\t\t\t\n\n3 Feb 2023\n • \nAccess Now’s Senior UN Advocacy Officer Laura O’Brien delivered an oral statement to the UN Global Digital Compact Informal Consultations with Member States and Stakeholders on Feb 3 2023. Publication\nAccess Now oral statement to the UN Global Digital Compact Informal Consultations with Member States and Stakeholders\n\n\n↗\n3 Feb 2023\n\nAccess Now oral statement to the UN Global Digital Compact Informal Consultations with Member States and Stakeholders\n\n\n\n\n\n\n\n\n\n\t\t\t\t\tInternet Shutdowns\t\t\t\t\n\n\n\n\nInternet Shutdowns \n\n\n\t\t\t\tዓፀቦ፣ ዓቕሊ ፅበትን ስቃይ: 15 ታሪኻት ከበባ ኢንተርነት ትግራይ\t\t\t\n\n25 Aug 2022\n\n\n\n\nPost\nዓፀቦ፣ ዓቕሊ ፅበትን ስቃይ: 15 ታሪኻት ከበባ ኢንተርነት ትግራይ\n25 Aug 2022\n\nዓፀቦ፣ ዓቕሊ ፅበትን ስቃይ: 15 ታሪኻት ከበባ ኢንተርነት ትግራይ\n\n\n\n\n\n\n\n\n\n\t\t\t\t\tInternet Shutdowns\t\t\t\t\n\n\n\n\nInternet Shutdowns \n\n\n\t\t\t\tStranded, suffocated, and in pain: 15 stories from Tigray’s internet siege\t\t\t\n\n28 Jul 2022\n • \nIt’s been two years since Tigray were cut off from the internet. Post\nStranded, suffocated, and in pain: 15 stories from Tigray’s internet siege\n28 Jul 2022\n\nStranded, suffocated, and in pain: 15 stories from Tigray’s internet siege\n\n\n\n\n\n\n\n\n\n\t\t\t\t\tContent Governance\t\t\t\t\n\n\n\n\nContent Governance \n\n\n\t\t\t\tJoin us June 6-10 for RightsCon 2022\t\t\t\n\n31 May 2022\n • \nLog in to the RightsCon platform to participate in the world’s leading summit on human rights in the digital age (June 6-10, 2022)! Campaign\nJoin us June 6-10 for RightsCon 2022\n\n\n↗\n31 May 2022\n\nJoin us June 6-10 for RightsCon 2022\n\n\n\n\n\n\n\n\n\n\t\t\t\t\tContent Governance\t\t\t\t\n\n\n\n\nContent Governance \n\n\n\t\t\t\tStop the misinformation experience: Spotify must intervene\t\t\t\n\n24 Feb 2022\n • \nThrough a letter to Daniel Ek, Co-Founder and CEO at Spotify, Access Now is urging the company to align with basic human rights principles. Press Release\nStop the misinformation experience: Spotify must intervene\n24 Feb 2022\n\nStop the misinformation experience: Spotify must intervene\n\n\n\n\n\n\n\n\n\n\t\t\t\t\tFreedom of Expression\t\t\t\t\n\n\n\n\nFreedom of Expression \n\n\n\t\t\t\tJoe Rogan and Spotify: Make content moderation about human rights\t\t\t\n\n10 Feb 2022\n • \nIs Spotify willing to allow harmful content like COVID misinformation to spread, prioritizing the companyʼs bottom line over public health? Post\nJoe Rogan and Spotify: Make content moderation about human rights\n10 Feb 2022\n\nJoe Rogan and Spotify: Make content moderation about human rights\n\n\n\n\n\n\n\n\n\n\t\t\t\t\tContent Governance\t\t\t\t\n\n\n\n\nContent Governance \n\n\n\t\t\t\tWhat is disinformation, why it spreads, and how to stop it\t\t\t\n\n21 Dec 2021\n • \nOur new report explores what disinformation is, and how lawmakers can address the harms it poses to democracy. Privacy\t\t\t\t\n\n\n\n\nPrivacy \n\n\n\t\t\t\tColombia’s mandatory CoronApp violates people’s privacy and freedom of movement\t\t\t\n\n23 Sep 2021\n\n\n\n\nPress Release\nColombia’s mandatory CoronApp violates people’s privacy and freedom of movement\n23 Sep 2021\n\nColombia’s mandatory CoronApp violates people’s privacy and freedom of movement\n\n\n\n\n\n\n\n\n\n\t\t\t\t\tPrivacy\t\t\t\t\n\n\n\n\nPrivacy \n\n\n\t\t\t\tColombia: CoronApp viola la privacidad y la libertad de movimiento de las personas\t\t\t\n\n23 Sep 2021\n\n\n\n\nPress Release\nColombia: CoronApp viola la privacidad y la libertad de movimiento de las personas\n23 Sep 2021\n\nColombia: CoronApp viola la privacidad y la libertad de movimiento de las personas\n\n\n\n\n\n\n\n\n\n\t\t\t\t\tFreedom of Expression\t\t\t\t\n\n\n\n\nFreedom of Expression \n\n\n\t\t\t\tThe internet shutdowns issue\t\t\t\n\n1 Sep 2021\n • \nWith support from the #KeepItOn coalition, Jigsaw is today publishing “The Current: The Internet Shutdowns Issue,” a deep-dive into internet shutdowns. Press Release\nThe internet shutdowns issue\n1 Sep 2021\n\nThe internet shutdowns issue\n\n\n\n\n\n\n\n\n\n\t\t\t\t\tFreedom of Expression\t\t\t\t\n\n\n\n\nFreedom of Expression \n\n\n\t\t\t\tHow Thailand handles COVID: it stokes fear among its critics\t\t\t\n\n24 Aug 2021\n • \nAmidst continuing protests, calls for political reform, and mass dissatisfaction with how Thailand handles COVID, Thailand’s government is doubling down on efforts to throttle dissent and protest online and off. Covid 19\n\n\n\t\t\t\n\t\t\t\tPrivacy and public health: the dos and don’ts for COVID-19 contact tracing apps\n\t\t\t\t\t\t\t\n\n\n\n\n\n\n\n\n\n\n\n\n\nContent Governance\n\n\n\t\t\t\n\t\t\t\tAccess Now releases “Fighting misinformation and defending free expression during COVID-19: recommendations for states”\n\t\t\t\t\t\t\t\n\n\nWe have identified practical examples and promising practices to support policy makers in respecting human rights while developing measures to address disinformation and misinformation during the COVID-19 crisis. Grid View\nList View\n\n\n\n\n\n\n\n\n\n\n\n\n\n\t\t\t\t\tFreedom of Expression\t\t\t\t\n\n\n\n\nFreedom of Expression \n\n\n\t\t\t\tAccess Now oral statement to the UN Global Digital Compact Informal Consultations with Member States and Stakeholders\t\t\t\n\n3 Feb 2023\n • \nAccess Now’s Senior UN Advocacy Officer Laura O’Brien delivered an oral statement to the UN Global Digital Compact Informal Consultations with Member States and Stakeholders on Feb 3 2023. Publication\nAccess Now oral statement to the UN Global Digital Compact Informal Consultations with Member States and Stakeholders\n\n\n↗\n3 Feb 2023\n\nAccess Now oral statement to the UN Global Digital Compact Informal Consultations with Member States and Stakeholders\n\n\n\n\n\n\n\n\n\n\t\t\t\t\tInternet Shutdowns\t\t\t\t\n\n\n\n\nInternet Shutdowns \n\n\n\t\t\t\tዓፀቦ፣ ዓቕሊ ፅበትን ስቃይ: 15 ታሪኻት ከበባ ኢንተርነት ትግራይ\t\t\t\n\n25 Aug 2022\n\n\n\n\nPost\nዓፀቦ፣ ዓቕሊ ፅበትን ስቃይ: 15 ታሪኻት ከበባ ኢንተርነት ትግራይ\n25 Aug 2022\n\nዓፀቦ፣ ዓቕሊ ፅበትን ስቃይ: 15 ታሪኻት ከበባ ኢንተርነት ትግራይ\n\n\n\n\n\n\n\n\n\n\t\t\t\t\tInternet Shutdowns\t\t\t\t\n\n\n\n\nInternet Shutdowns \n\n\n\t\t\t\tStranded, suffocated, and in pain: 15 stories from Tigray’s internet siege\t\t\t\n\n28 Jul 2022\n • \nIt’s been two years since Tigray were cut off from the internet. Post\nStranded, suffocated, and in pain: 15 stories from Tigray’s internet siege\n28 Jul 2022\n\nStranded, suffocated, and in pain: 15 stories from Tigray’s internet siege\n\n\n\n\n\n\n\n\n\n\t\t\t\t\tContent Governance\t\t\t\t\n\n\n\n\nContent Governance \n\n\n\t\t\t\tJoin us June 6-10 for RightsCon 2022\t\t\t\n\n31 May 2022\n • \nLog in to the RightsCon platform to participate in the world’s leading summit on human rights in the digital age (June 6-10, 2022)! Campaign\nJoin us June 6-10 for RightsCon 2022\n\n\n↗\n31 May 2022\n\nJoin us June 6-10 for RightsCon 2022\n\n\n\n\n\n\n\n\n\n\t\t\t\t\tContent Governance\t\t\t\t\n\n\n\n\nContent Governance \n\n\n\t\t\t\tStop the misinformation experience: Spotify must intervene\t\t\t\n\n24 Feb 2022\n • \nThrough a letter to Daniel Ek, Co-Founder and CEO at Spotify, Access Now is urging the company to align with basic human rights principles. Press Release\nStop the misinformation experience: Spotify must intervene\n24 Feb 2022\n\nStop the misinformation experience: Spotify must intervene\n\n\n\n\n\n\n\n\n\n\t\t\t\t\tFreedom of Expression\t\t\t\t\n\n\n\n\nFreedom of Expression \n\n\n\t\t\t\tJoe Rogan and Spotify: Make content moderation about human rights\t\t\t\n\n10 Feb 2022\n • \nIs Spotify willing to allow harmful content like COVID misinformation to spread, prioritizing the companyʼs bottom line over public health? Post\nJoe Rogan and Spotify: Make content moderation about human rights\n10 Feb 2022\n\nJoe Rogan and Spotify: Make content moderation about human rights\n\n\n\n\n\n\n\n\n\n\t\t\t\t\tContent Governance\t\t\t\t\n\n\n\n\nContent Governance \n\n\n\t\t\t\tWhat is disinformation, why it spreads, and how to stop it\t\t\t\n\n21 Dec 2021\n • \nOur new report explores what disinformation is, and how lawmakers can address the harms it poses to democracy. Privacy\t\t\t\t\n\n\n\n\nPrivacy \n\n\n\t\t\t\tColombia’s mandatory CoronApp violates people’s privacy and freedom of movement\t\t\t\n\n23 Sep 2021\n\n\n\n\nPress Release\nColombia’s mandatory CoronApp violates people’s privacy and freedom of movement\n23 Sep 2021\n\nColombia’s mandatory CoronApp violates people’s privacy and freedom of movement\n\n\n\n\n\n\n\n\n\n\t\t\t\t\tPrivacy\t\t\t\t\n\n\n\n\nPrivacy \n\n\n\t\t\t\tColombia: CoronApp viola la privacidad y la libertad de movimiento de las personas\t\t\t\n\n23 Sep 2021\n\n\n\n\nPress Release\nColombia: CoronApp viola la privacidad y la libertad de movimiento de las personas\n23 Sep 2021\n\nColombia: CoronApp viola la privacidad y la libertad de movimiento de las personas\n\n\n\n\n\n\n\n\n\n\t\t\t\t\tFreedom of Expression\t\t\t\t\n\n\n\n\nFreedom of Expression \n\n\n\t\t\t\tThe internet shutdowns issue\t\t\t\n\n1 Sep 2021\n • \nWith support from the #KeepItOn coalition, Jigsaw is today publishing “The Current: The Internet Shutdowns Issue,” a deep-dive into internet shutdowns. Press Release\nThe internet shutdowns issue\n1 Sep 2021\n\nThe internet shutdowns issue\n\n\n\n\n\n\n\n\n\n\t\t\t\t\tFreedom of Expression\t\t\t\t\n\n\n\n\nFreedom of Expression \n\n\n\t\t\t\tHow Thailand handles COVID: it stokes fear among its critics\t\t\t\n\n24 Aug 2021\n • \nAmidst continuing protests, calls for political reform, and mass dissatisfaction with how Thailand handles COVID, Thailand’s government is doubling down on efforts to throttle dissent and protest online and off. Covid 19\n\n\n\t\t\t\n\t\t\t\tPrivacy and public health: the dos and don’ts for COVID-19 contact tracing apps\n\t\t\t\t\t\t\t\n\n\n\n\n\n\n\n\n\n\n\n\n\nContent Governance\n\n\n\t\t\t\n\t\t\t\tAccess Now releases “Fighting misinformation and defending free expression during COVID-19: recommendations for states”\n\t\t\t\t\t\t\t\n\n\nWe have identified practical examples and promising practices to support policy makers in respecting human rights while developing measures to address disinformation and misinformation during the COVID-19 crisis. Grid View\nList View\n\n\n\n\n\n\n\n\n\n\n\n\n\n\t\t\t\t\tFreedom of Expression\t\t\t\t\n\n\n\n\nFreedom of Expression \n\n\n\t\t\t\tAccess Now oral statement to the UN Global Digital Compact Informal Consultations with Member States and Stakeholders\t\t\t\n\n3 Feb 2023\n • \nAccess Now’s Senior UN Advocacy Officer Laura O’Brien delivered an oral statement to the UN Global Digital Compact Informal Consultations with Member States and Stakeholders on Feb 3 2023. Publication\nAccess Now oral statement to the UN Global Digital Compact Informal Consultations with Member States and Stakeholders\n\n\n↗\n3 Feb 2023\n\nAccess Now oral statement to the UN Global Digital Compact Informal Consultations with Member States and Stakeholders\n\n\n\n\n\n\n\n\n\n\t\t\t\t\tInternet Shutdowns\t\t\t\t\n\n\n\n\nInternet Shutdowns \n\n\n\t\t\t\tዓፀቦ፣ ዓቕሊ ፅበትን ስቃይ: 15 ታሪኻት ከበባ ኢንተርነት ትግራይ\t\t\t\n\n25 Aug 2022\n\n\n\n\nPost\nዓፀቦ፣ ዓቕሊ ፅበትን ስቃይ: 15 ታሪኻት ከበባ ኢንተርነት ትግራይ\n25 Aug 2022\n\nዓፀቦ፣ ዓቕሊ ፅበትን ስቃይ: 15 ታሪኻት ከበባ ኢንተርነት ትግራይ\n\n\n\n\n\n\n\n\n\n\t\t\t\t\tInternet Shutdowns\t\t\t\t\n\n\n\n\nInternet Shutdowns \n\n\n\t\t\t\tStranded, suffocated, and in pain: 15 stories from Tigray’s internet siege\t\t\t\n\n28 Jul 2022\n • \nIt’s been two years since Tigray were cut off from the internet. Post\nStranded, suffocated, and in pain: 15 stories from Tigray’s internet siege\n28 Jul 2022\n\nStranded, suffocated, and in pain: 15 stories from Tigray’s internet siege\n\n\n\n\n\n\n\n\n\n\t\t\t\t\tContent Governance\t\t\t\t\n\n\n\n\nContent Governance \n\n\n\t\t\t\tJoin us June 6-10 for RightsCon 2022\t\t\t\n\n31 May 2022\n • \nLog in to the RightsCon platform to participate in the world’s leading summit on human rights in the digital age (June 6-10, 2022)! Campaign\nJoin us June 6-10 for RightsCon 2022\n\n\n↗\n31 May 2022\n\nJoin us June 6-10 for RightsCon 2022\n\n\n\n\n\n\n\n\n\n\t\t\t\t\tContent Governance\t\t\t\t\n\n\n\n\nContent Governance \n\n\n\t\t\t\tStop the misinformation experience: Spotify must intervene\t\t\t\n\n24 Feb 2022\n • \nThrough a letter to Daniel Ek, Co-Founder and CEO at Spotify, Access Now is urging the company to align with basic human rights principles. Press Release\nStop the misinformation experience: Spotify must intervene\n24 Feb 2022\n\nStop the misinformation experience: Spotify must intervene\n\n\n\n\n\n\n\n\n\n\t\t\t\t\tFreedom of Expression\t\t\t\t\n\n\n\n\nFreedom of Expression \n\n\n\t\t\t\tJoe Rogan and Spotify: Make content moderation about human rights\t\t\t\n\n10 Feb 2022\n • \nIs Spotify willing to allow harmful content like COVID misinformation to spread, prioritizing the companyʼs bottom line over public health? Post\nJoe Rogan and Spotify: Make content moderation about human rights\n10 Feb 2022\n\nJoe Rogan and Spotify: Make content moderation about human rights\n\n\n\n\n\n\n\n\n\n\t\t\t\t\tContent Governance\t\t\t\t\n\n\n\n\nContent Governance \n\n\n\t\t\t\tWhat is disinformation, why it spreads, and how to stop it\t\t\t\n\n21 Dec 2021\n • \nOur new report explores what disinformation is, and how lawmakers can address the harms it poses to democracy. Privacy\t\t\t\t\n\n\n\n\nPrivacy \n\n\n\t\t\t\tColombia’s mandatory CoronApp violates people’s privacy and freedom of movement\t\t\t\n\n23 Sep 2021\n\n\n\n\nPress Release\nColombia’s mandatory CoronApp violates people’s privacy and freedom of movement\n23 Sep 2021\n\nColombia’s mandatory CoronApp violates people’s privacy and freedom of movement\n\n\n\n\n\n\n\n\n\n\t\t\t\t\tPrivacy\t\t\t\t\n\n\n\n\nPrivacy \n\n\n\t\t\t\tColombia: CoronApp viola la privacidad y la libertad de movimiento de las personas\t\t\t\n\n23 Sep 2021\n\n\n\n\nPress Release\nColombia: CoronApp viola la privacidad y la libertad de movimiento de las personas\n23 Sep 2021\n\nColombia: CoronApp viola la privacidad y la libertad de movimiento de las personas\n\n\n\n\n\n\n\n\n\n\t\t\t\t\tFreedom of Expression\t\t\t\t\n\n\n\n\nFreedom of Expression \n\n\n\t\t\t\tThe internet shutdowns issue\t\t\t\n\n1 Sep 2021\n • \nWith support from the #KeepItOn coalition, Jigsaw is today publishing “The Current: The Internet Shutdowns Issue,” a deep-dive into internet shutdowns. Press Release\nThe internet shutdowns issue\n1 Sep 2021\n\nThe internet shutdowns issue\n\n\n\n\n\n\n\n\n\n\t\t\t\t\tFreedom of Expression\t\t\t\t\n\n\n\n\nFreedom of Expression \n\n\n\t\t\t\tHow Thailand handles COVID: it stokes fear among its critics\t\t\t\n\n24 Aug 2021\n • \nAmidst continuing protests, calls for political reform, and mass dissatisfaction with how Thailand handles COVID, Thailand’s government is doubling down on efforts to throttle dissent and protest online and off. Covid 19\n\n\n\t\t\t\n\t\t\t\tPrivacy and public health: the dos and don’ts for COVID-19 contact tracing apps\n\t\t\t\t\t\t\t\n\n\n\n\n\n\n\n\n\n\n\n\n\nContent Governance\n\n\n\t\t\t\n\t\t\t\tAccess Now releases “Fighting misinformation and defending free expression during COVID-19: recommendations for states”\n\t\t\t\t\t\t\t\n\n\nWe have identified practical examples and promising practices to support policy makers in respecting human rights while developing measures to address disinformation and misinformation during the COVID-19 crisis. Grid View\nList View\n\n\n\n\n\n\n\n\n\n\n\n\n\n\t\t\t\t\tFreedom of Expression\t\t\t\t\n\n\n\n\nFreedom of Expression \n\n\n\t\t\t\tAccess Now oral statement to the UN Global Digital Compact Informal Consultations with Member States and Stakeholders\t\t\t\n\n3 Feb 2023\n • \nAccess Now’s Senior UN Advocacy Officer Laura O’Brien delivered an oral statement to the UN Global Digital Compact Informal Consultations with Member States and Stakeholders on Feb 3 2023. Publication\nAccess Now oral statement to the UN Global Digital Compact Informal Consultations with Member States and Stakeholders\n\n\n↗\n3 Feb 2023\n\nAccess Now oral statement to the UN Global Digital Compact Informal Consultations with Member States and Stakeholders\n\n\n\n\n\n\n\n\n\n\t\t\t\t\tInternet Shutdowns\t\t\t\t\n\n\n\n\nInternet Shutdowns \n\n\n\t\t\t\tዓፀቦ፣ ዓቕሊ ፅበትን ስቃይ: 15 ታሪኻት ከበባ ኢንተርነት ትግራይ\t\t\t\n\n25 Aug 2022\n\n\n\n\nPost\nዓፀቦ፣ ዓቕሊ ፅበትን ስቃይ: 15 ታሪኻት ከበባ ኢንተርነት ትግራይ\n25 Aug 2022\n\nዓፀቦ፣ ዓቕሊ ፅበትን ስቃይ: 15 ታሪኻት ከበባ ኢንተርነት ትግራይ\n\n\n\n\n\n\n\n\n\n\t\t\t\t\tInternet Shutdowns\t\t\t\t\n\n\n\n\nInternet Shutdowns \n\n\n\t\t\t\tStranded, suffocated, and in pain: 15 stories from Tigray’s internet siege\t\t\t\n\n28 Jul 2022\n • \nIt’s been two years since Tigray were cut off from the internet. Post\nStranded, suffocated, and in pain: 15 stories from Tigray’s internet siege\n28 Jul 2022\n\nStranded, suffocated, and in pain: 15 stories from Tigray’s internet siege\n\n\n\n\n\n\n\n\n\n\t\t\t\t\tContent Governance\t\t\t\t\n\n\n\n\nContent Governance \n\n\n\t\t\t\tJoin us June 6-10 for RightsCon 2022\t\t\t\n\n31 May 2022\n • \nLog in to the RightsCon platform to participate in the world’s leading summit on human rights in the digital age (June 6-10, 2022)! Campaign\nJoin us June 6-10 for RightsCon 2022\n\n\n↗\n31 May 2022\n\nJoin us June 6-10 for RightsCon 2022\n\n\n\n\n\n\n\n\n\n\t\t\t\t\tContent Governance\t\t\t\t\n\n\n\n\nContent Governance \n\n\n\t\t\t\tStop the misinformation experience: Spotify must intervene\t\t\t\n\n24 Feb 2022\n • \nThrough a letter to Daniel Ek, Co-Founder and CEO at Spotify, Access Now is urging the company to align with basic human rights principles. Press Release\nStop the misinformation experience: Spotify must intervene\n24 Feb 2022\n\nStop the misinformation experience: Spotify must intervene\n\n\n\n\n\n\n\n\n\n\t\t\t\t\tFreedom of Expression\t\t\t\t\n\n\n\n\nFreedom of Expression \n\n\n\t\t\t\tJoe Rogan and Spotify: Make content moderation about human rights\t\t\t\n\n10 Feb 2022\n • \nIs Spotify willing to allow harmful content like COVID misinformation to spread, prioritizing the companyʼs bottom line over public health? Post\nJoe Rogan and Spotify: Make content moderation about human rights\n10 Feb 2022\n\nJoe Rogan and Spotify: Make content moderation about human rights\n\n\n\n\n\n\n\n\n\n\t\t\t\t\tContent Governance\t\t\t\t\n\n\n\n\nContent Governance \n\n\n\t\t\t\tWhat is disinformation, why it spreads, and how to stop it\t\t\t\n\n21 Dec 2021\n • \nOur new report explores what disinformation is, and how lawmakers can address the harms it poses to democracy. Privacy\t\t\t\t\n\n\n\n\nPrivacy \n\n\n\t\t\t\tColombia’s mandatory CoronApp violates people’s privacy and freedom of movement\t\t\t\n\n23 Sep 2021\n\n\n\n\nPress Release\nColombia’s mandatory CoronApp violates people’s privacy and freedom of movement\n23 Sep 2021\n\nColombia’s mandatory CoronApp violates people’s privacy and freedom of movement\n\n\n\n\n\n\n\n\n\n\t\t\t\t\tPrivacy\t\t\t\t\n\n\n\n\nPrivacy \n\n\n\t\t\t\tColombia: CoronApp viola la privacidad y la libertad de movimiento de las personas\t\t\t\n\n23 Sep 2021\n\n\n\n\nPress Release\nColombia: CoronApp viola la privacidad y la libertad de movimiento de las personas\n23 Sep 2021\n\nColombia: CoronApp viola la privacidad y la libertad de movimiento de las personas\n\n\n\n\n\n\n\n\n\n\t\t\t\t\tFreedom of Expression\t\t\t\t\n\n\n\n\nFreedom of Expression \n\n\n\t\t\t\tThe internet shutdowns issue\t\t\t\n\n1 Sep 2021\n • \nWith support from the #KeepItOn coalition, Jigsaw is today publishing “The Current: The Internet Shutdowns Issue,” a deep-dive into internet shutdowns. Press Release\nThe internet shutdowns issue\n1 Sep 2021\n\nThe internet shutdowns issue\n\n\n\n\n\n\n\n\n\n\t\t\t\t\tFreedom of Expression\t\t\t\t\n\n\n\n\nFreedom of Expression \n\n\n\t\t\t\tHow Thailand handles COVID: it stokes fear among its critics\t\t\t\n\n24 Aug 2021\n • \nAmidst continuing protests, calls for political reform, and mass dissatisfaction with how Thailand handles COVID, Thailand’s government is doubling down on efforts to throttle dissent and protest online and off. Covid 19\n\n\n\t\t\t\n\t\t\t\tPrivacy and public health: the dos and don’ts for COVID-19 contact tracing apps\n\t\t\t\t\t\t\t\n\n\n\n\n\n\n\n\n\n\n\n\n\nContent Governance\n\n\n\t\t\t\n\t\t\t\tAccess Now releases “Fighting misinformation and defending free expression during COVID-19: recommendations for states”\n\t\t\t\t\t\t\t\n\n\nWe have identified practical examples and promising practices to support policy makers in respecting human rights while developing measures to address disinformation and misinformation during the COVID-19 crisis. Grid View\nList View\n\n\n\n\n\n\n\n\n\n\n\n\n\n\t\t\t\t\tFreedom of Expression\t\t\t\t\n\n\n\n\nFreedom of Expression \n\n\n\t\t\t\tAccess Now oral statement to the UN Global Digital Compact Informal Consultations with Member States and Stakeholders\t\t\t\n\n3 Feb 2023\n • \nAccess Now’s Senior UN Advocacy Officer Laura O’Brien delivered an oral statement to the UN Global Digital Compact Informal Consultations with Member States and Stakeholders on Feb 3 2023. Publication\nAccess Now oral statement to the UN Global Digital Compact Informal Consultations with Member States and Stakeholders\n\n\n↗\n3 Feb 2023\n\nAccess Now oral statement to the UN Global Digital Compact Informal Consultations with Member States and Stakeholders\n\n\n\n\n\n\n\n\n\n\t\t\t\t\tInternet Shutdowns\t\t\t\t\n\n\n\n\nInternet Shutdowns \n\n\n\t\t\t\tዓፀቦ፣ ዓቕሊ ፅበትን ስቃይ: 15 ታሪኻት ከበባ ኢንተርነት ትግራይ\t\t\t\n\n25 Aug 2022\n\n\n\n\nPost\nዓፀቦ፣ ዓቕሊ ፅበትን ስቃይ: 15 ታሪኻት ከበባ ኢንተርነት ትግራይ\n25 Aug 2022\n\nዓፀቦ፣ ዓቕሊ ፅበትን ስቃይ: 15 ታሪኻት ከበባ ኢንተርነት ትግራይ\n\n\n\n\n\n\n\n\n\n\t\t\t\t\tInternet Shutdowns\t\t\t\t\n\n\n\n\nInternet Shutdowns \n\n\n\t\t\t\tStranded, suffocated, and in pain: 15 stories from Tigray’s internet siege\t\t\t\n\n28 Jul 2022\n • \nIt’s been two years since Tigray were cut off from the internet. Post\nStranded, suffocated, and in pain: 15 stories from Tigray’s internet siege\n28 Jul 2022\n\nStranded, suffocated, and in pain: 15 stories from Tigray’s internet siege\n\n\n\n\n\n\n\n\n\n\t\t\t\t\tContent Governance\t\t\t\t\n\n\n\n\nContent Governance \n\n\n\t\t\t\tJoin us June 6-10 for RightsCon 2022\t\t\t\n\n31 May 2022\n • \nLog in to the RightsCon platform to participate in the world’s leading summit on human rights in the digital age (June 6-10, 2022)! Campaign\nJoin us June 6-10 for RightsCon 2022\n\n\n↗\n31 May 2022\n\nJoin us June 6-10 for RightsCon 2022\n\n\n\n\n\n\n\n\n\n\t\t\t\t\tContent Governance\t\t\t\t\n\n\n\n\nContent Governance \n\n\n\t\t\t\tStop the misinformation experience: Spotify must intervene\t\t\t\n\n24 Feb 2022\n • \nThrough a letter to Daniel Ek, Co-Founder and CEO at Spotify, Access Now is urging the company to align with basic human rights principles. Press Release\nStop the misinformation experience: Spotify must intervene\n24 Feb 2022\n\nStop the misinformation experience: Spotify must intervene\n\n\n\n\n\n\n\n\n\n\t\t\t\t\tFreedom of Expression\t\t\t\t\n\n\n\n\nFreedom of Expression \n\n\n\t\t\t\tJoe Rogan and Spotify: Make content moderation about human rights\t\t\t\n\n10 Feb 2022\n • \nIs Spotify willing to allow harmful content like COVID misinformation to spread, prioritizing the companyʼs bottom line over public health? Post\nJoe Rogan and Spotify: Make content moderation about human rights\n10 Feb 2022\n\nJoe Rogan and Spotify: Make content moderation about human rights\n\n\n\n\n\n\n\n\n\n\t\t\t\t\tContent Governance\t\t\t\t\n\n\n\n\nContent Governance \n\n\n\t\t\t\tWhat is disinformation, why it spreads, and how to stop it\t\t\t\n\n21 Dec 2021\n • \nOur new report explores what disinformation is, and how lawmakers can address the harms it poses to democracy. Privacy\t\t\t\t\n\n\n\n\nPrivacy \n\n\n\t\t\t\tColombia’s mandatory CoronApp violates people’s privacy and freedom of movement\t\t\t\n\n23 Sep 2021\n\n\n\n\nPress Release\nColombia’s mandatory CoronApp violates people’s privacy and freedom of movement\n23 Sep 2021\n\nColombia’s mandatory CoronApp violates people’s privacy and freedom of movement\n\n\n\n\n\n\n\n\n\n\t\t\t\t\tPrivacy\t\t\t\t\n\n\n\n\nPrivacy \n\n\n\t\t\t\tColombia: CoronApp viola la privacidad y la libertad de movimiento de las personas\t\t\t\n\n23 Sep 2021\n\n\n\n\nPress Release\nColombia: CoronApp viola la privacidad y la libertad de movimiento de las personas\n23 Sep 2021\n\nColombia: CoronApp viola la privacidad y la libertad de movimiento de las personas\n\n\n\n\n\n\n\n\n\n\t\t\t\t\tFreedom of Expression\t\t\t\t\n\n\n\n\nFreedom of Expression \n\n\n\t\t\t\tThe internet shutdowns issue\t\t\t\n\n1 Sep 2021\n • \nWith support from the #KeepItOn coalition, Jigsaw is today publishing “The Current: The Internet Shutdowns Issue,” a deep-dive into internet shutdowns. Press Release\nThe internet shutdowns issue\n1 Sep 2021\n\nThe internet shutdowns issue\n\n\n\n\n\n\n\n\n\n\t\t\t\t\tFreedom of Expression\t\t\t\t\n\n\n\n\nFreedom of Expression \n\n\n\t\t\t\tHow Thailand handles COVID: it stokes fear among its critics\t\t\t\n\n24 Aug 2021\n • \nAmidst continuing protests, calls for political reform, and mass dissatisfaction with how Thailand handles COVID, Thailand’s government is doubling down on efforts to throttle dissent and protest online and off. Grid View\nList View\n\n\n\n\n\n\n\n\n\n\n\n\n\n\t\t\t\t\tFreedom of Expression\t\t\t\t\n\n\n\n\nFreedom of Expression \n\n\n\t\t\t\tAccess Now oral statement to the UN Global Digital Compact Informal Consultations with Member States and Stakeholders\t\t\t\n\n3 Feb 2023\n • \nAccess Now’s Senior UN Advocacy Officer Laura O’Brien delivered an oral statement to the UN Global Digital Compact Informal Consultations with Member States and Stakeholders on Feb 3 2023. Publication\nAccess Now oral statement to the UN Global Digital Compact Informal Consultations with Member States and Stakeholders\n\n\n↗\n3 Feb 2023\n\nAccess Now oral statement to the UN Global Digital Compact Informal Consultations with Member States and Stakeholders\n\n\n\n\n\n\n\n\n\n\t\t\t\t\tInternet Shutdowns\t\t\t\t\n\n\n\n\nInternet Shutdowns \n\n\n\t\t\t\tዓፀቦ፣ ዓቕሊ ፅበትን ስቃይ: 15 ታሪኻት ከበባ ኢንተርነት ትግራይ\t\t\t\n\n25 Aug 2022\n\n\n\n\nPost\nዓፀቦ፣ ዓቕሊ ፅበትን ስቃይ: 15 ታሪኻት ከበባ ኢንተርነት ትግራይ\n25 Aug 2022\n\nዓፀቦ፣ ዓቕሊ ፅበትን ስቃይ: 15 ታሪኻት ከበባ ኢንተርነት ትግራይ\n\n\n\n\n\n\n\n\n\n\t\t\t\t\tInternet Shutdowns\t\t\t\t\n\n\n\n\nInternet Shutdowns \n\n\n\t\t\t\tStranded, suffocated, and in pain: 15 stories from Tigray’s internet siege\t\t\t\n\n28 Jul 2022\n • \nIt’s been two years since Tigray were cut off from the internet. Post\nStranded, suffocated, and in pain: 15 stories from Tigray’s internet siege\n28 Jul 2022\n\nStranded, suffocated, and in pain: 15 stories from Tigray’s internet siege\n\n\n\n\n\n\n\n\n\n\t\t\t\t\tContent Governance\t\t\t\t\n\n\n\n\nContent Governance \n\n\n\t\t\t\tJoin us June 6-10 for RightsCon 2022\t\t\t\n\n31 May 2022\n • \nLog in to the RightsCon platform to participate in the world’s leading summit on human rights in the digital age (June 6-10, 2022)! Campaign\nJoin us June 6-10 for RightsCon 2022\n\n\n↗\n31 May 2022\n\nJoin us June 6-10 for RightsCon 2022\n\n\n\n\n\n\n\n\n\n\t\t\t\t\tContent Governance\t\t\t\t\n\n\n\n\nContent Governance \n\n\n\t\t\t\tStop the misinformation experience: Spotify must intervene\t\t\t\n\n24 Feb 2022\n • \nThrough a letter to Daniel Ek, Co-Founder and CEO at Spotify, Access Now is urging the company to align with basic human rights principles. Press Release\nStop the misinformation experience: Spotify must intervene\n24 Feb 2022\n\nStop the misinformation experience: Spotify must intervene\n\n\n\n\n\n\n\n\n\n\t\t\t\t\tFreedom of Expression\t\t\t\t\n\n\n\n\nFreedom of Expression \n\n\n\t\t\t\tJoe Rogan and Spotify: Make content moderation about human rights\t\t\t\n\n10 Feb 2022\n • \nIs Spotify willing to allow harmful content like COVID misinformation to spread, prioritizing the companyʼs bottom line over public health? Post\nJoe Rogan and Spotify: Make content moderation about human rights\n10 Feb 2022\n\nJoe Rogan and Spotify: Make content moderation about human rights\n\n\n\n\n\n\n\n\n\n\t\t\t\t\tContent Governance\t\t\t\t\n\n\n\n\nContent Governance \n\n\n\t\t\t\tWhat is disinformation, why it spreads, and how to stop it\t\t\t\n\n21 Dec 2021\n • \nOur new report explores what disinformation is, and how lawmakers can address the harms it poses to democracy. Privacy\t\t\t\t\n\n\n\n\nPrivacy \n\n\n\t\t\t\tColombia’s mandatory CoronApp violates people’s privacy and freedom of movement\t\t\t\n\n23 Sep 2021\n\n\n\n\nPress Release\nColombia’s mandatory CoronApp violates people’s privacy and freedom of movement\n23 Sep 2021\n\nColombia’s mandatory CoronApp violates people’s privacy and freedom of movement\n\n\n\n\n\n\n\n\n\n\t\t\t\t\tPrivacy\t\t\t\t\n\n\n\n\nPrivacy \n\n\n\t\t\t\tColombia: CoronApp viola la privacidad y la libertad de movimiento de las personas\t\t\t\n\n23 Sep 2021\n\n\n\n\nPress Release\nColombia: CoronApp viola la privacidad y la libertad de movimiento de las personas\n23 Sep 2021\n\nColombia: CoronApp viola la privacidad y la libertad de movimiento de las personas\n\n\n\n\n\n\n\n\n\n\t\t\t\t\tFreedom of Expression\t\t\t\t\n\n\n\n\nFreedom of Expression \n\n\n\t\t\t\tThe internet shutdowns issue\t\t\t\n\n1 Sep 2021\n • \nWith support from the #KeepItOn coalition, Jigsaw is today publishing “The Current: The Internet Shutdowns Issue,” a deep-dive into internet shutdowns. Press Release\nThe internet shutdowns issue\n1 Sep 2021\n\nThe internet shutdowns issue\n\n\n\n\n\n\n\n\n\n\t\t\t\t\tFreedom of Expression\t\t\t\t\n\n\n\n\nFreedom of Expression \n\n\n\t\t\t\tHow Thailand handles COVID: it stokes fear among its critics\t\t\t\n\n24 Aug 2021\n • \nAmidst continuing protests, calls for political reform, and mass dissatisfaction with how Thailand handles COVID, Thailand’s government is doubling down on efforts to throttle dissent and protest online and off. Covid 19\n\n\n\t\t\t\n\t\t\t\tPrivacy and public health: the dos and don’ts for COVID-19 contact tracing apps\n\nCovid 19\n\n\n\t\t\t\n\t\t\t\tPrivacy and public health: the dos and don’ts for COVID-19 contact tracing apps\n\nCovid 19\n\n\n\t\t\t\n\t\t\t\tPrivacy and public health: the dos and don’ts for COVID-19 contact tracing apps\n\nCovid 19\n\nContent Governance\n\n\n\t\t\t\n\t\t\t\tAccess Now releases “Fighting misinformation and defending free expression during COVID-19: recommendations for states”\n\t\t\t\t\t\t\t\n\n\nWe have identified practical examples and promising practices to support policy makers in respecting human rights while developing measures to address disinformation and misinformation during the COVID-19 crisis. Grid View\nList View\n\n\n\n\n\n\n\n\n\n\n\n\n\n\t\t\t\t\tFreedom of Expression\t\t\t\t\n\n\n\n\nFreedom of Expression \n\n\n\t\t\t\tAccess Now oral statement to the UN Global Digital Compact Informal Consultations with Member States and Stakeholders\t\t\t\n\n3 Feb 2023\n • \nAccess Now’s Senior UN Advocacy Officer Laura O’Brien delivered an oral statement to the UN Global Digital Compact Informal Consultations with Member States and Stakeholders on Feb 3 2023. Publication\nAccess Now oral statement to the UN Global Digital Compact Informal Consultations with Member States and Stakeholders\n\n\n↗\n3 Feb 2023\n\nAccess Now oral statement to the UN Global Digital Compact Informal Consultations with Member States and Stakeholders\n\n\n\n\n\n\n\n\n\n\t\t\t\t\tInternet Shutdowns\t\t\t\t\n\n\n\n\nInternet Shutdowns \n\n\n\t\t\t\tዓፀቦ፣ ዓቕሊ ፅበትን ስቃይ: 15 ታሪኻት ከበባ ኢንተርነት ትግራይ\t\t\t\n\n25 Aug 2022\n\n\n\n\nPost\nዓፀቦ፣ ዓቕሊ ፅበትን ስቃይ: 15 ታሪኻት ከበባ ኢንተርነት ትግራይ\n25 Aug 2022\n\nዓፀቦ፣ ዓቕሊ ፅበትን ስቃይ: 15 ታሪኻት ከበባ ኢንተርነት ትግራይ\n\n\n\n\n\n\n\n\n\n\t\t\t\t\tInternet Shutdowns\t\t\t\t\n\n\n\n\nInternet Shutdowns \n\n\n\t\t\t\tStranded, suffocated, and in pain: 15 stories from Tigray’s internet siege\t\t\t\n\n28 Jul 2022\n • \nIt’s been two years since Tigray were cut off from the internet. Post\nStranded, suffocated, and in pain: 15 stories from Tigray’s internet siege\n28 Jul 2022\n\nStranded, suffocated, and in pain: 15 stories from Tigray’s internet siege\n\n\n\n\n\n\n\n\n\n\t\t\t\t\tContent Governance\t\t\t\t\n\n\n\n\nContent Governance \n\n\n\t\t\t\tJoin us June 6-10 for RightsCon 2022\t\t\t\n\n31 May 2022\n • \nLog in to the RightsCon platform to participate in the world’s leading summit on human rights in the digital age (June 6-10, 2022)! Campaign\nJoin us June 6-10 for RightsCon 2022\n\n\n↗\n31 May 2022\n\nJoin us June 6-10 for RightsCon 2022\n\n\n\n\n\n\n\n\n\n\t\t\t\t\tContent Governance\t\t\t\t\n\n\n\n\nContent Governance \n\n\n\t\t\t\tStop the misinformation experience: Spotify must intervene\t\t\t\n\n24 Feb 2022\n • \nThrough a letter to Daniel Ek, Co-Founder and CEO at Spotify, Access Now is urging the company to align with basic human rights principles. Press Release\nStop the misinformation experience: Spotify must intervene\n24 Feb 2022\n\nStop the misinformation experience: Spotify must intervene\n\n\n\n\n\n\n\n\n\n\t\t\t\t\tFreedom of Expression\t\t\t\t\n\n\n\n\nFreedom of Expression \n\n\n\t\t\t\tJoe Rogan and Spotify: Make content moderation about human rights\t\t\t\n\n10 Feb 2022\n • \nIs Spotify willing to allow harmful content like COVID misinformation to spread, prioritizing the companyʼs bottom line over public health? Post\nJoe Rogan and Spotify: Make content moderation about human rights\n10 Feb 2022\n\nJoe Rogan and Spotify: Make content moderation about human rights\n\n\n\n\n\n\n\n\n\n\t\t\t\t\tContent Governance\t\t\t\t\n\n\n\n\nContent Governance \n\n\n\t\t\t\tWhat is disinformation, why it spreads, and how to stop it\t\t\t\n\n21 Dec 2021\n • \nOur new report explores what disinformation is, and how lawmakers can address the harms it poses to democracy. Privacy\t\t\t\t\n\n\n\n\nPrivacy \n\n\n\t\t\t\tColombia’s mandatory CoronApp violates people’s privacy and freedom of movement\t\t\t\n\n23 Sep 2021\n\n\n\n\nPress Release\nColombia’s mandatory CoronApp violates people’s privacy and freedom of movement\n23 Sep 2021\n\nColombia’s mandatory CoronApp violates people’s privacy and freedom of movement\n\n\n\n\n\n\n\n\n\n\t\t\t\t\tPrivacy\t\t\t\t\n\n\n\n\nPrivacy \n\n\n\t\t\t\tColombia: CoronApp viola la privacidad y la libertad de movimiento de las personas\t\t\t\n\n23 Sep 2021\n\n\n\n\nPress Release\nColombia: CoronApp viola la privacidad y la libertad de movimiento de las personas\n23 Sep 2021\n\nColombia: CoronApp viola la privacidad y la libertad de movimiento de las personas\n\n\n\n\n\n\n\n\n\n\t\t\t\t\tFreedom of Expression\t\t\t\t\n\n\n\n\nFreedom of Expression \n\n\n\t\t\t\tThe internet shutdowns issue\t\t\t\n\n1 Sep 2021\n • \nWith support from the #KeepItOn coalition, Jigsaw is today publishing “The Current: The Internet Shutdowns Issue,” a deep-dive into internet shutdowns. Press Release\nThe internet shutdowns issue\n1 Sep 2021\n\nThe internet shutdowns issue\n\n\n\n\n\n\n\n\n\n\t\t\t\t\tFreedom of Expression\t\t\t\t\n\n\n\n\nFreedom of Expression \n\n\n\t\t\t\tHow Thailand handles COVID: it stokes fear among its critics\t\t\t\n\n24 Aug 2021\n • \nAmidst continuing protests, calls for political reform, and mass dissatisfaction with how Thailand handles COVID, Thailand’s government is doubling down on efforts to throttle dissent and protest online and off. Grid View\nList View\n\nGrid View\nList View\n\nGrid View\nList View\n\nFreedom of Expression\t\t\t\t\n\n\n\n\nFreedom of Expression \n\n\n\t\t\t\tAccess Now oral statement to the UN Global Digital Compact Informal Consultations with Member States and Stakeholders\t\t\t\n\n3 Feb 2023\n • \nAccess Now’s Senior UN Advocacy Officer Laura O’Brien delivered an oral statement to the UN Global Digital Compact Informal Consultations with Member States and Stakeholders on Feb 3 2023. Publication\nAccess Now oral statement to the UN Global Digital Compact Informal Consultations with Member States and Stakeholders\n\n\n↗\n3 Feb 2023\n\nAccess Now oral statement to the UN Global Digital Compact Informal Consultations with Member States and Stakeholders\n\n\n\n\n\n\n\n\n\n\t\t\t\t\tInternet Shutdowns\t\t\t\t\n\n\n\n\nInternet Shutdowns \n\n\n\t\t\t\tዓፀቦ፣ ዓቕሊ ፅበትን ስቃይ: 15 ታሪኻት ከበባ ኢንተርነት ትግራይ\t\t\t\n\n25 Aug 2022\n\n\n\n\nPost\nዓፀቦ፣ ዓቕሊ ፅበትን ስቃይ: 15 ታሪኻት ከበባ ኢንተርነት ትግራይ\n25 Aug 2022\n\nዓፀቦ፣ ዓቕሊ ፅበትን ስቃይ: 15 ታሪኻት ከበባ ኢንተርነት ትግራይ\n\n\n\n\n\n\n\n\n\n\t\t\t\t\tInternet Shutdowns\t\t\t\t\n\n\n\n\nInternet Shutdowns \n\n\n\t\t\t\tStranded, suffocated, and in pain: 15 stories from Tigray’s internet siege\t\t\t\n\n28 Jul 2022\n • \nIt’s been two years since Tigray were cut off from the internet. Post\nStranded, suffocated, and in pain: 15 stories from Tigray’s internet siege\n28 Jul 2022\n\nStranded, suffocated, and in pain: 15 stories from Tigray’s internet siege\n\n\n\n\n\n\n\n\n\n\t\t\t\t\tContent Governance\t\t\t\t\n\n\n\n\nContent Governance \n\n\n\t\t\t\tJoin us June 6-10 for RightsCon 2022\t\t\t\n\n31 May 2022\n • \nLog in to the RightsCon platform to participate in the world’s leading summit on human rights in the digital age (June 6-10, 2022)! Campaign\nJoin us June 6-10 for RightsCon 2022\n\n\n↗\n31 May 2022\n\nJoin us June 6-10 for RightsCon 2022\n\n\n\n\n\n\n\n\n\n\t\t\t\t\tContent Governance\t\t\t\t\n\n\n\n\nContent Governance \n\n\n\t\t\t\tStop the misinformation experience: Spotify must intervene\t\t\t\n\n24 Feb 2022\n • \nThrough a letter to Daniel Ek, Co-Founder and CEO at Spotify, Access Now is urging the company to align with basic human rights principles. Press Release\nStop the misinformation experience: Spotify must intervene\n24 Feb 2022\n\nStop the misinformation experience: Spotify must intervene\n\n\n\n\n\n\n\n\n\n\t\t\t\t\tFreedom of Expression\t\t\t\t\n\n\n\n\nFreedom of Expression \n\n\n\t\t\t\tJoe Rogan and Spotify: Make content moderation about human rights\t\t\t\n\n10 Feb 2022\n • \nIs Spotify willing to allow harmful content like COVID misinformation to spread, prioritizing the companyʼs bottom line over public health? Post\nJoe Rogan and Spotify: Make content moderation about human rights\n10 Feb 2022\n\nJoe Rogan and Spotify: Make content moderation about human rights\n\n\n\n\n\n\n\n\n\n\t\t\t\t\tContent Governance\t\t\t\t\n\n\n\n\nContent Governance \n\n\n\t\t\t\tWhat is disinformation, why it spreads, and how to stop it\t\t\t\n\n21 Dec 2021\n • \nOur new report explores what disinformation is, and how lawmakers can address the harms it poses to democracy. Privacy\t\t\t\t\n\n\n\n\nPrivacy \n\n\n\t\t\t\tColombia’s mandatory CoronApp violates people’s privacy and freedom of movement\t\t\t\n\n23 Sep 2021\n\n\n\n\nPress Release\nColombia’s mandatory CoronApp violates people’s privacy and freedom of movement\n23 Sep 2021\n\nColombia’s mandatory CoronApp violates people’s privacy and freedom of movement\n\n\n\n\n\n\n\n\n\n\t\t\t\t\tPrivacy\t\t\t\t\n\n\n\n\nPrivacy \n\n\n\t\t\t\tColombia: CoronApp viola la privacidad y la libertad de movimiento de las personas\t\t\t\n\n23 Sep 2021\n\n\n\n\nPress Release\nColombia: CoronApp viola la privacidad y la libertad de movimiento de las personas\n23 Sep 2021\n\nColombia: CoronApp viola la privacidad y la libertad de movimiento de las personas\n\n\n\n\n\n\n\n\n\n\t\t\t\t\tFreedom of Expression\t\t\t\t\n\n\n\n\nFreedom of Expression \n\n\n\t\t\t\tThe internet shutdowns issue\t\t\t\n\n1 Sep 2021\n • \nWith support from the #KeepItOn coalition, Jigsaw is today publishing “The Current: The Internet Shutdowns Issue,” a deep-dive into internet shutdowns. Press Release\nThe internet shutdowns issue\n1 Sep 2021\n\nThe internet shutdowns issue\n\n\n\n\n\n\n\n\n\n\t\t\t\t\tFreedom of Expression\t\t\t\t\n\n\n\n\nFreedom of Expression \n\n\n\t\t\t\tHow Thailand handles COVID: it stokes fear among its critics\t\t\t\n\n24 Aug 2021\n • \nAmidst continuing protests, calls for political reform, and mass dissatisfaction with how Thailand handles COVID, Thailand’s government is doubling down on efforts to throttle dissent and protest online and off. Freedom of Expression\t\t\t\t\n\n\n\n\nFreedom of Expression \n\n\n\t\t\t\tAccess Now oral statement to the UN Global Digital Compact Informal Consultations with Member States and Stakeholders\t\t\t\n\n3 Feb 2023\n • \nAccess Now’s Senior UN Advocacy Officer Laura O’Brien delivered an oral statement to the UN Global Digital Compact Informal Consultations with Member States and Stakeholders on Feb 3 2023. Publication\nAccess Now oral statement to the UN Global Digital Compact Informal Consultations with Member States and Stakeholders\n\n\n↗\n3 Feb 2023\n\nAccess Now oral statement to the UN Global Digital Compact Informal Consultations with Member States and Stakeholders\n\nFreedom of Expression\t\t\t\t\n\n\n\n\nFreedom of Expression \n\n\n\t\t\t\tAccess Now oral statement to the UN Global Digital Compact Informal Consultations with Member States and Stakeholders\t\t\t\n\n3 Feb 2023\n • \nAccess Now’s Senior UN Advocacy Officer Laura O’Brien delivered an oral statement to the UN Global Digital Compact Informal Consultations with Member States and Stakeholders on Feb 3 2023. Freedom of Expression\n\nFreedom of Expression\n\nFreedom of Expression \n\n\n\t\t\t\tAccess Now oral statement to the UN Global Digital Compact Informal Consultations with Member States and Stakeholders\t\t\t\n\n3 Feb 2023\n • \nAccess Now’s Senior UN Advocacy Officer Laura O’Brien delivered an oral statement to the UN Global Digital Compact Informal Consultations with Member States and Stakeholders on Feb 3 2023. Publication\nAccess Now oral statement to the UN Global Digital Compact Informal Consultations with Member States and Stakeholders\n\n\n↗\n3 Feb 2023\n\nPublication\n\nAccess Now oral statement to the UN Global Digital Compact Informal Consultations with Member States and Stakeholders\n\n↗\n\n3 Feb 2023\n\nInternet Shutdowns\t\t\t\t\n\n\n\n\nInternet Shutdowns \n\n\n\t\t\t\tዓፀቦ፣ ዓቕሊ ፅበትን ስቃይ: 15 ታሪኻት ከበባ ኢንተርነት ትግራይ\t\t\t\n\n25 Aug 2022\n\n\n\n\nPost\nዓፀቦ፣ ዓቕሊ ፅበትን ስቃይ: 15 ታሪኻት ከበባ ኢንተርነት ትግራይ\n25 Aug 2022\n\nዓፀቦ፣ ዓቕሊ ፅበትን ስቃይ: 15 ታሪኻት ከበባ ኢንተርነት ትግራይ\n\nInternet Shutdowns\t\t\t\t\n\n\n\n\nInternet Shutdowns \n\n\n\t\t\t\tዓፀቦ፣ ዓቕሊ ፅበትን ስቃይ: 15 ታሪኻት ከበባ ኢንተርነት ትግራይ\t\t\t\n\n25 Aug 2022\n\nInternet Shutdowns\n\nInternet Shutdowns\n\nInternet Shutdowns \n\n\n\t\t\t\tዓፀቦ፣ ዓቕሊ ፅበትን ስቃይ: 15 ታሪኻት ከበባ ኢንተርነት ትግራይ\t\t\t\n\n25 Aug 2022\n\nInternet Shutdowns\n\nInternet Shutdowns\n\n25 Aug 2022\n\nPost\nዓፀቦ፣ ዓቕሊ ፅበትን ስቃይ: 15 ታሪኻት ከበባ ኢንተርነት ትግራይ\n25 Aug 2022\n\nPost\n\nዓፀቦ፣ ዓቕሊ ፅበትን ስቃይ: 15 ታሪኻት ከበባ ኢንተርነት ትግራይ\n\n25 Aug 2022\n\nInternet Shutdowns\t\t\t\t\n\n\n\n\nInternet Shutdowns \n\n\n\t\t\t\tStranded, suffocated, and in pain: 15 stories from Tigray’s internet siege\t\t\t\n\n28 Jul 2022\n • \nIt’s been two years since Tigray were cut off from the internet. Post\nStranded, suffocated, and in pain: 15 stories from Tigray’s internet siege\n28 Jul 2022\n\nStranded, suffocated, and in pain: 15 stories from Tigray’s internet siege\n\nInternet Shutdowns\t\t\t\t\n\n\n\n\nInternet Shutdowns \n\n\n\t\t\t\tStranded, suffocated, and in pain: 15 stories from Tigray’s internet siege\t\t\t\n\n28 Jul 2022\n • \nIt’s been two years since Tigray were cut off from the internet. Internet Shutdowns\n\nInternet Shutdowns\n\nInternet Shutdowns \n\n\n\t\t\t\tStranded, suffocated, and in pain: 15 stories from Tigray’s internet siege\t\t\t\n\n28 Jul 2022\n • \nIt’s been two years since Tigray were cut off from the internet. Post\nStranded, suffocated, and in pain: 15 stories from Tigray’s internet siege\n28 Jul 2022\n\nPost\n\nStranded, suffocated, and in pain: 15 stories from Tigray’s internet siege\n\n28 Jul 2022\n\nContent Governance\t\t\t\t\n\n\n\n\nContent Governance \n\n\n\t\t\t\tJoin us June 6-10 for RightsCon 2022\t\t\t\n\n31 May 2022\n • \nLog in to the RightsCon platform to participate in the world’s leading summit on human rights in the digital age (June 6-10, 2022)! Campaign\nJoin us June 6-10 for RightsCon 2022\n\n\n↗\n31 May 2022\n\nJoin us June 6-10 for RightsCon 2022\n\nContent Governance\t\t\t\t\n\n\n\n\nContent Governance \n\n\n\t\t\t\tJoin us June 6-10 for RightsCon 2022\t\t\t\n\n31 May 2022\n • \nLog in to the RightsCon platform to participate in the world’s leading summit on human rights in the digital age (June 6-10, 2022)! Content Governance\n\nContent Governance\n\nContent Governance \n\n\n\t\t\t\tJoin us June 6-10 for RightsCon 2022\t\t\t\n\n31 May 2022\n • \nLog in to the RightsCon platform to participate in the world’s leading summit on human rights in the digital age (June 6-10, 2022)! Campaign\nJoin us June 6-10 for RightsCon 2022\n\n\n↗\n31 May 2022\n\nCampaign\n\nJoin us June 6-10 for RightsCon 2022\n\n↗\n\n31 May 2022\n\nContent Governance\t\t\t\t\n\n\n\n\nContent Governance \n\n\n\t\t\t\tStop the misinformation experience: Spotify must intervene\t\t\t\n\n24 Feb 2022\n • \nThrough a letter to Daniel Ek, Co-Founder and CEO at Spotify, Access Now is urging the company to align with basic human rights principles. Press Release\nStop the misinformation experience: Spotify must intervene\n24 Feb 2022\n\nStop the misinformation experience: Spotify must intervene\n\nContent Governance\t\t\t\t\n\n\n\n\nContent Governance \n\n\n\t\t\t\tStop the misinformation experience: Spotify must intervene\t\t\t\n\n24 Feb 2022\n • \nThrough a letter to Daniel Ek, Co-Founder and CEO at Spotify, Access Now is urging the company to align with basic human rights principles. Content Governance\n\nContent Governance\n\nContent Governance \n\n\n\t\t\t\tStop the misinformation experience: Spotify must intervene\t\t\t\n\n24 Feb 2022\n • \nThrough a letter to Daniel Ek, Co-Founder and CEO at Spotify, Access Now is urging the company to align with basic human rights principles. Press Release\nStop the misinformation experience: Spotify must intervene\n24 Feb 2022\n\nPress Release\n\nStop the misinformation experience: Spotify must intervene\n\n24 Feb 2022\n\nFreedom of Expression\t\t\t\t\n\n\n\n\nFreedom of Expression \n\n\n\t\t\t\tJoe Rogan and Spotify: Make content moderation about human rights\t\t\t\n\n10 Feb 2022\n • \nIs Spotify willing to allow harmful content like COVID misinformation to spread, prioritizing the companyʼs bottom line over public health? Post\nJoe Rogan and Spotify: Make content moderation about human rights\n10 Feb 2022\n\nJoe Rogan and Spotify: Make content moderation about human rights\n\nFreedom of Expression\t\t\t\t\n\n\n\n\nFreedom of Expression \n\n\n\t\t\t\tJoe Rogan and Spotify: Make content moderation about human rights\t\t\t\n\n10 Feb 2022\n • \nIs Spotify willing to allow harmful content like COVID misinformation to spread, prioritizing the companyʼs bottom line over public health? Freedom of Expression\n\nFreedom of Expression\n\nFreedom of Expression \n\n\n\t\t\t\tJoe Rogan and Spotify: Make content moderation about human rights\t\t\t\n\n10 Feb 2022\n • \nIs Spotify willing to allow harmful content like COVID misinformation to spread, prioritizing the companyʼs bottom line over public health? Post\nJoe Rogan and Spotify: Make content moderation about human rights\n10 Feb 2022\n\nPost\n\nJoe Rogan and Spotify: Make content moderation about human rights\n\n10 Feb 2022\n\nContent Governance\t\t\t\t\n\n\n\n\nContent Governance \n\n\n\t\t\t\tWhat is disinformation, why it spreads, and how to stop it\t\t\t\n\n21 Dec 2021\n • \nOur new report explores what disinformation is, and how lawmakers can address the harms it poses to democracy. 20 Oct 2021\n\nPrivacy\t\t\t\t\n\n\n\n\nPrivacy \n\n\n\t\t\t\tColombia’s mandatory CoronApp violates people’s privacy and freedom of movement\t\t\t\n\n23 Sep 2021\n\n\n\n\nPress Release\nColombia’s mandatory CoronApp violates people’s privacy and freedom of movement\n23 Sep 2021\n\nColombia’s mandatory CoronApp violates people’s privacy and freedom of movement\n\nPrivacy\t\t\t\t\n\n\n\n\nPrivacy \n\n\n\t\t\t\tColombia’s mandatory CoronApp violates people’s privacy and freedom of movement\t\t\t\n\n23 Sep 2021\n\nPrivacy\n\nPrivacy\n\nPrivacy \n\n\n\t\t\t\tColombia’s mandatory CoronApp violates people’s privacy and freedom of movement\t\t\t\n\n23 Sep 2021\n\nPrivacy\n\nPrivacy\n\n23 Sep 2021\n\nPress Release\nColombia’s mandatory CoronApp violates people’s privacy and freedom of movement\n23 Sep 2021\n\nPress Release\n\nColombia’s mandatory CoronApp violates people’s privacy and freedom of movement\n\n23 Sep 2021\n\nPrivacy\t\t\t\t\n\n\n\n\nPrivacy \n\n\n\t\t\t\tColombia: CoronApp viola la privacidad y la libertad de movimiento de las personas\t\t\t\n\n23 Sep 2021\n\n\n\n\nPress Release\nColombia: CoronApp viola la privacidad y la libertad de movimiento de las personas\n23 Sep 2021\n\nColombia: CoronApp viola la privacidad y la libertad de movimiento de las personas\n\nPrivacy\t\t\t\t\n\n\n\n\nPrivacy \n\n\n\t\t\t\tColombia: CoronApp viola la privacidad y la libertad de movimiento de las personas\t\t\t\n\n23 Sep 2021\n\nPrivacy\n\nPrivacy\n\nPrivacy \n\n\n\t\t\t\tColombia: CoronApp viola la privacidad y la libertad de movimiento de las personas\t\t\t\n\n23 Sep 2021\n\nPrivacy\n\nPrivacy\n\n23 Sep 2021\n\nPress Release\nColombia: CoronApp viola la privacidad y la libertad de movimiento de las personas\n23 Sep 2021\n\nPress Release\n\nColombia: CoronApp viola la privacidad y la libertad de movimiento de las personas\n\n23 Sep 2021\n\nFreedom of Expression\t\t\t\t\n\n\n\n\nFreedom of Expression \n\n\n\t\t\t\tThe internet shutdowns issue\t\t\t\n\n1 Sep 2021\n • \nWith support from the #KeepItOn coalition, Jigsaw is today publishing “The Current: The Internet Shutdowns Issue,” a deep-dive into internet shutdowns. Press Release\nThe internet shutdowns issue\n1 Sep 2021\n\nThe internet shutdowns issue\n\nFreedom of Expression\t\t\t\t\n\n\n\n\nFreedom of Expression \n\n\n\t\t\t\tThe internet shutdowns issue\t\t\t\n\n1 Sep 2021\n • \nWith support from the #KeepItOn coalition, Jigsaw is today publishing “The Current: The Internet Shutdowns Issue,” a deep-dive into internet shutdowns. Freedom of Expression\n\nFreedom of Expression\n\nFreedom of Expression \n\n\n\t\t\t\tThe internet shutdowns issue\t\t\t\n\n1 Sep 2021\n • \nWith support from the #KeepItOn coalition, Jigsaw is today publishing “The Current: The Internet Shutdowns Issue,” a deep-dive into internet shutdowns. Press Release\nThe internet shutdowns issue\n1 Sep 2021\n\nPress Release\n\nThe internet shutdowns issue\n\n1 Sep 2021\n\nFreedom of Expression\t\t\t\t\n\n\n\n\nFreedom of Expression \n\n\n\t\t\t\tHow Thailand handles COVID: it stokes fear among its critics\t\t\t\n\n24 Aug 2021\n • \nAmidst continuing protests, calls for political reform, and mass dissatisfaction with how Thailand handles COVID, Thailand’s government is doubling down on efforts to throttle dissent and protest online and off. Post\nHow Thailand handles COVID: it stokes fear among its critics\n24 Aug 2021\n\nHow Thailand handles COVID: it stokes fear among its critics\n\nFreedom of Expression\t\t\t\t\n\n\n\n\nFreedom of Expression \n\n\n\t\t\t\tHow Thailand handles COVID: it stokes fear among its critics\t\t\t\n\n24 Aug 2021\n • \nAmidst continuing protests, calls for political reform, and mass dissatisfaction with how Thailand handles COVID, Thailand’s government is doubling down on efforts to throttle dissent and protest online and off.",
  "entities": {
    "countries": [
      "afghanistan",
      "australia",
      "brazil",
      "canada",
      "china",
      "france",
      "germany",
      "india",
      "iran",
      "iraq",
      "israel",
      "japan",
      "mexico",
      "north korea",
      "pakistan",
      "russia",
      "south korea",
      "syria",
      "united kingdom",
      "united states",
      "yemen"
    ],
    "organizations": [
      "un",
      "who"
    ],
    "key_issues": [
      "issue",
      "crisis",
      "country",
      "nation",
      "state",
      "government",
      "territory",
      "policy",
      "action",
      "human rights",
      "un",
      "ngo"
    ]
  },
  "committee": "First Committee",
  "topic": "Creating systems to protect against state-sponsored cyber attacks"
}