{
  "url": "https://www.accessnow.org/our-work/",
  "title": "Our Work - Access Now",
  "text": "Back to content\n\nOur work\nAccess Now engages on a wide range of issues at the intersection of human rights and technology, advancing our mission through direct stakeholder engagement and deep collaboration with civil society partners and human rights defenders around the world.\n\n\n\nKey issues\n\n\n\n\nArtificial Intelligence\n\n\n\n\n\n\n\nConnectivity\n\n\n\n\n\n\n\nContent Governance\n\n\n\n\n\n\n\nCovid-19\n\n\n\n\n\n\n\nCybersecurity\n\n\n\n\n\n\n\nData Protection\n\n\n\n\n\n\n\nDigital Divide\n\n\n\n\n\n\n\nDigital Identity Systems\n\n\n\n\n\n\n\nDigital Security\n\n\n\n\n\n\n\nFreedom of Expression\n\n\n\n\n\n\n\nInternet Shutdowns\n\n\n\n\n\n\n\nNet Neutrality\n\n\n\n\n\n\n\nPrivacy\n\n\n\n\n\n\n\nProtest and Online Organizing\n\n\n\n\n\n\n\nSurveillance\n\n\n\n\n\n\n\nTransparency\n\n\n\n\n\n\n\n\n\n\nWho we work with\n\n\n\n\n\n\n\n\nPartnerships\n\nPartnerships\n\nAccess Now is proud to work alongside a vast network of partners across civil society, academia, international and regional bodies, and both the public and private sectors.\n\n\n\n\n\nStakeholders\n\n\n\n\n\n\nPrivate Sector\nWe urge companies to make their practices more transparent, accountable, and rights-respecting, and work with investors to center human rights in their engagement with the tech sector.\n\n\n\n\nInternational Organizations\nWe strategically engage with multilateral institutions, such as the United Nations, to build international norms that strengthen digital rights and to encourage rights-respecting tech policy and governance.\n\n\n\n\nPolicymakers\nWe provide expert guidance to legislators, regulators, and others on best practices for rights-respecting policymaking in the digital age.\n\n\n\n\n\n\nRegions\n\n\n\n\n\n\nMeet Our Team\nWork With Us\n\n\n\n\n\n\n\n\n\n\n \n\n\n\n\n\n\nHelp keep the internet open and secure.\nSubscribe to our action alerts and weekly newsletter\n\"*\" indicates required fields\n\nThis field is hidden when viewing the form\n\nSubscribe to Access Express\nThis field is hidden when viewing the form\n\nSubscribe to Action Alerts\nName\n\n\nFirst\n\n\n\nLast\n\nEmail*\n\nCountryCountryAfghanistanÅland IslandsAlbaniaAlgeriaAmerican SamoaAndorraAngolaAnguillaAntigua and BarbudaArgentinaArmeniaArubaAustraliaAustriaAzerbaijanBahamasBahrainBangladeshBarbadosBelarusBelgiumBelizeBeninBermudaBhutanBoliviaBonaire, Sint Eustatius and SabaBosnia and HerzegovinaBotswanaBrazilBritish Indian Ocean TerritoryBritish Virgin IslandsBruneiBulgariaBurkina FasoBurundiCambodiaCameroonCanadaCape VerdeCayman IslandsCentral African RepublicChadChileChinaChristmas IslandColombiaComorosCook IslandsCosta RicaCôte d'IvoireCroatiaCubaCuraçaoCyprusCzech RepublicDemocratic Republic of the CongoDenmarkDjiboutiDominicaDominican RepublicEast TimorEcuadorEgyptEl SalvadorEquatorial GuineaEritreaEstoniaEswatiniEthiopiaFalkland IslandsFaroe IslandsFijiFinlandFranceFrench GuianaFrench PolynesiaFrench Southern TerritoriesGabonGeorgiaGermanyGhanaGibraltarGreeceGreenlandGrenadaGuadeloupeGuamGuatemalaGuernseyGuineaGuinea-BissauGuyanaHaitiHondurasHong KongHungaryIcelandIndiaIndonesiaIranIraqIrelandIsraelItalyJamaicaJapanJordanKazakhstanKenyaKiribatiKosovoKuwaitKyrgyzstanLaosLatviaLebanonLesothoLiberiaLibyaLiechtensteinLithuaniaLuxembourgMacauMadagascarMalawiMalaysiaMaldivesMaliMaltaMarshall IslandsMartiniqueMauritaniaMauritiusMayotteMexicoMicronesiaMoldovaMonacoMongoliaMontenegroMontserratMoroccoMozambiqueMyanmarNamibiaNauruNepalNetherlands AntillesNew CaledoniaNew ZealandNicaraguaNigerNigeriaNiueNorfolk IslandNorth KoreaNorth MacedoniaNorthern Mariana IslandsNorwayOmanPakistanPalauPalestinePanamaPapua New GuineaParaguayPeruPhilippinesPitcairn IslandPolandPortugalPuerto RicoQatarRepublic of the CongoReunionRomaniaRussiaRwandaSaint BarthélemySaint Kitts and NevisSaint LuciaSaint Vincent and the GrenadinesSamoaSan MarinoSão Tomé and PríncipeSaudi ArabiaSenegalSerbiaSeychellesSierra LeoneSingaporeSlovakiaSloveniaSolomon IslandsSomaliaSomalilandSouth AfricaSouth KoreaSouth SudanSpainSri LankaSt. HelenaSt. Pierre and MiquelonSudanSurinameSwedenSwitzerlandSyriaTaiwanTajikistanTanzaniaThailandThe GambiaThe NetherlandsTogoTokelauTongaTrinidad and TobagoTunisiaTurkeyTurkmenistanTurks and Caicos IslandsTuvaluUgandaUkraineUnited Arab EmiratesUnited KingdomUnited StatesUruguayUzbekistanVanuatuVatican CityVenezuelaVietnamVirgin Islands (U.S.)Wallis and Futuna IslandsWestern SaharaYemenZambiaZimbabwePostal CodeCommentsThis field is for validation purposes and should be left unchanged.\n \n\n\n\n\n\n\n\n\n\n\n\n\n\n\n\nYour info is secure with us\n\nOur work\nAccess Now engages on a wide range of issues at the intersection of human rights and technology, advancing our mission through direct stakeholder engagement and deep collaboration with civil society partners and human rights defenders around the world.\n\n\n\nKey issues\n\n\n\n\nArtificial Intelligence\n\n\n\n\n\n\n\nConnectivity\n\n\n\n\n\n\n\nContent Governance\n\n\n\n\n\n\n\nCovid-19\n\n\n\n\n\n\n\nCybersecurity\n\n\n\n\n\n\n\nData Protection\n\n\n\n\n\n\n\nDigital Divide\n\n\n\n\n\n\n\nDigital Identity Systems\n\n\n\n\n\n\n\nDigital Security\n\n\n\n\n\n\n\nFreedom of Expression\n\n\n\n\n\n\n\nInternet Shutdowns\n\n\n\n\n\n\n\nNet Neutrality\n\n\n\n\n\n\n\nPrivacy\n\n\n\n\n\n\n\nProtest and Online Organizing\n\n\n\n\n\n\n\nSurveillance\n\n\n\n\n\n\n\nTransparency\n\n\n\n\n\n\n\n\n\n\nWho we work with\n\n\n\n\n\n\n\n\nPartnerships\n\nPartnerships\n\nAccess Now is proud to work alongside a vast network of partners across civil society, academia, international and regional bodies, and both the public and private sectors.\n\n\n\n\n\nStakeholders\n\n\n\n\n\n\nPrivate Sector\nWe urge companies to make their practices more transparent, accountable, and rights-respecting, and work with investors to center human rights in their engagement with the tech sector.\n\n\n\n\nInternational Organizations\nWe strategically engage with multilateral institutions, such as the United Nations, to build international norms that strengthen digital rights and to encourage rights-respecting tech policy and governance.\n\n\n\n\nPolicymakers\nWe provide expert guidance to legislators, regulators, and others on best practices for rights-respecting policymaking in the digital age.\n\n\n\n\n\n\nRegions\n\n\n\n\n\n\nMeet Our Team\nWork With Us\n\nOur work\nAccess Now engages on a wide range of issues at the intersection of human rights and technology, advancing our mission through direct stakeholder engagement and deep collaboration with civil society partners and human rights defenders around the world.\n\n\n\nKey issues\n\n\n\n\nArtificial Intelligence\n\n\n\n\n\n\n\nConnectivity\n\n\n\n\n\n\n\nContent Governance\n\n\n\n\n\n\n\nCovid-19\n\n\n\n\n\n\n\nCybersecurity\n\n\n\n\n\n\n\nData Protection\n\n\n\n\n\n\n\nDigital Divide\n\n\n\n\n\n\n\nDigital Identity Systems\n\n\n\n\n\n\n\nDigital Security\n\n\n\n\n\n\n\nFreedom of Expression\n\n\n\n\n\n\n\nInternet Shutdowns\n\n\n\n\n\n\n\nNet Neutrality\n\n\n\n\n\n\n\nPrivacy\n\n\n\n\n\n\n\nProtest and Online Organizing\n\n\n\n\n\n\n\nSurveillance\n\n\n\n\n\n\n\nTransparency\n\n\n\n\n\n\n\n\n\n\nWho we work with\n\n\n\n\n\n\n\n\nPartnerships\n\nPartnerships\n\nAccess Now is proud to work alongside a vast network of partners across civil society, academia, international and regional bodies, and both the public and private sectors.\n\n\n\n\n\nStakeholders\n\n\n\n\n\n\nPrivate Sector\nWe urge companies to make their practices more transparent, accountable, and rights-respecting, and work with investors to center human rights in their engagement with the tech sector.\n\n\n\n\nInternational Organizations\nWe strategically engage with multilateral institutions, such as the United Nations, to build international norms that strengthen digital rights and to encourage rights-respecting tech policy and governance.\n\n\n\n\nPolicymakers\nWe provide expert guidance to legislators, regulators, and others on best practices for rights-respecting policymaking in the digital age.\n\n\n\n\n\n\nRegions\n\n\n\n\n\n\nMeet Our Team\nWork With Us\n\nOur work\nAccess Now engages on a wide range of issues at the intersection of human rights and technology, advancing our mission through direct stakeholder engagement and deep collaboration with civil society partners and human rights defenders around the world.\n\n\n\nKey issues\n\n\n\n\nArtificial Intelligence\n\n\n\n\n\n\n\nConnectivity\n\n\n\n\n\n\n\nContent Governance\n\n\n\n\n\n\n\nCovid-19\n\n\n\n\n\n\n\nCybersecurity\n\n\n\n\n\n\n\nData Protection\n\n\n\n\n\n\n\nDigital Divide\n\n\n\n\n\n\n\nDigital Identity Systems\n\n\n\n\n\n\n\nDigital Security\n\n\n\n\n\n\n\nFreedom of Expression\n\n\n\n\n\n\n\nInternet Shutdowns\n\n\n\n\n\n\n\nNet Neutrality\n\n\n\n\n\n\n\nPrivacy\n\n\n\n\n\n\n\nProtest and Online Organizing\n\n\n\n\n\n\n\nSurveillance\n\n\n\n\n\n\n\nTransparency\n\n\n\n\n\n\n\n\n\n\nWho we work with\n\n\n\n\n\n\n\n\nPartnerships\n\nPartnerships\n\nAccess Now is proud to work alongside a vast network of partners across civil society, academia, international and regional bodies, and both the public and private sectors.\n\n\n\n\n\nStakeholders\n\n\n\n\n\n\nPrivate Sector\nWe urge companies to make their practices more transparent, accountable, and rights-respecting, and work with investors to center human rights in their engagement with the tech sector.\n\n\n\n\nInternational Organizations\nWe strategically engage with multilateral institutions, such as the United Nations, to build international norms that strengthen digital rights and to encourage rights-respecting tech policy and governance.\n\n\n\n\nPolicymakers\nWe provide expert guidance to legislators, regulators, and others on best practices for rights-respecting policymaking in the digital age.\n\n\n\n\n\n\nRegions\n\n\n\n\n\n\nMeet Our Team\nWork With Us\n\nOur work\nAccess Now engages on a wide range of issues at the intersection of human rights and technology, advancing our mission through direct stakeholder engagement and deep collaboration with civil society partners and human rights defenders around the world.\n\n\n\nKey issues\n\n\n\n\nArtificial Intelligence\n\n\n\n\n\n\n\nConnectivity\n\n\n\n\n\n\n\nContent Governance\n\n\n\n\n\n\n\nCovid-19\n\n\n\n\n\n\n\nCybersecurity\n\n\n\n\n\n\n\nData Protection\n\n\n\n\n\n\n\nDigital Divide\n\n\n\n\n\n\n\nDigital Identity Systems\n\n\n\n\n\n\n\nDigital Security\n\n\n\n\n\n\n\nFreedom of Expression\n\n\n\n\n\n\n\nInternet Shutdowns\n\n\n\n\n\n\n\nNet Neutrality\n\n\n\n\n\n\n\nPrivacy\n\n\n\n\n\n\n\nProtest and Online Organizing\n\n\n\n\n\n\n\nSurveillance\n\n\n\n\n\n\n\nTransparency\n\n\n\n\n\n\n\n\n\n\nWho we work with\n\n\n\n\n\n\n\n\nPartnerships\n\nPartnerships\n\nAccess Now is proud to work alongside a vast network of partners across civil society, academia, international and regional bodies, and both the public and private sectors.\n\n\n\n\n\nStakeholders\n\n\n\n\n\n\nPrivate Sector\nWe urge companies to make their practices more transparent, accountable, and rights-respecting, and work with investors to center human rights in their engagement with the tech sector.\n\n\n\n\nInternational Organizations\nWe strategically engage with multilateral institutions, such as the United Nations, to build international norms that strengthen digital rights and to encourage rights-respecting tech policy and governance.\n\n\n\n\nPolicymakers\nWe provide expert guidance to legislators, regulators, and others on best practices for rights-respecting policymaking in the digital age.\n\n\n\n\n\n\nRegions\n\n\n\n\n\n\nMeet Our Team\nWork With Us\n\nOur work\nAccess Now engages on a wide range of issues at the intersection of human rights and technology, advancing our mission through direct stakeholder engagement and deep collaboration with civil society partners and human rights defenders around the world.\n\n\n\nKey issues\n\n\n\n\nArtificial Intelligence\n\n\n\n\n\n\n\nConnectivity\n\n\n\n\n\n\n\nContent Governance\n\n\n\n\n\n\n\nCovid-19\n\n\n\n\n\n\n\nCybersecurity\n\n\n\n\n\n\n\nData Protection\n\n\n\n\n\n\n\nDigital Divide\n\n\n\n\n\n\n\nDigital Identity Systems\n\n\n\n\n\n\n\nDigital Security\n\n\n\n\n\n\n\nFreedom of Expression\n\n\n\n\n\n\n\nInternet Shutdowns\n\n\n\n\n\n\n\nNet Neutrality\n\n\n\n\n\n\n\nPrivacy\n\n\n\n\n\n\n\nProtest and Online Organizing\n\n\n\n\n\n\n\nSurveillance\n\n\n\n\n\n\n\nTransparency\n\n\n\n\n\n\n\n\n\n\nWho we work with\n\n\n\n\n\n\n\n\nPartnerships\n\nPartnerships\n\nAccess Now is proud to work alongside a vast network of partners across civil society, academia, international and regional bodies, and both the public and private sectors.\n\n\n\n\n\nStakeholders\n\n\n\n\n\n\nPrivate Sector\nWe urge companies to make their practices more transparent, accountable, and rights-respecting, and work with investors to center human rights in their engagement with the tech sector.\n\n\n\n\nInternational Organizations\nWe strategically engage with multilateral institutions, such as the United Nations, to build international norms that strengthen digital rights and to encourage rights-respecting tech policy and governance.\n\n\n\n\nPolicymakers\nWe provide expert guidance to legislators, regulators, and others on best practices for rights-respecting policymaking in the digital age.\n\n\n\n\n\n\nRegions\n\n\n\n\n\n\nMeet Our Team\nWork With Us\n\nOur work\nAccess Now engages on a wide range of issues at the intersection of human rights and technology, advancing our mission through direct stakeholder engagement and deep collaboration with civil society partners and human rights defenders around the world.\n\nOur work\nAccess Now engages on a wide range of issues at the intersection of human rights and technology, advancing our mission through direct stakeholder engagement and deep collaboration with civil society partners and human rights defenders around the world.\n\nOur work\nAccess Now engages on a wide range of issues at the intersection of human rights and technology, advancing our mission through direct stakeholder engagement and deep collaboration with civil society partners and human rights defenders around the world.\n\nAccess Now engages on a wide range of issues at the intersection of human rights and technology, advancing our mission through direct stakeholder engagement and deep collaboration with civil society partners and human rights defenders around the world.\n\nKey issues\n\nArtificial Intelligence\n\n\n\n\n\n\n\nConnectivity\n\n\n\n\n\n\n\nContent Governance\n\n\n\n\n\n\n\nCovid-19\n\n\n\n\n\n\n\nCybersecurity\n\n\n\n\n\n\n\nData Protection\n\n\n\n\n\n\n\nDigital Divide\n\n\n\n\n\n\n\nDigital Identity Systems\n\n\n\n\n\n\n\nDigital Security\n\n\n\n\n\n\n\nFreedom of Expression\n\n\n\n\n\n\n\nInternet Shutdowns\n\n\n\n\n\n\n\nNet Neutrality\n\n\n\n\n\n\n\nPrivacy\n\n\n\n\n\n\n\nProtest and Online Organizing\n\n\n\n\n\n\n\nSurveillance\n\n\n\n\n\n\n\nTransparency\n\nArtificial Intelligence\n\n\n\n\n\n\n\nConnectivity\n\n\n\n\n\n\n\nContent Governance\n\n\n\n\n\n\n\nCovid-19\n\n\n\n\n\n\n\nCybersecurity\n\n\n\n\n\n\n\nData Protection\n\n\n\n\n\n\n\nDigital Divide\n\n\n\n\n\n\n\nDigital Identity Systems\n\n\n\n\n\n\n\nDigital Security\n\n\n\n\n\n\n\nFreedom of Expression\n\n\n\n\n\n\n\nInternet Shutdowns\n\n\n\n\n\n\n\nNet Neutrality\n\n\n\n\n\n\n\nPrivacy\n\n\n\n\n\n\n\nProtest and Online Organizing\n\n\n\n\n\n\n\nSurveillance\n\n\n\n\n\n\n\nTransparency\n\nArtificial Intelligence\n\n\n\n\n\n\n\nConnectivity\n\n\n\n\n\n\n\nContent Governance\n\n\n\n\n\n\n\nCovid-19\n\n\n\n\n\n\n\nCybersecurity\n\n\n\n\n\n\n\nData Protection\n\n\n\n\n\n\n\nDigital Divide\n\n\n\n\n\n\n\nDigital Identity Systems\n\n\n\n\n\n\n\nDigital Security\n\n\n\n\n\n\n\nFreedom of Expression\n\n\n\n\n\n\n\nInternet Shutdowns\n\n\n\n\n\n\n\nNet Neutrality\n\n\n\n\n\n\n\nPrivacy\n\n\n\n\n\n\n\nProtest and Online Organizing\n\n\n\n\n\n\n\nSurveillance\n\n\n\n\n\n\n\nTransparency\n\nArtificial Intelligence\n\nConnectivity\n\nContent Governance\n\nCovid-19\n\nCybersecurity\n\nData Protection\n\nDigital Divide\n\nDigital Identity Systems\n\nDigital Security\n\nFreedom of Expression\n\nInternet Shutdowns\n\nNet Neutrality\n\nPrivacy\n\nProtest and Online Organizing\n\nSurveillance\n\nTransparency\n\nWho we work with\n\nPartnerships\n\nPartnerships\n\nAccess Now is proud to work alongside a vast network of partners across civil society, academia, international and regional bodies, and both the public and private sectors.\n\nPartnerships\n\nPartnerships\n\nAccess Now is proud to work alongside a vast network of partners across civil society, academia, international and regional bodies, and both the public and private sectors.\n\nPartnerships\n\nAccess Now is proud to work alongside a vast network of partners across civil society, academia, international and regional bodies, and both the public and private sectors.\n\nAccess Now is proud to work alongside a vast network of partners across civil society, academia, international and regional bodies, and both the public and private sectors.\n\nAccess Now is proud to work alongside a vast network of partners across civil society, academia, international and regional bodies, and both the public and private sectors.\n\nStakeholders\n\nPrivate Sector\nWe urge companies to make their practices more transparent, accountable, and rights-respecting, and work with investors to center human rights in their engagement with the tech sector.\n\n\n\n\nInternational Organizations\nWe strategically engage with multilateral institutions, such as the United Nations, to build international norms that strengthen digital rights and to encourage rights-respecting tech policy and governance.\n\n\n\n\nPolicymakers\nWe provide expert guidance to legislators, regulators, and others on best practices for rights-respecting policymaking in the digital age.\n\nPrivate Sector\nWe urge companies to make their practices more transparent, accountable, and rights-respecting, and work with investors to center human rights in their engagement with the tech sector.\n\n\n\n\nInternational Organizations\nWe strategically engage with multilateral institutions, such as the United Nations, to build international norms that strengthen digital rights and to encourage rights-respecting tech policy and governance.\n\n\n\n\nPolicymakers\nWe provide expert guidance to legislators, regulators, and others on best practices for rights-respecting policymaking in the digital age.\n\nPrivate Sector\nWe urge companies to make their practices more transparent, accountable, and rights-respecting, and work with investors to center human rights in their engagement with the tech sector.\n\n\n\n\nInternational Organizations\nWe strategically engage with multilateral institutions, such as the United Nations, to build international norms that strengthen digital rights and to encourage rights-respecting tech policy and governance.\n\n\n\n\nPolicymakers\nWe provide expert guidance to legislators, regulators, and others on best practices for rights-respecting policymaking in the digital age.\n\nPrivate Sector\nWe urge companies to make their practices more transparent, accountable, and rights-respecting, and work with investors to center human rights in their engagement with the tech sector.\n\nPrivate Sector\nWe urge companies to make their practices more transparent, accountable, and rights-respecting, and work with investors to center human rights in their engagement with the tech sector.\n\nWe urge companies to make their practices more transparent, accountable, and rights-respecting, and work with investors to center human rights in their engagement with the tech sector.\n\nInternational Organizations\nWe strategically engage with multilateral institutions, such as the United Nations, to build international norms that strengthen digital rights and to encourage rights-respecting tech policy and governance.\n\nInternational Organizations\nWe strategically engage with multilateral institutions, such as the United Nations, to build international norms that strengthen digital rights and to encourage rights-respecting tech policy and governance.\n\nWe strategically engage with multilateral institutions, such as the United Nations, to build international norms that strengthen digital rights and to encourage rights-respecting tech policy and governance.\n\nPolicymakers\nWe provide expert guidance to legislators, regulators, and others on best practices for rights-respecting policymaking in the digital age.\n\nPolicymakers\nWe provide expert guidance to legislators, regulators, and others on best practices for rights-respecting policymaking in the digital age.\n\nWe provide expert guidance to legislators, regulators, and others on best practices for rights-respecting policymaking in the digital age.\n\nRegions\n\nMeet Our Team\nWork With Us\n\nMeet Our Team\nWork With Us\n\nMeet Our Team\nWork With Us\n\nMeet Our Team\nWork With Us\n\nMeet Our Team\n\nWork With Us\n\nHelp keep the internet open and secure.\nSubscribe to our action alerts and weekly newsletter\n\"*\" indicates required fields\n\nThis field is hidden when viewing the form\n\nSubscribe to Access Express\nThis field is hidden when viewing the form\n\nSubscribe to Action Alerts\nName\n\n\nFirst\n\n\n\nLast\n\nEmail*\n\nCountryCountryAfghanistanÅland IslandsAlbaniaAlgeriaAmerican SamoaAndorraAngolaAnguillaAntigua and BarbudaArgentinaArmeniaArubaAustraliaAustriaAzerbaijanBahamasBahrainBangladeshBarbadosBelarusBelgiumBelizeBeninBermudaBhutanBoliviaBonaire, Sint Eustatius and SabaBosnia and HerzegovinaBotswanaBrazilBritish Indian Ocean TerritoryBritish Virgin IslandsBruneiBulgariaBurkina FasoBurundiCambodiaCameroonCanadaCape VerdeCayman IslandsCentral African RepublicChadChileChinaChristmas IslandColombiaComorosCook IslandsCosta RicaCôte d'IvoireCroatiaCubaCuraçaoCyprusCzech RepublicDemocratic Republic of the CongoDenmarkDjiboutiDominicaDominican RepublicEast TimorEcuadorEgyptEl SalvadorEquatorial GuineaEritreaEstoniaEswatiniEthiopiaFalkland IslandsFaroe IslandsFijiFinlandFranceFrench GuianaFrench PolynesiaFrench Southern TerritoriesGabonGeorgiaGermanyGhanaGibraltarGreeceGreenlandGrenadaGuadeloupeGuamGuatemalaGuernseyGuineaGuinea-BissauGuyanaHaitiHondurasHong KongHungaryIcelandIndiaIndonesiaIranIraqIrelandIsraelItalyJamaicaJapanJordanKazakhstanKenyaKiribatiKosovoKuwaitKyrgyzstanLaosLatviaLebanonLesothoLiberiaLibyaLiechtensteinLithuaniaLuxembourgMacauMadagascarMalawiMalaysiaMaldivesMaliMaltaMarshall IslandsMartiniqueMauritaniaMauritiusMayotteMexicoMicronesiaMoldovaMonacoMongoliaMontenegroMontserratMoroccoMozambiqueMyanmarNamibiaNauruNepalNetherlands AntillesNew CaledoniaNew ZealandNicaraguaNigerNigeriaNiueNorfolk IslandNorth KoreaNorth MacedoniaNorthern Mariana IslandsNorwayOmanPakistanPalauPalestinePanamaPapua New GuineaParaguayPeruPhilippinesPitcairn IslandPolandPortugalPuerto RicoQatarRepublic of the CongoReunionRomaniaRussiaRwandaSaint BarthélemySaint Kitts and NevisSaint LuciaSaint Vincent and the GrenadinesSamoaSan MarinoSão Tomé and PríncipeSaudi ArabiaSenegalSerbiaSeychellesSierra LeoneSingaporeSlovakiaSloveniaSolomon IslandsSomaliaSomalilandSouth AfricaSouth KoreaSouth SudanSpainSri LankaSt. HelenaSt. Pierre and MiquelonSudanSurinameSwedenSwitzerlandSyriaTaiwanTajikistanTanzaniaThailandThe GambiaThe NetherlandsTogoTokelauTongaTrinidad and TobagoTunisiaTurkeyTurkmenistanTurks and Caicos IslandsTuvaluUgandaUkraineUnited Arab EmiratesUnited KingdomUnited StatesUruguayUzbekistanVanuatuVatican CityVenezuelaVietnamVirgin Islands (U.S.)Wallis and Futuna IslandsWestern SaharaYemenZambiaZimbabwePostal CodeCommentsThis field is for validation purposes and should be left unchanged.\n \n\n\n\n\n\n\n\n\n\n\n\n\n\n\n\nYour info is secure with us\n\nHelp keep the internet open and secure.\nSubscribe to our action alerts and weekly newsletter\n\"*\" indicates required fields\n\nThis field is hidden when viewing the form\n\nSubscribe to Access Express\nThis field is hidden when viewing the form\n\nSubscribe to Action Alerts\nName\n\n\nFirst\n\n\n\nLast\n\nEmail*\n\nCountryCountryAfghanistanÅland IslandsAlbaniaAlgeriaAmerican SamoaAndorraAngolaAnguillaAntigua and BarbudaArgentinaArmeniaArubaAustraliaAustriaAzerbaijanBahamasBahrainBangladeshBarbadosBelarusBelgiumBelizeBeninBermudaBhutanBoliviaBonaire, Sint Eustatius and SabaBosnia and HerzegovinaBotswanaBrazilBritish Indian Ocean TerritoryBritish Virgin IslandsBruneiBulgariaBurkina FasoBurundiCambodiaCameroonCanadaCape VerdeCayman IslandsCentral African RepublicChadChileChinaChristmas IslandColombiaComorosCook IslandsCosta RicaCôte d'IvoireCroatiaCubaCuraçaoCyprusCzech RepublicDemocratic Republic of the CongoDenmarkDjiboutiDominicaDominican RepublicEast TimorEcuadorEgyptEl SalvadorEquatorial GuineaEritreaEstoniaEswatiniEthiopiaFalkland IslandsFaroe IslandsFijiFinlandFranceFrench GuianaFrench PolynesiaFrench Southern TerritoriesGabonGeorgiaGermanyGhanaGibraltarGreeceGreenlandGrenadaGuadeloupeGuamGuatemalaGuernseyGuineaGuinea-BissauGuyanaHaitiHondurasHong KongHungaryIcelandIndiaIndonesiaIranIraqIrelandIsraelItalyJamaicaJapanJordanKazakhstanKenyaKiribatiKosovoKuwaitKyrgyzstanLaosLatviaLebanonLesothoLiberiaLibyaLiechtensteinLithuaniaLuxembourgMacauMadagascarMalawiMalaysiaMaldivesMaliMaltaMarshall IslandsMartiniqueMauritaniaMauritiusMayotteMexicoMicronesiaMoldovaMonacoMongoliaMontenegroMontserratMoroccoMozambiqueMyanmarNamibiaNauruNepalNetherlands AntillesNew CaledoniaNew ZealandNicaraguaNigerNigeriaNiueNorfolk IslandNorth KoreaNorth MacedoniaNorthern Mariana IslandsNorwayOmanPakistanPalauPalestinePanamaPapua New GuineaParaguayPeruPhilippinesPitcairn IslandPolandPortugalPuerto RicoQatarRepublic of the CongoReunionRomaniaRussiaRwandaSaint BarthélemySaint Kitts and NevisSaint LuciaSaint Vincent and the GrenadinesSamoaSan MarinoSão Tomé and PríncipeSaudi ArabiaSenegalSerbiaSeychellesSierra LeoneSingaporeSlovakiaSloveniaSolomon IslandsSomaliaSomalilandSouth AfricaSouth KoreaSouth SudanSpainSri LankaSt. HelenaSt. Pierre and MiquelonSudanSurinameSwedenSwitzerlandSyriaTaiwanTajikistanTanzaniaThailandThe GambiaThe NetherlandsTogoTokelauTongaTrinidad and TobagoTunisiaTurkeyTurkmenistanTurks and Caicos IslandsTuvaluUgandaUkraineUnited Arab EmiratesUnited KingdomUnited StatesUruguayUzbekistanVanuatuVatican CityVenezuelaVietnamVirgin Islands (U.S.)Wallis and Futuna IslandsWestern SaharaYemenZambiaZimbabwePostal CodeCommentsThis field is for validation purposes and should be left unchanged.\n \n\n\n\n\n\n\n\n\n\n\n\n\n\n\n\nYour info is secure with us\n\nHelp keep the internet open and secure.\nSubscribe to our action alerts and weekly newsletter\n\"*\" indicates required fields\n\nThis field is hidden when viewing the form\n\nSubscribe to Access Express\nThis field is hidden when viewing the form\n\nSubscribe to Action Alerts\nName\n\n\nFirst\n\n\n\nLast\n\nEmail*\n\nCountryCountryAfghanistanÅland IslandsAlbaniaAlgeriaAmerican SamoaAndorraAngolaAnguillaAntigua and BarbudaArgentinaArmeniaArubaAustraliaAustriaAzerbaijanBahamasBahrainBangladeshBarbadosBelarusBelgiumBelizeBeninBermudaBhutanBoliviaBonaire, Sint Eustatius and SabaBosnia and HerzegovinaBotswanaBrazilBritish Indian Ocean TerritoryBritish Virgin IslandsBruneiBulgariaBurkina FasoBurundiCambodiaCameroonCanadaCape VerdeCayman IslandsCentral African RepublicChadChileChinaChristmas IslandColombiaComorosCook IslandsCosta RicaCôte d'IvoireCroatiaCubaCuraçaoCyprusCzech RepublicDemocratic Republic of the CongoDenmarkDjiboutiDominicaDominican RepublicEast TimorEcuadorEgyptEl SalvadorEquatorial GuineaEritreaEstoniaEswatiniEthiopiaFalkland IslandsFaroe IslandsFijiFinlandFranceFrench GuianaFrench PolynesiaFrench Southern TerritoriesGabonGeorgiaGermanyGhanaGibraltarGreeceGreenlandGrenadaGuadeloupeGuamGuatemalaGuernseyGuineaGuinea-BissauGuyanaHaitiHondurasHong KongHungaryIcelandIndiaIndonesiaIranIraqIrelandIsraelItalyJamaicaJapanJordanKazakhstanKenyaKiribatiKosovoKuwaitKyrgyzstanLaosLatviaLebanonLesothoLiberiaLibyaLiechtensteinLithuaniaLuxembourgMacauMadagascarMalawiMalaysiaMaldivesMaliMaltaMarshall IslandsMartiniqueMauritaniaMauritiusMayotteMexicoMicronesiaMoldovaMonacoMongoliaMontenegroMontserratMoroccoMozambiqueMyanmarNamibiaNauruNepalNetherlands AntillesNew CaledoniaNew ZealandNicaraguaNigerNigeriaNiueNorfolk IslandNorth KoreaNorth MacedoniaNorthern Mariana IslandsNorwayOmanPakistanPalauPalestinePanamaPapua New GuineaParaguayPeruPhilippinesPitcairn IslandPolandPortugalPuerto RicoQatarRepublic of the CongoReunionRomaniaRussiaRwandaSaint BarthélemySaint Kitts and NevisSaint LuciaSaint Vincent and the GrenadinesSamoaSan MarinoSão Tomé and PríncipeSaudi ArabiaSenegalSerbiaSeychellesSierra LeoneSingaporeSlovakiaSloveniaSolomon IslandsSomaliaSomalilandSouth AfricaSouth KoreaSouth SudanSpainSri LankaSt. HelenaSt. Pierre and MiquelonSudanSurinameSwedenSwitzerlandSyriaTaiwanTajikistanTanzaniaThailandThe GambiaThe NetherlandsTogoTokelauTongaTrinidad and TobagoTunisiaTurkeyTurkmenistanTurks and Caicos IslandsTuvaluUgandaUkraineUnited Arab EmiratesUnited KingdomUnited StatesUruguayUzbekistanVanuatuVatican CityVenezuelaVietnamVirgin Islands (U.S.)Wallis and Futuna IslandsWestern SaharaYemenZambiaZimbabwePostal CodeCommentsThis field is for validation purposes and should be left unchanged.\n\nHelp keep the internet open and secure.\nSubscribe to our action alerts and weekly newsletter\n\"*\" indicates required fields\n\nSubscribe to our action alerts and weekly newsletter\n\n\"*\" indicates required fields\n\nThis field is hidden when viewing the form\n\nSubscribe to Access Express\nThis field is hidden when viewing the form\n\nSubscribe to Action Alerts\nName\n\n\nFirst\n\n\n\nLast\n\nEmail*\n\nCountryCountryAfghanistanÅland IslandsAlbaniaAlgeriaAmerican SamoaAndorraAngolaAnguillaAntigua and BarbudaArgentinaArmeniaArubaAustraliaAustriaAzerbaijanBahamasBahrainBangladeshBarbadosBelarusBelgiumBelizeBeninBermudaBhutanBoliviaBonaire, Sint Eustatius and SabaBosnia and HerzegovinaBotswanaBrazilBritish Indian Ocean TerritoryBritish Virgin IslandsBruneiBulgariaBurkina FasoBurundiCambodiaCameroonCanadaCape VerdeCayman IslandsCentral African RepublicChadChileChinaChristmas IslandColombiaComorosCook IslandsCosta RicaCôte d'IvoireCroatiaCubaCuraçaoCyprusCzech RepublicDemocratic Republic of the CongoDenmarkDjiboutiDominicaDominican RepublicEast TimorEcuadorEgyptEl SalvadorEquatorial GuineaEritreaEstoniaEswatiniEthiopiaFalkland IslandsFaroe IslandsFijiFinlandFranceFrench GuianaFrench PolynesiaFrench Southern TerritoriesGabonGeorgiaGermanyGhanaGibraltarGreeceGreenlandGrenadaGuadeloupeGuamGuatemalaGuernseyGuineaGuinea-BissauGuyanaHaitiHondurasHong KongHungaryIcelandIndiaIndonesiaIranIraqIrelandIsraelItalyJamaicaJapanJordanKazakhstanKenyaKiribatiKosovoKuwaitKyrgyzstanLaosLatviaLebanonLesothoLiberiaLibyaLiechtensteinLithuaniaLuxembourgMacauMadagascarMalawiMalaysiaMaldivesMaliMaltaMarshall IslandsMartiniqueMauritaniaMauritiusMayotteMexicoMicronesiaMoldovaMonacoMongoliaMontenegroMontserratMoroccoMozambiqueMyanmarNamibiaNauruNepalNetherlands AntillesNew CaledoniaNew ZealandNicaraguaNigerNigeriaNiueNorfolk IslandNorth KoreaNorth MacedoniaNorthern Mariana IslandsNorwayOmanPakistanPalauPalestinePanamaPapua New GuineaParaguayPeruPhilippinesPitcairn IslandPolandPortugalPuerto RicoQatarRepublic of the CongoReunionRomaniaRussiaRwandaSaint BarthélemySaint Kitts and NevisSaint LuciaSaint Vincent and the GrenadinesSamoaSan MarinoSão Tomé and PríncipeSaudi ArabiaSenegalSerbiaSeychellesSierra LeoneSingaporeSlovakiaSloveniaSolomon IslandsSomaliaSomalilandSouth AfricaSouth KoreaSouth SudanSpainSri LankaSt. HelenaSt. Pierre and MiquelonSudanSurinameSwedenSwitzerlandSyriaTaiwanTajikistanTanzaniaThailandThe GambiaThe NetherlandsTogoTokelauTongaTrinidad and TobagoTunisiaTurkeyTurkmenistanTurks and Caicos IslandsTuvaluUgandaUkraineUnited Arab EmiratesUnited KingdomUnited StatesUruguayUzbekistanVanuatuVatican CityVenezuelaVietnamVirgin Islands (U.S.)Wallis and Futuna IslandsWestern SaharaYemenZambiaZimbabwePostal CodeCommentsThis field is for validation purposes and should be left unchanged.\n\nThis field is hidden when viewing the form\n\nSubscribe to Access Express\nThis field is hidden when viewing the form\n\nSubscribe to Action Alerts\nName\n\n\nFirst\n\n\n\nLast\n\nEmail*\n\nCountryCountryAfghanistanÅland IslandsAlbaniaAlgeriaAmerican SamoaAndorraAngolaAnguillaAntigua and BarbudaArgentinaArmeniaArubaAustraliaAustriaAzerbaijanBahamasBahrainBangladeshBarbadosBelarusBelgiumBelizeBeninBermudaBhutanBoliviaBonaire, Sint Eustatius and SabaBosnia and HerzegovinaBotswanaBrazilBritish Indian Ocean TerritoryBritish Virgin IslandsBruneiBulgariaBurkina FasoBurundiCambodiaCameroonCanadaCape VerdeCayman IslandsCentral African RepublicChadChileChinaChristmas IslandColombiaComorosCook IslandsCosta RicaCôte d'IvoireCroatiaCubaCuraçaoCyprusCzech RepublicDemocratic Republic of the CongoDenmarkDjiboutiDominicaDominican RepublicEast TimorEcuadorEgyptEl SalvadorEquatorial GuineaEritreaEstoniaEswatiniEthiopiaFalkland IslandsFaroe IslandsFijiFinlandFranceFrench GuianaFrench PolynesiaFrench Southern TerritoriesGabonGeorgiaGermanyGhanaGibraltarGreeceGreenlandGrenadaGuadeloupeGuamGuatemalaGuernseyGuineaGuinea-BissauGuyanaHaitiHondurasHong KongHungaryIcelandIndiaIndonesiaIranIraqIrelandIsraelItalyJamaicaJapanJordanKazakhstanKenyaKiribatiKosovoKuwaitKyrgyzstanLaosLatviaLebanonLesothoLiberiaLibyaLiechtensteinLithuaniaLuxembourgMacauMadagascarMalawiMalaysiaMaldivesMaliMaltaMarshall IslandsMartiniqueMauritaniaMauritiusMayotteMexicoMicronesiaMoldovaMonacoMongoliaMontenegroMontserratMoroccoMozambiqueMyanmarNamibiaNauruNepalNetherlands AntillesNew CaledoniaNew ZealandNicaraguaNigerNigeriaNiueNorfolk IslandNorth KoreaNorth MacedoniaNorthern Mariana IslandsNorwayOmanPakistanPalauPalestinePanamaPapua New GuineaParaguayPeruPhilippinesPitcairn IslandPolandPortugalPuerto RicoQatarRepublic of the CongoReunionRomaniaRussiaRwandaSaint BarthélemySaint Kitts and NevisSaint LuciaSaint Vincent and the GrenadinesSamoaSan MarinoSão Tomé and PríncipeSaudi ArabiaSenegalSerbiaSeychellesSierra LeoneSingaporeSlovakiaSloveniaSolomon IslandsSomaliaSomalilandSouth AfricaSouth KoreaSouth SudanSpainSri LankaSt. HelenaSt. Pierre and MiquelonSudanSurinameSwedenSwitzerlandSyriaTaiwanTajikistanTanzaniaThailandThe GambiaThe NetherlandsTogoTokelauTongaTrinidad and TobagoTunisiaTurkeyTurkmenistanTurks and Caicos IslandsTuvaluUgandaUkraineUnited Arab EmiratesUnited KingdomUnited StatesUruguayUzbekistanVanuatuVatican CityVenezuelaVietnamVirgin Islands (U.S.)Wallis and Futuna IslandsWestern SaharaYemenZambiaZimbabwePostal CodeCommentsThis field is for validation purposes and should be left unchanged.\n\nThis field is hidden when viewing the form\n\nSubscribe to Access Express\n\nSubscribe to Access Express\n\nSubscribe to Access Express\n\nThis field is hidden when viewing the form\n\nSubscribe to Action Alerts\n\nSubscribe to Action Alerts\n\nSubscribe to Action Alerts\n\nFirst\n\n\n\nLast\n\nEmail*\n\nCountryCountryAfghanistanÅland IslandsAlbaniaAlgeriaAmerican SamoaAndorraAngolaAnguillaAntigua and BarbudaArgentinaArmeniaArubaAustraliaAustriaAzerbaijanBahamasBahrainBangladeshBarbadosBelarusBelgiumBelizeBeninBermudaBhutanBoliviaBonaire, Sint Eustatius and SabaBosnia and HerzegovinaBotswanaBrazilBritish Indian Ocean TerritoryBritish Virgin IslandsBruneiBulgariaBurkina FasoBurundiCambodiaCameroonCanadaCape VerdeCayman IslandsCentral African RepublicChadChileChinaChristmas IslandColombiaComorosCook IslandsCosta RicaCôte d'IvoireCroatiaCubaCuraçaoCyprusCzech RepublicDemocratic Republic of the CongoDenmarkDjiboutiDominicaDominican RepublicEast TimorEcuadorEgyptEl SalvadorEquatorial GuineaEritreaEstoniaEswatiniEthiopiaFalkland IslandsFaroe IslandsFijiFinlandFranceFrench GuianaFrench PolynesiaFrench Southern TerritoriesGabonGeorgiaGermanyGhanaGibraltarGreeceGreenlandGrenadaGuadeloupeGuamGuatemalaGuernseyGuineaGuinea-BissauGuyanaHaitiHondurasHong KongHungaryIcelandIndiaIndonesiaIranIraqIrelandIsraelItalyJamaicaJapanJordanKazakhstanKenyaKiribatiKosovoKuwaitKyrgyzstanLaosLatviaLebanonLesothoLiberiaLibyaLiechtensteinLithuaniaLuxembourgMacauMadagascarMalawiMalaysiaMaldivesMaliMaltaMarshall IslandsMartiniqueMauritaniaMauritiusMayotteMexicoMicronesiaMoldovaMonacoMongoliaMontenegroMontserratMoroccoMozambiqueMyanmarNamibiaNauruNepalNetherlands AntillesNew CaledoniaNew ZealandNicaraguaNigerNigeriaNiueNorfolk IslandNorth KoreaNorth MacedoniaNorthern Mariana IslandsNorwayOmanPakistanPalauPalestinePanamaPapua New GuineaParaguayPeruPhilippinesPitcairn IslandPolandPortugalPuerto RicoQatarRepublic of the CongoReunionRomaniaRussiaRwandaSaint BarthélemySaint Kitts and NevisSaint LuciaSaint Vincent and the GrenadinesSamoaSan MarinoSão Tomé and PríncipeSaudi ArabiaSenegalSerbiaSeychellesSierra LeoneSingaporeSlovakiaSloveniaSolomon IslandsSomaliaSomalilandSouth AfricaSouth KoreaSouth SudanSpainSri LankaSt. HelenaSt. Pierre and MiquelonSudanSurinameSwedenSwitzerlandSyriaTaiwanTajikistanTanzaniaThailandThe GambiaThe NetherlandsTogoTokelauTongaTrinidad and TobagoTunisiaTurkeyTurkmenistanTurks and Caicos IslandsTuvaluUgandaUkraineUnited Arab EmiratesUnited KingdomUnited StatesUruguayUzbekistanVanuatuVatican CityVenezuelaVietnamVirgin Islands (U.S.)Wallis and Futuna IslandsWestern SaharaYemenZambiaZimbabwe\n\nCountryAfghanistanÅland IslandsAlbaniaAlgeriaAmerican SamoaAndorraAngolaAnguillaAntigua and BarbudaArgentinaArmeniaArubaAustraliaAustriaAzerbaijanBahamasBahrainBangladeshBarbadosBelarusBelgiumBelizeBeninBermudaBhutanBoliviaBonaire, Sint Eustatius and SabaBosnia and HerzegovinaBotswanaBrazilBritish Indian Ocean TerritoryBritish Virgin IslandsBruneiBulgariaBurkina FasoBurundiCambodiaCameroonCanadaCape VerdeCayman IslandsCentral African RepublicChadChileChinaChristmas IslandColombiaComorosCook IslandsCosta RicaCôte d'IvoireCroatiaCubaCuraçaoCyprusCzech RepublicDemocratic Republic of the CongoDenmarkDjiboutiDominicaDominican RepublicEast TimorEcuadorEgyptEl SalvadorEquatorial GuineaEritreaEstoniaEswatiniEthiopiaFalkland IslandsFaroe IslandsFijiFinlandFranceFrench GuianaFrench PolynesiaFrench Southern TerritoriesGabonGeorgiaGermanyGhanaGibraltarGreeceGreenlandGrenadaGuadeloupeGuamGuatemalaGuernseyGuineaGuinea-BissauGuyanaHaitiHondurasHong KongHungaryIcelandIndiaIndonesiaIranIraqIrelandIsraelItalyJamaicaJapanJordanKazakhstanKenyaKiribatiKosovoKuwaitKyrgyzstanLaosLatviaLebanonLesothoLiberiaLibyaLiechtensteinLithuaniaLuxembourgMacauMadagascarMalawiMalaysiaMaldivesMaliMaltaMarshall IslandsMartiniqueMauritaniaMauritiusMayotteMexicoMicronesiaMoldovaMonacoMongoliaMontenegroMontserratMoroccoMozambiqueMyanmarNamibiaNauruNepalNetherlands AntillesNew CaledoniaNew ZealandNicaraguaNigerNigeriaNiueNorfolk IslandNorth KoreaNorth MacedoniaNorthern Mariana IslandsNorwayOmanPakistanPalauPalestinePanamaPapua New GuineaParaguayPeruPhilippinesPitcairn IslandPolandPortugalPuerto RicoQatarRepublic of the CongoReunionRomaniaRussiaRwandaSaint BarthélemySaint Kitts and NevisSaint LuciaSaint Vincent and the GrenadinesSamoaSan MarinoSão Tomé and PríncipeSaudi ArabiaSenegalSerbiaSeychellesSierra LeoneSingaporeSlovakiaSloveniaSolomon IslandsSomaliaSomalilandSouth AfricaSouth KoreaSouth SudanSpainSri LankaSt. HelenaSt. Pierre and MiquelonSudanSurinameSwedenSwitzerlandSyriaTaiwanTajikistanTanzaniaThailandThe GambiaThe NetherlandsTogoTokelauTongaTrinidad and TobagoTunisiaTurkeyTurkmenistanTurks and Caicos IslandsTuvaluUgandaUkraineUnited Arab EmiratesUnited KingdomUnited StatesUruguayUzbekistanVanuatuVatican CityVenezuelaVietnamVirgin Islands (U.S.)Wallis and Futuna IslandsWestern SaharaYemenZambiaZimbabwe\n\nPostal Code\n\nCommentsThis field is for validation purposes and should be left unchanged.\n\nThis field is for validation purposes and should be left unchanged.\n\nYour info is secure with us",
  "date": "",
  "source_type": "other",
  "extracted_at": "2025-04-07T13:46:28.068205",
  "metadata": {
    "description": "Our work Access Now engages on a wide range of issues at the intersection of human rights and technology, advancing our mission through direct stakeholder",
    "og:type": "article",
    "og:site_name": "Access Now"
  },
  "relevance_score": 0.45,
  "summary": "Key issues\n\n\n\n\nArtificial Intelligence\n\n\n\n\n\n\n\nConnectivity\n\n\n\n\n\n\n\nContent Governance\n\n\n\n\n\n\n\nCovid-19\n\n\n\n\n\n\n\nCybersecurity\n\n\n\n\n\n\n\nData Protection\n\n\n\n\n\n\n\nDigital Divide\n\n\n\n\n\n\n\nDigital Identity Systems\n\n\n\n\n\n\n\nDigital Security\n\n\n\n\n\n\n\nFreedom of Expression\n\n\n\n\n\n\n\nInternet Shutdowns\n\n\n\n\n\n\n\nNet Neutrality\n\n\n\n\n\n\n\nPrivacy\n\n\n\n\n\n\n\nProtest and Online Organizing\n\n\n\n\n\n\n\nSurveillance\n\n\n\n\n\n\n\nTransparency\n\n\n\n\n\n\n\n\n\n\nWho we work with\n\n\n\n\n\n\n\n\nPartnerships\n\nPartnerships\n\nAccess Now is proud to work alongside a vast network of partners across civil society, academia, international and regional bodies, and both the public and private sectors. Subscribe to our action alerts and weekly newsletter\n\"*\" indicates required fields\n\nThis field is hidden when viewing the form\n\nSubscribe to Access Express\nThis field is hidden when viewing the form\n\nSubscribe to Action Alerts\nName\n\n\nFirst\n\n\n\nLast\n\nEmail*\n\nCountryCountryAfghanistanÅland IslandsAlbaniaAlgeriaAmerican SamoaAndorraAngolaAnguillaAntigua and BarbudaArgentinaArmeniaArubaAustraliaAustriaAzerbaijanBahamasBahrainBangladeshBarbadosBelarusBelgiumBelizeBeninBermudaBhutanBoliviaBonaire, Sint Eustatius and SabaBosnia and HerzegovinaBotswanaBrazilBritish Indian Ocean TerritoryBritish Virgin IslandsBruneiBulgariaBurkina FasoBurundiCambodiaCameroonCanadaCape VerdeCayman IslandsCentral African RepublicChadChileChinaChristmas IslandColombiaComorosCook IslandsCosta RicaCôte d'IvoireCroatiaCubaCuraçaoCyprusCzech RepublicDemocratic Republic of the CongoDenmarkDjiboutiDominicaDominican RepublicEast TimorEcuadorEgyptEl SalvadorEquatorial GuineaEritreaEstoniaEswatiniEthiopiaFalkland IslandsFaroe IslandsFijiFinlandFranceFrench GuianaFrench PolynesiaFrench Southern TerritoriesGabonGeorgiaGermanyGhanaGibraltarGreeceGreenlandGrenadaGuadeloupeGuamGuatemalaGuernseyGuineaGuinea-BissauGuyanaHaitiHondurasHong KongHungaryIcelandIndiaIndonesiaIranIraqIrelandIsraelItalyJamaicaJapanJordanKazakhstanKenyaKiribatiKosovoKuwaitKyrgyzstanLaosLatviaLebanonLesothoLiberiaLibyaLiechtensteinLithuaniaLuxembourgMacauMadagascarMalawiMalaysiaMaldivesMaliMaltaMarshall IslandsMartiniqueMauritaniaMauritiusMayotteMexicoMicronesiaMoldovaMonacoMongoliaMontenegroMontserratMoroccoMozambiqueMyanmarNamibiaNauruNepalNetherlands AntillesNew CaledoniaNew ZealandNicaraguaNigerNigeriaNiueNorfolk IslandNorth KoreaNorth MacedoniaNorthern Mariana IslandsNorwayOmanPakistanPalauPalestinePanamaPapua New GuineaParaguayPeruPhilippinesPitcairn IslandPolandPortugalPuerto RicoQatarRepublic of the CongoReunionRomaniaRussiaRwandaSaint BarthélemySaint Kitts and NevisSaint LuciaSaint Vincent and the GrenadinesSamoaSan MarinoSão Tomé and PríncipeSaudi ArabiaSenegalSerbiaSeychellesSierra LeoneSingaporeSlovakiaSloveniaSolomon IslandsSomaliaSomalilandSouth AfricaSouth KoreaSouth SudanSpainSri LankaSt. Key issues\n\n\n\n\nArtificial Intelligence\n\n\n\n\n\n\n\nConnectivity\n\n\n\n\n\n\n\nContent Governance\n\n\n\n\n\n\n\nCovid-19\n\n\n\n\n\n\n\nCybersecurity\n\n\n\n\n\n\n\nData Protection\n\n\n\n\n\n\n\nDigital Divide\n\n\n\n\n\n\n\nDigital Identity Systems\n\n\n\n\n\n\n\nDigital Security\n\n\n\n\n\n\n\nFreedom of Expression\n\n\n\n\n\n\n\nInternet Shutdowns\n\n\n\n\n\n\n\nNet Neutrality\n\n\n\n\n\n\n\nPrivacy\n\n\n\n\n\n\n\nProtest and Online Organizing\n\n\n\n\n\n\n\nSurveillance\n\n\n\n\n\n\n\nTransparency\n\n\n\n\n\n\n\n\n\n\nWho we work with\n\n\n\n\n\n\n\n\nPartnerships\n\nPartnerships\n\nAccess Now is proud to work alongside a vast network of partners across civil society, academia, international and regional bodies, and both the public and private sectors. Regions\n\n\n\n\n\n\nMeet Our Team\nWork With Us\n\nOur work\nAccess Now engages on a wide range of issues at the intersection of human rights and technology, advancing our mission through direct stakeholder engagement and deep collaboration with civil society partners and human rights defenders around the world. Key issues\n\n\n\n\nArtificial Intelligence\n\n\n\n\n\n\n\nConnectivity\n\n\n\n\n\n\n\nContent Governance\n\n\n\n\n\n\n\nCovid-19\n\n\n\n\n\n\n\nCybersecurity\n\n\n\n\n\n\n\nData Protection\n\n\n\n\n\n\n\nDigital Divide\n\n\n\n\n\n\n\nDigital Identity Systems\n\n\n\n\n\n\n\nDigital Security\n\n\n\n\n\n\n\nFreedom of Expression\n\n\n\n\n\n\n\nInternet Shutdowns\n\n\n\n\n\n\n\nNet Neutrality\n\n\n\n\n\n\n\nPrivacy\n\n\n\n\n\n\n\nProtest and Online Organizing\n\n\n\n\n\n\n\nSurveillance\n\n\n\n\n\n\n\nTransparency\n\n\n\n\n\n\n\n\n\n\nWho we work with\n\n\n\n\n\n\n\n\nPartnerships\n\nPartnerships\n\nAccess Now is proud to work alongside a vast network of partners across civil society, academia, international and regional bodies, and both the public and private sectors. Regions\n\n\n\n\n\n\nMeet Our Team\nWork With Us\n\nOur work\nAccess Now engages on a wide range of issues at the intersection of human rights and technology, advancing our mission through direct stakeholder engagement and deep collaboration with civil society partners and human rights defenders around the world. Key issues\n\n\n\n\nArtificial Intelligence\n\n\n\n\n\n\n\nConnectivity\n\n\n\n\n\n\n\nContent Governance\n\n\n\n\n\n\n\nCovid-19\n\n\n\n\n\n\n\nCybersecurity\n\n\n\n\n\n\n\nData Protection\n\n\n\n\n\n\n\nDigital Divide\n\n\n\n\n\n\n\nDigital Identity Systems\n\n\n\n\n\n\n\nDigital Security\n\n\n\n\n\n\n\nFreedom of Expression\n\n\n\n\n\n\n\nInternet Shutdowns\n\n\n\n\n\n\n\nNet Neutrality\n\n\n\n\n\n\n\nPrivacy\n\n\n\n\n\n\n\nProtest and Online Organizing\n\n\n\n\n\n\n\nSurveillance\n\n\n\n\n\n\n\nTransparency\n\n\n\n\n\n\n\n\n\n\nWho we work with\n\n\n\n\n\n\n\n\nPartnerships\n\nPartnerships\n\nAccess Now is proud to work alongside a vast network of partners across civil society, academia, international and regional bodies, and both the public and private sectors. Key issues\n\n\n\n\nArtificial Intelligence\n\n\n\n\n\n\n\nConnectivity\n\n\n\n\n\n\n\nContent Governance\n\n\n\n\n\n\n\nCovid-19\n\n\n\n\n\n\n\nCybersecurity\n\n\n\n\n\n\n\nData Protection\n\n\n\n\n\n\n\nDigital Divide\n\n\n\n\n\n\n\nDigital Identity Systems\n\n\n\n\n\n\n\nDigital Security\n\n\n\n\n\n\n\nFreedom of Expression\n\n\n\n\n\n\n\nInternet Shutdowns\n\n\n\n\n\n\n\nNet Neutrality\n\n\n\n\n\n\n\nPrivacy\n\n\n\n\n\n\n\nProtest and Online Organizing\n\n\n\n\n\n\n\nSurveillance\n\n\n\n\n\n\n\nTransparency\n\n\n\n\n\n\n\n\n\n\nWho we work with\n\n\n\n\n\n\n\n\nPartnerships\n\nPartnerships\n\nAccess Now is proud to work alongside a vast network of partners across civil society, academia, international and regional bodies, and both the public and private sectors. Key issues\n\n\n\n\nArtificial Intelligence\n\n\n\n\n\n\n\nConnectivity\n\n\n\n\n\n\n\nContent Governance\n\n\n\n\n\n\n\nCovid-19\n\n\n\n\n\n\n\nCybersecurity\n\n\n\n\n\n\n\nData Protection\n\n\n\n\n\n\n\nDigital Divide\n\n\n\n\n\n\n\nDigital Identity Systems\n\n\n\n\n\n\n\nDigital Security\n\n\n\n\n\n\n\nFreedom of Expression\n\n\n\n\n\n\n\nInternet Shutdowns\n\n\n\n\n\n\n\nNet Neutrality\n\n\n\n\n\n\n\nPrivacy\n\n\n\n\n\n\n\nProtest and Online Organizing\n\n\n\n\n\n\n\nSurveillance\n\n\n\n\n\n\n\nTransparency\n\n\n\n\n\n\n\n\n\n\nWho we work with\n\n\n\n\n\n\n\n\nPartnerships\n\nPartnerships\n\nAccess Now is proud to work alongside a vast network of partners across civil society, academia, international and regional bodies, and both the public and private sectors. Key issues\n\nArtificial Intelligence\n\n\n\n\n\n\n\nConnectivity\n\n\n\n\n\n\n\nContent Governance\n\n\n\n\n\n\n\nCovid-19\n\n\n\n\n\n\n\nCybersecurity\n\n\n\n\n\n\n\nData Protection\n\n\n\n\n\n\n\nDigital Divide\n\n\n\n\n\n\n\nDigital Identity Systems\n\n\n\n\n\n\n\nDigital Security\n\n\n\n\n\n\n\nFreedom of Expression\n\n\n\n\n\n\n\nInternet Shutdowns\n\n\n\n\n\n\n\nNet Neutrality\n\n\n\n\n\n\n\nPrivacy\n\n\n\n\n\n\n\nProtest and Online Organizing\n\n\n\n\n\n\n\nSurveillance\n\n\n\n\n\n\n\nTransparency\n\nArtificial Intelligence\n\n\n\n\n\n\n\nConnectivity\n\n\n\n\n\n\n\nContent Governance\n\n\n\n\n\n\n\nCovid-19\n\n\n\n\n\n\n\nCybersecurity\n\n\n\n\n\n\n\nData Protection\n\n\n\n\n\n\n\nDigital Divide\n\n\n\n\n\n\n\nDigital Identity Systems\n\n\n\n\n\n\n\nDigital Security\n\n\n\n\n\n\n\nFreedom of Expression\n\n\n\n\n\n\n\nInternet Shutdowns\n\n\n\n\n\n\n\nNet Neutrality\n\n\n\n\n\n\n\nPrivacy\n\n\n\n\n\n\n\nProtest and Online Organizing\n\n\n\n\n\n\n\nSurveillance\n\n\n\n\n\n\n\nTransparency\n\nArtificial Intelligence\n\n\n\n\n\n\n\nConnectivity\n\n\n\n\n\n\n\nContent Governance\n\n\n\n\n\n\n\nCovid-19\n\n\n\n\n\n\n\nCybersecurity\n\n\n\n\n\n\n\nData Protection\n\n\n\n\n\n\n\nDigital Divide\n\n\n\n\n\n\n\nDigital Identity Systems\n\n\n\n\n\n\n\nDigital Security\n\n\n\n\n\n\n\nFreedom of Expression\n\n\n\n\n\n\n\nInternet Shutdowns\n\n\n\n\n\n\n\nNet Neutrality\n\n\n\n\n\n\n\nPrivacy\n\n\n\n\n\n\n\nProtest and Online Organizing\n\n\n\n\n\n\n\nSurveillance\n\n\n\n\n\n\n\nTransparency\n\nArtificial Intelligence\n\nConnectivity\n\nContent Governance\n\nCovid-19\n\nCybersecurity\n\nData Protection\n\nDigital Divide\n\nDigital Identity Systems\n\nDigital Security\n\nFreedom of Expression\n\nInternet Shutdowns\n\nNet Neutrality\n\nPrivacy\n\nProtest and Online Organizing\n\nSurveillance\n\nTransparency\n\nWho we work with\n\nPartnerships\n\nPartnerships\n\nAccess Now is proud to work alongside a vast network of partners across civil society, academia, international and regional bodies, and both the public and private sectors. Subscribe to our action alerts and weekly newsletter\n\"*\" indicates required fields\n\nThis field is hidden when viewing the form\n\nSubscribe to Access Express\nThis field is hidden when viewing the form\n\nSubscribe to Action Alerts\nName\n\n\nFirst\n\n\n\nLast\n\nEmail*\n\nCountryCountryAfghanistanÅland IslandsAlbaniaAlgeriaAmerican SamoaAndorraAngolaAnguillaAntigua and BarbudaArgentinaArmeniaArubaAustraliaAustriaAzerbaijanBahamasBahrainBangladeshBarbadosBelarusBelgiumBelizeBeninBermudaBhutanBoliviaBonaire, Sint Eustatius and SabaBosnia and HerzegovinaBotswanaBrazilBritish Indian Ocean TerritoryBritish Virgin IslandsBruneiBulgariaBurkina FasoBurundiCambodiaCameroonCanadaCape VerdeCayman IslandsCentral African RepublicChadChileChinaChristmas IslandColombiaComorosCook IslandsCosta RicaCôte d'IvoireCroatiaCubaCuraçaoCyprusCzech RepublicDemocratic Republic of the CongoDenmarkDjiboutiDominicaDominican RepublicEast TimorEcuadorEgyptEl SalvadorEquatorial GuineaEritreaEstoniaEswatiniEthiopiaFalkland IslandsFaroe IslandsFijiFinlandFranceFrench GuianaFrench PolynesiaFrench Southern TerritoriesGabonGeorgiaGermanyGhanaGibraltarGreeceGreenlandGrenadaGuadeloupeGuamGuatemalaGuernseyGuineaGuinea-BissauGuyanaHaitiHondurasHong KongHungaryIcelandIndiaIndonesiaIranIraqIrelandIsraelItalyJamaicaJapanJordanKazakhstanKenyaKiribatiKosovoKuwaitKyrgyzstanLaosLatviaLebanonLesothoLiberiaLibyaLiechtensteinLithuaniaLuxembourgMacauMadagascarMalawiMalaysiaMaldivesMaliMaltaMarshall IslandsMartiniqueMauritaniaMauritiusMayotteMexicoMicronesiaMoldovaMonacoMongoliaMontenegroMontserratMoroccoMozambiqueMyanmarNamibiaNauruNepalNetherlands AntillesNew CaledoniaNew ZealandNicaraguaNigerNigeriaNiueNorfolk IslandNorth KoreaNorth MacedoniaNorthern Mariana IslandsNorwayOmanPakistanPalauPalestinePanamaPapua New GuineaParaguayPeruPhilippinesPitcairn IslandPolandPortugalPuerto RicoQatarRepublic of the CongoReunionRomaniaRussiaRwandaSaint BarthélemySaint Kitts and NevisSaint LuciaSaint Vincent and the GrenadinesSamoaSan MarinoSão Tomé and PríncipeSaudi ArabiaSenegalSerbiaSeychellesSierra LeoneSingaporeSlovakiaSloveniaSolomon IslandsSomaliaSomalilandSouth AfricaSouth KoreaSouth SudanSpainSri LankaSt. Subscribe to our action alerts and weekly newsletter\n\"*\" indicates required fields\n\nThis field is hidden when viewing the form\n\nSubscribe to Access Express\nThis field is hidden when viewing the form\n\nSubscribe to Action Alerts\nName\n\n\nFirst\n\n\n\nLast\n\nEmail*\n\nCountryCountryAfghanistanÅland IslandsAlbaniaAlgeriaAmerican SamoaAndorraAngolaAnguillaAntigua and BarbudaArgentinaArmeniaArubaAustraliaAustriaAzerbaijanBahamasBahrainBangladeshBarbadosBelarusBelgiumBelizeBeninBermudaBhutanBoliviaBonaire, Sint Eustatius and SabaBosnia and HerzegovinaBotswanaBrazilBritish Indian Ocean TerritoryBritish Virgin IslandsBruneiBulgariaBurkina FasoBurundiCambodiaCameroonCanadaCape VerdeCayman IslandsCentral African RepublicChadChileChinaChristmas IslandColombiaComorosCook IslandsCosta RicaCôte d'IvoireCroatiaCubaCuraçaoCyprusCzech RepublicDemocratic Republic of the CongoDenmarkDjiboutiDominicaDominican RepublicEast TimorEcuadorEgyptEl SalvadorEquatorial GuineaEritreaEstoniaEswatiniEthiopiaFalkland IslandsFaroe IslandsFijiFinlandFranceFrench GuianaFrench PolynesiaFrench Southern TerritoriesGabonGeorgiaGermanyGhanaGibraltarGreeceGreenlandGrenadaGuadeloupeGuamGuatemalaGuernseyGuineaGuinea-BissauGuyanaHaitiHondurasHong KongHungaryIcelandIndiaIndonesiaIranIraqIrelandIsraelItalyJamaicaJapanJordanKazakhstanKenyaKiribatiKosovoKuwaitKyrgyzstanLaosLatviaLebanonLesothoLiberiaLibyaLiechtensteinLithuaniaLuxembourgMacauMadagascarMalawiMalaysiaMaldivesMaliMaltaMarshall IslandsMartiniqueMauritaniaMauritiusMayotteMexicoMicronesiaMoldovaMonacoMongoliaMontenegroMontserratMoroccoMozambiqueMyanmarNamibiaNauruNepalNetherlands AntillesNew CaledoniaNew ZealandNicaraguaNigerNigeriaNiueNorfolk IslandNorth KoreaNorth MacedoniaNorthern Mariana IslandsNorwayOmanPakistanPalauPalestinePanamaPapua New GuineaParaguayPeruPhilippinesPitcairn IslandPolandPortugalPuerto RicoQatarRepublic of the CongoReunionRomaniaRussiaRwandaSaint BarthélemySaint Kitts and NevisSaint LuciaSaint Vincent and the GrenadinesSamoaSan MarinoSão Tomé and PríncipeSaudi ArabiaSenegalSerbiaSeychellesSierra LeoneSingaporeSlovakiaSloveniaSolomon IslandsSomaliaSomalilandSouth AfricaSouth KoreaSouth SudanSpainSri LankaSt. Subscribe to our action alerts and weekly newsletter\n\"*\" indicates required fields\n\nThis field is hidden when viewing the form\n\nSubscribe to Access Express\nThis field is hidden when viewing the form\n\nSubscribe to Action Alerts\nName\n\n\nFirst\n\n\n\nLast\n\nEmail*\n\nCountryCountryAfghanistanÅland IslandsAlbaniaAlgeriaAmerican SamoaAndorraAngolaAnguillaAntigua and BarbudaArgentinaArmeniaArubaAustraliaAustriaAzerbaijanBahamasBahrainBangladeshBarbadosBelarusBelgiumBelizeBeninBermudaBhutanBoliviaBonaire, Sint Eustatius and SabaBosnia and HerzegovinaBotswanaBrazilBritish Indian Ocean TerritoryBritish Virgin IslandsBruneiBulgariaBurkina FasoBurundiCambodiaCameroonCanadaCape VerdeCayman IslandsCentral African RepublicChadChileChinaChristmas IslandColombiaComorosCook IslandsCosta RicaCôte d'IvoireCroatiaCubaCuraçaoCyprusCzech RepublicDemocratic Republic of the CongoDenmarkDjiboutiDominicaDominican RepublicEast TimorEcuadorEgyptEl SalvadorEquatorial GuineaEritreaEstoniaEswatiniEthiopiaFalkland IslandsFaroe IslandsFijiFinlandFranceFrench GuianaFrench PolynesiaFrench Southern TerritoriesGabonGeorgiaGermanyGhanaGibraltarGreeceGreenlandGrenadaGuadeloupeGuamGuatemalaGuernseyGuineaGuinea-BissauGuyanaHaitiHondurasHong KongHungaryIcelandIndiaIndonesiaIranIraqIrelandIsraelItalyJamaicaJapanJordanKazakhstanKenyaKiribatiKosovoKuwaitKyrgyzstanLaosLatviaLebanonLesothoLiberiaLibyaLiechtensteinLithuaniaLuxembourgMacauMadagascarMalawiMalaysiaMaldivesMaliMaltaMarshall IslandsMartiniqueMauritaniaMauritiusMayotteMexicoMicronesiaMoldovaMonacoMongoliaMontenegroMontserratMoroccoMozambiqueMyanmarNamibiaNauruNepalNetherlands AntillesNew CaledoniaNew ZealandNicaraguaNigerNigeriaNiueNorfolk IslandNorth KoreaNorth MacedoniaNorthern Mariana IslandsNorwayOmanPakistanPalauPalestinePanamaPapua New GuineaParaguayPeruPhilippinesPitcairn IslandPolandPortugalPuerto RicoQatarRepublic of the CongoReunionRomaniaRussiaRwandaSaint BarthélemySaint Kitts and NevisSaint LuciaSaint Vincent and the GrenadinesSamoaSan MarinoSão Tomé and PríncipeSaudi ArabiaSenegalSerbiaSeychellesSierra LeoneSingaporeSlovakiaSloveniaSolomon IslandsSomaliaSomalilandSouth AfricaSouth KoreaSouth SudanSpainSri LankaSt. Subscribe to our action alerts and weekly newsletter\n\"*\" indicates required fields\n\nSubscribe to our action alerts and weekly newsletter\n\n\"*\" indicates required fields\n\nThis field is hidden when viewing the form\n\nSubscribe to Access Express\nThis field is hidden when viewing the form\n\nSubscribe to Action Alerts\nName\n\n\nFirst\n\n\n\nLast\n\nEmail*\n\nCountryCountryAfghanistanÅland IslandsAlbaniaAlgeriaAmerican SamoaAndorraAngolaAnguillaAntigua and BarbudaArgentinaArmeniaArubaAustraliaAustriaAzerbaijanBahamasBahrainBangladeshBarbadosBelarusBelgiumBelizeBeninBermudaBhutanBoliviaBonaire, Sint Eustatius and SabaBosnia and HerzegovinaBotswanaBrazilBritish Indian Ocean TerritoryBritish Virgin IslandsBruneiBulgariaBurkina FasoBurundiCambodiaCameroonCanadaCape VerdeCayman IslandsCentral African RepublicChadChileChinaChristmas IslandColombiaComorosCook IslandsCosta RicaCôte d'IvoireCroatiaCubaCuraçaoCyprusCzech RepublicDemocratic Republic of the CongoDenmarkDjiboutiDominicaDominican RepublicEast TimorEcuadorEgyptEl SalvadorEquatorial GuineaEritreaEstoniaEswatiniEthiopiaFalkland IslandsFaroe IslandsFijiFinlandFranceFrench GuianaFrench PolynesiaFrench Southern TerritoriesGabonGeorgiaGermanyGhanaGibraltarGreeceGreenlandGrenadaGuadeloupeGuamGuatemalaGuernseyGuineaGuinea-BissauGuyanaHaitiHondurasHong KongHungaryIcelandIndiaIndonesiaIranIraqIrelandIsraelItalyJamaicaJapanJordanKazakhstanKenyaKiribatiKosovoKuwaitKyrgyzstanLaosLatviaLebanonLesothoLiberiaLibyaLiechtensteinLithuaniaLuxembourgMacauMadagascarMalawiMalaysiaMaldivesMaliMaltaMarshall IslandsMartiniqueMauritaniaMauritiusMayotteMexicoMicronesiaMoldovaMonacoMongoliaMontenegroMontserratMoroccoMozambiqueMyanmarNamibiaNauruNepalNetherlands AntillesNew CaledoniaNew ZealandNicaraguaNigerNigeriaNiueNorfolk IslandNorth KoreaNorth MacedoniaNorthern Mariana IslandsNorwayOmanPakistanPalauPalestinePanamaPapua New GuineaParaguayPeruPhilippinesPitcairn IslandPolandPortugalPuerto RicoQatarRepublic of the CongoReunionRomaniaRussiaRwandaSaint BarthélemySaint Kitts and NevisSaint LuciaSaint Vincent and the GrenadinesSamoaSan MarinoSão Tomé and PríncipeSaudi ArabiaSenegalSerbiaSeychellesSierra LeoneSingaporeSlovakiaSloveniaSolomon IslandsSomaliaSomalilandSouth AfricaSouth KoreaSouth SudanSpainSri LankaSt. This field is hidden when viewing the form\n\nSubscribe to Access Express\nThis field is hidden when viewing the form\n\nSubscribe to Action Alerts\nName\n\n\nFirst\n\n\n\nLast\n\nEmail*\n\nCountryCountryAfghanistanÅland IslandsAlbaniaAlgeriaAmerican SamoaAndorraAngolaAnguillaAntigua and BarbudaArgentinaArmeniaArubaAustraliaAustriaAzerbaijanBahamasBahrainBangladeshBarbadosBelarusBelgiumBelizeBeninBermudaBhutanBoliviaBonaire, Sint Eustatius and SabaBosnia and HerzegovinaBotswanaBrazilBritish Indian Ocean TerritoryBritish Virgin IslandsBruneiBulgariaBurkina FasoBurundiCambodiaCameroonCanadaCape VerdeCayman IslandsCentral African RepublicChadChileChinaChristmas IslandColombiaComorosCook IslandsCosta RicaCôte d'IvoireCroatiaCubaCuraçaoCyprusCzech RepublicDemocratic Republic of the CongoDenmarkDjiboutiDominicaDominican RepublicEast TimorEcuadorEgyptEl SalvadorEquatorial GuineaEritreaEstoniaEswatiniEthiopiaFalkland IslandsFaroe IslandsFijiFinlandFranceFrench GuianaFrench PolynesiaFrench Southern TerritoriesGabonGeorgiaGermanyGhanaGibraltarGreeceGreenlandGrenadaGuadeloupeGuamGuatemalaGuernseyGuineaGuinea-BissauGuyanaHaitiHondurasHong KongHungaryIcelandIndiaIndonesiaIranIraqIrelandIsraelItalyJamaicaJapanJordanKazakhstanKenyaKiribatiKosovoKuwaitKyrgyzstanLaosLatviaLebanonLesothoLiberiaLibyaLiechtensteinLithuaniaLuxembourgMacauMadagascarMalawiMalaysiaMaldivesMaliMaltaMarshall IslandsMartiniqueMauritaniaMauritiusMayotteMexicoMicronesiaMoldovaMonacoMongoliaMontenegroMontserratMoroccoMozambiqueMyanmarNamibiaNauruNepalNetherlands AntillesNew CaledoniaNew ZealandNicaraguaNigerNigeriaNiueNorfolk IslandNorth KoreaNorth MacedoniaNorthern Mariana IslandsNorwayOmanPakistanPalauPalestinePanamaPapua New GuineaParaguayPeruPhilippinesPitcairn IslandPolandPortugalPuerto RicoQatarRepublic of the CongoReunionRomaniaRussiaRwandaSaint BarthélemySaint Kitts and NevisSaint LuciaSaint Vincent and the GrenadinesSamoaSan MarinoSão Tomé and PríncipeSaudi ArabiaSenegalSerbiaSeychellesSierra LeoneSingaporeSlovakiaSloveniaSolomon IslandsSomaliaSomalilandSouth AfricaSouth KoreaSouth SudanSpainSri LankaSt. This field is hidden when viewing the form\n\nSubscribe to Access Express\n\nSubscribe to Access Express\n\nSubscribe to Access Express\n\nThis field is hidden when viewing the form\n\nSubscribe to Action Alerts\n\nSubscribe to Action Alerts\n\nSubscribe to Action Alerts\n\nFirst\n\n\n\nLast\n\nEmail*\n\nCountryCountryAfghanistanÅland IslandsAlbaniaAlgeriaAmerican SamoaAndorraAngolaAnguillaAntigua and BarbudaArgentinaArmeniaArubaAustraliaAustriaAzerbaijanBahamasBahrainBangladeshBarbadosBelarusBelgiumBelizeBeninBermudaBhutanBoliviaBonaire, Sint Eustatius and SabaBosnia and HerzegovinaBotswanaBrazilBritish Indian Ocean TerritoryBritish Virgin IslandsBruneiBulgariaBurkina FasoBurundiCambodiaCameroonCanadaCape VerdeCayman IslandsCentral African RepublicChadChileChinaChristmas IslandColombiaComorosCook IslandsCosta RicaCôte d'IvoireCroatiaCubaCuraçaoCyprusCzech RepublicDemocratic Republic of the CongoDenmarkDjiboutiDominicaDominican RepublicEast TimorEcuadorEgyptEl SalvadorEquatorial GuineaEritreaEstoniaEswatiniEthiopiaFalkland IslandsFaroe IslandsFijiFinlandFranceFrench GuianaFrench PolynesiaFrench Southern TerritoriesGabonGeorgiaGermanyGhanaGibraltarGreeceGreenlandGrenadaGuadeloupeGuamGuatemalaGuernseyGuineaGuinea-BissauGuyanaHaitiHondurasHong KongHungaryIcelandIndiaIndonesiaIranIraqIrelandIsraelItalyJamaicaJapanJordanKazakhstanKenyaKiribatiKosovoKuwaitKyrgyzstanLaosLatviaLebanonLesothoLiberiaLibyaLiechtensteinLithuaniaLuxembourgMacauMadagascarMalawiMalaysiaMaldivesMaliMaltaMarshall IslandsMartiniqueMauritaniaMauritiusMayotteMexicoMicronesiaMoldovaMonacoMongoliaMontenegroMontserratMoroccoMozambiqueMyanmarNamibiaNauruNepalNetherlands AntillesNew CaledoniaNew ZealandNicaraguaNigerNigeriaNiueNorfolk IslandNorth KoreaNorth MacedoniaNorthern Mariana IslandsNorwayOmanPakistanPalauPalestinePanamaPapua New GuineaParaguayPeruPhilippinesPitcairn IslandPolandPortugalPuerto RicoQatarRepublic of the CongoReunionRomaniaRussiaRwandaSaint BarthélemySaint Kitts and NevisSaint LuciaSaint Vincent and the GrenadinesSamoaSan MarinoSão Tomé and PríncipeSaudi ArabiaSenegalSerbiaSeychellesSierra LeoneSingaporeSlovakiaSloveniaSolomon IslandsSomaliaSomalilandSouth AfricaSouth KoreaSouth SudanSpainSri LankaSt. Pierre and MiquelonSudanSurinameSwedenSwitzerlandSyriaTaiwanTajikistanTanzaniaThailandThe GambiaThe NetherlandsTogoTokelauTongaTrinidad and TobagoTunisiaTurkeyTurkmenistanTurks and Caicos IslandsTuvaluUgandaUkraineUnited Arab EmiratesUnited KingdomUnited StatesUruguayUzbekistanVanuatuVatican CityVenezuelaVietnamVirgin Islands (U.S.)Wallis and Futuna IslandsWestern SaharaYemenZambiaZimbabwe\n\nCountryAfghanistanÅland IslandsAlbaniaAlgeriaAmerican SamoaAndorraAngolaAnguillaAntigua and BarbudaArgentinaArmeniaArubaAustraliaAustriaAzerbaijanBahamasBahrainBangladeshBarbadosBelarusBelgiumBelizeBeninBermudaBhutanBoliviaBonaire, Sint Eustatius and SabaBosnia and HerzegovinaBotswanaBrazilBritish Indian Ocean TerritoryBritish Virgin IslandsBruneiBulgariaBurkina FasoBurundiCambodiaCameroonCanadaCape VerdeCayman IslandsCentral African RepublicChadChileChinaChristmas IslandColombiaComorosCook IslandsCosta RicaCôte d'IvoireCroatiaCubaCuraçaoCyprusCzech RepublicDemocratic Republic of the CongoDenmarkDjiboutiDominicaDominican RepublicEast TimorEcuadorEgyptEl SalvadorEquatorial GuineaEritreaEstoniaEswatiniEthiopiaFalkland IslandsFaroe IslandsFijiFinlandFranceFrench GuianaFrench PolynesiaFrench Southern TerritoriesGabonGeorgiaGermanyGhanaGibraltarGreeceGreenlandGrenadaGuadeloupeGuamGuatemalaGuernseyGuineaGuinea-BissauGuyanaHaitiHondurasHong KongHungaryIcelandIndiaIndonesiaIranIraqIrelandIsraelItalyJamaicaJapanJordanKazakhstanKenyaKiribatiKosovoKuwaitKyrgyzstanLaosLatviaLebanonLesothoLiberiaLibyaLiechtensteinLithuaniaLuxembourgMacauMadagascarMalawiMalaysiaMaldivesMaliMaltaMarshall IslandsMartiniqueMauritaniaMauritiusMayotteMexicoMicronesiaMoldovaMonacoMongoliaMontenegroMontserratMoroccoMozambiqueMyanmarNamibiaNauruNepalNetherlands AntillesNew CaledoniaNew ZealandNicaraguaNigerNigeriaNiueNorfolk IslandNorth KoreaNorth MacedoniaNorthern Mariana IslandsNorwayOmanPakistanPalauPalestinePanamaPapua New GuineaParaguayPeruPhilippinesPitcairn IslandPolandPortugalPuerto RicoQatarRepublic of the CongoReunionRomaniaRussiaRwandaSaint BarthélemySaint Kitts and NevisSaint LuciaSaint Vincent and the GrenadinesSamoaSan MarinoSão Tomé and PríncipeSaudi ArabiaSenegalSerbiaSeychellesSierra LeoneSingaporeSlovakiaSloveniaSolomon IslandsSomaliaSomalilandSouth AfricaSouth KoreaSouth SudanSpainSri LankaSt.",
  "entities": {
    "countries": [
      "afghanistan",
      "australia",
      "brazil",
      "canada",
      "china",
      "france",
      "germany",
      "india",
      "iran",
      "iraq",
      "israel",
      "japan",
      "mexico",
      "north korea",
      "pakistan",
      "russia",
      "south korea",
      "syria",
      "united kingdom",
      "united states",
      "yemen"
    ],
    "organizations": [
      "united nations",
      "un",
      "who"
    ],
    "key_issues": [
      "issue",
      "country",
      "nation",
      "state",
      "region",
      "territory",
      "policy",
      "action",
      "human rights",
      "united nations",
      "un",
      "ngo",
      "organization"
    ]
  },
  "committee": "First Committee",
  "topic": "Creating systems to protect against state-sponsored cyber attacks"
}