{
  "url": "https://www.unoosa.org/oosa/index.html",
  "title": "UNOOSA",
  "text": "United NationsOffice for Outer Space Affairs\n\nUnited NationsOffice for Outer Space Affairs\n\nUnited NationsOffice for Outer Space Affairs\n\nUnited NationsOffice for Outer Space Affairs\n\nAbout UsRoles and ResponsibilitiesAnnual ReportsDirectorStructurePartnershipsUNOOSA Space Camp 2024HistoryTreatiesUNISPACE ConferencesTimeline: UN and SpaceEmploymentContact UsOur WorkSecretariat of COPUOS Committee and its SubcommitteesCOPUOS 2023 Session STSC 2024 SessionLSC 2024 SessionPast sessionsWorking Groups Action Team on Lunar Activities Consultation (ATLAC)General Assembly Joint PanelHistoryMember States and Observer OrganizationsMembership Evolution Observer OrganizationsMeetings ScheduleDocumentsVIC OnlineTechnical PresentationsDigital RecordingsProgramme on Space Applications PSA NewsSchedule of Activities202520242023202220212020201920182017201620152014201320122011201020092008FellowshipsDropTESPNSTBasic Space Science Initiative (BSSI)BSS Workshops (1991-2004)International Heliophysical Year 2007International Space Weather Initiative (ISWI)Basic Space Technology Initiative (BSTI)Events and ActivitiesFellowship ProgrammeResourcesEducationProjectsHuman Space Technology Initiative (HSTI)EventsGround-based ExperimentsZGIPDropTESHyperGESOrbital OpportunitiesKiboCUBEOrbital MissionChina Space StationBartolomeoCubeSats with Vega-CAreas of workBiodiversity/EcosystemsClimate ChangeDisaster ManagementEnvironmental Monitoring and Natural Resource ManagementGlobal HealthGlobal Navigation Satellite SystemsCurrent WorkshopPast WorkshopsSatellite CommunicationsRegional Centres for Space Science and Technology EducationAfrica, Nigeria (ARCSSTE-E)Africa, Morocco (CRASTE-LF)Latin America & Caribbean, Mexico & Brazil (CRECTEALC)Asia/Pacific, India (CSSTEAP)West Asia, Jordan (RCSSTEWA)Asia/Pacific, China (RCSSTEAP)Education CurriculaPublicationsReportsUN-SPIDERKnowledge ManagementTechnical Advisory SupportNetworkNews and EventsContact UsInternational Committee on GNSSOverviewMembersICG Terms of ReferenceProviders' ForumGNSS ProvidersMeetingsWorking GroupsWorking Group SIDMPerformance StandardsWorking Group BWorking Group CWorking Group DTemplatesRecommendationsICG Annual MeetingsCurrent MeetingPast MeetingsICG Programme on GNSS Applications WorkshopsSpace WeatherResourcesReference SystemsEducation MaterialsICG DocumentsA/AC.105/ seriesTerms of ReferenceWorking Group ReportsPublicationsVideosPerformance StandardsICG Reports ExtractsICG WG RecommendationsICG TimelineUN-SpaceInter-Agency MeetingCurrent/Upcoming SessionOpen Informal SessionsList of Participating OrganizationsSecretary-General's and meeting reportsSpecial Reports & PublicationsContactsSpace LawTreaties & PrinciplesTreaty StatusTravaux PréparatoiresSpace Law ResolutionsNational Space LawBilateral & Multilateral Agreements Non-legally Binding UN Instruments on Outer SpaceTreaty ImplementationSpace Object RegisterPublicationsCapacity BuildingUN Conference on Space Law and PolicyFirst UN Conference on Space Law & PolicyUN/Turkey/APSCO ConferenceUN Conference - African PerspectivesUN/Chile Conference on Space Law and PolicyUN Conference on Space Law and Policy: The Outer Space Treaty for the 21st Century2024 UN Conference on Space Law and PolicySpace Law WorkshopsSpace Law CurriculumRegistration Project: Supporting Space Object RegistrationMoon, Mars and Beyond Sustainable Lunar Activities Conference 2024Benefits of SpaceAgricultureGlobal HealthEnvironmentSustainable DevelopmentDisastersEducationHuman SettlementsResearch & DevelomentTransportationCommunicationHumanitarian Assistance  International Peace & Security Access to Space for AllFor Member StatesPartnershipsOpportunitiesHypergravity/Microgravity TrackSatellite Development TrackSpace Exploration TrackAwardeesAcknowledgementSpace Law for New Space ActorsSpace for Persons with Disabilities Space4YouthSpace4Youth Competition 2025 Competition2024 Competition2022 Competition2021 Competition2020 Competition2019 CompetitionSpace4Youth StoriesSubmitting Stories Space4WaterSpace4WomenWorld Space ForumCurrent Event - WSF 2024Past EventsWorldwide Space AgenciesCapacity Building ActivitiesCapacity Building ProjectsSpace Treaty ImplementationLong-term Sustainability of Outer Space ActivitiesDisaster ManagementNear Earth ObjectsSMPAGIAWNPlanetary Defence ConferencesInternational Asteroid DayDocumentsSpace and Climate ChangeNuclear Power SourcesGNSSRemote Sensing Space DebrisSpace Debris CompendiumSpace WeatherSpace Solutions for the PacificSpace Exploration and Innovation Space EconomySpace and Global HealthPromoting Space SustainabilitySpace4SDGsSDG 1: No PovertySDG 2: Zero HungerSDG 3: Good Health & Well-beingSDG 4: Quality EducationSDG 5: Gender EqualitySDG 6: Clean Water & SanitationSDG 7: Affordable & Clean EnergySDG 8: Decent Work & Economic GrowthSDG 9: Industry, Innovation & InfrastructureSDG 10: Reduced InequalitiesSDG 11: Sustainable Cities & CommunitiesSDG 12: Responsible Consumption & ProductionSDG 13: Climate ActionSDG 14: Life Below WaterSDG 15: Life on Land SDG 16: Peace, Justice & Strong InstitutionsSDG 17: Partnerships for the GoalsInformation for...For Member States & OrganizationsAccessMeeting logistics UNOOSA Space Camp 2024For StudentsOnline LearningFor MediaMedia ArchivePhoto Gallery For Industry & the Private SectorEventsSearch Events202520242023202220212020201920182017201620152014201320122011201020092008CalendarMapFeatured EventsWorld Space ForumInternational Day of Human Space FlightMessages from Space Explorers to Future Generations International Asteroid DayWorld Space WeekInternational Moon DayUNOOSA Space Camp 2024Space Object Register Registration ConventionRegistration SubmissionsBy States and Organizations By Year of IssueNational Registry NotificationsNational Focal PointsNational Space Object RegistriesOnline Index of Objects Launched into Outer SpaceSearch indexTreaty ImplementationResources on Space Object RegistrationDocumentsGeneral Assembly ResolutionsCOPUOS ReportsUN-Space PSA Activity ReportsUN-SPIDERICG ReportsPublicationsOther DocumentsCOPUOS 2025COPUOS 2025 Session STSC 2025 SessionLSC 2025 SessionWorking GroupsPast SessionsSpace2030Digital RecordingsReport ArchiveTechnical Presentations\n\nAbout UsRoles and ResponsibilitiesAnnual ReportsDirectorStructurePartnershipsUNOOSA Space Camp 2024HistoryTreatiesUNISPACE ConferencesTimeline: UN and SpaceEmploymentContact UsOur WorkSecretariat of COPUOS Committee and its SubcommitteesCOPUOS 2023 Session STSC 2024 SessionLSC 2024 SessionPast sessionsWorking Groups Action Team on Lunar Activities Consultation (ATLAC)General Assembly Joint PanelHistoryMember States and Observer OrganizationsMembership Evolution Observer OrganizationsMeetings ScheduleDocumentsVIC OnlineTechnical PresentationsDigital RecordingsProgramme on Space Applications PSA NewsSchedule of Activities202520242023202220212020201920182017201620152014201320122011201020092008FellowshipsDropTESPNSTBasic Space Science Initiative (BSSI)BSS Workshops (1991-2004)International Heliophysical Year 2007International Space Weather Initiative (ISWI)Basic Space Technology Initiative (BSTI)Events and ActivitiesFellowship ProgrammeResourcesEducationProjectsHuman Space Technology Initiative (HSTI)EventsGround-based ExperimentsZGIPDropTESHyperGESOrbital OpportunitiesKiboCUBEOrbital MissionChina Space StationBartolomeoCubeSats with Vega-CAreas of workBiodiversity/EcosystemsClimate ChangeDisaster ManagementEnvironmental Monitoring and Natural Resource ManagementGlobal HealthGlobal Navigation Satellite SystemsCurrent WorkshopPast WorkshopsSatellite CommunicationsRegional Centres for Space Science and Technology EducationAfrica, Nigeria (ARCSSTE-E)Africa, Morocco (CRASTE-LF)Latin America & Caribbean, Mexico & Brazil (CRECTEALC)Asia/Pacific, India (CSSTEAP)West Asia, Jordan (RCSSTEWA)Asia/Pacific, China (RCSSTEAP)Education CurriculaPublicationsReportsUN-SPIDERKnowledge ManagementTechnical Advisory SupportNetworkNews and EventsContact UsInternational Committee on GNSSOverviewMembersICG Terms of ReferenceProviders' ForumGNSS ProvidersMeetingsWorking GroupsWorking Group SIDMPerformance StandardsWorking Group BWorking Group CWorking Group DTemplatesRecommendationsICG Annual MeetingsCurrent MeetingPast MeetingsICG Programme on GNSS Applications WorkshopsSpace WeatherResourcesReference SystemsEducation MaterialsICG DocumentsA/AC.105/ seriesTerms of ReferenceWorking Group ReportsPublicationsVideosPerformance StandardsICG Reports ExtractsICG WG RecommendationsICG TimelineUN-SpaceInter-Agency MeetingCurrent/Upcoming SessionOpen Informal SessionsList of Participating OrganizationsSecretary-General's and meeting reportsSpecial Reports & PublicationsContactsSpace LawTreaties & PrinciplesTreaty StatusTravaux PréparatoiresSpace Law ResolutionsNational Space LawBilateral & Multilateral Agreements Non-legally Binding UN Instruments on Outer SpaceTreaty ImplementationSpace Object RegisterPublicationsCapacity BuildingUN Conference on Space Law and PolicyFirst UN Conference on Space Law & PolicyUN/Turkey/APSCO ConferenceUN Conference - African PerspectivesUN/Chile Conference on Space Law and PolicyUN Conference on Space Law and Policy: The Outer Space Treaty for the 21st Century2024 UN Conference on Space Law and PolicySpace Law WorkshopsSpace Law CurriculumRegistration Project: Supporting Space Object RegistrationMoon, Mars and Beyond Sustainable Lunar Activities Conference 2024Benefits of SpaceAgricultureGlobal HealthEnvironmentSustainable DevelopmentDisastersEducationHuman SettlementsResearch & DevelomentTransportationCommunicationHumanitarian Assistance  International Peace & Security Access to Space for AllFor Member StatesPartnershipsOpportunitiesHypergravity/Microgravity TrackSatellite Development TrackSpace Exploration TrackAwardeesAcknowledgementSpace Law for New Space ActorsSpace for Persons with Disabilities Space4YouthSpace4Youth Competition 2025 Competition2024 Competition2022 Competition2021 Competition2020 Competition2019 CompetitionSpace4Youth StoriesSubmitting Stories Space4WaterSpace4WomenWorld Space ForumCurrent Event - WSF 2024Past EventsWorldwide Space AgenciesCapacity Building ActivitiesCapacity Building ProjectsSpace Treaty ImplementationLong-term Sustainability of Outer Space ActivitiesDisaster ManagementNear Earth ObjectsSMPAGIAWNPlanetary Defence ConferencesInternational Asteroid DayDocumentsSpace and Climate ChangeNuclear Power SourcesGNSSRemote Sensing Space DebrisSpace Debris CompendiumSpace WeatherSpace Solutions for the PacificSpace Exploration and Innovation Space EconomySpace and Global HealthPromoting Space SustainabilitySpace4SDGsSDG 1: No PovertySDG 2: Zero HungerSDG 3: Good Health & Well-beingSDG 4: Quality EducationSDG 5: Gender EqualitySDG 6: Clean Water & SanitationSDG 7: Affordable & Clean EnergySDG 8: Decent Work & Economic GrowthSDG 9: Industry, Innovation & InfrastructureSDG 10: Reduced InequalitiesSDG 11: Sustainable Cities & CommunitiesSDG 12: Responsible Consumption & ProductionSDG 13: Climate ActionSDG 14: Life Below WaterSDG 15: Life on Land SDG 16: Peace, Justice & Strong InstitutionsSDG 17: Partnerships for the GoalsInformation for...For Member States & OrganizationsAccessMeeting logistics UNOOSA Space Camp 2024For StudentsOnline LearningFor MediaMedia ArchivePhoto Gallery For Industry & the Private SectorEventsSearch Events202520242023202220212020201920182017201620152014201320122011201020092008CalendarMapFeatured EventsWorld Space ForumInternational Day of Human Space FlightMessages from Space Explorers to Future Generations International Asteroid DayWorld Space WeekInternational Moon DayUNOOSA Space Camp 2024Space Object Register Registration ConventionRegistration SubmissionsBy States and Organizations By Year of IssueNational Registry NotificationsNational Focal PointsNational Space Object RegistriesOnline Index of Objects Launched into Outer SpaceSearch indexTreaty ImplementationResources on Space Object RegistrationDocumentsGeneral Assembly ResolutionsCOPUOS ReportsUN-Space PSA Activity ReportsUN-SPIDERICG ReportsPublicationsOther DocumentsCOPUOS 2025COPUOS 2025 Session STSC 2025 SessionLSC 2025 SessionWorking GroupsPast SessionsSpace2030Digital RecordingsReport ArchiveTechnical Presentations\n\nAbout UsRoles and ResponsibilitiesAnnual ReportsDirectorStructurePartnershipsUNOOSA Space Camp 2024HistoryTreatiesUNISPACE ConferencesTimeline: UN and SpaceEmploymentContact UsOur WorkSecretariat of COPUOS Committee and its SubcommitteesCOPUOS 2023 Session STSC 2024 SessionLSC 2024 SessionPast sessionsWorking Groups Action Team on Lunar Activities Consultation (ATLAC)General Assembly Joint PanelHistoryMember States and Observer OrganizationsMembership Evolution Observer OrganizationsMeetings ScheduleDocumentsVIC OnlineTechnical PresentationsDigital RecordingsProgramme on Space Applications PSA NewsSchedule of Activities202520242023202220212020201920182017201620152014201320122011201020092008FellowshipsDropTESPNSTBasic Space Science Initiative (BSSI)BSS Workshops (1991-2004)International Heliophysical Year 2007International Space Weather Initiative (ISWI)Basic Space Technology Initiative (BSTI)Events and ActivitiesFellowship ProgrammeResourcesEducationProjectsHuman Space Technology Initiative (HSTI)EventsGround-based ExperimentsZGIPDropTESHyperGESOrbital OpportunitiesKiboCUBEOrbital MissionChina Space StationBartolomeoCubeSats with Vega-CAreas of workBiodiversity/EcosystemsClimate ChangeDisaster ManagementEnvironmental Monitoring and Natural Resource ManagementGlobal HealthGlobal Navigation Satellite SystemsCurrent WorkshopPast WorkshopsSatellite CommunicationsRegional Centres for Space Science and Technology EducationAfrica, Nigeria (ARCSSTE-E)Africa, Morocco (CRASTE-LF)Latin America & Caribbean, Mexico & Brazil (CRECTEALC)Asia/Pacific, India (CSSTEAP)West Asia, Jordan (RCSSTEWA)Asia/Pacific, China (RCSSTEAP)Education CurriculaPublicationsReportsUN-SPIDERKnowledge ManagementTechnical Advisory SupportNetworkNews and EventsContact UsInternational Committee on GNSSOverviewMembersICG Terms of ReferenceProviders' ForumGNSS ProvidersMeetingsWorking GroupsWorking Group SIDMPerformance StandardsWorking Group BWorking Group CWorking Group DTemplatesRecommendationsICG Annual MeetingsCurrent MeetingPast MeetingsICG Programme on GNSS Applications WorkshopsSpace WeatherResourcesReference SystemsEducation MaterialsICG DocumentsA/AC.105/ seriesTerms of ReferenceWorking Group ReportsPublicationsVideosPerformance StandardsICG Reports ExtractsICG WG RecommendationsICG TimelineUN-SpaceInter-Agency MeetingCurrent/Upcoming SessionOpen Informal SessionsList of Participating OrganizationsSecretary-General's and meeting reportsSpecial Reports & PublicationsContactsSpace LawTreaties & PrinciplesTreaty StatusTravaux PréparatoiresSpace Law ResolutionsNational Space LawBilateral & Multilateral Agreements Non-legally Binding UN Instruments on Outer SpaceTreaty ImplementationSpace Object RegisterPublicationsCapacity BuildingUN Conference on Space Law and PolicyFirst UN Conference on Space Law & PolicyUN/Turkey/APSCO ConferenceUN Conference - African PerspectivesUN/Chile Conference on Space Law and PolicyUN Conference on Space Law and Policy: The Outer Space Treaty for the 21st Century2024 UN Conference on Space Law and PolicySpace Law WorkshopsSpace Law CurriculumRegistration Project: Supporting Space Object RegistrationMoon, Mars and Beyond Sustainable Lunar Activities Conference 2024Benefits of SpaceAgricultureGlobal HealthEnvironmentSustainable DevelopmentDisastersEducationHuman SettlementsResearch & DevelomentTransportationCommunicationHumanitarian Assistance  International Peace & Security Access to Space for AllFor Member StatesPartnershipsOpportunitiesHypergravity/Microgravity TrackSatellite Development TrackSpace Exploration TrackAwardeesAcknowledgementSpace Law for New Space ActorsSpace for Persons with Disabilities Space4YouthSpace4Youth Competition 2025 Competition2024 Competition2022 Competition2021 Competition2020 Competition2019 CompetitionSpace4Youth StoriesSubmitting Stories Space4WaterSpace4WomenWorld Space ForumCurrent Event - WSF 2024Past EventsWorldwide Space AgenciesCapacity Building ActivitiesCapacity Building ProjectsSpace Treaty ImplementationLong-term Sustainability of Outer Space ActivitiesDisaster ManagementNear Earth ObjectsSMPAGIAWNPlanetary Defence ConferencesInternational Asteroid DayDocumentsSpace and Climate ChangeNuclear Power SourcesGNSSRemote Sensing Space DebrisSpace Debris CompendiumSpace WeatherSpace Solutions for the PacificSpace Exploration and Innovation Space EconomySpace and Global HealthPromoting Space SustainabilitySpace4SDGsSDG 1: No PovertySDG 2: Zero HungerSDG 3: Good Health & Well-beingSDG 4: Quality EducationSDG 5: Gender EqualitySDG 6: Clean Water & SanitationSDG 7: Affordable & Clean EnergySDG 8: Decent Work & Economic GrowthSDG 9: Industry, Innovation & InfrastructureSDG 10: Reduced InequalitiesSDG 11: Sustainable Cities & CommunitiesSDG 12: Responsible Consumption & ProductionSDG 13: Climate ActionSDG 14: Life Below WaterSDG 15: Life on Land SDG 16: Peace, Justice & Strong InstitutionsSDG 17: Partnerships for the GoalsInformation for...For Member States & OrganizationsAccessMeeting logistics UNOOSA Space Camp 2024For StudentsOnline LearningFor MediaMedia ArchivePhoto Gallery For Industry & the Private SectorEventsSearch Events202520242023202220212020201920182017201620152014201320122011201020092008CalendarMapFeatured EventsWorld Space ForumInternational Day of Human Space FlightMessages from Space Explorers to Future Generations International Asteroid DayWorld Space WeekInternational Moon DayUNOOSA Space Camp 2024Space Object Register Registration ConventionRegistration SubmissionsBy States and Organizations By Year of IssueNational Registry NotificationsNational Focal PointsNational Space Object RegistriesOnline Index of Objects Launched into Outer SpaceSearch indexTreaty ImplementationResources on Space Object RegistrationDocumentsGeneral Assembly ResolutionsCOPUOS ReportsUN-Space PSA Activity ReportsUN-SPIDERICG ReportsPublicationsOther DocumentsCOPUOS 2025COPUOS 2025 Session STSC 2025 SessionLSC 2025 SessionWorking GroupsPast SessionsSpace2030Digital RecordingsReport ArchiveTechnical Presentations\n\nAbout UsRoles and ResponsibilitiesAnnual ReportsDirectorStructurePartnershipsUNOOSA Space Camp 2024HistoryTreatiesUNISPACE ConferencesTimeline: UN and SpaceEmploymentContact UsOur WorkSecretariat of COPUOS Committee and its SubcommitteesCOPUOS 2023 Session STSC 2024 SessionLSC 2024 SessionPast sessionsWorking Groups Action Team on Lunar Activities Consultation (ATLAC)General Assembly Joint PanelHistoryMember States and Observer OrganizationsMembership Evolution Observer OrganizationsMeetings ScheduleDocumentsVIC OnlineTechnical PresentationsDigital RecordingsProgramme on Space Applications PSA NewsSchedule of Activities202520242023202220212020201920182017201620152014201320122011201020092008FellowshipsDropTESPNSTBasic Space Science Initiative (BSSI)BSS Workshops (1991-2004)International Heliophysical Year 2007International Space Weather Initiative (ISWI)Basic Space Technology Initiative (BSTI)Events and ActivitiesFellowship ProgrammeResourcesEducationProjectsHuman Space Technology Initiative (HSTI)EventsGround-based ExperimentsZGIPDropTESHyperGESOrbital OpportunitiesKiboCUBEOrbital MissionChina Space StationBartolomeoCubeSats with Vega-CAreas of workBiodiversity/EcosystemsClimate ChangeDisaster ManagementEnvironmental Monitoring and Natural Resource ManagementGlobal HealthGlobal Navigation Satellite SystemsCurrent WorkshopPast WorkshopsSatellite CommunicationsRegional Centres for Space Science and Technology EducationAfrica, Nigeria (ARCSSTE-E)Africa, Morocco (CRASTE-LF)Latin America & Caribbean, Mexico & Brazil (CRECTEALC)Asia/Pacific, India (CSSTEAP)West Asia, Jordan (RCSSTEWA)Asia/Pacific, China (RCSSTEAP)Education CurriculaPublicationsReportsUN-SPIDERKnowledge ManagementTechnical Advisory SupportNetworkNews and EventsContact UsInternational Committee on GNSSOverviewMembersICG Terms of ReferenceProviders' ForumGNSS ProvidersMeetingsWorking GroupsWorking Group SIDMPerformance StandardsWorking Group BWorking Group CWorking Group DTemplatesRecommendationsICG Annual MeetingsCurrent MeetingPast MeetingsICG Programme on GNSS Applications WorkshopsSpace WeatherResourcesReference SystemsEducation MaterialsICG DocumentsA/AC.105/ seriesTerms of ReferenceWorking Group ReportsPublicationsVideosPerformance StandardsICG Reports ExtractsICG WG RecommendationsICG TimelineUN-SpaceInter-Agency MeetingCurrent/Upcoming SessionOpen Informal SessionsList of Participating OrganizationsSecretary-General's and meeting reportsSpecial Reports & PublicationsContactsSpace LawTreaties & PrinciplesTreaty StatusTravaux PréparatoiresSpace Law ResolutionsNational Space LawBilateral & Multilateral Agreements Non-legally Binding UN Instruments on Outer SpaceTreaty ImplementationSpace Object RegisterPublicationsCapacity BuildingUN Conference on Space Law and PolicyFirst UN Conference on Space Law & PolicyUN/Turkey/APSCO ConferenceUN Conference - African PerspectivesUN/Chile Conference on Space Law and PolicyUN Conference on Space Law and Policy: The Outer Space Treaty for the 21st Century2024 UN Conference on Space Law and PolicySpace Law WorkshopsSpace Law CurriculumRegistration Project: Supporting Space Object RegistrationMoon, Mars and Beyond Sustainable Lunar Activities Conference 2024Benefits of SpaceAgricultureGlobal HealthEnvironmentSustainable DevelopmentDisastersEducationHuman SettlementsResearch & DevelomentTransportationCommunicationHumanitarian Assistance  International Peace & Security Access to Space for AllFor Member StatesPartnershipsOpportunitiesHypergravity/Microgravity TrackSatellite Development TrackSpace Exploration TrackAwardeesAcknowledgementSpace Law for New Space ActorsSpace for Persons with Disabilities Space4YouthSpace4Youth Competition 2025 Competition2024 Competition2022 Competition2021 Competition2020 Competition2019 CompetitionSpace4Youth StoriesSubmitting Stories Space4WaterSpace4WomenWorld Space ForumCurrent Event - WSF 2024Past EventsWorldwide Space AgenciesCapacity Building ActivitiesCapacity Building ProjectsSpace Treaty ImplementationLong-term Sustainability of Outer Space ActivitiesDisaster ManagementNear Earth ObjectsSMPAGIAWNPlanetary Defence ConferencesInternational Asteroid DayDocumentsSpace and Climate ChangeNuclear Power SourcesGNSSRemote Sensing Space DebrisSpace Debris CompendiumSpace WeatherSpace Solutions for the PacificSpace Exploration and Innovation Space EconomySpace and Global HealthPromoting Space SustainabilitySpace4SDGsSDG 1: No PovertySDG 2: Zero HungerSDG 3: Good Health & Well-beingSDG 4: Quality EducationSDG 5: Gender EqualitySDG 6: Clean Water & SanitationSDG 7: Affordable & Clean EnergySDG 8: Decent Work & Economic GrowthSDG 9: Industry, Innovation & InfrastructureSDG 10: Reduced InequalitiesSDG 11: Sustainable Cities & CommunitiesSDG 12: Responsible Consumption & ProductionSDG 13: Climate ActionSDG 14: Life Below WaterSDG 15: Life on Land SDG 16: Peace, Justice & Strong InstitutionsSDG 17: Partnerships for the GoalsInformation for...For Member States & OrganizationsAccessMeeting logistics UNOOSA Space Camp 2024For StudentsOnline LearningFor MediaMedia ArchivePhoto Gallery For Industry & the Private SectorEventsSearch Events202520242023202220212020201920182017201620152014201320122011201020092008CalendarMapFeatured EventsWorld Space ForumInternational Day of Human Space FlightMessages from Space Explorers to Future Generations International Asteroid DayWorld Space WeekInternational Moon DayUNOOSA Space Camp 2024Space Object Register Registration ConventionRegistration SubmissionsBy States and Organizations By Year of IssueNational Registry NotificationsNational Focal PointsNational Space Object RegistriesOnline Index of Objects Launched into Outer SpaceSearch indexTreaty ImplementationResources on Space Object RegistrationDocumentsGeneral Assembly ResolutionsCOPUOS ReportsUN-Space PSA Activity ReportsUN-SPIDERICG ReportsPublicationsOther DocumentsCOPUOS 2025COPUOS 2025 Session STSC 2025 SessionLSC 2025 SessionWorking GroupsPast SessionsSpace2030Digital RecordingsReport ArchiveTechnical Presentations\n\nSixth Space4Youth Essay Competition\nWinners Announced!\n\nRead more  \nLeveraging Space Technology for Agricultural Development and Food Security\nJoint Publication by the Food and Agriculture Organization of the United Nations (FAO) and the United Nations Office for Outer Space Affairs (UNOOSA)\n\nDownload here\n\n\nGraduate Programs in Space Technology Applications: MASTA and DOCSTA\n\nThe RCSSTEAP, affiliated with the United Nations, is pleased to offer 8 postgraduate programs on Space Technology Applications for the 2025 academic year.\nApply before March 15! \n\nRead more\n\nSpace Supporting the Sustainable Development Goals\nSpace technology and its applications play an important role in supporting the 17 Sustainable Development Goals (SDGs). Find out how space research, technology and applications can help us achieve the SDGs. \n\nRead more\n\nSpace Law for New Space Actors: Fostering Responsible National Space Activities\nUNOOSA's Legal Advisory Project \"Space Law for New Space Actors\" offers Member States tailored capacity building to facilitate drafting of national space legislation in line with international space law.\n\nRead more\n\nIn Focus\n\n\nSpace4SDGs\nSee UNOOSA's \n\nbrochure to understand how space technology and its myriad applications play an important role in supporting the 17 Sustainable Development Goals (SDGs) established under the 2030 Agenda for Sustainable Development. \n\n\n\n\n\nRead more\n\n\n\n\nAccess to Space for All\nAccess to Space for All enables communities from all over the world to use and benefit from space technologies and applications thanks to the cooperation among established space actors, the United Nations and non or emerging space entities.\n\nRead more\n\n\n\n\nUNOOSA Annual Report 2023\nFor UNOOSA, 2023 was an eventful year of building capacities, advancing gender equality, facilitating space sustainability, enhancing disaster preparedness, raising awareness of the benefits of space and promoting cooperation in space activities. Discover more in the latest Annual Report.\n\nRead more \n\n\n\nOnline courses\nStudying online boosts career opportunities and broadens horizons. In cooperation with various partners, UNOOSA has launched several online courses in different languages teaching about the space economy, space law and policy, and the long-term sustainability of space activities.\n\nRead more\n\nWhat's newNewsPublicationsReportsApril 7, 2025A/AC.105/C.2/L.342 - Summary by the Chair of the Working Group on the Status and Application of the Five United Nations Treaties on Outer Space of views on the implementation of article XI of  the Treaty on Principles Governing the Activities of States in  the Exploration and Use of Outer Space, including the Moon and Other Celestial BodiesApril 7, 2025A/AC.105/1226/Add.5 -  Information relating to any practical case known that would warrant the definition and delimitation of outer space: Djibouti, Ecuador, Jamaica, Myanmar and TunisiaApril 2, 2025Workshop on Ionospheric Impacts on GNSS and International Collaboration to Meet Current and Future Solar Activity Period Challenges, 25 - 26 June 2025, Vienna International Centre, AustriaApril 2, 2025A/AC.105/1039/Add.20 - Questions on suborbital flights for scientific missions and/or for human transportation: Djibouti, Ecuador, Greece, Jamaica, Mexico, Myanmar, Senegal, Slovakia and TunisiaApril 1, 2025A/AC.105/1338 - Report of the Scientific and Technical Subcommittee on its sixty-second session, held in Vienna from 3 to 14 February 2025April 1, 2025A/AC.105/1352 - Report on the United Nations Conference on Space Law and  Policy  (Vienna, Austria, 19–21 November 2024)January 31, 2025ST/SPACE/89 - Leveraging Space Technology for Agricultural Development and Food Security: Joint Publication by the Food and Agriculture Organization of the United Nations (FAO) and the United Nations Office for Outer Space Affairs (UNOOSA)June 19, 2024ST/SPACE/90 - UNOOSA 2023 Annual ReportJune 19, 2024ST/SPACE/92 - Gender Mainstreaming Toolkit for the Space SectorFebruary 9, 2024ST/SPACE/88 - The “Space2030” Agenda: Space as a Driver of Sustainable DevelopmentDecember 4, 2023ST/SPACE/91: Registration of Objects Launched into Outer Space: Stakeholder StudyJuly 11, 2023ST/SPACE/85 - Contribution to the “Space2030” Agenda: EU Space - Supporting A World Of 8 Billion People April 7, 2025A/AC.105/C.2/L.342 - Summary by the Chair of the Working Group on the Status and Application of the Five United Nations Treaties on Outer Space of views on the implementation of article XI of  the Treaty on Principles Governing the Activities of States in  the Exploration and Use of Outer Space, including the Moon and Other Celestial BodiesApril 7, 2025A/AC.105/1226/Add.5 -  Information relating to any practical case known that would warrant the definition and delimitation of outer space: Djibouti, Ecuador, Jamaica, Myanmar and TunisiaApril 2, 2025A/AC.105/1039/Add.20 - Questions on suborbital flights for scientific missions and/or for human transportation: Djibouti, Ecuador, Greece, Jamaica, Mexico, Myanmar, Senegal, Slovakia and TunisiaApril 1, 2025A/AC.105/1338 - Report of the Scientific and Technical Subcommittee on its sixty-second session, held in Vienna from 3 to 14 February 2025April 1, 2025A/AC.105/1352 - Report on the United Nations Conference on Space Law and  Policy  (Vienna, Austria, 19–21 November 2024)April 1, 2025A/AC.105/865/Add.29 - National legislation and practice relating to definition and delimitation of outer space: Djibouti, Ecuador, Greece, Mexico, Slovakia and TunisiaCalendar@UNOOSA\n\nSixth Space4Youth Essay Competition\nWinners Announced!\n\nRead more  \nLeveraging Space Technology for Agricultural Development and Food Security\nJoint Publication by the Food and Agriculture Organization of the United Nations (FAO) and the United Nations Office for Outer Space Affairs (UNOOSA)\n\nDownload here\n\n\nGraduate Programs in Space Technology Applications: MASTA and DOCSTA\n\nThe RCSSTEAP, affiliated with the United Nations, is pleased to offer 8 postgraduate programs on Space Technology Applications for the 2025 academic year.\nApply before March 15! \n\nRead more\n\nSpace Supporting the Sustainable Development Goals\nSpace technology and its applications play an important role in supporting the 17 Sustainable Development Goals (SDGs). Find out how space research, technology and applications can help us achieve the SDGs. \n\nRead more\n\nSpace Law for New Space Actors: Fostering Responsible National Space Activities\nUNOOSA's Legal Advisory Project \"Space Law for New Space Actors\" offers Member States tailored capacity building to facilitate drafting of national space legislation in line with international space law.\n\nRead more\n\nIn Focus\n\n\nSpace4SDGs\nSee UNOOSA's \n\nbrochure to understand how space technology and its myriad applications play an important role in supporting the 17 Sustainable Development Goals (SDGs) established under the 2030 Agenda for Sustainable Development. \n\n\n\n\n\nRead more\n\n\n\n\nAccess to Space for All\nAccess to Space for All enables communities from all over the world to use and benefit from space technologies and applications thanks to the cooperation among established space actors, the United Nations and non or emerging space entities.\n\nRead more\n\n\n\n\nUNOOSA Annual Report 2023\nFor UNOOSA, 2023 was an eventful year of building capacities, advancing gender equality, facilitating space sustainability, enhancing disaster preparedness, raising awareness of the benefits of space and promoting cooperation in space activities. Discover more in the latest Annual Report.\n\nRead more \n\n\n\nOnline courses\nStudying online boosts career opportunities and broadens horizons. In cooperation with various partners, UNOOSA has launched several online courses in different languages teaching about the space economy, space law and policy, and the long-term sustainability of space activities.\n\nRead more\n\nWhat's newNewsPublicationsReportsApril 7, 2025A/AC.105/C.2/L.342 - Summary by the Chair of the Working Group on the Status and Application of the Five United Nations Treaties on Outer Space of views on the implementation of article XI of  the Treaty on Principles Governing the Activities of States in  the Exploration and Use of Outer Space, including the Moon and Other Celestial BodiesApril 7, 2025A/AC.105/1226/Add.5 -  Information relating to any practical case known that would warrant the definition and delimitation of outer space: Djibouti, Ecuador, Jamaica, Myanmar and TunisiaApril 2, 2025Workshop on Ionospheric Impacts on GNSS and International Collaboration to Meet Current and Future Solar Activity Period Challenges, 25 - 26 June 2025, Vienna International Centre, AustriaApril 2, 2025A/AC.105/1039/Add.20 - Questions on suborbital flights for scientific missions and/or for human transportation: Djibouti, Ecuador, Greece, Jamaica, Mexico, Myanmar, Senegal, Slovakia and TunisiaApril 1, 2025A/AC.105/1338 - Report of the Scientific and Technical Subcommittee on its sixty-second session, held in Vienna from 3 to 14 February 2025April 1, 2025A/AC.105/1352 - Report on the United Nations Conference on Space Law and  Policy  (Vienna, Austria, 19–21 November 2024)January 31, 2025ST/SPACE/89 - Leveraging Space Technology for Agricultural Development and Food Security: Joint Publication by the Food and Agriculture Organization of the United Nations (FAO) and the United Nations Office for Outer Space Affairs (UNOOSA)June 19, 2024ST/SPACE/90 - UNOOSA 2023 Annual ReportJune 19, 2024ST/SPACE/92 - Gender Mainstreaming Toolkit for the Space SectorFebruary 9, 2024ST/SPACE/88 - The “Space2030” Agenda: Space as a Driver of Sustainable DevelopmentDecember 4, 2023ST/SPACE/91: Registration of Objects Launched into Outer Space: Stakeholder StudyJuly 11, 2023ST/SPACE/85 - Contribution to the “Space2030” Agenda: EU Space - Supporting A World Of 8 Billion People April 7, 2025A/AC.105/C.2/L.342 - Summary by the Chair of the Working Group on the Status and Application of the Five United Nations Treaties on Outer Space of views on the implementation of article XI of  the Treaty on Principles Governing the Activities of States in  the Exploration and Use of Outer Space, including the Moon and Other Celestial BodiesApril 7, 2025A/AC.105/1226/Add.5 -  Information relating to any practical case known that would warrant the definition and delimitation of outer space: Djibouti, Ecuador, Jamaica, Myanmar and TunisiaApril 2, 2025A/AC.105/1039/Add.20 - Questions on suborbital flights for scientific missions and/or for human transportation: Djibouti, Ecuador, Greece, Jamaica, Mexico, Myanmar, Senegal, Slovakia and TunisiaApril 1, 2025A/AC.105/1338 - Report of the Scientific and Technical Subcommittee on its sixty-second session, held in Vienna from 3 to 14 February 2025April 1, 2025A/AC.105/1352 - Report on the United Nations Conference on Space Law and  Policy  (Vienna, Austria, 19–21 November 2024)April 1, 2025A/AC.105/865/Add.29 - National legislation and practice relating to definition and delimitation of outer space: Djibouti, Ecuador, Greece, Mexico, Slovakia and TunisiaCalendar@UNOOSA\n\nSixth Space4Youth Essay Competition\nWinners Announced!\n\nRead more  \nLeveraging Space Technology for Agricultural Development and Food Security\nJoint Publication by the Food and Agriculture Organization of the United Nations (FAO) and the United Nations Office for Outer Space Affairs (UNOOSA)\n\nDownload here\n\n\nGraduate Programs in Space Technology Applications: MASTA and DOCSTA\n\nThe RCSSTEAP, affiliated with the United Nations, is pleased to offer 8 postgraduate programs on Space Technology Applications for the 2025 academic year.\nApply before March 15! \n\nRead more\n\nSpace Supporting the Sustainable Development Goals\nSpace technology and its applications play an important role in supporting the 17 Sustainable Development Goals (SDGs). Find out how space research, technology and applications can help us achieve the SDGs. \n\nRead more\n\nSpace Law for New Space Actors: Fostering Responsible National Space Activities\nUNOOSA's Legal Advisory Project \"Space Law for New Space Actors\" offers Member States tailored capacity building to facilitate drafting of national space legislation in line with international space law.\n\nRead more\n\nIn Focus\n\n\nSpace4SDGs\nSee UNOOSA's \n\nbrochure to understand how space technology and its myriad applications play an important role in supporting the 17 Sustainable Development Goals (SDGs) established under the 2030 Agenda for Sustainable Development. \n\n\n\n\n\nRead more\n\n\n\n\nAccess to Space for All\nAccess to Space for All enables communities from all over the world to use and benefit from space technologies and applications thanks to the cooperation among established space actors, the United Nations and non or emerging space entities.\n\nRead more\n\n\n\n\nUNOOSA Annual Report 2023\nFor UNOOSA, 2023 was an eventful year of building capacities, advancing gender equality, facilitating space sustainability, enhancing disaster preparedness, raising awareness of the benefits of space and promoting cooperation in space activities. Discover more in the latest Annual Report.\n\nRead more \n\n\n\nOnline courses\nStudying online boosts career opportunities and broadens horizons. In cooperation with various partners, UNOOSA has launched several online courses in different languages teaching about the space economy, space law and policy, and the long-term sustainability of space activities.\n\nRead more\n\nWhat's newNewsPublicationsReportsApril 7, 2025A/AC.105/C.2/L.342 - Summary by the Chair of the Working Group on the Status and Application of the Five United Nations Treaties on Outer Space of views on the implementation of article XI of  the Treaty on Principles Governing the Activities of States in  the Exploration and Use of Outer Space, including the Moon and Other Celestial BodiesApril 7, 2025A/AC.105/1226/Add.5 -  Information relating to any practical case known that would warrant the definition and delimitation of outer space: Djibouti, Ecuador, Jamaica, Myanmar and TunisiaApril 2, 2025Workshop on Ionospheric Impacts on GNSS and International Collaboration to Meet Current and Future Solar Activity Period Challenges, 25 - 26 June 2025, Vienna International Centre, AustriaApril 2, 2025A/AC.105/1039/Add.20 - Questions on suborbital flights for scientific missions and/or for human transportation: Djibouti, Ecuador, Greece, Jamaica, Mexico, Myanmar, Senegal, Slovakia and TunisiaApril 1, 2025A/AC.105/1338 - Report of the Scientific and Technical Subcommittee on its sixty-second session, held in Vienna from 3 to 14 February 2025April 1, 2025A/AC.105/1352 - Report on the United Nations Conference on Space Law and  Policy  (Vienna, Austria, 19–21 November 2024)January 31, 2025ST/SPACE/89 - Leveraging Space Technology for Agricultural Development and Food Security: Joint Publication by the Food and Agriculture Organization of the United Nations (FAO) and the United Nations Office for Outer Space Affairs (UNOOSA)June 19, 2024ST/SPACE/90 - UNOOSA 2023 Annual ReportJune 19, 2024ST/SPACE/92 - Gender Mainstreaming Toolkit for the Space SectorFebruary 9, 2024ST/SPACE/88 - The “Space2030” Agenda: Space as a Driver of Sustainable DevelopmentDecember 4, 2023ST/SPACE/91: Registration of Objects Launched into Outer Space: Stakeholder StudyJuly 11, 2023ST/SPACE/85 - Contribution to the “Space2030” Agenda: EU Space - Supporting A World Of 8 Billion People April 7, 2025A/AC.105/C.2/L.342 - Summary by the Chair of the Working Group on the Status and Application of the Five United Nations Treaties on Outer Space of views on the implementation of article XI of  the Treaty on Principles Governing the Activities of States in  the Exploration and Use of Outer Space, including the Moon and Other Celestial BodiesApril 7, 2025A/AC.105/1226/Add.5 -  Information relating to any practical case known that would warrant the definition and delimitation of outer space: Djibouti, Ecuador, Jamaica, Myanmar and TunisiaApril 2, 2025A/AC.105/1039/Add.20 - Questions on suborbital flights for scientific missions and/or for human transportation: Djibouti, Ecuador, Greece, Jamaica, Mexico, Myanmar, Senegal, Slovakia and TunisiaApril 1, 2025A/AC.105/1338 - Report of the Scientific and Technical Subcommittee on its sixty-second session, held in Vienna from 3 to 14 February 2025April 1, 2025A/AC.105/1352 - Report on the United Nations Conference on Space Law and  Policy  (Vienna, Austria, 19–21 November 2024)April 1, 2025A/AC.105/865/Add.29 - National legislation and practice relating to definition and delimitation of outer space: Djibouti, Ecuador, Greece, Mexico, Slovakia and TunisiaCalendar@UNOOSA\n\nSixth Space4Youth Essay Competition\nWinners Announced!\n\nRead more  \nLeveraging Space Technology for Agricultural Development and Food Security\nJoint Publication by the Food and Agriculture Organization of the United Nations (FAO) and the United Nations Office for Outer Space Affairs (UNOOSA)\n\nDownload here\n\n\nGraduate Programs in Space Technology Applications: MASTA and DOCSTA\n\nThe RCSSTEAP, affiliated with the United Nations, is pleased to offer 8 postgraduate programs on Space Technology Applications for the 2025 academic year.\nApply before March 15! \n\nRead more\n\nSpace Supporting the Sustainable Development Goals\nSpace technology and its applications play an important role in supporting the 17 Sustainable Development Goals (SDGs). Find out how space research, technology and applications can help us achieve the SDGs. \n\nRead more\n\nSpace Law for New Space Actors: Fostering Responsible National Space Activities\nUNOOSA's Legal Advisory Project \"Space Law for New Space Actors\" offers Member States tailored capacity building to facilitate drafting of national space legislation in line with international space law.\n\nRead more\n\nSixth Space4Youth Essay Competition\nWinners Announced!\n\nRead more  \nLeveraging Space Technology for Agricultural Development and Food Security\nJoint Publication by the Food and Agriculture Organization of the United Nations (FAO) and the United Nations Office for Outer Space Affairs (UNOOSA)\n\nDownload here\n\n\nGraduate Programs in Space Technology Applications: MASTA and DOCSTA\n\nThe RCSSTEAP, affiliated with the United Nations, is pleased to offer 8 postgraduate programs on Space Technology Applications for the 2025 academic year.\nApply before March 15! \n\nRead more\n\nSpace Supporting the Sustainable Development Goals\nSpace technology and its applications play an important role in supporting the 17 Sustainable Development Goals (SDGs). Find out how space research, technology and applications can help us achieve the SDGs. \n\nRead more\n\nSpace Law for New Space Actors: Fostering Responsible National Space Activities\nUNOOSA's Legal Advisory Project \"Space Law for New Space Actors\" offers Member States tailored capacity building to facilitate drafting of national space legislation in line with international space law.\n\nRead more\n\nSixth Space4Youth Essay Competition\nWinners Announced!\n\nRead more  \nLeveraging Space Technology for Agricultural Development and Food Security\nJoint Publication by the Food and Agriculture Organization of the United Nations (FAO) and the United Nations Office for Outer Space Affairs (UNOOSA)\n\nDownload here\n\n\nGraduate Programs in Space Technology Applications: MASTA and DOCSTA\n\nThe RCSSTEAP, affiliated with the United Nations, is pleased to offer 8 postgraduate programs on Space Technology Applications for the 2025 academic year.\nApply before March 15! \n\nRead more\n\nSpace Supporting the Sustainable Development Goals\nSpace technology and its applications play an important role in supporting the 17 Sustainable Development Goals (SDGs). Find out how space research, technology and applications can help us achieve the SDGs. \n\nRead more\n\nSpace Law for New Space Actors: Fostering Responsible National Space Activities\nUNOOSA's Legal Advisory Project \"Space Law for New Space Actors\" offers Member States tailored capacity building to facilitate drafting of national space legislation in line with international space law.\n\nRead more\n\nSixth Space4Youth Essay Competition\nWinners Announced!\n\nRead more  \nLeveraging Space Technology for Agricultural Development and Food Security\nJoint Publication by the Food and Agriculture Organization of the United Nations (FAO) and the United Nations Office for Outer Space Affairs (UNOOSA)\n\nDownload here\n\n\nGraduate Programs in Space Technology Applications: MASTA and DOCSTA\n\nThe RCSSTEAP, affiliated with the United Nations, is pleased to offer 8 postgraduate programs on Space Technology Applications for the 2025 academic year.\nApply before March 15! \n\nRead more\n\nSpace Supporting the Sustainable Development Goals\nSpace technology and its applications play an important role in supporting the 17 Sustainable Development Goals (SDGs). Find out how space research, technology and applications can help us achieve the SDGs. \n\nRead more\n\nSpace Law for New Space Actors: Fostering Responsible National Space Activities\nUNOOSA's Legal Advisory Project \"Space Law for New Space Actors\" offers Member States tailored capacity building to facilitate drafting of national space legislation in line with international space law.\n\nRead more\n\nSixth Space4Youth Essay Competition\nWinners Announced!\n\nRead more  \nLeveraging Space Technology for Agricultural Development and Food Security\nJoint Publication by the Food and Agriculture Organization of the United Nations (FAO) and the United Nations Office for Outer Space Affairs (UNOOSA)\n\nDownload here\n\n\nGraduate Programs in Space Technology Applications: MASTA and DOCSTA\n\nThe RCSSTEAP, affiliated with the United Nations, is pleased to offer 8 postgraduate programs on Space Technology Applications for the 2025 academic year.\nApply before March 15! \n\nRead more\n\nSpace Supporting the Sustainable Development Goals\nSpace technology and its applications play an important role in supporting the 17 Sustainable Development Goals (SDGs). Find out how space research, technology and applications can help us achieve the SDGs. \n\nRead more\n\nSpace Law for New Space Actors: Fostering Responsible National Space Activities\nUNOOSA's Legal Advisory Project \"Space Law for New Space Actors\" offers Member States tailored capacity building to facilitate drafting of national space legislation in line with international space law.\n\nRead more\n\nSixth Space4Youth Essay Competition\nWinners Announced!\n\nRead more\n\nSixth Space4Youth Essay Competition\nWinners Announced!\n\nRead more\n\nSixth Space4Youth Essay Competition\nWinners Announced!\n\nRead more\n\nWinners Announced!\n\nRead more\n\nLeveraging Space Technology for Agricultural Development and Food Security\nJoint Publication by the Food and Agriculture Organization of the United Nations (FAO) and the United Nations Office for Outer Space Affairs (UNOOSA)\n\nDownload here\n\nLeveraging Space Technology for Agricultural Development and Food Security\nJoint Publication by the Food and Agriculture Organization of the United Nations (FAO) and the United Nations Office for Outer Space Affairs (UNOOSA)\n\nDownload here\n\nLeveraging Space Technology for Agricultural Development and Food Security\nJoint Publication by the Food and Agriculture Organization of the United Nations (FAO) and the United Nations Office for Outer Space Affairs (UNOOSA)\n\nDownload here\n\nJoint Publication by the Food and Agriculture Organization of the United Nations (FAO) and the United Nations Office for Outer Space Affairs (UNOOSA)\n\nDownload here\n\nGraduate Programs in Space Technology Applications: MASTA and DOCSTA\n\nThe RCSSTEAP, affiliated with the United Nations, is pleased to offer 8 postgraduate programs on Space Technology Applications for the 2025 academic year.\nApply before March 15! \n\nRead more\n\nGraduate Programs in Space Technology Applications: MASTA and DOCSTA\n\nThe RCSSTEAP, affiliated with the United Nations, is pleased to offer 8 postgraduate programs on Space Technology Applications for the 2025 academic year.\nApply before March 15! \n\nRead more\n\nGraduate Programs in Space Technology Applications: MASTA and DOCSTA\n\nThe RCSSTEAP, affiliated with the United Nations, is pleased to offer 8 postgraduate programs on Space Technology Applications for the 2025 academic year.\nApply before March 15! \n\nRead more\n\nThe RCSSTEAP, affiliated with the United Nations, is pleased to offer 8 postgraduate programs on Space Technology Applications for the 2025 academic year.\nApply before March 15!\n\nRead more\n\nSpace Supporting the Sustainable Development Goals\nSpace technology and its applications play an important role in supporting the 17 Sustainable Development Goals (SDGs). Find out how space research, technology and applications can help us achieve the SDGs. \n\nRead more\n\nSpace Supporting the Sustainable Development Goals\nSpace technology and its applications play an important role in supporting the 17 Sustainable Development Goals (SDGs). Find out how space research, technology and applications can help us achieve the SDGs. \n\nRead more\n\nSpace Supporting the Sustainable Development Goals\nSpace technology and its applications play an important role in supporting the 17 Sustainable Development Goals (SDGs). Find out how space research, technology and applications can help us achieve the SDGs. \n\nRead more\n\nSpace technology and its applications play an important role in supporting the 17 Sustainable Development Goals (SDGs). Find out how space research, technology and applications can help us achieve the SDGs.\n\nRead more\n\nSpace Law for New Space Actors: Fostering Responsible National Space Activities\nUNOOSA's Legal Advisory Project \"Space Law for New Space Actors\" offers Member States tailored capacity building to facilitate drafting of national space legislation in line with international space law.\n\nRead more\n\nSpace Law for New Space Actors: Fostering Responsible National Space Activities\nUNOOSA's Legal Advisory Project \"Space Law for New Space Actors\" offers Member States tailored capacity building to facilitate drafting of national space legislation in line with international space law.\n\nRead more\n\nSpace Law for New Space Actors: Fostering Responsible National Space Activities\nUNOOSA's Legal Advisory Project \"Space Law for New Space Actors\" offers Member States tailored capacity building to facilitate drafting of national space legislation in line with international space law.\n\nRead more\n\nUNOOSA's Legal Advisory Project \"Space Law for New Space Actors\" offers Member States tailored capacity building to facilitate drafting of national space legislation in line with international space law.\n\nRead more\n\nIn Focus\n\n\nSpace4SDGs\nSee UNOOSA's \n\nbrochure to understand how space technology and its myriad applications play an important role in supporting the 17 Sustainable Development Goals (SDGs) established under the 2030 Agenda for Sustainable Development. \n\n\n\n\n\nRead more\n\n\n\n\nAccess to Space for All\nAccess to Space for All enables communities from all over the world to use and benefit from space technologies and applications thanks to the cooperation among established space actors, the United Nations and non or emerging space entities.\n\nRead more\n\n\n\n\nUNOOSA Annual Report 2023\nFor UNOOSA, 2023 was an eventful year of building capacities, advancing gender equality, facilitating space sustainability, enhancing disaster preparedness, raising awareness of the benefits of space and promoting cooperation in space activities. Discover more in the latest Annual Report.\n\nRead more \n\n\n\nOnline courses\nStudying online boosts career opportunities and broadens horizons. In cooperation with various partners, UNOOSA has launched several online courses in different languages teaching about the space economy, space law and policy, and the long-term sustainability of space activities.\n\nRead more\n\nWhat's newNewsPublicationsReportsApril 7, 2025A/AC.105/C.2/L.342 - Summary by the Chair of the Working Group on the Status and Application of the Five United Nations Treaties on Outer Space of views on the implementation of article XI of  the Treaty on Principles Governing the Activities of States in  the Exploration and Use of Outer Space, including the Moon and Other Celestial BodiesApril 7, 2025A/AC.105/1226/Add.5 -  Information relating to any practical case known that would warrant the definition and delimitation of outer space: Djibouti, Ecuador, Jamaica, Myanmar and TunisiaApril 2, 2025Workshop on Ionospheric Impacts on GNSS and International Collaboration to Meet Current and Future Solar Activity Period Challenges, 25 - 26 June 2025, Vienna International Centre, AustriaApril 2, 2025A/AC.105/1039/Add.20 - Questions on suborbital flights for scientific missions and/or for human transportation: Djibouti, Ecuador, Greece, Jamaica, Mexico, Myanmar, Senegal, Slovakia and TunisiaApril 1, 2025A/AC.105/1338 - Report of the Scientific and Technical Subcommittee on its sixty-second session, held in Vienna from 3 to 14 February 2025April 1, 2025A/AC.105/1352 - Report on the United Nations Conference on Space Law and  Policy  (Vienna, Austria, 19–21 November 2024)January 31, 2025ST/SPACE/89 - Leveraging Space Technology for Agricultural Development and Food Security: Joint Publication by the Food and Agriculture Organization of the United Nations (FAO) and the United Nations Office for Outer Space Affairs (UNOOSA)June 19, 2024ST/SPACE/90 - UNOOSA 2023 Annual ReportJune 19, 2024ST/SPACE/92 - Gender Mainstreaming Toolkit for the Space SectorFebruary 9, 2024ST/SPACE/88 - The “Space2030” Agenda: Space as a Driver of Sustainable DevelopmentDecember 4, 2023ST/SPACE/91: Registration of Objects Launched into Outer Space: Stakeholder StudyJuly 11, 2023ST/SPACE/85 - Contribution to the “Space2030” Agenda: EU Space - Supporting A World Of 8 Billion People April 7, 2025A/AC.105/C.2/L.342 - Summary by the Chair of the Working Group on the Status and Application of the Five United Nations Treaties on Outer Space of views on the implementation of article XI of  the Treaty on Principles Governing the Activities of States in  the Exploration and Use of Outer Space, including the Moon and Other Celestial BodiesApril 7, 2025A/AC.105/1226/Add.5 -  Information relating to any practical case known that would warrant the definition and delimitation of outer space: Djibouti, Ecuador, Jamaica, Myanmar and TunisiaApril 2, 2025A/AC.105/1039/Add.20 - Questions on suborbital flights for scientific missions and/or for human transportation: Djibouti, Ecuador, Greece, Jamaica, Mexico, Myanmar, Senegal, Slovakia and TunisiaApril 1, 2025A/AC.105/1338 - Report of the Scientific and Technical Subcommittee on its sixty-second session, held in Vienna from 3 to 14 February 2025April 1, 2025A/AC.105/1352 - Report on the United Nations Conference on Space Law and  Policy  (Vienna, Austria, 19–21 November 2024)April 1, 2025A/AC.105/865/Add.29 - National legislation and practice relating to definition and delimitation of outer space: Djibouti, Ecuador, Greece, Mexico, Slovakia and TunisiaCalendar@UNOOSA\n\nSpace4SDGs\nSee UNOOSA's \n\nbrochure to understand how space technology and its myriad applications play an important role in supporting the 17 Sustainable Development Goals (SDGs) established under the 2030 Agenda for Sustainable Development. \n\n\n\n\n\nRead more\n\n\n\n\nAccess to Space for All\nAccess to Space for All enables communities from all over the world to use and benefit from space technologies and applications thanks to the cooperation among established space actors, the United Nations and non or emerging space entities.\n\nRead more\n\n\n\n\nUNOOSA Annual Report 2023\nFor UNOOSA, 2023 was an eventful year of building capacities, advancing gender equality, facilitating space sustainability, enhancing disaster preparedness, raising awareness of the benefits of space and promoting cooperation in space activities. Discover more in the latest Annual Report.\n\nRead more \n\n\n\nOnline courses\nStudying online boosts career opportunities and broadens horizons. In cooperation with various partners, UNOOSA has launched several online courses in different languages teaching about the space economy, space law and policy, and the long-term sustainability of space activities.\n\nRead more\n\nSpace4SDGs\nSee UNOOSA's \n\nbrochure to understand how space technology and its myriad applications play an important role in supporting the 17 Sustainable Development Goals (SDGs) established under the 2030 Agenda for Sustainable Development. \n\n\n\n\n\nRead more\n\nSee UNOOSA's \n\nbrochure to understand how space technology and its myriad applications play an important role in supporting the 17 Sustainable Development Goals (SDGs) established under the 2030 Agenda for Sustainable Development.\n\nRead more\n\nAccess to Space for All\nAccess to Space for All enables communities from all over the world to use and benefit from space technologies and applications thanks to the cooperation among established space actors, the United Nations and non or emerging space entities.\n\nRead more\n\nAccess to Space for All enables communities from all over the world to use and benefit from space technologies and applications thanks to the cooperation among established space actors, the United Nations and non or emerging space entities.\n\nRead more\n\nUNOOSA Annual Report 2023\nFor UNOOSA, 2023 was an eventful year of building capacities, advancing gender equality, facilitating space sustainability, enhancing disaster preparedness, raising awareness of the benefits of space and promoting cooperation in space activities. Discover more in the latest Annual Report.\n\nRead more\n\nFor UNOOSA, 2023 was an eventful year of building capacities, advancing gender equality, facilitating space sustainability, enhancing disaster preparedness, raising awareness of the benefits of space and promoting cooperation in space activities. Discover more in the latest Annual Report.\n\nRead more\n\nOnline courses\nStudying online boosts career opportunities and broadens horizons. In cooperation with various partners, UNOOSA has launched several online courses in different languages teaching about the space economy, space law and policy, and the long-term sustainability of space activities.\n\nRead more\n\nStudying online boosts career opportunities and broadens horizons. In cooperation with various partners, UNOOSA has launched several online courses in different languages teaching about the space economy, space law and policy, and the long-term sustainability of space activities.\n\nRead more\n\nNewsPublicationsReportsApril 7, 2025A/AC.105/C.2/L.342 - Summary by the Chair of the Working Group on the Status and Application of the Five United Nations Treaties on Outer Space of views on the implementation of article XI of  the Treaty on Principles Governing the Activities of States in  the Exploration and Use of Outer Space, including the Moon and Other Celestial BodiesApril 7, 2025A/AC.105/1226/Add.5 -  Information relating to any practical case known that would warrant the definition and delimitation of outer space: Djibouti, Ecuador, Jamaica, Myanmar and TunisiaApril 2, 2025Workshop on Ionospheric Impacts on GNSS and International Collaboration to Meet Current and Future Solar Activity Period Challenges, 25 - 26 June 2025, Vienna International Centre, AustriaApril 2, 2025A/AC.105/1039/Add.20 - Questions on suborbital flights for scientific missions and/or for human transportation: Djibouti, Ecuador, Greece, Jamaica, Mexico, Myanmar, Senegal, Slovakia and TunisiaApril 1, 2025A/AC.105/1338 - Report of the Scientific and Technical Subcommittee on its sixty-second session, held in Vienna from 3 to 14 February 2025April 1, 2025A/AC.105/1352 - Report on the United Nations Conference on Space Law and  Policy  (Vienna, Austria, 19–21 November 2024)January 31, 2025ST/SPACE/89 - Leveraging Space Technology for Agricultural Development and Food Security: Joint Publication by the Food and Agriculture Organization of the United Nations (FAO) and the United Nations Office for Outer Space Affairs (UNOOSA)June 19, 2024ST/SPACE/90 - UNOOSA 2023 Annual ReportJune 19, 2024ST/SPACE/92 - Gender Mainstreaming Toolkit for the Space SectorFebruary 9, 2024ST/SPACE/88 - The “Space2030” Agenda: Space as a Driver of Sustainable DevelopmentDecember 4, 2023ST/SPACE/91: Registration of Objects Launched into Outer Space: Stakeholder StudyJuly 11, 2023ST/SPACE/85 - Contribution to the “Space2030” Agenda: EU Space - Supporting A World Of 8 Billion People April 7, 2025A/AC.105/C.2/L.342 - Summary by the Chair of the Working Group on the Status and Application of the Five United Nations Treaties on Outer Space of views on the implementation of article XI of  the Treaty on Principles Governing the Activities of States in  the Exploration and Use of Outer Space, including the Moon and Other Celestial BodiesApril 7, 2025A/AC.105/1226/Add.5 -  Information relating to any practical case known that would warrant the definition and delimitation of outer space: Djibouti, Ecuador, Jamaica, Myanmar and TunisiaApril 2, 2025A/AC.105/1039/Add.20 - Questions on suborbital flights for scientific missions and/or for human transportation: Djibouti, Ecuador, Greece, Jamaica, Mexico, Myanmar, Senegal, Slovakia and TunisiaApril 1, 2025A/AC.105/1338 - Report of the Scientific and Technical Subcommittee on its sixty-second session, held in Vienna from 3 to 14 February 2025April 1, 2025A/AC.105/1352 - Report on the United Nations Conference on Space Law and  Policy  (Vienna, Austria, 19–21 November 2024)April 1, 2025A/AC.105/865/Add.29 - National legislation and practice relating to definition and delimitation of outer space: Djibouti, Ecuador, Greece, Mexico, Slovakia and TunisiaCalendar@UNOOSA\n\nNewsPublicationsReportsApril 7, 2025A/AC.105/C.2/L.342 - Summary by the Chair of the Working Group on the Status and Application of the Five United Nations Treaties on Outer Space of views on the implementation of article XI of  the Treaty on Principles Governing the Activities of States in  the Exploration and Use of Outer Space, including the Moon and Other Celestial BodiesApril 7, 2025A/AC.105/1226/Add.5 -  Information relating to any practical case known that would warrant the definition and delimitation of outer space: Djibouti, Ecuador, Jamaica, Myanmar and TunisiaApril 2, 2025Workshop on Ionospheric Impacts on GNSS and International Collaboration to Meet Current and Future Solar Activity Period Challenges, 25 - 26 June 2025, Vienna International Centre, AustriaApril 2, 2025A/AC.105/1039/Add.20 - Questions on suborbital flights for scientific missions and/or for human transportation: Djibouti, Ecuador, Greece, Jamaica, Mexico, Myanmar, Senegal, Slovakia and TunisiaApril 1, 2025A/AC.105/1338 - Report of the Scientific and Technical Subcommittee on its sixty-second session, held in Vienna from 3 to 14 February 2025April 1, 2025A/AC.105/1352 - Report on the United Nations Conference on Space Law and  Policy  (Vienna, Austria, 19–21 November 2024)January 31, 2025ST/SPACE/89 - Leveraging Space Technology for Agricultural Development and Food Security: Joint Publication by the Food and Agriculture Organization of the United Nations (FAO) and the United Nations Office for Outer Space Affairs (UNOOSA)June 19, 2024ST/SPACE/90 - UNOOSA 2023 Annual ReportJune 19, 2024ST/SPACE/92 - Gender Mainstreaming Toolkit for the Space SectorFebruary 9, 2024ST/SPACE/88 - The “Space2030” Agenda: Space as a Driver of Sustainable DevelopmentDecember 4, 2023ST/SPACE/91: Registration of Objects Launched into Outer Space: Stakeholder StudyJuly 11, 2023ST/SPACE/85 - Contribution to the “Space2030” Agenda: EU Space - Supporting A World Of 8 Billion People April 7, 2025A/AC.105/C.2/L.342 - Summary by the Chair of the Working Group on the Status and Application of the Five United Nations Treaties on Outer Space of views on the implementation of article XI of  the Treaty on Principles Governing the Activities of States in  the Exploration and Use of Outer Space, including the Moon and Other Celestial BodiesApril 7, 2025A/AC.105/1226/Add.5 -  Information relating to any practical case known that would warrant the definition and delimitation of outer space: Djibouti, Ecuador, Jamaica, Myanmar and TunisiaApril 2, 2025A/AC.105/1039/Add.20 - Questions on suborbital flights for scientific missions and/or for human transportation: Djibouti, Ecuador, Greece, Jamaica, Mexico, Myanmar, Senegal, Slovakia and TunisiaApril 1, 2025A/AC.105/1338 - Report of the Scientific and Technical Subcommittee on its sixty-second session, held in Vienna from 3 to 14 February 2025April 1, 2025A/AC.105/1352 - Report on the United Nations Conference on Space Law and  Policy  (Vienna, Austria, 19–21 November 2024)April 1, 2025A/AC.105/865/Add.29 - National legislation and practice relating to definition and delimitation of outer space: Djibouti, Ecuador, Greece, Mexico, Slovakia and Tunisia\n\nNewsPublicationsReportsApril 7, 2025A/AC.105/C.2/L.342 - Summary by the Chair of the Working Group on the Status and Application of the Five United Nations Treaties on Outer Space of views on the implementation of article XI of  the Treaty on Principles Governing the Activities of States in  the Exploration and Use of Outer Space, including the Moon and Other Celestial BodiesApril 7, 2025A/AC.105/1226/Add.5 -  Information relating to any practical case known that would warrant the definition and delimitation of outer space: Djibouti, Ecuador, Jamaica, Myanmar and TunisiaApril 2, 2025Workshop on Ionospheric Impacts on GNSS and International Collaboration to Meet Current and Future Solar Activity Period Challenges, 25 - 26 June 2025, Vienna International Centre, AustriaApril 2, 2025A/AC.105/1039/Add.20 - Questions on suborbital flights for scientific missions and/or for human transportation: Djibouti, Ecuador, Greece, Jamaica, Mexico, Myanmar, Senegal, Slovakia and TunisiaApril 1, 2025A/AC.105/1338 - Report of the Scientific and Technical Subcommittee on its sixty-second session, held in Vienna from 3 to 14 February 2025April 1, 2025A/AC.105/1352 - Report on the United Nations Conference on Space Law and  Policy  (Vienna, Austria, 19–21 November 2024)January 31, 2025ST/SPACE/89 - Leveraging Space Technology for Agricultural Development and Food Security: Joint Publication by the Food and Agriculture Organization of the United Nations (FAO) and the United Nations Office for Outer Space Affairs (UNOOSA)June 19, 2024ST/SPACE/90 - UNOOSA 2023 Annual ReportJune 19, 2024ST/SPACE/92 - Gender Mainstreaming Toolkit for the Space SectorFebruary 9, 2024ST/SPACE/88 - The “Space2030” Agenda: Space as a Driver of Sustainable DevelopmentDecember 4, 2023ST/SPACE/91: Registration of Objects Launched into Outer Space: Stakeholder StudyJuly 11, 2023ST/SPACE/85 - Contribution to the “Space2030” Agenda: EU Space - Supporting A World Of 8 Billion People April 7, 2025A/AC.105/C.2/L.342 - Summary by the Chair of the Working Group on the Status and Application of the Five United Nations Treaties on Outer Space of views on the implementation of article XI of  the Treaty on Principles Governing the Activities of States in  the Exploration and Use of Outer Space, including the Moon and Other Celestial BodiesApril 7, 2025A/AC.105/1226/Add.5 -  Information relating to any practical case known that would warrant the definition and delimitation of outer space: Djibouti, Ecuador, Jamaica, Myanmar and TunisiaApril 2, 2025A/AC.105/1039/Add.20 - Questions on suborbital flights for scientific missions and/or for human transportation: Djibouti, Ecuador, Greece, Jamaica, Mexico, Myanmar, Senegal, Slovakia and TunisiaApril 1, 2025A/AC.105/1338 - Report of the Scientific and Technical Subcommittee on its sixty-second session, held in Vienna from 3 to 14 February 2025April 1, 2025A/AC.105/1352 - Report on the United Nations Conference on Space Law and  Policy  (Vienna, Austria, 19–21 November 2024)April 1, 2025A/AC.105/865/Add.29 - National legislation and practice relating to definition and delimitation of outer space: Djibouti, Ecuador, Greece, Mexico, Slovakia and Tunisia\n\nApril 7, 2025A/AC.105/C.2/L.342 - Summary by the Chair of the Working Group on the Status and Application of the Five United Nations Treaties on Outer Space of views on the implementation of article XI of  the Treaty on Principles Governing the Activities of States in  the Exploration and Use of Outer Space, including the Moon and Other Celestial BodiesApril 7, 2025A/AC.105/1226/Add.5 -  Information relating to any practical case known that would warrant the definition and delimitation of outer space: Djibouti, Ecuador, Jamaica, Myanmar and TunisiaApril 2, 2025Workshop on Ionospheric Impacts on GNSS and International Collaboration to Meet Current and Future Solar Activity Period Challenges, 25 - 26 June 2025, Vienna International Centre, AustriaApril 2, 2025A/AC.105/1039/Add.20 - Questions on suborbital flights for scientific missions and/or for human transportation: Djibouti, Ecuador, Greece, Jamaica, Mexico, Myanmar, Senegal, Slovakia and TunisiaApril 1, 2025A/AC.105/1338 - Report of the Scientific and Technical Subcommittee on its sixty-second session, held in Vienna from 3 to 14 February 2025April 1, 2025A/AC.105/1352 - Report on the United Nations Conference on Space Law and  Policy  (Vienna, Austria, 19–21 November 2024)January 31, 2025ST/SPACE/89 - Leveraging Space Technology for Agricultural Development and Food Security: Joint Publication by the Food and Agriculture Organization of the United Nations (FAO) and the United Nations Office for Outer Space Affairs (UNOOSA)June 19, 2024ST/SPACE/90 - UNOOSA 2023 Annual ReportJune 19, 2024ST/SPACE/92 - Gender Mainstreaming Toolkit for the Space SectorFebruary 9, 2024ST/SPACE/88 - The “Space2030” Agenda: Space as a Driver of Sustainable DevelopmentDecember 4, 2023ST/SPACE/91: Registration of Objects Launched into Outer Space: Stakeholder StudyJuly 11, 2023ST/SPACE/85 - Contribution to the “Space2030” Agenda: EU Space - Supporting A World Of 8 Billion People April 7, 2025A/AC.105/C.2/L.342 - Summary by the Chair of the Working Group on the Status and Application of the Five United Nations Treaties on Outer Space of views on the implementation of article XI of  the Treaty on Principles Governing the Activities of States in  the Exploration and Use of Outer Space, including the Moon and Other Celestial BodiesApril 7, 2025A/AC.105/1226/Add.5 -  Information relating to any practical case known that would warrant the definition and delimitation of outer space: Djibouti, Ecuador, Jamaica, Myanmar and TunisiaApril 2, 2025A/AC.105/1039/Add.20 - Questions on suborbital flights for scientific missions and/or for human transportation: Djibouti, Ecuador, Greece, Jamaica, Mexico, Myanmar, Senegal, Slovakia and TunisiaApril 1, 2025A/AC.105/1338 - Report of the Scientific and Technical Subcommittee on its sixty-second session, held in Vienna from 3 to 14 February 2025April 1, 2025A/AC.105/1352 - Report on the United Nations Conference on Space Law and  Policy  (Vienna, Austria, 19–21 November 2024)April 1, 2025A/AC.105/865/Add.29 - National legislation and practice relating to definition and delimitation of outer space: Djibouti, Ecuador, Greece, Mexico, Slovakia and Tunisia\n\nApril 7, 2025A/AC.105/C.2/L.342 - Summary by the Chair of the Working Group on the Status and Application of the Five United Nations Treaties on Outer Space of views on the implementation of article XI of  the Treaty on Principles Governing the Activities of States in  the Exploration and Use of Outer Space, including the Moon and Other Celestial BodiesApril 7, 2025A/AC.105/1226/Add.5 -  Information relating to any practical case known that would warrant the definition and delimitation of outer space: Djibouti, Ecuador, Jamaica, Myanmar and TunisiaApril 2, 2025Workshop on Ionospheric Impacts on GNSS and International Collaboration to Meet Current and Future Solar Activity Period Challenges, 25 - 26 June 2025, Vienna International Centre, AustriaApril 2, 2025A/AC.105/1039/Add.20 - Questions on suborbital flights for scientific missions and/or for human transportation: Djibouti, Ecuador, Greece, Jamaica, Mexico, Myanmar, Senegal, Slovakia and TunisiaApril 1, 2025A/AC.105/1338 - Report of the Scientific and Technical Subcommittee on its sixty-second session, held in Vienna from 3 to 14 February 2025April 1, 2025A/AC.105/1352 - Report on the United Nations Conference on Space Law and  Policy  (Vienna, Austria, 19–21 November 2024)\n\nApril 7, 2025\n\nA/AC.105/C.2/L.342 - Summary by the Chair of the Working Group on the Status and Application of the Five United Nations Treaties on Outer Space of views on the implementation of article XI of  the Treaty on Principles Governing the Activities of States in  the Exploration and Use of Outer Space, including the Moon and Other Celestial Bodies\n\nApril 7, 2025\n\nA/AC.105/1226/Add.5 -  Information relating to any practical case known that would warrant the definition and delimitation of outer space: Djibouti, Ecuador, Jamaica, Myanmar and Tunisia\n\nApril 2, 2025\n\nWorkshop on Ionospheric Impacts on GNSS and International Collaboration to Meet Current and Future Solar Activity Period Challenges, 25 - 26 June 2025, Vienna International Centre, Austria\n\nApril 2, 2025\n\nA/AC.105/1039/Add.20 - Questions on suborbital flights for scientific missions and/or for human transportation: Djibouti, Ecuador, Greece, Jamaica, Mexico, Myanmar, Senegal, Slovakia and Tunisia\n\nApril 1, 2025\n\nA/AC.105/1338 - Report of the Scientific and Technical Subcommittee on its sixty-second session, held in Vienna from 3 to 14 February 2025\n\nApril 1, 2025\n\nA/AC.105/1352 - Report on the United Nations Conference on Space Law and  Policy  (Vienna, Austria, 19–21 November 2024)\n\nJanuary 31, 2025ST/SPACE/89 - Leveraging Space Technology for Agricultural Development and Food Security: Joint Publication by the Food and Agriculture Organization of the United Nations (FAO) and the United Nations Office for Outer Space Affairs (UNOOSA)June 19, 2024ST/SPACE/90 - UNOOSA 2023 Annual ReportJune 19, 2024ST/SPACE/92 - Gender Mainstreaming Toolkit for the Space SectorFebruary 9, 2024ST/SPACE/88 - The “Space2030” Agenda: Space as a Driver of Sustainable DevelopmentDecember 4, 2023ST/SPACE/91: Registration of Objects Launched into Outer Space: Stakeholder StudyJuly 11, 2023ST/SPACE/85 - Contribution to the “Space2030” Agenda: EU Space - Supporting A World Of 8 Billion People\n\nJanuary 31, 2025\n\nST/SPACE/89 - Leveraging Space Technology for Agricultural Development and Food Security: Joint Publication by the Food and Agriculture Organization of the United Nations (FAO) and the United Nations Office for Outer Space Affairs (UNOOSA)\n\nJune 19, 2024\n\nST/SPACE/90 - UNOOSA 2023 Annual Report\n\nJune 19, 2024\n\nST/SPACE/92 - Gender Mainstreaming Toolkit for the Space Sector\n\nFebruary 9, 2024\n\nST/SPACE/88 - The “Space2030” Agenda: Space as a Driver of Sustainable Development\n\nDecember 4, 2023\n\nST/SPACE/91: Registration of Objects Launched into Outer Space: Stakeholder Study\n\nJuly 11, 2023\n\nST/SPACE/85 - Contribution to the “Space2030” Agenda: EU Space - Supporting A World Of 8 Billion People\n\nApril 7, 2025A/AC.105/C.2/L.342 - Summary by the Chair of the Working Group on the Status and Application of the Five United Nations Treaties on Outer Space of views on the implementation of article XI of  the Treaty on Principles Governing the Activities of States in  the Exploration and Use of Outer Space, including the Moon and Other Celestial BodiesApril 7, 2025A/AC.105/1226/Add.5 -  Information relating to any practical case known that would warrant the definition and delimitation of outer space: Djibouti, Ecuador, Jamaica, Myanmar and TunisiaApril 2, 2025A/AC.105/1039/Add.20 - Questions on suborbital flights for scientific missions and/or for human transportation: Djibouti, Ecuador, Greece, Jamaica, Mexico, Myanmar, Senegal, Slovakia and TunisiaApril 1, 2025A/AC.105/1338 - Report of the Scientific and Technical Subcommittee on its sixty-second session, held in Vienna from 3 to 14 February 2025April 1, 2025A/AC.105/1352 - Report on the United Nations Conference on Space Law and  Policy  (Vienna, Austria, 19–21 November 2024)April 1, 2025A/AC.105/865/Add.29 - National legislation and practice relating to definition and delimitation of outer space: Djibouti, Ecuador, Greece, Mexico, Slovakia and Tunisia\n\nApril 7, 2025\n\nA/AC.105/C.2/L.342 - Summary by the Chair of the Working Group on the Status and Application of the Five United Nations Treaties on Outer Space of views on the implementation of article XI of  the Treaty on Principles Governing the Activities of States in  the Exploration and Use of Outer Space, including the Moon and Other Celestial Bodies\n\nApril 7, 2025\n\nA/AC.105/1226/Add.5 -  Information relating to any practical case known that would warrant the definition and delimitation of outer space: Djibouti, Ecuador, Jamaica, Myanmar and Tunisia\n\nApril 2, 2025\n\nA/AC.105/1039/Add.20 - Questions on suborbital flights for scientific missions and/or for human transportation: Djibouti, Ecuador, Greece, Jamaica, Mexico, Myanmar, Senegal, Slovakia and Tunisia\n\nApril 1, 2025\n\nA/AC.105/1338 - Report of the Scientific and Technical Subcommittee on its sixty-second session, held in Vienna from 3 to 14 February 2025\n\nApril 1, 2025\n\nA/AC.105/1352 - Report on the United Nations Conference on Space Law and  Policy  (Vienna, Austria, 19–21 November 2024)\n\nApril 1, 2025\n\nA/AC.105/865/Add.29 - National legislation and practice relating to definition and delimitation of outer space: Djibouti, Ecuador, Greece, Mexico, Slovakia and Tunisia\n\nCalendar\n\n@UNOOSA\n\nLatestApril 7, 2025NewsA/AC.105/C.2/L.342 - Summary by the Chair of the Working Group on the Status and Application of the Five United Nations Treaties on Outer Space of views on the implementation of article XI of  the Treaty on Principles Governing the Activities of States in  the Exploration and Use of Outer Space, including the Moon and Other Celestial BodiesJanuary 31, 2025PublicationsST/SPACE/89 - Leveraging Space Technology for Agricultural Development and Food Security: Joint Publication by the Food and Agriculture Organization of the United Nations (FAO) and the United Nations Office for Outer Space Affairs (UNOOSA)April 7, 2025ReportsA/AC.105/C.2/L.342 - Summary by the Chair of the Working Group on the Status and Application of the Five United Nations Treaties on Outer Space of views on the implementation of article XI of  the Treaty on Principles Governing the Activities of States in  the Exploration and Use of Outer Space, including the Moon and Other Celestial BodiesLinks\n\nVIC Online\n\n\nUNIS Vienna\n\n\nUN-SPIDER\n\n\nUnited Nations\n  \n\n\nTerms of Use\n\nContact us\nUnited Nations Office for Outer Space Affairs\nUnited Nations Office at Vienna\n Vienna International Centre\n Wagramerstrasse 5\n A-1220 Vienna\n AUSTRIA\nTel.: +43-1 26060-84950\nFax: +43-1-26060-5830\n\nSend us a message!\n\nLatestApril 7, 2025NewsA/AC.105/C.2/L.342 - Summary by the Chair of the Working Group on the Status and Application of the Five United Nations Treaties on Outer Space of views on the implementation of article XI of  the Treaty on Principles Governing the Activities of States in  the Exploration and Use of Outer Space, including the Moon and Other Celestial BodiesJanuary 31, 2025PublicationsST/SPACE/89 - Leveraging Space Technology for Agricultural Development and Food Security: Joint Publication by the Food and Agriculture Organization of the United Nations (FAO) and the United Nations Office for Outer Space Affairs (UNOOSA)April 7, 2025ReportsA/AC.105/C.2/L.342 - Summary by the Chair of the Working Group on the Status and Application of the Five United Nations Treaties on Outer Space of views on the implementation of article XI of  the Treaty on Principles Governing the Activities of States in  the Exploration and Use of Outer Space, including the Moon and Other Celestial BodiesLinks\n\nVIC Online\n\n\nUNIS Vienna\n\n\nUN-SPIDER\n\n\nUnited Nations\n  \n\n\nTerms of Use\n\nContact us\nUnited Nations Office for Outer Space Affairs\nUnited Nations Office at Vienna\n Vienna International Centre\n Wagramerstrasse 5\n A-1220 Vienna\n AUSTRIA\nTel.: +43-1 26060-84950\nFax: +43-1-26060-5830\n\nSend us a message!\n\nLatestApril 7, 2025NewsA/AC.105/C.2/L.342 - Summary by the Chair of the Working Group on the Status and Application of the Five United Nations Treaties on Outer Space of views on the implementation of article XI of  the Treaty on Principles Governing the Activities of States in  the Exploration and Use of Outer Space, including the Moon and Other Celestial BodiesJanuary 31, 2025PublicationsST/SPACE/89 - Leveraging Space Technology for Agricultural Development and Food Security: Joint Publication by the Food and Agriculture Organization of the United Nations (FAO) and the United Nations Office for Outer Space Affairs (UNOOSA)April 7, 2025ReportsA/AC.105/C.2/L.342 - Summary by the Chair of the Working Group on the Status and Application of the Five United Nations Treaties on Outer Space of views on the implementation of article XI of  the Treaty on Principles Governing the Activities of States in  the Exploration and Use of Outer Space, including the Moon and Other Celestial Bodies\n\nApril 7, 2025\n\nNewsA/AC.105/C.2/L.342 - Summary by the Chair of the Working Group on the Status and Application of the Five United Nations Treaties on Outer Space of views on the implementation of article XI of  the Treaty on Principles Governing the Activities of States in  the Exploration and Use of Outer Space, including the Moon and Other Celestial Bodies\n\nJanuary 31, 2025\n\nPublicationsST/SPACE/89 - Leveraging Space Technology for Agricultural Development and Food Security: Joint Publication by the Food and Agriculture Organization of the United Nations (FAO) and the United Nations Office for Outer Space Affairs (UNOOSA)\n\nApril 7, 2025\n\nReportsA/AC.105/C.2/L.342 - Summary by the Chair of the Working Group on the Status and Application of the Five United Nations Treaties on Outer Space of views on the implementation of article XI of  the Treaty on Principles Governing the Activities of States in  the Exploration and Use of Outer Space, including the Moon and Other Celestial Bodies\n\nLinks\n\nVIC Online\n\n\nUNIS Vienna\n\n\nUN-SPIDER\n\n\nUnited Nations\n  \n\n\nTerms of Use\n\nVIC Online\n\nUNIS Vienna\n\nUN-SPIDER\n\nUnited Nations\n\nTerms of Use\n\nContact us\nUnited Nations Office for Outer Space Affairs\nUnited Nations Office at Vienna\n Vienna International Centre\n Wagramerstrasse 5\n A-1220 Vienna\n AUSTRIA\nTel.: +43-1 26060-84950\nFax: +43-1-26060-5830\n\nSend us a message!\n\nUnited Nations Office at Vienna\n Vienna International Centre\n Wagramerstrasse 5\n A-1220 Vienna\n AUSTRIA\n\nTel.: +43-1 26060-84950\nFax: +43-1-26060-5830\n\nSend us a message!\n\nCopyright ©2025 UNOOSA,\n            All Rights Reserved\n\nCopyright ©2025 UNOOSA,\n            All Rights Reserved\n\nCopyright ©2025 UNOOSA,\n            All Rights Reserved\n\nCopyright ©2025 UNOOSA,\n            All Rights Reserved",
  "date": "",
  "source_type": "other",
  "extracted_at": "2025-04-07T13:54:15.835726",
  "metadata": {
    "author": "agt",
    "description": "United Nations Office for Outer Space Affairs",
    "keywords": "United Nations Office Outer Space Affairs UN"
  },
  "relevance_score": 0.5571428571428572,
  "summary": "United NationsOffice for Outer Space Affairs\n\nUnited NationsOffice for Outer Space Affairs\n\nUnited NationsOffice for Outer Space Affairs\n\nUnited NationsOffice for Outer Space Affairs\n\nAbout UsRoles and ResponsibilitiesAnnual ReportsDirectorStructurePartnershipsUNOOSA Space Camp 2024HistoryTreatiesUNISPACE ConferencesTimeline: UN and SpaceEmploymentContact UsOur WorkSecretariat of COPUOS Committee and its SubcommitteesCOPUOS 2023 Session STSC 2024 SessionLSC 2024 SessionPast sessionsWorking Groups Action Team on Lunar Activities Consultation (ATLAC)General Assembly Joint PanelHistoryMember States and Observer OrganizationsMembership Evolution Observer OrganizationsMeetings ScheduleDocumentsVIC OnlineTechnical PresentationsDigital RecordingsProgramme on Space Applications PSA NewsSchedule of Activities202520242023202220212020201920182017201620152014201320122011201020092008FellowshipsDropTESPNSTBasic Space Science Initiative (BSSI)BSS Workshops (1991-2004)International Heliophysical Year 2007International Space Weather Initiative (ISWI)Basic Space Technology Initiative (BSTI)Events and ActivitiesFellowship ProgrammeResourcesEducationProjectsHuman Space Technology Initiative (HSTI)EventsGround-based ExperimentsZGIPDropTESHyperGESOrbital OpportunitiesKiboCUBEOrbital MissionChina Space StationBartolomeoCubeSats with Vega-CAreas of workBiodiversity/EcosystemsClimate ChangeDisaster ManagementEnvironmental Monitoring and Natural Resource ManagementGlobal HealthGlobal Navigation Satellite SystemsCurrent WorkshopPast WorkshopsSatellite CommunicationsRegional Centres for Space Science and Technology EducationAfrica, Nigeria (ARCSSTE-E)Africa, Morocco (CRASTE-LF)Latin America & Caribbean, Mexico & Brazil (CRECTEALC)Asia/Pacific, India (CSSTEAP)West Asia, Jordan (RCSSTEWA)Asia/Pacific, China (RCSSTEAP)Education CurriculaPublicationsReportsUN-SPIDERKnowledge ManagementTechnical Advisory SupportNetworkNews and EventsContact UsInternational Committee on GNSSOverviewMembersICG Terms of ReferenceProviders' ForumGNSS ProvidersMeetingsWorking GroupsWorking Group SIDMPerformance StandardsWorking Group BWorking Group CWorking Group DTemplatesRecommendationsICG Annual MeetingsCurrent MeetingPast MeetingsICG Programme on GNSS Applications WorkshopsSpace WeatherResourcesReference SystemsEducation MaterialsICG DocumentsA/AC.105/ seriesTerms of ReferenceWorking Group ReportsPublicationsVideosPerformance StandardsICG Reports ExtractsICG WG RecommendationsICG TimelineUN-SpaceInter-Agency MeetingCurrent/Upcoming SessionOpen Informal SessionsList of Participating OrganizationsSecretary-General's and meeting reportsSpecial Reports & PublicationsContactsSpace LawTreaties & PrinciplesTreaty StatusTravaux PréparatoiresSpace Law ResolutionsNational Space LawBilateral & Multilateral Agreements Non-legally Binding UN Instruments on Outer SpaceTreaty ImplementationSpace Object RegisterPublicationsCapacity BuildingUN Conference on Space Law and PolicyFirst UN Conference on Space Law & PolicyUN/Turkey/APSCO ConferenceUN Conference - African PerspectivesUN/Chile Conference on Space Law and PolicyUN Conference on Space Law and Policy: The Outer Space Treaty for the 21st Century2024 UN Conference on Space Law and PolicySpace Law WorkshopsSpace Law CurriculumRegistration Project: Supporting Space Object RegistrationMoon, Mars and Beyond Sustainable Lunar Activities Conference 2024Benefits of SpaceAgricultureGlobal HealthEnvironmentSustainable DevelopmentDisastersEducationHuman SettlementsResearch & DevelomentTransportationCommunicationHumanitarian Assistance  International Peace & Security Access to Space for AllFor Member StatesPartnershipsOpportunitiesHypergravity/Microgravity TrackSatellite Development TrackSpace Exploration TrackAwardeesAcknowledgementSpace Law for New Space ActorsSpace for Persons with Disabilities Space4YouthSpace4Youth Competition 2025 Competition2024 Competition2022 Competition2021 Competition2020 Competition2019 CompetitionSpace4Youth StoriesSubmitting Stories Space4WaterSpace4WomenWorld Space ForumCurrent Event - WSF 2024Past EventsWorldwide Space AgenciesCapacity Building ActivitiesCapacity Building ProjectsSpace Treaty ImplementationLong-term Sustainability of Outer Space ActivitiesDisaster ManagementNear Earth ObjectsSMPAGIAWNPlanetary Defence ConferencesInternational Asteroid DayDocumentsSpace and Climate ChangeNuclear Power SourcesGNSSRemote Sensing Space DebrisSpace Debris CompendiumSpace WeatherSpace Solutions for the PacificSpace Exploration and Innovation Space EconomySpace and Global HealthPromoting Space SustainabilitySpace4SDGsSDG 1: No PovertySDG 2: Zero HungerSDG 3: Good Health & Well-beingSDG 4: Quality EducationSDG 5: Gender EqualitySDG 6: Clean Water & SanitationSDG 7: Affordable & Clean EnergySDG 8: Decent Work & Economic GrowthSDG 9: Industry, Innovation & InfrastructureSDG 10: Reduced InequalitiesSDG 11: Sustainable Cities & CommunitiesSDG 12: Responsible Consumption & ProductionSDG 13: Climate ActionSDG 14: Life Below WaterSDG 15: Life on Land SDG 16: Peace, Justice & Strong InstitutionsSDG 17: Partnerships for the GoalsInformation for...For Member States & OrganizationsAccessMeeting logistics UNOOSA Space Camp 2024For StudentsOnline LearningFor MediaMedia ArchivePhoto Gallery For Industry & the Private SectorEventsSearch Events202520242023202220212020201920182017201620152014201320122011201020092008CalendarMapFeatured EventsWorld Space ForumInternational Day of Human Space FlightMessages from Space Explorers to Future Generations International Asteroid DayWorld Space WeekInternational Moon DayUNOOSA Space Camp 2024Space Object Register Registration ConventionRegistration SubmissionsBy States and Organizations By Year of IssueNational Registry NotificationsNational Focal PointsNational Space Object RegistriesOnline Index of Objects Launched into Outer SpaceSearch indexTreaty ImplementationResources on Space Object RegistrationDocumentsGeneral Assembly ResolutionsCOPUOS ReportsUN-Space PSA Activity ReportsUN-SPIDERICG ReportsPublicationsOther DocumentsCOPUOS 2025COPUOS 2025 Session STSC 2025 SessionLSC 2025 SessionWorking GroupsPast SessionsSpace2030Digital RecordingsReport ArchiveTechnical Presentations\n\nAbout UsRoles and ResponsibilitiesAnnual ReportsDirectorStructurePartnershipsUNOOSA Space Camp 2024HistoryTreatiesUNISPACE ConferencesTimeline: UN and SpaceEmploymentContact UsOur WorkSecretariat of COPUOS Committee and its SubcommitteesCOPUOS 2023 Session STSC 2024 SessionLSC 2024 SessionPast sessionsWorking Groups Action Team on Lunar Activities Consultation (ATLAC)General Assembly Joint PanelHistoryMember States and Observer OrganizationsMembership Evolution Observer OrganizationsMeetings ScheduleDocumentsVIC OnlineTechnical PresentationsDigital RecordingsProgramme on Space Applications PSA NewsSchedule of Activities202520242023202220212020201920182017201620152014201320122011201020092008FellowshipsDropTESPNSTBasic Space Science Initiative (BSSI)BSS Workshops (1991-2004)International Heliophysical Year 2007International Space Weather Initiative (ISWI)Basic Space Technology Initiative (BSTI)Events and ActivitiesFellowship ProgrammeResourcesEducationProjectsHuman Space Technology Initiative (HSTI)EventsGround-based ExperimentsZGIPDropTESHyperGESOrbital OpportunitiesKiboCUBEOrbital MissionChina Space StationBartolomeoCubeSats with Vega-CAreas of workBiodiversity/EcosystemsClimate ChangeDisaster ManagementEnvironmental Monitoring and Natural Resource ManagementGlobal HealthGlobal Navigation Satellite SystemsCurrent WorkshopPast WorkshopsSatellite CommunicationsRegional Centres for Space Science and Technology EducationAfrica, Nigeria (ARCSSTE-E)Africa, Morocco (CRASTE-LF)Latin America & Caribbean, Mexico & Brazil (CRECTEALC)Asia/Pacific, India (CSSTEAP)West Asia, Jordan (RCSSTEWA)Asia/Pacific, China (RCSSTEAP)Education CurriculaPublicationsReportsUN-SPIDERKnowledge ManagementTechnical Advisory SupportNetworkNews and EventsContact UsInternational Committee on GNSSOverviewMembersICG Terms of ReferenceProviders' ForumGNSS ProvidersMeetingsWorking GroupsWorking Group SIDMPerformance StandardsWorking Group BWorking Group CWorking Group DTemplatesRecommendationsICG Annual MeetingsCurrent MeetingPast MeetingsICG Programme on GNSS Applications WorkshopsSpace WeatherResourcesReference SystemsEducation MaterialsICG DocumentsA/AC.105/ seriesTerms of ReferenceWorking Group ReportsPublicationsVideosPerformance StandardsICG Reports ExtractsICG WG RecommendationsICG TimelineUN-SpaceInter-Agency MeetingCurrent/Upcoming SessionOpen Informal SessionsList of Participating OrganizationsSecretary-General's and meeting reportsSpecial Reports & PublicationsContactsSpace LawTreaties & PrinciplesTreaty StatusTravaux PréparatoiresSpace Law ResolutionsNational Space LawBilateral & Multilateral Agreements Non-legally Binding UN Instruments on Outer SpaceTreaty ImplementationSpace Object RegisterPublicationsCapacity BuildingUN Conference on Space Law and PolicyFirst UN Conference on Space Law & PolicyUN/Turkey/APSCO ConferenceUN Conference - African PerspectivesUN/Chile Conference on Space Law and PolicyUN Conference on Space Law and Policy: The Outer Space Treaty for the 21st Century2024 UN Conference on Space Law and PolicySpace Law WorkshopsSpace Law CurriculumRegistration Project: Supporting Space Object RegistrationMoon, Mars and Beyond Sustainable Lunar Activities Conference 2024Benefits of SpaceAgricultureGlobal HealthEnvironmentSustainable DevelopmentDisastersEducationHuman SettlementsResearch & DevelomentTransportationCommunicationHumanitarian Assistance  International Peace & Security Access to Space for AllFor Member StatesPartnershipsOpportunitiesHypergravity/Microgravity TrackSatellite Development TrackSpace Exploration TrackAwardeesAcknowledgementSpace Law for New Space ActorsSpace for Persons with Disabilities Space4YouthSpace4Youth Competition 2025 Competition2024 Competition2022 Competition2021 Competition2020 Competition2019 CompetitionSpace4Youth StoriesSubmitting Stories Space4WaterSpace4WomenWorld Space ForumCurrent Event - WSF 2024Past EventsWorldwide Space AgenciesCapacity Building ActivitiesCapacity Building ProjectsSpace Treaty ImplementationLong-term Sustainability of Outer Space ActivitiesDisaster ManagementNear Earth ObjectsSMPAGIAWNPlanetary Defence ConferencesInternational Asteroid DayDocumentsSpace and Climate ChangeNuclear Power SourcesGNSSRemote Sensing Space DebrisSpace Debris CompendiumSpace WeatherSpace Solutions for the PacificSpace Exploration and Innovation Space EconomySpace and Global HealthPromoting Space SustainabilitySpace4SDGsSDG 1: No PovertySDG 2: Zero HungerSDG 3: Good Health & Well-beingSDG 4: Quality EducationSDG 5: Gender EqualitySDG 6: Clean Water & SanitationSDG 7: Affordable & Clean EnergySDG 8: Decent Work & Economic GrowthSDG 9: Industry, Innovation & InfrastructureSDG 10: Reduced InequalitiesSDG 11: Sustainable Cities & CommunitiesSDG 12: Responsible Consumption & ProductionSDG 13: Climate ActionSDG 14: Life Below WaterSDG 15: Life on Land SDG 16: Peace, Justice & Strong InstitutionsSDG 17: Partnerships for the GoalsInformation for...For Member States & OrganizationsAccessMeeting logistics UNOOSA Space Camp 2024For StudentsOnline LearningFor MediaMedia ArchivePhoto Gallery For Industry & the Private SectorEventsSearch Events202520242023202220212020201920182017201620152014201320122011201020092008CalendarMapFeatured EventsWorld Space ForumInternational Day of Human Space FlightMessages from Space Explorers to Future Generations International Asteroid DayWorld Space WeekInternational Moon DayUNOOSA Space Camp 2024Space Object Register Registration ConventionRegistration SubmissionsBy States and Organizations By Year of IssueNational Registry NotificationsNational Focal PointsNational Space Object RegistriesOnline Index of Objects Launched into Outer SpaceSearch indexTreaty ImplementationResources on Space Object RegistrationDocumentsGeneral Assembly ResolutionsCOPUOS ReportsUN-Space PSA Activity ReportsUN-SPIDERICG ReportsPublicationsOther DocumentsCOPUOS 2025COPUOS 2025 Session STSC 2025 SessionLSC 2025 SessionWorking GroupsPast SessionsSpace2030Digital RecordingsReport ArchiveTechnical Presentations\n\nAbout UsRoles and ResponsibilitiesAnnual ReportsDirectorStructurePartnershipsUNOOSA Space Camp 2024HistoryTreatiesUNISPACE ConferencesTimeline: UN and SpaceEmploymentContact UsOur WorkSecretariat of COPUOS Committee and its SubcommitteesCOPUOS 2023 Session STSC 2024 SessionLSC 2024 SessionPast sessionsWorking Groups Action Team on Lunar Activities Consultation (ATLAC)General Assembly Joint PanelHistoryMember States and Observer OrganizationsMembership Evolution Observer OrganizationsMeetings ScheduleDocumentsVIC OnlineTechnical PresentationsDigital RecordingsProgramme on Space Applications PSA NewsSchedule of Activities202520242023202220212020201920182017201620152014201320122011201020092008FellowshipsDropTESPNSTBasic Space Science Initiative (BSSI)BSS Workshops (1991-2004)International Heliophysical Year 2007International Space Weather Initiative (ISWI)Basic Space Technology Initiative (BSTI)Events and ActivitiesFellowship ProgrammeResourcesEducationProjectsHuman Space Technology Initiative (HSTI)EventsGround-based ExperimentsZGIPDropTESHyperGESOrbital OpportunitiesKiboCUBEOrbital MissionChina Space StationBartolomeoCubeSats with Vega-CAreas of workBiodiversity/EcosystemsClimate ChangeDisaster ManagementEnvironmental Monitoring and Natural Resource ManagementGlobal HealthGlobal Navigation Satellite SystemsCurrent WorkshopPast WorkshopsSatellite CommunicationsRegional Centres for Space Science and Technology EducationAfrica, Nigeria (ARCSSTE-E)Africa, Morocco (CRASTE-LF)Latin America & Caribbean, Mexico & Brazil (CRECTEALC)Asia/Pacific, India (CSSTEAP)West Asia, Jordan (RCSSTEWA)Asia/Pacific, China (RCSSTEAP)Education CurriculaPublicationsReportsUN-SPIDERKnowledge ManagementTechnical Advisory SupportNetworkNews and EventsContact UsInternational Committee on GNSSOverviewMembersICG Terms of ReferenceProviders' ForumGNSS ProvidersMeetingsWorking GroupsWorking Group SIDMPerformance StandardsWorking Group BWorking Group CWorking Group DTemplatesRecommendationsICG Annual MeetingsCurrent MeetingPast MeetingsICG Programme on GNSS Applications WorkshopsSpace WeatherResourcesReference SystemsEducation MaterialsICG DocumentsA/AC.105/ seriesTerms of ReferenceWorking Group ReportsPublicationsVideosPerformance StandardsICG Reports ExtractsICG WG RecommendationsICG TimelineUN-SpaceInter-Agency MeetingCurrent/Upcoming SessionOpen Informal SessionsList of Participating OrganizationsSecretary-General's and meeting reportsSpecial Reports & PublicationsContactsSpace LawTreaties & PrinciplesTreaty StatusTravaux PréparatoiresSpace Law ResolutionsNational Space LawBilateral & Multilateral Agreements Non-legally Binding UN Instruments on Outer SpaceTreaty ImplementationSpace Object RegisterPublicationsCapacity BuildingUN Conference on Space Law and PolicyFirst UN Conference on Space Law & PolicyUN/Turkey/APSCO ConferenceUN Conference - African PerspectivesUN/Chile Conference on Space Law and PolicyUN Conference on Space Law and Policy: The Outer Space Treaty for the 21st Century2024 UN Conference on Space Law and PolicySpace Law WorkshopsSpace Law CurriculumRegistration Project: Supporting Space Object RegistrationMoon, Mars and Beyond Sustainable Lunar Activities Conference 2024Benefits of SpaceAgricultureGlobal HealthEnvironmentSustainable DevelopmentDisastersEducationHuman SettlementsResearch & DevelomentTransportationCommunicationHumanitarian Assistance  International Peace & Security Access to Space for AllFor Member StatesPartnershipsOpportunitiesHypergravity/Microgravity TrackSatellite Development TrackSpace Exploration TrackAwardeesAcknowledgementSpace Law for New Space ActorsSpace for Persons with Disabilities Space4YouthSpace4Youth Competition 2025 Competition2024 Competition2022 Competition2021 Competition2020 Competition2019 CompetitionSpace4Youth StoriesSubmitting Stories Space4WaterSpace4WomenWorld Space ForumCurrent Event - WSF 2024Past EventsWorldwide Space AgenciesCapacity Building ActivitiesCapacity Building ProjectsSpace Treaty ImplementationLong-term Sustainability of Outer Space ActivitiesDisaster ManagementNear Earth ObjectsSMPAGIAWNPlanetary Defence ConferencesInternational Asteroid DayDocumentsSpace and Climate ChangeNuclear Power SourcesGNSSRemote Sensing Space DebrisSpace Debris CompendiumSpace WeatherSpace Solutions for the PacificSpace Exploration and Innovation Space EconomySpace and Global HealthPromoting Space SustainabilitySpace4SDGsSDG 1: No PovertySDG 2: Zero HungerSDG 3: Good Health & Well-beingSDG 4: Quality EducationSDG 5: Gender EqualitySDG 6: Clean Water & SanitationSDG 7: Affordable & Clean EnergySDG 8: Decent Work & Economic GrowthSDG 9: Industry, Innovation & InfrastructureSDG 10: Reduced InequalitiesSDG 11: Sustainable Cities & CommunitiesSDG 12: Responsible Consumption & ProductionSDG 13: Climate ActionSDG 14: Life Below WaterSDG 15: Life on Land SDG 16: Peace, Justice & Strong InstitutionsSDG 17: Partnerships for the GoalsInformation for...For Member States & OrganizationsAccessMeeting logistics UNOOSA Space Camp 2024For StudentsOnline LearningFor MediaMedia ArchivePhoto Gallery For Industry & the Private SectorEventsSearch Events202520242023202220212020201920182017201620152014201320122011201020092008CalendarMapFeatured EventsWorld Space ForumInternational Day of Human Space FlightMessages from Space Explorers to Future Generations International Asteroid DayWorld Space WeekInternational Moon DayUNOOSA Space Camp 2024Space Object Register Registration ConventionRegistration SubmissionsBy States and Organizations By Year of IssueNational Registry NotificationsNational Focal PointsNational Space Object RegistriesOnline Index of Objects Launched into Outer SpaceSearch indexTreaty ImplementationResources on Space Object RegistrationDocumentsGeneral Assembly ResolutionsCOPUOS ReportsUN-Space PSA Activity ReportsUN-SPIDERICG ReportsPublicationsOther DocumentsCOPUOS 2025COPUOS 2025 Session STSC 2025 SessionLSC 2025 SessionWorking GroupsPast SessionsSpace2030Digital RecordingsReport ArchiveTechnical Presentations\n\nAbout UsRoles and ResponsibilitiesAnnual ReportsDirectorStructurePartnershipsUNOOSA Space Camp 2024HistoryTreatiesUNISPACE ConferencesTimeline: UN and SpaceEmploymentContact UsOur WorkSecretariat of COPUOS Committee and its SubcommitteesCOPUOS 2023 Session STSC 2024 SessionLSC 2024 SessionPast sessionsWorking Groups Action Team on Lunar Activities Consultation (ATLAC)General Assembly Joint PanelHistoryMember States and Observer OrganizationsMembership Evolution Observer OrganizationsMeetings ScheduleDocumentsVIC OnlineTechnical PresentationsDigital RecordingsProgramme on Space Applications PSA NewsSchedule of Activities202520242023202220212020201920182017201620152014201320122011201020092008FellowshipsDropTESPNSTBasic Space Science Initiative (BSSI)BSS Workshops (1991-2004)International Heliophysical Year 2007International Space Weather Initiative (ISWI)Basic Space Technology Initiative (BSTI)Events and ActivitiesFellowship ProgrammeResourcesEducationProjectsHuman Space Technology Initiative (HSTI)EventsGround-based ExperimentsZGIPDropTESHyperGESOrbital OpportunitiesKiboCUBEOrbital MissionChina Space StationBartolomeoCubeSats with Vega-CAreas of workBiodiversity/EcosystemsClimate ChangeDisaster ManagementEnvironmental Monitoring and Natural Resource ManagementGlobal HealthGlobal Navigation Satellite SystemsCurrent WorkshopPast WorkshopsSatellite CommunicationsRegional Centres for Space Science and Technology EducationAfrica, Nigeria (ARCSSTE-E)Africa, Morocco (CRASTE-LF)Latin America & Caribbean, Mexico & Brazil (CRECTEALC)Asia/Pacific, India (CSSTEAP)West Asia, Jordan (RCSSTEWA)Asia/Pacific, China (RCSSTEAP)Education CurriculaPublicationsReportsUN-SPIDERKnowledge ManagementTechnical Advisory SupportNetworkNews and EventsContact UsInternational Committee on GNSSOverviewMembersICG Terms of ReferenceProviders' ForumGNSS ProvidersMeetingsWorking GroupsWorking Group SIDMPerformance StandardsWorking Group BWorking Group CWorking Group DTemplatesRecommendationsICG Annual MeetingsCurrent MeetingPast MeetingsICG Programme on GNSS Applications WorkshopsSpace WeatherResourcesReference SystemsEducation MaterialsICG DocumentsA/AC.105/ seriesTerms of ReferenceWorking Group ReportsPublicationsVideosPerformance StandardsICG Reports ExtractsICG WG RecommendationsICG TimelineUN-SpaceInter-Agency MeetingCurrent/Upcoming SessionOpen Informal SessionsList of Participating OrganizationsSecretary-General's and meeting reportsSpecial Reports & PublicationsContactsSpace LawTreaties & PrinciplesTreaty StatusTravaux PréparatoiresSpace Law ResolutionsNational Space LawBilateral & Multilateral Agreements Non-legally Binding UN Instruments on Outer SpaceTreaty ImplementationSpace Object RegisterPublicationsCapacity BuildingUN Conference on Space Law and PolicyFirst UN Conference on Space Law & PolicyUN/Turkey/APSCO ConferenceUN Conference - African PerspectivesUN/Chile Conference on Space Law and PolicyUN Conference on Space Law and Policy: The Outer Space Treaty for the 21st Century2024 UN Conference on Space Law and PolicySpace Law WorkshopsSpace Law CurriculumRegistration Project: Supporting Space Object RegistrationMoon, Mars and Beyond Sustainable Lunar Activities Conference 2024Benefits of SpaceAgricultureGlobal HealthEnvironmentSustainable DevelopmentDisastersEducationHuman SettlementsResearch & DevelomentTransportationCommunicationHumanitarian Assistance  International Peace & Security Access to Space for AllFor Member StatesPartnershipsOpportunitiesHypergravity/Microgravity TrackSatellite Development TrackSpace Exploration TrackAwardeesAcknowledgementSpace Law for New Space ActorsSpace for Persons with Disabilities Space4YouthSpace4Youth Competition 2025 Competition2024 Competition2022 Competition2021 Competition2020 Competition2019 CompetitionSpace4Youth StoriesSubmitting Stories Space4WaterSpace4WomenWorld Space ForumCurrent Event - WSF 2024Past EventsWorldwide Space AgenciesCapacity Building ActivitiesCapacity Building ProjectsSpace Treaty ImplementationLong-term Sustainability of Outer Space ActivitiesDisaster ManagementNear Earth ObjectsSMPAGIAWNPlanetary Defence ConferencesInternational Asteroid DayDocumentsSpace and Climate ChangeNuclear Power SourcesGNSSRemote Sensing Space DebrisSpace Debris CompendiumSpace WeatherSpace Solutions for the PacificSpace Exploration and Innovation Space EconomySpace and Global HealthPromoting Space SustainabilitySpace4SDGsSDG 1: No PovertySDG 2: Zero HungerSDG 3: Good Health & Well-beingSDG 4: Quality EducationSDG 5: Gender EqualitySDG 6: Clean Water & SanitationSDG 7: Affordable & Clean EnergySDG 8: Decent Work & Economic GrowthSDG 9: Industry, Innovation & InfrastructureSDG 10: Reduced InequalitiesSDG 11: Sustainable Cities & CommunitiesSDG 12: Responsible Consumption & ProductionSDG 13: Climate ActionSDG 14: Life Below WaterSDG 15: Life on Land SDG 16: Peace, Justice & Strong InstitutionsSDG 17: Partnerships for the GoalsInformation for...For Member States & OrganizationsAccessMeeting logistics UNOOSA Space Camp 2024For StudentsOnline LearningFor MediaMedia ArchivePhoto Gallery For Industry & the Private SectorEventsSearch Events202520242023202220212020201920182017201620152014201320122011201020092008CalendarMapFeatured EventsWorld Space ForumInternational Day of Human Space FlightMessages from Space Explorers to Future Generations International Asteroid DayWorld Space WeekInternational Moon DayUNOOSA Space Camp 2024Space Object Register Registration ConventionRegistration SubmissionsBy States and Organizations By Year of IssueNational Registry NotificationsNational Focal PointsNational Space Object RegistriesOnline Index of Objects Launched into Outer SpaceSearch indexTreaty ImplementationResources on Space Object RegistrationDocumentsGeneral Assembly ResolutionsCOPUOS ReportsUN-Space PSA Activity ReportsUN-SPIDERICG ReportsPublicationsOther DocumentsCOPUOS 2025COPUOS 2025 Session STSC 2025 SessionLSC 2025 SessionWorking GroupsPast SessionsSpace2030Digital RecordingsReport ArchiveTechnical Presentations\n\nSixth Space4Youth Essay Competition\nWinners Announced! Read more  \nLeveraging Space Technology for Agricultural Development and Food Security\nJoint Publication by the Food and Agriculture Organization of the United Nations (FAO) and the United Nations Office for Outer Space Affairs (UNOOSA)\n\nDownload here\n\n\nGraduate Programs in Space Technology Applications: MASTA and DOCSTA\n\nThe RCSSTEAP, affiliated with the United Nations, is pleased to offer 8 postgraduate programs on Space Technology Applications for the 2025 academic year. Read more\n\nSpace Law for New Space Actors: Fostering Responsible National Space Activities\nUNOOSA's Legal Advisory Project \"Space Law for New Space Actors\" offers Member States tailored capacity building to facilitate drafting of national space legislation in line with international space law. Read more\n\nWhat's newNewsPublicationsReportsApril 7, 2025A/AC.105/C.2/L.342 - Summary by the Chair of the Working Group on the Status and Application of the Five United Nations Treaties on Outer Space of views on the implementation of article XI of  the Treaty on Principles Governing the Activities of States in  the Exploration and Use of Outer Space, including the Moon and Other Celestial BodiesApril 7, 2025A/AC.105/1226/Add.5 -  Information relating to any practical case known that would warrant the definition and delimitation of outer space: Djibouti, Ecuador, Jamaica, Myanmar and TunisiaApril 2, 2025Workshop on Ionospheric Impacts on GNSS and International Collaboration to Meet Current and Future Solar Activity Period Challenges, 25 - 26 June 2025, Vienna International Centre, AustriaApril 2, 2025A/AC.105/1039/Add.20 - Questions on suborbital flights for scientific missions and/or for human transportation: Djibouti, Ecuador, Greece, Jamaica, Mexico, Myanmar, Senegal, Slovakia and TunisiaApril 1, 2025A/AC.105/1338 - Report of the Scientific and Technical Subcommittee on its sixty-second session, held in Vienna from 3 to 14 February 2025April 1, 2025A/AC.105/1352 - Report on the United Nations Conference on Space Law and  Policy  (Vienna, Austria, 19–21 November 2024)January 31, 2025ST/SPACE/89 - Leveraging Space Technology for Agricultural Development and Food Security: Joint Publication by the Food and Agriculture Organization of the United Nations (FAO) and the United Nations Office for Outer Space Affairs (UNOOSA)June 19, 2024ST/SPACE/90 - UNOOSA 2023 Annual ReportJune 19, 2024ST/SPACE/92 - Gender Mainstreaming Toolkit for the Space SectorFebruary 9, 2024ST/SPACE/88 - The “Space2030” Agenda: Space as a Driver of Sustainable DevelopmentDecember 4, 2023ST/SPACE/91: Registration of Objects Launched into Outer Space: Stakeholder StudyJuly 11, 2023ST/SPACE/85 - Contribution to the “Space2030” Agenda: EU Space - Supporting A World Of 8 Billion People April 7, 2025A/AC.105/C.2/L.342 - Summary by the Chair of the Working Group on the Status and Application of the Five United Nations Treaties on Outer Space of views on the implementation of article XI of  the Treaty on Principles Governing the Activities of States in  the Exploration and Use of Outer Space, including the Moon and Other Celestial BodiesApril 7, 2025A/AC.105/1226/Add.5 -  Information relating to any practical case known that would warrant the definition and delimitation of outer space: Djibouti, Ecuador, Jamaica, Myanmar and TunisiaApril 2, 2025A/AC.105/1039/Add.20 - Questions on suborbital flights for scientific missions and/or for human transportation: Djibouti, Ecuador, Greece, Jamaica, Mexico, Myanmar, Senegal, Slovakia and TunisiaApril 1, 2025A/AC.105/1338 - Report of the Scientific and Technical Subcommittee on its sixty-second session, held in Vienna from 3 to 14 February 2025April 1, 2025A/AC.105/1352 - Report on the United Nations Conference on Space Law and  Policy  (Vienna, Austria, 19–21 November 2024)April 1, 2025A/AC.105/865/Add.29 - National legislation and practice relating to definition and delimitation of outer space: Djibouti, Ecuador, Greece, Mexico, Slovakia and TunisiaCalendar@UNOOSA\n\nSixth Space4Youth Essay Competition\nWinners Announced! Read more  \nLeveraging Space Technology for Agricultural Development and Food Security\nJoint Publication by the Food and Agriculture Organization of the United Nations (FAO) and the United Nations Office for Outer Space Affairs (UNOOSA)\n\nDownload here\n\n\nGraduate Programs in Space Technology Applications: MASTA and DOCSTA\n\nThe RCSSTEAP, affiliated with the United Nations, is pleased to offer 8 postgraduate programs on Space Technology Applications for the 2025 academic year. Read more\n\nSpace Law for New Space Actors: Fostering Responsible National Space Activities\nUNOOSA's Legal Advisory Project \"Space Law for New Space Actors\" offers Member States tailored capacity building to facilitate drafting of national space legislation in line with international space law. Read more\n\nWhat's newNewsPublicationsReportsApril 7, 2025A/AC.105/C.2/L.342 - Summary by the Chair of the Working Group on the Status and Application of the Five United Nations Treaties on Outer Space of views on the implementation of article XI of  the Treaty on Principles Governing the Activities of States in  the Exploration and Use of Outer Space, including the Moon and Other Celestial BodiesApril 7, 2025A/AC.105/1226/Add.5 -  Information relating to any practical case known that would warrant the definition and delimitation of outer space: Djibouti, Ecuador, Jamaica, Myanmar and TunisiaApril 2, 2025Workshop on Ionospheric Impacts on GNSS and International Collaboration to Meet Current and Future Solar Activity Period Challenges, 25 - 26 June 2025, Vienna International Centre, AustriaApril 2, 2025A/AC.105/1039/Add.20 - Questions on suborbital flights for scientific missions and/or for human transportation: Djibouti, Ecuador, Greece, Jamaica, Mexico, Myanmar, Senegal, Slovakia and TunisiaApril 1, 2025A/AC.105/1338 - Report of the Scientific and Technical Subcommittee on its sixty-second session, held in Vienna from 3 to 14 February 2025April 1, 2025A/AC.105/1352 - Report on the United Nations Conference on Space Law and  Policy  (Vienna, Austria, 19–21 November 2024)January 31, 2025ST/SPACE/89 - Leveraging Space Technology for Agricultural Development and Food Security: Joint Publication by the Food and Agriculture Organization of the United Nations (FAO) and the United Nations Office for Outer Space Affairs (UNOOSA)June 19, 2024ST/SPACE/90 - UNOOSA 2023 Annual ReportJune 19, 2024ST/SPACE/92 - Gender Mainstreaming Toolkit for the Space SectorFebruary 9, 2024ST/SPACE/88 - The “Space2030” Agenda: Space as a Driver of Sustainable DevelopmentDecember 4, 2023ST/SPACE/91: Registration of Objects Launched into Outer Space: Stakeholder StudyJuly 11, 2023ST/SPACE/85 - Contribution to the “Space2030” Agenda: EU Space - Supporting A World Of 8 Billion People April 7, 2025A/AC.105/C.2/L.342 - Summary by the Chair of the Working Group on the Status and Application of the Five United Nations Treaties on Outer Space of views on the implementation of article XI of  the Treaty on Principles Governing the Activities of States in  the Exploration and Use of Outer Space, including the Moon and Other Celestial BodiesApril 7, 2025A/AC.105/1226/Add.5 -  Information relating to any practical case known that would warrant the definition and delimitation of outer space: Djibouti, Ecuador, Jamaica, Myanmar and TunisiaApril 2, 2025A/AC.105/1039/Add.20 - Questions on suborbital flights for scientific missions and/or for human transportation: Djibouti, Ecuador, Greece, Jamaica, Mexico, Myanmar, Senegal, Slovakia and TunisiaApril 1, 2025A/AC.105/1338 - Report of the Scientific and Technical Subcommittee on its sixty-second session, held in Vienna from 3 to 14 February 2025April 1, 2025A/AC.105/1352 - Report on the United Nations Conference on Space Law and  Policy  (Vienna, Austria, 19–21 November 2024)April 1, 2025A/AC.105/865/Add.29 - National legislation and practice relating to definition and delimitation of outer space: Djibouti, Ecuador, Greece, Mexico, Slovakia and TunisiaCalendar@UNOOSA\n\nSixth Space4Youth Essay Competition\nWinners Announced! Read more  \nLeveraging Space Technology for Agricultural Development and Food Security\nJoint Publication by the Food and Agriculture Organization of the United Nations (FAO) and the United Nations Office for Outer Space Affairs (UNOOSA)\n\nDownload here\n\n\nGraduate Programs in Space Technology Applications: MASTA and DOCSTA\n\nThe RCSSTEAP, affiliated with the United Nations, is pleased to offer 8 postgraduate programs on Space Technology Applications for the 2025 academic year. Read more\n\nSpace Law for New Space Actors: Fostering Responsible National Space Activities\nUNOOSA's Legal Advisory Project \"Space Law for New Space Actors\" offers Member States tailored capacity building to facilitate drafting of national space legislation in line with international space law. Read more\n\nWhat's newNewsPublicationsReportsApril 7, 2025A/AC.105/C.2/L.342 - Summary by the Chair of the Working Group on the Status and Application of the Five United Nations Treaties on Outer Space of views on the implementation of article XI of  the Treaty on Principles Governing the Activities of States in  the Exploration and Use of Outer Space, including the Moon and Other Celestial BodiesApril 7, 2025A/AC.105/1226/Add.5 -  Information relating to any practical case known that would warrant the definition and delimitation of outer space: Djibouti, Ecuador, Jamaica, Myanmar and TunisiaApril 2, 2025Workshop on Ionospheric Impacts on GNSS and International Collaboration to Meet Current and Future Solar Activity Period Challenges, 25 - 26 June 2025, Vienna International Centre, AustriaApril 2, 2025A/AC.105/1039/Add.20 - Questions on suborbital flights for scientific missions and/or for human transportation: Djibouti, Ecuador, Greece, Jamaica, Mexico, Myanmar, Senegal, Slovakia and TunisiaApril 1, 2025A/AC.105/1338 - Report of the Scientific and Technical Subcommittee on its sixty-second session, held in Vienna from 3 to 14 February 2025April 1, 2025A/AC.105/1352 - Report on the United Nations Conference on Space Law and  Policy  (Vienna, Austria, 19–21 November 2024)January 31, 2025ST/SPACE/89 - Leveraging Space Technology for Agricultural Development and Food Security: Joint Publication by the Food and Agriculture Organization of the United Nations (FAO) and the United Nations Office for Outer Space Affairs (UNOOSA)June 19, 2024ST/SPACE/90 - UNOOSA 2023 Annual ReportJune 19, 2024ST/SPACE/92 - Gender Mainstreaming Toolkit for the Space SectorFebruary 9, 2024ST/SPACE/88 - The “Space2030” Agenda: Space as a Driver of Sustainable DevelopmentDecember 4, 2023ST/SPACE/91: Registration of Objects Launched into Outer Space: Stakeholder StudyJuly 11, 2023ST/SPACE/85 - Contribution to the “Space2030” Agenda: EU Space - Supporting A World Of 8 Billion People April 7, 2025A/AC.105/C.2/L.342 - Summary by the Chair of the Working Group on the Status and Application of the Five United Nations Treaties on Outer Space of views on the implementation of article XI of  the Treaty on Principles Governing the Activities of States in  the Exploration and Use of Outer Space, including the Moon and Other Celestial BodiesApril 7, 2025A/AC.105/1226/Add.5 -  Information relating to any practical case known that would warrant the definition and delimitation of outer space: Djibouti, Ecuador, Jamaica, Myanmar and TunisiaApril 2, 2025A/AC.105/1039/Add.20 - Questions on suborbital flights for scientific missions and/or for human transportation: Djibouti, Ecuador, Greece, Jamaica, Mexico, Myanmar, Senegal, Slovakia and TunisiaApril 1, 2025A/AC.105/1338 - Report of the Scientific and Technical Subcommittee on its sixty-second session, held in Vienna from 3 to 14 February 2025April 1, 2025A/AC.105/1352 - Report on the United Nations Conference on Space Law and  Policy  (Vienna, Austria, 19–21 November 2024)April 1, 2025A/AC.105/865/Add.29 - National legislation and practice relating to definition and delimitation of outer space: Djibouti, Ecuador, Greece, Mexico, Slovakia and TunisiaCalendar@UNOOSA\n\nSixth Space4Youth Essay Competition\nWinners Announced! Read more\n\nSpace Law for New Space Actors: Fostering Responsible National Space Activities\nUNOOSA's Legal Advisory Project \"Space Law for New Space Actors\" offers Member States tailored capacity building to facilitate drafting of national space legislation in line with international space law. Read more\n\nSpace Law for New Space Actors: Fostering Responsible National Space Activities\nUNOOSA's Legal Advisory Project \"Space Law for New Space Actors\" offers Member States tailored capacity building to facilitate drafting of national space legislation in line with international space law. Read more\n\nSpace Law for New Space Actors: Fostering Responsible National Space Activities\nUNOOSA's Legal Advisory Project \"Space Law for New Space Actors\" offers Member States tailored capacity building to facilitate drafting of national space legislation in line with international space law. Read more\n\nSpace Law for New Space Actors: Fostering Responsible National Space Activities\nUNOOSA's Legal Advisory Project \"Space Law for New Space Actors\" offers Member States tailored capacity building to facilitate drafting of national space legislation in line with international space law. Read more\n\nSpace Law for New Space Actors: Fostering Responsible National Space Activities\nUNOOSA's Legal Advisory Project \"Space Law for New Space Actors\" offers Member States tailored capacity building to facilitate drafting of national space legislation in line with international space law. Read more\n\nLeveraging Space Technology for Agricultural Development and Food Security\nJoint Publication by the Food and Agriculture Organization of the United Nations (FAO) and the United Nations Office for Outer Space Affairs (UNOOSA)\n\nDownload here\n\nLeveraging Space Technology for Agricultural Development and Food Security\nJoint Publication by the Food and Agriculture Organization of the United Nations (FAO) and the United Nations Office for Outer Space Affairs (UNOOSA)\n\nDownload here\n\nLeveraging Space Technology for Agricultural Development and Food Security\nJoint Publication by the Food and Agriculture Organization of the United Nations (FAO) and the United Nations Office for Outer Space Affairs (UNOOSA)\n\nDownload here\n\nJoint Publication by the Food and Agriculture Organization of the United Nations (FAO) and the United Nations Office for Outer Space Affairs (UNOOSA)\n\nDownload here\n\nGraduate Programs in Space Technology Applications: MASTA and DOCSTA\n\nThe RCSSTEAP, affiliated with the United Nations, is pleased to offer 8 postgraduate programs on Space Technology Applications for the 2025 academic year. Read more\n\nSpace Law for New Space Actors: Fostering Responsible National Space Activities\nUNOOSA's Legal Advisory Project \"Space Law for New Space Actors\" offers Member States tailored capacity building to facilitate drafting of national space legislation in line with international space law. Read more\n\nSpace Law for New Space Actors: Fostering Responsible National Space Activities\nUNOOSA's Legal Advisory Project \"Space Law for New Space Actors\" offers Member States tailored capacity building to facilitate drafting of national space legislation in line with international space law. Read more\n\nSpace Law for New Space Actors: Fostering Responsible National Space Activities\nUNOOSA's Legal Advisory Project \"Space Law for New Space Actors\" offers Member States tailored capacity building to facilitate drafting of national space legislation in line with international space law. Read more\n\nWhat's newNewsPublicationsReportsApril 7, 2025A/AC.105/C.2/L.342 - Summary by the Chair of the Working Group on the Status and Application of the Five United Nations Treaties on Outer Space of views on the implementation of article XI of  the Treaty on Principles Governing the Activities of States in  the Exploration and Use of Outer Space, including the Moon and Other Celestial BodiesApril 7, 2025A/AC.105/1226/Add.5 -  Information relating to any practical case known that would warrant the definition and delimitation of outer space: Djibouti, Ecuador, Jamaica, Myanmar and TunisiaApril 2, 2025Workshop on Ionospheric Impacts on GNSS and International Collaboration to Meet Current and Future Solar Activity Period Challenges, 25 - 26 June 2025, Vienna International Centre, AustriaApril 2, 2025A/AC.105/1039/Add.20 - Questions on suborbital flights for scientific missions and/or for human transportation: Djibouti, Ecuador, Greece, Jamaica, Mexico, Myanmar, Senegal, Slovakia and TunisiaApril 1, 2025A/AC.105/1338 - Report of the Scientific and Technical Subcommittee on its sixty-second session, held in Vienna from 3 to 14 February 2025April 1, 2025A/AC.105/1352 - Report on the United Nations Conference on Space Law and  Policy  (Vienna, Austria, 19–21 November 2024)January 31, 2025ST/SPACE/89 - Leveraging Space Technology for Agricultural Development and Food Security: Joint Publication by the Food and Agriculture Organization of the United Nations (FAO) and the United Nations Office for Outer Space Affairs (UNOOSA)June 19, 2024ST/SPACE/90 - UNOOSA 2023 Annual ReportJune 19, 2024ST/SPACE/92 - Gender Mainstreaming Toolkit for the Space SectorFebruary 9, 2024ST/SPACE/88 - The “Space2030” Agenda: Space as a Driver of Sustainable DevelopmentDecember 4, 2023ST/SPACE/91: Registration of Objects Launched into Outer Space: Stakeholder StudyJuly 11, 2023ST/SPACE/85 - Contribution to the “Space2030” Agenda: EU Space - Supporting A World Of 8 Billion People April 7, 2025A/AC.105/C.2/L.342 - Summary by the Chair of the Working Group on the Status and Application of the Five United Nations Treaties on Outer Space of views on the implementation of article XI of  the Treaty on Principles Governing the Activities of States in  the Exploration and Use of Outer Space, including the Moon and Other Celestial BodiesApril 7, 2025A/AC.105/1226/Add.5 -  Information relating to any practical case known that would warrant the definition and delimitation of outer space: Djibouti, Ecuador, Jamaica, Myanmar and TunisiaApril 2, 2025A/AC.105/1039/Add.20 - Questions on suborbital flights for scientific missions and/or for human transportation: Djibouti, Ecuador, Greece, Jamaica, Mexico, Myanmar, Senegal, Slovakia and TunisiaApril 1, 2025A/AC.105/1338 - Report of the Scientific and Technical Subcommittee on its sixty-second session, held in Vienna from 3 to 14 February 2025April 1, 2025A/AC.105/1352 - Report on the United Nations Conference on Space Law and  Policy  (Vienna, Austria, 19–21 November 2024)April 1, 2025A/AC.105/865/Add.29 - National legislation and practice relating to definition and delimitation of outer space: Djibouti, Ecuador, Greece, Mexico, Slovakia and TunisiaCalendar@UNOOSA\n\nSpace4SDGs\nSee UNOOSA's \n\nbrochure to understand how space technology and its myriad applications play an important role in supporting the 17 Sustainable Development Goals (SDGs) established under the 2030 Agenda for Sustainable Development. Read more\n\nNewsPublicationsReportsApril 7, 2025A/AC.105/C.2/L.342 - Summary by the Chair of the Working Group on the Status and Application of the Five United Nations Treaties on Outer Space of views on the implementation of article XI of  the Treaty on Principles Governing the Activities of States in  the Exploration and Use of Outer Space, including the Moon and Other Celestial BodiesApril 7, 2025A/AC.105/1226/Add.5 -  Information relating to any practical case known that would warrant the definition and delimitation of outer space: Djibouti, Ecuador, Jamaica, Myanmar and TunisiaApril 2, 2025Workshop on Ionospheric Impacts on GNSS and International Collaboration to Meet Current and Future Solar Activity Period Challenges, 25 - 26 June 2025, Vienna International Centre, AustriaApril 2, 2025A/AC.105/1039/Add.20 - Questions on suborbital flights for scientific missions and/or for human transportation: Djibouti, Ecuador, Greece, Jamaica, Mexico, Myanmar, Senegal, Slovakia and TunisiaApril 1, 2025A/AC.105/1338 - Report of the Scientific and Technical Subcommittee on its sixty-second session, held in Vienna from 3 to 14 February 2025April 1, 2025A/AC.105/1352 - Report on the United Nations Conference on Space Law and  Policy  (Vienna, Austria, 19–21 November 2024)January 31, 2025ST/SPACE/89 - Leveraging Space Technology for Agricultural Development and Food Security: Joint Publication by the Food and Agriculture Organization of the United Nations (FAO) and the United Nations Office for Outer Space Affairs (UNOOSA)June 19, 2024ST/SPACE/90 - UNOOSA 2023 Annual ReportJune 19, 2024ST/SPACE/92 - Gender Mainstreaming Toolkit for the Space SectorFebruary 9, 2024ST/SPACE/88 - The “Space2030” Agenda: Space as a Driver of Sustainable DevelopmentDecember 4, 2023ST/SPACE/91: Registration of Objects Launched into Outer Space: Stakeholder StudyJuly 11, 2023ST/SPACE/85 - Contribution to the “Space2030” Agenda: EU Space - Supporting A World Of 8 Billion People April 7, 2025A/AC.105/C.2/L.342 - Summary by the Chair of the Working Group on the Status and Application of the Five United Nations Treaties on Outer Space of views on the implementation of article XI of  the Treaty on Principles Governing the Activities of States in  the Exploration and Use of Outer Space, including the Moon and Other Celestial BodiesApril 7, 2025A/AC.105/1226/Add.5 -  Information relating to any practical case known that would warrant the definition and delimitation of outer space: Djibouti, Ecuador, Jamaica, Myanmar and TunisiaApril 2, 2025A/AC.105/1039/Add.20 - Questions on suborbital flights for scientific missions and/or for human transportation: Djibouti, Ecuador, Greece, Jamaica, Mexico, Myanmar, Senegal, Slovakia and TunisiaApril 1, 2025A/AC.105/1338 - Report of the Scientific and Technical Subcommittee on its sixty-second session, held in Vienna from 3 to 14 February 2025April 1, 2025A/AC.105/1352 - Report on the United Nations Conference on Space Law and  Policy  (Vienna, Austria, 19–21 November 2024)April 1, 2025A/AC.105/865/Add.29 - National legislation and practice relating to definition and delimitation of outer space: Djibouti, Ecuador, Greece, Mexico, Slovakia and TunisiaCalendar@UNOOSA\n\nNewsPublicationsReportsApril 7, 2025A/AC.105/C.2/L.342 - Summary by the Chair of the Working Group on the Status and Application of the Five United Nations Treaties on Outer Space of views on the implementation of article XI of  the Treaty on Principles Governing the Activities of States in  the Exploration and Use of Outer Space, including the Moon and Other Celestial BodiesApril 7, 2025A/AC.105/1226/Add.5 -  Information relating to any practical case known that would warrant the definition and delimitation of outer space: Djibouti, Ecuador, Jamaica, Myanmar and TunisiaApril 2, 2025Workshop on Ionospheric Impacts on GNSS and International Collaboration to Meet Current and Future Solar Activity Period Challenges, 25 - 26 June 2025, Vienna International Centre, AustriaApril 2, 2025A/AC.105/1039/Add.20 - Questions on suborbital flights for scientific missions and/or for human transportation: Djibouti, Ecuador, Greece, Jamaica, Mexico, Myanmar, Senegal, Slovakia and TunisiaApril 1, 2025A/AC.105/1338 - Report of the Scientific and Technical Subcommittee on its sixty-second session, held in Vienna from 3 to 14 February 2025April 1, 2025A/AC.105/1352 - Report on the United Nations Conference on Space Law and  Policy  (Vienna, Austria, 19–21 November 2024)January 31, 2025ST/SPACE/89 - Leveraging Space Technology for Agricultural Development and Food Security: Joint Publication by the Food and Agriculture Organization of the United Nations (FAO) and the United Nations Office for Outer Space Affairs (UNOOSA)June 19, 2024ST/SPACE/90 - UNOOSA 2023 Annual ReportJune 19, 2024ST/SPACE/92 - Gender Mainstreaming Toolkit for the Space SectorFebruary 9, 2024ST/SPACE/88 - The “Space2030” Agenda: Space as a Driver of Sustainable DevelopmentDecember 4, 2023ST/SPACE/91: Registration of Objects Launched into Outer Space: Stakeholder StudyJuly 11, 2023ST/SPACE/85 - Contribution to the “Space2030” Agenda: EU Space - Supporting A World Of 8 Billion People April 7, 2025A/AC.105/C.2/L.342 - Summary by the Chair of the Working Group on the Status and Application of the Five United Nations Treaties on Outer Space of views on the implementation of article XI of  the Treaty on Principles Governing the Activities of States in  the Exploration and Use of Outer Space, including the Moon and Other Celestial BodiesApril 7, 2025A/AC.105/1226/Add.5 -  Information relating to any practical case known that would warrant the definition and delimitation of outer space: Djibouti, Ecuador, Jamaica, Myanmar and TunisiaApril 2, 2025A/AC.105/1039/Add.20 - Questions on suborbital flights for scientific missions and/or for human transportation: Djibouti, Ecuador, Greece, Jamaica, Mexico, Myanmar, Senegal, Slovakia and TunisiaApril 1, 2025A/AC.105/1338 - Report of the Scientific and Technical Subcommittee on its sixty-second session, held in Vienna from 3 to 14 February 2025April 1, 2025A/AC.105/1352 - Report on the United Nations Conference on Space Law and  Policy  (Vienna, Austria, 19–21 November 2024)April 1, 2025A/AC.105/865/Add.29 - National legislation and practice relating to definition and delimitation of outer space: Djibouti, Ecuador, Greece, Mexico, Slovakia and Tunisia\n\nNewsPublicationsReportsApril 7, 2025A/AC.105/C.2/L.342 - Summary by the Chair of the Working Group on the Status and Application of the Five United Nations Treaties on Outer Space of views on the implementation of article XI of  the Treaty on Principles Governing the Activities of States in  the Exploration and Use of Outer Space, including the Moon and Other Celestial BodiesApril 7, 2025A/AC.105/1226/Add.5 -  Information relating to any practical case known that would warrant the definition and delimitation of outer space: Djibouti, Ecuador, Jamaica, Myanmar and TunisiaApril 2, 2025Workshop on Ionospheric Impacts on GNSS and International Collaboration to Meet Current and Future Solar Activity Period Challenges, 25 - 26 June 2025, Vienna International Centre, AustriaApril 2, 2025A/AC.105/1039/Add.20 - Questions on suborbital flights for scientific missions and/or for human transportation: Djibouti, Ecuador, Greece, Jamaica, Mexico, Myanmar, Senegal, Slovakia and TunisiaApril 1, 2025A/AC.105/1338 - Report of the Scientific and Technical Subcommittee on its sixty-second session, held in Vienna from 3 to 14 February 2025April 1, 2025A/AC.105/1352 - Report on the United Nations Conference on Space Law and  Policy  (Vienna, Austria, 19–21 November 2024)January 31, 2025ST/SPACE/89 - Leveraging Space Technology for Agricultural Development and Food Security: Joint Publication by the Food and Agriculture Organization of the United Nations (FAO) and the United Nations Office for Outer Space Affairs (UNOOSA)June 19, 2024ST/SPACE/90 - UNOOSA 2023 Annual ReportJune 19, 2024ST/SPACE/92 - Gender Mainstreaming Toolkit for the Space SectorFebruary 9, 2024ST/SPACE/88 - The “Space2030” Agenda: Space as a Driver of Sustainable DevelopmentDecember 4, 2023ST/SPACE/91: Registration of Objects Launched into Outer Space: Stakeholder StudyJuly 11, 2023ST/SPACE/85 - Contribution to the “Space2030” Agenda: EU Space - Supporting A World Of 8 Billion People April 7, 2025A/AC.105/C.2/L.342 - Summary by the Chair of the Working Group on the Status and Application of the Five United Nations Treaties on Outer Space of views on the implementation of article XI of  the Treaty on Principles Governing the Activities of States in  the Exploration and Use of Outer Space, including the Moon and Other Celestial BodiesApril 7, 2025A/AC.105/1226/Add.5 -  Information relating to any practical case known that would warrant the definition and delimitation of outer space: Djibouti, Ecuador, Jamaica, Myanmar and TunisiaApril 2, 2025A/AC.105/1039/Add.20 - Questions on suborbital flights for scientific missions and/or for human transportation: Djibouti, Ecuador, Greece, Jamaica, Mexico, Myanmar, Senegal, Slovakia and TunisiaApril 1, 2025A/AC.105/1338 - Report of the Scientific and Technical Subcommittee on its sixty-second session, held in Vienna from 3 to 14 February 2025April 1, 2025A/AC.105/1352 - Report on the United Nations Conference on Space Law and  Policy  (Vienna, Austria, 19–21 November 2024)April 1, 2025A/AC.105/865/Add.29 - National legislation and practice relating to definition and delimitation of outer space: Djibouti, Ecuador, Greece, Mexico, Slovakia and Tunisia\n\nApril 7, 2025A/AC.105/C.2/L.342 - Summary by the Chair of the Working Group on the Status and Application of the Five United Nations Treaties on Outer Space of views on the implementation of article XI of  the Treaty on Principles Governing the Activities of States in  the Exploration and Use of Outer Space, including the Moon and Other Celestial BodiesApril 7, 2025A/AC.105/1226/Add.5 -  Information relating to any practical case known that would warrant the definition and delimitation of outer space: Djibouti, Ecuador, Jamaica, Myanmar and TunisiaApril 2, 2025Workshop on Ionospheric Impacts on GNSS and International Collaboration to Meet Current and Future Solar Activity Period Challenges, 25 - 26 June 2025, Vienna International Centre, AustriaApril 2, 2025A/AC.105/1039/Add.20 - Questions on suborbital flights for scientific missions and/or for human transportation: Djibouti, Ecuador, Greece, Jamaica, Mexico, Myanmar, Senegal, Slovakia and TunisiaApril 1, 2025A/AC.105/1338 - Report of the Scientific and Technical Subcommittee on its sixty-second session, held in Vienna from 3 to 14 February 2025April 1, 2025A/AC.105/1352 - Report on the United Nations Conference on Space Law and  Policy  (Vienna, Austria, 19–21 November 2024)January 31, 2025ST/SPACE/89 - Leveraging Space Technology for Agricultural Development and Food Security: Joint Publication by the Food and Agriculture Organization of the United Nations (FAO) and the United Nations Office for Outer Space Affairs (UNOOSA)June 19, 2024ST/SPACE/90 - UNOOSA 2023 Annual ReportJune 19, 2024ST/SPACE/92 - Gender Mainstreaming Toolkit for the Space SectorFebruary 9, 2024ST/SPACE/88 - The “Space2030” Agenda: Space as a Driver of Sustainable DevelopmentDecember 4, 2023ST/SPACE/91: Registration of Objects Launched into Outer Space: Stakeholder StudyJuly 11, 2023ST/SPACE/85 - Contribution to the “Space2030” Agenda: EU Space - Supporting A World Of 8 Billion People April 7, 2025A/AC.105/C.2/L.342 - Summary by the Chair of the Working Group on the Status and Application of the Five United Nations Treaties on Outer Space of views on the implementation of article XI of  the Treaty on Principles Governing the Activities of States in  the Exploration and Use of Outer Space, including the Moon and Other Celestial BodiesApril 7, 2025A/AC.105/1226/Add.5 -  Information relating to any practical case known that would warrant the definition and delimitation of outer space: Djibouti, Ecuador, Jamaica, Myanmar and TunisiaApril 2, 2025A/AC.105/1039/Add.20 - Questions on suborbital flights for scientific missions and/or for human transportation: Djibouti, Ecuador, Greece, Jamaica, Mexico, Myanmar, Senegal, Slovakia and TunisiaApril 1, 2025A/AC.105/1338 - Report of the Scientific and Technical Subcommittee on its sixty-second session, held in Vienna from 3 to 14 February 2025April 1, 2025A/AC.105/1352 - Report on the United Nations Conference on Space Law and  Policy  (Vienna, Austria, 19–21 November 2024)April 1, 2025A/AC.105/865/Add.29 - National legislation and practice relating to definition and delimitation of outer space: Djibouti, Ecuador, Greece, Mexico, Slovakia and Tunisia\n\nApril 7, 2025A/AC.105/C.2/L.342 - Summary by the Chair of the Working Group on the Status and Application of the Five United Nations Treaties on Outer Space of views on the implementation of article XI of  the Treaty on Principles Governing the Activities of States in  the Exploration and Use of Outer Space, including the Moon and Other Celestial BodiesApril 7, 2025A/AC.105/1226/Add.5 -  Information relating to any practical case known that would warrant the definition and delimitation of outer space: Djibouti, Ecuador, Jamaica, Myanmar and TunisiaApril 2, 2025Workshop on Ionospheric Impacts on GNSS and International Collaboration to Meet Current and Future Solar Activity Period Challenges, 25 - 26 June 2025, Vienna International Centre, AustriaApril 2, 2025A/AC.105/1039/Add.20 - Questions on suborbital flights for scientific missions and/or for human transportation: Djibouti, Ecuador, Greece, Jamaica, Mexico, Myanmar, Senegal, Slovakia and TunisiaApril 1, 2025A/AC.105/1338 - Report of the Scientific and Technical Subcommittee on its sixty-second session, held in Vienna from 3 to 14 February 2025April 1, 2025A/AC.105/1352 - Report on the United Nations Conference on Space Law and  Policy  (Vienna, Austria, 19–21 November 2024)\n\nApril 7, 2025\n\nA/AC.105/C.2/L.342 - Summary by the Chair of the Working Group on the Status and Application of the Five United Nations Treaties on Outer Space of views on the implementation of article XI of  the Treaty on Principles Governing the Activities of States in  the Exploration and Use of Outer Space, including the Moon and Other Celestial Bodies\n\nApril 7, 2025\n\nA/AC.105/1226/Add.5 -  Information relating to any practical case known that would warrant the definition and delimitation of outer space: Djibouti, Ecuador, Jamaica, Myanmar and Tunisia\n\nApril 2, 2025\n\nWorkshop on Ionospheric Impacts on GNSS and International Collaboration to Meet Current and Future Solar Activity Period Challenges, 25 - 26 June 2025, Vienna International Centre, Austria\n\nApril 2, 2025\n\nA/AC.105/1039/Add.20 - Questions on suborbital flights for scientific missions and/or for human transportation: Djibouti, Ecuador, Greece, Jamaica, Mexico, Myanmar, Senegal, Slovakia and Tunisia\n\nApril 1, 2025\n\nA/AC.105/1338 - Report of the Scientific and Technical Subcommittee on its sixty-second session, held in Vienna from 3 to 14 February 2025\n\nApril 1, 2025\n\nA/AC.105/1352 - Report on the United Nations Conference on Space Law and  Policy  (Vienna, Austria, 19–21 November 2024)\n\nJanuary 31, 2025ST/SPACE/89 - Leveraging Space Technology for Agricultural Development and Food Security: Joint Publication by the Food and Agriculture Organization of the United Nations (FAO) and the United Nations Office for Outer Space Affairs (UNOOSA)June 19, 2024ST/SPACE/90 - UNOOSA 2023 Annual ReportJune 19, 2024ST/SPACE/92 - Gender Mainstreaming Toolkit for the Space SectorFebruary 9, 2024ST/SPACE/88 - The “Space2030” Agenda: Space as a Driver of Sustainable DevelopmentDecember 4, 2023ST/SPACE/91: Registration of Objects Launched into Outer Space: Stakeholder StudyJuly 11, 2023ST/SPACE/85 - Contribution to the “Space2030” Agenda: EU Space - Supporting A World Of 8 Billion People\n\nJanuary 31, 2025\n\nST/SPACE/89 - Leveraging Space Technology for Agricultural Development and Food Security: Joint Publication by the Food and Agriculture Organization of the United Nations (FAO) and the United Nations Office for Outer Space Affairs (UNOOSA)\n\nJune 19, 2024\n\nST/SPACE/90 - UNOOSA 2023 Annual Report\n\nJune 19, 2024\n\nST/SPACE/92 - Gender Mainstreaming Toolkit for the Space Sector\n\nFebruary 9, 2024\n\nST/SPACE/88 - The “Space2030” Agenda: Space as a Driver of Sustainable Development\n\nDecember 4, 2023\n\nST/SPACE/91: Registration of Objects Launched into Outer Space: Stakeholder Study\n\nJuly 11, 2023\n\nST/SPACE/85 - Contribution to the “Space2030” Agenda: EU Space - Supporting A World Of 8 Billion People\n\nApril 7, 2025A/AC.105/C.2/L.342 - Summary by the Chair of the Working Group on the Status and Application of the Five United Nations Treaties on Outer Space of views on the implementation of article XI of  the Treaty on Principles Governing the Activities of States in  the Exploration and Use of Outer Space, including the Moon and Other Celestial BodiesApril 7, 2025A/AC.105/1226/Add.5 -  Information relating to any practical case known that would warrant the definition and delimitation of outer space: Djibouti, Ecuador, Jamaica, Myanmar and TunisiaApril 2, 2025A/AC.105/1039/Add.20 - Questions on suborbital flights for scientific missions and/or for human transportation: Djibouti, Ecuador, Greece, Jamaica, Mexico, Myanmar, Senegal, Slovakia and TunisiaApril 1, 2025A/AC.105/1338 - Report of the Scientific and Technical Subcommittee on its sixty-second session, held in Vienna from 3 to 14 February 2025April 1, 2025A/AC.105/1352 - Report on the United Nations Conference on Space Law and  Policy  (Vienna, Austria, 19–21 November 2024)April 1, 2025A/AC.105/865/Add.29 - National legislation and practice relating to definition and delimitation of outer space: Djibouti, Ecuador, Greece, Mexico, Slovakia and Tunisia\n\nApril 7, 2025\n\nA/AC.105/C.2/L.342 - Summary by the Chair of the Working Group on the Status and Application of the Five United Nations Treaties on Outer Space of views on the implementation of article XI of  the Treaty on Principles Governing the Activities of States in  the Exploration and Use of Outer Space, including the Moon and Other Celestial Bodies\n\nApril 7, 2025\n\nA/AC.105/1226/Add.5 -  Information relating to any practical case known that would warrant the definition and delimitation of outer space: Djibouti, Ecuador, Jamaica, Myanmar and Tunisia\n\nApril 2, 2025\n\nA/AC.105/1039/Add.20 - Questions on suborbital flights for scientific missions and/or for human transportation: Djibouti, Ecuador, Greece, Jamaica, Mexico, Myanmar, Senegal, Slovakia and Tunisia\n\nApril 1, 2025\n\nA/AC.105/1338 - Report of the Scientific and Technical Subcommittee on its sixty-second session, held in Vienna from 3 to 14 February 2025\n\nApril 1, 2025\n\nA/AC.105/1352 - Report on the United Nations Conference on Space Law and  Policy  (Vienna, Austria, 19–21 November 2024)\n\nApril 1, 2025\n\nA/AC.105/865/Add.29 - National legislation and practice relating to definition and delimitation of outer space: Djibouti, Ecuador, Greece, Mexico, Slovakia and Tunisia\n\nCalendar\n\n@UNOOSA\n\nLatestApril 7, 2025NewsA/AC.105/C.2/L.342 - Summary by the Chair of the Working Group on the Status and Application of the Five United Nations Treaties on Outer Space of views on the implementation of article XI of  the Treaty on Principles Governing the Activities of States in  the Exploration and Use of Outer Space, including the Moon and Other Celestial BodiesJanuary 31, 2025PublicationsST/SPACE/89 - Leveraging Space Technology for Agricultural Development and Food Security: Joint Publication by the Food and Agriculture Organization of the United Nations (FAO) and the United Nations Office for Outer Space Affairs (UNOOSA)April 7, 2025ReportsA/AC.105/C.2/L.342 - Summary by the Chair of the Working Group on the Status and Application of the Five United Nations Treaties on Outer Space of views on the implementation of article XI of  the Treaty on Principles Governing the Activities of States in  the Exploration and Use of Outer Space, including the Moon and Other Celestial BodiesLinks\n\nVIC Online\n\n\nUNIS Vienna\n\n\nUN-SPIDER\n\n\nUnited Nations\n  \n\n\nTerms of Use\n\nContact us\nUnited Nations Office for Outer Space Affairs\nUnited Nations Office at Vienna\n Vienna International Centre\n Wagramerstrasse 5\n A-1220 Vienna\n AUSTRIA\nTel.: +43-1 26060-84950\nFax: +43-1-26060-5830\n\nSend us a message! LatestApril 7, 2025NewsA/AC.105/C.2/L.342 - Summary by the Chair of the Working Group on the Status and Application of the Five United Nations Treaties on Outer Space of views on the implementation of article XI of  the Treaty on Principles Governing the Activities of States in  the Exploration and Use of Outer Space, including the Moon and Other Celestial BodiesJanuary 31, 2025PublicationsST/SPACE/89 - Leveraging Space Technology for Agricultural Development and Food Security: Joint Publication by the Food and Agriculture Organization of the United Nations (FAO) and the United Nations Office for Outer Space Affairs (UNOOSA)April 7, 2025ReportsA/AC.105/C.2/L.342 - Summary by the Chair of the Working Group on the Status and Application of the Five United Nations Treaties on Outer Space of views on the implementation of article XI of  the Treaty on Principles Governing the Activities of States in  the Exploration and Use of Outer Space, including the Moon and Other Celestial BodiesLinks\n\nVIC Online\n\n\nUNIS Vienna\n\n\nUN-SPIDER\n\n\nUnited Nations\n  \n\n\nTerms of Use\n\nContact us\nUnited Nations Office for Outer Space Affairs\nUnited Nations Office at Vienna\n Vienna International Centre\n Wagramerstrasse 5\n A-1220 Vienna\n AUSTRIA\nTel.: +43-1 26060-84950\nFax: +43-1-26060-5830\n\nSend us a message! LatestApril 7, 2025NewsA/AC.105/C.2/L.342 - Summary by the Chair of the Working Group on the Status and Application of the Five United Nations Treaties on Outer Space of views on the implementation of article XI of  the Treaty on Principles Governing the Activities of States in  the Exploration and Use of Outer Space, including the Moon and Other Celestial BodiesJanuary 31, 2025PublicationsST/SPACE/89 - Leveraging Space Technology for Agricultural Development and Food Security: Joint Publication by the Food and Agriculture Organization of the United Nations (FAO) and the United Nations Office for Outer Space Affairs (UNOOSA)April 7, 2025ReportsA/AC.105/C.2/L.342 - Summary by the Chair of the Working Group on the Status and Application of the Five United Nations Treaties on Outer Space of views on the implementation of article XI of  the Treaty on Principles Governing the Activities of States in  the Exploration and Use of Outer Space, including the Moon and Other Celestial Bodies\n\nApril 7, 2025\n\nNewsA/AC.105/C.2/L.342 - Summary by the Chair of the Working Group on the Status and Application of the Five United Nations Treaties on Outer Space of views on the implementation of article XI of  the Treaty on Principles Governing the Activities of States in  the Exploration and Use of Outer Space, including the Moon and Other Celestial Bodies\n\nJanuary 31, 2025\n\nPublicationsST/SPACE/89 - Leveraging Space Technology for Agricultural Development and Food Security: Joint Publication by the Food and Agriculture Organization of the United Nations (FAO) and the United Nations Office for Outer Space Affairs (UNOOSA)\n\nApril 7, 2025\n\nReportsA/AC.105/C.2/L.342 - Summary by the Chair of the Working Group on the Status and Application of the Five United Nations Treaties on Outer Space of views on the implementation of article XI of  the Treaty on Principles Governing the Activities of States in  the Exploration and Use of Outer Space, including the Moon and Other Celestial Bodies\n\nLinks\n\nVIC Online\n\n\nUNIS Vienna\n\n\nUN-SPIDER\n\n\nUnited Nations\n  \n\n\nTerms of Use\n\nVIC Online\n\nUNIS Vienna\n\nUN-SPIDER\n\nUnited Nations\n\nTerms of Use\n\nContact us\nUnited Nations Office for Outer Space Affairs\nUnited Nations Office at Vienna\n Vienna International Centre\n Wagramerstrasse 5\n A-1220 Vienna\n AUSTRIA\nTel.: +43-1 26060-84950\nFax: +43-1-26060-5830\n\nSend us a message!",
  "entities": {
    "countries": [
      "brazil",
      "china",
      "india",
      "mexico"
    ],
    "organizations": [
      "united nations",
      "un"
    ],
    "key_issues": [
      "issue",
      "challenge",
      "nation",
      "state",
      "region",
      "solution",
      "resolution",
      "policy",
      "initiative",
      "program",
      "action",
      "history",
      "development",
      "evolution",
      "humanitarian",
      "assistance",
      "economic",
      "economy",
      "industry",
      "united nations",
      "un",
      "general assembly",
      "organization",
      "agency"
    ]
  },
  "committee": "Fourth Committee",
  "topic": "Preventing the militarization of outer space"
}