{
  "url": "https://www.icj-cij.org/case/196",
  "title": "Obligations of Israel in relation to the Presence and Activities of the United Nations, Other International Or",
  "text": "Obligations of Israel in relation to the Presence and Activities of the United Nations, Other International Organizations and Third States in and in relation to the Occupied Palestinian Territory\n\n\n\n\n\nLatest Developments\n\n\n\n                  Press release 2025/13\n                \n\n\n                12 \n                March \n                2025\n              \nObligations of Israel in relation to the Presence and Activities of the United Nations, Other International Organizations and Third States in and in relation to the Occupied Palestinian Territory (Request for Advisory Opinion) - Filing of written statements and opening date of the public hearings\nAvailable in:\n\nEnglish\nFrench\n\n\n\n\n\n                  Press release 2025/9\n                \n\n\n                20 \n                February \n                2025\n              \nObligations of Israel in relation to the Presence and Activities of the United Nations, Other International Organizations and Third States in and in relation to the Occupied Palestinian Territory (Request for Advisory Opinion) - The Court authorizes the African Union to participate in the proceedings\nAvailable in:\n\nEnglish\nFrench\n\n\n\n\n\n                  Press release 2025/8\n                \n\n\n                7 \n                February \n                2025\n              \nObligations of Israel in relation to the Presence and Activities of the United Nations, Other International Organizations and Third States in and in relation to the Occupied Palestinian Territory (Request for Advisory Opinion) - The Court authorizes the League of Arab States to participate in the proceedings\nAvailable in:\n\nEnglish\nFrench\n\n\n\n\n\n                  Press release 2025/7\n                \n\n\n                4 \n                February \n                2025\n              \nObligations of Israel in relation to the Presence and Activities of the United Nations, Other International Organizations and Third States in and in relation to the Occupied Palestinian Territory (Request for Advisory Opinion) - The Court authorizes the Organisation of Islamic Cooperation to participate in the proceedings\nAvailable in:\n\nEnglish\nFrench\n\n\n\n\n\nPart II (F): Other documents without document symbols (documents received from the Secretariat of the United Nations)\n\n\n\n                30 \n                January \n                2025\n              \nPart II (F): Other documents without document symbols (documents received from the Secretariat of the United Nations)\nAvailable in:\n\nEnglish\nFrench\n\n\n\n\n\nPart II (E): Relevant instruments (documents received from the Secretariat of the United Nations)\n\n\n\n                30 \n                January \n                2025\n              \nPart II (E): Relevant instruments (documents received from the Secretariat of the United Nations)\nAvailable in:\n\nEnglish\nFrench\n\n\n\n\nPart II (D): Human rights documentation\n\n\n                30 \n                January \n                2025\n              \nPart II (D): Human rights documentation\n\n\n\nPart II (D) (1): General Assembly\n\n\nEnglish\nFrench\n\n\n\n\nPart II (D) (2): Human Rights Council\n\n\nEnglish\nFrench\n\n\n\n\nPart II (D) (3): Commission on Human Rights\n\n\nEnglish\nFrench\n\n\n\n\nPart II (D) (4): Treaty bodies\n\n\nEnglish\nFrench\n\n\n\n\nPart II (D) (5): Universal periodic review\n\n\nEnglish\nFrench\n\n\n\n\n\n\nPart II (C) - Security Council (documents received from the Secretariat of the United Nations)\n\n\n                30 \n                January \n                2025\n              \nPart II (C) - Security Council (documents received from the Secretariat of the United Nations)\n\n\n\nPart II (C) (1): Documentation relating to the situation in the Occupied Palestinian Territories\n\n\nEnglish\nFrench\n\n\n\n\nPart II (C) (2): Documentation relating to the safety and security of humanitarian personnel and United Nations and associated personnel\n\n\nEnglish\nFrench\n\n\n\n\n\n\n\nPart II (B) - General Assembly Emergency Special Sessions (documents received from the Secretariat of the United Nations)\n\n\n\n                30 \n                January \n                2025\n              \nPart II (B) - General Assembly Emergency Special Sessions (documents received from the Secretariat of the United Nations)\nAvailable in:\n\nEnglish\nFrench\n\n\n\n\nPart II (A) - Material of the United Nations Relating to the Questions before the Court (documents received from the Secretariat of the United Nations)\n\n\n                30 \n                January \n                2025\n              \nPart II (A) - Material of the United Nations Relating to the Questions before the Court (documents received from the Secretariat of the United Nations)\n\n\n\nPart II (A) (1): Israeli settlements\n\n\nEnglish\nFrench\n\n\n\n\nPart II (A) (2): Living conditions of the Palestinian people\n\n\nEnglish\nFrench\n\n\n\n\nPart II (A) (3): Palestinian women and children\n\n\nEnglish\nFrench\n\n\n\n\nPart II (A) (4): Permanent sovereignty over natural and national resources\n\n\nEnglish\nFrench\n\n\n\n\nPart II (A) (5): Right to self-determination\n\n\nEnglish\nFrench\n\n\n\n\nPart II (A) (6): Question of Palestine\n\n\nEnglish\nFrench\n\n\n\n\nPart II (A) (7): Situation in the Middle East\n\n\nEnglish\nFrench\n\n\n\n\nPart II (A) (8): Special Committee to investigate Israeli practices affecting the human rights of the Palestinian people\n\n\nEnglish\nFrench\n\n\n\n\nPart II (A) (9): United Nations Relief and Works Agency for Palestine refugees in the Near East (UNRWA)\n\n\nEnglish\nFrench\n\n\n\n\nPart II (A) (10): Assistance to the Palestinian people\n\n\nEnglish\nFrench\n\n\n\n\nPart II (A) (11): Safety and security of humanitarian personnel and protection of United Nations personnel\n\n\nEnglish\nFrench\n\n\n\n\n\n\n\nPart I: Material relating to the request by the General Assembly for an advisory opinion of the Court\n\n\n\n                30 \n                January \n                2025\n              \nPart I: Material relating to the request by the General Assembly for an advisory opinion of the Court\nAvailable in:\n\nEnglish\nFrench\n\n\n\n\n\nList of Documents (documents received from the Secretariat of the United Nations)\n\n\n\n                30 \n                January \n                2025\n              \nList of Documents (documents received from the Secretariat of the United Nations)\nAvailable in:\n\nEnglish\nFrench\n\n\n\n\n\nIntroductory Note (documents received from the Secretariat of the United Nations)\n\n\n\n                30 \n                January \n                2025\n              \nIntroductory Note (documents received from the Secretariat of the United Nations)\nAvailable in:\n\nEnglish\nFrench\n\n\n\n\n\n                  Press release 2024/86\n                \n\n\n                24 \n                December \n                2024\n              \nObligations of Israel in relation to the presence and activities of the United Nations, other international organizations and third States in and in relation to the Occupied Palestinian Territory (Request for Advisory Opinion) - The President of the Court makes an Order organizing the proceedings and fixes the time-limits for the presentation of written statements\nAvailable in:\n\nEnglish\nFrench\n\n\n\n\n\nOrder of 23 December 2024\n\n\nFixing of time-limits: Presentation of written statements\nAvailable in:\n\nEnglish\nFrench\n\n\n\n\n\n                  Press release 2024/84\n                \n\n\n                23 \n                December \n                2024\n              \nThe General Assembly of the United Nations requests an advisory opinion from the Court on “the obligations of Israel in relation to the presence and activities of the United Nations, other international organizations and third States” in and in relation to the Occupied Palestinian Territory\nAvailable in:\n\nEnglish\nFrench\n\n\n\n\n\nRequest for Advisory Opinion\n\n\n\n                23 \n                December \n                2024\n              \nRequest for Advisory Opinion\nAvailable in:\n\nEnglish\nFrench\n\n\n\n\n\n\n\n\n\n\n\n\n\n\n\n\nLinks\n\nObligations of Israel in relation to the Presence and Activities of the United Nations, Other International Organizations and Third States in and in relation to the Occupied Palestinian Territory\n\n\n\n\n\nLatest Developments\n\n\n\n                  Press release 2025/13\n                \n\n\n                12 \n                March \n                2025\n              \nObligations of Israel in relation to the Presence and Activities of the United Nations, Other International Organizations and Third States in and in relation to the Occupied Palestinian Territory (Request for Advisory Opinion) - Filing of written statements and opening date of the public hearings\nAvailable in:\n\nEnglish\nFrench\n\n\n\n\n\n                  Press release 2025/9\n                \n\n\n                20 \n                February \n                2025\n              \nObligations of Israel in relation to the Presence and Activities of the United Nations, Other International Organizations and Third States in and in relation to the Occupied Palestinian Territory (Request for Advisory Opinion) - The Court authorizes the African Union to participate in the proceedings\nAvailable in:\n\nEnglish\nFrench\n\n\n\n\n\n                  Press release 2025/8\n                \n\n\n                7 \n                February \n                2025\n              \nObligations of Israel in relation to the Presence and Activities of the United Nations, Other International Organizations and Third States in and in relation to the Occupied Palestinian Territory (Request for Advisory Opinion) - The Court authorizes the League of Arab States to participate in the proceedings\nAvailable in:\n\nEnglish\nFrench\n\n\n\n\n\n                  Press release 2025/7\n                \n\n\n                4 \n                February \n                2025\n              \nObligations of Israel in relation to the Presence and Activities of the United Nations, Other International Organizations and Third States in and in relation to the Occupied Palestinian Territory (Request for Advisory Opinion) - The Court authorizes the Organisation of Islamic Cooperation to participate in the proceedings\nAvailable in:\n\nEnglish\nFrench\n\n\n\n\n\nPart II (F): Other documents without document symbols (documents received from the Secretariat of the United Nations)\n\n\n\n                30 \n                January \n                2025\n              \nPart II (F): Other documents without document symbols (documents received from the Secretariat of the United Nations)\nAvailable in:\n\nEnglish\nFrench\n\n\n\n\n\nPart II (E): Relevant instruments (documents received from the Secretariat of the United Nations)\n\n\n\n                30 \n                January \n                2025\n              \nPart II (E): Relevant instruments (documents received from the Secretariat of the United Nations)\nAvailable in:\n\nEnglish\nFrench\n\n\n\n\nPart II (D): Human rights documentation\n\n\n                30 \n                January \n                2025\n              \nPart II (D): Human rights documentation\n\n\n\nPart II (D) (1): General Assembly\n\n\nEnglish\nFrench\n\n\n\n\nPart II (D) (2): Human Rights Council\n\n\nEnglish\nFrench\n\n\n\n\nPart II (D) (3): Commission on Human Rights\n\n\nEnglish\nFrench\n\n\n\n\nPart II (D) (4): Treaty bodies\n\n\nEnglish\nFrench\n\n\n\n\nPart II (D) (5): Universal periodic review\n\n\nEnglish\nFrench\n\n\n\n\n\n\nPart II (C) - Security Council (documents received from the Secretariat of the United Nations)\n\n\n                30 \n                January \n                2025\n              \nPart II (C) - Security Council (documents received from the Secretariat of the United Nations)\n\n\n\nPart II (C) (1): Documentation relating to the situation in the Occupied Palestinian Territories\n\n\nEnglish\nFrench\n\n\n\n\nPart II (C) (2): Documentation relating to the safety and security of humanitarian personnel and United Nations and associated personnel\n\n\nEnglish\nFrench\n\n\n\n\n\n\n\nPart II (B) - General Assembly Emergency Special Sessions (documents received from the Secretariat of the United Nations)\n\n\n\n                30 \n                January \n                2025\n              \nPart II (B) - General Assembly Emergency Special Sessions (documents received from the Secretariat of the United Nations)\nAvailable in:\n\nEnglish\nFrench\n\n\n\n\nPart II (A) - Material of the United Nations Relating to the Questions before the Court (documents received from the Secretariat of the United Nations)\n\n\n                30 \n                January \n                2025\n              \nPart II (A) - Material of the United Nations Relating to the Questions before the Court (documents received from the Secretariat of the United Nations)\n\n\n\nPart II (A) (1): Israeli settlements\n\n\nEnglish\nFrench\n\n\n\n\nPart II (A) (2): Living conditions of the Palestinian people\n\n\nEnglish\nFrench\n\n\n\n\nPart II (A) (3): Palestinian women and children\n\n\nEnglish\nFrench\n\n\n\n\nPart II (A) (4): Permanent sovereignty over natural and national resources\n\n\nEnglish\nFrench\n\n\n\n\nPart II (A) (5): Right to self-determination\n\n\nEnglish\nFrench\n\n\n\n\nPart II (A) (6): Question of Palestine\n\n\nEnglish\nFrench\n\n\n\n\nPart II (A) (7): Situation in the Middle East\n\n\nEnglish\nFrench\n\n\n\n\nPart II (A) (8): Special Committee to investigate Israeli practices affecting the human rights of the Palestinian people\n\n\nEnglish\nFrench\n\n\n\n\nPart II (A) (9): United Nations Relief and Works Agency for Palestine refugees in the Near East (UNRWA)\n\n\nEnglish\nFrench\n\n\n\n\nPart II (A) (10): Assistance to the Palestinian people\n\n\nEnglish\nFrench\n\n\n\n\nPart II (A) (11): Safety and security of humanitarian personnel and protection of United Nations personnel\n\n\nEnglish\nFrench\n\n\n\n\n\n\n\nPart I: Material relating to the request by the General Assembly for an advisory opinion of the Court\n\n\n\n                30 \n                January \n                2025\n              \nPart I: Material relating to the request by the General Assembly for an advisory opinion of the Court\nAvailable in:\n\nEnglish\nFrench\n\n\n\n\n\nList of Documents (documents received from the Secretariat of the United Nations)\n\n\n\n                30 \n                January \n                2025\n              \nList of Documents (documents received from the Secretariat of the United Nations)\nAvailable in:\n\nEnglish\nFrench\n\n\n\n\n\nIntroductory Note (documents received from the Secretariat of the United Nations)\n\n\n\n                30 \n                January \n                2025\n              \nIntroductory Note (documents received from the Secretariat of the United Nations)\nAvailable in:\n\nEnglish\nFrench\n\n\n\n\n\n                  Press release 2024/86\n                \n\n\n                24 \n                December \n                2024\n              \nObligations of Israel in relation to the presence and activities of the United Nations, other international organizations and third States in and in relation to the Occupied Palestinian Territory (Request for Advisory Opinion) - The President of the Court makes an Order organizing the proceedings and fixes the time-limits for the presentation of written statements\nAvailable in:\n\nEnglish\nFrench\n\n\n\n\n\nOrder of 23 December 2024\n\n\nFixing of time-limits: Presentation of written statements\nAvailable in:\n\nEnglish\nFrench\n\n\n\n\n\n                  Press release 2024/84\n                \n\n\n                23 \n                December \n                2024\n              \nThe General Assembly of the United Nations requests an advisory opinion from the Court on “the obligations of Israel in relation to the presence and activities of the United Nations, other international organizations and third States” in and in relation to the Occupied Palestinian Territory\nAvailable in:\n\nEnglish\nFrench\n\n\n\n\n\nRequest for Advisory Opinion\n\n\n\n                23 \n                December \n                2024\n              \nRequest for Advisory Opinion\nAvailable in:\n\nEnglish\nFrench\n\n\n\n\n\n\n\n\n\n\n\n\n\n\n\n\nLinks\n\nObligations of Israel in relation to the Presence and Activities of the United Nations, Other International Organizations and Third States in and in relation to the Occupied Palestinian Territory\n\n\n\n\n\nLatest Developments\n\n\n\n                  Press release 2025/13\n                \n\n\n                12 \n                March \n                2025\n              \nObligations of Israel in relation to the Presence and Activities of the United Nations, Other International Organizations and Third States in and in relation to the Occupied Palestinian Territory (Request for Advisory Opinion) - Filing of written statements and opening date of the public hearings\nAvailable in:\n\nEnglish\nFrench\n\n\n\n\n\n                  Press release 2025/9\n                \n\n\n                20 \n                February \n                2025\n              \nObligations of Israel in relation to the Presence and Activities of the United Nations, Other International Organizations and Third States in and in relation to the Occupied Palestinian Territory (Request for Advisory Opinion) - The Court authorizes the African Union to participate in the proceedings\nAvailable in:\n\nEnglish\nFrench\n\n\n\n\n\n                  Press release 2025/8\n                \n\n\n                7 \n                February \n                2025\n              \nObligations of Israel in relation to the Presence and Activities of the United Nations, Other International Organizations and Third States in and in relation to the Occupied Palestinian Territory (Request for Advisory Opinion) - The Court authorizes the League of Arab States to participate in the proceedings\nAvailable in:\n\nEnglish\nFrench\n\n\n\n\n\n                  Press release 2025/7\n                \n\n\n                4 \n                February \n                2025\n              \nObligations of Israel in relation to the Presence and Activities of the United Nations, Other International Organizations and Third States in and in relation to the Occupied Palestinian Territory (Request for Advisory Opinion) - The Court authorizes the Organisation of Islamic Cooperation to participate in the proceedings\nAvailable in:\n\nEnglish\nFrench\n\n\n\n\n\nPart II (F): Other documents without document symbols (documents received from the Secretariat of the United Nations)\n\n\n\n                30 \n                January \n                2025\n              \nPart II (F): Other documents without document symbols (documents received from the Secretariat of the United Nations)\nAvailable in:\n\nEnglish\nFrench\n\n\n\n\n\nPart II (E): Relevant instruments (documents received from the Secretariat of the United Nations)\n\n\n\n                30 \n                January \n                2025\n              \nPart II (E): Relevant instruments (documents received from the Secretariat of the United Nations)\nAvailable in:\n\nEnglish\nFrench\n\n\n\n\nPart II (D): Human rights documentation\n\n\n                30 \n                January \n                2025\n              \nPart II (D): Human rights documentation\n\n\n\nPart II (D) (1): General Assembly\n\n\nEnglish\nFrench\n\n\n\n\nPart II (D) (2): Human Rights Council\n\n\nEnglish\nFrench\n\n\n\n\nPart II (D) (3): Commission on Human Rights\n\n\nEnglish\nFrench\n\n\n\n\nPart II (D) (4): Treaty bodies\n\n\nEnglish\nFrench\n\n\n\n\nPart II (D) (5): Universal periodic review\n\n\nEnglish\nFrench\n\n\n\n\n\n\nPart II (C) - Security Council (documents received from the Secretariat of the United Nations)\n\n\n                30 \n                January \n                2025\n              \nPart II (C) - Security Council (documents received from the Secretariat of the United Nations)\n\n\n\nPart II (C) (1): Documentation relating to the situation in the Occupied Palestinian Territories\n\n\nEnglish\nFrench\n\n\n\n\nPart II (C) (2): Documentation relating to the safety and security of humanitarian personnel and United Nations and associated personnel\n\n\nEnglish\nFrench\n\n\n\n\n\n\n\nPart II (B) - General Assembly Emergency Special Sessions (documents received from the Secretariat of the United Nations)\n\n\n\n                30 \n                January \n                2025\n              \nPart II (B) - General Assembly Emergency Special Sessions (documents received from the Secretariat of the United Nations)\nAvailable in:\n\nEnglish\nFrench\n\n\n\n\nPart II (A) - Material of the United Nations Relating to the Questions before the Court (documents received from the Secretariat of the United Nations)\n\n\n                30 \n                January \n                2025\n              \nPart II (A) - Material of the United Nations Relating to the Questions before the Court (documents received from the Secretariat of the United Nations)\n\n\n\nPart II (A) (1): Israeli settlements\n\n\nEnglish\nFrench\n\n\n\n\nPart II (A) (2): Living conditions of the Palestinian people\n\n\nEnglish\nFrench\n\n\n\n\nPart II (A) (3): Palestinian women and children\n\n\nEnglish\nFrench\n\n\n\n\nPart II (A) (4): Permanent sovereignty over natural and national resources\n\n\nEnglish\nFrench\n\n\n\n\nPart II (A) (5): Right to self-determination\n\n\nEnglish\nFrench\n\n\n\n\nPart II (A) (6): Question of Palestine\n\n\nEnglish\nFrench\n\n\n\n\nPart II (A) (7): Situation in the Middle East\n\n\nEnglish\nFrench\n\n\n\n\nPart II (A) (8): Special Committee to investigate Israeli practices affecting the human rights of the Palestinian people\n\n\nEnglish\nFrench\n\n\n\n\nPart II (A) (9): United Nations Relief and Works Agency for Palestine refugees in the Near East (UNRWA)\n\n\nEnglish\nFrench\n\n\n\n\nPart II (A) (10): Assistance to the Palestinian people\n\n\nEnglish\nFrench\n\n\n\n\nPart II (A) (11): Safety and security of humanitarian personnel and protection of United Nations personnel\n\n\nEnglish\nFrench\n\n\n\n\n\n\n\nPart I: Material relating to the request by the General Assembly for an advisory opinion of the Court\n\n\n\n                30 \n                January \n                2025\n              \nPart I: Material relating to the request by the General Assembly for an advisory opinion of the Court\nAvailable in:\n\nEnglish\nFrench\n\n\n\n\n\nList of Documents (documents received from the Secretariat of the United Nations)\n\n\n\n                30 \n                January \n                2025\n              \nList of Documents (documents received from the Secretariat of the United Nations)\nAvailable in:\n\nEnglish\nFrench\n\n\n\n\n\nIntroductory Note (documents received from the Secretariat of the United Nations)\n\n\n\n                30 \n                January \n                2025\n              \nIntroductory Note (documents received from the Secretariat of the United Nations)\nAvailable in:\n\nEnglish\nFrench\n\n\n\n\n\n                  Press release 2024/86\n                \n\n\n                24 \n                December \n                2024\n              \nObligations of Israel in relation to the presence and activities of the United Nations, other international organizations and third States in and in relation to the Occupied Palestinian Territory (Request for Advisory Opinion) - The President of the Court makes an Order organizing the proceedings and fixes the time-limits for the presentation of written statements\nAvailable in:\n\nEnglish\nFrench\n\n\n\n\n\nOrder of 23 December 2024\n\n\nFixing of time-limits: Presentation of written statements\nAvailable in:\n\nEnglish\nFrench\n\n\n\n\n\n                  Press release 2024/84\n                \n\n\n                23 \n                December \n                2024\n              \nThe General Assembly of the United Nations requests an advisory opinion from the Court on “the obligations of Israel in relation to the presence and activities of the United Nations, other international organizations and third States” in and in relation to the Occupied Palestinian Territory\nAvailable in:\n\nEnglish\nFrench\n\n\n\n\n\nRequest for Advisory Opinion\n\n\n\n                23 \n                December \n                2024\n              \nRequest for Advisory Opinion\nAvailable in:\n\nEnglish\nFrench\n\n\n\n\n\n\n\n\n\n\n\n\n\n\n\n\nLinks\n\nObligations of Israel in relation to the Presence and Activities of the United Nations, Other International Organizations and Third States in and in relation to the Occupied Palestinian Territory\n\n\n\n\n\nLatest Developments\n\n\n\n                  Press release 2025/13\n                \n\n\n                12 \n                March \n                2025\n              \nObligations of Israel in relation to the Presence and Activities of the United Nations, Other International Organizations and Third States in and in relation to the Occupied Palestinian Territory (Request for Advisory Opinion) - Filing of written statements and opening date of the public hearings\nAvailable in:\n\nEnglish\nFrench\n\n\n\n\n\n                  Press release 2025/9\n                \n\n\n                20 \n                February \n                2025\n              \nObligations of Israel in relation to the Presence and Activities of the United Nations, Other International Organizations and Third States in and in relation to the Occupied Palestinian Territory (Request for Advisory Opinion) - The Court authorizes the African Union to participate in the proceedings\nAvailable in:\n\nEnglish\nFrench\n\n\n\n\n\n                  Press release 2025/8\n                \n\n\n                7 \n                February \n                2025\n              \nObligations of Israel in relation to the Presence and Activities of the United Nations, Other International Organizations and Third States in and in relation to the Occupied Palestinian Territory (Request for Advisory Opinion) - The Court authorizes the League of Arab States to participate in the proceedings\nAvailable in:\n\nEnglish\nFrench\n\n\n\n\n\n                  Press release 2025/7\n                \n\n\n                4 \n                February \n                2025\n              \nObligations of Israel in relation to the Presence and Activities of the United Nations, Other International Organizations and Third States in and in relation to the Occupied Palestinian Territory (Request for Advisory Opinion) - The Court authorizes the Organisation of Islamic Cooperation to participate in the proceedings\nAvailable in:\n\nEnglish\nFrench\n\n\n\n\n\nPart II (F): Other documents without document symbols (documents received from the Secretariat of the United Nations)\n\n\n\n                30 \n                January \n                2025\n              \nPart II (F): Other documents without document symbols (documents received from the Secretariat of the United Nations)\nAvailable in:\n\nEnglish\nFrench\n\n\n\n\n\nPart II (E): Relevant instruments (documents received from the Secretariat of the United Nations)\n\n\n\n                30 \n                January \n                2025\n              \nPart II (E): Relevant instruments (documents received from the Secretariat of the United Nations)\nAvailable in:\n\nEnglish\nFrench\n\n\n\n\nPart II (D): Human rights documentation\n\n\n                30 \n                January \n                2025\n              \nPart II (D): Human rights documentation\n\n\n\nPart II (D) (1): General Assembly\n\n\nEnglish\nFrench\n\n\n\n\nPart II (D) (2): Human Rights Council\n\n\nEnglish\nFrench\n\n\n\n\nPart II (D) (3): Commission on Human Rights\n\n\nEnglish\nFrench\n\n\n\n\nPart II (D) (4): Treaty bodies\n\n\nEnglish\nFrench\n\n\n\n\nPart II (D) (5): Universal periodic review\n\n\nEnglish\nFrench\n\n\n\n\n\n\nPart II (C) - Security Council (documents received from the Secretariat of the United Nations)\n\n\n                30 \n                January \n                2025\n              \nPart II (C) - Security Council (documents received from the Secretariat of the United Nations)\n\n\n\nPart II (C) (1): Documentation relating to the situation in the Occupied Palestinian Territories\n\n\nEnglish\nFrench\n\n\n\n\nPart II (C) (2): Documentation relating to the safety and security of humanitarian personnel and United Nations and associated personnel\n\n\nEnglish\nFrench\n\n\n\n\n\n\n\nPart II (B) - General Assembly Emergency Special Sessions (documents received from the Secretariat of the United Nations)\n\n\n\n                30 \n                January \n                2025\n              \nPart II (B) - General Assembly Emergency Special Sessions (documents received from the Secretariat of the United Nations)\nAvailable in:\n\nEnglish\nFrench\n\n\n\n\nPart II (A) - Material of the United Nations Relating to the Questions before the Court (documents received from the Secretariat of the United Nations)\n\n\n                30 \n                January \n                2025\n              \nPart II (A) - Material of the United Nations Relating to the Questions before the Court (documents received from the Secretariat of the United Nations)\n\n\n\nPart II (A) (1): Israeli settlements\n\n\nEnglish\nFrench\n\n\n\n\nPart II (A) (2): Living conditions of the Palestinian people\n\n\nEnglish\nFrench\n\n\n\n\nPart II (A) (3): Palestinian women and children\n\n\nEnglish\nFrench\n\n\n\n\nPart II (A) (4): Permanent sovereignty over natural and national resources\n\n\nEnglish\nFrench\n\n\n\n\nPart II (A) (5): Right to self-determination\n\n\nEnglish\nFrench\n\n\n\n\nPart II (A) (6): Question of Palestine\n\n\nEnglish\nFrench\n\n\n\n\nPart II (A) (7): Situation in the Middle East\n\n\nEnglish\nFrench\n\n\n\n\nPart II (A) (8): Special Committee to investigate Israeli practices affecting the human rights of the Palestinian people\n\n\nEnglish\nFrench\n\n\n\n\nPart II (A) (9): United Nations Relief and Works Agency for Palestine refugees in the Near East (UNRWA)\n\n\nEnglish\nFrench\n\n\n\n\nPart II (A) (10): Assistance to the Palestinian people\n\n\nEnglish\nFrench\n\n\n\n\nPart II (A) (11): Safety and security of humanitarian personnel and protection of United Nations personnel\n\n\nEnglish\nFrench\n\n\n\n\n\n\n\nPart I: Material relating to the request by the General Assembly for an advisory opinion of the Court\n\n\n\n                30 \n                January \n                2025\n              \nPart I: Material relating to the request by the General Assembly for an advisory opinion of the Court\nAvailable in:\n\nEnglish\nFrench\n\n\n\n\n\nList of Documents (documents received from the Secretariat of the United Nations)\n\n\n\n                30 \n                January \n                2025\n              \nList of Documents (documents received from the Secretariat of the United Nations)\nAvailable in:\n\nEnglish\nFrench\n\n\n\n\n\nIntroductory Note (documents received from the Secretariat of the United Nations)\n\n\n\n                30 \n                January \n                2025\n              \nIntroductory Note (documents received from the Secretariat of the United Nations)\nAvailable in:\n\nEnglish\nFrench\n\n\n\n\n\n                  Press release 2024/86\n                \n\n\n                24 \n                December \n                2024\n              \nObligations of Israel in relation to the presence and activities of the United Nations, other international organizations and third States in and in relation to the Occupied Palestinian Territory (Request for Advisory Opinion) - The President of the Court makes an Order organizing the proceedings and fixes the time-limits for the presentation of written statements\nAvailable in:\n\nEnglish\nFrench\n\n\n\n\n\nOrder of 23 December 2024\n\n\nFixing of time-limits: Presentation of written statements\nAvailable in:\n\nEnglish\nFrench\n\n\n\n\n\n                  Press release 2024/84\n                \n\n\n                23 \n                December \n                2024\n              \nThe General Assembly of the United Nations requests an advisory opinion from the Court on “the obligations of Israel in relation to the presence and activities of the United Nations, other international organizations and third States” in and in relation to the Occupied Palestinian Territory\nAvailable in:\n\nEnglish\nFrench\n\n\n\n\n\nRequest for Advisory Opinion\n\n\n\n                23 \n                December \n                2024\n              \nRequest for Advisory Opinion\nAvailable in:\n\nEnglish\nFrench\n\n\n\n\n\n\n\n\n\n\n\n\n\n\n\n\nLinks\n\nObligations of Israel in relation to the Presence and Activities of the United Nations, Other International Organizations and Third States in and in relation to the Occupied Palestinian Territory\n\n\n\n\n\nLatest Developments\n\n\n\n                  Press release 2025/13\n                \n\n\n                12 \n                March \n                2025\n              \nObligations of Israel in relation to the Presence and Activities of the United Nations, Other International Organizations and Third States in and in relation to the Occupied Palestinian Territory (Request for Advisory Opinion) - Filing of written statements and opening date of the public hearings\nAvailable in:\n\nEnglish\nFrench\n\n\n\n\n\n                  Press release 2025/9\n                \n\n\n                20 \n                February \n                2025\n              \nObligations of Israel in relation to the Presence and Activities of the United Nations, Other International Organizations and Third States in and in relation to the Occupied Palestinian Territory (Request for Advisory Opinion) - The Court authorizes the African Union to participate in the proceedings\nAvailable in:\n\nEnglish\nFrench\n\n\n\n\n\n                  Press release 2025/8\n                \n\n\n                7 \n                February \n                2025\n              \nObligations of Israel in relation to the Presence and Activities of the United Nations, Other International Organizations and Third States in and in relation to the Occupied Palestinian Territory (Request for Advisory Opinion) - The Court authorizes the League of Arab States to participate in the proceedings\nAvailable in:\n\nEnglish\nFrench\n\n\n\n\n\n                  Press release 2025/7\n                \n\n\n                4 \n                February \n                2025\n              \nObligations of Israel in relation to the Presence and Activities of the United Nations, Other International Organizations and Third States in and in relation to the Occupied Palestinian Territory (Request for Advisory Opinion) - The Court authorizes the Organisation of Islamic Cooperation to participate in the proceedings\nAvailable in:\n\nEnglish\nFrench\n\n\n\n\n\nPart II (F): Other documents without document symbols (documents received from the Secretariat of the United Nations)\n\n\n\n                30 \n                January \n                2025\n              \nPart II (F): Other documents without document symbols (documents received from the Secretariat of the United Nations)\nAvailable in:\n\nEnglish\nFrench\n\n\n\n\n\nPart II (E): Relevant instruments (documents received from the Secretariat of the United Nations)\n\n\n\n                30 \n                January \n                2025\n              \nPart II (E): Relevant instruments (documents received from the Secretariat of the United Nations)\nAvailable in:\n\nEnglish\nFrench\n\n\n\n\nPart II (D): Human rights documentation\n\n\n                30 \n                January \n                2025\n              \nPart II (D): Human rights documentation\n\n\n\nPart II (D) (1): General Assembly\n\n\nEnglish\nFrench\n\n\n\n\nPart II (D) (2): Human Rights Council\n\n\nEnglish\nFrench\n\n\n\n\nPart II (D) (3): Commission on Human Rights\n\n\nEnglish\nFrench\n\n\n\n\nPart II (D) (4): Treaty bodies\n\n\nEnglish\nFrench\n\n\n\n\nPart II (D) (5): Universal periodic review\n\n\nEnglish\nFrench\n\n\n\n\n\n\nPart II (C) - Security Council (documents received from the Secretariat of the United Nations)\n\n\n                30 \n                January \n                2025\n              \nPart II (C) - Security Council (documents received from the Secretariat of the United Nations)\n\n\n\nPart II (C) (1): Documentation relating to the situation in the Occupied Palestinian Territories\n\n\nEnglish\nFrench\n\n\n\n\nPart II (C) (2): Documentation relating to the safety and security of humanitarian personnel and United Nations and associated personnel\n\n\nEnglish\nFrench\n\n\n\n\n\n\n\nPart II (B) - General Assembly Emergency Special Sessions (documents received from the Secretariat of the United Nations)\n\n\n\n                30 \n                January \n                2025\n              \nPart II (B) - General Assembly Emergency Special Sessions (documents received from the Secretariat of the United Nations)\nAvailable in:\n\nEnglish\nFrench\n\n\n\n\nPart II (A) - Material of the United Nations Relating to the Questions before the Court (documents received from the Secretariat of the United Nations)\n\n\n                30 \n                January \n                2025\n              \nPart II (A) - Material of the United Nations Relating to the Questions before the Court (documents received from the Secretariat of the United Nations)\n\n\n\nPart II (A) (1): Israeli settlements\n\n\nEnglish\nFrench\n\n\n\n\nPart II (A) (2): Living conditions of the Palestinian people\n\n\nEnglish\nFrench\n\n\n\n\nPart II (A) (3): Palestinian women and children\n\n\nEnglish\nFrench\n\n\n\n\nPart II (A) (4): Permanent sovereignty over natural and national resources\n\n\nEnglish\nFrench\n\n\n\n\nPart II (A) (5): Right to self-determination\n\n\nEnglish\nFrench\n\n\n\n\nPart II (A) (6): Question of Palestine\n\n\nEnglish\nFrench\n\n\n\n\nPart II (A) (7): Situation in the Middle East\n\n\nEnglish\nFrench\n\n\n\n\nPart II (A) (8): Special Committee to investigate Israeli practices affecting the human rights of the Palestinian people\n\n\nEnglish\nFrench\n\n\n\n\nPart II (A) (9): United Nations Relief and Works Agency for Palestine refugees in the Near East (UNRWA)\n\n\nEnglish\nFrench\n\n\n\n\nPart II (A) (10): Assistance to the Palestinian people\n\n\nEnglish\nFrench\n\n\n\n\nPart II (A) (11): Safety and security of humanitarian personnel and protection of United Nations personnel\n\n\nEnglish\nFrench\n\n\n\n\n\n\n\nPart I: Material relating to the request by the General Assembly for an advisory opinion of the Court\n\n\n\n                30 \n                January \n                2025\n              \nPart I: Material relating to the request by the General Assembly for an advisory opinion of the Court\nAvailable in:\n\nEnglish\nFrench\n\n\n\n\n\nList of Documents (documents received from the Secretariat of the United Nations)\n\n\n\n                30 \n                January \n                2025\n              \nList of Documents (documents received from the Secretariat of the United Nations)\nAvailable in:\n\nEnglish\nFrench\n\n\n\n\n\nIntroductory Note (documents received from the Secretariat of the United Nations)\n\n\n\n                30 \n                January \n                2025\n              \nIntroductory Note (documents received from the Secretariat of the United Nations)\nAvailable in:\n\nEnglish\nFrench\n\n\n\n\n\n                  Press release 2024/86\n                \n\n\n                24 \n                December \n                2024\n              \nObligations of Israel in relation to the presence and activities of the United Nations, other international organizations and third States in and in relation to the Occupied Palestinian Territory (Request for Advisory Opinion) - The President of the Court makes an Order organizing the proceedings and fixes the time-limits for the presentation of written statements\nAvailable in:\n\nEnglish\nFrench\n\n\n\n\n\nOrder of 23 December 2024\n\n\nFixing of time-limits: Presentation of written statements\nAvailable in:\n\nEnglish\nFrench\n\n\n\n\n\n                  Press release 2024/84\n                \n\n\n                23 \n                December \n                2024\n              \nThe General Assembly of the United Nations requests an advisory opinion from the Court on “the obligations of Israel in relation to the presence and activities of the United Nations, other international organizations and third States” in and in relation to the Occupied Palestinian Territory\nAvailable in:\n\nEnglish\nFrench\n\n\n\n\n\nRequest for Advisory Opinion\n\n\n\n                23 \n                December \n                2024\n              \nRequest for Advisory Opinion\nAvailable in:\n\nEnglish\nFrench\n\n\n\n\n\n\n\n\n\n\n\n\n\n\n\n\nLinks\n\nObligations of Israel in relation to the Presence and Activities of the United Nations, Other International Organizations and Third States in and in relation to the Occupied Palestinian Territory\n\n\n\n\n\nLatest Developments\n\n\n\n                  Press release 2025/13\n                \n\n\n                12 \n                March \n                2025\n              \nObligations of Israel in relation to the Presence and Activities of the United Nations, Other International Organizations and Third States in and in relation to the Occupied Palestinian Territory (Request for Advisory Opinion) - Filing of written statements and opening date of the public hearings\nAvailable in:\n\nEnglish\nFrench\n\n\n\n\n\n                  Press release 2025/9\n                \n\n\n                20 \n                February \n                2025\n              \nObligations of Israel in relation to the Presence and Activities of the United Nations, Other International Organizations and Third States in and in relation to the Occupied Palestinian Territory (Request for Advisory Opinion) - The Court authorizes the African Union to participate in the proceedings\nAvailable in:\n\nEnglish\nFrench\n\n\n\n\n\n                  Press release 2025/8\n                \n\n\n                7 \n                February \n                2025\n              \nObligations of Israel in relation to the Presence and Activities of the United Nations, Other International Organizations and Third States in and in relation to the Occupied Palestinian Territory (Request for Advisory Opinion) - The Court authorizes the League of Arab States to participate in the proceedings\nAvailable in:\n\nEnglish\nFrench\n\n\n\n\n\n                  Press release 2025/7\n                \n\n\n                4 \n                February \n                2025\n              \nObligations of Israel in relation to the Presence and Activities of the United Nations, Other International Organizations and Third States in and in relation to the Occupied Palestinian Territory (Request for Advisory Opinion) - The Court authorizes the Organisation of Islamic Cooperation to participate in the proceedings\nAvailable in:\n\nEnglish\nFrench\n\n\n\n\n\nPart II (F): Other documents without document symbols (documents received from the Secretariat of the United Nations)\n\n\n\n                30 \n                January \n                2025\n              \nPart II (F): Other documents without document symbols (documents received from the Secretariat of the United Nations)\nAvailable in:\n\nEnglish\nFrench\n\n\n\n\n\nPart II (E): Relevant instruments (documents received from the Secretariat of the United Nations)\n\n\n\n                30 \n                January \n                2025\n              \nPart II (E): Relevant instruments (documents received from the Secretariat of the United Nations)\nAvailable in:\n\nEnglish\nFrench\n\n\n\n\nPart II (D): Human rights documentation\n\n\n                30 \n                January \n                2025\n              \nPart II (D): Human rights documentation\n\n\n\nPart II (D) (1): General Assembly\n\n\nEnglish\nFrench\n\n\n\n\nPart II (D) (2): Human Rights Council\n\n\nEnglish\nFrench\n\n\n\n\nPart II (D) (3): Commission on Human Rights\n\n\nEnglish\nFrench\n\n\n\n\nPart II (D) (4): Treaty bodies\n\n\nEnglish\nFrench\n\n\n\n\nPart II (D) (5): Universal periodic review\n\n\nEnglish\nFrench\n\n\n\n\n\n\nPart II (C) - Security Council (documents received from the Secretariat of the United Nations)\n\n\n                30 \n                January \n                2025\n              \nPart II (C) - Security Council (documents received from the Secretariat of the United Nations)\n\n\n\nPart II (C) (1): Documentation relating to the situation in the Occupied Palestinian Territories\n\n\nEnglish\nFrench\n\n\n\n\nPart II (C) (2): Documentation relating to the safety and security of humanitarian personnel and United Nations and associated personnel\n\n\nEnglish\nFrench\n\n\n\n\n\n\n\nPart II (B) - General Assembly Emergency Special Sessions (documents received from the Secretariat of the United Nations)\n\n\n\n                30 \n                January \n                2025\n              \nPart II (B) - General Assembly Emergency Special Sessions (documents received from the Secretariat of the United Nations)\nAvailable in:\n\nEnglish\nFrench\n\n\n\n\nPart II (A) - Material of the United Nations Relating to the Questions before the Court (documents received from the Secretariat of the United Nations)\n\n\n                30 \n                January \n                2025\n              \nPart II (A) - Material of the United Nations Relating to the Questions before the Court (documents received from the Secretariat of the United Nations)\n\n\n\nPart II (A) (1): Israeli settlements\n\n\nEnglish\nFrench\n\n\n\n\nPart II (A) (2): Living conditions of the Palestinian people\n\n\nEnglish\nFrench\n\n\n\n\nPart II (A) (3): Palestinian women and children\n\n\nEnglish\nFrench\n\n\n\n\nPart II (A) (4): Permanent sovereignty over natural and national resources\n\n\nEnglish\nFrench\n\n\n\n\nPart II (A) (5): Right to self-determination\n\n\nEnglish\nFrench\n\n\n\n\nPart II (A) (6): Question of Palestine\n\n\nEnglish\nFrench\n\n\n\n\nPart II (A) (7): Situation in the Middle East\n\n\nEnglish\nFrench\n\n\n\n\nPart II (A) (8): Special Committee to investigate Israeli practices affecting the human rights of the Palestinian people\n\n\nEnglish\nFrench\n\n\n\n\nPart II (A) (9): United Nations Relief and Works Agency for Palestine refugees in the Near East (UNRWA)\n\n\nEnglish\nFrench\n\n\n\n\nPart II (A) (10): Assistance to the Palestinian people\n\n\nEnglish\nFrench\n\n\n\n\nPart II (A) (11): Safety and security of humanitarian personnel and protection of United Nations personnel\n\n\nEnglish\nFrench\n\n\n\n\n\n\n\nPart I: Material relating to the request by the General Assembly for an advisory opinion of the Court\n\n\n\n                30 \n                January \n                2025\n              \nPart I: Material relating to the request by the General Assembly for an advisory opinion of the Court\nAvailable in:\n\nEnglish\nFrench\n\n\n\n\n\nList of Documents (documents received from the Secretariat of the United Nations)\n\n\n\n                30 \n                January \n                2025\n              \nList of Documents (documents received from the Secretariat of the United Nations)\nAvailable in:\n\nEnglish\nFrench\n\n\n\n\n\nIntroductory Note (documents received from the Secretariat of the United Nations)\n\n\n\n                30 \n                January \n                2025\n              \nIntroductory Note (documents received from the Secretariat of the United Nations)\nAvailable in:\n\nEnglish\nFrench\n\n\n\n\n\n                  Press release 2024/86\n                \n\n\n                24 \n                December \n                2024\n              \nObligations of Israel in relation to the presence and activities of the United Nations, other international organizations and third States in and in relation to the Occupied Palestinian Territory (Request for Advisory Opinion) - The President of the Court makes an Order organizing the proceedings and fixes the time-limits for the presentation of written statements\nAvailable in:\n\nEnglish\nFrench\n\n\n\n\n\nOrder of 23 December 2024\n\n\nFixing of time-limits: Presentation of written statements\nAvailable in:\n\nEnglish\nFrench\n\n\n\n\n\n                  Press release 2024/84\n                \n\n\n                23 \n                December \n                2024\n              \nThe General Assembly of the United Nations requests an advisory opinion from the Court on “the obligations of Israel in relation to the presence and activities of the United Nations, other international organizations and third States” in and in relation to the Occupied Palestinian Territory\nAvailable in:\n\nEnglish\nFrench\n\n\n\n\n\nRequest for Advisory Opinion\n\n\n\n                23 \n                December \n                2024\n              \nRequest for Advisory Opinion\nAvailable in:\n\nEnglish\nFrench\n\nObligations of Israel in relation to the Presence and Activities of the United Nations, Other International Organizations and Third States in and in relation to the Occupied Palestinian Territory\n\n\n\n\n\nLatest Developments\n\n\n\n                  Press release 2025/13\n                \n\n\n                12 \n                March \n                2025\n              \nObligations of Israel in relation to the Presence and Activities of the United Nations, Other International Organizations and Third States in and in relation to the Occupied Palestinian Territory (Request for Advisory Opinion) - Filing of written statements and opening date of the public hearings\nAvailable in:\n\nEnglish\nFrench\n\n\n\n\n\n                  Press release 2025/9\n                \n\n\n                20 \n                February \n                2025\n              \nObligations of Israel in relation to the Presence and Activities of the United Nations, Other International Organizations and Third States in and in relation to the Occupied Palestinian Territory (Request for Advisory Opinion) - The Court authorizes the African Union to participate in the proceedings\nAvailable in:\n\nEnglish\nFrench\n\n\n\n\n\n                  Press release 2025/8\n                \n\n\n                7 \n                February \n                2025\n              \nObligations of Israel in relation to the Presence and Activities of the United Nations, Other International Organizations and Third States in and in relation to the Occupied Palestinian Territory (Request for Advisory Opinion) - The Court authorizes the League of Arab States to participate in the proceedings\nAvailable in:\n\nEnglish\nFrench\n\n\n\n\n\n                  Press release 2025/7\n                \n\n\n                4 \n                February \n                2025\n              \nObligations of Israel in relation to the Presence and Activities of the United Nations, Other International Organizations and Third States in and in relation to the Occupied Palestinian Territory (Request for Advisory Opinion) - The Court authorizes the Organisation of Islamic Cooperation to participate in the proceedings\nAvailable in:\n\nEnglish\nFrench\n\n\n\n\n\nPart II (F): Other documents without document symbols (documents received from the Secretariat of the United Nations)\n\n\n\n                30 \n                January \n                2025\n              \nPart II (F): Other documents without document symbols (documents received from the Secretariat of the United Nations)\nAvailable in:\n\nEnglish\nFrench\n\n\n\n\n\nPart II (E): Relevant instruments (documents received from the Secretariat of the United Nations)\n\n\n\n                30 \n                January \n                2025\n              \nPart II (E): Relevant instruments (documents received from the Secretariat of the United Nations)\nAvailable in:\n\nEnglish\nFrench\n\n\n\n\nPart II (D): Human rights documentation\n\n\n                30 \n                January \n                2025\n              \nPart II (D): Human rights documentation\n\n\n\nPart II (D) (1): General Assembly\n\n\nEnglish\nFrench\n\n\n\n\nPart II (D) (2): Human Rights Council\n\n\nEnglish\nFrench\n\n\n\n\nPart II (D) (3): Commission on Human Rights\n\n\nEnglish\nFrench\n\n\n\n\nPart II (D) (4): Treaty bodies\n\n\nEnglish\nFrench\n\n\n\n\nPart II (D) (5): Universal periodic review\n\n\nEnglish\nFrench\n\n\n\n\n\n\nPart II (C) - Security Council (documents received from the Secretariat of the United Nations)\n\n\n                30 \n                January \n                2025\n              \nPart II (C) - Security Council (documents received from the Secretariat of the United Nations)\n\n\n\nPart II (C) (1): Documentation relating to the situation in the Occupied Palestinian Territories\n\n\nEnglish\nFrench\n\n\n\n\nPart II (C) (2): Documentation relating to the safety and security of humanitarian personnel and United Nations and associated personnel\n\n\nEnglish\nFrench\n\n\n\n\n\n\n\nPart II (B) - General Assembly Emergency Special Sessions (documents received from the Secretariat of the United Nations)\n\n\n\n                30 \n                January \n                2025\n              \nPart II (B) - General Assembly Emergency Special Sessions (documents received from the Secretariat of the United Nations)\nAvailable in:\n\nEnglish\nFrench\n\n\n\n\nPart II (A) - Material of the United Nations Relating to the Questions before the Court (documents received from the Secretariat of the United Nations)\n\n\n                30 \n                January \n                2025\n              \nPart II (A) - Material of the United Nations Relating to the Questions before the Court (documents received from the Secretariat of the United Nations)\n\n\n\nPart II (A) (1): Israeli settlements\n\n\nEnglish\nFrench\n\n\n\n\nPart II (A) (2): Living conditions of the Palestinian people\n\n\nEnglish\nFrench\n\n\n\n\nPart II (A) (3): Palestinian women and children\n\n\nEnglish\nFrench\n\n\n\n\nPart II (A) (4): Permanent sovereignty over natural and national resources\n\n\nEnglish\nFrench\n\n\n\n\nPart II (A) (5): Right to self-determination\n\n\nEnglish\nFrench\n\n\n\n\nPart II (A) (6): Question of Palestine\n\n\nEnglish\nFrench\n\n\n\n\nPart II (A) (7): Situation in the Middle East\n\n\nEnglish\nFrench\n\n\n\n\nPart II (A) (8): Special Committee to investigate Israeli practices affecting the human rights of the Palestinian people\n\n\nEnglish\nFrench\n\n\n\n\nPart II (A) (9): United Nations Relief and Works Agency for Palestine refugees in the Near East (UNRWA)\n\n\nEnglish\nFrench\n\n\n\n\nPart II (A) (10): Assistance to the Palestinian people\n\n\nEnglish\nFrench\n\n\n\n\nPart II (A) (11): Safety and security of humanitarian personnel and protection of United Nations personnel\n\n\nEnglish\nFrench\n\n\n\n\n\n\n\nPart I: Material relating to the request by the General Assembly for an advisory opinion of the Court\n\n\n\n                30 \n                January \n                2025\n              \nPart I: Material relating to the request by the General Assembly for an advisory opinion of the Court\nAvailable in:\n\nEnglish\nFrench\n\n\n\n\n\nList of Documents (documents received from the Secretariat of the United Nations)\n\n\n\n                30 \n                January \n                2025\n              \nList of Documents (documents received from the Secretariat of the United Nations)\nAvailable in:\n\nEnglish\nFrench\n\n\n\n\n\nIntroductory Note (documents received from the Secretariat of the United Nations)\n\n\n\n                30 \n                January \n                2025\n              \nIntroductory Note (documents received from the Secretariat of the United Nations)\nAvailable in:\n\nEnglish\nFrench\n\n\n\n\n\n                  Press release 2024/86\n                \n\n\n                24 \n                December \n                2024\n              \nObligations of Israel in relation to the presence and activities of the United Nations, other international organizations and third States in and in relation to the Occupied Palestinian Territory (Request for Advisory Opinion) - The President of the Court makes an Order organizing the proceedings and fixes the time-limits for the presentation of written statements\nAvailable in:\n\nEnglish\nFrench\n\n\n\n\n\nOrder of 23 December 2024\n\n\nFixing of time-limits: Presentation of written statements\nAvailable in:\n\nEnglish\nFrench\n\n\n\n\n\n                  Press release 2024/84\n                \n\n\n                23 \n                December \n                2024\n              \nThe General Assembly of the United Nations requests an advisory opinion from the Court on “the obligations of Israel in relation to the presence and activities of the United Nations, other international organizations and third States” in and in relation to the Occupied Palestinian Territory\nAvailable in:\n\nEnglish\nFrench\n\n\n\n\n\nRequest for Advisory Opinion\n\n\n\n                23 \n                December \n                2024\n              \nRequest for Advisory Opinion\nAvailable in:\n\nEnglish\nFrench\n\nObligations of Israel in relation to the Presence and Activities of the United Nations, Other International Organizations and Third States in and in relation to the Occupied Palestinian Territory\n\n\n\n\n\nLatest Developments\n\n\n\n                  Press release 2025/13\n                \n\n\n                12 \n                March \n                2025\n              \nObligations of Israel in relation to the Presence and Activities of the United Nations, Other International Organizations and Third States in and in relation to the Occupied Palestinian Territory (Request for Advisory Opinion) - Filing of written statements and opening date of the public hearings\nAvailable in:\n\nEnglish\nFrench\n\n\n\n\n\n                  Press release 2025/9\n                \n\n\n                20 \n                February \n                2025\n              \nObligations of Israel in relation to the Presence and Activities of the United Nations, Other International Organizations and Third States in and in relation to the Occupied Palestinian Territory (Request for Advisory Opinion) - The Court authorizes the African Union to participate in the proceedings\nAvailable in:\n\nEnglish\nFrench\n\n\n\n\n\n                  Press release 2025/8\n                \n\n\n                7 \n                February \n                2025\n              \nObligations of Israel in relation to the Presence and Activities of the United Nations, Other International Organizations and Third States in and in relation to the Occupied Palestinian Territory (Request for Advisory Opinion) - The Court authorizes the League of Arab States to participate in the proceedings\nAvailable in:\n\nEnglish\nFrench\n\n\n\n\n\n                  Press release 2025/7\n                \n\n\n                4 \n                February \n                2025\n              \nObligations of Israel in relation to the Presence and Activities of the United Nations, Other International Organizations and Third States in and in relation to the Occupied Palestinian Territory (Request for Advisory Opinion) - The Court authorizes the Organisation of Islamic Cooperation to participate in the proceedings\nAvailable in:\n\nEnglish\nFrench\n\n\n\n\n\nPart II (F): Other documents without document symbols (documents received from the Secretariat of the United Nations)\n\n\n\n                30 \n                January \n                2025\n              \nPart II (F): Other documents without document symbols (documents received from the Secretariat of the United Nations)\nAvailable in:\n\nEnglish\nFrench\n\n\n\n\n\nPart II (E): Relevant instruments (documents received from the Secretariat of the United Nations)\n\n\n\n                30 \n                January \n                2025\n              \nPart II (E): Relevant instruments (documents received from the Secretariat of the United Nations)\nAvailable in:\n\nEnglish\nFrench\n\n\n\n\nPart II (D): Human rights documentation\n\n\n                30 \n                January \n                2025\n              \nPart II (D): Human rights documentation\n\n\n\nPart II (D) (1): General Assembly\n\n\nEnglish\nFrench\n\n\n\n\nPart II (D) (2): Human Rights Council\n\n\nEnglish\nFrench\n\n\n\n\nPart II (D) (3): Commission on Human Rights\n\n\nEnglish\nFrench\n\n\n\n\nPart II (D) (4): Treaty bodies\n\n\nEnglish\nFrench\n\n\n\n\nPart II (D) (5): Universal periodic review\n\n\nEnglish\nFrench\n\n\n\n\n\n\nPart II (C) - Security Council (documents received from the Secretariat of the United Nations)\n\n\n                30 \n                January \n                2025\n              \nPart II (C) - Security Council (documents received from the Secretariat of the United Nations)\n\n\n\nPart II (C) (1): Documentation relating to the situation in the Occupied Palestinian Territories\n\n\nEnglish\nFrench\n\n\n\n\nPart II (C) (2): Documentation relating to the safety and security of humanitarian personnel and United Nations and associated personnel\n\n\nEnglish\nFrench\n\n\n\n\n\n\n\nPart II (B) - General Assembly Emergency Special Sessions (documents received from the Secretariat of the United Nations)\n\n\n\n                30 \n                January \n                2025\n              \nPart II (B) - General Assembly Emergency Special Sessions (documents received from the Secretariat of the United Nations)\nAvailable in:\n\nEnglish\nFrench\n\n\n\n\nPart II (A) - Material of the United Nations Relating to the Questions before the Court (documents received from the Secretariat of the United Nations)\n\n\n                30 \n                January \n                2025\n              \nPart II (A) - Material of the United Nations Relating to the Questions before the Court (documents received from the Secretariat of the United Nations)\n\n\n\nPart II (A) (1): Israeli settlements\n\n\nEnglish\nFrench\n\n\n\n\nPart II (A) (2): Living conditions of the Palestinian people\n\n\nEnglish\nFrench\n\n\n\n\nPart II (A) (3): Palestinian women and children\n\n\nEnglish\nFrench\n\n\n\n\nPart II (A) (4): Permanent sovereignty over natural and national resources\n\n\nEnglish\nFrench\n\n\n\n\nPart II (A) (5): Right to self-determination\n\n\nEnglish\nFrench\n\n\n\n\nPart II (A) (6): Question of Palestine\n\n\nEnglish\nFrench\n\n\n\n\nPart II (A) (7): Situation in the Middle East\n\n\nEnglish\nFrench\n\n\n\n\nPart II (A) (8): Special Committee to investigate Israeli practices affecting the human rights of the Palestinian people\n\n\nEnglish\nFrench\n\n\n\n\nPart II (A) (9): United Nations Relief and Works Agency for Palestine refugees in the Near East (UNRWA)\n\n\nEnglish\nFrench\n\n\n\n\nPart II (A) (10): Assistance to the Palestinian people\n\n\nEnglish\nFrench\n\n\n\n\nPart II (A) (11): Safety and security of humanitarian personnel and protection of United Nations personnel\n\n\nEnglish\nFrench\n\n\n\n\n\n\n\nPart I: Material relating to the request by the General Assembly for an advisory opinion of the Court\n\n\n\n                30 \n                January \n                2025\n              \nPart I: Material relating to the request by the General Assembly for an advisory opinion of the Court\nAvailable in:\n\nEnglish\nFrench\n\n\n\n\n\nList of Documents (documents received from the Secretariat of the United Nations)\n\n\n\n                30 \n                January \n                2025\n              \nList of Documents (documents received from the Secretariat of the United Nations)\nAvailable in:\n\nEnglish\nFrench\n\n\n\n\n\nIntroductory Note (documents received from the Secretariat of the United Nations)\n\n\n\n                30 \n                January \n                2025\n              \nIntroductory Note (documents received from the Secretariat of the United Nations)\nAvailable in:\n\nEnglish\nFrench\n\n\n\n\n\n                  Press release 2024/86\n                \n\n\n                24 \n                December \n                2024\n              \nObligations of Israel in relation to the presence and activities of the United Nations, other international organizations and third States in and in relation to the Occupied Palestinian Territory (Request for Advisory Opinion) - The President of the Court makes an Order organizing the proceedings and fixes the time-limits for the presentation of written statements\nAvailable in:\n\nEnglish\nFrench\n\n\n\n\n\nOrder of 23 December 2024\n\n\nFixing of time-limits: Presentation of written statements\nAvailable in:\n\nEnglish\nFrench\n\n\n\n\n\n                  Press release 2024/84\n                \n\n\n                23 \n                December \n                2024\n              \nThe General Assembly of the United Nations requests an advisory opinion from the Court on “the obligations of Israel in relation to the presence and activities of the United Nations, other international organizations and third States” in and in relation to the Occupied Palestinian Territory\nAvailable in:\n\nEnglish\nFrench\n\n\n\n\n\nRequest for Advisory Opinion\n\n\n\n                23 \n                December \n                2024\n              \nRequest for Advisory Opinion\nAvailable in:\n\nEnglish\nFrench\n\nObligations of Israel in relation to the Presence and Activities of the United Nations, Other International Organizations and Third States in and in relation to the Occupied Palestinian Territory\n\nObligations of Israel in relation to the Presence and Activities of the United Nations, Other International Organizations and Third States in and in relation to the Occupied Palestinian Territory\n\nObligations of Israel in relation to the Presence and Activities of the United Nations, Other International Organizations and Third States in and in relation to the Occupied Palestinian Territory\n\nLatest Developments\n\n\n\n                  Press release 2025/13\n                \n\n\n                12 \n                March \n                2025\n              \nObligations of Israel in relation to the Presence and Activities of the United Nations, Other International Organizations and Third States in and in relation to the Occupied Palestinian Territory (Request for Advisory Opinion) - Filing of written statements and opening date of the public hearings\nAvailable in:\n\nEnglish\nFrench\n\n\n\n\n\n                  Press release 2025/9\n                \n\n\n                20 \n                February \n                2025\n              \nObligations of Israel in relation to the Presence and Activities of the United Nations, Other International Organizations and Third States in and in relation to the Occupied Palestinian Territory (Request for Advisory Opinion) - The Court authorizes the African Union to participate in the proceedings\nAvailable in:\n\nEnglish\nFrench\n\n\n\n\n\n                  Press release 2025/8\n                \n\n\n                7 \n                February \n                2025\n              \nObligations of Israel in relation to the Presence and Activities of the United Nations, Other International Organizations and Third States in and in relation to the Occupied Palestinian Territory (Request for Advisory Opinion) - The Court authorizes the League of Arab States to participate in the proceedings\nAvailable in:\n\nEnglish\nFrench\n\n\n\n\n\n                  Press release 2025/7\n                \n\n\n                4 \n                February \n                2025\n              \nObligations of Israel in relation to the Presence and Activities of the United Nations, Other International Organizations and Third States in and in relation to the Occupied Palestinian Territory (Request for Advisory Opinion) - The Court authorizes the Organisation of Islamic Cooperation to participate in the proceedings\nAvailable in:\n\nEnglish\nFrench\n\n\n\n\n\nPart II (F): Other documents without document symbols (documents received from the Secretariat of the United Nations)\n\n\n\n                30 \n                January \n                2025\n              \nPart II (F): Other documents without document symbols (documents received from the Secretariat of the United Nations)\nAvailable in:\n\nEnglish\nFrench\n\n\n\n\n\nPart II (E): Relevant instruments (documents received from the Secretariat of the United Nations)\n\n\n\n                30 \n                January \n                2025\n              \nPart II (E): Relevant instruments (documents received from the Secretariat of the United Nations)\nAvailable in:\n\nEnglish\nFrench\n\n\n\n\nPart II (D): Human rights documentation\n\n\n                30 \n                January \n                2025\n              \nPart II (D): Human rights documentation\n\n\n\nPart II (D) (1): General Assembly\n\n\nEnglish\nFrench\n\n\n\n\nPart II (D) (2): Human Rights Council\n\n\nEnglish\nFrench\n\n\n\n\nPart II (D) (3): Commission on Human Rights\n\n\nEnglish\nFrench\n\n\n\n\nPart II (D) (4): Treaty bodies\n\n\nEnglish\nFrench\n\n\n\n\nPart II (D) (5): Universal periodic review\n\n\nEnglish\nFrench\n\n\n\n\n\n\nPart II (C) - Security Council (documents received from the Secretariat of the United Nations)\n\n\n                30 \n                January \n                2025\n              \nPart II (C) - Security Council (documents received from the Secretariat of the United Nations)\n\n\n\nPart II (C) (1): Documentation relating to the situation in the Occupied Palestinian Territories\n\n\nEnglish\nFrench\n\n\n\n\nPart II (C) (2): Documentation relating to the safety and security of humanitarian personnel and United Nations and associated personnel\n\n\nEnglish\nFrench\n\n\n\n\n\n\n\nPart II (B) - General Assembly Emergency Special Sessions (documents received from the Secretariat of the United Nations)\n\n\n\n                30 \n                January \n                2025\n              \nPart II (B) - General Assembly Emergency Special Sessions (documents received from the Secretariat of the United Nations)\nAvailable in:\n\nEnglish\nFrench\n\n\n\n\nPart II (A) - Material of the United Nations Relating to the Questions before the Court (documents received from the Secretariat of the United Nations)\n\n\n                30 \n                January \n                2025\n              \nPart II (A) - Material of the United Nations Relating to the Questions before the Court (documents received from the Secretariat of the United Nations)\n\n\n\nPart II (A) (1): Israeli settlements\n\n\nEnglish\nFrench\n\n\n\n\nPart II (A) (2): Living conditions of the Palestinian people\n\n\nEnglish\nFrench\n\n\n\n\nPart II (A) (3): Palestinian women and children\n\n\nEnglish\nFrench\n\n\n\n\nPart II (A) (4): Permanent sovereignty over natural and national resources\n\n\nEnglish\nFrench\n\n\n\n\nPart II (A) (5): Right to self-determination\n\n\nEnglish\nFrench\n\n\n\n\nPart II (A) (6): Question of Palestine\n\n\nEnglish\nFrench\n\n\n\n\nPart II (A) (7): Situation in the Middle East\n\n\nEnglish\nFrench\n\n\n\n\nPart II (A) (8): Special Committee to investigate Israeli practices affecting the human rights of the Palestinian people\n\n\nEnglish\nFrench\n\n\n\n\nPart II (A) (9): United Nations Relief and Works Agency for Palestine refugees in the Near East (UNRWA)\n\n\nEnglish\nFrench\n\n\n\n\nPart II (A) (10): Assistance to the Palestinian people\n\n\nEnglish\nFrench\n\n\n\n\nPart II (A) (11): Safety and security of humanitarian personnel and protection of United Nations personnel\n\n\nEnglish\nFrench\n\n\n\n\n\n\n\nPart I: Material relating to the request by the General Assembly for an advisory opinion of the Court\n\n\n\n                30 \n                January \n                2025\n              \nPart I: Material relating to the request by the General Assembly for an advisory opinion of the Court\nAvailable in:\n\nEnglish\nFrench\n\n\n\n\n\nList of Documents (documents received from the Secretariat of the United Nations)\n\n\n\n                30 \n                January \n                2025\n              \nList of Documents (documents received from the Secretariat of the United Nations)\nAvailable in:\n\nEnglish\nFrench\n\n\n\n\n\nIntroductory Note (documents received from the Secretariat of the United Nations)\n\n\n\n                30 \n                January \n                2025\n              \nIntroductory Note (documents received from the Secretariat of the United Nations)\nAvailable in:\n\nEnglish\nFrench\n\n\n\n\n\n                  Press release 2024/86\n                \n\n\n                24 \n                December \n                2024\n              \nObligations of Israel in relation to the presence and activities of the United Nations, other international organizations and third States in and in relation to the Occupied Palestinian Territory (Request for Advisory Opinion) - The President of the Court makes an Order organizing the proceedings and fixes the time-limits for the presentation of written statements\nAvailable in:\n\nEnglish\nFrench\n\n\n\n\n\nOrder of 23 December 2024\n\n\nFixing of time-limits: Presentation of written statements\nAvailable in:\n\nEnglish\nFrench\n\n\n\n\n\n                  Press release 2024/84\n                \n\n\n                23 \n                December \n                2024\n              \nThe General Assembly of the United Nations requests an advisory opinion from the Court on “the obligations of Israel in relation to the presence and activities of the United Nations, other international organizations and third States” in and in relation to the Occupied Palestinian Territory\nAvailable in:\n\nEnglish\nFrench\n\n\n\n\n\nRequest for Advisory Opinion\n\n\n\n                23 \n                December \n                2024\n              \nRequest for Advisory Opinion\nAvailable in:\n\nEnglish\nFrench\n\nLatest Developments\n\n\n\n                  Press release 2025/13\n                \n\n\n                12 \n                March \n                2025\n              \nObligations of Israel in relation to the Presence and Activities of the United Nations, Other International Organizations and Third States in and in relation to the Occupied Palestinian Territory (Request for Advisory Opinion) - Filing of written statements and opening date of the public hearings\nAvailable in:\n\nEnglish\nFrench\n\n\n\n\n\n                  Press release 2025/9\n                \n\n\n                20 \n                February \n                2025\n              \nObligations of Israel in relation to the Presence and Activities of the United Nations, Other International Organizations and Third States in and in relation to the Occupied Palestinian Territory (Request for Advisory Opinion) - The Court authorizes the African Union to participate in the proceedings\nAvailable in:\n\nEnglish\nFrench\n\n\n\n\n\n                  Press release 2025/8\n                \n\n\n                7 \n                February \n                2025\n              \nObligations of Israel in relation to the Presence and Activities of the United Nations, Other International Organizations and Third States in and in relation to the Occupied Palestinian Territory (Request for Advisory Opinion) - The Court authorizes the League of Arab States to participate in the proceedings\nAvailable in:\n\nEnglish\nFrench\n\n\n\n\n\n                  Press release 2025/7\n                \n\n\n                4 \n                February \n                2025\n              \nObligations of Israel in relation to the Presence and Activities of the United Nations, Other International Organizations and Third States in and in relation to the Occupied Palestinian Territory (Request for Advisory Opinion) - The Court authorizes the Organisation of Islamic Cooperation to participate in the proceedings\nAvailable in:\n\nEnglish\nFrench\n\n\n\n\n\nPart II (F): Other documents without document symbols (documents received from the Secretariat of the United Nations)\n\n\n\n                30 \n                January \n                2025\n              \nPart II (F): Other documents without document symbols (documents received from the Secretariat of the United Nations)\nAvailable in:\n\nEnglish\nFrench\n\n\n\n\n\nPart II (E): Relevant instruments (documents received from the Secretariat of the United Nations)\n\n\n\n                30 \n                January \n                2025\n              \nPart II (E): Relevant instruments (documents received from the Secretariat of the United Nations)\nAvailable in:\n\nEnglish\nFrench\n\n\n\n\nPart II (D): Human rights documentation\n\n\n                30 \n                January \n                2025\n              \nPart II (D): Human rights documentation\n\n\n\nPart II (D) (1): General Assembly\n\n\nEnglish\nFrench\n\n\n\n\nPart II (D) (2): Human Rights Council\n\n\nEnglish\nFrench\n\n\n\n\nPart II (D) (3): Commission on Human Rights\n\n\nEnglish\nFrench\n\n\n\n\nPart II (D) (4): Treaty bodies\n\n\nEnglish\nFrench\n\n\n\n\nPart II (D) (5): Universal periodic review\n\n\nEnglish\nFrench\n\n\n\n\n\n\nPart II (C) - Security Council (documents received from the Secretariat of the United Nations)\n\n\n                30 \n                January \n                2025\n              \nPart II (C) - Security Council (documents received from the Secretariat of the United Nations)\n\n\n\nPart II (C) (1): Documentation relating to the situation in the Occupied Palestinian Territories\n\n\nEnglish\nFrench\n\n\n\n\nPart II (C) (2): Documentation relating to the safety and security of humanitarian personnel and United Nations and associated personnel\n\n\nEnglish\nFrench\n\n\n\n\n\n\n\nPart II (B) - General Assembly Emergency Special Sessions (documents received from the Secretariat of the United Nations)\n\n\n\n                30 \n                January \n                2025\n              \nPart II (B) - General Assembly Emergency Special Sessions (documents received from the Secretariat of the United Nations)\nAvailable in:\n\nEnglish\nFrench\n\n\n\n\nPart II (A) - Material of the United Nations Relating to the Questions before the Court (documents received from the Secretariat of the United Nations)\n\n\n                30 \n                January \n                2025\n              \nPart II (A) - Material of the United Nations Relating to the Questions before the Court (documents received from the Secretariat of the United Nations)\n\n\n\nPart II (A) (1): Israeli settlements\n\n\nEnglish\nFrench\n\n\n\n\nPart II (A) (2): Living conditions of the Palestinian people\n\n\nEnglish\nFrench\n\n\n\n\nPart II (A) (3): Palestinian women and children\n\n\nEnglish\nFrench\n\n\n\n\nPart II (A) (4): Permanent sovereignty over natural and national resources\n\n\nEnglish\nFrench\n\n\n\n\nPart II (A) (5): Right to self-determination\n\n\nEnglish\nFrench\n\n\n\n\nPart II (A) (6): Question of Palestine\n\n\nEnglish\nFrench\n\n\n\n\nPart II (A) (7): Situation in the Middle East\n\n\nEnglish\nFrench\n\n\n\n\nPart II (A) (8): Special Committee to investigate Israeli practices affecting the human rights of the Palestinian people\n\n\nEnglish\nFrench\n\n\n\n\nPart II (A) (9): United Nations Relief and Works Agency for Palestine refugees in the Near East (UNRWA)\n\n\nEnglish\nFrench\n\n\n\n\nPart II (A) (10): Assistance to the Palestinian people\n\n\nEnglish\nFrench\n\n\n\n\nPart II (A) (11): Safety and security of humanitarian personnel and protection of United Nations personnel\n\n\nEnglish\nFrench\n\n\n\n\n\n\n\nPart I: Material relating to the request by the General Assembly for an advisory opinion of the Court\n\n\n\n                30 \n                January \n                2025\n              \nPart I: Material relating to the request by the General Assembly for an advisory opinion of the Court\nAvailable in:\n\nEnglish\nFrench\n\n\n\n\n\nList of Documents (documents received from the Secretariat of the United Nations)\n\n\n\n                30 \n                January \n                2025\n              \nList of Documents (documents received from the Secretariat of the United Nations)\nAvailable in:\n\nEnglish\nFrench\n\n\n\n\n\nIntroductory Note (documents received from the Secretariat of the United Nations)\n\n\n\n                30 \n                January \n                2025\n              \nIntroductory Note (documents received from the Secretariat of the United Nations)\nAvailable in:\n\nEnglish\nFrench\n\n\n\n\n\n                  Press release 2024/86\n                \n\n\n                24 \n                December \n                2024\n              \nObligations of Israel in relation to the presence and activities of the United Nations, other international organizations and third States in and in relation to the Occupied Palestinian Territory (Request for Advisory Opinion) - The President of the Court makes an Order organizing the proceedings and fixes the time-limits for the presentation of written statements\nAvailable in:\n\nEnglish\nFrench\n\n\n\n\n\nOrder of 23 December 2024\n\n\nFixing of time-limits: Presentation of written statements\nAvailable in:\n\nEnglish\nFrench\n\n\n\n\n\n                  Press release 2024/84\n                \n\n\n                23 \n                December \n                2024\n              \nThe General Assembly of the United Nations requests an advisory opinion from the Court on “the obligations of Israel in relation to the presence and activities of the United Nations, other international organizations and third States” in and in relation to the Occupied Palestinian Territory\nAvailable in:\n\nEnglish\nFrench\n\n\n\n\n\nRequest for Advisory Opinion\n\n\n\n                23 \n                December \n                2024\n              \nRequest for Advisory Opinion\nAvailable in:\n\nEnglish\nFrench\n\nLatest Developments\n\n\n\n                  Press release 2025/13\n                \n\n\n                12 \n                March \n                2025\n              \nObligations of Israel in relation to the Presence and Activities of the United Nations, Other International Organizations and Third States in and in relation to the Occupied Palestinian Territory (Request for Advisory Opinion) - Filing of written statements and opening date of the public hearings\nAvailable in:\n\nEnglish\nFrench\n\n\n\n\n\n                  Press release 2025/9\n                \n\n\n                20 \n                February \n                2025\n              \nObligations of Israel in relation to the Presence and Activities of the United Nations, Other International Organizations and Third States in and in relation to the Occupied Palestinian Territory (Request for Advisory Opinion) - The Court authorizes the African Union to participate in the proceedings\nAvailable in:\n\nEnglish\nFrench\n\n\n\n\n\n                  Press release 2025/8\n                \n\n\n                7 \n                February \n                2025\n              \nObligations of Israel in relation to the Presence and Activities of the United Nations, Other International Organizations and Third States in and in relation to the Occupied Palestinian Territory (Request for Advisory Opinion) - The Court authorizes the League of Arab States to participate in the proceedings\nAvailable in:\n\nEnglish\nFrench\n\n\n\n\n\n                  Press release 2025/7\n                \n\n\n                4 \n                February \n                2025\n              \nObligations of Israel in relation to the Presence and Activities of the United Nations, Other International Organizations and Third States in and in relation to the Occupied Palestinian Territory (Request for Advisory Opinion) - The Court authorizes the Organisation of Islamic Cooperation to participate in the proceedings\nAvailable in:\n\nEnglish\nFrench\n\n\n\n\n\nPart II (F): Other documents without document symbols (documents received from the Secretariat of the United Nations)\n\n\n\n                30 \n                January \n                2025\n              \nPart II (F): Other documents without document symbols (documents received from the Secretariat of the United Nations)\nAvailable in:\n\nEnglish\nFrench\n\n\n\n\n\nPart II (E): Relevant instruments (documents received from the Secretariat of the United Nations)\n\n\n\n                30 \n                January \n                2025\n              \nPart II (E): Relevant instruments (documents received from the Secretariat of the United Nations)\nAvailable in:\n\nEnglish\nFrench\n\n\n\n\nPart II (D): Human rights documentation\n\n\n                30 \n                January \n                2025\n              \nPart II (D): Human rights documentation\n\n\n\nPart II (D) (1): General Assembly\n\n\nEnglish\nFrench\n\n\n\n\nPart II (D) (2): Human Rights Council\n\n\nEnglish\nFrench\n\n\n\n\nPart II (D) (3): Commission on Human Rights\n\n\nEnglish\nFrench\n\n\n\n\nPart II (D) (4): Treaty bodies\n\n\nEnglish\nFrench\n\n\n\n\nPart II (D) (5): Universal periodic review\n\n\nEnglish\nFrench\n\n\n\n\n\n\nPart II (C) - Security Council (documents received from the Secretariat of the United Nations)\n\n\n                30 \n                January \n                2025\n              \nPart II (C) - Security Council (documents received from the Secretariat of the United Nations)\n\n\n\nPart II (C) (1): Documentation relating to the situation in the Occupied Palestinian Territories\n\n\nEnglish\nFrench\n\n\n\n\nPart II (C) (2): Documentation relating to the safety and security of humanitarian personnel and United Nations and associated personnel\n\n\nEnglish\nFrench\n\n\n\n\n\n\n\nPart II (B) - General Assembly Emergency Special Sessions (documents received from the Secretariat of the United Nations)\n\n\n\n                30 \n                January \n                2025\n              \nPart II (B) - General Assembly Emergency Special Sessions (documents received from the Secretariat of the United Nations)\nAvailable in:\n\nEnglish\nFrench\n\n\n\n\nPart II (A) - Material of the United Nations Relating to the Questions before the Court (documents received from the Secretariat of the United Nations)\n\n\n                30 \n                January \n                2025\n              \nPart II (A) - Material of the United Nations Relating to the Questions before the Court (documents received from the Secretariat of the United Nations)\n\n\n\nPart II (A) (1): Israeli settlements\n\n\nEnglish\nFrench\n\n\n\n\nPart II (A) (2): Living conditions of the Palestinian people\n\n\nEnglish\nFrench\n\n\n\n\nPart II (A) (3): Palestinian women and children\n\n\nEnglish\nFrench\n\n\n\n\nPart II (A) (4): Permanent sovereignty over natural and national resources\n\n\nEnglish\nFrench\n\n\n\n\nPart II (A) (5): Right to self-determination\n\n\nEnglish\nFrench\n\n\n\n\nPart II (A) (6): Question of Palestine\n\n\nEnglish\nFrench\n\n\n\n\nPart II (A) (7): Situation in the Middle East\n\n\nEnglish\nFrench\n\n\n\n\nPart II (A) (8): Special Committee to investigate Israeli practices affecting the human rights of the Palestinian people\n\n\nEnglish\nFrench\n\n\n\n\nPart II (A) (9): United Nations Relief and Works Agency for Palestine refugees in the Near East (UNRWA)\n\n\nEnglish\nFrench\n\n\n\n\nPart II (A) (10): Assistance to the Palestinian people\n\n\nEnglish\nFrench\n\n\n\n\nPart II (A) (11): Safety and security of humanitarian personnel and protection of United Nations personnel\n\n\nEnglish\nFrench\n\n\n\n\n\n\n\nPart I: Material relating to the request by the General Assembly for an advisory opinion of the Court\n\n\n\n                30 \n                January \n                2025\n              \nPart I: Material relating to the request by the General Assembly for an advisory opinion of the Court\nAvailable in:\n\nEnglish\nFrench\n\n\n\n\n\nList of Documents (documents received from the Secretariat of the United Nations)\n\n\n\n                30 \n                January \n                2025\n              \nList of Documents (documents received from the Secretariat of the United Nations)\nAvailable in:\n\nEnglish\nFrench\n\n\n\n\n\nIntroductory Note (documents received from the Secretariat of the United Nations)\n\n\n\n                30 \n                January \n                2025\n              \nIntroductory Note (documents received from the Secretariat of the United Nations)\nAvailable in:\n\nEnglish\nFrench\n\n\n\n\n\n                  Press release 2024/86\n                \n\n\n                24 \n                December \n                2024\n              \nObligations of Israel in relation to the presence and activities of the United Nations, other international organizations and third States in and in relation to the Occupied Palestinian Territory (Request for Advisory Opinion) - The President of the Court makes an Order organizing the proceedings and fixes the time-limits for the presentation of written statements\nAvailable in:\n\nEnglish\nFrench\n\n\n\n\n\nOrder of 23 December 2024\n\n\nFixing of time-limits: Presentation of written statements\nAvailable in:\n\nEnglish\nFrench\n\n\n\n\n\n                  Press release 2024/84\n                \n\n\n                23 \n                December \n                2024\n              \nThe General Assembly of the United Nations requests an advisory opinion from the Court on “the obligations of Israel in relation to the presence and activities of the United Nations, other international organizations and third States” in and in relation to the Occupied Palestinian Territory\nAvailable in:\n\nEnglish\nFrench\n\n\n\n\n\nRequest for Advisory Opinion\n\n\n\n                23 \n                December \n                2024\n              \nRequest for Advisory Opinion\nAvailable in:\n\nEnglish\nFrench\n\nPress release 2025/13\n                \n\n\n                12 \n                March \n                2025\n              \nObligations of Israel in relation to the Presence and Activities of the United Nations, Other International Organizations and Third States in and in relation to the Occupied Palestinian Territory (Request for Advisory Opinion) - Filing of written statements and opening date of the public hearings\nAvailable in:\n\nEnglish\nFrench\n\nPress release 2025/13\n\nObligations of Israel in relation to the Presence and Activities of the United Nations, Other International Organizations and Third States in and in relation to the Occupied Palestinian Territory (Request for Advisory Opinion) - Filing of written statements and opening date of the public hearings\n\nEnglish\nFrench\n\nPress release 2025/9\n                \n\n\n                20 \n                February \n                2025\n              \nObligations of Israel in relation to the Presence and Activities of the United Nations, Other International Organizations and Third States in and in relation to the Occupied Palestinian Territory (Request for Advisory Opinion) - The Court authorizes the African Union to participate in the proceedings\nAvailable in:\n\nEnglish\nFrench\n\nPress release 2025/9\n\nObligations of Israel in relation to the Presence and Activities of the United Nations, Other International Organizations and Third States in and in relation to the Occupied Palestinian Territory (Request for Advisory Opinion) - The Court authorizes the African Union to participate in the proceedings\n\nEnglish\nFrench\n\nPress release 2025/8\n                \n\n\n                7 \n                February \n                2025\n              \nObligations of Israel in relation to the Presence and Activities of the United Nations, Other International Organizations and Third States in and in relation to the Occupied Palestinian Territory (Request for Advisory Opinion) - The Court authorizes the League of Arab States to participate in the proceedings\nAvailable in:\n\nEnglish\nFrench\n\nPress release 2025/8\n\nObligations of Israel in relation to the Presence and Activities of the United Nations, Other International Organizations and Third States in and in relation to the Occupied Palestinian Territory (Request for Advisory Opinion) - The Court authorizes the League of Arab States to participate in the proceedings\n\nEnglish\nFrench\n\nPress release 2025/7\n                \n\n\n                4 \n                February \n                2025\n              \nObligations of Israel in relation to the Presence and Activities of the United Nations, Other International Organizations and Third States in and in relation to the Occupied Palestinian Territory (Request for Advisory Opinion) - The Court authorizes the Organisation of Islamic Cooperation to participate in the proceedings\nAvailable in:\n\nEnglish\nFrench\n\nPress release 2025/7\n\nObligations of Israel in relation to the Presence and Activities of the United Nations, Other International Organizations and Third States in and in relation to the Occupied Palestinian Territory (Request for Advisory Opinion) - The Court authorizes the Organisation of Islamic Cooperation to participate in the proceedings\n\nEnglish\nFrench\n\nPart II (F): Other documents without document symbols (documents received from the Secretariat of the United Nations)\n\n\n\n                30 \n                January \n                2025\n              \nPart II (F): Other documents without document symbols (documents received from the Secretariat of the United Nations)\nAvailable in:\n\nEnglish\nFrench\n\nPart II (F): Other documents without document symbols (documents received from the Secretariat of the United Nations)\n\nPart II (F): Other documents without document symbols (documents received from the Secretariat of the United Nations)\n\nPart II (F): Other documents without document symbols (documents received from the Secretariat of the United Nations)\n\nEnglish\nFrench\n\nPart II (E): Relevant instruments (documents received from the Secretariat of the United Nations)\n\n\n\n                30 \n                January \n                2025\n              \nPart II (E): Relevant instruments (documents received from the Secretariat of the United Nations)\nAvailable in:\n\nEnglish\nFrench\n\nPart II (E): Relevant instruments (documents received from the Secretariat of the United Nations)\n\nPart II (E): Relevant instruments (documents received from the Secretariat of the United Nations)\n\nPart II (E): Relevant instruments (documents received from the Secretariat of the United Nations)\n\nEnglish\nFrench\n\nPart II (D): Human rights documentation\n\n\n                30 \n                January \n                2025\n              \nPart II (D): Human rights documentation\n\n\n\nPart II (D) (1): General Assembly\n\n\nEnglish\nFrench\n\n\n\n\nPart II (D) (2): Human Rights Council\n\n\nEnglish\nFrench\n\n\n\n\nPart II (D) (3): Commission on Human Rights\n\n\nEnglish\nFrench\n\n\n\n\nPart II (D) (4): Treaty bodies\n\n\nEnglish\nFrench\n\n\n\n\nPart II (D) (5): Universal periodic review\n\n\nEnglish\nFrench\n\nPart II (D): Human rights documentation\n\nPart II (D): Human rights documentation\n\nPart II (D): Human rights documentation\n\nPart II (D) (1): General Assembly\n\n\nEnglish\nFrench\n\n\n\n\nPart II (D) (2): Human Rights Council\n\n\nEnglish\nFrench\n\n\n\n\nPart II (D) (3): Commission on Human Rights\n\n\nEnglish\nFrench\n\n\n\n\nPart II (D) (4): Treaty bodies\n\n\nEnglish\nFrench\n\n\n\n\nPart II (D) (5): Universal periodic review\n\n\nEnglish\nFrench\n\nPart II (D) (1): General Assembly\n\n\nEnglish\nFrench\n\nPart II (D) (1): General Assembly\n\nEnglish\nFrench\n\nPart II (D) (2): Human Rights Council\n\n\nEnglish\nFrench\n\nPart II (D) (2): Human Rights Council\n\nEnglish\nFrench\n\nPart II (D) (3): Commission on Human Rights\n\n\nEnglish\nFrench\n\nPart II (D) (3): Commission on Human Rights\n\nEnglish\nFrench\n\nPart II (D) (4): Treaty bodies\n\n\nEnglish\nFrench\n\nPart II (D) (4): Treaty bodies\n\nEnglish\nFrench\n\nPart II (D) (5): Universal periodic review\n\n\nEnglish\nFrench\n\nPart II (D) (5): Universal periodic review\n\nEnglish\nFrench\n\nPart II (C) - Security Council (documents received from the Secretariat of the United Nations)\n\n\n                30 \n                January \n                2025\n              \nPart II (C) - Security Council (documents received from the Secretariat of the United Nations)\n\n\n\nPart II (C) (1): Documentation relating to the situation in the Occupied Palestinian Territories\n\n\nEnglish\nFrench\n\n\n\n\nPart II (C) (2): Documentation relating to the safety and security of humanitarian personnel and United Nations and associated personnel\n\n\nEnglish\nFrench\n\nPart II (C) - Security Council (documents received from the Secretariat of the United Nations)\n\nPart II (C) - Security Council (documents received from the Secretariat of the United Nations)\n\nPart II (C) - Security Council (documents received from the Secretariat of the United Nations)\n\nPart II (C) (1): Documentation relating to the situation in the Occupied Palestinian Territories\n\n\nEnglish\nFrench\n\n\n\n\nPart II (C) (2): Documentation relating to the safety and security of humanitarian personnel and United Nations and associated personnel\n\n\nEnglish\nFrench\n\nPart II (C) (1): Documentation relating to the situation in the Occupied Palestinian Territories\n\n\nEnglish\nFrench\n\nPart II (C) (1): Documentation relating to the situation in the Occupied Palestinian Territories\n\nEnglish\nFrench\n\nPart II (C) (2): Documentation relating to the safety and security of humanitarian personnel and United Nations and associated personnel\n\n\nEnglish\nFrench\n\nPart II (C) (2): Documentation relating to the safety and security of humanitarian personnel and United Nations and associated personnel\n\nEnglish\nFrench\n\nPart II (B) - General Assembly Emergency Special Sessions (documents received from the Secretariat of the United Nations)\n\n\n\n                30 \n                January \n                2025\n              \nPart II (B) - General Assembly Emergency Special Sessions (documents received from the Secretariat of the United Nations)\nAvailable in:\n\nEnglish\nFrench\n\nPart II (B) - General Assembly Emergency Special Sessions (documents received from the Secretariat of the United Nations)\n\nPart II (B) - General Assembly Emergency Special Sessions (documents received from the Secretariat of the United Nations)\n\nPart II (B) - General Assembly Emergency Special Sessions (documents received from the Secretariat of the United Nations)\n\nEnglish\nFrench\n\nPart II (A) - Material of the United Nations Relating to the Questions before the Court (documents received from the Secretariat of the United Nations)\n\n\n                30 \n                January \n                2025\n              \nPart II (A) - Material of the United Nations Relating to the Questions before the Court (documents received from the Secretariat of the United Nations)\n\n\n\nPart II (A) (1): Israeli settlements\n\n\nEnglish\nFrench\n\n\n\n\nPart II (A) (2): Living conditions of the Palestinian people\n\n\nEnglish\nFrench\n\n\n\n\nPart II (A) (3): Palestinian women and children\n\n\nEnglish\nFrench\n\n\n\n\nPart II (A) (4): Permanent sovereignty over natural and national resources\n\n\nEnglish\nFrench\n\n\n\n\nPart II (A) (5): Right to self-determination\n\n\nEnglish\nFrench\n\n\n\n\nPart II (A) (6): Question of Palestine\n\n\nEnglish\nFrench\n\n\n\n\nPart II (A) (7): Situation in the Middle East\n\n\nEnglish\nFrench\n\n\n\n\nPart II (A) (8): Special Committee to investigate Israeli practices affecting the human rights of the Palestinian people\n\n\nEnglish\nFrench\n\n\n\n\nPart II (A) (9): United Nations Relief and Works Agency for Palestine refugees in the Near East (UNRWA)\n\n\nEnglish\nFrench\n\n\n\n\nPart II (A) (10): Assistance to the Palestinian people\n\n\nEnglish\nFrench\n\n\n\n\nPart II (A) (11): Safety and security of humanitarian personnel and protection of United Nations personnel\n\n\nEnglish\nFrench\n\nPart II (A) - Material of the United Nations Relating to the Questions before the Court (documents received from the Secretariat of the United Nations)\n\nPart II (A) - Material of the United Nations Relating to the Questions before the Court (documents received from the Secretariat of the United Nations)\n\nPart II (A) - Material of the United Nations Relating to the Questions before the Court (documents received from the Secretariat of the United Nations)\n\nPart II (A) (1): Israeli settlements\n\n\nEnglish\nFrench\n\n\n\n\nPart II (A) (2): Living conditions of the Palestinian people\n\n\nEnglish\nFrench\n\n\n\n\nPart II (A) (3): Palestinian women and children\n\n\nEnglish\nFrench\n\n\n\n\nPart II (A) (4): Permanent sovereignty over natural and national resources\n\n\nEnglish\nFrench\n\n\n\n\nPart II (A) (5): Right to self-determination\n\n\nEnglish\nFrench\n\n\n\n\nPart II (A) (6): Question of Palestine\n\n\nEnglish\nFrench\n\n\n\n\nPart II (A) (7): Situation in the Middle East\n\n\nEnglish\nFrench\n\n\n\n\nPart II (A) (8): Special Committee to investigate Israeli practices affecting the human rights of the Palestinian people\n\n\nEnglish\nFrench\n\n\n\n\nPart II (A) (9): United Nations Relief and Works Agency for Palestine refugees in the Near East (UNRWA)\n\n\nEnglish\nFrench\n\n\n\n\nPart II (A) (10): Assistance to the Palestinian people\n\n\nEnglish\nFrench\n\n\n\n\nPart II (A) (11): Safety and security of humanitarian personnel and protection of United Nations personnel\n\n\nEnglish\nFrench\n\nPart II (A) (1): Israeli settlements\n\n\nEnglish\nFrench\n\nPart II (A) (1): Israeli settlements\n\nEnglish\nFrench\n\nPart II (A) (2): Living conditions of the Palestinian people\n\n\nEnglish\nFrench\n\nPart II (A) (2): Living conditions of the Palestinian people\n\nEnglish\nFrench\n\nPart II (A) (3): Palestinian women and children\n\n\nEnglish\nFrench\n\nPart II (A) (3): Palestinian women and children\n\nEnglish\nFrench\n\nPart II (A) (4): Permanent sovereignty over natural and national resources\n\n\nEnglish\nFrench\n\nPart II (A) (4): Permanent sovereignty over natural and national resources\n\nEnglish\nFrench\n\nPart II (A) (5): Right to self-determination\n\n\nEnglish\nFrench\n\nPart II (A) (5): Right to self-determination\n\nEnglish\nFrench\n\nPart II (A) (6): Question of Palestine\n\n\nEnglish\nFrench\n\nPart II (A) (6): Question of Palestine\n\nEnglish\nFrench\n\nPart II (A) (7): Situation in the Middle East\n\n\nEnglish\nFrench\n\nPart II (A) (7): Situation in the Middle East\n\nEnglish\nFrench\n\nPart II (A) (8): Special Committee to investigate Israeli practices affecting the human rights of the Palestinian people\n\n\nEnglish\nFrench\n\nPart II (A) (8): Special Committee to investigate Israeli practices affecting the human rights of the Palestinian people\n\nEnglish\nFrench\n\nPart II (A) (9): United Nations Relief and Works Agency for Palestine refugees in the Near East (UNRWA)\n\n\nEnglish\nFrench\n\nPart II (A) (9): United Nations Relief and Works Agency for Palestine refugees in the Near East (UNRWA)\n\nEnglish\nFrench\n\nPart II (A) (10): Assistance to the Palestinian people\n\n\nEnglish\nFrench\n\nPart II (A) (10): Assistance to the Palestinian people\n\nEnglish\nFrench\n\nPart II (A) (11): Safety and security of humanitarian personnel and protection of United Nations personnel\n\n\nEnglish\nFrench\n\nPart II (A) (11): Safety and security of humanitarian personnel and protection of United Nations personnel\n\nEnglish\nFrench\n\nPart I: Material relating to the request by the General Assembly for an advisory opinion of the Court\n\n\n\n                30 \n                January \n                2025\n              \nPart I: Material relating to the request by the General Assembly for an advisory opinion of the Court\nAvailable in:\n\nEnglish\nFrench\n\nPart I: Material relating to the request by the General Assembly for an advisory opinion of the Court\n\nPart I: Material relating to the request by the General Assembly for an advisory opinion of the Court\n\nPart I: Material relating to the request by the General Assembly for an advisory opinion of the Court\n\nEnglish\nFrench\n\nList of Documents (documents received from the Secretariat of the United Nations)\n\n\n\n                30 \n                January \n                2025\n              \nList of Documents (documents received from the Secretariat of the United Nations)\nAvailable in:\n\nEnglish\nFrench\n\nList of Documents (documents received from the Secretariat of the United Nations)\n\nList of Documents (documents received from the Secretariat of the United Nations)\n\nList of Documents (documents received from the Secretariat of the United Nations)\n\nEnglish\nFrench\n\nIntroductory Note (documents received from the Secretariat of the United Nations)\n\n\n\n                30 \n                January \n                2025\n              \nIntroductory Note (documents received from the Secretariat of the United Nations)\nAvailable in:\n\nEnglish\nFrench\n\nIntroductory Note (documents received from the Secretariat of the United Nations)\n\nIntroductory Note (documents received from the Secretariat of the United Nations)\n\nIntroductory Note (documents received from the Secretariat of the United Nations)\n\nEnglish\nFrench\n\nPress release 2024/86\n                \n\n\n                24 \n                December \n                2024\n              \nObligations of Israel in relation to the presence and activities of the United Nations, other international organizations and third States in and in relation to the Occupied Palestinian Territory (Request for Advisory Opinion) - The President of the Court makes an Order organizing the proceedings and fixes the time-limits for the presentation of written statements\nAvailable in:\n\nEnglish\nFrench\n\nPress release 2024/86\n\nObligations of Israel in relation to the presence and activities of the United Nations, other international organizations and third States in and in relation to the Occupied Palestinian Territory (Request for Advisory Opinion) - The President of the Court makes an Order organizing the proceedings and fixes the time-limits for the presentation of written statements\n\nEnglish\nFrench\n\nOrder of 23 December 2024\n\n\nFixing of time-limits: Presentation of written statements\nAvailable in:\n\nEnglish\nFrench\n\nOrder of 23 December 2024\n\nOrder of 23 December 2024\n\nFixing of time-limits: Presentation of written statements\n\nEnglish\nFrench\n\nPress release 2024/84\n                \n\n\n                23 \n                December \n                2024\n              \nThe General Assembly of the United Nations requests an advisory opinion from the Court on “the obligations of Israel in relation to the presence and activities of the United Nations, other international organizations and third States” in and in relation to the Occupied Palestinian Territory\nAvailable in:\n\nEnglish\nFrench\n\nPress release 2024/84\n\nThe General Assembly of the United Nations requests an advisory opinion from the Court on “the obligations of Israel in relation to the presence and activities of the United Nations, other international organizations and third States” in and in relation to the Occupied Palestinian Territory\n\nEnglish\nFrench\n\nRequest for Advisory Opinion\n\n\n\n                23 \n                December \n                2024\n              \nRequest for Advisory Opinion\nAvailable in:\n\nEnglish\nFrench\n\nRequest for Advisory Opinion\n\nRequest for Advisory Opinion\n\nRequest for Advisory Opinion\n\nEnglish\nFrench\n\nLinks\n\nLinks",
  "date": "",
  "source_type": "other",
  "extracted_at": "2025-04-07T13:50:51.261408",
  "metadata": {},
  "relevance_score": 0.5136363636363637,
  "summary": "Obligations of Israel in relation to the Presence and Activities of the United Nations, Other International Organizations and Third States in and in relation to the Occupied Palestinian Territory\n\n\n\n\n\nLatest Developments\n\n\n\n                  Press release 2025/13\n                \n\n\n                12 \n                March \n                2025\n              \nObligations of Israel in relation to the Presence and Activities of the United Nations, Other International Organizations and Third States in and in relation to the Occupied Palestinian Territory (Request for Advisory Opinion) - Filing of written statements and opening date of the public hearings\nAvailable in:\n\nEnglish\nFrench\n\n\n\n\n\n                  Press release 2025/9\n                \n\n\n                20 \n                February \n                2025\n              \nObligations of Israel in relation to the Presence and Activities of the United Nations, Other International Organizations and Third States in and in relation to the Occupied Palestinian Territory (Request for Advisory Opinion) - The Court authorizes the African Union to participate in the proceedings\nAvailable in:\n\nEnglish\nFrench\n\n\n\n\n\n                  Press release 2025/8\n                \n\n\n                7 \n                February \n                2025\n              \nObligations of Israel in relation to the Presence and Activities of the United Nations, Other International Organizations and Third States in and in relation to the Occupied Palestinian Territory (Request for Advisory Opinion) - The Court authorizes the League of Arab States to participate in the proceedings\nAvailable in:\n\nEnglish\nFrench\n\n\n\n\n\n                  Press release 2025/7\n                \n\n\n                4 \n                February \n                2025\n              \nObligations of Israel in relation to the Presence and Activities of the United Nations, Other International Organizations and Third States in and in relation to the Occupied Palestinian Territory (Request for Advisory Opinion) - The Court authorizes the Organisation of Islamic Cooperation to participate in the proceedings\nAvailable in:\n\nEnglish\nFrench\n\n\n\n\n\nPart II (F): Other documents without document symbols (documents received from the Secretariat of the United Nations)\n\n\n\n                30 \n                January \n                2025\n              \nPart II (F): Other documents without document symbols (documents received from the Secretariat of the United Nations)\nAvailable in:\n\nEnglish\nFrench\n\n\n\n\n\nPart II (E): Relevant instruments (documents received from the Secretariat of the United Nations)\n\n\n\n                30 \n                January \n                2025\n              \nPart II (E): Relevant instruments (documents received from the Secretariat of the United Nations)\nAvailable in:\n\nEnglish\nFrench\n\n\n\n\nPart II (D): Human rights documentation\n\n\n                30 \n                January \n                2025\n              \nPart II (D): Human rights documentation\n\n\n\nPart II (D) (1): General Assembly\n\n\nEnglish\nFrench\n\n\n\n\nPart II (D) (2): Human Rights Council\n\n\nEnglish\nFrench\n\n\n\n\nPart II (D) (3): Commission on Human Rights\n\n\nEnglish\nFrench\n\n\n\n\nPart II (D) (4): Treaty bodies\n\n\nEnglish\nFrench\n\n\n\n\nPart II (D) (5): Universal periodic review\n\n\nEnglish\nFrench\n\n\n\n\n\n\nPart II (C) - Security Council (documents received from the Secretariat of the United Nations)\n\n\n                30 \n                January \n                2025\n              \nPart II (C) - Security Council (documents received from the Secretariat of the United Nations)\n\n\n\nPart II (C) (1): Documentation relating to the situation in the Occupied Palestinian Territories\n\n\nEnglish\nFrench\n\n\n\n\nPart II (C) (2): Documentation relating to the safety and security of humanitarian personnel and United Nations and associated personnel\n\n\nEnglish\nFrench\n\n\n\n\n\n\n\nPart II (B) - General Assembly Emergency Special Sessions (documents received from the Secretariat of the United Nations)\n\n\n\n                30 \n                January \n                2025\n              \nPart II (B) - General Assembly Emergency Special Sessions (documents received from the Secretariat of the United Nations)\nAvailable in:\n\nEnglish\nFrench\n\n\n\n\nPart II (A) - Material of the United Nations Relating to the Questions before the Court (documents received from the Secretariat of the United Nations)\n\n\n                30 \n                January \n                2025\n              \nPart II (A) - Material of the United Nations Relating to the Questions before the Court (documents received from the Secretariat of the United Nations)\n\n\n\nPart II (A) (1): Israeli settlements\n\n\nEnglish\nFrench\n\n\n\n\nPart II (A) (2): Living conditions of the Palestinian people\n\n\nEnglish\nFrench\n\n\n\n\nPart II (A) (3): Palestinian women and children\n\n\nEnglish\nFrench\n\n\n\n\nPart II (A) (4): Permanent sovereignty over natural and national resources\n\n\nEnglish\nFrench\n\n\n\n\nPart II (A) (5): Right to self-determination\n\n\nEnglish\nFrench\n\n\n\n\nPart II (A) (6): Question of Palestine\n\n\nEnglish\nFrench\n\n\n\n\nPart II (A) (7): Situation in the Middle East\n\n\nEnglish\nFrench\n\n\n\n\nPart II (A) (8): Special Committee to investigate Israeli practices affecting the human rights of the Palestinian people\n\n\nEnglish\nFrench\n\n\n\n\nPart II (A) (9): United Nations Relief and Works Agency for Palestine refugees in the Near East (UNRWA)\n\n\nEnglish\nFrench\n\n\n\n\nPart II (A) (10): Assistance to the Palestinian people\n\n\nEnglish\nFrench\n\n\n\n\nPart II (A) (11): Safety and security of humanitarian personnel and protection of United Nations personnel\n\n\nEnglish\nFrench\n\n\n\n\n\n\n\nPart I: Material relating to the request by the General Assembly for an advisory opinion of the Court\n\n\n\n                30 \n                January \n                2025\n              \nPart I: Material relating to the request by the General Assembly for an advisory opinion of the Court\nAvailable in:\n\nEnglish\nFrench\n\n\n\n\n\nList of Documents (documents received from the Secretariat of the United Nations)\n\n\n\n                30 \n                January \n                2025\n              \nList of Documents (documents received from the Secretariat of the United Nations)\nAvailable in:\n\nEnglish\nFrench\n\n\n\n\n\nIntroductory Note (documents received from the Secretariat of the United Nations)\n\n\n\n                30 \n                January \n                2025\n              \nIntroductory Note (documents received from the Secretariat of the United Nations)\nAvailable in:\n\nEnglish\nFrench\n\n\n\n\n\n                  Press release 2024/86\n                \n\n\n                24 \n                December \n                2024\n              \nObligations of Israel in relation to the presence and activities of the United Nations, other international organizations and third States in and in relation to the Occupied Palestinian Territory (Request for Advisory Opinion) - The President of the Court makes an Order organizing the proceedings and fixes the time-limits for the presentation of written statements\nAvailable in:\n\nEnglish\nFrench\n\n\n\n\n\nOrder of 23 December 2024\n\n\nFixing of time-limits: Presentation of written statements\nAvailable in:\n\nEnglish\nFrench\n\n\n\n\n\n                  Press release 2024/84\n                \n\n\n                23 \n                December \n                2024\n              \nThe General Assembly of the United Nations requests an advisory opinion from the Court on “the obligations of Israel in relation to the presence and activities of the United Nations, other international organizations and third States” in and in relation to the Occupied Palestinian Territory\nAvailable in:\n\nEnglish\nFrench\n\n\n\n\n\nRequest for Advisory Opinion\n\n\n\n                23 \n                December \n                2024\n              \nRequest for Advisory Opinion\nAvailable in:\n\nEnglish\nFrench\n\n\n\n\n\n\n\n\n\n\n\n\n\n\n\n\nLinks\n\nObligations of Israel in relation to the Presence and Activities of the United Nations, Other International Organizations and Third States in and in relation to the Occupied Palestinian Territory\n\n\n\n\n\nLatest Developments\n\n\n\n                  Press release 2025/13\n                \n\n\n                12 \n                March \n                2025\n              \nObligations of Israel in relation to the Presence and Activities of the United Nations, Other International Organizations and Third States in and in relation to the Occupied Palestinian Territory (Request for Advisory Opinion) - Filing of written statements and opening date of the public hearings\nAvailable in:\n\nEnglish\nFrench\n\n\n\n\n\n                  Press release 2025/9\n                \n\n\n                20 \n                February \n                2025\n              \nObligations of Israel in relation to the Presence and Activities of the United Nations, Other International Organizations and Third States in and in relation to the Occupied Palestinian Territory (Request for Advisory Opinion) - The Court authorizes the African Union to participate in the proceedings\nAvailable in:\n\nEnglish\nFrench\n\n\n\n\n\n                  Press release 2025/8\n                \n\n\n                7 \n                February \n                2025\n              \nObligations of Israel in relation to the Presence and Activities of the United Nations, Other International Organizations and Third States in and in relation to the Occupied Palestinian Territory (Request for Advisory Opinion) - The Court authorizes the League of Arab States to participate in the proceedings\nAvailable in:\n\nEnglish\nFrench\n\n\n\n\n\n                  Press release 2025/7\n                \n\n\n                4 \n                February \n                2025\n              \nObligations of Israel in relation to the Presence and Activities of the United Nations, Other International Organizations and Third States in and in relation to the Occupied Palestinian Territory (Request for Advisory Opinion) - The Court authorizes the Organisation of Islamic Cooperation to participate in the proceedings\nAvailable in:\n\nEnglish\nFrench\n\n\n\n\n\nPart II (F): Other documents without document symbols (documents received from the Secretariat of the United Nations)\n\n\n\n                30 \n                January \n                2025\n              \nPart II (F): Other documents without document symbols (documents received from the Secretariat of the United Nations)\nAvailable in:\n\nEnglish\nFrench\n\n\n\n\n\nPart II (E): Relevant instruments (documents received from the Secretariat of the United Nations)\n\n\n\n                30 \n                January \n                2025\n              \nPart II (E): Relevant instruments (documents received from the Secretariat of the United Nations)\nAvailable in:\n\nEnglish\nFrench\n\n\n\n\nPart II (D): Human rights documentation\n\n\n                30 \n                January \n                2025\n              \nPart II (D): Human rights documentation\n\n\n\nPart II (D) (1): General Assembly\n\n\nEnglish\nFrench\n\n\n\n\nPart II (D) (2): Human Rights Council\n\n\nEnglish\nFrench\n\n\n\n\nPart II (D) (3): Commission on Human Rights\n\n\nEnglish\nFrench\n\n\n\n\nPart II (D) (4): Treaty bodies\n\n\nEnglish\nFrench\n\n\n\n\nPart II (D) (5): Universal periodic review\n\n\nEnglish\nFrench\n\n\n\n\n\n\nPart II (C) - Security Council (documents received from the Secretariat of the United Nations)\n\n\n                30 \n                January \n                2025\n              \nPart II (C) - Security Council (documents received from the Secretariat of the United Nations)\n\n\n\nPart II (C) (1): Documentation relating to the situation in the Occupied Palestinian Territories\n\n\nEnglish\nFrench\n\n\n\n\nPart II (C) (2): Documentation relating to the safety and security of humanitarian personnel and United Nations and associated personnel\n\n\nEnglish\nFrench\n\n\n\n\n\n\n\nPart II (B) - General Assembly Emergency Special Sessions (documents received from the Secretariat of the United Nations)\n\n\n\n                30 \n                January \n                2025\n              \nPart II (B) - General Assembly Emergency Special Sessions (documents received from the Secretariat of the United Nations)\nAvailable in:\n\nEnglish\nFrench\n\n\n\n\nPart II (A) - Material of the United Nations Relating to the Questions before the Court (documents received from the Secretariat of the United Nations)\n\n\n                30 \n                January \n                2025\n              \nPart II (A) - Material of the United Nations Relating to the Questions before the Court (documents received from the Secretariat of the United Nations)\n\n\n\nPart II (A) (1): Israeli settlements\n\n\nEnglish\nFrench\n\n\n\n\nPart II (A) (2): Living conditions of the Palestinian people\n\n\nEnglish\nFrench\n\n\n\n\nPart II (A) (3): Palestinian women and children\n\n\nEnglish\nFrench\n\n\n\n\nPart II (A) (4): Permanent sovereignty over natural and national resources\n\n\nEnglish\nFrench\n\n\n\n\nPart II (A) (5): Right to self-determination\n\n\nEnglish\nFrench\n\n\n\n\nPart II (A) (6): Question of Palestine\n\n\nEnglish\nFrench\n\n\n\n\nPart II (A) (7): Situation in the Middle East\n\n\nEnglish\nFrench\n\n\n\n\nPart II (A) (8): Special Committee to investigate Israeli practices affecting the human rights of the Palestinian people\n\n\nEnglish\nFrench\n\n\n\n\nPart II (A) (9): United Nations Relief and Works Agency for Palestine refugees in the Near East (UNRWA)\n\n\nEnglish\nFrench\n\n\n\n\nPart II (A) (10): Assistance to the Palestinian people\n\n\nEnglish\nFrench\n\n\n\n\nPart II (A) (11): Safety and security of humanitarian personnel and protection of United Nations personnel\n\n\nEnglish\nFrench\n\n\n\n\n\n\n\nPart I: Material relating to the request by the General Assembly for an advisory opinion of the Court\n\n\n\n                30 \n                January \n                2025\n              \nPart I: Material relating to the request by the General Assembly for an advisory opinion of the Court\nAvailable in:\n\nEnglish\nFrench\n\n\n\n\n\nList of Documents (documents received from the Secretariat of the United Nations)\n\n\n\n                30 \n                January \n                2025\n              \nList of Documents (documents received from the Secretariat of the United Nations)\nAvailable in:\n\nEnglish\nFrench\n\n\n\n\n\nIntroductory Note (documents received from the Secretariat of the United Nations)\n\n\n\n                30 \n                January \n                2025\n              \nIntroductory Note (documents received from the Secretariat of the United Nations)\nAvailable in:\n\nEnglish\nFrench\n\n\n\n\n\n                  Press release 2024/86\n                \n\n\n                24 \n                December \n                2024\n              \nObligations of Israel in relation to the presence and activities of the United Nations, other international organizations and third States in and in relation to the Occupied Palestinian Territory (Request for Advisory Opinion) - The President of the Court makes an Order organizing the proceedings and fixes the time-limits for the presentation of written statements\nAvailable in:\n\nEnglish\nFrench\n\n\n\n\n\nOrder of 23 December 2024\n\n\nFixing of time-limits: Presentation of written statements\nAvailable in:\n\nEnglish\nFrench\n\n\n\n\n\n                  Press release 2024/84\n                \n\n\n                23 \n                December \n                2024\n              \nThe General Assembly of the United Nations requests an advisory opinion from the Court on “the obligations of Israel in relation to the presence and activities of the United Nations, other international organizations and third States” in and in relation to the Occupied Palestinian Territory\nAvailable in:\n\nEnglish\nFrench\n\n\n\n\n\nRequest for Advisory Opinion\n\n\n\n                23 \n                December \n                2024\n              \nRequest for Advisory Opinion\nAvailable in:\n\nEnglish\nFrench\n\n\n\n\n\n\n\n\n\n\n\n\n\n\n\n\nLinks\n\nObligations of Israel in relation to the Presence and Activities of the United Nations, Other International Organizations and Third States in and in relation to the Occupied Palestinian Territory\n\n\n\n\n\nLatest Developments\n\n\n\n                  Press release 2025/13\n                \n\n\n                12 \n                March \n                2025\n              \nObligations of Israel in relation to the Presence and Activities of the United Nations, Other International Organizations and Third States in and in relation to the Occupied Palestinian Territory (Request for Advisory Opinion) - Filing of written statements and opening date of the public hearings\nAvailable in:\n\nEnglish\nFrench\n\n\n\n\n\n                  Press release 2025/9\n                \n\n\n                20 \n                February \n                2025\n              \nObligations of Israel in relation to the Presence and Activities of the United Nations, Other International Organizations and Third States in and in relation to the Occupied Palestinian Territory (Request for Advisory Opinion) - The Court authorizes the African Union to participate in the proceedings\nAvailable in:\n\nEnglish\nFrench\n\n\n\n\n\n                  Press release 2025/8\n                \n\n\n                7 \n                February \n                2025\n              \nObligations of Israel in relation to the Presence and Activities of the United Nations, Other International Organizations and Third States in and in relation to the Occupied Palestinian Territory (Request for Advisory Opinion) - The Court authorizes the League of Arab States to participate in the proceedings\nAvailable in:\n\nEnglish\nFrench\n\n\n\n\n\n                  Press release 2025/7\n                \n\n\n                4 \n                February \n                2025\n              \nObligations of Israel in relation to the Presence and Activities of the United Nations, Other International Organizations and Third States in and in relation to the Occupied Palestinian Territory (Request for Advisory Opinion) - The Court authorizes the Organisation of Islamic Cooperation to participate in the proceedings\nAvailable in:\n\nEnglish\nFrench\n\n\n\n\n\nPart II (F): Other documents without document symbols (documents received from the Secretariat of the United Nations)\n\n\n\n                30 \n                January \n                2025\n              \nPart II (F): Other documents without document symbols (documents received from the Secretariat of the United Nations)\nAvailable in:\n\nEnglish\nFrench\n\n\n\n\n\nPart II (E): Relevant instruments (documents received from the Secretariat of the United Nations)\n\n\n\n                30 \n                January \n                2025\n              \nPart II (E): Relevant instruments (documents received from the Secretariat of the United Nations)\nAvailable in:\n\nEnglish\nFrench\n\n\n\n\nPart II (D): Human rights documentation\n\n\n                30 \n                January \n                2025\n              \nPart II (D): Human rights documentation\n\n\n\nPart II (D) (1): General Assembly\n\n\nEnglish\nFrench\n\n\n\n\nPart II (D) (2): Human Rights Council\n\n\nEnglish\nFrench\n\n\n\n\nPart II (D) (3): Commission on Human Rights\n\n\nEnglish\nFrench\n\n\n\n\nPart II (D) (4): Treaty bodies\n\n\nEnglish\nFrench\n\n\n\n\nPart II (D) (5): Universal periodic review\n\n\nEnglish\nFrench\n\n\n\n\n\n\nPart II (C) - Security Council (documents received from the Secretariat of the United Nations)\n\n\n                30 \n                January \n                2025\n              \nPart II (C) - Security Council (documents received from the Secretariat of the United Nations)\n\n\n\nPart II (C) (1): Documentation relating to the situation in the Occupied Palestinian Territories\n\n\nEnglish\nFrench\n\n\n\n\nPart II (C) (2): Documentation relating to the safety and security of humanitarian personnel and United Nations and associated personnel\n\n\nEnglish\nFrench\n\n\n\n\n\n\n\nPart II (B) - General Assembly Emergency Special Sessions (documents received from the Secretariat of the United Nations)\n\n\n\n                30 \n                January \n                2025\n              \nPart II (B) - General Assembly Emergency Special Sessions (documents received from the Secretariat of the United Nations)\nAvailable in:\n\nEnglish\nFrench\n\n\n\n\nPart II (A) - Material of the United Nations Relating to the Questions before the Court (documents received from the Secretariat of the United Nations)\n\n\n                30 \n                January \n                2025\n              \nPart II (A) - Material of the United Nations Relating to the Questions before the Court (documents received from the Secretariat of the United Nations)\n\n\n\nPart II (A) (1): Israeli settlements\n\n\nEnglish\nFrench\n\n\n\n\nPart II (A) (2): Living conditions of the Palestinian people\n\n\nEnglish\nFrench\n\n\n\n\nPart II (A) (3): Palestinian women and children\n\n\nEnglish\nFrench\n\n\n\n\nPart II (A) (4): Permanent sovereignty over natural and national resources\n\n\nEnglish\nFrench\n\n\n\n\nPart II (A) (5): Right to self-determination\n\n\nEnglish\nFrench\n\n\n\n\nPart II (A) (6): Question of Palestine\n\n\nEnglish\nFrench\n\n\n\n\nPart II (A) (7): Situation in the Middle East\n\n\nEnglish\nFrench\n\n\n\n\nPart II (A) (8): Special Committee to investigate Israeli practices affecting the human rights of the Palestinian people\n\n\nEnglish\nFrench\n\n\n\n\nPart II (A) (9): United Nations Relief and Works Agency for Palestine refugees in the Near East (UNRWA)\n\n\nEnglish\nFrench\n\n\n\n\nPart II (A) (10): Assistance to the Palestinian people\n\n\nEnglish\nFrench\n\n\n\n\nPart II (A) (11): Safety and security of humanitarian personnel and protection of United Nations personnel\n\n\nEnglish\nFrench\n\n\n\n\n\n\n\nPart I: Material relating to the request by the General Assembly for an advisory opinion of the Court\n\n\n\n                30 \n                January \n                2025\n              \nPart I: Material relating to the request by the General Assembly for an advisory opinion of the Court\nAvailable in:\n\nEnglish\nFrench\n\n\n\n\n\nList of Documents (documents received from the Secretariat of the United Nations)\n\n\n\n                30 \n                January \n                2025\n              \nList of Documents (documents received from the Secretariat of the United Nations)\nAvailable in:\n\nEnglish\nFrench\n\n\n\n\n\nIntroductory Note (documents received from the Secretariat of the United Nations)\n\n\n\n                30 \n                January \n                2025\n              \nIntroductory Note (documents received from the Secretariat of the United Nations)\nAvailable in:\n\nEnglish\nFrench\n\n\n\n\n\n                  Press release 2024/86\n                \n\n\n                24 \n                December \n                2024\n              \nObligations of Israel in relation to the presence and activities of the United Nations, other international organizations and third States in and in relation to the Occupied Palestinian Territory (Request for Advisory Opinion) - The President of the Court makes an Order organizing the proceedings and fixes the time-limits for the presentation of written statements\nAvailable in:\n\nEnglish\nFrench\n\n\n\n\n\nOrder of 23 December 2024\n\n\nFixing of time-limits: Presentation of written statements\nAvailable in:\n\nEnglish\nFrench\n\n\n\n\n\n                  Press release 2024/84\n                \n\n\n                23 \n                December \n                2024\n              \nThe General Assembly of the United Nations requests an advisory opinion from the Court on “the obligations of Israel in relation to the presence and activities of the United Nations, other international organizations and third States” in and in relation to the Occupied Palestinian Territory\nAvailable in:\n\nEnglish\nFrench\n\n\n\n\n\nRequest for Advisory Opinion\n\n\n\n                23 \n                December \n                2024\n              \nRequest for Advisory Opinion\nAvailable in:\n\nEnglish\nFrench\n\n\n\n\n\n\n\n\n\n\n\n\n\n\n\n\nLinks\n\nObligations of Israel in relation to the Presence and Activities of the United Nations, Other International Organizations and Third States in and in relation to the Occupied Palestinian Territory\n\n\n\n\n\nLatest Developments\n\n\n\n                  Press release 2025/13\n                \n\n\n                12 \n                March \n                2025\n              \nObligations of Israel in relation to the Presence and Activities of the United Nations, Other International Organizations and Third States in and in relation to the Occupied Palestinian Territory (Request for Advisory Opinion) - Filing of written statements and opening date of the public hearings\nAvailable in:\n\nEnglish\nFrench\n\n\n\n\n\n                  Press release 2025/9\n                \n\n\n                20 \n                February \n                2025\n              \nObligations of Israel in relation to the Presence and Activities of the United Nations, Other International Organizations and Third States in and in relation to the Occupied Palestinian Territory (Request for Advisory Opinion) - The Court authorizes the African Union to participate in the proceedings\nAvailable in:\n\nEnglish\nFrench\n\n\n\n\n\n                  Press release 2025/8\n                \n\n\n                7 \n                February \n                2025\n              \nObligations of Israel in relation to the Presence and Activities of the United Nations, Other International Organizations and Third States in and in relation to the Occupied Palestinian Territory (Request for Advisory Opinion) - The Court authorizes the League of Arab States to participate in the proceedings\nAvailable in:\n\nEnglish\nFrench\n\n\n\n\n\n                  Press release 2025/7\n                \n\n\n                4 \n                February \n                2025\n              \nObligations of Israel in relation to the Presence and Activities of the United Nations, Other International Organizations and Third States in and in relation to the Occupied Palestinian Territory (Request for Advisory Opinion) - The Court authorizes the Organisation of Islamic Cooperation to participate in the proceedings\nAvailable in:\n\nEnglish\nFrench\n\n\n\n\n\nPart II (F): Other documents without document symbols (documents received from the Secretariat of the United Nations)\n\n\n\n                30 \n                January \n                2025\n              \nPart II (F): Other documents without document symbols (documents received from the Secretariat of the United Nations)\nAvailable in:\n\nEnglish\nFrench\n\n\n\n\n\nPart II (E): Relevant instruments (documents received from the Secretariat of the United Nations)\n\n\n\n                30 \n                January \n                2025\n              \nPart II (E): Relevant instruments (documents received from the Secretariat of the United Nations)\nAvailable in:\n\nEnglish\nFrench\n\n\n\n\nPart II (D): Human rights documentation\n\n\n                30 \n                January \n                2025\n              \nPart II (D): Human rights documentation\n\n\n\nPart II (D) (1): General Assembly\n\n\nEnglish\nFrench\n\n\n\n\nPart II (D) (2): Human Rights Council\n\n\nEnglish\nFrench\n\n\n\n\nPart II (D) (3): Commission on Human Rights\n\n\nEnglish\nFrench\n\n\n\n\nPart II (D) (4): Treaty bodies\n\n\nEnglish\nFrench\n\n\n\n\nPart II (D) (5): Universal periodic review\n\n\nEnglish\nFrench\n\n\n\n\n\n\nPart II (C) - Security Council (documents received from the Secretariat of the United Nations)\n\n\n                30 \n                January \n                2025\n              \nPart II (C) - Security Council (documents received from the Secretariat of the United Nations)\n\n\n\nPart II (C) (1): Documentation relating to the situation in the Occupied Palestinian Territories\n\n\nEnglish\nFrench\n\n\n\n\nPart II (C) (2): Documentation relating to the safety and security of humanitarian personnel and United Nations and associated personnel\n\n\nEnglish\nFrench\n\n\n\n\n\n\n\nPart II (B) - General Assembly Emergency Special Sessions (documents received from the Secretariat of the United Nations)\n\n\n\n                30 \n                January \n                2025\n              \nPart II (B) - General Assembly Emergency Special Sessions (documents received from the Secretariat of the United Nations)\nAvailable in:\n\nEnglish\nFrench\n\n\n\n\nPart II (A) - Material of the United Nations Relating to the Questions before the Court (documents received from the Secretariat of the United Nations)\n\n\n                30 \n                January \n                2025\n              \nPart II (A) - Material of the United Nations Relating to the Questions before the Court (documents received from the Secretariat of the United Nations)\n\n\n\nPart II (A) (1): Israeli settlements\n\n\nEnglish\nFrench\n\n\n\n\nPart II (A) (2): Living conditions of the Palestinian people\n\n\nEnglish\nFrench\n\n\n\n\nPart II (A) (3): Palestinian women and children\n\n\nEnglish\nFrench\n\n\n\n\nPart II (A) (4): Permanent sovereignty over natural and national resources\n\n\nEnglish\nFrench\n\n\n\n\nPart II (A) (5): Right to self-determination\n\n\nEnglish\nFrench\n\n\n\n\nPart II (A) (6): Question of Palestine\n\n\nEnglish\nFrench\n\n\n\n\nPart II (A) (7): Situation in the Middle East\n\n\nEnglish\nFrench\n\n\n\n\nPart II (A) (8): Special Committee to investigate Israeli practices affecting the human rights of the Palestinian people\n\n\nEnglish\nFrench\n\n\n\n\nPart II (A) (9): United Nations Relief and Works Agency for Palestine refugees in the Near East (UNRWA)\n\n\nEnglish\nFrench\n\n\n\n\nPart II (A) (10): Assistance to the Palestinian people\n\n\nEnglish\nFrench\n\n\n\n\nPart II (A) (11): Safety and security of humanitarian personnel and protection of United Nations personnel\n\n\nEnglish\nFrench\n\n\n\n\n\n\n\nPart I: Material relating to the request by the General Assembly for an advisory opinion of the Court\n\n\n\n                30 \n                January \n                2025\n              \nPart I: Material relating to the request by the General Assembly for an advisory opinion of the Court\nAvailable in:\n\nEnglish\nFrench\n\n\n\n\n\nList of Documents (documents received from the Secretariat of the United Nations)\n\n\n\n                30 \n                January \n                2025\n              \nList of Documents (documents received from the Secretariat of the United Nations)\nAvailable in:\n\nEnglish\nFrench\n\n\n\n\n\nIntroductory Note (documents received from the Secretariat of the United Nations)\n\n\n\n                30 \n                January \n                2025\n              \nIntroductory Note (documents received from the Secretariat of the United Nations)\nAvailable in:\n\nEnglish\nFrench\n\n\n\n\n\n                  Press release 2024/86\n                \n\n\n                24 \n                December \n                2024\n              \nObligations of Israel in relation to the presence and activities of the United Nations, other international organizations and third States in and in relation to the Occupied Palestinian Territory (Request for Advisory Opinion) - The President of the Court makes an Order organizing the proceedings and fixes the time-limits for the presentation of written statements\nAvailable in:\n\nEnglish\nFrench\n\n\n\n\n\nOrder of 23 December 2024\n\n\nFixing of time-limits: Presentation of written statements\nAvailable in:\n\nEnglish\nFrench\n\n\n\n\n\n                  Press release 2024/84\n                \n\n\n                23 \n                December \n                2024\n              \nThe General Assembly of the United Nations requests an advisory opinion from the Court on “the obligations of Israel in relation to the presence and activities of the United Nations, other international organizations and third States” in and in relation to the Occupied Palestinian Territory\nAvailable in:\n\nEnglish\nFrench\n\n\n\n\n\nRequest for Advisory Opinion\n\n\n\n                23 \n                December \n                2024\n              \nRequest for Advisory Opinion\nAvailable in:\n\nEnglish\nFrench\n\n\n\n\n\n\n\n\n\n\n\n\n\n\n\n\nLinks\n\nObligations of Israel in relation to the Presence and Activities of the United Nations, Other International Organizations and Third States in and in relation to the Occupied Palestinian Territory\n\n\n\n\n\nLatest Developments\n\n\n\n                  Press release 2025/13\n                \n\n\n                12 \n                March \n                2025\n              \nObligations of Israel in relation to the Presence and Activities of the United Nations, Other International Organizations and Third States in and in relation to the Occupied Palestinian Territory (Request for Advisory Opinion) - Filing of written statements and opening date of the public hearings\nAvailable in:\n\nEnglish\nFrench\n\n\n\n\n\n                  Press release 2025/9\n                \n\n\n                20 \n                February \n                2025\n              \nObligations of Israel in relation to the Presence and Activities of the United Nations, Other International Organizations and Third States in and in relation to the Occupied Palestinian Territory (Request for Advisory Opinion) - The Court authorizes the African Union to participate in the proceedings\nAvailable in:\n\nEnglish\nFrench\n\n\n\n\n\n                  Press release 2025/8\n                \n\n\n                7 \n                February \n                2025\n              \nObligations of Israel in relation to the Presence and Activities of the United Nations, Other International Organizations and Third States in and in relation to the Occupied Palestinian Territory (Request for Advisory Opinion) - The Court authorizes the League of Arab States to participate in the proceedings\nAvailable in:\n\nEnglish\nFrench\n\n\n\n\n\n                  Press release 2025/7\n                \n\n\n                4 \n                February \n                2025\n              \nObligations of Israel in relation to the Presence and Activities of the United Nations, Other International Organizations and Third States in and in relation to the Occupied Palestinian Territory (Request for Advisory Opinion) - The Court authorizes the Organisation of Islamic Cooperation to participate in the proceedings\nAvailable in:\n\nEnglish\nFrench\n\n\n\n\n\nPart II (F): Other documents without document symbols (documents received from the Secretariat of the United Nations)\n\n\n\n                30 \n                January \n                2025\n              \nPart II (F): Other documents without document symbols (documents received from the Secretariat of the United Nations)\nAvailable in:\n\nEnglish\nFrench\n\n\n\n\n\nPart II (E): Relevant instruments (documents received from the Secretariat of the United Nations)\n\n\n\n                30 \n                January \n                2025\n              \nPart II (E): Relevant instruments (documents received from the Secretariat of the United Nations)\nAvailable in:\n\nEnglish\nFrench\n\n\n\n\nPart II (D): Human rights documentation\n\n\n                30 \n                January \n                2025\n              \nPart II (D): Human rights documentation\n\n\n\nPart II (D) (1): General Assembly\n\n\nEnglish\nFrench\n\n\n\n\nPart II (D) (2): Human Rights Council\n\n\nEnglish\nFrench\n\n\n\n\nPart II (D) (3): Commission on Human Rights\n\n\nEnglish\nFrench\n\n\n\n\nPart II (D) (4): Treaty bodies\n\n\nEnglish\nFrench\n\n\n\n\nPart II (D) (5): Universal periodic review\n\n\nEnglish\nFrench\n\n\n\n\n\n\nPart II (C) - Security Council (documents received from the Secretariat of the United Nations)\n\n\n                30 \n                January \n                2025\n              \nPart II (C) - Security Council (documents received from the Secretariat of the United Nations)\n\n\n\nPart II (C) (1): Documentation relating to the situation in the Occupied Palestinian Territories\n\n\nEnglish\nFrench\n\n\n\n\nPart II (C) (2): Documentation relating to the safety and security of humanitarian personnel and United Nations and associated personnel\n\n\nEnglish\nFrench\n\n\n\n\n\n\n\nPart II (B) - General Assembly Emergency Special Sessions (documents received from the Secretariat of the United Nations)\n\n\n\n                30 \n                January \n                2025\n              \nPart II (B) - General Assembly Emergency Special Sessions (documents received from the Secretariat of the United Nations)\nAvailable in:\n\nEnglish\nFrench\n\n\n\n\nPart II (A) - Material of the United Nations Relating to the Questions before the Court (documents received from the Secretariat of the United Nations)\n\n\n                30 \n                January \n                2025\n              \nPart II (A) - Material of the United Nations Relating to the Questions before the Court (documents received from the Secretariat of the United Nations)\n\n\n\nPart II (A) (1): Israeli settlements\n\n\nEnglish\nFrench\n\n\n\n\nPart II (A) (2): Living conditions of the Palestinian people\n\n\nEnglish\nFrench\n\n\n\n\nPart II (A) (3): Palestinian women and children\n\n\nEnglish\nFrench\n\n\n\n\nPart II (A) (4): Permanent sovereignty over natural and national resources\n\n\nEnglish\nFrench\n\n\n\n\nPart II (A) (5): Right to self-determination\n\n\nEnglish\nFrench\n\n\n\n\nPart II (A) (6): Question of Palestine\n\n\nEnglish\nFrench\n\n\n\n\nPart II (A) (7): Situation in the Middle East\n\n\nEnglish\nFrench\n\n\n\n\nPart II (A) (8): Special Committee to investigate Israeli practices affecting the human rights of the Palestinian people\n\n\nEnglish\nFrench\n\n\n\n\nPart II (A) (9): United Nations Relief and Works Agency for Palestine refugees in the Near East (UNRWA)\n\n\nEnglish\nFrench\n\n\n\n\nPart II (A) (10): Assistance to the Palestinian people\n\n\nEnglish\nFrench\n\n\n\n\nPart II (A) (11): Safety and security of humanitarian personnel and protection of United Nations personnel\n\n\nEnglish\nFrench\n\n\n\n\n\n\n\nPart I: Material relating to the request by the General Assembly for an advisory opinion of the Court\n\n\n\n                30 \n                January \n                2025\n              \nPart I: Material relating to the request by the General Assembly for an advisory opinion of the Court\nAvailable in:\n\nEnglish\nFrench\n\n\n\n\n\nList of Documents (documents received from the Secretariat of the United Nations)\n\n\n\n                30 \n                January \n                2025\n              \nList of Documents (documents received from the Secretariat of the United Nations)\nAvailable in:\n\nEnglish\nFrench\n\n\n\n\n\nIntroductory Note (documents received from the Secretariat of the United Nations)\n\n\n\n                30 \n                January \n                2025\n              \nIntroductory Note (documents received from the Secretariat of the United Nations)\nAvailable in:\n\nEnglish\nFrench\n\n\n\n\n\n                  Press release 2024/86\n                \n\n\n                24 \n                December \n                2024\n              \nObligations of Israel in relation to the presence and activities of the United Nations, other international organizations and third States in and in relation to the Occupied Palestinian Territory (Request for Advisory Opinion) - The President of the Court makes an Order organizing the proceedings and fixes the time-limits for the presentation of written statements\nAvailable in:\n\nEnglish\nFrench\n\n\n\n\n\nOrder of 23 December 2024\n\n\nFixing of time-limits: Presentation of written statements\nAvailable in:\n\nEnglish\nFrench\n\n\n\n\n\n                  Press release 2024/84\n                \n\n\n                23 \n                December \n                2024\n              \nThe General Assembly of the United Nations requests an advisory opinion from the Court on “the obligations of Israel in relation to the presence and activities of the United Nations, other international organizations and third States” in and in relation to the Occupied Palestinian Territory\nAvailable in:\n\nEnglish\nFrench\n\n\n\n\n\nRequest for Advisory Opinion\n\n\n\n                23 \n                December \n                2024\n              \nRequest for Advisory Opinion\nAvailable in:\n\nEnglish\nFrench\n\n\n\n\n\n\n\n\n\n\n\n\n\n\n\n\nLinks\n\nObligations of Israel in relation to the Presence and Activities of the United Nations, Other International Organizations and Third States in and in relation to the Occupied Palestinian Territory\n\n\n\n\n\nLatest Developments\n\n\n\n                  Press release 2025/13\n                \n\n\n                12 \n                March \n                2025\n              \nObligations of Israel in relation to the Presence and Activities of the United Nations, Other International Organizations and Third States in and in relation to the Occupied Palestinian Territory (Request for Advisory Opinion) - Filing of written statements and opening date of the public hearings\nAvailable in:\n\nEnglish\nFrench\n\n\n\n\n\n                  Press release 2025/9\n                \n\n\n                20 \n                February \n                2025\n              \nObligations of Israel in relation to the Presence and Activities of the United Nations, Other International Organizations and Third States in and in relation to the Occupied Palestinian Territory (Request for Advisory Opinion) - The Court authorizes the African Union to participate in the proceedings\nAvailable in:\n\nEnglish\nFrench\n\n\n\n\n\n                  Press release 2025/8\n                \n\n\n                7 \n                February \n                2025\n              \nObligations of Israel in relation to the Presence and Activities of the United Nations, Other International Organizations and Third States in and in relation to the Occupied Palestinian Territory (Request for Advisory Opinion) - The Court authorizes the League of Arab States to participate in the proceedings\nAvailable in:\n\nEnglish\nFrench\n\n\n\n\n\n                  Press release 2025/7\n                \n\n\n                4 \n                February \n                2025\n              \nObligations of Israel in relation to the Presence and Activities of the United Nations, Other International Organizations and Third States in and in relation to the Occupied Palestinian Territory (Request for Advisory Opinion) - The Court authorizes the Organisation of Islamic Cooperation to participate in the proceedings\nAvailable in:\n\nEnglish\nFrench\n\n\n\n\n\nPart II (F): Other documents without document symbols (documents received from the Secretariat of the United Nations)\n\n\n\n                30 \n                January \n                2025\n              \nPart II (F): Other documents without document symbols (documents received from the Secretariat of the United Nations)\nAvailable in:\n\nEnglish\nFrench\n\n\n\n\n\nPart II (E): Relevant instruments (documents received from the Secretariat of the United Nations)\n\n\n\n                30 \n                January \n                2025\n              \nPart II (E): Relevant instruments (documents received from the Secretariat of the United Nations)\nAvailable in:\n\nEnglish\nFrench\n\n\n\n\nPart II (D): Human rights documentation\n\n\n                30 \n                January \n                2025\n              \nPart II (D): Human rights documentation\n\n\n\nPart II (D) (1): General Assembly\n\n\nEnglish\nFrench\n\n\n\n\nPart II (D) (2): Human Rights Council\n\n\nEnglish\nFrench\n\n\n\n\nPart II (D) (3): Commission on Human Rights\n\n\nEnglish\nFrench\n\n\n\n\nPart II (D) (4): Treaty bodies\n\n\nEnglish\nFrench\n\n\n\n\nPart II (D) (5): Universal periodic review\n\n\nEnglish\nFrench\n\n\n\n\n\n\nPart II (C) - Security Council (documents received from the Secretariat of the United Nations)\n\n\n                30 \n                January \n                2025\n              \nPart II (C) - Security Council (documents received from the Secretariat of the United Nations)\n\n\n\nPart II (C) (1): Documentation relating to the situation in the Occupied Palestinian Territories\n\n\nEnglish\nFrench\n\n\n\n\nPart II (C) (2): Documentation relating to the safety and security of humanitarian personnel and United Nations and associated personnel\n\n\nEnglish\nFrench\n\n\n\n\n\n\n\nPart II (B) - General Assembly Emergency Special Sessions (documents received from the Secretariat of the United Nations)\n\n\n\n                30 \n                January \n                2025\n              \nPart II (B) - General Assembly Emergency Special Sessions (documents received from the Secretariat of the United Nations)\nAvailable in:\n\nEnglish\nFrench\n\n\n\n\nPart II (A) - Material of the United Nations Relating to the Questions before the Court (documents received from the Secretariat of the United Nations)\n\n\n                30 \n                January \n                2025\n              \nPart II (A) - Material of the United Nations Relating to the Questions before the Court (documents received from the Secretariat of the United Nations)\n\n\n\nPart II (A) (1): Israeli settlements\n\n\nEnglish\nFrench\n\n\n\n\nPart II (A) (2): Living conditions of the Palestinian people\n\n\nEnglish\nFrench\n\n\n\n\nPart II (A) (3): Palestinian women and children\n\n\nEnglish\nFrench\n\n\n\n\nPart II (A) (4): Permanent sovereignty over natural and national resources\n\n\nEnglish\nFrench\n\n\n\n\nPart II (A) (5): Right to self-determination\n\n\nEnglish\nFrench\n\n\n\n\nPart II (A) (6): Question of Palestine\n\n\nEnglish\nFrench\n\n\n\n\nPart II (A) (7): Situation in the Middle East\n\n\nEnglish\nFrench\n\n\n\n\nPart II (A) (8): Special Committee to investigate Israeli practices affecting the human rights of the Palestinian people\n\n\nEnglish\nFrench\n\n\n\n\nPart II (A) (9): United Nations Relief and Works Agency for Palestine refugees in the Near East (UNRWA)\n\n\nEnglish\nFrench\n\n\n\n\nPart II (A) (10): Assistance to the Palestinian people\n\n\nEnglish\nFrench\n\n\n\n\nPart II (A) (11): Safety and security of humanitarian personnel and protection of United Nations personnel\n\n\nEnglish\nFrench\n\n\n\n\n\n\n\nPart I: Material relating to the request by the General Assembly for an advisory opinion of the Court\n\n\n\n                30 \n                January \n                2025\n              \nPart I: Material relating to the request by the General Assembly for an advisory opinion of the Court\nAvailable in:\n\nEnglish\nFrench\n\n\n\n\n\nList of Documents (documents received from the Secretariat of the United Nations)\n\n\n\n                30 \n                January \n                2025\n              \nList of Documents (documents received from the Secretariat of the United Nations)\nAvailable in:\n\nEnglish\nFrench\n\n\n\n\n\nIntroductory Note (documents received from the Secretariat of the United Nations)\n\n\n\n                30 \n                January \n                2025\n              \nIntroductory Note (documents received from the Secretariat of the United Nations)\nAvailable in:\n\nEnglish\nFrench\n\n\n\n\n\n                  Press release 2024/86\n                \n\n\n                24 \n                December \n                2024\n              \nObligations of Israel in relation to the presence and activities of the United Nations, other international organizations and third States in and in relation to the Occupied Palestinian Territory (Request for Advisory Opinion) - The President of the Court makes an Order organizing the proceedings and fixes the time-limits for the presentation of written statements\nAvailable in:\n\nEnglish\nFrench\n\n\n\n\n\nOrder of 23 December 2024\n\n\nFixing of time-limits: Presentation of written statements\nAvailable in:\n\nEnglish\nFrench\n\n\n\n\n\n                  Press release 2024/84\n                \n\n\n                23 \n                December \n                2024\n              \nThe General Assembly of the United Nations requests an advisory opinion from the Court on “the obligations of Israel in relation to the presence and activities of the United Nations, other international organizations and third States” in and in relation to the Occupied Palestinian Territory\nAvailable in:\n\nEnglish\nFrench\n\n\n\n\n\nRequest for Advisory Opinion\n\n\n\n                23 \n                December \n                2024\n              \nRequest for Advisory Opinion\nAvailable in:\n\nEnglish\nFrench\n\nObligations of Israel in relation to the Presence and Activities of the United Nations, Other International Organizations and Third States in and in relation to the Occupied Palestinian Territory\n\n\n\n\n\nLatest Developments\n\n\n\n                  Press release 2025/13\n                \n\n\n                12 \n                March \n                2025\n              \nObligations of Israel in relation to the Presence and Activities of the United Nations, Other International Organizations and Third States in and in relation to the Occupied Palestinian Territory (Request for Advisory Opinion) - Filing of written statements and opening date of the public hearings\nAvailable in:\n\nEnglish\nFrench\n\n\n\n\n\n                  Press release 2025/9\n                \n\n\n                20 \n                February \n                2025\n              \nObligations of Israel in relation to the Presence and Activities of the United Nations, Other International Organizations and Third States in and in relation to the Occupied Palestinian Territory (Request for Advisory Opinion) - The Court authorizes the African Union to participate in the proceedings\nAvailable in:\n\nEnglish\nFrench\n\n\n\n\n\n                  Press release 2025/8\n                \n\n\n                7 \n                February \n                2025\n              \nObligations of Israel in relation to the Presence and Activities of the United Nations, Other International Organizations and Third States in and in relation to the Occupied Palestinian Territory (Request for Advisory Opinion) - The Court authorizes the League of Arab States to participate in the proceedings\nAvailable in:\n\nEnglish\nFrench\n\n\n\n\n\n                  Press release 2025/7\n                \n\n\n                4 \n                February \n                2025\n              \nObligations of Israel in relation to the Presence and Activities of the United Nations, Other International Organizations and Third States in and in relation to the Occupied Palestinian Territory (Request for Advisory Opinion) - The Court authorizes the Organisation of Islamic Cooperation to participate in the proceedings\nAvailable in:\n\nEnglish\nFrench\n\n\n\n\n\nPart II (F): Other documents without document symbols (documents received from the Secretariat of the United Nations)\n\n\n\n                30 \n                January \n                2025\n              \nPart II (F): Other documents without document symbols (documents received from the Secretariat of the United Nations)\nAvailable in:\n\nEnglish\nFrench\n\n\n\n\n\nPart II (E): Relevant instruments (documents received from the Secretariat of the United Nations)\n\n\n\n                30 \n                January \n                2025\n              \nPart II (E): Relevant instruments (documents received from the Secretariat of the United Nations)\nAvailable in:\n\nEnglish\nFrench\n\n\n\n\nPart II (D): Human rights documentation\n\n\n                30 \n                January \n                2025\n              \nPart II (D): Human rights documentation\n\n\n\nPart II (D) (1): General Assembly\n\n\nEnglish\nFrench\n\n\n\n\nPart II (D) (2): Human Rights Council\n\n\nEnglish\nFrench\n\n\n\n\nPart II (D) (3): Commission on Human Rights\n\n\nEnglish\nFrench\n\n\n\n\nPart II (D) (4): Treaty bodies\n\n\nEnglish\nFrench\n\n\n\n\nPart II (D) (5): Universal periodic review\n\n\nEnglish\nFrench\n\n\n\n\n\n\nPart II (C) - Security Council (documents received from the Secretariat of the United Nations)\n\n\n                30 \n                January \n                2025\n              \nPart II (C) - Security Council (documents received from the Secretariat of the United Nations)\n\n\n\nPart II (C) (1): Documentation relating to the situation in the Occupied Palestinian Territories\n\n\nEnglish\nFrench\n\n\n\n\nPart II (C) (2): Documentation relating to the safety and security of humanitarian personnel and United Nations and associated personnel\n\n\nEnglish\nFrench\n\n\n\n\n\n\n\nPart II (B) - General Assembly Emergency Special Sessions (documents received from the Secretariat of the United Nations)\n\n\n\n                30 \n                January \n                2025\n              \nPart II (B) - General Assembly Emergency Special Sessions (documents received from the Secretariat of the United Nations)\nAvailable in:\n\nEnglish\nFrench\n\n\n\n\nPart II (A) - Material of the United Nations Relating to the Questions before the Court (documents received from the Secretariat of the United Nations)\n\n\n                30 \n                January \n                2025\n              \nPart II (A) - Material of the United Nations Relating to the Questions before the Court (documents received from the Secretariat of the United Nations)\n\n\n\nPart II (A) (1): Israeli settlements\n\n\nEnglish\nFrench\n\n\n\n\nPart II (A) (2): Living conditions of the Palestinian people\n\n\nEnglish\nFrench\n\n\n\n\nPart II (A) (3): Palestinian women and children\n\n\nEnglish\nFrench\n\n\n\n\nPart II (A) (4): Permanent sovereignty over natural and national resources\n\n\nEnglish\nFrench\n\n\n\n\nPart II (A) (5): Right to self-determination\n\n\nEnglish\nFrench\n\n\n\n\nPart II (A) (6): Question of Palestine\n\n\nEnglish\nFrench\n\n\n\n\nPart II (A) (7): Situation in the Middle East\n\n\nEnglish\nFrench\n\n\n\n\nPart II (A) (8): Special Committee to investigate Israeli practices affecting the human rights of the Palestinian people\n\n\nEnglish\nFrench\n\n\n\n\nPart II (A) (9): United Nations Relief and Works Agency for Palestine refugees in the Near East (UNRWA)\n\n\nEnglish\nFrench\n\n\n\n\nPart II (A) (10): Assistance to the Palestinian people\n\n\nEnglish\nFrench\n\n\n\n\nPart II (A) (11): Safety and security of humanitarian personnel and protection of United Nations personnel\n\n\nEnglish\nFrench\n\n\n\n\n\n\n\nPart I: Material relating to the request by the General Assembly for an advisory opinion of the Court\n\n\n\n                30 \n                January \n                2025\n              \nPart I: Material relating to the request by the General Assembly for an advisory opinion of the Court\nAvailable in:\n\nEnglish\nFrench\n\n\n\n\n\nList of Documents (documents received from the Secretariat of the United Nations)\n\n\n\n                30 \n                January \n                2025\n              \nList of Documents (documents received from the Secretariat of the United Nations)\nAvailable in:\n\nEnglish\nFrench\n\n\n\n\n\nIntroductory Note (documents received from the Secretariat of the United Nations)\n\n\n\n                30 \n                January \n                2025\n              \nIntroductory Note (documents received from the Secretariat of the United Nations)\nAvailable in:\n\nEnglish\nFrench\n\n\n\n\n\n                  Press release 2024/86\n                \n\n\n                24 \n                December \n                2024\n              \nObligations of Israel in relation to the presence and activities of the United Nations, other international organizations and third States in and in relation to the Occupied Palestinian Territory (Request for Advisory Opinion) - The President of the Court makes an Order organizing the proceedings and fixes the time-limits for the presentation of written statements\nAvailable in:\n\nEnglish\nFrench\n\n\n\n\n\nOrder of 23 December 2024\n\n\nFixing of time-limits: Presentation of written statements\nAvailable in:\n\nEnglish\nFrench\n\n\n\n\n\n                  Press release 2024/84\n                \n\n\n                23 \n                December \n                2024\n              \nThe General Assembly of the United Nations requests an advisory opinion from the Court on “the obligations of Israel in relation to the presence and activities of the United Nations, other international organizations and third States” in and in relation to the Occupied Palestinian Territory\nAvailable in:\n\nEnglish\nFrench\n\n\n\n\n\nRequest for Advisory Opinion\n\n\n\n                23 \n                December \n                2024\n              \nRequest for Advisory Opinion\nAvailable in:\n\nEnglish\nFrench\n\nObligations of Israel in relation to the Presence and Activities of the United Nations, Other International Organizations and Third States in and in relation to the Occupied Palestinian Territory\n\n\n\n\n\nLatest Developments\n\n\n\n                  Press release 2025/13\n                \n\n\n                12 \n                March \n                2025\n              \nObligations of Israel in relation to the Presence and Activities of the United Nations, Other International Organizations and Third States in and in relation to the Occupied Palestinian Territory (Request for Advisory Opinion) - Filing of written statements and opening date of the public hearings\nAvailable in:\n\nEnglish\nFrench\n\n\n\n\n\n                  Press release 2025/9\n                \n\n\n                20 \n                February \n                2025\n              \nObligations of Israel in relation to the Presence and Activities of the United Nations, Other International Organizations and Third States in and in relation to the Occupied Palestinian Territory (Request for Advisory Opinion) - The Court authorizes the African Union to participate in the proceedings\nAvailable in:\n\nEnglish\nFrench\n\n\n\n\n\n                  Press release 2025/8\n                \n\n\n                7 \n                February \n                2025\n              \nObligations of Israel in relation to the Presence and Activities of the United Nations, Other International Organizations and Third States in and in relation to the Occupied Palestinian Territory (Request for Advisory Opinion) - The Court authorizes the League of Arab States to participate in the proceedings\nAvailable in:\n\nEnglish\nFrench\n\n\n\n\n\n                  Press release 2025/7\n                \n\n\n                4 \n                February \n                2025\n              \nObligations of Israel in relation to the Presence and Activities of the United Nations, Other International Organizations and Third States in and in relation to the Occupied Palestinian Territory (Request for Advisory Opinion) - The Court authorizes the Organisation of Islamic Cooperation to participate in the proceedings\nAvailable in:\n\nEnglish\nFrench\n\n\n\n\n\nPart II (F): Other documents without document symbols (documents received from the Secretariat of the United Nations)\n\n\n\n                30 \n                January \n                2025\n              \nPart II (F): Other documents without document symbols (documents received from the Secretariat of the United Nations)\nAvailable in:\n\nEnglish\nFrench\n\n\n\n\n\nPart II (E): Relevant instruments (documents received from the Secretariat of the United Nations)\n\n\n\n                30 \n                January \n                2025\n              \nPart II (E): Relevant instruments (documents received from the Secretariat of the United Nations)\nAvailable in:\n\nEnglish\nFrench\n\n\n\n\nPart II (D): Human rights documentation\n\n\n                30 \n                January \n                2025\n              \nPart II (D): Human rights documentation\n\n\n\nPart II (D) (1): General Assembly\n\n\nEnglish\nFrench\n\n\n\n\nPart II (D) (2): Human Rights Council\n\n\nEnglish\nFrench\n\n\n\n\nPart II (D) (3): Commission on Human Rights\n\n\nEnglish\nFrench\n\n\n\n\nPart II (D) (4): Treaty bodies\n\n\nEnglish\nFrench\n\n\n\n\nPart II (D) (5): Universal periodic review\n\n\nEnglish\nFrench\n\n\n\n\n\n\nPart II (C) - Security Council (documents received from the Secretariat of the United Nations)\n\n\n                30 \n                January \n                2025\n              \nPart II (C) - Security Council (documents received from the Secretariat of the United Nations)\n\n\n\nPart II (C) (1): Documentation relating to the situation in the Occupied Palestinian Territories\n\n\nEnglish\nFrench\n\n\n\n\nPart II (C) (2): Documentation relating to the safety and security of humanitarian personnel and United Nations and associated personnel\n\n\nEnglish\nFrench\n\n\n\n\n\n\n\nPart II (B) - General Assembly Emergency Special Sessions (documents received from the Secretariat of the United Nations)\n\n\n\n                30 \n                January \n                2025\n              \nPart II (B) - General Assembly Emergency Special Sessions (documents received from the Secretariat of the United Nations)\nAvailable in:\n\nEnglish\nFrench\n\n\n\n\nPart II (A) - Material of the United Nations Relating to the Questions before the Court (documents received from the Secretariat of the United Nations)\n\n\n                30 \n                January \n                2025\n              \nPart II (A) - Material of the United Nations Relating to the Questions before the Court (documents received from the Secretariat of the United Nations)\n\n\n\nPart II (A) (1): Israeli settlements\n\n\nEnglish\nFrench\n\n\n\n\nPart II (A) (2): Living conditions of the Palestinian people\n\n\nEnglish\nFrench\n\n\n\n\nPart II (A) (3): Palestinian women and children\n\n\nEnglish\nFrench\n\n\n\n\nPart II (A) (4): Permanent sovereignty over natural and national resources\n\n\nEnglish\nFrench\n\n\n\n\nPart II (A) (5): Right to self-determination\n\n\nEnglish\nFrench\n\n\n\n\nPart II (A) (6): Question of Palestine\n\n\nEnglish\nFrench\n\n\n\n\nPart II (A) (7): Situation in the Middle East\n\n\nEnglish\nFrench\n\n\n\n\nPart II (A) (8): Special Committee to investigate Israeli practices affecting the human rights of the Palestinian people\n\n\nEnglish\nFrench\n\n\n\n\nPart II (A) (9): United Nations Relief and Works Agency for Palestine refugees in the Near East (UNRWA)\n\n\nEnglish\nFrench\n\n\n\n\nPart II (A) (10): Assistance to the Palestinian people\n\n\nEnglish\nFrench\n\n\n\n\nPart II (A) (11): Safety and security of humanitarian personnel and protection of United Nations personnel\n\n\nEnglish\nFrench\n\n\n\n\n\n\n\nPart I: Material relating to the request by the General Assembly for an advisory opinion of the Court\n\n\n\n                30 \n                January \n                2025\n              \nPart I: Material relating to the request by the General Assembly for an advisory opinion of the Court\nAvailable in:\n\nEnglish\nFrench\n\n\n\n\n\nList of Documents (documents received from the Secretariat of the United Nations)\n\n\n\n                30 \n                January \n                2025\n              \nList of Documents (documents received from the Secretariat of the United Nations)\nAvailable in:\n\nEnglish\nFrench\n\n\n\n\n\nIntroductory Note (documents received from the Secretariat of the United Nations)\n\n\n\n                30 \n                January \n                2025\n              \nIntroductory Note (documents received from the Secretariat of the United Nations)\nAvailable in:\n\nEnglish\nFrench\n\n\n\n\n\n                  Press release 2024/86\n                \n\n\n                24 \n                December \n                2024\n              \nObligations of Israel in relation to the presence and activities of the United Nations, other international organizations and third States in and in relation to the Occupied Palestinian Territory (Request for Advisory Opinion) - The President of the Court makes an Order organizing the proceedings and fixes the time-limits for the presentation of written statements\nAvailable in:\n\nEnglish\nFrench\n\n\n\n\n\nOrder of 23 December 2024\n\n\nFixing of time-limits: Presentation of written statements\nAvailable in:\n\nEnglish\nFrench\n\n\n\n\n\n                  Press release 2024/84\n                \n\n\n                23 \n                December \n                2024\n              \nThe General Assembly of the United Nations requests an advisory opinion from the Court on “the obligations of Israel in relation to the presence and activities of the United Nations, other international organizations and third States” in and in relation to the Occupied Palestinian Territory\nAvailable in:\n\nEnglish\nFrench\n\n\n\n\n\nRequest for Advisory Opinion\n\n\n\n                23 \n                December \n                2024\n              \nRequest for Advisory Opinion\nAvailable in:\n\nEnglish\nFrench\n\nObligations of Israel in relation to the Presence and Activities of the United Nations, Other International Organizations and Third States in and in relation to the Occupied Palestinian Territory\n\nObligations of Israel in relation to the Presence and Activities of the United Nations, Other International Organizations and Third States in and in relation to the Occupied Palestinian Territory\n\nObligations of Israel in relation to the Presence and Activities of the United Nations, Other International Organizations and Third States in and in relation to the Occupied Palestinian Territory\n\nLatest Developments\n\n\n\n                  Press release 2025/13\n                \n\n\n                12 \n                March \n                2025\n              \nObligations of Israel in relation to the Presence and Activities of the United Nations, Other International Organizations and Third States in and in relation to the Occupied Palestinian Territory (Request for Advisory Opinion) - Filing of written statements and opening date of the public hearings\nAvailable in:\n\nEnglish\nFrench\n\n\n\n\n\n                  Press release 2025/9\n                \n\n\n                20 \n                February \n                2025\n              \nObligations of Israel in relation to the Presence and Activities of the United Nations, Other International Organizations and Third States in and in relation to the Occupied Palestinian Territory (Request for Advisory Opinion) - The Court authorizes the African Union to participate in the proceedings\nAvailable in:\n\nEnglish\nFrench\n\n\n\n\n\n                  Press release 2025/8\n                \n\n\n                7 \n                February \n                2025\n              \nObligations of Israel in relation to the Presence and Activities of the United Nations, Other International Organizations and Third States in and in relation to the Occupied Palestinian Territory (Request for Advisory Opinion) - The Court authorizes the League of Arab States to participate in the proceedings\nAvailable in:\n\nEnglish\nFrench\n\n\n\n\n\n                  Press release 2025/7\n                \n\n\n                4 \n                February \n                2025\n              \nObligations of Israel in relation to the Presence and Activities of the United Nations, Other International Organizations and Third States in and in relation to the Occupied Palestinian Territory (Request for Advisory Opinion) - The Court authorizes the Organisation of Islamic Cooperation to participate in the proceedings\nAvailable in:\n\nEnglish\nFrench\n\n\n\n\n\nPart II (F): Other documents without document symbols (documents received from the Secretariat of the United Nations)\n\n\n\n                30 \n                January \n                2025\n              \nPart II (F): Other documents without document symbols (documents received from the Secretariat of the United Nations)\nAvailable in:\n\nEnglish\nFrench\n\n\n\n\n\nPart II (E): Relevant instruments (documents received from the Secretariat of the United Nations)\n\n\n\n                30 \n                January \n                2025\n              \nPart II (E): Relevant instruments (documents received from the Secretariat of the United Nations)\nAvailable in:\n\nEnglish\nFrench\n\n\n\n\nPart II (D): Human rights documentation\n\n\n                30 \n                January \n                2025\n              \nPart II (D): Human rights documentation\n\n\n\nPart II (D) (1): General Assembly\n\n\nEnglish\nFrench\n\n\n\n\nPart II (D) (2): Human Rights Council\n\n\nEnglish\nFrench\n\n\n\n\nPart II (D) (3): Commission on Human Rights\n\n\nEnglish\nFrench\n\n\n\n\nPart II (D) (4): Treaty bodies\n\n\nEnglish\nFrench\n\n\n\n\nPart II (D) (5): Universal periodic review\n\n\nEnglish\nFrench\n\n\n\n\n\n\nPart II (C) - Security Council (documents received from the Secretariat of the United Nations)\n\n\n                30 \n                January \n                2025\n              \nPart II (C) - Security Council (documents received from the Secretariat of the United Nations)\n\n\n\nPart II (C) (1): Documentation relating to the situation in the Occupied Palestinian Territories\n\n\nEnglish\nFrench\n\n\n\n\nPart II (C) (2): Documentation relating to the safety and security of humanitarian personnel and United Nations and associated personnel\n\n\nEnglish\nFrench\n\n\n\n\n\n\n\nPart II (B) - General Assembly Emergency Special Sessions (documents received from the Secretariat of the United Nations)\n\n\n\n                30 \n                January \n                2025\n              \nPart II (B) - General Assembly Emergency Special Sessions (documents received from the Secretariat of the United Nations)\nAvailable in:\n\nEnglish\nFrench\n\n\n\n\nPart II (A) - Material of the United Nations Relating to the Questions before the Court (documents received from the Secretariat of the United Nations)\n\n\n                30 \n                January \n                2025\n              \nPart II (A) - Material of the United Nations Relating to the Questions before the Court (documents received from the Secretariat of the United Nations)\n\n\n\nPart II (A) (1): Israeli settlements\n\n\nEnglish\nFrench\n\n\n\n\nPart II (A) (2): Living conditions of the Palestinian people\n\n\nEnglish\nFrench\n\n\n\n\nPart II (A) (3): Palestinian women and children\n\n\nEnglish\nFrench\n\n\n\n\nPart II (A) (4): Permanent sovereignty over natural and national resources\n\n\nEnglish\nFrench\n\n\n\n\nPart II (A) (5): Right to self-determination\n\n\nEnglish\nFrench\n\n\n\n\nPart II (A) (6): Question of Palestine\n\n\nEnglish\nFrench\n\n\n\n\nPart II (A) (7): Situation in the Middle East\n\n\nEnglish\nFrench\n\n\n\n\nPart II (A) (8): Special Committee to investigate Israeli practices affecting the human rights of the Palestinian people\n\n\nEnglish\nFrench\n\n\n\n\nPart II (A) (9): United Nations Relief and Works Agency for Palestine refugees in the Near East (UNRWA)\n\n\nEnglish\nFrench\n\n\n\n\nPart II (A) (10): Assistance to the Palestinian people\n\n\nEnglish\nFrench\n\n\n\n\nPart II (A) (11): Safety and security of humanitarian personnel and protection of United Nations personnel\n\n\nEnglish\nFrench\n\n\n\n\n\n\n\nPart I: Material relating to the request by the General Assembly for an advisory opinion of the Court\n\n\n\n                30 \n                January \n                2025\n              \nPart I: Material relating to the request by the General Assembly for an advisory opinion of the Court\nAvailable in:\n\nEnglish\nFrench\n\n\n\n\n\nList of Documents (documents received from the Secretariat of the United Nations)\n\n\n\n                30 \n                January \n                2025\n              \nList of Documents (documents received from the Secretariat of the United Nations)\nAvailable in:\n\nEnglish\nFrench\n\n\n\n\n\nIntroductory Note (documents received from the Secretariat of the United Nations)\n\n\n\n                30 \n                January \n                2025\n              \nIntroductory Note (documents received from the Secretariat of the United Nations)\nAvailable in:\n\nEnglish\nFrench\n\n\n\n\n\n                  Press release 2024/86\n                \n\n\n                24 \n                December \n                2024\n              \nObligations of Israel in relation to the presence and activities of the United Nations, other international organizations and third States in and in relation to the Occupied Palestinian Territory (Request for Advisory Opinion) - The President of the Court makes an Order organizing the proceedings and fixes the time-limits for the presentation of written statements\nAvailable in:\n\nEnglish\nFrench\n\n\n\n\n\nOrder of 23 December 2024\n\n\nFixing of time-limits: Presentation of written statements\nAvailable in:\n\nEnglish\nFrench\n\n\n\n\n\n                  Press release 2024/84\n                \n\n\n                23 \n                December \n                2024\n              \nThe General Assembly of the United Nations requests an advisory opinion from the Court on “the obligations of Israel in relation to the presence and activities of the United Nations, other international organizations and third States” in and in relation to the Occupied Palestinian Territory\nAvailable in:\n\nEnglish\nFrench\n\n\n\n\n\nRequest for Advisory Opinion\n\n\n\n                23 \n                December \n                2024\n              \nRequest for Advisory Opinion\nAvailable in:\n\nEnglish\nFrench\n\nLatest Developments\n\n\n\n                  Press release 2025/13\n                \n\n\n                12 \n                March \n                2025\n              \nObligations of Israel in relation to the Presence and Activities of the United Nations, Other International Organizations and Third States in and in relation to the Occupied Palestinian Territory (Request for Advisory Opinion) - Filing of written statements and opening date of the public hearings\nAvailable in:\n\nEnglish\nFrench\n\n\n\n\n\n                  Press release 2025/9\n                \n\n\n                20 \n                February \n                2025\n              \nObligations of Israel in relation to the Presence and Activities of the United Nations, Other International Organizations and Third States in and in relation to the Occupied Palestinian Territory (Request for Advisory Opinion) - The Court authorizes the African Union to participate in the proceedings\nAvailable in:\n\nEnglish\nFrench\n\n\n\n\n\n                  Press release 2025/8\n                \n\n\n                7 \n                February \n                2025\n              \nObligations of Israel in relation to the Presence and Activities of the United Nations, Other International Organizations and Third States in and in relation to the Occupied Palestinian Territory (Request for Advisory Opinion) - The Court authorizes the League of Arab States to participate in the proceedings\nAvailable in:\n\nEnglish\nFrench\n\n\n\n\n\n                  Press release 2025/7\n                \n\n\n                4 \n                February \n                2025\n              \nObligations of Israel in relation to the Presence and Activities of the United Nations, Other International Organizations and Third States in and in relation to the Occupied Palestinian Territory (Request for Advisory Opinion) - The Court authorizes the Organisation of Islamic Cooperation to participate in the proceedings\nAvailable in:\n\nEnglish\nFrench\n\n\n\n\n\nPart II (F): Other documents without document symbols (documents received from the Secretariat of the United Nations)\n\n\n\n                30 \n                January \n                2025\n              \nPart II (F): Other documents without document symbols (documents received from the Secretariat of the United Nations)\nAvailable in:\n\nEnglish\nFrench\n\n\n\n\n\nPart II (E): Relevant instruments (documents received from the Secretariat of the United Nations)\n\n\n\n                30 \n                January \n                2025\n              \nPart II (E): Relevant instruments (documents received from the Secretariat of the United Nations)\nAvailable in:\n\nEnglish\nFrench\n\n\n\n\nPart II (D): Human rights documentation\n\n\n                30 \n                January \n                2025\n              \nPart II (D): Human rights documentation\n\n\n\nPart II (D) (1): General Assembly\n\n\nEnglish\nFrench\n\n\n\n\nPart II (D) (2): Human Rights Council\n\n\nEnglish\nFrench\n\n\n\n\nPart II (D) (3): Commission on Human Rights\n\n\nEnglish\nFrench\n\n\n\n\nPart II (D) (4): Treaty bodies\n\n\nEnglish\nFrench\n\n\n\n\nPart II (D) (5): Universal periodic review\n\n\nEnglish\nFrench\n\n\n\n\n\n\nPart II (C) - Security Council (documents received from the Secretariat of the United Nations)\n\n\n                30 \n                January \n                2025\n              \nPart II (C) - Security Council (documents received from the Secretariat of the United Nations)\n\n\n\nPart II (C) (1): Documentation relating to the situation in the Occupied Palestinian Territories\n\n\nEnglish\nFrench\n\n\n\n\nPart II (C) (2): Documentation relating to the safety and security of humanitarian personnel and United Nations and associated personnel\n\n\nEnglish\nFrench\n\n\n\n\n\n\n\nPart II (B) - General Assembly Emergency Special Sessions (documents received from the Secretariat of the United Nations)\n\n\n\n                30 \n                January \n                2025\n              \nPart II (B) - General Assembly Emergency Special Sessions (documents received from the Secretariat of the United Nations)\nAvailable in:\n\nEnglish\nFrench\n\n\n\n\nPart II (A) - Material of the United Nations Relating to the Questions before the Court (documents received from the Secretariat of the United Nations)\n\n\n                30 \n                January \n                2025\n              \nPart II (A) - Material of the United Nations Relating to the Questions before the Court (documents received from the Secretariat of the United Nations)\n\n\n\nPart II (A) (1): Israeli settlements\n\n\nEnglish\nFrench\n\n\n\n\nPart II (A) (2): Living conditions of the Palestinian people\n\n\nEnglish\nFrench\n\n\n\n\nPart II (A) (3): Palestinian women and children\n\n\nEnglish\nFrench\n\n\n\n\nPart II (A) (4): Permanent sovereignty over natural and national resources\n\n\nEnglish\nFrench\n\n\n\n\nPart II (A) (5): Right to self-determination\n\n\nEnglish\nFrench\n\n\n\n\nPart II (A) (6): Question of Palestine\n\n\nEnglish\nFrench\n\n\n\n\nPart II (A) (7): Situation in the Middle East\n\n\nEnglish\nFrench\n\n\n\n\nPart II (A) (8): Special Committee to investigate Israeli practices affecting the human rights of the Palestinian people\n\n\nEnglish\nFrench\n\n\n\n\nPart II (A) (9): United Nations Relief and Works Agency for Palestine refugees in the Near East (UNRWA)\n\n\nEnglish\nFrench\n\n\n\n\nPart II (A) (10): Assistance to the Palestinian people\n\n\nEnglish\nFrench\n\n\n\n\nPart II (A) (11): Safety and security of humanitarian personnel and protection of United Nations personnel\n\n\nEnglish\nFrench\n\n\n\n\n\n\n\nPart I: Material relating to the request by the General Assembly for an advisory opinion of the Court\n\n\n\n                30 \n                January \n                2025\n              \nPart I: Material relating to the request by the General Assembly for an advisory opinion of the Court\nAvailable in:\n\nEnglish\nFrench\n\n\n\n\n\nList of Documents (documents received from the Secretariat of the United Nations)\n\n\n\n                30 \n                January \n                2025\n              \nList of Documents (documents received from the Secretariat of the United Nations)\nAvailable in:\n\nEnglish\nFrench\n\n\n\n\n\nIntroductory Note (documents received from the Secretariat of the United Nations)\n\n\n\n                30 \n                January \n                2025\n              \nIntroductory Note (documents received from the Secretariat of the United Nations)\nAvailable in:\n\nEnglish\nFrench\n\n\n\n\n\n                  Press release 2024/86\n                \n\n\n                24 \n                December \n                2024\n              \nObligations of Israel in relation to the presence and activities of the United Nations, other international organizations and third States in and in relation to the Occupied Palestinian Territory (Request for Advisory Opinion) - The President of the Court makes an Order organizing the proceedings and fixes the time-limits for the presentation of written statements\nAvailable in:\n\nEnglish\nFrench\n\n\n\n\n\nOrder of 23 December 2024\n\n\nFixing of time-limits: Presentation of written statements\nAvailable in:\n\nEnglish\nFrench\n\n\n\n\n\n                  Press release 2024/84\n                \n\n\n                23 \n                December \n                2024\n              \nThe General Assembly of the United Nations requests an advisory opinion from the Court on “the obligations of Israel in relation to the presence and activities of the United Nations, other international organizations and third States” in and in relation to the Occupied Palestinian Territory\nAvailable in:\n\nEnglish\nFrench\n\n\n\n\n\nRequest for Advisory Opinion\n\n\n\n                23 \n                December \n                2024\n              \nRequest for Advisory Opinion\nAvailable in:\n\nEnglish\nFrench\n\nLatest Developments\n\n\n\n                  Press release 2025/13\n                \n\n\n                12 \n                March \n                2025\n              \nObligations of Israel in relation to the Presence and Activities of the United Nations, Other International Organizations and Third States in and in relation to the Occupied Palestinian Territory (Request for Advisory Opinion) - Filing of written statements and opening date of the public hearings\nAvailable in:\n\nEnglish\nFrench\n\n\n\n\n\n                  Press release 2025/9\n                \n\n\n                20 \n                February \n                2025\n              \nObligations of Israel in relation to the Presence and Activities of the United Nations, Other International Organizations and Third States in and in relation to the Occupied Palestinian Territory (Request for Advisory Opinion) - The Court authorizes the African Union to participate in the proceedings\nAvailable in:\n\nEnglish\nFrench\n\n\n\n\n\n                  Press release 2025/8\n                \n\n\n                7 \n                February \n                2025\n              \nObligations of Israel in relation to the Presence and Activities of the United Nations, Other International Organizations and Third States in and in relation to the Occupied Palestinian Territory (Request for Advisory Opinion) - The Court authorizes the League of Arab States to participate in the proceedings\nAvailable in:\n\nEnglish\nFrench\n\n\n\n\n\n                  Press release 2025/7\n                \n\n\n                4 \n                February \n                2025\n              \nObligations of Israel in relation to the Presence and Activities of the United Nations, Other International Organizations and Third States in and in relation to the Occupied Palestinian Territory (Request for Advisory Opinion) - The Court authorizes the Organisation of Islamic Cooperation to participate in the proceedings\nAvailable in:\n\nEnglish\nFrench\n\n\n\n\n\nPart II (F): Other documents without document symbols (documents received from the Secretariat of the United Nations)\n\n\n\n                30 \n                January \n                2025\n              \nPart II (F): Other documents without document symbols (documents received from the Secretariat of the United Nations)\nAvailable in:\n\nEnglish\nFrench\n\n\n\n\n\nPart II (E): Relevant instruments (documents received from the Secretariat of the United Nations)\n\n\n\n                30 \n                January \n                2025\n              \nPart II (E): Relevant instruments (documents received from the Secretariat of the United Nations)\nAvailable in:\n\nEnglish\nFrench\n\n\n\n\nPart II (D): Human rights documentation\n\n\n                30 \n                January \n                2025\n              \nPart II (D): Human rights documentation\n\n\n\nPart II (D) (1): General Assembly\n\n\nEnglish\nFrench\n\n\n\n\nPart II (D) (2): Human Rights Council\n\n\nEnglish\nFrench\n\n\n\n\nPart II (D) (3): Commission on Human Rights\n\n\nEnglish\nFrench\n\n\n\n\nPart II (D) (4): Treaty bodies\n\n\nEnglish\nFrench\n\n\n\n\nPart II (D) (5): Universal periodic review\n\n\nEnglish\nFrench\n\n\n\n\n\n\nPart II (C) - Security Council (documents received from the Secretariat of the United Nations)\n\n\n                30 \n                January \n                2025\n              \nPart II (C) - Security Council (documents received from the Secretariat of the United Nations)\n\n\n\nPart II (C) (1): Documentation relating to the situation in the Occupied Palestinian Territories\n\n\nEnglish\nFrench\n\n\n\n\nPart II (C) (2): Documentation relating to the safety and security of humanitarian personnel and United Nations and associated personnel\n\n\nEnglish\nFrench\n\n\n\n\n\n\n\nPart II (B) - General Assembly Emergency Special Sessions (documents received from the Secretariat of the United Nations)\n\n\n\n                30 \n                January \n                2025\n              \nPart II (B) - General Assembly Emergency Special Sessions (documents received from the Secretariat of the United Nations)\nAvailable in:\n\nEnglish\nFrench\n\n\n\n\nPart II (A) - Material of the United Nations Relating to the Questions before the Court (documents received from the Secretariat of the United Nations)\n\n\n                30 \n                January \n                2025\n              \nPart II (A) - Material of the United Nations Relating to the Questions before the Court (documents received from the Secretariat of the United Nations)\n\n\n\nPart II (A) (1): Israeli settlements\n\n\nEnglish\nFrench\n\n\n\n\nPart II (A) (2): Living conditions of the Palestinian people\n\n\nEnglish\nFrench\n\n\n\n\nPart II (A) (3): Palestinian women and children\n\n\nEnglish\nFrench\n\n\n\n\nPart II (A) (4): Permanent sovereignty over natural and national resources\n\n\nEnglish\nFrench\n\n\n\n\nPart II (A) (5): Right to self-determination\n\n\nEnglish\nFrench\n\n\n\n\nPart II (A) (6): Question of Palestine\n\n\nEnglish\nFrench\n\n\n\n\nPart II (A) (7): Situation in the Middle East\n\n\nEnglish\nFrench\n\n\n\n\nPart II (A) (8): Special Committee to investigate Israeli practices affecting the human rights of the Palestinian people\n\n\nEnglish\nFrench\n\n\n\n\nPart II (A) (9): United Nations Relief and Works Agency for Palestine refugees in the Near East (UNRWA)\n\n\nEnglish\nFrench\n\n\n\n\nPart II (A) (10): Assistance to the Palestinian people\n\n\nEnglish\nFrench\n\n\n\n\nPart II (A) (11): Safety and security of humanitarian personnel and protection of United Nations personnel\n\n\nEnglish\nFrench\n\n\n\n\n\n\n\nPart I: Material relating to the request by the General Assembly for an advisory opinion of the Court\n\n\n\n                30 \n                January \n                2025\n              \nPart I: Material relating to the request by the General Assembly for an advisory opinion of the Court\nAvailable in:\n\nEnglish\nFrench\n\n\n\n\n\nList of Documents (documents received from the Secretariat of the United Nations)\n\n\n\n                30 \n                January \n                2025\n              \nList of Documents (documents received from the Secretariat of the United Nations)\nAvailable in:\n\nEnglish\nFrench\n\n\n\n\n\nIntroductory Note (documents received from the Secretariat of the United Nations)\n\n\n\n                30 \n                January \n                2025\n              \nIntroductory Note (documents received from the Secretariat of the United Nations)\nAvailable in:\n\nEnglish\nFrench\n\n\n\n\n\n                  Press release 2024/86\n                \n\n\n                24 \n                December \n                2024\n              \nObligations of Israel in relation to the presence and activities of the United Nations, other international organizations and third States in and in relation to the Occupied Palestinian Territory (Request for Advisory Opinion) - The President of the Court makes an Order organizing the proceedings and fixes the time-limits for the presentation of written statements\nAvailable in:\n\nEnglish\nFrench\n\n\n\n\n\nOrder of 23 December 2024\n\n\nFixing of time-limits: Presentation of written statements\nAvailable in:\n\nEnglish\nFrench\n\n\n\n\n\n                  Press release 2024/84\n                \n\n\n                23 \n                December \n                2024\n              \nThe General Assembly of the United Nations requests an advisory opinion from the Court on “the obligations of Israel in relation to the presence and activities of the United Nations, other international organizations and third States” in and in relation to the Occupied Palestinian Territory\nAvailable in:\n\nEnglish\nFrench\n\n\n\n\n\nRequest for Advisory Opinion\n\n\n\n                23 \n                December \n                2024\n              \nRequest for Advisory Opinion\nAvailable in:\n\nEnglish\nFrench\n\nPress release 2025/13\n                \n\n\n                12 \n                March \n                2025\n              \nObligations of Israel in relation to the Presence and Activities of the United Nations, Other International Organizations and Third States in and in relation to the Occupied Palestinian Territory (Request for Advisory Opinion) - Filing of written statements and opening date of the public hearings\nAvailable in:\n\nEnglish\nFrench\n\nPress release 2025/13\n\nObligations of Israel in relation to the Presence and Activities of the United Nations, Other International Organizations and Third States in and in relation to the Occupied Palestinian Territory (Request for Advisory Opinion) - Filing of written statements and opening date of the public hearings\n\nEnglish\nFrench\n\nPress release 2025/9\n                \n\n\n                20 \n                February \n                2025\n              \nObligations of Israel in relation to the Presence and Activities of the United Nations, Other International Organizations and Third States in and in relation to the Occupied Palestinian Territory (Request for Advisory Opinion) - The Court authorizes the African Union to participate in the proceedings\nAvailable in:\n\nEnglish\nFrench\n\nPress release 2025/9\n\nObligations of Israel in relation to the Presence and Activities of the United Nations, Other International Organizations and Third States in and in relation to the Occupied Palestinian Territory (Request for Advisory Opinion) - The Court authorizes the African Union to participate in the proceedings\n\nEnglish\nFrench\n\nPress release 2025/8\n                \n\n\n                7 \n                February \n                2025\n              \nObligations of Israel in relation to the Presence and Activities of the United Nations, Other International Organizations and Third States in and in relation to the Occupied Palestinian Territory (Request for Advisory Opinion) - The Court authorizes the League of Arab States to participate in the proceedings\nAvailable in:\n\nEnglish\nFrench\n\nPress release 2025/8\n\nObligations of Israel in relation to the Presence and Activities of the United Nations, Other International Organizations and Third States in and in relation to the Occupied Palestinian Territory (Request for Advisory Opinion) - The Court authorizes the League of Arab States to participate in the proceedings\n\nEnglish\nFrench\n\nPress release 2025/7\n                \n\n\n                4 \n                February \n                2025\n              \nObligations of Israel in relation to the Presence and Activities of the United Nations, Other International Organizations and Third States in and in relation to the Occupied Palestinian Territory (Request for Advisory Opinion) - The Court authorizes the Organisation of Islamic Cooperation to participate in the proceedings\nAvailable in:\n\nEnglish\nFrench\n\nPress release 2025/7\n\nObligations of Israel in relation to the Presence and Activities of the United Nations, Other International Organizations and Third States in and in relation to the Occupied Palestinian Territory (Request for Advisory Opinion) - The Court authorizes the Organisation of Islamic Cooperation to participate in the proceedings\n\nEnglish\nFrench\n\nPart II (F): Other documents without document symbols (documents received from the Secretariat of the United Nations)\n\n\n\n                30 \n                January \n                2025\n              \nPart II (F): Other documents without document symbols (documents received from the Secretariat of the United Nations)\nAvailable in:\n\nEnglish\nFrench\n\nPart II (F): Other documents without document symbols (documents received from the Secretariat of the United Nations)\n\nPart II (F): Other documents without document symbols (documents received from the Secretariat of the United Nations)\n\nPart II (F): Other documents without document symbols (documents received from the Secretariat of the United Nations)\n\nEnglish\nFrench\n\nPart II (E): Relevant instruments (documents received from the Secretariat of the United Nations)\n\n\n\n                30 \n                January \n                2025\n              \nPart II (E): Relevant instruments (documents received from the Secretariat of the United Nations)\nAvailable in:\n\nEnglish\nFrench\n\nPart II (E): Relevant instruments (documents received from the Secretariat of the United Nations)\n\nPart II (E): Relevant instruments (documents received from the Secretariat of the United Nations)\n\nPart II (E): Relevant instruments (documents received from the Secretariat of the United Nations)\n\nEnglish\nFrench\n\nPart II (D): Human rights documentation\n\n\n                30 \n                January \n                2025\n              \nPart II (D): Human rights documentation\n\n\n\nPart II (D) (1): General Assembly\n\n\nEnglish\nFrench\n\n\n\n\nPart II (D) (2): Human Rights Council\n\n\nEnglish\nFrench\n\n\n\n\nPart II (D) (3): Commission on Human Rights\n\n\nEnglish\nFrench\n\n\n\n\nPart II (D) (4): Treaty bodies\n\n\nEnglish\nFrench\n\n\n\n\nPart II (D) (5): Universal periodic review\n\n\nEnglish\nFrench\n\nPart II (D): Human rights documentation\n\nPart II (D): Human rights documentation\n\nPart II (D): Human rights documentation\n\nPart II (D) (1): General Assembly\n\n\nEnglish\nFrench\n\n\n\n\nPart II (D) (2): Human Rights Council\n\n\nEnglish\nFrench\n\n\n\n\nPart II (D) (3): Commission on Human Rights\n\n\nEnglish\nFrench\n\n\n\n\nPart II (D) (4): Treaty bodies\n\n\nEnglish\nFrench\n\n\n\n\nPart II (D) (5): Universal periodic review\n\n\nEnglish\nFrench\n\nPart II (D) (1): General Assembly\n\n\nEnglish\nFrench\n\nPart II (D) (1): General Assembly\n\nEnglish\nFrench\n\nPart II (D) (2): Human Rights Council\n\n\nEnglish\nFrench\n\nPart II (D) (2): Human Rights Council\n\nEnglish\nFrench\n\nPart II (D) (3): Commission on Human Rights\n\n\nEnglish\nFrench\n\nPart II (D) (3): Commission on Human Rights\n\nEnglish\nFrench\n\nPart II (D) (4): Treaty bodies\n\n\nEnglish\nFrench\n\nPart II (D) (4): Treaty bodies\n\nEnglish\nFrench\n\nPart II (D) (5): Universal periodic review\n\n\nEnglish\nFrench\n\nPart II (D) (5): Universal periodic review\n\nEnglish\nFrench\n\nPart II (C) - Security Council (documents received from the Secretariat of the United Nations)\n\n\n                30 \n                January \n                2025\n              \nPart II (C) - Security Council (documents received from the Secretariat of the United Nations)\n\n\n\nPart II (C) (1): Documentation relating to the situation in the Occupied Palestinian Territories\n\n\nEnglish\nFrench\n\n\n\n\nPart II (C) (2): Documentation relating to the safety and security of humanitarian personnel and United Nations and associated personnel\n\n\nEnglish\nFrench\n\nPart II (C) - Security Council (documents received from the Secretariat of the United Nations)\n\nPart II (C) - Security Council (documents received from the Secretariat of the United Nations)\n\nPart II (C) - Security Council (documents received from the Secretariat of the United Nations)\n\nPart II (C) (1): Documentation relating to the situation in the Occupied Palestinian Territories\n\n\nEnglish\nFrench\n\n\n\n\nPart II (C) (2): Documentation relating to the safety and security of humanitarian personnel and United Nations and associated personnel\n\n\nEnglish\nFrench\n\nPart II (C) (1): Documentation relating to the situation in the Occupied Palestinian Territories\n\n\nEnglish\nFrench\n\nPart II (C) (1): Documentation relating to the situation in the Occupied Palestinian Territories\n\nEnglish\nFrench\n\nPart II (C) (2): Documentation relating to the safety and security of humanitarian personnel and United Nations and associated personnel\n\n\nEnglish\nFrench\n\nPart II (C) (2): Documentation relating to the safety and security of humanitarian personnel and United Nations and associated personnel\n\nEnglish\nFrench\n\nPart II (B) - General Assembly Emergency Special Sessions (documents received from the Secretariat of the United Nations)\n\n\n\n                30 \n                January \n                2025\n              \nPart II (B) - General Assembly Emergency Special Sessions (documents received from the Secretariat of the United Nations)\nAvailable in:\n\nEnglish\nFrench\n\nPart II (B) - General Assembly Emergency Special Sessions (documents received from the Secretariat of the United Nations)\n\nPart II (B) - General Assembly Emergency Special Sessions (documents received from the Secretariat of the United Nations)\n\nPart II (B) - General Assembly Emergency Special Sessions (documents received from the Secretariat of the United Nations)\n\nEnglish\nFrench\n\nPart II (A) - Material of the United Nations Relating to the Questions before the Court (documents received from the Secretariat of the United Nations)\n\n\n                30 \n                January \n                2025\n              \nPart II (A) - Material of the United Nations Relating to the Questions before the Court (documents received from the Secretariat of the United Nations)\n\n\n\nPart II (A) (1): Israeli settlements\n\n\nEnglish\nFrench\n\n\n\n\nPart II (A) (2): Living conditions of the Palestinian people\n\n\nEnglish\nFrench\n\n\n\n\nPart II (A) (3): Palestinian women and children\n\n\nEnglish\nFrench\n\n\n\n\nPart II (A) (4): Permanent sovereignty over natural and national resources\n\n\nEnglish\nFrench\n\n\n\n\nPart II (A) (5): Right to self-determination\n\n\nEnglish\nFrench\n\n\n\n\nPart II (A) (6): Question of Palestine\n\n\nEnglish\nFrench\n\n\n\n\nPart II (A) (7): Situation in the Middle East\n\n\nEnglish\nFrench\n\n\n\n\nPart II (A) (8): Special Committee to investigate Israeli practices affecting the human rights of the Palestinian people\n\n\nEnglish\nFrench\n\n\n\n\nPart II (A) (9): United Nations Relief and Works Agency for Palestine refugees in the Near East (UNRWA)\n\n\nEnglish\nFrench\n\n\n\n\nPart II (A) (10): Assistance to the Palestinian people\n\n\nEnglish\nFrench\n\n\n\n\nPart II (A) (11): Safety and security of humanitarian personnel and protection of United Nations personnel\n\n\nEnglish\nFrench\n\nPart II (A) - Material of the United Nations Relating to the Questions before the Court (documents received from the Secretariat of the United Nations)\n\nPart II (A) - Material of the United Nations Relating to the Questions before the Court (documents received from the Secretariat of the United Nations)\n\nPart II (A) - Material of the United Nations Relating to the Questions before the Court (documents received from the Secretariat of the United Nations)\n\nPart II (A) (1): Israeli settlements\n\n\nEnglish\nFrench\n\n\n\n\nPart II (A) (2): Living conditions of the Palestinian people\n\n\nEnglish\nFrench\n\n\n\n\nPart II (A) (3): Palestinian women and children\n\n\nEnglish\nFrench\n\n\n\n\nPart II (A) (4): Permanent sovereignty over natural and national resources\n\n\nEnglish\nFrench\n\n\n\n\nPart II (A) (5): Right to self-determination\n\n\nEnglish\nFrench\n\n\n\n\nPart II (A) (6): Question of Palestine\n\n\nEnglish\nFrench\n\n\n\n\nPart II (A) (7): Situation in the Middle East\n\n\nEnglish\nFrench\n\n\n\n\nPart II (A) (8): Special Committee to investigate Israeli practices affecting the human rights of the Palestinian people\n\n\nEnglish\nFrench\n\n\n\n\nPart II (A) (9): United Nations Relief and Works Agency for Palestine refugees in the Near East (UNRWA)\n\n\nEnglish\nFrench\n\n\n\n\nPart II (A) (10): Assistance to the Palestinian people\n\n\nEnglish\nFrench\n\n\n\n\nPart II (A) (11): Safety and security of humanitarian personnel and protection of United Nations personnel\n\n\nEnglish\nFrench\n\nPart II (A) (1): Israeli settlements\n\n\nEnglish\nFrench\n\nPart II (A) (1): Israeli settlements\n\nEnglish\nFrench\n\nPart II (A) (2): Living conditions of the Palestinian people\n\n\nEnglish\nFrench\n\nPart II (A) (2): Living conditions of the Palestinian people\n\nEnglish\nFrench\n\nPart II (A) (3): Palestinian women and children\n\n\nEnglish\nFrench\n\nPart II (A) (3): Palestinian women and children\n\nEnglish\nFrench\n\nPart II (A) (4): Permanent sovereignty over natural and national resources\n\n\nEnglish\nFrench\n\nPart II (A) (4): Permanent sovereignty over natural and national resources\n\nEnglish\nFrench\n\nPart II (A) (5): Right to self-determination\n\n\nEnglish\nFrench\n\nPart II (A) (5): Right to self-determination\n\nEnglish\nFrench\n\nPart II (A) (6): Question of Palestine\n\n\nEnglish\nFrench\n\nPart II (A) (6): Question of Palestine\n\nEnglish\nFrench\n\nPart II (A) (7): Situation in the Middle East\n\n\nEnglish\nFrench\n\nPart II (A) (7): Situation in the Middle East\n\nEnglish\nFrench\n\nPart II (A) (8): Special Committee to investigate Israeli practices affecting the human rights of the Palestinian people\n\n\nEnglish\nFrench\n\nPart II (A) (8): Special Committee to investigate Israeli practices affecting the human rights of the Palestinian people\n\nEnglish\nFrench\n\nPart II (A) (9): United Nations Relief and Works Agency for Palestine refugees in the Near East (UNRWA)\n\n\nEnglish\nFrench\n\nPart II (A) (9): United Nations Relief and Works Agency for Palestine refugees in the Near East (UNRWA)\n\nEnglish\nFrench\n\nPart II (A) (10): Assistance to the Palestinian people\n\n\nEnglish\nFrench\n\nPart II (A) (10): Assistance to the Palestinian people\n\nEnglish\nFrench\n\nPart II (A) (11): Safety and security of humanitarian personnel and protection of United Nations personnel\n\n\nEnglish\nFrench\n\nPart II (A) (11): Safety and security of humanitarian personnel and protection of United Nations personnel\n\nEnglish\nFrench\n\nPart I: Material relating to the request by the General Assembly for an advisory opinion of the Court\n\n\n\n                30 \n                January \n                2025\n              \nPart I: Material relating to the request by the General Assembly for an advisory opinion of the Court\nAvailable in:\n\nEnglish\nFrench\n\nPart I: Material relating to the request by the General Assembly for an advisory opinion of the Court\n\nPart I: Material relating to the request by the General Assembly for an advisory opinion of the Court\n\nPart I: Material relating to the request by the General Assembly for an advisory opinion of the Court\n\nEnglish\nFrench\n\nList of Documents (documents received from the Secretariat of the United Nations)\n\n\n\n                30 \n                January \n                2025\n              \nList of Documents (documents received from the Secretariat of the United Nations)\nAvailable in:\n\nEnglish\nFrench\n\nList of Documents (documents received from the Secretariat of the United Nations)\n\nList of Documents (documents received from the Secretariat of the United Nations)\n\nList of Documents (documents received from the Secretariat of the United Nations)\n\nEnglish\nFrench\n\nIntroductory Note (documents received from the Secretariat of the United Nations)\n\n\n\n                30 \n                January \n                2025\n              \nIntroductory Note (documents received from the Secretariat of the United Nations)\nAvailable in:\n\nEnglish\nFrench\n\nIntroductory Note (documents received from the Secretariat of the United Nations)\n\nIntroductory Note (documents received from the Secretariat of the United Nations)\n\nIntroductory Note (documents received from the Secretariat of the United Nations)\n\nEnglish\nFrench\n\nPress release 2024/86\n                \n\n\n                24 \n                December \n                2024\n              \nObligations of Israel in relation to the presence and activities of the United Nations, other international organizations and third States in and in relation to the Occupied Palestinian Territory (Request for Advisory Opinion) - The President of the Court makes an Order organizing the proceedings and fixes the time-limits for the presentation of written statements\nAvailable in:\n\nEnglish\nFrench\n\nPress release 2024/86\n\nObligations of Israel in relation to the presence and activities of the United Nations, other international organizations and third States in and in relation to the Occupied Palestinian Territory (Request for Advisory Opinion) - The President of the Court makes an Order organizing the proceedings and fixes the time-limits for the presentation of written statements\n\nEnglish\nFrench\n\nOrder of 23 December 2024\n\n\nFixing of time-limits: Presentation of written statements\nAvailable in:\n\nEnglish\nFrench\n\nOrder of 23 December 2024\n\nOrder of 23 December 2024\n\nFixing of time-limits: Presentation of written statements\n\nEnglish\nFrench\n\nPress release 2024/84\n                \n\n\n                23 \n                December \n                2024\n              \nThe General Assembly of the United Nations requests an advisory opinion from the Court on “the obligations of Israel in relation to the presence and activities of the United Nations, other international organizations and third States” in and in relation to the Occupied Palestinian Territory\nAvailable in:\n\nEnglish\nFrench\n\nPress release 2024/84\n\nThe General Assembly of the United Nations requests an advisory opinion from the Court on “the obligations of Israel in relation to the presence and activities of the United Nations, other international organizations and third States” in and in relation to the Occupied Palestinian Territory\n\nEnglish\nFrench\n\nRequest for Advisory Opinion\n\n\n\n                23 \n                December \n                2024\n              \nRequest for Advisory Opinion\nAvailable in:\n\nEnglish\nFrench\n\nRequest for Advisory Opinion\n\nRequest for Advisory Opinion\n\nRequest for Advisory Opinion\n\nEnglish\nFrench\n\nLinks\n\nLinks",
  "entities": {
    "countries": [
      "israel"
    ],
    "organizations": [
      "united nations",
      "un"
    ],
    "key_issues": [
      "situation",
      "nation",
      "state",
      "territory",
      "development",
      "humanitarian",
      "human rights",
      "assistance",
      "relief",
      "united nations",
      "un",
      "security council",
      "general assembly",
      "organization",
      "agency"
    ]
  },
  "committee": "Third Committee",
  "topic": "Upholding the international criminal justice system for public safety"
}