{
  "url": "https://www.imo.org",
  "title": "International Maritime Organization",
  "text": "Top Story\r\n                            \n\n\nIMO takes action on seafarers’ rights, substandard shipping\nLegal Committee adopts guidelines on fair treatment of seafarers detained in connection with alleged crimes; launches work on substandard shipping. \nFind out more\n\n\n\n\n\n\n\n\r\n                                Top Story\r\n                            \n\n\nProtect satellite navigation from interference, UN agencies urge\nAviation, maritime and telecoms agencies raise alarm over increase in jamming and spoofing of satellite navigation systems.  \nFind out more\n\n\n\n\n\n\n\n\r\n                                Top Story\r\n                            \n\n\nIMO to develop global strategy for maritime digitalization\nFirst steps taken towards a cross-cutting strategy that will leverage new technology to advance international shipping.\nFind out more\n\n\n\n\n\n\n\n\r\n                                Top Story\r\n                            \n\n\nStatement on the loss of seafarers in the attack on a merchant ship in Odesa \n\nFind out more\n\n\n\n\n\n\n\n\n\n\n\n\n\n\r\n                        IMO – \r\nthe International Maritime Organization – is the United Nations specialized agency with responsibility for the safety and security of shipping and the prevention of marine and atmospheric pollution by ships. IMO's work supports the UN sustainable development goals.\n\n\n\n\n\nIMO At Glance\n\n\n176\n//\n\n\r\n                                    Member States\r\n                                \n\n\n\n\n50\n//\n\n\r\n                                    Conventions And Protocols\r\n                                \n\n\n\n\nFind out more about IMO\n\n\n\n\n\n\n\n\n\n\n\nWhat's New\nView All\n\n\n\n\n\n\n\n\n\n\n02 April 2025\n\n\n\n\nFurther progress on IMO \"net zero framework\" in Working Group\n\nThe Intersessional Working Group on Reduction of Greenhouse Gas (GHG) Emissions from Ships (ISWG-GHG 19) met for its 19th session from 31 March to 1 April 2025, chaired by Mr. Sveinung Oftedal (Norway). The meeting was attended by some 1,000 delegates.\n\nContinue Reading\n\n\n\n\n\n\n\n\n\n02 April 2025\n\n\n\n\nITLOS-IMO joint Workshop explores maritime legal issues \n\nThe  International Maritime Organization (IMO) and International Tribunal for the Law of the Sea (ITLOS) joint Workshop (28 March), held at IMO Headquarters in London, brought together a range of legal experts from both organizations to discuss key maritime issues.  \n\nContinue Reading\n\n\n\n\n\n\n\n\n\n25 March 2025\n\n\n\n\nGetting on board the green shipping revolution (video)   \n\nExplore the solutions propelling the green shipping revolution! A new video from the International Maritime Organization (IMO) delves into the innovative technologies and transformative approaches shaping the future of sustainable shipping, driven by the ambitious 2023 IMO GHG Strategy.\n\nContinue Reading\n\n\n\n\n\n\n\n\n\n\n\n\n\nHot Topics\nView All Topics\n\n\n\n\n\n\n\n\n\n\n\n\n\nMEPC 83 PREVIEW (7-11 April 2025) - Media information\n\r\n                                Read more\n\n\n\n\n\n\n\n\n\n\n\n\nRed Sea area\n\r\n                                Read more\n\n\n\n\n\n\n\n\n\n\n\n\nWorld Maritime Day theme 2025\n\r\n                                Read more\n\n\n\n\n\n\n\n\n\n\n\n\nIMO’s work to cut GHG emissions from ships\n\r\n                                Read more\n\n\n\n\n\n\n\n\n\n\n\n\n\n\n\n\n\nSECRETARY-GENERAL\n\n\n\n\n\n\n\n\n\n​IMO Secretary-General Mr. Arsenio Dominguez\nPlease see more information about IMO Secretary-General here \n\n\n\n\n\nTweets by IMOHQ\n\n\n\n\n@IMOHQ posts\n\n\n\n\n\n\n\nTweets by IMOSecGen\n\n\n\n\n@IMOSecGen posts\n\n\n\n\n\n\n\n\n\n\n\nLatest video\n\n\n\n\n​\n\n\n\n\n\n\n\n\n\n\n\n\n\n\n\n\n\n\n\nOUR WORK\n\nFind out more\n\n\n\n\n\n\n\n\nMarine Environment\n\nFind out more\n\n\n\n\n\n\n\n\nMaritime Safety\n\nFind out more\n\n\n\n\n\n\n\n\n\n\n\n\n\nCONVENTIONS\nIMO has adopted more than 50 international treaties.\nFIND OUT MORE\n\n\n\n\n\n\n\n\nPUBLICATIONS\nIMO has over 200 titles available in English. Many are translated into French, Spanish, Arabic, Chinese and Russian.\nFIND OUT MORE\n\n\n\n\n\n\n\n\n\n\n\n\nWORLD MARITIME THEME\n\nFIND OUT MORE\n\n\n\n\n\n\n\n\nDay of the Seafarer\n\nFIND OUT MORE\n\n\n\n\n\n\n\n\nIMO Awards\n\nFIND OUT MORE\n\n\n\n\n\n\n\n\n\n\n\n\n\n\n\n\n\n\n\n\nRESOURCES\n\n\n\n\nGlobal Integrated Shipping Information System (GISIS)\nAnnual IOEO Summary Report for 2023\nIMO Financial Statements\nFinancial Regulations and Financial Rules\nIMO Code of Ethics\nCode of Conduct for Delegates, Observers and Other Participants at IMO Meetings, Events and Activities to Prevent Harassment including Sexual Harassment\nWomen in Maritime Speakers Bureau\nLessons Learned from Marine Casualties\nIMO Secretariat Policy On Access To Information\nMaritime Safety Investigation Reports\n\n\nACCESS IMO DOCUMENTS\n\n\n\n\n\n\n\nIMO MEETINGS\n\n\n\n\nMarine Environment Protection Committee (MEPC)\nSub-Committee on Navigation, Communications and Search and Rescue (NCSR)\nTechnical Cooperation Committee (TC)\nMaritime Safety Committee (MSC)\nIMO Council\n\n\nVIEW CALENDAR AND MEETING OUTCOMES\n\nTop Story\r\n                            \n\n\nIMO takes action on seafarers’ rights, substandard shipping\nLegal Committee adopts guidelines on fair treatment of seafarers detained in connection with alleged crimes; launches work on substandard shipping. \nFind out more\n\n\n\n\n\n\n\n\r\n                                Top Story\r\n                            \n\n\nProtect satellite navigation from interference, UN agencies urge\nAviation, maritime and telecoms agencies raise alarm over increase in jamming and spoofing of satellite navigation systems.  \nFind out more\n\n\n\n\n\n\n\n\r\n                                Top Story\r\n                            \n\n\nIMO to develop global strategy for maritime digitalization\nFirst steps taken towards a cross-cutting strategy that will leverage new technology to advance international shipping.\nFind out more\n\n\n\n\n\n\n\n\r\n                                Top Story\r\n                            \n\n\nStatement on the loss of seafarers in the attack on a merchant ship in Odesa \n\nFind out more\n\nTop Story\r\n                            \n\n\nIMO takes action on seafarers’ rights, substandard shipping\nLegal Committee adopts guidelines on fair treatment of seafarers detained in connection with alleged crimes; launches work on substandard shipping. \nFind out more\n\n\n\n\n\n\n\n\r\n                                Top Story\r\n                            \n\n\nProtect satellite navigation from interference, UN agencies urge\nAviation, maritime and telecoms agencies raise alarm over increase in jamming and spoofing of satellite navigation systems.  \nFind out more\n\n\n\n\n\n\n\n\r\n                                Top Story\r\n                            \n\n\nIMO to develop global strategy for maritime digitalization\nFirst steps taken towards a cross-cutting strategy that will leverage new technology to advance international shipping.\nFind out more\n\n\n\n\n\n\n\n\r\n                                Top Story\r\n                            \n\n\nStatement on the loss of seafarers in the attack on a merchant ship in Odesa \n\nFind out more\n\nTop Story\r\n                            \n\n\nIMO takes action on seafarers’ rights, substandard shipping\nLegal Committee adopts guidelines on fair treatment of seafarers detained in connection with alleged crimes; launches work on substandard shipping. \nFind out more\n\n\n\n\n\n\n\n\r\n                                Top Story\r\n                            \n\n\nProtect satellite navigation from interference, UN agencies urge\nAviation, maritime and telecoms agencies raise alarm over increase in jamming and spoofing of satellite navigation systems.  \nFind out more\n\n\n\n\n\n\n\n\r\n                                Top Story\r\n                            \n\n\nIMO to develop global strategy for maritime digitalization\nFirst steps taken towards a cross-cutting strategy that will leverage new technology to advance international shipping.\nFind out more\n\n\n\n\n\n\n\n\r\n                                Top Story\r\n                            \n\n\nStatement on the loss of seafarers in the attack on a merchant ship in Odesa \n\nFind out more\n\nTop Story\r\n                            \n\n\nIMO takes action on seafarers’ rights, substandard shipping\nLegal Committee adopts guidelines on fair treatment of seafarers detained in connection with alleged crimes; launches work on substandard shipping. \nFind out more\n\nTop Story\r\n                            \n\n\nIMO takes action on seafarers’ rights, substandard shipping\nLegal Committee adopts guidelines on fair treatment of seafarers detained in connection with alleged crimes; launches work on substandard shipping. \nFind out more\n\nTop Story\n\nIMO takes action on seafarers’ rights, substandard shipping\nLegal Committee adopts guidelines on fair treatment of seafarers detained in connection with alleged crimes; launches work on substandard shipping. \nFind out more\n\nLegal Committee adopts guidelines on fair treatment of seafarers detained in connection with alleged crimes; launches work on substandard shipping.\n\nTop Story\r\n                            \n\n\nProtect satellite navigation from interference, UN agencies urge\nAviation, maritime and telecoms agencies raise alarm over increase in jamming and spoofing of satellite navigation systems.  \nFind out more\n\nTop Story\r\n                            \n\n\nProtect satellite navigation from interference, UN agencies urge\nAviation, maritime and telecoms agencies raise alarm over increase in jamming and spoofing of satellite navigation systems.  \nFind out more\n\nTop Story\n\nProtect satellite navigation from interference, UN agencies urge\nAviation, maritime and telecoms agencies raise alarm over increase in jamming and spoofing of satellite navigation systems.  \nFind out more\n\nAviation, maritime and telecoms agencies raise alarm over increase in jamming and spoofing of satellite navigation systems.\n\nTop Story\r\n                            \n\n\nIMO to develop global strategy for maritime digitalization\nFirst steps taken towards a cross-cutting strategy that will leverage new technology to advance international shipping.\nFind out more\n\nTop Story\r\n                            \n\n\nIMO to develop global strategy for maritime digitalization\nFirst steps taken towards a cross-cutting strategy that will leverage new technology to advance international shipping.\nFind out more\n\nTop Story\n\nIMO to develop global strategy for maritime digitalization\nFirst steps taken towards a cross-cutting strategy that will leverage new technology to advance international shipping.\nFind out more\n\nFirst steps taken towards a cross-cutting strategy that will leverage new technology to advance international shipping.\n\nTop Story\r\n                            \n\n\nStatement on the loss of seafarers in the attack on a merchant ship in Odesa \n\nFind out more\n\nTop Story\r\n                            \n\n\nStatement on the loss of seafarers in the attack on a merchant ship in Odesa \n\nFind out more\n\nTop Story\n\nStatement on the loss of seafarers in the attack on a merchant ship in Odesa \n\nFind out more\n\nIMO – \r\nthe International Maritime Organization – is the United Nations specialized agency with responsibility for the safety and security of shipping and the prevention of marine and atmospheric pollution by ships. IMO's work supports the UN sustainable development goals.\n\n\n\n\n\nIMO At Glance\n\n\n176\n//\n\n\r\n                                    Member States\r\n                                \n\n\n\n\n50\n//\n\n\r\n                                    Conventions And Protocols\r\n                                \n\n\n\n\nFind out more about IMO\n\nIMO – \r\nthe International Maritime Organization – is the United Nations specialized agency with responsibility for the safety and security of shipping and the prevention of marine and atmospheric pollution by ships. IMO's work supports the UN sustainable development goals.\n\n\n\n\n\nIMO At Glance\n\n\n176\n//\n\n\r\n                                    Member States\r\n                                \n\n\n\n\n50\n//\n\n\r\n                                    Conventions And Protocols\r\n                                \n\n\n\n\nFind out more about IMO\n\nIMO – \r\nthe International Maritime Organization – is the United Nations specialized agency with responsibility for the safety and security of shipping and the prevention of marine and atmospheric pollution by ships. IMO's work supports the UN sustainable development goals.\n\n\n\n\n\nIMO At Glance\n\n\n176\n//\n\n\r\n                                    Member States\r\n                                \n\n\n\n\n50\n//\n\n\r\n                                    Conventions And Protocols\r\n                                \n\n\n\n\nFind out more about IMO\n\nIMO – \r\nthe International Maritime Organization – is the United Nations specialized agency with responsibility for the safety and security of shipping and the prevention of marine and atmospheric pollution by ships. IMO's work supports the UN sustainable development goals.\n\nIMO – \r\nthe International Maritime Organization – is the United Nations specialized agency with responsibility for the safety and security of shipping and the prevention of marine and atmospheric pollution by ships. IMO's work supports the UN sustainable development goals.\n\nIMO – \r\nthe International Maritime Organization – is the United Nations specialized agency with responsibility for the safety and security of shipping and the prevention of marine and atmospheric pollution by ships. IMO's work supports the UN sustainable development goals.\n\nIMO At Glance\n\n\n176\n//\n\n\r\n                                    Member States\r\n                                \n\n\n\n\n50\n//\n\n\r\n                                    Conventions And Protocols\r\n                                \n\n\n\n\nFind out more about IMO\n\nIMO At Glance\n\n\n176\n//\n\n\r\n                                    Member States\r\n                                \n\n\n\n\n50\n//\n\n\r\n                                    Conventions And Protocols\r\n                                \n\n\n\n\nFind out more about IMO\n\n176\n\n//\n\n50\n\n//\n\nWhat's New\nView All\n\n\n\n\n\n\n\n\n\n\n02 April 2025\n\n\n\n\nFurther progress on IMO \"net zero framework\" in Working Group\n\nThe Intersessional Working Group on Reduction of Greenhouse Gas (GHG) Emissions from Ships (ISWG-GHG 19) met for its 19th session from 31 March to 1 April 2025, chaired by Mr. Sveinung Oftedal (Norway). The meeting was attended by some 1,000 delegates.\n\nContinue Reading\n\n\n\n\n\n\n\n\n\n02 April 2025\n\n\n\n\nITLOS-IMO joint Workshop explores maritime legal issues \n\nThe  International Maritime Organization (IMO) and International Tribunal for the Law of the Sea (ITLOS) joint Workshop (28 March), held at IMO Headquarters in London, brought together a range of legal experts from both organizations to discuss key maritime issues.  \n\nContinue Reading\n\n\n\n\n\n\n\n\n\n25 March 2025\n\n\n\n\nGetting on board the green shipping revolution (video)   \n\nExplore the solutions propelling the green shipping revolution! A new video from the International Maritime Organization (IMO) delves into the innovative technologies and transformative approaches shaping the future of sustainable shipping, driven by the ambitious 2023 IMO GHG Strategy.\n\nContinue Reading\n\nWhat's New\nView All\n\nWhat's New\nView All\n\nWhat's New\nView All\n\nWhat's New\n\nView All\n\n02 April 2025\n\n\n\n\nFurther progress on IMO \"net zero framework\" in Working Group\n\nThe Intersessional Working Group on Reduction of Greenhouse Gas (GHG) Emissions from Ships (ISWG-GHG 19) met for its 19th session from 31 March to 1 April 2025, chaired by Mr. Sveinung Oftedal (Norway). The meeting was attended by some 1,000 delegates.\n\nContinue Reading\n\n\n\n\n\n\n\n\n\n02 April 2025\n\n\n\n\nITLOS-IMO joint Workshop explores maritime legal issues \n\nThe  International Maritime Organization (IMO) and International Tribunal for the Law of the Sea (ITLOS) joint Workshop (28 March), held at IMO Headquarters in London, brought together a range of legal experts from both organizations to discuss key maritime issues.  \n\nContinue Reading\n\n\n\n\n\n\n\n\n\n25 March 2025\n\n\n\n\nGetting on board the green shipping revolution (video)   \n\nExplore the solutions propelling the green shipping revolution! A new video from the International Maritime Organization (IMO) delves into the innovative technologies and transformative approaches shaping the future of sustainable shipping, driven by the ambitious 2023 IMO GHG Strategy.\n\nContinue Reading\n\n02 April 2025\n\n\n\n\nFurther progress on IMO \"net zero framework\" in Working Group\n\nThe Intersessional Working Group on Reduction of Greenhouse Gas (GHG) Emissions from Ships (ISWG-GHG 19) met for its 19th session from 31 March to 1 April 2025, chaired by Mr. Sveinung Oftedal (Norway). The meeting was attended by some 1,000 delegates.\n\nContinue Reading\n\n\n\n\n\n\n\n\n\n02 April 2025\n\n\n\n\nITLOS-IMO joint Workshop explores maritime legal issues \n\nThe  International Maritime Organization (IMO) and International Tribunal for the Law of the Sea (ITLOS) joint Workshop (28 March), held at IMO Headquarters in London, brought together a range of legal experts from both organizations to discuss key maritime issues.  \n\nContinue Reading\n\n\n\n\n\n\n\n\n\n25 March 2025\n\n\n\n\nGetting on board the green shipping revolution (video)   \n\nExplore the solutions propelling the green shipping revolution! A new video from the International Maritime Organization (IMO) delves into the innovative technologies and transformative approaches shaping the future of sustainable shipping, driven by the ambitious 2023 IMO GHG Strategy.\n\nContinue Reading\n\n02 April 2025\n\n\n\n\nFurther progress on IMO \"net zero framework\" in Working Group\n\nThe Intersessional Working Group on Reduction of Greenhouse Gas (GHG) Emissions from Ships (ISWG-GHG 19) met for its 19th session from 31 March to 1 April 2025, chaired by Mr. Sveinung Oftedal (Norway). The meeting was attended by some 1,000 delegates.\n\nContinue Reading\n\n02 April 2025\n\n\n\n\nFurther progress on IMO \"net zero framework\" in Working Group\n\nThe Intersessional Working Group on Reduction of Greenhouse Gas (GHG) Emissions from Ships (ISWG-GHG 19) met for its 19th session from 31 March to 1 April 2025, chaired by Mr. Sveinung Oftedal (Norway). The meeting was attended by some 1,000 delegates.\n\nContinue Reading\n\n02 April 2025\n\n02 April 2025\n\nFurther progress on IMO \"net zero framework\" in Working Group\n\nThe Intersessional Working Group on Reduction of Greenhouse Gas (GHG) Emissions from Ships (ISWG-GHG 19) met for its 19th session from 31 March to 1 April 2025, chaired by Mr. Sveinung Oftedal (Norway). The meeting was attended by some 1,000 delegates.\n\nContinue Reading\n\nThe Intersessional Working Group on Reduction of Greenhouse Gas (GHG) Emissions from Ships (ISWG-GHG 19) met for its 19th session from 31 March to 1 April 2025, chaired by Mr. Sveinung Oftedal (Norway). The meeting was attended by some 1,000 delegates.\n\nThe Intersessional Working Group on Reduction of Greenhouse Gas (GHG) Emissions from Ships (ISWG-GHG 19) met for its 19th session from 31 March to 1 April 2025, chaired by Mr. Sveinung Oftedal (Norway). The meeting was attended by some 1,000 delegates.\n\nThe Intersessional Working Group on Reduction of Greenhouse Gas (GHG) Emissions from Ships (ISWG-GHG 19) met for its 19th session from 31 March to 1 April 2025, chaired by Mr. Sveinung Oftedal (Norway). The meeting was attended by some 1,000 delegates.\n\n02 April 2025\n\n\n\n\nITLOS-IMO joint Workshop explores maritime legal issues \n\nThe  International Maritime Organization (IMO) and International Tribunal for the Law of the Sea (ITLOS) joint Workshop (28 March), held at IMO Headquarters in London, brought together a range of legal experts from both organizations to discuss key maritime issues.  \n\nContinue Reading\n\n02 April 2025\n\n\n\n\nITLOS-IMO joint Workshop explores maritime legal issues \n\nThe  International Maritime Organization (IMO) and International Tribunal for the Law of the Sea (ITLOS) joint Workshop (28 March), held at IMO Headquarters in London, brought together a range of legal experts from both organizations to discuss key maritime issues.  \n\nContinue Reading\n\n02 April 2025\n\n02 April 2025\n\nITLOS-IMO joint Workshop explores maritime legal issues \n\nThe  International Maritime Organization (IMO) and International Tribunal for the Law of the Sea (ITLOS) joint Workshop (28 March), held at IMO Headquarters in London, brought together a range of legal experts from both organizations to discuss key maritime issues.  \n\nContinue Reading\n\nThe  International Maritime Organization (IMO) and International Tribunal for the Law of the Sea (ITLOS) joint Workshop (28 March), held at IMO Headquarters in London, brought together a range of legal experts from both organizations to discuss key maritime issues.\n\nThe  International Maritime Organization (IMO) and International Tribunal for the Law of the Sea (ITLOS) joint Workshop (28 March), held at IMO Headquarters in London, brought together a range of legal experts from both organizations to discuss key maritime issues.\n\nThe  International Maritime Organization (IMO) and International Tribunal for the Law of the Sea (ITLOS) joint Workshop (28 March), held at IMO Headquarters in London, brought together a range of legal experts from both organizations to discuss key maritime issues.\n\n25 March 2025\n\n\n\n\nGetting on board the green shipping revolution (video)   \n\nExplore the solutions propelling the green shipping revolution! A new video from the International Maritime Organization (IMO) delves into the innovative technologies and transformative approaches shaping the future of sustainable shipping, driven by the ambitious 2023 IMO GHG Strategy.\n\nContinue Reading\n\n25 March 2025\n\n\n\n\nGetting on board the green shipping revolution (video)   \n\nExplore the solutions propelling the green shipping revolution! A new video from the International Maritime Organization (IMO) delves into the innovative technologies and transformative approaches shaping the future of sustainable shipping, driven by the ambitious 2023 IMO GHG Strategy.\n\nContinue Reading\n\n25 March 2025\n\n25 March 2025\n\nGetting on board the green shipping revolution (video)   \n\nExplore the solutions propelling the green shipping revolution! A new video from the International Maritime Organization (IMO) delves into the innovative technologies and transformative approaches shaping the future of sustainable shipping, driven by the ambitious 2023 IMO GHG Strategy.\n\nContinue Reading\n\nExplore the solutions propelling the green shipping revolution! A new video from the International Maritime Organization (IMO) delves into the innovative technologies and transformative approaches shaping the future of sustainable shipping, driven by the ambitious 2023 IMO GHG Strategy.\n\nExplore the solutions propelling the green shipping revolution! A new video from the International Maritime Organization (IMO) delves into the innovative technologies and transformative approaches shaping the future of sustainable shipping, driven by the ambitious 2023 IMO GHG Strategy.\n\nExplore the solutions propelling the green shipping revolution! A new video from the International Maritime Organization (IMO) delves into the innovative technologies and transformative approaches shaping the future of sustainable shipping, driven by the ambitious 2023 IMO GHG Strategy.\n\nHot Topics\nView All Topics\n\n\n\n\n\n\n\n\n\n\n\n\n\nMEPC 83 PREVIEW (7-11 April 2025) - Media information\n\r\n                                Read more\n\n\n\n\n\n\n\n\n\n\n\n\nRed Sea area\n\r\n                                Read more\n\n\n\n\n\n\n\n\n\n\n\n\nWorld Maritime Day theme 2025\n\r\n                                Read more\n\n\n\n\n\n\n\n\n\n\n\n\nIMO’s work to cut GHG emissions from ships\n\r\n                                Read more\n\nHot Topics\nView All Topics\n\nHot Topics\nView All Topics\n\nHot Topics\nView All Topics\n\nHot Topics\n\nView All Topics\n\nMEPC 83 PREVIEW (7-11 April 2025) - Media information\n\r\n                                Read more\n\n\n\n\n\n\n\n\n\n\n\n\nRed Sea area\n\r\n                                Read more\n\n\n\n\n\n\n\n\n\n\n\n\nWorld Maritime Day theme 2025\n\r\n                                Read more\n\n\n\n\n\n\n\n\n\n\n\n\nIMO’s work to cut GHG emissions from ships\n\r\n                                Read more\n\nMEPC 83 PREVIEW (7-11 April 2025) - Media information\n\r\n                                Read more\n\n\n\n\n\n\n\n\n\n\n\n\nRed Sea area\n\r\n                                Read more\n\n\n\n\n\n\n\n\n\n\n\n\nWorld Maritime Day theme 2025\n\r\n                                Read more\n\n\n\n\n\n\n\n\n\n\n\n\nIMO’s work to cut GHG emissions from ships\n\r\n                                Read more\n\nMEPC 83 PREVIEW (7-11 April 2025) - Media information\n\r\n                                Read more\n\nMEPC 83 PREVIEW (7-11 April 2025) - Media information\n\r\n                                Read more\n\nMEPC 83 PREVIEW (7-11 April 2025) - Media information\n\r\n                                Read more\n\nRed Sea area\n\r\n                                Read more\n\nRed Sea area\n\r\n                                Read more\n\nRed Sea area\n\r\n                                Read more\n\nWorld Maritime Day theme 2025\n\r\n                                Read more\n\nWorld Maritime Day theme 2025\n\r\n                                Read more\n\nWorld Maritime Day theme 2025\n\r\n                                Read more\n\nIMO’s work to cut GHG emissions from ships\n\r\n                                Read more\n\nIMO’s work to cut GHG emissions from ships\n\r\n                                Read more\n\nIMO’s work to cut GHG emissions from ships\n\r\n                                Read more\n\nSECRETARY-GENERAL\n\n\n\n\n\n\n\n\n\n​IMO Secretary-General Mr. Arsenio Dominguez\nPlease see more information about IMO Secretary-General here \n\n\n\n\n\nTweets by IMOHQ\n\n\n\n\n@IMOHQ posts\n\n\n\n\n\n\n\nTweets by IMOSecGen\n\n\n\n\n@IMOSecGen posts\n\n\n\n\n\n\n\n\n\n\n\nLatest video\n\n\n\n\n​\n\nSECRETARY-GENERAL\n\nSECRETARY-GENERAL\n\nSECRETARY-GENERAL\n\n​IMO Secretary-General Mr. Arsenio Dominguez\nPlease see more information about IMO Secretary-General here \n\n\n\n\n\nTweets by IMOHQ\n\n\n\n\n@IMOHQ posts\n\n\n\n\n\n\n\nTweets by IMOSecGen\n\n\n\n\n@IMOSecGen posts\n\n\n\n\n\n\n\n\n\n\n\nLatest video\n\n\n\n\n​\n\n​IMO Secretary-General Mr. Arsenio Dominguez\nPlease see more information about IMO Secretary-General here \n\n\n\n\n\nTweets by IMOHQ\n\n\n\n\n@IMOHQ posts\n\n\n\n\n\n\n\nTweets by IMOSecGen\n\n\n\n\n@IMOSecGen posts\n\n\n\n\n\n\n\n\n\n\n\nLatest video\n\n\n\n\n​\n\n​IMO Secretary-General Mr. Arsenio Dominguez\nPlease see more information about IMO Secretary-General here \n\n\n\n\n\nTweets by IMOHQ\n\n\n\n\n@IMOHQ posts\n\n\n\n\n\n\n\nTweets by IMOSecGen\n\n\n\n\n@IMOSecGen posts\n\n\n\n\n\n\n\n\n\n\n\nLatest video\n\n\n\n\n​\n\n​IMO Secretary-General Mr. Arsenio Dominguez\nPlease see more information about IMO Secretary-General here \n\n\n\n\n\nTweets by IMOHQ\n\n\n\n\n@IMOHQ posts\n\n\n\n\n\n\n\nTweets by IMOSecGen\n\n\n\n\n@IMOSecGen posts\n\n\n\n\n\n\n\n\n\n\n\nLatest video\n\n\n\n\n​\n\n​IMO Secretary-General Mr. Arsenio Dominguez\nPlease see more information about IMO Secretary-General here\n\nPlease see more information about IMO Secretary-General here\n\nTweets by IMOHQ\n\n\n\n\n@IMOHQ posts\n\n\n\n\n\n\n\nTweets by IMOSecGen\n\n\n\n\n@IMOSecGen posts\n\n\n\n\n\n\n\n\n\n\n\nLatest video\n\nTweets by IMOHQ\n\n\n\n\n@IMOHQ posts\n\nTweets by IMOHQ\n\n\n\n\n@IMOHQ posts\n\nTweets by IMOHQ\n\n@IMOHQ posts\n\nTweets by IMOSecGen\n\n\n\n\n@IMOSecGen posts\n\nTweets by IMOSecGen\n\n\n\n\n@IMOSecGen posts\n\nTweets by IMOSecGen\n\n@IMOSecGen posts\n\nLatest video\n\nLatest video\n\nLatest video\n\nOUR WORK\n\nFind out more\n\n\n\n\n\n\n\n\nMarine Environment\n\nFind out more\n\n\n\n\n\n\n\n\nMaritime Safety\n\nFind out more\n\n\n\n\n\n\n\n\n\n\n\n\n\nCONVENTIONS\nIMO has adopted more than 50 international treaties.\nFIND OUT MORE\n\n\n\n\n\n\n\n\nPUBLICATIONS\nIMO has over 200 titles available in English. Many are translated into French, Spanish, Arabic, Chinese and Russian.\nFIND OUT MORE\n\n\n\n\n\n\n\n\n\n\n\n\nWORLD MARITIME THEME\n\nFIND OUT MORE\n\n\n\n\n\n\n\n\nDay of the Seafarer\n\nFIND OUT MORE\n\n\n\n\n\n\n\n\nIMO Awards\n\nFIND OUT MORE\n\nOUR WORK\n\nFind out more\n\n\n\n\n\n\n\n\nMarine Environment\n\nFind out more\n\n\n\n\n\n\n\n\nMaritime Safety\n\nFind out more\n\n\n\n\n\n\n\n\n\n\n\n\n\nCONVENTIONS\nIMO has adopted more than 50 international treaties.\nFIND OUT MORE\n\n\n\n\n\n\n\n\nPUBLICATIONS\nIMO has over 200 titles available in English. Many are translated into French, Spanish, Arabic, Chinese and Russian.\nFIND OUT MORE\n\n\n\n\n\n\n\n\n\n\n\n\nWORLD MARITIME THEME\n\nFIND OUT MORE\n\n\n\n\n\n\n\n\nDay of the Seafarer\n\nFIND OUT MORE\n\n\n\n\n\n\n\n\nIMO Awards\n\nFIND OUT MORE\n\nOUR WORK\n\nFind out more\n\n\n\n\n\n\n\n\nMarine Environment\n\nFind out more\n\n\n\n\n\n\n\n\nMaritime Safety\n\nFind out more\n\n\n\n\n\n\n\n\n\n\n\n\n\nCONVENTIONS\nIMO has adopted more than 50 international treaties.\nFIND OUT MORE\n\n\n\n\n\n\n\n\nPUBLICATIONS\nIMO has over 200 titles available in English. Many are translated into French, Spanish, Arabic, Chinese and Russian.\nFIND OUT MORE\n\n\n\n\n\n\n\n\n\n\n\n\nWORLD MARITIME THEME\n\nFIND OUT MORE\n\n\n\n\n\n\n\n\nDay of the Seafarer\n\nFIND OUT MORE\n\n\n\n\n\n\n\n\nIMO Awards\n\nFIND OUT MORE\n\nOUR WORK\n\nFind out more\n\n\n\n\n\n\n\n\nMarine Environment\n\nFind out more\n\n\n\n\n\n\n\n\nMaritime Safety\n\nFind out more\n\nOUR WORK\n\nFind out more\n\n\n\n\n\n\n\n\nMarine Environment\n\nFind out more\n\n\n\n\n\n\n\n\nMaritime Safety\n\nFind out more\n\nOUR WORK\n\nFind out more\n\n\n\n\n\n\n\n\nMarine Environment\n\nFind out more\n\n\n\n\n\n\n\n\nMaritime Safety\n\nFind out more\n\nOUR WORK\n\nFind out more\n\nOUR WORK\n\nFind out more\n\nMarine Environment\n\nFind out more\n\nMarine Environment\n\nFind out more\n\nMaritime Safety\n\nFind out more\n\nMaritime Safety\n\nFind out more\n\nCONVENTIONS\nIMO has adopted more than 50 international treaties.\nFIND OUT MORE\n\n\n\n\n\n\n\n\nPUBLICATIONS\nIMO has over 200 titles available in English. Many are translated into French, Spanish, Arabic, Chinese and Russian.\nFIND OUT MORE\n\nCONVENTIONS\nIMO has adopted more than 50 international treaties.\nFIND OUT MORE\n\nCONVENTIONS\nIMO has adopted more than 50 international treaties.\nFIND OUT MORE\n\nIMO has adopted more than 50 international treaties.\n\nPUBLICATIONS\nIMO has over 200 titles available in English. Many are translated into French, Spanish, Arabic, Chinese and Russian.\nFIND OUT MORE\n\nPUBLICATIONS\nIMO has over 200 titles available in English. Many are translated into French, Spanish, Arabic, Chinese and Russian.\nFIND OUT MORE\n\nIMO has over 200 titles available in English. Many are translated into French, Spanish, Arabic, Chinese and Russian.\n\nWORLD MARITIME THEME\n\nFIND OUT MORE\n\n\n\n\n\n\n\n\nDay of the Seafarer\n\nFIND OUT MORE\n\n\n\n\n\n\n\n\nIMO Awards\n\nFIND OUT MORE\n\nWORLD MARITIME THEME\n\nFIND OUT MORE\n\n\n\n\n\n\n\n\nDay of the Seafarer\n\nFIND OUT MORE\n\n\n\n\n\n\n\n\nIMO Awards\n\nFIND OUT MORE\n\nWORLD MARITIME THEME\n\nFIND OUT MORE\n\n\n\n\n\n\n\n\nDay of the Seafarer\n\nFIND OUT MORE\n\n\n\n\n\n\n\n\nIMO Awards\n\nFIND OUT MORE\n\nWORLD MARITIME THEME\n\nFIND OUT MORE\n\nWORLD MARITIME THEME\n\nFIND OUT MORE\n\nDay of the Seafarer\n\nFIND OUT MORE\n\nDay of the Seafarer\n\nFIND OUT MORE\n\nIMO Awards\n\nFIND OUT MORE\n\nIMO Awards\n\nFIND OUT MORE\n\nRESOURCES\n\n\n\n\nGlobal Integrated Shipping Information System (GISIS)\nAnnual IOEO Summary Report for 2023\nIMO Financial Statements\nFinancial Regulations and Financial Rules\nIMO Code of Ethics\nCode of Conduct for Delegates, Observers and Other Participants at IMO Meetings, Events and Activities to Prevent Harassment including Sexual Harassment\nWomen in Maritime Speakers Bureau\nLessons Learned from Marine Casualties\nIMO Secretariat Policy On Access To Information\nMaritime Safety Investigation Reports\n\n\nACCESS IMO DOCUMENTS\n\n\n\n\n\n\n\nIMO MEETINGS\n\n\n\n\nMarine Environment Protection Committee (MEPC)\nSub-Committee on Navigation, Communications and Search and Rescue (NCSR)\nTechnical Cooperation Committee (TC)\nMaritime Safety Committee (MSC)\nIMO Council\n\n\nVIEW CALENDAR AND MEETING OUTCOMES\n\nRESOURCES\n\n\n\n\nGlobal Integrated Shipping Information System (GISIS)\nAnnual IOEO Summary Report for 2023\nIMO Financial Statements\nFinancial Regulations and Financial Rules\nIMO Code of Ethics\nCode of Conduct for Delegates, Observers and Other Participants at IMO Meetings, Events and Activities to Prevent Harassment including Sexual Harassment\nWomen in Maritime Speakers Bureau\nLessons Learned from Marine Casualties\nIMO Secretariat Policy On Access To Information\nMaritime Safety Investigation Reports\n\n\nACCESS IMO DOCUMENTS\n\n\n\n\n\n\n\nIMO MEETINGS\n\n\n\n\nMarine Environment Protection Committee (MEPC)\nSub-Committee on Navigation, Communications and Search and Rescue (NCSR)\nTechnical Cooperation Committee (TC)\nMaritime Safety Committee (MSC)\nIMO Council\n\n\nVIEW CALENDAR AND MEETING OUTCOMES\n\nRESOURCES\n\n\n\n\nGlobal Integrated Shipping Information System (GISIS)\nAnnual IOEO Summary Report for 2023\nIMO Financial Statements\nFinancial Regulations and Financial Rules\nIMO Code of Ethics\nCode of Conduct for Delegates, Observers and Other Participants at IMO Meetings, Events and Activities to Prevent Harassment including Sexual Harassment\nWomen in Maritime Speakers Bureau\nLessons Learned from Marine Casualties\nIMO Secretariat Policy On Access To Information\nMaritime Safety Investigation Reports\n\n\nACCESS IMO DOCUMENTS\n\n\n\n\n\n\n\nIMO MEETINGS\n\n\n\n\nMarine Environment Protection Committee (MEPC)\nSub-Committee on Navigation, Communications and Search and Rescue (NCSR)\nTechnical Cooperation Committee (TC)\nMaritime Safety Committee (MSC)\nIMO Council\n\n\nVIEW CALENDAR AND MEETING OUTCOMES\n\nRESOURCES\n\n\n\n\nGlobal Integrated Shipping Information System (GISIS)\nAnnual IOEO Summary Report for 2023\nIMO Financial Statements\nFinancial Regulations and Financial Rules\nIMO Code of Ethics\nCode of Conduct for Delegates, Observers and Other Participants at IMO Meetings, Events and Activities to Prevent Harassment including Sexual Harassment\nWomen in Maritime Speakers Bureau\nLessons Learned from Marine Casualties\nIMO Secretariat Policy On Access To Information\nMaritime Safety Investigation Reports\n\n\nACCESS IMO DOCUMENTS\n\nRESOURCES\n\n\n\n\nGlobal Integrated Shipping Information System (GISIS)\nAnnual IOEO Summary Report for 2023\nIMO Financial Statements\nFinancial Regulations and Financial Rules\nIMO Code of Ethics\nCode of Conduct for Delegates, Observers and Other Participants at IMO Meetings, Events and Activities to Prevent Harassment including Sexual Harassment\nWomen in Maritime Speakers Bureau\nLessons Learned from Marine Casualties\nIMO Secretariat Policy On Access To Information\nMaritime Safety Investigation Reports\n\n\nACCESS IMO DOCUMENTS\n\nRESOURCES\n\nRESOURCES\n\nRESOURCES\n\nGlobal Integrated Shipping Information System (GISIS)\nAnnual IOEO Summary Report for 2023\nIMO Financial Statements\nFinancial Regulations and Financial Rules\nIMO Code of Ethics\nCode of Conduct for Delegates, Observers and Other Participants at IMO Meetings, Events and Activities to Prevent Harassment including Sexual Harassment\nWomen in Maritime Speakers Bureau\nLessons Learned from Marine Casualties\nIMO Secretariat Policy On Access To Information\nMaritime Safety Investigation Reports\n\nIMO MEETINGS\n\n\n\n\nMarine Environment Protection Committee (MEPC)\nSub-Committee on Navigation, Communications and Search and Rescue (NCSR)\nTechnical Cooperation Committee (TC)\nMaritime Safety Committee (MSC)\nIMO Council\n\n\nVIEW CALENDAR AND MEETING OUTCOMES\n\nIMO MEETINGS\n\n\n\n\nMarine Environment Protection Committee (MEPC)\nSub-Committee on Navigation, Communications and Search and Rescue (NCSR)\nTechnical Cooperation Committee (TC)\nMaritime Safety Committee (MSC)\nIMO Council\n\n\nVIEW CALENDAR AND MEETING OUTCOMES\n\nIMO MEETINGS\n\nIMO MEETINGS\n\nIMO MEETINGS\n\nMarine Environment Protection Committee (MEPC)\nSub-Committee on Navigation, Communications and Search and Rescue (NCSR)\nTechnical Cooperation Committee (TC)\nMaritime Safety Committee (MSC)\nIMO Council",
  "date": "",
  "source_type": "other",
  "extracted_at": "2025-04-07T14:18:28.223444",
  "metadata": {
    "description": "",
    "og:type": "website"
  },
  "relevance_score": 0.5386363636363637,
  "summary": "IMO At Glance\n\n\n176\n//\n\n\r\n                                    Member States\r\n                                \n\n\n\n\n50\n//\n\n\r\n                                    Conventions And Protocols\r\n                                \n\n\n\n\nFind out more about IMO\n\n\n\n\n\n\n\n\n\n\n\nWhat's New\nView All\n\n\n\n\n\n\n\n\n\n\n02 April 2025\n\n\n\n\nFurther progress on IMO \"net zero framework\" in Working Group\n\nThe Intersessional Working Group on Reduction of Greenhouse Gas (GHG) Emissions from Ships (ISWG-GHG 19) met for its 19th session from 31 March to 1 April 2025, chaired by Mr. Continue Reading\n\n\n\n\n\n\n\n\n\n02 April 2025\n\n\n\n\nITLOS-IMO joint Workshop explores maritime legal issues \n\nThe  International Maritime Organization (IMO) and International Tribunal for the Law of the Sea (ITLOS) joint Workshop (28 March), held at IMO Headquarters in London, brought together a range of legal experts from both organizations to discuss key maritime issues. Arsenio Dominguez\nPlease see more information about IMO Secretary-General here \n\n\n\n\n\nTweets by IMOHQ\n\n\n\n\n@IMOHQ posts\n\n\n\n\n\n\n\nTweets by IMOSecGen\n\n\n\n\n@IMOSecGen posts\n\n\n\n\n\n\n\n\n\n\n\nLatest video\n\n\n\n\n​\n\n\n\n\n\n\n\n\n\n\n\n\n\n\n\n\n\n\n\nOUR WORK\n\nFind out more\n\n\n\n\n\n\n\n\nMarine Environment\n\nFind out more\n\n\n\n\n\n\n\n\nMaritime Safety\n\nFind out more\n\n\n\n\n\n\n\n\n\n\n\n\n\nCONVENTIONS\nIMO has adopted more than 50 international treaties. FIND OUT MORE\n\n\n\n\n\n\n\n\n\n\n\n\nWORLD MARITIME THEME\n\nFIND OUT MORE\n\n\n\n\n\n\n\n\nDay of the Seafarer\n\nFIND OUT MORE\n\n\n\n\n\n\n\n\nIMO Awards\n\nFIND OUT MORE\n\n\n\n\n\n\n\n\n\n\n\n\n\n\n\n\n\n\n\n\nRESOURCES\n\n\n\n\nGlobal Integrated Shipping Information System (GISIS)\nAnnual IOEO Summary Report for 2023\nIMO Financial Statements\nFinancial Regulations and Financial Rules\nIMO Code of Ethics\nCode of Conduct for Delegates, Observers and Other Participants at IMO Meetings, Events and Activities to Prevent Harassment including Sexual Harassment\nWomen in Maritime Speakers Bureau\nLessons Learned from Marine Casualties\nIMO Secretariat Policy On Access To Information\nMaritime Safety Investigation Reports\n\n\nACCESS IMO DOCUMENTS\n\n\n\n\n\n\n\nIMO MEETINGS\n\n\n\n\nMarine Environment Protection Committee (MEPC)\nSub-Committee on Navigation, Communications and Search and Rescue (NCSR)\nTechnical Cooperation Committee (TC)\nMaritime Safety Committee (MSC)\nIMO Council\n\n\nVIEW CALENDAR AND MEETING OUTCOMES\n\nTop Story\r\n                            \n\n\nIMO takes action on seafarers’ rights, substandard shipping\nLegal Committee adopts guidelines on fair treatment of seafarers detained in connection with alleged crimes; launches work on substandard shipping. Find out more\n\n\n\n\n\n\n\n\r\n                                Top Story\r\n                            \n\n\nStatement on the loss of seafarers in the attack on a merchant ship in Odesa \n\nFind out more\n\nTop Story\r\n                            \n\n\nIMO takes action on seafarers’ rights, substandard shipping\nLegal Committee adopts guidelines on fair treatment of seafarers detained in connection with alleged crimes; launches work on substandard shipping. Find out more\n\n\n\n\n\n\n\n\r\n                                Top Story\r\n                            \n\n\nStatement on the loss of seafarers in the attack on a merchant ship in Odesa \n\nFind out more\n\nTop Story\r\n                            \n\n\nIMO takes action on seafarers’ rights, substandard shipping\nLegal Committee adopts guidelines on fair treatment of seafarers detained in connection with alleged crimes; launches work on substandard shipping. Top Story\r\n                            \n\n\nStatement on the loss of seafarers in the attack on a merchant ship in Odesa \n\nFind out more\n\nTop Story\r\n                            \n\n\nStatement on the loss of seafarers in the attack on a merchant ship in Odesa \n\nFind out more\n\nTop Story\n\nStatement on the loss of seafarers in the attack on a merchant ship in Odesa \n\nFind out more\n\nIMO – \r\nthe International Maritime Organization – is the United Nations specialized agency with responsibility for the safety and security of shipping and the prevention of marine and atmospheric pollution by ships. IMO At Glance\n\n\n176\n//\n\n\r\n                                    Member States\r\n                                \n\n\n\n\n50\n//\n\n\r\n                                    Conventions And Protocols\r\n                                \n\n\n\n\nFind out more about IMO\n\nIMO – \r\nthe International Maritime Organization – is the United Nations specialized agency with responsibility for the safety and security of shipping and the prevention of marine and atmospheric pollution by ships. IMO At Glance\n\n\n176\n//\n\n\r\n                                    Member States\r\n                                \n\n\n\n\n50\n//\n\n\r\n                                    Conventions And Protocols\r\n                                \n\n\n\n\nFind out more about IMO\n\nIMO – \r\nthe International Maritime Organization – is the United Nations specialized agency with responsibility for the safety and security of shipping and the prevention of marine and atmospheric pollution by ships. IMO At Glance\n\n\n176\n//\n\n\r\n                                    Member States\r\n                                \n\n\n\n\n50\n//\n\n\r\n                                    Conventions And Protocols\r\n                                \n\n\n\n\nFind out more about IMO\n\nIMO – \r\nthe International Maritime Organization – is the United Nations specialized agency with responsibility for the safety and security of shipping and the prevention of marine and atmospheric pollution by ships. IMO At Glance\n\n\n176\n//\n\n\r\n                                    Member States\r\n                                \n\n\n\n\n50\n//\n\n\r\n                                    Conventions And Protocols\r\n                                \n\n\n\n\nFind out more about IMO\n\nIMO At Glance\n\n\n176\n//\n\n\r\n                                    Member States\r\n                                \n\n\n\n\n50\n//\n\n\r\n                                    Conventions And Protocols\r\n                                \n\n\n\n\nFind out more about IMO\n\n176\n\n//\n\n50\n\n//\n\nWhat's New\nView All\n\n\n\n\n\n\n\n\n\n\n02 April 2025\n\n\n\n\nFurther progress on IMO \"net zero framework\" in Working Group\n\nThe Intersessional Working Group on Reduction of Greenhouse Gas (GHG) Emissions from Ships (ISWG-GHG 19) met for its 19th session from 31 March to 1 April 2025, chaired by Mr. Continue Reading\n\n\n\n\n\n\n\n\n\n02 April 2025\n\n\n\n\nITLOS-IMO joint Workshop explores maritime legal issues \n\nThe  International Maritime Organization (IMO) and International Tribunal for the Law of the Sea (ITLOS) joint Workshop (28 March), held at IMO Headquarters in London, brought together a range of legal experts from both organizations to discuss key maritime issues. Continue Reading\n\n\n\n\n\n\n\n\n\n02 April 2025\n\n\n\n\nITLOS-IMO joint Workshop explores maritime legal issues \n\nThe  International Maritime Organization (IMO) and International Tribunal for the Law of the Sea (ITLOS) joint Workshop (28 March), held at IMO Headquarters in London, brought together a range of legal experts from both organizations to discuss key maritime issues. Continue Reading\n\n\n\n\n\n\n\n\n\n02 April 2025\n\n\n\n\nITLOS-IMO joint Workshop explores maritime legal issues \n\nThe  International Maritime Organization (IMO) and International Tribunal for the Law of the Sea (ITLOS) joint Workshop (28 March), held at IMO Headquarters in London, brought together a range of legal experts from both organizations to discuss key maritime issues. 02 April 2025\n\n\n\n\nITLOS-IMO joint Workshop explores maritime legal issues \n\nThe  International Maritime Organization (IMO) and International Tribunal for the Law of the Sea (ITLOS) joint Workshop (28 March), held at IMO Headquarters in London, brought together a range of legal experts from both organizations to discuss key maritime issues. Continue Reading\n\n02 April 2025\n\n\n\n\nITLOS-IMO joint Workshop explores maritime legal issues \n\nThe  International Maritime Organization (IMO) and International Tribunal for the Law of the Sea (ITLOS) joint Workshop (28 March), held at IMO Headquarters in London, brought together a range of legal experts from both organizations to discuss key maritime issues. Continue Reading\n\n02 April 2025\n\n02 April 2025\n\nITLOS-IMO joint Workshop explores maritime legal issues \n\nThe  International Maritime Organization (IMO) and International Tribunal for the Law of the Sea (ITLOS) joint Workshop (28 March), held at IMO Headquarters in London, brought together a range of legal experts from both organizations to discuss key maritime issues. Continue Reading\n\nThe  International Maritime Organization (IMO) and International Tribunal for the Law of the Sea (ITLOS) joint Workshop (28 March), held at IMO Headquarters in London, brought together a range of legal experts from both organizations to discuss key maritime issues. The  International Maritime Organization (IMO) and International Tribunal for the Law of the Sea (ITLOS) joint Workshop (28 March), held at IMO Headquarters in London, brought together a range of legal experts from both organizations to discuss key maritime issues. The  International Maritime Organization (IMO) and International Tribunal for the Law of the Sea (ITLOS) joint Workshop (28 March), held at IMO Headquarters in London, brought together a range of legal experts from both organizations to discuss key maritime issues. Hot Topics\nView All Topics\n\n\n\n\n\n\n\n\n\n\n\n\n\nMEPC 83 PREVIEW (7-11 April 2025) - Media information\n\r\n                                Read more\n\n\n\n\n\n\n\n\n\n\n\n\nRed Sea area\n\r\n                                Read more\n\n\n\n\n\n\n\n\n\n\n\n\nWorld Maritime Day theme 2025\n\r\n                                Read more\n\n\n\n\n\n\n\n\n\n\n\n\nIMO’s work to cut GHG emissions from ships\n\r\n                                Read more\n\nHot Topics\nView All Topics\n\nHot Topics\nView All Topics\n\nHot Topics\nView All Topics\n\nHot Topics\n\nView All Topics\n\nMEPC 83 PREVIEW (7-11 April 2025) - Media information\n\r\n                                Read more\n\n\n\n\n\n\n\n\n\n\n\n\nRed Sea area\n\r\n                                Read more\n\n\n\n\n\n\n\n\n\n\n\n\nWorld Maritime Day theme 2025\n\r\n                                Read more\n\n\n\n\n\n\n\n\n\n\n\n\nIMO’s work to cut GHG emissions from ships\n\r\n                                Read more\n\nMEPC 83 PREVIEW (7-11 April 2025) - Media information\n\r\n                                Read more\n\n\n\n\n\n\n\n\n\n\n\n\nRed Sea area\n\r\n                                Read more\n\n\n\n\n\n\n\n\n\n\n\n\nWorld Maritime Day theme 2025\n\r\n                                Read more\n\n\n\n\n\n\n\n\n\n\n\n\nIMO’s work to cut GHG emissions from ships\n\r\n                                Read more\n\nMEPC 83 PREVIEW (7-11 April 2025) - Media information\n\r\n                                Read more\n\nMEPC 83 PREVIEW (7-11 April 2025) - Media information\n\r\n                                Read more\n\nMEPC 83 PREVIEW (7-11 April 2025) - Media information\n\r\n                                Read more\n\nRed Sea area\n\r\n                                Read more\n\nRed Sea area\n\r\n                                Read more\n\nRed Sea area\n\r\n                                Read more\n\nWorld Maritime Day theme 2025\n\r\n                                Read more\n\nWorld Maritime Day theme 2025\n\r\n                                Read more\n\nWorld Maritime Day theme 2025\n\r\n                                Read more\n\nIMO’s work to cut GHG emissions from ships\n\r\n                                Read more\n\nIMO’s work to cut GHG emissions from ships\n\r\n                                Read more\n\nIMO’s work to cut GHG emissions from ships\n\r\n                                Read more\n\nSECRETARY-GENERAL\n\n\n\n\n\n\n\n\n\n​IMO Secretary-General Mr. Arsenio Dominguez\nPlease see more information about IMO Secretary-General here\n\nPlease see more information about IMO Secretary-General here\n\nTweets by IMOHQ\n\n\n\n\n@IMOHQ posts\n\n\n\n\n\n\n\nTweets by IMOSecGen\n\n\n\n\n@IMOSecGen posts\n\n\n\n\n\n\n\n\n\n\n\nLatest video\n\nTweets by IMOHQ\n\n\n\n\n@IMOHQ posts\n\nTweets by IMOHQ\n\n\n\n\n@IMOHQ posts\n\nTweets by IMOHQ\n\n@IMOHQ posts\n\nTweets by IMOSecGen\n\n\n\n\n@IMOSecGen posts\n\nTweets by IMOSecGen\n\n\n\n\n@IMOSecGen posts\n\nTweets by IMOSecGen\n\n@IMOSecGen posts\n\nLatest video\n\nLatest video\n\nLatest video\n\nOUR WORK\n\nFind out more\n\n\n\n\n\n\n\n\nMarine Environment\n\nFind out more\n\n\n\n\n\n\n\n\nMaritime Safety\n\nFind out more\n\n\n\n\n\n\n\n\n\n\n\n\n\nCONVENTIONS\nIMO has adopted more than 50 international treaties. FIND OUT MORE\n\n\n\n\n\n\n\n\n\n\n\n\nWORLD MARITIME THEME\n\nFIND OUT MORE\n\n\n\n\n\n\n\n\nDay of the Seafarer\n\nFIND OUT MORE\n\n\n\n\n\n\n\n\nIMO Awards\n\nFIND OUT MORE\n\nOUR WORK\n\nFind out more\n\n\n\n\n\n\n\n\nMarine Environment\n\nFind out more\n\n\n\n\n\n\n\n\nMaritime Safety\n\nFind out more\n\n\n\n\n\n\n\n\n\n\n\n\n\nCONVENTIONS\nIMO has adopted more than 50 international treaties. FIND OUT MORE\n\n\n\n\n\n\n\n\n\n\n\n\nWORLD MARITIME THEME\n\nFIND OUT MORE\n\n\n\n\n\n\n\n\nDay of the Seafarer\n\nFIND OUT MORE\n\n\n\n\n\n\n\n\nIMO Awards\n\nFIND OUT MORE\n\nOUR WORK\n\nFind out more\n\n\n\n\n\n\n\n\nMarine Environment\n\nFind out more\n\n\n\n\n\n\n\n\nMaritime Safety\n\nFind out more\n\n\n\n\n\n\n\n\n\n\n\n\n\nCONVENTIONS\nIMO has adopted more than 50 international treaties. FIND OUT MORE\n\n\n\n\n\n\n\n\n\n\n\n\nWORLD MARITIME THEME\n\nFIND OUT MORE\n\n\n\n\n\n\n\n\nDay of the Seafarer\n\nFIND OUT MORE\n\n\n\n\n\n\n\n\nIMO Awards\n\nFIND OUT MORE\n\nOUR WORK\n\nFind out more\n\n\n\n\n\n\n\n\nMarine Environment\n\nFind out more\n\n\n\n\n\n\n\n\nMaritime Safety\n\nFind out more\n\nOUR WORK\n\nFind out more\n\n\n\n\n\n\n\n\nMarine Environment\n\nFind out more\n\n\n\n\n\n\n\n\nMaritime Safety\n\nFind out more\n\nOUR WORK\n\nFind out more\n\n\n\n\n\n\n\n\nMarine Environment\n\nFind out more\n\n\n\n\n\n\n\n\nMaritime Safety\n\nFind out more\n\nOUR WORK\n\nFind out more\n\nOUR WORK\n\nFind out more\n\nMarine Environment\n\nFind out more\n\nMarine Environment\n\nFind out more\n\nMaritime Safety\n\nFind out more\n\nMaritime Safety\n\nFind out more\n\nCONVENTIONS\nIMO has adopted more than 50 international treaties. WORLD MARITIME THEME\n\nFIND OUT MORE\n\n\n\n\n\n\n\n\nDay of the Seafarer\n\nFIND OUT MORE\n\n\n\n\n\n\n\n\nIMO Awards\n\nFIND OUT MORE\n\nWORLD MARITIME THEME\n\nFIND OUT MORE\n\n\n\n\n\n\n\n\nDay of the Seafarer\n\nFIND OUT MORE\n\n\n\n\n\n\n\n\nIMO Awards\n\nFIND OUT MORE\n\nWORLD MARITIME THEME\n\nFIND OUT MORE\n\n\n\n\n\n\n\n\nDay of the Seafarer\n\nFIND OUT MORE\n\n\n\n\n\n\n\n\nIMO Awards\n\nFIND OUT MORE\n\nWORLD MARITIME THEME\n\nFIND OUT MORE\n\nWORLD MARITIME THEME\n\nFIND OUT MORE\n\nDay of the Seafarer\n\nFIND OUT MORE\n\nDay of the Seafarer\n\nFIND OUT MORE\n\nIMO Awards\n\nFIND OUT MORE\n\nIMO Awards\n\nFIND OUT MORE\n\nRESOURCES\n\n\n\n\nGlobal Integrated Shipping Information System (GISIS)\nAnnual IOEO Summary Report for 2023\nIMO Financial Statements\nFinancial Regulations and Financial Rules\nIMO Code of Ethics\nCode of Conduct for Delegates, Observers and Other Participants at IMO Meetings, Events and Activities to Prevent Harassment including Sexual Harassment\nWomen in Maritime Speakers Bureau\nLessons Learned from Marine Casualties\nIMO Secretariat Policy On Access To Information\nMaritime Safety Investigation Reports\n\n\nACCESS IMO DOCUMENTS\n\n\n\n\n\n\n\nIMO MEETINGS\n\n\n\n\nMarine Environment Protection Committee (MEPC)\nSub-Committee on Navigation, Communications and Search and Rescue (NCSR)\nTechnical Cooperation Committee (TC)\nMaritime Safety Committee (MSC)\nIMO Council\n\n\nVIEW CALENDAR AND MEETING OUTCOMES\n\nRESOURCES\n\n\n\n\nGlobal Integrated Shipping Information System (GISIS)\nAnnual IOEO Summary Report for 2023\nIMO Financial Statements\nFinancial Regulations and Financial Rules\nIMO Code of Ethics\nCode of Conduct for Delegates, Observers and Other Participants at IMO Meetings, Events and Activities to Prevent Harassment including Sexual Harassment\nWomen in Maritime Speakers Bureau\nLessons Learned from Marine Casualties\nIMO Secretariat Policy On Access To Information\nMaritime Safety Investigation Reports\n\n\nACCESS IMO DOCUMENTS\n\n\n\n\n\n\n\nIMO MEETINGS\n\n\n\n\nMarine Environment Protection Committee (MEPC)\nSub-Committee on Navigation, Communications and Search and Rescue (NCSR)\nTechnical Cooperation Committee (TC)\nMaritime Safety Committee (MSC)\nIMO Council\n\n\nVIEW CALENDAR AND MEETING OUTCOMES\n\nRESOURCES\n\n\n\n\nGlobal Integrated Shipping Information System (GISIS)\nAnnual IOEO Summary Report for 2023\nIMO Financial Statements\nFinancial Regulations and Financial Rules\nIMO Code of Ethics\nCode of Conduct for Delegates, Observers and Other Participants at IMO Meetings, Events and Activities to Prevent Harassment including Sexual Harassment\nWomen in Maritime Speakers Bureau\nLessons Learned from Marine Casualties\nIMO Secretariat Policy On Access To Information\nMaritime Safety Investigation Reports\n\n\nACCESS IMO DOCUMENTS\n\n\n\n\n\n\n\nIMO MEETINGS\n\n\n\n\nMarine Environment Protection Committee (MEPC)\nSub-Committee on Navigation, Communications and Search and Rescue (NCSR)\nTechnical Cooperation Committee (TC)\nMaritime Safety Committee (MSC)\nIMO Council\n\n\nVIEW CALENDAR AND MEETING OUTCOMES\n\nRESOURCES\n\n\n\n\nGlobal Integrated Shipping Information System (GISIS)\nAnnual IOEO Summary Report for 2023\nIMO Financial Statements\nFinancial Regulations and Financial Rules\nIMO Code of Ethics\nCode of Conduct for Delegates, Observers and Other Participants at IMO Meetings, Events and Activities to Prevent Harassment including Sexual Harassment\nWomen in Maritime Speakers Bureau\nLessons Learned from Marine Casualties\nIMO Secretariat Policy On Access To Information\nMaritime Safety Investigation Reports\n\n\nACCESS IMO DOCUMENTS\n\nRESOURCES\n\n\n\n\nGlobal Integrated Shipping Information System (GISIS)\nAnnual IOEO Summary Report for 2023\nIMO Financial Statements\nFinancial Regulations and Financial Rules\nIMO Code of Ethics\nCode of Conduct for Delegates, Observers and Other Participants at IMO Meetings, Events and Activities to Prevent Harassment including Sexual Harassment\nWomen in Maritime Speakers Bureau\nLessons Learned from Marine Casualties\nIMO Secretariat Policy On Access To Information\nMaritime Safety Investigation Reports\n\n\nACCESS IMO DOCUMENTS\n\nRESOURCES\n\nRESOURCES\n\nRESOURCES\n\nGlobal Integrated Shipping Information System (GISIS)\nAnnual IOEO Summary Report for 2023\nIMO Financial Statements\nFinancial Regulations and Financial Rules\nIMO Code of Ethics\nCode of Conduct for Delegates, Observers and Other Participants at IMO Meetings, Events and Activities to Prevent Harassment including Sexual Harassment\nWomen in Maritime Speakers Bureau\nLessons Learned from Marine Casualties\nIMO Secretariat Policy On Access To Information\nMaritime Safety Investigation Reports\n\nIMO MEETINGS\n\n\n\n\nMarine Environment Protection Committee (MEPC)\nSub-Committee on Navigation, Communications and Search and Rescue (NCSR)\nTechnical Cooperation Committee (TC)\nMaritime Safety Committee (MSC)\nIMO Council\n\n\nVIEW CALENDAR AND MEETING OUTCOMES\n\nIMO MEETINGS\n\n\n\n\nMarine Environment Protection Committee (MEPC)\nSub-Committee on Navigation, Communications and Search and Rescue (NCSR)\nTechnical Cooperation Committee (TC)\nMaritime Safety Committee (MSC)\nIMO Council\n\n\nVIEW CALENDAR AND MEETING OUTCOMES\n\nIMO MEETINGS\n\nIMO MEETINGS\n\nIMO MEETINGS\n\nMarine Environment Protection Committee (MEPC)\nSub-Committee on Navigation, Communications and Search and Rescue (NCSR)\nTechnical Cooperation Committee (TC)\nMaritime Safety Committee (MSC)\nIMO Council",
  "entities": {
    "countries": [
      "russia"
    ],
    "organizations": [
      "united nations",
      "un"
    ],
    "key_issues": [
      "issue",
      "nation",
      "state",
      "solution",
      "approach",
      "strategy",
      "policy",
      "action",
      "development",
      "evolution",
      "financial",
      "united nations",
      "un",
      "organization",
      "agency"
    ]
  },
  "committee": "International Maritime Organization",
  "topic": "Discussing the use of maritime autonomous surface ships (MASS)"
}