{
  "url": "https://www.ics-shipping.org",
  "title": "International Chamber of Shipping – Shaping the future of shipping",
  "text": "ICS is the global trade association for shipowners and operators\nICS represents the world’s national shipowner associations, and over 80% of the world merchant fleet\n\n\n\nRead more\n\n\n\n\n\n\n\n\n\n\n\n\n\n\n\n\n\n\n\n\n\n\r\n                            Latest updates                        \n\n\n\n\n\n \n\n\nPress Release\n\r\n                Maritime Industry Associations launch consolidated BMP Maritime Security publication            \n\n\r\n\t\t\t31 March 2025        \n\n\n\n\n\n \n\n\nStatement\n\r\n                International Chamber of Shipping’s comment post USTR (United States Trade Representative) Section 301 Investigation public hearing            \n\n\r\n\t\t\t27 March 2025        \n\n\n\n\n\n \n\n\nPress Release\n\r\n                The New Second Edition of ‘Maritime Security: A Comprehensive Guide for Shipowners, Seafarers and Administrations’ is now available in hardback            \n\n\r\n\t\t\t18 March 2025        \n\n\n\n\n\n \n\n\nPress Release\n\r\n                ICS and CMI launch updated campaign Promoting Maritime Treaty Ratification            \n\n\r\n\t\t\t17 March 2025        \n\n\n\n\n\n\n\n\n\r\n                            Featured resources                        \n\n\n\n\n\n \n\n\nGuidelines\n\r\n                BMP Maritime Security            \n\n\r\n\t\t\tMarch 2025        \n\n\n\n\n\n \n\n\nReports, Positions and Papers\n\r\n                Promoting Maritime Treaty Ratification – The ICS and CMI Campaign 2025            \n\n\r\n\t\t\tMarch 2025        \n\n\n\n\n\n \n\n\nReports, Positions and Papers\n\r\n                Shipping Industry Flag State Performance Table 2024/2025            \n\n\r\n\t\t\tFebruary 2025        \n\n\n\n\n\n \n\n\nGuidelines\n\r\n                Drug Trafficking and Drug Abuse On Board Ship, 2025-2026 Edition            \n\n\r\n\t\t\tFebruary 2025        \n\n\n\n\n\n\n\n\n \n\n\n\n\r\n\t\t\t\t\t\t\tICS Maritime Hub                        \n\nThe ICS Maritime Hub is an ideal destination and venue to host and cater for business meetings and receptions of all sizes.\n\n\n\n\n\r\n                                Read more\n\n\n\n\n\n\n\n\n\n\n\n\n\n\nWhat we do\n\n\n\nRepresenting\nICS represents shipowners with the various intergovernmental bodies that regulate shipping. First is the UN International Maritime Organization (IMO), where ICS was the first shipping industry association to be granted consultative status in 1961. ICS has established an excellent network within the shipping community and partners with other trade bodies, always striving for a global regulatory framework.\n\n\n\r\n                                        Read more                                    \n\n\n\n\n\n\n\n\nExplaining\nAbout 90% of world trade is carried by the international shipping industry. Without shipping, the import/export of affordable food and goods would not be possible – half the world would starve and the other half would freeze!\nShipping is a highly complex and global industry, at the forefront of technological innovation and committed to sustainability and the 2050 targets.\n\n\n\r\n                                        Read more                                    \n\n\n\n\n\n\n\n\nSupporting\nICS is concerned with all technical, legal, employment and trade policy issues that impact on international ship operations. It works towards regulation of shipping at an international level, and opposes unilateral and regional action by governments. ICS also develops best practices and guidance, including a wide range of publications and free resources that are used by ship operators globally.\n\n\n\r\n                                        Read more                                    \n\n\n\n\n\n\n\n\n\n\n\n\n\n \n\n\n\n\r\n\t\t\t\t\t\t\tICS develops and promotes shipping industry best practices                        \n\nICS also develops best practices and guidance, including a wide range of publications and free resources that are used by ship operators globally.\n\n\n\n\n\r\n                                Read more\n\n\n\n\n\n\n\n\n\n\n\n\n\n\n\r\n                            Watch our latest videos                        \n\n\n\n\n\n \n\n\nMultimedia\n\r\n                Life After Sea            \n\n\r\n\t\t\tJune 2024        \n\n\n\n\n\n \n\n\nPage\n\r\n                Shaping the Future of Shipping Summit – COP28 Highlights            \n\n\n\n\n\n\n \n\n\nPage\n\r\n                An Adventurous Spirit            \n\n\n\n\n\n\n \n\n\nMultimedia\n\r\n                100 years of International Chamber of Shipping            \n\n\r\n\t\t\tApril 2022        \n\n\n\n\n\n \n\n\nMultimedia\n\r\n                About ICS and our network            \n\n\r\n\t\t\tNovember 2020        \n\n\n\n\n\n \n\n\nMultimedia\n\r\n                About International Chamber of Shipping (ICS) Publications – Video            \n\n\r\n\t\t\tJanuary 2025\n\nICS is the global trade association for shipowners and operators\nICS represents the world’s national shipowner associations, and over 80% of the world merchant fleet\n\n\n\nRead more\n\nICS is the global trade association for shipowners and operators\nICS represents the world’s national shipowner associations, and over 80% of the world merchant fleet\n\n\n\nRead more\n\nICS is the global trade association for shipowners and operators\nICS represents the world’s national shipowner associations, and over 80% of the world merchant fleet\n\n\n\nRead more\n\nICS is the global trade association for shipowners and operators\nICS represents the world’s national shipowner associations, and over 80% of the world merchant fleet\n\n\n\nRead more\n\nICS represents the world’s national shipowner associations, and over 80% of the world merchant fleet\n\nLatest updates                        \n\n\n\n\n\n \n\n\nPress Release\n\r\n                Maritime Industry Associations launch consolidated BMP Maritime Security publication            \n\n\r\n\t\t\t31 March 2025        \n\n\n\n\n\n \n\n\nStatement\n\r\n                International Chamber of Shipping’s comment post USTR (United States Trade Representative) Section 301 Investigation public hearing            \n\n\r\n\t\t\t27 March 2025        \n\n\n\n\n\n \n\n\nPress Release\n\r\n                The New Second Edition of ‘Maritime Security: A Comprehensive Guide for Shipowners, Seafarers and Administrations’ is now available in hardback            \n\n\r\n\t\t\t18 March 2025        \n\n\n\n\n\n \n\n\nPress Release\n\r\n                ICS and CMI launch updated campaign Promoting Maritime Treaty Ratification            \n\n\r\n\t\t\t17 March 2025\n\nLatest updates                        \n\n\n\n\n\n \n\n\nPress Release\n\r\n                Maritime Industry Associations launch consolidated BMP Maritime Security publication            \n\n\r\n\t\t\t31 March 2025        \n\n\n\n\n\n \n\n\nStatement\n\r\n                International Chamber of Shipping’s comment post USTR (United States Trade Representative) Section 301 Investigation public hearing            \n\n\r\n\t\t\t27 March 2025        \n\n\n\n\n\n \n\n\nPress Release\n\r\n                The New Second Edition of ‘Maritime Security: A Comprehensive Guide for Shipowners, Seafarers and Administrations’ is now available in hardback            \n\n\r\n\t\t\t18 March 2025        \n\n\n\n\n\n \n\n\nPress Release\n\r\n                ICS and CMI launch updated campaign Promoting Maritime Treaty Ratification            \n\n\r\n\t\t\t17 March 2025\n\nLatest updates\n\nPress Release\n\r\n                Maritime Industry Associations launch consolidated BMP Maritime Security publication            \n\n\r\n\t\t\t31 March 2025        \n\n\n\n\n\n \n\n\nStatement\n\r\n                International Chamber of Shipping’s comment post USTR (United States Trade Representative) Section 301 Investigation public hearing            \n\n\r\n\t\t\t27 March 2025        \n\n\n\n\n\n \n\n\nPress Release\n\r\n                The New Second Edition of ‘Maritime Security: A Comprehensive Guide for Shipowners, Seafarers and Administrations’ is now available in hardback            \n\n\r\n\t\t\t18 March 2025        \n\n\n\n\n\n \n\n\nPress Release\n\r\n                ICS and CMI launch updated campaign Promoting Maritime Treaty Ratification            \n\n\r\n\t\t\t17 March 2025\n\nPress Release\n\r\n                Maritime Industry Associations launch consolidated BMP Maritime Security publication            \n\n\r\n\t\t\t31 March 2025\n\nPress Release\n\r\n                Maritime Industry Associations launch consolidated BMP Maritime Security publication\n\nStatement\n\r\n                International Chamber of Shipping’s comment post USTR (United States Trade Representative) Section 301 Investigation public hearing            \n\n\r\n\t\t\t27 March 2025\n\nStatement\n\r\n                International Chamber of Shipping’s comment post USTR (United States Trade Representative) Section 301 Investigation public hearing\n\nPress Release\n\r\n                The New Second Edition of ‘Maritime Security: A Comprehensive Guide for Shipowners, Seafarers and Administrations’ is now available in hardback            \n\n\r\n\t\t\t18 March 2025\n\nPress Release\n\r\n                The New Second Edition of ‘Maritime Security: A Comprehensive Guide for Shipowners, Seafarers and Administrations’ is now available in hardback\n\nPress Release\n\r\n                ICS and CMI launch updated campaign Promoting Maritime Treaty Ratification            \n\n\r\n\t\t\t17 March 2025\n\nPress Release\n\r\n                ICS and CMI launch updated campaign Promoting Maritime Treaty Ratification\n\nFeatured resources                        \n\n\n\n\n\n \n\n\nGuidelines\n\r\n                BMP Maritime Security            \n\n\r\n\t\t\tMarch 2025        \n\n\n\n\n\n \n\n\nReports, Positions and Papers\n\r\n                Promoting Maritime Treaty Ratification – The ICS and CMI Campaign 2025            \n\n\r\n\t\t\tMarch 2025        \n\n\n\n\n\n \n\n\nReports, Positions and Papers\n\r\n                Shipping Industry Flag State Performance Table 2024/2025            \n\n\r\n\t\t\tFebruary 2025        \n\n\n\n\n\n \n\n\nGuidelines\n\r\n                Drug Trafficking and Drug Abuse On Board Ship, 2025-2026 Edition            \n\n\r\n\t\t\tFebruary 2025\n\nFeatured resources                        \n\n\n\n\n\n \n\n\nGuidelines\n\r\n                BMP Maritime Security            \n\n\r\n\t\t\tMarch 2025        \n\n\n\n\n\n \n\n\nReports, Positions and Papers\n\r\n                Promoting Maritime Treaty Ratification – The ICS and CMI Campaign 2025            \n\n\r\n\t\t\tMarch 2025        \n\n\n\n\n\n \n\n\nReports, Positions and Papers\n\r\n                Shipping Industry Flag State Performance Table 2024/2025            \n\n\r\n\t\t\tFebruary 2025        \n\n\n\n\n\n \n\n\nGuidelines\n\r\n                Drug Trafficking and Drug Abuse On Board Ship, 2025-2026 Edition            \n\n\r\n\t\t\tFebruary 2025\n\nFeatured resources\n\nGuidelines\n\r\n                BMP Maritime Security            \n\n\r\n\t\t\tMarch 2025        \n\n\n\n\n\n \n\n\nReports, Positions and Papers\n\r\n                Promoting Maritime Treaty Ratification – The ICS and CMI Campaign 2025            \n\n\r\n\t\t\tMarch 2025        \n\n\n\n\n\n \n\n\nReports, Positions and Papers\n\r\n                Shipping Industry Flag State Performance Table 2024/2025            \n\n\r\n\t\t\tFebruary 2025        \n\n\n\n\n\n \n\n\nGuidelines\n\r\n                Drug Trafficking and Drug Abuse On Board Ship, 2025-2026 Edition            \n\n\r\n\t\t\tFebruary 2025\n\nGuidelines\n\r\n                BMP Maritime Security            \n\n\r\n\t\t\tMarch 2025\n\nGuidelines\n\r\n                BMP Maritime Security\n\nReports, Positions and Papers\n\r\n                Promoting Maritime Treaty Ratification – The ICS and CMI Campaign 2025            \n\n\r\n\t\t\tMarch 2025\n\nReports, Positions and Papers\n\r\n                Promoting Maritime Treaty Ratification – The ICS and CMI Campaign 2025\n\nReports, Positions and Papers\n\r\n                Shipping Industry Flag State Performance Table 2024/2025            \n\n\r\n\t\t\tFebruary 2025\n\nReports, Positions and Papers\n\r\n                Shipping Industry Flag State Performance Table 2024/2025\n\nGuidelines\n\r\n                Drug Trafficking and Drug Abuse On Board Ship, 2025-2026 Edition            \n\n\r\n\t\t\tFebruary 2025\n\nGuidelines\n\r\n                Drug Trafficking and Drug Abuse On Board Ship, 2025-2026 Edition\n\nICS Maritime Hub                        \n\nThe ICS Maritime Hub is an ideal destination and venue to host and cater for business meetings and receptions of all sizes.\n\n\n\n\n\r\n                                Read more\n\nICS Maritime Hub                        \n\nThe ICS Maritime Hub is an ideal destination and venue to host and cater for business meetings and receptions of all sizes.\n\n\n\n\n\r\n                                Read more\n\nICS Maritime Hub                        \n\nThe ICS Maritime Hub is an ideal destination and venue to host and cater for business meetings and receptions of all sizes.\n\n\n\n\n\r\n                                Read more\n\nICS Maritime Hub                        \n\nThe ICS Maritime Hub is an ideal destination and venue to host and cater for business meetings and receptions of all sizes.\n\n\n\n\n\r\n                                Read more\n\nThe ICS Maritime Hub is an ideal destination and venue to host and cater for business meetings and receptions of all sizes.\n\nWhat we do\n\n\n\nRepresenting\nICS represents shipowners with the various intergovernmental bodies that regulate shipping. First is the UN International Maritime Organization (IMO), where ICS was the first shipping industry association to be granted consultative status in 1961. ICS has established an excellent network within the shipping community and partners with other trade bodies, always striving for a global regulatory framework.\n\n\n\r\n                                        Read more                                    \n\n\n\n\n\n\n\n\nExplaining\nAbout 90% of world trade is carried by the international shipping industry. Without shipping, the import/export of affordable food and goods would not be possible – half the world would starve and the other half would freeze!\nShipping is a highly complex and global industry, at the forefront of technological innovation and committed to sustainability and the 2050 targets.\n\n\n\r\n                                        Read more                                    \n\n\n\n\n\n\n\n\nSupporting\nICS is concerned with all technical, legal, employment and trade policy issues that impact on international ship operations. It works towards regulation of shipping at an international level, and opposes unilateral and regional action by governments. ICS also develops best practices and guidance, including a wide range of publications and free resources that are used by ship operators globally.\n\n\n\r\n                                        Read more\n\nWhat we do\n\n\n\nRepresenting\nICS represents shipowners with the various intergovernmental bodies that regulate shipping. First is the UN International Maritime Organization (IMO), where ICS was the first shipping industry association to be granted consultative status in 1961. ICS has established an excellent network within the shipping community and partners with other trade bodies, always striving for a global regulatory framework.\n\n\n\r\n                                        Read more                                    \n\n\n\n\n\n\n\n\nExplaining\nAbout 90% of world trade is carried by the international shipping industry. Without shipping, the import/export of affordable food and goods would not be possible – half the world would starve and the other half would freeze!\nShipping is a highly complex and global industry, at the forefront of technological innovation and committed to sustainability and the 2050 targets.\n\n\n\r\n                                        Read more                                    \n\n\n\n\n\n\n\n\nSupporting\nICS is concerned with all technical, legal, employment and trade policy issues that impact on international ship operations. It works towards regulation of shipping at an international level, and opposes unilateral and regional action by governments. ICS also develops best practices and guidance, including a wide range of publications and free resources that are used by ship operators globally.\n\n\n\r\n                                        Read more\n\nWhat we do\n\nRepresenting\nICS represents shipowners with the various intergovernmental bodies that regulate shipping. First is the UN International Maritime Organization (IMO), where ICS was the first shipping industry association to be granted consultative status in 1961. ICS has established an excellent network within the shipping community and partners with other trade bodies, always striving for a global regulatory framework.\n\n\n\r\n                                        Read more                                    \n\n\n\n\n\n\n\n\nExplaining\nAbout 90% of world trade is carried by the international shipping industry. Without shipping, the import/export of affordable food and goods would not be possible – half the world would starve and the other half would freeze!\nShipping is a highly complex and global industry, at the forefront of technological innovation and committed to sustainability and the 2050 targets.\n\n\n\r\n                                        Read more                                    \n\n\n\n\n\n\n\n\nSupporting\nICS is concerned with all technical, legal, employment and trade policy issues that impact on international ship operations. It works towards regulation of shipping at an international level, and opposes unilateral and regional action by governments. ICS also develops best practices and guidance, including a wide range of publications and free resources that are used by ship operators globally.\n\n\n\r\n                                        Read more\n\nRepresenting\nICS represents shipowners with the various intergovernmental bodies that regulate shipping. First is the UN International Maritime Organization (IMO), where ICS was the first shipping industry association to be granted consultative status in 1961. ICS has established an excellent network within the shipping community and partners with other trade bodies, always striving for a global regulatory framework.\n\n\n\r\n                                        Read more\n\nICS represents shipowners with the various intergovernmental bodies that regulate shipping. First is the UN International Maritime Organization (IMO), where ICS was the first shipping industry association to be granted consultative status in 1961. ICS has established an excellent network within the shipping community and partners with other trade bodies, always striving for a global regulatory framework.\n\nICS represents shipowners with the various intergovernmental bodies that regulate shipping. First is the UN International Maritime Organization (IMO), where ICS was the first shipping industry association to be granted consultative status in 1961. ICS has established an excellent network within the shipping community and partners with other trade bodies, always striving for a global regulatory framework.\n\nExplaining\nAbout 90% of world trade is carried by the international shipping industry. Without shipping, the import/export of affordable food and goods would not be possible – half the world would starve and the other half would freeze!\nShipping is a highly complex and global industry, at the forefront of technological innovation and committed to sustainability and the 2050 targets.\n\n\n\r\n                                        Read more\n\nAbout 90% of world trade is carried by the international shipping industry. Without shipping, the import/export of affordable food and goods would not be possible – half the world would starve and the other half would freeze!\nShipping is a highly complex and global industry, at the forefront of technological innovation and committed to sustainability and the 2050 targets.\n\nAbout 90% of world trade is carried by the international shipping industry. Without shipping, the import/export of affordable food and goods would not be possible – half the world would starve and the other half would freeze!\n\nShipping is a highly complex and global industry, at the forefront of technological innovation and committed to sustainability and the 2050 targets.\n\nSupporting\nICS is concerned with all technical, legal, employment and trade policy issues that impact on international ship operations. It works towards regulation of shipping at an international level, and opposes unilateral and regional action by governments. ICS also develops best practices and guidance, including a wide range of publications and free resources that are used by ship operators globally.\n\n\n\r\n                                        Read more\n\nICS is concerned with all technical, legal, employment and trade policy issues that impact on international ship operations. It works towards regulation of shipping at an international level, and opposes unilateral and regional action by governments. ICS also develops best practices and guidance, including a wide range of publications and free resources that are used by ship operators globally.\n\nICS is concerned with all technical, legal, employment and trade policy issues that impact on international ship operations. It works towards regulation of shipping at an international level, and opposes unilateral and regional action by governments. ICS also develops best practices and guidance, including a wide range of publications and free resources that are used by ship operators globally.\n\nICS develops and promotes shipping industry best practices                        \n\nICS also develops best practices and guidance, including a wide range of publications and free resources that are used by ship operators globally.\n\n\n\n\n\r\n                                Read more\n\nICS develops and promotes shipping industry best practices                        \n\nICS also develops best practices and guidance, including a wide range of publications and free resources that are used by ship operators globally.\n\n\n\n\n\r\n                                Read more\n\nICS develops and promotes shipping industry best practices                        \n\nICS also develops best practices and guidance, including a wide range of publications and free resources that are used by ship operators globally.\n\n\n\n\n\r\n                                Read more\n\nICS develops and promotes shipping industry best practices                        \n\nICS also develops best practices and guidance, including a wide range of publications and free resources that are used by ship operators globally.\n\n\n\n\n\r\n                                Read more\n\nICS also develops best practices and guidance, including a wide range of publications and free resources that are used by ship operators globally.\n\nICS also develops best practices and guidance, including a wide range of publications and free resources that are used by ship operators globally.\n\nWatch our latest videos                        \n\n\n\n\n\n \n\n\nMultimedia\n\r\n                Life After Sea            \n\n\r\n\t\t\tJune 2024        \n\n\n\n\n\n \n\n\nPage\n\r\n                Shaping the Future of Shipping Summit – COP28 Highlights            \n\n\n\n\n\n\n \n\n\nPage\n\r\n                An Adventurous Spirit            \n\n\n\n\n\n\n \n\n\nMultimedia\n\r\n                100 years of International Chamber of Shipping            \n\n\r\n\t\t\tApril 2022        \n\n\n\n\n\n \n\n\nMultimedia\n\r\n                About ICS and our network            \n\n\r\n\t\t\tNovember 2020        \n\n\n\n\n\n \n\n\nMultimedia\n\r\n                About International Chamber of Shipping (ICS) Publications – Video            \n\n\r\n\t\t\tJanuary 2025\n\nWatch our latest videos                        \n\n\n\n\n\n \n\n\nMultimedia\n\r\n                Life After Sea            \n\n\r\n\t\t\tJune 2024        \n\n\n\n\n\n \n\n\nPage\n\r\n                Shaping the Future of Shipping Summit – COP28 Highlights            \n\n\n\n\n\n\n \n\n\nPage\n\r\n                An Adventurous Spirit            \n\n\n\n\n\n\n \n\n\nMultimedia\n\r\n                100 years of International Chamber of Shipping            \n\n\r\n\t\t\tApril 2022        \n\n\n\n\n\n \n\n\nMultimedia\n\r\n                About ICS and our network            \n\n\r\n\t\t\tNovember 2020        \n\n\n\n\n\n \n\n\nMultimedia\n\r\n                About International Chamber of Shipping (ICS) Publications – Video            \n\n\r\n\t\t\tJanuary 2025\n\nWatch our latest videos\n\nMultimedia\n\r\n                Life After Sea            \n\n\r\n\t\t\tJune 2024        \n\n\n\n\n\n \n\n\nPage\n\r\n                Shaping the Future of Shipping Summit – COP28 Highlights            \n\n\n\n\n\n\n \n\n\nPage\n\r\n                An Adventurous Spirit            \n\n\n\n\n\n\n \n\n\nMultimedia\n\r\n                100 years of International Chamber of Shipping            \n\n\r\n\t\t\tApril 2022        \n\n\n\n\n\n \n\n\nMultimedia\n\r\n                About ICS and our network            \n\n\r\n\t\t\tNovember 2020        \n\n\n\n\n\n \n\n\nMultimedia\n\r\n                About International Chamber of Shipping (ICS) Publications – Video            \n\n\r\n\t\t\tJanuary 2025\n\nMultimedia\n\r\n                Life After Sea            \n\n\r\n\t\t\tJune 2024\n\nMultimedia\n\r\n                Life After Sea\n\nPage\n\r\n                Shaping the Future of Shipping Summit – COP28 Highlights\n\nPage\n\r\n                Shaping the Future of Shipping Summit – COP28 Highlights\n\nPage\n\r\n                An Adventurous Spirit\n\nPage\n\r\n                An Adventurous Spirit\n\nMultimedia\n\r\n                100 years of International Chamber of Shipping            \n\n\r\n\t\t\tApril 2022\n\nMultimedia\n\r\n                100 years of International Chamber of Shipping\n\nMultimedia\n\r\n                About ICS and our network            \n\n\r\n\t\t\tNovember 2020\n\nMultimedia\n\r\n                About ICS and our network\n\nMultimedia\n\r\n                About International Chamber of Shipping (ICS) Publications – Video            \n\n\r\n\t\t\tJanuary 2025\n\nMultimedia\n\r\n                About International Chamber of Shipping (ICS) Publications – Video\n\nClick to close the person overlay\n\nClick to close the person overlay\n\nClick to close the person overlay\n\nClick to close the person overlay",
  "date": "",
  "source_type": "other",
  "extracted_at": "2025-04-07T14:19:41.587011",
  "metadata": {
    "description": "Shaping the future of shipping",
    "og:type": "website"
  },
  "relevance_score": 0.4590909090909091,
  "summary": "ICS is the global trade association for shipowners and operators\nICS represents the world’s national shipowner associations, and over 80% of the world merchant fleet\n\n\n\nRead more\n\n\n\n\n\n\n\n\n\n\n\n\n\n\n\n\n\n\n\n\n\n\r\n                            Latest updates                        \n\n\n\n\n\n \n\n\nPress Release\n\r\n                Maritime Industry Associations launch consolidated BMP Maritime Security publication            \n\n\r\n\t\t\t31 March 2025        \n\n\n\n\n\n \n\n\nStatement\n\r\n                International Chamber of Shipping’s comment post USTR (United States Trade Representative) Section 301 Investigation public hearing            \n\n\r\n\t\t\t27 March 2025        \n\n\n\n\n\n \n\n\nPress Release\n\r\n                The New Second Edition of ‘Maritime Security: A Comprehensive Guide for Shipowners, Seafarers and Administrations’ is now available in hardback            \n\n\r\n\t\t\t18 March 2025        \n\n\n\n\n\n \n\n\nPress Release\n\r\n                ICS and CMI launch updated campaign Promoting Maritime Treaty Ratification            \n\n\r\n\t\t\t17 March 2025        \n\n\n\n\n\n\n\n\n\r\n                            Featured resources                        \n\n\n\n\n\n \n\n\nGuidelines\n\r\n                BMP Maritime Security            \n\n\r\n\t\t\tMarch 2025        \n\n\n\n\n\n \n\n\nReports, Positions and Papers\n\r\n                Promoting Maritime Treaty Ratification – The ICS and CMI Campaign 2025            \n\n\r\n\t\t\tMarch 2025        \n\n\n\n\n\n \n\n\nReports, Positions and Papers\n\r\n                Shipping Industry Flag State Performance Table 2024/2025            \n\n\r\n\t\t\tFebruary 2025        \n\n\n\n\n\n \n\n\nGuidelines\n\r\n                Drug Trafficking and Drug Abuse On Board Ship, 2025-2026 Edition            \n\n\r\n\t\t\tFebruary 2025        \n\n\n\n\n\n\n\n\n \n\n\n\n\r\n\t\t\t\t\t\t\tICS Maritime Hub                        \n\nThe ICS Maritime Hub is an ideal destination and venue to host and cater for business meetings and receptions of all sizes. First is the UN International Maritime Organization (IMO), where ICS was the first shipping industry association to be granted consultative status in 1961. Read more                                    \n\n\n\n\n\n\n\n\n\n\n\n\n\n \n\n\n\n\r\n\t\t\t\t\t\t\tICS develops and promotes shipping industry best practices                        \n\nICS also develops best practices and guidance, including a wide range of publications and free resources that are used by ship operators globally. Read more\n\n\n\n\n\n\n\n\n\n\n\n\n\n\n\r\n                            Watch our latest videos                        \n\n\n\n\n\n \n\n\nMultimedia\n\r\n                Life After Sea            \n\n\r\n\t\t\tJune 2024        \n\n\n\n\n\n \n\n\nPage\n\r\n                Shaping the Future of Shipping Summit – COP28 Highlights            \n\n\n\n\n\n\n \n\n\nPage\n\r\n                An Adventurous Spirit            \n\n\n\n\n\n\n \n\n\nMultimedia\n\r\n                100 years of International Chamber of Shipping            \n\n\r\n\t\t\tApril 2022        \n\n\n\n\n\n \n\n\nMultimedia\n\r\n                About ICS and our network            \n\n\r\n\t\t\tNovember 2020        \n\n\n\n\n\n \n\n\nMultimedia\n\r\n                About International Chamber of Shipping (ICS) Publications – Video            \n\n\r\n\t\t\tJanuary 2025\n\nICS is the global trade association for shipowners and operators\nICS represents the world’s national shipowner associations, and over 80% of the world merchant fleet\n\n\n\nRead more\n\nICS is the global trade association for shipowners and operators\nICS represents the world’s national shipowner associations, and over 80% of the world merchant fleet\n\n\n\nRead more\n\nICS is the global trade association for shipowners and operators\nICS represents the world’s national shipowner associations, and over 80% of the world merchant fleet\n\n\n\nRead more\n\nICS is the global trade association for shipowners and operators\nICS represents the world’s national shipowner associations, and over 80% of the world merchant fleet\n\n\n\nRead more\n\nICS represents the world’s national shipowner associations, and over 80% of the world merchant fleet\n\nLatest updates                        \n\n\n\n\n\n \n\n\nPress Release\n\r\n                Maritime Industry Associations launch consolidated BMP Maritime Security publication            \n\n\r\n\t\t\t31 March 2025        \n\n\n\n\n\n \n\n\nStatement\n\r\n                International Chamber of Shipping’s comment post USTR (United States Trade Representative) Section 301 Investigation public hearing            \n\n\r\n\t\t\t27 March 2025        \n\n\n\n\n\n \n\n\nPress Release\n\r\n                The New Second Edition of ‘Maritime Security: A Comprehensive Guide for Shipowners, Seafarers and Administrations’ is now available in hardback            \n\n\r\n\t\t\t18 March 2025        \n\n\n\n\n\n \n\n\nPress Release\n\r\n                ICS and CMI launch updated campaign Promoting Maritime Treaty Ratification            \n\n\r\n\t\t\t17 March 2025\n\nLatest updates                        \n\n\n\n\n\n \n\n\nPress Release\n\r\n                Maritime Industry Associations launch consolidated BMP Maritime Security publication            \n\n\r\n\t\t\t31 March 2025        \n\n\n\n\n\n \n\n\nStatement\n\r\n                International Chamber of Shipping’s comment post USTR (United States Trade Representative) Section 301 Investigation public hearing            \n\n\r\n\t\t\t27 March 2025        \n\n\n\n\n\n \n\n\nPress Release\n\r\n                The New Second Edition of ‘Maritime Security: A Comprehensive Guide for Shipowners, Seafarers and Administrations’ is now available in hardback            \n\n\r\n\t\t\t18 March 2025        \n\n\n\n\n\n \n\n\nPress Release\n\r\n                ICS and CMI launch updated campaign Promoting Maritime Treaty Ratification            \n\n\r\n\t\t\t17 March 2025\n\nLatest updates\n\nPress Release\n\r\n                Maritime Industry Associations launch consolidated BMP Maritime Security publication            \n\n\r\n\t\t\t31 March 2025        \n\n\n\n\n\n \n\n\nStatement\n\r\n                International Chamber of Shipping’s comment post USTR (United States Trade Representative) Section 301 Investigation public hearing            \n\n\r\n\t\t\t27 March 2025        \n\n\n\n\n\n \n\n\nPress Release\n\r\n                The New Second Edition of ‘Maritime Security: A Comprehensive Guide for Shipowners, Seafarers and Administrations’ is now available in hardback            \n\n\r\n\t\t\t18 March 2025        \n\n\n\n\n\n \n\n\nPress Release\n\r\n                ICS and CMI launch updated campaign Promoting Maritime Treaty Ratification            \n\n\r\n\t\t\t17 March 2025\n\nPress Release\n\r\n                Maritime Industry Associations launch consolidated BMP Maritime Security publication            \n\n\r\n\t\t\t31 March 2025\n\nPress Release\n\r\n                Maritime Industry Associations launch consolidated BMP Maritime Security publication\n\nStatement\n\r\n                International Chamber of Shipping’s comment post USTR (United States Trade Representative) Section 301 Investigation public hearing            \n\n\r\n\t\t\t27 March 2025\n\nStatement\n\r\n                International Chamber of Shipping’s comment post USTR (United States Trade Representative) Section 301 Investigation public hearing\n\nPress Release\n\r\n                The New Second Edition of ‘Maritime Security: A Comprehensive Guide for Shipowners, Seafarers and Administrations’ is now available in hardback            \n\n\r\n\t\t\t18 March 2025\n\nPress Release\n\r\n                The New Second Edition of ‘Maritime Security: A Comprehensive Guide for Shipowners, Seafarers and Administrations’ is now available in hardback\n\nPress Release\n\r\n                ICS and CMI launch updated campaign Promoting Maritime Treaty Ratification            \n\n\r\n\t\t\t17 March 2025\n\nPress Release\n\r\n                ICS and CMI launch updated campaign Promoting Maritime Treaty Ratification\n\nFeatured resources                        \n\n\n\n\n\n \n\n\nGuidelines\n\r\n                BMP Maritime Security            \n\n\r\n\t\t\tMarch 2025        \n\n\n\n\n\n \n\n\nReports, Positions and Papers\n\r\n                Promoting Maritime Treaty Ratification – The ICS and CMI Campaign 2025            \n\n\r\n\t\t\tMarch 2025        \n\n\n\n\n\n \n\n\nReports, Positions and Papers\n\r\n                Shipping Industry Flag State Performance Table 2024/2025            \n\n\r\n\t\t\tFebruary 2025        \n\n\n\n\n\n \n\n\nGuidelines\n\r\n                Drug Trafficking and Drug Abuse On Board Ship, 2025-2026 Edition            \n\n\r\n\t\t\tFebruary 2025\n\nFeatured resources                        \n\n\n\n\n\n \n\n\nGuidelines\n\r\n                BMP Maritime Security            \n\n\r\n\t\t\tMarch 2025        \n\n\n\n\n\n \n\n\nReports, Positions and Papers\n\r\n                Promoting Maritime Treaty Ratification – The ICS and CMI Campaign 2025            \n\n\r\n\t\t\tMarch 2025        \n\n\n\n\n\n \n\n\nReports, Positions and Papers\n\r\n                Shipping Industry Flag State Performance Table 2024/2025            \n\n\r\n\t\t\tFebruary 2025        \n\n\n\n\n\n \n\n\nGuidelines\n\r\n                Drug Trafficking and Drug Abuse On Board Ship, 2025-2026 Edition            \n\n\r\n\t\t\tFebruary 2025\n\nFeatured resources\n\nGuidelines\n\r\n                BMP Maritime Security            \n\n\r\n\t\t\tMarch 2025        \n\n\n\n\n\n \n\n\nReports, Positions and Papers\n\r\n                Promoting Maritime Treaty Ratification – The ICS and CMI Campaign 2025            \n\n\r\n\t\t\tMarch 2025        \n\n\n\n\n\n \n\n\nReports, Positions and Papers\n\r\n                Shipping Industry Flag State Performance Table 2024/2025            \n\n\r\n\t\t\tFebruary 2025        \n\n\n\n\n\n \n\n\nGuidelines\n\r\n                Drug Trafficking and Drug Abuse On Board Ship, 2025-2026 Edition            \n\n\r\n\t\t\tFebruary 2025\n\nGuidelines\n\r\n                BMP Maritime Security            \n\n\r\n\t\t\tMarch 2025\n\nGuidelines\n\r\n                BMP Maritime Security\n\nReports, Positions and Papers\n\r\n                Promoting Maritime Treaty Ratification – The ICS and CMI Campaign 2025            \n\n\r\n\t\t\tMarch 2025\n\nReports, Positions and Papers\n\r\n                Promoting Maritime Treaty Ratification – The ICS and CMI Campaign 2025\n\nReports, Positions and Papers\n\r\n                Shipping Industry Flag State Performance Table 2024/2025            \n\n\r\n\t\t\tFebruary 2025\n\nReports, Positions and Papers\n\r\n                Shipping Industry Flag State Performance Table 2024/2025\n\nGuidelines\n\r\n                Drug Trafficking and Drug Abuse On Board Ship, 2025-2026 Edition            \n\n\r\n\t\t\tFebruary 2025\n\nGuidelines\n\r\n                Drug Trafficking and Drug Abuse On Board Ship, 2025-2026 Edition\n\nICS Maritime Hub                        \n\nThe ICS Maritime Hub is an ideal destination and venue to host and cater for business meetings and receptions of all sizes. First is the UN International Maritime Organization (IMO), where ICS was the first shipping industry association to be granted consultative status in 1961. First is the UN International Maritime Organization (IMO), where ICS was the first shipping industry association to be granted consultative status in 1961. First is the UN International Maritime Organization (IMO), where ICS was the first shipping industry association to be granted consultative status in 1961. First is the UN International Maritime Organization (IMO), where ICS was the first shipping industry association to be granted consultative status in 1961. First is the UN International Maritime Organization (IMO), where ICS was the first shipping industry association to be granted consultative status in 1961. First is the UN International Maritime Organization (IMO), where ICS was the first shipping industry association to be granted consultative status in 1961. ICS develops and promotes shipping industry best practices                        \n\nICS also develops best practices and guidance, including a wide range of publications and free resources that are used by ship operators globally. Read more\n\nICS develops and promotes shipping industry best practices                        \n\nICS also develops best practices and guidance, including a wide range of publications and free resources that are used by ship operators globally. Read more\n\nICS develops and promotes shipping industry best practices                        \n\nICS also develops best practices and guidance, including a wide range of publications and free resources that are used by ship operators globally. Read more\n\nICS develops and promotes shipping industry best practices                        \n\nICS also develops best practices and guidance, including a wide range of publications and free resources that are used by ship operators globally. Watch our latest videos                        \n\n\n\n\n\n \n\n\nMultimedia\n\r\n                Life After Sea            \n\n\r\n\t\t\tJune 2024        \n\n\n\n\n\n \n\n\nPage\n\r\n                Shaping the Future of Shipping Summit – COP28 Highlights            \n\n\n\n\n\n\n \n\n\nPage\n\r\n                An Adventurous Spirit            \n\n\n\n\n\n\n \n\n\nMultimedia\n\r\n                100 years of International Chamber of Shipping            \n\n\r\n\t\t\tApril 2022        \n\n\n\n\n\n \n\n\nMultimedia\n\r\n                About ICS and our network            \n\n\r\n\t\t\tNovember 2020        \n\n\n\n\n\n \n\n\nMultimedia\n\r\n                About International Chamber of Shipping (ICS) Publications – Video            \n\n\r\n\t\t\tJanuary 2025\n\nWatch our latest videos                        \n\n\n\n\n\n \n\n\nMultimedia\n\r\n                Life After Sea            \n\n\r\n\t\t\tJune 2024        \n\n\n\n\n\n \n\n\nPage\n\r\n                Shaping the Future of Shipping Summit – COP28 Highlights            \n\n\n\n\n\n\n \n\n\nPage\n\r\n                An Adventurous Spirit            \n\n\n\n\n\n\n \n\n\nMultimedia\n\r\n                100 years of International Chamber of Shipping            \n\n\r\n\t\t\tApril 2022        \n\n\n\n\n\n \n\n\nMultimedia\n\r\n                About ICS and our network            \n\n\r\n\t\t\tNovember 2020        \n\n\n\n\n\n \n\n\nMultimedia\n\r\n                About International Chamber of Shipping (ICS) Publications – Video            \n\n\r\n\t\t\tJanuary 2025\n\nWatch our latest videos\n\nMultimedia\n\r\n                Life After Sea            \n\n\r\n\t\t\tJune 2024        \n\n\n\n\n\n \n\n\nPage\n\r\n                Shaping the Future of Shipping Summit – COP28 Highlights            \n\n\n\n\n\n\n \n\n\nPage\n\r\n                An Adventurous Spirit            \n\n\n\n\n\n\n \n\n\nMultimedia\n\r\n                100 years of International Chamber of Shipping            \n\n\r\n\t\t\tApril 2022        \n\n\n\n\n\n \n\n\nMultimedia\n\r\n                About ICS and our network            \n\n\r\n\t\t\tNovember 2020        \n\n\n\n\n\n \n\n\nMultimedia\n\r\n                About International Chamber of Shipping (ICS) Publications – Video            \n\n\r\n\t\t\tJanuary 2025\n\nMultimedia\n\r\n                Life After Sea            \n\n\r\n\t\t\tJune 2024\n\nMultimedia\n\r\n                Life After Sea\n\nPage\n\r\n                Shaping the Future of Shipping Summit – COP28 Highlights\n\nPage\n\r\n                Shaping the Future of Shipping Summit – COP28 Highlights\n\nPage\n\r\n                An Adventurous Spirit\n\nPage\n\r\n                An Adventurous Spirit\n\nMultimedia\n\r\n                100 years of International Chamber of Shipping            \n\n\r\n\t\t\tApril 2022\n\nMultimedia\n\r\n                100 years of International Chamber of Shipping\n\nMultimedia\n\r\n                About ICS and our network            \n\n\r\n\t\t\tNovember 2020\n\nMultimedia\n\r\n                About ICS and our network\n\nMultimedia\n\r\n                About International Chamber of Shipping (ICS) Publications – Video            \n\n\r\n\t\t\tJanuary 2025\n\nMultimedia\n\r\n                About International Chamber of Shipping (ICS) Publications – Video\n\nClick to close the person overlay\n\nClick to close the person overlay\n\nClick to close the person overlay\n\nClick to close the person overlay",
  "entities": {
    "countries": [
      "united states"
    ],
    "organizations": [
      "un"
    ],
    "key_issues": [
      "issue",
      "concern",
      "nation",
      "state",
      "government",
      "region",
      "policy",
      "action",
      "trade",
      "industry",
      "un",
      "organization"
    ]
  },
  "committee": "International Maritime Organization",
  "topic": "Discussing the use of maritime autonomous surface ships (MASS)"
}